{
  "type": "Feature",
  "properties": {
    "addr:full":"56548 Doc Jones Rd Mankato MN 56001",
    "addr:housenumber":"56548",
    "addr:postcode":"56001",
    "addr:street":"Doc Jones Rd",
    "iso:country":"US",
    "sg:address":"56548 Doc Jones Rd",
    "sg:city":"Mankato",
    "sg:classifiers":[
        {
            "category":"Local Transit",
            "type":"Transportation"
        }
    ],
    "sg:phone":"+1 507 345 5470",
    "sg:postcode":"56001",
    "sg:province":"MN",
    "sg:tags":[
        "bus",
        "line"
    ],
    "wof:name":"Yaeger Bus Svc Inc",
    "wof:placetype":"venue"
},
  "geometry": {"coordinates":[-94.01265100000001,44.137566],"type":"Point"}
}