{
  "type": "Feature",
  "properties": {
    "addr:full":"1304 4th St NW Kasson MN 55944",
    "addr:housenumber":"1304",
    "addr:postcode":"55944",
    "addr:street":"4Th St Nw",
    "iso:country":"US",
    "sg:address":"1304 4th St NW",
    "sg:city":"Kasson",
    "sg:classifiers":[
        {
            "category":"Real Estate",
            "subcategory":"Real Estate Services",
            "type":"Services"
        },
        {
            "category":"Real Estate",
            "subcategory":"Real Estate Agent",
            "type":"Services"
        }
    ],
    "sg:phone":"+1 507 477 3450",
    "sg:postcode":"55944",
    "sg:province":"MN",
    "sg:tags":[
        "buyer",
        "broker"
    ],
    "wof:name":"Quad County Realty Appraisal",
    "wof:placetype":"venue"
},
  "geometry": {"coordinates":[-92.75550800000001,44.033157],"type":"Point"}
}