{
  "type": "Feature",
  "properties": {
    "iso:country":"US",
    "sg:address":"16502 S Jefferson Rd",
    "sg:city":"Hutchinson",
    "sg:classifiers":[
        {
            "category":"Personal",
            "subcategory":"Beauty Salon",
            "type":"Services"
        }
    ],
    "sg:phone":"+1 320 587 7775",
    "sg:postcode":"55350",
    "sg:province":"MN",
    "sg:tags":[
        "shop"
    ],
    "wof:name":"Inspiration",
    "wof:placetype":"venue"
},
  "geometry": {"coordinates":[-94.348163,44.852333],"type":"Point"}
}