{
  "type": "Feature",
  "properties": {
    "iso:country":"US",
    "sg:address":"220 N Nokomis St",
    "sg:city":"Alexandria",
    "sg:classifiers":[
        {
            "category":"Shopping",
            "subcategory":"Computers & Home Electronics",
            "type":"Retail Goods"
        }
    ],
    "sg:phone":"+1 320 762 1212",
    "sg:postcode":"56308",
    "sg:province":"MN",
    "sg:tags":[
        "equipment",
        "dealer"
    ],
    "sg:website":"www.rndcomputers.com",
    "wof:name":"RND Computer",
    "wof:placetype":"venue"
},
  "geometry": {"coordinates":[-95.366518,45.893127],"type":"Point"}
}