{
  "type": "Feature",
  "properties": {
    "iso:country":"US",
    "sg:address":"312 4th St E",
    "sg:city":"Jordan",
    "sg:classifiers":[
        {
            "category":"Professional",
            "subcategory":"Accounting & Tax Preparation",
            "type":"Services"
        }
    ],
    "sg:phone":"+1 952 492 2236",
    "sg:postcode":"55352",
    "sg:province":"MN",
    "sg:tags":[
        "return"
    ],
    "wof:name":"Cragoe & Cragoe",
    "wof:placetype":"venue"
},
  "geometry": {"coordinates":[-93.625404,44.669275],"type":"Point"}
}