{
  "type": "Feature",
  "properties": {
    "addr:full":"1104 106th Ave NE Minneapolis MN 55434",
    "addr:housenumber":"1104",
    "addr:postcode":"55434",
    "addr:street":"106Th Ave Ne",
    "iso:country":"US",
    "sg:address":"1104 106th Ave NE",
    "sg:city":"Minneapolis",
    "sg:classifiers":[
        {
            "category":"Insurance",
            "subcategory":"Insurance Agent",
            "type":"Services"
        }
    ],
    "sg:phone":"+1 763 784 7754",
    "sg:postcode":"55434",
    "sg:province":"MN",
    "wof:name":"Horace Mann Insurance Co",
    "wof:placetype":"venue"
},
  "geometry": {"coordinates":[-93.241134,45.162697],"type":"Point"}
}