{
  "type": "Feature",
  "properties": {
    "iso:country":"US",
    "sg:address":"5905 Golden Valley Rd",
    "sg:city":"Minneapolis",
    "sg:classifiers":[
        {
            "category":"Professional",
            "subcategory":"Business Services",
            "type":"Services"
        }
    ],
    "sg:phone":"+1 763 540 0174",
    "sg:postcode":"55422",
    "sg:province":"MN",
    "sg:tags":[
        "nonphysical",
        "commercial",
        "research"
    ],
    "wof:name":"Residential Research Inc",
    "wof:placetype":"venue"
},
  "geometry": {"coordinates":[-93.356292,44.992472],"type":"Point"}
}