{
  "type": "Feature",
  "properties": {
    "addr:full":"136 River Edge Way NE Minneapolis MN 55432",
    "addr:housenumber":"136",
    "addr:postcode":"55432",
    "addr:street":"River Edge Way Ne",
    "iso:country":"US",
    "sg:address":"136 River Edge Way NE",
    "sg:city":"Minneapolis",
    "sg:classifiers":[
        {
            "category":"Wholesale",
            "subcategory":"Medical Equipment & Supplies",
            "type":"Manufacturing & Wholesale Goods"
        }
    ],
    "sg:phone":"+1 763 586 9648",
    "sg:postcode":"55432",
    "sg:province":"MN",
    "sg:tags":[
        "wheelchair"
    ],
    "wof:name":"Ramp & Roll Inc",
    "wof:placetype":"venue"
},
  "geometry": {"coordinates":[-93.27616500000001,45.079539],"type":"Point"}
}