{
  "type": "Feature",
  "properties": {
    "iso:country":"US",
    "sg:address":"3557 Lexington Ave N",
    "sg:city":"St Paul",
    "sg:classifiers":[
        {
            "category":"Shopping",
            "type":"Retail Goods"
        },
        {
            "category":"Shopping",
            "subcategory":"Jewelry",
            "type":"Retail Goods"
        }
    ],
    "sg:phone":"+1 651 486 8990",
    "sg:postcode":"55126",
    "sg:province":"MN",
    "sg:tags":[
        "art",
        "dealer",
        "merchandise",
        "gallery"
    ],
    "wof:name":"Vine & Branches Gallery",
    "wof:placetype":"venue"
},
  "geometry": {"coordinates":[-93.14712900000001,45.047907],"type":"Point"}
}