{
  "type": "Feature",
  "properties": {
    "addr:full":"408 Main St E Saint Clair MN 56080",
    "addr:housenumber":"408",
    "addr:postcode":"56080",
    "addr:street":"Main St E Saint",
    "iso:country":"US",
    "sg:address":"408 Main St E",
    "sg:city":"Saint Clair",
    "sg:classifiers":[
        {
            "category":"Real Estate",
            "subcategory":"Real Estate Operator",
            "type":"Services"
        }
    ],
    "sg:phone":"+1 507 245 3345",
    "sg:postcode":"56080",
    "sg:province":"MN",
    "sg:tags":[
        "building",
        "nonresidential"
    ],
    "wof:name":"Fitzloff Properties LLC",
    "wof:placetype":"venue"
},
  "geometry": {"coordinates":[-93.852907,44.080453],"type":"Point"}
}