{
  "type": "Feature",
  "properties": {
    "iso:country":"US",
    "sg:address":"124 Main St E",
    "sg:city":"Pipestone",
    "sg:classifiers":[
        {
            "category":"Shopping",
            "subcategory":"Gifts & Souvenirs",
            "type":"Retail Goods"
        }
    ],
    "sg:phone":"+1 507 825 4463",
    "sg:postcode":"56164",
    "sg:province":"MN",
    "sg:tags":[
        "shop"
    ],
    "wof:name":"Thoughtfulness Shop",
    "wof:placetype":"venue"
},
  "geometry": {"coordinates":[-96.317453,44.000429],"type":"Point"}
}