{
  "type": "Feature",
  "properties": {
    "iso:country":"US",
    "sg:address":"550 Flying Cloud Dr",
    "sg:city":"Chaska",
    "sg:classifiers":[
        {
            "category":"Retail",
            "subcategory":"Repair Shop",
            "type":"Services"
        }
    ],
    "sg:phone":"+1 952 445 3501",
    "sg:postcode":"55318",
    "sg:province":"MN",
    "sg:tags":[
        "upholsterer"
    ],
    "wof:name":"C & E Upholstery",
    "wof:placetype":"venue"
},
  "geometry": {"coordinates":[-93.531465,44.814077],"type":"Point"}
}