{
  "type": "Feature",
  "properties": {
    "iso:country":"US",
    "sg:address":"3520 Noble Ave N",
    "sg:city":"Minneapolis",
    "sg:classifiers":[
        {
            "category":"Social Services",
            "subcategory":"Child Care",
            "type":"Services"
        }
    ],
    "sg:phone":"+1 763 521 5430",
    "sg:postcode":"55422",
    "sg:province":"MN",
    "sg:tags":[
        "daycare",
        "provider"
    ],
    "wof:name":"Pammies Daycare",
    "wof:placetype":"venue"
},
  "geometry": {"coordinates":[-93.33873,45.02014],"type":"Point"}
}