{
  "type": "Feature",
  "properties": {
    "iso:country":"US",
    "sg:address":"8241 120th St",
    "sg:city":"Milaca",
    "sg:classifiers":[
        {
            "category":"Professional",
            "type":"Services"
        }
    ],
    "sg:phone":"+1 320 983 2026",
    "sg:postcode":"56353",
    "sg:province":"MN",
    "wof:name":"Rum River Wheelers Inc",
    "wof:placetype":"venue"
},
  "geometry": {"coordinates":[-93.57966,45.719551],"type":"Point"}
}