{
  "type": "Feature",
  "properties": {
    "addr:full":"14270 Scandia Trl N Scandia MN 55073",
    "addr:postcode":"14270;55073",
    "addr:street":"Scandia Trl N Scandia",
    "iso:country":"US",
    "sg:address":"14270 Scandia Trl N",
    "sg:city":"Scandia",
    "sg:classifiers":[
        {
            "category":"Building & Trades",
            "subcategory":"Plumbing",
            "type":"Services"
        }
    ],
    "sg:phone":"+1 651 433 2111",
    "sg:postcode":"55073",
    "sg:province":"MN",
    "sg:tags":[
        "contractor"
    ],
    "wof:name":"Mechanical Services Inc",
    "wof:placetype":"venue"
},
  "geometry": {"coordinates":[-92.81555,45.256671],"type":"Point"}
}