{
  "type": "Feature",
  "properties": {
    "iso:country":"US",
    "sg:address":"4070 Deerwood Trl",
    "sg:city":"Saint Paul",
    "sg:classifiers":[
        {
            "category":"Professional",
            "subcategory":"Management & Consulting",
            "type":"Services"
        }
    ],
    "sg:phone":"+1 651 454 5144",
    "sg:postcode":"55122",
    "sg:province":"MN",
    "wof:name":"Lmf Investments Inc",
    "wof:placetype":"venue"
},
  "geometry": {"coordinates":[-93.16895100000001,44.811268],"type":"Point"}
}