{
  "type": "Feature",
  "properties": {
    "addr:full":"83 91st Ln NE Minneapolis MN 55434",
    "addr:housenumber":"83",
    "addr:postcode":"55434",
    "addr:street":"91St Ln Ne",
    "iso:country":"US",
    "sg:address":"83 91st Ln NE",
    "sg:city":"Minneapolis",
    "sg:classifiers":[
        {
            "category":"Building & Trades",
            "subcategory":"Construction",
            "type":"Services"
        }
    ],
    "sg:phone":"+1 763 786 4238",
    "sg:postcode":"55434",
    "sg:province":"MN",
    "sg:tags":[
        "house"
    ],
    "wof:name":"Byron W Eilertson",
    "wof:placetype":"venue"
},
  "geometry": {"coordinates":[-93.266019,45.136891],"type":"Point"}
}