{
  "type": "Feature",
  "properties": {
    "addr:full":"1000 W Franklin Ave # 210 Minneapolis MN 55405",
    "addr:housenumber":"1000",
    "addr:postcode":"55405",
    "addr:street":"W Franklin Ave # 210",
    "iso:country":"US",
    "sg:address":"1000 W Franklin Ave # 210",
    "sg:city":"Minneapolis",
    "sg:classifiers":[
        {
            "category":"Professional",
            "type":"Services"
        },
        {
            "category":"Arts & Performance",
            "subcategory":"Music",
            "type":"Entertainment"
        }
    ],
    "sg:phone":"+1 612 229 9959",
    "sg:postcode":"55405",
    "sg:province":"MN",
    "sg:tags":[
        "record",
        "producer",
        "label"
    ],
    "sg:website":"http://www.interference.ie",
    "wof:name":"Interference",
    "wof:placetype":"venue"
},
  "geometry": {"coordinates":[-93.291786,44.962719],"type":"Point"}
}