{
  "type": "Feature",
  "properties": {
    "iso:country":"US",
    "sg:address":"3597 Johnson Rd N",
    "sg:city":"Brainerd",
    "sg:classifiers":[
        {
            "category":"Manufacturing",
            "subcategory":"Retail Goods",
            "type":"Manufacturing & Wholesale Goods"
        }
    ],
    "sg:phone":"+1 218 828 9439",
    "sg:postcode":"56401",
    "sg:province":"MN",
    "sg:tags":[
        "manufacturer"
    ],
    "wof:name":"Bell Industries",
    "wof:placetype":"venue"
},
  "geometry": {"coordinates":[-94.26541400000001,46.409392],"type":"Point"}
}