{
  "type": "Feature",
  "properties": {
    "addr:full":"18323 Minnetonka Blvd Wayzata MN 55391",
    "addr:housenumber":"18323",
    "addr:postcode":"55391",
    "addr:street":"Minnetonka Blvd",
    "iso:country":"US",
    "sg:address":"18323 Minnetonka Blvd",
    "sg:city":"Wayzata",
    "sg:classifiers":[
        {
            "category":"Place Of Worship",
            "subcategory":"Church",
            "type":"Public Place"
        },
        {
            "category":"Place Of Worship",
            "type":"Public Place"
        },
        {
            "category":"Organizations",
            "subcategory":"Religious Organization",
            "type":"Services"
        }
    ],
    "sg:phone":"+1 952 473 4422",
    "sg:postcode":"55391",
    "sg:province":"MN",
    "sg:tags":[
        "churches-catholic"
    ],
    "sg:website":"http://www.st-therese.org",
    "wof:name":"Church of St Therese Of Deephaven",
    "wof:placetype":"venue"
},
  "geometry": {"coordinates":[-93.512474,44.940902],"type":"Point"}
}