{
  "type": "Feature",
  "properties": {
    "addr:full":"2370 7th Ave Anoka MN 55303",
    "addr:housenumber":"2370",
    "addr:postcode":"55303",
    "addr:street":"7Th Ave",
    "iso:country":"US",
    "sg:address":"2370 7th Ave",
    "sg:city":"Anoka",
    "sg:classifiers":[
        {
            "category":"Autos & Motor Vehicles",
            "subcategory":"Fuel & Gas Station",
            "type":"Retail Goods"
        },
        {
            "category":"Retail",
            "subcategory":"Car Wash",
            "type":"Services"
        }
    ],
    "sg:phone":"+1 763 427 8603",
    "sg:postcode":"55303",
    "sg:province":"MN",
    "sg:website":"www.marathon.com",
    "wof:name":"Anoka Marathon",
    "wof:placetype":"venue"
},
  "geometry": {"coordinates":[-93.378106,45.202734],"type":"Point"}
}