{
  "type": "Feature",
  "properties": {
    "addr:full":"801 Crestview Dr Saint Paul MN 55119",
    "addr:housenumber":"801",
    "addr:postcode":"55119",
    "addr:street":"Crestview Dr",
    "iso:country":"US",
    "sg:address":"801 Crestview Dr",
    "sg:city":"Saint Paul",
    "sg:classifiers":[
        {
            "category":"Building & Trades",
            "subcategory":"Construction",
            "type":"Services"
        }
    ],
    "sg:phone":"+1 651 738 2694",
    "sg:postcode":"55119",
    "sg:province":"MN",
    "sg:tags":[
        "general",
        "contractor"
    ],
    "wof:name":"ONeil Associates Inc",
    "wof:placetype":"venue"
},
  "geometry": {"coordinates":[-92.999095,44.915564],"type":"Point"}
}