{
  "type": "Feature",
  "properties": {
    "addr:full":"2200 Paul Bunyan Dr NW Bemidji MN 56601",
    "addr:housenumber":"2200",
    "addr:postcode":"56601",
    "addr:street":"Paul Bunyan Dr Nw",
    "iso:country":"US",
    "sg:address":"2200 Paul Bunyan Dr NW",
    "sg:city":"Bemidji",
    "sg:classifiers":[
        {
            "category":"Bars & Pubs",
            "type":"Food & Drink"
        }
    ],
    "sg:menulink":"http://www.allmenus.com/mn/bemidji/241276-ground-round-bar--grill/menu/",
    "sg:phone":"+1 218 444 3201",
    "sg:postcode":"56601",
    "sg:province":"MN",
    "sg:tags":[
        "american"
    ],
    "wof:name":"Ground Round Bar & Grill",
    "wof:placetype":"venue"
},
  "geometry": {"coordinates":[-94.911704,47.495992],"type":"Point"}
}