{
  "type": "Feature",
  "properties": {
    "iso:country":"US",
    "sg:address":"1006 Commercial Dr",
    "sg:city":"Buffalo",
    "sg:classifiers":[
        {
            "category":"Education",
            "subcategory":"Dance Studio",
            "type":"Public Place"
        }
    ],
    "sg:phone":"+1 763 682 9685",
    "sg:postcode":"55313",
    "sg:province":"MN",
    "wof:name":"On Stage School Of Dance",
    "wof:placetype":"venue"
},
  "geometry": {"coordinates":[-93.87458100000001,45.182043],"type":"Point"}
}