{
  "type": "Feature",
  "properties": {
    "addr:full":"751 2nd St Holdingford MN 56340",
    "addr:housenumber":"751",
    "addr:postcode":"56340",
    "addr:street":"2Nd St",
    "iso:country":"US",
    "sg:address":"751 2nd St",
    "sg:city":"Holdingford",
    "sg:classifiers":[
        {
            "category":"Home & Garden",
            "subcategory":"Carpets & Floor Coverings",
            "type":"Retail Goods"
        }
    ],
    "sg:phone":"+1 320 333 4226",
    "sg:postcode":"56340",
    "sg:province":"MN",
    "wof:name":"Floor Authority",
    "wof:placetype":"venue"
},
  "geometry": {"coordinates":[-94.473657,45.731744],"type":"Point"}
}