{
  "type": "Feature",
  "properties": {
    "iso:country":"US",
    "sg:address":"301 Washburn Ave N",
    "sg:city":"Minneapolis",
    "sg:classifiers":[
        {
            "category":"Building & Trades",
            "subcategory":"Construction",
            "type":"Services"
        }
    ],
    "sg:phone":"+1 612 377 6325",
    "sg:postcode":"55405",
    "sg:province":"MN",
    "sg:tags":[
        "system",
        "contractor",
        "air conditioning"
    ],
    "wof:name":"Allan Heating And Air Conditioning Inc.",
    "wof:placetype":"venue"
},
  "geometry": {"coordinates":[-93.31723,44.97945],"type":"Point"}
}