{
  "type": "Feature",
  "properties": {
    "addr:full":"719 E 16th St Minneapolis MN 55404",
    "addr:housenumber":"719",
    "addr:postcode":"55404",
    "addr:street":"E 16Th St",
    "iso:country":"US",
    "sg:address":"719 E 16th St",
    "sg:city":"Minneapolis",
    "sg:classifiers":[
        {
            "category":"Real Estate",
            "subcategory":"Real Estate Operator",
            "type":"Services"
        }
    ],
    "sg:phone":"+1 612 630 3600",
    "sg:postcode":"55404",
    "sg:province":"MN",
    "sg:tags":[
        "apartment"
    ],
    "wof:name":"Alliance Housing Limited Partnership",
    "wof:placetype":"venue"
},
  "geometry": {"coordinates":[-93.263199,44.9673],"type":"Point"}
}