{
  "type": "Feature",
  "properties": {
    "iso:country":"US",
    "sg:address":"112 Northtown Dr NE",
    "sg:city":"Minneapolis",
    "sg:classifiers":[
        {
            "category":"Personal",
            "subcategory":"Beauty Salon",
            "type":"Services"
        }
    ],
    "sg:phone":"+1 763 786 0990",
    "sg:postcode":"55434",
    "sg:province":"MN",
    "sg:tags":[
        "hair"
    ],
    "wof:name":"First Barber Stylists Company",
    "wof:placetype":"venue"
},
  "geometry": {"coordinates":[-93.261146,45.128922],"type":"Point"}
}