{
  "type": "Feature",
  "properties": {
    "addr:full":"733 Marquette Ave #235 Minneapolis MN 55402",
    "addr:housenumber":"733",
    "addr:postcode":"55402",
    "addr:street":"Marquette Ave # 235",
    "iso:country":"US",
    "sg:address":"733 Marquette Ave #235",
    "sg:city":"Minneapolis",
    "sg:classifiers":[
        {
            "category":"Shopping",
            "subcategory":"Jewelry",
            "type":"Retail Goods"
        }
    ],
    "sg:phone":"+1 612 225 9520",
    "sg:postcode":"55402",
    "sg:province":"MN",
    "sg:tags":[
        "watch",
        "jeweler"
    ],
    "wof:name":"G Allan Jewelers",
    "wof:placetype":"venue"
},
  "geometry": {"coordinates":[-93.27114899999999,44.976002],"type":"Point"}
}