{
  "type": "Feature",
  "properties": {
    "addr:full":"1219 S Cleveland Ave Saint Paul MN 55116",
    "addr:housenumber":"1219",
    "addr:postcode":"55116",
    "addr:street":"S Cleveland Ave",
    "iso:country":"US",
    "sg:address":"1219 S Cleveland Ave",
    "sg:city":"Saint Paul",
    "sg:classifiers":[
        {
            "category":"Professional",
            "subcategory":"Management & Consulting",
            "type":"Services"
        }
    ],
    "sg:phone":"+1 651 690 2395",
    "sg:postcode":"55116",
    "sg:province":"MN",
    "wof:name":"AGM World Trade Co",
    "wof:placetype":"venue"
},
  "geometry": {"coordinates":[-93.187476,44.903803],"type":"Point"}
}