{
  "type": "Feature",
  "properties": {
    "iso:country":"US",
    "sg:address":"768 State Hwy 65",
    "sg:city":"Mora",
    "sg:classifiers":[
        {
            "category":"Autos & Motor Vehicles",
            "subcategory":"Automobile Sales",
            "type":"Retail Goods"
        }
    ],
    "sg:phone":"+1 320 679 1383",
    "sg:postcode":"55051",
    "sg:province":"MN",
    "sg:tags":[
        "personal",
        "lawnmowers",
        "snowmobile",
        "motorcycle"
    ],
    "wof:name":"Caswell Cycle",
    "wof:placetype":"venue"
},
  "geometry": {"coordinates":[-93.29312400000001,45.868709],"type":"Point"}
}