{
  "type": "Feature",
  "properties": {
    "addr:full":"4345 Peony Ln N Minneapolis MN 55446",
    "addr:housenumber":"4345",
    "addr:postcode":"55446",
    "addr:street":"Peony Ln N",
    "iso:country":"US",
    "sg:address":"4345 Peony Ln N",
    "sg:city":"Minneapolis",
    "sg:classifiers":[
        {
            "category":"Social Services",
            "subcategory":"Child Care",
            "type":"Services"
        }
    ],
    "sg:phone":"+1 763 478 2412",
    "sg:postcode":"55446",
    "sg:province":"MN",
    "sg:tags":[
        "center"
    ],
    "wof:name":"New Horizon Child Care Inc",
    "wof:placetype":"venue"
},
  "geometry": {"coordinates":[-93.507385,45.031906],"type":"Point"}
}