{
  "type": "Feature",
  "properties": {
    "addr:full":"40439 348th Ln Aitkin MN 56431",
    "addr:housenumber":"40439",
    "addr:postcode":"56431",
    "addr:street":"348Th Ln",
    "iso:country":"US",
    "sg:address":"40439 348th Ln",
    "sg:city":"Aitkin",
    "sg:classifiers":[
        {
            "category":"Manufacturing",
            "subcategory":"Buildings",
            "type":"Manufacturing & Wholesale Goods"
        },
        {
            "category":"Building & Trades",
            "subcategory":"Construction",
            "type":"Services"
        }
    ],
    "sg:phone":"+1 218 821 3419",
    "sg:postcode":"56431",
    "sg:province":"MN",
    "sg:tags":[
        "home",
        "builder",
        "contractor"
    ],
    "wof:name":"Mystic Meadow Homes Inc",
    "wof:placetype":"venue"
},
  "geometry": {"coordinates":[-93.76851499999999,46.515552],"type":"Point"}
}