{
  "type": "Feature",
  "properties": {
    "iso:country":"US",
    "sg:address":"1726 Terrace Dr",
    "sg:city":"Saint Paul",
    "sg:classifiers":[
        {
            "category":"Manufacturing",
            "subcategory":"Apparel",
            "type":"Manufacturing & Wholesale Goods"
        }
    ],
    "sg:phone":"+1 651 697 1129",
    "sg:postcode":"55113",
    "sg:province":"MN",
    "sg:tags":[
        "product",
        "mfg"
    ],
    "wof:name":"G & J Awning & Canvas Inc",
    "wof:placetype":"venue"
},
  "geometry": {"coordinates":[-93.173827,45.025595],"type":"Point"}
}