{
  "type": "Feature",
  "properties": {
    "iso:country":"US",
    "sg:address":"219 Front St W",
    "sg:city":"Detroit Lakes",
    "sg:classifiers":[
        {
            "category":"Wholesale",
            "subcategory":"Chemicals & Plastics",
            "type":"Manufacturing & Wholesale Goods"
        }
    ],
    "sg:phone":"+1 218 844 5601",
    "sg:postcode":"56501",
    "sg:province":"MN",
    "wof:name":"American Oxygen",
    "wof:placetype":"venue"
},
  "geometry": {"coordinates":[-95.847995,46.818577],"type":"Point"}
}