{
  "type": "Feature",
  "properties": {
    "iso:country":"US",
    "sg:address":"5613 157th Way N",
    "sg:city":"Hugo",
    "sg:classifiers":[
        {
            "category":"Professional",
            "subcategory":"Business Services",
            "type":"Services"
        }
    ],
    "sg:phone":"+1 651 407 2922",
    "sg:postcode":"55038",
    "sg:province":"MN",
    "sg:tags":[
        "pool",
        "swimming"
    ],
    "wof:name":"Cal's Spas & Pool Svc",
    "wof:placetype":"venue"
},
  "geometry": {"coordinates":[-92.99143599999999,45.175913],"type":"Point"}
}