{
  "type": "Feature",
  "properties": {
    "addr:full":"641 E Main St Anoka MN 55303",
    "addr:housenumber":"641",
    "addr:postcode":"55303",
    "addr:street":"E Main St",
    "iso:country":"US",
    "sg:address":"641 E Main St",
    "sg:city":"Anoka",
    "sg:classifiers":[
        {
            "category":"Cinema",
            "subcategory":"Movie Rental",
            "type":"Entertainment"
        }
    ],
    "sg:phone":"+1 763 323 8700",
    "sg:postcode":"55303",
    "sg:province":"MN",
    "sg:tags":[
        "video",
        "tape"
    ],
    "wof:name":"Hollywood Video",
    "wof:placetype":"venue"
},
  "geometry": {"coordinates":[-93.379284,45.197818],"type":"Point"}
}