{
  "type": "Feature",
  "properties": {
    "addr:full":"4773 County Road 101 Minnetonka MN 55345",
    "addr:housenumber":"4773",
    "addr:postcode":"55345",
    "addr:street":"County Road 101",
    "iso:country":"US",
    "sg:address":"4773 County Road 101",
    "sg:city":"Minnetonka",
    "sg:classifiers":[
        {
            "category":"Restaurant",
            "type":"Food & Drink"
        }
    ],
    "sg:phone":"+1 952 933 6361",
    "sg:postcode":"55345",
    "sg:province":"MN",
    "wof:name":"Beijing",
    "wof:placetype":"venue"
},
  "geometry": {"coordinates":[-93.502899,44.917702],"type":"Point"}
}