{
  "type": "Feature",
  "properties": {
    "addr:full":"799 Salmi Rd Cloquet MN 55720",
    "addr:housenumber":"799",
    "addr:postcode":"55720",
    "addr:street":"Salmi Rd",
    "iso:country":"US",
    "sg:address":"799 Salmi Rd",
    "sg:city":"Cloquet",
    "sg:classifiers":[
        {
            "category":"Building & Trades",
            "subcategory":"Construction",
            "type":"Services"
        }
    ],
    "sg:phone":"+1 218 878 0991",
    "sg:postcode":"55720",
    "sg:province":"MN",
    "wof:name":"Decaigny Paving Inc",
    "wof:placetype":"venue"
},
  "geometry": {"coordinates":[-92.59705599999999,46.713756],"type":"Point"}
}