{
  "type": "Feature",
  "properties": {
    "iso:country":"US",
    "sg:address":"4621 Central Ave. NE",
    "sg:city":"Minneapolis",
    "sg:classifiers":[
        {
            "category":"Restaurant",
            "type":"Food & Drink"
        }
    ],
    "sg:phone":"+1 763 231 2030",
    "sg:postcode":"55421",
    "sg:province":"MN",
    "sg:tags":[
        "barbeque"
    ],
    "sg:website":"mrbbqribs.com/",
    "wof:name":"Mr. BBQ",
    "wof:placetype":"venue"
},
  "geometry": {"coordinates":[-93.247393,45.052459],"type":"Point"}
}