{
  "type": "Feature",
  "properties": {
    "addr:full":"821 3rd Ave SE Rochester MN 55904",
    "addr:housenumber":"821",
    "addr:postcode":"55904",
    "addr:street":"3Rd Ave Se",
    "iso:country":"US",
    "sg:address":"821 3rd Ave SE",
    "sg:city":"Rochester",
    "sg:classifiers":[
        {
            "category":"Shopping",
            "subcategory":"Clothing, Apparel, & Fashions",
            "type":"Retail Goods"
        }
    ],
    "sg:phone":"+1 507 529 0464",
    "sg:postcode":"55904",
    "sg:province":"MN",
    "wof:name":"Super Clothing Store",
    "wof:placetype":"venue"
},
  "geometry": {"coordinates":[-92.458842,44.014298],"type":"Point"}
}