{
  "type": "Feature",
  "properties": {
    "iso:country":"US",
    "sg:address":"420 66th Ave N",
    "sg:city":"Minneapolis",
    "sg:classifiers":[
        {
            "category":"Autos & Motor Vehicles",
            "subcategory":"Fuel & Gas Station",
            "type":"Retail Goods"
        }
    ],
    "sg:phone":"+1 763 566 4311",
    "sg:postcode":"55430",
    "sg:province":"MN",
    "sg:tags":[
        "store"
    ],
    "wof:name":"Spencer Oil Company",
    "wof:placetype":"venue"
},
  "geometry": {"coordinates":[-93.288948,45.074387],"type":"Point"}
}