{
  "type": "Feature",
  "properties": {
    "addr:full":"3829 Florida Ave N Minneapolis MN 55427",
    "addr:housenumber":"3829",
    "addr:postcode":"55427",
    "addr:street":"Florida Ave N",
    "iso:country":"US",
    "sg:address":"3829 Florida Ave N",
    "sg:city":"Minneapolis",
    "sg:classifiers":[
        {
            "category":"Travel",
            "subcategory":"Travel Agent",
            "type":"Entertainment"
        }
    ],
    "sg:phone":"+1 612 720 5659",
    "sg:postcode":"55427",
    "sg:province":"MN",
    "sg:tags":[
        "agency"
    ],
    "wof:name":"Cruise Aweigh, Inc.",
    "wof:placetype":"venue"
},
  "geometry": {"coordinates":[-93.362602,45.02576],"type":"Point"}
}