{
  "type": "Feature",
  "properties": {
    "addr:full":"300 S Bruce St Marshall MN 56258",
    "addr:housenumber":"300",
    "addr:postcode":"56258",
    "addr:street":"S Bruce St",
    "iso:country":"US",
    "sg:address":"300 S Bruce St",
    "sg:city":"Marshall",
    "sg:classifiers":[
        {
            "category":"Sports & Exercise",
            "subcategory":"Gym",
            "type":"Entertainment"
        }
    ],
    "sg:phone":"+1 507 537 9094",
    "sg:postcode":"56258",
    "sg:province":"MN",
    "sg:tags":[
        "club",
        "health",
        "studio",
        "gymnasium"
    ],
    "sg:website":"www.wmmc.org",
    "wof:name":"W Mmc Wellness & Rehab Ctr",
    "wof:placetype":"venue"
},
  "geometry": {"coordinates":[-95.77616999999999,44.44883],"type":"Point"}
}