{
  "type": "Feature",
  "properties": {
    "addr:full":"944 110th Ave Welcome MN 56181",
    "addr:housenumber":"944",
    "addr:postcode":"56181",
    "addr:street":"110Th Ave",
    "iso:country":"US",
    "sg:address":"944 110th Ave",
    "sg:city":"Welcome",
    "sg:classifiers":[
        {
            "category":"Farming",
            "subcategory":"Dairy Farm",
            "type":"Manufacturing & Wholesale Goods"
        },
        {
            "category":"Farming",
            "subcategory":"Farm",
            "type":"Manufacturing & Wholesale Goods"
        }
    ],
    "sg:phone":"+1 507 728 8847",
    "sg:postcode":"56181",
    "sg:province":"MN",
    "wof:name":"Wayne Hartwig",
    "wof:placetype":"venue"
},
  "geometry": {"coordinates":[-94.654377,43.618934],"type":"Point"}
}