{
  "type": "Feature",
  "properties": {
    "addr:full":"11901 470th St Hewitt MN 56453",
    "addr:housenumber":"11901",
    "addr:postcode":"56453",
    "addr:street":"470Th St",
    "iso:country":"US",
    "sg:address":"11901 470th St",
    "sg:city":"Hewitt",
    "sg:classifiers":[
        {
            "category":"Farming",
            "subcategory":"Farm",
            "type":"Manufacturing & Wholesale Goods"
        }
    ],
    "sg:phone":"+1 218 924 2513",
    "sg:postcode":"56453",
    "sg:province":"MN",
    "sg:tags":[
        "crop",
        "general"
    ],
    "wof:name":"Roy Isvik",
    "wof:placetype":"venue"
},
  "geometry": {"coordinates":[-95.11871600000001,46.3111],"type":"Point"}
}