{
  "type": "Feature",
  "properties": {
    "addr:full":"3021 Harbor Ln N Minneapolis MN 55447",
    "addr:housenumber":"3021",
    "addr:postcode":"55447",
    "addr:street":"Harbor Ln N",
    "iso:country":"US",
    "sg:address":"3021 Harbor Ln N",
    "sg:city":"Minneapolis",
    "sg:classifiers":[
        {
            "category":"Insurance",
            "subcategory":"Insurance Agent",
            "type":"Services"
        }
    ],
    "sg:phone":"+1 763 545 5657",
    "sg:postcode":"55447",
    "sg:province":"MN",
    "wof:name":"Bob Neuberger Agency",
    "wof:placetype":"venue"
},
  "geometry": {"coordinates":[-93.46129500000001,45.014061],"type":"Point"}
}