{
  "type": "Feature",
  "properties": {
    "iso:country":"US",
    "sg:address":"100 14th St SW",
    "sg:city":"Austin",
    "sg:classifiers":[
        {
            "category":"Restaurant",
            "type":"Food & Drink"
        }
    ],
    "sg:phone":"+1 507 437 6078",
    "sg:postcode":"55912",
    "sg:province":"MN",
    "wof:name":"Tolly's Time Out Restaurant",
    "wof:placetype":"venue"
},
  "geometry": {"coordinates":[-92.992864,43.666584],"type":"Point"}
}