{
  "type": "Feature",
  "properties": {
    "addr:full":"2414 E 24th St Minneapolis MN 55406",
    "addr:housenumber":"2414",
    "addr:postcode":"55406",
    "addr:street":"E 24Th St",
    "iso:country":"US",
    "sg:address":"2414 E 24th St",
    "sg:city":"Minneapolis",
    "sg:classifiers":[
        {
            "category":"Arts & Performance",
            "subcategory":"Theater",
            "type":"Entertainment"
        }
    ],
    "sg:phone":"+1 612 722 4670",
    "sg:postcode":"55406",
    "sg:province":"MN",
    "sg:tags":[
        "musician"
    ],
    "wof:name":"Terrastar",
    "wof:placetype":"venue"
},
  "geometry": {"coordinates":[-93.236369,44.959225],"type":"Point"}
}