{
  "type": "Feature",
  "properties": {
    "addr:full":"421 2nd Ave NE Staples MN 56479",
    "addr:housenumber":"421",
    "addr:postcode":"56479",
    "addr:street":"2Nd Ave Ne",
    "iso:country":"US",
    "sg:address":"421 2nd Ave NE",
    "sg:city":"Staples",
    "sg:classifiers":[
        {
            "category":"Shopping",
            "type":"Retail Goods"
        },
        {
            "category":"Shopping",
            "subcategory":"Pharmacy",
            "type":"Retail Goods"
        }
    ],
    "sg:phone":"+1 218 894 2242",
    "sg:postcode":"56479",
    "sg:province":"MN",
    "sg:tags":[
        "drug",
        "equipment",
        "health",
        "home",
        "store",
        "care"
    ],
    "wof:name":"Longbella Drug Inc",
    "wof:placetype":"venue"
},
  "geometry": {"coordinates":[-94.79463800000001,46.355725],"type":"Point"}
}