{
  "type": "Feature",
  "properties": {
    "iso:country":"US",
    "sg:address":"113 S Liberty St",
    "sg:city":"Danvers",
    "sg:classifiers":[
        {
            "category":"Wholesale",
            "subcategory":"Construction Materials",
            "type":"Manufacturing & Wholesale Goods"
        }
    ],
    "sg:phone":"+1 320 567 2335",
    "sg:postcode":"56231",
    "sg:province":"MN",
    "sg:tags":[
        "sand",
        "gravel"
    ],
    "wof:name":"Commerford Gravel Inc",
    "wof:placetype":"venue"
},
  "geometry": {"coordinates":[-95.752163,45.281956],"type":"Point"}
}