{
  "type": "Feature",
  "properties": {
    "addr:full":"10800 Normandale Blvd Minneapolis MN 55437",
    "addr:housenumber":"10800",
    "addr:postcode":"55437",
    "addr:street":"Normandale Blvd",
    "iso:country":"US",
    "sg:address":"10800 Normandale Blvd",
    "sg:city":"Minneapolis",
    "sg:classifiers":[
        {
            "category":"Insurance",
            "subcategory":"Hazard Insurance",
            "type":"Services"
        }
    ],
    "sg:phone":"+1 952 884 1674",
    "sg:postcode":"55437",
    "sg:province":"MN",
    "sg:tags":[
        "carrier"
    ],
    "wof:name":"Lee Neng Ins",
    "wof:placetype":"venue"
},
  "geometry": {"coordinates":[-93.350436,44.807137],"type":"Point"}
}