{
  "type": "Feature",
  "properties": {
    "iso:country":"US",
    "sg:address":"4201 W Division St",
    "sg:city":"St Cloud",
    "sg:classifiers":[
        {
            "category":"Shopping",
            "subcategory":"Shoes",
            "type":"Retail Goods"
        }
    ],
    "sg:phone":"+1 320 259 9009",
    "sg:postcode":"56301",
    "sg:province":"MN",
    "wof:name":"Journeys",
    "wof:placetype":"venue"
},
  "geometry": {"coordinates":[-94.212526,45.553478],"type":"Point"}
}