{
  "type": "Feature",
  "properties": {
    "iso:country":"US",
    "sg:address":"11968 Hwy 25",
    "sg:city":"Watertown",
    "sg:classifiers":[
        {
            "category":"Wholesale",
            "subcategory":"Machinery & Supplies",
            "type":"Manufacturing & Wholesale Goods"
        },
        {
            "category":"Home & Garden",
            "subcategory":"Garden Supply",
            "type":"Retail Goods"
        }
    ],
    "sg:phone":"+1 952 955 3313",
    "sg:postcode":"55388",
    "sg:province":"MN",
    "sg:tags":[
        "sprinkler"
    ],
    "wof:name":"Greenhead Irrigation LLP",
    "wof:placetype":"venue"
},
  "geometry": {"coordinates":[-93.889353,44.978903],"type":"Point"}
}