{
  "type": "Feature",
  "properties": {
    "addr:full":"519 Dill Ave SW Madelia MN 56062",
    "addr:housenumber":"519",
    "addr:postcode":"56062",
    "addr:street":"Dill Ave Sw",
    "iso:country":"US",
    "sg:address":"519 Dill Ave SW",
    "sg:city":"Madelia",
    "sg:classifiers":[
        {
            "category":"Recreation",
            "type":"Entertainment"
        }
    ],
    "sg:phone":"+1 507 642 8952",
    "sg:postcode":"56062",
    "sg:province":"MN",
    "wof:name":"Madelia Swimming Pool",
    "wof:placetype":"venue"
},
  "geometry": {"coordinates":[-94.42257600000001,44.045491],"type":"Point"}
}