{
  "type": "Feature",
  "properties": {
    "addr:full":"7259 County Road 226 Meadowlands MN 55765",
    "addr:housenumber":"7259",
    "addr:postcode":"55765",
    "addr:street":"County Road 226",
    "iso:country":"US",
    "sg:address":"7259 County Road 226",
    "sg:city":"Meadowlands",
    "sg:classifiers":[
        {
            "category":"Restaurant",
            "type":"Food & Drink"
        }
    ],
    "sg:phone":"+1 218 427 2612",
    "sg:postcode":"55765",
    "sg:province":"MN",
    "wof:name":"Bridgemans Embers Of America",
    "wof:placetype":"venue"
},
  "geometry": {"coordinates":[-92.763903,47.030165],"type":"Point"}
}