{
  "type": "Feature",
  "properties": {
    "iso:country":"US",
    "sg:address":"304 5th St E",
    "sg:city":"Halstad",
    "sg:classifiers":[
        {
            "category":"Organizations",
            "subcategory":"Religious Organization",
            "type":"Services"
        }
    ],
    "sg:phone":"+1 218 456 2144",
    "sg:postcode":"56548",
    "sg:province":"MN",
    "sg:tags":[
        "church"
    ],
    "wof:name":"Halstad Lutheran Church",
    "wof:placetype":"venue"
},
  "geometry": {"coordinates":[-96.823936,47.349625],"type":"Point"}
}