{
  "type": "Feature",
  "properties": {
    "iso:country":"US",
    "sg:address":"200 6th St S",
    "sg:city":"Minneapolis",
    "sg:classifiers":[
        {
            "category":"Professional",
            "subcategory":"Lawyer & Legal Services",
            "type":"Services"
        }
    ],
    "sg:phone":"+1 612 492 7320",
    "sg:postcode":"55402",
    "sg:province":"MN",
    "sg:tags":[
        "attorney"
    ],
    "wof:name":"Nicole M Moen",
    "wof:placetype":"venue"
},
  "geometry": {"coordinates":[-93.26733299999999,44.976112],"type":"Point"}
}