{
  "type": "Feature",
  "properties": {
    "iso:country":"US",
    "sg:address":"28518 E Hwy 55",
    "sg:city":"Paynesville",
    "sg:classifiers":[
        {
            "category":"Sports & Exercise",
            "subcategory":"Gym",
            "type":"Entertainment"
        }
    ],
    "sg:phone":"+1 320 243 4232",
    "sg:postcode":"56362",
    "sg:province":"MN",
    "sg:tags":[
        "club",
        "health",
        "studio",
        "gymnasium"
    ],
    "wof:name":"LA Physique",
    "wof:placetype":"venue"
},
  "geometry": {"coordinates":[-94.70527,45.361736],"type":"Point"}
}