{
  "type": "Feature",
  "properties": {
    "addr:full":"411 Beltrami Ave NW Bemidji MN 56601",
    "addr:housenumber":"411",
    "addr:postcode":"56601",
    "addr:street":"Beltrami Ave Nw",
    "iso:country":"US",
    "sg:address":"411 Beltrami Ave NW",
    "sg:city":"Bemidji",
    "sg:classifiers":[
        {
            "category":"Shopping",
            "subcategory":"Used Merchandise",
            "type":"Retail Goods"
        }
    ],
    "sg:phone":"+1 218 751 4241",
    "sg:postcode":"56601",
    "sg:province":"MN",
    "wof:name":"Twice But Nice",
    "wof:placetype":"venue"
},
  "geometry": {"coordinates":[-94.88126,47.472525],"type":"Point"}
}