{
  "type": "Feature",
  "properties": {
    "addr:full":"1428 Nicollet Ave Minneapolis MN 55403",
    "addr:housenumber":"1428",
    "addr:postcode":"55403",
    "addr:street":"Nicollet Ave",
    "iso:country":"US",
    "sg:address":"1428 Nicollet Ave",
    "sg:city":"Minneapolis",
    "sg:classifiers":[
        {
            "category":"Professional",
            "type":"Services"
        }
    ],
    "sg:phone":"+1 612 870 0604",
    "sg:postcode":"55403",
    "sg:province":"MN",
    "wof:name":"Urban Mobile Inc",
    "wof:placetype":"venue"
},
  "geometry": {"coordinates":[-93.27789199999999,44.968301],"type":"Point"}
}