{
  "type": "Feature",
  "properties": {
    "addr:full":"212 Central Ave Osseo MN 55369",
    "addr:housenumber":"212",
    "addr:postcode":"55369",
    "addr:street":"Central Ave",
    "iso:country":"US",
    "sg:address":"212 Central Ave",
    "sg:city":"Osseo",
    "sg:classifiers":[
        {
            "category":"Wholesale",
            "subcategory":"Painting Supplies",
            "type":"Manufacturing & Wholesale Goods"
        },
        {
            "category":"Home & Garden",
            "subcategory":"Building Materials",
            "type":"Retail Goods"
        }
    ],
    "sg:phone":"+1 763 424 7404",
    "sg:postcode":"55369",
    "sg:province":"MN",
    "sg:tags":[
        "paint",
        "wallpaper",
        "wallcoverings"
    ],
    "sg:website":"http://www.osseopaint.com",
    "wof:name":"Osseo Paint & Wallpaper",
    "wof:placetype":"venue"
},
  "geometry": {"coordinates":[-93.40216700000001,45.118312],"type":"Point"}
}