{
  "type": "Feature",
  "properties": {
    "iso:country":"US",
    "sg:address":"200 9th St",
    "sg:city":"Internatl Falls",
    "sg:classifiers":[
        {
            "category":"Home & Garden",
            "subcategory":"Building Materials",
            "type":"Retail Goods"
        }
    ],
    "sg:phone":"+1 218 283 9404",
    "sg:postcode":"56649",
    "sg:province":"MN",
    "sg:tags":[
        "glass",
        "window",
        "plate"
    ],
    "wof:name":"Glass Doctor",
    "wof:placetype":"venue"
},
  "geometry": {"coordinates":[-93.40313500000001,48.596457],"type":"Point"}
}