{
  "type": "Feature",
  "properties": {
    "iso:country":"US",
    "sg:address":"1672 Brunswick Ave S",
    "sg:city":"Minneapolis",
    "sg:classifiers":[
        {
            "category":"Professional",
            "type":"Services"
        }
    ],
    "sg:phone":"+1 952 525 9897",
    "sg:postcode":"55416",
    "sg:province":"MN",
    "wof:name":"Micromac Ltd",
    "wof:placetype":"venue"
},
  "geometry": {"coordinates":[-93.358992,44.964996],"type":"Point"}
}