{
  "type": "Feature",
  "properties": {
    "iso:country":"US",
    "sg:address":"16420 N Hillcrest Ct",
    "sg:city":"Eden Prairie",
    "sg:classifiers":[
        {
            "category":"Professional",
            "type":"Services"
        }
    ],
    "sg:phone":"+1 952 975 9173",
    "sg:postcode":"55346",
    "sg:province":"MN",
    "wof:name":"Metropcworks",
    "wof:placetype":"venue"
},
  "geometry": {"coordinates":[-93.487573,44.874624],"type":"Point"}
}