{
  "type": "Feature",
  "properties": {
    "iso:country":"US",
    "sg:address":"59550 273rd St",
    "sg:city":"Brownsdale",
    "sg:classifiers":[
        {
            "category":"Retail",
            "subcategory":"Repair Shop",
            "type":"Services"
        }
    ],
    "sg:phone":"+1 507 567 2155",
    "sg:postcode":"55918",
    "sg:province":"MN",
    "sg:tags":[
        "welding"
    ],
    "wof:name":"Gillette Welding & Fabrication",
    "wof:placetype":"venue"
},
  "geometry": {"coordinates":[-92.858249,43.750557],"type":"Point"}
}