{
  "type": "Feature",
  "properties": {
    "addr:full":"110 7th St NW Willmar MN 56201",
    "addr:housenumber":"110",
    "addr:postcode":"56201",
    "addr:street":"7Th St Nw",
    "iso:country":"US",
    "sg:address":"110 7th St NW",
    "sg:city":"Willmar",
    "sg:classifiers":[
        {
            "category":"Building & Trades",
            "subcategory":"Construction",
            "type":"Services"
        }
    ],
    "sg:phone":"+1 320 214 7302",
    "sg:postcode":"56201",
    "sg:province":"MN",
    "sg:tags":[
        "painter"
    ],
    "wof:name":"Affordable Painting",
    "wof:placetype":"venue"
},
  "geometry": {"coordinates":[-95.052663,45.122437],"type":"Point"}
}