{
  "type": "Feature",
  "properties": {
    "iso:country":"US",
    "sg:address":"510 W Hwy 60",
    "sg:city":"Elysian",
    "sg:classifiers":[
        {
            "category":"Restaurant",
            "type":"Food & Drink"
        }
    ],
    "sg:phone":"+1 507 267 4646",
    "sg:postcode":"56028",
    "sg:province":"MN",
    "sg:tags":[
        "eating"
    ],
    "wof:name":"Bear's Den",
    "wof:placetype":"venue"
},
  "geometry": {"coordinates":[-93.681927,44.198129],"type":"Point"}
}