{
  "type": "Feature",
  "properties": {
    "iso:country":"US",
    "sg:address":"11877 260 Ave",
    "sg:city":"Detroit Lakes",
    "sg:classifiers":[
        {
            "category":"Farming",
            "subcategory":"Dairy Farm",
            "type":"Manufacturing & Wholesale Goods"
        }
    ],
    "sg:phone":"+1 218 847 4340",
    "sg:postcode":"56501",
    "sg:province":"MN",
    "wof:name":"Clearview Dairy Farm Inc",
    "wof:placetype":"venue"
},
  "geometry": {"coordinates":[-95.85884900000001,46.719508],"type":"Point"}
}