{
  "type": "Feature",
  "properties": {
    "addr:full":"1526 Queen Ave N Minneapolis MN 55411",
    "addr:housenumber":"1526",
    "addr:postcode":"55411",
    "addr:street":"Queen Ave N",
    "iso:country":"US",
    "sg:address":"1526 Queen Ave N",
    "sg:city":"Minneapolis",
    "sg:classifiers":[
        {
            "category":"Place Of Worship",
            "subcategory":"Church",
            "type":"Public Place"
        },
        {
            "category":"Place Of Worship",
            "type":"Public Place"
        }
    ],
    "sg:phone":"+1 612 521 3586",
    "sg:postcode":"55411",
    "sg:province":"MN",
    "sg:tags":[
        "churches-interdenominational",
        "churches-various",
        "denomination"
    ],
    "wof:name":"Open Door House Of Prayer",
    "wof:placetype":"venue"
},
  "geometry": {"coordinates":[-93.30947999999999,44.994082],"type":"Point"}
}