{
  "type": "Feature",
  "properties": {
    "addr:full":"1041 Ashland Ave Saint Paul Park MN 55071",
    "addr:housenumber":"1041",
    "addr:postcode":"55071",
    "addr:street":"Ashland Ave;Park",
    "iso:country":"US",
    "sg:address":"1041 Ashland Ave",
    "sg:city":"Saint Paul Park",
    "sg:classifiers":[
        {
            "category":"Real Estate",
            "subcategory":"Developer",
            "type":"Services"
        }
    ],
    "sg:phone":"+1 651 459 9356",
    "sg:postcode":"55071",
    "sg:province":"MN",
    "sg:tags":[
        "cemetery"
    ],
    "wof:name":"Newport Cemetery Assoc",
    "wof:placetype":"venue"
},
  "geometry": {"coordinates":[-92.987133,44.839281],"type":"Point"}
}