{
  "type": "Feature",
  "properties": {
    "iso:country":"US",
    "sg:address":"143 E Main St",
    "sg:city":"Albert Lea",
    "sg:classifiers":[
        {
            "category":"Taxi",
            "type":"Transportation"
        }
    ],
    "sg:phone":"+1 507 373 3800",
    "sg:postcode":"56007",
    "sg:province":"MN",
    "sg:tags":[
        "taxicab"
    ],
    "wof:name":"AB Taxi",
    "wof:placetype":"venue"
},
  "geometry": {"coordinates":[-93.367789,43.647975],"type":"Point"}
}