{
  "type": "Feature",
  "properties": {
    "addr:full":"4950 Rebecca Park Trl Loretto MN 55357",
    "addr:housenumber":"4950",
    "addr:postcode":"55357",
    "addr:street":"Rebecca Park Trl",
    "iso:country":"US",
    "sg:address":"4950 Rebecca Park Trl",
    "sg:city":"Loretto",
    "sg:classifiers":[
        {
            "category":"Utilities",
            "subcategory":"Refuse",
            "type":"Services"
        }
    ],
    "sg:phone":"+1 763 560 2385",
    "sg:postcode":"55357",
    "sg:province":"MN",
    "sg:tags":[
        "garbage",
        "collection"
    ],
    "wof:name":"Roll Off CCS Containers",
    "wof:placetype":"venue"
},
  "geometry": {"coordinates":[-93.64666699999999,45.094626],"type":"Point"}
}