{
  "type": "Feature",
  "properties": {
    "iso:country":"US",
    "sg:address":"74727 265th St",
    "sg:city":"Grand Meadow",
    "sg:classifiers":[
        {
            "category":"Organizations",
            "subcategory":"Religious Organization",
            "type":"Services"
        }
    ],
    "sg:phone":"+1 507 754 5914",
    "sg:postcode":"55936",
    "sg:province":"MN",
    "sg:tags":[
        "church"
    ],
    "wof:name":"Bear Creek Lutheran Church",
    "wof:placetype":"venue"
},
  "geometry": {"coordinates":[-92.55223100000001,43.739389],"type":"Point"}
}