{
  "type": "Feature",
  "properties": {
    "iso:country":"US",
    "sg:address":"112 5th Ave SE",
    "sg:city":"Waseca",
    "sg:classifiers":[
        {
            "category":"Wholesale",
            "subcategory":"Toys & Hobbies",
            "type":"Manufacturing & Wholesale Goods"
        }
    ],
    "sg:phone":"+1 507 835 5624",
    "sg:postcode":"56093",
    "sg:province":"MN",
    "sg:tags":[
        "gambling",
        "supply",
        "specialty",
        "item"
    ],
    "wof:name":"M Peters Enterprises Inc",
    "wof:placetype":"venue"
},
  "geometry": {"coordinates":[-93.507599,44.074995],"type":"Point"}
}