{
  "type": "Feature",
  "properties": {
    "addr:full":"7162 165th Ave Becker MN 55308",
    "addr:housenumber":"7162",
    "addr:postcode":"55308",
    "addr:street":"165Th Ave",
    "iso:country":"US",
    "sg:address":"7162 165th Ave",
    "sg:city":"Becker",
    "sg:classifiers":[
        {
            "category":"Building & Trades",
            "subcategory":"Landscaping Services",
            "type":"Services"
        }
    ],
    "sg:phone":"+1 763 261 5363",
    "sg:postcode":"55308",
    "sg:province":"MN",
    "wof:name":"Becker Sod",
    "wof:placetype":"venue"
},
  "geometry": {"coordinates":[-93.820138,45.46571],"type":"Point"}
}