{
  "type": "Feature",
  "properties": {
    "addr:full":"21 Oak Ave S Maple Lake MN 55358",
    "addr:housenumber":"21",
    "addr:postcode":"55358",
    "addr:street":"Oak Ave S Maple Lake",
    "iso:country":"US",
    "sg:address":"21 Oak Ave S",
    "sg:city":"Maple Lake",
    "sg:classifiers":[
        {
            "category":"Building & Trades",
            "subcategory":"Plumbing",
            "type":"Services"
        }
    ],
    "sg:phone":"+1 320 963 2071",
    "sg:postcode":"55358",
    "sg:province":"MN",
    "sg:tags":[
        "heating",
        "contractor"
    ],
    "wof:name":"C & C Hvac Inc",
    "wof:placetype":"venue"
},
  "geometry": {"coordinates":[-94.001931,45.22961],"type":"Point"}
}