{
  "type": "Feature",
  "properties": {
    "addr:full":"305 2nd St Hardwick MN 56134",
    "addr:housenumber":"305",
    "addr:postcode":"56134",
    "addr:street":"2Nd St",
    "iso:country":"US",
    "sg:address":"305 2nd St",
    "sg:city":"Hardwick",
    "sg:classifiers":[
        {
            "category":"Organizations",
            "subcategory":"Religious Organization",
            "type":"Services"
        }
    ],
    "sg:phone":"+1 507 669 2855",
    "sg:postcode":"56134",
    "sg:province":"MN",
    "sg:tags":[
        "church"
    ],
    "wof:name":"Zion Lutheran Church",
    "wof:placetype":"venue"
},
  "geometry": {"coordinates":[-96.195521,43.776715],"type":"Point"}
}