{
  "type": "Feature",
  "properties": {
    "addr:full":"3600 Minnesota Dr Edina MN 55435",
    "addr:housenumber":"3600",
    "addr:postcode":"55435",
    "addr:street":"Minnesota Dr",
    "iso:country":"US",
    "sg:address":"3600 Minnesota Dr",
    "sg:city":"Edina",
    "sg:classifiers":[
        {
            "category":"Banks & Credit Unions",
            "subcategory":"Bank",
            "type":"Services"
        }
    ],
    "sg:phone":"+1 952 842 0181",
    "sg:postcode":"55435",
    "sg:province":"MN",
    "sg:tags":[
        "financing"
    ],
    "wof:name":"Tate Capital Partners",
    "wof:placetype":"venue"
},
  "geometry": {"coordinates":[-93.32443499999999,44.862376],"type":"Point"}
}