{
  "type": "Feature",
  "properties": {
    "iso:country":"US",
    "sg:address":"3757 211th Ln NW",
    "sg:city":"Anoka",
    "sg:classifiers":[
        {
            "category":"Real Estate",
            "subcategory":"Real Estate Agent",
            "type":"Services"
        }
    ],
    "sg:phone":"+1 763 753 0487",
    "sg:postcode":"55303",
    "sg:province":"MN",
    "wof:name":"Northern Metro Realty Corp",
    "wof:placetype":"venue"
},
  "geometry": {"coordinates":[-93.360461,45.353669],"type":"Point"}
}