{
  "type": "Feature",
  "properties": {
    "iso:country":"US",
    "sg:address":"21 2nd St",
    "sg:city":"Grand Marais",
    "sg:classifiers":[
        {
            "category":"Social Services",
            "type":"Services"
        }
    ],
    "sg:phone":"+1 218 387 2216",
    "sg:postcode":"55604",
    "sg:province":"MN",
    "sg:tags":[
        "information",
        "planning",
        "center",
        "family"
    ],
    "wof:name":"Family Planning Special Prjct",
    "wof:placetype":"venue"
},
  "geometry": {"coordinates":[-90.33455499999999,47.751889],"type":"Point"}
}