{
  "type": "Feature",
  "properties": {
    "addr:full":"567 Oak St Dawson MN 56232",
    "addr:housenumber":"567",
    "addr:postcode":"56232",
    "addr:street":"Oak St",
    "iso:country":"US",
    "sg:address":"567 Oak St",
    "sg:city":"Dawson",
    "sg:classifiers":[
        {
            "category":"Restaurant",
            "type":"Food & Drink"
        }
    ],
    "sg:menulink":"http://www.allmenus.com/mn/dawson/225546-caseys-general-store/menu/",
    "sg:phone":"+1 320 769 4511",
    "sg:postcode":"56232",
    "sg:province":"MN",
    "sg:tags":[
        "american",
        "pizza"
    ],
    "wof:name":"Casey's General Store",
    "wof:placetype":"venue"
},
  "geometry": {"coordinates":[-96.054147,44.935807],"type":"Point"}
}