{
  "type": "Feature",
  "properties": {
    "addr:full":"7200 Upton Ave S Minneapolis MN 55423",
    "addr:housenumber":"7200",
    "addr:postcode":"55423",
    "addr:street":"Upton Ave S",
    "iso:country":"US",
    "sg:address":"7200 Upton Ave S",
    "sg:city":"Minneapolis",
    "sg:classifiers":[
        {
            "category":"Social Services",
            "subcategory":"Child Care",
            "type":"Services"
        }
    ],
    "sg:phone":"+1 612 866 3410",
    "sg:postcode":"55423",
    "sg:province":"MN",
    "sg:tags":[
        "daycare"
    ],
    "wof:name":"Jones Catherine",
    "wof:placetype":"venue"
},
  "geometry": {"coordinates":[-93.314978,44.870926],"type":"Point"}
}