{
  "type": "Feature",
  "properties": {
    "addr:full":"12659 Co Rd 10 Caledonia MN 55921",
    "addr:housenumber":"12659;10",
    "addr:postcode":"55921",
    "addr:street":"Co Rd",
    "iso:country":"US",
    "sg:address":"12659 Co Rd 10",
    "sg:city":"Caledonia",
    "sg:classifiers":[
        {
            "category":"Social Services",
            "subcategory":"Child Care",
            "type":"Services"
        }
    ],
    "sg:phone":"+1 507 724 2295",
    "sg:postcode":"55921",
    "sg:province":"MN",
    "sg:tags":[
        "day",
        "provider"
    ],
    "wof:name":"Caroline H Heimerdinger",
    "wof:placetype":"venue"
},
  "geometry": {"coordinates":[-91.531397,43.659523],"type":"Point"}
}