{
  "type": "Feature",
  "properties": {
    "addr:full":"16985 Kenyon Ave Lakeville MN 55044",
    "addr:housenumber":"16985",
    "addr:postcode":"55044",
    "addr:street":"Kenyon Ave",
    "iso:country":"US",
    "sg:address":"16985 Kenyon Ave",
    "sg:city":"Lakeville",
    "sg:classifiers":[
        {
            "category":"Home & Garden",
            "subcategory":"Carpets & Floor Coverings",
            "type":"Retail Goods"
        }
    ],
    "sg:phone":"+1 952 435 6354",
    "sg:postcode":"55044",
    "sg:province":"MN",
    "sg:tags":[
        "carpeting"
    ],
    "sg:website":"www.floordealers/Ccflooring.Com",
    "wof:name":"C & C Flooring Inc",
    "wof:placetype":"venue"
},
  "geometry": {"coordinates":[-93.28624000000001,44.703739],"type":"Point"}
}