{
  "type": "Feature",
  "properties": {
    "addr:full":"10905 Xerxes Ave S Minneapolis MN 55431",
    "addr:housenumber":"10905",
    "addr:postcode":"55431",
    "addr:street":"Xerxes Ave S",
    "iso:country":"US",
    "sg:address":"10905 Xerxes Ave S",
    "sg:city":"Minneapolis",
    "sg:classifiers":[
        {
            "category":"Social Services",
            "subcategory":"Child Care",
            "type":"Services"
        }
    ],
    "sg:phone":"+1 952 885 9715",
    "sg:postcode":"55431",
    "sg:province":"MN",
    "sg:tags":[
        "daycare",
        "provider"
    ],
    "wof:name":"J C Child Care",
    "wof:placetype":"venue"
},
  "geometry": {"coordinates":[-93.31930199999999,44.806631],"type":"Point"}
}