{
  "type": "Feature",
  "properties": {
    "addr:full":"5500 Wayzata Blvd. Suite 215 Golden Valley MN 55416",
    "addr:housenumber":"5500",
    "addr:postcode":"55416",
    "addr:street":"Wayzata Blvd. Suite 215",
    "iso:country":"US",
    "sg:address":"5500 Wayzata Blvd. Suite 215",
    "sg:city":"Golden Valley",
    "sg:classifiers":[
        {
            "category":"Professional",
            "subcategory":"Computer Services",
            "type":"Services"
        }
    ],
    "sg:phone":"+1 877 452 7342",
    "sg:postcode":"55416",
    "sg:province":"MN",
    "sg:tags":[
        "healthcare",
        "information-technology",
        "saas"
    ],
    "sg:website":"http://www.kardiahealth.com/",
    "wof:name":"Kardia Health Systems",
    "wof:placetype":"venue"
},
  "geometry": {"coordinates":[-93.32874200000001,44.969851],"type":"Point"}
}