{
  "type": "Feature",
  "properties": {
    "iso:country":"US",
    "sg:address":"1900 Silver Lake Rd NW",
    "sg:city":"Saint Paul",
    "sg:classifiers":[
        {
            "category":"Professional",
            "subcategory":"Engineering",
            "type":"Services"
        }
    ],
    "sg:phone":"+1 651 631 8838",
    "sg:postcode":"55112",
    "sg:province":"MN",
    "wof:name":"Dames & Moore",
    "wof:placetype":"venue"
},
  "geometry": {"coordinates":[-93.218985,45.080928],"type":"Point"}
}