{
  "type": "Feature",
  "properties": {
    "iso:country":"US",
    "sg:address":"310 Jansa Dr",
    "sg:city":"Saint Paul",
    "sg:classifiers":[
        {
            "category":"Insurance",
            "subcategory":"Insurance Agent",
            "type":"Services"
        }
    ],
    "sg:phone":"+1 651 483 8079",
    "sg:postcode":"55126",
    "sg:province":"MN",
    "wof:name":"Lynn OLeary",
    "wof:placetype":"venue"
},
  "geometry": {"coordinates":[-93.111422,45.07506],"type":"Point"}
}