{
  "type": "Feature",
  "properties": {
    "addr:full":"19504 Hwy 27 Little Falls MN 56345",
    "addr:housenumber":"19504",
    "addr:postcode":"56345",
    "addr:street":"Hwy 27",
    "iso:country":"US",
    "sg:address":"19504 Hwy 27",
    "sg:city":"Little Falls",
    "sg:classifiers":[
        {
            "category":"Organizations",
            "subcategory":"Membership Organization",
            "type":"Services"
        }
    ],
    "sg:phone":"+1 320 632 0527",
    "sg:postcode":"56345",
    "sg:province":"MN",
    "sg:tags":[
        "provide",
        "need",
        "disability",
        "for",
        "people"
    ],
    "wof:name":"Green Pastures Inc",
    "wof:placetype":"venue"
},
  "geometry": {"coordinates":[-94.245406,45.970692],"type":"Point"}
}