{
  "type": "Feature",
  "properties": {
    "addr:full":"1207 Lake Ave Fairmont MN 56031",
    "addr:housenumber":"1207",
    "addr:postcode":"56031",
    "addr:street":"Lake Ave",
    "iso:country":"US",
    "sg:address":"1207 Lake Ave",
    "sg:city":"Fairmont",
    "sg:classifiers":[
        {
            "category":"Shopping",
            "type":"Retail Goods"
        }
    ],
    "sg:phone":"+1 507 235 5108",
    "sg:postcode":"56031",
    "sg:province":"MN",
    "sg:tags":[
        "monument"
    ],
    "wof:name":"Fairmont Monument Co",
    "wof:placetype":"venue"
},
  "geometry": {"coordinates":[-94.484025,43.659214],"type":"Point"}
}