{
  "type": "Feature",
  "properties": {
    "addr:full":"675 E Nicollet Blvd Ste 100 Burnsville MN 55337",
    "addr:housenumber":"675",
    "addr:postcode":"55337",
    "addr:street":"E Nicollet Blvd Ste 100",
    "iso:country":"US",
    "sg:address":"675 E Nicollet Blvd Ste 100",
    "sg:city":"Burnsville",
    "sg:classifiers":[
        {
            "category":"Health Services",
            "subcategory":"Clinic",
            "type":"Services"
        }
    ],
    "sg:phone":"+1 952 435 8516",
    "sg:postcode":"55337",
    "sg:province":"MN",
    "wof:name":"Abols, Ingrid A, Md - Minneapolis Clinic-Neurology",
    "wof:placetype":"venue"
},
  "geometry": {"coordinates":[-93.26728,44.751577],"type":"Point"}
}