{
  "type": "Feature",
  "properties": {
    "iso:country":"US",
    "sg:address":"7060 Springhill Cir",
    "sg:city":"Eden Prairie",
    "sg:classifiers":[
        {
            "category":"Health Services",
            "subcategory":"Health Practitioner",
            "type":"Services"
        }
    ],
    "sg:phone":"+1 952 936 8437",
    "sg:postcode":"55346",
    "sg:province":"MN",
    "sg:tags":[
        "therapy",
        "physical"
    ],
    "wof:name":"Enterostomal Therapy-Pat Keegan",
    "wof:placetype":"venue"
},
  "geometry": {"coordinates":[-93.46929900000001,44.874802],"type":"Point"}
}