{
  "type": "Feature",
  "properties": {
    "iso:country":"US",
    "sg:address":"9 1st St NE",
    "sg:city":"Deer River",
    "sg:classifiers":[
        {
            "category":"Banks & Credit Unions",
            "subcategory":"Financial Services",
            "type":"Services"
        }
    ],
    "sg:phone":"+1 218 246 8221",
    "sg:postcode":"56636",
    "sg:province":"MN",
    "sg:tags":[
        "company",
        "holding"
    ],
    "wof:name":"First National Agency Co",
    "wof:placetype":"venue"
},
  "geometry": {"coordinates":[-93.792795,47.332834],"type":"Point"}
}