{
  "type": "Feature",
  "properties": {
    "addr:full":"1755 S Broadway Rochester MN 55904",
    "addr:housenumber":"1755",
    "addr:postcode":"55904",
    "addr:street":"S Broadway",
    "iso:country":"US",
    "sg:address":"1755 S Broadway",
    "sg:city":"Rochester",
    "sg:classifiers":[
        {
            "category":"Travel",
            "subcategory":"Hotels & Motels",
            "type":"Entertainment"
        }
    ],
    "sg:phone":"+1 507 287 9050",
    "sg:postcode":"55904",
    "sg:province":"MN",
    "sg:tags":[
        "operation",
        "fitness",
        "physical",
        "facility"
    ],
    "sg:website":"www.hamptoninn.com",
    "wof:name":"Hampton Inn",
    "wof:placetype":"venue"
},
  "geometry": {"coordinates":[-92.46341200000001,43.996449],"type":"Point"}
}