{
  "type": "Feature",
  "properties": {
    "iso:country":"US",
    "sg:address":"1701 S College Rd",
    "sg:city":"Baxter",
    "sg:classifiers":[
        {
            "category":"Communications",
            "subcategory":"Film & Video Production",
            "type":"Services"
        }
    ],
    "sg:phone":"+1 218 829 9500",
    "sg:postcode":"56425",
    "sg:province":"MN",
    "sg:tags":[
        "taping"
    ],
    "wof:name":"Lindner's Angling Edge",
    "wof:placetype":"venue"
},
  "geometry": {"coordinates":[-94.23908,46.344719],"type":"Point"}
}