{
  "type": "Feature",
  "properties": {
    "addr:full":"2567 River Rd Marshall MN 56258",
    "addr:housenumber":"2567",
    "addr:postcode":"56258",
    "addr:street":"River Rd",
    "iso:country":"US",
    "sg:address":"2567 River Rd",
    "sg:city":"Marshall",
    "sg:classifiers":[
        {
            "category":"Banks & Credit Unions",
            "subcategory":"Investment Brokerage",
            "type":"Services"
        }
    ],
    "sg:phone":"+1 612 860 9002",
    "sg:postcode":"56258",
    "sg:province":"MN",
    "sg:tags":[
        "security"
    ],
    "wof:name":"Edward Jones 28191",
    "wof:placetype":"venue"
},
  "geometry": {"coordinates":[-95.85483000000001,44.417089],"type":"Point"}
}