{
  "type": "Feature",
  "properties": {
    "iso:country":"US",
    "sg:address":"3800 W 80th St",
    "sg:city":"Minneapolis",
    "sg:classifiers":[
        {
            "category":"Manufacturing",
            "subcategory":"Electronics",
            "type":"Manufacturing & Wholesale Goods"
        }
    ],
    "sg:phone":"+1 952 831 7847",
    "sg:postcode":"55431",
    "sg:province":"MN",
    "sg:tags":[
        "prerecorded",
        "mfg"
    ],
    "wof:name":"Polygram Records",
    "wof:placetype":"venue"
},
  "geometry": {"coordinates":[-93.328053,44.855769],"type":"Point"}
}