{
  "type": "Feature",
  "properties": {
    "addr:full":"16085 Delarma Dr Carver MN 55315",
    "addr:housenumber":"16085",
    "addr:postcode":"55315",
    "addr:street":"Delarma Dr",
    "iso:country":"US",
    "sg:address":"16085 Delarma Dr",
    "sg:city":"Carver",
    "sg:classifiers":[
        {
            "category":"Retail",
            "subcategory":"Laundry & Dry Cleaning",
            "type":"Services"
        }
    ],
    "sg:phone":"+1 952 448 6912",
    "sg:postcode":"55315",
    "sg:province":"MN",
    "sg:tags":[
        "cleaner",
        "rug",
        "carpet"
    ],
    "wof:name":"Meger's Carpet Cleaning",
    "wof:placetype":"venue"
},
  "geometry": {"coordinates":[-93.645045,44.710475],"type":"Point"}
}