{
  "type": "Feature",
  "properties": {
    "iso:country":"US",
    "sg:address":"506 7th Ave NE",
    "sg:city":"Brainerd",
    "sg:classifiers":[
        {
            "category":"Social Services",
            "subcategory":"Child Care",
            "type":"Services"
        }
    ],
    "sg:phone":"+1 218 825 7432",
    "sg:postcode":"56401",
    "sg:province":"MN",
    "sg:tags":[
        "day",
        "provider"
    ],
    "wof:name":"Foster Homes",
    "wof:placetype":"venue"
},
  "geometry": {"coordinates":[-94.178794,46.364917],"type":"Point"}
}