{
  "type": "Feature",
  "properties": {
    "iso:country":"US",
    "sg:address":"1511 Southview Ln",
    "sg:city":"Albert Lea",
    "sg:classifiers":[
        {
            "category":"Building & Trades",
            "subcategory":"Electrical",
            "type":"Services"
        }
    ],
    "sg:phone":"+1 507 373 1229",
    "sg:postcode":"56007",
    "sg:province":"MN",
    "sg:tags":[
        "electrical",
        "contractor"
    ],
    "wof:name":"Interstate Electric LLC",
    "wof:placetype":"venue"
},
  "geometry": {"coordinates":[-93.388273,43.637119],"type":"Point"}
}