{
  "type": "Feature",
  "properties": {
    "iso:country":"US",
    "sg:address":"2668 McNair Dr N",
    "sg:city":"Minneapolis",
    "sg:classifiers":[
        {
            "category":"Professional",
            "type":"Services"
        }
    ],
    "sg:phone":"+1 763 521 9629",
    "sg:postcode":"55422",
    "sg:province":"MN",
    "wof:name":"Hollander Horizon Intl",
    "wof:placetype":"venue"
},
  "geometry": {"coordinates":[-93.32654100000001,45.00732],"type":"Point"}
}