{
  "type": "Feature",
  "properties": {
    "addr:full":"455 US Hwy 12 Benson MN 56215",
    "addr:housenumber":"455",
    "addr:postcode":"56215",
    "addr:street":"Us Hwy 12",
    "iso:country":"US",
    "sg:address":"455 US Hwy 12",
    "sg:city":"Benson",
    "sg:classifiers":[
        {
            "category":"Building & Trades",
            "subcategory":"Construction",
            "type":"Services"
        }
    ],
    "sg:phone":"+1 320 843 2678",
    "sg:postcode":"56215",
    "sg:province":"MN",
    "sg:tags":[
        "concrete",
        "contractor"
    ],
    "wof:name":"Molden Concrete Construction",
    "wof:placetype":"venue"
},
  "geometry": {"coordinates":[-95.602009,45.311029],"type":"Point"}
}