{
  "type": "Feature",
  "properties": {
    "addr:full":"1952 Mckinley St NE Minneapolis MN 55418",
    "addr:housenumber":"1952",
    "addr:postcode":"55418",
    "addr:street":"Mckinley St Ne",
    "iso:country":"US",
    "sg:address":"1952 Mckinley St NE",
    "sg:city":"Minneapolis",
    "sg:classifiers":[
        {
            "category":"Travel",
            "subcategory":"Travel Agent",
            "type":"Entertainment"
        }
    ],
    "sg:phone":"+1 612 781 7155",
    "sg:postcode":"55418",
    "sg:province":"MN",
    "sg:tags":[
        "agency",
        "services-commercial"
    ],
    "wof:name":"Have Grill Will Travel",
    "wof:placetype":"venue"
},
  "geometry": {"coordinates":[-93.228194,45.008725],"type":"Point"}
}