{
  "type": "Feature",
  "properties": {
    "addr:full":"3441 Willow Ave White Bear Lake MN 55110",
    "addr:housenumber":"3441",
    "addr:postcode":"bear;55110",
    "addr:street":"Willow Ave",
    "iso:country":"US",
    "sg:address":"3441 Willow Ave",
    "sg:city":"White Bear Lake",
    "sg:classifiers":[
        {
            "category":"Real Estate",
            "subcategory":"Real Estate Operator",
            "type":"Services"
        }
    ],
    "sg:phone":"+1 651 748 0084",
    "sg:postcode":"55110",
    "sg:province":"MN",
    "sg:tags":[
        "apartment"
    ],
    "wof:name":"Willow Wood Apartments",
    "wof:placetype":"venue"
},
  "geometry": {"coordinates":[-93.025648,45.044844],"type":"Point"}
}