{
  "type": "Feature",
  "properties": {
    "iso:country":"US",
    "sg:address":"1015 E 6th St",
    "sg:city":"Blue Earth",
    "sg:classifiers":[
        {
            "category":"Wholesale",
            "subcategory":"Auto Parts",
            "type":"Manufacturing & Wholesale Goods"
        }
    ],
    "sg:phone":"+1 507 526 7217",
    "sg:postcode":"56013",
    "sg:province":"MN",
    "wof:name":"Esser Distributing",
    "wof:placetype":"venue"
},
  "geometry": {"coordinates":[-94.089297,43.638802],"type":"Point"}
}