{
  "type": "Feature",
  "properties": {
    "iso:country":"US",
    "sg:address":"3020 Centerville Rd",
    "sg:city":"St Paul",
    "sg:classifiers":[
        {
            "category":"Wholesale",
            "subcategory":"Machinery & Supplies",
            "type":"Manufacturing & Wholesale Goods"
        }
    ],
    "sg:phone":"+1 651 771 8874",
    "sg:postcode":"55117",
    "sg:province":"MN",
    "sg:tags":[
        "sprinkler"
    ],
    "wof:name":"Escape Fire Protection",
    "wof:placetype":"venue"
},
  "geometry": {"coordinates":[-93.085779,45.034127],"type":"Point"}
}