{
  "type": "Feature",
  "properties": {
    "iso:country":"US",
    "sg:address":"6600 France Ave S",
    "sg:city":"Edina",
    "sg:classifiers":[
        {
            "category":"Health Services",
            "subcategory":"Health Practitioner",
            "type":"Services"
        }
    ],
    "sg:phone":"+1 952 922 5427",
    "sg:postcode":"55435",
    "sg:province":"MN",
    "sg:tags":[
        "psychologist"
    ],
    "wof:name":"Cindy D Nollette",
    "wof:placetype":"venue"
},
  "geometry": {"coordinates":[-93.32894899999999,44.879861],"type":"Point"}
}