{
  "type": "Feature",
  "properties": {
    "addr:full":"403 2nd St SE Wadena MN 56482",
    "addr:housenumber":"403",
    "addr:postcode":"56482",
    "addr:street":"2Nd St Se",
    "iso:country":"US",
    "sg:address":"403 2nd St SE",
    "sg:city":"Wadena",
    "sg:classifiers":[
        {
            "category":"Organizations",
            "subcategory":"Religious Organization",
            "type":"Services"
        }
    ],
    "sg:phone":"+1 218 631 2738",
    "sg:postcode":"56482",
    "sg:province":"MN",
    "sg:tags":[
        "church"
    ],
    "sg:website":"www.wadenaimmanuellutheran.com",
    "wof:name":"Immanuel Lutheran Church",
    "wof:placetype":"venue"
},
  "geometry": {"coordinates":[-95.136358,46.437422],"type":"Point"}
}