{
  "type": "Feature",
  "properties": {
    "addr:full":"2081 E Hyacinth Ave Saint Paul MN 55119",
    "addr:housenumber":"2081",
    "addr:postcode":"55119",
    "addr:street":"E Hyacinth Ave",
    "iso:country":"US",
    "sg:address":"2081 E Hyacinth Ave",
    "sg:city":"Saint Paul",
    "sg:classifiers":[
        {
            "category":"Building & Trades",
            "subcategory":"Construction",
            "type":"Services"
        }
    ],
    "sg:phone":"+1 651 772 2610",
    "sg:postcode":"55119",
    "sg:province":"MN",
    "sg:tags":[
        "house"
    ],
    "wof:name":"RG Remodelers",
    "wof:placetype":"venue"
},
  "geometry": {"coordinates":[-93.01468199999999,44.980282],"type":"Point"}
}