{
  "type": "Feature",
  "properties": {
    "addr:full":"740 Harding St NE Minneapolis MN 55413",
    "addr:housenumber":"740",
    "addr:postcode":"55413",
    "addr:street":"Harding St Ne",
    "iso:country":"US",
    "sg:address":"740 Harding St NE",
    "sg:city":"Minneapolis",
    "sg:classifiers":[
        {
            "category":"Professional",
            "subcategory":"Advertising",
            "type":"Services"
        }
    ],
    "sg:phone":"+1 612 331 4830",
    "sg:postcode":"55413",
    "sg:province":"MN",
    "sg:tags":[
        "distribution"
    ],
    "wof:name":"Absolute Distribution",
    "wof:placetype":"venue"
},
  "geometry": {"coordinates":[-93.2218,44.998567],"type":"Point"}
}