{
  "type": "Feature",
  "properties": {
    "iso:country":"US",
    "sg:address":"35386 Co Rd 177",
    "sg:city":"Grand Rapids",
    "sg:classifiers":[
        {
            "category":"Organizations",
            "subcategory":"Religious Organization",
            "type":"Services"
        }
    ],
    "sg:phone":"+1 218 326 1041",
    "sg:postcode":"55744",
    "sg:province":"MN",
    "wof:name":"Calvary Pines Baptist Church",
    "wof:placetype":"venue"
},
  "geometry": {"coordinates":[-93.60745900000001,47.34003],"type":"Point"}
}