{
  "type": "Feature",
  "properties": {
    "addr:full":"101 Main St S Hutchinson MN 55350",
    "addr:housenumber":"101",
    "addr:postcode":"55350",
    "addr:street":"Main St S Hutchinson",
    "iso:country":"US",
    "sg:address":"101 Main St S",
    "sg:city":"Hutchinson",
    "sg:classifiers":[
        {
            "category":"Freight",
            "type":"Transportation"
        },
        {
            "category":"Professional",
            "subcategory":"Business Services",
            "type":"Services"
        }
    ],
    "sg:phone":"+1 320 587 9226",
    "sg:postcode":"55350",
    "sg:province":"MN",
    "sg:tags":[
        "shipping",
        "agent"
    ],
    "wof:name":"Drop N Go Shipping Inc",
    "wof:placetype":"venue"
},
  "geometry": {"coordinates":[-94.369281,44.891103],"type":"Point"}
}