{
  "type": "Feature",
  "properties": {
    "addr:full":"5041 Haenke Rd Mountain Iron MN 55768",
    "addr:housenumber":"5041",
    "addr:postcode":"55768",
    "addr:street":"Haenke Rd",
    "iso:country":"US",
    "sg:address":"5041 Haenke Rd",
    "sg:city":"Mountain Iron",
    "sg:classifiers":[
        {
            "category":"Retail",
            "subcategory":"Portrait Studio",
            "type":"Services"
        }
    ],
    "sg:phone":"+1 218 735 8030",
    "sg:postcode":"55768",
    "sg:province":"MN",
    "sg:tags":[
        "photo"
    ],
    "wof:name":"Hocevar Richard",
    "wof:placetype":"venue"
},
  "geometry": {"coordinates":[-92.624713,47.481799],"type":"Point"}
}