{
  "type": "Feature",
  "properties": {
    "iso:country":"US",
    "sg:address":"13705 27th Ave N",
    "sg:city":"Minneapolis",
    "sg:classifiers":[
        {
            "category":"Restaurant",
            "type":"Food & Drink"
        }
    ],
    "sg:phone":"+1 763 551 0155",
    "sg:postcode":"55441",
    "sg:province":"MN",
    "sg:tags":[
        "pizza"
    ],
    "sg:website":"http://broadwaypizza.com",
    "wof:name":"Broadway Pizza",
    "wof:placetype":"venue"
},
  "geometry": {"coordinates":[-93.454093,45.009202],"type":"Point"}
}