{
  "type": "Feature",
  "properties": {
    "addr:full":"11796 Bass Lake Rd Brainerd MN 56401",
    "addr:housenumber":"11796",
    "addr:postcode":"56401",
    "addr:street":"Bass Lake Rd",
    "iso:country":"US",
    "sg:address":"11796 Bass Lake Rd",
    "sg:city":"Brainerd",
    "sg:classifiers":[
        {
            "category":"Personal",
            "subcategory":"Beauty Salon",
            "type":"Services"
        }
    ],
    "sg:phone":"+1 218 829 8150",
    "sg:postcode":"56401",
    "sg:province":"MN",
    "wof:name":"Renee's Country Salon",
    "wof:placetype":"venue"
},
  "geometry": {"coordinates":[-94.349914,46.377606],"type":"Point"}
}