{
  "type": "Feature",
  "properties": {
    "addr:full":"9009 44th Cir N New Hope MN 55428",
    "addr:housenumber":"9009",
    "addr:postcode":"55428",
    "addr:street":"44Th Cir N",
    "iso:country":"US",
    "sg:address":"9009 44th Cir N",
    "sg:city":"New Hope",
    "sg:classifiers":[
        {
            "category":"Building & Trades",
            "subcategory":"Construction",
            "type":"Services"
        }
    ],
    "sg:phone":"+1 763 535 0708",
    "sg:postcode":"55428",
    "sg:province":"MN",
    "sg:tags":[
        "plastering",
        "contractor"
    ],
    "wof:name":"G S Construction",
    "wof:placetype":"venue"
},
  "geometry": {"coordinates":[-93.395458,45.035496],"type":"Point"}
}