{
  "type": "Feature",
  "properties": {
    "iso:country":"US",
    "sg:address":"4107 14th Ave NW",
    "sg:city":"Rochester",
    "sg:classifiers":[
        {
            "category":"Wholesale",
            "subcategory":"Jewelry",
            "type":"Manufacturing & Wholesale Goods"
        }
    ],
    "sg:phone":"+1 507 285 4930",
    "sg:postcode":"55901",
    "sg:province":"MN",
    "sg:tags":[
        "stone"
    ],
    "wof:name":"Bohemian Belle",
    "wof:placetype":"venue"
},
  "geometry": {"coordinates":[-92.484235,44.066319],"type":"Point"}
}