{
  "type": "Feature",
  "properties": {
    "addr:full":"145 2nd Ave SW Cambridge MN 55008",
    "addr:housenumber":"145",
    "addr:postcode":"55008",
    "addr:street":"2Nd Ave Sw",
    "iso:country":"US",
    "sg:address":"145 2nd Ave SW",
    "sg:city":"Cambridge",
    "sg:classifiers":[
        {
            "category":"Real Estate",
            "subcategory":"Architect",
            "type":"Services"
        }
    ],
    "sg:phone":"+1 763 689 9869",
    "sg:postcode":"55008",
    "sg:province":"MN",
    "sg:tags":[
        "house",
        "designer"
    ],
    "wof:name":"Dave Erickson Designers",
    "wof:placetype":"venue"
},
  "geometry": {"coordinates":[-93.224994,45.57155],"type":"Point"}
}