{
  "type": "Feature",
  "properties": {
    "addr:full":"10704 Pilgrim Ln N Maple Grove MN 55369",
    "addr:housenumber":"10704",
    "addr:postcode":"55369",
    "addr:street":"Pilgrim Ln N",
    "iso:country":"US",
    "sg:address":"10704 Pilgrim Ln N",
    "sg:city":"Maple Grove",
    "sg:classifiers":[
        {
            "category":"Restaurant",
            "type":"Food & Drink"
        }
    ],
    "sg:phone":"+1 763 424 6200",
    "sg:postcode":"55369",
    "sg:province":"MN",
    "sg:tags":[
        "pizza"
    ],
    "wof:name":"Angeno's Pizza and Pasta",
    "wof:placetype":"venue"
},
  "geometry": {"coordinates":[-93.409515,45.14936],"type":"Point"}
}