{
  "type": "Feature",
  "properties": {
    "iso:country":"US",
    "sg:address":"13210 35th Ave N",
    "sg:city":"Minneapolis",
    "sg:classifiers":[
        {
            "category":"Organizations",
            "subcategory":"Membership Organization",
            "type":"Services"
        }
    ],
    "sg:phone":"+1 763 559 1797",
    "sg:postcode":"55441",
    "sg:province":"MN",
    "wof:name":"Oaa",
    "wof:placetype":"venue"
},
  "geometry": {"coordinates":[-93.45051100000001,45.020671],"type":"Point"}
}