{
  "type": "Feature",
  "properties": {
    "addr:full":"909 Main St NE Blaine MN 55434",
    "addr:housenumber":"909",
    "addr:postcode":"55434",
    "addr:street":"Main St Ne",
    "iso:country":"US",
    "sg:address":"909 Main St NE",
    "sg:city":"Blaine",
    "sg:classifiers":[
        {
            "category":"Professional",
            "subcategory":"Management & Consulting",
            "type":"Services"
        }
    ],
    "sg:phone":"+1 612 378 7985",
    "sg:postcode":"55434",
    "sg:province":"MN",
    "sg:tags":[
        "consultant",
        "business"
    ],
    "wof:name":"Northeast Housing Resource Ctr",
    "wof:placetype":"venue"
},
  "geometry": {"coordinates":[-93.24801600000001,45.197252],"type":"Point"}
}