{
  "type": "Feature",
  "properties": {
    "iso:country":"US",
    "sg:address":"2701 17th Ave S",
    "sg:city":"Minneapolis",
    "sg:classifiers":[
        {
            "category":"Organizations",
            "subcategory":"Religious Organization",
            "type":"Services"
        }
    ],
    "sg:phone":"+1 612 874 6333",
    "sg:postcode":"55407",
    "sg:province":"MN",
    "sg:tags":[
        "church"
    ],
    "sg:website":"www.solomonsporch.com",
    "wof:name":"Solomon's Porch",
    "wof:placetype":"venue"
},
  "geometry": {"coordinates":[-93.24992399999999,44.951952],"type":"Point"}
}