{
  "type": "Feature",
  "properties": {
    "addr:full":"116 S 3rd St Saint Peter MN 56082",
    "addr:housenumber":"116",
    "addr:postcode":"56082",
    "addr:street":"S 3Rd St",
    "iso:country":"US",
    "sg:address":"116 S 3rd St",
    "sg:city":"Saint Peter",
    "sg:classifiers":[
        {
            "category":"Health Services",
            "subcategory":"Hospital",
            "type":"Services"
        }
    ],
    "sg:phone":"+1 507 931 0918",
    "sg:postcode":"56082",
    "sg:province":"MN",
    "sg:tags":[
        "specialty"
    ],
    "wof:name":"Charter Bhvioral Hlth Sys St P",
    "wof:placetype":"venue"
},
  "geometry": {"coordinates":[-93.957234,44.326372],"type":"Point"}
}