{
  "type": "Feature",
  "properties": {
    "addr:full":"7800 150th St W Saint Paul MN 55124",
    "addr:housenumber":"7800",
    "addr:postcode":"55124",
    "addr:street":"150Th St W",
    "iso:country":"US",
    "sg:address":"7800 150th St W",
    "sg:city":"Saint Paul",
    "sg:classifiers":[
        {
            "category":"Social Services",
            "subcategory":"Child Care",
            "type":"Services"
        }
    ],
    "sg:phone":"+1 952 432 5451",
    "sg:postcode":"55124",
    "sg:province":"MN",
    "sg:tags":[
        "elementary",
        "kindergarten",
        "school",
        "academic"
    ],
    "wof:name":"Grace Nursery School",
    "wof:placetype":"venue"
},
  "geometry": {"coordinates":[-93.221298,44.731899],"type":"Point"}
}