{
  "type": "Feature",
  "properties": {
    "addr:full":"8201 Pleasant Ave S Minneapolis MN 55420",
    "addr:housenumber":"8201",
    "addr:postcode":"55420",
    "addr:street":"Pleasant Ave S",
    "iso:country":"US",
    "sg:address":"8201 Pleasant Ave S",
    "sg:city":"Minneapolis",
    "sg:classifiers":[
        {
            "category":"Building & Trades",
            "subcategory":"Construction",
            "type":"Services"
        }
    ],
    "sg:phone":"+1 952 888 6333",
    "sg:postcode":"55420",
    "sg:province":"MN",
    "sg:tags":[
        "system",
        "specialty",
        "heating",
        "contractor",
        "air conditioning"
    ],
    "wof:name":"Key Metalcraft Inc",
    "wof:placetype":"venue"
},
  "geometry": {"coordinates":[-93.283287,44.85516],"type":"Point"}
}