{
  "type": "Feature",
  "properties": {
    "addr:full":"1107 Cross St North Mankato MN 56003",
    "addr:housenumber":"1107",
    "addr:postcode":"56003",
    "addr:street":"Cross St North",
    "iso:country":"US",
    "sg:address":"1107 Cross St",
    "sg:city":"North Mankato",
    "sg:classifiers":[
        {
            "category":"Home & Garden",
            "subcategory":"Carpets & Floor Coverings",
            "type":"Retail Goods"
        }
    ],
    "sg:phone":"+1 507 625 3089",
    "sg:postcode":"56003",
    "sg:province":"MN",
    "sg:tags":[
        "dealer",
        "rug"
    ],
    "wof:name":"Rickway Carpet",
    "wof:placetype":"venue"
},
  "geometry": {"coordinates":[-94.011216,44.181809],"type":"Point"}
}