{
  "type": "Feature",
  "properties": {
    "iso:country":"US",
    "sg:address":"337 Co Rd 81",
    "sg:city":"Osseo",
    "sg:classifiers":[
        {
            "category":"Retail",
            "subcategory":"Auto Repair",
            "type":"Services"
        }
    ],
    "sg:phone":"+1 763 425 3868",
    "sg:postcode":"55369",
    "sg:province":"MN",
    "sg:tags":[
        "repairing",
        "automobile",
        "radiator"
    ],
    "wof:name":"Osseo Radiator Repair Shop",
    "wof:placetype":"venue"
},
  "geometry": {"coordinates":[-93.40703499999999,45.118179],"type":"Point"}
}