{
  "type": "Feature",
  "properties": {
    "iso:country":"US",
    "sg:address":"1525 Northway Dr",
    "sg:city":"Saint Cloud",
    "sg:classifiers":[
        {
            "category":"Professional",
            "subcategory":"Management & Consulting",
            "type":"Services"
        }
    ],
    "sg:phone":"+1 320 255 5410",
    "sg:postcode":"56303",
    "sg:province":"MN",
    "sg:tags":[
        "retail",
        "direct",
        "sales"
    ],
    "wof:name":"Amway 528823",
    "wof:placetype":"venue"
},
  "geometry": {"coordinates":[-94.182254,45.578958],"type":"Point"}
}