{
  "type": "Feature",
  "properties": {
    "addr:full":"695 Tower Dr Hamel MN 55340",
    "addr:housenumber":"695",
    "addr:postcode":"55340",
    "addr:street":"Tower Dr Hamel",
    "iso:country":"US",
    "sg:address":"695 Tower Dr",
    "sg:city":"Hamel",
    "sg:classifiers":[
        {
            "category":"Wholesale",
            "subcategory":"Auto Parts",
            "type":"Manufacturing & Wholesale Goods"
        }
    ],
    "sg:phone":"+1 763 478 6484",
    "sg:postcode":"55340",
    "sg:province":"MN",
    "sg:tags":[
        "automobile",
        "supply"
    ],
    "wof:name":"Severson Products",
    "wof:placetype":"venue"
},
  "geometry": {"coordinates":[-93.53979099999999,45.043978],"type":"Point"}
}