{
  "type": "Feature",
  "properties": {
    "addr:full":"937 E Magnolia Ave St Paul MN 55106",
    "addr:housenumber":"937",
    "addr:postcode":"55106",
    "addr:street":"E Magnolia Ave",
    "iso:country":"US",
    "sg:address":"937 E Magnolia Ave",
    "sg:city":"St Paul",
    "sg:classifiers":[
        {
            "category":"Food & Beverages",
            "subcategory":"Groceries & Convenience Stores",
            "type":"Retail Goods"
        }
    ],
    "sg:phone":"+1 651 771 6150",
    "sg:postcode":"55106",
    "sg:province":"MN",
    "sg:tags":[
        "grocer"
    ],
    "wof:name":"JMB",
    "wof:placetype":"venue"
},
  "geometry": {"coordinates":[-93.062622,44.973982],"type":"Point"}
}