{
  "type": "Feature",
  "properties": {
    "iso:country":"US",
    "sg:address":"1879 134th Ln NW",
    "sg:city":"Anoka",
    "sg:classifiers":[
        {
            "category":"Building & Trades",
            "subcategory":"Construction",
            "type":"Services"
        }
    ],
    "sg:phone":"+1 763 862 9953",
    "sg:postcode":"55304",
    "sg:province":"MN",
    "sg:tags":[
        "floor",
        "laying",
        "contractor"
    ],
    "wof:name":"Timberline Hardwood Floor",
    "wof:placetype":"venue"
},
  "geometry": {"coordinates":[-93.313743,45.214513],"type":"Point"}
}