{
  "type": "Feature",
  "properties": {
    "addr:full":"8791 Lexington Ave N Circle Pines MN 55014",
    "addr:housenumber":"8791",
    "addr:postcode":"55014",
    "addr:street":"Lexington Ave N Circle",
    "iso:country":"US",
    "sg:address":"8791 Lexington Ave N",
    "sg:city":"Circle Pines",
    "sg:classifiers":[
        {
            "category":"Sports & Exercise",
            "subcategory":"Golf",
            "type":"Entertainment"
        }
    ],
    "sg:phone":"+1 763 786 2945",
    "sg:postcode":"55014",
    "sg:province":"MN",
    "sg:tags":[
        "course"
    ],
    "sg:website":"www.katehaven.com",
    "wof:name":"Kate Haven Golf Course",
    "wof:placetype":"venue"
},
  "geometry": {"coordinates":[-93.163589,45.135197],"type":"Point"}
}