{
  "type": "Feature",
  "properties": {
    "iso:country":"US",
    "sg:address":"202 W Main St",
    "sg:city":"Ada",
    "sg:classifiers":[
        {
            "category":"Organizations",
            "subcategory":"Community Association",
            "type":"Services"
        }
    ],
    "sg:phone":"+1 218 456 2131",
    "sg:postcode":"56510",
    "sg:province":"MN",
    "wof:name":"Ada Cooperative Oil Association",
    "wof:placetype":"venue"
},
  "geometry": {"coordinates":[-96.51617299999999,47.297523],"type":"Point"}
}