{
  "type": "Feature",
  "properties": {
    "addr:full":"6550 Highway 14 E Rochester MN 55904",
    "addr:housenumber":"6550",
    "addr:postcode":"55904",
    "addr:street":"Highway 14 E",
    "iso:country":"US",
    "sg:address":"6550 Highway 14 E",
    "sg:city":"Rochester",
    "sg:classifiers":[
        {
            "category":"Autos & Motor Vehicles",
            "subcategory":"Fuel & Gas Station",
            "type":"Retail Goods"
        },
        {
            "category":"Food & Beverages",
            "subcategory":"Groceries & Convenience Stores",
            "type":"Retail Goods"
        }
    ],
    "sg:phone":"+1 507 289 3149",
    "sg:postcode":"55904",
    "sg:province":"MN",
    "wof:name":"Pump & Munch 12",
    "wof:placetype":"venue"
},
  "geometry": {"coordinates":[-92.34977499999999,44.004347],"type":"Point"}
}