{
  "type": "Feature",
  "properties": {
    "addr:full":"28567 263rd Ave Albany MN 56307",
    "addr:housenumber":"28567",
    "addr:postcode":"56307",
    "addr:street":"263Rd Ave",
    "iso:country":"US",
    "sg:address":"28567 263rd Ave",
    "sg:city":"Albany",
    "sg:classifiers":[
        {
            "category":"Farming",
            "subcategory":"Dairy Farm",
            "type":"Manufacturing & Wholesale Goods"
        }
    ],
    "sg:phone":"+1 320 548 3283",
    "sg:postcode":"56307",
    "sg:province":"MN",
    "wof:name":"Norman Euteneuer Dairy Farm",
    "wof:placetype":"venue"
},
  "geometry": {"coordinates":[-94.660247,45.534818],"type":"Point"}
}