{
  "type": "Feature",
  "properties": {
    "addr:full":"210 2nd St Campbell MN 56522",
    "addr:housenumber":"210",
    "addr:postcode":"56522",
    "addr:street":"2Nd St",
    "iso:country":"US",
    "sg:address":"210 2nd St",
    "sg:city":"Campbell",
    "sg:classifiers":[
        {
            "category":"Personal",
            "subcategory":"Beauty Salon",
            "type":"Services"
        }
    ],
    "sg:phone":"+1 218 630 5726",
    "sg:postcode":"56522",
    "sg:province":"MN",
    "sg:tags":[
        "shop"
    ],
    "wof:name":"Betty's Beauty Shop",
    "wof:placetype":"venue"
},
  "geometry": {"coordinates":[-96.40124,46.095679],"type":"Point"}
}