{
  "type": "Feature",
  "properties": {
    "iso:country":"US",
    "sg:address":"12835 34th Ave N",
    "sg:city":"Minneapolis",
    "sg:classifiers":[
        {
            "category":"Building & Trades",
            "subcategory":"Construction",
            "type":"Services"
        }
    ],
    "sg:phone":"+1 612 327 7843",
    "sg:postcode":"55441",
    "sg:province":"MN",
    "sg:tags":[
        "general",
        "contractor"
    ],
    "wof:name":"Ct Construction",
    "wof:placetype":"venue"
},
  "geometry": {"coordinates":[-93.442679,45.02105],"type":"Point"}
}