{
  "type": "Feature",
  "properties": {
    "addr:full":"3431 144th St NW Monticello MN 55362",
    "addr:housenumber":"3431",
    "addr:postcode":"55362",
    "addr:street":"144Th St Nw",
    "iso:country":"US",
    "sg:address":"3431 144th St NW",
    "sg:city":"Monticello",
    "sg:classifiers":[
        {
            "category":"Transit Center",
            "subcategory":"Freight",
            "type":"Transportation"
        },
        {
            "category":"Freight",
            "type":"Transportation"
        }
    ],
    "sg:phone":"+1 763 878 2556",
    "sg:postcode":"55362",
    "sg:province":"MN",
    "sg:tags":[
        "trucking-motor",
        "trucking"
    ],
    "wof:name":"Clifford S Johnson",
    "wof:placetype":"venue"
},
  "geometry": {"coordinates":[-93.96462200000001,45.362023],"type":"Point"}
}