{
  "type": "Feature",
  "properties": {
    "addr:full":"16047 65th Ave NW Cass Lake MN 56633",
    "addr:housenumber":"16047",
    "addr:postcode":"56633",
    "addr:street":"65Th Ave Nw Cass",
    "iso:country":"US",
    "sg:address":"16047 65th Ave NW",
    "sg:city":"Cass Lake",
    "sg:classifiers":[
        {
            "category":"Retail",
            "subcategory":"Auto Repair",
            "type":"Services"
        }
    ],
    "sg:phone":"+1 218 335 0091",
    "sg:postcode":"56633",
    "sg:province":"MN",
    "sg:tags":[
        "repairing",
        "automobile"
    ],
    "wof:name":"Ken's Repair",
    "wof:placetype":"venue"
},
  "geometry": {"coordinates":[-94.628961,47.38379],"type":"Point"}
}