{
  "type": "Feature",
  "properties": {
    "iso:country":"US",
    "sg:address":"705 1st St SE",
    "sg:city":"Richmond",
    "sg:classifiers":[
        {
            "category":"Home & Garden",
            "subcategory":"Household Appliances",
            "type":"Retail Goods"
        },
        {
            "category":"Utilities",
            "subcategory":"Fuel Oil & Lpg",
            "type":"Services"
        }
    ],
    "sg:phone":"+1 320 597 4400",
    "sg:postcode":"56368",
    "sg:province":"MN",
    "sg:tags":[
        "oils-fuel",
        "major"
    ],
    "sg:website":"http://www.lakesgasco.com",
    "wof:name":"Lakes Gas Co.",
    "wof:placetype":"venue"
},
  "geometry": {"coordinates":[-94.50546799999999,45.452518],"type":"Point"}
}