{
  "type": "Feature",
  "properties": {
    "addr:full":"4993 Mitchell Rd Big Lake MN 55309",
    "addr:housenumber":"4993",
    "addr:postcode":"55309",
    "addr:street":"Mitchell Rd",
    "iso:country":"US",
    "sg:address":"4993 Mitchell Rd",
    "sg:city":"Big Lake",
    "sg:classifiers":[
        {
            "category":"Shopping",
            "subcategory":"Gifts & Souvenirs",
            "type":"Retail Goods"
        }
    ],
    "sg:phone":"+1 763 263 6488",
    "sg:postcode":"55309",
    "sg:province":"MN",
    "wof:name":"Stinas Gifts & Collectibles",
    "wof:placetype":"venue"
},
  "geometry": {"coordinates":[-93.76769299999999,45.351096],"type":"Point"}
}