{
  "type": "Feature",
  "properties": {
    "addr:full":"6308 Shingle Creek Dr Minneapolis MN 55445",
    "addr:housenumber":"6308",
    "addr:postcode":"55445",
    "addr:street":"Shingle Creek Dr",
    "iso:country":"US",
    "sg:address":"6308 Shingle Creek Dr",
    "sg:city":"Minneapolis",
    "sg:classifiers":[
        {
            "category":"Health Services",
            "subcategory":"Health Practitioner",
            "type":"Services"
        }
    ],
    "sg:phone":"+1 763 560 7574",
    "sg:postcode":"55445",
    "sg:province":"MN",
    "sg:tags":[
        "nurse",
        "registry"
    ],
    "wof:name":"Uni Care Inc",
    "wof:placetype":"venue"
},
  "geometry": {"coordinates":[-93.369103,45.101502],"type":"Point"}
}