{
  "type": "Feature",
  "properties": {
    "iso:country":"US",
    "sg:address":"212 Central Ave N",
    "sg:city":"Faribault",
    "sg:classifiers":[
        {
            "category":"Shopping",
            "subcategory":"Used Merchandise",
            "type":"Retail Goods"
        }
    ],
    "sg:phone":"+1 507 334 3980",
    "sg:postcode":"55021",
    "sg:province":"MN",
    "sg:tags":[
        "antique"
    ],
    "wof:name":"Antiques On Central",
    "wof:placetype":"venue"
},
  "geometry": {"coordinates":[-93.268435,44.293494],"type":"Point"}
}