{
  "type": "Feature",
  "properties": {
    "addr:full":"2800 Cliff Rd E Burnsville MN 55337",
    "addr:housenumber":"2800",
    "addr:postcode":"55337",
    "addr:street":"Cliff Rd E",
    "iso:country":"US",
    "sg:address":"2800 Cliff Rd E",
    "sg:city":"Burnsville",
    "sg:classifiers":[
        {
            "category":"Insurance",
            "subcategory":"Insurance Agent",
            "type":"Services"
        }
    ],
    "sg:phone":"+1 952 890 2800",
    "sg:postcode":"55337",
    "sg:province":"MN",
    "wof:name":"Detlefsen Insurance",
    "wof:placetype":"venue"
},
  "geometry": {"coordinates":[-93.23652800000001,44.79036],"type":"Point"}
}