{
  "type": "Feature",
  "properties": {
    "iso:country":"US",
    "sg:address":"1581 103rd Ave NW",
    "sg:city":"Minneapolis",
    "sg:classifiers":[
        {
            "category":"Building & Trades",
            "subcategory":"Equipment Rental",
            "type":"Services"
        }
    ],
    "sg:phone":"+1 612 309 6189",
    "sg:postcode":"55433",
    "sg:province":"MN",
    "sg:tags":[
        "leasing",
        "stereo",
        "audio",
        "video",
        "equipment-renting"
    ],
    "wof:name":"Windy Shores Sound Inc",
    "wof:placetype":"venue"
},
  "geometry": {"coordinates":[-93.30601,45.157211],"type":"Point"}
}