{
  "type": "Feature",
  "properties": {
    "addr:full":"19 W Vermilion Dr Cook MN 55723",
    "addr:housenumber":"19",
    "addr:postcode":"55723",
    "addr:street":"W Vermilion Dr",
    "iso:country":"US",
    "sg:address":"19 W Vermilion Dr",
    "sg:city":"Cook",
    "sg:classifiers":[
        {
            "category":"Health Services",
            "subcategory":"Chiropractor",
            "type":"Services"
        }
    ],
    "sg:phone":"+1 218 666 5104",
    "sg:postcode":"55723",
    "sg:province":"MN",
    "sg:tags":[
        "chiropractic"
    ],
    "wof:name":"Horoshak Chiropractic",
    "wof:placetype":"venue"
},
  "geometry": {"coordinates":[-92.689159,47.853737],"type":"Point"}
}