{
  "type": "Feature",
  "properties": {
    "addr:full":"7300 France Ave S Minneapolis MN 55435",
    "addr:housenumber":"7300",
    "addr:postcode":"55435",
    "addr:street":"France Ave S",
    "iso:country":"US",
    "sg:address":"7300 France Ave S",
    "sg:city":"Minneapolis",
    "sg:classifiers":[
        {
            "category":"Real Estate",
            "subcategory":"Real Estate Services",
            "type":"Services"
        },
        {
            "category":"Real Estate",
            "subcategory":"Real Estate Agent",
            "type":"Services"
        }
    ],
    "sg:phone":"+1 952 831 3728",
    "sg:postcode":"55435",
    "sg:province":"MN",
    "sg:tags":[
        "buyer",
        "broker"
    ],
    "wof:name":"The Esau Company Incorporated",
    "wof:placetype":"venue"
},
  "geometry": {"coordinates":[-93.32901,44.871109],"type":"Point"}
}