{
  "type": "Feature",
  "properties": {
    "iso:country":"US",
    "sg:address":"6031 Pinewood Ln",
    "sg:city":"Minnetonka",
    "sg:classifiers":[
        {
            "category":"Home & Garden",
            "subcategory":"Furniture",
            "type":"Retail Goods"
        },
        {
            "category":"Wholesale",
            "subcategory":"Home Furnishings",
            "type":"Manufacturing & Wholesale Goods"
        }
    ],
    "sg:phone":"+1 952 934 5633",
    "sg:postcode":"55345",
    "sg:province":"MN",
    "sg:tags":[
        "equipment-wholesale",
        "kitchen",
        "equipment-household",
        "manufacturer",
        "cabinet"
    ],
    "wof:name":"B Mcinturf Cabinets",
    "wof:placetype":"venue"
},
  "geometry": {"coordinates":[-93.471418,44.89446],"type":"Point"}
}