{
  "type": "Feature",
  "properties": {
    "addr:full":"5500 Opportunity Ct Hopkins MN 55343",
    "addr:housenumber":"5500",
    "addr:postcode":"55343",
    "addr:street":"Opportunity Ct",
    "iso:country":"US",
    "sg:address":"5500 Opportunity Ct",
    "sg:city":"Hopkins",
    "sg:classifiers":[
        {
            "category":"Social Services",
            "subcategory":"Job Training",
            "type":"Services"
        },
        {
            "category":"Manufacturing",
            "subcategory":"Rubber & Plastics",
            "type":"Manufacturing & Wholesale Goods"
        }
    ],
    "sg:phone":"+1 952 938 5511",
    "sg:postcode":"55343",
    "sg:province":"MN",
    "sg:tags":[
        "product",
        "for",
        "residential",
        "vocational",
        "handicapped",
        "care"
    ],
    "wof:name":"Opportunity Partners Inc",
    "wof:placetype":"venue"
},
  "geometry": {"coordinates":[-93.404093,44.903439],"type":"Point"}
}