{
  "type": "Feature",
  "properties": {
    "iso:country":"US",
    "sg:address":"4226 Pleasant Ave",
    "sg:city":"Minneapolis",
    "sg:classifiers":[
        {
            "category":"Arts & Performance",
            "subcategory":"Music",
            "type":"Entertainment"
        }
    ],
    "sg:phone":"+1 612 827 7165",
    "sg:postcode":"55409",
    "sg:province":"MN",
    "sg:tags":[
        "wedding"
    ],
    "wof:name":"J & J Productions",
    "wof:placetype":"venue"
},
  "geometry": {"coordinates":[-93.28311600000001,44.926341],"type":"Point"}
}