{
  "type": "Feature",
  "properties": {
    "addr:full":"4603 Azalea Rd Motley MN 56466",
    "addr:housenumber":"4603",
    "addr:postcode":"56466",
    "addr:street":"Azalea Rd",
    "iso:country":"US",
    "sg:address":"4603 Azalea Rd",
    "sg:city":"Motley",
    "sg:classifiers":[
        {
            "category":"Professional",
            "type":"Services"
        }
    ],
    "sg:phone":"+1 218 746 3675",
    "sg:postcode":"56466",
    "sg:province":"MN",
    "wof:name":"Robert F McGree",
    "wof:placetype":"venue"
},
  "geometry": {"coordinates":[-94.56621,46.31142],"type":"Point"}
}