{
  "type": "Feature",
  "properties": {
    "iso:country":"US",
    "sg:address":"30 W Central St",
    "sg:city":"Springfield",
    "sg:classifiers":[
        {
            "category":"Insurance",
            "subcategory":"Insurance Agent",
            "type":"Services"
        }
    ],
    "sg:phone":"+1 507 723 4241",
    "sg:postcode":"56087",
    "sg:province":"MN",
    "wof:name":"Americana Insurance",
    "wof:placetype":"venue"
},
  "geometry": {"coordinates":[-94.97639599999999,44.239036],"type":"Point"}
}