{
  "type": "Feature",
  "properties": {
    "iso:country":"US",
    "sg:address":"10056 Flanders Ct NE",
    "sg:city":"Blaine",
    "sg:classifiers":[
        {
            "category":"Professional",
            "type":"Services"
        }
    ],
    "sg:phone":"+1 763 398 0356",
    "sg:postcode":"55449",
    "sg:province":"MN",
    "sg:tags":[
        "establishment"
    ],
    "wof:name":"Adelmann Engines",
    "wof:placetype":"venue"
},
  "geometry": {"coordinates":[-93.19408199999999,45.152412],"type":"Point"}
}