{
  "type": "Feature",
  "properties": {
    "addr:full":"1920 W 94th St Bloomington MN 55431",
    "addr:housenumber":"1920",
    "addr:postcode":"55431",
    "addr:street":"W 94Th St",
    "iso:country":"US",
    "sg:address":"1920 W 94th St",
    "sg:city":"Bloomington",
    "sg:classifiers":[
        {
            "category":"Manufacturing",
            "subcategory":"Retail Goods",
            "type":"Manufacturing & Wholesale Goods"
        }
    ],
    "sg:phone":"+1 952 888 6464",
    "sg:postcode":"55431",
    "sg:province":"MN",
    "sg:tags":[
        "candle"
    ],
    "sg:website":"www.acadiancandles.com",
    "wof:name":"Acadian Candles Co",
    "wof:placetype":"venue"
},
  "geometry": {"coordinates":[-93.306814,44.833632],"type":"Point"}
}