{
  "type": "Feature",
  "properties": {
    "iso:country":"US",
    "sg:address":"14391 45th St SE",
    "sg:city":"Lake Lillian",
    "sg:classifiers":[
        {
            "category":"Recreation",
            "type":"Entertainment"
        }
    ],
    "sg:phone":"+1 320 995 6599",
    "sg:postcode":"56253",
    "sg:province":"MN",
    "sg:tags":[
        "parks"
    ],
    "wof:name":"Kandiyohi County Park #1",
    "wof:placetype":"venue"
},
  "geometry": {"coordinates":[-94.982288,44.987203],"type":"Point"}
}