{
  "type": "Feature",
  "properties": {
    "addr:full":"1800 Oakwood Ave New Ulm MN 56073",
    "addr:housenumber":"1800",
    "addr:postcode":"56073",
    "addr:street":"Oakwood Ave",
    "iso:country":"US",
    "sg:address":"1800 Oakwood Ave",
    "sg:city":"New Ulm",
    "sg:classifiers":[
        {
            "category":"Social Services",
            "subcategory":"Child Care",
            "type":"Services"
        }
    ],
    "sg:phone":"+1 507 359 2776",
    "sg:postcode":"56073",
    "sg:province":"MN",
    "sg:tags":[
        "daycare",
        "provider"
    ],
    "wof:name":"Kathleen Howk",
    "wof:placetype":"venue"
},
  "geometry": {"coordinates":[-94.48212700000001,44.303361],"type":"Point"}
}