{
  "type": "Feature",
  "properties": {
    "addr:full":"603 Eaton St Saint Paul MN 55107",
    "addr:housenumber":"603",
    "addr:postcode":"55107",
    "addr:street":"Eaton St",
    "iso:country":"US",
    "sg:address":"603 Eaton St",
    "sg:city":"Saint Paul",
    "sg:classifiers":[
        {
            "category":"Freight",
            "type":"Transportation"
        }
    ],
    "sg:phone":"+1 651 227 7007",
    "sg:postcode":"55107",
    "sg:province":"MN",
    "wof:name":"Jostens Flight Operation",
    "wof:placetype":"venue"
},
  "geometry": {"coordinates":[-93.07033800000001,44.931852],"type":"Point"}
}