{
  "type": "Feature",
  "properties": {
    "addr:full":"113 3rd St Balaton MN 56115",
    "addr:housenumber":"113",
    "addr:postcode":"56115",
    "addr:street":"3Rd St",
    "iso:country":"US",
    "sg:address":"113 3rd St",
    "sg:city":"Balaton",
    "sg:classifiers":[
        {
            "category":"Education",
            "subcategory":"School",
            "type":"Public Place"
        }
    ],
    "sg:phone":"+1 507 734 2677",
    "sg:postcode":"56115",
    "sg:province":"MN",
    "wof:name":"Yankton Country School",
    "wof:placetype":"venue"
},
  "geometry": {"coordinates":[-95.87127599999999,44.233879],"type":"Point"}
}