{
  "type": "Feature",
  "properties": {
    "addr:full":"1188 Hwy 169 Ely MN 55731",
    "addr:housenumber":"1188",
    "addr:postcode":"55731",
    "addr:street":"Hwy 169",
    "iso:country":"US",
    "sg:address":"1188 Hwy 169",
    "sg:city":"Ely",
    "sg:classifiers":[
        {
            "category":"Building & Trades",
            "subcategory":"Construction",
            "type":"Services"
        }
    ],
    "sg:phone":"+1 218 365 2442",
    "sg:postcode":"55731",
    "sg:province":"MN",
    "sg:tags":[
        "insulation",
        "heat",
        "contractor"
    ],
    "wof:name":"FOM-Hom",
    "wof:placetype":"venue"
},
  "geometry": {"coordinates":[-91.80404799999999,47.919261],"type":"Point"}
}