{
  "type": "Feature",
  "properties": {
    "iso:country":"US",
    "sg:address":"5804 Arbour Ave",
    "sg:city":"Minneapolis",
    "sg:classifiers":[
        {
            "category":"Professional",
            "subcategory":"Advertising",
            "type":"Services"
        }
    ],
    "sg:phone":"+1 952 922 5500",
    "sg:postcode":"55436",
    "sg:province":"MN",
    "sg:tags":[
        "consultant",
        "agency"
    ],
    "wof:name":"Simpson Michaels & Associates",
    "wof:placetype":"venue"
},
  "geometry": {"coordinates":[-93.371656,44.896577],"type":"Point"}
}