{
  "type": "Feature",
  "properties": {
    "iso:country":"US",
    "sg:address":"1175 Eagan Industrial Rd",
    "sg:city":"Eagan",
    "sg:classifiers":[
        {
            "category":"Manufacturing",
            "subcategory":"Glass & Minerals",
            "type":"Manufacturing & Wholesale Goods"
        },
        {
            "category":"Building & Trades",
            "subcategory":"Construction",
            "type":"Services"
        }
    ],
    "sg:phone":"+1 651 452 2700",
    "sg:postcode":"55121",
    "sg:province":"MN",
    "sg:tags":[
        "product",
        "terrazzo",
        "floor",
        "wall",
        "ceramic",
        "contractor",
        "using",
        "tile",
        "granite"
    ],
    "sg:website":"www.grazzini.com",
    "wof:name":"Grazzini Brothers & Company",
    "wof:placetype":"venue"
},
  "geometry": {"coordinates":[-93.155404,44.855832],"type":"Point"}
}