{
  "type": "Feature",
  "properties": {
    "iso:country":"US",
    "sg:address":"1858 610th St",
    "sg:city":"Echo",
    "sg:phone":"+1 507 925 4276",
    "sg:postcode":"56237",
    "sg:province":"MN",
    "sg:tags":[
        "farm",
        "corn",
        "soybean"
    ],
    "wof:name":"Douglas Lecy",
    "wof:placetype":"venue"
},
  "geometry": {"coordinates":[-95.421784,44.666508],"type":"Point"}
}