{
  "type": "Feature",
  "properties": {
    "iso:country":"US",
    "sg:address":"32149 Northwoods Ln",
    "sg:city":"Pequot Lakes",
    "sg:classifiers":[
        {
            "category":"Social Services",
            "subcategory":"Child Care",
            "type":"Services"
        }
    ],
    "sg:phone":"+1 218 562 4140",
    "sg:postcode":"56472",
    "sg:province":"MN",
    "wof:name":"Little People Learning Ctr",
    "wof:placetype":"venue"
},
  "geometry": {"coordinates":[-94.22389099999999,46.619945],"type":"Point"}
}