{
  "type": "Feature",
  "properties": {
    "addr:full":"1201 E Lake St Ste 5 Minneapolis MN 55407",
    "addr:housenumber":"1201",
    "addr:postcode":"55407",
    "addr:street":"E Lake St Ste 5",
    "iso:country":"US",
    "sg:address":"1201 E Lake St Ste 5",
    "sg:city":"Minneapolis",
    "sg:classifiers":[
        {
            "category":"Community Center",
            "subcategory":"Youth",
            "type":"Public Place"
        }
    ],
    "sg:phone":"+1 612 721 1549",
    "sg:postcode":"55407",
    "sg:province":"MN",
    "sg:website":"http://www.circleofdiscipline.org",
    "wof:name":"Circle Of Discipline Inc",
    "wof:placetype":"venue"
},
  "geometry": {"coordinates":[-93.25758399999999,44.94836],"type":"Point"}
}