{
  "type": "Feature",
  "properties": {
    "iso:country":"US",
    "sg:address":"109 Lewis Ave N",
    "sg:city":"Watertown",
    "sg:classifiers":[
        {
            "category":"Home & Garden",
            "subcategory":"Home Furnishings",
            "type":"Retail Goods"
        },
        {
            "category":"Building & Trades",
            "subcategory":"Construction",
            "type":"Services"
        },
        {
            "category":"Manufacturing",
            "subcategory":"Building Materials",
            "type":"Manufacturing & Wholesale Goods"
        }
    ],
    "sg:phone":"+1 952 955 1321",
    "sg:postcode":"55388",
    "sg:province":"MN",
    "sg:tags":[
        "industrial",
        "cabinetmakers-commercial",
        "cabinet",
        "refacing",
        "resurfacing",
        "maker",
        "cabinets-refinishing",
        "kitchen"
    ],
    "wof:name":"Kel's Kustom Kabinets",
    "wof:placetype":"venue"
},
  "geometry": {"coordinates":[-93.847095,44.963683],"type":"Point"}
}