{
  "type": "Feature",
  "properties": {
    "addr:full":"385 90th Ave NW Minneapolis MN 55433",
    "addr:housenumber":"385",
    "addr:postcode":"55433",
    "addr:street":"90Th Ave Nw",
    "iso:country":"US",
    "sg:address":"385 90th Ave NW",
    "sg:city":"Minneapolis",
    "sg:classifiers":[
        {
            "category":"Manufacturing",
            "subcategory":"Metals",
            "type":"Manufacturing & Wholesale Goods"
        }
    ],
    "sg:phone":"+1 763 785 2429",
    "sg:postcode":"55433",
    "sg:province":"MN",
    "sg:tags":[
        "sheet",
        "fabrication"
    ],
    "sg:website":"www.lakeairmetals.com",
    "wof:name":"Lake Air Metal Products",
    "wof:placetype":"venue"
},
  "geometry": {"coordinates":[-93.276646,45.133941],"type":"Point"}
}