{
  "type": "Feature",
  "properties": {
    "addr:full":"1535 Greenview Dr SW Rochester MN 55902",
    "addr:housenumber":"1535",
    "addr:postcode":"55902",
    "addr:street":"Greenview Dr Sw",
    "iso:country":"US",
    "sg:address":"1535 Greenview Dr SW",
    "sg:city":"Rochester",
    "sg:classifiers":[
        {
            "category":"Travel",
            "subcategory":"Travel Agent",
            "type":"Entertainment"
        }
    ],
    "sg:phone":"+1 507 289 0418",
    "sg:postcode":"55902",
    "sg:province":"MN",
    "sg:tags":[
        "agency"
    ],
    "wof:name":"A A A Minnesota Trvl Agencies",
    "wof:placetype":"venue"
},
  "geometry": {"coordinates":[-92.486841,44.002621],"type":"Point"}
}