{
  "type": "Feature",
  "properties": {
    "addr:full":"13 2nd St SE Dodge Center MN 55927",
    "addr:housenumber":"13",
    "addr:postcode":"55927",
    "addr:street":"2Nd St Se",
    "iso:country":"US",
    "sg:address":"13 2nd St SE",
    "sg:city":"Dodge Center",
    "sg:classifiers":[
        {
            "category":"Building & Trades",
            "subcategory":"Construction",
            "type":"Services"
        }
    ],
    "sg:phone":"+1 507 634 6001",
    "sg:postcode":"55927",
    "sg:province":"MN",
    "sg:tags":[
        "downspouts",
        "gutter"
    ],
    "wof:name":"Millennium Seamless Gutters",
    "wof:placetype":"venue"
},
  "geometry": {"coordinates":[-92.854652,44.026227],"type":"Point"}
}