{
  "type": "Feature",
  "properties": {
    "addr:full":"968 Gunflint Trl Grand Marais MN 55604",
    "addr:housenumber":"968",
    "addr:postcode":"55604",
    "addr:street":"Gunflint Trl",
    "iso:country":"US",
    "sg:address":"968 Gunflint Trl",
    "sg:city":"Grand Marais",
    "sg:classifiers":[
        {
            "category":"Travel",
            "subcategory":"Hotels & Motels",
            "type":"Entertainment"
        }
    ],
    "sg:phone":"+1 218 387 1276",
    "sg:postcode":"55604",
    "sg:province":"MN",
    "sg:tags":[
        "operation"
    ],
    "wof:name":"Pincushion Bed & Breakfast",
    "wof:placetype":"venue"
},
  "geometry": {"coordinates":[-90.322107,47.783837],"type":"Point"}
}