{
  "type": "Feature",
  "properties": {
    "addr:full":"125 E Maine St Amboy MN 56010",
    "addr:housenumber":"125",
    "addr:postcode":"56010",
    "addr:street":"E Maine St",
    "iso:country":"US",
    "sg:address":"125 E Maine St",
    "sg:city":"Amboy",
    "sg:classifiers":[
        {
            "category":"Shopping",
            "subcategory":"Used Merchandise",
            "type":"Retail Goods"
        }
    ],
    "sg:phone":"+1 507 674 3024",
    "sg:postcode":"56010",
    "sg:province":"MN",
    "sg:tags":[
        "antique"
    ],
    "wof:name":"Villager Antiques",
    "wof:placetype":"venue"
},
  "geometry": {"coordinates":[-94.158136,43.887858],"type":"Point"}
}