{
  "type": "Feature",
  "properties": {
    "iso:country":"US",
    "sg:address":"1501 University Ave SE",
    "sg:city":"Minneapolis",
    "sg:classifiers":[
        {
            "category":"Real Estate",
            "subcategory":"Real Estate Agent",
            "type":"Services"
        }
    ],
    "sg:phone":"+1 612 379 1546",
    "sg:postcode":"55414",
    "sg:province":"MN",
    "sg:tags":[
        "agency",
        "rental"
    ],
    "wof:name":"Smails Rentals",
    "wof:placetype":"venue"
},
  "geometry": {"coordinates":[-93.23491,44.978867],"type":"Point"}
}