{
  "type": "Feature",
  "properties": {
    "addr:full":"819 W Laurel St Fergus Falls MN 56537",
    "addr:housenumber":"819",
    "addr:postcode":"56537",
    "addr:street":"W Laurel St",
    "iso:country":"US",
    "sg:address":"819 W Laurel St",
    "sg:city":"Fergus Falls",
    "sg:classifiers":[
        {
            "category":"Real Estate",
            "subcategory":"Real Estate Operator",
            "type":"Services"
        }
    ],
    "sg:phone":"+1 218 736 6683",
    "sg:postcode":"56537",
    "sg:province":"MN",
    "sg:tags":[
        "building",
        "apartment"
    ],
    "wof:name":"West Town Manor Apartments",
    "wof:placetype":"venue"
},
  "geometry": {"coordinates":[-96.088847,46.287543],"type":"Point"}
}