{
  "type": "Feature",
  "properties": {
    "iso:country":"US",
    "sg:address":"10775 Co Rd 33",
    "sg:city":"Young America",
    "sg:classifiers":[
        {
            "category":"Shopping",
            "type":"Retail Goods"
        }
    ],
    "sg:phone":"+1 952 467 2426",
    "sg:postcode":"55397",
    "sg:province":"MN",
    "sg:tags":[
        "telescope"
    ],
    "wof:name":"Minnesota Astronomical",
    "wof:placetype":"venue"
},
  "geometry": {"coordinates":[-93.946915,44.810084],"type":"Point"}
}