{
  "type": "Feature",
  "properties": {
    "iso:country":"US",
    "sg:address":"600 US Hwy 169",
    "sg:city":"St Louis Park",
    "sg:classifiers":[
        {
            "category":"Health Services",
            "subcategory":"Clinic",
            "type":"Services"
        }
    ],
    "sg:phone":"+1 952 544 6136",
    "sg:postcode":"55426",
    "sg:province":"MN",
    "wof:name":"Health Activation Svc",
    "wof:placetype":"venue"
},
  "geometry": {"coordinates":[-93.40041100000001,44.975609],"type":"Point"}
}