{
  "type": "Feature",
  "properties": {
    "iso:country":"US",
    "sg:address":"1540 Humboldt Ave",
    "sg:city":"Saint Paul",
    "sg:classifiers":[
        {
            "category":"Real Estate",
            "subcategory":"Real Estate Operator",
            "type":"Services"
        }
    ],
    "sg:phone":"+1 651 450 9669",
    "sg:postcode":"55118",
    "sg:province":"MN",
    "sg:tags":[
        "building",
        "nonresidential"
    ],
    "wof:name":"Langer Real Estate Services",
    "wof:placetype":"venue"
},
  "geometry": {"coordinates":[-93.08497300000001,44.898889],"type":"Point"}
}