{
  "type": "Feature",
  "properties": {
    "addr:full":"111 E Clark St Albert Lea MN 56007",
    "addr:housenumber":"111",
    "addr:postcode":"56007",
    "addr:street":"E Clark St",
    "iso:country":"US",
    "sg:address":"111 E Clark St",
    "sg:city":"Albert Lea",
    "sg:classifiers":[
        {
            "category":"Health Services",
            "subcategory":"Clinic",
            "type":"Services"
        }
    ],
    "sg:phone":"+1 507 377 2224",
    "sg:postcode":"56007",
    "sg:province":"MN",
    "sg:tags":[
        "specialty",
        "outpatient"
    ],
    "wof:name":"Individual & Family Services",
    "wof:placetype":"venue"
},
  "geometry": {"coordinates":[-93.368618,43.649828],"type":"Point"}
}