{
  "type": "Feature",
  "properties": {
    "iso:country":"US",
    "sg:address":"2785 50th St",
    "sg:city":"Granada",
    "sg:classifiers":[
        {
            "category":"Farming",
            "subcategory":"Farm",
            "type":"Manufacturing & Wholesale Goods"
        }
    ],
    "sg:phone":"+1 507 773 4476",
    "sg:postcode":"56039",
    "sg:province":"MN",
    "sg:tags":[
        "crop",
        "general"
    ],
    "wof:name":"Lawrence Whitman",
    "wof:placetype":"venue"
},
  "geometry": {"coordinates":[-94.31433800000001,43.558257],"type":"Point"}
}