{
  "type": "Feature",
  "properties": {
    "addr:full":"16186 Main Ave SE Prior Lake MN 55372",
    "addr:housenumber":"16186",
    "addr:postcode":"55372",
    "addr:street":"Main Ave Se",
    "iso:country":"US",
    "sg:address":"16186 Main Ave SE",
    "sg:city":"Prior Lake",
    "sg:classifiers":[
        {
            "category":"Travel",
            "subcategory":"Hotels & Motels",
            "type":"Entertainment"
        }
    ],
    "sg:phone":"+1 952 447 2952",
    "sg:postcode":"55372",
    "sg:province":"MN",
    "sg:tags":[
        "resort"
    ],
    "wof:name":"Kabeelo Lodge",
    "wof:placetype":"venue"
},
  "geometry": {"coordinates":[-93.422415,44.716377],"type":"Point"}
}