{
  "type": "Feature",
  "properties": {
    "addr:full":"5063 Old Hwy 33 Saginaw MN 55779",
    "addr:housenumber":"5063",
    "addr:postcode":"55779",
    "addr:street":"Old Hwy 33",
    "iso:country":"US",
    "sg:address":"5063 Old Hwy 33",
    "sg:city":"Saginaw",
    "sg:classifiers":[
        {
            "category":"Real Estate",
            "subcategory":"Real Estate Agent",
            "type":"Services"
        }
    ],
    "sg:phone":"+1 218 729 4686",
    "sg:postcode":"55779",
    "sg:province":"MN",
    "sg:tags":[
        "appraiser"
    ],
    "wof:name":"Anderson Real Estate",
    "wof:placetype":"venue"
},
  "geometry": {"coordinates":[-92.46731699999999,46.879905],"type":"Point"}
}