{
  "type": "Feature",
  "properties": {
    "addr:full":"592 120th St Sherburn MN 56171",
    "addr:housenumber":"592",
    "addr:postcode":"56171",
    "addr:street":"120Th St",
    "iso:country":"US",
    "sg:address":"592 120th St",
    "sg:city":"Sherburn",
    "sg:phone":"+1 507 764 5793",
    "sg:postcode":"56171",
    "sg:province":"MN",
    "sg:tags":[
        "farm",
        "corn",
        "soybean"
    ],
    "wof:name":"Joel Burmeister",
    "wof:placetype":"venue"
},
  "geometry": {"coordinates":[-94.765016,43.660683],"type":"Point"}
}