{
  "type": "Feature",
  "properties": {
    "iso:country":"US",
    "sg:address":"1401 155th St W",
    "sg:city":"Burnsville",
    "sg:classifiers":[
        {
            "category":"Taxi",
            "type":"Transportation"
        }
    ],
    "sg:phone":"+1 952 898 4998",
    "sg:postcode":"55306",
    "sg:province":"MN",
    "sg:tags":[
        "limo"
    ],
    "wof:name":"Country Taxi",
    "wof:placetype":"venue"
},
  "geometry": {"coordinates":[-93.296091,44.722603],"type":"Point"}
}