{
  "type": "Feature",
  "properties": {
    "iso:country":"US",
    "sg:address":"224 Madison Cir S",
    "sg:city":"Hopkins",
    "sg:classifiers":[
        {
            "category":"Retail",
            "subcategory":"Auto Repair",
            "type":"Services"
        }
    ],
    "sg:phone":"+1 952 939 4110",
    "sg:postcode":"55343",
    "sg:province":"MN",
    "sg:tags":[
        "general"
    ],
    "wof:name":"Chriss Auto",
    "wof:placetype":"venue"
},
  "geometry": {"coordinates":[-93.396495,44.92978],"type":"Point"}
}