{
  "type": "Feature",
  "properties": {
    "addr:full":"929 Highway 52 N Rochester MN 55901",
    "addr:housenumber":"929",
    "addr:postcode":"55901",
    "addr:street":"Highway 52 N",
    "iso:country":"US",
    "sg:address":"929 Highway 52 N",
    "sg:city":"Rochester",
    "sg:classifiers":[
        {
            "category":"Restaurant",
            "type":"Food & Drink"
        }
    ],
    "sg:phone":"+1 507 288 3936",
    "sg:postcode":"55901",
    "sg:province":"MN",
    "sg:tags":[
        "house",
        "steak",
        "barbecue"
    ],
    "wof:name":"John Hardy's Bar-B-Q",
    "wof:placetype":"venue"
},
  "geometry": {"coordinates":[-92.488855,44.034814],"type":"Point"}
}