{
  "type": "Feature",
  "properties": {
    "addr:full":"1367 Willow Street Minneapolis MN 55403",
    "addr:housenumber":"1367",
    "addr:postcode":"55403",
    "addr:street":"Willow Street",
    "iso:country":"US",
    "sg:address":"1367 Willow Street",
    "sg:city":"Minneapolis",
    "sg:classifiers":[
        {
            "category":"Real Estate",
            "subcategory":"Real Estate Operator",
            "type":"Services"
        }
    ],
    "sg:phone":"+1 888 822 4289",
    "sg:postcode":"55403",
    "sg:province":"MN",
    "sg:tags":[
        "apartment"
    ],
    "sg:website":"www.eitelbuildingcityapartments....",
    "wof:name":"Eitel Building City Apartments",
    "wof:placetype":"venue"
},
  "geometry": {"coordinates":[-93.281344,44.969353],"type":"Point"}
}