{
  "type": "Feature",
  "properties": {
    "iso:country":"US",
    "sg:address":"111 Main St S",
    "sg:city":"Greenbush",
    "sg:classifiers":[
        {
            "category":"Autos & Motor Vehicles",
            "subcategory":"Auto Supplies",
            "type":"Retail Goods"
        }
    ],
    "sg:phone":"+1 218 782 5000",
    "sg:postcode":"56726",
    "sg:province":"MN",
    "sg:tags":[
        "automobile",
        "parts"
    ],
    "wof:name":"Dan's Bumper To Bumper",
    "wof:placetype":"venue"
},
  "geometry": {"coordinates":[-96.18165500000001,48.699578],"type":"Point"}
}