{
  "type": "Feature",
  "properties": {
    "iso:country":"US",
    "sg:address":"8120 Penn Ave S",
    "sg:city":"Minneapolis",
    "sg:classifiers":[
        {
            "category":"Health Services",
            "subcategory":"Chiropractor",
            "type":"Services"
        }
    ],
    "sg:phone":"+1 952 884 1850",
    "sg:postcode":"55431",
    "sg:province":"MN",
    "sg:tags":[
        "chiropractic"
    ],
    "sg:website":"http://www.chirocenterbloomington.com",
    "wof:name":"Chiropractic Center - Bloomington",
    "wof:placetype":"venue"
},
  "geometry": {"coordinates":[-93.308899,44.855679],"type":"Point"}
}