{
  "type": "Feature",
  "properties": {
    "iso:country":"US",
    "sg:address":"5835 Amy Ln",
    "sg:city":"Maple Plain",
    "sg:classifiers":[
        {
            "category":"Wholesale",
            "subcategory":"Chemicals & Plastics",
            "type":"Manufacturing & Wholesale Goods"
        }
    ],
    "sg:phone":"+1 763 479 2400",
    "sg:postcode":"55359",
    "sg:province":"MN",
    "wof:name":"Ungerer & Co",
    "wof:placetype":"venue"
},
  "geometry": {"coordinates":[-93.670563,45.006352],"type":"Point"}
}