{
  "type": "Feature",
  "properties": {
    "iso:country":"US",
    "sg:address":"13197 274th Ave",
    "sg:city":"Zimmerman",
    "sg:classifiers":[
        {
            "category":"Building & Trades",
            "subcategory":"Construction",
            "type":"Services"
        }
    ],
    "sg:phone":"+1 763 856 3665",
    "sg:postcode":"55398",
    "sg:province":"MN",
    "sg:tags":[
        "house"
    ],
    "wof:name":"Roberts Construction Svc",
    "wof:placetype":"venue"
},
  "geometry": {"coordinates":[-93.60010699999999,45.466154],"type":"Point"}
}