{
  "type": "Feature",
  "properties": {
    "iso:country":"US",
    "sg:address":"7842 Yucca Ln N",
    "sg:city":"Maple Grove",
    "sg:classifiers":[
        {
            "category":"Insurance",
            "subcategory":"Insurance Agent",
            "type":"Services"
        }
    ],
    "sg:phone":"+1 763 494 9333",
    "sg:postcode":"55311",
    "sg:province":"MN",
    "wof:name":"Thrivent Financial-Lutherans",
    "wof:placetype":"venue"
},
  "geometry": {"coordinates":[-93.453441,45.096956],"type":"Point"}
}