{
  "type": "Feature",
  "properties": {
    "addr:full":"7817 440th Ave Blue Earth MN 56013",
    "addr:housenumber":"7817",
    "addr:postcode":"56013",
    "addr:street":"440Th Ave",
    "iso:country":"US",
    "sg:address":"7817 440th Ave",
    "sg:city":"Blue Earth",
    "sg:classifiers":[
        {
            "category":"Shopping",
            "subcategory":"Clothing, Apparel, & Fashions",
            "type":"Retail Goods"
        }
    ],
    "sg:phone":"+1 507 878 3372",
    "sg:postcode":"56013",
    "sg:province":"MN",
    "wof:name":"Perfect Gentleman",
    "wof:placetype":"venue"
},
  "geometry": {"coordinates":[-93.98796400000001,43.598389],"type":"Point"}
}