{
  "type": "Feature",
  "properties": {
    "iso:country":"US",
    "sg:address":"277 Coon Rapids Blvd NW",
    "sg:city":"Coon Rapids",
    "sg:classifiers":[
        {
            "category":"Health Services",
            "subcategory":"Health Practitioner",
            "type":"Services"
        },
        {
            "category":"Health Services",
            "subcategory":"Doctor",
            "type":"Services"
        }
    ],
    "sg:phone":"+1 763 717 4979",
    "sg:postcode":"55433",
    "sg:province":"MN",
    "sg:tags":[
        "clinic"
    ],
    "wof:name":"Primary Clinical Associates",
    "wof:placetype":"venue"
},
  "geometry": {"coordinates":[-93.27366000000001,45.138076],"type":"Point"}
}