{
  "type": "Feature",
  "properties": {
    "addr:full":"111 3rd Ave SW Rochester MN 55902",
    "addr:housenumber":"111",
    "addr:postcode":"55902",
    "addr:street":"3Rd Ave Sw",
    "iso:country":"US",
    "sg:address":"111 3rd Ave SW",
    "sg:city":"Rochester",
    "sg:classifiers":[
        {
            "category":"Organizations",
            "subcategory":"Religious Organization",
            "type":"Services"
        }
    ],
    "sg:phone":"+1 507 282 9429",
    "sg:postcode":"55902",
    "sg:province":"MN",
    "wof:name":"Calvary Episcopal Church",
    "wof:placetype":"venue"
},
  "geometry": {"coordinates":[-92.467529,44.021672],"type":"Point"}
}