{
  "type": "Feature",
  "properties": {
    "addr:full":"5413 Nicklaus Dr NW Rochester MN 55901",
    "addr:housenumber":"5413",
    "addr:postcode":"55901",
    "addr:street":"Nicklaus Dr Nw",
    "iso:country":"US",
    "sg:address":"5413 Nicklaus Dr NW",
    "sg:city":"Rochester",
    "sg:classifiers":[
        {
            "category":"Shopping",
            "type":"Retail Goods"
        }
    ],
    "sg:phone":"+1 507 252 0823",
    "sg:postcode":"55901",
    "sg:province":"MN",
    "sg:tags":[
        "merchandise"
    ],
    "wof:name":"My Button Store",
    "wof:placetype":"venue"
},
  "geometry": {"coordinates":[-92.534442,44.079061],"type":"Point"}
}