{
  "type": "Feature",
  "properties": {
    "iso:country":"US",
    "sg:address":"4817 W 86th St",
    "sg:city":"Bloomington",
    "sg:classifiers":[
        {
            "category":"Manufacturing",
            "subcategory":"Signs",
            "type":"Manufacturing & Wholesale Goods"
        },
        {
            "category":"Manufacturing",
            "subcategory":"Printing",
            "type":"Manufacturing & Wholesale Goods"
        }
    ],
    "sg:phone":"+1 952 893 9790",
    "sg:postcode":"55437",
    "sg:province":"MN",
    "sg:tags":[
        "engraver",
        "wood",
        "specialty",
        "business",
        "mfg"
    ],
    "wof:name":"Bloomington Budget Sign Shop",
    "wof:placetype":"venue"
},
  "geometry": {"coordinates":[-93.34324599999999,44.847746],"type":"Point"}
}