{
  "type": "Feature",
  "properties": {
    "addr:full":"26683 101st St Zimmerman MN 55398",
    "addr:housenumber":"26683",
    "addr:postcode":"55398",
    "addr:street":"101St St",
    "iso:country":"US",
    "sg:address":"26683 101st St",
    "sg:city":"Zimmerman",
    "sg:classifiers":[
        {
            "category":"Manufacturing",
            "subcategory":"Wood Products",
            "type":"Manufacturing & Wholesale Goods"
        }
    ],
    "sg:phone":"+1 763 856 4895",
    "sg:postcode":"55398",
    "sg:province":"MN",
    "sg:tags":[
        "mfg"
    ],
    "wof:name":"Contour Closets",
    "wof:placetype":"venue"
},
  "geometry": {"coordinates":[-93.523544,45.452357],"type":"Point"}
}