{
  "type": "Feature",
  "properties": {
    "iso:country":"US",
    "sg:address":"13727 855th Ave",
    "sg:city":"Glenville",
    "sg:classifiers":[
        {
            "category":"Shopping",
            "subcategory":"Party Supplies",
            "type":"Retail Goods"
        },
        {
            "category":"Retail",
            "subcategory":"Auto Rental",
            "type":"Services"
        },
        {
            "category":"Local Transit",
            "type":"Transportation"
        }
    ],
    "sg:phone":"+1 507 402 0606",
    "sg:postcode":"56036",
    "sg:province":"MN",
    "sg:tags":[
        "shuttle",
        "limousine",
        "wedding"
    ],
    "wof:name":"Dawson Limousine",
    "wof:placetype":"venue"
},
  "geometry": {"coordinates":[-93.159368,43.549006],"type":"Point"}
}