{
  "type": "Feature",
  "properties": {
    "addr:full":"7525 147 St W Burnsville MN 55337",
    "addr:housenumber":"7525",
    "addr:postcode":"55337",
    "addr:street":"147 St W",
    "iso:country":"US",
    "sg:address":"7525 147 St W",
    "sg:city":"Burnsville",
    "sg:classifiers":[
        {
            "category":"Autos & Motor Vehicles",
            "subcategory":"Fuel & Gas Station",
            "type":"Retail Goods"
        },
        {
            "category":"Autos & Motor Vehicles",
            "subcategory":"Auto Supplies",
            "type":"Retail Goods"
        },
        {
            "category":"Personal",
            "type":"Services"
        },
        {
            "category":"Retail",
            "subcategory":"Auto Repair",
            "type":"Services"
        }
    ],
    "sg:phone":"+1 952 432 7676",
    "sg:postcode":"55337",
    "sg:province":"MN",
    "sg:tags":[
        "towing",
        "tire"
    ],
    "wof:name":"Cedar Avenue Tire & Auto",
    "wof:placetype":"venue"
},
  "geometry": {"coordinates":[-93.268799,44.771702],"type":"Point"}
}