{
  "type": "Feature",
  "properties": {
    "addr:full":"1109 Stagecoach Rd Shakopee MN 55379",
    "addr:housenumber":"1109",
    "addr:postcode":"55379",
    "addr:street":"Stagecoach Rd",
    "iso:country":"US",
    "sg:address":"1109 Stagecoach Rd",
    "sg:city":"Shakopee",
    "sg:classifiers":[
        {
            "category":"Structure",
            "subcategory":"Warehouse",
            "type":"Public Place"
        },
        {
            "category":"Retail",
            "subcategory":"Storage",
            "type":"Services"
        }
    ],
    "sg:phone":"+1 952 445 1514",
    "sg:postcode":"55379",
    "sg:province":"MN",
    "sg:tags":[
        "self",
        "warehouses-public-commercial"
    ],
    "sg:website":"http://www.cherne.com",
    "wof:name":"Cherne Contracting Corporation",
    "wof:placetype":"venue"
},
  "geometry": {"coordinates":[-93.41007399999999,44.78664],"type":"Point"}
}