{
  "type": "Feature",
  "properties": {
    "iso:country":"US",
    "sg:address":"724 W 98th St",
    "sg:city":"Minneapolis",
    "sg:classifiers":[
        {
            "category":"Retail",
            "subcategory":"Laundry & Dry Cleaning",
            "type":"Services"
        }
    ],
    "sg:phone":"+1 952 888 1100",
    "sg:postcode":"55420",
    "sg:province":"MN",
    "sg:tags":[
        "cleaner"
    ],
    "wof:name":"Prestige Cleaners",
    "wof:placetype":"venue"
},
  "geometry": {"coordinates":[-93.28980300000001,44.826401],"type":"Point"}
}