{
  "type": "Feature",
  "properties": {
    "addr:full":"2102 Milwaukee Ave Minneapolis MN 55404",
    "addr:housenumber":"2102",
    "addr:postcode":"55404",
    "addr:street":"Milwaukee Ave",
    "iso:country":"US",
    "sg:address":"2102 Milwaukee Ave",
    "sg:city":"Minneapolis",
    "sg:classifiers":[
        {
            "category":"Building & Trades",
            "subcategory":"Construction",
            "type":"Services"
        }
    ],
    "sg:phone":"+1 612 369 7646",
    "sg:postcode":"55404",
    "sg:province":"MN",
    "sg:tags":[
        "carpenter"
    ],
    "sg:website":"http://www.sagawoodworking.com",
    "wof:name":"Stehr Cabinets Shop",
    "wof:placetype":"venue"
},
  "geometry": {"coordinates":[-93.240048,44.960934],"type":"Point"}
}