{
  "type": "Feature",
  "properties": {
    "iso:country":"US",
    "sg:address":"11510 39th Ave N",
    "sg:city":"Minneapolis",
    "sg:classifiers":[
        {
            "category":"Shopping",
            "type":"Retail Goods"
        }
    ],
    "sg:phone":"+1 763 557 8831",
    "sg:postcode":"55441",
    "sg:province":"MN",
    "sg:tags":[
        "merchandise"
    ],
    "wof:name":"International Art Store",
    "wof:placetype":"venue"
},
  "geometry": {"coordinates":[-93.426408,45.026508],"type":"Point"}
}