{
  "type": "Feature",
  "properties": {
    "addr:full":"2019 Northview Ln NE Rochester MN 55906",
    "addr:housenumber":"2019",
    "addr:postcode":"55906",
    "addr:street":"Northview Ln Ne",
    "iso:country":"US",
    "sg:address":"2019 Northview Ln NE",
    "sg:city":"Rochester",
    "sg:classifiers":[
        {
            "category":"Shopping",
            "subcategory":"Catalog Store",
            "type":"Retail Goods"
        }
    ],
    "sg:phone":"+1 507 280 8183",
    "sg:postcode":"55906",
    "sg:province":"MN",
    "sg:tags":[
        "house",
        "mail"
    ],
    "wof:name":"Gsh Enterprises",
    "wof:placetype":"venue"
},
  "geometry": {"coordinates":[-92.43589900000001,44.04624],"type":"Point"}
}