{
  "type": "Feature",
  "properties": {
    "addr:full":"10243 Valley Forge Ln N Osseo MN 55369",
    "addr:housenumber":"10243",
    "addr:postcode":"55369",
    "addr:street":"Valley Forge Ln N",
    "iso:country":"US",
    "sg:address":"10243 Valley Forge Ln N",
    "sg:city":"Osseo",
    "sg:classifiers":[
        {
            "category":"Professional",
            "subcategory":"Engineering",
            "type":"Services"
        }
    ],
    "sg:phone":"+1 763 425 8690",
    "sg:postcode":"55369",
    "sg:province":"MN",
    "wof:name":"Uncommon Solutions",
    "wof:placetype":"venue"
},
  "geometry": {"coordinates":[-93.417832,45.140555],"type":"Point"}
}