{
  "type": "Feature",
  "properties": {
    "addr:full":"1023 Washington Ave S Minneapolis MN 55415",
    "addr:housenumber":"1023",
    "addr:postcode":"55415",
    "addr:street":"Washington Ave S",
    "iso:country":"US",
    "sg:address":"1023 Washington Ave S",
    "sg:city":"Minneapolis",
    "sg:classifiers":[
        {
            "category":"Home & Garden",
            "subcategory":"Kitchen Supply",
            "type":"Retail Goods"
        }
    ],
    "sg:phone":"+1 612 722 6622",
    "sg:postcode":"55415",
    "sg:province":"MN",
    "sg:tags":[
        "equipment",
        "restaurant"
    ],
    "wof:name":"Extentions Plus",
    "wof:placetype":"venue"
},
  "geometry": {"coordinates":[-93.254265,44.975789],"type":"Point"}
}