{
  "type": "Feature",
  "properties": {
    "iso:country":"US",
    "sg:address":"2010 E Hennepin Ave",
    "sg:city":"Minneapolis",
    "sg:classifiers":[
        {
            "category":"Shopping",
            "subcategory":"Bicycles & Sporting Goods",
            "type":"Retail Goods"
        }
    ],
    "sg:phone":"+1 612 788 6812",
    "sg:postcode":"55413",
    "sg:province":"MN",
    "sg:tags":[
        "bike"
    ],
    "wof:name":"Goodrich Curt Bycycles",
    "wof:placetype":"venue"
},
  "geometry": {"coordinates":[-93.2239,44.991501],"type":"Point"}
}