{
  "type": "Feature",
  "properties": {
    "iso:country":"US",
    "sg:address":"4612 Mill St NE",
    "sg:city":"Bemidji",
    "sg:phone":"+1 218 751 2771",
    "sg:postcode":"56601",
    "sg:province":"MN",
    "sg:tags":[
        "farm",
        "field",
        "crop"
    ],
    "wof:name":"Arnold Eichstadt",
    "wof:placetype":"venue"
},
  "geometry": {"coordinates":[-94.819503,47.467768],"type":"Point"}
}