{
  "type": "Feature",
  "properties": {
    "addr:full":"225 1st Ave N Perham MN 56573",
    "addr:housenumber":"225",
    "addr:postcode":"56573",
    "addr:street":"1St Ave N",
    "iso:country":"US",
    "sg:address":"225 1st Ave N",
    "sg:city":"Perham",
    "sg:classifiers":[
        {
            "category":"Insurance",
            "subcategory":"Insurance Agent",
            "type":"Services"
        }
    ],
    "sg:phone":"+1 218 346 5648",
    "sg:postcode":"56573",
    "sg:province":"MN",
    "wof:name":"East Ottertail Insurance",
    "wof:placetype":"venue"
},
  "geometry": {"coordinates":[-95.570955,46.595854],"type":"Point"}
}