{
  "type": "Feature",
  "properties": {
    "addr:full":"2027 Thom Dr Saint Paul MN 55112",
    "addr:housenumber":"2027",
    "addr:postcode":"55112",
    "addr:street":"Thom Dr",
    "iso:country":"US",
    "sg:address":"2027 Thom Dr",
    "sg:city":"Saint Paul",
    "sg:classifiers":[
        {
            "category":"Social Services",
            "subcategory":"Child Care",
            "type":"Services"
        }
    ],
    "sg:phone":"+1 651 631 3312",
    "sg:postcode":"55112",
    "sg:province":"MN",
    "sg:tags":[
        "daycare"
    ],
    "wof:name":"Katherine Mauricio",
    "wof:placetype":"venue"
},
  "geometry": {"coordinates":[-93.187196,45.052483],"type":"Point"}
}