{
  "type": "Feature",
  "properties": {
    "iso:country":"US",
    "sg:address":"8500 44th Ave N",
    "sg:city":"Minneapolis",
    "sg:classifiers":[
        {
            "category":"Professional",
            "subcategory":"Business Services",
            "type":"Services"
        }
    ],
    "sg:phone":"+1 763 535 6508",
    "sg:postcode":"55428",
    "sg:province":"MN",
    "sg:tags":[
        "consulting",
        "trade",
        "show"
    ],
    "wof:name":"Show Smart",
    "wof:placetype":"venue"
},
  "geometry": {"coordinates":[-93.388863,45.036128],"type":"Point"}
}