{
  "type": "Feature",
  "properties": {
    "iso:country":"US",
    "sg:address":"204 8th Ave NE",
    "sg:city":"Kasson",
    "sg:classifiers":[
        {
            "category":"Social Services",
            "subcategory":"Child Care",
            "type":"Services"
        }
    ],
    "sg:phone":"+1 507 634 7114",
    "sg:postcode":"55944",
    "sg:province":"MN",
    "sg:tags":[
        "day",
        "provides"
    ],
    "wof:name":"Joan M Kyllo",
    "wof:placetype":"venue"
},
  "geometry": {"coordinates":[-92.73904400000001,44.03141],"type":"Point"}
}