{
  "type": "Feature",
  "properties": {
    "addr:full":"206 S Swain St Redwood Falls MN 56283",
    "addr:housenumber":"206",
    "addr:postcode":"56283",
    "addr:street":"S Swain St",
    "iso:country":"US",
    "sg:address":"206 S Swain St",
    "sg:city":"Redwood Falls",
    "sg:phone":"+1 507 637 8727",
    "sg:postcode":"56283",
    "sg:province":"MN",
    "sg:tags":[
        "farm",
        "corn",
        "soybean"
    ],
    "wof:name":"Harlan Raddatz",
    "wof:placetype":"venue"
},
  "geometry": {"coordinates":[-95.10986,44.540441],"type":"Point"}
}