{
  "type": "Feature",
  "properties": {
    "iso:country":"US",
    "sg:address":"20701 150th St",
    "sg:city":"New Richland",
    "sg:phone":"+1 507 465 3756",
    "sg:postcode":"56072",
    "sg:province":"MN",
    "sg:tags":[
        "farm",
        "field",
        "crop"
    ],
    "wof:name":"Wakefield Farm",
    "wof:placetype":"venue"
},
  "geometry": {"coordinates":[-93.466994,43.857154],"type":"Point"}
}