{
  "type": "Feature",
  "properties": {
    "iso:country":"US",
    "sg:address":"100 6th St N",
    "sg:city":"Minneapolis",
    "sg:classifiers":[
        {
            "category":"Shopping",
            "subcategory":"Computers & Home Electronics",
            "type":"Retail Goods"
        }
    ],
    "sg:phone":"+1 612 455 2300",
    "sg:postcode":"55403",
    "sg:province":"MN",
    "sg:tags":[
        "software"
    ],
    "sg:website":"www.verisae.com",
    "wof:name":"Verisae",
    "wof:placetype":"venue"
},
  "geometry": {"coordinates":[-93.27597799999999,44.980438],"type":"Point"}
}