{
  "type": "Feature",
  "properties": {
    "addr:full":"9511 W Broadway Ave Forest Lake MN 55025",
    "addr:housenumber":"9511",
    "addr:postcode":"55025",
    "addr:street":"W Broadway Ave",
    "iso:country":"US",
    "sg:address":"9511 W Broadway Ave",
    "sg:city":"Forest Lake",
    "sg:classifiers":[
        {
            "category":"Organizations",
            "subcategory":"Religious Organization",
            "type":"Services"
        }
    ],
    "sg:phone":"+1 651 464 7504",
    "sg:postcode":"55025",
    "sg:province":"MN",
    "sg:tags":[
        "church"
    ],
    "sg:website":"www.immanuelonline.net",
    "wof:name":"Immanuel Church Of Forest Lake",
    "wof:placetype":"venue"
},
  "geometry": {"coordinates":[-93.026425,45.286564],"type":"Point"}
}