{
  "type": "Feature",
  "properties": {
    "addr:full":"2383 University Ave W Saint Paul MN 55104",
    "addr:housenumber":"2383",
    "addr:postcode":"55104",
    "addr:street":"University Ave W",
    "iso:country":"US",
    "sg:address":"2383 University Ave W",
    "sg:city":"Saint Paul",
    "sg:classifiers":[
        {
            "category":"Banks & Credit Unions",
            "subcategory":"Bank",
            "type":"Services"
        }
    ],
    "sg:phone":"+1 651 647 3500",
    "sg:postcode":"55104",
    "sg:province":"MN",
    "sg:tags":[
        "national"
    ],
    "wof:name":"First Bank Midway",
    "wof:placetype":"venue"
},
  "geometry": {"coordinates":[-93.19660500000001,44.96347],"type":"Point"}
}