{
  "type": "Feature",
  "properties": {
    "addr:full":"370 Tiffany Dr Hastings MN 55033",
    "addr:housenumber":"370",
    "addr:postcode":"55033",
    "addr:street":"Tiffany Dr",
    "iso:country":"US",
    "sg:address":"370 Tiffany Dr",
    "sg:city":"Hastings",
    "sg:classifiers":[
        {
            "category":"Home & Garden",
            "subcategory":"Carpets & Floor Coverings",
            "type":"Retail Goods"
        }
    ],
    "sg:phone":"+1 612 868 5564",
    "sg:postcode":"55033",
    "sg:province":"MN",
    "wof:name":"Color Tile",
    "wof:placetype":"venue"
},
  "geometry": {"coordinates":[-92.847189,44.710052],"type":"Point"}
}