{
  "type": "Feature",
  "properties": {
    "iso:country":"US",
    "sg:address":"1650 Excelsior Rd N",
    "sg:city":"Baxter",
    "sg:classifiers":[
        {
            "category":"Real Estate",
            "subcategory":"Real Estate Agent",
            "type":"Services"
        }
    ],
    "sg:phone":"+1 218 822 7355",
    "sg:postcode":"56425",
    "sg:province":"MN",
    "wof:name":"Assist 2 Sell",
    "wof:placetype":"venue"
},
  "geometry": {"coordinates":[-94.24041200000001,46.354653],"type":"Point"}
}