{
  "type": "Feature",
  "properties": {
    "addr:full":"9899 140th St W Montgomery MN 56069",
    "addr:housenumber":"9899",
    "addr:postcode":"56069",
    "addr:street":"140Th St W",
    "iso:country":"US",
    "sg:address":"9899 140th St W",
    "sg:city":"Montgomery",
    "sg:classifiers":[
        {
            "category":"Building & Trades",
            "subcategory":"Construction",
            "type":"Services"
        }
    ],
    "sg:phone":"+1 507 334 1501",
    "sg:postcode":"56069",
    "sg:province":"MN",
    "sg:tags":[
        "residential"
    ],
    "wof:name":"Velishek Construction",
    "wof:placetype":"venue"
},
  "geometry": {"coordinates":[-93.46741900000001,44.384991],"type":"Point"}
}