{
  "type": "Feature",
  "properties": {
    "addr:full":"15640 Co Rd 14 NE Eagle Bend MN 56446",
    "addr:housenumber":"15640;14",
    "addr:postcode":"56446",
    "addr:street":"Co Rd;Ne Eagle Bend",
    "iso:country":"US",
    "sg:address":"15640 Co Rd 14 NE",
    "sg:city":"Eagle Bend",
    "sg:classifiers":[
        {
            "category":"Building & Trades",
            "subcategory":"Plumbing",
            "type":"Services"
        }
    ],
    "sg:phone":"+1 218 943 5054",
    "sg:postcode":"56446",
    "sg:province":"MN",
    "sg:tags":[
        "contractor"
    ],
    "wof:name":"Eagle Plumbing & Heating",
    "wof:placetype":"venue"
},
  "geometry": {"coordinates":[-95.166973,46.066447],"type":"Point"}
}