{
  "type": "Feature",
  "properties": {
    "addr:full":"2345 70th Ave Balaton MN 56115",
    "addr:housenumber":"2345",
    "addr:postcode":"56115",
    "addr:street":"70Th Ave",
    "iso:country":"US",
    "sg:address":"2345 70th Ave",
    "sg:city":"Balaton",
    "sg:classifiers":[
        {
            "category":"Farming",
            "subcategory":"Livestock Farm",
            "type":"Manufacturing & Wholesale Goods"
        }
    ],
    "sg:phone":"+1 507 734 4984",
    "sg:postcode":"56115",
    "sg:province":"MN",
    "sg:tags":[
        "feeding"
    ],
    "wof:name":"Dwayne Eisfeld",
    "wof:placetype":"venue"
},
  "geometry": {"coordinates":[-95.924402,44.192058],"type":"Point"}
}