{
  "type": "Feature",
  "properties": {
    "iso:country":"US",
    "sg:address":"8908 Prestwick Cir",
    "sg:city":"Minneapolis",
    "sg:classifiers":[
        {
            "category":"Professional",
            "subcategory":"Management & Consulting",
            "type":"Services"
        }
    ],
    "sg:phone":"+1 763 424 2377",
    "sg:postcode":"55443",
    "sg:province":"MN",
    "sg:tags":[
        "energy"
    ],
    "wof:name":"Progrssive Enrgy Solutions LLC",
    "wof:placetype":"venue"
},
  "geometry": {"coordinates":[-93.341706,45.117657],"type":"Point"}
}