{
  "type": "Feature",
  "properties": {
    "addr:full":"1901 Skyline Dr N Burnsville MN 55337",
    "addr:housenumber":"1901",
    "addr:postcode":"55337",
    "addr:street":"Skyline Dr N",
    "iso:country":"US",
    "sg:address":"1901 Skyline Dr N",
    "sg:city":"Burnsville",
    "sg:classifiers":[
        {
            "category":"Restaurant",
            "type":"Food & Drink"
        }
    ],
    "sg:phone":"+1 952 220 0314",
    "sg:postcode":"55337",
    "sg:province":"MN",
    "sg:tags":[
        "caterer"
    ],
    "wof:name":"Guy's Down The Street Catering",
    "wof:placetype":"venue"
},
  "geometry": {"coordinates":[-93.250092,44.778843],"type":"Point"}
}