{
  "type": "Feature",
  "properties": {
    "addr:full":"12208 State Hwy 11 Greenbush MN 56726",
    "addr:housenumber":"12208",
    "addr:postcode":"56726",
    "addr:street":"State Hwy 11",
    "iso:country":"US",
    "sg:address":"12208 State Hwy 11",
    "sg:city":"Greenbush",
    "sg:classifiers":[
        {
            "category":"Freight",
            "type":"Transportation"
        }
    ],
    "sg:phone":"+1 218 782 2970",
    "sg:postcode":"56726",
    "sg:province":"MN",
    "sg:tags":[
        "operator",
        "local",
        "trucking"
    ],
    "wof:name":"Langaas Trucking Inc",
    "wof:placetype":"venue"
},
  "geometry": {"coordinates":[-96.341556,48.656682],"type":"Point"}
}