{
  "type": "Feature",
  "properties": {
    "iso:country":"US",
    "sg:address":"2528 Maple Ln",
    "sg:city":"Saint Paul",
    "sg:classifiers":[
        {
            "category":"Shopping",
            "subcategory":"Clothing, Apparel, & Fashions",
            "type":"Retail Goods"
        }
    ],
    "sg:phone":"+1 651 631 3324",
    "sg:postcode":"55113",
    "sg:province":"MN",
    "wof:name":"Jersey Station",
    "wof:placetype":"venue"
},
  "geometry": {"coordinates":[-93.207836,45.029292],"type":"Point"}
}