{
  "type": "Feature",
  "properties": {
    "iso:country":"US",
    "sg:address":"50 9th Ave S",
    "sg:city":"Hopkins",
    "sg:classifiers":[
        {
            "category":"Health Services",
            "subcategory":"Health Practitioner",
            "type":"Services"
        }
    ],
    "sg:phone":"+1 952 938 7672",
    "sg:postcode":"55343",
    "sg:province":"MN",
    "sg:tags":[
        "nutritionist"
    ],
    "wof:name":"Laboratory Research Assoc",
    "wof:placetype":"venue"
},
  "geometry": {"coordinates":[-93.411586,44.923361],"type":"Point"}
}