{
  "type": "Feature",
  "properties": {
    "addr:full":"13783 Ibis St NW Andover MN 55304",
    "addr:housenumber":"13783",
    "addr:postcode":"55304",
    "addr:street":"Ibis St Nw",
    "iso:country":"US",
    "sg:address":"13783 Ibis St NW",
    "sg:city":"Andover",
    "sg:classifiers":[
        {
            "category":"Shopping",
            "subcategory":"Party Supplies",
            "type":"Retail Goods"
        },
        {
            "category":"Shopping",
            "subcategory":"Bridal",
            "type":"Retail Goods"
        }
    ],
    "sg:phone":"+1 763 427 5600",
    "sg:postcode":"55304",
    "sg:province":"MN",
    "sg:tags":[
        "shop",
        "wedding"
    ],
    "wof:name":"The Glass Slipper Bridal Salon",
    "wof:placetype":"venue"
},
  "geometry": {"coordinates":[-93.309921,45.220688],"type":"Point"}
}