{
  "type": "Feature",
  "properties": {
    "iso:country":"US",
    "sg:address":"2522 Lyndale Ave N",
    "sg:city":"Minneapolis",
    "sg:classifiers":[
        {
            "category":"Professional",
            "subcategory":"Printing & Photocopies",
            "type":"Services"
        }
    ],
    "sg:phone":"+1 612 870 8882",
    "sg:postcode":"55411",
    "sg:province":"MN",
    "wof:name":"SIR Speedy Printing Centers",
    "wof:placetype":"venue"
},
  "geometry": {"coordinates":[-93.28780399999999,45.0056],"type":"Point"}
}