{
  "type": "Feature",
  "properties": {
    "iso:country":"US",
    "sg:address":"909 W Laurel Ave",
    "sg:city":"St Paul",
    "sg:classifiers":[
        {
            "category":"Arts & Performance",
            "subcategory":"Theater",
            "type":"Entertainment"
        }
    ],
    "sg:phone":"+1 651 224 4272",
    "sg:postcode":"55104",
    "sg:province":"MN",
    "sg:tags":[
        "theatrical",
        "music"
    ],
    "wof:name":"Sentwali Entertainment",
    "wof:placetype":"venue"
},
  "geometry": {"coordinates":[-93.13750400000001,44.94504],"type":"Point"}
}