{
  "type": "Feature",
  "properties": {
    "iso:country":"US",
    "sg:address":"3800 W 80th St",
    "sg:city":"Minneapolis",
    "sg:classifiers":[
        {
            "category":"Professional",
            "subcategory":"Accounting & Tax Preparation",
            "type":"Services"
        }
    ],
    "sg:phone":"+1 612 871 2285",
    "sg:postcode":"55431",
    "sg:province":"MN",
    "sg:tags":[
        "accountant",
        "public",
        "certified"
    ],
    "wof:name":"Belvedere & Hysjulien PA",
    "wof:placetype":"venue"
},
  "geometry": {"coordinates":[-93.328053,44.855769],"type":"Point"}
}