{
  "type": "Feature",
  "properties": {
    "addr:full":"8014 Highway 55 # 120 Minneapolis MN 55427",
    "addr:housenumber":"8014",
    "addr:postcode":"55427",
    "addr:street":"Highway 55 # 120",
    "iso:country":"US",
    "sg:address":"8014 Highway 55 # 120",
    "sg:city":"Minneapolis",
    "sg:classifiers":[
        {
            "category":"Banks & Credit Unions",
            "subcategory":"Financial Services",
            "type":"Services"
        }
    ],
    "sg:phone":"+1 612 605 0825",
    "sg:postcode":"55427",
    "sg:province":"MN",
    "sg:tags":[
        "loan"
    ],
    "wof:name":"Liquid Logo",
    "wof:placetype":"venue"
},
  "geometry": {"coordinates":[-93.381613,44.984068],"type":"Point"}
}