{
  "type": "Feature",
  "properties": {
    "addr:full":"6325 Bergquist Rd Duluth MN 55804",
    "addr:housenumber":"6325",
    "addr:postcode":"55804",
    "addr:street":"Bergquist Rd",
    "iso:country":"US",
    "sg:address":"6325 Bergquist Rd",
    "sg:city":"Duluth",
    "sg:classifiers":[
        {
            "category":"Building & Trades",
            "subcategory":"Construction",
            "type":"Services"
        }
    ],
    "sg:phone":"+1 218 591 7350",
    "sg:postcode":"55804",
    "sg:province":"MN",
    "sg:tags":[
        "hanging",
        "contractor"
    ],
    "wof:name":"Calco Painting",
    "wof:placetype":"venue"
},
  "geometry": {"coordinates":[-91.88935499999999,46.968161],"type":"Point"}
}