{
  "type": "Feature",
  "properties": {
    "addr:full":"9 9th Ave N Hopkins MN 55343",
    "addr:housenumber":"9",
    "addr:postcode":"55343",
    "addr:street":"9Th Ave N",
    "iso:country":"US",
    "sg:address":"9 9th Ave N",
    "sg:city":"Hopkins",
    "sg:classifiers":[
        {
            "category":"Professional",
            "subcategory":"Engineering",
            "type":"Services"
        }
    ],
    "sg:phone":"+1 952 938 7407",
    "sg:postcode":"55343",
    "sg:province":"MN",
    "sg:tags":[
        "engineer"
    ],
    "sg:website":"www.smeng.com",
    "wof:name":"S & M Engineering",
    "wof:placetype":"venue"
},
  "geometry": {"coordinates":[-93.41130800000001,44.925248],"type":"Point"}
}