{
  "type": "Feature",
  "properties": {
    "iso:country":"US",
    "sg:address":"5001 University Ave NE",
    "sg:city":"Minneapolis",
    "sg:classifiers":[
        {
            "category":"Building & Trades",
            "subcategory":"Construction",
            "type":"Services"
        }
    ],
    "sg:phone":"+1 763 572 4027",
    "sg:postcode":"55421",
    "sg:province":"MN",
    "sg:tags":[
        "marking",
        "maintenance",
        "parking"
    ],
    "wof:name":"Taylor Seal & Striping Co",
    "wof:placetype":"venue"
},
  "geometry": {"coordinates":[-93.26288700000001,45.060852],"type":"Point"}
}