{
  "type": "Feature",
  "properties": {
    "addr:full":"7855 Lake Dr Circle Pines MN 55014",
    "addr:housenumber":"7855",
    "addr:postcode":"55014",
    "addr:street":"Lake Dr Circle",
    "iso:country":"US",
    "sg:address":"7855 Lake Dr",
    "sg:city":"Circle Pines",
    "sg:classifiers":[
        {
            "category":"Home & Garden",
            "subcategory":"Garden Supply",
            "type":"Retail Goods"
        }
    ],
    "sg:phone":"+1 651 786 9455",
    "sg:postcode":"55014",
    "sg:province":"MN",
    "sg:tags":[
        "nurseryman"
    ],
    "wof:name":"Minnesota Groundcovers",
    "wof:placetype":"venue"
},
  "geometry": {"coordinates":[-93.104795,45.191325],"type":"Point"}
}