{
  "type": "Feature",
  "properties": {
    "iso:country":"US",
    "sg:address":"1916 College Way",
    "sg:city":"Fergus Falls",
    "sg:classifiers":[
        {
            "category":"Shopping",
            "type":"Retail Goods"
        }
    ],
    "sg:phone":"+1 218 998 2254",
    "sg:postcode":"56537",
    "sg:province":"MN",
    "sg:tags":[
        "feed",
        "animal"
    ],
    "wof:name":"Country Store",
    "wof:placetype":"venue"
},
  "geometry": {"coordinates":[-96.10575900000001,46.28949],"type":"Point"}
}