{
  "type": "Feature",
  "properties": {
    "addr:full":"344 W Sidney St Saint Paul MN 55107",
    "addr:housenumber":"344",
    "addr:postcode":"55107",
    "addr:street":"W Sidney St",
    "iso:country":"US",
    "sg:address":"344 W Sidney St",
    "sg:city":"Saint Paul",
    "sg:classifiers":[
        {
            "category":"Social Services",
            "subcategory":"Child Care",
            "type":"Services"
        }
    ],
    "sg:phone":"+1 651 221 9076",
    "sg:postcode":"55107",
    "sg:province":"MN",
    "sg:tags":[
        "day",
        "provider"
    ],
    "wof:name":"Amy L Lengsfeld",
    "wof:placetype":"venue"
},
  "geometry": {"coordinates":[-93.100116,44.923557],"type":"Point"}
}