{
  "type": "Feature",
  "properties": {
    "iso:country":"US",
    "sg:address":"7711 20th St SE",
    "sg:city":"Buffalo",
    "sg:classifiers":[
        {
            "category":"Building & Trades",
            "subcategory":"Plumbing",
            "type":"Services"
        }
    ],
    "sg:phone":"+1 763 477 5636",
    "sg:postcode":"55313",
    "sg:province":"MN",
    "sg:tags":[
        "contractor"
    ],
    "wof:name":"A-Perc Test Design & Insptn",
    "wof:placetype":"venue"
},
  "geometry": {"coordinates":[-93.737088,45.122429],"type":"Point"}
}