{
  "type": "Feature",
  "properties": {
    "addr:full":"1933 E Camp St Ely MN 55731",
    "addr:housenumber":"1933",
    "addr:postcode":"55731",
    "addr:street":"E Camp St",
    "iso:country":"US",
    "sg:address":"1933 E Camp St",
    "sg:city":"Ely",
    "sg:classifiers":[
        {
            "category":"Government",
            "subcategory":"Office",
            "type":"Public Place"
        }
    ],
    "sg:phone":"+1 218 365 6309",
    "sg:postcode":"55731",
    "sg:province":"MN",
    "wof:name":"Vermillion Hall Office",
    "wof:placetype":"venue"
},
  "geometry": {"coordinates":[-91.838052,47.904258],"type":"Point"}
}