{
  "type": "Feature",
  "properties": {
    "addr:full":"617 W Minnehaha Ave St Paul MN 55104",
    "addr:housenumber":"617",
    "addr:postcode":"55104",
    "addr:street":"W Minnehaha Ave",
    "iso:country":"US",
    "sg:address":"617 W Minnehaha Ave",
    "sg:city":"St Paul",
    "sg:classifiers":[
        {
            "category":"Professional",
            "type":"Services"
        }
    ],
    "sg:phone":"+1 651 489 0411",
    "sg:postcode":"55104",
    "sg:province":"MN",
    "sg:tags":[
        "establishment"
    ],
    "wof:name":"Railtransfer Inc",
    "wof:placetype":"venue"
},
  "geometry": {"coordinates":[-93.124635,44.96303],"type":"Point"}
}