{
  "type": "Feature",
  "properties": {
    "iso:country":"US",
    "sg:address":"6743 Scott Ave N",
    "sg:city":"Minneapolis",
    "sg:classifiers":[
        {
            "category":"Transit Center",
            "subcategory":"Freight",
            "type":"Transportation"
        },
        {
            "category":"Freight",
            "type":"Transportation"
        }
    ],
    "sg:phone":"+1 763 561 0561",
    "sg:postcode":"55429",
    "sg:province":"MN",
    "sg:tags":[
        "local",
        "trucking-motor",
        "trucking"
    ],
    "wof:name":"Rol Small Trucking",
    "wof:placetype":"venue"
},
  "geometry": {"coordinates":[-93.346977,45.077259],"type":"Point"}
}