{
  "type": "Feature",
  "properties": {
    "iso:country":"US",
    "sg:address":"912 E 24th St",
    "sg:city":"Minneapolis",
    "sg:classifiers":[
        {
            "category":"Professional",
            "type":"Services"
        }
    ],
    "sg:phone":"+1 612 354 7863",
    "sg:postcode":"55404",
    "sg:province":"MN",
    "sg:tags":[
        "transportation"
    ],
    "wof:name":"Nep Logistics Inc",
    "wof:placetype":"venue"
},
  "geometry": {"coordinates":[-93.260915,44.959103],"type":"Point"}
}