{
  "type": "Feature",
  "properties": {
    "iso:country":"US",
    "sg:address":"103 Craig Ln",
    "sg:city":"Monticello",
    "sg:classifiers":[
        {
            "category":"Social Services",
            "subcategory":"Child Care",
            "type":"Services"
        }
    ],
    "sg:phone":"+1 763 295 5831",
    "sg:postcode":"55362",
    "sg:province":"MN",
    "sg:tags":[
        "day"
    ],
    "wof:name":"Debra D Anderson",
    "wof:placetype":"venue"
},
  "geometry": {"coordinates":[-93.819137,45.316408],"type":"Point"}
}