{
  "type": "Feature",
  "properties": {
    "iso:country":"US",
    "sg:address":"7887 Fuller Rd",
    "sg:city":"Eden Prairie",
    "sg:classifiers":[
        {
            "category":"Professional",
            "type":"Services"
        }
    ],
    "sg:phone":"+1 612 836 0495",
    "sg:postcode":"55344",
    "sg:province":"MN",
    "sg:tags":[
        "establishment"
    ],
    "wof:name":"Fibrenew International LTD",
    "wof:placetype":"venue"
},
  "geometry": {"coordinates":[-93.479851,44.861652],"type":"Point"}
}