{
  "type": "Feature",
  "properties": {
    "addr:full":"10071 Co Rd 6 NW Alexandria MN 56308",
    "addr:housenumber":"10071",
    "addr:postcode":"56308",
    "addr:street":"Co Rd 6 Nw",
    "iso:country":"US",
    "sg:address":"10071 Co Rd 6 NW",
    "sg:city":"Alexandria",
    "sg:classifiers":[
        {
            "category":"Freight",
            "type":"Transportation"
        }
    ],
    "sg:phone":"+1 320 834 2677",
    "sg:postcode":"56308",
    "sg:province":"MN",
    "sg:tags":[
        "trucking"
    ],
    "wof:name":"M & J Eisel Trucking",
    "wof:placetype":"venue"
},
  "geometry": {"coordinates":[-95.457493,45.991346],"type":"Point"}
}