{
  "type": "Feature",
  "properties": {
    "addr:full":"245 E 6th St Saint Paul MN 55101",
    "addr:housenumber":"245",
    "addr:postcode":"55101",
    "addr:street":"E 6Th St",
    "iso:country":"US",
    "sg:address":"245 E 6th St",
    "sg:city":"Saint Paul",
    "sg:classifiers":[
        {
            "category":"Real Estate",
            "subcategory":"Real Estate Operator",
            "type":"Services"
        }
    ],
    "sg:phone":"+1 651 291 8995",
    "sg:postcode":"55101",
    "sg:province":"MN",
    "sg:tags":[
        "management",
        "commercial"
    ],
    "wof:name":"Lowertown Business Center",
    "wof:placetype":"venue"
},
  "geometry": {"coordinates":[-93.08672,44.950616],"type":"Point"}
}