{
  "type": "Feature",
  "properties": {
    "addr:full":"7812 Bush Lake Dr Minneapolis MN 55438",
    "addr:housenumber":"7812",
    "addr:postcode":"55438",
    "addr:street":"Bush Lake Dr",
    "iso:country":"US",
    "sg:address":"7812 Bush Lake Dr",
    "sg:city":"Minneapolis",
    "sg:classifiers":[
        {
            "category":"Recreation",
            "type":"Entertainment"
        }
    ],
    "sg:phone":"+1 612 889 6944",
    "sg:postcode":"55438",
    "sg:province":"MN",
    "sg:tags":[
        "camps-recreational"
    ],
    "wof:name":"Tri Star Select Hockey",
    "wof:placetype":"venue"
},
  "geometry": {"coordinates":[-93.387877,44.825409],"type":"Point"}
}