{
  "type": "Feature",
  "properties": {
    "iso:country":"US",
    "sg:address":"1309 8th Ave SW",
    "sg:city":"Austin",
    "sg:classifiers":[
        {
            "category":"Building & Trades",
            "subcategory":"Construction",
            "type":"Services"
        }
    ],
    "sg:phone":"+1 507 433 7117",
    "sg:postcode":"55912",
    "sg:province":"MN",
    "sg:tags":[
        "general",
        "contractor"
    ],
    "wof:name":"B & B Better Built Builders",
    "wof:placetype":"venue"
},
  "geometry": {"coordinates":[-92.99343,43.659246],"type":"Point"}
}