{
  "type": "Feature",
  "properties": {
    "addr:full":"200 14th Ave NE Glenwood MN 56334",
    "addr:housenumber":"200",
    "addr:postcode":"56334",
    "addr:street":"14Th Ave Ne",
    "iso:country":"US",
    "sg:address":"200 14th Ave NE",
    "sg:city":"Glenwood",
    "sg:classifiers":[
        {
            "category":"Retail",
            "subcategory":"Repair Shop",
            "type":"Services"
        }
    ],
    "sg:phone":"+1 320 634 4681",
    "sg:postcode":"56334",
    "sg:province":"MN",
    "sg:tags":[
        "farm",
        "machinery"
    ],
    "wof:name":"Grants Service",
    "wof:placetype":"venue"
},
  "geometry": {"coordinates":[-95.38581600000001,45.663678],"type":"Point"}
}