{
  "type": "Feature",
  "properties": {
    "addr:full":"1841 University Ave W Saint Paul MN 55104",
    "addr:housenumber":"1841",
    "addr:postcode":"55104",
    "addr:street":"University Ave W",
    "iso:country":"US",
    "sg:address":"1841 University Ave W",
    "sg:city":"Saint Paul",
    "sg:classifiers":[
        {
            "category":"Building & Trades",
            "subcategory":"Construction",
            "type":"Services"
        }
    ],
    "sg:phone":"+1 651 647 4925",
    "sg:postcode":"55104",
    "sg:province":"MN",
    "sg:tags":[
        "house"
    ],
    "wof:name":"Honka Log Homes",
    "wof:placetype":"venue"
},
  "geometry": {"coordinates":[-93.17768,44.956054],"type":"Point"}
}