{
  "type": "Feature",
  "properties": {
    "addr:full":"8324 Co Rd 25 Houston MN 55943",
    "addr:housenumber":"8324;25",
    "addr:postcode":"55943",
    "addr:street":"Co Rd",
    "iso:country":"US",
    "sg:address":"8324 Co Rd 25",
    "sg:city":"Houston",
    "sg:classifiers":[
        {
            "category":"Farming",
            "subcategory":"Dairy Farm",
            "type":"Manufacturing & Wholesale Goods"
        }
    ],
    "sg:phone":"+1 507 896 3229",
    "sg:postcode":"55943",
    "sg:province":"MN",
    "wof:name":"Von Moos Roger",
    "wof:placetype":"venue"
},
  "geometry": {"coordinates":[-91.449977,43.819834],"type":"Point"}
}