{
  "type": "Feature",
  "properties": {
    "addr:full":"12381 N Shore Dr Spicer MN 56288",
    "addr:housenumber":"12381",
    "addr:postcode":"56288",
    "addr:street":"N Shore Dr Spicer",
    "iso:country":"US",
    "sg:address":"12381 N Shore Dr",
    "sg:city":"Spicer",
    "sg:classifiers":[
        {
            "category":"Travel",
            "subcategory":"Campground",
            "type":"Entertainment"
        }
    ],
    "sg:phone":"+1 320 796 5564",
    "sg:postcode":"56288",
    "sg:province":"MN",
    "wof:name":"Kandiyohi County Park",
    "wof:placetype":"venue"
},
  "geometry": {"coordinates":[-94.87575,45.273783],"type":"Point"}
}