{
  "type": "Feature",
  "properties": {
    "addr:full":"203 5th St NE Saint Stephen MN 56375",
    "addr:housenumber":"203",
    "addr:postcode":"56375",
    "addr:street":"5Th St Ne Saint Stephen",
    "iso:country":"US",
    "sg:address":"203 5th St NE",
    "sg:city":"Saint Stephen",
    "sg:classifiers":[
        {
            "category":"Building & Trades",
            "subcategory":"Construction",
            "type":"Services"
        }
    ],
    "sg:phone":"+1 320 259 1005",
    "sg:postcode":"56375",
    "sg:province":"MN",
    "sg:tags":[
        "house",
        "nonresidential"
    ],
    "wof:name":"Dale Kremers Construction",
    "wof:placetype":"venue"
},
  "geometry": {"coordinates":[-94.269943,45.70917],"type":"Point"}
}