{
  "type": "Feature",
  "properties": {
    "addr:full":"4716 Minnetonka Blvd Minneapolis MN 55416",
    "addr:housenumber":"4716",
    "addr:postcode":"55416",
    "addr:street":"Minnetonka Blvd",
    "iso:country":"US",
    "sg:address":"4716 Minnetonka Blvd",
    "sg:city":"Minneapolis",
    "sg:classifiers":[
        {
            "category":"Professional",
            "subcategory":"Management & Consulting",
            "type":"Services"
        }
    ],
    "sg:phone":"+1 952 925 0145",
    "sg:postcode":"55416",
    "sg:province":"MN",
    "wof:name":"People Solutions Inc",
    "wof:placetype":"venue"
},
  "geometry": {"coordinates":[-93.340199,44.948541],"type":"Point"}
}