{
  "type": "Feature",
  "properties": {
    "iso:country":"US",
    "sg:address":"23511 Greenfield Rd",
    "sg:city":"Richmond",
    "sg:classifiers":[
        {
            "category":"Professional",
            "type":"Services"
        }
    ],
    "sg:phone":"+1 320 597 3322",
    "sg:postcode":"56368",
    "sg:province":"MN",
    "wof:name":"Lieser Donal",
    "wof:placetype":"venue"
},
  "geometry": {"coordinates":[-94.578226,45.462575],"type":"Point"}
}