{
  "type": "Feature",
  "properties": {
    "addr:full":"725 70th Ave NE Benson MN 56215",
    "addr:housenumber":"725",
    "addr:postcode":"56215",
    "addr:street":"70Th Ave Ne",
    "iso:country":"US",
    "sg:address":"725 70th Ave NE",
    "sg:city":"Benson",
    "sg:classifiers":[
        {
            "category":"Farming",
            "subcategory":"Dairy Farm",
            "type":"Manufacturing & Wholesale Goods"
        }
    ],
    "sg:phone":"+1 320 843 3714",
    "sg:postcode":"56215",
    "sg:province":"MN",
    "sg:tags":[
        "beef",
        "feedlot",
        "cattle"
    ],
    "wof:name":"Nelsons Farms",
    "wof:placetype":"venue"
},
  "geometry": {"coordinates":[-95.48040399999999,45.39937],"type":"Point"}
}