{
  "type": "Feature",
  "properties": {
    "iso:country":"US",
    "sg:address":"6355 Pierce St NE",
    "sg:city":"Fridley",
    "sg:classifiers":[
        {
            "category":"Retail",
            "subcategory":"Repair Shop",
            "type":"Services"
        }
    ],
    "sg:phone":"+1 952 920 6195",
    "sg:postcode":"55432",
    "sg:province":"MN",
    "sg:tags":[
        "appliance",
        "electrical",
        "refrigeration"
    ],
    "wof:name":"Direct Home Appliance Service",
    "wof:placetype":"venue"
},
  "geometry": {"coordinates":[-93.24042799999999,45.082153],"type":"Point"}
}