{
  "type": "Feature",
  "properties": {
    "iso:country":"US",
    "sg:address":"2928 M T Nelson Rd",
    "sg:city":"Barnum",
    "sg:classifiers":[
        {
            "category":"Building & Trades",
            "subcategory":"Construction",
            "type":"Services"
        }
    ],
    "sg:phone":"+1 218 389 6758",
    "sg:postcode":"55707",
    "sg:province":"MN",
    "sg:tags":[
        "contractor"
    ],
    "wof:name":"B P Masonry Inc",
    "wof:placetype":"venue"
},
  "geometry": {"coordinates":[-92.678034,46.563062],"type":"Point"}
}