{
  "type": "Feature",
  "properties": {
    "iso:country":"US",
    "sg:address":"817 2nd St W",
    "sg:city":"Northfield",
    "sg:classifiers":[
        {
            "category":"Professional",
            "subcategory":"Business Services",
            "type":"Services"
        }
    ],
    "sg:phone":"+1 507 645 3574",
    "sg:postcode":"55057",
    "sg:province":"MN",
    "sg:tags":[
        "consultant",
        "coach"
    ],
    "wof:name":"Tao",
    "wof:placetype":"venue"
},
  "geometry": {"coordinates":[-93.171244,44.45844],"type":"Point"}
}