{
  "type": "Feature",
  "properties": {
    "iso:country":"US",
    "sg:address":"1304 Birchwood Dr",
    "sg:city":"New Ulm",
    "sg:classifiers":[
        {
            "category":"Health Services",
            "subcategory":"Nursing And Care Facility",
            "type":"Services"
        }
    ],
    "sg:phone":"+1 507 359 3420",
    "sg:postcode":"56073",
    "sg:province":"MN",
    "sg:tags":[
        "intermediate",
        "skilled",
        "convalescent",
        "home"
    ],
    "wof:name":"Prairie Senior Cottages New",
    "wof:placetype":"venue"
},
  "geometry": {"coordinates":[-94.489323,44.326426],"type":"Point"}
}