{
  "type": "Feature",
  "properties": {
    "iso:country":"US",
    "sg:address":"111 Main St S",
    "sg:city":"Austin",
    "sg:classifiers":[
        {
            "category":"Banks & Credit Unions",
            "subcategory":"Investment Brokerage",
            "type":"Services"
        }
    ],
    "sg:phone":"+1 507 437 8080",
    "sg:postcode":"55912",
    "sg:province":"MN",
    "sg:tags":[
        "consultant",
        "planning",
        "financial"
    ],
    "wof:name":"American Express Financial Adv",
    "wof:placetype":"venue"
},
  "geometry": {"coordinates":[-92.974779,43.666486],"type":"Point"}
}