{
  "type": "Feature",
  "properties": {
    "iso:country":"US",
    "sg:address":"8784 Mogensen Shores Rd",
    "sg:city":"Brainerd",
    "sg:classifiers":[
        {
            "category":"Building & Trades",
            "subcategory":"Construction",
            "type":"Services"
        }
    ],
    "sg:phone":"+1 218 828 3580",
    "sg:postcode":"56401",
    "sg:province":"MN",
    "sg:tags":[
        "house"
    ],
    "wof:name":"Rakow Construction",
    "wof:placetype":"venue"
},
  "geometry": {"coordinates":[-94.10330999999999,46.277989],"type":"Point"}
}