{
  "type": "Feature",
  "properties": {
    "iso:country":"US",
    "sg:address":"18820 County 9 Blvd",
    "sg:city":"Goodhue",
    "sg:classifiers":[
        {
            "category":"Farming",
            "subcategory":"Dairy Farm",
            "type":"Manufacturing & Wholesale Goods"
        },
        {
            "category":"Farming",
            "subcategory":"Farm",
            "type":"Manufacturing & Wholesale Goods"
        }
    ],
    "sg:phone":"+1 651 923 4216",
    "sg:postcode":"55027",
    "sg:province":"MN",
    "wof:name":"David Burfeind",
    "wof:placetype":"venue"
},
  "geometry": {"coordinates":[-92.655159,44.3982],"type":"Point"}
}