{
  "type": "Feature",
  "properties": {
    "iso:country":"US",
    "sg:address":"231 E Superior St",
    "sg:city":"Duluth",
    "sg:classifiers":[
        {
            "category":"Restaurant",
            "type":"Food & Drink"
        }
    ],
    "sg:phone":"+1 218 723 1866",
    "sg:postcode":"55802",
    "sg:province":"MN",
    "wof:name":"Chinese Garden Restaurant",
    "wof:placetype":"venue"
},
  "geometry": {"coordinates":[-92.094854,46.789547],"type":"Point"}
}