{
  "type": "Feature",
  "properties": {
    "iso:country":"US",
    "sg:address":"36304 US Hwy 169",
    "sg:city":"Aitkin",
    "sg:classifiers":[
        {
            "category":"Retail",
            "subcategory":"Repair Shop",
            "type":"Services"
        }
    ],
    "sg:phone":"+1 218 927 4228",
    "sg:postcode":"56431",
    "sg:province":"MN",
    "sg:tags":[
        "welding"
    ],
    "wof:name":"Al's Welding & Sand Blasting",
    "wof:placetype":"venue"
},
  "geometry": {"coordinates":[-93.69601900000001,46.533374],"type":"Point"}
}