{
  "type": "Feature",
  "properties": {
    "iso:country":"US",
    "sg:address":"101 N German St",
    "sg:city":"New Ulm",
    "sg:classifiers":[
        {
            "category":"Personal",
            "subcategory":"Beauty Salon",
            "type":"Services"
        }
    ],
    "sg:phone":"+1 507 354 7267",
    "sg:postcode":"56073",
    "sg:province":"MN",
    "wof:name":"Escapes Hair Design",
    "wof:placetype":"venue"
},
  "geometry": {"coordinates":[-94.45944799999999,44.315937],"type":"Point"}
}