{
  "type": "Feature",
  "properties": {
    "iso:country":"US",
    "sg:address":"3 2nd St",
    "sg:city":"Nashwauk",
    "sg:classifiers":[
        {
            "category":"Building & Trades",
            "subcategory":"Construction",
            "type":"Services"
        }
    ],
    "sg:phone":"+1 218 885 1221",
    "sg:postcode":"55769",
    "sg:province":"MN",
    "sg:tags":[
        "marking",
        "maintenance",
        "parking"
    ],
    "wof:name":"Nashwauk Street Dept",
    "wof:placetype":"venue"
},
  "geometry": {"coordinates":[-93.167295,47.38102],"type":"Point"}
}