{
  "type": "Feature",
  "properties": {
    "iso:country":"US",
    "sg:address":"14474 Alabama Ave S",
    "sg:city":"Savage",
    "sg:classifiers":[
        {
            "category":"Building & Trades",
            "subcategory":"Plumbing",
            "type":"Services"
        }
    ],
    "sg:phone":"+1 952 440 6566",
    "sg:postcode":"55378",
    "sg:province":"MN",
    "sg:tags":[
        "contractor"
    ],
    "wof:name":"Koll Mechanical",
    "wof:placetype":"venue"
},
  "geometry": {"coordinates":[-93.356613,44.743107],"type":"Point"}
}