{
  "type": "Feature",
  "properties": {
    "iso:country":"US",
    "sg:address":"905 Westbriar Rd",
    "sg:city":"Jackson",
    "sg:classifiers":[
        {
            "category":"Farming",
            "subcategory":"Livestock Farm",
            "type":"Manufacturing & Wholesale Goods"
        }
    ],
    "sg:phone":"+1 507 847 3104",
    "sg:postcode":"56143",
    "sg:province":"MN",
    "sg:tags":[
        "beef",
        "feedlot",
        "soybean",
        "cattle"
    ],
    "wof:name":"Prochazka Farm",
    "wof:placetype":"venue"
},
  "geometry": {"coordinates":[-94.99573100000001,43.61723],"type":"Point"}
}