{
  "type": "Feature",
  "properties": {
    "iso:country":"US",
    "sg:address":"4672 Slater Rd",
    "sg:city":"Saint Paul",
    "sg:classifiers":[
        {
            "category":"Professional",
            "type":"Services"
        }
    ],
    "sg:phone":"+1 651 882 7771",
    "sg:postcode":"55122",
    "sg:province":"MN",
    "wof:name":"Wentworth Park Assc",
    "wof:placetype":"venue"
},
  "geometry": {"coordinates":[-93.22288,44.785518],"type":"Point"}
}