{
  "type": "Feature",
  "properties": {
    "iso:country":"US",
    "sg:address":"28108 243rd Ave",
    "sg:city":"Belle Plaine",
    "sg:phone":"+1 952 873 6223",
    "sg:postcode":"56011",
    "sg:province":"MN",
    "sg:tags":[
        "farm",
        "corn"
    ],
    "wof:name":"Jerry Hanlon",
    "wof:placetype":"venue"
},
  "geometry": {"coordinates":[-93.753344,44.54169],"type":"Point"}
}