{
  "type": "Feature",
  "properties": {
    "iso:country":"US",
    "sg:address":"109 S State St",
    "sg:city":"New Ulm",
    "sg:classifiers":[
        {
            "category":"Building & Trades",
            "subcategory":"Construction",
            "type":"Services"
        }
    ],
    "sg:phone":"+1 507 354 3060",
    "sg:postcode":"56073",
    "sg:province":"MN",
    "sg:tags":[
        "layer",
        "floor",
        "covering",
        "laying",
        "contractor",
        "carpet"
    ],
    "wof:name":"Rod's Floor Covering",
    "wof:placetype":"venue"
},
  "geometry": {"coordinates":[-94.460677,44.310847],"type":"Point"}
}