{
  "type": "Feature",
  "properties": {
    "addr:full":"5601 Melody Lake Dr Minneapolis MN 55436",
    "addr:housenumber":"5601",
    "addr:postcode":"55436",
    "addr:street":"Melody Lake Dr",
    "iso:country":"US",
    "sg:address":"5601 Melody Lake Dr",
    "sg:city":"Minneapolis",
    "sg:classifiers":[
        {
            "category":"Government",
            "subcategory":"City Hall",
            "type":"Public Place"
        },
        {
            "category":"Government",
            "subcategory":"Office",
            "type":"Public Place"
        }
    ],
    "sg:phone":"+1 952 826 0367",
    "sg:postcode":"55436",
    "sg:province":"MN",
    "sg:tags":[
        "town",
        "township",
        "planner",
        "government-city",
        "village"
    ],
    "sg:website":"http://www.edinaartcenter.com",
    "wof:name":"Melody Lake Park",
    "wof:placetype":"venue"
},
  "geometry": {"coordinates":[-93.355743,44.902451],"type":"Point"}
}