{
  "type": "Feature",
  "properties": {
    "iso:country":"US",
    "sg:address":"515 2nd St",
    "sg:city":"Morgan",
    "sg:classifiers":[
        {
            "category":"Wholesale",
            "subcategory":"Electrical",
            "type":"Manufacturing & Wholesale Goods"
        }
    ],
    "sg:phone":"+1 507 249 2081",
    "sg:postcode":"56266",
    "sg:province":"MN",
    "sg:tags":[
        "electric",
        "motor"
    ],
    "wof:name":"Forebrook Motor Sports Racing",
    "wof:placetype":"venue"
},
  "geometry": {"coordinates":[-94.927406,44.416509],"type":"Point"}
}