{
  "type": "Feature",
  "properties": {
    "addr:full":"6400 Wayzata Blvd Golden Valley MN 55426",
    "addr:housenumber":"6400",
    "addr:postcode":"55426",
    "addr:street":"Wayzata Blvd",
    "iso:country":"US",
    "sg:address":"6400 Wayzata Blvd",
    "sg:city":"Golden Valley",
    "sg:classifiers":[
        {
            "category":"Restaurant",
            "type":"Food & Drink"
        }
    ],
    "sg:phone":"+1 763 595 8771",
    "sg:postcode":"55426",
    "sg:province":"MN",
    "sg:website":"http://www.jjsclubhousemn.com",
    "wof:name":"JJ's Club House",
    "wof:placetype":"venue"
},
  "geometry": {"coordinates":[-93.36199499999999,44.971987],"type":"Point"}
}