{
  "type": "Feature",
  "properties": {
    "addr:full":"400 Cedar Ave S Minneapolis MN 55454",
    "addr:housenumber":"400",
    "addr:postcode":"55454",
    "addr:street":"Cedar Ave S",
    "iso:country":"US",
    "sg:address":"400 Cedar Ave S",
    "sg:city":"Minneapolis",
    "sg:classifiers":[
        {
            "category":"Arts & Performance",
            "subcategory":"Music",
            "type":"Entertainment"
        }
    ],
    "sg:phone":"+1 612 332 2903",
    "sg:postcode":"55454",
    "sg:province":"MN",
    "sg:tags":[
        "venue"
    ],
    "sg:website":"www.400bar.com",
    "wof:name":"400 Bar",
    "wof:placetype":"venue"
},
  "geometry": {"coordinates":[-93.247255,44.970226],"type":"Point"}
}