{
  "type": "Feature",
  "properties": {
    "iso:country":"US",
    "sg:address":"3821 Zenith Ave N",
    "sg:city":"Minneapolis",
    "sg:classifiers":[
        {
            "category":"Organizations",
            "subcategory":"Religious Organization",
            "type":"Services"
        }
    ],
    "sg:phone":"+1 763 535 7211",
    "sg:postcode":"55422",
    "sg:province":"MN",
    "wof:name":"Power Source Ministries",
    "wof:placetype":"venue"
},
  "geometry": {"coordinates":[-93.321197,45.02554],"type":"Point"}
}