{
  "type": "Feature",
  "properties": {
    "addr:full":"1318 Wilderness Curve Saint Paul MN 55123",
    "addr:housenumber":"1318",
    "addr:postcode":"55123",
    "addr:street":"Wilderness Curve",
    "iso:country":"US",
    "sg:address":"1318 Wilderness Curve",
    "sg:city":"Saint Paul",
    "sg:classifiers":[
        {
            "category":"Wholesale",
            "subcategory":"Non-durable Goods",
            "type":"Manufacturing & Wholesale Goods"
        }
    ],
    "sg:phone":"+1 651 330 6244",
    "sg:postcode":"55123",
    "sg:province":"MN",
    "wof:name":"Lakeside Specialties",
    "wof:placetype":"venue"
},
  "geometry": {"coordinates":[-93.157687,44.794377],"type":"Point"}
}