{
  "type": "Feature",
  "properties": {
    "addr:full":"93 E 24th St Minneapolis MN 55404",
    "addr:housenumber":"93",
    "addr:postcode":"55404",
    "addr:street":"E 24Th St",
    "iso:country":"US",
    "sg:address":"93 E 24th St",
    "sg:city":"Minneapolis",
    "sg:classifiers":[
        {
            "category":"Autos & Motor Vehicles",
            "subcategory":"Fuel & Gas Station",
            "type":"Retail Goods"
        }
    ],
    "sg:phone":"+1 651 917 9362",
    "sg:postcode":"55404",
    "sg:province":"MN",
    "sg:tags":[
        "station",
        "gasoline"
    ],
    "wof:name":"H I J A Z",
    "wof:placetype":"venue"
},
  "geometry": {"coordinates":[-93.277418,44.959127],"type":"Point"}
}