{
  "type": "Feature",
  "properties": {
    "addr:full":"3433 E 25th St Minneapolis MN 55406",
    "addr:housenumber":"3433",
    "addr:postcode":"55406",
    "addr:street":"E 25Th St",
    "iso:country":"US",
    "sg:address":"3433 E 25th St",
    "sg:city":"Minneapolis",
    "sg:classifiers":[
        {
            "category":"Wholesale",
            "subcategory":"Electrical",
            "type":"Manufacturing & Wholesale Goods"
        }
    ],
    "sg:phone":"+1 612 721 6555",
    "sg:postcode":"55406",
    "sg:province":"MN",
    "sg:tags":[
        "electronic"
    ],
    "wof:name":"Cds/ Nedco",
    "wof:placetype":"venue"
},
  "geometry": {"coordinates":[-93.22125800000001,44.957307],"type":"Point"}
}