{
  "type": "Feature",
  "properties": {
    "addr:full":"1011 Meadowlands Dr Saint Paul MN 55127",
    "addr:housenumber":"1011",
    "addr:postcode":"55127",
    "addr:street":"Meadowlands Dr",
    "iso:country":"US",
    "sg:address":"1011 Meadowlands Dr",
    "sg:city":"Saint Paul",
    "sg:classifiers":[
        {
            "category":"Restaurant",
            "type":"Food & Drink"
        }
    ],
    "sg:phone":"+1 612 426 2440",
    "sg:postcode":"55127",
    "sg:province":"MN",
    "sg:tags":[
        "eating"
    ],
    "wof:name":"Nesting Grounds Coffee Hse",
    "wof:placetype":"venue"
},
  "geometry": {"coordinates":[-93.060937,45.080331],"type":"Point"}
}