{
  "type": "Feature",
  "properties": {
    "addr:full":"1705 SE Broadway Ave Albert Lea MN 56007",
    "addr:housenumber":"1705",
    "addr:postcode":"56007",
    "addr:street":"Se Broadway Ave",
    "iso:country":"US",
    "sg:address":"1705 SE Broadway Ave",
    "sg:city":"Albert Lea",
    "sg:classifiers":[
        {
            "category":"Health Services",
            "subcategory":"Health Practitioner",
            "type":"Services"
        }
    ],
    "sg:phone":"+1 507 377 5900",
    "sg:postcode":"56007",
    "sg:province":"MN",
    "sg:tags":[
        "therapist",
        "physical"
    ],
    "sg:website":"www.almedcenter.org",
    "wof:name":"Healthreach",
    "wof:placetype":"venue"
},
  "geometry": {"coordinates":[-93.358501,43.630862],"type":"Point"}
}