{
  "type": "Feature",
  "properties": {
    "addr:full":"1587 Evergreen Dr Cloquet MN 55720",
    "addr:housenumber":"1587",
    "addr:postcode":"55720",
    "addr:street":"Evergreen Dr",
    "iso:country":"US",
    "sg:address":"1587 Evergreen Dr",
    "sg:city":"Cloquet",
    "sg:classifiers":[
        {
            "category":"Wholesale",
            "subcategory":"Hardware",
            "type":"Manufacturing & Wholesale Goods"
        }
    ],
    "sg:phone":"+1 218 879 4792",
    "sg:postcode":"55720",
    "sg:province":"MN",
    "sg:tags":[
        "purifying",
        "cleaning",
        "air"
    ],
    "wof:name":"Ecoquest",
    "wof:placetype":"venue"
},
  "geometry": {"coordinates":[-92.45638700000001,46.673492],"type":"Point"}
}