{
  "type": "Feature",
  "properties": {
    "addr:full":"206 Main St W Eagle Bend MN 56446",
    "addr:housenumber":"206",
    "addr:postcode":"56446",
    "addr:street":"Main St W Eagle Bend",
    "iso:country":"US",
    "sg:address":"206 Main St W",
    "sg:city":"Eagle Bend",
    "sg:classifiers":[
        {
            "category":"Professional",
            "subcategory":"Accounting & Tax Preparation",
            "type":"Services"
        }
    ],
    "sg:phone":"+1 218 738 1040",
    "sg:postcode":"56446",
    "sg:province":"MN",
    "sg:tags":[
        "accountant"
    ],
    "wof:name":"Tom Murch CPA",
    "wof:placetype":"venue"
},
  "geometry": {"coordinates":[-95.039793,46.164754],"type":"Point"}
}