{
  "type": "Feature",
  "properties": {
    "addr:full":"105 Carmel Ave W Saint Paul MN 55118",
    "addr:housenumber":"105",
    "addr:postcode":"55118",
    "addr:street":"Carmel Ave W",
    "iso:country":"US",
    "sg:address":"105 Carmel Ave W",
    "sg:city":"Saint Paul",
    "sg:classifiers":[
        {
            "category":"Retail",
            "subcategory":"Photofinishing",
            "type":"Services"
        }
    ],
    "sg:phone":"+1 651 457 3313",
    "sg:postcode":"55118",
    "sg:province":"MN",
    "sg:tags":[
        "laboratory"
    ],
    "wof:name":"Photo Retouching/Restoration",
    "wof:placetype":"venue"
},
  "geometry": {"coordinates":[-93.090383,44.899917],"type":"Point"}
}