{
  "type": "Feature",
  "properties": {
    "iso:country":"US",
    "sg:address":"4707 Hazeltine Ln",
    "sg:city":"Saint Paul",
    "sg:classifiers":[
        {
            "category":"Building & Trades",
            "subcategory":"Construction",
            "type":"Services"
        }
    ],
    "sg:phone":"+1 651 686 5639",
    "sg:postcode":"55123",
    "sg:province":"MN",
    "sg:tags":[
        "concrete",
        "contractor"
    ],
    "wof:name":"Black Star Seal Coating",
    "wof:placetype":"venue"
},
  "geometry": {"coordinates":[-93.16475,44.785357],"type":"Point"}
}