{
  "type": "Feature",
  "properties": {
    "iso:country":"US",
    "sg:address":"4510 W 77th St",
    "sg:city":"Minneapolis",
    "sg:classifiers":[
        {
            "category":"Professional",
            "subcategory":"Business Services",
            "type":"Services"
        }
    ],
    "sg:phone":"+1 952 893 9020",
    "sg:postcode":"55435",
    "sg:province":"MN",
    "sg:tags":[
        "interior",
        "design",
        "architecture"
    ],
    "wof:name":"B D H & Young Space Design",
    "wof:placetype":"venue"
},
  "geometry": {"coordinates":[-93.34041499999999,44.863272],"type":"Point"}
}