{
  "type": "Feature",
  "properties": {
    "iso:country":"US",
    "sg:address":"101 Lakeside Dr",
    "sg:city":"Stillwater",
    "sg:classifiers":[
        {
            "category":"Autos & Motor Vehicles",
            "subcategory":"Recreational Vehicle Sales",
            "type":"Retail Goods"
        }
    ],
    "sg:phone":"+1 651 430 3227",
    "sg:postcode":"55082",
    "sg:province":"MN",
    "wof:name":"R V Specialties & Repair",
    "wof:placetype":"venue"
},
  "geometry": {"coordinates":[-92.80604599999999,45.07371],"type":"Point"}
}