{
  "type": "Feature",
  "properties": {
    "iso:country":"US",
    "sg:address":"20843 State Hwy 6",
    "sg:city":"Deerwood",
    "sg:classifiers":[
        {
            "category":"Freight",
            "type":"Transportation"
        }
    ],
    "sg:phone":"+1 218 534 3743",
    "sg:postcode":"56444",
    "sg:province":"MN",
    "sg:tags":[
        "commercial",
        "storage"
    ],
    "wof:name":"Bear's Den Storage",
    "wof:placetype":"venue"
},
  "geometry": {"coordinates":[-93.887169,46.467764],"type":"Point"}
}