{
  "type": "Feature",
  "properties": {
    "addr:full":"435 3rd St SW Plainview MN 55964",
    "addr:housenumber":"435",
    "addr:postcode":"55964",
    "addr:street":"3Rd St Sw",
    "iso:country":"US",
    "sg:address":"435 3rd St SW",
    "sg:city":"Plainview",
    "sg:classifiers":[
        {
            "category":"Freight",
            "type":"Transportation"
        }
    ],
    "sg:phone":"+1 507 534 3206",
    "sg:postcode":"55964",
    "sg:province":"MN",
    "sg:tags":[
        "operator",
        "local",
        "trucking"
    ],
    "wof:name":"Haley Transportation",
    "wof:placetype":"venue"
},
  "geometry": {"coordinates":[-92.169196,44.160121],"type":"Point"}
}