{
  "type": "Feature",
  "properties": {
    "addr:full":"1436 Dixon Dr Saint Paul Park MN 55071",
    "addr:housenumber":"1436",
    "addr:postcode":"55071",
    "addr:street":"Dixon Dr",
    "iso:country":"US",
    "sg:address":"1436 Dixon Dr",
    "sg:city":"Saint Paul Park",
    "sg:classifiers":[
        {
            "category":"Personal",
            "type":"Services"
        }
    ],
    "sg:phone":"+1 651 459 1145",
    "sg:postcode":"55071",
    "sg:province":"MN",
    "wof:name":"Take Off Pounds Sensibly Tops",
    "wof:placetype":"venue"
},
  "geometry": {"coordinates":[-92.97763,44.832203],"type":"Point"}
}