{
  "type": "Feature",
  "properties": {
    "addr:full":"7001 78th Ave N Ste 500 Minneapolis MN 55445",
    "addr:housenumber":"7001",
    "addr:postcode":"55445",
    "addr:street":"78Th Ave N Ste 500",
    "iso:country":"US",
    "sg:address":"7001 78th Ave N Ste 500",
    "sg:city":"Minneapolis",
    "sg:classifiers":[
        {
            "category":"Community Center",
            "type":"Public Place"
        }
    ],
    "sg:phone":"+1 763 566 4535",
    "sg:postcode":"55445",
    "sg:province":"MN",
    "sg:tags":[
        "medical"
    ],
    "wof:name":"Crown Medical Center",
    "wof:placetype":"venue"
},
  "geometry": {"coordinates":[-93.369958,45.095244],"type":"Point"}
}