{
  "type": "Feature",
  "properties": {
    "iso:country":"US",
    "sg:address":"12133 Martin St NW",
    "sg:city":"Minneapolis",
    "sg:classifiers":[
        {
            "category":"Professional",
            "subcategory":"Employment Agencies",
            "type":"Services"
        }
    ],
    "sg:phone":"+1 763 755 1603",
    "sg:postcode":"55448",
    "sg:province":"MN",
    "sg:tags":[
        "help",
        "supply"
    ],
    "wof:name":"Applied Staffing Inc",
    "wof:placetype":"venue"
},
  "geometry": {"coordinates":[-93.31592999999999,45.191282],"type":"Point"}
}