{
  "type": "Feature",
  "properties": {
    "addr:full":"255 Mill St Excelsior MN 55331",
    "addr:housenumber":"255",
    "addr:postcode":"55331",
    "addr:street":"Mill St",
    "iso:country":"US",
    "sg:address":"255 Mill St",
    "sg:city":"Excelsior",
    "sg:classifiers":[
        {
            "category":"Real Estate",
            "subcategory":"Real Estate Operator",
            "type":"Services"
        }
    ],
    "sg:phone":"+1 952 474 9036",
    "sg:postcode":"55331",
    "sg:province":"MN",
    "sg:tags":[
        "apartment"
    ],
    "wof:name":"South Shore Apartments",
    "wof:placetype":"venue"
},
  "geometry": {"coordinates":[-93.5625,44.900902],"type":"Point"}
}