{
  "type": "Feature",
  "properties": {
    "addr:full":"525 E 7th St Morris MN 56267",
    "addr:housenumber":"525",
    "addr:postcode":"56267",
    "addr:street":"E 7Th St",
    "iso:country":"US",
    "sg:address":"525 E 7th St",
    "sg:city":"Morris",
    "sg:classifiers":[
        {
            "category":"Home & Garden",
            "subcategory":"Building Materials",
            "type":"Retail Goods"
        }
    ],
    "sg:phone":"+1 320 589 2777",
    "sg:postcode":"56267",
    "sg:province":"MN",
    "sg:tags":[
        "interior",
        "designer",
        "decorator",
        "hanging"
    ],
    "wof:name":"Wilcox Decorating",
    "wof:placetype":"venue"
},
  "geometry": {"coordinates":[-95.908787,45.591048],"type":"Point"}
}