{
  "type": "Feature",
  "properties": {
    "iso:country":"US",
    "sg:address":"4019 W Old Shakopee Rd",
    "sg:city":"Bloomington",
    "sg:classifiers":[
        {
            "category":"Shopping",
            "subcategory":"Clothing, Apparel, & Fashions",
            "type":"Retail Goods"
        }
    ],
    "sg:phone":"+1 952 881 3813",
    "sg:postcode":"55437",
    "sg:province":"MN",
    "sg:tags":[
        "alteration"
    ],
    "wof:name":"Sew What",
    "wof:placetype":"venue"
},
  "geometry": {"coordinates":[-93.333277,44.809578],"type":"Point"}
}