{
  "type": "Feature",
  "properties": {
    "addr:full":"3909 Silver Lake Rd NE Minneapolis MN 55421",
    "addr:housenumber":"3909",
    "addr:postcode":"55421",
    "addr:street":"Silver Lake Rd Ne",
    "iso:country":"US",
    "sg:address":"3909 Silver Lake Rd NE",
    "sg:city":"Minneapolis",
    "sg:classifiers":[
        {
            "category":"Health Services",
            "subcategory":"Doctor",
            "type":"Services"
        }
    ],
    "sg:phone":"+1 612 781 7234",
    "sg:postcode":"55421",
    "sg:province":"MN",
    "sg:tags":[
        "dentist"
    ],
    "wof:name":"J David Steen DDS",
    "wof:placetype":"venue"
},
  "geometry": {"coordinates":[-93.218211,45.040566],"type":"Point"}
}