{
  "type": "Feature",
  "properties": {
    "addr:full":"1808 Plymouth Rd Hopkins MN 55305",
    "addr:housenumber":"1808",
    "addr:postcode":"55305",
    "addr:street":"Plymouth Rd",
    "iso:country":"US",
    "sg:address":"1808 Plymouth Rd",
    "sg:city":"Hopkins",
    "sg:classifiers":[
        {
            "category":"Food & Beverages",
            "subcategory":"Specialty",
            "type":"Retail Goods"
        },
        {
            "category":"Coffee & Tea",
            "type":"Food & Drink"
        }
    ],
    "sg:menulink":"http://www.allmenus.com/mn/minnetonka/58625-caribou-coffee/menu/",
    "sg:phone":"+1 952 797 0677",
    "sg:postcode":"55305",
    "sg:province":"MN",
    "sg:tags":[
        "tea",
        "coffee",
        "american"
    ],
    "wof:name":"Caribou Coffee",
    "wof:placetype":"venue"
},
  "geometry": {"coordinates":[-93.442601,44.966245],"type":"Point"}
}