{
  "type": "Feature",
  "properties": {
    "addr:full":"688 E 6th St St Paul MN 55106",
    "addr:housenumber":"688",
    "addr:postcode":"55106",
    "addr:street":"E 6Th St",
    "iso:country":"US",
    "sg:address":"688 E 6th St",
    "sg:city":"St Paul",
    "sg:classifiers":[
        {
            "category":"Personal",
            "subcategory":"Adult",
            "type":"Services"
        }
    ],
    "sg:phone":"+1 952 854 4226",
    "sg:postcode":"55106",
    "sg:province":"MN",
    "sg:tags":[
        "escort"
    ],
    "wof:name":"Escorts Express",
    "wof:placetype":"venue"
},
  "geometry": {"coordinates":[-93.071235,44.957457],"type":"Point"}
}