{
  "type": "Feature",
  "properties": {
    "iso:country":"US",
    "sg:address":"409 Marquette Ave",
    "sg:city":"Minneapolis",
    "sg:classifiers":[
        {
            "category":"Parking",
            "type":"Transportation"
        }
    ],
    "sg:phone":"+1 612 330 0420",
    "sg:postcode":"55401",
    "sg:province":"MN",
    "sg:website":"www.downtownautopark.com",
    "wof:name":"Downtown Auto Park",
    "wof:placetype":"venue"
},
  "geometry": {"coordinates":[-93.268501,44.979099],"type":"Point"}
}