{
  "type": "Feature",
  "properties": {
    "addr:full":"3405 Annapolis Ln N Minneapolis MN 55447",
    "addr:housenumber":"3405",
    "addr:postcode":"55447",
    "addr:street":"Annapolis Ln N",
    "iso:country":"US",
    "sg:address":"3405 Annapolis Ln N",
    "sg:city":"Minneapolis",
    "sg:classifiers":[
        {
            "category":"Banks & Credit Unions",
            "subcategory":"Bank",
            "type":"Services"
        }
    ],
    "sg:phone":"+1 763 278 4900",
    "sg:postcode":"55447",
    "sg:province":"MN",
    "sg:tags":[
        "consumer",
        "finance"
    ],
    "wof:name":"Marquette Consumer Finance LLC",
    "wof:placetype":"venue"
},
  "geometry": {"coordinates":[-93.458859,45.019647],"type":"Point"}
}