{
  "type": "Feature",
  "properties": {
    "addr:full":"641 Riverside Ave Owatonna MN 55060",
    "addr:housenumber":"641",
    "addr:postcode":"55060",
    "addr:street":"Riverside Ave",
    "iso:country":"US",
    "sg:address":"641 Riverside Ave",
    "sg:city":"Owatonna",
    "sg:classifiers":[
        {
            "category":"Freight",
            "type":"Transportation"
        }
    ],
    "sg:phone":"+1 507 451 2865",
    "sg:postcode":"55060",
    "sg:province":"MN",
    "sg:tags":[
        "trucking"
    ],
    "wof:name":"Con-Way Central Express",
    "wof:placetype":"venue"
},
  "geometry": {"coordinates":[-93.23205299999999,44.092604],"type":"Point"}
}