{
  "type": "Feature",
  "properties": {
    "iso:country":"US",
    "sg:address":"15500 Wayzata Blvd",
    "sg:city":"Wayzata",
    "sg:classifiers":[
        {
            "category":"Personal",
            "type":"Services"
        }
    ],
    "sg:phone":"+1 952 476 9565",
    "sg:postcode":"55391",
    "sg:province":"MN",
    "sg:tags":[
        "consultant",
        "program",
        "health",
        "fitness"
    ],
    "wof:name":"Breakaway Technology",
    "wof:placetype":"venue"
},
  "geometry": {"coordinates":[-93.47614799999999,44.971471],"type":"Point"}
}