{
  "type": "Feature",
  "properties": {
    "addr:full":"14111 Aldrich Ave S Burnsville MN 55337",
    "addr:housenumber":"14111",
    "addr:postcode":"55337",
    "addr:street":"Aldrich Ave S",
    "iso:country":"US",
    "sg:address":"14111 Aldrich Ave S",
    "sg:city":"Burnsville",
    "sg:classifiers":[
        {
            "category":"Home & Garden",
            "subcategory":"Furniture",
            "type":"Retail Goods"
        }
    ],
    "sg:phone":"+1 952 898 5525",
    "sg:postcode":"55337",
    "sg:province":"MN",
    "sg:tags":[
        "store"
    ],
    "sg:website":"www.bassettfurniture.com",
    "wof:name":"Bassett Furniture Direct",
    "wof:placetype":"venue"
},
  "geometry": {"coordinates":[-93.287648,44.747798],"type":"Point"}
}