{
  "type": "Feature",
  "properties": {
    "iso:country":"US",
    "sg:address":"13490 Georgia Ct",
    "sg:city":"Saint Paul",
    "sg:classifiers":[
        {
            "category":"Health Services",
            "subcategory":"Clinic",
            "type":"Services"
        }
    ],
    "sg:phone":"+1 952 432 8533",
    "sg:postcode":"55124",
    "sg:province":"MN",
    "sg:tags":[
        "home",
        "care"
    ],
    "wof:name":"Helpful Home Care",
    "wof:placetype":"venue"
},
  "geometry": {"coordinates":[-93.21364,44.754285],"type":"Point"}
}