{
  "type": "Feature",
  "properties": {
    "iso:country":"US",
    "sg:address":"2 3rd Ave SE",
    "sg:city":"Remer",
    "sg:classifiers":[
        {
            "category":"Organizations",
            "subcategory":"Religious Organization",
            "type":"Services"
        }
    ],
    "sg:phone":"+1 218 566 2695",
    "sg:postcode":"56672",
    "sg:province":"MN",
    "sg:tags":[
        "church"
    ],
    "wof:name":"Northland Alliance Church",
    "wof:placetype":"venue"
},
  "geometry": {"coordinates":[-93.91327099999999,47.055243],"type":"Point"}
}