{
  "type": "Feature",
  "properties": {
    "iso:country":"US",
    "sg:address":"524 Apollo Dr",
    "sg:city":"Circle Pines",
    "sg:classifiers":[
        {
            "category":"Professional",
            "type":"Services"
        }
    ],
    "sg:phone":"+1 651 784 6400",
    "sg:postcode":"55014",
    "sg:province":"MN",
    "sg:tags":[
        "establishment"
    ],
    "wof:name":"American Compressor",
    "wof:placetype":"venue"
},
  "geometry": {"coordinates":[-93.118363,45.1798],"type":"Point"}
}