{
  "type": "Feature",
  "properties": {
    "iso:country":"US",
    "sg:address":"13690 302nd Ave NW",
    "sg:city":"Princeton",
    "sg:classifiers":[
        {
            "category":"Building & Trades",
            "subcategory":"Construction",
            "type":"Services"
        }
    ],
    "sg:phone":"+1 763 389 7910",
    "sg:postcode":"55371",
    "sg:province":"MN",
    "sg:tags":[
        "contractor"
    ],
    "wof:name":"Stafki General Contractors",
    "wof:placetype":"venue"
},
  "geometry": {"coordinates":[-93.61667300000001,45.518107],"type":"Point"}
}