{
  "type": "Feature",
  "properties": {
    "iso:country":"US",
    "sg:address":"12377 Drake St NW",
    "sg:city":"Minneapolis",
    "sg:classifiers":[
        {
            "category":"Building & Trades",
            "subcategory":"Construction",
            "type":"Services"
        }
    ],
    "sg:phone":"+1 612 839 0251",
    "sg:postcode":"55448",
    "sg:province":"MN",
    "sg:tags":[
        "contractor"
    ],
    "wof:name":"Bob Stenman Drywall",
    "wof:placetype":"venue"
},
  "geometry": {"coordinates":[-93.303624,45.193612],"type":"Point"}
}