{
  "type": "Feature",
  "properties": {
    "iso:country":"US",
    "sg:address":"140 Buchanan St N",
    "sg:city":"Cambridge",
    "sg:classifiers":[
        {
            "category":"Organizations",
            "subcategory":"Professional Association",
            "type":"Services"
        }
    ],
    "sg:phone":"+1 763 689 2505",
    "sg:postcode":"55008",
    "sg:province":"MN",
    "sg:tags":[
        "chambers",
        "commerce"
    ],
    "wof:name":"Cambridge Chamber Of Commerce",
    "wof:placetype":"venue"
},
  "geometry": {"coordinates":[-93.22147,45.573102],"type":"Point"}
}