{
  "type": "Feature",
  "properties": {
    "addr:full":"12 S 6th St Ste 924 Minneapolis MN 55402",
    "addr:housenumber":"12",
    "addr:postcode":"55402",
    "addr:street":"S 6Th St Ste 924",
    "iso:country":"US",
    "sg:address":"12 S 6th St Ste 924",
    "sg:city":"Minneapolis",
    "sg:classifiers":[
        {
            "category":"Professional",
            "type":"Services"
        },
        {
            "category":"Professional",
            "subcategory":"Advertising",
            "type":"Services"
        }
    ],
    "sg:phone":"+1 612 342 0106",
    "sg:postcode":"55402",
    "sg:province":"MN",
    "sg:tags":[
        "sample",
        "product",
        "service-circular",
        "fair",
        "specialty",
        "trade",
        "distributing",
        "exposition",
        "advertising-promotional",
        "shows"
    ],
    "sg:website":"http://www.wefetch.com",
    "wof:name":"Matrix Resourcing Corporation",
    "wof:placetype":"venue"
},
  "geometry": {"coordinates":[-93.27338899999999,44.978655],"type":"Point"}
}