{
  "type": "Feature",
  "properties": {
    "addr:full":"703 14 St NW Bemidji MN 56601",
    "addr:housenumber":"14",
    "addr:postcode":"56601",
    "addr:street":"703;St Nw",
    "iso:country":"US",
    "sg:address":"703 14 St NW",
    "sg:city":"Bemidji",
    "sg:classifiers":[
        {
            "category":"Retail",
            "subcategory":"Portrait Studio",
            "type":"Services"
        }
    ],
    "sg:phone":"+1 218 751 4036",
    "sg:postcode":"56601",
    "sg:province":"MN",
    "sg:tags":[
        "photo",
        "photography",
        "commercial"
    ],
    "wof:name":"Nature Trail Photography",
    "wof:placetype":"venue"
},
  "geometry": {"coordinates":[-94.83642999999999,48.741513],"type":"Point"}
}