{
  "type": "Feature",
  "properties": {
    "iso:country":"US",
    "sg:address":"2853 44th Ave S",
    "sg:city":"Minneapolis",
    "sg:classifiers":[
        {
            "category":"Professional",
            "type":"Services"
        }
    ],
    "sg:phone":"+1 612 729 9277",
    "sg:postcode":"55406",
    "sg:province":"MN",
    "wof:name":"Sue Roberts Homeopath Llc",
    "wof:placetype":"venue"
},
  "geometry": {"coordinates":[-93.210116,44.950591],"type":"Point"}
}