{
  "type": "Feature",
  "properties": {
    "addr:full":"18 Ottawa Ave N Golden Valley MN 55422",
    "addr:housenumber":"18",
    "addr:postcode":"55422",
    "addr:street":"Ottawa Ave N",
    "iso:country":"US",
    "sg:address":"18 Ottawa Ave N",
    "sg:city":"Golden Valley",
    "sg:classifiers":[
        {
            "category":"Building & Trades",
            "subcategory":"Construction",
            "type":"Services"
        }
    ],
    "sg:phone":"+1 612 377 3631",
    "sg:postcode":"55422",
    "sg:province":"MN",
    "sg:tags":[
        "plastering",
        "contractor"
    ],
    "wof:name":"W E Nelson Stucco Co",
    "wof:placetype":"venue"
},
  "geometry": {"coordinates":[-93.340234,44.978746],"type":"Point"}
}