{
  "type": "Feature",
  "properties": {
    "iso:country":"US",
    "sg:address":"924 N Main St",
    "sg:city":"Stewartville",
    "sg:classifiers":[
        {
            "category":"Autos & Motor Vehicles",
            "subcategory":"Automobile Sales",
            "type":"Retail Goods"
        }
    ],
    "sg:phone":"+1 507 533 6504",
    "sg:postcode":"55976",
    "sg:province":"MN",
    "sg:tags":[
        "car",
        "dealer"
    ],
    "wof:name":"Stewartville Auto Sales",
    "wof:placetype":"venue"
},
  "geometry": {"coordinates":[-92.488505,43.862545],"type":"Point"}
}