{
  "type": "Feature",
  "properties": {
    "addr:full":"16535 Beaver Ridge Dr Caledonia MN 55921",
    "addr:housenumber":"16535",
    "addr:postcode":"55921",
    "addr:street":"Beaver Ridge Dr",
    "iso:country":"US",
    "sg:address":"16535 Beaver Ridge Dr",
    "sg:city":"Caledonia",
    "sg:classifiers":[
        {
            "category":"Professional",
            "type":"Services"
        }
    ],
    "sg:phone":"+1 507 724 2974",
    "sg:postcode":"55921",
    "sg:province":"MN",
    "wof:name":"Gary Massman",
    "wof:placetype":"venue"
},
  "geometry": {"coordinates":[-91.575565,43.630466],"type":"Point"}
}