{
  "type": "Feature",
  "properties": {
    "addr:full":"1374 110th Ave Welcome MN 56181",
    "addr:housenumber":"1374",
    "addr:postcode":"56181",
    "addr:street":"110Th Ave",
    "iso:country":"US",
    "sg:address":"1374 110th Ave",
    "sg:city":"Welcome",
    "sg:phone":"+1 507 728 8895",
    "sg:postcode":"56181",
    "sg:province":"MN",
    "sg:tags":[
        "farm",
        "corn",
        "grain",
        "cash",
        "soybean"
    ],
    "wof:name":"Robert Moffit",
    "wof:placetype":"venue"
},
  "geometry": {"coordinates":[-94.65467599999999,43.686348],"type":"Point"}
}