{
  "type": "Feature",
  "properties": {
    "addr:full":"22340 Bracketts Rd Excelsior MN 55331",
    "addr:postcode":"22340;55331",
    "addr:street":"Bracketts Rd",
    "iso:country":"US",
    "sg:address":"22340 Bracketts Rd",
    "sg:city":"Excelsior",
    "sg:classifiers":[
        {
            "category":"Manufacturing",
            "subcategory":"Tools & Machinery",
            "type":"Manufacturing & Wholesale Goods"
        }
    ],
    "sg:phone":"+1 952 401 0862",
    "sg:postcode":"55331",
    "sg:province":"MN",
    "sg:tags":[
        "industry",
        "mfg"
    ],
    "wof:name":"Rockmore Sales Corporation",
    "wof:placetype":"venue"
},
  "geometry": {"coordinates":[-93.561926,44.894891],"type":"Point"}
}