{
  "type": "Feature",
  "properties": {
    "addr:full":"471 E Roselawn Ave Saint Paul MN 55117",
    "addr:housenumber":"471",
    "addr:postcode":"55117",
    "addr:street":"E Roselawn Ave",
    "iso:country":"US",
    "sg:address":"471 E Roselawn Ave",
    "sg:city":"Saint Paul",
    "sg:classifiers":[
        {
            "category":"Professional",
            "subcategory":"Management & Consulting",
            "type":"Services"
        }
    ],
    "sg:phone":"+1 651 774 6496",
    "sg:postcode":"55117",
    "sg:province":"MN",
    "sg:tags":[
        "business"
    ],
    "wof:name":"Educe Consulting Inc",
    "wof:placetype":"venue"
},
  "geometry": {"coordinates":[-93.076334,44.99919],"type":"Point"}
}