{
  "type": "Feature",
  "properties": {
    "addr:full":"1200 5th St S Sauk Rapids MN 56379",
    "addr:housenumber":"1200",
    "addr:postcode":"56379",
    "addr:street":"5Th St S Sauk",
    "iso:country":"US",
    "sg:address":"1200 5th St S",
    "sg:city":"Sauk Rapids",
    "sg:classifiers":[
        {
            "category":"Building & Trades",
            "subcategory":"Construction",
            "type":"Services"
        }
    ],
    "sg:phone":"+1 320 258 3900",
    "sg:postcode":"56379",
    "sg:province":"MN",
    "sg:tags":[
        "hanging",
        "painter",
        "contractor"
    ],
    "wof:name":"Masterpiece Painting LLC",
    "wof:placetype":"venue"
},
  "geometry": {"coordinates":[-94.146918,45.582001],"type":"Point"}
}