{
  "type": "Feature",
  "properties": {
    "addr:full":"709 N Kniss Ave Luverne MN 56156",
    "addr:housenumber":"709",
    "addr:postcode":"56156",
    "addr:street":"N Kniss Ave",
    "iso:country":"US",
    "sg:address":"709 N Kniss Ave",
    "sg:city":"Luverne",
    "sg:classifiers":[
        {
            "category":"Education",
            "subcategory":"School",
            "type":"Public Place"
        }
    ],
    "sg:phone":"+1 507 283 4724",
    "sg:postcode":"56156",
    "sg:province":"MN",
    "wof:name":"Community Education",
    "wof:placetype":"venue"
},
  "geometry": {"coordinates":[-96.212727,43.661833],"type":"Point"}
}