{
  "type": "Feature",
  "properties": {
    "addr:full":"1535 W 5th St Winona MN 55987",
    "addr:housenumber":"1535",
    "addr:postcode":"55987",
    "addr:street":"W 5Th St",
    "iso:country":"US",
    "sg:address":"1535 W 5th St",
    "sg:city":"Winona",
    "sg:classifiers":[
        {
            "category":"Real Estate",
            "subcategory":"Real Estate Operator",
            "type":"Services"
        }
    ],
    "sg:phone":"+1 507 457 0890",
    "sg:postcode":"55987",
    "sg:province":"MN",
    "sg:tags":[
        "apartment"
    ],
    "wof:name":"Home Apartment Of Winnona",
    "wof:placetype":"venue"
},
  "geometry": {"coordinates":[-91.678361,44.054061],"type":"Point"}
}