{
  "type": "Feature",
  "properties": {
    "addr:full":"4035 253rd Ave NW Isanti MN 55040",
    "addr:housenumber":"4035",
    "addr:postcode":"55040",
    "addr:street":"253Rd Ave Nw Isanti",
    "iso:country":"US",
    "sg:address":"4035 253rd Ave NW",
    "sg:city":"Isanti",
    "sg:classifiers":[
        {
            "category":"Retail",
            "subcategory":"Veterinary Services",
            "type":"Services"
        }
    ],
    "sg:phone":"+1 763 444 9359",
    "sg:postcode":"55040",
    "sg:province":"MN",
    "sg:tags":[
        "veterinarian"
    ],
    "sg:website":"http://www.sfvetclinic.com",
    "wof:name":"St Francis Veterinary Clinic",
    "wof:placetype":"venue"
},
  "geometry": {"coordinates":[-93.37089899999999,45.428228],"type":"Point"}
}