{
  "type": "Feature",
  "properties": {
    "addr:full":"23190 Meadowview Dr Rogers MN 55374",
    "addr:housenumber":"23190",
    "addr:postcode":"55374",
    "addr:street":"Meadowview Dr",
    "iso:country":"US",
    "sg:address":"23190 Meadowview Dr",
    "sg:city":"Rogers",
    "sg:classifiers":[
        {
            "category":"Social Services",
            "subcategory":"Child Care",
            "type":"Services"
        }
    ],
    "sg:phone":"+1 763 498 0033",
    "sg:postcode":"55374",
    "sg:province":"MN",
    "sg:tags":[
        "daycare",
        "provider"
    ],
    "wof:name":"Patti Jo Mc Clellan",
    "wof:placetype":"venue"
},
  "geometry": {"coordinates":[-93.62452399999999,45.141753],"type":"Point"}
}