{
  "type": "Feature",
  "properties": {
    "iso:country":"US",
    "sg:address":"1127 Cherry St",
    "sg:city":"Owatonna",
    "sg:classifiers":[
        {
            "category":"Personal",
            "subcategory":"Beauty Salon",
            "type":"Services"
        }
    ],
    "sg:phone":"+1 507 451 3440",
    "sg:postcode":"55060",
    "sg:province":"MN",
    "sg:tags":[
        "shop",
        "barber"
    ],
    "wof:name":"Hair Designers",
    "wof:placetype":"venue"
},
  "geometry": {"coordinates":[-93.20371299999999,44.093534],"type":"Point"}
}