{
  "type": "Feature",
  "properties": {
    "iso:country":"US",
    "sg:address":"1285 Pleasant St",
    "sg:city":"Worthington",
    "sg:classifiers":[
        {
            "category":"Social Services",
            "subcategory":"Child Care",
            "type":"Services"
        }
    ],
    "sg:phone":"+1 507 372 2756",
    "sg:postcode":"56187",
    "sg:province":"MN",
    "sg:tags":[
        "daycare",
        "provider"
    ],
    "wof:name":"Barb Boltjes",
    "wof:placetype":"venue"
},
  "geometry": {"coordinates":[-95.616592,43.605918],"type":"Point"}
}