{
  "type": "Feature",
  "properties": {
    "addr:full":"233 2nd St S Stillwater MN 55082",
    "addr:housenumber":"233",
    "addr:postcode":"55082",
    "addr:street":"2Nd St S",
    "iso:country":"US",
    "sg:address":"233 2nd St S",
    "sg:city":"Stillwater",
    "sg:classifiers":[
        {
            "category":"Shopping",
            "subcategory":"Clothing, Apparel, & Fashions",
            "type":"Retail Goods"
        }
    ],
    "sg:phone":"+1 651 439 3308",
    "sg:postcode":"55082",
    "sg:province":"MN",
    "wof:name":"River Rats",
    "wof:placetype":"venue"
},
  "geometry": {"coordinates":[-92.806792,45.054966],"type":"Point"}
}