{
  "type": "Feature",
  "properties": {
    "addr:full":"224 W 3rd St Monticello MN 55362",
    "addr:housenumber":"224",
    "addr:postcode":"55362",
    "addr:street":"W 3Rd St",
    "iso:country":"US",
    "sg:address":"224 W 3rd St",
    "sg:city":"Monticello",
    "sg:classifiers":[
        {
            "category":"Autos & Motor Vehicles",
            "subcategory":"Auto Supplies",
            "type":"Retail Goods"
        }
    ],
    "sg:phone":"+1 763 295 5699",
    "sg:postcode":"55362",
    "sg:province":"MN",
    "sg:tags":[
        "automobile",
        "parts"
    ],
    "wof:name":"NAPA Auto Parts",
    "wof:placetype":"venue"
},
  "geometry": {"coordinates":[-93.797487,45.305449],"type":"Point"}
}