{
  "type": "Feature",
  "properties": {
    "addr:full":"5017 Crofoot Ave NW Buffalo MN 55313",
    "addr:housenumber":"5017",
    "addr:postcode":"55313",
    "addr:street":"Crofoot Ave Nw",
    "iso:country":"US",
    "sg:address":"5017 Crofoot Ave NW",
    "sg:city":"Buffalo",
    "sg:classifiers":[
        {
            "category":"Building & Trades",
            "subcategory":"Landscaping Services",
            "type":"Services"
        }
    ],
    "sg:phone":"+1 320 963 2003",
    "sg:postcode":"55313",
    "sg:province":"MN",
    "sg:tags":[
        "landscape",
        "contractor"
    ],
    "wof:name":"Ryan M Bresnahan Landscpg LLC",
    "wof:placetype":"venue"
},
  "geometry": {"coordinates":[-93.94026700000001,45.224974],"type":"Point"}
}