{
  "type": "Feature",
  "properties": {
    "iso:country":"US",
    "sg:address":"1515 Pinewood Dr",
    "sg:city":"Saint Paul",
    "sg:classifiers":[
        {
            "category":"Retail",
            "subcategory":"Car Wash",
            "type":"Services"
        }
    ],
    "sg:phone":"+1 651 295 8008",
    "sg:postcode":"55126",
    "sg:province":"MN",
    "sg:tags":[
        "carwash"
    ],
    "wof:name":"Excell One Detailing Inc",
    "wof:placetype":"venue"
},
  "geometry": {"coordinates":[-93.164613,45.108784],"type":"Point"}
}