{
  "type": "Feature",
  "properties": {
    "iso:country":"US",
    "sg:address":"18897 240th St NE",
    "sg:city":"Brooks",
    "sg:phone":"+1 218 698 4442",
    "sg:postcode":"56701",
    "sg:province":"MN",
    "sg:tags":[
        "farm",
        "soybean"
    ],
    "wof:name":"Ray Novak",
    "wof:placetype":"venue"
},
  "geometry": {"coordinates":[-96.07622000000001,48.221814],"type":"Point"}
}