{
  "type": "Feature",
  "properties": {
    "addr:full":"801 6th St NW Kasson MN 55944",
    "addr:housenumber":"801",
    "addr:postcode":"55944",
    "addr:street":"6Th St Nw",
    "iso:country":"US",
    "sg:address":"801 6th St NW",
    "sg:city":"Kasson",
    "sg:classifiers":[
        {
            "category":"Organizations",
            "subcategory":"Professional Association",
            "type":"Services"
        }
    ],
    "sg:phone":"+1 507 634 4455",
    "sg:postcode":"55944",
    "sg:province":"MN",
    "wof:name":"Aid Association For Lutherans",
    "wof:placetype":"venue"
},
  "geometry": {"coordinates":[-92.758292,44.034966],"type":"Point"}
}