{
  "type": "Feature",
  "properties": {
    "addr:full":"7527 W 111th St Minneapolis MN 55438",
    "addr:housenumber":"7527",
    "addr:postcode":"55438",
    "addr:street":"W 111Th St",
    "iso:country":"US",
    "sg:address":"7527 W 111th St",
    "sg:city":"Minneapolis",
    "sg:classifiers":[
        {
            "category":"Professional",
            "subcategory":"Management & Consulting",
            "type":"Services"
        }
    ],
    "sg:phone":"+1 952 944 0763",
    "sg:postcode":"55438",
    "sg:province":"MN",
    "sg:tags":[
        "business"
    ],
    "wof:name":"Tower Consultants",
    "wof:placetype":"venue"
},
  "geometry": {"coordinates":[-93.38079500000001,44.803902],"type":"Point"}
}