{
  "type": "Feature",
  "properties": {
    "iso:country":"US",
    "sg:address":"1301 Cannon Ave",
    "sg:city":"Saint Paul",
    "sg:classifiers":[
        {
            "category":"Building & Trades",
            "subcategory":"Construction",
            "type":"Services"
        }
    ],
    "sg:phone":"+1 651 773 1340",
    "sg:postcode":"55112",
    "sg:province":"MN",
    "sg:tags":[
        "house"
    ],
    "wof:name":"Arend Remodeling",
    "wof:placetype":"venue"
},
  "geometry": {"coordinates":[-93.156612,45.043302],"type":"Point"}
}