{
  "type": "Feature",
  "properties": {
    "iso:country":"US",
    "sg:address":"817 Main St NW",
    "sg:city":"Elk River",
    "sg:classifiers":[
        {
            "category":"Shopping",
            "subcategory":"Florist",
            "type":"Retail Goods"
        }
    ],
    "sg:phone":"+1 763 441 6888",
    "sg:postcode":"55330",
    "sg:province":"MN",
    "wof:name":"Natural Expressions Florist",
    "wof:placetype":"venue"
},
  "geometry": {"coordinates":[-93.552516,45.312712],"type":"Point"}
}