{
  "type": "Feature",
  "properties": {
    "iso:country":"US",
    "sg:address":"16 2nd St NW",
    "sg:city":"Aitkin",
    "sg:classifiers":[
        {
            "category":"Shopping",
            "subcategory":"Gifts & Souvenirs",
            "type":"Retail Goods"
        }
    ],
    "sg:phone":"+1 218 927 2253",
    "sg:postcode":"56431",
    "sg:province":"MN",
    "wof:name":"Gumdrop Tree",
    "wof:placetype":"venue"
},
  "geometry": {"coordinates":[-93.70797,46.533439],"type":"Point"}
}