{
  "type": "Feature",
  "properties": {
    "iso:country":"US",
    "sg:address":"818 E Lincoln Ave",
    "sg:city":"Olivia",
    "sg:classifiers":[
        {
            "category":"Social Services",
            "type":"Services"
        }
    ],
    "sg:phone":"+1 320 523 1352",
    "sg:postcode":"56277",
    "sg:province":"MN",
    "wof:name":"Olivia Senior Citizens Inc",
    "wof:placetype":"venue"
},
  "geometry": {"coordinates":[-94.989287,44.776559],"type":"Point"}
}