{
  "type": "Feature",
  "properties": {
    "iso:country":"US",
    "sg:address":"3330 Roosevelt Rd",
    "sg:city":"Saint Cloud",
    "sg:classifiers":[
        {
            "category":"Professional",
            "subcategory":"Business Services",
            "type":"Services"
        }
    ],
    "sg:phone":"+1 320 251 0121",
    "sg:postcode":"56301",
    "sg:province":"MN",
    "wof:name":"Federal Express MN",
    "wof:placetype":"venue"
},
  "geometry": {"coordinates":[-94.159599,45.514969],"type":"Point"}
}