{
  "type": "Feature",
  "properties": {
    "iso:country":"US",
    "sg:address":"2410 1st St N",
    "sg:city":"St Cloud",
    "sg:classifiers":[
        {
            "category":"Education",
            "subcategory":"School",
            "type":"Public Place"
        }
    ],
    "sg:phone":"+1 320 251 6231",
    "sg:postcode":"56303",
    "sg:province":"MN",
    "sg:tags":[
        "elementary"
    ],
    "sg:website":"www.stelizabethannseton.net",
    "wof:name":"St Elizabeth Ann Seton Int Sch",
    "wof:placetype":"venue"
},
  "geometry": {"coordinates":[-94.186808,45.554864],"type":"Point"}
}