{
  "type": "Feature",
  "properties": {
    "addr:full":"413 Nebraska Ave Breckenridge MN 56520",
    "addr:housenumber":"413",
    "addr:postcode":"56520",
    "addr:street":"Nebraska Ave",
    "iso:country":"US",
    "sg:address":"413 Nebraska Ave",
    "sg:city":"Breckenridge",
    "sg:classifiers":[
        {
            "category":"Professional",
            "subcategory":"Lawyer & Legal Services",
            "type":"Services"
        }
    ],
    "sg:phone":"+1 218 643 5519",
    "sg:postcode":"56520",
    "sg:province":"MN",
    "sg:tags":[
        "attorney"
    ],
    "wof:name":"Robertson Law Office",
    "wof:placetype":"venue"
},
  "geometry": {"coordinates":[-96.589253,46.26452],"type":"Point"}
}