{
  "type": "Feature",
  "properties": {
    "addr:full":"3001 White Bear Ave N Saint Paul MN 55109",
    "addr:housenumber":"3001",
    "addr:postcode":"55109",
    "addr:street":"White Bear Ave N",
    "iso:country":"US",
    "sg:address":"3001 White Bear Ave N",
    "sg:city":"Saint Paul",
    "sg:classifiers":[
        {
            "category":"Restaurant",
            "type":"Food & Drink"
        }
    ],
    "sg:menulink":"http://www.allmenus.com/mn/maplewood/240307-panda-express/menu/",
    "sg:phone":"+1 651 777 7639",
    "sg:postcode":"55109",
    "sg:province":"MN",
    "sg:tags":[
        "asian",
        "chinese"
    ],
    "wof:name":"Panda Express",
    "wof:placetype":"venue"
},
  "geometry": {"coordinates":[-93.02193800000001,45.029306],"type":"Point"}
}