{
  "type": "Feature",
  "properties": {
    "addr:full":"1004 1st Pl NW Kasson MN 55944",
    "addr:housenumber":"1004",
    "addr:postcode":"55944",
    "addr:street":"1St Pl Nw",
    "iso:country":"US",
    "sg:address":"1004 1st Pl NW",
    "sg:city":"Kasson",
    "sg:classifiers":[
        {
            "category":"Recreation",
            "type":"Entertainment"
        }
    ],
    "sg:phone":"+1 507 634 6460",
    "sg:postcode":"55944",
    "sg:province":"MN",
    "sg:tags":[
        "skating",
        "rink"
    ],
    "wof:name":"Eminent Skate Mag",
    "wof:placetype":"venue"
},
  "geometry": {"coordinates":[-92.761556,44.030074],"type":"Point"}
}