{
  "type": "Feature",
  "properties": {
    "iso:country":"US",
    "sg:address":"1324 15th Ave SE",
    "sg:city":"Forest Lake",
    "sg:classifiers":[
        {
            "category":"Restaurant",
            "type":"Food & Drink"
        }
    ],
    "sg:phone":"+1 651 982 9415",
    "sg:postcode":"55025",
    "sg:province":"MN",
    "sg:tags":[
        "eating"
    ],
    "wof:name":"Jelly Jar Cafe Inc",
    "wof:placetype":"venue"
},
  "geometry": {"coordinates":[-92.965329,45.263996],"type":"Point"}
}