{
  "type": "Feature",
  "properties": {
    "addr:full":"1300 Vermillion St Hastings MN 55033",
    "addr:housenumber":"1300",
    "addr:postcode":"55033",
    "addr:street":"Vermillion St",
    "iso:country":"US",
    "sg:address":"1300 Vermillion St",
    "sg:city":"Hastings",
    "sg:classifiers":[
        {
            "category":"Insurance",
            "subcategory":"Insurance Agent",
            "type":"Services"
        }
    ],
    "sg:phone":"+1 651 437 1910",
    "sg:postcode":"55033",
    "sg:province":"MN",
    "wof:name":"Modern Woodmen of America",
    "wof:placetype":"venue"
},
  "geometry": {"coordinates":[-92.852673,44.732285],"type":"Point"}
}