{
  "type": "Feature",
  "properties": {
    "iso:country":"US",
    "sg:address":"12342 Pierce St NE",
    "sg:city":"Minneapolis",
    "sg:classifiers":[
        {
            "category":"Social Services",
            "subcategory":"Child Care",
            "type":"Services"
        }
    ],
    "sg:phone":"+1 763 767 9067",
    "sg:postcode":"55434",
    "sg:province":"MN",
    "sg:tags":[
        "daycare",
        "provider"
    ],
    "wof:name":"Nicole Moeller",
    "wof:placetype":"venue"
},
  "geometry": {"coordinates":[-93.24146500000001,45.194381],"type":"Point"}
}