{
  "type": "Feature",
  "properties": {
    "addr:full":"14304 60th St N Stillwater MN 55082",
    "addr:housenumber":"14304",
    "addr:postcode":"55082",
    "addr:street":"60Th St N",
    "iso:country":"US",
    "sg:address":"14304 60th St N",
    "sg:city":"Stillwater",
    "sg:classifiers":[
        {
            "category":"Autos & Motor Vehicles",
            "subcategory":"Auto Supplies",
            "type":"Retail Goods"
        },
        {
            "category":"Retail",
            "subcategory":"Auto Repair",
            "type":"Services"
        }
    ],
    "sg:phone":"+1 651 439 2520",
    "sg:postcode":"55082",
    "sg:province":"MN",
    "sg:tags":[
        "repairing",
        "automobile"
    ],
    "sg:website":"www.tiresplus.com",
    "wof:name":"Team Tires Plus",
    "wof:placetype":"venue"
},
  "geometry": {"coordinates":[-92.815659,45.036286],"type":"Point"}
}