{
  "type": "Feature",
  "properties": {
    "addr:full":"3500 213th St W Farmington MN 55024",
    "addr:housenumber":"3500",
    "addr:postcode":"55024",
    "addr:street":"213Th St W",
    "iso:country":"US",
    "sg:address":"3500 213th St W",
    "sg:city":"Farmington",
    "sg:classifiers":[
        {
            "category":"Health Services",
            "subcategory":"Health Practitioner",
            "type":"Services"
        }
    ],
    "sg:phone":"+1 952 460 7010",
    "sg:postcode":"55024",
    "sg:province":"MN",
    "wof:name":"Gerald Gregersen PHD",
    "wof:placetype":"venue"
},
  "geometry": {"coordinates":[-93.130281,44.641356],"type":"Point"}
}