{
  "type": "Feature",
  "properties": {
    "iso:country":"US",
    "sg:address":"610 Fillmore St",
    "sg:city":"Alexandria",
    "sg:classifiers":[
        {
            "category":"Professional",
            "subcategory":"Management & Consulting",
            "type":"Services"
        }
    ],
    "sg:phone":"+1 320 762 9244",
    "sg:postcode":"56308",
    "sg:province":"MN",
    "sg:tags":[
        "consultant",
        "business"
    ],
    "wof:name":"Community Growth Institute",
    "wof:placetype":"venue"
},
  "geometry": {"coordinates":[-95.37928599999999,45.885835],"type":"Point"}
}