{
  "type": "Feature",
  "properties": {
    "addr:full":"21284 Knauf Ave Reading MN 56165",
    "addr:postcode":"21284;56165",
    "addr:street":"Knauf Ave",
    "iso:country":"US",
    "sg:address":"21284 Knauf Ave",
    "sg:city":"Reading",
    "sg:phone":"+1 507 478 4552",
    "sg:postcode":"56165",
    "sg:province":"MN",
    "sg:tags":[
        "hog",
        "farm",
        "corn",
        "soybean",
        "or",
        "feedlot"
    ],
    "wof:name":"Vanwesten Steffen",
    "wof:placetype":"venue"
},
  "geometry": {"coordinates":[-95.753366,43.684539],"type":"Point"}
}