{
  "type": "Feature",
  "properties": {
    "iso:country":"US",
    "sg:address":"15035 Mystic Lake Dr NW",
    "sg:city":"Prior Lake",
    "sg:classifiers":[
        {
            "category":"Food & Beverages",
            "subcategory":"Groceries & Convenience Stores",
            "type":"Retail Goods"
        }
    ],
    "sg:phone":"+1 952 445 5520",
    "sg:postcode":"55372",
    "sg:province":"MN",
    "sg:tags":[
        "carwash"
    ],
    "wof:name":"Shakopee Dkota Convenience Str",
    "wof:placetype":"venue"
},
  "geometry": {"coordinates":[-93.469577,44.731651],"type":"Point"}
}