{
  "type": "Feature",
  "properties": {
    "iso:country":"US",
    "sg:address":"523 S 7th St",
    "sg:city":"La Crescent",
    "sg:classifiers":[
        {
            "category":"Home & Garden",
            "subcategory":"Garden Supply",
            "type":"Retail Goods"
        }
    ],
    "sg:phone":"+1 507 895 2177",
    "sg:postcode":"55947",
    "sg:province":"MN",
    "sg:tags":[
        "repair",
        "lawn",
        "saw",
        "chain",
        "mower"
    ],
    "wof:name":"Breyers Sales & Service",
    "wof:placetype":"venue"
},
  "geometry": {"coordinates":[-91.310632,43.822135],"type":"Point"}
}