{
  "type": "Feature",
  "properties": {
    "addr:full":"2035 W Main St Wabasso MN 56293",
    "addr:housenumber":"2035",
    "addr:postcode":"56293",
    "addr:street":"W Main St",
    "iso:country":"US",
    "sg:address":"2035 W Main St",
    "sg:city":"Wabasso",
    "sg:classifiers":[
        {
            "category":"Building & Trades",
            "subcategory":"Construction",
            "type":"Services"
        }
    ],
    "sg:phone":"+1 507 342 5417",
    "sg:postcode":"56293",
    "sg:province":"MN",
    "sg:tags":[
        "grading",
        "contractor"
    ],
    "wof:name":"Redwood County Highway Dept",
    "wof:placetype":"venue"
},
  "geometry": {"coordinates":[-95.26237,44.402106],"type":"Point"}
}