{
  "type": "Feature",
  "properties": {
    "iso:country":"US",
    "sg:address":"729 Marshall St NE",
    "sg:city":"Minneapolis",
    "sg:classifiers":[
        {
            "category":"Bars & Pubs",
            "type":"Food & Drink"
        },
        {
            "category":"Restaurant",
            "type":"Food & Drink"
        },
        {
            "category":"Sports & Exercise",
            "subcategory":"Bowling",
            "type":"Entertainment"
        }
    ],
    "sg:phone":"+1 612 789 4714",
    "sg:postcode":"55413",
    "sg:province":"MN",
    "sg:tags":[
        "traditional",
        "american"
    ],
    "sg:website":"www.elsies.com",
    "wof:name":"Elsie's Restaurant Bar & Bowling Center",
    "wof:placetype":"venue"
},
  "geometry": {"coordinates":[-93.266502,44.994801],"type":"Point"}
}