{
  "type": "Feature",
  "properties": {
    "addr:full":"34541 491st Ave Lafayette MN 56054",
    "addr:housenumber":"34541",
    "addr:postcode":"56054",
    "addr:street":"491St Ave",
    "iso:country":"US",
    "sg:address":"34541 491st Ave",
    "sg:city":"Lafayette",
    "sg:classifiers":[
        {
            "category":"Farming",
            "subcategory":"Farm",
            "type":"Manufacturing & Wholesale Goods"
        }
    ],
    "sg:phone":"+1 507 228 8685",
    "sg:postcode":"56054",
    "sg:province":"MN",
    "sg:tags":[
        "crop",
        "general"
    ],
    "wof:name":"R Bruss",
    "wof:placetype":"venue"
},
  "geometry": {"coordinates":[-94.25075,44.4488],"type":"Point"}
}