{
  "type": "Feature",
  "properties": {
    "iso:country":"US",
    "sg:address":"4825 W 82nd St",
    "sg:city":"Minneapolis",
    "sg:classifiers":[
        {
            "category":"Building & Trades",
            "subcategory":"Construction",
            "type":"Services"
        }
    ],
    "sg:phone":"+1 952 831 5178",
    "sg:postcode":"55437",
    "sg:province":"MN",
    "sg:tags":[
        "cleaning"
    ],
    "wof:name":"Kds Cleaning Services Inc",
    "wof:placetype":"venue"
},
  "geometry": {"coordinates":[-93.34165400000001,44.854659],"type":"Point"}
}