{
  "type": "Feature",
  "properties": {
    "addr:full":"720 N Kniss Ave Luverne MN 56156",
    "addr:housenumber":"720",
    "addr:postcode":"56156",
    "addr:street":"N Kniss Ave",
    "iso:country":"US",
    "sg:address":"720 N Kniss Ave",
    "sg:city":"Luverne",
    "sg:classifiers":[
        {
            "category":"Organizations",
            "subcategory":"Religious Organization",
            "type":"Services"
        }
    ],
    "sg:phone":"+1 507 283 4571",
    "sg:postcode":"56156",
    "sg:province":"MN",
    "wof:name":"Bethany Lutheran Church",
    "wof:placetype":"venue"
},
  "geometry": {"coordinates":[-96.212582,43.661594],"type":"Point"}
}