{
  "type": "Feature",
  "properties": {
    "addr:full":"9081 W Staring Ln Eden Prairie MN 55347",
    "addr:housenumber":"9081",
    "addr:postcode":"55347",
    "addr:street":"W Staring Ln",
    "iso:country":"US",
    "sg:address":"9081 W Staring Ln",
    "sg:city":"Eden Prairie",
    "sg:classifiers":[
        {
            "category":"Building & Trades",
            "subcategory":"Construction",
            "type":"Services"
        }
    ],
    "sg:phone":"+1 952 974 7975",
    "sg:postcode":"55347",
    "sg:province":"MN",
    "sg:tags":[
        "restoration",
        "cleaning",
        "patio",
        "deck"
    ],
    "wof:name":"Pure Pressure",
    "wof:placetype":"venue"
},
  "geometry": {"coordinates":[-93.46585,44.839611],"type":"Point"}
}