{
  "type": "Feature",
  "properties": {
    "addr:full":"8600 175th St W Lakeville MN 55044",
    "addr:housenumber":"8600",
    "addr:postcode":"55044",
    "addr:street":"175Th St W",
    "iso:country":"US",
    "sg:address":"8600 175th St W",
    "sg:city":"Lakeville",
    "sg:classifiers":[
        {
            "category":"Education",
            "subcategory":"School",
            "type":"Public Place"
        }
    ],
    "sg:phone":"+1 952 469 7232",
    "sg:postcode":"55044",
    "sg:province":"MN",
    "sg:tags":[
        "elementary"
    ],
    "sg:website":"www.isd194.k12.mn.us",
    "wof:name":"Cherry View Elementary School",
    "wof:placetype":"venue"
},
  "geometry": {"coordinates":[-93.23989899999999,44.695801],"type":"Point"}
}