{
  "type": "Feature",
  "properties": {
    "addr:full":"4963 Old Hwy 33 Saginaw MN 55779",
    "addr:housenumber":"4963",
    "addr:postcode":"55779",
    "addr:street":"Old Hwy 33",
    "iso:country":"US",
    "sg:address":"4963 Old Hwy 33",
    "sg:city":"Saginaw",
    "sg:classifiers":[
        {
            "category":"Wholesale",
            "subcategory":"Scrap",
            "type":"Manufacturing & Wholesale Goods"
        }
    ],
    "sg:phone":"+1 218 729 6130",
    "sg:postcode":"55779",
    "sg:province":"MN",
    "sg:tags":[
        "recycling",
        "center"
    ],
    "wof:name":"A-1 Disposal",
    "wof:placetype":"venue"
},
  "geometry": {"coordinates":[-92.459211,46.869823],"type":"Point"}
}