{
  "type": "Feature",
  "properties": {
    "addr:full":"221 W Lake St Minneapolis MN 55408",
    "addr:housenumber":"221",
    "addr:postcode":"55408",
    "addr:street":"W Lake St",
    "iso:country":"US",
    "sg:address":"221 W Lake St",
    "sg:city":"Minneapolis",
    "sg:classifiers":[
        {
            "category":"Restaurant",
            "type":"Food & Drink"
        }
    ],
    "sg:phone":"+1 612 822 8802",
    "sg:postcode":"55408",
    "sg:province":"MN",
    "wof:name":"Wendy's Old Fashioned Hamburgers",
    "wof:placetype":"venue"
},
  "geometry": {"coordinates":[-93.28160099999999,44.9482],"type":"Point"}
}