{
  "type": "Feature",
  "properties": {
    "iso:country":"US",
    "sg:address":"2408 40th St S",
    "sg:city":"Saint Cloud",
    "sg:classifiers":[
        {
            "category":"Retail",
            "subcategory":"Auto Repair",
            "type":"Services"
        }
    ],
    "sg:phone":"+1 320 252 3164",
    "sg:postcode":"56301",
    "sg:province":"MN",
    "sg:tags":[
        "body"
    ],
    "wof:name":"Granite City Auto Body",
    "wof:placetype":"venue"
},
  "geometry": {"coordinates":[-94.186871,45.500561],"type":"Point"}
}