{
  "type": "Feature",
  "properties": {
    "addr:full":"27538 Co Rd 34 Paynesville MN 56362",
    "addr:housenumber":"27538;34",
    "addr:postcode":"56362",
    "addr:street":"Co Rd",
    "iso:country":"US",
    "sg:address":"27538 Co Rd 34",
    "sg:city":"Paynesville",
    "sg:classifiers":[
        {
            "category":"Wholesale",
            "subcategory":"Hardware",
            "type":"Manufacturing & Wholesale Goods"
        }
    ],
    "sg:phone":"+1 320 243 3211",
    "sg:postcode":"56362",
    "sg:province":"MN",
    "sg:tags":[
        "refrigerating"
    ],
    "wof:name":"Regal Refrigeration",
    "wof:placetype":"venue"
},
  "geometry": {"coordinates":[-94.68226,45.36185],"type":"Point"}
}