{
  "type": "Feature",
  "properties": {
    "iso:country":"US",
    "sg:address":"2065 151st Ave NE",
    "sg:city":"Anoka",
    "sg:classifiers":[
        {
            "category":"Retail",
            "subcategory":"Auto Repair",
            "type":"Services"
        }
    ],
    "sg:phone":"+1 763 572 0882",
    "sg:postcode":"55304",
    "sg:province":"MN",
    "sg:tags":[
        "body"
    ],
    "wof:name":"Buttweiler Auto Body",
    "wof:placetype":"venue"
},
  "geometry": {"coordinates":[-93.216992,45.243225],"type":"Point"}
}