{
  "type": "Feature",
  "properties": {
    "addr:full":"422 S Minnesota Ave St Peter MN 56082",
    "addr:housenumber":"422",
    "addr:postcode":"56082",
    "addr:street":"S Minnesota Ave",
    "iso:country":"US",
    "sg:address":"422 S Minnesota Ave",
    "sg:city":"St Peter",
    "sg:classifiers":[
        {
            "category":"Banks & Credit Unions",
            "subcategory":"Investment Brokerage",
            "type":"Services"
        }
    ],
    "sg:phone":"+1 507 934 5510",
    "sg:postcode":"56082",
    "sg:province":"MN",
    "sg:tags":[
        "consultant",
        "planning",
        "financial"
    ],
    "wof:name":"American Express Financial Adv",
    "wof:placetype":"venue"
},
  "geometry": {"coordinates":[-93.95820000000001,44.323157],"type":"Point"}
}