{
  "type": "Feature",
  "properties": {
    "iso:country":"US",
    "sg:address":"23037 360th St",
    "sg:city":"Menahga",
    "sg:classifiers":[
        {
            "category":"Wholesale",
            "subcategory":"Sporting Goods",
            "type":"Manufacturing & Wholesale Goods"
        }
    ],
    "sg:phone":"+1 218 472 3018",
    "sg:postcode":"56464",
    "sg:province":"MN",
    "wof:name":"Country Canvas",
    "wof:placetype":"venue"
},
  "geometry": {"coordinates":[-94.885783,46.746633],"type":"Point"}
}