{
  "type": "Feature",
  "properties": {
    "iso:country":"US",
    "sg:address":"125 Main St S",
    "sg:city":"Hutchinson",
    "sg:classifiers":[
        {
            "category":"Insurance",
            "subcategory":"Insurance Agent",
            "type":"Services"
        }
    ],
    "sg:phone":"+1 320 587 6746",
    "sg:postcode":"55350",
    "sg:province":"MN",
    "wof:name":"Country Insurance",
    "wof:placetype":"venue"
},
  "geometry": {"coordinates":[-94.369202,44.890828],"type":"Point"}
}