{
  "type": "Feature",
  "properties": {
    "addr:full":"253 Main St W Waconia MN 55387",
    "addr:housenumber":"253",
    "addr:postcode":"55387",
    "addr:street":"Main St W Waconia",
    "iso:country":"US",
    "sg:address":"253 Main St W",
    "sg:city":"Waconia",
    "sg:classifiers":[
        {
            "category":"Professional",
            "subcategory":"Management & Consulting",
            "type":"Services"
        }
    ],
    "sg:phone":"+1 952 442 8656",
    "sg:postcode":"55387",
    "sg:province":"MN",
    "sg:tags":[
        "marketing",
        "business",
        "consultant"
    ],
    "sg:website":"www.rkmarketing.com",
    "wof:name":"R K Marketing Enterprises Inc",
    "wof:placetype":"venue"
},
  "geometry": {"coordinates":[-93.789858,44.850381],"type":"Point"}
}