{
  "type": "Feature",
  "properties": {
    "iso:country":"US",
    "sg:address":"6750 France Ave S",
    "sg:city":"Edina",
    "sg:classifiers":[
        {
            "category":"Health Services",
            "subcategory":"Clinic",
            "type":"Services"
        }
    ],
    "sg:phone":"+1 952 653 0525",
    "sg:postcode":"55435",
    "sg:province":"MN",
    "sg:tags":[
        "hypnotherapy"
    ],
    "wof:name":"Hypno Sis",
    "wof:placetype":"venue"
},
  "geometry": {"coordinates":[-93.329015,44.88269],"type":"Point"}
}