{
  "type": "Feature",
  "properties": {
    "iso:country":"US",
    "sg:address":"970 Dague Ave NE",
    "sg:city":"Buffalo",
    "sg:classifiers":[
        {
            "category":"Farming",
            "subcategory":"Farm",
            "type":"Manufacturing & Wholesale Goods"
        }
    ],
    "sg:phone":"+1 763 682 2124",
    "sg:postcode":"55313",
    "sg:province":"MN",
    "sg:tags":[
        "crop",
        "general"
    ],
    "wof:name":"Franklin Hohl",
    "wof:placetype":"venue"
},
  "geometry": {"coordinates":[-93.827084,45.162306],"type":"Point"}
}