{
  "type": "Feature",
  "properties": {
    "addr:full":"19845 Lillehei Ave Hastings MN 55033",
    "addr:housenumber":"19845",
    "addr:postcode":"55033",
    "addr:street":"Lillehei Ave",
    "iso:country":"US",
    "sg:address":"19845 Lillehei Ave",
    "sg:city":"Hastings",
    "sg:classifiers":[
        {
            "category":"Health Services",
            "subcategory":"Nursing And Care Facility",
            "type":"Services"
        }
    ],
    "sg:phone":"+1 651 437 9363",
    "sg:postcode":"55033",
    "sg:province":"MN",
    "sg:tags":[
        "personal"
    ],
    "wof:name":"Henry Hagen Residence",
    "wof:placetype":"venue"
},
  "geometry": {"coordinates":[-92.853272,44.659127],"type":"Point"}
}