{
  "type": "Feature",
  "properties": {
    "iso:country":"US",
    "sg:address":"9221 Clyde Ave",
    "sg:city":"Duluth",
    "sg:classifiers":[
        {
            "category":"Professional",
            "type":"Services"
        }
    ],
    "sg:phone":"+1 218 626 1170",
    "sg:postcode":"55808",
    "sg:province":"MN",
    "wof:name":"Service Plus International",
    "wof:placetype":"venue"
},
  "geometry": {"coordinates":[-92.216776,46.700835],"type":"Point"}
}