{
  "type": "Feature",
  "properties": {
    "addr:full":"9201 Penn Ave S Bloomington MN 55431",
    "addr:housenumber":"9201",
    "addr:postcode":"55431",
    "addr:street":"Penn Ave S",
    "iso:country":"US",
    "sg:address":"9201 Penn Ave S",
    "sg:city":"Bloomington",
    "sg:classifiers":[
        {
            "category":"Professional",
            "subcategory":"Art Services",
            "type":"Services"
        }
    ],
    "sg:phone":"+1 952 885 0008",
    "sg:postcode":"55431",
    "sg:province":"MN",
    "sg:tags":[
        "development",
        "package",
        "designing"
    ],
    "wof:name":"Bliss Design",
    "wof:placetype":"venue"
},
  "geometry": {"coordinates":[-93.308768,44.838108],"type":"Point"}
}