{
  "type": "Feature",
  "properties": {
    "iso:country":"US",
    "sg:address":"645 Sibley Memorial Hwy",
    "sg:city":"Saint Paul",
    "sg:classifiers":[
        {
            "category":"Manufacturing",
            "subcategory":"Wood Products",
            "type":"Manufacturing & Wholesale Goods"
        }
    ],
    "sg:phone":"+1 651 699 5529",
    "sg:postcode":"55118",
    "sg:province":"MN",
    "sg:tags":[
        "decorative",
        "glass",
        "mfg"
    ],
    "wof:name":"Stakkers Inc",
    "wof:placetype":"venue"
},
  "geometry": {"coordinates":[-93.114726,44.915643],"type":"Point"}
}