{
  "type": "Feature",
  "properties": {
    "addr:full":"743 73rd Way N Minneapolis MN 55444",
    "addr:housenumber":"743",
    "addr:postcode":"55444",
    "addr:street":"73Rd Way N",
    "iso:country":"US",
    "sg:address":"743 73rd Way N",
    "sg:city":"Minneapolis",
    "sg:classifiers":[
        {
            "category":"Manufacturing",
            "subcategory":"Textiles",
            "type":"Manufacturing & Wholesale Goods"
        }
    ],
    "sg:phone":"+1 763 560 8236",
    "sg:postcode":"55444",
    "sg:province":"MN",
    "sg:tags":[
        "mill",
        "wool",
        "textiles-manufacturers",
        "fabric"
    ],
    "wof:name":"Georgie Anne Weavers",
    "wof:placetype":"venue"
},
  "geometry": {"coordinates":[-93.290893,45.088007],"type":"Point"}
}