{
  "type": "Feature",
  "properties": {
    "iso:country":"US",
    "sg:address":"151 W Burnsville Pkwy",
    "sg:city":"Burnsville",
    "sg:classifiers":[
        {
            "category":"Professional",
            "subcategory":"Management & Consulting",
            "type":"Services"
        }
    ],
    "sg:phone":"+1 952 882 8122",
    "sg:postcode":"55337",
    "sg:province":"MN",
    "wof:name":"Rmg",
    "wof:placetype":"venue"
},
  "geometry": {"coordinates":[-93.279752,44.771788],"type":"Point"}
}