{
  "type": "Feature",
  "properties": {
    "iso:country":"US",
    "sg:address":"2829 Verndale Ave",
    "sg:city":"Anoka",
    "sg:classifiers":[
        {
            "category":"Social Services",
            "type":"Services"
        }
    ],
    "sg:phone":"+1 763 421 8530",
    "sg:postcode":"55303",
    "sg:province":"MN",
    "sg:tags":[
        "youth",
        "organization",
        "center"
    ],
    "wof:name":"Youth First Neighbor Helping",
    "wof:placetype":"venue"
},
  "geometry": {"coordinates":[-93.407442,45.21014],"type":"Point"}
}