{
  "type": "Feature",
  "properties": {
    "addr:full":"412 19th Ave SW Willmar MN 56201",
    "addr:housenumber":"412",
    "addr:postcode":"56201",
    "addr:street":"19Th Ave Sw",
    "iso:country":"US",
    "sg:address":"412 19th Ave SW",
    "sg:city":"Willmar",
    "sg:classifiers":[
        {
            "category":"Health Services",
            "subcategory":"Chiropractor",
            "type":"Services"
        }
    ],
    "sg:phone":"+1 320 235 8380",
    "sg:postcode":"56201",
    "sg:province":"MN",
    "wof:name":"Pauly Chiropractic Center PA",
    "wof:placetype":"venue"
},
  "geometry": {"coordinates":[-95.045389,45.103435],"type":"Point"}
}