{
  "type": "Feature",
  "properties": {
    "addr:full":"2076 Wallingford Cir St Paul MN 55125",
    "addr:housenumber":"2076",
    "addr:postcode":"55125",
    "addr:street":"Wallingford Cir",
    "iso:country":"US",
    "sg:address":"2076 Wallingford Cir",
    "sg:city":"St Paul",
    "sg:classifiers":[
        {
            "category":"Professional",
            "type":"Services"
        }
    ],
    "sg:phone":"+1 651 735 6591",
    "sg:postcode":"55125",
    "sg:province":"MN",
    "sg:tags":[
        "establishment"
    ],
    "wof:name":"D & A Flores Corp",
    "wof:placetype":"venue"
},
  "geometry": {"coordinates":[-92.91589500000001,44.918803],"type":"Point"}
}