{
  "type": "Feature",
  "properties": {
    "addr:full":"300 International Dr Red Lake Falls MN 56750",
    "addr:housenumber":"300",
    "addr:postcode":"56750",
    "addr:street":"International Dr",
    "iso:country":"US",
    "sg:address":"300 International Dr",
    "sg:city":"Red Lake Falls",
    "sg:classifiers":[
        {
            "category":"Social Services",
            "type":"Services"
        }
    ],
    "sg:phone":"+1 218 253 4454",
    "sg:postcode":"56750",
    "sg:province":"MN",
    "sg:tags":[
        "senior",
        "citizen"
    ],
    "wof:name":"L S S Senior Nutrition Program",
    "wof:placetype":"venue"
},
  "geometry": {"coordinates":[-96.278818,47.875025],"type":"Point"}
}