{
  "type": "Feature",
  "properties": {
    "iso:country":"US",
    "sg:address":"1493 Crescent Hills Dr",
    "sg:city":"La Crescent",
    "sg:classifiers":[
        {
            "category":"Insurance",
            "subcategory":"Insurance Agent",
            "type":"Services"
        }
    ],
    "sg:phone":"+1 507 895 6535",
    "sg:postcode":"55947",
    "sg:province":"MN",
    "wof:name":"Horace Mann Insurance Agency",
    "wof:placetype":"venue"
},
  "geometry": {"coordinates":[-91.31730399999999,43.844228],"type":"Point"}
}