{
  "type": "Feature",
  "properties": {
    "addr:full":"1641 N Broadway Rochester MN 55906",
    "addr:housenumber":"1641",
    "addr:postcode":"55906",
    "addr:street":"N Broadway",
    "iso:country":"US",
    "sg:address":"1641 N Broadway",
    "sg:city":"Rochester",
    "sg:classifiers":[
        {
            "category":"Shopping",
            "subcategory":"Gifts & Souvenirs",
            "type":"Retail Goods"
        }
    ],
    "sg:phone":"+1 507 287 1059",
    "sg:postcode":"55906",
    "sg:province":"MN",
    "wof:name":"Party America",
    "wof:placetype":"venue"
},
  "geometry": {"coordinates":[-92.461316,44.040649],"type":"Point"}
}