{
  "type": "Feature",
  "properties": {
    "iso:country":"US",
    "sg:address":"7328 Ohms Ln",
    "sg:city":"Edina",
    "sg:classifiers":[
        {
            "category":"Wholesale",
            "subcategory":"Hardware",
            "type":"Manufacturing & Wholesale Goods"
        },
        {
            "category":"Manufacturing",
            "subcategory":"Metals",
            "type":"Manufacturing & Wholesale Goods"
        }
    ],
    "sg:phone":"+1 952 941 1740",
    "sg:postcode":"55439",
    "sg:province":"MN",
    "sg:tags":[
        "plant",
        "valve",
        "pipe",
        "equipment",
        "fitting",
        "representative"
    ],
    "wof:name":"Fluid Specialties Inc",
    "wof:placetype":"venue"
},
  "geometry": {"coordinates":[-93.354784,44.869458],"type":"Point"}
}