{
  "type": "Feature",
  "properties": {
    "iso:country":"US",
    "sg:address":"578 E 4th St",
    "sg:city":"Winona",
    "sg:classifiers":[
        {
            "category":"Shopping",
            "type":"Retail Goods"
        }
    ],
    "sg:phone":"+1 507 474 0007",
    "sg:postcode":"55987",
    "sg:province":"MN",
    "sg:tags":[
        "candle"
    ],
    "wof:name":"Sugar Loaf Candle Co",
    "wof:placetype":"venue"
},
  "geometry": {"coordinates":[-91.62309,44.04756],"type":"Point"}
}