{
  "type": "Feature",
  "properties": {
    "iso:country":"US",
    "sg:address":"13750 Reimer Dr N",
    "sg:city":"Maple Grove",
    "sg:classifiers":[
        {
            "category":"Real Estate",
            "subcategory":"Developer",
            "type":"Services"
        }
    ],
    "sg:phone":"+1 763 416 0002",
    "sg:postcode":"55311",
    "sg:province":"MN",
    "wof:name":"Town Center Development LLC",
    "wof:placetype":"venue"
},
  "geometry": {"coordinates":[-93.455017,45.09856],"type":"Point"}
}