{
  "type": "Feature",
  "properties": {
    "addr:full":"23697 Wass Ave Brewster MN 56119",
    "addr:postcode":"23697;56119",
    "addr:street":"Wass Ave",
    "iso:country":"US",
    "sg:address":"23697 Wass Ave",
    "sg:city":"Brewster",
    "sg:phone":"+1 507 842 5215",
    "sg:postcode":"56119",
    "sg:province":"MN",
    "sg:tags":[
        "farm",
        "corn"
    ],
    "wof:name":"Jerry Luinenburg",
    "wof:placetype":"venue"
},
  "geometry": {"coordinates":[-95.472616,43.649026],"type":"Point"}
}