{
  "type": "Feature",
  "properties": {
    "addr:full":"2218 Martin St Grand Rapids MN 55744",
    "addr:housenumber":"2218",
    "addr:postcode":"55744",
    "addr:street":"Martin St",
    "iso:country":"US",
    "sg:address":"2218 Martin St",
    "sg:city":"Grand Rapids",
    "sg:classifiers":[
        {
            "category":"Social Services",
            "subcategory":"Child Care",
            "type":"Services"
        }
    ],
    "sg:phone":"+1 218 327 0416",
    "sg:postcode":"55744",
    "sg:province":"MN",
    "sg:tags":[
        "day",
        "provider"
    ],
    "wof:name":"Rose A Damjanovich",
    "wof:placetype":"venue"
},
  "geometry": {"coordinates":[-93.490193,47.240467],"type":"Point"}
}