{
  "type": "Feature",
  "properties": {
    "iso:country":"US",
    "sg:address":"4138 160th Ave SE",
    "sg:city":"Dover",
    "sg:classifiers":[
        {
            "category":"Manufacturing",
            "subcategory":"Food",
            "type":"Manufacturing & Wholesale Goods"
        },
        {
            "category":"Farming",
            "subcategory":"Farm",
            "type":"Manufacturing & Wholesale Goods"
        }
    ],
    "sg:phone":"+1 507 932 5521",
    "sg:postcode":"55929",
    "sg:province":"MN",
    "sg:tags":[
        "corn",
        "product"
    ],
    "wof:name":"Barrs, John",
    "wof:placetype":"venue"
},
  "geometry": {"coordinates":[-92.159149,43.960731],"type":"Point"}
}