{
  "type": "Feature",
  "properties": {
    "addr:full":"8404 137th Ct Saint Paul MN 55124",
    "addr:housenumber":"8404",
    "addr:postcode":"55124",
    "addr:street":"137Th Ct",
    "iso:country":"US",
    "sg:address":"8404 137th Ct",
    "sg:city":"Saint Paul",
    "sg:classifiers":[
        {
            "category":"Professional",
            "subcategory":"Business Services",
            "type":"Services"
        }
    ],
    "sg:phone":"+1 952 432 7129",
    "sg:postcode":"55124",
    "sg:province":"MN",
    "wof:name":"Rave On Entertainment",
    "wof:placetype":"venue"
},
  "geometry": {"coordinates":[-93.235846,44.749994],"type":"Point"}
}