{
  "type": "Feature",
  "properties": {
    "addr:full":"5622 Grand Ave Duluth MN 55807",
    "addr:housenumber":"5622",
    "addr:postcode":"55807",
    "addr:street":"Grand Ave",
    "iso:country":"US",
    "sg:address":"5622 Grand Ave",
    "sg:city":"Duluth",
    "sg:classifiers":[
        {
            "category":"Restaurant",
            "type":"Food & Drink"
        }
    ],
    "sg:phone":"+1 218 628 3793",
    "sg:postcode":"55807",
    "sg:province":"MN",
    "sg:tags":[
        "eating"
    ],
    "wof:name":"Styles Catering",
    "wof:placetype":"venue"
},
  "geometry": {"coordinates":[-92.16874199999999,46.739214],"type":"Point"}
}