{
  "type": "Feature",
  "properties": {
    "iso:country":"US",
    "sg:address":"120 2nd St NW",
    "sg:city":"Fosston",
    "sg:classifiers":[
        {
            "category":"Insurance",
            "subcategory":"Insurance Agent",
            "type":"Services"
        }
    ],
    "sg:phone":"+1 218 435 6585",
    "sg:postcode":"56542",
    "sg:province":"MN",
    "sg:website":"www.lindforsagency.com",
    "wof:name":"Lindfors Insurance",
    "wof:placetype":"venue"
},
  "geometry": {"coordinates":[-95.75137700000001,47.577117],"type":"Point"}
}