{
  "type": "Feature",
  "properties": {
    "iso:country":"US",
    "sg:address":"8810 27th Street Ct N",
    "sg:city":"Lake Elmo",
    "sg:classifiers":[
        {
            "category":"Professional",
            "subcategory":"Business Services",
            "type":"Services"
        }
    ],
    "sg:phone":"+1 651 770 0443",
    "sg:postcode":"55042",
    "sg:province":"MN",
    "wof:name":"South Kawishiwi Cabin Group LL",
    "wof:placetype":"venue"
},
  "geometry": {"coordinates":[-92.927232,44.988974],"type":"Point"}
}