{
  "type": "Feature",
  "properties": {
    "addr:full":"2211 1st St S Willmar MN 56201",
    "addr:housenumber":"2211",
    "addr:postcode":"56201",
    "addr:street":"1St St S",
    "iso:country":"US",
    "sg:address":"2211 1st St S",
    "sg:city":"Willmar",
    "sg:classifiers":[
        {
            "category":"Personal",
            "subcategory":"Beauty Salon",
            "type":"Services"
        }
    ],
    "sg:phone":"+1 320 235 8818",
    "sg:postcode":"56201",
    "sg:province":"MN",
    "sg:tags":[
        "manicuring"
    ],
    "wof:name":"Fashion Nails",
    "wof:placetype":"venue"
},
  "geometry": {"coordinates":[-95.042562,45.100826],"type":"Point"}
}