{
  "type": "Feature",
  "properties": {
    "iso:country":"US",
    "sg:address":"30340 Newlander Ct",
    "sg:city":"Lindstrom",
    "sg:classifiers":[
        {
            "category":"Professional",
            "subcategory":"Business Services",
            "type":"Services"
        }
    ],
    "sg:phone":"+1 651 257 2855",
    "sg:postcode":"55045",
    "sg:province":"MN",
    "sg:tags":[
        "water",
        "treatment"
    ],
    "sg:website":"www.wettechnology.com",
    "wof:name":"Wet Technology Inc",
    "wof:placetype":"venue"
},
  "geometry": {"coordinates":[-92.833359,45.387022],"type":"Point"}
}