{
  "type": "Feature",
  "properties": {
    "iso:country":"US",
    "sg:address":"1501 University Ave SE",
    "sg:city":"Minneapolis",
    "sg:classifiers":[
        {
            "category":"Bars & Pubs",
            "type":"Food & Drink"
        },
        {
            "category":"Restaurant",
            "type":"Food & Drink"
        }
    ],
    "sg:phone":"+1 612 379 1224",
    "sg:postcode":"55467",
    "sg:province":"MN",
    "wof:name":"Downtime Bar & Grill",
    "wof:placetype":"venue"
},
  "geometry": {"coordinates":[-93.235151,44.978969],"type":"Point"}
}