{
  "type": "Feature",
  "properties": {
    "addr:full":"120 Euclid Ave Big Lake MN 55309",
    "addr:housenumber":"120",
    "addr:postcode":"55309",
    "addr:street":"Euclid Ave",
    "iso:country":"US",
    "sg:address":"120 Euclid Ave",
    "sg:city":"Big Lake",
    "sg:classifiers":[
        {
            "category":"Professional",
            "subcategory":"Business Services",
            "type":"Services"
        }
    ],
    "sg:phone":"+1 763 263 3377",
    "sg:postcode":"55309",
    "sg:province":"MN",
    "sg:tags":[
        "recording",
        "studio"
    ],
    "wof:name":"Rhythm Water Productions",
    "wof:placetype":"venue"
},
  "geometry": {"coordinates":[-93.76162100000001,45.337731],"type":"Point"}
}