{
  "type": "Feature",
  "properties": {
    "iso:country":"US",
    "sg:address":"1121 Town Centre Dr",
    "sg:city":"Eagan",
    "sg:classifiers":[
        {
            "category":"Health Services",
            "subcategory":"Doctor",
            "type":"Services"
        }
    ],
    "sg:phone":"+1 651 209 8640",
    "sg:postcode":"55123",
    "sg:province":"MN",
    "sg:tags":[
        "clinic",
        "practice",
        "medical"
    ],
    "wof:name":"Mendota Health PA",
    "wof:placetype":"venue"
},
  "geometry": {"coordinates":[-93.14864799999999,44.831388],"type":"Point"}
}