{
  "type": "Feature",
  "properties": {
    "iso:country":"US",
    "sg:address":"2575 University Ave W",
    "sg:city":"St Paul",
    "sg:classifiers":[
        {
            "category":"Wholesale",
            "subcategory":"Stationery",
            "type":"Manufacturing & Wholesale Goods"
        }
    ],
    "sg:phone":"+1 651 783 5955",
    "sg:postcode":"55114",
    "sg:province":"MN",
    "sg:tags":[
        "card"
    ],
    "sg:website":"www.anchorpaper.com",
    "wof:name":"Anchor Paper Express",
    "wof:placetype":"venue"
},
  "geometry": {"coordinates":[-93.20391100000001,44.967275],"type":"Point"}
}