{
  "type": "Feature",
  "properties": {
    "iso:country":"US",
    "sg:address":"600 Northtown Dr NE",
    "sg:city":"Minneapolis",
    "sg:classifiers":[
        {
            "category":"Shopping",
            "subcategory":"Clothing, Apparel, & Fashions",
            "type":"Retail Goods"
        }
    ],
    "sg:phone":"+1 763 783 1143",
    "sg:postcode":"55434",
    "sg:province":"MN",
    "sg:tags":[
        "clothing",
        "store"
    ],
    "sg:website":"http://www.burlingtoncoatfactory.com",
    "wof:name":"Burlington Coat Factory",
    "wof:placetype":"venue"
},
  "geometry": {"coordinates":[-93.257437,45.12725],"type":"Point"}
}