{
  "type": "Feature",
  "properties": {
    "addr:full":"710 N 2nd St Minneapolis MN 55401",
    "addr:housenumber":"710",
    "addr:postcode":"55401",
    "addr:street":"N 2Nd St",
    "iso:country":"US",
    "sg:address":"710 N 2nd St",
    "sg:city":"Minneapolis",
    "sg:classifiers":[
        {
            "category":"Professional",
            "type":"Services"
        }
    ],
    "sg:phone":"+1 612 378 7002",
    "sg:postcode":"55401",
    "sg:province":"MN",
    "sg:tags":[
        "establishment"
    ],
    "wof:name":"Invioni",
    "wof:placetype":"venue"
},
  "geometry": {"coordinates":[-93.27697499999999,44.989276],"type":"Point"}
}