{
  "type": "Feature",
  "properties": {
    "iso:country":"US",
    "sg:address":"5051 State Hwy 7",
    "sg:city":"Minneapolis",
    "sg:classifiers":[
        {
            "category":"Professional",
            "subcategory":"Advertising",
            "type":"Services"
        }
    ],
    "sg:phone":"+1 952 920 7191",
    "sg:postcode":"55416",
    "sg:province":"MN",
    "sg:tags":[
        "agency"
    ],
    "wof:name":"Lighthouse Brands",
    "wof:placetype":"venue"
},
  "geometry": {"coordinates":[-93.342451,44.944913],"type":"Point"}
}