{
  "type": "Feature",
  "properties": {
    "iso:country":"US",
    "sg:address":"11307 Robinson Dr NW",
    "sg:city":"Coon Rapids",
    "sg:classifiers":[
        {
            "category":"Real Estate",
            "subcategory":"Real Estate Operator",
            "type":"Services"
        }
    ],
    "sg:phone":"+1 763 755 8150",
    "sg:postcode":"55433",
    "sg:province":"MN",
    "sg:tags":[
        "building",
        "apartment"
    ],
    "wof:name":"Winchester Place Apartments",
    "wof:placetype":"venue"
},
  "geometry": {"coordinates":[-93.308673,45.177234],"type":"Point"}
}