{
  "type": "Feature",
  "properties": {
    "iso:country":"US",
    "sg:address":"4355 Peavy Rd",
    "sg:city":"Chanhassen",
    "sg:classifiers":[
        {
            "category":"Retail",
            "subcategory":"Auto Rental",
            "type":"Services"
        }
    ],
    "sg:phone":"+1 952 448 6539",
    "sg:postcode":"55317",
    "sg:province":"MN",
    "sg:tags":[
        "car"
    ],
    "wof:name":"Eden Prairie A To Z Rentals",
    "wof:placetype":"venue"
},
  "geometry": {"coordinates":[-93.55549600000001,44.862598],"type":"Point"}
}