{
  "type": "Feature",
  "properties": {
    "iso:country":"US",
    "sg:address":"63348 320th St",
    "sg:city":"Sargeant",
    "sg:phone":"+1 507 584 6309",
    "sg:postcode":"55973",
    "sg:province":"MN",
    "sg:tags":[
        "farm",
        "corn"
    ],
    "wof:name":"Bradley Heydt",
    "wof:placetype":"venue"
},
  "geometry": {"coordinates":[-92.782878,43.819563],"type":"Point"}
}