{
  "type": "Feature",
  "properties": {
    "iso:country":"US",
    "sg:address":"2860 Willow Dr",
    "sg:city":"Hamel",
    "sg:classifiers":[
        {
            "category":"Professional",
            "subcategory":"Research",
            "type":"Services"
        }
    ],
    "sg:phone":"+1 763 478 6724",
    "sg:postcode":"55340",
    "sg:province":"MN",
    "sg:tags":[
        "nonphysical",
        "commercial"
    ],
    "wof:name":"N K Friedrichs Consulting Inc",
    "wof:placetype":"venue"
},
  "geometry": {"coordinates":[-93.58346400000001,45.032209],"type":"Point"}
}