{
  "type": "Feature",
  "properties": {
    "addr:full":"8651 Graff Rd Forbes MN 55738",
    "addr:housenumber":"8651",
    "addr:postcode":"55738",
    "addr:street":"Graff Rd",
    "iso:country":"US",
    "sg:address":"8651 Graff Rd",
    "sg:city":"Forbes",
    "sg:classifiers":[
        {
            "category":"Building & Trades",
            "subcategory":"Electrical",
            "type":"Services"
        }
    ],
    "sg:phone":"+1 218 744 3378",
    "sg:postcode":"55738",
    "sg:province":"MN",
    "sg:tags":[
        "electrical",
        "contractor"
    ],
    "wof:name":"Lightening Electric",
    "wof:placetype":"venue"
},
  "geometry": {"coordinates":[-92.59166,47.335867],"type":"Point"}
}