{
  "type": "Feature",
  "properties": {
    "addr:full":"5015 US Hwy 212 Chaska MN 55318",
    "addr:housenumber":"5015",
    "addr:postcode":"55318",
    "addr:street":"Us Hwy 212",
    "iso:country":"US",
    "sg:address":"5015 US Hwy 212",
    "sg:city":"Chaska",
    "sg:classifiers":[
        {
            "category":"Shopping",
            "type":"Retail Goods"
        }
    ],
    "sg:phone":"+1 952 448 5930",
    "sg:postcode":"55318",
    "sg:province":"MN",
    "sg:tags":[
        "merchandise"
    ],
    "wof:name":"Silk Tree",
    "wof:placetype":"venue"
},
  "geometry": {"coordinates":[-93.646355,44.776342],"type":"Point"}
}