{
  "type": "Feature",
  "properties": {
    "addr:full":"181 Broadway Ave Hamburg MN 55339",
    "addr:housenumber":"181",
    "addr:postcode":"55339",
    "addr:street":"Broadway Ave",
    "iso:country":"US",
    "sg:address":"181 Broadway Ave",
    "sg:city":"Hamburg",
    "sg:classifiers":[
        {
            "category":"Government",
            "subcategory":"Fire Station",
            "type":"Public Place"
        }
    ],
    "sg:phone":"+1 952 467 3232",
    "sg:postcode":"55339",
    "sg:province":"MN",
    "sg:tags":[
        "department"
    ],
    "wof:name":"Fire Dept.",
    "wof:placetype":"venue"
},
  "geometry": {"coordinates":[-93.97139,44.73188],"type":"Point"}
}