{
  "type": "Feature",
  "properties": {
    "addr:full":"430 W State Highway 5 Waconia MN 55387",
    "addr:housenumber":"430",
    "addr:postcode":"55387",
    "addr:street":"W State Highway 5 Waconia",
    "iso:country":"US",
    "sg:address":"430 W State Highway 5",
    "sg:city":"Waconia",
    "sg:classifiers":[
        {
            "category":"Shopping",
            "subcategory":"Pharmacy",
            "type":"Retail Goods"
        }
    ],
    "sg:phone":"+1 952 442 3274",
    "sg:postcode":"55387",
    "sg:province":"MN",
    "sg:tags":[
        "drugstore"
    ],
    "wof:name":"Waconia Pharmacy",
    "wof:placetype":"venue"
},
  "geometry": {"coordinates":[-93.544495,44.79321],"type":"Point"}
}