{
  "type": "Feature",
  "properties": {
    "addr:full":"17565 Central Ave NE Andover MN 55304",
    "addr:postcode":"17565;55304",
    "addr:street":"Central Ave Ne",
    "iso:country":"US",
    "sg:address":"17565 Central Ave NE",
    "sg:city":"Andover",
    "sg:classifiers":[
        {
            "category":"Sports & Exercise",
            "subcategory":"Gym",
            "type":"Entertainment"
        }
    ],
    "sg:phone":"+1 763 413 0200",
    "sg:postcode":"55304",
    "sg:province":"MN",
    "sg:tags":[
        "club",
        "health",
        "studio",
        "gymnasium"
    ],
    "wof:name":"Curves For Women",
    "wof:placetype":"venue"
},
  "geometry": {"coordinates":[-93.233531,45.289151],"type":"Point"}
}