{
  "type": "Feature",
  "properties": {
    "iso:country":"US",
    "sg:address":"276 Market St",
    "sg:city":"Bloomington",
    "sg:classifiers":[
        {
            "category":"Restaurant",
            "type":"Food & Drink"
        }
    ],
    "sg:phone":"+1 952 853 1274",
    "sg:postcode":"55405",
    "sg:province":"MN",
    "sg:tags":[
        "shop",
        "coffee"
    ],
    "wof:name":"Starbuck's Coffee",
    "wof:placetype":"venue"
},
  "geometry": {"coordinates":[-93.289737,44.979949],"type":"Point"}
}