{
  "type": "Feature",
  "properties": {
    "addr:full":"P.O. Box 1101 Minneapolis MN 55440-1101",
    "addr:housenumber":"p.o. box 1101",
    "addr:postcode":"55440-1101",
    "iso:country":"US",
    "sg:address":"P.O. Box 1101",
    "sg:city":"Minneapolis",
    "sg:classifiers":[
        {
            "category":"Professional",
            "subcategory":"Computer Services",
            "type":"Services"
        }
    ],
    "sg:phone":"+1 800 366 3889",
    "sg:postcode":"55440-1101",
    "sg:province":"MN",
    "sg:website":"http://www.adc.com/",
    "wof:name":"ADC",
    "wof:placetype":"venue"
},
  "geometry": {"coordinates":[-93.47188,45.015914],"type":"Point"}
}