{
  "type": "Feature",
  "properties": {
    "addr:full":"213 Bush St Red Wing MN 55066",
    "addr:housenumber":"213",
    "addr:postcode":"55066",
    "addr:street":"Bush St",
    "iso:country":"US",
    "sg:address":"213 Bush St",
    "sg:city":"Red Wing",
    "sg:classifiers":[
        {
            "category":"Shopping",
            "subcategory":"Gifts & Souvenirs",
            "type":"Retail Goods"
        }
    ],
    "sg:phone":"+1 651 388 5171",
    "sg:postcode":"55066",
    "sg:province":"MN",
    "wof:name":"Lifes Little Oasis",
    "wof:placetype":"venue"
},
  "geometry": {"coordinates":[-92.535014,44.565893],"type":"Point"}
}