{
  "type": "Feature",
  "properties": {
    "iso:country":"US",
    "sg:address":"127 E Lincoln Ave",
    "sg:city":"Fergus Falls",
    "sg:classifiers":[
        {
            "category":"Restaurant",
            "type":"Food & Drink"
        }
    ],
    "sg:phone":"+1 218 736 2090",
    "sg:postcode":"56537",
    "sg:province":"MN",
    "sg:tags":[
        "shop",
        "coffee"
    ],
    "wof:name":"Barringers Coffee House Ltd",
    "wof:placetype":"venue"
},
  "geometry": {"coordinates":[-96.072739,46.283582],"type":"Point"}
}