{
  "type": "Feature",
  "properties": {
    "addr:full":"509 Morin St Hartland MN 56042",
    "addr:housenumber":"509",
    "addr:postcode":"56042",
    "addr:street":"Morin St",
    "iso:country":"US",
    "sg:address":"509 Morin St",
    "sg:city":"Hartland",
    "sg:classifiers":[
        {
            "category":"Professional",
            "type":"Services"
        }
    ],
    "sg:phone":"+1 507 845 2571",
    "sg:postcode":"56042",
    "sg:province":"MN",
    "sg:tags":[
        "establishment"
    ],
    "wof:name":"Measner Jamie",
    "wof:placetype":"venue"
},
  "geometry": {"coordinates":[-93.48551399999999,43.802314],"type":"Point"}
}