{
  "type": "Feature",
  "properties": {
    "addr:full":"1337 24th St NW Apt 301 Willmar MN 56201",
    "addr:housenumber":"1337;301",
    "addr:postcode":"56201",
    "addr:street":"24Th St Nw Apt",
    "iso:country":"US",
    "sg:address":"1337 24th St NW Apt 301",
    "sg:city":"Willmar",
    "sg:classifiers":[
        {
            "category":"Real Estate",
            "subcategory":"Real Estate Operator",
            "type":"Services"
        }
    ],
    "sg:phone":"+1 320 235 6136",
    "sg:postcode":"56201",
    "sg:province":"MN",
    "sg:tags":[
        "apartment"
    ],
    "wof:name":"Infinity Financial Evergreen",
    "wof:placetype":"venue"
},
  "geometry": {"coordinates":[-95.07680000000001,45.138701],"type":"Point"}
}