{
  "type": "Feature",
  "properties": {
    "iso:country":"US",
    "sg:address":"22324 37th St SW",
    "sg:city":"Blomkest",
    "sg:classifiers":[
        {
            "category":"Professional",
            "type":"Services"
        }
    ],
    "sg:phone":"+1 320 978 6072",
    "sg:postcode":"56216",
    "sg:province":"MN",
    "wof:name":"Mike Roufs",
    "wof:placetype":"venue"
},
  "geometry": {"coordinates":[-95.09495800000001,44.918735],"type":"Point"}
}