{
  "type": "Feature",
  "properties": {
    "addr:full":"1037 Chatsworth St N Saint Paul MN 55103",
    "addr:housenumber":"1037",
    "addr:postcode":"55103",
    "addr:street":"Chatsworth St N",
    "iso:country":"US",
    "sg:address":"1037 Chatsworth St N",
    "sg:city":"Saint Paul",
    "sg:classifiers":[
        {
            "category":"Food & Beverages",
            "subcategory":"Groceries & Convenience Stores",
            "type":"Retail Goods"
        }
    ],
    "sg:phone":"+1 651 488 0749",
    "sg:postcode":"55103",
    "sg:province":"MN",
    "wof:name":"Rogers Market",
    "wof:placetype":"venue"
},
  "geometry": {"coordinates":[-93.141595,44.971391],"type":"Point"}
}