{
  "type": "Feature",
  "properties": {
    "iso:country":"US",
    "sg:address":"1937 2nd Ave E",
    "sg:city":"Hibbing",
    "sg:classifiers":[
        {
            "category":"Professional",
            "subcategory":"Lawyer & Legal Services",
            "type":"Services"
        }
    ],
    "sg:phone":"+1 218 262 5100",
    "sg:postcode":"55746",
    "sg:province":"MN",
    "sg:tags":[
        "attorney"
    ],
    "wof:name":"Clark Law Offices",
    "wof:placetype":"venue"
},
  "geometry": {"coordinates":[-92.940667,47.427986],"type":"Point"}
}