{
  "type": "Feature",
  "properties": {
    "addr:full":"25890 Finch Ct Wyoming MN 55092",
    "addr:housenumber":"25890",
    "addr:postcode":"55092",
    "addr:street":"Finch Ct",
    "iso:country":"US",
    "sg:address":"25890 Finch Ct",
    "sg:city":"Wyoming",
    "sg:classifiers":[
        {
            "category":"Banks & Credit Unions",
            "subcategory":"Financial Services",
            "type":"Services"
        }
    ],
    "sg:phone":"+1 651 462 3572",
    "sg:postcode":"55092",
    "sg:province":"MN",
    "sg:tags":[
        "trust",
        "management"
    ],
    "wof:name":"Dorothy J Will Trust",
    "wof:placetype":"venue"
},
  "geometry": {"coordinates":[-92.99213,45.325093],"type":"Point"}
}