{
  "type": "Feature",
  "properties": {
    "iso:country":"US",
    "sg:address":"4840 Orleans Ln N",
    "sg:city":"Minneapolis",
    "sg:classifiers":[
        {
            "category":"Shopping",
            "type":"Retail Goods"
        }
    ],
    "sg:phone":"+1 763 559 5586",
    "sg:postcode":"55442",
    "sg:province":"MN",
    "sg:tags":[
        "cosmetic",
        "perfume"
    ],
    "wof:name":"Healthwatch Minnesota",
    "wof:placetype":"venue"
},
  "geometry": {"coordinates":[-93.406784,45.042491],"type":"Point"}
}