{
  "type": "Feature",
  "properties": {
    "iso:country":"US",
    "sg:address":"4431 Otter Lake Rd",
    "sg:city":"Saint Paul",
    "sg:classifiers":[
        {
            "category":"Home & Garden",
            "subcategory":"Building Materials",
            "type":"Retail Goods"
        }
    ],
    "sg:phone":"+1 651 735 9211",
    "sg:postcode":"55110",
    "sg:province":"MN",
    "sg:tags":[
        "window",
        "door",
        "product"
    ],
    "wof:name":"JMS Builders",
    "wof:placetype":"venue"
},
  "geometry": {"coordinates":[-93.03555900000001,45.076611],"type":"Point"}
}