{
  "type": "Feature",
  "properties": {
    "iso:country":"US",
    "sg:address":"15706 535th Ave",
    "sg:city":"Austin",
    "sg:phone":"+1 507 437 7002",
    "sg:postcode":"55912",
    "sg:province":"MN",
    "sg:tags":[
        "farm"
    ],
    "wof:name":"Everett C Hansen",
    "wof:placetype":"venue"
},
  "geometry": {"coordinates":[-92.979432,43.577605],"type":"Point"}
}