{
  "type": "Feature",
  "properties": {
    "iso:country":"US",
    "sg:address":"400 2nd Ave N",
    "sg:city":"Sartell",
    "sg:classifiers":[
        {
            "category":"Recreation",
            "type":"Entertainment"
        }
    ],
    "sg:phone":"+1 320 230 5484",
    "sg:postcode":"56377",
    "sg:province":"MN",
    "wof:name":"Glens Guide Service",
    "wof:placetype":"venue"
},
  "geometry": {"coordinates":[-94.206529,45.625524],"type":"Point"}
}