{
  "type": "Feature",
  "properties": {
    "iso:country":"US",
    "sg:address":"7770 23rd St N",
    "sg:city":"Saint Paul",
    "sg:classifiers":[
        {
            "category":"Health Services",
            "subcategory":"Doctor",
            "type":"Services"
        }
    ],
    "sg:phone":"+1 651 779 4516",
    "sg:postcode":"55128",
    "sg:province":"MN",
    "sg:tags":[
        "medical"
    ],
    "wof:name":"Premiere Hlth Care Consultancy",
    "wof:placetype":"venue"
},
  "geometry": {"coordinates":[-92.94797699999999,44.980917],"type":"Point"}
}