{
  "type": "Feature",
  "properties": {
    "iso:country":"US",
    "sg:address":"2601 Cedar Ave S",
    "sg:city":"Minneapolis",
    "sg:classifiers":[
        {
            "category":"Professional",
            "subcategory":"Management & Consulting",
            "type":"Services"
        }
    ],
    "sg:phone":"+1 612 721 5350",
    "sg:postcode":"55407",
    "sg:province":"MN",
    "sg:tags":[
        "business"
    ],
    "wof:name":"River Aide Consulting Services",
    "wof:placetype":"venue"
},
  "geometry": {"coordinates":[-93.24736799999999,44.953758],"type":"Point"}
}