{
  "type": "Feature",
  "properties": {
    "addr:full":"14216 Freeport Trl St Paul MN 55124",
    "addr:housenumber":"14216",
    "addr:postcode":"55124",
    "addr:street":"Freeport Trl",
    "iso:country":"US",
    "sg:address":"14216 Freeport Trl",
    "sg:city":"St Paul",
    "sg:classifiers":[
        {
            "category":"Professional",
            "subcategory":"Management & Consulting",
            "type":"Services"
        }
    ],
    "sg:phone":"+1 952 891 4945",
    "sg:postcode":"55124",
    "sg:province":"MN",
    "sg:tags":[
        "consultant"
    ],
    "wof:name":"C & T Housing Consultants Inc",
    "wof:placetype":"venue"
},
  "geometry": {"coordinates":[-93.203743,44.741675],"type":"Point"}
}