{
  "type": "Feature",
  "properties": {
    "iso:country":"US",
    "sg:address":"11088 60th St NW",
    "sg:city":"Pennock",
    "sg:classifiers":[
        {
            "category":"Building & Trades",
            "subcategory":"Construction",
            "type":"Services"
        }
    ],
    "sg:phone":"+1 320 599 8019",
    "sg:postcode":"56279",
    "sg:province":"MN",
    "sg:tags":[
        "carpentry",
        "contractor"
    ],
    "wof:name":"Nail It Down",
    "wof:placetype":"venue"
},
  "geometry": {"coordinates":[-95.123987,45.227259],"type":"Point"}
}