{
  "type": "Feature",
  "properties": {
    "iso:country":"US",
    "sg:address":"203 River Park Ct",
    "sg:city":"Mankato",
    "sg:classifiers":[
        {
            "category":"Building & Trades",
            "subcategory":"Landscaping Services",
            "type":"Services"
        }
    ],
    "sg:phone":"+1 507 387 2446",
    "sg:postcode":"56001",
    "sg:province":"MN",
    "sg:tags":[
        "tree"
    ],
    "wof:name":"All State Tree Svc",
    "wof:placetype":"venue"
},
  "geometry": {"coordinates":[-93.934428,44.122007],"type":"Point"}
}