{
  "type": "Feature",
  "properties": {
    "addr:full":"301 E Winona St Sanborn MN 56083",
    "addr:housenumber":"301",
    "addr:postcode":"56083",
    "addr:street":"E Winona St",
    "iso:country":"US",
    "sg:address":"301 E Winona St",
    "sg:city":"Sanborn",
    "sg:classifiers":[
        {
            "category":"Organizations",
            "subcategory":"Religious Organization",
            "type":"Services"
        }
    ],
    "sg:phone":"+1 507 648 3754",
    "sg:postcode":"56083",
    "sg:province":"MN",
    "sg:tags":[
        "church"
    ],
    "wof:name":"St Thomas Parish House",
    "wof:placetype":"venue"
},
  "geometry": {"coordinates":[-95.125925,44.20869],"type":"Point"}
}