{
  "type": "Feature",
  "properties": {
    "iso:country":"US",
    "sg:address":"4748 105th Ln NE",
    "sg:city":"Circle Pines",
    "sg:classifiers":[
        {
            "category":"Social Services",
            "subcategory":"Child Care",
            "type":"Services"
        }
    ],
    "sg:phone":"+1 763 780 7982",
    "sg:postcode":"55014",
    "sg:province":"MN",
    "sg:tags":[
        "day",
        "provider"
    ],
    "wof:name":"Day Care",
    "wof:placetype":"venue"
},
  "geometry": {"coordinates":[-93.149033,45.160637],"type":"Point"}
}