{
  "type": "Feature",
  "properties": {
    "iso:country":"US",
    "sg:address":"6314 13th Ave S",
    "sg:city":"Minneapolis",
    "sg:classifiers":[
        {
            "category":"Real Estate",
            "subcategory":"Real Estate Agent",
            "type":"Services"
        }
    ],
    "sg:phone":"+1 612 869 0623",
    "sg:postcode":"55423",
    "sg:province":"MN",
    "wof:name":"Nicki Nunn",
    "wof:placetype":"venue"
},
  "geometry": {"coordinates":[-93.256703,44.888645],"type":"Point"}
}