{
  "type": "Feature",
  "properties": {
    "iso:country":"US",
    "sg:address":"11447 Olive St NW",
    "sg:city":"Coon Rapids",
    "sg:classifiers":[
        {
            "category":"Retail",
            "subcategory":"Repair Shop",
            "type":"Services"
        }
    ],
    "sg:phone":"+1 763 757 9643",
    "sg:postcode":"55448",
    "sg:province":"MN",
    "sg:tags":[
        "equipment",
        "establishment",
        "taxidermist"
    ],
    "wof:name":"Rohde's North Bound Taxidermy",
    "wof:placetype":"venue"
},
  "geometry": {"coordinates":[-93.286751,45.175116],"type":"Point"}
}