{
  "type": "Feature",
  "properties": {
    "iso:country":"US",
    "sg:address":"5722 Homestead Rd",
    "sg:city":"Duluth",
    "sg:classifiers":[
        {
            "category":"Professional",
            "subcategory":"Engineering",
            "type":"Services"
        }
    ],
    "sg:phone":"+1 218 525 5210",
    "sg:postcode":"55804",
    "sg:province":"MN",
    "sg:tags":[
        "general",
        "contractor"
    ],
    "wof:name":"Arrowhead Product Dev Inc",
    "wof:placetype":"venue"
},
  "geometry": {"coordinates":[-91.847027,46.927258],"type":"Point"}
}