{
  "type": "Feature",
  "properties": {
    "addr:full":"100 W Lake St Chisholm MN 55719",
    "addr:housenumber":"100",
    "addr:postcode":"55719",
    "addr:street":"W Lake St",
    "iso:country":"US",
    "sg:address":"100 W Lake St",
    "sg:city":"Chisholm",
    "sg:classifiers":[
        {
            "category":"Food & Beverages",
            "subcategory":"Groceries & Convenience Stores",
            "type":"Retail Goods"
        }
    ],
    "sg:phone":"+1 218 254 3100",
    "sg:postcode":"55719",
    "sg:province":"MN",
    "wof:name":"Freedom Valu Ctr",
    "wof:placetype":"venue"
},
  "geometry": {"coordinates":[-92.88199400000001,47.48916],"type":"Point"}
}