{
  "type": "Feature",
  "properties": {
    "addr:full":"3959 2nd St S Saint Cloud MN 56301",
    "addr:housenumber":"3959",
    "addr:postcode":"56301",
    "addr:street":"2Nd St S",
    "iso:country":"US",
    "sg:address":"3959 2nd St S",
    "sg:city":"Saint Cloud",
    "sg:classifiers":[
        {
            "category":"Home & Garden",
            "subcategory":"Furniture",
            "type":"Retail Goods"
        }
    ],
    "sg:phone":"+1 320 259 0005",
    "sg:postcode":"56301",
    "sg:province":"MN",
    "wof:name":"Mattress Giant Corporation",
    "wof:placetype":"venue"
},
  "geometry": {"coordinates":[-94.20699399999999,45.549662],"type":"Point"}
}