{
  "type": "Feature",
  "properties": {
    "iso:country":"US",
    "sg:address":"813 2nd St NW",
    "sg:city":"Baudette",
    "sg:classifiers":[
        {
            "category":"Coffee & Tea",
            "type":"Food & Drink"
        },
        {
            "category":"Restaurant",
            "type":"Food & Drink"
        }
    ],
    "sg:phone":"+1 218 634 9807",
    "sg:postcode":"56623",
    "sg:province":"MN",
    "sg:tags":[
        "espresso"
    ],
    "wof:name":"Northlake Cafe",
    "wof:placetype":"venue"
},
  "geometry": {"coordinates":[-94.613074,48.714359],"type":"Point"}
}