{
  "type": "Feature",
  "properties": {
    "addr:full":"8870 Excelsior Blvd Hopkins MN 55343",
    "addr:housenumber":"8870",
    "addr:postcode":"55343",
    "addr:street":"Excelsior Blvd",
    "iso:country":"US",
    "sg:address":"8870 Excelsior Blvd",
    "sg:city":"Hopkins",
    "sg:classifiers":[
        {
            "category":"Retail",
            "subcategory":"Veterinary Services",
            "type":"Services"
        }
    ],
    "sg:phone":"+1 952 935 5566",
    "sg:postcode":"55343",
    "sg:province":"MN",
    "sg:tags":[
        "clinic",
        "veterinarian"
    ],
    "wof:name":"Hopkins Pet Hospital",
    "wof:placetype":"venue"
},
  "geometry": {"coordinates":[-93.39151,44.924842],"type":"Point"}
}