{
  "type": "Feature",
  "properties": {
    "iso:country":"US",
    "sg:address":"4618 Parkridge Dr",
    "sg:city":"Saint Paul",
    "sg:classifiers":[
        {
            "category":"Shopping",
            "subcategory":"Gifts & Souvenirs",
            "type":"Retail Goods"
        }
    ],
    "sg:phone":"+1 651 452 4916",
    "sg:postcode":"55123",
    "sg:province":"MN",
    "wof:name":"Gold Leaf Gifts",
    "wof:placetype":"venue"
},
  "geometry": {"coordinates":[-93.155913,44.788147],"type":"Point"}
}