{
  "type": "Feature",
  "properties": {
    "iso:country":"US",
    "sg:address":"203 1st St W",
    "sg:city":"Canby",
    "sg:classifiers":[
        {
            "category":"Wholesale",
            "subcategory":"Farm Supplies",
            "type":"Manufacturing & Wholesale Goods"
        },
        {
            "category":"Shopping",
            "subcategory":"Pets & Pet Supplies",
            "type":"Retail Goods"
        }
    ],
    "sg:phone":"+1 507 223 7236",
    "sg:postcode":"56220",
    "sg:province":"MN",
    "sg:tags":[
        "feed",
        "concentrate",
        "supplement",
        "grain",
        "elevator"
    ],
    "sg:website":"http://www.cfgrain.com",
    "wof:name":"Canby Farmers Grain Co",
    "wof:placetype":"venue"
},
  "geometry": {"coordinates":[-96.277619,44.7095],"type":"Point"}
}