{
  "type": "Feature",
  "properties": {
    "addr:full":"740 110th Ave SE Murdock MN 56271",
    "addr:housenumber":"740",
    "addr:postcode":"56271",
    "addr:street":"110Th Ave Se",
    "iso:country":"US",
    "sg:address":"740 110th Ave SE",
    "sg:city":"Murdock",
    "sg:phone":"+1 320 875 2026",
    "sg:postcode":"56271",
    "sg:province":"MN",
    "sg:tags":[
        "farm",
        "corn",
        "soybean"
    ],
    "wof:name":"Rod Yost",
    "wof:placetype":"venue"
},
  "geometry": {"coordinates":[-95.389523,45.217652],"type":"Point"}
}