{
  "type": "Feature",
  "properties": {
    "addr:full":"332 Farmington Ave SE Buffalo MN 55313",
    "addr:housenumber":"332",
    "addr:postcode":"55313",
    "addr:street":"Farmington Ave Se",
    "iso:country":"US",
    "sg:address":"332 Farmington Ave SE",
    "sg:city":"Buffalo",
    "sg:classifiers":[
        {
            "category":"Mining & Drilling",
            "type":"Manufacturing & Wholesale Goods"
        }
    ],
    "sg:phone":"+1 763 684 0612",
    "sg:postcode":"55313",
    "sg:province":"MN",
    "sg:tags":[
        "ore",
        "silver"
    ],
    "wof:name":"Silver Recovery of Minn",
    "wof:placetype":"venue"
},
  "geometry": {"coordinates":[-93.77602,45.146374],"type":"Point"}
}