{
  "type": "Feature",
  "properties": {
    "addr:full":"1001 Timberlake Rd Fairmont MN 56031",
    "addr:housenumber":"1001",
    "addr:postcode":"56031",
    "addr:street":"Timberlake Rd",
    "iso:country":"US",
    "sg:address":"1001 Timberlake Rd",
    "sg:city":"Fairmont",
    "sg:classifiers":[
        {
            "category":"Manufacturing",
            "subcategory":"Rubber & Plastics",
            "type":"Manufacturing & Wholesale Goods"
        }
    ],
    "sg:phone":"+1 507 238 4791",
    "sg:postcode":"56031",
    "sg:province":"MN",
    "sg:tags":[
        "pipe",
        "material",
        "mfg"
    ],
    "wof:name":"Hancor Inc",
    "wof:placetype":"venue"
},
  "geometry": {"coordinates":[-94.51058500000001,43.662943],"type":"Point"}
}