{
  "type": "Feature",
  "properties": {
    "addr:full":"7245 Pontiac Cir Chanhassen MN 55317",
    "addr:housenumber":"7245",
    "addr:postcode":"55317",
    "addr:street":"Pontiac Cir",
    "iso:country":"US",
    "sg:address":"7245 Pontiac Cir",
    "sg:city":"Chanhassen",
    "sg:classifiers":[
        {
            "category":"Building & Trades",
            "subcategory":"Locksmith",
            "type":"Services"
        }
    ],
    "sg:phone":"+1 952 562 0075",
    "sg:postcode":"55317",
    "sg:province":"MN",
    "sg:tags":[
        "key"
    ],
    "wof:name":"Aaland 24 Hour Locksmith",
    "wof:placetype":"venue"
},
  "geometry": {"coordinates":[-93.548427,44.873932],"type":"Point"}
}