{
  "type": "Feature",
  "properties": {
    "iso:country":"US",
    "sg:address":"1275 Hewitt Ave",
    "sg:city":"St Paul",
    "sg:classifiers":[
        {
            "category":"Wholesale",
            "subcategory":"Machinery & Supplies",
            "type":"Manufacturing & Wholesale Goods"
        },
        {
            "category":"Wholesale",
            "subcategory":"Non-durable Goods",
            "type":"Manufacturing & Wholesale Goods"
        }
    ],
    "sg:phone":"+1 651 641 0836",
    "sg:postcode":"55104",
    "sg:province":"MN",
    "sg:tags":[
        "establishment",
        "carnival"
    ],
    "wof:name":"Carnival Time Equipment Rental",
    "wof:placetype":"venue"
},
  "geometry": {"coordinates":[-93.15258300000001,44.966644],"type":"Point"}
}