{
  "type": "Feature",
  "properties": {
    "addr:full":"4825 Pleasant Ave S Minneapolis MN 55419",
    "addr:housenumber":"4825",
    "addr:postcode":"55419",
    "addr:street":"Pleasant Ave S",
    "iso:country":"US",
    "sg:address":"4825 Pleasant Ave S",
    "sg:city":"Minneapolis",
    "sg:classifiers":[
        {
            "category":"Real Estate",
            "subcategory":"Real Estate Agent",
            "type":"Services"
        }
    ],
    "sg:phone":"+1 612 861 1494",
    "sg:postcode":"55419",
    "sg:province":"MN",
    "wof:name":"Medallion Realty",
    "wof:placetype":"venue"
},
  "geometry": {"coordinates":[-93.283062,44.915692],"type":"Point"}
}