{
  "type": "Feature",
  "properties": {
    "iso:country":"US",
    "sg:address":"5933 Westcliffe Pl",
    "sg:city":"St Cloud",
    "sg:classifiers":[
        {
            "category":"Personal",
            "subcategory":"Beauty Salon",
            "type":"Services"
        }
    ],
    "sg:phone":"+1 320 253 3875",
    "sg:postcode":"56303",
    "sg:province":"MN",
    "wof:name":"Sandi's Styling Salon",
    "wof:placetype":"venue"
},
  "geometry": {"coordinates":[-94.23172700000001,45.575975],"type":"Point"}
}