{
  "type": "Feature",
  "properties": {
    "addr:full":"403 N 1st St Montevideo MN 56265",
    "addr:housenumber":"403",
    "addr:postcode":"56265",
    "addr:street":"N 1St St",
    "iso:country":"US",
    "sg:address":"403 N 1st St",
    "sg:city":"Montevideo",
    "sg:classifiers":[
        {
            "category":"Personal",
            "subcategory":"Beauty Salon",
            "type":"Services"
        }
    ],
    "sg:phone":"+1 320 269 5518",
    "sg:postcode":"56265",
    "sg:province":"MN",
    "sg:tags":[
        "shop"
    ],
    "wof:name":"Bobs Olde-Tyme Barber Shoppe",
    "wof:placetype":"venue"
},
  "geometry": {"coordinates":[-95.725279,44.94852],"type":"Point"}
}