{
  "type": "Feature",
  "properties": {
    "addr:full":"835 2nd Ave NW New Brighton MN 55112",
    "addr:housenumber":"835",
    "addr:postcode":"55112",
    "addr:street":"2Nd Ave Nw",
    "iso:country":"US",
    "sg:address":"835 2nd Ave NW",
    "sg:city":"New Brighton",
    "sg:classifiers":[
        {
            "category":"Building & Trades",
            "subcategory":"Construction",
            "type":"Services"
        }
    ],
    "sg:phone":"+1 651 633 2942",
    "sg:postcode":"55112",
    "sg:province":"MN",
    "sg:tags":[
        "company"
    ],
    "wof:name":"Hagman Construction Icn",
    "wof:placetype":"venue"
},
  "geometry": {"coordinates":[-93.18931000000001,45.064658],"type":"Point"}
}