{
  "type": "Feature",
  "properties": {
    "iso:country":"US",
    "sg:address":"14091 Co Rd 106",
    "sg:city":"Baxter",
    "sg:classifiers":[
        {
            "category":"Health Services",
            "subcategory":"Doctor",
            "type":"Services"
        }
    ],
    "sg:phone":"+1 218 829 4207",
    "sg:postcode":"56482",
    "sg:province":"MN",
    "sg:tags":[
        "dentist"
    ],
    "wof:name":"Randahl B Hoghaug DDS",
    "wof:placetype":"venue"
},
  "geometry": {"coordinates":[-95.072711,46.412145],"type":"Point"}
}