{
  "type": "Feature",
  "properties": {
    "iso:country":"US",
    "sg:address":"2080 Eaglewood Ln",
    "sg:city":"Shakopee",
    "sg:classifiers":[
        {
            "category":"Building & Trades",
            "subcategory":"Pest Control",
            "type":"Services"
        }
    ],
    "sg:phone":"+1 952 403 9223",
    "sg:postcode":"55379",
    "sg:province":"MN",
    "wof:name":"Suburban Wildlife Control",
    "wof:placetype":"venue"
},
  "geometry": {"coordinates":[-93.49316399999999,44.727104],"type":"Point"}
}