{
  "type": "Feature",
  "properties": {
    "iso:country":"US",
    "sg:address":"103 W 61st St",
    "sg:city":"Minneapolis",
    "sg:classifiers":[
        {
            "category":"Building & Trades",
            "subcategory":"Cleaning & Sanitation",
            "type":"Services"
        }
    ],
    "sg:phone":"+1 612 798 5136",
    "sg:postcode":"55419",
    "sg:province":"MN",
    "sg:tags":[
        "maintenance"
    ],
    "wof:name":"Andrews Cleaning",
    "wof:placetype":"venue"
},
  "geometry": {"coordinates":[-93.280012,44.892272],"type":"Point"}
}