{
  "type": "Feature",
  "properties": {
    "iso:country":"US",
    "sg:address":"1205 2nd Ave NW",
    "sg:city":"Stewartville",
    "sg:classifiers":[
        {
            "category":"Wholesale",
            "subcategory":"Machinery & Supplies",
            "type":"Manufacturing & Wholesale Goods"
        }
    ],
    "sg:phone":"+1 507 288 9204",
    "sg:postcode":"55976",
    "sg:province":"MN",
    "sg:tags":[
        "equipment",
        "station"
    ],
    "sg:website":"www.rochpetro.com",
    "wof:name":"Rochester Petroleum Equipment",
    "wof:placetype":"venue"
},
  "geometry": {"coordinates":[-92.489991,43.864523],"type":"Point"}
}