{
  "type": "Feature",
  "properties": {
    "addr:full":"3120 Prow Ln NW Rochester MN 55901",
    "addr:housenumber":"3120",
    "addr:postcode":"55901",
    "addr:street":"Prow Ln Nw",
    "iso:country":"US",
    "sg:address":"3120 Prow Ln NW",
    "sg:city":"Rochester",
    "sg:classifiers":[
        {
            "category":"Transit Center",
            "subcategory":"Freight",
            "type":"Transportation"
        },
        {
            "category":"Freight",
            "type":"Transportation"
        }
    ],
    "sg:phone":"+1 507 289 9902",
    "sg:postcode":"55901",
    "sg:province":"MN",
    "sg:tags":[
        "local",
        "trucking-motor",
        "trucking"
    ],
    "wof:name":"Waltco, Inc.",
    "wof:placetype":"venue"
},
  "geometry": {"coordinates":[-92.52000200000001,44.055982],"type":"Point"}
}