{
  "type": "Feature",
  "properties": {
    "addr:full":"6560 168th St W Rosemount MN 55068",
    "addr:housenumber":"6560",
    "addr:postcode":"55068",
    "addr:street":"168Th St W",
    "iso:country":"US",
    "sg:address":"6560 168th St W",
    "sg:city":"Rosemount",
    "sg:classifiers":[
        {
            "category":"Retail",
            "subcategory":"Laundry & Dry Cleaning",
            "type":"Services"
        }
    ],
    "sg:phone":"+1 952 891 3022",
    "sg:postcode":"55068",
    "sg:province":"MN",
    "sg:tags":[
        "cleaner",
        "rug",
        "carpet"
    ],
    "sg:website":"www.commercialsteamteam.com",
    "wof:name":"Commercial Steam Team",
    "wof:placetype":"venue"
},
  "geometry": {"coordinates":[-93.19899700000001,44.707001],"type":"Point"}
}