{
  "type": "Feature",
  "properties": {
    "addr:full":"18844 Easton Ave Farmington MN 55024",
    "addr:housenumber":"18844",
    "addr:postcode":"55024",
    "addr:street":"Easton Ave",
    "iso:country":"US",
    "sg:address":"18844 Easton Ave",
    "sg:city":"Farmington",
    "sg:classifiers":[
        {
            "category":"Manufacturing",
            "subcategory":"Food",
            "type":"Manufacturing & Wholesale Goods"
        }
    ],
    "sg:phone":"+1 651 460 3421",
    "sg:postcode":"55024",
    "sg:province":"MN",
    "sg:tags":[
        "canned",
        "mfg"
    ],
    "wof:name":"Amerra",
    "wof:placetype":"venue"
},
  "geometry": {"coordinates":[-93.167334,44.676366],"type":"Point"}
}