{
  "type": "Feature",
  "properties": {
    "addr:full":"21144 Malibu Ave Prior Lake MN 55372",
    "addr:housenumber":"21144",
    "addr:postcode":"55372",
    "addr:street":"Malibu Ave",
    "iso:country":"US",
    "sg:address":"21144 Malibu Ave",
    "sg:city":"Prior Lake",
    "sg:classifiers":[
        {
            "category":"Building & Trades",
            "subcategory":"Cleaning & Sanitation",
            "type":"Services"
        }
    ],
    "sg:phone":"+1 952 492 7777",
    "sg:postcode":"55372",
    "sg:province":"MN",
    "wof:name":"Exterior Building Svc Inc",
    "wof:placetype":"venue"
},
  "geometry": {"coordinates":[-93.47045199999999,44.641851],"type":"Point"}
}