{
  "type": "Feature",
  "properties": {
    "iso:country":"US",
    "sg:address":"16681 Garnet St NW",
    "sg:city":"Anoka",
    "sg:classifiers":[
        {
            "category":"Social Services",
            "subcategory":"Child Care",
            "type":"Services"
        }
    ],
    "sg:phone":"+1 763 753 1373",
    "sg:postcode":"55303",
    "sg:province":"MN",
    "sg:tags":[
        "day"
    ],
    "wof:name":"Kaleidoscope Learning Center",
    "wof:placetype":"venue"
},
  "geometry": {"coordinates":[-93.44122299999999,45.273555],"type":"Point"}
}