{
  "type": "Feature",
  "properties": {
    "addr:full":"2543 62nd St NW Maple Lake MN 55358",
    "addr:housenumber":"2543",
    "addr:postcode":"55358",
    "addr:street":"62Nd St Nw",
    "iso:country":"US",
    "sg:address":"2543 62nd St NW",
    "sg:city":"Maple Lake",
    "sg:classifiers":[
        {
            "category":"Building & Trades",
            "subcategory":"Electrical",
            "type":"Services"
        }
    ],
    "sg:phone":"+1 320 963 3239",
    "sg:postcode":"55358",
    "sg:province":"MN",
    "sg:tags":[
        "electric",
        "contractor"
    ],
    "wof:name":"Lebrun Electric",
    "wof:placetype":"venue"
},
  "geometry": {"coordinates":[-93.945375,45.240343],"type":"Point"}
}