{
  "type": "Feature",
  "properties": {
    "addr:full":"948 Birch St Circle Pines MN 55014",
    "addr:housenumber":"948",
    "addr:postcode":"55014",
    "addr:street":"Birch St",
    "iso:country":"US",
    "sg:address":"948 Birch St",
    "sg:city":"Circle Pines",
    "sg:classifiers":[
        {
            "category":"Social Services",
            "subcategory":"Child Care",
            "type":"Services"
        }
    ],
    "sg:phone":"+1 651 490 5607",
    "sg:postcode":"55014",
    "sg:province":"MN",
    "sg:tags":[
        "day",
        "provider"
    ],
    "wof:name":"Kay M Phillips",
    "wof:placetype":"venue"
},
  "geometry": {"coordinates":[-93.094391,45.145728],"type":"Point"}
}