{
  "type": "Feature",
  "properties": {
    "addr:full":"10609 Town Rd 34 Mizpah MN 56660",
    "addr:housenumber":"10609;34",
    "addr:postcode":"56660",
    "addr:street":"Town Rd",
    "iso:country":"US",
    "sg:address":"10609 Town Rd 34",
    "sg:city":"Mizpah",
    "sg:classifiers":[
        {
            "category":"Organizations",
            "subcategory":"Religious Organization",
            "type":"Services"
        }
    ],
    "sg:phone":"+1 218 897 5966",
    "sg:postcode":"56660",
    "sg:province":"MN",
    "sg:tags":[
        "church"
    ],
    "sg:website":"www.gemmellcommunitychurch.org",
    "wof:name":"Gemmell Community Church",
    "wof:placetype":"venue"
},
  "geometry": {"coordinates":[-94.12641600000001,47.971925],"type":"Point"}
}