{
  "type": "Feature",
  "properties": {
    "iso:country":"US",
    "sg:address":"500 Southcross Dr W",
    "sg:city":"Burnsville",
    "sg:classifiers":[
        {
            "category":"Autos & Motor Vehicles",
            "subcategory":"Fuel & Gas Station",
            "type":"Retail Goods"
        }
    ],
    "sg:phone":"+1 952 892 1799",
    "sg:postcode":"55306",
    "sg:province":"MN",
    "sg:tags":[
        "grocery",
        "station",
        "gasoline"
    ],
    "wof:name":"Amoco",
    "wof:placetype":"venue"
},
  "geometry": {"coordinates":[-93.28765799999999,44.738257],"type":"Point"}
}