{
  "type": "Feature",
  "properties": {
    "iso:country":"US",
    "sg:address":"1604 Frost Ave",
    "sg:city":"St Paul",
    "sg:classifiers":[
        {
            "category":"Professional",
            "subcategory":"Business Services",
            "type":"Services"
        }
    ],
    "sg:phone":"+1 651 770 3270",
    "sg:postcode":"55109",
    "sg:province":"MN",
    "sg:tags":[
        "recording",
        "studio"
    ],
    "sg:website":"www.naturalsoundstudio.com",
    "wof:name":"Natural Sound Recording Studio",
    "wof:placetype":"venue"
},
  "geometry": {"coordinates":[-93.03279999999999,44.999112],"type":"Point"}
}