{
  "type": "Feature",
  "properties": {
    "iso:country":"US",
    "sg:address":"150 S Eva St",
    "sg:city":"Saint Paul",
    "sg:classifiers":[
        {
            "category":"Retail",
            "subcategory":"Auto Repair",
            "type":"Services"
        }
    ],
    "sg:phone":"+1 952 894 3700",
    "sg:postcode":"55107",
    "sg:province":"MN",
    "sg:tags":[
        "glass",
        "replacement"
    ],
    "wof:name":"Auto Glass Minnesota Inc",
    "wof:placetype":"venue"
},
  "geometry": {"coordinates":[-93.08131400000001,44.941685],"type":"Point"}
}