{
  "type": "Feature",
  "properties": {
    "addr:full":"5952 Large Ave NE Albertville MN 55301",
    "addr:housenumber":"5952",
    "addr:postcode":"55301",
    "addr:street":"Large Ave Ne",
    "iso:country":"US",
    "sg:address":"5952 Large Ave NE",
    "sg:city":"Albertville",
    "sg:classifiers":[
        {
            "category":"Restaurant",
            "type":"Food & Drink"
        }
    ],
    "sg:phone":"+1 763 497 4400",
    "sg:postcode":"55301",
    "sg:province":"MN",
    "sg:tags":[
        "pizza"
    ],
    "wof:name":"Pats 66 Hot Stuff Pizza",
    "wof:placetype":"venue"
},
  "geometry": {"coordinates":[-93.652451,45.237768],"type":"Point"}
}