{
  "type": "Feature",
  "properties": {
    "addr:full":"51954 200th St Lake Crystal MN 56055",
    "addr:housenumber":"51954",
    "addr:postcode":"56055",
    "addr:street":"200Th St",
    "iso:country":"US",
    "sg:address":"51954 200th St",
    "sg:city":"Lake Crystal",
    "sg:classifiers":[
        {
            "category":"Building & Trades",
            "subcategory":"Construction",
            "type":"Services"
        }
    ],
    "sg:phone":"+1 507 726 6065",
    "sg:postcode":"56055",
    "sg:province":"MN",
    "sg:tags":[
        "concrete",
        "contractor"
    ],
    "wof:name":"Ullrich Construction",
    "wof:placetype":"venue"
},
  "geometry": {"coordinates":[-94.18059,44.12305],"type":"Point"}
}