{
  "type": "Feature",
  "properties": {
    "addr:full":"Cedar & 147th Saint Paul MN 55124",
    "addr:postcode":"55124",
    "iso:country":"US",
    "sg:address":"Cedar & 147th",
    "sg:city":"Saint Paul",
    "sg:classifiers":[
        {
            "category":"Autos & Motor Vehicles",
            "subcategory":"Fuel & Gas Station",
            "type":"Retail Goods"
        },
        {
            "category":"Retail",
            "subcategory":"Auto Repair",
            "type":"Services"
        }
    ],
    "sg:phone":"+1 952 432 5200",
    "sg:postcode":"55124",
    "sg:province":"MN",
    "wof:name":"Cedar Avenue Tire & Auto",
    "wof:placetype":"venue"
},
  "geometry": {"coordinates":[-93.210503,44.744999],"type":"Point"}
}