{
  "type": "Feature",
  "properties": {
    "iso:country":"US",
    "sg:address":"3850 Hidden Way NE",
    "sg:city":"Rochester",
    "sg:classifiers":[
        {
            "category":"Health Services",
            "subcategory":"Doctor",
            "type":"Services"
        }
    ],
    "sg:phone":"+1 507 255 6449",
    "sg:postcode":"55906",
    "sg:province":"MN",
    "sg:tags":[
        "consulting"
    ],
    "wof:name":"Jensen Md Michael Dennis",
    "wof:placetype":"venue"
},
  "geometry": {"coordinates":[-92.402869,44.063484],"type":"Point"}
}