{
  "type": "Feature",
  "properties": {
    "addr:full":"1086 13th Ave SE Minneapolis MN 55414",
    "addr:housenumber":"1086",
    "addr:postcode":"55414",
    "addr:street":"13Th Ave Se",
    "iso:country":"US",
    "sg:address":"1086 13th Ave SE",
    "sg:city":"Minneapolis",
    "sg:classifiers":[
        {
            "category":"Arts & Performance",
            "subcategory":"Theater",
            "type":"Entertainment"
        }
    ],
    "sg:phone":"+1 612 379 9611",
    "sg:postcode":"55414",
    "sg:province":"MN",
    "sg:tags":[
        "group"
    ],
    "wof:name":"Puppet Forge",
    "wof:placetype":"venue"
},
  "geometry": {"coordinates":[-93.233238,44.990682],"type":"Point"}
}