{
  "type": "Feature",
  "properties": {
    "addr:full":"55 Franklin St Winona MN 55987",
    "addr:housenumber":"55",
    "addr:postcode":"55987",
    "addr:street":"Franklin St",
    "iso:country":"US",
    "sg:address":"55 Franklin St",
    "sg:city":"Winona",
    "sg:classifiers":[
        {
            "category":"Manufacturing",
            "subcategory":"Pet Food",
            "type":"Manufacturing & Wholesale Goods"
        },
        {
            "category":"Wholesale",
            "subcategory":"Groceries",
            "type":"Manufacturing & Wholesale Goods"
        }
    ],
    "sg:phone":"+1 507 452 1770",
    "sg:postcode":"55987",
    "sg:province":"MN",
    "sg:tags":[
        "flour",
        "mill",
        "mfg"
    ],
    "sg:website":"http://www.bsm.com",
    "wof:name":"Bay State Milling Company",
    "wof:placetype":"venue"
},
  "geometry": {"coordinates":[-91.630314,44.05241],"type":"Point"}
}