{
  "type": "Feature",
  "properties": {
    "addr:full":"725 Tower Dr Hamel MN 55340",
    "addr:housenumber":"725",
    "addr:postcode":"55340",
    "addr:street":"Tower Dr Hamel",
    "iso:country":"US",
    "sg:address":"725 Tower Dr",
    "sg:city":"Hamel",
    "sg:classifiers":[
        {
            "category":"Building & Trades",
            "subcategory":"Plumbing",
            "type":"Services"
        }
    ],
    "sg:phone":"+1 763 478 8950",
    "sg:postcode":"55340",
    "sg:province":"MN",
    "sg:tags":[
        "contractor"
    ],
    "wof:name":"Action Autmtc Fire Protection",
    "wof:placetype":"venue"
},
  "geometry": {"coordinates":[-93.539834,45.04426],"type":"Point"}
}