{
  "type": "Feature",
  "properties": {
    "addr:full":"209 S High St Lake City MN 55041",
    "addr:housenumber":"209",
    "addr:postcode":"55041",
    "addr:street":"S High St",
    "iso:country":"US",
    "sg:address":"209 S High St",
    "sg:city":"Lake City",
    "sg:classifiers":[
        {
            "category":"Government",
            "subcategory":"Office",
            "type":"Public Place"
        }
    ],
    "sg:phone":"+1 651 345 3030",
    "sg:postcode":"55041",
    "sg:province":"MN",
    "sg:tags":[
        "civil",
        "defense",
        "agency"
    ],
    "wof:name":"Lake City Emergency Management",
    "wof:placetype":"venue"
},
  "geometry": {"coordinates":[-92.266353,44.44806],"type":"Point"}
}