{
  "type": "Feature",
  "properties": {
    "iso:country":"US",
    "sg:address":"3381 Gorham Ave",
    "sg:city":"Minneapolis",
    "sg:classifiers":[
        {
            "category":"Health Services",
            "subcategory":"Doctor",
            "type":"Services"
        }
    ],
    "sg:phone":"+1 612 728 1983",
    "sg:postcode":"55426",
    "sg:province":"MN",
    "sg:tags":[
        "medical"
    ],
    "wof:name":"Thomas Tibbetts",
    "wof:placetype":"venue"
},
  "geometry": {"coordinates":[-93.366303,44.939889],"type":"Point"}
}