{
  "type": "Feature",
  "properties": {
    "addr:full":"1080 Hwy 110 Mendota Heights MN 55120",
    "addr:housenumber":"1080",
    "addr:postcode":"55120",
    "addr:street":"Hwy 110",
    "iso:country":"US",
    "sg:address":"1080 Hwy 110",
    "sg:city":"Mendota Heights",
    "sg:classifiers":[
        {
            "category":"Autos & Motor Vehicles",
            "subcategory":"Fuel & Gas Station",
            "type":"Retail Goods"
        }
    ],
    "sg:phone":"+1 651 905 0710",
    "sg:postcode":"55120",
    "sg:province":"MN",
    "sg:tags":[
        "oil"
    ],
    "wof:name":"Super America",
    "wof:placetype":"venue"
},
  "geometry": {"coordinates":[-93.14647600000001,44.88356],"type":"Point"}
}