{
  "type": "Feature",
  "properties": {
    "addr:full":"211 1st St SE Little Falls MN 56345",
    "addr:housenumber":"211",
    "addr:postcode":"56345",
    "addr:street":"1St St Se",
    "iso:country":"US",
    "sg:address":"211 1st St SE",
    "sg:city":"Little Falls",
    "sg:classifiers":[
        {
            "category":"Professional",
            "subcategory":"Accounting & Tax Preparation",
            "type":"Services"
        }
    ],
    "sg:phone":"+1 320 632 3646",
    "sg:postcode":"56345",
    "sg:province":"MN",
    "sg:tags":[
        "accountant"
    ],
    "wof:name":"Riitters & Scearcy PA",
    "wof:placetype":"venue"
},
  "geometry": {"coordinates":[-94.36279,45.975217],"type":"Point"}
}