{
  "type": "Feature",
  "properties": {
    "iso:country":"US",
    "sg:address":"111 E Kellogg Blvd",
    "sg:city":"St Paul",
    "sg:classifiers":[
        {
            "category":"Organizations",
            "subcategory":"Community Association",
            "type":"Services"
        }
    ],
    "sg:phone":"+1 651 222 2028",
    "sg:postcode":"55105",
    "sg:province":"MN",
    "sg:tags":[
        "club"
    ],
    "wof:name":"Rotary Club",
    "wof:placetype":"venue"
},
  "geometry": {"coordinates":[-93.089921,44.94532],"type":"Point"}
}