{
  "type": "Feature",
  "properties": {
    "addr:full":"20510 Dodd Blvd Lakeville MN 55044",
    "addr:housenumber":"20510",
    "addr:postcode":"55044",
    "addr:street":"Dodd Blvd",
    "iso:country":"US",
    "sg:address":"20510 Dodd Blvd",
    "sg:city":"Lakeville",
    "sg:classifiers":[
        {
            "category":"Building & Trades",
            "subcategory":"Landscaping Services",
            "type":"Services"
        }
    ],
    "sg:phone":"+1 952 469 5138",
    "sg:postcode":"55044",
    "sg:province":"MN",
    "wof:name":"S & S Lawn & Snow Inc",
    "wof:placetype":"venue"
},
  "geometry": {"coordinates":[-93.252792,44.652297],"type":"Point"}
}