{
  "type": "Feature",
  "properties": {
    "addr:full":"1420 London Rd Duluth MN 55805",
    "addr:housenumber":"1420",
    "addr:postcode":"55805",
    "addr:street":"London Rd",
    "iso:country":"US",
    "sg:address":"1420 London Rd",
    "sg:city":"Duluth",
    "sg:classifiers":[
        {
            "category":"Health Services",
            "subcategory":"Health Practitioner",
            "type":"Services"
        }
    ],
    "sg:phone":"+1 218 728 3774",
    "sg:postcode":"55805",
    "sg:province":"MN",
    "sg:tags":[
        "therapist",
        "physical"
    ],
    "wof:name":"Northern Arm & Hand Ctr Inc",
    "wof:placetype":"venue"
},
  "geometry": {"coordinates":[-92.078154,46.799723],"type":"Point"}
}