{
  "type": "Feature",
  "properties": {
    "iso:country":"US",
    "sg:address":"12095 Hanson Blvd NW",
    "sg:city":"Coon Rapids",
    "sg:classifiers":[
        {
            "category":"Food & Beverages",
            "subcategory":"Groceries & Convenience Stores",
            "type":"Retail Goods"
        }
    ],
    "sg:phone":"+1 763 754 3998",
    "sg:postcode":"55433",
    "sg:province":"MN",
    "wof:name":"Oasis Market",
    "wof:placetype":"venue"
},
  "geometry": {"coordinates":[-93.30954699999999,45.189384],"type":"Point"}
}