{
  "type": "Feature",
  "properties": {
    "iso:country":"US",
    "sg:address":"17805 Highway 7",
    "sg:city":"Minnetonka",
    "sg:classifiers":[
        {
            "category":"Restaurant",
            "type":"Food & Drink"
        }
    ],
    "sg:phone":"+1 952 380 0333",
    "sg:postcode":"55345",
    "sg:province":"MN",
    "sg:tags":[
        "pizza"
    ],
    "wof:name":"Prima Pasta Salads Panini and Pizza",
    "wof:placetype":"venue"
},
  "geometry": {"coordinates":[-93.50626,44.912215],"type":"Point"}
}