{
  "type": "Feature",
  "properties": {
    "addr:full":"387 Moose Valley Rd Hovland MN 55606",
    "addr:housenumber":"387",
    "addr:postcode":"55606",
    "addr:street":"Moose Valley Rd",
    "iso:country":"US",
    "sg:address":"387 Moose Valley Rd",
    "sg:city":"Hovland",
    "sg:classifiers":[
        {
            "category":"Building & Trades",
            "subcategory":"Plumbing",
            "type":"Services"
        }
    ],
    "sg:phone":"+1 218 475 2390",
    "sg:postcode":"55606",
    "sg:province":"MN",
    "sg:tags":[
        "contractor"
    ],
    "wof:name":"Jays Heating Cs",
    "wof:placetype":"venue"
},
  "geometry": {"coordinates":[-89.919453,47.888671],"type":"Point"}
}