{
  "type": "Feature",
  "properties": {
    "addr:full":"455 1st Ave NW Blooming Prairie MN 55917",
    "addr:housenumber":"455",
    "addr:postcode":"55917",
    "addr:street":"1St Ave Nw",
    "iso:country":"US",
    "sg:address":"455 1st Ave NW",
    "sg:city":"Blooming Prairie",
    "sg:classifiers":[
        {
            "category":"Wholesale",
            "subcategory":"Construction Materials",
            "type":"Manufacturing & Wholesale Goods"
        },
        {
            "category":"Building & Trades",
            "subcategory":"Construction",
            "type":"Services"
        }
    ],
    "sg:phone":"+1 507 583 2999",
    "sg:postcode":"55917",
    "sg:province":"MN",
    "sg:tags":[
        "excavation",
        "sand",
        "gravel",
        "contractor"
    ],
    "wof:name":"Bishop Excavating Inc",
    "wof:placetype":"venue"
},
  "geometry": {"coordinates":[-93.057034,43.870938],"type":"Point"}
}