{
  "type": "Feature",
  "properties": {
    "addr:full":"217 N 59th Ave W Duluth MN 55807",
    "addr:housenumber":"217",
    "addr:postcode":"55807",
    "addr:street":"N 59Th Ave W",
    "iso:country":"US",
    "sg:address":"217 N 59th Ave W",
    "sg:city":"Duluth",
    "sg:classifiers":[
        {
            "category":"Insurance",
            "subcategory":"Insurance Agent",
            "type":"Services"
        }
    ],
    "sg:phone":"+1 218 624 7730",
    "sg:postcode":"55807",
    "sg:province":"MN",
    "wof:name":"Roman Miller Agency",
    "wof:placetype":"venue"
},
  "geometry": {"coordinates":[-92.172059,46.736071],"type":"Point"}
}