{
  "type": "Feature",
  "properties": {
    "addr:full":"701 Bonner Ct SE Stewartville MN 55976",
    "addr:housenumber":"701",
    "addr:postcode":"55976",
    "addr:street":"Bonner Ct Se",
    "iso:country":"US",
    "sg:address":"701 Bonner Ct SE",
    "sg:city":"Stewartville",
    "sg:classifiers":[
        {
            "category":"Professional",
            "subcategory":"Management & Consulting",
            "type":"Services"
        }
    ],
    "sg:phone":"+1 507 533 6383",
    "sg:postcode":"55976",
    "sg:province":"MN",
    "wof:name":"Willow Bay Management LLC",
    "wof:placetype":"venue"
},
  "geometry": {"coordinates":[-92.47686899999999,43.846859],"type":"Point"}
}