{
  "type": "Feature",
  "properties": {
    "iso:country":"US",
    "sg:address":"208 Dean Rd",
    "sg:city":"Esko",
    "sg:classifiers":[
        {
            "category":"Organizations",
            "subcategory":"Membership Organization",
            "type":"Services"
        }
    ],
    "sg:phone":"+1 218 879 3414",
    "sg:postcode":"55733",
    "sg:province":"MN",
    "wof:name":"Best Monthly Clubs LLC",
    "wof:placetype":"venue"
},
  "geometry": {"coordinates":[-92.36458,46.672826],"type":"Point"}
}