{
  "type": "Feature",
  "properties": {
    "iso:country":"US",
    "sg:address":"5120 Bass Lake Rd",
    "sg:city":"Minneapolis",
    "sg:classifiers":[
        {
            "category":"Food & Beverages",
            "subcategory":"Groceries & Convenience Stores",
            "type":"Retail Goods"
        }
    ],
    "sg:phone":"+1 763 537 0399",
    "sg:postcode":"55429",
    "sg:province":"MN",
    "wof:name":"Crystal Foods Smoke Shop",
    "wof:placetype":"venue"
},
  "geometry": {"coordinates":[-93.346475,45.054047],"type":"Point"}
}