{
  "type": "Feature",
  "properties": {
    "addr:full":"72 Viking Ter Northfield MN 55057",
    "addr:housenumber":"72",
    "addr:postcode":"55057",
    "addr:street":"Viking Ter",
    "iso:country":"US",
    "sg:address":"72 Viking Ter",
    "sg:city":"Northfield",
    "sg:classifiers":[
        {
            "category":"Professional",
            "subcategory":"Computer Services",
            "type":"Services"
        }
    ],
    "sg:phone":"+1 507 645 7110",
    "sg:postcode":"55057",
    "sg:province":"MN",
    "sg:tags":[
        "repair"
    ],
    "wof:name":"Computers Service",
    "wof:placetype":"venue"
},
  "geometry": {"coordinates":[-93.16338,44.469663],"type":"Point"}
}