{
  "type": "Feature",
  "properties": {
    "iso:country":"US",
    "sg:address":"30995 Forest Blvd",
    "sg:city":"Stacy",
    "sg:classifiers":[
        {
            "category":"Autos & Motor Vehicles",
            "subcategory":"Automobile Sales",
            "type":"Retail Goods"
        }
    ],
    "sg:phone":"+1 651 462 0998",
    "sg:postcode":"55079",
    "sg:province":"MN",
    "sg:tags":[
        "used"
    ],
    "wof:name":"Sunrise Auto Sales",
    "wof:placetype":"venue"
},
  "geometry": {"coordinates":[-92.983204,45.395649],"type":"Point"}
}