{
  "type": "Feature",
  "properties": {
    "iso:country":"US",
    "sg:address":"570 N Asbury St",
    "sg:city":"St Paul",
    "sg:classifiers":[
        {
            "category":"Education",
            "subcategory":"Special Training",
            "type":"Public Place"
        }
    ],
    "sg:phone":"+1 651 644 5559",
    "sg:postcode":"55104",
    "sg:province":"MN",
    "sg:tags":[
        "center"
    ],
    "wof:name":"Spiritual & Educational Assoc",
    "wof:placetype":"venue"
},
  "geometry": {"coordinates":[-93.16532100000001,44.957468],"type":"Point"}
}