{
  "type": "Feature",
  "properties": {
    "iso:country":"US",
    "sg:address":"318 E Ashley St",
    "sg:city":"Jackson",
    "sg:classifiers":[
        {
            "category":"Building & Trades",
            "subcategory":"Construction",
            "type":"Services"
        }
    ],
    "sg:phone":"+1 507 847 5710",
    "sg:postcode":"56143",
    "sg:province":"MN",
    "sg:tags":[
        "house"
    ],
    "wof:name":"Four Seasons Sunrooms",
    "wof:placetype":"venue"
},
  "geometry": {"coordinates":[-94.975076,43.62706],"type":"Point"}
}