{
  "type": "Feature",
  "properties": {
    "addr:full":"1332 Lakeview Ave Winona MN 55987",
    "addr:housenumber":"1332",
    "addr:postcode":"55987",
    "addr:street":"Lakeview Ave",
    "iso:country":"US",
    "sg:address":"1332 Lakeview Ave",
    "sg:city":"Winona",
    "sg:classifiers":[
        {
            "category":"Social Services",
            "subcategory":"Child Care",
            "type":"Services"
        }
    ],
    "sg:phone":"+1 507 454 4776",
    "sg:postcode":"55987",
    "sg:province":"MN",
    "sg:tags":[
        "daycare",
        "provider"
    ],
    "wof:name":"Betsy Loucks",
    "wof:placetype":"venue"
},
  "geometry": {"coordinates":[-91.67415,44.044529],"type":"Point"}
}