{
  "type": "Feature",
  "properties": {
    "iso:country":"US",
    "sg:address":"1469 University Ave W",
    "sg:city":"St Paul",
    "sg:classifiers":[
        {
            "category":"Autos & Motor Vehicles",
            "subcategory":"Auto Supplies",
            "type":"Retail Goods"
        }
    ],
    "sg:phone":"+1 651 917 7747",
    "sg:postcode":"55104",
    "sg:province":"MN",
    "sg:tags":[
        "equipment",
        "racing",
        "car",
        "automobile"
    ],
    "wof:name":"Propulshun Auto Sports",
    "wof:placetype":"venue"
},
  "geometry": {"coordinates":[-93.16333299999999,44.955762],"type":"Point"}
}