{
  "type": "Feature",
  "properties": {
    "iso:country":"US",
    "sg:address":"1609 Long Lake Rd",
    "sg:city":"Eveleth",
    "sg:classifiers":[
        {
            "category":"Freight",
            "type":"Transportation"
        }
    ],
    "sg:phone":"+1 218 780 2984",
    "sg:postcode":"55734",
    "sg:province":"MN",
    "sg:tags":[
        "storage"
    ],
    "wof:name":"Laurentian Group",
    "wof:placetype":"venue"
},
  "geometry": {"coordinates":[-92.537758,47.406607],"type":"Point"}
}