{
  "type": "Feature",
  "properties": {
    "addr:full":"3230 Aldrich Ave N Minneapolis MN 55412",
    "addr:housenumber":"3230",
    "addr:postcode":"55412",
    "addr:street":"Aldrich Ave N",
    "iso:country":"US",
    "sg:address":"3230 Aldrich Ave N",
    "sg:city":"Minneapolis",
    "sg:classifiers":[
        {
            "category":"Banks & Credit Unions",
            "subcategory":"Bank",
            "type":"Services"
        }
    ],
    "sg:phone":"+1 612 522 7989",
    "sg:postcode":"55412",
    "sg:province":"MN",
    "sg:tags":[
        "loan",
        "real estate"
    ],
    "wof:name":"North Shore Mortgage Svc",
    "wof:placetype":"venue"
},
  "geometry": {"coordinates":[-93.289351,45.01436],"type":"Point"}
}