{
  "type": "Feature",
  "properties": {
    "addr:full":"716 Oxford St Worthington MN 56187",
    "addr:housenumber":"716",
    "addr:postcode":"56187",
    "addr:street":"Oxford St",
    "iso:country":"US",
    "sg:address":"716 Oxford St",
    "sg:city":"Worthington",
    "sg:classifiers":[
        {
            "category":"Banks & Credit Unions",
            "subcategory":"Investment Brokerage",
            "type":"Services"
        }
    ],
    "sg:phone":"+1 507 376 5759",
    "sg:postcode":"56187",
    "sg:province":"MN",
    "sg:tags":[
        "consultant",
        "planning",
        "financial"
    ],
    "wof:name":"George Nasers Financial Svc",
    "wof:placetype":"venue"
},
  "geometry": {"coordinates":[-95.60458,43.631034],"type":"Point"}
}