{
  "type": "Feature",
  "properties": {
    "addr:full":"14300 Judicial Rd Burnsville MN 55306",
    "addr:postcode":"55306",
    "addr:street":"Judicial Rd",
    "iso:country":"US",
    "sg:address":"14300 Judicial Rd",
    "sg:city":"Burnsville",
    "sg:classifiers":[
        {
            "category":"Manufacturing",
            "subcategory":"Tools & Machinery",
            "type":"Manufacturing & Wholesale Goods"
        }
    ],
    "sg:phone":"+1 952 892 4300",
    "sg:postcode":"55306",
    "sg:province":"MN",
    "sg:tags":[
        "industry",
        "aerospace"
    ],
    "wof:name":"Goodrich Aerospace-Aircraft",
    "wof:placetype":"venue"
},
  "geometry": {"coordinates":[-93.307981,44.739157],"type":"Point"}
}