{
  "type": "Feature",
  "properties": {
    "addr:full":"1608 1st St NW Rochester MN 55901",
    "addr:housenumber":"1608",
    "addr:postcode":"55901",
    "addr:street":"1St St Nw",
    "iso:country":"US",
    "sg:address":"1608 1st St NW",
    "sg:city":"Rochester",
    "sg:classifiers":[
        {
            "category":"Health Services",
            "subcategory":"Optometrist",
            "type":"Services"
        }
    ],
    "sg:phone":"+1 507 282 7121",
    "sg:postcode":"55901",
    "sg:province":"MN",
    "wof:name":"J L Block Od",
    "wof:placetype":"venue"
},
  "geometry": {"coordinates":[-92.486108,44.024263],"type":"Point"}
}