{
  "type": "Feature",
  "properties": {
    "iso:country":"US",
    "sg:address":"21279 Okinawa St NE",
    "sg:city":"Cedar",
    "sg:classifiers":[
        {
            "category":"Autos & Motor Vehicles",
            "subcategory":"Automobile Sales",
            "type":"Retail Goods"
        },
        {
            "category":"Autos & Motor Vehicles",
            "subcategory":"Auto Supplies",
            "type":"Retail Goods"
        },
        {
            "category":"Autos & Motor Vehicles",
            "subcategory":"Recreational Vehicle Sales",
            "type":"Retail Goods"
        }
    ],
    "sg:phone":"+1 612 998 9643",
    "sg:postcode":"55011",
    "sg:province":"MN",
    "sg:tags":[
        "plug",
        "vehicles-sports",
        "atv's",
        "all-terrain",
        "part",
        "snowmobile",
        "spark",
        "utility"
    ],
    "sg:website":"http://www.syntheticperformanceofmn.com",
    "wof:name":"Synthetic Performance",
    "wof:placetype":"venue"
},
  "geometry": {"coordinates":[-93.183651,45.35126],"type":"Point"}
}