{
  "type": "Feature",
  "properties": {
    "iso:country":"US",
    "sg:address":"14630 State Hwy 65",
    "sg:city":"Andover",
    "sg:classifiers":[
        {
            "category":"Health Services",
            "subcategory":"Chiropractor",
            "type":"Services"
        }
    ],
    "sg:phone":"+1 612 987 6666",
    "sg:postcode":"55304",
    "sg:province":"MN",
    "wof:name":"Kragness Chiropractic",
    "wof:placetype":"venue"
},
  "geometry": {"coordinates":[-93.235034,45.23575],"type":"Point"}
}