{
  "type": "Feature",
  "properties": {
    "addr:full":"15265 Galaxie Ave Ste 400 Apple Valley MN 55124",
    "addr:housenumber":"15265",
    "addr:postcode":"55124",
    "addr:street":"Galaxie Ave Ste 400",
    "iso:country":"US",
    "sg:address":"15265 Galaxie Ave Ste 400",
    "sg:city":"Apple Valley",
    "sg:classifiers":[
        {
            "category":"Restaurant",
            "type":"Food & Drink"
        }
    ],
    "sg:phone":"+1 952 431 0610",
    "sg:postcode":"55124",
    "sg:province":"MN",
    "sg:tags":[
        "barbeque"
    ],
    "wof:name":"House of Wing",
    "wof:placetype":"venue"
},
  "geometry": {"coordinates":[-93.208095,44.727625],"type":"Point"}
}