{
  "type": "Feature",
  "properties": {
    "iso:country":"US",
    "sg:address":"1827 44th Ave N",
    "sg:city":"Minneapolis",
    "sg:classifiers":[
        {
            "category":"Organizations",
            "subcategory":"Non-profit Organization",
            "type":"Services"
        }
    ],
    "sg:phone":"+1 612 521 4859",
    "sg:postcode":"55412",
    "sg:province":"MN",
    "sg:tags":[
        "service/non-profit",
        "community"
    ],
    "wof:name":"Southeast Asian Community Council",
    "wof:placetype":"venue"
},
  "geometry": {"coordinates":[-93.302882,45.035303],"type":"Point"}
}