{
  "type": "Feature",
  "properties": {
    "addr:full":"2661 Arcola Ln Wayzata MN 55391",
    "addr:housenumber":"2661",
    "addr:postcode":"55391",
    "addr:street":"Arcola Ln",
    "iso:country":"US",
    "sg:address":"2661 Arcola Ln",
    "sg:city":"Wayzata",
    "sg:classifiers":[
        {
            "category":"Professional",
            "type":"Services"
        }
    ],
    "sg:phone":"+1 952 471 8398",
    "sg:postcode":"55391",
    "sg:province":"MN",
    "wof:name":"L J Martin Inc",
    "wof:placetype":"venue"
},
  "geometry": {"coordinates":[-93.586731,44.940141],"type":"Point"}
}