{
  "type": "Feature",
  "properties": {
    "iso:country":"US",
    "sg:address":"101 1st Ave N",
    "sg:city":"Minneapolis",
    "sg:classifiers":[
        {
            "category":"Building & Trades",
            "subcategory":"Construction",
            "type":"Services"
        }
    ],
    "sg:phone":"+1 763 286 5876",
    "sg:postcode":"55401",
    "sg:province":"MN",
    "sg:tags":[
        "painting",
        "contractor"
    ],
    "wof:name":"Five Star Painting",
    "wof:placetype":"venue"
},
  "geometry": {"coordinates":[-93.26786800000001,44.984566],"type":"Point"}
}