{
  "type": "Feature",
  "properties": {
    "addr:full":"9475 65th Ave Milaca MN 56353",
    "addr:housenumber":"9475",
    "addr:postcode":"56353",
    "addr:street":"65Th Ave",
    "iso:country":"US",
    "sg:address":"9475 65th Ave",
    "sg:city":"Milaca",
    "sg:classifiers":[
        {
            "category":"Shopping",
            "type":"Retail Goods"
        }
    ],
    "sg:phone":"+1 763 389 8801",
    "sg:postcode":"56353",
    "sg:province":"MN",
    "sg:tags":[
        "merchandise"
    ],
    "wof:name":"Royal Nobles Inc",
    "wof:placetype":"venue"
},
  "geometry": {"coordinates":[-93.54379400000001,45.682784],"type":"Point"}
}