{
  "type": "Feature",
  "properties": {
    "addr:full":"5209 Woodlawn Blvd Minneapolis MN 55417",
    "addr:housenumber":"5209",
    "addr:postcode":"55417",
    "addr:street":"Woodlawn Blvd",
    "iso:country":"US",
    "sg:address":"5209 Woodlawn Blvd",
    "sg:city":"Minneapolis",
    "sg:classifiers":[
        {
            "category":"Travel",
            "subcategory":"Campground",
            "type":"Entertainment"
        }
    ],
    "sg:phone":"+1 612 724 3442",
    "sg:postcode":"55417",
    "sg:province":"MN",
    "sg:tags":[
        "trailer"
    ],
    "wof:name":"River Hills Estates",
    "wof:placetype":"venue"
},
  "geometry": {"coordinates":[-93.23632000000001,44.907557],"type":"Point"}
}