{
  "type": "Feature",
  "properties": {
    "addr:full":"10900 Orchard Trl Lakeville MN 55044",
    "addr:housenumber":"10900",
    "addr:postcode":"55044",
    "addr:street":"Orchard Trl",
    "iso:country":"US",
    "sg:address":"10900 Orchard Trl",
    "sg:city":"Lakeville",
    "sg:classifiers":[
        {
            "category":"Home & Garden",
            "subcategory":"Mobile Homes",
            "type":"Retail Goods"
        }
    ],
    "sg:phone":"+1 952 435 6364",
    "sg:postcode":"55044",
    "sg:province":"MN",
    "sg:tags":[
        "commercial",
        "unit"
    ],
    "wof:name":"Space Mobile & Modular Strctr",
    "wof:placetype":"venue"
},
  "geometry": {"coordinates":[-93.28728700000001,44.679254],"type":"Point"}
}