{
  "type": "Feature",
  "properties": {
    "iso:country":"US",
    "sg:address":"8400 Coral Sea St NE",
    "sg:city":"Minneapolis",
    "sg:classifiers":[
        {
            "category":"Professional",
            "type":"Services"
        }
    ],
    "sg:phone":"+1 763 785 1234",
    "sg:postcode":"55449",
    "sg:province":"MN",
    "wof:name":"Medipets",
    "wof:placetype":"venue"
},
  "geometry": {"coordinates":[-93.19883299999999,45.124393],"type":"Point"}
}