{
  "type": "Feature",
  "properties": {
    "addr:full":"2365 Carter Ave Saint Paul MN 55108",
    "addr:housenumber":"2365",
    "addr:postcode":"55108",
    "addr:street":"Carter Ave",
    "iso:country":"US",
    "sg:address":"2365 Carter Ave",
    "sg:city":"Saint Paul",
    "sg:classifiers":[
        {
            "category":"Health Services",
            "subcategory":"Health Practitioner",
            "type":"Services"
        }
    ],
    "sg:phone":"+1 651 917 2611",
    "sg:postcode":"55108",
    "sg:province":"MN",
    "wof:name":"Andrew S Crowley",
    "wof:placetype":"venue"
},
  "geometry": {"coordinates":[-93.198325,44.980072],"type":"Point"}
}