{
  "type": "Feature",
  "properties": {
    "addr:full":"12026 Riverwood Dr Burnsville MN 55337",
    "addr:housenumber":"12026",
    "addr:postcode":"55337",
    "addr:street":"Riverwood Dr",
    "iso:country":"US",
    "sg:address":"12026 Riverwood Dr",
    "sg:city":"Burnsville",
    "sg:classifiers":[
        {
            "category":"Building & Trades",
            "subcategory":"Construction",
            "type":"Services"
        }
    ],
    "sg:phone":"+1 952 890 1650",
    "sg:postcode":"55337",
    "sg:province":"MN",
    "sg:tags":[
        "concrete",
        "masonry",
        "contractor"
    ],
    "wof:name":"Northland Concrete & Masnry Co",
    "wof:placetype":"venue"
},
  "geometry": {"coordinates":[-93.261206,44.787666],"type":"Point"}
}