{
  "type": "Feature",
  "properties": {
    "iso:country":"US",
    "sg:address":"4790 Echo Ct",
    "sg:city":"Faribault",
    "sg:classifiers":[
        {
            "category":"Home & Garden",
            "subcategory":"Building Materials",
            "type":"Retail Goods"
        }
    ],
    "sg:phone":"+1 507 332 4097",
    "sg:postcode":"55021",
    "sg:province":"MN",
    "wof:name":"Esenrich Construction",
    "wof:placetype":"venue"
},
  "geometry": {"coordinates":[-93.361048,44.272744],"type":"Point"}
}