{
  "type": "Feature",
  "properties": {
    "iso:country":"US",
    "sg:address":"3750 Annapolis Ln N",
    "sg:city":"Minneapolis",
    "sg:classifiers":[
        {
            "category":"Manufacturing",
            "subcategory":"Tools & Machinery",
            "type":"Manufacturing & Wholesale Goods"
        }
    ],
    "sg:phone":"+1 763 258 0250",
    "sg:postcode":"55447",
    "sg:province":"MN",
    "sg:tags":[
        "instrument",
        "mfg"
    ],
    "wof:name":"Atritech Inc",
    "wof:placetype":"venue"
},
  "geometry": {"coordinates":[-93.457261,45.025635],"type":"Point"}
}