{
  "type": "Feature",
  "properties": {
    "addr:full":"6600 France Ave S #164 Minneapolis MN 55435",
    "addr:housenumber":"6600",
    "addr:postcode":"55435",
    "addr:street":"France Ave S # 164",
    "iso:country":"US",
    "sg:address":"6600 France Ave S #164",
    "sg:city":"Minneapolis",
    "sg:classifiers":[
        {
            "category":"Food & Beverages",
            "subcategory":"Specialty",
            "type":"Retail Goods"
        },
        {
            "category":"Health Services",
            "subcategory":"Health Practitioner",
            "type":"Services"
        }
    ],
    "sg:phone":"+1 952 920 8644",
    "sg:postcode":"55435",
    "sg:province":"MN",
    "sg:tags":[
        "control",
        "product",
        "reducing",
        "diet",
        "weight"
    ],
    "sg:website":"http://www.vivifyhcgdiet.com",
    "wof:name":"Vivify HCG Weight Loss",
    "wof:placetype":"venue"
},
  "geometry": {"coordinates":[-93.329048,44.88282],"type":"Point"}
}