{
  "type": "Feature",
  "properties": {
    "addr:full":"200 N Broadway Ave Albert Lea MN 56007",
    "addr:housenumber":"200",
    "addr:postcode":"56007",
    "addr:street":"N Broadway Ave",
    "iso:country":"US",
    "sg:address":"200 N Broadway Ave",
    "sg:city":"Albert Lea",
    "sg:classifiers":[
        {
            "category":"Professional",
            "subcategory":"Business Services",
            "type":"Services"
        }
    ],
    "sg:phone":"+1 507 373 0687",
    "sg:postcode":"56007",
    "sg:province":"MN",
    "sg:tags":[
        "auctioneer"
    ],
    "wof:name":"Hugh O'Bryne",
    "wof:placetype":"venue"
},
  "geometry": {"coordinates":[-93.36872700000001,43.651298],"type":"Point"}
}