{
  "type": "Feature",
  "properties": {
    "iso:country":"US",
    "sg:address":"1406 6th Ave N",
    "sg:city":"Saint Cloud",
    "sg:classifiers":[
        {
            "category":"Health Services",
            "subcategory":"Doctor",
            "type":"Services"
        }
    ],
    "sg:phone":"+1 320 255 5777",
    "sg:postcode":"56303",
    "sg:province":"MN",
    "sg:tags":[
        "medical"
    ],
    "wof:name":"Chris K Moellentine MD",
    "wof:placetype":"venue"
},
  "geometry": {"coordinates":[-94.170356,45.57531],"type":"Point"}
}