{
  "type": "Feature",
  "properties": {
    "addr:full":"2501 Horizon Dr Burnsville MN 55337",
    "addr:housenumber":"2501",
    "addr:postcode":"55337",
    "addr:street":"Horizon Dr",
    "iso:country":"US",
    "sg:address":"2501 Horizon Dr",
    "sg:city":"Burnsville",
    "sg:classifiers":[
        {
            "category":"Restaurant",
            "type":"Food & Drink"
        }
    ],
    "sg:phone":"+1 952 808 0068",
    "sg:postcode":"55337",
    "sg:province":"MN",
    "wof:name":"El Loro",
    "wof:placetype":"venue"
},
  "geometry": {"coordinates":[-93.240402,44.792599],"type":"Point"}
}