{
  "type": "Feature",
  "properties": {
    "addr:full":"3900 W River Pkwy Minneapolis MN 55406",
    "addr:housenumber":"3900",
    "addr:postcode":"55406",
    "addr:street":"W River Pkwy",
    "iso:country":"US",
    "sg:address":"3900 W River Pkwy",
    "sg:city":"Minneapolis",
    "sg:classifiers":[
        {
            "category":"Education",
            "subcategory":"School",
            "type":"Public Place"
        }
    ],
    "sg:phone":"+1 612 668 4410",
    "sg:postcode":"55406",
    "sg:province":"MN",
    "sg:tags":[
        "high",
        "middle",
        "elementary"
    ],
    "sg:website":"www.mpls.k12.mn.us",
    "wof:name":"Minneapolis Public Schools",
    "wof:placetype":"venue"
},
  "geometry": {"coordinates":[-93.203003,44.932899],"type":"Point"}
}