{
  "type": "Feature",
  "properties": {
    "addr:full":"1450 W Lake St Minneapolis MN 55408",
    "addr:housenumber":"1450",
    "addr:postcode":"55408",
    "addr:street":"W Lake St",
    "iso:country":"US",
    "sg:address":"1450 W Lake St",
    "sg:city":"Minneapolis",
    "sg:classifiers":[
        {
            "category":"Coffee & Tea",
            "type":"Food & Drink"
        }
    ],
    "sg:menulink":"http://www.allmenus.com/mn/minneapolis/58602-caribou-coffee/menu/",
    "sg:phone":"+1 612 825 6720",
    "sg:postcode":"55408",
    "sg:province":"MN",
    "sg:tags":[
        "american"
    ],
    "wof:name":"Caribou Coffee",
    "wof:placetype":"venue"
},
  "geometry": {"coordinates":[-93.299582,44.948301],"type":"Point"}
}