{
  "type": "Feature",
  "properties": {
    "iso:country":"US",
    "sg:address":"2948 240th Ave",
    "sg:city":"Ada",
    "sg:classifiers":[
        {
            "category":"Place Of Worship",
            "subcategory":"Church",
            "type":"Public Place"
        },
        {
            "category":"Place Of Worship",
            "type":"Public Place"
        }
    ],
    "sg:phone":"+1 218 784 4644",
    "sg:postcode":"56510",
    "sg:province":"MN",
    "sg:tags":[
        "lutheran",
        "america",
        "churches-lutheran",
        "churches-lutheran-evangelical"
    ],
    "wof:name":"St John's Lutheran",
    "wof:placetype":"venue"
},
  "geometry": {"coordinates":[-96.438183,47.354224],"type":"Point"}
}