{
  "type": "Feature",
  "properties": {
    "addr:full":"1015 Snelling Ave S Saint Paul MN 55116",
    "addr:housenumber":"1015",
    "addr:postcode":"55116",
    "addr:street":"Snelling Ave S",
    "iso:country":"US",
    "sg:address":"1015 Snelling Ave S",
    "sg:city":"Saint Paul",
    "sg:classifiers":[
        {
            "category":"Education",
            "subcategory":"School",
            "type":"Public Place"
        }
    ],
    "sg:phone":"+1 651 293 8940",
    "sg:postcode":"55116",
    "sg:province":"MN",
    "wof:name":"Highland Park Senior High School",
    "wof:placetype":"venue"
},
  "geometry": {"coordinates":[-93.166901,44.91],"type":"Point"}
}