{
  "type": "Feature",
  "properties": {
    "addr:full":"4017 Lynn Ave Minneapolis MN 55416",
    "addr:housenumber":"4017",
    "addr:postcode":"55416",
    "addr:street":"Lynn Ave",
    "iso:country":"US",
    "sg:address":"4017 Lynn Ave",
    "sg:city":"Minneapolis",
    "sg:classifiers":[
        {
            "category":"Banks & Credit Unions",
            "subcategory":"Investment Brokerage",
            "type":"Services"
        },
        {
            "category":"Banks & Credit Unions",
            "subcategory":"Bank",
            "type":"Services"
        },
        {
            "category":"Banks & Credit Unions",
            "subcategory":"Financial Services",
            "type":"Services"
        },
        {
            "category":"Insurance",
            "subcategory":"Insurance Agent",
            "type":"Services"
        },
        {
            "category":"Insurance",
            "subcategory":"Life Insurance",
            "type":"Services"
        },
        {
            "category":"Professional",
            "subcategory":"Management & Consulting",
            "type":"Services"
        },
        {
            "category":"Insurance",
            "subcategory":"Hazard Insurance",
            "type":"Services"
        }
    ],
    "sg:phone":"+1 888 335 2088",
    "sg:postcode":"55416",
    "sg:province":"MN",
    "sg:tags":[
        "advisory",
        "mutual",
        "retirement",
        "planner",
        "profit",
        "transfer",
        "sharing",
        "broker",
        "pension",
        "fund",
        "consultant",
        "planning",
        "plan",
        "annuity",
        "bond",
        "counseling",
        "security",
        "debt",
        "analyst",
        "financing",
        "stock"
    ],
    "wof:name":"Edward Jones",
    "wof:placetype":"venue"
},
  "geometry": {"coordinates":[-93.336707,44.930283],"type":"Point"}
}