{
  "type": "Feature",
  "properties": {
    "addr:full":"3439 Logan Ave N Minneapolis MN 55412",
    "addr:housenumber":"3439",
    "addr:postcode":"55412",
    "addr:street":"Logan Ave N",
    "iso:country":"US",
    "sg:address":"3439 Logan Ave N",
    "sg:city":"Minneapolis",
    "sg:classifiers":[
        {
            "category":"Real Estate",
            "subcategory":"Real Estate Agent",
            "type":"Services"
        }
    ],
    "sg:phone":"+1 763 443 9378",
    "sg:postcode":"55412",
    "sg:province":"MN",
    "sg:tags":[
        "investment"
    ],
    "wof:name":"M P Real Estate Investments",
    "wof:placetype":"venue"
},
  "geometry": {"coordinates":[-93.30326700000001,45.017922],"type":"Point"}
}