{
  "type": "Feature",
  "properties": {
    "iso:country":"US",
    "sg:address":"201 Hamel Rd",
    "sg:city":"Hamel",
    "sg:classifiers":[
        {
            "category":"Building & Trades",
            "subcategory":"Electrical",
            "type":"Services"
        }
    ],
    "sg:phone":"+1 763 478 6791",
    "sg:postcode":"55340",
    "sg:province":"MN",
    "sg:tags":[
        "electric",
        "contractor"
    ],
    "wof:name":"Hamel Electric Inc",
    "wof:placetype":"venue"
},
  "geometry": {"coordinates":[-93.52922100000001,45.041289],"type":"Point"}
}