{
  "type": "Feature",
  "properties": {
    "iso:country":"US",
    "sg:address":"45299 US Hwy 59",
    "sg:city":"Pelican Rapids",
    "sg:classifiers":[
        {
            "category":"Shopping",
            "subcategory":"Gifts & Souvenirs",
            "type":"Retail Goods"
        }
    ],
    "sg:phone":"+1 218 863 5585",
    "sg:postcode":"56572",
    "sg:province":"MN",
    "wof:name":"Karens Korner",
    "wof:placetype":"venue"
},
  "geometry": {"coordinates":[-96.05311500000001,46.625598],"type":"Point"}
}