{
  "type": "Feature",
  "properties": {
    "iso:country":"US",
    "sg:address":"12810 50th Ave N",
    "sg:city":"Minneapolis",
    "sg:classifiers":[
        {
            "category":"Professional",
            "subcategory":"Engineering",
            "type":"Services"
        },
        {
            "category":"Professional",
            "subcategory":"Business Services",
            "type":"Services"
        }
    ],
    "sg:phone":"+1 952 217 1445",
    "sg:postcode":"55442",
    "sg:province":"MN",
    "sg:tags":[
        "consultant",
        "consulting",
        "coach",
        "management",
        "engineer"
    ],
    "sg:website":"http://www.businessefficacy.com",
    "wof:name":"Business Efficacy Incorporated",
    "wof:placetype":"venue"
},
  "geometry": {"coordinates":[-93.44204000000001,45.044929],"type":"Point"}
}