{
  "type": "Feature",
  "properties": {
    "iso:country":"US",
    "sg:address":"8944 Darnel Rd",
    "sg:city":"Eden Prairie",
    "sg:classifiers":[
        {
            "category":"Professional",
            "subcategory":"Employment Agencies",
            "type":"Services"
        }
    ],
    "sg:phone":"+1 952 829 7441",
    "sg:postcode":"55347",
    "sg:province":"MN",
    "wof:name":"Employment On Line Inc",
    "wof:placetype":"venue"
},
  "geometry": {"coordinates":[-93.432852,44.84113],"type":"Point"}
}