{
  "type": "Feature",
  "properties": {
    "iso:country":"US",
    "sg:address":"211 Main St",
    "sg:city":"Elrosa",
    "sg:classifiers":[
        {
            "category":"Food & Beverages",
            "subcategory":"Meat & Fish",
            "type":"Retail Goods"
        }
    ],
    "sg:phone":"+1 320 697 5638",
    "sg:postcode":"56325",
    "sg:province":"MN",
    "sg:tags":[
        "frozen"
    ],
    "wof:name":"Harry's Frozen Food",
    "wof:placetype":"venue"
},
  "geometry": {"coordinates":[-94.948446,45.562796],"type":"Point"}
}