{
  "type": "Feature",
  "properties": {
    "addr:full":"738 Elmwood Ave Le Sueur MN 56058",
    "addr:housenumber":"738",
    "addr:postcode":"56058",
    "addr:street":"Elmwood Ave",
    "iso:country":"US",
    "sg:address":"738 Elmwood Ave",
    "sg:city":"Le Sueur",
    "sg:classifiers":[
        {
            "category":"Retail",
            "subcategory":"Auto Repair",
            "type":"Services"
        }
    ],
    "sg:phone":"+1 507 665 3063",
    "sg:postcode":"56058",
    "sg:province":"MN",
    "sg:tags":[
        "wheel",
        "axle",
        "alignment"
    ],
    "wof:name":"Voss's Southside Frame",
    "wof:placetype":"venue"
},
  "geometry": {"coordinates":[-93.90921899999999,44.43617],"type":"Point"}
}