{
  "type": "Feature",
  "properties": {
    "iso:country":"US",
    "sg:address":"459 3rd Ave SE",
    "sg:city":"Perham",
    "sg:classifiers":[
        {
            "category":"Manufacturing",
            "subcategory":"Retail Goods",
            "type":"Manufacturing & Wholesale Goods"
        }
    ],
    "sg:phone":"+1 218 346 7075",
    "sg:postcode":"56573",
    "sg:province":"MN",
    "sg:tags":[
        "product",
        "mfg"
    ],
    "sg:website":"www.perhamcoop.com",
    "wof:name":"Country Store",
    "wof:placetype":"venue"
},
  "geometry": {"coordinates":[-95.57378,46.589991],"type":"Point"}
}