{
  "type": "Feature",
  "properties": {
    "addr:full":"5320 Hyland Greens Dr Minneapolis MN 55437",
    "addr:housenumber":"5320",
    "addr:postcode":"55437",
    "addr:street":"Hyland Greens Dr",
    "iso:country":"US",
    "sg:address":"5320 Hyland Greens Dr",
    "sg:city":"Minneapolis",
    "sg:classifiers":[
        {
            "category":"Health Services",
            "subcategory":"Doctor",
            "type":"Services"
        }
    ],
    "sg:phone":"+1 952 993 3230",
    "sg:postcode":"55437",
    "sg:province":"MN",
    "sg:tags":[
        "orthopedist"
    ],
    "wof:name":"Johnson Paul G MD",
    "wof:placetype":"venue"
},
  "geometry": {"coordinates":[-93.351097,44.8237],"type":"Point"}
}