{
  "type": "Feature",
  "properties": {
    "iso:country":"US",
    "sg:address":"301 Northtown Dr NE",
    "sg:city":"Minneapolis",
    "sg:classifiers":[
        {
            "category":"Autos & Motor Vehicles",
            "subcategory":"Boat Sales",
            "type":"Retail Goods"
        }
    ],
    "sg:phone":"+1 763 785 8953",
    "sg:postcode":"55434",
    "sg:province":"MN",
    "sg:tags":[
        "equipment",
        "marine",
        "supply"
    ],
    "wof:name":"Crystals Piers Marine",
    "wof:placetype":"venue"
},
  "geometry": {"coordinates":[-93.260048,45.128349],"type":"Point"}
}