{
  "type": "Feature",
  "properties": {
    "addr:full":"220 N Pokegama Ave Grand Rapids MN 55744",
    "addr:housenumber":"220",
    "addr:postcode":"55744",
    "addr:street":"N Pokegama Ave",
    "iso:country":"US",
    "sg:address":"220 N Pokegama Ave",
    "sg:city":"Grand Rapids",
    "sg:classifiers":[
        {
            "category":"Retail",
            "subcategory":"Animal Services",
            "type":"Services"
        }
    ],
    "sg:phone":"+1 218 327 0156",
    "sg:postcode":"55744",
    "sg:province":"MN",
    "wof:name":"4 Paws Pet Grooming",
    "wof:placetype":"venue"
},
  "geometry": {"coordinates":[-93.52825900000001,47.234074],"type":"Point"}
}