{
  "type": "Feature",
  "properties": {
    "addr:full":"120 Armstrong Blvd S St James MN 56081",
    "addr:housenumber":"120",
    "addr:postcode":"56081",
    "addr:street":"Armstrong Blvd S St James",
    "iso:country":"US",
    "sg:address":"120 Armstrong Blvd S",
    "sg:city":"St James",
    "sg:classifiers":[
        {
            "category":"Retail",
            "subcategory":"Laundry & Dry Cleaning",
            "type":"Services"
        }
    ],
    "sg:phone":"+1 507 375 4461",
    "sg:postcode":"56081",
    "sg:province":"MN",
    "sg:tags":[
        "cleaners"
    ],
    "wof:name":"St James Cleaners",
    "wof:placetype":"venue"
},
  "geometry": {"coordinates":[-94.628207,43.981782],"type":"Point"}
}