{
  "type": "Feature",
  "properties": {
    "iso:country":"US",
    "sg:address":"1041 Toledo Ave N",
    "sg:city":"Minneapolis",
    "sg:classifiers":[
        {
            "category":"Professional",
            "subcategory":"Management & Consulting",
            "type":"Services"
        }
    ],
    "sg:phone":"+1 763 588 8366",
    "sg:postcode":"55422",
    "sg:province":"MN",
    "wof:name":"Pro Events International Inc",
    "wof:placetype":"venue"
},
  "geometry": {"coordinates":[-93.346413,44.98835],"type":"Point"}
}