{
  "type": "Feature",
  "properties": {
    "addr:full":"224 Park Ave Avoca MN 56114",
    "addr:housenumber":"224",
    "addr:postcode":"56114",
    "addr:street":"Park Ave",
    "iso:country":"US",
    "sg:address":"224 Park Ave",
    "sg:city":"Avoca",
    "sg:classifiers":[
        {
            "category":"Government",
            "subcategory":"Fire Station",
            "type":"Public Place"
        }
    ],
    "sg:phone":"+1 507 335 7878",
    "sg:postcode":"56114",
    "sg:province":"MN",
    "sg:tags":[
        "department"
    ],
    "wof:name":"Avoca Volunteer Fire Department",
    "wof:placetype":"venue"
},
  "geometry": {"coordinates":[-95.642792,43.945599],"type":"Point"}
}