{
  "type": "Feature",
  "properties": {
    "addr:full":"3617 E Lake St Minneapolis MN 55406",
    "addr:housenumber":"3617",
    "addr:postcode":"55406",
    "addr:street":"E Lake St",
    "iso:country":"US",
    "sg:address":"3617 E Lake St",
    "sg:city":"Minneapolis",
    "sg:classifiers":[
        {
            "category":"Manufacturing",
            "subcategory":"Tools & Machinery",
            "type":"Manufacturing & Wholesale Goods"
        },
        {
            "category":"Retail",
            "subcategory":"Auto Repair",
            "type":"Services"
        }
    ],
    "sg:phone":"+1 612 724 3697",
    "sg:postcode":"55406",
    "sg:province":"MN",
    "sg:tags":[
        "engines-rebuild",
        "lawn",
        "exchange",
        "mowers-sharpening",
        "engine",
        "rebuilding",
        "repairing"
    ],
    "sg:website":"http://www.riverlakeracing.com",
    "wof:name":"Riverlake Small Engines",
    "wof:placetype":"venue"
},
  "geometry": {"coordinates":[-93.220162,44.948372],"type":"Point"}
}