{
  "type": "Feature",
  "properties": {
    "addr:full":"1242 290th Ave Westbrook MN 56183",
    "addr:housenumber":"1242",
    "addr:postcode":"56183",
    "addr:street":"290Th Ave",
    "iso:country":"US",
    "sg:address":"1242 290th Ave",
    "sg:city":"Westbrook",
    "sg:phone":"+1 507 274 6201",
    "sg:postcode":"56183",
    "sg:province":"MN",
    "sg:tags":[
        "farm",
        "corn",
        "soybean"
    ],
    "wof:name":"Richard Cooley",
    "wof:placetype":"venue"
},
  "geometry": {"coordinates":[-95.482395,44.026413],"type":"Point"}
}