{
  "type": "Feature",
  "properties": {
    "addr:full":"3013 Restormel St Duluth MN 55806",
    "addr:housenumber":"3013",
    "addr:postcode":"55806",
    "addr:street":"Restormel St",
    "iso:country":"US",
    "sg:address":"3013 Restormel St",
    "sg:city":"Duluth",
    "sg:classifiers":[
        {
            "category":"Social Services",
            "subcategory":"Child Care",
            "type":"Services"
        }
    ],
    "sg:phone":"+1 218 624 3387",
    "sg:postcode":"55806",
    "sg:province":"MN",
    "sg:tags":[
        "day"
    ],
    "wof:name":"Becky Fechner",
    "wof:placetype":"venue"
},
  "geometry": {"coordinates":[-92.13982799999999,46.760269],"type":"Point"}
}