{
  "type": "Feature",
  "properties": {
    "addr:full":"16755 Langley Ave Lakeville MN 55044",
    "addr:housenumber":"16755",
    "addr:postcode":"55044",
    "addr:street":"Langley Ave",
    "iso:country":"US",
    "sg:address":"16755 Langley Ave",
    "sg:city":"Lakeville",
    "sg:classifiers":[
        {
            "category":"Building & Trades",
            "subcategory":"Landscaping Services",
            "type":"Services"
        }
    ],
    "sg:phone":"+1 952 898 2002",
    "sg:postcode":"55044",
    "sg:province":"MN",
    "sg:tags":[
        "home",
        "landscape",
        "contractor"
    ],
    "sg:website":"gardenexp.com",
    "wof:name":"Garden Expressions",
    "wof:placetype":"venue"
},
  "geometry": {"coordinates":[-93.310501,44.705799],"type":"Point"}
}