{
  "type": "Feature",
  "properties": {
    "addr:full":"8424 Sunset Rd NE Minneapolis MN 55432",
    "addr:housenumber":"8424",
    "addr:postcode":"55432",
    "addr:street":"Sunset Rd Ne",
    "iso:country":"US",
    "sg:address":"8424 Sunset Rd NE",
    "sg:city":"Minneapolis",
    "sg:classifiers":[
        {
            "category":"Manufacturing",
            "subcategory":"Metals",
            "type":"Manufacturing & Wholesale Goods"
        },
        {
            "category":"Wholesale",
            "subcategory":"Metals & Minerals",
            "type":"Manufacturing & Wholesale Goods"
        }
    ],
    "sg:phone":"+1 763 560 1100",
    "sg:postcode":"55432",
    "sg:province":"MN",
    "sg:tags":[
        "fabricator",
        "specialty",
        "custom"
    ],
    "wof:name":"L S V Metals Inc",
    "wof:placetype":"venue"
},
  "geometry": {"coordinates":[-93.231492,45.123613],"type":"Point"}
}