{
  "type": "Feature",
  "properties": {
    "iso:country":"US",
    "sg:address":"1974 W Palace Ave",
    "sg:city":"Saint Paul",
    "sg:classifiers":[
        {
            "category":"Personal",
            "subcategory":"Beauty Salon",
            "type":"Services"
        }
    ],
    "sg:phone":"+1 651 699 0214",
    "sg:postcode":"55105",
    "sg:province":"MN",
    "sg:tags":[
        "shop"
    ],
    "wof:name":"Jean Kinde",
    "wof:placetype":"venue"
},
  "geometry": {"coordinates":[-93.183781,44.928789],"type":"Point"}
}