{
  "type": "Feature",
  "properties": {
    "addr:full":"306 2nd St S Virginia MN 55792",
    "addr:housenumber":"306",
    "addr:postcode":"55792",
    "addr:street":"2Nd St S",
    "iso:country":"US",
    "sg:address":"306 2nd St S",
    "sg:city":"Virginia",
    "sg:classifiers":[
        {
            "category":"Place Of Worship",
            "subcategory":"Church",
            "type":"Public Place"
        },
        {
            "category":"Place Of Worship",
            "type":"Public Place"
        },
        {
            "category":"Organizations",
            "subcategory":"Religious Organization",
            "type":"Services"
        }
    ],
    "sg:phone":"+1 218 741 2322",
    "sg:postcode":"55792",
    "sg:province":"MN",
    "sg:tags":[
        "churches-catholic-traditional",
        "churches-catholic"
    ],
    "wof:name":"Sacred Heart Church",
    "wof:placetype":"venue"
},
  "geometry": {"coordinates":[-92.53490600000001,47.521368],"type":"Point"}
}