{
  "type": "Feature",
  "properties": {
    "iso:country":"US",
    "sg:address":"818 Brook St",
    "sg:city":"Brainerd",
    "sg:classifiers":[
        {
            "category":"Retail",
            "subcategory":"Auto Repair",
            "type":"Services"
        }
    ],
    "sg:phone":"+1 218 829 7323",
    "sg:postcode":"56401",
    "sg:province":"MN",
    "sg:tags":[
        "repairing",
        "automobile"
    ],
    "wof:name":"Wetzel's Auto Svc Ctr",
    "wof:placetype":"venue"
},
  "geometry": {"coordinates":[-94.197559,46.342166],"type":"Point"}
}