{
  "type": "Feature",
  "properties": {
    "iso:country":"US",
    "sg:address":"12005 41st Ave N",
    "sg:city":"Minneapolis",
    "sg:classifiers":[
        {
            "category":"Farming",
            "subcategory":"Fish & Marine Products",
            "type":"Manufacturing & Wholesale Goods"
        },
        {
            "category":"Recreation",
            "subcategory":"Fishing",
            "type":"Entertainment"
        }
    ],
    "sg:phone":"+1 612 865 8480",
    "sg:postcode":"55441",
    "sg:province":"MN",
    "sg:tags":[
        "pond",
        "pier",
        "lake"
    ],
    "sg:website":"http://www.rippinlipswalleyeguides.com/",
    "wof:name":"Rippin Lips Walleye Guides",
    "wof:placetype":"venue"
},
  "geometry": {"coordinates":[-93.43282499999999,45.027912],"type":"Point"}
}