{
  "type": "Feature",
  "properties": {
    "addr:full":"560 Dunnell Dr Owatonna MN 55060",
    "addr:housenumber":"560",
    "addr:postcode":"55060",
    "addr:street":"Dunnell Dr",
    "iso:country":"US",
    "sg:address":"560 Dunnell Dr",
    "sg:city":"Owatonna",
    "sg:classifiers":[
        {
            "category":"Social Services",
            "type":"Services"
        }
    ],
    "sg:phone":"+1 507 446 9315",
    "sg:postcode":"55060",
    "sg:province":"MN",
    "sg:tags":[
        "shelter",
        "homeless"
    ],
    "wof:name":"Steele County Transitional",
    "wof:placetype":"venue"
},
  "geometry": {"coordinates":[-93.240148,44.089973],"type":"Point"}
}