{
  "type": "Feature",
  "properties": {
    "addr:full":"206 W Lake St Chisholm MN 55719",
    "addr:housenumber":"206",
    "addr:postcode":"55719",
    "addr:street":"W Lake St",
    "iso:country":"US",
    "sg:address":"206 W Lake St",
    "sg:city":"Chisholm",
    "sg:classifiers":[
        {
            "category":"Bars & Pubs",
            "type":"Food & Drink"
        }
    ],
    "sg:phone":"+1 218 254 3980",
    "sg:postcode":"55719",
    "sg:province":"MN",
    "wof:name":"Koscak's Bar",
    "wof:placetype":"venue"
},
  "geometry": {"coordinates":[-92.883787,47.489379],"type":"Point"}
}