{
  "type": "Feature",
  "properties": {
    "iso:country":"US",
    "sg:address":"24962 Co Hwy 22",
    "sg:city":"Detroit Lakes",
    "sg:classifiers":[
        {
            "category":"Sports & Exercise",
            "subcategory":"Golf",
            "type":"Entertainment"
        }
    ],
    "sg:phone":"+1 218 847 8942",
    "sg:postcode":"56501",
    "sg:province":"MN",
    "sg:tags":[
        "course"
    ],
    "wof:name":"Lakeview Executive Golf Course",
    "wof:placetype":"venue"
},
  "geometry": {"coordinates":[-95.879948,46.761862],"type":"Point"}
}