{
  "type": "Feature",
  "properties": {
    "iso:country":"US",
    "sg:address":"850 2nd St NW",
    "sg:city":"Aitkin",
    "sg:classifiers":[
        {
            "category":"Health Services",
            "subcategory":"Nursing And Care Facility",
            "type":"Services"
        }
    ],
    "sg:phone":"+1 218 927 2164",
    "sg:postcode":"56431",
    "sg:province":"MN",
    "sg:tags":[
        "home"
    ],
    "wof:name":"Aicota Health Care Center Inc",
    "wof:placetype":"venue"
},
  "geometry": {"coordinates":[-93.71941700000001,46.533423],"type":"Point"}
}