{
  "type": "Feature",
  "properties": {
    "addr:full":"123 N Union St Norwood MN 55368",
    "addr:housenumber":"123",
    "addr:postcode":"55368",
    "addr:street":"N Union St",
    "iso:country":"US",
    "sg:address":"123 N Union St",
    "sg:city":"Norwood",
    "sg:classifiers":[
        {
            "category":"Manufacturing",
            "subcategory":"Food",
            "type":"Manufacturing & Wholesale Goods"
        }
    ],
    "sg:phone":"+1 952 467 2212",
    "sg:postcode":"55368",
    "sg:province":"MN",
    "sg:tags":[
        "fluid",
        "milk"
    ],
    "wof:name":"Oak Grove Dairy",
    "wof:placetype":"venue"
},
  "geometry": {"coordinates":[-93.92886300000001,44.768197],"type":"Point"}
}