{
  "type": "Feature",
  "properties": {
    "iso:country":"US",
    "sg:address":"2301 E 24th St",
    "sg:city":"Minneapolis",
    "sg:classifiers":[
        {
            "category":"Retail",
            "subcategory":"Portrait Studio",
            "type":"Services"
        }
    ],
    "sg:phone":"+1 612 721 6900",
    "sg:postcode":"55406",
    "sg:province":"MN",
    "sg:tags":[
        "photographer"
    ],
    "sg:website":"www.coedcheerleaders.com",
    "wof:name":"Eddie Mulkeen Wedding Photo",
    "wof:placetype":"venue"
},
  "geometry": {"coordinates":[-93.23775500000001,44.959156],"type":"Point"}
}