{
  "type": "Feature",
  "properties": {
    "addr:full":"11 S 7th St Minneapolis MN 55402",
    "addr:housenumber":"11",
    "addr:postcode":"55402",
    "addr:street":"S 7Th St",
    "iso:country":"US",
    "sg:address":"11 S 7th St",
    "sg:city":"Minneapolis",
    "sg:classifiers":[
        {
            "category":"Restaurant",
            "type":"Food & Drink"
        }
    ],
    "sg:postcode":"55402",
    "sg:province":"MN",
    "sg:tags":[
        "thai"
    ],
    "wof:name":"Taste of Thailand",
    "wof:placetype":"venue"
},
  "geometry": {"coordinates":[-93.27242099999999,44.976944],"type":"Point"}
}