{
  "type": "Feature",
  "properties": {
    "iso:country":"US",
    "sg:address":"2662 Randy Ave",
    "sg:city":"St Paul",
    "sg:classifiers":[
        {
            "category":"Building & Trades",
            "subcategory":"Construction",
            "type":"Services"
        }
    ],
    "sg:phone":"+1 651 426 1886",
    "sg:postcode":"55110",
    "sg:province":"MN",
    "sg:tags":[
        "woodworker"
    ],
    "wof:name":"Creative Woodworking",
    "wof:placetype":"venue"
},
  "geometry": {"coordinates":[-92.98756400000001,45.060088],"type":"Point"}
}