{
  "type": "Feature",
  "properties": {
    "iso:country":"US",
    "sg:address":"400 E 134th St",
    "sg:city":"Burnsville",
    "sg:classifiers":[
        {
            "category":"Education",
            "subcategory":"School",
            "type":"Public Place"
        }
    ],
    "sg:phone":"+1 952 707 2600",
    "sg:postcode":"55337",
    "sg:province":"MN",
    "sg:tags":[
        "high",
        "middle"
    ],
    "wof:name":"Joseph Nicollet Junior High School",
    "wof:placetype":"venue"
},
  "geometry": {"coordinates":[-93.275597,44.761902],"type":"Point"}
}