{
  "type": "Feature",
  "properties": {
    "iso:country":"US",
    "sg:address":"10 S 5th St",
    "sg:city":"Minneapolis",
    "sg:classifiers":[
        {
            "category":"Professional",
            "subcategory":"Lawyer & Legal Services",
            "type":"Services"
        }
    ],
    "sg:phone":"+1 612 204 4533",
    "sg:postcode":"55402",
    "sg:province":"MN",
    "wof:name":"Klassen John A",
    "wof:placetype":"venue"
},
  "geometry": {"coordinates":[-93.27216199999999,44.979629],"type":"Point"}
}