{
  "type": "Feature",
  "properties": {
    "iso:country":"US",
    "sg:address":"1300 Nicollet Ave",
    "sg:city":"Minneapolis",
    "sg:classifiers":[
        {
            "category":"Professional",
            "subcategory":"Business Services",
            "type":"Services"
        }
    ],
    "sg:phone":"+1 612 288 9494",
    "sg:postcode":"55403",
    "sg:province":"MN",
    "sg:tags":[
        "translation"
    ],
    "wof:name":"Kj International Resources",
    "wof:placetype":"venue"
},
  "geometry": {"coordinates":[-93.277817,44.969879],"type":"Point"}
}