{
  "type": "Feature",
  "properties": {
    "iso:country":"US",
    "sg:address":"1296 Jasper Rd",
    "sg:city":"Shakopee",
    "sg:classifiers":[
        {
            "category":"Building & Trades",
            "subcategory":"Construction",
            "type":"Services"
        }
    ],
    "sg:phone":"+1 952 445 7024",
    "sg:postcode":"55379",
    "sg:province":"MN",
    "sg:tags":[
        "house"
    ],
    "wof:name":"Stanley Pint",
    "wof:placetype":"venue"
},
  "geometry": {"coordinates":[-93.486634,44.782168],"type":"Point"}
}