{
  "type": "Feature",
  "properties": {
    "iso:country":"US",
    "sg:address":"6520 Edenvale Blvd",
    "sg:city":"Eden Prairie",
    "sg:classifiers":[
        {
            "category":"Professional",
            "type":"Services"
        }
    ],
    "sg:phone":"+1 952 937 0298",
    "sg:postcode":"55346",
    "sg:province":"MN",
    "sg:tags":[
        "establishment"
    ],
    "wof:name":"Devax Inc",
    "wof:placetype":"venue"
},
  "geometry": {"coordinates":[-93.46265,44.882732],"type":"Point"}
}