{
  "type": "Feature",
  "properties": {
    "iso:country":"US",
    "sg:address":"2402 1st Ave",
    "sg:city":"Hibbing",
    "sg:classifiers":[
        {
            "category":"Retail",
            "subcategory":"Repair Shop",
            "type":"Services"
        }
    ],
    "sg:phone":"+1 218 263 5715",
    "sg:postcode":"55746",
    "sg:province":"MN",
    "sg:tags":[
        "water",
        "equipment",
        "softening"
    ],
    "wof:name":"Culligan Water Conditioning",
    "wof:placetype":"venue"
},
  "geometry": {"coordinates":[-92.94163500000001,47.422122],"type":"Point"}
}