{
  "type": "Feature",
  "properties": {
    "addr:full":"3165 Fernbrook Ln N Minneapolis MN 55447",
    "addr:housenumber":"3165",
    "addr:postcode":"55447",
    "addr:street":"Fernbrook Ln N",
    "iso:country":"US",
    "sg:address":"3165 Fernbrook Ln N",
    "sg:city":"Minneapolis",
    "sg:classifiers":[
        {
            "category":"Banks & Credit Unions",
            "subcategory":"Bank",
            "type":"Services"
        }
    ],
    "sg:phone":"+1 763 694 9100",
    "sg:postcode":"55447",
    "sg:province":"MN",
    "sg:tags":[
        "loan",
        "real estate"
    ],
    "wof:name":"Headwaters Mortgage",
    "wof:placetype":"venue"
},
  "geometry": {"coordinates":[-93.46150400000001,45.016616],"type":"Point"}
}