{
  "type": "Feature",
  "properties": {
    "iso:country":"US",
    "sg:address":"420 3rd Ave S",
    "sg:city":"Minneapolis",
    "sg:classifiers":[
        {
            "category":"Travel",
            "subcategory":"Hotels & Motels",
            "type":"Entertainment"
        }
    ],
    "sg:phone":"+1 612 326 6525",
    "sg:postcode":"55415",
    "sg:province":"MN",
    "wof:name":"Henry Hotels",
    "wof:placetype":"venue"
},
  "geometry": {"coordinates":[-93.266098,44.977699],"type":"Point"}
}