{
  "type": "Feature",
  "properties": {
    "iso:country":"US",
    "sg:address":"2990 Niagara Ln N",
    "sg:city":"Plymouth",
    "sg:classifiers":[
        {
            "category":"Wholesale",
            "subcategory":"Toys & Hobbies",
            "type":"Manufacturing & Wholesale Goods"
        }
    ],
    "sg:phone":"+1 763 550 3915",
    "sg:postcode":"55447",
    "sg:province":"MN",
    "sg:tags":[
        "wholesaler"
    ],
    "wof:name":"Werner Co",
    "wof:placetype":"venue"
},
  "geometry": {"coordinates":[-93.471453,45.013334],"type":"Point"}
}