{
  "type": "Feature",
  "properties": {
    "iso:country":"US",
    "sg:address":"9057 Lyndale Ave S",
    "sg:city":"Bloomington",
    "sg:classifiers":[
        {
            "category":"Wholesale",
            "subcategory":"Electrical",
            "type":"Manufacturing & Wholesale Goods"
        }
    ],
    "sg:phone":"+1 952 346 9452",
    "sg:postcode":"55420",
    "sg:province":"MN",
    "sg:tags":[
        "alarm",
        "burglar",
        "system"
    ],
    "wof:name":"SDN Dispatch",
    "wof:placetype":"venue"
},
  "geometry": {"coordinates":[-93.28853100000001,44.838124],"type":"Point"}
}