{
  "type": "Feature",
  "properties": {
    "addr:full":"37955 Bridge Rd North Branch MN 55056",
    "addr:housenumber":"37955",
    "addr:postcode":"55056",
    "addr:street":"Bridge Rd",
    "iso:country":"US",
    "sg:address":"37955 Bridge Rd",
    "sg:city":"North Branch",
    "sg:classifiers":[
        {
            "category":"Building & Trades",
            "subcategory":"Construction",
            "type":"Services"
        },
        {
            "category":"Manufacturing",
            "subcategory":"Buildings",
            "type":"Manufacturing & Wholesale Goods"
        }
    ],
    "sg:phone":"+1 651 674 4292",
    "sg:postcode":"55056",
    "sg:province":"MN",
    "sg:tags":[
        "mfg",
        "geodesic",
        "construct",
        "dome",
        "home",
        "structure"
    ],
    "sg:website":"www.naturalspacesdomes.com",
    "wof:name":"Natural Spaces Domes Inc",
    "wof:placetype":"venue"
},
  "geometry": {"coordinates":[-92.92937999999999,45.498273],"type":"Point"}
}