{
  "type": "Feature",
  "properties": {
    "addr:full":"3733 Nicollet Ave Minneapolis MN 55409",
    "addr:housenumber":"3733",
    "addr:postcode":"55409",
    "addr:street":"Nicollet Ave",
    "iso:country":"US",
    "sg:address":"3733 Nicollet Ave",
    "sg:city":"Minneapolis",
    "sg:classifiers":[
        {
            "category":"Food & Beverages",
            "subcategory":"Bakery",
            "type":"Retail Goods"
        }
    ],
    "sg:phone":"+1 612 822 0448",
    "sg:postcode":"55409",
    "sg:province":"MN",
    "sg:tags":[
        "baker"
    ],
    "wof:name":"Marissa's Bakery",
    "wof:placetype":"venue"
},
  "geometry": {"coordinates":[-93.277835,44.934687],"type":"Point"}
}