{
  "type": "Feature",
  "properties": {
    "iso:country":"US",
    "sg:address":"16 S 6th St",
    "sg:city":"Minneapolis",
    "sg:classifiers":[
        {
            "category":"Bars & Pubs",
            "type":"Food & Drink"
        },
        {
            "category":"Restaurant",
            "type":"Food & Drink"
        }
    ],
    "sg:phone":"+1 612 333 6612",
    "sg:postcode":"55402",
    "sg:province":"MN",
    "sg:website":"www.lyonspub.com",
    "wof:name":"Lyons Pub",
    "wof:placetype":"venue"
},
  "geometry": {"coordinates":[-93.27330000000001,44.9785],"type":"Point"}
}