{
  "type": "Feature",
  "properties": {
    "addr:full":"615 N 11th Ave E Duluth MN 55805",
    "addr:housenumber":"615",
    "addr:postcode":"55805",
    "addr:street":"N 11Th Ave E",
    "iso:country":"US",
    "sg:address":"615 N 11th Ave E",
    "sg:city":"Duluth",
    "sg:classifiers":[
        {
            "category":"Real Estate",
            "subcategory":"Real Estate Agent",
            "type":"Services"
        }
    ],
    "sg:phone":"+1 218 391 1466",
    "sg:postcode":"55805",
    "sg:province":"MN",
    "sg:tags":[
        "inspection"
    ],
    "wof:name":"Mc Rae's Home Inspection Svc",
    "wof:placetype":"venue"
},
  "geometry": {"coordinates":[-92.09207499999999,46.80196],"type":"Point"}
}