{
  "type": "Feature",
  "properties": {
    "addr:full":"35603 200th St Green Isle MN 55338",
    "addr:housenumber":"35603",
    "addr:postcode":"55338",
    "addr:street":"200Th St;Isle",
    "iso:country":"US",
    "sg:address":"35603 200th St",
    "sg:city":"Green Isle",
    "sg:classifiers":[
        {
            "category":"Farming",
            "subcategory":"Farm",
            "type":"Manufacturing & Wholesale Goods"
        }
    ],
    "sg:phone":"+1 507 326 3204",
    "sg:postcode":"55338",
    "sg:province":"MN",
    "sg:tags":[
        "crop",
        "general"
    ],
    "wof:name":"Circle East Spread",
    "wof:placetype":"venue"
},
  "geometry": {"coordinates":[-93.989256,44.658767],"type":"Point"}
}