{
  "type": "Feature",
  "properties": {
    "iso:country":"US",
    "sg:address":"3630 Dakota Ave",
    "sg:city":"Saint Paul",
    "sg:classifiers":[
        {
            "category":"Building & Trades",
            "subcategory":"Electrical",
            "type":"Services"
        }
    ],
    "sg:phone":"+1 651 734 9383",
    "sg:postcode":"55125",
    "sg:province":"MN",
    "sg:tags":[
        "electrical",
        "contractor"
    ],
    "wof:name":"Grip Electric",
    "wof:placetype":"venue"
},
  "geometry": {"coordinates":[-92.937589,44.897693],"type":"Point"}
}