{
  "type": "Feature",
  "properties": {
    "iso:country":"US",
    "sg:address":"318 Jefferson St S",
    "sg:city":"Wadena",
    "sg:classifiers":[
        {
            "category":"Shopping",
            "type":"Retail Goods"
        }
    ],
    "sg:phone":"+1 218 632 4327",
    "sg:postcode":"56482",
    "sg:province":"MN",
    "sg:tags":[
        "hearing",
        "equipment",
        "supply",
        "impaired"
    ],
    "wof:name":"Certiear Hearing Ctr",
    "wof:placetype":"venue"
},
  "geometry": {"coordinates":[-95.13831399999999,46.439074],"type":"Point"}
}