{
  "type": "Feature",
  "properties": {
    "iso:country":"US",
    "sg:address":"26552 Taylor Rd",
    "sg:city":"Deerwood",
    "sg:classifiers":[
        {
            "category":"Farming",
            "subcategory":"Nursery",
            "type":"Manufacturing & Wholesale Goods"
        }
    ],
    "sg:phone":"+1 218 678 2542",
    "sg:postcode":"56444",
    "sg:province":"MN",
    "sg:tags":[
        "perennial",
        "grower"
    ],
    "wof:name":"Arbor Lake Nursery",
    "wof:placetype":"venue"
},
  "geometry": {"coordinates":[-93.832633,46.417381],"type":"Point"}
}