{
  "type": "Feature",
  "properties": {
    "iso:country":"US",
    "sg:address":"321 W Superior St",
    "sg:city":"Duluth",
    "sg:classifiers":[
        {
            "category":"Shopping",
            "type":"Retail Goods"
        }
    ],
    "sg:phone":"+1 218 727 2224",
    "sg:postcode":"55802",
    "sg:province":"MN",
    "sg:tags":[
        "picture",
        "frame"
    ],
    "wof:name":"True North Gallery Custom Gfts",
    "wof:placetype":"venue"
},
  "geometry": {"coordinates":[-92.10290999999999,46.783375],"type":"Point"}
}