{
  "type": "Feature",
  "properties": {
    "iso:country":"US",
    "sg:address":"315 27th Ave SE",
    "sg:city":"Minneapolis",
    "sg:classifiers":[
        {
            "category":"Manufacturing",
            "subcategory":"Printing",
            "type":"Manufacturing & Wholesale Goods"
        }
    ],
    "sg:phone":"+1 612 331 3373",
    "sg:postcode":"55414",
    "sg:province":"MN",
    "sg:tags":[
        "commercial"
    ],
    "wof:name":"Bruce Printing Inc",
    "wof:placetype":"venue"
},
  "geometry": {"coordinates":[-93.217984,44.973206],"type":"Point"}
}