{
  "type": "Feature",
  "properties": {
    "addr:full":"601 Taft St NE Minneapolis MN 55413",
    "addr:housenumber":"601",
    "addr:postcode":"55413",
    "addr:street":"Taft St Ne",
    "iso:country":"US",
    "sg:address":"601 Taft St NE",
    "sg:city":"Minneapolis",
    "sg:classifiers":[
        {
            "category":"Food & Beverages",
            "subcategory":"Groceries & Convenience Stores",
            "type":"Retail Goods"
        }
    ],
    "sg:phone":"+1 612 623 1068",
    "sg:postcode":"55413",
    "sg:province":"MN",
    "sg:tags":[
        "product"
    ],
    "wof:name":"Marigold Foods",
    "wof:placetype":"venue"
},
  "geometry": {"coordinates":[-93.224159,44.99691],"type":"Point"}
}