{
  "type": "Feature",
  "properties": {
    "addr:full":"1320 Vermillion St Hastings MN 55033",
    "addr:housenumber":"1320",
    "addr:postcode":"55033",
    "addr:street":"Vermillion St",
    "iso:country":"US",
    "sg:address":"1320 Vermillion St",
    "sg:city":"Hastings",
    "sg:classifiers":[
        {
            "category":"Health Services",
            "subcategory":"Optometrist",
            "type":"Services"
        }
    ],
    "sg:phone":"+1 651 437 5469",
    "sg:postcode":"55033",
    "sg:province":"MN",
    "wof:name":"Paula J Becker OD",
    "wof:placetype":"venue"
},
  "geometry": {"coordinates":[-92.85274800000001,44.732488],"type":"Point"}
}