{
  "type": "Feature",
  "properties": {
    "iso:country":"US",
    "sg:address":"8661 Bluebird Ln",
    "sg:city":"Pequot Lakes",
    "sg:classifiers":[
        {
            "category":"Banks & Credit Unions",
            "subcategory":"Investment Brokerage",
            "type":"Services"
        }
    ],
    "sg:phone":"+1 218 562 4900",
    "sg:postcode":"56472",
    "sg:province":"MN",
    "sg:tags":[
        "trade",
        "barter",
        "exchange"
    ],
    "wof:name":"Remington Investment Inc",
    "wof:placetype":"venue"
},
  "geometry": {"coordinates":[-94.22053699999999,46.589932],"type":"Point"}
}