{
  "type": "Feature",
  "properties": {
    "iso:country":"US",
    "sg:address":"1455 W Almond Ave",
    "sg:city":"St Paul",
    "sg:classifiers":[
        {
            "category":"Real Estate",
            "subcategory":"Real Estate Operator",
            "type":"Services"
        }
    ],
    "sg:phone":"+1 651 632 5422",
    "sg:postcode":"55108",
    "sg:province":"MN",
    "sg:tags":[
        "apartment"
    ],
    "wof:name":"Lynglomsten Apartments",
    "wof:placetype":"venue"
},
  "geometry": {"coordinates":[-93.16024299999999,44.979263],"type":"Point"}
}