{
  "type": "Feature",
  "properties": {
    "addr:full":"34 N Klondike Dr Ely MN 55731",
    "addr:housenumber":"34",
    "addr:postcode":"55731",
    "addr:street":"N Klondike Dr",
    "iso:country":"US",
    "sg:address":"34 N Klondike Dr",
    "sg:city":"Ely",
    "sg:classifiers":[
        {
            "category":"Utilities",
            "subcategory":"Refuse",
            "type":"Services"
        }
    ],
    "sg:phone":"+1 218 365 3895",
    "sg:postcode":"55731",
    "sg:province":"MN",
    "sg:tags":[
        "system"
    ],
    "wof:name":"Northwood Solid Waste Comm",
    "wof:placetype":"venue"
},
  "geometry": {"coordinates":[-91.86832800000001,47.910274],"type":"Point"}
}