{
  "type": "Feature",
  "properties": {
    "iso:country":"US",
    "sg:address":"120 S Main St",
    "sg:city":"Stewartville",
    "sg:classifiers":[
        {
            "category":"Manufacturing",
            "subcategory":"Motor Vehicles & Parts",
            "type":"Manufacturing & Wholesale Goods"
        }
    ],
    "sg:phone":"+1 507 533 9201",
    "sg:postcode":"55976",
    "sg:province":"MN",
    "sg:tags":[
        "mfg",
        "trimming"
    ],
    "wof:name":"Uptys Screen Printing",
    "wof:placetype":"venue"
},
  "geometry": {"coordinates":[-92.488406,43.855385],"type":"Point"}
}