{
  "type": "Feature",
  "properties": {
    "iso:country":"US",
    "sg:address":"724 19th Ave N",
    "sg:city":"South St Paul",
    "sg:classifiers":[
        {
            "category":"Health Services",
            "subcategory":"Nursing And Care Facility",
            "type":"Services"
        }
    ],
    "sg:phone":"+1 651 232 6000",
    "sg:postcode":"55075",
    "sg:province":"MN",
    "sg:tags":[
        "home",
        "convalescent"
    ],
    "wof:name":"Bethesda Care Ctr",
    "wof:placetype":"venue"
},
  "geometry": {"coordinates":[-93.05760100000001,44.904694],"type":"Point"}
}