{
  "type": "Feature",
  "properties": {
    "iso:country":"US",
    "sg:address":"1200 1st St NE",
    "sg:city":"Buffalo",
    "sg:phone":"+1 763 746 0540",
    "sg:postcode":"55313",
    "sg:province":"MN",
    "sg:tags":[
        "product",
        "petroleum"
    ],
    "wof:name":"Lpg & Nh3 Supply",
    "wof:placetype":"venue"
},
  "geometry": {"coordinates":[-93.85426099999999,45.172772],"type":"Point"}
}