{
  "type": "Feature",
  "properties": {
    "addr:full":"312 3rd St Pipestone MN 56164",
    "addr:housenumber":"312",
    "addr:postcode":"56164",
    "addr:street":"3Rd St",
    "iso:country":"US",
    "sg:address":"312 3rd St",
    "sg:city":"Pipestone",
    "sg:classifiers":[
        {
            "category":"Building & Trades",
            "subcategory":"Electrical",
            "type":"Services"
        }
    ],
    "sg:phone":"+1 507 825 4206",
    "sg:postcode":"56164",
    "sg:province":"MN",
    "sg:tags":[
        "electrical",
        "contractor"
    ],
    "wof:name":"Kor Electric LLC",
    "wof:placetype":"venue"
},
  "geometry": {"coordinates":[-96.19497200000001,43.958647],"type":"Point"}
}