{
  "type": "Feature",
  "properties": {
    "addr:full":"8729 Central Ave NE Minneapolis MN 55434",
    "addr:housenumber":"8729",
    "addr:postcode":"55434",
    "addr:street":"Central Ave Ne",
    "iso:country":"US",
    "sg:address":"8729 Central Ave NE",
    "sg:city":"Minneapolis",
    "sg:classifiers":[
        {
            "category":"Real Estate",
            "subcategory":"Real Estate Agent",
            "type":"Services"
        }
    ],
    "sg:phone":"+1 763 780 3900",
    "sg:postcode":"55434",
    "sg:province":"MN",
    "wof:name":"Northway Real Estate",
    "wof:placetype":"venue"
},
  "geometry": {"coordinates":[-93.23539599999999,45.131297],"type":"Point"}
}