{
  "type": "Feature",
  "properties": {
    "addr:full":"426 N Minnesota St New Ulm MN 56073",
    "addr:housenumber":"426",
    "addr:postcode":"56073",
    "addr:street":"N Minnesota St",
    "iso:country":"US",
    "sg:address":"426 N Minnesota St",
    "sg:city":"New Ulm",
    "sg:classifiers":[
        {
            "category":"Autos & Motor Vehicles",
            "subcategory":"Auto Supplies",
            "type":"Retail Goods"
        }
    ],
    "sg:phone":"+1 507 354 3154",
    "sg:postcode":"56073",
    "sg:province":"MN",
    "sg:tags":[
        "automobile",
        "parts"
    ],
    "wof:name":"General Trading Co",
    "wof:placetype":"venue"
},
  "geometry": {"coordinates":[-94.463317,44.318004],"type":"Point"}
}