{
  "type": "Feature",
  "properties": {
    "addr:full":"515 Lake Dr Chanhassen MN 55317",
    "addr:housenumber":"515",
    "addr:postcode":"55317",
    "addr:street":"Lake Dr",
    "iso:country":"US",
    "sg:address":"515 Lake Dr",
    "sg:city":"Chanhassen",
    "sg:classifiers":[
        {
            "category":"Personal",
            "subcategory":"Nail Salon",
            "type":"Services"
        }
    ],
    "sg:phone":"+1 952 949 1087",
    "sg:postcode":"55317",
    "sg:province":"MN",
    "wof:name":"Nail Gallery On the Ponds",
    "wof:placetype":"venue"
},
  "geometry": {"coordinates":[-93.533413,44.856023],"type":"Point"}
}