{
  "type": "Feature",
  "properties": {
    "addr:full":"20514 Idalia Ave Lakeville MN 55044",
    "addr:postcode":"20514;55044",
    "addr:street":"Idalia Ave",
    "iso:country":"US",
    "sg:address":"20514 Idalia Ave",
    "sg:city":"Lakeville",
    "sg:classifiers":[
        {
            "category":"Manufacturing",
            "subcategory":"Soap",
            "type":"Manufacturing & Wholesale Goods"
        }
    ],
    "sg:phone":"+1 952 469 1876",
    "sg:postcode":"55044",
    "sg:province":"MN",
    "sg:tags":[
        "detergent",
        "mfg"
    ],
    "wof:name":"A Garden of Soap",
    "wof:placetype":"venue"
},
  "geometry": {"coordinates":[-93.251535,44.652245],"type":"Point"}
}