{
  "type": "Feature",
  "properties": {
    "iso:country":"US",
    "sg:address":"811 Mainstreet",
    "sg:city":"Hopkins",
    "sg:classifiers":[
        {
            "category":"Banks & Credit Unions",
            "subcategory":"Financial Services",
            "type":"Services"
        }
    ],
    "sg:phone":"+1 952 767 6611",
    "sg:postcode":"55343",
    "sg:province":"MN",
    "sg:tags":[
        "accountant",
        "referral"
    ],
    "wof:name":"Insurance Claims Auditing And Professional Services Inc",
    "wof:placetype":"venue"
},
  "geometry": {"coordinates":[-93.410252,44.92438],"type":"Point"}
}