{
  "type": "Feature",
  "properties": {
    "iso:country":"US",
    "sg:address":"3082 Riviera Rd",
    "sg:city":"Sartell",
    "sg:classifiers":[
        {
            "category":"Building & Trades",
            "subcategory":"Construction",
            "type":"Services"
        }
    ],
    "sg:phone":"+1 320 252 7345",
    "sg:postcode":"56377",
    "sg:province":"MN",
    "sg:tags":[
        "residential",
        "nonresidential"
    ],
    "wof:name":"Schaefer Development Corp",
    "wof:placetype":"venue"
},
  "geometry": {"coordinates":[-94.20002700000001,45.659656],"type":"Point"}
}