{
  "type": "Feature",
  "properties": {
    "iso:country":"US",
    "sg:address":"17903 440th St",
    "sg:city":"Winger",
    "sg:classifiers":[
        {
            "category":"Professional",
            "type":"Services"
        }
    ],
    "sg:phone":"+1 218 945 6259",
    "sg:postcode":"56572",
    "sg:province":"MN",
    "wof:name":"Brad Hanson",
    "wof:placetype":"venue"
},
  "geometry": {"coordinates":[-96.119636,46.600875],"type":"Point"}
}