{
  "type": "Feature",
  "properties": {
    "addr:full":"2520 151st Ct W Rosemount MN 55068",
    "addr:housenumber":"2520",
    "addr:postcode":"55068",
    "addr:street":"151St Ct W",
    "iso:country":"US",
    "sg:address":"2520 151st Ct W",
    "sg:city":"Rosemount",
    "sg:classifiers":[
        {
            "category":"Real Estate",
            "subcategory":"Real Estate Services",
            "type":"Services"
        },
        {
            "category":"Real Estate",
            "subcategory":"Real Estate Agent",
            "type":"Services"
        }
    ],
    "sg:phone":"+1 651 322 4943",
    "sg:postcode":"55068",
    "sg:province":"MN",
    "sg:tags":[
        "management"
    ],
    "wof:name":"Pce Realty Inc",
    "wof:placetype":"venue"
},
  "geometry": {"coordinates":[-93.116895,44.730038],"type":"Point"}
}