{
  "type": "Feature",
  "properties": {
    "addr:full":"2354 Sioux Trl NW Prior Lake MN 55372",
    "addr:housenumber":"2354",
    "addr:postcode":"55372",
    "addr:street":"Sioux Trl Nw",
    "iso:country":"US",
    "sg:address":"2354 Sioux Trl NW",
    "sg:city":"Prior Lake",
    "sg:classifiers":[
        {
            "category":"Restaurant",
            "type":"Food & Drink"
        }
    ],
    "sg:phone":"+1 952 445 8982",
    "sg:postcode":"55372",
    "sg:province":"MN",
    "sg:tags":[
        "eating"
    ],
    "wof:name":"Tipi Restaurant",
    "wof:placetype":"venue"
},
  "geometry": {"coordinates":[-93.47176399999999,44.736962],"type":"Point"}
}