{
  "type": "Feature",
  "properties": {
    "addr:full":"2902 Eagle Dr Moorhead MN 56560",
    "addr:housenumber":"2902",
    "addr:postcode":"56560",
    "addr:street":"Eagle Dr",
    "iso:country":"US",
    "sg:address":"2902 Eagle Dr",
    "sg:city":"Moorhead",
    "sg:classifiers":[
        {
            "category":"Food & Beverages",
            "subcategory":"Meat & Fish",
            "type":"Retail Goods"
        }
    ],
    "sg:phone":"+1 218 233 6789",
    "sg:postcode":"56560",
    "sg:province":"MN",
    "wof:name":"Prairie Bison Meats",
    "wof:placetype":"venue"
},
  "geometry": {"coordinates":[-96.734826,46.872871],"type":"Point"}
}