{
  "type": "Feature",
  "properties": {
    "iso:country":"US",
    "sg:address":"13516 Heather Hills Dr",
    "sg:city":"Burnsville",
    "sg:classifiers":[
        {
            "category":"Retail",
            "subcategory":"Laundry & Dry Cleaning",
            "type":"Services"
        }
    ],
    "sg:phone":"+1 651 274 6357",
    "sg:postcode":"55337",
    "sg:province":"MN",
    "wof:name":"Lloyds Fiber Care",
    "wof:placetype":"venue"
},
  "geometry": {"coordinates":[-93.25671800000001,44.757648],"type":"Point"}
}