{
  "type": "Feature",
  "properties": {
    "iso:country":"US",
    "sg:address":"6445 James Ave S",
    "sg:city":"Minneapolis",
    "sg:classifiers":[
        {
            "category":"Social Services",
            "subcategory":"Child Care",
            "type":"Services"
        }
    ],
    "sg:phone":"+1 612 866 6169",
    "sg:postcode":"55423",
    "sg:province":"MN",
    "sg:tags":[
        "day"
    ],
    "wof:name":"Barbara White",
    "wof:placetype":"venue"
},
  "geometry": {"coordinates":[-93.30094800000001,44.886083],"type":"Point"}
}