{
  "type": "Feature",
  "properties": {
    "iso:country":"US",
    "sg:address":"9743 Almond Ave N",
    "sg:city":"Minneapolis",
    "sg:classifiers":[
        {
            "category":"Shopping",
            "type":"Retail Goods"
        }
    ],
    "sg:phone":"+1 763 425 0556",
    "sg:postcode":"55443",
    "sg:province":"MN",
    "sg:tags":[
        "merchandise"
    ],
    "wof:name":"Princton Town Mart",
    "wof:placetype":"venue"
},
  "geometry": {"coordinates":[-93.321567,45.13145],"type":"Point"}
}