{
  "type": "Feature",
  "properties": {
    "iso:country":"US",
    "sg:address":"1413 4th St SE",
    "sg:city":"Minneapolis",
    "sg:classifiers":[
        {
            "category":"Professional",
            "subcategory":"Detective & Security Services",
            "type":"Services"
        }
    ],
    "sg:phone":"+1 612 362 0162",
    "sg:postcode":"55414",
    "sg:province":"MN",
    "sg:tags":[
        "guard",
        "patrol"
    ],
    "wof:name":"Millennium Security",
    "wof:placetype":"venue"
},
  "geometry": {"coordinates":[-93.23485700000001,44.980084],"type":"Point"}
}