{
  "type": "Feature",
  "properties": {
    "iso:country":"US",
    "sg:address":"2853 Johnson St NE",
    "sg:city":"Minneapolis",
    "sg:classifiers":[
        {
            "category":"Food & Beverages",
            "subcategory":"Bakery",
            "type":"Retail Goods"
        },
        {
            "category":"Bakery",
            "type":"Food & Drink"
        }
    ],
    "sg:phone":"+1 612 789 2827",
    "sg:postcode":"55418",
    "sg:province":"MN",
    "sg:tags":[
        "bakers-wholesale"
    ],
    "wof:name":"Sarah Jane's Bakery",
    "wof:placetype":"venue"
},
  "geometry": {"coordinates":[-93.237117,45.019594],"type":"Point"}
}