{
  "type": "Feature",
  "properties": {
    "iso:country":"US",
    "sg:address":"200 1st St SW",
    "sg:city":"Rochester",
    "sg:classifiers":[
        {
            "category":"Health Services",
            "subcategory":"Health Practitioner",
            "type":"Services"
        }
    ],
    "sg:phone":"+1 507 284 2012",
    "sg:postcode":"55917",
    "sg:province":"MN",
    "sg:tags":[
        "therapist",
        "physical"
    ],
    "wof:name":"Mayo Clinic Physical Therapy",
    "wof:placetype":"venue"
},
  "geometry": {"coordinates":[-93.058666,43.865476],"type":"Point"}
}