{
  "type": "Feature",
  "properties": {
    "addr:full":"10024 Zinran Rd S Bloomington MN 55438",
    "addr:housenumber":"10024",
    "addr:postcode":"55438",
    "addr:street":"Zinran Rd S",
    "iso:country":"US",
    "sg:address":"10024 Zinran Rd S",
    "sg:city":"Bloomington",
    "sg:classifiers":[
        {
            "category":"Insurance",
            "subcategory":"Insurance Agent",
            "type":"Services"
        }
    ],
    "sg:phone":"+1 952 942 5596",
    "sg:postcode":"55438",
    "sg:province":"MN",
    "wof:name":"Affiliated Insurance South",
    "wof:placetype":"venue"
},
  "geometry": {"coordinates":[-93.387867,44.821462],"type":"Point"}
}