{
  "type": "Feature",
  "properties": {
    "iso:country":"US",
    "sg:address":"12491 Hwy 71",
    "sg:city":"Northome",
    "sg:classifiers":[
        {
            "category":"Shopping",
            "subcategory":"Florist",
            "type":"Retail Goods"
        }
    ],
    "sg:phone":"+1 218 897 5007",
    "sg:postcode":"56661",
    "sg:province":"MN",
    "wof:name":"Jungleland",
    "wof:placetype":"venue"
},
  "geometry": {"coordinates":[-94.325642,47.861618],"type":"Point"}
}