{
  "type": "Feature",
  "properties": {
    "addr:full":"3808 Chowen Ave S Minneapolis MN 55410",
    "addr:housenumber":"3808",
    "addr:postcode":"55410",
    "addr:street":"Chowen Ave S",
    "iso:country":"US",
    "sg:address":"3808 Chowen Ave S",
    "sg:city":"Minneapolis",
    "sg:classifiers":[
        {
            "category":"Professional",
            "subcategory":"Advertising",
            "type":"Services"
        }
    ],
    "sg:phone":"+1 612 920 3562",
    "sg:postcode":"55410",
    "sg:province":"MN",
    "sg:tags":[
        "mail",
        "direct"
    ],
    "wof:name":"Circus Software",
    "wof:placetype":"venue"
},
  "geometry": {"coordinates":[-93.32526900000001,44.932486],"type":"Point"}
}