{
  "type": "Feature",
  "properties": {
    "addr:full":"306 98th Ave W Duluth MN 55808",
    "addr:housenumber":"306",
    "addr:postcode":"55808",
    "addr:street":"98Th Ave W",
    "iso:country":"US",
    "sg:address":"306 98th Ave W",
    "sg:city":"Duluth",
    "sg:classifiers":[
        {
            "category":"Building & Trades",
            "subcategory":"Construction",
            "type":"Services"
        }
    ],
    "sg:phone":"+1 218 626 1651",
    "sg:postcode":"55808",
    "sg:province":"MN",
    "wof:name":"Blazevic Flatworks",
    "wof:placetype":"venue"
},
  "geometry": {"coordinates":[-92.22341400000001,46.659769],"type":"Point"}
}