{
  "type": "Feature",
  "properties": {
    "addr:full":"9905 Hamilton Rd Eden Prairie MN 55344",
    "addr:housenumber":"9905",
    "addr:postcode":"55344",
    "addr:street":"Hamilton Rd",
    "iso:country":"US",
    "sg:address":"9905 Hamilton Rd",
    "sg:city":"Eden Prairie",
    "sg:classifiers":[
        {
            "category":"Manufacturing",
            "subcategory":"Metals",
            "type":"Manufacturing & Wholesale Goods"
        }
    ],
    "sg:phone":"+1 952 946 1018",
    "sg:postcode":"55344",
    "sg:province":"MN",
    "sg:tags":[
        "tube",
        "fabricating"
    ],
    "sg:website":"www.bendingtech.com",
    "wof:name":"Bending Technologies",
    "wof:placetype":"venue"
},
  "geometry": {"coordinates":[-93.40165399999999,44.880854],"type":"Point"}
}