{
  "type": "Feature",
  "properties": {
    "addr:full":"11114 240th St S Hawley MN 56549",
    "addr:housenumber":"11114",
    "addr:postcode":"56549",
    "addr:street":"240Th St S",
    "iso:country":"US",
    "sg:address":"11114 240th St S",
    "sg:city":"Hawley",
    "sg:classifiers":[
        {
            "category":"Farming",
            "subcategory":"Livestock Farm",
            "type":"Manufacturing & Wholesale Goods"
        }
    ],
    "sg:phone":"+1 218 937 5461",
    "sg:postcode":"56549",
    "sg:province":"MN",
    "sg:tags":[
        "beef",
        "feedlot",
        "cattle"
    ],
    "wof:name":"Leslie Dunham",
    "wof:placetype":"venue"
},
  "geometry": {"coordinates":[-96.30071599999999,46.73143],"type":"Point"}
}