{
  "type": "Feature",
  "properties": {
    "addr:full":"1810 7th St W Saint Paul MN 55116",
    "addr:housenumber":"1810",
    "addr:postcode":"55116",
    "addr:street":"7Th St W",
    "iso:country":"US",
    "sg:address":"1810 7th St W",
    "sg:city":"Saint Paul",
    "sg:classifiers":[
        {
            "category":"Real Estate",
            "subcategory":"Real Estate Agent",
            "type":"Services"
        }
    ],
    "sg:phone":"+1 651 698 1988",
    "sg:postcode":"55116",
    "sg:province":"MN",
    "wof:name":"Galles Properties",
    "wof:placetype":"venue"
},
  "geometry": {"coordinates":[-93.148696,44.912881],"type":"Point"}
}