{
  "type": "Feature",
  "properties": {
    "iso:country":"US",
    "sg:address":"540 Lilac Dr N",
    "sg:city":"Minneapolis",
    "sg:classifiers":[
        {
            "category":"Building & Trades",
            "subcategory":"Construction",
            "type":"Services"
        }
    ],
    "sg:phone":"+1 763 542 8433",
    "sg:postcode":"55422",
    "sg:province":"MN",
    "sg:tags":[
        "residential",
        "contractor"
    ],
    "wof:name":"Chriden Enterprises",
    "wof:placetype":"venue"
},
  "geometry": {"coordinates":[-93.34826099999999,44.983318],"type":"Point"}
}