{
  "type": "Feature",
  "properties": {
    "addr:full":"10825 Jonquil Ln Hanover MN 55357",
    "addr:housenumber":"10825",
    "addr:postcode":"55357",
    "addr:street":"Jonquil Ln",
    "iso:country":"US",
    "sg:address":"10825 Jonquil Ln",
    "sg:city":"Hanover",
    "sg:classifiers":[
        {
            "category":"Building & Trades",
            "subcategory":"Construction",
            "type":"Services"
        }
    ],
    "sg:phone":"+1 763 498 8095",
    "sg:postcode":"55357",
    "sg:province":"MN",
    "sg:tags":[
        "concrete",
        "contractor"
    ],
    "wof:name":"C Olson Concrete Inc",
    "wof:placetype":"venue"
},
  "geometry": {"coordinates":[-93.645866,45.151576],"type":"Point"}
}