{
  "type": "Feature",
  "properties": {
    "iso:country":"US",
    "sg:address":"6240 State Hwy 65",
    "sg:city":"Fridley",
    "sg:classifiers":[
        {
            "category":"Insurance",
            "subcategory":"Insurance Agent",
            "type":"Services"
        }
    ],
    "sg:phone":"+1 763 572 9512",
    "sg:postcode":"55432",
    "sg:province":"MN",
    "wof:name":"Bankson Almquist Agency Inc",
    "wof:placetype":"venue"
},
  "geometry": {"coordinates":[-93.24354599999999,45.081744],"type":"Point"}
}