{
  "type": "Feature",
  "properties": {
    "addr:full":"19690 Kenwood Ave Wabasso MN 56293",
    "addr:housenumber":"19690",
    "addr:postcode":"56293",
    "addr:street":"Kenwood Ave",
    "iso:country":"US",
    "sg:address":"19690 Kenwood Ave",
    "sg:city":"Wabasso",
    "sg:phone":"+1 507 342 5554",
    "sg:postcode":"56293",
    "sg:province":"MN",
    "sg:tags":[
        "farm",
        "corn",
        "soybean"
    ],
    "wof:name":"Kenneth Kruse",
    "wof:placetype":"venue"
},
  "geometry": {"coordinates":[-95.18747999999999,44.340055],"type":"Point"}
}