{
  "type": "Feature",
  "properties": {
    "iso:country":"US",
    "sg:address":"12527 Central Ave NE",
    "sg:city":"Minneapolis",
    "sg:classifiers":[
        {
            "category":"Autos & Motor Vehicles",
            "subcategory":"Automobile Sales",
            "type":"Retail Goods"
        }
    ],
    "sg:phone":"+1 763 783 3900",
    "sg:postcode":"55434",
    "sg:province":"MN",
    "sg:tags":[
        "used"
    ],
    "wof:name":"Express Auto Sales",
    "wof:placetype":"venue"
},
  "geometry": {"coordinates":[-93.231899,45.197953],"type":"Point"}
}