{
  "type": "Feature",
  "properties": {
    "addr:full":"5015 W 70th St Edina MN 55439",
    "addr:housenumber":"5015",
    "addr:postcode":"55439",
    "addr:street":"W 70Th St",
    "iso:country":"US",
    "sg:address":"5015 W 70th St",
    "sg:city":"Edina",
    "sg:classifiers":[
        {
            "category":"Social Services",
            "subcategory":"Child Care",
            "type":"Services"
        }
    ],
    "sg:phone":"+1 952 946 9971",
    "sg:postcode":"55439",
    "sg:province":"MN",
    "sg:tags":[
        "day"
    ],
    "sg:website":"www.especiallyforchildren.com",
    "wof:name":"Especially For Children",
    "wof:placetype":"venue"
},
  "geometry": {"coordinates":[-93.354275,44.875237],"type":"Point"}
}