{
  "type": "Feature",
  "properties": {
    "iso:country":"US",
    "sg:address":"400 W Main St",
    "sg:city":"Marshall",
    "sg:classifiers":[
        {
            "category":"Insurance",
            "subcategory":"Insurance Agent",
            "type":"Services"
        }
    ],
    "sg:phone":"+1 507 532 5739",
    "sg:postcode":"56258",
    "sg:province":"MN",
    "sg:tags":[
        "audit"
    ],
    "sg:website":"www.hoffmanbrobst.com",
    "wof:name":"Hoffman & Brobst",
    "wof:placetype":"venue"
},
  "geometry": {"coordinates":[-95.79228999999999,44.44947],"type":"Point"}
}