{
  "type": "Feature",
  "properties": {
    "addr:full":"480 Grand Hill Saint Paul MN 55102",
    "addr:housenumber":"480",
    "addr:postcode":"55102",
    "addr:street":"Grand Hill",
    "iso:country":"US",
    "sg:address":"480 Grand Hill",
    "sg:city":"Saint Paul",
    "sg:classifiers":[
        {
            "category":"Organizations",
            "subcategory":"Membership Organization",
            "type":"Services"
        }
    ],
    "sg:phone":"+1 651 227 4351",
    "sg:postcode":"55102",
    "sg:province":"MN",
    "wof:name":"Alice M OBrien Foundation",
    "wof:placetype":"venue"
},
  "geometry": {"coordinates":[-93.120655,44.939949],"type":"Point"}
}