{
  "type": "Feature",
  "properties": {
    "addr:full":"12498 Co Rd 5 NE Carlos MN 56319",
    "addr:housenumber":"12498;5",
    "addr:postcode":"56319",
    "addr:street":"Co Rd;Ne Carlos",
    "iso:country":"US",
    "sg:address":"12498 Co Rd 5 NE",
    "sg:city":"Carlos",
    "sg:classifiers":[
        {
            "category":"Farming",
            "subcategory":"Livestock Farm",
            "type":"Manufacturing & Wholesale Goods"
        }
    ],
    "sg:phone":"+1 320 852 7731",
    "sg:postcode":"56319",
    "sg:province":"MN",
    "sg:tags":[
        "beef",
        "feedlot",
        "cattle"
    ],
    "wof:name":"Paul Leonard",
    "wof:placetype":"venue"
},
  "geometry": {"coordinates":[-95.20795200000001,46.019783],"type":"Point"}
}