{
  "type": "Feature",
  "properties": {
    "addr:full":"27355 Biscayne Ave Randolph MN 55065",
    "addr:housenumber":"27355",
    "addr:postcode":"55065",
    "addr:street":"Biscayne Ave",
    "iso:country":"US",
    "sg:address":"27355 Biscayne Ave",
    "sg:city":"Randolph",
    "sg:classifiers":[
        {
            "category":"Professional",
            "subcategory":"Detective & Security Services",
            "type":"Services"
        }
    ],
    "sg:phone":"+1 507 663 0029",
    "sg:postcode":"55065",
    "sg:province":"MN",
    "sg:tags":[
        "system"
    ],
    "wof:name":"Universal Security Systems",
    "wof:placetype":"venue"
},
  "geometry": {"coordinates":[-93.116331,44.553124],"type":"Point"}
}