{
  "type": "Feature",
  "properties": {
    "addr:full":"1327 66th Ave NE Minneapolis MN 55432",
    "addr:housenumber":"1327",
    "addr:postcode":"55432",
    "addr:street":"66Th Ave Ne",
    "iso:country":"US",
    "sg:address":"1327 66th Ave NE",
    "sg:city":"Minneapolis",
    "sg:classifiers":[
        {
            "category":"Shopping",
            "subcategory":"Computers & Home Electronics",
            "type":"Retail Goods"
        }
    ],
    "sg:phone":"+1 763 277 5206",
    "sg:postcode":"55432",
    "sg:province":"MN",
    "sg:tags":[
        "programing",
        "custom"
    ],
    "wof:name":"Lifease Inc",
    "wof:placetype":"venue"
},
  "geometry": {"coordinates":[-93.233446,45.088888],"type":"Point"}
}