{
  "type": "Feature",
  "properties": {
    "iso:country":"US",
    "sg:address":"1285 S Pokegama Ave",
    "sg:city":"Grand Rapids",
    "sg:classifiers":[
        {
            "category":"Wholesale",
            "subcategory":"Chemicals & Plastics",
            "type":"Manufacturing & Wholesale Goods"
        }
    ],
    "sg:phone":"+1 218 326 2008",
    "sg:postcode":"55744",
    "sg:province":"MN",
    "sg:tags":[
        "repair",
        "merchandise",
        "oxygen"
    ],
    "wof:name":"Home Medical Products & Svcs",
    "wof:placetype":"venue"
},
  "geometry": {"coordinates":[-93.528797,47.218204],"type":"Point"}
}