{
  "type": "Feature",
  "properties": {
    "iso:country":"US",
    "sg:address":"300 S 1st St",
    "sg:city":"La Crescent",
    "sg:classifiers":[
        {
            "category":"Government",
            "subcategory":"Office",
            "type":"Public Place"
        }
    ],
    "sg:phone":"+1 507 895 6341",
    "sg:postcode":"55947",
    "sg:province":"MN",
    "wof:name":"NATURAL Resource Section",
    "wof:placetype":"venue"
},
  "geometry": {"coordinates":[-91.306032,43.828151],"type":"Point"}
}