{
  "type": "Feature",
  "properties": {
    "addr:full":"25 6th Avenue North St. Cloud MN 56303",
    "addr:housenumber":"25",
    "addr:postcode":"56303",
    "addr:street":"6Th Avenue North",
    "iso:country":"US",
    "sg:address":"25 6th Avenue North",
    "sg:city":"St. Cloud",
    "sg:classifiers":[
        {
            "category":"Professional",
            "subcategory":"Computer Services",
            "type":"Services"
        }
    ],
    "sg:phone":"+1 320 534 5000",
    "sg:postcode":"56303",
    "sg:province":"MN",
    "sg:website":"http://www.ebureau.com",
    "wof:name":"eBureau",
    "wof:placetype":"venue"
},
  "geometry": {"coordinates":[-94.160009,45.561315],"type":"Point"}
}