{
  "type": "Feature",
  "properties": {
    "addr:full":"1110 6th St NW Rochester MN 55901",
    "addr:housenumber":"1110",
    "addr:postcode":"55901",
    "addr:street":"6Th St Nw",
    "iso:country":"US",
    "sg:address":"1110 6th St NW",
    "sg:city":"Rochester",
    "sg:classifiers":[
        {
            "category":"Social Services",
            "type":"Services"
        }
    ],
    "sg:phone":"+1 507 287 2014",
    "sg:postcode":"55901",
    "sg:province":"MN",
    "sg:tags":[
        "organization",
        "welfare"
    ],
    "wof:name":"Family Access Ctr",
    "wof:placetype":"venue"
},
  "geometry": {"coordinates":[-92.480367,44.028953],"type":"Point"}
}