{
  "type": "Feature",
  "properties": {
    "addr:full":"525 2nd St Mora MN 55051",
    "addr:housenumber":"525",
    "addr:postcode":"55051",
    "addr:street":"2Nd St",
    "iso:country":"US",
    "sg:address":"525 2nd St",
    "sg:city":"Mora",
    "sg:classifiers":[
        {
            "category":"Place Of Worship",
            "subcategory":"Church",
            "type":"Public Place"
        },
        {
            "category":"Place Of Worship",
            "type":"Public Place"
        }
    ],
    "sg:phone":"+1 320 679 1125",
    "sg:postcode":"55051",
    "sg:province":"MN",
    "sg:tags":[
        "nazarene",
        "churches-church",
        "churches-nazarene"
    ],
    "sg:website":"http://www.nazarene.org",
    "wof:name":"Church Of Nazarene",
    "wof:placetype":"venue"
},
  "geometry": {"coordinates":[-93.304734,45.879791],"type":"Point"}
}