{
  "type": "Feature",
  "properties": {
    "iso:country":"US",
    "sg:address":"5770 Blackshire Path",
    "sg:city":"Inver Grove Heights",
    "sg:classifiers":[
        {
            "category":"Real Estate",
            "subcategory":"Architect",
            "type":"Services"
        }
    ],
    "sg:phone":"+1 651 389 1290",
    "sg:postcode":"55076",
    "sg:province":"MN",
    "sg:tags":[
        "architectural"
    ],
    "wof:name":"Beyond Dimensions",
    "wof:placetype":"venue"
},
  "geometry": {"coordinates":[-93.05156599999999,44.865036],"type":"Point"}
}