{
  "type": "Feature",
  "properties": {
    "iso:country":"US",
    "sg:address":"58056 205th St",
    "sg:city":"Austin",
    "sg:classifiers":[
        {
            "category":"Professional",
            "subcategory":"Computer Services",
            "type":"Services"
        }
    ],
    "sg:phone":"+1 612 281 5132",
    "sg:postcode":"55912",
    "sg:province":"MN",
    "sg:tags":[
        "datum"
    ],
    "wof:name":"Joker Media",
    "wof:placetype":"venue"
},
  "geometry": {"coordinates":[-92.883657,43.652511],"type":"Point"}
}