{
  "type": "Feature",
  "properties": {
    "addr:full":"150 Hwy 10 N Saint Cloud MN 56304",
    "addr:housenumber":"150",
    "addr:postcode":"56304",
    "addr:street":"Hwy 10 N",
    "iso:country":"US",
    "sg:address":"150 Hwy 10 N",
    "sg:city":"Saint Cloud",
    "sg:classifiers":[
        {
            "category":"Building & Trades",
            "subcategory":"Construction",
            "type":"Services"
        }
    ],
    "sg:phone":"+1 320 654 8003",
    "sg:postcode":"56304",
    "sg:province":"MN",
    "sg:tags":[
        "contractor"
    ],
    "wof:name":"Bustillos Brothers Stucco LLC",
    "wof:placetype":"venue"
},
  "geometry": {"coordinates":[-94.142825,45.570498],"type":"Point"}
}