{
  "type": "Feature",
  "properties": {
    "iso:country":"US",
    "sg:address":"3914 Cedar Grove Pkwy",
    "sg:city":"Eagan",
    "sg:classifiers":[
        {
            "category":"Insurance",
            "subcategory":"Insurance Agent",
            "type":"Services"
        }
    ],
    "sg:phone":"+1 651 452 4065",
    "sg:postcode":"55122",
    "sg:province":"MN",
    "wof:name":"State Farm Insurance",
    "wof:placetype":"venue"
},
  "geometry": {"coordinates":[-93.214153,44.813717],"type":"Point"}
}