{
  "type": "Feature",
  "properties": {
    "addr:full":"10087 Horseshoe Trl Eden Prairie MN 55347",
    "addr:housenumber":"10087",
    "addr:postcode":"55347",
    "addr:street":"Horseshoe Trl",
    "iso:country":"US",
    "sg:address":"10087 Horseshoe Trl",
    "sg:city":"Eden Prairie",
    "sg:classifiers":[
        {
            "category":"Professional",
            "subcategory":"Accounting & Tax Preparation",
            "type":"Services"
        }
    ],
    "sg:phone":"+1 952 941 3753",
    "sg:postcode":"55347",
    "sg:province":"MN",
    "sg:tags":[
        "bookkeeping",
        "general"
    ],
    "wof:name":"Regal Bookkeeping Svc",
    "wof:placetype":"venue"
},
  "geometry": {"coordinates":[-93.427499,44.820861],"type":"Point"}
}