{
  "type": "Feature",
  "properties": {
    "iso:country":"US",
    "sg:address":"826 Bald Lake Ct",
    "sg:city":"Saint Paul",
    "sg:classifiers":[
        {
            "category":"Professional",
            "subcategory":"Management & Consulting",
            "type":"Services"
        }
    ],
    "sg:phone":"+1 651 681 0278",
    "sg:postcode":"55123",
    "sg:province":"MN",
    "sg:tags":[
        "business"
    ],
    "wof:name":"RE Link",
    "wof:placetype":"venue"
},
  "geometry": {"coordinates":[-93.13080100000001,44.814663],"type":"Point"}
}