{
  "type": "Feature",
  "properties": {
    "addr:full":"821 3rd St Farmington MN 55024",
    "addr:housenumber":"821",
    "addr:postcode":"55024",
    "addr:street":"3Rd St",
    "iso:country":"US",
    "sg:address":"821 3rd St",
    "sg:city":"Farmington",
    "sg:classifiers":[
        {
            "category":"Organizations",
            "subcategory":"Non-profit Organization",
            "type":"Services"
        },
        {
            "category":"Health Services",
            "subcategory":"Clinic",
            "type":"Services"
        }
    ],
    "sg:phone":"+1 651 460 8085",
    "sg:postcode":"55024",
    "sg:province":"MN",
    "sg:tags":[
        "information",
        "alcoholism",
        "treatment"
    ],
    "wof:name":"Journey Counseling Svcs",
    "wof:placetype":"venue"
},
  "geometry": {"coordinates":[-93.14522599999999,44.63339],"type":"Point"}
}