{
  "type": "Feature",
  "properties": {
    "iso:country":"US",
    "sg:address":"206 9th Ave SE",
    "sg:city":"Saint Joseph",
    "sg:classifiers":[
        {
            "category":"Building & Trades",
            "subcategory":"Construction",
            "type":"Services"
        }
    ],
    "sg:phone":"+1 320 363 4260",
    "sg:postcode":"56374",
    "sg:province":"MN",
    "sg:tags":[
        "hanging",
        "contractor"
    ],
    "wof:name":"Brush Roll Painting Company",
    "wof:placetype":"venue"
},
  "geometry": {"coordinates":[-94.304114,45.562413],"type":"Point"}
}