{
  "type": "Feature",
  "properties": {
    "addr:full":"10087 42nd St Clear Lake MN 55319",
    "addr:housenumber":"10087",
    "addr:postcode":"55319",
    "addr:street":"42Nd St",
    "iso:country":"US",
    "sg:address":"10087 42nd St",
    "sg:city":"Clear Lake",
    "sg:classifiers":[
        {
            "category":"Building & Trades",
            "subcategory":"Construction",
            "type":"Services"
        }
    ],
    "sg:phone":"+1 320 251 9230",
    "sg:postcode":"55319",
    "sg:province":"MN",
    "sg:tags":[
        "excavation",
        "contractor"
    ],
    "wof:name":"Metropolitan Dirtworks",
    "wof:placetype":"venue"
},
  "geometry": {"coordinates":[-93.952585,45.508765],"type":"Point"}
}