{
  "type": "Feature",
  "properties": {
    "iso:country":"US",
    "sg:address":"811 221st Ave NE",
    "sg:city":"Cedar",
    "sg:classifiers":[
        {
            "category":"Wholesale",
            "subcategory":"Construction Materials",
            "type":"Manufacturing & Wholesale Goods"
        },
        {
            "category":"Building & Trades",
            "subcategory":"Construction",
            "type":"Services"
        },
        {
            "category":"Military Area",
            "subcategory":"Armory",
            "type":"Public Place"
        }
    ],
    "sg:phone":"+1 763 413 5000",
    "sg:postcode":"55011",
    "sg:province":"MN",
    "sg:tags":[
        "repair",
        "fence",
        "contractor",
        "fence-wholesale",
        "fence-sales",
        "manufacturer"
    ],
    "wof:name":"Top Notch Fence",
    "wof:placetype":"venue"
},
  "geometry": {"coordinates":[-93.251305,45.370627],"type":"Point"}
}