{
  "type": "Feature",
  "properties": {
    "addr:full":"2600 26th Ave S Minneapolis MN 55406",
    "addr:housenumber":"2600",
    "addr:postcode":"55406",
    "addr:street":"26Th Ave S",
    "iso:country":"US",
    "sg:address":"2600 26th Ave S",
    "sg:city":"Minneapolis",
    "sg:classifiers":[
        {
            "category":"Wholesale",
            "subcategory":"Computers",
            "type":"Manufacturing & Wholesale Goods"
        }
    ],
    "sg:phone":"+1 612 870 1415",
    "sg:postcode":"55406",
    "sg:province":"MN",
    "wof:name":"Mustaqbal Computer Ctr",
    "wof:placetype":"venue"
},
  "geometry": {"coordinates":[-93.234844,44.955584],"type":"Point"}
}