{
  "type": "Feature",
  "properties": {
    "iso:country":"US",
    "sg:address":"5821 Cedar Lake Rd S",
    "sg:city":"Minneapolis",
    "sg:classifiers":[
        {
            "category":"Professional",
            "subcategory":"Employment Agencies",
            "type":"Services"
        }
    ],
    "sg:phone":"+1 952 544 9555",
    "sg:postcode":"55416",
    "sg:province":"MN",
    "sg:tags":[
        "opportunity",
        "contractor"
    ],
    "wof:name":"Merit Search Inc",
    "wof:placetype":"venue"
},
  "geometry": {"coordinates":[-93.354271,44.965127],"type":"Point"}
}