{
  "type": "Feature",
  "properties": {
    "iso:country":"US",
    "sg:address":"11135 Terrace Rd NE",
    "sg:city":"Minneapolis",
    "sg:classifiers":[
        {
            "category":"Professional",
            "subcategory":"Accounting & Tax Preparation",
            "type":"Services"
        }
    ],
    "sg:phone":"+1 763 757 1294",
    "sg:postcode":"55434",
    "sg:province":"MN",
    "sg:tags":[
        "return"
    ],
    "wof:name":"Floyd M Stolt",
    "wof:placetype":"venue"
},
  "geometry": {"coordinates":[-93.258995,45.17487],"type":"Point"}
}