{
  "type": "Feature",
  "properties": {
    "addr:full":"1050 3rd Ave Mountain Lake MN 56159",
    "addr:housenumber":"1050",
    "addr:postcode":"56159",
    "addr:street":"3Rd Ave",
    "iso:country":"US",
    "sg:address":"1050 3rd Ave",
    "sg:city":"Mountain Lake",
    "sg:classifiers":[
        {
            "category":"Real Estate",
            "subcategory":"Real Estate Operator",
            "type":"Services"
        }
    ],
    "sg:phone":"+1 507 427 3829",
    "sg:postcode":"56159",
    "sg:province":"MN",
    "sg:tags":[
        "apartment"
    ],
    "wof:name":"Mountain Lake Apartments",
    "wof:placetype":"venue"
},
  "geometry": {"coordinates":[-94.92845199999999,43.939389],"type":"Point"}
}