{
  "type": "Feature",
  "properties": {
    "iso:country":"US",
    "sg:address":"3841 Main St",
    "sg:city":"St Bonifacius",
    "sg:classifiers":[
        {
            "category":"Building & Trades",
            "subcategory":"Construction",
            "type":"Services"
        }
    ],
    "sg:phone":"+1 952 938 2111",
    "sg:postcode":"55375",
    "sg:province":"MN",
    "sg:tags":[
        "water",
        "well",
        "drilling"
    ],
    "wof:name":"Don Stodola Well Drilling Co",
    "wof:placetype":"venue"
},
  "geometry": {"coordinates":[-93.74731300000001,44.908905],"type":"Point"}
}