{
  "type": "Feature",
  "properties": {
    "addr:full":"1001 Bruce St Crookston MN 56716",
    "addr:housenumber":"1001",
    "addr:postcode":"56716",
    "addr:street":"Bruce St",
    "iso:country":"US",
    "sg:address":"1001 Bruce St",
    "sg:city":"Crookston",
    "sg:classifiers":[
        {
            "category":"Autos & Motor Vehicles",
            "subcategory":"Boat Sales",
            "type":"Retail Goods"
        }
    ],
    "sg:phone":"+1 218 281 5617",
    "sg:postcode":"56716",
    "sg:province":"MN",
    "sg:tags":[
        "snowmobiles-parts",
        "accessory"
    ],
    "wof:name":"Grove Motor Sports",
    "wof:placetype":"venue"
},
  "geometry": {"coordinates":[-96.623581,47.76754],"type":"Point"}
}