{
  "type": "Feature",
  "properties": {
    "addr:full":"716 50th Ave Lake Wilson MN 56151",
    "addr:housenumber":"716",
    "addr:postcode":"56151",
    "addr:street":"50Th Ave",
    "iso:country":"US",
    "sg:address":"716 50th Ave",
    "sg:city":"Lake Wilson",
    "sg:phone":"+1 507 879 3324",
    "sg:postcode":"56151",
    "sg:province":"MN",
    "sg:tags":[
        "hog",
        "fee",
        "farm",
        "corn",
        "cash",
        "grain",
        "soybean",
        "or"
    ],
    "wof:name":"Glen Talsma",
    "wof:placetype":"venue"
},
  "geometry": {"coordinates":[-95.963587,43.955169],"type":"Point"}
}