{
  "type": "Feature",
  "properties": {
    "iso:country":"US",
    "sg:address":"5040 Highview Dr SW",
    "sg:city":"Montevideo",
    "sg:classifiers":[
        {
            "category":"Retail",
            "subcategory":"Photofinishing",
            "type":"Services"
        }
    ],
    "sg:phone":"+1 320 269 8161",
    "sg:postcode":"56265",
    "sg:province":"MN",
    "sg:tags":[
        "laboratory"
    ],
    "wof:name":"Andresen Photo",
    "wof:placetype":"venue"
},
  "geometry": {"coordinates":[-95.697091,44.928105],"type":"Point"}
}