{
  "type": "Feature",
  "properties": {
    "addr:full":"6975 Danielle Ln NE Bemidji MN 56601",
    "addr:housenumber":"6975",
    "addr:postcode":"56601",
    "addr:street":"Danielle Ln Ne",
    "iso:country":"US",
    "sg:address":"6975 Danielle Ln NE",
    "sg:city":"Bemidji",
    "sg:classifiers":[
        {
            "category":"Building & Trades",
            "subcategory":"Construction",
            "type":"Services"
        }
    ],
    "sg:phone":"+1 218 766 2669",
    "sg:postcode":"56601",
    "sg:province":"MN",
    "sg:tags":[
        "residential"
    ],
    "wof:name":"Frenzel Construction",
    "wof:placetype":"venue"
},
  "geometry": {"coordinates":[-94.77657600000001,47.593799],"type":"Point"}
}