{
  "type": "Feature",
  "properties": {
    "iso:country":"US",
    "sg:address":"5401 Morris Thomas Rd",
    "sg:city":"Duluth",
    "sg:classifiers":[
        {
            "category":"Shopping",
            "subcategory":"Used Merchandise",
            "type":"Retail Goods"
        }
    ],
    "sg:phone":"+1 218 740 3399",
    "sg:postcode":"55810",
    "sg:province":"MN",
    "wof:name":"Lakewalk Antiques",
    "wof:placetype":"venue"
},
  "geometry": {"coordinates":[-92.24874699999999,46.778545],"type":"Point"}
}