{
  "type": "Feature",
  "properties": {
    "addr:full":"9052 Lyndale Ave S Minneapolis MN 55420",
    "addr:housenumber":"9052",
    "addr:postcode":"55420",
    "addr:street":"Lyndale Ave S",
    "iso:country":"US",
    "sg:address":"9052 Lyndale Ave S",
    "sg:city":"Minneapolis",
    "sg:classifiers":[
        {
            "category":"Insurance",
            "subcategory":"Insurance Agent",
            "type":"Services"
        },
        {
            "category":"Insurance",
            "subcategory":"Hazard Insurance",
            "type":"Services"
        },
        {
            "category":"Insurance",
            "subcategory":"Title Insurance",
            "type":"Services"
        },
        {
            "category":"Insurance",
            "subcategory":"Health Insurance",
            "type":"Services"
        },
        {
            "category":"Insurance",
            "subcategory":"Life Insurance",
            "type":"Services"
        }
    ],
    "sg:phone":"+1 952 884 2358",
    "sg:postcode":"55420",
    "sg:province":"MN",
    "sg:tags":[
        "business",
        "fire",
        "auto",
        "commercial",
        "homeowner",
        "property",
        "casualty"
    ],
    "sg:website":"http://www.bluecrossmn.com",
    "wof:name":"Ken Jarcho Agency LLP",
    "wof:placetype":"venue"
},
  "geometry": {"coordinates":[-93.28868300000001,44.83977],"type":"Point"}
}