{
  "type": "Feature",
  "properties": {
    "iso:country":"US",
    "sg:address":"2 1st St SE",
    "sg:city":"Crosby",
    "sg:classifiers":[
        {
            "category":"Building & Trades",
            "subcategory":"Construction",
            "type":"Services"
        }
    ],
    "sg:phone":"+1 218 546 8382",
    "sg:postcode":"56441",
    "sg:province":"MN",
    "sg:tags":[
        "sandblasting"
    ],
    "wof:name":"Dustbusters Sandblasting",
    "wof:placetype":"venue"
},
  "geometry": {"coordinates":[-93.95231,46.48149],"type":"Point"}
}