{
  "type": "Feature",
  "properties": {
    "iso:country":"US",
    "sg:address":"1114 Zane Ave N",
    "sg:city":"Minneapolis",
    "sg:classifiers":[
        {
            "category":"Restaurant",
            "type":"Food & Drink"
        }
    ],
    "sg:phone":"+1 952 927 5061",
    "sg:postcode":"55422",
    "sg:province":"MN",
    "sg:tags":[
        "eating"
    ],
    "wof:name":"Coronet Steaks",
    "wof:placetype":"venue"
},
  "geometry": {"coordinates":[-93.35641,44.99232],"type":"Point"}
}