{
  "type": "Feature",
  "properties": {
    "addr:full":"59830 Century Rd Bluffton MN 56518",
    "addr:housenumber":"59830",
    "addr:postcode":"56518",
    "addr:street":"Century Rd",
    "iso:country":"US",
    "sg:address":"59830 Century Rd",
    "sg:city":"Bluffton",
    "sg:classifiers":[
        {
            "category":"Farming",
            "subcategory":"Dairy Farm",
            "type":"Manufacturing & Wholesale Goods"
        }
    ],
    "sg:phone":"+1 218 385 2523",
    "sg:postcode":"56518",
    "sg:province":"MN",
    "wof:name":"Endres Dairy",
    "wof:placetype":"venue"
},
  "geometry": {"coordinates":[-95.243528,46.48875],"type":"Point"}
}