{
  "type": "Feature",
  "properties": {
    "addr:full":"400 3rd Ave Albany MN 56307",
    "addr:housenumber":"400",
    "addr:postcode":"56307",
    "addr:street":"3Rd Ave",
    "iso:country":"US",
    "sg:address":"400 3rd Ave",
    "sg:city":"Albany",
    "sg:classifiers":[
        {
            "category":"Professional",
            "type":"Services"
        }
    ],
    "sg:phone":"+1 320 845 4077",
    "sg:postcode":"56307",
    "sg:province":"MN",
    "sg:tags":[
        "establishment"
    ],
    "wof:name":"Catholic Aid/Shirley Burr",
    "wof:placetype":"venue"
},
  "geometry": {"coordinates":[-94.568393,45.63867],"type":"Point"}
}