{
  "type": "Feature",
  "properties": {
    "addr:city":"Plainview",
    "addr:full":"40 4Th St Sw Plainview, Mn 55964",
    "addr:house_number":"40",
    "addr:housenumber":"40",
    "addr:phone":"+1 507-534-4173",
    "addr:postcode":"55964",
    "addr:road":"4Th St Sw",
    "addr:state":"MN",
    "addr:street":"4Th St Sw",
    "iso:country":"US",
    "sg:address":"40 4th St SW",
    "sg:city":"Plainview",
    "sg:classifiers":[
        {
            "category":"Museum",
            "type":"Entertainment"
        }
    ],
    "sg:phone":"+1 507 534 4173",
    "sg:postcode":"55964",
    "sg:province":"MN",
    "wof:name":"Plainview Area History Center",
    "wof:placetype":"venue"
},
  "geometry": {"coordinates":[-92.17140000000001,44.16481],"type":"Point"}
}