{
  "type": "Feature",
  "properties": {
    "addr:full":"40 4th St SW Plainview MN 55964",
    "addr:housenumber":"40",
    "addr:postcode":"55964",
    "addr:street":"4Th St Sw",
    "iso:country":"US",
    "sg:address":"40 4th St SW",
    "sg:city":"Plainview",
    "sg:classifiers":[
        {
            "category":"Museum",
            "type":"Entertainment"
        }
    ],
    "sg:phone":"+1 507 534 4173",
    "sg:postcode":"55964",
    "sg:province":"MN",
    "wof:name":"Plainview Area History Ctr",
    "wof:placetype":"venue"
},
  "geometry": {"coordinates":[-92.17138799999999,44.16452],"type":"Point"}
}