{
  "type": "Feature",
  "properties": {
    "iso:country":"US",
    "sg:address":"10340 Viking Dr",
    "sg:city":"Eden Prairie",
    "sg:classifiers":[
        {
            "category":"Professional",
            "subcategory":"Computer Services",
            "type":"Services"
        }
    ],
    "sg:phone":"+1 952 914 1491",
    "sg:postcode":"55344",
    "sg:province":"MN",
    "sg:tags":[
        "development",
        "software"
    ],
    "wof:name":"Bsquare Corporation",
    "wof:placetype":"venue"
},
  "geometry": {"coordinates":[-93.409721,44.859785],"type":"Point"}
}