{
  "type": "Feature",
  "properties": {
    "addr:full":"1767 Co Rd 24 Minneota MN 56264",
    "addr:housenumber":"1767;24",
    "addr:postcode":"56264",
    "addr:street":"Co Rd",
    "iso:country":"US",
    "sg:address":"1767 Co Rd 24",
    "sg:city":"Minneota",
    "sg:phone":"+1 507 428 3543",
    "sg:postcode":"56264",
    "sg:province":"MN",
    "sg:tags":[
        "hog",
        "beef",
        "farm",
        "cash",
        "grain",
        "cattle",
        "or",
        "feedlot"
    ],
    "wof:name":"Neal Bot",
    "wof:placetype":"venue"
},
  "geometry": {"coordinates":[-95.93682,44.57259],"type":"Point"}
}