{
  "type": "Feature",
  "properties": {
    "addr:full":"4125 220th St E Faribault MN 55021",
    "addr:housenumber":"4125",
    "addr:postcode":"55021",
    "addr:street":"220Th St E",
    "iso:country":"US",
    "sg:address":"4125 220th St E",
    "sg:city":"Faribault",
    "sg:phone":"+1 507 334 3152",
    "sg:postcode":"55021",
    "sg:province":"MN",
    "sg:tags":[
        "farm",
        "soybean"
    ],
    "wof:name":"Zabel  Merwyn",
    "wof:placetype":"venue"
},
  "geometry": {"coordinates":[-93.217418,44.26874],"type":"Point"}
}