{
  "type": "Feature",
  "properties": {
    "iso:country":"US",
    "sg:address":"3800 American Blvd W",
    "sg:city":"Minneapolis",
    "sg:classifiers":[
        {
            "category":"Insurance",
            "subcategory":"Title Insurance",
            "type":"Services"
        }
    ],
    "sg:phone":"+1 952 806 6430",
    "sg:postcode":"55431",
    "sg:province":"MN",
    "sg:tags":[
        "abstract",
        "carrier"
    ],
    "wof:name":"Title One Inc",
    "wof:placetype":"venue"
},
  "geometry": {"coordinates":[-93.328053,44.855769],"type":"Point"}
}