{
  "type": "Feature",
  "properties": {
    "addr:full":"30827 Pequot Blvd Pequot Lakes MN 56472",
    "addr:housenumber":"30827",
    "addr:postcode":"56472",
    "addr:street":"Pequot Blvd",
    "iso:country":"US",
    "sg:address":"30827 Pequot Blvd",
    "sg:city":"Pequot Lakes",
    "sg:classifiers":[
        {
            "category":"Restaurant",
            "type":"Food & Drink"
        }
    ],
    "sg:phone":"+1 218 568 5262",
    "sg:postcode":"56472",
    "sg:province":"MN",
    "sg:tags":[
        "eating"
    ],
    "wof:name":"Timber Ridge Supper Club",
    "wof:placetype":"venue"
},
  "geometry": {"coordinates":[-94.323711,46.602891],"type":"Point"}
}