{
  "type": "Feature",
  "properties": {
    "iso:country":"US",
    "sg:address":"316 4th Ave",
    "sg:city":"Wilmont",
    "sg:classifiers":[
        {
            "category":"Social Services",
            "type":"Services"
        }
    ],
    "sg:phone":"+1 507 926 5152",
    "sg:postcode":"56185",
    "sg:province":"MN",
    "sg:tags":[
        "senior",
        "citizen"
    ],
    "wof:name":"Wilmont Senior Citizens Ctr",
    "wof:placetype":"venue"
},
  "geometry": {"coordinates":[-95.82772300000001,43.765539],"type":"Point"}
}