{
  "type": "Feature",
  "properties": {
    "addr:full":"506 81st St Lake Wilson MN 56151",
    "addr:housenumber":"506",
    "addr:postcode":"56151",
    "addr:street":"81St St",
    "iso:country":"US",
    "sg:address":"506 81st St",
    "sg:city":"Lake Wilson",
    "sg:classifiers":[
        {
            "category":"Farming",
            "subcategory":"Livestock Farm",
            "type":"Manufacturing & Wholesale Goods"
        }
    ],
    "sg:phone":"+1 507 879 3429",
    "sg:postcode":"56151",
    "sg:province":"MN",
    "sg:tags":[
        "animal",
        "general"
    ],
    "wof:name":"Mark Beek",
    "wof:placetype":"venue"
},
  "geometry": {"coordinates":[-95.9623,43.96449],"type":"Point"}
}