{
  "type": "Feature",
  "properties": {
    "iso:country":"US",
    "sg:address":"502 E 2nd St",
    "sg:city":"Duluth",
    "sg:classifiers":[
        {
            "category":"Organizations",
            "subcategory":"Non-profit Organization",
            "type":"Services"
        }
    ],
    "sg:phone":"+1 218 720 1943",
    "sg:postcode":"55805",
    "sg:province":"MN",
    "sg:tags":[
        "fund",
        "gift",
        "raising"
    ],
    "wof:name":"Miller Dwan Gift Shop",
    "wof:placetype":"venue"
},
  "geometry": {"coordinates":[-92.09291399999999,46.793861],"type":"Point"}
}