{
  "type": "Feature",
  "properties": {
    "addr:full":"14295 Valley View Rd Eden Prairie MN 55344",
    "addr:housenumber":"14295",
    "addr:postcode":"55344",
    "addr:street":"Valley View Rd",
    "iso:country":"US",
    "sg:address":"14295 Valley View Rd",
    "sg:city":"Eden Prairie",
    "sg:classifiers":[
        {
            "category":"Utilities",
            "subcategory":"Telephone",
            "type":"Services"
        }
    ],
    "sg:phone":"+1 952 230 4448",
    "sg:postcode":"55344",
    "sg:province":"MN",
    "sg:tags":[
        "communications"
    ],
    "wof:name":"Onvoy",
    "wof:placetype":"venue"
},
  "geometry": {"coordinates":[-93.46217,44.870461],"type":"Point"}
}