{
  "type": "Feature",
  "properties": {
    "addr:full":"512 10th St S Virginia MN 55792",
    "addr:housenumber":"512",
    "addr:postcode":"55792",
    "addr:street":"10Th St S",
    "iso:country":"US",
    "sg:address":"512 10th St S",
    "sg:city":"Virginia",
    "sg:classifiers":[
        {
            "category":"Communications",
            "subcategory":"Film & Video Production",
            "type":"Services"
        }
    ],
    "sg:phone":"+1 218 741 1836",
    "sg:postcode":"55792",
    "sg:province":"MN",
    "sg:tags":[
        "motion",
        "picture",
        "agency",
        "advertising"
    ],
    "wof:name":"New North Video Production",
    "wof:placetype":"venue"
},
  "geometry": {"coordinates":[-92.540831,47.513877],"type":"Point"}
}