{
  "type": "Feature",
  "properties": {
    "addr:full":"15020 Garrett Ave Saint Paul MN 55124",
    "addr:housenumber":"15020",
    "addr:postcode":"55124",
    "addr:street":"Garrett Ave",
    "iso:country":"US",
    "sg:address":"15020 Garrett Ave",
    "sg:city":"Saint Paul",
    "sg:classifiers":[
        {
            "category":"Food & Beverages",
            "subcategory":"Groceries & Convenience Stores",
            "type":"Retail Goods"
        }
    ],
    "sg:phone":"+1 952 431 6630",
    "sg:postcode":"55124",
    "sg:province":"MN",
    "wof:name":"Superamerica",
    "wof:placetype":"venue"
},
  "geometry": {"coordinates":[-93.2127,44.7314],"type":"Point"}
}