{
  "type": "Feature",
  "properties": {
    "iso:country":"US",
    "sg:address":"8009 Nicollet Ave",
    "sg:city":"Minneapolis",
    "sg:classifiers":[
        {
            "category":"Banks & Credit Unions",
            "subcategory":"Investment Brokerage",
            "type":"Services"
        }
    ],
    "sg:phone":"+1 952 888 8877",
    "sg:postcode":"55420",
    "sg:province":"MN",
    "sg:tags":[
        "advisory",
        "financial"
    ],
    "wof:name":"Neighborhood Financial Svc",
    "wof:placetype":"venue"
},
  "geometry": {"coordinates":[-93.27824200000001,44.858315],"type":"Point"}
}