{
  "type": "Feature",
  "properties": {
    "iso:country":"US",
    "sg:address":"617 130th St",
    "sg:city":"Sherburn",
    "sg:classifiers":[
        {
            "category":"Building & Trades",
            "subcategory":"Construction",
            "type":"Services"
        }
    ],
    "sg:phone":"+1 507 764 8752",
    "sg:postcode":"56171",
    "sg:province":"MN",
    "sg:tags":[
        "nonresidential"
    ],
    "wof:name":"Wayne Lutterman Construction",
    "wof:placetype":"venue"
},
  "geometry": {"coordinates":[-94.75099,43.674866],"type":"Point"}
}