{
  "type": "Feature",
  "properties": {
    "iso:country":"US",
    "sg:address":"2500 Co Rd 88",
    "sg:city":"Minneapolis",
    "sg:classifiers":[
        {
            "category":"Banks & Credit Unions",
            "subcategory":"Bank",
            "type":"Services"
        }
    ],
    "sg:phone":"+1 612 789 4663",
    "sg:postcode":"55418",
    "sg:province":"MN",
    "sg:tags":[
        "loan"
    ],
    "wof:name":"Lake Pointe Lending",
    "wof:placetype":"venue"
},
  "geometry": {"coordinates":[-93.219498,45.013321],"type":"Point"}
}