{
  "type": "Feature",
  "properties": {
    "addr:full":"287 Marschall Rd Ste 106 Shakopee MN 55379",
    "addr:housenumber":"287",
    "addr:postcode":"55379",
    "addr:street":"Marschall Rd Ste 106",
    "iso:country":"US",
    "sg:address":"287 Marschall Rd Ste 106",
    "sg:city":"Shakopee",
    "sg:classifiers":[
        {
            "category":"Health Services",
            "subcategory":"Doctor",
            "type":"Services"
        },
        {
            "category":"Health Services",
            "subcategory":"Clinic",
            "type":"Services"
        },
        {
            "category":"Health Services",
            "subcategory":"Podiatrist",
            "type":"Services"
        }
    ],
    "sg:phone":"+1 952 445 5390",
    "sg:postcode":"55379",
    "sg:province":"MN",
    "sg:tags":[
        "physician",
        "medical",
        "surgeons",
        "medicine",
        "surgeon",
        "sport"
    ],
    "wof:name":"Foot Specialists & Surgeons",
    "wof:placetype":"venue"
},
  "geometry": {"coordinates":[-93.50859800000001,44.798801],"type":"Point"}
}