{
  "type": "Feature",
  "properties": {
    "iso:country":"US",
    "sg:address":"2851 310th Ave",
    "sg:city":"Foxhome",
    "sg:phone":"+1 218 736 6262",
    "sg:postcode":"56510",
    "sg:province":"MN",
    "sg:tags":[
        "farm"
    ],
    "wof:name":"Charles Steiner Farms",
    "wof:placetype":"venue"
},
  "geometry": {"coordinates":[-96.45550900000001,47.455743],"type":"Point"}
}