{
  "type": "Feature",
  "properties": {
    "iso:country":"US",
    "sg:address":"403 Eli Rd",
    "sg:city":"Saint Paul",
    "sg:classifiers":[
        {
            "category":"Professional",
            "subcategory":"Business Services",
            "type":"Services"
        }
    ],
    "sg:phone":"+1 651 483 8506",
    "sg:postcode":"55117",
    "sg:province":"MN",
    "wof:name":"Sandpaper Design Studios",
    "wof:placetype":"venue"
},
  "geometry": {"coordinates":[-93.083893,45.02538],"type":"Point"}
}