{
  "type": "Feature",
  "properties": {
    "iso:country":"US",
    "sg:address":"72670 State Hwy 16",
    "sg:city":"Grand Meadow",
    "sg:classifiers":[
        {
            "category":"Freight",
            "type":"Transportation"
        }
    ],
    "sg:phone":"+1 507 754 5247",
    "sg:postcode":"55936",
    "sg:province":"MN",
    "sg:tags":[
        "dry",
        "bulk",
        "trucking"
    ],
    "wof:name":"Irlbeck Grain Inc",
    "wof:placetype":"venue"
},
  "geometry": {"coordinates":[-92.596446,43.710339],"type":"Point"}
}