{
  "type": "Feature",
  "properties": {
    "iso:country":"US",
    "sg:address":"116 W 2nd St",
    "sg:city":"Litchfield",
    "sg:classifiers":[
        {
            "category":"Professional",
            "type":"Services"
        }
    ],
    "sg:phone":"+1 320 593 1955",
    "sg:postcode":"55355",
    "sg:province":"MN",
    "wof:name":"Ls Customs",
    "wof:placetype":"venue"
},
  "geometry": {"coordinates":[-94.530839,45.127464],"type":"Point"}
}