{
  "type": "Feature",
  "properties": {
    "iso:country":"US",
    "sg:address":"68996 205th St",
    "sg:city":"Darwin",
    "sg:classifiers":[
        {
            "category":"Farming",
            "subcategory":"Farm",
            "type":"Manufacturing & Wholesale Goods"
        }
    ],
    "sg:phone":"+1 320 275 5418",
    "sg:postcode":"55324",
    "sg:province":"MN",
    "wof:name":"Carlson Brothers Of Darwin",
    "wof:placetype":"venue"
},
  "geometry": {"coordinates":[-94.378266,45.044132],"type":"Point"}
}