{
  "type": "Feature",
  "properties": {
    "iso:country":"US",
    "sg:address":"9 Joymar Dr",
    "sg:city":"St Cloud",
    "sg:classifiers":[
        {
            "category":"Food & Beverages",
            "subcategory":"Groceries & Convenience Stores",
            "type":"Retail Goods"
        }
    ],
    "sg:phone":"+1 320 230 2915",
    "sg:postcode":"56301",
    "sg:province":"MN",
    "sg:tags":[
        "grocer"
    ],
    "wof:name":"Gallito Tienda Mexicana",
    "wof:placetype":"venue"
},
  "geometry": {"coordinates":[-94.26342,45.525949],"type":"Point"}
}