{
  "type": "Feature",
  "properties": {
    "iso:country":"US",
    "sg:address":"230 E 3rd St",
    "sg:city":"Redwood Falls",
    "sg:classifiers":[
        {
            "category":"Professional",
            "subcategory":"Lawyer & Legal Services",
            "type":"Services"
        }
    ],
    "sg:phone":"+1 507 637 8909",
    "sg:postcode":"56283",
    "sg:province":"MN",
    "sg:tags":[
        "attorney"
    ],
    "wof:name":"WALZ Law Office",
    "wof:placetype":"venue"
},
  "geometry": {"coordinates":[-95.117593,44.539512],"type":"Point"}
}