{
  "type": "Feature",
  "properties": {
    "addr:full":"6300 Earle Brown Dr Minneapolis MN 55430",
    "addr:housenumber":"6300",
    "addr:postcode":"55430",
    "addr:street":"Earle Brown Dr",
    "iso:country":"US",
    "sg:address":"6300 Earle Brown Dr",
    "sg:city":"Minneapolis",
    "sg:classifiers":[
        {
            "category":"Travel",
            "subcategory":"Hotels & Motels",
            "type":"Entertainment"
        }
    ],
    "sg:phone":"+1 763 560 2700",
    "sg:postcode":"55430",
    "sg:province":"MN",
    "sg:tags":[
        "lodging"
    ],
    "wof:name":"Embassy Suites Minneapolis-Brooklyn Center",
    "wof:placetype":"venue"
},
  "geometry": {"coordinates":[-93.303337,45.068601],"type":"Point"}
}