{
  "type": "Feature",
  "properties": {
    "addr:full":"12844 Co Rd 1 Wadena MN 56482",
    "addr:housenumber":"12844",
    "addr:postcode":"56482",
    "addr:street":"Co Rd 1",
    "iso:country":"US",
    "sg:address":"12844 Co Rd 1",
    "sg:city":"Wadena",
    "sg:classifiers":[
        {
            "category":"Farming",
            "subcategory":"Dairy Farm",
            "type":"Manufacturing & Wholesale Goods"
        }
    ],
    "sg:phone":"+1 218 631 2064",
    "sg:postcode":"56482",
    "sg:province":"MN",
    "wof:name":"Jack Witthuhn",
    "wof:placetype":"venue"
},
  "geometry": {"coordinates":[-95.098637,46.383509],"type":"Point"}
}