{
  "type": "Feature",
  "properties": {
    "addr:full":"317 4th St NW Bemidji MN 56601",
    "addr:housenumber":"317",
    "addr:postcode":"56601",
    "addr:street":"4Th St Nw",
    "iso:country":"US",
    "sg:address":"317 4th St NW",
    "sg:city":"Bemidji",
    "sg:classifiers":[
        {
            "category":"Government",
            "subcategory":"Court House",
            "type":"Public Place"
        }
    ],
    "sg:phone":"+1 218 759 3575",
    "sg:postcode":"56601",
    "sg:province":"MN",
    "sg:tags":[
        "city",
        "counsel"
    ],
    "wof:name":"Bemidji City Attorney",
    "wof:placetype":"venue"
},
  "geometry": {"coordinates":[-94.88406999999999,47.471664],"type":"Point"}
}