{
  "type": "Feature",
  "properties": {
    "iso:country":"US",
    "sg:address":"28 Nathan Ln N",
    "sg:city":"Plymouth",
    "sg:classifiers":[
        {
            "category":"Health Services",
            "subcategory":"Doctor",
            "type":"Services"
        }
    ],
    "sg:phone":"+1 763 541 4898",
    "sg:postcode":"55441",
    "sg:province":"MN",
    "sg:tags":[
        "dentist"
    ],
    "wof:name":"Gilbert Dental",
    "wof:placetype":"venue"
},
  "geometry": {"coordinates":[-93.40825,44.978917],"type":"Point"}
}