{
  "type": "Feature",
  "properties": {
    "addr:full":"3939 W 50th St Ste 201 Minneapolis MN 55424",
    "addr:housenumber":"3939",
    "addr:postcode":"55424",
    "addr:street":"W 50Th St Ste 201",
    "iso:country":"US",
    "sg:address":"3939 W 50th St Ste 201",
    "sg:city":"Minneapolis",
    "sg:classifiers":[
        {
            "category":"Health Services",
            "subcategory":"Dentist",
            "type":"Services"
        }
    ],
    "sg:phone":"+1 952 922 4118",
    "sg:postcode":"55424",
    "sg:province":"MN",
    "sg:tags":[
        "dentists-endodontists"
    ],
    "wof:name":"Kitzenberg Tillie-Advanced Endodontics Specialists",
    "wof:placetype":"venue"
},
  "geometry": {"coordinates":[-93.32956799999999,44.912538],"type":"Point"}
}