{
  "type": "Feature",
  "properties": {
    "iso:country":"US",
    "sg:address":"325 Van Brunt St",
    "sg:city":"Mankato",
    "sg:classifiers":[
        {
            "category":"Building & Trades",
            "subcategory":"Construction",
            "type":"Services"
        }
    ],
    "sg:phone":"+1 507 387 7004",
    "sg:postcode":"56001",
    "sg:province":"MN",
    "sg:tags":[
        "general",
        "contractor"
    ],
    "wof:name":"Randy Johnson Construction",
    "wof:placetype":"venue"
},
  "geometry": {"coordinates":[-94.011697,44.158366],"type":"Point"}
}