{
  "type": "Feature",
  "properties": {
    "iso:country":"US",
    "sg:address":"55678 Farm Camp Rd",
    "sg:city":"Bigfork",
    "sg:classifiers":[
        {
            "category":"Farming",
            "subcategory":"Livestock Farm",
            "type":"Manufacturing & Wholesale Goods"
        }
    ],
    "sg:phone":"+1 218 743 3379",
    "sg:postcode":"56628",
    "sg:province":"MN",
    "sg:tags":[
        "beef",
        "cash",
        "crop",
        "field",
        "grain",
        "cattle",
        "feedlot"
    ],
    "wof:name":"Rice River Ranch",
    "wof:placetype":"venue"
},
  "geometry": {"coordinates":[-93.656397,47.682241],"type":"Point"}
}