{
  "type": "Feature",
  "properties": {
    "addr:full":"818 Grand St SE Chatfield MN 55923",
    "addr:housenumber":"818",
    "addr:postcode":"55923",
    "addr:street":"Grand St Se",
    "iso:country":"US",
    "sg:address":"818 Grand St SE",
    "sg:city":"Chatfield",
    "sg:classifiers":[
        {
            "category":"Autos & Motor Vehicles",
            "subcategory":"Automobile Sales",
            "type":"Retail Goods"
        }
    ],
    "sg:phone":"+1 507 273 5778",
    "sg:postcode":"55923",
    "sg:province":"MN",
    "wof:name":"Street Dreams",
    "wof:placetype":"venue"
},
  "geometry": {"coordinates":[-92.180604,43.843161],"type":"Point"}
}