{
  "type": "Feature",
  "properties": {
    "iso:country":"US",
    "sg:address":"1685 University Ave W",
    "sg:city":"Saint Paul",
    "sg:classifiers":[
        {
            "category":"Shopping",
            "subcategory":"Clothing, Apparel, & Fashions",
            "type":"Retail Goods"
        }
    ],
    "sg:phone":"+1 651 645 2922",
    "sg:postcode":"55104",
    "sg:province":"MN",
    "wof:name":"MILTON CLOTHING DIVISION (MEN",
    "wof:placetype":"venue"
},
  "geometry": {"coordinates":[-93.17163499999999,44.955733],"type":"Point"}
}