{
  "type": "Feature",
  "properties": {
    "addr:full":"1400 Lagoon Ave Minneapolis MN 55408",
    "addr:housenumber":"1400",
    "addr:postcode":"55408",
    "addr:street":"Lagoon Ave",
    "iso:country":"US",
    "sg:address":"1400 Lagoon Ave",
    "sg:city":"Minneapolis",
    "sg:classifiers":[
        {
            "category":"Restaurant",
            "type":"Food & Drink"
        }
    ],
    "sg:phone":"+1 612 455 5626",
    "sg:postcode":"55408",
    "sg:province":"MN",
    "sg:website":"www.burrito-loco.com",
    "wof:name":"Burrito Loco Uptown",
    "wof:placetype":"venue"
},
  "geometry": {"coordinates":[-93.29827899999999,44.949256],"type":"Point"}
}