{
  "type": "Feature",
  "properties": {
    "iso:country":"US",
    "sg:address":"824 Aspen Cir",
    "sg:city":"Saint Paul",
    "sg:classifiers":[
        {
            "category":"Organizations",
            "subcategory":"Membership Organization",
            "type":"Services"
        }
    ],
    "sg:phone":"+1 651 490 0997",
    "sg:postcode":"55109",
    "sg:province":"MN",
    "wof:name":"Minnesota Bass Chpter Fdration",
    "wof:placetype":"venue"
},
  "geometry": {"coordinates":[-93.063323,45.034862],"type":"Point"}
}