{
  "type": "Feature",
  "properties": {
    "addr:full":"119 State Hwy 34 Nevis MN 56467",
    "addr:housenumber":"119",
    "addr:postcode":"nevis;56467",
    "addr:street":"State Hwy 34",
    "iso:country":"US",
    "sg:address":"119 State Hwy 34",
    "sg:city":"Nevis",
    "sg:classifiers":[
        {
            "category":"Professional",
            "type":"Services"
        }
    ],
    "sg:phone":"+1 218 652 3465",
    "sg:postcode":"56467",
    "sg:province":"MN",
    "sg:tags":[
        "establishment"
    ],
    "wof:name":"Terry's Shop",
    "wof:placetype":"venue"
},
  "geometry": {"coordinates":[-94.839039,46.964179],"type":"Point"}
}