{
  "type": "Feature",
  "properties": {
    "iso:country":"US",
    "sg:address":"2347 Commerce Dr",
    "sg:city":"Hastings",
    "sg:classifiers":[
        {
            "category":"Building & Trades",
            "subcategory":"Construction",
            "type":"Services"
        }
    ],
    "sg:phone":"+1 651 480 8575",
    "sg:postcode":"55033",
    "sg:province":"MN",
    "sg:tags":[
        "sewer",
        "contractor"
    ],
    "wof:name":"Nova Frost Inc",
    "wof:placetype":"venue"
},
  "geometry": {"coordinates":[-92.844111,44.720067],"type":"Point"}
}