{
  "type": "Feature",
  "properties": {
    "addr:full":"4741 Munger Shaw Rd Saginaw MN 55779",
    "addr:housenumber":"4741",
    "addr:postcode":"55779",
    "addr:street":"Munger Shaw Rd",
    "iso:country":"US",
    "sg:address":"4741 Munger Shaw Rd",
    "sg:city":"Saginaw",
    "sg:classifiers":[
        {
            "category":"Real Estate",
            "subcategory":"Developer",
            "type":"Services"
        }
    ],
    "sg:phone":"+1 218 729 5284",
    "sg:postcode":"55779",
    "sg:province":"MN",
    "sg:tags":[
        "investing"
    ],
    "wof:name":"North Star Real Estate Inc",
    "wof:placetype":"venue"
},
  "geometry": {"coordinates":[-92.34353400000001,46.863898],"type":"Point"}
}