{
  "type": "Feature",
  "properties": {
    "addr:full":"11552 Spruce Center Dr NE Miltona MN 56354",
    "addr:housenumber":"11552",
    "addr:postcode":"56354",
    "addr:street":"Spruce Center Dr Ne",
    "iso:country":"US",
    "sg:address":"11552 Spruce Center Dr NE",
    "sg:city":"Miltona",
    "sg:classifiers":[
        {
            "category":"Shopping",
            "subcategory":"Bicycles & Sporting Goods",
            "type":"Retail Goods"
        },
        {
            "category":"Farming",
            "subcategory":"Aquatic Farm",
            "type":"Manufacturing & Wholesale Goods"
        }
    ],
    "sg:phone":"+1 218 943 2825",
    "sg:postcode":"56354",
    "sg:province":"MN",
    "sg:tags":[
        "bait",
        "fishing"
    ],
    "wof:name":"Spruce Center Bait Co",
    "wof:placetype":"venue"
},
  "geometry": {"coordinates":[-95.22161699999999,46.07051],"type":"Point"}
}