{
  "type": "Feature",
  "properties": {
    "addr:full":"3434 Washington Dr Eagan MN 55122",
    "addr:housenumber":"3434",
    "addr:postcode":"55122",
    "addr:street":"Washington Dr",
    "iso:country":"US",
    "sg:address":"3434 Washington Dr",
    "sg:city":"Eagan",
    "sg:classifiers":[
        {
            "category":"Restaurant",
            "type":"Food & Drink"
        }
    ],
    "sg:phone":"+1 651 454 9000",
    "sg:postcode":"55122",
    "sg:province":"MN",
    "sg:website":"www.albakers.com",
    "wof:name":"Al Baker's Restaurant",
    "wof:placetype":"venue"
},
  "geometry": {"coordinates":[-93.16939499999999,44.832868],"type":"Point"}
}