{
  "type": "Feature",
  "properties": {
    "iso:country":"US",
    "sg:address":"3516 Rum River Dr",
    "sg:city":"Anoka",
    "sg:classifiers":[
        {
            "category":"Professional",
            "type":"Services"
        }
    ],
    "sg:phone":"+1 763 421 6866",
    "sg:postcode":"55303",
    "sg:province":"MN",
    "wof:name":"Eleanor Zwiers",
    "wof:placetype":"venue"
},
  "geometry": {"coordinates":[-93.387936,45.21806],"type":"Point"}
}