{
  "type": "Feature",
  "properties": {
    "addr:full":"42322 Co Hwy 41 Vergas MN 56587",
    "addr:housenumber":"42322",
    "addr:postcode":"56587",
    "addr:street":"Co Hwy 41",
    "iso:country":"US",
    "sg:address":"42322 Co Hwy 41",
    "sg:city":"Vergas",
    "sg:classifiers":[
        {
            "category":"Food & Beverages",
            "subcategory":"Specialty",
            "type":"Retail Goods"
        }
    ],
    "sg:phone":"+1 218 342 2748",
    "sg:postcode":"56587",
    "sg:province":"MN",
    "wof:name":"Rimfire Brand",
    "wof:placetype":"venue"
},
  "geometry": {"coordinates":[-95.854907,46.576902],"type":"Point"}
}