{
  "type": "Feature",
  "properties": {
    "iso:country":"US",
    "sg:address":"12130 Lynn Ave",
    "sg:city":"Savage",
    "sg:classifiers":[
        {
            "category":"Shopping",
            "subcategory":"Stationery & Office Supplies",
            "type":"Retail Goods"
        }
    ],
    "sg:phone":"+1 952 890 2120",
    "sg:postcode":"55378",
    "sg:province":"MN",
    "sg:website":"http://www.silgancontainers.com",
    "wof:name":"Silgan",
    "wof:placetype":"venue"
},
  "geometry": {"coordinates":[-93.33638500000001,44.780609],"type":"Point"}
}