{
  "type": "Feature",
  "properties": {
    "addr:full":"927 S State St Fairmont MN 56031",
    "addr:housenumber":"927",
    "addr:postcode":"56031",
    "addr:street":"S State St",
    "iso:country":"US",
    "sg:address":"927 S State St",
    "sg:city":"Fairmont",
    "sg:classifiers":[
        {
            "category":"Cinema",
            "subcategory":"Movie Rental",
            "type":"Entertainment"
        }
    ],
    "sg:phone":"+1 507 235 8033",
    "sg:postcode":"56031",
    "sg:province":"MN",
    "sg:tags":[
        "video",
        "tape"
    ],
    "wof:name":"Movie Brands Inc",
    "wof:placetype":"venue"
},
  "geometry": {"coordinates":[-94.44741999999999,43.645186],"type":"Point"}
}