{
  "type": "Feature",
  "properties": {
    "addr:full":"953 Park Ave Hamburg MN 55339",
    "addr:housenumber":"953",
    "addr:postcode":"55339",
    "addr:street":"Park Ave",
    "iso:country":"US",
    "sg:address":"953 Park Ave",
    "sg:city":"Hamburg",
    "sg:classifiers":[
        {
            "category":"Professional",
            "type":"Services"
        }
    ],
    "sg:phone":"+1 952 467 3858",
    "sg:postcode":"55339",
    "sg:province":"MN",
    "wof:name":"Thaemert Custom Work Inc",
    "wof:placetype":"venue"
},
  "geometry": {"coordinates":[-93.95694399999999,44.731869],"type":"Point"}
}