{
  "type": "Feature",
  "properties": {
    "addr:full":"695 Jefferson St N Wadena MN 56482",
    "addr:housenumber":"695",
    "addr:postcode":"56482",
    "addr:street":"Jefferson St N",
    "iso:country":"US",
    "sg:address":"695 Jefferson St N",
    "sg:city":"Wadena",
    "sg:classifiers":[
        {
            "category":"Travel",
            "subcategory":"Hotels & Motels",
            "type":"Entertainment"
        }
    ],
    "sg:phone":"+1 218 631 1580",
    "sg:postcode":"56482",
    "sg:province":"MN",
    "wof:name":"AmericInn",
    "wof:placetype":"venue"
},
  "geometry": {"coordinates":[-95.13101,46.447719],"type":"Point"}
}