{
  "type": "Feature",
  "properties": {
    "addr:full":"9957 65th St NE Albertville MN 55301",
    "addr:housenumber":"9957",
    "addr:postcode":"55301",
    "addr:street":"65Th St Ne",
    "iso:country":"US",
    "sg:address":"9957 65th St NE",
    "sg:city":"Albertville",
    "sg:classifiers":[
        {
            "category":"Restaurant",
            "type":"Food & Drink"
        }
    ],
    "sg:phone":"+1 763 497 2714",
    "sg:postcode":"55301",
    "sg:province":"MN",
    "sg:tags":[
        "eating",
        "caterer"
    ],
    "sg:website":"http://www.broastercateringmn.com/",
    "wof:name":"Broaster Catering",
    "wof:placetype":"venue"
},
  "geometry": {"coordinates":[-93.68509899999999,45.24514],"type":"Point"}
}