{
  "type": "Feature",
  "properties": {
    "addr:full":"730 Mainstreet Hopkins MN 55343",
    "addr:housenumber":"730",
    "addr:postcode":"55343",
    "addr:street":"Mainstreet",
    "iso:country":"US",
    "sg:address":"730 Mainstreet",
    "sg:city":"Hopkins",
    "sg:classifiers":[
        {
            "category":"Personal",
            "subcategory":"Beauty Salon",
            "type":"Services"
        }
    ],
    "sg:phone":"+1 952 746 1899",
    "sg:postcode":"55343",
    "sg:province":"MN",
    "sg:tags":[
        "shop",
        "manicuring"
    ],
    "wof:name":"B T Nails",
    "wof:placetype":"venue"
},
  "geometry": {"coordinates":[-93.40984,44.924325],"type":"Point"}
}