{
  "type": "Feature",
  "properties": {
    "addr:full":"11064 Zumbrota Ct NE Minneapolis MN 55449",
    "addr:housenumber":"11064",
    "addr:postcode":"55449",
    "addr:street":"Zumbrota Ct Ne",
    "iso:country":"US",
    "sg:address":"11064 Zumbrota Ct NE",
    "sg:city":"Minneapolis",
    "sg:classifiers":[
        {
            "category":"Building & Trades",
            "subcategory":"Construction",
            "type":"Services"
        }
    ],
    "sg:phone":"+1 763 780 2678",
    "sg:postcode":"55449",
    "sg:province":"MN",
    "sg:tags":[
        "painting",
        "contractor"
    ],
    "wof:name":"Jerry Slepica Painting Inc",
    "wof:placetype":"venue"
},
  "geometry": {"coordinates":[-93.20168200000001,45.169667],"type":"Point"}
}