{
  "type": "Feature",
  "properties": {
    "addr:full":"7133 Morgan Ave S Minneapolis MN 55423",
    "addr:housenumber":"7133",
    "addr:postcode":"55423",
    "addr:street":"Morgan Ave S",
    "iso:country":"US",
    "sg:address":"7133 Morgan Ave S",
    "sg:city":"Minneapolis",
    "sg:classifiers":[
        {
            "category":"Insurance",
            "subcategory":"Insurance Agent",
            "type":"Services"
        }
    ],
    "sg:phone":"+1 612 861 1927",
    "sg:postcode":"55423",
    "sg:province":"MN",
    "wof:name":"Dawald Agency",
    "wof:placetype":"venue"
},
  "geometry": {"coordinates":[-93.30474100000001,44.873299],"type":"Point"}
}