{
  "type": "Feature",
  "properties": {
    "iso:country":"US",
    "sg:address":"206 6th St NE",
    "sg:city":"Barnesville",
    "sg:classifiers":[
        {
            "category":"Building & Trades",
            "subcategory":"Construction",
            "type":"Services"
        }
    ],
    "sg:phone":"+1 218 354 7391",
    "sg:postcode":"56514",
    "sg:province":"MN",
    "sg:tags":[
        "masonry",
        "contractor",
        "mason"
    ],
    "wof:name":"L & H Masonry",
    "wof:placetype":"venue"
},
  "geometry": {"coordinates":[-96.41301,46.654414],"type":"Point"}
}