{
  "type": "Feature",
  "properties": {
    "addr:full":"105 Parkway Ave S Lanesboro MN 55949",
    "addr:housenumber":"105",
    "addr:postcode":"55949",
    "addr:street":"Parkway Ave S Lanesboro",
    "iso:country":"US",
    "sg:address":"105 Parkway Ave S",
    "sg:city":"Lanesboro",
    "sg:classifiers":[
        {
            "category":"Museum",
            "type":"Entertainment"
        }
    ],
    "sg:phone":"+1 507 467 2177",
    "sg:postcode":"55949",
    "sg:province":"MN",
    "wof:name":"Lanesboro Historical Prsrvtn",
    "wof:placetype":"venue"
},
  "geometry": {"coordinates":[-91.977064,43.720906],"type":"Point"}
}