{
  "type": "Feature",
  "properties": {
    "addr:full":"155 S Broadway Alden MN 56009",
    "addr:housenumber":"155",
    "addr:postcode":"56009",
    "addr:street":"S Broadway",
    "iso:country":"US",
    "sg:address":"155 S Broadway",
    "sg:city":"Alden",
    "sg:classifiers":[
        {
            "category":"Personal",
            "type":"Services"
        },
        {
            "category":"Shopping",
            "subcategory":"Florist",
            "type":"Retail Goods"
        }
    ],
    "sg:phone":"+1 507 874 3425",
    "sg:postcode":"56009",
    "sg:province":"MN",
    "sg:tags":[
        "party",
        "planning"
    ],
    "wof:name":"Accents",
    "wof:placetype":"venue"
},
  "geometry": {"coordinates":[-93.576364,43.669571],"type":"Point"}
}