{
  "type": "Feature",
  "properties": {
    "iso:country":"US",
    "sg:address":"2300 American Blvd E",
    "sg:city":"Minneapolis",
    "sg:classifiers":[
        {
            "category":"Travel",
            "subcategory":"Hotels & Motels",
            "type":"Entertainment"
        },
        {
            "category":"Personal",
            "type":"Services"
        },
        {
            "category":"Retail",
            "subcategory":"Event Space",
            "type":"Services"
        },
        {
            "category":"Conference Center",
            "type":"Public Place"
        }
    ],
    "sg:phone":"+1 952 854 3411",
    "sg:postcode":"55425",
    "sg:province":"MN",
    "sg:tags":[
        "facility",
        "lodging",
        "hall",
        "planning",
        "reception",
        "convention",
        "party",
        "meeting",
        "banquet"
    ],
    "sg:website":"http://www.ramada.com/hotel/14208&cid=RANE",
    "wof:name":"Ramada Mall of America - Airport",
    "wof:placetype":"venue"
},
  "geometry": {"coordinates":[-93.238885,44.859135],"type":"Point"}
}