{
  "type": "Feature",
  "properties": {
    "addr:full":"14784 Waco St NW Anoka MN 55303",
    "addr:postcode":"14784;55303",
    "addr:street":"Waco St Nw",
    "iso:country":"US",
    "sg:address":"14784 Waco St NW",
    "sg:city":"Anoka",
    "sg:classifiers":[
        {
            "category":"Professional",
            "subcategory":"Computer Services",
            "type":"Services"
        }
    ],
    "sg:phone":"+1 763 323 9115",
    "sg:postcode":"55303",
    "sg:province":"MN",
    "sg:tags":[
        "communications",
        "datum",
        "telephone"
    ],
    "wof:name":"Creative Juices Web Desig",
    "wof:placetype":"venue"
},
  "geometry": {"coordinates":[-93.39510300000001,45.240281],"type":"Point"}
}