{
  "type": "Feature",
  "properties": {
    "iso:country":"US",
    "sg:address":"5465 260th St",
    "sg:city":"Wyoming",
    "sg:classifiers":[
        {
            "category":"Autos & Motor Vehicles",
            "subcategory":"Automobile Sales",
            "type":"Retail Goods"
        }
    ],
    "sg:phone":"+1 651 462 5161",
    "sg:postcode":"55092",
    "sg:province":"MN",
    "sg:tags":[
        "car",
        "dealer"
    ],
    "wof:name":"Good Used Cars Inc",
    "wof:placetype":"venue"
},
  "geometry": {"coordinates":[-92.99620899999999,45.326534],"type":"Point"}
}