{
  "type": "Feature",
  "properties": {
    "iso:country":"US",
    "sg:address":"2929 University Ave SE",
    "sg:city":"Minneapolis",
    "sg:classifiers":[
        {
            "category":"Coffee & Tea",
            "type":"Food & Drink"
        },
        {
            "category":"Restaurant",
            "type":"Food & Drink"
        }
    ],
    "sg:phone":"+1 612 331 4632",
    "sg:postcode":"55414",
    "sg:province":"MN",
    "sg:tags":[
        "shop",
        "espresso"
    ],
    "wof:name":"Overflow Espresso Cafe",
    "wof:placetype":"venue"
},
  "geometry": {"coordinates":[-93.21463799999999,44.97073],"type":"Point"}
}