{
  "type": "Feature",
  "properties": {
    "iso:country":"US",
    "sg:address":"415 3rd St N",
    "sg:city":"Waite Park",
    "sg:classifiers":[
        {
            "category":"Building & Trades",
            "subcategory":"Electrical",
            "type":"Services"
        },
        {
            "category":"Professional",
            "subcategory":"Detective & Security Services",
            "type":"Services"
        }
    ],
    "sg:phone":"+1 320 255 7027",
    "sg:postcode":"56387",
    "sg:province":"MN",
    "sg:tags":[
        "home",
        "system",
        "automation"
    ],
    "sg:website":"www.cybermationinc.com",
    "wof:name":"Cybermation Inc",
    "wof:placetype":"venue"
},
  "geometry": {"coordinates":[-94.22259699999999,45.558985],"type":"Point"}
}