{
  "type": "Feature",
  "properties": {
    "addr:full":"1515 7th Ave E Hibbing MN 55746",
    "addr:housenumber":"1515",
    "addr:postcode":"55746",
    "addr:street":"7Th Ave E Hibbing",
    "iso:country":"US",
    "sg:address":"1515 7th Ave E",
    "sg:city":"Hibbing",
    "sg:classifiers":[
        {
            "category":"Sports & Exercise",
            "subcategory":"Gym",
            "type":"Entertainment"
        }
    ],
    "sg:phone":"+1 218 262 5593",
    "sg:postcode":"55746",
    "sg:province":"MN",
    "sg:tags":[
        "club",
        "studio",
        "health",
        "gymnasium"
    ],
    "sg:website":"www.mesabaathleticclub.com",
    "wof:name":"Mesaba Athletic Club, Inc",
    "wof:placetype":"venue"
},
  "geometry": {"coordinates":[-92.93414300000001,47.435344],"type":"Point"}
}