{
  "type": "Feature",
  "properties": {
    "addr:full":"315 S Columbia Ave Morris MN 56267",
    "addr:housenumber":"315",
    "addr:postcode":"56267",
    "addr:street":"S Columbia Ave",
    "iso:country":"US",
    "sg:address":"315 S Columbia Ave",
    "sg:city":"Morris",
    "sg:classifiers":[
        {
            "category":"Place Of Worship",
            "subcategory":"Church",
            "type":"Public Place"
        },
        {
            "category":"Place Of Worship",
            "type":"Public Place"
        }
    ],
    "sg:phone":"+1 320 589 2744",
    "sg:postcode":"56267",
    "sg:province":"MN",
    "sg:tags":[
        "lutheran",
        "america",
        "churches-lutheran",
        "churches-lutheran-evangelical"
    ],
    "wof:name":"Zion Lutheran Church LCMS",
    "wof:placetype":"venue"
},
  "geometry": {"coordinates":[-95.901462,45.579553],"type":"Point"}
}