{
  "type": "Feature",
  "properties": {
    "addr:full":"109 E 3rd St Winona MN 55987",
    "addr:housenumber":"109",
    "addr:postcode":"55987",
    "addr:street":"E 3Rd St",
    "iso:country":"US",
    "sg:address":"109 E 3rd St",
    "sg:city":"Winona",
    "sg:classifiers":[
        {
            "category":"Shopping",
            "subcategory":"Stationery & Office Supplies",
            "type":"Retail Goods"
        }
    ],
    "sg:phone":"+1 507 454 4357",
    "sg:postcode":"55987",
    "sg:province":"MN",
    "sg:tags":[
        "merchandise",
        "furniture"
    ],
    "wof:name":"J & K Office Products",
    "wof:placetype":"venue"
},
  "geometry": {"coordinates":[-91.63502099999999,44.05187],"type":"Point"}
}