{
  "type": "Feature",
  "properties": {
    "iso:country":"US",
    "sg:address":"3856 Dight Ave",
    "sg:city":"Minneapolis",
    "sg:classifiers":[
        {
            "category":"Shopping",
            "subcategory":"Stationery & Office Supplies",
            "type":"Retail Goods"
        }
    ],
    "sg:phone":"+1 612 721 2138",
    "sg:postcode":"55406",
    "sg:province":"MN",
    "sg:tags":[
        "partition"
    ],
    "wof:name":"L T Systems",
    "wof:placetype":"venue"
},
  "geometry": {"coordinates":[-93.225863,44.933099],"type":"Point"}
}