{
  "type": "Feature",
  "properties": {
    "addr:full":"15320 75th St SW Prinsburg MN 56281",
    "addr:housenumber":"15320",
    "addr:postcode":"56281",
    "addr:street":"75Th St Sw",
    "iso:country":"US",
    "sg:address":"15320 75th St SW",
    "sg:city":"Prinsburg",
    "sg:phone":"+1 320 978 8740",
    "sg:postcode":"56281",
    "sg:province":"MN",
    "sg:tags":[
        "farm",
        "corn"
    ],
    "wof:name":"Vern Marcus",
    "wof:placetype":"venue"
},
  "geometry": {"coordinates":[-95.145723,44.975325],"type":"Point"}
}