{
  "type": "Feature",
  "properties": {
    "addr:full":"4741 Zealand Ave N Minneapolis MN 55428",
    "addr:housenumber":"4741",
    "addr:postcode":"55428",
    "addr:street":"Zealand Ave N",
    "iso:country":"US",
    "sg:address":"4741 Zealand Ave N",
    "sg:city":"Minneapolis",
    "sg:classifiers":[
        {
            "category":"Organizations",
            "subcategory":"Religious Organization",
            "type":"Services"
        }
    ],
    "sg:phone":"+1 763 533 3473",
    "sg:postcode":"55428",
    "sg:province":"MN",
    "sg:tags":[
        "church"
    ],
    "wof:name":"Joni & Friends",
    "wof:placetype":"venue"
},
  "geometry": {"coordinates":[-93.38806599999999,45.043027],"type":"Point"}
}