{
  "type": "Feature",
  "properties": {
    "addr:full":"810 Lilac Dr N Ste 218 Minneapolis MN 55422",
    "addr:housenumber":"810",
    "addr:postcode":"55422",
    "addr:street":"Lilac Dr N Ste 218",
    "iso:country":"US",
    "sg:address":"810 Lilac Dr N Ste 218",
    "sg:city":"Minneapolis",
    "sg:classifiers":[
        {
            "category":"Professional",
            "subcategory":"Lawyer & Legal Services",
            "type":"Services"
        }
    ],
    "sg:phone":"+1 763 521 6636",
    "sg:postcode":"55422",
    "sg:province":"MN",
    "wof:name":"Corporate Legal Advisors",
    "wof:placetype":"venue"
},
  "geometry": {"coordinates":[-93.348185,44.987123],"type":"Point"}
}