{
  "type": "Feature",
  "properties": {
    "iso:country":"US",
    "sg:address":"5945 University Ave NE",
    "sg:city":"Minneapolis",
    "sg:classifiers":[
        {
            "category":"Wholesale",
            "subcategory":"Electrical",
            "type":"Manufacturing & Wholesale Goods"
        }
    ],
    "sg:phone":"+1 763 571 3001",
    "sg:postcode":"55432",
    "sg:province":"MN",
    "sg:tags":[
        "accessory"
    ],
    "wof:name":"Compact Offer",
    "wof:placetype":"venue"
},
  "geometry": {"coordinates":[-93.263347,45.076534],"type":"Point"}
}