{
  "type": "Feature",
  "properties": {
    "addr:full":"33111 State Hwy 108 Dent MN 56528",
    "addr:housenumber":"33111",
    "addr:postcode":"56528",
    "addr:street":"State Hwy 108",
    "iso:country":"US",
    "sg:address":"33111 State Hwy 108",
    "sg:city":"Dent",
    "sg:phone":"+1 218 758 2181",
    "sg:postcode":"56528",
    "sg:province":"MN",
    "sg:tags":[
        "beef",
        "farm",
        "corn",
        "crop",
        "field",
        "cattle"
    ],
    "wof:name":"Gregory Meyer",
    "wof:placetype":"venue"
},
  "geometry": {"coordinates":[-95.800479,46.556779],"type":"Point"}
}