{
  "type": "Feature",
  "properties": {
    "iso:country":"US",
    "sg:address":"2104 175th St",
    "sg:city":"Fairmont",
    "sg:classifiers":[
        {
            "category":"Farming",
            "subcategory":"Livestock Farm",
            "type":"Manufacturing & Wholesale Goods"
        }
    ],
    "sg:phone":"+1 507 436 5440",
    "sg:postcode":"56031",
    "sg:province":"MN",
    "sg:tags":[
        "hog",
        "corn",
        "soybean"
    ],
    "wof:name":"Lb Pork Inc",
    "wof:placetype":"venue"
},
  "geometry": {"coordinates":[-94.44708799999999,43.738687],"type":"Point"}
}