{
  "type": "Feature",
  "properties": {
    "iso:country":"US",
    "sg:address":"5300 Alpine Dr NW",
    "sg:city":"Anoka",
    "sg:classifiers":[
        {
            "category":"Health Services",
            "subcategory":"Doctor",
            "type":"Services"
        }
    ],
    "sg:phone":"+1 763 427 7180",
    "sg:postcode":"55303",
    "sg:province":"MN",
    "sg:tags":[
        "practice",
        "family"
    ],
    "wof:name":"Probst Timothy J MD",
    "wof:placetype":"venue"
},
  "geometry": {"coordinates":[-93.41439800000001,45.240501],"type":"Point"}
}