{
  "type": "Feature",
  "properties": {
    "addr:full":"317 Minnesota Ave NW Bemidji MN 56601",
    "addr:housenumber":"317",
    "addr:postcode":"56601",
    "addr:street":"Minnesota Ave Nw",
    "iso:country":"US",
    "sg:address":"317 Minnesota Ave NW",
    "sg:city":"Bemidji",
    "sg:classifiers":[
        {
            "category":"Government",
            "subcategory":"Office",
            "type":"Public Place"
        }
    ],
    "sg:phone":"+1 218 759 3583",
    "sg:postcode":"56601",
    "sg:province":"MN",
    "sg:tags":[
        "village"
    ],
    "wof:name":"Bemidji City Streets & Mntnc",
    "wof:placetype":"venue"
},
  "geometry": {"coordinates":[-94.88279799999999,47.471416],"type":"Point"}
}