{
  "type": "Feature",
  "properties": {
    "iso:country":"US",
    "sg:address":"40763 W Island Dr",
    "sg:city":"Rochert",
    "sg:classifiers":[
        {
            "category":"Professional",
            "subcategory":"Business Services",
            "type":"Services"
        }
    ],
    "sg:phone":"+1 218 847 2818",
    "sg:postcode":"56578",
    "sg:province":"MN",
    "wof:name":"Bender Inspection Services",
    "wof:placetype":"venue"
},
  "geometry": {"coordinates":[-95.557119,46.933479],"type":"Point"}
}