{
  "type": "Feature",
  "properties": {
    "addr:full":"62384 310th St Litchfield MN 55355",
    "addr:housenumber":"62384",
    "addr:postcode":"55355",
    "addr:street":"310Th St",
    "iso:country":"US",
    "sg:address":"62384 310th St",
    "sg:city":"Litchfield",
    "sg:classifiers":[
        {
            "category":"Recreation",
            "type":"Entertainment"
        }
    ],
    "sg:phone":"+1 320 693 6658",
    "sg:postcode":"55355",
    "sg:province":"MN",
    "sg:tags":[
        "club",
        "membership"
    ],
    "wof:name":"Mannanah Snow Blazers",
    "wof:placetype":"venue"
},
  "geometry": {"coordinates":[-94.516069,45.196291],"type":"Point"}
}