{
  "type": "Feature",
  "properties": {
    "iso:country":"US",
    "sg:address":"27782 Quarry Rd",
    "sg:city":"Lindstrom",
    "sg:classifiers":[
        {
            "category":"Building & Trades",
            "subcategory":"Construction",
            "type":"Services"
        }
    ],
    "sg:phone":"+1 651 213 2622",
    "sg:postcode":"55045",
    "sg:province":"MN",
    "sg:tags":[
        "concrete",
        "contractor"
    ],
    "wof:name":"A E S Construction Inc",
    "wof:placetype":"venue"
},
  "geometry": {"coordinates":[-92.77112099999999,45.353881],"type":"Point"}
}