{
  "type": "Feature",
  "properties": {
    "addr:full":"2051 Killebrew Dr Bloomington MN 55425",
    "addr:housenumber":"2051",
    "addr:postcode":"55425",
    "addr:street":"Killebrew Dr",
    "iso:country":"US",
    "sg:address":"2051 Killebrew Dr",
    "sg:city":"Bloomington",
    "sg:classifiers":[
        {
            "category":"Banks & Credit Unions",
            "subcategory":"Investment Brokerage",
            "type":"Services"
        }
    ],
    "sg:phone":"+1 952 808 2333",
    "sg:postcode":"55425",
    "sg:province":"MN",
    "sg:tags":[
        "information",
        "security"
    ],
    "wof:name":"Safe Net Inc",
    "wof:placetype":"venue"
},
  "geometry": {"coordinates":[-93.23965699999999,44.852196],"type":"Point"}
}