{
  "type": "Feature",
  "properties": {
    "iso:country":"US",
    "sg:address":"8182 71st St S",
    "sg:city":"Cottage Grove",
    "sg:classifiers":[
        {
            "category":"Social Services",
            "subcategory":"Child Care",
            "type":"Services"
        }
    ],
    "sg:phone":"+1 651 458 9366",
    "sg:postcode":"55016",
    "sg:province":"MN",
    "sg:tags":[
        "day",
        "provider"
    ],
    "wof:name":"Amy Reeves",
    "wof:placetype":"venue"
},
  "geometry": {"coordinates":[-92.940179,44.847424],"type":"Point"}
}