{
  "type": "Feature",
  "properties": {
    "addr:full":"1001 7th St NW Waseca MN 56093",
    "addr:housenumber":"1001",
    "addr:postcode":"56093",
    "addr:street":"7Th St Nw",
    "iso:country":"US",
    "sg:address":"1001 7th St NW",
    "sg:city":"Waseca",
    "sg:classifiers":[
        {
            "category":"Professional",
            "subcategory":"Computer Services",
            "type":"Services"
        }
    ],
    "sg:phone":"+1 507 835 4847",
    "sg:postcode":"56093",
    "sg:province":"MN",
    "sg:tags":[
        "prepackaged",
        "software"
    ],
    "wof:name":"Crystal Image Software In",
    "wof:placetype":"venue"
},
  "geometry": {"coordinates":[-93.516447,44.08759],"type":"Point"}
}