{
  "type": "Feature",
  "properties": {
    "addr:full":"1771 Energy Park Dr Saint Paul MN 55108",
    "addr:housenumber":"1771",
    "addr:postcode":"55108",
    "addr:street":"Energy Park Dr",
    "iso:country":"US",
    "sg:address":"1771 Energy Park Dr",
    "sg:city":"Saint Paul",
    "sg:classifiers":[
        {
            "category":"Arena",
            "subcategory":"Sports Club",
            "type":"Entertainment"
        }
    ],
    "sg:phone":"+1 651 644 6659",
    "sg:postcode":"55108",
    "sg:province":"MN",
    "sg:tags":[
        "professional",
        "team"
    ],
    "wof:name":"St Paul Saints Baseball Team",
    "wof:placetype":"venue"
},
  "geometry": {"coordinates":[-93.1782,44.972301],"type":"Point"}
}