{
  "type": "Feature",
  "properties": {
    "addr:full":"3901 W 50th St Minneapolis MN 55467",
    "addr:housenumber":"3901",
    "addr:postcode":"55467",
    "addr:street":"W 50Th St",
    "iso:country":"US",
    "sg:address":"3901 W 50th St",
    "sg:city":"Minneapolis",
    "sg:classifiers":[
        {
            "category":"Home & Garden",
            "subcategory":"Home Furnishings",
            "type":"Retail Goods"
        }
    ],
    "sg:phone":"+1 952 656 0045",
    "sg:postcode":"55467",
    "sg:province":"MN",
    "sg:tags":[
        "bath",
        "kitchen"
    ],
    "sg:website":"www.surlatable.com",
    "wof:name":"Sur La Table",
    "wof:placetype":"venue"
},
  "geometry": {"coordinates":[-93.32905,44.912516],"type":"Point"}
}