{
  "type": "Feature",
  "properties": {
    "iso:country":"US",
    "sg:address":"134 W Snelling Ave",
    "sg:city":"Appleton",
    "sg:classifiers":[
        {
            "category":"Organizations",
            "subcategory":"Professional Association",
            "type":"Services"
        }
    ],
    "sg:phone":"+1 320 289 1527",
    "sg:postcode":"56208",
    "sg:province":"MN",
    "sg:tags":[
        "business"
    ],
    "sg:website":"www.appletonmn.com",
    "wof:name":"Appleton Chamber Of Commerce",
    "wof:placetype":"venue"
},
  "geometry": {"coordinates":[-96.019789,45.200827],"type":"Point"}
}