{
  "type": "Feature",
  "properties": {
    "addr:full":"14204 Burnhaven Dr Burnsville MN 55306",
    "addr:housenumber":"14204",
    "addr:postcode":"55306",
    "addr:street":"Burnhaven Dr",
    "iso:country":"US",
    "sg:address":"14204 Burnhaven Dr",
    "sg:city":"Burnsville",
    "sg:classifiers":[
        {
            "category":"Shopping",
            "subcategory":"Jewelry",
            "type":"Retail Goods"
        }
    ],
    "sg:phone":"+1 952 435 8601",
    "sg:postcode":"55306",
    "sg:province":"MN",
    "sg:tags":[
        "jeweler"
    ],
    "wof:name":"Gordon's Jewelers",
    "wof:placetype":"venue"
},
  "geometry": {"coordinates":[-93.293986,44.743621],"type":"Point"}
}