{
  "type": "Feature",
  "properties": {
    "addr:full":"56247 Co Rd 13 Mountain Lake MN 56159",
    "addr:housenumber":"56247;13",
    "addr:postcode":"56159",
    "addr:street":"Co Rd",
    "iso:country":"US",
    "sg:address":"56247 Co Rd 13",
    "sg:city":"Mountain Lake",
    "sg:classifiers":[
        {
            "category":"Farming",
            "subcategory":"Livestock Farm",
            "type":"Manufacturing & Wholesale Goods"
        }
    ],
    "sg:phone":"+1 507 427 3561",
    "sg:postcode":"56159",
    "sg:province":"MN",
    "sg:tags":[
        "feedlot",
        "hog",
        "corn",
        "or",
        "soybean"
    ],
    "wof:name":"L H Harder Farms",
    "wof:placetype":"venue"
},
  "geometry": {"coordinates":[-94.95392200000001,43.876774],"type":"Point"}
}