{
  "type": "Feature",
  "properties": {
    "iso:country":"US",
    "sg:address":"415 Oak St",
    "sg:city":"Breckenridge",
    "sg:classifiers":[
        {
            "category":"Health Services",
            "subcategory":"Doctor",
            "type":"Services"
        }
    ],
    "sg:phone":"+1 218 643 3000",
    "sg:postcode":"56520",
    "sg:province":"MN",
    "sg:tags":[
        "dentist"
    ],
    "wof:name":"St Francis Medical Ctr",
    "wof:placetype":"venue"
},
  "geometry": {"coordinates":[-96.594156,46.271618],"type":"Point"}
}