{
  "type": "Feature",
  "properties": {
    "addr:full":"10641 Vincent Ave S Minneapolis MN 55431",
    "addr:housenumber":"10641",
    "addr:postcode":"55431",
    "addr:street":"Vincent Ave S",
    "iso:country":"US",
    "sg:address":"10641 Vincent Ave S",
    "sg:city":"Minneapolis",
    "sg:classifiers":[
        {
            "category":"Professional",
            "subcategory":"Accounting & Tax Preparation",
            "type":"Services"
        }
    ],
    "sg:phone":"+1 952 881 6002",
    "sg:postcode":"55431",
    "sg:province":"MN",
    "sg:tags":[
        "accountant"
    ],
    "wof:name":"Anderson & Anderson",
    "wof:placetype":"venue"
},
  "geometry": {"coordinates":[-93.316712,44.809056],"type":"Point"}
}