{
  "type": "Feature",
  "properties": {
    "addr:full":"103 Main St E Ottertail MN 56571",
    "addr:housenumber":"103",
    "addr:postcode":"56571",
    "addr:street":"Main St E Ottertail",
    "iso:country":"US",
    "sg:address":"103 Main St E",
    "sg:city":"Ottertail",
    "sg:classifiers":[
        {
            "category":"Shopping",
            "subcategory":"Used Merchandise",
            "type":"Retail Goods"
        }
    ],
    "sg:phone":"+1 218 367 2951",
    "sg:postcode":"56571",
    "sg:province":"MN",
    "sg:tags":[
        "antique"
    ],
    "wof:name":"Timeless Wonders",
    "wof:placetype":"venue"
},
  "geometry": {"coordinates":[-95.556665,46.426475],"type":"Point"}
}