{
  "type": "Feature",
  "properties": {
    "iso:country":"US",
    "sg:address":"200 8th Ave NW",
    "sg:city":"Faribault",
    "sg:classifiers":[
        {
            "category":"Airline",
            "type":"Transportation"
        },
        {
            "category":"Professional",
            "subcategory":"Business Services",
            "type":"Services"
        }
    ],
    "sg:phone":"+1 507 332 8765",
    "sg:postcode":"55021",
    "sg:province":"MN",
    "sg:tags":[
        "packaging",
        "courier",
        "air"
    ],
    "wof:name":"1 Stop Postal",
    "wof:placetype":"venue"
},
  "geometry": {"coordinates":[-93.28125,44.292629],"type":"Point"}
}