{
  "type": "Feature",
  "properties": {
    "iso:country":"US",
    "sg:address":"6678 Kara Dr",
    "sg:city":"Eden Prairie",
    "sg:classifiers":[
        {
            "category":"Organizations",
            "subcategory":"Membership Organization",
            "type":"Services"
        }
    ],
    "sg:phone":"+1 952 937 2201",
    "sg:postcode":"55346",
    "sg:province":"MN",
    "wof:name":"Childrens Support Network",
    "wof:placetype":"venue"
},
  "geometry": {"coordinates":[-93.466656,44.881821],"type":"Point"}
}