{
  "type": "Feature",
  "properties": {
    "addr:full":"9839 13th Ave N Plymouth MN 55441",
    "addr:housenumber":"9839",
    "addr:postcode":"55441",
    "addr:street":"13Th Ave N",
    "iso:country":"US",
    "sg:address":"9839 13th Ave N",
    "sg:city":"Plymouth",
    "sg:classifiers":[
        {
            "category":"Wholesale",
            "subcategory":"Electrical",
            "type":"Manufacturing & Wholesale Goods"
        }
    ],
    "sg:phone":"+1 763 533 2030",
    "sg:postcode":"55441",
    "sg:province":"MN",
    "sg:tags":[
        "equipment",
        "lighting",
        "system"
    ],
    "wof:name":"Musco Sports Lighting",
    "wof:placetype":"venue"
},
  "geometry": {"coordinates":[-93.402067,44.992904],"type":"Point"}
}