{
  "type": "Feature",
  "properties": {
    "iso:country":"US",
    "sg:address":"6709 Golden Spike Rd NE",
    "sg:city":"Sauk Rapids",
    "sg:classifiers":[
        {
            "category":"Building & Trades",
            "subcategory":"Construction",
            "type":"Services"
        }
    ],
    "sg:phone":"+1 320 387 3264",
    "sg:postcode":"56379",
    "sg:province":"MN",
    "sg:tags":[
        "nonresidential"
    ],
    "wof:name":"D & D Renovators and Cnstr",
    "wof:placetype":"venue"
},
  "geometry": {"coordinates":[-94.023319,45.663616],"type":"Point"}
}