{
  "type": "Feature",
  "properties": {
    "addr:full":"15700 28th Ave N Minneapolis MN 55447",
    "addr:housenumber":"15700",
    "addr:postcode":"55447",
    "addr:street":"28Th Ave N",
    "iso:country":"US",
    "sg:address":"15700 28th Ave N",
    "sg:city":"Minneapolis",
    "sg:classifiers":[
        {
            "category":"Professional",
            "type":"Services"
        }
    ],
    "sg:phone":"+1 763 553 7868",
    "sg:postcode":"55447",
    "sg:province":"MN",
    "wof:name":"Don J Lucker",
    "wof:placetype":"venue"
},
  "geometry": {"coordinates":[-93.478554,45.011346],"type":"Point"}
}