{
  "type": "Feature",
  "properties": {
    "addr:full":"2202 Meadow Dr Buffalo MN 55313",
    "addr:housenumber":"2202",
    "addr:postcode":"55313",
    "addr:street":"Meadow Dr",
    "iso:country":"US",
    "sg:address":"2202 Meadow Dr",
    "sg:city":"Buffalo",
    "sg:classifiers":[
        {
            "category":"Building & Trades",
            "subcategory":"Construction",
            "type":"Services"
        }
    ],
    "sg:phone":"+1 763 684 4107",
    "sg:postcode":"55313",
    "sg:province":"MN",
    "sg:tags":[
        "house",
        "builder",
        "contractor",
        "home"
    ],
    "wof:name":"M J B Custom Homes Inc",
    "wof:placetype":"venue"
},
  "geometry": {"coordinates":[-93.83595800000001,45.201862],"type":"Point"}
}