{
  "type": "Feature",
  "properties": {
    "iso:country":"US",
    "sg:address":"316 Elm Creek Rd",
    "sg:city":"Champlin",
    "sg:classifiers":[
        {
            "category":"Shopping",
            "subcategory":"Bicycles & Sporting Goods",
            "type":"Retail Goods"
        }
    ],
    "sg:phone":"+1 763 323 4124",
    "sg:postcode":"55316",
    "sg:province":"MN",
    "wof:name":"K&J Sporting Goods",
    "wof:placetype":"venue"
},
  "geometry": {"coordinates":[-93.402349,45.181918],"type":"Point"}
}