{
  "type": "Feature",
  "properties": {
    "addr:full":"1359 Park Rd Chanhassen MN 55317",
    "addr:housenumber":"1359",
    "addr:postcode":"55317",
    "addr:street":"Park Rd",
    "iso:country":"US",
    "sg:address":"1359 Park Rd",
    "sg:city":"Chanhassen",
    "sg:classifiers":[
        {
            "category":"Building & Trades",
            "subcategory":"Construction",
            "type":"Services"
        }
    ],
    "sg:phone":"+1 952 401 9473",
    "sg:postcode":"55317",
    "sg:province":"MN",
    "sg:tags":[
        "residential"
    ],
    "wof:name":"Dream Home Development LLC",
    "wof:placetype":"venue"
},
  "geometry": {"coordinates":[-93.55598000000001,44.858446],"type":"Point"}
}