{
  "type": "Feature",
  "properties": {
    "iso:country":"US",
    "sg:address":"242 E 5th St",
    "sg:city":"Saint Paul",
    "sg:classifiers":[
        {
            "category":"Professional",
            "subcategory":"Management & Consulting",
            "type":"Services"
        }
    ],
    "sg:phone":"+1 651 292 9105",
    "sg:postcode":"55101",
    "sg:province":"MN",
    "sg:tags":[
        "construction",
        "program"
    ],
    "wof:name":"Pegasus Group LLC",
    "wof:placetype":"venue"
},
  "geometry": {"coordinates":[-93.085831,44.949829],"type":"Point"}
}