{
  "type": "Feature",
  "properties": {
    "addr:full":"419 Washington Ave N Minneapolis MN 55401",
    "addr:housenumber":"419",
    "addr:postcode":"55401",
    "addr:street":"Washington Ave N",
    "iso:country":"US",
    "sg:address":"419 Washington Ave N",
    "sg:city":"Minneapolis",
    "sg:classifiers":[
        {
            "category":"Freight",
            "type":"Transportation"
        }
    ],
    "sg:phone":"+1 612 333 4700",
    "sg:postcode":"55401",
    "sg:province":"MN",
    "sg:tags":[
        "self",
        "storage"
    ],
    "sg:website":"http://www.internetexchangebldg.com",
    "wof:name":"S & S Development Corporation",
    "wof:placetype":"venue"
},
  "geometry": {"coordinates":[-93.27430099999999,44.985796],"type":"Point"}
}