{
  "type": "Feature",
  "properties": {
    "addr:full":"2586 SE 28th St Owatonna MN 55060",
    "addr:housenumber":"2586",
    "addr:postcode":"55060",
    "addr:street":"Se 28Th St",
    "iso:country":"US",
    "sg:address":"2586 SE 28th St",
    "sg:city":"Owatonna",
    "sg:classifiers":[
        {
            "category":"Utilities",
            "subcategory":"Natural Gas",
            "type":"Services"
        }
    ],
    "sg:phone":"+1 507 451 7760",
    "sg:postcode":"55060",
    "sg:province":"MN",
    "sg:tags":[
        "transmission"
    ],
    "wof:name":"Northern Natural Gas Company",
    "wof:placetype":"venue"
},
  "geometry": {"coordinates":[-93.182498,44.051603],"type":"Point"}
}