{
  "type": "Feature",
  "properties": {
    "addr:full":"410 2nd Ave SE Waseca MN 56093",
    "addr:housenumber":"410",
    "addr:postcode":"56093",
    "addr:street":"2Nd Ave Se",
    "iso:country":"US",
    "sg:address":"410 2nd Ave SE",
    "sg:city":"Waseca",
    "sg:classifiers":[
        {
            "category":"Professional",
            "subcategory":"Business Services",
            "type":"Services"
        }
    ],
    "sg:phone":"+1 507 833 2311",
    "sg:postcode":"56093",
    "sg:province":"MN",
    "wof:name":"Renovator Plus",
    "wof:placetype":"venue"
},
  "geometry": {"coordinates":[-93.501955,44.076735],"type":"Point"}
}