{
  "type": "Feature",
  "properties": {
    "addr:full":"6800 Brooklyn Blvd Minneapolis MN 55429",
    "addr:housenumber":"6800",
    "addr:postcode":"55429",
    "addr:street":"Brooklyn Blvd",
    "iso:country":"US",
    "sg:address":"6800 Brooklyn Blvd",
    "sg:city":"Minneapolis",
    "sg:classifiers":[
        {
            "category":"Autos & Motor Vehicles",
            "subcategory":"Automobile Sales",
            "type":"Retail Goods"
        }
    ],
    "sg:phone":"+1 763 560 8000",
    "sg:postcode":"55429",
    "sg:province":"MN",
    "sg:tags":[
        "new",
        "car"
    ],
    "wof:name":"Luther Brookdale Dodge",
    "wof:placetype":"venue"
},
  "geometry": {"coordinates":[-93.334999,45.07835],"type":"Point"}
}