{
  "type": "Feature",
  "properties": {
    "iso:country":"US",
    "sg:address":"16890 280th Ave",
    "sg:city":"Glenwood",
    "sg:classifiers":[
        {
            "category":"Real Estate",
            "subcategory":"Real Estate Operator",
            "type":"Services"
        }
    ],
    "sg:phone":"+1 320 239 2639",
    "sg:postcode":"56334",
    "sg:province":"MN",
    "sg:tags":[
        "property",
        "lessor"
    ],
    "wof:name":"Darwin Boe",
    "wof:placetype":"venue"
},
  "geometry": {"coordinates":[-95.51014499999999,45.667778],"type":"Point"}
}