{
  "type": "Feature",
  "properties": {
    "iso:country":"US",
    "sg:address":"790 S Cleveland Ave",
    "sg:city":"St Paul",
    "sg:classifiers":[
        {
            "category":"Manufacturing",
            "subcategory":"Rubber & Plastics",
            "type":"Manufacturing & Wholesale Goods"
        }
    ],
    "sg:phone":"+1 651 646 1414",
    "sg:postcode":"55116",
    "sg:province":"MN",
    "sg:tags":[
        "product",
        "mfg"
    ],
    "sg:website":"www.lidcoproducts.com",
    "wof:name":"Lidco Products",
    "wof:placetype":"venue"
},
  "geometry": {"coordinates":[-93.187299,44.917599],"type":"Point"}
}