{
  "type": "Feature",
  "properties": {
    "iso:country":"US",
    "sg:address":"16563 Fallbrook Dr",
    "sg:city":"Farmington",
    "sg:classifiers":[
        {
            "category":"Professional",
            "subcategory":"Testing Lab",
            "type":"Services"
        }
    ],
    "sg:phone":"+1 952 997 3178",
    "sg:postcode":"55024",
    "sg:province":"MN",
    "sg:tags":[
        "chemist"
    ],
    "wof:name":"Envirospin, Inc.",
    "wof:placetype":"venue"
},
  "geometry": {"coordinates":[-93.191141,44.7082],"type":"Point"}
}