{
  "type": "Feature",
  "properties": {
    "addr:full":"525 Beverly St Wanamingo MN 55983",
    "addr:housenumber":"525",
    "addr:postcode":"55983",
    "addr:street":"Beverly St",
    "iso:country":"US",
    "sg:address":"525 Beverly St",
    "sg:city":"Wanamingo",
    "sg:classifiers":[
        {
            "category":"Organizations",
            "subcategory":"Religious Organization",
            "type":"Services"
        }
    ],
    "sg:phone":"+1 507 824 3019",
    "sg:postcode":"55983",
    "sg:province":"MN",
    "sg:tags":[
        "church"
    ],
    "wof:name":"New Life Church",
    "wof:placetype":"venue"
},
  "geometry": {"coordinates":[-92.782021,44.299679],"type":"Point"}
}