{
  "type": "Feature",
  "properties": {
    "addr:full":"823 N 56th Ave W Duluth MN 55807",
    "addr:housenumber":"823",
    "addr:postcode":"55807",
    "addr:street":"N 56Th Ave W",
    "iso:country":"US",
    "sg:address":"823 N 56th Ave W",
    "sg:city":"Duluth",
    "sg:classifiers":[
        {
            "category":"Professional",
            "type":"Services"
        }
    ],
    "sg:phone":"+1 218 628 7014",
    "sg:postcode":"55807",
    "sg:province":"MN",
    "wof:name":"Tori Tjaden",
    "wof:placetype":"venue"
},
  "geometry": {"coordinates":[-92.167928,46.744715],"type":"Point"}
}