{
  "type": "Feature",
  "properties": {
    "iso:country":"US",
    "sg:address":"617 S State St",
    "sg:city":"Fairmont",
    "sg:classifiers":[
        {
            "category":"Sports & Exercise",
            "subcategory":"Bowling",
            "type":"Entertainment"
        }
    ],
    "sg:phone":"+1 507 235 5719",
    "sg:postcode":"56031",
    "sg:province":"MN",
    "sg:tags":[
        "lounge",
        "center",
        "cocktail"
    ],
    "sg:website":"www.bowlmor-lanes.com",
    "wof:name":"Bowlmor Lanes & Lounge",
    "wof:placetype":"venue"
},
  "geometry": {"coordinates":[-94.447221,43.648025],"type":"Point"}
}