{
  "type": "Feature",
  "properties": {
    "iso:country":"US",
    "sg:address":"404 W Superior St",
    "sg:city":"Duluth",
    "sg:classifiers":[
        {
            "category":"Health Services",
            "subcategory":"Chiropractor",
            "type":"Services"
        }
    ],
    "sg:phone":"+1 218 740 4321",
    "sg:postcode":"55802",
    "sg:province":"MN",
    "wof:name":"Pure Chiropractic",
    "wof:placetype":"venue"
},
  "geometry": {"coordinates":[-92.10418300000001,46.782172],"type":"Point"}
}