{
  "type": "Feature",
  "properties": {
    "addr:full":"19480 Rochester St NE Cedar MN 55011",
    "addr:housenumber":"19480",
    "addr:postcode":"55011",
    "addr:street":"Rochester St Ne Cedar",
    "iso:country":"US",
    "sg:address":"19480 Rochester St NE",
    "sg:city":"Cedar",
    "sg:classifiers":[
        {
            "category":"Building & Trades",
            "subcategory":"Equipment Rental",
            "type":"Services"
        }
    ],
    "sg:phone":"+1 763 639 4986",
    "sg:postcode":"55011",
    "sg:province":"MN",
    "sg:tags":[
        "aircraft",
        "leasing",
        "charter"
    ],
    "sg:website":"www.completehelicopters.com",
    "wof:name":"Complete Helicopters Inc",
    "wof:placetype":"venue"
},
  "geometry": {"coordinates":[-93.21303399999999,45.320609],"type":"Point"}
}