{
  "type": "Feature",
  "properties": {
    "iso:country":"US",
    "sg:address":"2619 Interlachen Dr",
    "sg:city":"Stillwater",
    "sg:classifiers":[
        {
            "category":"Freight",
            "type":"Transportation"
        }
    ],
    "sg:phone":"+1 651 430 9388",
    "sg:postcode":"55082",
    "sg:province":"MN",
    "sg:tags":[
        "trucking"
    ],
    "wof:name":"Midwest Inbound Transport",
    "wof:placetype":"venue"
},
  "geometry": {"coordinates":[-92.84130999999999,45.054025],"type":"Point"}
}