{
  "type": "Feature",
  "properties": {
    "addr:full":"13762 Widgeon Ln Rogers MN 55374",
    "addr:housenumber":"13762",
    "addr:postcode":"55374",
    "addr:street":"Widgeon Ln",
    "iso:country":"US",
    "sg:address":"13762 Widgeon Ln",
    "sg:city":"Rogers",
    "sg:classifiers":[
        {
            "category":"Social Services",
            "subcategory":"Child Care",
            "type":"Services"
        }
    ],
    "sg:phone":"+1 763 428 9709",
    "sg:postcode":"55374",
    "sg:province":"MN",
    "sg:tags":[
        "nursery",
        "day"
    ],
    "wof:name":"Little Learners Child Care",
    "wof:placetype":"venue"
},
  "geometry": {"coordinates":[-93.541208,45.203864],"type":"Point"}
}