{
  "type": "Feature",
  "properties": {
    "addr:full":"506 Central Ave Osseo MN 55369",
    "addr:housenumber":"506",
    "addr:postcode":"55369",
    "addr:street":"Central Ave",
    "iso:country":"US",
    "sg:address":"506 Central Ave",
    "sg:city":"Osseo",
    "sg:classifiers":[
        {
            "category":"Insurance",
            "subcategory":"Insurance Agent",
            "type":"Services"
        }
    ],
    "sg:phone":"+1 763 323 3366",
    "sg:postcode":"55369",
    "sg:province":"MN",
    "wof:name":"American Family Insurance",
    "wof:placetype":"venue"
},
  "geometry": {"coordinates":[-93.402018,45.122061],"type":"Point"}
}