{
  "type": "Feature",
  "properties": {
    "iso:country":"US",
    "sg:address":"165 13th Ave. NE",
    "sg:city":"Minneapolis",
    "sg:classifiers":[
        {
            "category":"Shopping",
            "subcategory":"Music",
            "type":"Retail Goods"
        },
        {
            "category":"Shopping",
            "type":"Retail Goods"
        }
    ],
    "sg:phone":"+1 612 455 6285",
    "sg:postcode":"55413",
    "sg:province":"MN",
    "sg:tags":[
        "record",
        "vinyl",
        "merchandise"
    ],
    "sg:website":"www.shugarecords.com",
    "wof:name":"Shuga Records",
    "wof:placetype":"venue"
},
  "geometry": {"coordinates":[-93.267205,45.000887],"type":"Point"}
}