{
  "type": "Feature",
  "properties": {
    "iso:country":"US",
    "sg:address":"1220 Bradford St SE",
    "sg:city":"Hutchinson",
    "sg:classifiers":[
        {
            "category":"Real Estate",
            "subcategory":"Real Estate Operator",
            "type":"Services"
        }
    ],
    "sg:phone":"+1 320 587 6336",
    "sg:postcode":"55350",
    "sg:province":"MN",
    "sg:tags":[
        "apartment"
    ],
    "wof:name":"Korngiebel Properties",
    "wof:placetype":"venue"
},
  "geometry": {"coordinates":[-94.368977,44.874247],"type":"Point"}
}