{
  "type": "Feature",
  "properties": {
    "iso:country":"US",
    "sg:address":"4016 Shoreline Dr",
    "sg:city":"Spring Park",
    "sg:classifiers":[
        {
            "category":"Restaurant",
            "type":"Food & Drink"
        }
    ],
    "sg:phone":"+1 952 471 7447",
    "sg:postcode":"55384",
    "sg:province":"MN",
    "sg:tags":[
        "eating"
    ],
    "wof:name":"Tonka Grill & Bbq Inc",
    "wof:placetype":"venue"
},
  "geometry": {"coordinates":[-93.625439,44.934994],"type":"Point"}
}