{
  "type": "Feature",
  "properties": {
    "iso:country":"US",
    "sg:address":"770 Kasota Ave SE",
    "sg:city":"Minneapolis",
    "sg:classifiers":[
        {
            "category":"Manufacturing",
            "subcategory":"Electronics",
            "type":"Manufacturing & Wholesale Goods"
        }
    ],
    "sg:phone":"+1 612 331 5020",
    "sg:postcode":"55414",
    "sg:province":"MN",
    "sg:tags":[
        "printed",
        "circuit",
        "etched"
    ],
    "wof:name":"Insulectro",
    "wof:placetype":"venue"
},
  "geometry": {"coordinates":[-93.216257,44.983218],"type":"Point"}
}