{
  "type": "Feature",
  "properties": {
    "iso:country":"US",
    "sg:address":"550 Market St",
    "sg:city":"Chanhassen",
    "sg:classifiers":[
        {
            "category":"Retail",
            "subcategory":"Event Space",
            "type":"Services"
        }
    ],
    "sg:phone":"+1 952 934 2160",
    "sg:postcode":"55317",
    "sg:province":"MN",
    "sg:tags":[
        "venue"
    ],
    "wof:name":"Champion Ballroom",
    "wof:placetype":"venue"
},
  "geometry": {"coordinates":[-93.535498,44.861036],"type":"Point"}
}