{
  "type": "Feature",
  "properties": {
    "addr:full":"17166 US Hwy 169 Grand Rapids MN 55744",
    "addr:postcode":"17166;55744",
    "addr:street":"Us Hwy 169",
    "iso:country":"US",
    "sg:address":"17166 US Hwy 169",
    "sg:city":"Grand Rapids",
    "sg:classifiers":[
        {
            "category":"Real Estate",
            "subcategory":"Real Estate Agent",
            "type":"Services"
        }
    ],
    "sg:phone":"+1 218 326 6997",
    "sg:postcode":"55744",
    "sg:province":"MN",
    "wof:name":"Ford Property Management",
    "wof:placetype":"venue"
},
  "geometry": {"coordinates":[-93.569958,47.127509],"type":"Point"}
}