{
  "type": "Feature",
  "properties": {
    "iso:country":"US",
    "sg:address":"8321 Westwood Rd N",
    "sg:city":"Brooklyn Park",
    "sg:classifiers":[
        {
            "category":"Building & Trades",
            "subcategory":"Construction",
            "type":"Services"
        }
    ],
    "sg:phone":"+1 763 221 5881",
    "sg:postcode":"55444",
    "sg:province":"MN",
    "sg:tags":[
        "repairing",
        "remodeling",
        "contractor"
    ],
    "wof:name":"Pozitiv Design & Remodeling",
    "wof:placetype":"venue"
},
  "geometry": {"coordinates":[-93.293491,45.10829],"type":"Point"}
}