{
  "type": "Feature",
  "properties": {
    "iso:country":"US",
    "sg:address":"2308 S Broadway St",
    "sg:city":"Alexandria",
    "sg:classifiers":[
        {
            "category":"Insurance",
            "subcategory":"Insurance Agent",
            "type":"Services"
        }
    ],
    "sg:phone":"+1 320 762 0730",
    "sg:postcode":"56308",
    "sg:province":"MN",
    "wof:name":"Holmes City Farmers Mutual Ins",
    "wof:placetype":"venue"
},
  "geometry": {"coordinates":[-95.377971,45.865669],"type":"Point"}
}