{
  "type": "Feature",
  "properties": {
    "addr:full":"8000 Morgan Cir N Minneapolis MN 55444",
    "addr:housenumber":"8000",
    "addr:postcode":"55444",
    "addr:street":"Morgan Cir N",
    "iso:country":"US",
    "sg:address":"8000 Morgan Cir N",
    "sg:city":"Minneapolis",
    "sg:classifiers":[
        {
            "category":"Health Services",
            "subcategory":"Clinic",
            "type":"Services"
        }
    ],
    "sg:phone":"+1 763 503 9507",
    "sg:postcode":"55444",
    "sg:province":"MN",
    "wof:name":"Family Alliance Healthcare Svc",
    "wof:placetype":"venue"
},
  "geometry": {"coordinates":[-93.30770099999999,45.101631],"type":"Point"}
}