{
  "type": "Feature",
  "properties": {
    "iso:country":"US",
    "sg:address":"5208 Hanson Ct N",
    "sg:city":"Minneapolis",
    "sg:classifiers":[
        {
            "category":"Wholesale",
            "subcategory":"Auto Parts",
            "type":"Manufacturing & Wholesale Goods"
        }
    ],
    "sg:phone":"+1 763 533 2401",
    "sg:postcode":"55429",
    "sg:province":"MN",
    "sg:tags":[
        "material",
        "used"
    ],
    "wof:name":"Crystal Auto Parts",
    "wof:placetype":"venue"
},
  "geometry": {"coordinates":[-93.35757,45.050283],"type":"Point"}
}