{
  "type": "Feature",
  "properties": {
    "iso:country":"US",
    "sg:address":"2220 E Franklin Ave # 215",
    "sg:city":"Minneapolis",
    "sg:classifiers":[
        {
            "category":"Manufacturing",
            "subcategory":"Buildings",
            "type":"Manufacturing & Wholesale Goods"
        },
        {
            "category":"Building & Trades",
            "subcategory":"Construction",
            "type":"Services"
        }
    ],
    "sg:phone":"+1 612 366 6744",
    "sg:postcode":"55404",
    "sg:province":"MN",
    "sg:tags":[
        "home",
        "builder",
        "contractor"
    ],
    "wof:name":"Kevin Maas Construction Inc.",
    "wof:placetype":"venue"
},
  "geometry": {"coordinates":[-93.239996,44.962761],"type":"Point"}
}