{
  "type": "Feature",
  "properties": {
    "addr:full":"106 Ash Ave NW Wadena MN 56482",
    "addr:housenumber":"106",
    "addr:postcode":"56482",
    "addr:street":"Ash Ave Nw",
    "iso:country":"US",
    "sg:address":"106 Ash Ave NW",
    "sg:city":"Wadena",
    "sg:classifiers":[
        {
            "category":"Restaurant",
            "type":"Food & Drink"
        },
        {
            "category":"Ice Cream",
            "type":"Food & Drink"
        }
    ],
    "sg:menulink":"http://www.allmenus.com/mn/wadena/167964-dairy-queen/menu/",
    "sg:phone":"+1 218 631 4390",
    "sg:postcode":"56482",
    "sg:province":"MN",
    "sg:tags":[
        "burger",
        "american",
        "ice",
        "cream"
    ],
    "wof:name":"Dairy Queen",
    "wof:placetype":"venue"
},
  "geometry": {"coordinates":[-95.13781899999999,46.442897],"type":"Point"}
}