{
  "type": "Feature",
  "properties": {
    "addr:full":"1005 Plymouth Ave N Minneapolis MN 55411",
    "addr:housenumber":"1005",
    "addr:postcode":"55411",
    "addr:street":"Plymouth Ave N",
    "iso:country":"US",
    "sg:address":"1005 Plymouth Ave N",
    "sg:city":"Minneapolis",
    "sg:classifiers":[
        {
            "category":"Shopping",
            "subcategory":"Stationery & Office Supplies",
            "type":"Retail Goods"
        },
        {
            "category":"Professional",
            "subcategory":"Printing & Photocopies",
            "type":"Services"
        },
        {
            "category":"Wholesale",
            "subcategory":"Computers",
            "type":"Manufacturing & Wholesale Goods"
        }
    ],
    "sg:phone":"+1 952 525 1919",
    "sg:postcode":"55411",
    "sg:province":"MN",
    "sg:tags":[
        "equipment"
    ],
    "wof:name":"Office Depot",
    "wof:placetype":"venue"
},
  "geometry": {"coordinates":[-93.303596,45.0028],"type":"Point"}
}