{
  "type": "Feature",
  "properties": {
    "addr:full":"6333 Zealand Ave N Minneapolis MN 55428",
    "addr:housenumber":"6333",
    "addr:postcode":"55428",
    "addr:street":"Zealand Ave N",
    "iso:country":"US",
    "sg:address":"6333 Zealand Ave N",
    "sg:city":"Minneapolis",
    "sg:classifiers":[
        {
            "category":"Wholesale",
            "subcategory":"Hardware",
            "type":"Manufacturing & Wholesale Goods"
        }
    ],
    "sg:phone":"+1 763 533 4726",
    "sg:postcode":"55428",
    "sg:province":"MN",
    "sg:tags":[
        "refrigeration"
    ],
    "wof:name":"Cogswell & Associates",
    "wof:placetype":"venue"
},
  "geometry": {"coordinates":[-93.38726699999999,45.070584],"type":"Point"}
}