{
  "type": "Feature",
  "properties": {
    "addr:full":"26994 Natchez Ave Elko MN 55020",
    "addr:housenumber":"26994",
    "addr:postcode":"55020",
    "addr:street":"Natchez Ave",
    "iso:country":"US",
    "sg:address":"26994 Natchez Ave",
    "sg:city":"Elko",
    "sg:classifiers":[
        {
            "category":"Building & Trades",
            "subcategory":"Construction",
            "type":"Services"
        }
    ],
    "sg:phone":"+1 952 461 4344",
    "sg:postcode":"55020",
    "sg:province":"MN",
    "sg:tags":[
        "contractor"
    ],
    "wof:name":"Walter Allison",
    "wof:placetype":"venue"
},
  "geometry": {"coordinates":[-93.339168,44.555522],"type":"Point"}
}