{
  "type": "Feature",
  "properties": {
    "iso:country":"US",
    "sg:address":"821 S Hubbard St",
    "sg:city":"Crookston",
    "sg:classifiers":[
        {
            "category":"Professional",
            "type":"Services"
        }
    ],
    "sg:phone":"+1 218 281 1190",
    "sg:postcode":"56716",
    "sg:province":"MN",
    "wof:name":"Thunderbolt Sound & Light Show",
    "wof:placetype":"venue"
},
  "geometry": {"coordinates":[-96.616546,47.768843],"type":"Point"}
}