{
  "type": "Feature",
  "properties": {
    "iso:country":"US",
    "sg:address":"17055 Mushtown Rd",
    "sg:city":"Prior Lake",
    "sg:classifiers":[
        {
            "category":"Professional",
            "subcategory":"Art Services",
            "type":"Services"
        }
    ],
    "sg:phone":"+1 952 200 1070",
    "sg:postcode":"55372",
    "sg:province":"MN",
    "sg:tags":[
        "commercial",
        "design"
    ],
    "wof:name":"Sharp Designs",
    "wof:placetype":"venue"
},
  "geometry": {"coordinates":[-93.432005,44.701288],"type":"Point"}
}