{
  "type": "Feature",
  "properties": {
    "addr:full":"947 41st St Slayton MN 56172",
    "addr:housenumber":"947",
    "addr:postcode":"56172",
    "addr:street":"41St St",
    "iso:country":"US",
    "sg:address":"947 41st St",
    "sg:city":"Slayton",
    "sg:classifiers":[
        {
            "category":"Farming",
            "subcategory":"Livestock Farm",
            "type":"Manufacturing & Wholesale Goods"
        }
    ],
    "sg:phone":"+1 507 264 3733",
    "sg:postcode":"56172",
    "sg:province":"MN",
    "sg:tags":[
        "feedlot",
        "grain",
        "cash",
        "beef",
        "cattle"
    ],
    "wof:name":"Albert Brouwer",
    "wof:placetype":"venue"
},
  "geometry": {"coordinates":[-95.8742,43.90631],"type":"Point"}
}