{
  "type": "Feature",
  "properties": {
    "iso:country":"US",
    "sg:address":"525 S Grade Rd SW",
    "sg:city":"Hutchinson",
    "sg:classifiers":[
        {
            "category":"Sports & Exercise",
            "subcategory":"Gym",
            "type":"Entertainment"
        }
    ],
    "sg:phone":"+1 320 587 6900",
    "sg:postcode":"55350",
    "sg:province":"MN",
    "sg:tags":[
        "club",
        "health",
        "including",
        "aerobics",
        "fitness"
    ],
    "wof:name":"Hutchinson Dance Center The",
    "wof:placetype":"venue"
},
  "geometry": {"coordinates":[-94.376036,44.878173],"type":"Point"}
}