{
  "type": "Feature",
  "properties": {
    "addr:full":"410 N Arlington Ave Duluth MN 55811",
    "addr:housenumber":"410",
    "addr:postcode":"55811",
    "addr:street":"N Arlington Ave",
    "iso:country":"US",
    "sg:address":"410 N Arlington Ave",
    "sg:city":"Duluth",
    "sg:classifiers":[
        {
            "category":"Government",
            "subcategory":"Office",
            "type":"Public Place"
        }
    ],
    "sg:phone":"+1 218 722 6022",
    "sg:postcode":"55811",
    "sg:province":"MN",
    "sg:tags":[
        "village"
    ],
    "wof:name":"Duluth Heights Holy Cross",
    "wof:placetype":"venue"
},
  "geometry": {"coordinates":[-92.132046,46.802937],"type":"Point"}
}