{
  "type": "Feature",
  "properties": {
    "addr:full":"48436 Pike Beach Rd Pelican Rapids MN 56572",
    "addr:housenumber":"48436",
    "addr:postcode":"56572",
    "addr:street":"Pike Beach Rd",
    "iso:country":"US",
    "sg:address":"48436 Pike Beach Rd",
    "sg:city":"Pelican Rapids",
    "sg:classifiers":[
        {
            "category":"Shopping",
            "subcategory":"Stationery & Office Supplies",
            "type":"Retail Goods"
        }
    ],
    "sg:phone":"+1 218 863 5122",
    "sg:postcode":"56572",
    "sg:province":"MN",
    "wof:name":"Selvig Business Forms",
    "wof:placetype":"venue"
},
  "geometry": {"coordinates":[-96.085291,46.665333],"type":"Point"}
}