{
  "type": "Feature",
  "properties": {
    "iso:country":"US",
    "sg:address":"15608 Cornell Trl",
    "sg:city":"Rosemount",
    "sg:classifiers":[
        {
            "category":"Travel",
            "subcategory":"Travel Agent",
            "type":"Entertainment"
        }
    ],
    "sg:phone":"+1 651 322 1816",
    "sg:postcode":"55068",
    "sg:province":"MN",
    "sg:tags":[
        "agency",
        "bureau"
    ],
    "wof:name":"Islands Under The Sun",
    "wof:placetype":"venue"
},
  "geometry": {"coordinates":[-93.141373,44.722018],"type":"Point"}
}