{
  "type": "Feature",
  "properties": {
    "iso:country":"US",
    "sg:address":"76514 300th St",
    "sg:city":"Olivia",
    "sg:classifiers":[
        {
            "category":"Farming",
            "subcategory":"Livestock Farm",
            "type":"Manufacturing & Wholesale Goods"
        }
    ],
    "sg:phone":"+1 320 523 5378",
    "sg:postcode":"56277",
    "sg:province":"MN",
    "sg:tags":[
        "feedlot",
        "hog",
        "or",
        "beef",
        "cattle"
    ],
    "wof:name":"Thomas Kodet",
    "wof:placetype":"venue"
},
  "geometry": {"coordinates":[-95.07620300000001,44.701305],"type":"Point"}
}