{
  "type": "Feature",
  "properties": {
    "addr:full":"31 W Main St Isanti MN 55040",
    "addr:housenumber":"31",
    "addr:postcode":"55040",
    "addr:street":"W Main St",
    "iso:country":"US",
    "sg:address":"31 W Main St",
    "sg:city":"Isanti",
    "sg:classifiers":[
        {
            "category":"Personal",
            "subcategory":"Barber",
            "type":"Services"
        }
    ],
    "sg:phone":"+1 763 444 8220",
    "sg:postcode":"55040",
    "sg:province":"MN",
    "wof:name":"Norm's Barber Shop",
    "wof:placetype":"venue"
},
  "geometry": {"coordinates":[-93.247789,45.490361],"type":"Point"}
}