{
  "type": "Feature",
  "properties": {
    "iso:country":"US",
    "sg:address":"15580 Co Rd 3",
    "sg:city":"Ellendale",
    "sg:classifiers":[
        {
            "category":"Social Services",
            "subcategory":"Child Care",
            "type":"Services"
        }
    ],
    "sg:phone":"+1 507 684 3505",
    "sg:postcode":"56026",
    "sg:province":"MN",
    "sg:tags":[
        "day",
        "provider"
    ],
    "wof:name":"Tracy S Smith",
    "wof:placetype":"venue"
},
  "geometry": {"coordinates":[-93.259871,43.872464],"type":"Point"}
}