{
  "type": "Feature",
  "properties": {
    "iso:country":"US",
    "sg:address":"125 Sherman St",
    "sg:city":"Garvin",
    "sg:classifiers":[
        {
            "category":"Government",
            "subcategory":"Fire Station",
            "type":"Public Place"
        }
    ],
    "sg:phone":"+1 507 746 4592",
    "sg:postcode":"56132",
    "sg:province":"MN",
    "sg:tags":[
        "department"
    ],
    "wof:name":"Garvin Fire Department",
    "wof:placetype":"venue"
},
  "geometry": {"coordinates":[-95.76038699999999,44.21705],"type":"Point"}
}