{
  "type": "Feature",
  "properties": {
    "iso:country":"US",
    "sg:address":"21421 County 24",
    "sg:city":"Park Rapids",
    "sg:classifiers":[
        {
            "category":"Travel",
            "subcategory":"Hotels & Motels",
            "type":"Entertainment"
        }
    ],
    "sg:phone":"+1 218 732 4639",
    "sg:postcode":"56470",
    "sg:province":"MN",
    "sg:tags":[
        "operation"
    ],
    "wof:name":"Whippoorwill Resort",
    "wof:placetype":"venue"
},
  "geometry": {"coordinates":[-94.923523,47.053692],"type":"Point"}
}