{
  "type": "Feature",
  "properties": {
    "addr:full":"2204 Co Rd 7 Barnum MN 55707",
    "addr:housenumber":"2204",
    "addr:postcode":"55707",
    "addr:street":"Co Rd 7",
    "iso:country":"US",
    "sg:address":"2204 Co Rd 7",
    "sg:city":"Barnum",
    "sg:phone":"+1 218 389 6750",
    "sg:postcode":"55707",
    "sg:province":"MN",
    "sg:tags":[
        "farm"
    ],
    "wof:name":"Park Lake Farm",
    "wof:placetype":"venue"
},
  "geometry": {"coordinates":[-92.639402,46.613327],"type":"Point"}
}