{
  "type": "Feature",
  "properties": {
    "iso:country":"US",
    "sg:address":"300 E Main St",
    "sg:city":"Anoka",
    "sg:classifiers":[
        {
            "category":"Shopping",
            "subcategory":"Hobbies, Toys, & Games",
            "type":"Retail Goods"
        }
    ],
    "sg:phone":"+1 763 506 0303",
    "sg:postcode":"55303",
    "sg:province":"MN",
    "wof:name":"Natural 20 Comics & Games",
    "wof:placetype":"venue"
},
  "geometry": {"coordinates":[-93.385409,45.197925],"type":"Point"}
}