{
  "type": "Feature",
  "properties": {
    "addr:full":"230 2nd Ave SW Milaca MN 56353",
    "addr:housenumber":"230",
    "addr:postcode":"56353",
    "addr:street":"2Nd Ave Sw",
    "iso:country":"US",
    "sg:address":"230 2nd Ave SW",
    "sg:city":"Milaca",
    "sg:classifiers":[
        {
            "category":"Government",
            "subcategory":"Post Office",
            "type":"Public Place"
        }
    ],
    "sg:phone":"+1 320 983 3229",
    "sg:postcode":"56353",
    "sg:province":"MN",
    "sg:tags":[
        "postal",
        "us"
    ],
    "wof:name":"US Post Office",
    "wof:placetype":"venue"
},
  "geometry": {"coordinates":[-93.652726,45.753192],"type":"Point"}
}