{
  "type": "Feature",
  "properties": {
    "addr:full":"105 Brown St W Comfrey MN 56019",
    "addr:housenumber":"105",
    "addr:postcode":"56019",
    "addr:street":"Brown St W Comfrey",
    "iso:country":"US",
    "sg:address":"105 Brown St W",
    "sg:city":"Comfrey",
    "sg:classifiers":[
        {
            "category":"Personal",
            "subcategory":"Beauty Salon",
            "type":"Services"
        },
        {
            "category":"Personal",
            "subcategory":"Tanning Parlor",
            "type":"Services"
        }
    ],
    "sg:phone":"+1 507 877 2551",
    "sg:postcode":"56019",
    "sg:province":"MN",
    "wof:name":"Styles Comfrey",
    "wof:placetype":"venue"
},
  "geometry": {"coordinates":[-94.90469,44.109878],"type":"Point"}
}