{
  "type": "Feature",
  "properties": {
    "iso:country":"US",
    "sg:address":"21114 State Hwy 65",
    "sg:city":"Goodland",
    "sg:classifiers":[
        {
            "category":"Retail",
            "subcategory":"Auto Repair",
            "type":"Services"
        }
    ],
    "sg:phone":"+1 218 326 6318",
    "sg:postcode":"55742",
    "sg:province":"MN",
    "sg:tags":[
        "general"
    ],
    "wof:name":"Mikes Auto Repair",
    "wof:placetype":"venue"
},
  "geometry": {"coordinates":[-93.143125,47.178242],"type":"Point"}
}