{
  "type": "Feature",
  "properties": {
    "addr:full":"1605 Independence Ave N Minneapolis MN 55427",
    "addr:housenumber":"1605",
    "addr:postcode":"55427",
    "addr:street":"Independence Ave N",
    "iso:country":"US",
    "sg:address":"1605 Independence Ave N",
    "sg:city":"Minneapolis",
    "sg:classifiers":[
        {
            "category":"Professional",
            "subcategory":"Accounting & Tax Preparation",
            "type":"Services"
        }
    ],
    "sg:phone":"+1 763 544 2201",
    "sg:postcode":"55427",
    "sg:province":"MN",
    "sg:tags":[
        "accountant"
    ],
    "wof:name":"Indoff",
    "wof:placetype":"venue"
},
  "geometry": {"coordinates":[-93.399412,44.998304],"type":"Point"}
}