{
  "type": "Feature",
  "properties": {
    "addr:full":"13420 Co Rd 3 NE Miltona MN 56354",
    "addr:housenumber":"13420;3",
    "addr:postcode":"56354",
    "addr:street":"Co Rd;Ne Miltona",
    "iso:country":"US",
    "sg:address":"13420 Co Rd 3 NE",
    "sg:city":"Miltona",
    "sg:classifiers":[
        {
            "category":"Real Estate",
            "subcategory":"Real Estate Operator",
            "type":"Services"
        }
    ],
    "sg:phone":"+1 218 943 6181",
    "sg:postcode":"56354",
    "sg:province":"MN",
    "sg:tags":[
        "property",
        "lessor"
    ],
    "wof:name":"Angeline Zimmel Farm",
    "wof:placetype":"venue"
},
  "geometry": {"coordinates":[-95.229821,46.028715],"type":"Point"}
}