{
  "type": "Feature",
  "properties": {
    "addr:full":"2 2nd Ave S Sauk Rapids MN 56379",
    "addr:housenumber":"2",
    "addr:postcode":"56379",
    "addr:street":"2Nd Ave S Sauk",
    "iso:country":"US",
    "sg:address":"2 2nd Ave S",
    "sg:city":"Sauk Rapids",
    "sg:classifiers":[
        {
            "category":"Insurance",
            "subcategory":"Insurance Agent",
            "type":"Services"
        }
    ],
    "sg:phone":"+1 320 251 8400",
    "sg:postcode":"56379",
    "sg:province":"MN",
    "wof:name":"Metropolitan Insurance",
    "wof:placetype":"venue"
},
  "geometry": {"coordinates":[-94.16418,45.588861],"type":"Point"}
}