{
  "type": "Feature",
  "properties": {
    "addr:full":"18668 370th St Beltrami MN 56534",
    "addr:housenumber":"18668",
    "addr:postcode":"56534",
    "addr:street":"370Th St",
    "iso:country":"US",
    "sg:address":"18668 370th St",
    "sg:city":"Beltrami",
    "sg:classifiers":[
        {
            "category":"Building & Trades",
            "subcategory":"Construction",
            "type":"Services"
        }
    ],
    "sg:phone":"+1 218 926 5614",
    "sg:postcode":"56534",
    "sg:province":"MN",
    "sg:tags":[
        "excavating",
        "contractor"
    ],
    "wof:name":"Wayne Demarais Excavating",
    "wof:placetype":"venue"
},
  "geometry": {"coordinates":[-96.094813,46.499329],"type":"Point"}
}