{
  "type": "Feature",
  "properties": {
    "addr:full":"1008 Washington Ave S Bemidji MN 56601",
    "addr:housenumber":"1008",
    "addr:postcode":"56601",
    "addr:street":"Washington Ave S",
    "iso:country":"US",
    "sg:address":"1008 Washington Ave S",
    "sg:city":"Bemidji",
    "sg:classifiers":[
        {
            "category":"Recreation",
            "type":"Entertainment"
        }
    ],
    "sg:phone":"+1 218 444 7080",
    "sg:postcode":"56601",
    "sg:province":"MN",
    "sg:tags":[
        "martial",
        "arts",
        "instruction"
    ],
    "wof:name":"Bemidji School Of Tae KWON Do",
    "wof:placetype":"venue"
},
  "geometry": {"coordinates":[-94.86359,47.452203],"type":"Point"}
}