{
  "type": "Feature",
  "properties": {
    "iso:country":"US",
    "sg:address":"2102 N Blackman Ave",
    "sg:city":"Duluth",
    "sg:classifiers":[
        {
            "category":"Education",
            "subcategory":"School",
            "type":"Public Place"
        }
    ],
    "sg:phone":"+1 218 733 2084",
    "sg:postcode":"55811",
    "sg:province":"MN",
    "wof:name":"Head Start",
    "wof:placetype":"venue"
},
  "geometry": {"coordinates":[-92.12160299999999,46.815286],"type":"Point"}
}