{
  "type": "Feature",
  "properties": {
    "addr:full":"905 S Douglas St Lamberton MN 56152",
    "addr:housenumber":"905",
    "addr:postcode":"56152",
    "addr:street":"S Douglas St",
    "iso:country":"US",
    "sg:address":"905 S Douglas St",
    "sg:city":"Lamberton",
    "sg:classifiers":[
        {
            "category":"Shopping",
            "subcategory":"Used Merchandise",
            "type":"Retail Goods"
        }
    ],
    "sg:phone":"+1 507 752 6137",
    "sg:postcode":"56152",
    "sg:province":"MN",
    "wof:name":"Uniquely Simple Antiques",
    "wof:placetype":"venue"
},
  "geometry": {"coordinates":[-95.263581,44.223881],"type":"Point"}
}