{
  "type": "Feature",
  "properties": {
    "iso:country":"US",
    "sg:address":"712 4th Ave",
    "sg:city":"Two Harbors",
    "sg:classifiers":[
        {
            "category":"Professional",
            "type":"Services"
        }
    ],
    "sg:phone":"+1 218 834 3300",
    "sg:postcode":"55616",
    "sg:province":"MN",
    "wof:name":"Northshore Property Service",
    "wof:placetype":"venue"
},
  "geometry": {"coordinates":[-91.67461400000001,47.022708],"type":"Point"}
}