{
  "type": "Feature",
  "properties": {
    "iso:country":"US",
    "sg:address":"703 Deschepper St",
    "sg:city":"Marshall",
    "sg:classifiers":[
        {
            "category":"Building & Trades",
            "subcategory":"Construction",
            "type":"Services"
        }
    ],
    "sg:phone":"+1 507 532 5122",
    "sg:postcode":"56258",
    "sg:province":"MN",
    "sg:tags":[
        "paving",
        "contractor"
    ],
    "wof:name":"Moorseal Inc",
    "wof:placetype":"venue"
},
  "geometry": {"coordinates":[-95.7872,44.437269],"type":"Point"}
}