{
  "type": "Feature",
  "properties": {
    "addr:full":"1149 Pond Curv Waconia MN 55387",
    "addr:housenumber":"1149",
    "addr:postcode":"55387",
    "addr:street":"Pond Curv Waconia",
    "iso:country":"US",
    "sg:address":"1149 Pond Curv",
    "sg:city":"Waconia",
    "sg:classifiers":[
        {
            "category":"Real Estate",
            "subcategory":"Real Estate Agent",
            "type":"Services"
        }
    ],
    "sg:phone":"+1 952 442 8635",
    "sg:postcode":"55387",
    "sg:province":"MN",
    "sg:tags":[
        "appraiser"
    ],
    "wof:name":"Bob Ludwig Appraiser",
    "wof:placetype":"venue"
},
  "geometry": {"coordinates":[-93.818243,44.837732],"type":"Point"}
}