{
  "type": "Feature",
  "properties": {
    "addr:full":"3844 Englund Rd SW Alexandria MN 56308",
    "addr:postcode":"3844;56308",
    "addr:street":"Englund Rd Sw",
    "iso:country":"US",
    "sg:address":"3844 Englund Rd SW",
    "sg:city":"Alexandria",
    "sg:classifiers":[
        {
            "category":"Wholesale",
            "subcategory":"Farm Supplies",
            "type":"Manufacturing & Wholesale Goods"
        }
    ],
    "sg:phone":"+1 320 762 1601",
    "sg:postcode":"56308",
    "sg:province":"MN",
    "sg:tags":[
        "fertilizer"
    ],
    "sg:website":"www.gobiobuilder.com",
    "wof:name":"Bio Builder Inc",
    "wof:placetype":"venue"
},
  "geometry": {"coordinates":[-95.470961,45.854911],"type":"Point"}
}