{
  "type": "Feature",
  "properties": {
    "addr:full":"7600 Humboldt Ave N Minneapolis MN 55444",
    "addr:housenumber":"7600",
    "addr:postcode":"55444",
    "addr:street":"Humboldt Ave N",
    "iso:country":"US",
    "sg:address":"7600 Humboldt Ave N",
    "sg:city":"Minneapolis",
    "sg:classifiers":[
        {
            "category":"Organizations",
            "subcategory":"Religious Organization",
            "type":"Services"
        }
    ],
    "sg:phone":"+1 763 566 7411",
    "sg:postcode":"55444",
    "sg:province":"MN",
    "sg:tags":[
        "churches-non-denominational"
    ],
    "sg:website":"http://www.rezzchurch.org",
    "wof:name":"Minnesota Prophetic Conference",
    "wof:placetype":"venue"
},
  "geometry": {"coordinates":[-93.300533,45.091421],"type":"Point"}
}