{
  "type": "Feature",
  "properties": {
    "iso:country":"US",
    "sg:address":"13105 Court Pl",
    "sg:city":"Burnsville",
    "sg:classifiers":[
        {
            "category":"Professional",
            "subcategory":"Business Services",
            "type":"Services"
        }
    ],
    "sg:phone":"+1 952 882 1552",
    "sg:postcode":"55337",
    "sg:province":"MN",
    "wof:name":"With Attitude",
    "wof:placetype":"venue"
},
  "geometry": {"coordinates":[-93.32693399999999,44.761986],"type":"Point"}
}