{
  "type": "Feature",
  "properties": {
    "iso:country":"US",
    "sg:address":"1620 Service Dr",
    "sg:city":"Winona",
    "sg:classifiers":[
        {
            "category":"Restaurant",
            "type":"Food & Drink"
        }
    ],
    "sg:phone":"+1 507 452 9488",
    "sg:postcode":"55987",
    "sg:province":"MN",
    "wof:name":"Mc Donald's",
    "wof:placetype":"venue"
},
  "geometry": {"coordinates":[-91.68168,44.05083],"type":"Point"}
}