{
  "type": "Feature",
  "properties": {
    "addr:full":"512 6th St W Adrian MN 56110",
    "addr:housenumber":"512",
    "addr:postcode":"56110",
    "addr:street":"6Th St W Adrian",
    "iso:country":"US",
    "sg:address":"512 6th St W",
    "sg:city":"Adrian",
    "sg:classifiers":[
        {
            "category":"Building & Trades",
            "subcategory":"Construction",
            "type":"Services"
        }
    ],
    "sg:phone":"+1 507 483 2096",
    "sg:postcode":"56110",
    "sg:province":"MN",
    "sg:tags":[
        "residential"
    ],
    "wof:name":"Honermann Builders",
    "wof:placetype":"venue"
},
  "geometry": {"coordinates":[-95.939482,43.630775],"type":"Point"}
}