{
  "type": "Feature",
  "properties": {
    "addr:full":"50760 390th St New York Mills MN 56567",
    "addr:housenumber":"50760",
    "addr:postcode":"56567",
    "addr:street":"390Th St;York",
    "iso:country":"US",
    "sg:address":"50760 390th St",
    "sg:city":"New York Mills",
    "sg:classifiers":[
        {
            "category":"Farming",
            "subcategory":"Farm",
            "type":"Manufacturing & Wholesale Goods"
        }
    ],
    "sg:phone":"+1 218 385 3484",
    "sg:postcode":"56567",
    "sg:province":"MN",
    "sg:tags":[
        "crop",
        "general"
    ],
    "wof:name":"David Bauck Farm",
    "wof:placetype":"venue"
},
  "geometry": {"coordinates":[-95.43477,46.527852],"type":"Point"}
}