{
  "type": "Feature",
  "properties": {
    "addr:full":"3818 W Old Shakopee Rd Minneapolis MN 55431",
    "addr:housenumber":"3818",
    "addr:postcode":"55431",
    "addr:street":"W Old Shakopee Rd",
    "iso:country":"US",
    "sg:address":"3818 W Old Shakopee Rd",
    "sg:city":"Minneapolis",
    "sg:classifiers":[
        {
            "category":"Cinema",
            "subcategory":"Movie Rental",
            "type":"Entertainment"
        }
    ],
    "sg:phone":"+1 952 345 7000",
    "sg:postcode":"55431",
    "sg:province":"MN",
    "sg:tags":[
        "game",
        "video"
    ],
    "wof:name":"Play N Trade",
    "wof:placetype":"venue"
},
  "geometry": {"coordinates":[-93.328338,44.810988],"type":"Point"}
}