{
  "type": "Feature",
  "properties": {
    "iso:country":"US",
    "sg:address":"1370 15th Ave SE",
    "sg:city":"St Cloud",
    "sg:classifiers":[
        {
            "category":"Autos & Motor Vehicles",
            "subcategory":"Fuel & Gas Station",
            "type":"Retail Goods"
        }
    ],
    "sg:phone":"+1 320 251 2296",
    "sg:postcode":"56304",
    "sg:province":"MN",
    "sg:tags":[
        "oil"
    ],
    "wof:name":"River Station",
    "wof:placetype":"venue"
},
  "geometry": {"coordinates":[-94.13162699999999,45.551692],"type":"Point"}
}