{
  "type": "Feature",
  "properties": {
    "addr:full":"328 Maple St Mahtomedi MN 55115",
    "addr:housenumber":"328",
    "addr:postcode":"55115",
    "addr:street":"Maple St",
    "iso:country":"US",
    "sg:address":"328 Maple St",
    "sg:city":"Mahtomedi",
    "sg:classifiers":[
        {
            "category":"Organizations",
            "subcategory":"Religious Organization",
            "type":"Services"
        }
    ],
    "sg:phone":"+1 651 426 2369",
    "sg:postcode":"55115",
    "sg:province":"MN",
    "sg:tags":[
        "church"
    ],
    "sg:website":"www.whitebearunitarian.org",
    "wof:name":"White Bear Unitarian Church",
    "wof:placetype":"venue"
},
  "geometry": {"coordinates":[-92.947717,45.071937],"type":"Point"}
}