{
  "type": "Feature",
  "properties": {
    "addr:full":"5640 International Pkwy Minneapolis MN 55428",
    "addr:housenumber":"5640",
    "addr:postcode":"55428",
    "addr:street":"International Pkwy",
    "iso:country":"US",
    "sg:address":"5640 International Pkwy",
    "sg:city":"Minneapolis",
    "sg:classifiers":[
        {
            "category":"Professional",
            "subcategory":"Computer Services",
            "type":"Services"
        }
    ],
    "sg:phone":"+1 763 557 9900",
    "sg:postcode":"55428",
    "sg:province":"MN",
    "sg:tags":[
        "consultant",
        "security"
    ],
    "wof:name":"Prodigen LLC",
    "wof:placetype":"venue"
},
  "geometry": {"coordinates":[-93.39452900000001,45.056992],"type":"Point"}
}