{
  "type": "Feature",
  "properties": {
    "addr:full":"60 E Tyrone St Le Center MN 56057",
    "addr:housenumber":"60",
    "addr:postcode":"56057",
    "addr:street":"E Tyrone St",
    "iso:country":"US",
    "sg:address":"60 E Tyrone St",
    "sg:city":"Le Center",
    "sg:classifiers":[
        {
            "category":"Manufacturing",
            "subcategory":"Apparel",
            "type":"Manufacturing & Wholesale Goods"
        }
    ],
    "sg:phone":"+1 507 357 4516",
    "sg:postcode":"56057",
    "sg:province":"MN",
    "wof:name":"Carlas Embroidery Nook",
    "wof:placetype":"venue"
},
  "geometry": {"coordinates":[-93.730914,44.390824],"type":"Point"}
}