{
  "type": "Feature",
  "properties": {
    "addr:full":"12450 29th Ave N Minneapolis MN 55441",
    "addr:housenumber":"12450",
    "addr:postcode":"55441",
    "addr:street":"29Th Ave N",
    "iso:country":"US",
    "sg:address":"12450 29th Ave N",
    "sg:city":"Minneapolis",
    "sg:classifiers":[
        {
            "category":"Building & Trades",
            "subcategory":"Electrical",
            "type":"Services"
        }
    ],
    "sg:phone":"+1 612 791 6156",
    "sg:postcode":"55441",
    "sg:province":"MN",
    "sg:tags":[
        "electrician"
    ],
    "wof:name":"Miesen Security",
    "wof:placetype":"venue"
},
  "geometry": {"coordinates":[-93.438599,45.01236],"type":"Point"}
}