{
  "type": "Feature",
  "properties": {
    "iso:country":"US",
    "sg:address":"3842 Regent Ave N",
    "sg:city":"Minneapolis",
    "sg:classifiers":[
        {
            "category":"Real Estate",
            "subcategory":"Real Estate Agent",
            "type":"Services"
        },
        {
            "category":"Building & Trades",
            "subcategory":"Construction",
            "type":"Services"
        }
    ],
    "sg:phone":"+1 763 504 0445",
    "sg:postcode":"55422",
    "sg:province":"MN",
    "sg:tags":[
        "house"
    ],
    "wof:name":"Land & Homes Inc",
    "wof:placetype":"venue"
},
  "geometry": {"coordinates":[-93.344088,45.025155],"type":"Point"}
}