{
  "type": "Feature",
  "properties": {
    "iso:country":"US",
    "sg:address":"62168 190th Ave",
    "sg:city":"Dodge Center",
    "sg:classifiers":[
        {
            "category":"Manufacturing",
            "subcategory":"Wood Products",
            "type":"Manufacturing & Wholesale Goods"
        }
    ],
    "sg:phone":"+1 507 374 6851",
    "sg:postcode":"55927",
    "sg:province":"MN",
    "sg:tags":[
        "mfg"
    ],
    "wof:name":"P/Boxes",
    "wof:placetype":"venue"
},
  "geometry": {"coordinates":[-92.859101,44.046192],"type":"Point"}
}