{
  "type": "Feature",
  "properties": {
    "iso:country":"US",
    "sg:address":"709 121st Ave NW",
    "sg:city":"Minneapolis",
    "sg:classifiers":[
        {
            "category":"Retail",
            "subcategory":"Portrait Studio",
            "type":"Services"
        }
    ],
    "sg:phone":"+1 763 767 3226",
    "sg:postcode":"55448",
    "sg:province":"MN",
    "sg:tags":[
        "photographer",
        "photographers-portrait"
    ],
    "sg:website":"http://www.bluediamondphoto.com",
    "wof:name":"Blue Diamond Photography & Vd",
    "wof:placetype":"venue"
},
  "geometry": {"coordinates":[-93.284307,45.190004],"type":"Point"}
}