{
  "type": "Feature",
  "properties": {
    "addr:full":"5740 Brooklyn Blvd Brooklyn Center MN 55429",
    "addr:housenumber":"5740",
    "addr:postcode":"55429",
    "addr:street":"Brooklyn Blvd",
    "iso:country":"US",
    "sg:address":"5740 Brooklyn Blvd",
    "sg:city":"Brooklyn Center",
    "sg:classifiers":[
        {
            "category":"Personal",
            "subcategory":"Beauty Salon",
            "type":"Services"
        }
    ],
    "sg:phone":"+1 763 566 9686",
    "sg:postcode":"55429",
    "sg:province":"MN",
    "sg:tags":[
        "shop"
    ],
    "wof:name":"Madia Styling Salon",
    "wof:placetype":"venue"
},
  "geometry": {"coordinates":[-93.324612,45.059358],"type":"Point"}
}