{
  "type": "Feature",
  "properties": {
    "iso:country":"US",
    "sg:address":"409 Heidi Pkwy",
    "sg:city":"New York Mills",
    "sg:classifiers":[
        {
            "category":"Freight",
            "type":"Transportation"
        }
    ],
    "sg:phone":"+1 218 385 3034",
    "sg:postcode":"56567",
    "sg:province":"MN",
    "sg:tags":[
        "trucking"
    ],
    "wof:name":"Tim Flanigan Trucking Inc",
    "wof:placetype":"venue"
},
  "geometry": {"coordinates":[-95.37634,46.510717],"type":"Point"}
}