{
  "type": "Feature",
  "properties": {
    "iso:country":"US",
    "sg:address":"2619 Coon Rapids Blvd NW Ste 205",
    "sg:city":"Minneapolis",
    "sg:classifiers":[
        {
            "category":"Insurance",
            "subcategory":"Insurance Agent",
            "type":"Services"
        }
    ],
    "sg:phone":"+1 763 754 6636",
    "sg:postcode":"55433",
    "sg:province":"MN",
    "sg:tags":[
        "auto"
    ],
    "sg:website":"http://clickserve.dartsearch.net/link/click?lid=43000000277021920",
    "wof:name":"Allstate Insurance Company - David Curtis",
    "wof:placetype":"venue"
},
  "geometry": {"coordinates":[-93.333206,45.168773],"type":"Point"}
}