{
  "type": "Feature",
  "properties": {
    "iso:country":"US",
    "sg:address":"9904 313th Ave",
    "sg:city":"Princeton",
    "sg:classifiers":[
        {
            "category":"Personal",
            "type":"Services"
        }
    ],
    "sg:phone":"+1 763 389 2359",
    "sg:postcode":"55371",
    "sg:province":"MN",
    "wof:name":"Wagon Maker Company",
    "wof:placetype":"venue"
},
  "geometry": {"coordinates":[-93.523467,45.537485],"type":"Point"}
}