{
  "type": "Feature",
  "properties": {
    "addr:full":"13195 Bayview Rd South Haven MN 55382",
    "addr:housenumber":"13195",
    "addr:postcode":"55382",
    "addr:street":"Bayview Rd",
    "iso:country":"US",
    "sg:address":"13195 Bayview Rd",
    "sg:city":"South Haven",
    "sg:classifiers":[
        {
            "category":"Restaurant",
            "type":"Food & Drink"
        }
    ],
    "sg:phone":"+1 320 274 9988",
    "sg:postcode":"55382",
    "sg:province":"MN",
    "wof:name":"Waterfront Bar & Supper Club",
    "wof:placetype":"venue"
},
  "geometry": {"coordinates":[-94.158073,45.316548],"type":"Point"}
}