{
  "type": "Feature",
  "properties": {
    "iso:country":"US",
    "sg:address":"7525 147th St W",
    "sg:city":"Saint Paul",
    "sg:classifiers":[
        {
            "category":"Autos & Motor Vehicles",
            "subcategory":"Fuel & Gas Station",
            "type":"Retail Goods"
        }
    ],
    "sg:phone":"+1 952 432 7676",
    "sg:postcode":"55124",
    "sg:province":"MN",
    "sg:tags":[
        "automotive",
        "station",
        "general",
        "repair"
    ],
    "wof:name":"Puals Tire and Auto",
    "wof:placetype":"venue"
},
  "geometry": {"coordinates":[-93.218166,44.735234],"type":"Point"}
}