{
  "type": "Feature",
  "properties": {
    "addr:full":"600 6th St Madison MN 56256",
    "addr:housenumber":"600",
    "addr:postcode":"56256",
    "addr:street":"6Th St",
    "iso:country":"US",
    "sg:address":"600 6th St",
    "sg:city":"Madison",
    "sg:classifiers":[
        {
            "category":"Government",
            "subcategory":"Office",
            "type":"Public Place"
        }
    ],
    "sg:phone":"+1 320 598 3325",
    "sg:postcode":"56256",
    "sg:province":"MN",
    "wof:name":"Lac Qui Parle Ag Extension Svc",
    "wof:placetype":"venue"
},
  "geometry": {"coordinates":[-96.19387999999999,45.01434],"type":"Point"}
}