{
  "type": "Feature",
  "properties": {
    "addr:full":"10810 Mississippi Blvd NW Minneapolis MN 55433",
    "addr:housenumber":"10810",
    "addr:postcode":"55433",
    "addr:street":"Mississippi Blvd Nw",
    "iso:country":"US",
    "sg:address":"10810 Mississippi Blvd NW",
    "sg:city":"Minneapolis",
    "sg:classifiers":[
        {
            "category":"Professional",
            "subcategory":"Engineering",
            "type":"Services"
        }
    ],
    "sg:phone":"+1 763 427 8900",
    "sg:postcode":"55433",
    "sg:province":"MN",
    "wof:name":"Nettum Consulting Inc",
    "wof:placetype":"venue"
},
  "geometry": {"coordinates":[-93.347482,45.166908],"type":"Point"}
}