{
  "type": "Feature",
  "properties": {
    "iso:country":"US",
    "sg:address":"3763 Lexington Ave N",
    "sg:city":"St Paul",
    "sg:classifiers":[
        {
            "category":"Retail",
            "subcategory":"Auto Repair",
            "type":"Services"
        }
    ],
    "sg:phone":"+1 651 482 9233",
    "sg:postcode":"55126",
    "sg:province":"MN",
    "sg:tags":[
        "repairing",
        "automobile"
    ],
    "wof:name":"Kennedy Transmission",
    "wof:placetype":"venue"
},
  "geometry": {"coordinates":[-93.147217,45.05606],"type":"Point"}
}