{
  "type": "Feature",
  "properties": {
    "iso:country":"US",
    "sg:address":"900 Long Lake Rd",
    "sg:city":"New Brighton",
    "sg:classifiers":[
        {
            "category":"Banks & Credit Unions",
            "subcategory":"Investment Brokerage",
            "type":"Services"
        }
    ],
    "sg:phone":"+1 651 631 2208",
    "sg:postcode":"55112",
    "sg:province":"MN",
    "sg:tags":[
        "consultant",
        "planning",
        "financial"
    ],
    "wof:name":"Ameriprize Financial",
    "wof:placetype":"venue"
},
  "geometry": {"coordinates":[-93.20217599999999,45.0653],"type":"Point"}
}