{
  "type": "Feature",
  "properties": {
    "addr:full":"3290 Lower 150th St W Rosemount MN 55068",
    "addr:housenumber":"3290",
    "addr:postcode":"55068",
    "addr:street":"Lower 150Th St W",
    "iso:country":"US",
    "sg:address":"3290 Lower 150th St W",
    "sg:city":"Rosemount",
    "sg:classifiers":[
        {
            "category":"Home & Garden",
            "subcategory":"Building Materials",
            "type":"Retail Goods"
        }
    ],
    "sg:phone":"+1 651 423 7444",
    "sg:postcode":"55068",
    "sg:province":"MN",
    "sg:tags":[
        "house"
    ],
    "wof:name":"Southside Garage Door Co",
    "wof:placetype":"venue"
},
  "geometry": {"coordinates":[-93.13166099999999,44.732325],"type":"Point"}
}