{
  "type": "Feature",
  "properties": {
    "iso:country":"US",
    "sg:address":"3777 Lexington Ave N",
    "sg:city":"Arden Hills",
    "sg:classifiers":[
        {
            "category":"Retail",
            "subcategory":"Auto Repair",
            "type":"Services"
        }
    ],
    "sg:phone":"+1 651 787 0633",
    "sg:postcode":"55126",
    "sg:province":"MN",
    "sg:tags":[
        "body",
        "automobile",
        "painting"
    ],
    "wof:name":"Abra Auto Body & Glass",
    "wof:placetype":"venue"
},
  "geometry": {"coordinates":[-93.14721400000001,45.055651],"type":"Point"}
}