{
  "type": "Feature",
  "properties": {
    "addr:full":"334 7th Ave N Bayport MN 55003",
    "addr:housenumber":"334",
    "addr:postcode":"55003",
    "addr:street":"7Th Ave N",
    "iso:country":"US",
    "sg:address":"334 7th Ave N",
    "sg:city":"Bayport",
    "sg:classifiers":[
        {
            "category":"Health Services",
            "subcategory":"Nursing And Care Facility",
            "type":"Services"
        },
        {
            "category":"Social Services",
            "subcategory":"Adult Care",
            "type":"Services"
        }
    ],
    "sg:phone":"+1 651 439 4946",
    "sg:postcode":"55003",
    "sg:province":"MN",
    "sg:tags":[
        "home",
        "intermediate",
        "residential"
    ],
    "wof:name":"Croixdale Residence & Apts",
    "wof:placetype":"venue"
},
  "geometry": {"coordinates":[-92.782021,45.023643],"type":"Point"}
}