{
  "type": "Feature",
  "properties": {
    "iso:country":"US",
    "sg:address":"2365 Carol Dr NE",
    "sg:city":"Bemidji",
    "sg:classifiers":[
        {
            "category":"Organizations",
            "subcategory":"Non-profit Organization",
            "type":"Services"
        }
    ],
    "sg:phone":"+1 218 751 5919",
    "sg:postcode":"56601",
    "sg:province":"MN",
    "sg:tags":[
        "human"
    ],
    "wof:name":"Stelher Human Svc",
    "wof:placetype":"venue"
},
  "geometry": {"coordinates":[-94.83448199999999,47.485514],"type":"Point"}
}