{
  "type": "Feature",
  "properties": {
    "iso:country":"US",
    "sg:address":"484 W Ashland Ave",
    "sg:city":"St Paul",
    "sg:classifiers":[
        {
            "category":"Health Services",
            "subcategory":"Nursing And Care Facility",
            "type":"Services"
        }
    ],
    "sg:phone":"+1 651 310 0119",
    "sg:postcode":"55102",
    "sg:province":"MN",
    "sg:tags":[
        "home",
        "convalescent"
    ],
    "sg:website":"www.spch.org",
    "wof:name":"St Paul's Church Home Inc",
    "wof:placetype":"venue"
},
  "geometry": {"coordinates":[-93.119792,44.944374],"type":"Point"}
}