{
  "type": "Feature",
  "properties": {
    "addr:full":"19236 740th St Hayfield MN 55940",
    "addr:housenumber":"19236",
    "addr:postcode":"55940",
    "addr:street":"740Th St",
    "iso:country":"US",
    "sg:address":"19236 740th St",
    "sg:city":"Hayfield",
    "sg:classifiers":[
        {
            "category":"Shopping",
            "subcategory":"Florist",
            "type":"Retail Goods"
        }
    ],
    "sg:phone":"+1 507 477 3149",
    "sg:postcode":"55940",
    "sg:province":"MN",
    "wof:name":"Goodman Greenhouse & Floral",
    "wof:placetype":"venue"
},
  "geometry": {"coordinates":[-92.856455,43.877931],"type":"Point"}
}