{
  "type": "Feature",
  "properties": {
    "iso:country":"US",
    "sg:address":"1015 Hillside Ave SW",
    "sg:city":"Pine City",
    "sg:classifiers":[
        {
            "category":"Banks & Credit Unions",
            "subcategory":"Bank",
            "type":"Services"
        }
    ],
    "sg:phone":"+1 320 629 5000",
    "sg:postcode":"55063",
    "sg:province":"MN",
    "wof:name":"Northwoods Bank",
    "wof:placetype":"venue"
},
  "geometry": {"coordinates":[-92.976928,45.819356],"type":"Point"}
}