{
  "type": "Feature",
  "properties": {
    "iso:country":"US",
    "sg:address":"58167 428th Ln",
    "sg:city":"New Ulm",
    "sg:classifiers":[
        {
            "category":"Professional",
            "subcategory":"Business Services",
            "type":"Services"
        }
    ],
    "sg:phone":"+1 507 354 3094",
    "sg:postcode":"56073",
    "sg:province":"MN",
    "wof:name":"Finstad Auctioneering Service",
    "wof:placetype":"venue"
},
  "geometry": {"coordinates":[-94.43340499999999,44.329751],"type":"Point"}
}