{
  "type": "Feature",
  "properties": {
    "iso:country":"US",
    "sg:address":"19711 Envoy Dr",
    "sg:city":"Park Rapids",
    "sg:classifiers":[
        {
            "category":"Building & Trades",
            "subcategory":"Construction",
            "type":"Services"
        }
    ],
    "sg:phone":"+1 218 732 4733",
    "sg:postcode":"56470",
    "sg:province":"MN",
    "sg:tags":[
        "residential"
    ],
    "wof:name":"Evans Construction Inc",
    "wof:placetype":"venue"
},
  "geometry": {"coordinates":[-94.955692,46.92867],"type":"Point"}
}