{
  "type": "Feature",
  "properties": {
    "addr:full":"4295 206th St W Farmington MN 55024",
    "addr:housenumber":"4295",
    "addr:postcode":"55024",
    "addr:street":"206Th St W",
    "iso:country":"US",
    "sg:address":"4295 206th St W",
    "sg:city":"Farmington",
    "sg:classifiers":[
        {
            "category":"Shopping",
            "subcategory":"Computers & Home Electronics",
            "type":"Retail Goods"
        }
    ],
    "sg:phone":"+1 612 670 6203",
    "sg:postcode":"55024",
    "sg:province":"MN",
    "wof:name":"Arron Systems",
    "wof:placetype":"venue"
},
  "geometry": {"coordinates":[-93.15214,44.648463],"type":"Point"}
}