{
  "type": "Feature",
  "properties": {
    "iso:country":"US",
    "sg:address":"9052 Woodhill Ln",
    "sg:city":"Nisswa",
    "sg:classifiers":[
        {
            "category":"Wholesale",
            "subcategory":"Non-durable Goods",
            "type":"Manufacturing & Wholesale Goods"
        }
    ],
    "sg:phone":"+1 218 562 5877",
    "sg:postcode":"56468",
    "sg:province":"MN",
    "wof:name":"Buckley Distributing Inc",
    "wof:placetype":"venue"
},
  "geometry": {"coordinates":[-94.21266799999999,46.541827],"type":"Point"}
}