{
  "type": "Feature",
  "properties": {
    "addr:full":"13084 25th St SW Cokato MN 55321",
    "addr:housenumber":"13084",
    "addr:postcode":"55321",
    "addr:street":"25Th St Sw",
    "iso:country":"US",
    "sg:address":"13084 25th St SW",
    "sg:city":"Cokato",
    "sg:classifiers":[
        {
            "category":"Food & Beverages",
            "subcategory":"Groceries & Convenience Stores",
            "type":"Retail Goods"
        }
    ],
    "sg:phone":"+1 952 932 4448",
    "sg:postcode":"55321",
    "sg:province":"MN",
    "wof:name":"Supervalu Inc",
    "wof:placetype":"venue"
},
  "geometry": {"coordinates":[-94.155935,45.115494],"type":"Point"}
}