{
  "type": "Feature",
  "properties": {
    "addr:full":"154 Blake Rd N Hopkins MN 55343",
    "addr:housenumber":"154",
    "addr:postcode":"55343",
    "addr:street":"Blake Rd N",
    "iso:country":"US",
    "sg:address":"154 Blake Rd N",
    "sg:city":"Hopkins",
    "sg:classifiers":[
        {
            "category":"Personal",
            "type":"Services"
        },
        {
            "category":"Sports & Exercise",
            "subcategory":"Gym",
            "type":"Entertainment"
        },
        {
            "category":"Health Services",
            "subcategory":"Health Practitioner",
            "type":"Services"
        },
        {
            "category":"Arena",
            "subcategory":"Sports Club",
            "type":"Entertainment"
        }
    ],
    "sg:phone":"+1 800 615 7352",
    "sg:postcode":"55343",
    "sg:province":"MN",
    "sg:tags":[
        "control",
        "weight",
        "consultant",
        "trainer",
        "program",
        "fitness",
        "physical"
    ],
    "sg:website":"http://twincities.citysearch.com/profile/external/36505442/hopkins_mn/curves.html?publisher=yellowpages&reference_id=1&placement=ypwebsitemip",
    "wof:name":"Curves",
    "wof:placetype":"venue"
},
  "geometry": {"coordinates":[-93.385696,44.927651],"type":"Point"}
}