{
  "type": "Feature",
  "properties": {
    "iso:country":"US",
    "sg:address":"1130 103rd Ave W",
    "sg:city":"Duluth",
    "sg:classifiers":[
        {
            "category":"Organizations",
            "subcategory":"Community Association",
            "type":"Services"
        }
    ],
    "sg:phone":"+1 218 626 1433",
    "sg:postcode":"55808",
    "sg:province":"MN",
    "wof:name":"Croatian Fraternal Union",
    "wof:placetype":"venue"
},
  "geometry": {"coordinates":[-92.229828,46.668457],"type":"Point"}
}