{
  "type": "Feature",
  "properties": {
    "iso:country":"US",
    "sg:address":"608 7th St W",
    "sg:city":"St Paul",
    "sg:classifiers":[
        {
            "category":"Retail",
            "subcategory":"Self-service Laundry",
            "type":"Services"
        }
    ],
    "sg:phone":"+1 651 291 0342",
    "sg:postcode":"55102",
    "sg:province":"MN",
    "wof:name":"Wooden Tub",
    "wof:placetype":"venue"
},
  "geometry": {"coordinates":[-93.115523,44.93541],"type":"Point"}
}