{
  "type": "Feature",
  "properties": {
    "addr:full":"1056 N Kilburn St Saint Paul MN 55103",
    "addr:housenumber":"1056",
    "addr:postcode":"55103",
    "addr:street":"N Kilburn St",
    "iso:country":"US",
    "sg:address":"1056 N Kilburn St",
    "sg:city":"Saint Paul",
    "sg:classifiers":[
        {
            "category":"Shopping",
            "type":"Retail Goods"
        }
    ],
    "sg:phone":"+1 651 489 9233",
    "sg:postcode":"55103",
    "sg:province":"MN",
    "sg:tags":[
        "merchandise"
    ],
    "wof:name":"Vanbergen & Assoc Inc",
    "wof:placetype":"venue"
},
  "geometry": {"coordinates":[-93.140372,44.973014],"type":"Point"}
}