{
  "type": "Feature",
  "properties": {
    "iso:country":"US",
    "sg:address":"5008 Xerxes Ave",
    "sg:city":"Minneapolis",
    "sg:classifiers":[
        {
            "category":"Food & Beverages",
            "subcategory":"Specialty",
            "type":"Retail Goods"
        }
    ],
    "sg:phone":"+1 612 928 0345",
    "sg:postcode":"55410",
    "sg:province":"MN",
    "sg:tags":[
        "tea",
        "coffee"
    ],
    "wof:name":"Dunn Brothers Coffee",
    "wof:placetype":"venue"
},
  "geometry": {"coordinates":[-93.318923,44.910788],"type":"Point"}
}