{
  "type": "Feature",
  "properties": {
    "addr:full":"380 Jackson St Saint Paul MN 55101",
    "addr:housenumber":"380",
    "addr:postcode":"55101",
    "addr:street":"Jackson St",
    "iso:country":"US",
    "sg:address":"380 Jackson St",
    "sg:city":"Saint Paul",
    "sg:classifiers":[
        {
            "category":"Government",
            "subcategory":"Office",
            "type":"Public Place"
        }
    ],
    "sg:phone":"+1 651 290 3861",
    "sg:postcode":"55101",
    "sg:province":"MN",
    "sg:tags":[
        "auditing"
    ],
    "wof:name":"Inspector General",
    "wof:placetype":"venue"
},
  "geometry": {"coordinates":[-93.089929,44.948468],"type":"Point"}
}