{
  "type": "Feature",
  "properties": {
    "addr:full":"1111 Franklin Ave NE Sauk Rapids MN 56304",
    "addr:housenumber":"1111",
    "addr:postcode":"56304",
    "addr:street":"Franklin Ave Ne",
    "iso:country":"US",
    "sg:address":"1111 Franklin Ave NE",
    "sg:city":"Sauk Rapids",
    "sg:classifiers":[
        {
            "category":"Freight",
            "type":"Transportation"
        }
    ],
    "sg:phone":"+1 320 251 0334",
    "sg:postcode":"56304",
    "sg:province":"MN",
    "sg:tags":[
        "commercial",
        "storage"
    ],
    "wof:name":"Public Storage",
    "wof:placetype":"venue"
},
  "geometry": {"coordinates":[-94.149379,45.577436],"type":"Point"}
}