{
  "type": "Feature",
  "properties": {
    "iso:country":"US",
    "sg:address":"600 Robert St N",
    "sg:city":"Saint Paul",
    "sg:classifiers":[
        {
            "category":"Government",
            "subcategory":"Office",
            "type":"Public Place"
        }
    ],
    "sg:phone":"+1 651 296 9125",
    "sg:postcode":"55101",
    "sg:province":"MN",
    "sg:tags":[
        "information",
        "tax"
    ],
    "wof:name":"Telephone Taxpayer Assistance",
    "wof:placetype":"venue"
},
  "geometry": {"coordinates":[-93.09731499999999,44.953966],"type":"Point"}
}