{
  "type": "Feature",
  "properties": {
    "addr:full":"212 Ellen St Stewartville MN 55961",
    "addr:housenumber":"212",
    "addr:postcode":"55961",
    "addr:street":"Ellen St",
    "iso:country":"US",
    "sg:address":"212 Ellen St",
    "sg:city":"Stewartville",
    "sg:classifiers":[
        {
            "category":"Professional",
            "subcategory":"Business Services",
            "type":"Services"
        }
    ],
    "sg:phone":"+1 507 657 2212",
    "sg:postcode":"55961",
    "sg:province":"MN",
    "wof:name":"Toad Runner Express",
    "wof:placetype":"venue"
},
  "geometry": {"coordinates":[-92.4251,43.61661],"type":"Point"}
}