{
  "type": "Feature",
  "properties": {
    "iso:country":"US",
    "sg:address":"212 Dewey St",
    "sg:city":"Jackson",
    "sg:phone":"+1 507 847 3234",
    "sg:postcode":"56143",
    "sg:province":"MN",
    "sg:tags":[
        "hog",
        "farm",
        "corn",
        "soybean",
        "or",
        "feedlot"
    ],
    "wof:name":"James Tusa",
    "wof:placetype":"venue"
},
  "geometry": {"coordinates":[-95.00097700000001,43.619303],"type":"Point"}
}