{
  "type": "Feature",
  "properties": {
    "addr:full":"2525 Fairview Ave N Saint Paul MN 55113",
    "addr:housenumber":"2525",
    "addr:postcode":"55113",
    "addr:street":"Fairview Ave N",
    "iso:country":"US",
    "sg:address":"2525 Fairview Ave N",
    "sg:city":"Saint Paul",
    "sg:classifiers":[
        {
            "category":"Wholesale",
            "subcategory":"Auto Parts",
            "type":"Manufacturing & Wholesale Goods"
        }
    ],
    "sg:phone":"+1 651 631 5735",
    "sg:postcode":"55113",
    "sg:province":"MN",
    "sg:tags":[
        "paint",
        "accessory"
    ],
    "wof:name":"Auto-Mate of Cedar Rapids",
    "wof:placetype":"venue"
},
  "geometry": {"coordinates":[-93.177019,45.017783],"type":"Point"}
}