{
  "type": "Feature",
  "properties": {
    "addr:full":"119 Friberg Ave Fergus Falls MN 56537",
    "addr:housenumber":"119",
    "addr:postcode":"56537",
    "addr:street":"Friberg Ave",
    "iso:country":"US",
    "sg:address":"119 Friberg Ave",
    "sg:city":"Fergus Falls",
    "sg:classifiers":[
        {
            "category":"Manufacturing",
            "subcategory":"Tools & Machinery",
            "type":"Manufacturing & Wholesale Goods"
        },
        {
            "category":"Building & Trades",
            "subcategory":"Plumbing",
            "type":"Services"
        }
    ],
    "sg:phone":"+1 218 998 9600",
    "sg:postcode":"56537",
    "sg:province":"MN",
    "sg:tags":[
        "product",
        "management",
        "energy",
        "system"
    ],
    "wof:name":"Lighthouse Energy Trading Co",
    "wof:placetype":"venue"
},
  "geometry": {"coordinates":[-96.071011,46.283674],"type":"Point"}
}