{
  "type": "Feature",
  "properties": {
    "iso:country":"US",
    "sg:address":"5000 Halifax Ave S",
    "sg:city":"Minneapolis",
    "sg:classifiers":[
        {
            "category":"Utilities",
            "subcategory":"Telephone",
            "type":"Services"
        }
    ],
    "sg:phone":"+1 952 929 9423",
    "sg:postcode":"55424",
    "sg:province":"MN",
    "sg:tags":[
        "communications"
    ],
    "wof:name":"Intervoice Brite",
    "wof:placetype":"venue"
},
  "geometry": {"coordinates":[-93.33154999999999,44.911469],"type":"Point"}
}