{
  "type": "Feature",
  "properties": {
    "addr:full":"53598 Co Hwy 148 Menahga MN 56464",
    "addr:housenumber":"53598",
    "addr:postcode":"56464",
    "addr:street":"Co Hwy 148 Menahga",
    "iso:country":"US",
    "sg:address":"53598 Co Hwy 148",
    "sg:city":"Menahga",
    "sg:classifiers":[
        {
            "category":"Farming",
            "subcategory":"Dairy Farm",
            "type":"Manufacturing & Wholesale Goods"
        }
    ],
    "sg:phone":"+1 218 385 3144",
    "sg:postcode":"56464",
    "sg:province":"MN",
    "wof:name":"Roberts Dairy",
    "wof:placetype":"venue"
},
  "geometry": {"coordinates":[-95.361513,46.687846],"type":"Point"}
}