{
  "type": "Feature",
  "properties": {
    "addr:full":"1509 Irvine Ave NW Bemidji MN 56601",
    "addr:housenumber":"1509",
    "addr:postcode":"56601",
    "addr:street":"Irvine Ave Nw",
    "iso:country":"US",
    "sg:address":"1509 Irvine Ave NW",
    "sg:city":"Bemidji",
    "sg:classifiers":[
        {
            "category":"Professional",
            "subcategory":"Employment Agencies",
            "type":"Services"
        }
    ],
    "sg:phone":"+1 218 759 3074",
    "sg:postcode":"56601",
    "sg:province":"MN",
    "sg:tags":[
        "nurse"
    ],
    "wof:name":"Lisa Buckanaga",
    "wof:placetype":"venue"
},
  "geometry": {"coordinates":[-94.885476,47.483929],"type":"Point"}
}