{
  "type": "Feature",
  "properties": {
    "addr:full":"3538 Fillmore St NE Minneapolis MN 55418",
    "addr:housenumber":"3538",
    "addr:postcode":"55418",
    "addr:street":"Fillmore St Ne",
    "iso:country":"US",
    "sg:address":"3538 Fillmore St NE",
    "sg:city":"Minneapolis",
    "sg:classifiers":[
        {
            "category":"Restaurant",
            "type":"Food & Drink"
        }
    ],
    "sg:phone":"+1 612 782 9141",
    "sg:postcode":"55418",
    "sg:province":"MN",
    "sg:tags":[
        "pizza"
    ],
    "wof:name":"Time Square Pizza & Subs",
    "wof:placetype":"venue"
},
  "geometry": {"coordinates":[-93.24221300000001,45.032099],"type":"Point"}
}