{
  "type": "Feature",
  "properties": {
    "iso:country":"US",
    "sg:address":"47 Little Canada Rd E",
    "sg:city":"Saint Paul",
    "sg:classifiers":[
        {
            "category":"Home & Garden",
            "subcategory":"Furniture",
            "type":"Retail Goods"
        }
    ],
    "sg:phone":"+1 952 431 5046",
    "sg:postcode":"55117",
    "sg:province":"MN",
    "wof:name":"Alter Ergo Inc",
    "wof:placetype":"venue"
},
  "geometry": {"coordinates":[-93.099756,45.025621],"type":"Point"}
}