{
  "type": "Feature",
  "properties": {
    "iso:country":"US",
    "sg:address":"1380 Highland Village Dr # 23",
    "sg:city":"Duluth",
    "sg:classifiers":[
        {
            "category":"Real Estate",
            "subcategory":"Real Estate Services",
            "type":"Services"
        }
    ],
    "sg:phone":"+1 218 727 5100",
    "sg:postcode":"55811",
    "sg:province":"MN",
    "sg:tags":[
        "consultant"
    ],
    "wof:name":"Integrity Resources",
    "wof:placetype":"venue"
},
  "geometry": {"coordinates":[-92.11715700000001,46.802238],"type":"Point"}
}