{
  "type": "Feature",
  "properties": {
    "iso:country":"US",
    "sg:address":"6910 E Lake Carlos Dr NE",
    "sg:city":"Carlos",
    "sg:classifiers":[
        {
            "category":"Food & Beverages",
            "subcategory":"Groceries & Convenience Stores",
            "type":"Retail Goods"
        }
    ],
    "sg:phone":"+1 320 846 1021",
    "sg:postcode":"56319",
    "sg:province":"MN",
    "wof:name":"Gas Mart of Carlos Conners",
    "wof:placetype":"venue"
},
  "geometry": {"coordinates":[-95.356234,45.966885],"type":"Point"}
}