{
  "type": "Feature",
  "properties": {
    "addr:full":"6727 Lakeview Ave Minneapolis MN 55423",
    "addr:housenumber":"6727",
    "addr:postcode":"55423",
    "addr:street":"Lakeview Ave",
    "iso:country":"US",
    "sg:address":"6727 Lakeview Ave",
    "sg:city":"Minneapolis",
    "sg:classifiers":[
        {
            "category":"Building & Trades",
            "subcategory":"Construction",
            "type":"Services"
        }
    ],
    "sg:phone":"+1 612 869 2024",
    "sg:postcode":"55423",
    "sg:province":"MN",
    "sg:tags":[
        "house"
    ],
    "wof:name":"City-Sites Developments Inc",
    "wof:placetype":"venue"
},
  "geometry": {"coordinates":[-93.301467,44.880096],"type":"Point"}
}