{
  "type": "Feature",
  "properties": {
    "iso:country":"US",
    "sg:address":"512 8th St S",
    "sg:city":"Brainerd",
    "sg:classifiers":[
        {
            "category":"Organizations",
            "subcategory":"Religious Organization",
            "type":"Services"
        }
    ],
    "sg:phone":"+1 218 829 6069",
    "sg:postcode":"56401",
    "sg:province":"MN",
    "wof:name":"Presbytery of Minnesota Valley",
    "wof:placetype":"venue"
},
  "geometry": {"coordinates":[-94.197694,46.353553],"type":"Point"}
}