{
  "type": "Feature",
  "properties": {
    "addr:full":"1805 W River St Monticello MN 55362",
    "addr:housenumber":"1805",
    "addr:postcode":"55362",
    "addr:street":"W River St",
    "iso:country":"US",
    "sg:address":"1805 W River St",
    "sg:city":"Monticello",
    "sg:classifiers":[
        {
            "category":"Building & Trades",
            "subcategory":"Landscaping Services",
            "type":"Services"
        }
    ],
    "sg:phone":"+1 763 295 6417",
    "sg:postcode":"55362",
    "sg:province":"MN",
    "wof:name":"High Expectations Gardening",
    "wof:placetype":"venue"
},
  "geometry": {"coordinates":[-93.828835,45.321219],"type":"Point"}
}