{
  "type": "Feature",
  "properties": {
    "addr:full":"8015 Grand Ave S Minneapolis MN 55420",
    "addr:housenumber":"8015",
    "addr:postcode":"55420",
    "addr:street":"Grand Ave S",
    "iso:country":"US",
    "sg:address":"8015 Grand Ave S",
    "sg:city":"Minneapolis",
    "sg:classifiers":[
        {
            "category":"Building & Trades",
            "subcategory":"Landscaping Services",
            "type":"Services"
        }
    ],
    "sg:phone":"+1 952 930 5159",
    "sg:postcode":"55420",
    "sg:province":"MN",
    "sg:tags":[
        "contracting",
        "landscape"
    ],
    "wof:name":"Pine To Prairie Landscapes",
    "wof:placetype":"venue"
},
  "geometry": {"coordinates":[-93.284569,44.857241],"type":"Point"}
}