{
  "type": "Feature",
  "properties": {
    "addr:full":"733 2 1/2 St N Sartell MN 56377",
    "addr:housenumber":"733;1 / 2",
    "addr:postcode":"56377",
    "addr:street":"2;St N",
    "iso:country":"US",
    "sg:address":"733 2 1/2 St N",
    "sg:city":"Sartell",
    "sg:classifiers":[
        {
            "category":"Social Services",
            "subcategory":"Child Care",
            "type":"Services"
        }
    ],
    "sg:phone":"+1 320 252 2743",
    "sg:postcode":"56377",
    "sg:province":"MN",
    "sg:tags":[
        "nursery",
        "day"
    ],
    "wof:name":"Darlene Gunderson",
    "wof:placetype":"venue"
},
  "geometry": {"coordinates":[-94.217142,45.622567],"type":"Point"}
}