{
  "type": "Feature",
  "properties": {
    "iso:country":"US",
    "sg:address":"2014 W Superior St",
    "sg:city":"Duluth",
    "sg:classifiers":[
        {
            "category":"Government",
            "subcategory":"Police Station",
            "type":"Public Place"
        }
    ],
    "sg:phone":"+1 218 723 3506",
    "sg:postcode":"55806",
    "sg:province":"MN",
    "sg:tags":[
        "department"
    ],
    "wof:name":"Duluth Police Dept",
    "wof:placetype":"venue"
},
  "geometry": {"coordinates":[-92.124087,46.767032],"type":"Point"}
}