{
  "type": "Feature",
  "properties": {
    "iso:country":"US",
    "sg:address":"950 Co Rd D W",
    "sg:city":"New Brighton",
    "sg:classifiers":[
        {
            "category":"Food & Beverages",
            "subcategory":"Groceries & Convenience Stores",
            "type":"Retail Goods"
        },
        {
            "category":"Autos & Motor Vehicles",
            "subcategory":"Fuel & Gas Station",
            "type":"Retail Goods"
        }
    ],
    "sg:phone":"+1 651 633 9180",
    "sg:postcode":"55112",
    "sg:province":"MN",
    "sg:tags":[
        "chain"
    ],
    "wof:name":"PDQ Food Stores Inc",
    "wof:placetype":"venue"
},
  "geometry": {"coordinates":[-93.202478,45.035662],"type":"Point"}
}