{
  "type": "Feature",
  "properties": {
    "addr:full":"160 Main St W Wabasha MN 55981",
    "addr:housenumber":"160",
    "addr:postcode":"55981",
    "addr:street":"Main St W",
    "iso:country":"US",
    "sg:address":"160 Main St W",
    "sg:city":"Wabasha",
    "sg:classifiers":[
        {
            "category":"Organizations",
            "subcategory":"Professional Association",
            "type":"Services"
        }
    ],
    "sg:phone":"+1 651 565 4158",
    "sg:postcode":"55981",
    "sg:province":"MN",
    "sg:tags":[
        "chambers",
        "commerce"
    ],
    "wof:name":"Chamber Of Commerce",
    "wof:placetype":"venue"
},
  "geometry": {"coordinates":[-92.033556,44.384428],"type":"Point"}
}