{
  "type": "Feature",
  "properties": {
    "addr:full":"105 Parker Ln Redwood Falls MN 56283",
    "addr:housenumber":"105",
    "addr:postcode":"56283",
    "addr:street":"Parker Ln",
    "iso:country":"US",
    "sg:address":"105 Parker Ln",
    "sg:city":"Redwood Falls",
    "sg:classifiers":[
        {
            "category":"Manufacturing",
            "subcategory":"Tools & Machinery",
            "type":"Manufacturing & Wholesale Goods"
        }
    ],
    "sg:phone":"+1 507 637 3436",
    "sg:postcode":"56283",
    "sg:province":"MN",
    "sg:tags":[
        "process",
        "control",
        "mfg",
        "instrument"
    ],
    "wof:name":"Sensor Measurement Technology",
    "wof:placetype":"venue"
},
  "geometry": {"coordinates":[-95.121709,44.533283],"type":"Point"}
}