{
  "type": "Feature",
  "properties": {
    "iso:country":"US",
    "sg:address":"6545 France Ave S",
    "sg:city":"Edina",
    "sg:classifiers":[
        {
            "category":"Health Services",
            "subcategory":"Clinic",
            "type":"Services"
        }
    ],
    "sg:phone":"+1 952 926 8887",
    "sg:postcode":"55435",
    "sg:province":"MN",
    "sg:tags":[
        "examination",
        "insurance"
    ],
    "wof:name":"Certified Medical Evaluations",
    "wof:placetype":"venue"
},
  "geometry": {"coordinates":[-93.328863,44.884544],"type":"Point"}
}