{
  "type": "Feature",
  "properties": {
    "iso:country":"US",
    "sg:address":"2000 Colfax Ave S",
    "sg:city":"Minneapolis",
    "sg:classifiers":[
        {
            "category":"Retail",
            "subcategory":"Laundry & Dry Cleaning",
            "type":"Services"
        }
    ],
    "sg:phone":"+1 612 871 2100",
    "sg:postcode":"55405",
    "sg:province":"MN",
    "wof:name":"Nokomis Cleaners & Launderers",
    "wof:placetype":"venue"
},
  "geometry": {"coordinates":[-93.29299899999999,44.960499],"type":"Point"}
}