{
  "type": "Feature",
  "properties": {
    "addr:full":"20298 Indian Ln Mankato MN 56001",
    "addr:housenumber":"20298",
    "addr:postcode":"56001",
    "addr:street":"Indian Ln",
    "iso:country":"US",
    "sg:address":"20298 Indian Ln",
    "sg:city":"Mankato",
    "sg:classifiers":[
        {
            "category":"Building & Trades",
            "subcategory":"Construction",
            "type":"Services"
        }
    ],
    "sg:phone":"+1 507 625 3321",
    "sg:postcode":"56001",
    "sg:province":"MN",
    "sg:tags":[
        "contractor"
    ],
    "wof:name":"Kroeger Plastering",
    "wof:placetype":"venue"
},
  "geometry": {"coordinates":[-94.02923199999999,44.126432],"type":"Point"}
}