{
  "type": "Feature",
  "properties": {
    "iso:country":"US",
    "sg:address":"13191 290th Ave",
    "sg:city":"Waseca",
    "sg:classifiers":[
        {
            "category":"Education",
            "subcategory":"College",
            "type":"Public Place"
        }
    ],
    "sg:phone":"+1 507 835 8261",
    "sg:postcode":"56093",
    "sg:province":"MN",
    "sg:tags":[
        "academic",
        "school"
    ],
    "wof:name":"South Central Technical Cllg",
    "wof:placetype":"venue"
},
  "geometry": {"coordinates":[-93.56667899999999,43.978698],"type":"Point"}
}