{
  "type": "Feature",
  "properties": {
    "iso:country":"US",
    "sg:address":"110 S Church St",
    "sg:city":"Peterson",
    "sg:classifiers":[
        {
            "category":"Farming",
            "subcategory":"Dairy Farm",
            "type":"Manufacturing & Wholesale Goods"
        }
    ],
    "sg:phone":"+1 507 875 2557",
    "sg:postcode":"55962",
    "sg:province":"MN",
    "wof:name":"Mike Boyum",
    "wof:placetype":"venue"
},
  "geometry": {"coordinates":[-91.834836,43.786351],"type":"Point"}
}