{
  "type": "Feature",
  "properties": {
    "iso:country":"US",
    "sg:address":"6425 Tanager Ln",
    "sg:city":"Eden Prairie",
    "sg:classifiers":[
        {
            "category":"Communications",
            "subcategory":"Film & Video Production",
            "type":"Services"
        }
    ],
    "sg:phone":"+1 952 974 8024",
    "sg:postcode":"55346",
    "sg:province":"MN",
    "sg:tags":[
        "taping"
    ],
    "wof:name":"C P Productions",
    "wof:placetype":"venue"
},
  "geometry": {"coordinates":[-93.453846,44.886652],"type":"Point"}
}