{
  "type": "Feature",
  "properties": {
    "addr:full":"7660 Banning Way Inver Grove Heights MN 55077",
    "addr:housenumber":"7660",
    "addr:postcode":"55077",
    "addr:street":"Banning Way",
    "iso:country":"US",
    "sg:address":"7660 Banning Way",
    "sg:city":"Inver Grove Heights",
    "sg:classifiers":[
        {
            "category":"Professional",
            "subcategory":"Art Services",
            "type":"Services"
        }
    ],
    "sg:phone":"+1 651 450 6960",
    "sg:postcode":"55077",
    "sg:province":"MN",
    "sg:tags":[
        "photography",
        "commercial"
    ],
    "wof:name":"Aerophoto Inc",
    "wof:placetype":"venue"
},
  "geometry": {"coordinates":[-93.063992,44.839011],"type":"Point"}
}