{
  "type": "Feature",
  "properties": {
    "addr:full":"2730 E 31st St Minneapolis MN 55406",
    "addr:housenumber":"2730",
    "addr:postcode":"55406",
    "addr:street":"E 31St St",
    "iso:country":"US",
    "sg:address":"2730 E 31st St",
    "sg:city":"Minneapolis",
    "sg:classifiers":[
        {
            "category":"Social Services",
            "subcategory":"Child Care",
            "type":"Services"
        }
    ],
    "sg:phone":"+1 612 729 8358",
    "sg:postcode":"55406",
    "sg:province":"MN",
    "sg:tags":[
        "organization",
        "religious",
        "day"
    ],
    "wof:name":"Holy Trinity Child Center",
    "wof:placetype":"venue"
},
  "geometry": {"coordinates":[-93.231934,44.946928],"type":"Point"}
}