{
  "type": "Feature",
  "properties": {
    "addr:full":"2500 27th Ave S Minneapolis MN 55406",
    "addr:housenumber":"2500",
    "addr:postcode":"55406",
    "addr:street":"27Th Ave S",
    "iso:country":"US",
    "sg:address":"2500 27th Ave S",
    "sg:city":"Minneapolis",
    "sg:classifiers":[
        {
            "category":"Building & Trades",
            "subcategory":"Locksmith",
            "type":"Services"
        }
    ],
    "sg:phone":"+1 612 564 1318",
    "sg:postcode":"55406",
    "sg:province":"MN",
    "sg:tags":[
        "locksmiths-commercial",
        "industrial",
        "lock"
    ],
    "wof:name":"All Day 24 Hour Locksmith",
    "wof:placetype":"venue"
},
  "geometry": {"coordinates":[-93.233063,44.957371],"type":"Point"}
}