{
  "type": "Feature",
  "properties": {
    "iso:country":"US",
    "sg:address":"275 Market St Ste 188",
    "sg:city":"Minneapolis",
    "sg:classifiers":[
        {
            "category":"Real Estate",
            "subcategory":"Architect",
            "type":"Services"
        }
    ],
    "sg:phone":"+1 612 341 0388",
    "sg:postcode":"55405",
    "sg:province":"MN",
    "wof:name":"Unique by Design",
    "wof:placetype":"venue"
},
  "geometry": {"coordinates":[-93.289643,44.980501],"type":"Point"}
}