{
  "type": "Feature",
  "properties": {
    "iso:country":"US",
    "sg:address":"8554 Hidden Bay Trl N",
    "sg:city":"Lake Elmo",
    "sg:classifiers":[
        {
            "category":"Professional",
            "type":"Services"
        }
    ],
    "sg:phone":"+1 651 777 6205",
    "sg:postcode":"55042",
    "sg:province":"MN",
    "wof:name":"BDB Inc",
    "wof:placetype":"venue"
},
  "geometry": {"coordinates":[-92.93274099999999,45.016936],"type":"Point"}
}