{
  "type": "Feature",
  "properties": {
    "iso:country":"US",
    "sg:address":"211 2nd St SW",
    "sg:city":"Rochester",
    "sg:classifiers":[
        {
            "category":"Social Services",
            "type":"Services"
        }
    ],
    "sg:phone":"+1 507 266 7851",
    "sg:postcode":"55923",
    "sg:province":"MN",
    "wof:name":"Charter Health",
    "wof:placetype":"venue"
},
  "geometry": {"coordinates":[-92.19148800000001,43.844049],"type":"Point"}
}