{
  "type": "Feature",
  "properties": {
    "addr:full":"28 3rd St NE Faribault MN 55021",
    "addr:housenumber":"28",
    "addr:postcode":"55021",
    "addr:street":"3Rd St Ne",
    "iso:country":"US",
    "sg:address":"28 3rd St NE",
    "sg:city":"Faribault",
    "sg:classifiers":[
        {
            "category":"Government",
            "subcategory":"Post Office",
            "type":"Public Place"
        }
    ],
    "sg:phone":"+1 507 334 5075",
    "sg:postcode":"55021",
    "sg:province":"MN",
    "wof:name":"US Post Office",
    "wof:placetype":"venue"
},
  "geometry": {"coordinates":[-93.268069,44.293714],"type":"Point"}
}