{
  "type": "Feature",
  "properties": {
    "addr:full":"1833 3rd Ave S Minneapolis MN 55404",
    "addr:housenumber":"1833",
    "addr:postcode":"55404",
    "addr:street":"3Rd Ave S",
    "iso:country":"US",
    "sg:address":"1833 3rd Ave S",
    "sg:city":"Minneapolis",
    "sg:classifiers":[
        {
            "category":"Health Services",
            "subcategory":"Doctor",
            "type":"Services"
        }
    ],
    "sg:phone":"+1 763 712 6200",
    "sg:postcode":"55404",
    "sg:province":"MN",
    "sg:tags":[
        "clinic"
    ],
    "wof:name":"River Way Clinic",
    "wof:placetype":"venue"
},
  "geometry": {"coordinates":[-93.272678,44.964372],"type":"Point"}
}