{
  "type": "Feature",
  "properties": {
    "iso:country":"US",
    "sg:address":"222 Market St",
    "sg:city":"Bloomington",
    "sg:classifiers":[
        {
            "category":"Shopping",
            "subcategory":"Bicycles & Sporting Goods",
            "type":"Retail Goods"
        }
    ],
    "sg:phone":"+1 952 854 9444",
    "sg:postcode":"55405",
    "sg:province":"MN",
    "sg:website":"www.sportmart.com",
    "wof:name":"Sportmart",
    "wof:placetype":"venue"
},
  "geometry": {"coordinates":[-93.289734,44.980516],"type":"Point"}
}