{
  "type": "Feature",
  "properties": {
    "iso:country":"US",
    "sg:address":"637 Cedar Lake Rd S",
    "sg:city":"Minneapolis",
    "sg:classifiers":[
        {
            "category":"Building & Trades",
            "subcategory":"Pest Control",
            "type":"Services"
        }
    ],
    "sg:phone":"+1 612 333 6969",
    "sg:postcode":"55405",
    "sg:province":"MN",
    "wof:name":"Professional Pest Control Co",
    "wof:placetype":"venue"
},
  "geometry": {"coordinates":[-93.31251899999999,44.971465],"type":"Point"}
}