{
  "type": "Feature",
  "properties": {
    "iso:country":"US",
    "sg:address":"315 7th Ave N",
    "sg:city":"Minneapolis",
    "sg:classifiers":[
        {
            "category":"Shopping",
            "subcategory":"Clothing, Apparel, & Fashions",
            "type":"Retail Goods"
        }
    ],
    "sg:phone":"+1 612 332 2369",
    "sg:postcode":"55401",
    "sg:province":"MN",
    "sg:tags":[
        "salvage",
        "surplus",
        "merchandise"
    ],
    "wof:name":"Industrial Surplus Inc",
    "wof:placetype":"venue"
},
  "geometry": {"coordinates":[-93.278199,44.98627],"type":"Point"}
}