{
  "type": "Feature",
  "properties": {
    "iso:country":"US",
    "sg:address":"310 6th Ave",
    "sg:city":"Madison",
    "sg:phone":"+1 320 598 7791",
    "sg:postcode":"56256",
    "sg:province":"MN",
    "wof:name":"Grand Theatre",
    "wof:placetype":"venue"
},
  "geometry": {"coordinates":[-96.193108,45.010051],"type":"Point"}
}