{
  "type": "Feature",
  "properties": {
    "addr:full":"615 N Main St Mantorville MN 55955",
    "addr:housenumber":"615",
    "addr:postcode":"55955",
    "addr:street":"N Main St",
    "iso:country":"US",
    "sg:address":"615 N Main St",
    "sg:city":"Mantorville",
    "sg:classifiers":[
        {
            "category":"Education",
            "subcategory":"Library",
            "type":"Public Place"
        }
    ],
    "sg:phone":"+1 507 635 5508",
    "sg:postcode":"55955",
    "sg:province":"MN",
    "sg:tags":[
        "special",
        "interest"
    ],
    "wof:name":"Dodge Co Historical Soc Libr",
    "wof:placetype":"venue"
},
  "geometry": {"coordinates":[-92.755388,44.068735],"type":"Point"}
}