{
  "type": "Feature",
  "properties": {
    "addr:full":"2020 Aldrich Ave N Minneapolis MN 55411",
    "addr:housenumber":"2020",
    "addr:postcode":"55411",
    "addr:street":"Aldrich Ave N",
    "iso:country":"US",
    "sg:address":"2020 Aldrich Ave N",
    "sg:city":"Minneapolis",
    "sg:classifiers":[
        {
            "category":"Building & Trades",
            "subcategory":"Construction",
            "type":"Services"
        }
    ],
    "sg:phone":"+1 612 522 0887",
    "sg:postcode":"55411",
    "sg:province":"MN",
    "sg:tags":[
        "home",
        "builder",
        "concrete",
        "contractor"
    ],
    "wof:name":"Vera Construction, Inc",
    "wof:placetype":"venue"
},
  "geometry": {"coordinates":[-93.28951600000001,44.999796],"type":"Point"}
}