{
  "type": "Feature",
  "properties": {
    "iso:country":"US",
    "sg:address":"3435 Anderson Rd",
    "sg:city":"Hibbing",
    "sg:classifiers":[
        {
            "category":"Travel",
            "subcategory":"Travel Agent",
            "type":"Entertainment"
        }
    ],
    "sg:phone":"+1 218 263 3424",
    "sg:postcode":"55746",
    "sg:province":"MN",
    "sg:tags":[
        "agency"
    ],
    "wof:name":"Cruiseone",
    "wof:placetype":"venue"
},
  "geometry": {"coordinates":[-92.96993999999999,47.370919],"type":"Point"}
}