{
  "type": "Feature",
  "properties": {
    "addr:full":"119 Cedar St S Grey Eagle MN 56336",
    "addr:housenumber":"119",
    "addr:postcode":"56336",
    "addr:street":"Cedar St S",
    "iso:country":"US",
    "sg:address":"119 Cedar St S",
    "sg:city":"Grey Eagle",
    "sg:classifiers":[
        {
            "category":"Freight",
            "type":"Transportation"
        }
    ],
    "sg:phone":"+1 320 285 3195",
    "sg:postcode":"56336",
    "sg:province":"MN",
    "wof:name":"Grey Eagle Transport Corp",
    "wof:placetype":"venue"
},
  "geometry": {"coordinates":[-94.74952999999999,45.824293],"type":"Point"}
}