{
  "type": "Feature",
  "properties": {
    "addr:full":"435 Fontaine Ct Saint Paul MN 55125",
    "addr:housenumber":"435",
    "addr:postcode":"55125",
    "addr:street":"Fontaine Ct",
    "iso:country":"US",
    "sg:address":"435 Fontaine Ct",
    "sg:city":"Saint Paul",
    "sg:classifiers":[
        {
            "category":"Home & Garden",
            "subcategory":"Home Furnishings",
            "type":"Retail Goods"
        }
    ],
    "sg:phone":"+1 651 730 6416",
    "sg:postcode":"55125",
    "sg:province":"MN",
    "wof:name":"Rick Gaundenberg",
    "wof:placetype":"venue"
},
  "geometry": {"coordinates":[-92.948796,44.941908],"type":"Point"}
}