{
  "type": "Feature",
  "properties": {
    "iso:country":"US",
    "sg:address":"8060 MN-55",
    "sg:city":"Rockford",
    "sg:classifiers":[
        {
            "category":"Restaurant",
            "type":"Food & Drink"
        }
    ],
    "sg:menulink":"http://www.allmenus.com/mn/rockford/58445-dominos-pizza/menu/",
    "sg:phone":"+1 763 477 4443",
    "sg:postcode":"55373",
    "sg:province":"MN",
    "sg:tags":[
        "american",
        "wing",
        "pizza"
    ],
    "wof:name":"Domino's Pizza",
    "wof:placetype":"venue"
},
  "geometry": {"coordinates":[-93.73075799999999,45.083646],"type":"Point"}
}