{
  "type": "Feature",
  "properties": {
    "addr:full":"2300 American Blvd E Minneapolis MN 55425",
    "addr:housenumber":"2300",
    "addr:postcode":"55425",
    "addr:street":"American Blvd E",
    "iso:country":"US",
    "sg:address":"2300 American Blvd E",
    "sg:city":"Minneapolis",
    "sg:classifiers":[
        {
            "category":"Bars & Pubs",
            "type":"Food & Drink"
        },
        {
            "category":"Arts & Performance",
            "subcategory":"Comedy Club",
            "type":"Entertainment"
        }
    ],
    "sg:phone":"+1 612 235 6223",
    "sg:postcode":"55425",
    "sg:province":"MN",
    "sg:website":"http://twincities.citysearch.com/profile/external/45327951/bloomington_mn/joke_joint_comedy_club.html?publisher=yellowpages&reference_id=1&placement=ypwebsitemip",
    "wof:name":"Joke Joint Comedy Club",
    "wof:placetype":"venue"
},
  "geometry": {"coordinates":[-93.238885,44.859135],"type":"Point"}
}