{
  "type": "Feature",
  "properties": {
    "iso:country":"US",
    "sg:address":"1114 Grand Ave",
    "sg:city":"Saint Paul",
    "sg:classifiers":[
        {
            "category":"Shopping",
            "subcategory":"Gifts & Souvenirs",
            "type":"Retail Goods"
        }
    ],
    "sg:phone":"+1 651 290 9745",
    "sg:postcode":"55105",
    "sg:province":"MN",
    "sg:tags":[
        "clothing",
        "jewelry"
    ],
    "wof:name":"Bibelot Shop Inc",
    "wof:placetype":"venue"
},
  "geometry": {"coordinates":[-93.148717,44.939929],"type":"Point"}
}