{
  "type": "Feature",
  "properties": {
    "iso:country":"US",
    "sg:address":"708 Schilling Dr N",
    "sg:city":"Dundas",
    "sg:classifiers":[
        {
            "category":"Health Services",
            "subcategory":"Doctor",
            "type":"Services"
        },
        {
            "category":"Health Services",
            "subcategory":"Clinic",
            "type":"Services"
        },
        {
            "category":"Health Services",
            "subcategory":"Chiropractor",
            "type":"Services"
        }
    ],
    "sg:phone":"+1 507 663 6006",
    "sg:postcode":"55019",
    "sg:province":"MN",
    "sg:tags":[
        "physician",
        "medical",
        "surgeon",
        "chiropractic"
    ],
    "wof:name":"Chiropractic USA",
    "wof:placetype":"venue"
},
  "geometry": {"coordinates":[-93.19452,44.431347],"type":"Point"}
}