{
  "type": "Feature",
  "properties": {
    "iso:country":"US",
    "sg:address":"3530 Co Rd 27",
    "sg:city":"Twin Valley",
    "sg:classifiers":[
        {
            "category":"Farming",
            "subcategory":"Livestock Farm",
            "type":"Manufacturing & Wholesale Goods"
        }
    ],
    "sg:phone":"+1 218 584 8350",
    "sg:postcode":"56584",
    "sg:province":"MN",
    "sg:tags":[
        "beef",
        "feedlot",
        "cattle"
    ],
    "wof:name":"Curtis Berg",
    "wof:placetype":"venue"
},
  "geometry": {"coordinates":[-96.31213,47.267249],"type":"Point"}
}