{
  "type": "Feature",
  "properties": {
    "addr:full":"305 N Lake St Frazee MN 56544",
    "addr:housenumber":"305",
    "addr:postcode":"56544",
    "addr:street":"N Lake St",
    "iso:country":"US",
    "sg:address":"305 N Lake St",
    "sg:city":"Frazee",
    "sg:classifiers":[
        {
            "category":"Education",
            "subcategory":"School",
            "type":"Public Place"
        }
    ],
    "sg:phone":"+1 218 334 3951",
    "sg:postcode":"56544",
    "sg:province":"MN",
    "sg:tags":[
        "k-",
        "private"
    ],
    "sg:website":"http://www.frazee.k12.mn.us",
    "wof:name":"Frazee-Vergas Elem School",
    "wof:placetype":"venue"
},
  "geometry": {"coordinates":[-95.699251,46.729095],"type":"Point"}
}