{
  "type": "Feature",
  "properties": {
    "addr:full":"4333 126th Ave Clear Lake MN 55319",
    "addr:housenumber":"4333",
    "addr:postcode":"55319",
    "addr:street":"126Th Ave",
    "iso:country":"US",
    "sg:address":"4333 126th Ave",
    "sg:city":"Clear Lake",
    "sg:classifiers":[
        {
            "category":"Building & Trades",
            "subcategory":"Construction",
            "type":"Services"
        }
    ],
    "sg:phone":"+1 320 743 3447",
    "sg:postcode":"55319",
    "sg:province":"MN",
    "sg:tags":[
        "home",
        "family"
    ],
    "wof:name":"Tricounty Professional Bldrs",
    "wof:placetype":"venue"
},
  "geometry": {"coordinates":[-93.900503,45.506898],"type":"Point"}
}