{
  "type": "Feature",
  "properties": {
    "addr:full":"9111 107th St N Stillwater MN 55082",
    "addr:housenumber":"9111",
    "addr:postcode":"55082",
    "addr:street":"107Th St N",
    "iso:country":"US",
    "sg:address":"9111 107th St N",
    "sg:city":"Stillwater",
    "sg:classifiers":[
        {
            "category":"Professional",
            "subcategory":"Business Services",
            "type":"Services"
        }
    ],
    "sg:phone":"+1 651 653 3698",
    "sg:postcode":"55082",
    "sg:province":"MN",
    "wof:name":"Bottom Line Business Solutions",
    "wof:placetype":"venue"
},
  "geometry": {"coordinates":[-92.92291899999999,45.10373],"type":"Point"}
}