{
  "type": "Feature",
  "properties": {
    "addr:full":"1125 US Hwy 169 Blue Earth MN 56013",
    "addr:housenumber":"1125",
    "addr:postcode":"56013",
    "addr:street":"Us Hwy 169",
    "iso:country":"US",
    "sg:address":"1125 US Hwy 169",
    "sg:city":"Blue Earth",
    "sg:classifiers":[
        {
            "category":"Education",
            "subcategory":"School",
            "type":"Public Place"
        }
    ],
    "sg:phone":"+1 507 526 3201",
    "sg:postcode":"56013",
    "sg:province":"MN",
    "wof:name":"Blue Earth Area High School",
    "wof:placetype":"venue"
},
  "geometry": {"coordinates":[-94.093261,43.649417],"type":"Point"}
}