{
  "type": "Feature",
  "properties": {
    "addr:full":"175 Hillside Ave SW Akeley MN 56433",
    "addr:housenumber":"175",
    "addr:postcode":"56433",
    "addr:street":"Hillside Ave Sw",
    "iso:country":"US",
    "sg:address":"175 Hillside Ave SW",
    "sg:city":"Akeley",
    "sg:classifiers":[
        {
            "category":"Personal",
            "subcategory":"Beauty Salon",
            "type":"Services"
        }
    ],
    "sg:phone":"+1 218 652 2081",
    "sg:postcode":"56433",
    "sg:province":"MN",
    "wof:name":"Lorraine's Hair Care",
    "wof:placetype":"venue"
},
  "geometry": {"coordinates":[-94.733763,47.000792],"type":"Point"}
}