{
  "type": "Feature",
  "properties": {
    "iso:country":"US",
    "sg:address":"11500 Terrace Rd NE",
    "sg:city":"Minneapolis",
    "sg:classifiers":[
        {
            "category":"Home & Garden",
            "subcategory":"Building Materials",
            "type":"Retail Goods"
        },
        {
            "category":"Manufacturing",
            "subcategory":"Paper Products",
            "type":"Manufacturing & Wholesale Goods"
        }
    ],
    "sg:phone":"+1 763 754 9074",
    "sg:postcode":"55434",
    "sg:province":"MN",
    "sg:tags":[
        "manufacturer",
        "wallpaper",
        "wallcoverings-wholesale",
        "wallcoverings"
    ],
    "wof:name":"Wallcovering Specialists",
    "wof:placetype":"venue"
},
  "geometry": {"coordinates":[-93.258292,45.178446],"type":"Point"}
}