{
  "type": "Feature",
  "properties": {
    "addr:full":"23 W Mankato St Duluth MN 55803",
    "addr:housenumber":"23",
    "addr:postcode":"55803",
    "addr:street":"W Mankato St",
    "iso:country":"US",
    "sg:address":"23 W Mankato St",
    "sg:city":"Duluth",
    "sg:classifiers":[
        {
            "category":"Professional",
            "subcategory":"Lawyer & Legal Services",
            "type":"Services"
        }
    ],
    "sg:phone":"+1 218 724 4562",
    "sg:postcode":"55803",
    "sg:province":"MN",
    "sg:tags":[
        "convention",
        "reporters-court"
    ],
    "wof:name":"Elizabeth A Mcbride",
    "wof:placetype":"venue"
},
  "geometry": {"coordinates":[-92.083175,46.845873],"type":"Point"}
}