{
  "type": "Feature",
  "properties": {
    "iso:country":"US",
    "sg:address":"9378 Norwood Ct",
    "sg:city":"Osseo",
    "sg:classifiers":[
        {
            "category":"Travel",
            "subcategory":"Hotels & Motels",
            "type":"Entertainment"
        }
    ],
    "sg:phone":"+1 763 424 5677",
    "sg:postcode":"55369",
    "sg:province":"MN",
    "sg:tags":[
        "operation"
    ],
    "wof:name":"T D & L Properties",
    "wof:placetype":"venue"
},
  "geometry": {"coordinates":[-93.440163,45.124389],"type":"Point"}
}