{
  "type": "Feature",
  "properties": {
    "iso:country":"US",
    "sg:address":"102 1st St SE",
    "sg:city":"Glenwood",
    "sg:classifiers":[
        {
            "category":"Personal",
            "subcategory":"Beauty Salon",
            "type":"Services"
        }
    ],
    "sg:phone":"+1 320 634 4986",
    "sg:postcode":"56334",
    "sg:province":"MN",
    "sg:tags":[
        "shop"
    ],
    "wof:name":"Brush Stop",
    "wof:placetype":"venue"
},
  "geometry": {"coordinates":[-95.388544,45.649309],"type":"Point"}
}