{
  "type": "Feature",
  "properties": {
    "iso:country":"US",
    "sg:address":"616 America Ave NW",
    "sg:city":"Bemidji",
    "sg:classifiers":[
        {
            "category":"Government",
            "subcategory":"Court House",
            "type":"Public Place"
        }
    ],
    "sg:phone":"+1 218 755 4500",
    "sg:postcode":"56601",
    "sg:province":"MN",
    "sg:tags":[
        "administrative"
    ],
    "wof:name":"District Administration",
    "wof:placetype":"venue"
},
  "geometry": {"coordinates":[-94.884198,47.474512],"type":"Point"}
}