{
  "type": "Feature",
  "properties": {
    "addr:full":"5898 Omaha Ave N Oak Park Heights MN 55082",
    "addr:housenumber":"5898",
    "addr:postcode":"55082",
    "addr:street":"Omaha Ave N",
    "iso:country":"US",
    "sg:address":"5898 Omaha Ave N",
    "sg:city":"Oak Park Heights",
    "sg:classifiers":[
        {
            "category":"Manufacturing",
            "subcategory":"Printing",
            "type":"Manufacturing & Wholesale Goods"
        }
    ],
    "sg:phone":"+1 651 439 8160",
    "sg:postcode":"55082",
    "sg:province":"MN",
    "sg:tags":[
        "printer"
    ],
    "wof:name":"North Graphic Communications",
    "wof:placetype":"venue"
},
  "geometry": {"coordinates":[-92.812631,45.034758],"type":"Point"}
}