{
  "type": "Feature",
  "properties": {
    "addr:full":"150 S Broadway Ave Rochester MN 55904",
    "addr:housenumber":"150",
    "addr:postcode":"55904",
    "addr:street":"S Broadway Ave",
    "iso:country":"US",
    "sg:address":"150 S Broadway Ave",
    "sg:city":"Rochester",
    "sg:classifiers":[
        {
            "category":"Restaurant",
            "type":"Food & Drink"
        }
    ],
    "sg:phone":"+1 507 281 5261",
    "sg:postcode":"55904",
    "sg:province":"MN",
    "sg:tags":[
        "eating"
    ],
    "wof:name":"Mc Cormicks Restaurant",
    "wof:placetype":"venue"
},
  "geometry": {"coordinates":[-92.46293799999999,44.022045],"type":"Point"}
}