{
  "type": "Feature",
  "properties": {
    "addr:full":"2601 1st Ave Hibbing MN 55746",
    "addr:housenumber":"2601",
    "addr:postcode":"55746",
    "addr:street":"1St Ave",
    "iso:country":"US",
    "sg:address":"2601 1st Ave",
    "sg:city":"Hibbing",
    "sg:classifiers":[
        {
            "category":"Restaurant",
            "type":"Food & Drink"
        }
    ],
    "sg:phone":"+1 218 263 7141",
    "sg:postcode":"55746",
    "sg:province":"MN",
    "wof:name":"Amelia's Family Cuisine",
    "wof:placetype":"venue"
},
  "geometry": {"coordinates":[-92.94169599999999,47.420373],"type":"Point"}
}