{
  "type": "Feature",
  "properties": {
    "addr:full":"19747 183rd Ave Big Lake MN 55309",
    "addr:housenumber":"19747",
    "addr:postcode":"55309",
    "addr:street":"183Rd Ave",
    "iso:country":"US",
    "sg:address":"19747 183rd Ave",
    "sg:city":"Big Lake",
    "sg:classifiers":[
        {
            "category":"Real Estate",
            "subcategory":"Real Estate Agent",
            "type":"Services"
        },
        {
            "category":"Professional",
            "subcategory":"Business Services",
            "type":"Services"
        }
    ],
    "sg:phone":"+1 763 263 8841",
    "sg:postcode":"55309",
    "sg:province":"MN",
    "sg:tags":[
        "inspection"
    ],
    "wof:name":"Quality Check Home Inspections",
    "wof:placetype":"venue"
},
  "geometry": {"coordinates":[-93.771259,45.302123],"type":"Point"}
}