{
  "type": "Feature",
  "properties": {
    "iso:country":"US",
    "sg:address":"3914 Humboldt Ave N",
    "sg:city":"Minneapolis",
    "sg:classifiers":[
        {
            "category":"Wholesale",
            "subcategory":"Hardware",
            "type":"Manufacturing & Wholesale Goods"
        }
    ],
    "sg:phone":"+1 612 529 0687",
    "sg:postcode":"55412",
    "sg:province":"MN",
    "wof:name":"Jct 81 Enterprises Home Pur",
    "wof:placetype":"venue"
},
  "geometry": {"coordinates":[-93.298136,45.027366],"type":"Point"}
}