{
  "type": "Feature",
  "properties": {
    "addr:full":"2061 190th Ave Ruthton MN 56170",
    "addr:housenumber":"2061",
    "addr:postcode":"56170",
    "addr:street":"190Th Ave",
    "iso:country":"US",
    "sg:address":"2061 190th Ave",
    "sg:city":"Ruthton",
    "sg:classifiers":[
        {
            "category":"Building & Trades",
            "subcategory":"Construction",
            "type":"Services"
        }
    ],
    "sg:phone":"+1 507 658 3559",
    "sg:postcode":"56170",
    "sg:province":"MN",
    "sg:tags":[
        "water",
        "well",
        "drilling"
    ],
    "wof:name":"Jerry Minett & Sons Well Svc",
    "wof:placetype":"venue"
},
  "geometry": {"coordinates":[-96.084147,44.148681],"type":"Point"}
}