{
  "type": "Feature",
  "properties": {
    "addr:full":"4840 Co Rd 10 Littlefork MN 56653",
    "addr:housenumber":"4840;10",
    "addr:postcode":"56653",
    "addr:street":"Co Rd",
    "iso:country":"US",
    "sg:address":"4840 Co Rd 10",
    "sg:city":"Littlefork",
    "sg:classifiers":[
        {
            "category":"Farming",
            "subcategory":"Livestock Farm",
            "type":"Manufacturing & Wholesale Goods"
        }
    ],
    "sg:phone":"+1 218 278 4494",
    "sg:postcode":"56653",
    "sg:province":"MN",
    "sg:tags":[
        "beef",
        "feedlot",
        "cattle"
    ],
    "wof:name":"Norman Reller",
    "wof:placetype":"venue"
},
  "geometry": {"coordinates":[-93.7414,48.432621],"type":"Point"}
}