{
  "type": "Feature",
  "properties": {
    "addr:full":"107 Wildwood Rd White Bear Lake MN 55115",
    "addr:housenumber":"107",
    "addr:postcode":"55115",
    "addr:street":"Wildwood Rd",
    "iso:country":"US",
    "sg:address":"107 Wildwood Rd",
    "sg:city":"White Bear Lake",
    "sg:classifiers":[
        {
            "category":"Restaurant",
            "type":"Food & Drink"
        }
    ],
    "sg:phone":"+1 651 429 4252",
    "sg:postcode":"55115",
    "sg:province":"MN",
    "wof:name":"Domino's Pizza",
    "wof:placetype":"venue"
},
  "geometry": {"coordinates":[-92.962907,45.055232],"type":"Point"}
}