{
  "type": "Feature",
  "properties": {
    "iso:country":"US",
    "sg:address":"2436 Eagle Valley Dr",
    "sg:city":"St Paul",
    "sg:classifiers":[
        {
            "category":"Food & Beverages",
            "subcategory":"Groceries & Convenience Stores",
            "type":"Retail Goods"
        }
    ],
    "sg:phone":"+1 651 714 5585",
    "sg:postcode":"55129",
    "sg:province":"MN",
    "sg:tags":[
        "product"
    ],
    "wof:name":"Country Cookie Basket",
    "wof:placetype":"venue"
},
  "geometry": {"coordinates":[-92.89643,44.912853],"type":"Point"}
}