{
  "type": "Feature",
  "properties": {
    "iso:country":"US",
    "sg:address":"10 Franklin St SW",
    "sg:city":"Hutchinson",
    "sg:classifiers":[
        {
            "category":"Professional",
            "type":"Services"
        }
    ],
    "sg:phone":"+1 320 587 7900",
    "sg:postcode":"55350",
    "sg:province":"MN",
    "sg:tags":[
        "establishment"
    ],
    "wof:name":"Crime Line",
    "wof:placetype":"venue"
},
  "geometry": {"coordinates":[-94.37073700000001,44.892161],"type":"Point"}
}