{
  "type": "Feature",
  "properties": {
    "addr:full":"2733 Roosevelt Rd SE Bemidji MN 56601",
    "addr:housenumber":"2733",
    "addr:postcode":"56601",
    "addr:street":"Roosevelt Rd Se",
    "iso:country":"US",
    "sg:address":"2733 Roosevelt Rd SE",
    "sg:city":"Bemidji",
    "sg:classifiers":[
        {
            "category":"Sports & Exercise",
            "subcategory":"Gym",
            "type":"Entertainment"
        }
    ],
    "sg:phone":"+1 218 444 7531",
    "sg:postcode":"56601",
    "sg:province":"MN",
    "sg:tags":[
        "fitness",
        "physical",
        "facility"
    ],
    "wof:name":"Triple Performance Plus",
    "wof:placetype":"venue"
},
  "geometry": {"coordinates":[-94.827832,47.453369],"type":"Point"}
}