{
  "type": "Feature",
  "properties": {
    "addr:full":"3204 4th St SE Minneapolis MN 55414",
    "addr:housenumber":"3204",
    "addr:postcode":"55414",
    "addr:street":"4Th St Se",
    "iso:country":"US",
    "sg:address":"3204 4th St SE",
    "sg:city":"Minneapolis",
    "sg:classifiers":[
        {
            "category":"Organizations",
            "subcategory":"Religious Organization",
            "type":"Services"
        }
    ],
    "sg:phone":"+1 612 378 9268",
    "sg:postcode":"55414",
    "sg:province":"MN",
    "wof:name":"Robert Barta",
    "wof:placetype":"venue"
},
  "geometry": {"coordinates":[-93.209412,44.969751],"type":"Point"}
}