{
  "type": "Feature",
  "properties": {
    "iso:country":"US",
    "sg:address":"1841 Hampshire Ave S",
    "sg:city":"Minneapolis",
    "sg:classifiers":[
        {
            "category":"Building & Trades",
            "subcategory":"Landscaping Services",
            "type":"Services"
        }
    ],
    "sg:phone":"+1 952 545 1760",
    "sg:postcode":"55426",
    "sg:province":"MN",
    "sg:tags":[
        "snow",
        "removal"
    ],
    "wof:name":"Murphy Plowing",
    "wof:placetype":"venue"
},
  "geometry": {"coordinates":[-93.365927,44.964683],"type":"Point"}
}