{
  "type": "Feature",
  "properties": {
    "iso:country":"US",
    "sg:address":"5133 148th St W",
    "sg:city":"Saint Paul",
    "sg:classifiers":[
        {
            "category":"Retail",
            "subcategory":"Auto Repair",
            "type":"Services"
        }
    ],
    "sg:phone":"+1 952 322 2172",
    "sg:postcode":"55124",
    "sg:province":"MN",
    "sg:tags":[
        "body"
    ],
    "wof:name":"Als Auto Body",
    "wof:placetype":"venue"
},
  "geometry": {"coordinates":[-93.170609,44.735274],"type":"Point"}
}