{
  "type": "Feature",
  "properties": {
    "addr:full":"18163 Hill Top Dr Fergus Falls MN 56537",
    "addr:housenumber":"18163",
    "addr:postcode":"56537",
    "addr:street":"Hill Top Dr",
    "iso:country":"US",
    "sg:address":"18163 Hill Top Dr",
    "sg:city":"Fergus Falls",
    "sg:phone":"+1 218 736 4084",
    "sg:postcode":"56537",
    "sg:province":"MN",
    "sg:tags":[
        "farm",
        "corn",
        "dairy",
        "soybean"
    ],
    "wof:name":"Victor Peterson",
    "wof:placetype":"venue"
},
  "geometry": {"coordinates":[-96.11049800000001,46.357633],"type":"Point"}
}