{
  "type": "Feature",
  "properties": {
    "iso:country":"US",
    "sg:address":"5322 Maywood Rd",
    "sg:city":"Mound",
    "sg:classifiers":[
        {
            "category":"Real Estate",
            "subcategory":"Real Estate Operator",
            "type":"Services"
        }
    ],
    "sg:phone":"+1 952 472 4431",
    "sg:postcode":"55364",
    "sg:province":"MN",
    "sg:tags":[
        "building",
        "apartment"
    ],
    "wof:name":"Royal Apts",
    "wof:placetype":"venue"
},
  "geometry": {"coordinates":[-93.658762,44.934804],"type":"Point"}
}