{
  "type": "Feature",
  "properties": {
    "iso:country":"US",
    "sg:address":"3315 Co Rd 9 NE",
    "sg:city":"Willmar",
    "sg:classifiers":[
        {
            "category":"Farming",
            "subcategory":"Dairy Farm",
            "type":"Manufacturing & Wholesale Goods"
        }
    ],
    "sg:phone":"+1 320 235 8224",
    "sg:postcode":"56201",
    "sg:province":"MN",
    "wof:name":"Mark Peterson",
    "wof:placetype":"venue"
},
  "geometry": {"coordinates":[-95.001518,45.157526],"type":"Point"}
}