{
  "type": "Feature",
  "properties": {
    "addr:full":"100 Linda Dr Eagle Lake MN 56024",
    "addr:housenumber":"100",
    "addr:postcode":"56024",
    "addr:street":"Linda Dr",
    "iso:country":"US",
    "sg:address":"100 Linda Dr",
    "sg:city":"Eagle Lake",
    "sg:classifiers":[
        {
            "category":"Professional",
            "type":"Services"
        }
    ],
    "sg:phone":"+1 507 257 3884",
    "sg:postcode":"56024",
    "sg:province":"MN",
    "wof:name":"Minnesota Valley Eaa Chap",
    "wof:placetype":"venue"
},
  "geometry": {"coordinates":[-93.88055199999999,44.160038],"type":"Point"}
}