{
  "type": "Feature",
  "properties": {
    "iso:country":"US",
    "sg:address":"7300 147th St W",
    "sg:city":"Apple Valley",
    "sg:classifiers":[
        {
            "category":"Real Estate",
            "subcategory":"Real Estate Services",
            "type":"Services"
        }
    ],
    "sg:phone":"+1 952 431 3100",
    "sg:postcode":"55124",
    "sg:province":"MN",
    "sg:tags":[
        "company",
        "abstract",
        "title"
    ],
    "wof:name":"Suburban Title Inc",
    "wof:placetype":"venue"
},
  "geometry": {"coordinates":[-93.213626,44.734716],"type":"Point"}
}