{
  "type": "Feature",
  "properties": {
    "iso:country":"US",
    "sg:address":"28493 Frontage Rd",
    "sg:city":"Saint Joseph",
    "sg:classifiers":[
        {
            "category":"Building & Trades",
            "subcategory":"Construction",
            "type":"Services"
        }
    ],
    "sg:phone":"+1 320 363 0690",
    "sg:postcode":"56374",
    "sg:province":"MN",
    "sg:tags":[
        "contractor"
    ],
    "wof:name":"Gregs Roofing",
    "wof:placetype":"venue"
},
  "geometry": {"coordinates":[-94.323927,45.539518],"type":"Point"}
}