{
  "type": "Feature",
  "properties": {
    "addr:full":"15156 Co Rd 8 Greenbush MN 56726",
    "addr:housenumber":"15156",
    "addr:postcode":"56726",
    "addr:street":"Co Rd 8",
    "iso:country":"US",
    "sg:address":"15156 Co Rd 8",
    "sg:city":"Greenbush",
    "sg:classifiers":[
        {
            "category":"Farming",
            "subcategory":"Dairy Farm",
            "type":"Manufacturing & Wholesale Goods"
        }
    ],
    "sg:phone":"+1 218 781 2634",
    "sg:postcode":"56726",
    "sg:province":"MN",
    "wof:name":"Hemp Ernerst",
    "wof:placetype":"venue"
},
  "geometry": {"coordinates":[-96.278386,48.603633],"type":"Point"}
}