{
  "type": "Feature",
  "properties": {
    "addr:full":"10720 Minnetonka Blvd Hopkins MN 55305",
    "addr:housenumber":"10720",
    "addr:postcode":"55305",
    "addr:street":"Minnetonka Blvd",
    "iso:country":"US",
    "sg:address":"10720 Minnetonka Blvd",
    "sg:city":"Hopkins",
    "sg:classifiers":[
        {
            "category":"Wholesale",
            "subcategory":"Durable Goods & Equipment",
            "type":"Manufacturing & Wholesale Goods"
        }
    ],
    "sg:phone":"+1 952 988 9155",
    "sg:postcode":"55305",
    "sg:province":"MN",
    "sg:tags":[
        "representative",
        "manufacturer"
    ],
    "wof:name":"Darrell J Sykes & Assoc",
    "wof:placetype":"venue"
},
  "geometry": {"coordinates":[-93.413586,44.944819],"type":"Point"}
}