{
  "type": "Feature",
  "properties": {
    "addr:full":"1428 4th St NE Minneapolis MN 55413",
    "addr:housenumber":"1428",
    "addr:postcode":"55413",
    "addr:street":"4Th St Ne",
    "iso:country":"US",
    "sg:address":"1428 4th St NE",
    "sg:city":"Minneapolis",
    "sg:classifiers":[
        {
            "category":"Restaurant",
            "type":"Food & Drink"
        }
    ],
    "sg:phone":"+1 612 789 9862",
    "sg:postcode":"55413",
    "sg:province":"MN",
    "sg:website":"www.mayslacksbar.com",
    "wof:name":"Mayslacks Music Lounge",
    "wof:placetype":"venue"
},
  "geometry": {"coordinates":[-93.261398,45.002899],"type":"Point"}
}