{
  "type": "Feature",
  "properties": {
    "addr:full":"310 Canal Park Dr Duluth MN 55802",
    "addr:housenumber":"310",
    "addr:postcode":"55802",
    "addr:street":"Canal Park Dr",
    "iso:country":"US",
    "sg:address":"310 Canal Park Dr",
    "sg:city":"Duluth",
    "sg:classifiers":[
        {
            "category":"Travel",
            "subcategory":"Hotels & Motels",
            "type":"Entertainment"
        }
    ],
    "sg:phone":"+1 218 720 3000",
    "sg:postcode":"55802",
    "sg:province":"MN",
    "sg:tags":[
        "operation"
    ],
    "sg:website":"www.hamptoninn.com",
    "wof:name":"Hampton Inn",
    "wof:placetype":"venue"
},
  "geometry": {"coordinates":[-92.09387099999999,46.782335],"type":"Point"}
}