{
  "type": "Feature",
  "properties": {
    "iso:country":"US",
    "sg:address":"103 Division St",
    "sg:city":"Sauk Rapids",
    "sg:classifiers":[
        {
            "category":"Home & Garden",
            "subcategory":"Mobile Homes",
            "type":"Retail Goods"
        }
    ],
    "sg:phone":"+1 320 654 8444",
    "sg:postcode":"56379",
    "sg:province":"MN",
    "wof:name":"Welcome Home II",
    "wof:placetype":"venue"
},
  "geometry": {"coordinates":[-94.16562500000001,45.589497],"type":"Point"}
}