{
  "type": "Feature",
  "properties": {
    "addr:full":"5358 Chicago Ave Minneapolis MN 55417",
    "addr:housenumber":"5358",
    "addr:postcode":"55417",
    "addr:street":"Chicago Ave",
    "iso:country":"US",
    "sg:address":"5358 Chicago Ave",
    "sg:city":"Minneapolis",
    "sg:classifiers":[
        {
            "category":"Restaurant",
            "type":"Food & Drink"
        }
    ],
    "sg:phone":"+1 612 824 5354",
    "sg:postcode":"55417",
    "sg:province":"MN",
    "sg:tags":[
        "asian",
        "chinese",
        "pan"
    ],
    "wof:name":"Hule's Chow Mein",
    "wof:placetype":"venue"
},
  "geometry": {"coordinates":[-93.26263299999999,44.905989],"type":"Point"}
}