{
  "type": "Feature",
  "properties": {
    "addr:full":"451 Industrial Blvd NE Minneapolis MN 55413",
    "addr:housenumber":"451",
    "addr:postcode":"55413",
    "addr:street":"Industrial Blvd Ne",
    "iso:country":"US",
    "sg:address":"451 Industrial Blvd NE",
    "sg:city":"Minneapolis",
    "sg:classifiers":[
        {
            "category":"Manufacturing",
            "subcategory":"Tools & Machinery",
            "type":"Manufacturing & Wholesale Goods"
        }
    ],
    "sg:phone":"+1 612 362 8500",
    "sg:postcode":"55413",
    "sg:province":"MN",
    "sg:tags":[
        "product",
        "industrial",
        "mfg",
        "food",
        "m",
        "equipment"
    ],
    "wof:name":"Tetrapak",
    "wof:placetype":"venue"
},
  "geometry": {"coordinates":[-93.211454,44.994784],"type":"Point"}
}