{
  "type": "Feature",
  "properties": {
    "addr:full":"35242 Weidenborner Rd NE Northome MN 56661",
    "addr:postcode":"35242;56661",
    "addr:street":"Weidenborner Rd Ne",
    "iso:country":"US",
    "sg:address":"35242 Weidenborner Rd NE",
    "sg:city":"Northome",
    "sg:classifiers":[
        {
            "category":"Farming",
            "subcategory":"Dairy Farm",
            "type":"Manufacturing & Wholesale Goods"
        }
    ],
    "sg:phone":"+1 218 647 8340",
    "sg:postcode":"56661",
    "sg:province":"MN",
    "wof:name":"Paul Weidenborner",
    "wof:placetype":"venue"
},
  "geometry": {"coordinates":[-94.49347899999999,47.876496],"type":"Point"}
}