{
  "type": "Feature",
  "properties": {
    "addr:full":"2339 2nd Ave SW Rochester MN 55902",
    "addr:housenumber":"2339",
    "addr:postcode":"55902",
    "addr:street":"2Nd Ave Sw",
    "iso:country":"US",
    "sg:address":"2339 2nd Ave SW",
    "sg:city":"Rochester",
    "sg:classifiers":[
        {
            "category":"Insurance",
            "subcategory":"Insurance Agent",
            "type":"Services"
        }
    ],
    "sg:phone":"+1 507 282 1846",
    "sg:postcode":"55902",
    "sg:province":"MN",
    "wof:name":"Creative Money Management Inc",
    "wof:placetype":"venue"
},
  "geometry": {"coordinates":[-92.464865,43.987738],"type":"Point"}
}