{
  "type": "Feature",
  "properties": {
    "addr:full":"3150 Century Ave Cannon Falls MN 55055",
    "addr:housenumber":"3150",
    "addr:postcode":"55055",
    "addr:street":"Century Ave",
    "iso:country":"US",
    "sg:address":"3150 Century Ave",
    "sg:city":"Cannon Falls",
    "sg:classifiers":[
        {
            "category":"Professional",
            "subcategory":"Credit Reporting & Collection",
            "type":"Services"
        }
    ],
    "sg:phone":"+1 651 779 4358",
    "sg:postcode":"55055",
    "sg:province":"MN",
    "sg:tags":[
        "agency"
    ],
    "wof:name":"Mn Recovery Bureau",
    "wof:placetype":"venue"
},
  "geometry": {"coordinates":[-92.984211,44.883512],"type":"Point"}
}