{
  "type": "Feature",
  "properties": {
    "iso:country":"US",
    "sg:address":"201 4th Ave SW",
    "sg:city":"Rochester",
    "sg:classifiers":[
        {
            "category":"Health Services",
            "subcategory":"Doctor",
            "type":"Services"
        }
    ],
    "sg:phone":"+1 507 284 5180",
    "sg:postcode":"55902",
    "sg:province":"MN",
    "sg:tags":[
        "physician",
        "surgeon"
    ],
    "wof:name":"Urgent Care Ctr",
    "wof:placetype":"venue"
},
  "geometry": {"coordinates":[-92.46817900000001,44.02044],"type":"Point"}
}