{
  "type": "Feature",
  "properties": {
    "iso:country":"US",
    "sg:address":"367 Jay Way",
    "sg:city":"Saint Paul",
    "sg:classifiers":[
        {
            "category":"Building & Trades",
            "subcategory":"Electrical",
            "type":"Services"
        }
    ],
    "sg:phone":"+1 651 775 2186",
    "sg:postcode":"55127",
    "sg:province":"MN",
    "sg:tags":[
        "electrical",
        "contractor"
    ],
    "wof:name":"Knight Custom Builders Inc",
    "wof:placetype":"venue"
},
  "geometry": {"coordinates":[-93.085832,45.071252],"type":"Point"}
}