{
  "type": "Feature",
  "properties": {
    "iso:country":"US",
    "sg:address":"2920 Hwy 14 W",
    "sg:city":"Rochester",
    "sg:classifiers":[
        {
            "category":"Professional",
            "subcategory":"Detective & Security Services",
            "type":"Services"
        }
    ],
    "sg:phone":"+1 507 288 9602",
    "sg:postcode":"55901",
    "sg:province":"MN",
    "sg:tags":[
        "car",
        "armored"
    ],
    "wof:name":"Rochester Armored Car Co Inc",
    "wof:placetype":"venue"
},
  "geometry": {"coordinates":[-92.513001,44.03589],"type":"Point"}
}