{
  "type": "Feature",
  "properties": {
    "addr:full":"4009 15th Ave NW Rochester MN 55901",
    "addr:housenumber":"4009",
    "addr:postcode":"55901",
    "addr:street":"15Th Ave Nw",
    "iso:country":"US",
    "sg:address":"4009 15th Ave NW",
    "sg:city":"Rochester",
    "sg:classifiers":[
        {
            "category":"Insurance",
            "subcategory":"Insurance Agent",
            "type":"Services"
        }
    ],
    "sg:phone":"+1 507 281 1601",
    "sg:postcode":"55901",
    "sg:province":"MN",
    "wof:name":"Bill Heim",
    "wof:placetype":"venue"
},
  "geometry": {"coordinates":[-92.485336,44.065089],"type":"Point"}
}