{
  "type": "Feature",
  "properties": {
    "addr:full":"13911 Ridgedale Dr Hopkins MN 55305",
    "addr:housenumber":"13911",
    "addr:postcode":"55305",
    "addr:street":"Ridgedale Dr",
    "iso:country":"US",
    "sg:address":"13911 Ridgedale Dr",
    "sg:city":"Hopkins",
    "sg:classifiers":[
        {
            "category":"Insurance",
            "subcategory":"Insurance Agent",
            "type":"Services"
        }
    ],
    "sg:phone":"+1 952 593 0400",
    "sg:postcode":"55305",
    "sg:province":"MN",
    "wof:name":"Dudley Bartholow Insurance",
    "wof:placetype":"venue"
},
  "geometry": {"coordinates":[-93.45894800000001,44.969347],"type":"Point"}
}