{
  "type": "Feature",
  "properties": {
    "addr:full":"12115 Nicollet Ave Burnsville MN 55337",
    "addr:housenumber":"12115",
    "addr:postcode":"55337",
    "addr:street":"Nicollet Ave",
    "iso:country":"US",
    "sg:address":"12115 Nicollet Ave",
    "sg:city":"Burnsville",
    "sg:classifiers":[
        {
            "category":"Social Services",
            "subcategory":"Job Training",
            "type":"Services"
        }
    ],
    "sg:phone":"+1 952 894 4680",
    "sg:postcode":"55337",
    "sg:province":"MN",
    "sg:tags":[
        "packaging",
        "mfg"
    ],
    "wof:name":"Mankato Rehabilitation Center",
    "wof:placetype":"venue"
},
  "geometry": {"coordinates":[-93.276111,44.782924],"type":"Point"}
}