{
  "type": "Feature",
  "properties": {
    "addr:full":"18605 Co Hwy 25 Fergus Falls MN 56537",
    "addr:housenumber":"18605",
    "addr:postcode":"56537",
    "addr:street":"Co Hwy 25 Fergus",
    "iso:country":"US",
    "sg:address":"18605 Co Hwy 25",
    "sg:city":"Fergus Falls",
    "sg:classifiers":[
        {
            "category":"Professional",
            "type":"Services"
        }
    ],
    "sg:phone":"+1 218 739 2667",
    "sg:postcode":"56537",
    "sg:province":"MN",
    "wof:name":"M Otnes Studios",
    "wof:placetype":"venue"
},
  "geometry": {"coordinates":[-96.100925,46.181163],"type":"Point"}
}