{
  "type": "Feature",
  "properties": {
    "addr:full":"623 29th St NW Rochester MN 55901",
    "addr:housenumber":"623",
    "addr:postcode":"55901",
    "addr:street":"29Th St Nw",
    "iso:country":"US",
    "sg:address":"623 29th St NW",
    "sg:city":"Rochester",
    "sg:classifiers":[
        {
            "category":"Insurance",
            "subcategory":"Insurance Agent",
            "type":"Services"
        }
    ],
    "sg:phone":"+1 507 281 5933",
    "sg:postcode":"55901",
    "sg:province":"MN",
    "wof:name":"John Kosse Insurance Agency",
    "wof:placetype":"venue"
},
  "geometry": {"coordinates":[-92.473744,44.054204],"type":"Point"}
}