{
  "type": "Feature",
  "properties": {
    "iso:country":"US",
    "sg:address":"324 W Welcome Ave",
    "sg:city":"Mankato",
    "sg:classifiers":[
        {
            "category":"Social Services",
            "subcategory":"Child Care",
            "type":"Services"
        }
    ],
    "sg:phone":"+1 507 387 5783",
    "sg:postcode":"56001",
    "sg:province":"MN",
    "sg:tags":[
        "day"
    ],
    "wof:name":"Karens Day Care",
    "wof:placetype":"venue"
},
  "geometry": {"coordinates":[-93.99302299999999,44.153609],"type":"Point"}
}