{
  "type": "Feature",
  "properties": {
    "addr:full":"2187 30th Ave SE Rochester MN 55904",
    "addr:housenumber":"2187",
    "addr:postcode":"55904",
    "addr:street":"30Th Ave Se",
    "iso:country":"US",
    "sg:address":"2187 30th Ave SE",
    "sg:city":"Rochester",
    "sg:classifiers":[
        {
            "category":"Retail",
            "subcategory":"Auto Repair",
            "type":"Services"
        }
    ],
    "sg:phone":"+1 517 282 6693",
    "sg:postcode":"55904",
    "sg:province":"MN",
    "sg:tags":[
        "shop",
        "automotive",
        "general"
    ],
    "wof:name":"Latino Auto and Tire Shop",
    "wof:placetype":"venue"
},
  "geometry": {"coordinates":[-92.41880500000001,43.990427],"type":"Point"}
}