{
  "type": "Feature",
  "properties": {
    "addr:full":"38 E Oaks Rd Saint Paul MN 55127",
    "addr:housenumber":"38",
    "addr:postcode":"55127",
    "addr:street":"E Oaks Rd",
    "iso:country":"US",
    "sg:address":"38 E Oaks Rd",
    "sg:city":"Saint Paul",
    "sg:classifiers":[
        {
            "category":"Manufacturing",
            "subcategory":"Musical Instruments",
            "type":"Manufacturing & Wholesale Goods"
        }
    ],
    "sg:phone":"+1 651 636 0780",
    "sg:postcode":"55127",
    "sg:province":"MN",
    "sg:tags":[
        "mfg"
    ],
    "wof:name":"Sartory String Quartet",
    "wof:placetype":"venue"
},
  "geometry": {"coordinates":[-93.082526,45.086244],"type":"Point"}
}