{
  "type": "Feature",
  "properties": {
    "addr:full":"8205 Groveland Rd Saint Paul MN 55112",
    "addr:housenumber":"8205",
    "addr:postcode":"55112",
    "addr:street":"Groveland Rd",
    "iso:country":"US",
    "sg:address":"8205 Groveland Rd",
    "sg:city":"Saint Paul",
    "sg:classifiers":[
        {
            "category":"Building & Trades",
            "subcategory":"Construction",
            "type":"Services"
        }
    ],
    "sg:phone":"+1 763 786 6679",
    "sg:postcode":"55112",
    "sg:province":"MN",
    "sg:tags":[
        "house",
        "nonresidential"
    ],
    "wof:name":"R D O Construction Company",
    "wof:placetype":"venue"
},
  "geometry": {"coordinates":[-93.22116800000001,45.117787],"type":"Point"}
}