{
  "type": "Feature",
  "properties": {
    "iso:country":"US",
    "sg:address":"19655 Cottagewood Rd",
    "sg:city":"Excelsior",
    "sg:classifiers":[
        {
            "category":"Building & Trades",
            "subcategory":"Landscaping Services",
            "type":"Services"
        }
    ],
    "sg:phone":"+1 952 474 4904",
    "sg:postcode":"55331",
    "sg:province":"MN",
    "sg:tags":[
        "sanitary",
        "tree"
    ],
    "wof:name":"Daves Stump Removal",
    "wof:placetype":"venue"
},
  "geometry": {"coordinates":[-93.529625,44.92051],"type":"Point"}
}