{
  "type": "Feature",
  "properties": {
    "iso:country":"US",
    "sg:address":"322 E 1st St",
    "sg:city":"Chaska",
    "sg:classifiers":[
        {
            "category":"Professional",
            "subcategory":"Detective & Security Services",
            "type":"Services"
        }
    ],
    "sg:phone":"+1 952 448 5550",
    "sg:postcode":"55318",
    "sg:province":"MN",
    "sg:tags":[
        "information",
        "bureau"
    ],
    "wof:name":"Interment Service",
    "wof:placetype":"venue"
},
  "geometry": {"coordinates":[-93.596806,44.784907],"type":"Point"}
}