{
  "type": "Feature",
  "properties": {
    "addr:full":"2728 Nicollet Ave Minneapolis MN 55408",
    "addr:housenumber":"2728",
    "addr:postcode":"55408",
    "addr:street":"Nicollet Ave",
    "iso:country":"US",
    "sg:address":"2728 Nicollet Ave",
    "sg:city":"Minneapolis",
    "sg:classifiers":[
        {
            "category":"Food & Beverages",
            "subcategory":"Groceries & Convenience Stores",
            "type":"Retail Goods"
        }
    ],
    "sg:phone":"+1 612 870 7761",
    "sg:postcode":"55408",
    "sg:province":"MN",
    "wof:name":"Dreams Quality Market",
    "wof:placetype":"venue"
},
  "geometry": {"coordinates":[-93.277985,44.952454],"type":"Point"}
}