{
  "type": "Feature",
  "properties": {
    "iso:country":"US",
    "sg:address":"1724 Canary Ln",
    "sg:city":"Mound",
    "sg:classifiers":[
        {
            "category":"Food & Beverages",
            "subcategory":"Meat & Fish",
            "type":"Retail Goods"
        }
    ],
    "sg:phone":"+1 952 472 1758",
    "sg:postcode":"55364",
    "sg:province":"MN",
    "wof:name":"Joseph Abel Fine Meats",
    "wof:placetype":"venue"
},
  "geometry": {"coordinates":[-93.65581,44.945497],"type":"Point"}
}