{
  "type": "Feature",
  "properties": {
    "iso:country":"US",
    "sg:address":"1303 W Beechwood Pl",
    "sg:city":"St Paul",
    "sg:classifiers":[
        {
            "category":"Real Estate",
            "subcategory":"Real Estate Agent",
            "type":"Services"
        }
    ],
    "sg:phone":"+1 651 698 4068",
    "sg:postcode":"55116",
    "sg:province":"MN",
    "sg:tags":[
        "management"
    ],
    "wof:name":"Paradise & Associates",
    "wof:placetype":"venue"
},
  "geometry": {"coordinates":[-93.15590400000001,44.915295],"type":"Point"}
}