{
  "type": "Feature",
  "properties": {
    "addr:full":"125 5th Ave S St Cloud MN 56301",
    "addr:housenumber":"125",
    "addr:postcode":"56301",
    "addr:street":"5Th Ave S",
    "iso:country":"US",
    "sg:address":"125 5th Ave S",
    "sg:city":"St Cloud",
    "sg:classifiers":[
        {
            "category":"Shopping",
            "subcategory":"Gifts & Souvenirs",
            "type":"Retail Goods"
        },
        {
            "category":"Shopping",
            "subcategory":"Books",
            "type":"Retail Goods"
        }
    ],
    "sg:phone":"+1 320 259 5830",
    "sg:postcode":"56301",
    "sg:province":"MN",
    "sg:tags":[
        "comic"
    ],
    "wof:name":"Granite City Comic and Games",
    "wof:placetype":"venue"
},
  "geometry": {"coordinates":[-94.156766,45.559446],"type":"Point"}
}