{
  "type": "Feature",
  "properties": {
    "iso:country":"US",
    "sg:address":"12311 Co Rd 160",
    "sg:city":"Saint Joseph",
    "sg:classifiers":[
        {
            "category":"Farming",
            "subcategory":"Farm",
            "type":"Manufacturing & Wholesale Goods"
        }
    ],
    "sg:phone":"+1 320 363 7684",
    "sg:postcode":"56374",
    "sg:province":"MN",
    "sg:tags":[
        "crop",
        "general"
    ],
    "wof:name":"William Stommes",
    "wof:placetype":"venue"
},
  "geometry": {"coordinates":[-94.36354900000001,45.525984],"type":"Point"}
}