{
  "type": "Feature",
  "properties": {
    "iso:country":"US",
    "sg:address":"2006 E Oak Knoll Dr NE",
    "sg:city":"Alexandria",
    "sg:classifiers":[
        {
            "category":"Social Services",
            "type":"Services"
        }
    ],
    "sg:phone":"+1 320 759 1756",
    "sg:postcode":"56308",
    "sg:province":"MN",
    "wof:name":"Cross Rd Counseling",
    "wof:placetype":"venue"
},
  "geometry": {"coordinates":[-95.347352,45.902607],"type":"Point"}
}