{
  "type": "Feature",
  "properties": {
    "addr:full":"1001 Holley Ave St Paul Park MN 55071",
    "addr:housenumber":"1001",
    "addr:postcode":"55071",
    "addr:street":"Holley Ave St;Park",
    "iso:country":"US",
    "sg:address":"1001 Holley Ave",
    "sg:city":"St Paul Park",
    "sg:classifiers":[
        {
            "category":"Education",
            "subcategory":"School",
            "type":"Public Place"
        }
    ],
    "sg:phone":"+1 651 459 3021",
    "sg:postcode":"55071",
    "sg:province":"MN",
    "wof:name":"St Andrew's Lutheran School",
    "wof:placetype":"venue"
},
  "geometry": {"coordinates":[-92.988519,44.838513],"type":"Point"}
}