{
  "type": "Feature",
  "properties": {
    "addr:full":"1601 23rd Ave NW New Brighton MN 55112",
    "addr:housenumber":"1601",
    "addr:postcode":"55112",
    "addr:street":"23Rd Ave Nw",
    "iso:country":"US",
    "sg:address":"1601 23rd Ave NW",
    "sg:city":"New Brighton",
    "sg:classifiers":[
        {
            "category":"Building & Trades",
            "subcategory":"Construction",
            "type":"Services"
        }
    ],
    "sg:phone":"+1 651 636 0509",
    "sg:postcode":"55112",
    "sg:province":"MN",
    "sg:tags":[
        "masonry",
        "contractor"
    ],
    "wof:name":"John Dalnes Masonry",
    "wof:placetype":"venue"
},
  "geometry": {"coordinates":[-93.21628699999999,45.076282],"type":"Point"}
}