{
  "type": "Feature",
  "properties": {
    "addr:full":"23106 420th St Belview MN 56214",
    "addr:housenumber":"23106",
    "addr:postcode":"56214",
    "addr:street":"420Th St",
    "iso:country":"US",
    "sg:address":"23106 420th St",
    "sg:city":"Belview",
    "sg:classifiers":[
        {
            "category":"Freight",
            "type":"Transportation"
        }
    ],
    "sg:phone":"+1 507 938 3024",
    "sg:postcode":"56214",
    "sg:province":"MN",
    "sg:tags":[
        "operator",
        "trucking"
    ],
    "wof:name":"Gilland Trucking",
    "wof:placetype":"venue"
},
  "geometry": {"coordinates":[-95.317927,44.657616],"type":"Point"}
}