{
  "type": "Feature",
  "properties": {
    "iso:country":"US",
    "sg:address":"1800 E Lake St",
    "sg:city":"Minneapolis",
    "sg:classifiers":[
        {
            "category":"Autos & Motor Vehicles",
            "subcategory":"Automobile Sales",
            "type":"Retail Goods"
        }
    ],
    "sg:phone":"+1 612 722 6667",
    "sg:postcode":"55407",
    "sg:province":"MN",
    "sg:tags":[
        "used"
    ],
    "wof:name":"Cedar Lake Auto Exchange",
    "wof:placetype":"venue"
},
  "geometry": {"coordinates":[-93.24741299999999,44.948372],"type":"Point"}
}