{
  "type": "Feature",
  "properties": {
    "addr:full":"47674 870th St Windom MN 56101",
    "addr:housenumber":"47674",
    "addr:postcode":"56101",
    "addr:street":"870Th St",
    "iso:country":"US",
    "sg:address":"47674 870th St",
    "sg:city":"Windom",
    "sg:classifiers":[
        {
            "category":"Farming",
            "subcategory":"Dairy Farm",
            "type":"Manufacturing & Wholesale Goods"
        }
    ],
    "sg:phone":"+1 507 662 5091",
    "sg:postcode":"56101",
    "sg:province":"MN",
    "wof:name":"Willis Hinkeldey Farm",
    "wof:placetype":"venue"
},
  "geometry": {"coordinates":[-95.13408699999999,43.746832],"type":"Point"}
}