{
  "type": "Feature",
  "properties": {
    "addr:full":"120 E Main Ave Frazee MN 56544",
    "addr:housenumber":"120",
    "addr:postcode":"56544",
    "addr:street":"E Main Ave",
    "iso:country":"US",
    "sg:address":"120 E Main Ave",
    "sg:city":"Frazee",
    "sg:classifiers":[
        {
            "category":"Food & Beverages",
            "subcategory":"Groceries & Convenience Stores",
            "type":"Retail Goods"
        }
    ],
    "sg:phone":"+1 218 334 2131",
    "sg:postcode":"56544",
    "sg:province":"MN",
    "sg:tags":[
        "grocer",
        "grocers-specialty"
    ],
    "wof:name":"Larson's Jack & Jill Food Center",
    "wof:placetype":"venue"
},
  "geometry": {"coordinates":[-95.700502,46.727706],"type":"Point"}
}