{
  "type": "Feature",
  "properties": {
    "iso:country":"US",
    "sg:address":"221 S Main St",
    "sg:city":"Fulda",
    "sg:phone":"+1 507 468 2475",
    "sg:postcode":"56131",
    "sg:province":"MN",
    "sg:tags":[
        "farm",
        "corn",
        "grain",
        "cash",
        "soybean"
    ],
    "wof:name":"Richard Brunk",
    "wof:placetype":"venue"
},
  "geometry": {"coordinates":[-95.46667100000001,43.843716],"type":"Point"}
}