{
  "type": "Feature",
  "properties": {
    "addr:full":"1 Carlson Pkwy S Minneapolis MN 55447",
    "addr:housenumber":"1",
    "addr:postcode":"55447",
    "addr:street":"Carlson Pkwy S",
    "iso:country":"US",
    "sg:address":"1 Carlson Pkwy S",
    "sg:city":"Minneapolis",
    "sg:classifiers":[
        {
            "category":"Building & Trades",
            "subcategory":"Construction",
            "type":"Services"
        }
    ],
    "sg:phone":"+1 763 404 1112",
    "sg:postcode":"55447",
    "sg:province":"MN",
    "sg:tags":[
        "industrial",
        "commercial"
    ],
    "wof:name":"Woodbridge Property Company",
    "wof:placetype":"venue"
},
  "geometry": {"coordinates":[-93.46420500000001,44.978546],"type":"Point"}
}