{
  "type": "Feature",
  "properties": {
    "addr:full":"20 Excelsior Ave S Annandale MN 55302",
    "addr:housenumber":"20",
    "addr:postcode":"55302",
    "addr:street":"Excelsior Ave S Annandale",
    "iso:country":"US",
    "sg:address":"20 Excelsior Ave S",
    "sg:city":"Annandale",
    "sg:classifiers":[
        {
            "category":"Building & Trades",
            "subcategory":"Construction",
            "type":"Services"
        }
    ],
    "sg:phone":"+1 320 274 2620",
    "sg:postcode":"55302",
    "sg:province":"MN",
    "sg:tags":[
        "contractor"
    ],
    "wof:name":"Sign City Inc",
    "wof:placetype":"venue"
},
  "geometry": {"coordinates":[-94.12739500000001,45.261696],"type":"Point"}
}