{
  "type": "Feature",
  "properties": {
    "iso:country":"US",
    "sg:address":"407 O'Day St S",
    "sg:city":"Saint Paul",
    "sg:classifiers":[
        {
            "category":"Professional",
            "type":"Services"
        }
    ],
    "sg:phone":"+1 651 731 3145",
    "sg:postcode":"55119",
    "sg:province":"MN",
    "sg:tags":[
        "business"
    ],
    "wof:name":"Complete Understanding",
    "wof:placetype":"venue"
},
  "geometry": {"coordinates":[-93.164643,44.888187],"type":"Point"}
}