{
  "type": "Feature",
  "properties": {
    "addr:full":"39960 531st Ave New Ulm MN 56073",
    "addr:housenumber":"39960",
    "addr:postcode":"56073",
    "addr:street":"531St Ave",
    "iso:country":"US",
    "sg:address":"39960 531st Ave",
    "sg:city":"New Ulm",
    "sg:classifiers":[
        {
            "category":"Manufacturing",
            "subcategory":"Tools & Machinery",
            "type":"Manufacturing & Wholesale Goods"
        }
    ],
    "sg:phone":"+1 507 354 7721",
    "sg:postcode":"56073",
    "sg:province":"MN",
    "sg:tags":[
        "mfg"
    ],
    "wof:name":"Midwest Mold Solutions",
    "wof:placetype":"venue"
},
  "geometry": {"coordinates":[-94.331502,44.370193],"type":"Point"}
}