{
  "type": "Feature",
  "properties": {
    "addr:full":"1418 Belmont Ln W Roseville MN 55113",
    "addr:housenumber":"1418",
    "addr:postcode":"55113",
    "addr:street":"Belmont Ln W",
    "iso:country":"US",
    "sg:address":"1418 Belmont Ln W",
    "sg:city":"Roseville",
    "sg:classifiers":[
        {
            "category":"Professional",
            "subcategory":"Art Services",
            "type":"Services"
        }
    ],
    "sg:phone":"+1 651 635 9942",
    "sg:postcode":"55113",
    "sg:province":"MN",
    "sg:tags":[
        "photographer",
        "photography",
        "commercial"
    ],
    "wof:name":"Burian Photography",
    "wof:placetype":"venue"
},
  "geometry": {"coordinates":[-93.159507,45.003488],"type":"Point"}
}