{
  "type": "Feature",
  "properties": {
    "addr:full":"70 1st Ave NE Little Falls MN 56345",
    "addr:housenumber":"70",
    "addr:postcode":"56345",
    "addr:street":"1St Ave Ne",
    "iso:country":"US",
    "sg:address":"70 1st Ave NE",
    "sg:city":"Little Falls",
    "sg:classifiers":[
        {
            "category":"Real Estate",
            "subcategory":"Architect",
            "type":"Services"
        }
    ],
    "sg:phone":"+1 320 632 9582",
    "sg:postcode":"56345",
    "sg:province":"MN",
    "wof:name":"Kevin James Anderson",
    "wof:placetype":"venue"
},
  "geometry": {"coordinates":[-94.36297500000001,45.977533],"type":"Point"}
}