{
  "type": "Feature",
  "properties": {
    "addr:full":"603 8th St SW Wells MN 56097",
    "addr:housenumber":"603",
    "addr:postcode":"56097",
    "addr:street":"8Th St Sw",
    "iso:country":"US",
    "sg:address":"603 8th St SW",
    "sg:city":"Wells",
    "sg:classifiers":[
        {
            "category":"Real Estate",
            "subcategory":"Real Estate Operator",
            "type":"Services"
        }
    ],
    "sg:phone":"+1 507 553 3502",
    "sg:postcode":"56097",
    "sg:province":"MN",
    "sg:tags":[
        "property",
        "lessor"
    ],
    "wof:name":"Victoria M Wilder",
    "wof:placetype":"venue"
},
  "geometry": {"coordinates":[-93.734667,43.737104],"type":"Point"}
}