{
  "type": "Feature",
  "properties": {
    "addr:full":"4756 Banning Ave Saint Paul MN 55110",
    "addr:housenumber":"4756",
    "addr:postcode":"55110",
    "addr:street":"Banning Ave",
    "iso:country":"US",
    "sg:address":"4756 Banning Ave",
    "sg:city":"Saint Paul",
    "sg:classifiers":[
        {
            "category":"Health Services",
            "subcategory":"Doctor",
            "type":"Services"
        }
    ],
    "sg:phone":"+1 651 426 9986",
    "sg:postcode":"55110",
    "sg:province":"MN",
    "wof:name":"Jennifer L Ddsms Eisenhuth",
    "wof:placetype":"venue"
},
  "geometry": {"coordinates":[-93.00755599999999,45.08448],"type":"Point"}
}