{
  "type": "Feature",
  "properties": {
    "iso:country":"US",
    "sg:address":"1637 Alabama Ave S",
    "sg:city":"Minneapolis",
    "sg:classifiers":[
        {
            "category":"Professional",
            "subcategory":"Business Services",
            "type":"Services"
        }
    ],
    "sg:phone":"+1 952 546 4217",
    "sg:postcode":"55416",
    "sg:province":"MN",
    "wof:name":"PI Audio/Design",
    "wof:placetype":"venue"
},
  "geometry": {"coordinates":[-93.356478,44.966147],"type":"Point"}
}