{
  "type": "Feature",
  "properties": {
    "iso:country":"US",
    "sg:address":"2130 S Broadway",
    "sg:city":"Rochester",
    "sg:classifiers":[
        {
            "category":"Professional",
            "subcategory":"Business Services",
            "type":"Services"
        }
    ],
    "sg:phone":"+1 507 288 8894",
    "sg:postcode":"55904",
    "sg:province":"MN",
    "wof:name":"Whipple Heights",
    "wof:placetype":"venue"
},
  "geometry": {"coordinates":[-92.462265,43.99002],"type":"Point"}
}