{
  "type": "Feature",
  "properties": {
    "iso:country":"US",
    "sg:address":"7100 Medicine Lake Rd",
    "sg:city":"Minneapolis",
    "sg:classifiers":[
        {
            "category":"Building & Trades",
            "subcategory":"Construction",
            "type":"Services"
        }
    ],
    "sg:phone":"+1 763 559 0808",
    "sg:postcode":"55427",
    "sg:province":"MN",
    "sg:tags":[
        "contractor",
        "mechanical"
    ],
    "sg:website":"http://www.tncind.com",
    "wof:name":"Plymovent Of Mn",
    "wof:placetype":"venue"
},
  "geometry": {"coordinates":[-93.370323,45.007332],"type":"Point"}
}