{
  "type": "Feature",
  "properties": {
    "iso:country":"US",
    "sg:address":"140 Barry Ave N",
    "sg:city":"Wayzata",
    "sg:classifiers":[
        {
            "category":"Banks & Credit Unions",
            "subcategory":"Investment Brokerage",
            "type":"Services"
        }
    ],
    "sg:phone":"+1 952 473 4133",
    "sg:postcode":"55391",
    "sg:province":"MN",
    "sg:tags":[
        "security"
    ],
    "wof:name":"Martinson & Company Ltd",
    "wof:placetype":"venue"
},
  "geometry": {"coordinates":[-93.517228,44.97444],"type":"Point"}
}