{
  "type": "Feature",
  "properties": {
    "addr:full":"6121 42nd Ave N Minneapolis MN 55422",
    "addr:housenumber":"6121",
    "addr:postcode":"55422",
    "addr:street":"42Nd Ave N",
    "iso:country":"US",
    "sg:address":"6121 42nd Ave N",
    "sg:city":"Minneapolis",
    "sg:classifiers":[
        {
            "category":"Restaurant",
            "type":"Food & Drink"
        }
    ],
    "sg:phone":"+1 763 537 3003",
    "sg:postcode":"55422",
    "sg:province":"MN",
    "sg:tags":[
        "chinese"
    ],
    "wof:name":"Kengs Chow Mein Chinese",
    "wof:placetype":"venue"
},
  "geometry": {"coordinates":[-93.35790299999999,45.032398],"type":"Point"}
}