{
  "type": "Feature",
  "properties": {
    "addr:full":"1840 Hartle Ave Owatonna MN 55060",
    "addr:housenumber":"1840",
    "addr:postcode":"55060",
    "addr:street":"Hartle Ave",
    "iso:country":"US",
    "sg:address":"1840 Hartle Ave",
    "sg:city":"Owatonna",
    "sg:classifiers":[
        {
            "category":"Retail",
            "subcategory":"Veterinary Services",
            "type":"Services"
        }
    ],
    "sg:phone":"+1 507 451 4591",
    "sg:postcode":"55060",
    "sg:province":"MN",
    "sg:tags":[
        "veterinarian"
    ],
    "wof:name":"Fairview Veterinary Hospital",
    "wof:placetype":"venue"
},
  "geometry": {"coordinates":[-93.22116200000001,44.065793],"type":"Point"}
}