{
  "type": "Feature",
  "properties": {
    "iso:country":"US",
    "sg:address":"3519 N 6th St",
    "sg:city":"Minneapolis",
    "sg:classifiers":[
        {
            "category":"Social Services",
            "subcategory":"Child Care",
            "type":"Services"
        }
    ],
    "sg:phone":"+1 612 529 3623",
    "sg:postcode":"55412",
    "sg:province":"MN",
    "sg:tags":[
        "home",
        "day"
    ],
    "wof:name":"Ellora M Jackson",
    "wof:placetype":"venue"
},
  "geometry": {"coordinates":[-93.28657200000001,45.01997],"type":"Point"}
}