{
  "type": "Feature",
  "properties": {
    "addr:full":"30979 Northfield Blvd Northfield MN 55057",
    "addr:housenumber":"30979",
    "addr:postcode":"55057",
    "addr:street":"Northfield Blvd",
    "iso:country":"US",
    "sg:address":"30979 Northfield Blvd",
    "sg:city":"Northfield",
    "sg:classifiers":[
        {
            "category":"Building & Trades",
            "subcategory":"Landscaping Services",
            "type":"Services"
        }
    ],
    "sg:phone":"+1 507 663 7720",
    "sg:postcode":"55057",
    "sg:province":"MN",
    "sg:tags":[
        "landscape"
    ],
    "wof:name":"Monarch Enterprise Inc",
    "wof:placetype":"venue"
},
  "geometry": {"coordinates":[-93.114124,44.499537],"type":"Point"}
}