{
  "type": "Feature",
  "properties": {
    "addr:full":"13732 Nicollet Ave Burnsville MN 55337",
    "addr:housenumber":"13732",
    "addr:postcode":"55337",
    "addr:street":"Nicollet Ave",
    "iso:country":"US",
    "sg:address":"13732 Nicollet Ave",
    "sg:city":"Burnsville",
    "sg:classifiers":[
        {
            "category":"Food & Beverages",
            "subcategory":"Groceries & Convenience Stores",
            "type":"Retail Goods"
        }
    ],
    "sg:phone":"+1 952 707 1260",
    "sg:postcode":"55337",
    "sg:province":"MN",
    "wof:name":"Dakota Halal Market",
    "wof:placetype":"venue"
},
  "geometry": {"coordinates":[-93.278069,44.754507],"type":"Point"}
}