{
  "type": "Feature",
  "properties": {
    "addr:full":"1209 S State St New Ulm MN 56073",
    "addr:housenumber":"1209",
    "addr:postcode":"56073",
    "addr:street":"S State St",
    "iso:country":"US",
    "sg:address":"1209 S State St",
    "sg:city":"New Ulm",
    "sg:classifiers":[
        {
            "category":"Home & Garden",
            "subcategory":"Hardware",
            "type":"Retail Goods"
        }
    ],
    "sg:phone":"+1 507 359 3006",
    "sg:postcode":"56073",
    "sg:province":"MN",
    "sg:tags":[
        "tool",
        "sales"
    ],
    "wof:name":"Chuck Effenberger Author",
    "wof:placetype":"venue"
},
  "geometry": {"coordinates":[-94.45051100000001,44.300112],"type":"Point"}
}