{
  "type": "Feature",
  "properties": {
    "iso:country":"US",
    "sg:address":"701 6th St W",
    "sg:city":"Ada",
    "sg:classifiers":[
        {
            "category":"Social Services",
            "subcategory":"Adult Care",
            "type":"Services"
        }
    ],
    "sg:phone":"+1 218 784 3366",
    "sg:postcode":"56510",
    "sg:province":"MN",
    "sg:tags":[
        "residential"
    ],
    "wof:name":"Integrity",
    "wof:placetype":"venue"
},
  "geometry": {"coordinates":[-96.52492100000001,47.303287],"type":"Point"}
}