{
  "type": "Feature",
  "properties": {
    "addr:full":"101 Main St Elkton MN 55933",
    "addr:housenumber":"101",
    "addr:postcode":"55933",
    "addr:street":"Main St",
    "iso:country":"US",
    "sg:address":"101 Main St",
    "sg:city":"Elkton",
    "sg:classifiers":[
        {
            "category":"Restaurant",
            "type":"Food & Drink"
        }
    ],
    "sg:phone":"+1 507 584 1225",
    "sg:postcode":"55933",
    "sg:province":"MN",
    "sg:tags":[
        "eating"
    ],
    "wof:name":"Elkton Restaurant & Lounge",
    "wof:placetype":"venue"
},
  "geometry": {"coordinates":[-92.70943,43.663053],"type":"Point"}
}