{
  "type": "Feature",
  "properties": {
    "addr:full":"637 1st St Taylors Falls MN 55084",
    "addr:housenumber":"637",
    "addr:postcode":"55084",
    "addr:street":"1St St",
    "iso:country":"US",
    "sg:address":"637 1st St",
    "sg:city":"Taylors Falls",
    "sg:classifiers":[
        {
            "category":"Government",
            "subcategory":"Office",
            "type":"Public Place"
        }
    ],
    "sg:phone":"+1 612 465 7315",
    "sg:postcode":"55084",
    "sg:province":"MN",
    "sg:tags":[
        "executive"
    ],
    "wof:name":"Taylors Falls City Offices",
    "wof:placetype":"venue"
},
  "geometry": {"coordinates":[-92.661497,45.402817],"type":"Point"}
}