{
  "type": "Feature",
  "properties": {
    "addr:full":"906 23rd Ave NE Minneapolis MN 55418",
    "addr:housenumber":"906",
    "addr:postcode":"55418",
    "addr:street":"23Rd Ave Ne",
    "iso:country":"US",
    "sg:address":"906 23rd Ave NE",
    "sg:city":"Minneapolis",
    "sg:classifiers":[
        {
            "category":"Building & Trades",
            "subcategory":"Construction",
            "type":"Services"
        }
    ],
    "sg:phone":"+1 612 789 6163",
    "sg:postcode":"55418",
    "sg:province":"MN",
    "sg:tags":[
        "house"
    ],
    "wof:name":"Kurt Nowacki Homes Inc",
    "wof:placetype":"venue"
},
  "geometry": {"coordinates":[-93.24911400000001,45.010872],"type":"Point"}
}