{
  "type": "Feature",
  "properties": {
    "iso:country":"US",
    "sg:address":"1710 Paul Bunyan Dr NW",
    "sg:city":"Bemidji",
    "sg:classifiers":[
        {
            "category":"Shopping",
            "subcategory":"Florist",
            "type":"Retail Goods"
        }
    ],
    "sg:phone":"+1 218 751 0850",
    "sg:postcode":"56601",
    "sg:province":"MN",
    "wof:name":"Bemidji Floral",
    "wof:placetype":"venue"
},
  "geometry": {"coordinates":[-94.906611,47.494421],"type":"Point"}
}