{
  "type": "Feature",
  "properties": {
    "iso:country":"US",
    "sg:address":"3224 Southdale Cir",
    "sg:city":"Minneapolis",
    "sg:classifiers":[
        {
            "category":"Retail",
            "subcategory":"Auto Repair",
            "type":"Services"
        }
    ],
    "sg:phone":"+1 952 925 1443",
    "sg:postcode":"55435",
    "sg:province":"MN",
    "sg:tags":[
        "transmission"
    ],
    "wof:name":"Midas Muffler",
    "wof:placetype":"venue"
},
  "geometry": {"coordinates":[-93.320494,44.882716],"type":"Point"}
}