{
  "type": "Feature",
  "properties": {
    "addr:full":"4255 Queen Ave N Minneapolis MN 55412",
    "addr:housenumber":"4255",
    "addr:postcode":"55412",
    "addr:street":"Queen Ave N",
    "iso:country":"US",
    "sg:address":"4255 Queen Ave N",
    "sg:city":"Minneapolis",
    "sg:classifiers":[
        {
            "category":"Professional",
            "subcategory":"Management & Consulting",
            "type":"Services"
        }
    ],
    "sg:phone":"+1 612 865 0421",
    "sg:postcode":"55412",
    "sg:province":"MN",
    "sg:tags":[
        "consultant",
        "medical",
        "practice"
    ],
    "wof:name":"Home Body Fitness",
    "wof:placetype":"venue"
},
  "geometry": {"coordinates":[-93.309799,45.03281],"type":"Point"}
}