{
  "type": "Feature",
  "properties": {
    "addr:full":"7877 150th St W Savage MN 55378",
    "addr:housenumber":"7877",
    "addr:postcode":"55378",
    "addr:street":"150Th St W",
    "iso:country":"US",
    "sg:address":"7877 150th St W",
    "sg:city":"Savage",
    "sg:classifiers":[
        {
            "category":"Retail",
            "subcategory":"Auto Repair",
            "type":"Services"
        }
    ],
    "sg:phone":"+1 612 369 5344",
    "sg:postcode":"55378",
    "sg:province":"MN",
    "wof:name":"Barry's Repair Llc",
    "wof:placetype":"venue"
},
  "geometry": {"coordinates":[-93.38085,44.731746],"type":"Point"}
}