{
  "type": "Feature",
  "properties": {
    "iso:country":"US",
    "sg:address":"905 102nd Ave NE",
    "sg:city":"Minneapolis",
    "sg:classifiers":[
        {
            "category":"Professional",
            "type":"Services"
        }
    ],
    "sg:phone":"+1 763 795 8453",
    "sg:postcode":"55434",
    "sg:province":"MN",
    "wof:name":"Housecalls Unlimited",
    "wof:placetype":"venue"
},
  "geometry": {"coordinates":[-93.247653,45.155054],"type":"Point"}
}