{
  "type": "Feature",
  "properties": {
    "addr:full":"2225 Curve Crest Blvd W Stillwater MN 55082",
    "addr:housenumber":"2225",
    "addr:postcode":"55082",
    "addr:street":"Curve Crest Blvd W",
    "iso:country":"US",
    "sg:address":"2225 Curve Crest Blvd W",
    "sg:city":"Stillwater",
    "sg:classifiers":[
        {
            "category":"Food & Beverages",
            "subcategory":"Liquor & Beverages",
            "type":"Retail Goods"
        }
    ],
    "sg:phone":"+1 651 439 3399",
    "sg:postcode":"55082",
    "sg:province":"MN",
    "sg:tags":[
        "eating",
        "alcoholic"
    ],
    "sg:website":"www.sutlers.com",
    "wof:name":"Sutler's Wines & Spirits",
    "wof:placetype":"venue"
},
  "geometry": {"coordinates":[-92.83713400000001,45.040254],"type":"Point"}
}