{
  "type": "Feature",
  "properties": {
    "addr:full":"5400 Douglas Dr N Minneapolis MN 55429",
    "addr:housenumber":"5400",
    "addr:postcode":"55429",
    "addr:street":"Douglas Dr N",
    "iso:country":"US",
    "sg:address":"5400 Douglas Dr N",
    "sg:city":"Minneapolis",
    "sg:classifiers":[
        {
            "category":"Manufacturing",
            "subcategory":"Metals",
            "type":"Manufacturing & Wholesale Goods"
        },
        {
            "category":"Retail",
            "subcategory":"Repair Shop",
            "type":"Services"
        },
        {
            "category":"Retail",
            "subcategory":"Auto Repair",
            "type":"Services"
        },
        {
            "category":"Wholesale",
            "subcategory":"Vending Machines",
            "type":"Manufacturing & Wholesale Goods"
        }
    ],
    "sg:phone":"+1 763 535 4445",
    "sg:postcode":"55429",
    "sg:province":"MN",
    "sg:tags":[
        "automobile",
        "precision",
        "grinding"
    ],
    "sg:website":"http://www.minnesotagrinding.com",
    "wof:name":"Minnesota Grinding Inc",
    "wof:placetype":"venue"
},
  "geometry": {"coordinates":[-93.36031,45.050585],"type":"Point"}
}