{
  "type": "Feature",
  "properties": {
    "addr:full":"8408 Medicine Lake Rd Minneapolis MN 55427",
    "addr:housenumber":"8408",
    "addr:postcode":"55427",
    "addr:street":"Medicine Lake Rd",
    "iso:country":"US",
    "sg:address":"8408 Medicine Lake Rd",
    "sg:city":"Minneapolis",
    "sg:classifiers":[
        {
            "category":"Wholesale",
            "subcategory":"Computers",
            "type":"Manufacturing & Wholesale Goods"
        }
    ],
    "sg:phone":"+1 763 541 0490",
    "sg:postcode":"55427",
    "sg:province":"MN",
    "wof:name":"Atp Computers",
    "wof:placetype":"venue"
},
  "geometry": {"coordinates":[-93.38769499999999,45.007473],"type":"Point"}
}