{
  "type": "Feature",
  "properties": {
    "iso:country":"US",
    "sg:address":"14937 Monterey Ave S",
    "sg:city":"Savage",
    "sg:classifiers":[
        {
            "category":"Professional",
            "subcategory":"Engineering",
            "type":"Services"
        }
    ],
    "sg:phone":"+1 952 440 4548",
    "sg:postcode":"55378",
    "sg:province":"MN",
    "sg:tags":[
        "feed",
        "consulting",
        "industrial",
        "design",
        "grain",
        "engineer"
    ],
    "wof:name":"Hanson Companies Inc",
    "wof:placetype":"venue"
},
  "geometry": {"coordinates":[-93.33718399999999,44.734025],"type":"Point"}
}