{
  "type": "Feature",
  "properties": {
    "iso:country":"US",
    "sg:address":"12446 Plaza Dr",
    "sg:city":"Eden Prairie",
    "sg:classifiers":[
        {
            "category":"Home & Garden",
            "subcategory":"Household Appliances",
            "type":"Retail Goods"
        }
    ],
    "sg:phone":"+1 952 941 7560",
    "sg:postcode":"55344",
    "sg:province":"MN",
    "wof:name":"E P Appliance Service Company",
    "wof:placetype":"venue"
},
  "geometry": {"coordinates":[-93.438975,44.863729],"type":"Point"}
}