{
  "type": "Feature",
  "properties": {
    "iso:country":"US",
    "sg:address":"4035 2nd St S",
    "sg:city":"St Cloud",
    "sg:classifiers":[
        {
            "category":"Retail",
            "subcategory":"Auto Repair",
            "type":"Services"
        }
    ],
    "sg:phone":"+1 320 240 2033",
    "sg:postcode":"56301",
    "sg:province":"MN",
    "sg:tags":[
        "automobile",
        "lubrication",
        "automotive"
    ],
    "wof:name":"Valvoline Instant Oil Change",
    "wof:placetype":"venue"
},
  "geometry": {"coordinates":[-94.20724199999999,45.549803],"type":"Point"}
}