{
  "type": "Feature",
  "properties": {
    "iso:country":"US",
    "sg:address":"4130 Blackhawk Rd Ste 134",
    "sg:city":"Saint Paul",
    "sg:classifiers":[
        {
            "category":"Retail",
            "subcategory":"Pet Boarding",
            "type":"Services"
        }
    ],
    "sg:phone":"+1 651 681 0267",
    "sg:postcode":"55122",
    "sg:province":"MN",
    "sg:tags":[
        "boarding/pet",
        "sitting"
    ],
    "sg:website":"www.groomingdalesmn.com",
    "wof:name":"Groomingdale's Pet Salon",
    "wof:placetype":"venue"
},
  "geometry": {"coordinates":[-93.195503,44.806499],"type":"Point"}
}