{
  "type": "Feature",
  "properties": {
    "iso:country":"US",
    "sg:address":"2215 21st Ave S",
    "sg:city":"Minneapolis",
    "sg:classifiers":[
        {
            "category":"Real Estate",
            "subcategory":"Architect",
            "type":"Services"
        }
    ],
    "sg:phone":"+1 612 239 5773",
    "sg:postcode":"55404",
    "sg:province":"MN",
    "sg:tags":[
        "architects'",
        "specification",
        "builders'",
        "construction",
        "architectural"
    ],
    "sg:website":"http://www.c3homedesign.com",
    "wof:name":"C Cubed Home Design Inc",
    "wof:placetype":"venue"
},
  "geometry": {"coordinates":[-93.242509,44.960885],"type":"Point"}
}