{
  "type": "Feature",
  "properties": {
    "iso:country":"US",
    "sg:address":"7317 W 83rd St",
    "sg:city":"Minneapolis",
    "sg:classifiers":[
        {
            "category":"Real Estate",
            "subcategory":"Real Estate Agent",
            "type":"Services"
        }
    ],
    "sg:phone":"+1 952 829 8979",
    "sg:postcode":"55438",
    "sg:province":"MN",
    "wof:name":"Petroff Inc",
    "wof:placetype":"venue"
},
  "geometry": {"coordinates":[-93.379524,44.851994],"type":"Point"}
}