{
  "type": "Feature",
  "properties": {
    "addr:full":"301 S Minnesota St New Ulm MN 56073",
    "addr:housenumber":"301",
    "addr:postcode":"56073",
    "addr:street":"S Minnesota St",
    "iso:country":"US",
    "sg:address":"301 S Minnesota St",
    "sg:city":"New Ulm",
    "sg:classifiers":[
        {
            "category":"Social Services",
            "type":"Services"
        }
    ],
    "sg:phone":"+1 507 354 5111",
    "sg:postcode":"56073",
    "sg:province":"MN",
    "sg:tags":[
        "care",
        "center",
        "day"
    ],
    "wof:name":"Adult Day Svc",
    "wof:placetype":"venue"
},
  "geometry": {"coordinates":[-94.456109,44.310318],"type":"Point"}
}