{
  "type": "Feature",
  "properties": {
    "addr:full":"2116 260th St E Webster MN 55088",
    "addr:housenumber":"2116",
    "addr:postcode":"55088",
    "addr:street":"260Th St E",
    "iso:country":"US",
    "sg:address":"2116 260th St E",
    "sg:city":"Webster",
    "sg:classifiers":[
        {
            "category":"Building & Trades",
            "subcategory":"Construction",
            "type":"Services"
        }
    ],
    "sg:phone":"+1 952 758 4022",
    "sg:postcode":"55088",
    "sg:province":"MN",
    "sg:tags":[
        "contractor"
    ],
    "wof:name":"Zweber Construction & Drywall",
    "wof:placetype":"venue"
},
  "geometry": {"coordinates":[-93.47997599999999,44.572686],"type":"Point"}
}