{
  "type": "Feature",
  "properties": {
    "addr:full":"1861 Viking Blvd NE Cedar MN 55011",
    "addr:housenumber":"1861",
    "addr:postcode":"55011",
    "addr:street":"Viking Blvd Ne Cedar",
    "iso:country":"US",
    "sg:address":"1861 Viking Blvd NE",
    "sg:city":"Cedar",
    "sg:classifiers":[
        {
            "category":"Home & Garden",
            "subcategory":"Furniture",
            "type":"Retail Goods"
        },
        {
            "category":"Home & Garden",
            "subcategory":"Home Furnishings",
            "type":"Retail Goods"
        },
        {
            "category":"Building & Trades",
            "subcategory":"Construction",
            "type":"Services"
        },
        {
            "category":"Manufacturing",
            "subcategory":"Building Materials",
            "type":"Manufacturing & Wholesale Goods"
        },
        {
            "category":"Wholesale",
            "subcategory":"Home Furnishings",
            "type":"Manufacturing & Wholesale Goods"
        }
    ],
    "sg:phone":"+1 763 434 7071",
    "sg:postcode":"55011",
    "sg:province":"MN",
    "sg:tags":[
        "manufacturer",
        "industrial",
        "equipment-wholesale",
        "cabinetmakers-commercial",
        "cabinet",
        "refacing",
        "resurfacing",
        "equipment-household",
        "maker",
        "cabinets-refinishing",
        "kitchen"
    ],
    "wof:name":"Gordy's Custom Cabinets",
    "wof:placetype":"venue"
},
  "geometry": {"coordinates":[-93.224065,45.319549],"type":"Point"}
}