{
  "type": "Feature",
  "properties": {
    "addr:full":"112 Milne Ave Henning MN 56551",
    "addr:housenumber":"112",
    "addr:postcode":"56551",
    "addr:street":"Milne Ave",
    "iso:country":"US",
    "sg:address":"112 Milne Ave",
    "sg:city":"Henning",
    "sg:classifiers":[
        {
            "category":"Building & Trades",
            "subcategory":"Construction",
            "type":"Services"
        }
    ],
    "sg:phone":"+1 218 731 8727",
    "sg:postcode":"56551",
    "sg:province":"MN",
    "sg:tags":[
        "residential"
    ],
    "wof:name":"Hagen Construction",
    "wof:placetype":"venue"
},
  "geometry": {"coordinates":[-95.45126399999999,46.323428],"type":"Point"}
}