{
  "type": "Feature",
  "properties": {
    "addr:full":"45354 Co Hwy 19 Sebeka MN 56477",
    "addr:housenumber":"45354",
    "addr:postcode":"56477",
    "addr:street":"Co Hwy 19 Sebeka",
    "iso:country":"US",
    "sg:address":"45354 Co Hwy 19",
    "sg:city":"Sebeka",
    "sg:classifiers":[
        {
            "category":"Farming",
            "subcategory":"Farm",
            "type":"Manufacturing & Wholesale Goods"
        }
    ],
    "sg:phone":"+1 218 837 5375",
    "sg:postcode":"56477",
    "sg:province":"MN",
    "wof:name":"Loch-Latch Farm",
    "wof:placetype":"venue"
},
  "geometry": {"coordinates":[-95.23921,46.615659],"type":"Point"}
}