{
  "type": "Feature",
  "properties": {
    "addr:full":"301 4th St E Thief River Falls MN 56701",
    "addr:housenumber":"301",
    "addr:postcode":"56701",
    "addr:street":"4Th St",
    "iso:country":"US",
    "sg:address":"301 4th St E",
    "sg:city":"Thief River Falls",
    "sg:classifiers":[
        {
            "category":"Social Services",
            "type":"Services"
        }
    ],
    "sg:phone":"+1 218 681 4507",
    "sg:postcode":"56701",
    "sg:province":"MN",
    "sg:tags":[
        "organization",
        "individual",
        "family",
        "welfare"
    ],
    "wof:name":"Northwest Senior Federation",
    "wof:placetype":"venue"
},
  "geometry": {"coordinates":[-96.17843999999999,48.120169],"type":"Point"}
}