{
  "type": "Feature",
  "properties": {
    "addr:full":"6256 34th Ave NW Rochester MN 55901",
    "addr:housenumber":"6256",
    "addr:postcode":"55901",
    "addr:street":"34Th Ave Nw",
    "iso:country":"US",
    "sg:address":"6256 34th Ave NW",
    "sg:city":"Rochester",
    "sg:classifiers":[
        {
            "category":"Professional",
            "type":"Services"
        }
    ],
    "sg:phone":"+1 507 288 0825",
    "sg:postcode":"55901",
    "sg:province":"MN",
    "sg:tags":[
        "establishment"
    ],
    "wof:name":"Advantagevending.Comllc",
    "wof:placetype":"venue"
},
  "geometry": {"coordinates":[-92.51405,44.091022],"type":"Point"}
}