{
  "type": "Feature",
  "properties": {
    "iso:country":"US",
    "sg:address":"4820 Minnetonka Blvd #101",
    "sg:city":"Minneapolis",
    "sg:classifiers":[
        {
            "category":"Health Services",
            "subcategory":"Doctor",
            "type":"Services"
        }
    ],
    "sg:phone":"+1 952 392 8862",
    "sg:postcode":"55416",
    "sg:province":"MN",
    "sg:tags":[
        "hair",
        "replacement"
    ],
    "sg:website":"http://www.apollonow.com",
    "wof:name":"Apollo International Hair Replacement & Restoration",
    "wof:placetype":"venue"
},
  "geometry": {"coordinates":[-93.34931899999999,44.948448],"type":"Point"}
}