{
  "type": "Feature",
  "properties": {
    "addr:full":"506 Minnesota Ave W Walker MN 56484",
    "addr:housenumber":"506",
    "addr:postcode":"56484",
    "addr:street":"Minnesota Ave W",
    "iso:country":"US",
    "sg:address":"506 Minnesota Ave W",
    "sg:city":"Walker",
    "sg:classifiers":[
        {
            "category":"Shopping",
            "subcategory":"Gifts & Souvenirs",
            "type":"Retail Goods"
        }
    ],
    "sg:phone":"+1 218 547 3440",
    "sg:postcode":"56484",
    "sg:province":"MN",
    "sg:tags":[
        "shop"
    ],
    "wof:name":"Northern Exposure",
    "wof:placetype":"venue"
},
  "geometry": {"coordinates":[-94.582089,47.101738],"type":"Point"}
}