{
  "type": "Feature",
  "properties": {
    "addr:full":"5445 120th Ave Princeton MN 55371",
    "addr:housenumber":"5445",
    "addr:postcode":"55371",
    "addr:street":"120Th Ave",
    "iso:country":"US",
    "sg:address":"5445 120th Ave",
    "sg:city":"Princeton",
    "sg:classifiers":[
        {
            "category":"Professional",
            "type":"Services"
        }
    ],
    "sg:phone":"+1 763 389 2639",
    "sg:postcode":"55371",
    "sg:province":"MN",
    "sg:tags":[
        "government"
    ],
    "wof:name":"Greenbush Government Center",
    "wof:placetype":"venue"
},
  "geometry": {"coordinates":[-93.655799,45.624544],"type":"Point"}
}