{
  "type": "Feature",
  "properties": {
    "addr:full":"23427 210th Ave Glenwood MN 56334",
    "addr:housenumber":"23427",
    "addr:postcode":"56334",
    "addr:street":"210Th Ave",
    "iso:country":"US",
    "sg:address":"23427 210th Ave",
    "sg:city":"Glenwood",
    "sg:classifiers":[
        {
            "category":"Professional",
            "type":"Services"
        }
    ],
    "sg:phone":"+1 320 634 5535",
    "sg:postcode":"56334",
    "sg:province":"MN",
    "wof:name":"Eipa Services Inc",
    "wof:placetype":"venue"
},
  "geometry": {"coordinates":[-95.357936,45.569331],"type":"Point"}
}