{
  "type": "Feature",
  "properties": {
    "iso:country":"US",
    "sg:address":"4445 W 77th St",
    "sg:city":"Edina",
    "sg:classifiers":[
        {
            "category":"Wholesale",
            "subcategory":"Electrical",
            "type":"Manufacturing & Wholesale Goods"
        }
    ],
    "sg:phone":"+1 952 224 5555",
    "sg:postcode":"55435",
    "sg:province":"MN",
    "sg:tags":[
        "telecommunication"
    ],
    "sg:website":"www.aexcom.com",
    "wof:name":"AEX Communications",
    "wof:placetype":"venue"
},
  "geometry": {"coordinates":[-93.341255,44.863119],"type":"Point"}
}