{
  "type": "Feature",
  "properties": {
    "addr:full":"12601 Homestead Dr Saint Paul MN 55110",
    "addr:housenumber":"12601",
    "addr:postcode":"55110",
    "addr:street":"Homestead Dr",
    "iso:country":"US",
    "sg:address":"12601 Homestead Dr",
    "sg:city":"Saint Paul",
    "sg:classifiers":[
        {
            "category":"Professional",
            "type":"Services"
        }
    ],
    "sg:phone":"+1 651 426 6797",
    "sg:postcode":"55110",
    "sg:province":"MN",
    "wof:name":"Edwards Lifesciences",
    "wof:placetype":"venue"
},
  "geometry": {"coordinates":[-92.946079,45.13119],"type":"Point"}
}