{
  "type": "Feature",
  "properties": {
    "addr:full":"4999 France Ave S Minneapolis MN 55410",
    "addr:housenumber":"4999",
    "addr:postcode":"55410",
    "addr:street":"France Ave S",
    "iso:country":"US",
    "sg:address":"4999 France Ave S",
    "sg:city":"Minneapolis",
    "sg:classifiers":[
        {
            "category":"Real Estate",
            "subcategory":"Real Estate Operator",
            "type":"Services"
        }
    ],
    "sg:phone":"+1 612 929 0010",
    "sg:postcode":"55410",
    "sg:province":"MN",
    "sg:tags":[
        "building",
        "nonresidential"
    ],
    "wof:name":"Manrose Properties Inc",
    "wof:placetype":"venue"
},
  "geometry": {"coordinates":[-93.329048,44.913452],"type":"Point"}
}