{
  "type": "Feature",
  "properties": {
    "addr:full":"20 6th St NW Rochester MN 55901",
    "addr:housenumber":"20",
    "addr:postcode":"55901",
    "addr:street":"6Th St Nw",
    "iso:country":"US",
    "sg:address":"20 6th St NW",
    "sg:city":"Rochester",
    "sg:classifiers":[
        {
            "category":"Health Services",
            "subcategory":"Clinic",
            "type":"Services"
        }
    ],
    "sg:phone":"+1 507 282 4411",
    "sg:postcode":"55901",
    "sg:province":"MN",
    "wof:name":"Farmers Union Insurance",
    "wof:placetype":"venue"
},
  "geometry": {"coordinates":[-92.46348500000001,44.029414],"type":"Point"}
}