{
  "type": "Feature",
  "properties": {
    "iso:country":"US",
    "sg:address":"27935 426th Ave",
    "sg:city":"Battle Lake",
    "sg:classifiers":[
        {
            "category":"Professional",
            "type":"Services"
        }
    ],
    "sg:phone":"+1 218 367 2925",
    "sg:postcode":"56515",
    "sg:province":"MN",
    "sg:tags":[
        "establishment"
    ],
    "wof:name":"Walker & Walker",
    "wof:placetype":"venue"
},
  "geometry": {"coordinates":[-95.60315,46.36805],"type":"Point"}
}