{
  "type": "Feature",
  "properties": {
    "iso:country":"US",
    "sg:address":"214 S Minnesota Ave",
    "sg:city":"St Peter",
    "sg:classifiers":[
        {
            "category":"Building & Trades",
            "subcategory":"Landscaping Services",
            "type":"Services"
        }
    ],
    "sg:phone":"+1 507 931 9058",
    "sg:postcode":"56082",
    "sg:province":"MN",
    "sg:tags":[
        "landscape",
        "contractor"
    ],
    "wof:name":"Down To Earth Landscaping",
    "wof:placetype":"venue"
},
  "geometry": {"coordinates":[-93.95663999999999,44.324919],"type":"Point"}
}