{
  "type": "Feature",
  "properties": {
    "addr:full":"110 E 7th St Morris MN 56267",
    "addr:housenumber":"110",
    "addr:postcode":"56267",
    "addr:street":"E 7Th St",
    "iso:country":"US",
    "sg:address":"110 E 7th St",
    "sg:city":"Morris",
    "sg:classifiers":[
        {
            "category":"Professional",
            "subcategory":"Business Services",
            "type":"Services"
        }
    ],
    "sg:phone":"+1 320 589 4106",
    "sg:postcode":"56267",
    "sg:province":"MN",
    "wof:name":"D & D Enterprises",
    "wof:placetype":"venue"
},
  "geometry": {"coordinates":[-95.912971,45.588884],"type":"Point"}
}