{
  "type": "Feature",
  "properties": {
    "addr:full":"101 1st Ave SW Rochester MN 55902",
    "addr:housenumber":"101",
    "addr:postcode":"55902",
    "addr:street":"1St Ave Sw",
    "iso:country":"US",
    "sg:address":"101 1st Ave SW",
    "sg:city":"Rochester",
    "sg:classifiers":[
        {
            "category":"Shopping",
            "subcategory":"Clothing, Apparel, & Fashions",
            "type":"Retail Goods"
        },
        {
            "category":"Utilities",
            "subcategory":"Mobile Phone",
            "type":"Services"
        }
    ],
    "sg:phone":"+1 507 288 2892",
    "sg:postcode":"55902",
    "sg:province":"MN",
    "sg:tags":[
        "handbag",
        "wi-fi",
        "hotspot"
    ],
    "wof:name":"The Ultra Shop",
    "wof:placetype":"venue"
},
  "geometry": {"coordinates":[-92.464409,44.022491],"type":"Point"}
}