{
  "type": "Feature",
  "properties": {
    "addr:full":"411 Washington Ave N Minneapolis MN 55401",
    "addr:housenumber":"411",
    "addr:postcode":"55401",
    "addr:street":"Washington Ave N",
    "iso:country":"US",
    "sg:address":"411 Washington Ave N",
    "sg:city":"Minneapolis",
    "sg:classifiers":[
        {
            "category":"Professional",
            "subcategory":"Art Services",
            "type":"Services"
        }
    ],
    "sg:phone":"+1 612 343 0042",
    "sg:postcode":"55401",
    "sg:province":"MN",
    "sg:tags":[
        "graphic",
        "design"
    ],
    "wof:name":"Boom Island Design",
    "wof:placetype":"venue"
},
  "geometry": {"coordinates":[-93.27475,44.986103],"type":"Point"}
}