{
  "type": "Feature",
  "properties": {
    "iso:country":"US",
    "sg:address":"7650 Currell Blvd",
    "sg:city":"Saint Paul",
    "sg:classifiers":[
        {
            "category":"Banks & Credit Unions",
            "subcategory":"Investment Brokerage",
            "type":"Services"
        }
    ],
    "sg:phone":"+1 651 702 9000",
    "sg:postcode":"55125",
    "sg:province":"MN",
    "sg:tags":[
        "brokerage",
        "stock"
    ],
    "wof:name":"H & R Block",
    "wof:placetype":"venue"
},
  "geometry": {"coordinates":[-92.950711,44.923683],"type":"Point"}
}