{
  "type": "Feature",
  "properties": {
    "addr:full":"8774 State Hwy 371 Brainerd MN 56401",
    "addr:housenumber":"8774",
    "addr:postcode":"56401",
    "addr:street":"State Hwy 371",
    "iso:country":"US",
    "sg:address":"8774 State Hwy 371",
    "sg:city":"Brainerd",
    "sg:classifiers":[
        {
            "category":"Retail",
            "subcategory":"Repair Shop",
            "type":"Services"
        }
    ],
    "sg:phone":"+1 218 829 5871",
    "sg:postcode":"56401",
    "sg:province":"MN",
    "wof:name":"In Stitches",
    "wof:placetype":"venue"
},
  "geometry": {"coordinates":[-94.350624,46.237888],"type":"Point"}
}