{
  "type": "Feature",
  "properties": {
    "iso:country":"US",
    "sg:address":"3947 Excelsior Blvd 114A",
    "sg:city":"Minneapolis",
    "sg:classifiers":[
        {
            "category":"Utilities",
            "subcategory":"Electric",
            "type":"Services"
        }
    ],
    "sg:phone":"+1 952 922 0274",
    "sg:postcode":"55416",
    "sg:province":"MN",
    "sg:tags":[
        "equipment",
        "supplies-repair",
        "electronic",
        "equipment-repair"
    ],
    "wof:name":"Foremost Electronic Services, Inc.",
    "wof:placetype":"venue"
},
  "geometry": {"coordinates":[-93.33003600000001,44.93966],"type":"Point"}
}