{
  "type": "Feature",
  "properties": {
    "addr:full":"415 Lake Ave NE Bemidji MN 56601",
    "addr:housenumber":"415",
    "addr:postcode":"56601",
    "addr:street":"Lake Ave Ne",
    "iso:country":"US",
    "sg:address":"415 Lake Ave NE",
    "sg:city":"Bemidji",
    "sg:classifiers":[
        {
            "category":"Building & Trades",
            "subcategory":"Cleaning & Sanitation",
            "type":"Services"
        }
    ],
    "sg:phone":"+1 218 444 5657",
    "sg:postcode":"56601",
    "sg:province":"MN",
    "sg:tags":[
        "janitor",
        "janitorial"
    ],
    "wof:name":"R K Cleaning",
    "wof:placetype":"venue"
},
  "geometry": {"coordinates":[-94.842631,47.462749],"type":"Point"}
}