{
  "type": "Feature",
  "properties": {
    "addr:full":"12065 Co Rd 30 Waconia MN 55387",
    "addr:housenumber":"12065;30",
    "addr:postcode":"55387",
    "addr:street":"Co Rd",
    "iso:country":"US",
    "sg:address":"12065 Co Rd 30",
    "sg:city":"Waconia",
    "sg:classifiers":[
        {
            "category":"Freight",
            "type":"Transportation"
        }
    ],
    "sg:phone":"+1 952 442 4564",
    "sg:postcode":"55387",
    "sg:province":"MN",
    "sg:tags":[
        "operator",
        "local",
        "trucking"
    ],
    "wof:name":"Kelzer Freight Trucking",
    "wof:placetype":"venue"
},
  "geometry": {"coordinates":[-93.831817,44.872012],"type":"Point"}
}