{
  "type": "Feature",
  "properties": {
    "addr:full":"28164 State Hwy 22 Litchfield MN 55355",
    "addr:housenumber":"28164",
    "addr:postcode":"55355",
    "addr:street":"State Hwy 22",
    "iso:country":"US",
    "sg:address":"28164 State Hwy 22",
    "sg:city":"Litchfield",
    "sg:classifiers":[
        {
            "category":"Organizations",
            "subcategory":"Religious Organization",
            "type":"Services"
        }
    ],
    "sg:phone":"+1 320 693 2202",
    "sg:postcode":"55355",
    "sg:province":"MN",
    "sg:tags":[
        "church"
    ],
    "wof:name":"Assembly Of God Church",
    "wof:placetype":"venue"
},
  "geometry": {"coordinates":[-94.54192,45.152986],"type":"Point"}
}