{
  "type": "Feature",
  "properties": {
    "iso:country":"US",
    "sg:address":"5601 E River Rd",
    "sg:city":"Minneapolis",
    "sg:classifiers":[
        {
            "category":"Manufacturing",
            "subcategory":"Chemicals & Compounds",
            "type":"Manufacturing & Wholesale Goods"
        }
    ],
    "sg:phone":"+1 763 572 2999",
    "sg:postcode":"55432",
    "sg:province":"MN",
    "sg:tags":[
        "mfg",
        "cosmetic",
        "cleaning",
        "specialty",
        "formulation"
    ],
    "wof:name":"Tiro Industries LLC",
    "wof:placetype":"venue"
},
  "geometry": {"coordinates":[-93.278319,45.070113],"type":"Point"}
}