{
  "type": "Feature",
  "properties": {
    "iso:country":"US",
    "sg:address":"12710 Cedar Lake Rd",
    "sg:city":"Hopkins",
    "sg:classifiers":[
        {
            "category":"Professional",
            "subcategory":"Art Services",
            "type":"Services"
        }
    ],
    "sg:phone":"+1 952 545 2591",
    "sg:postcode":"55305",
    "sg:province":"MN",
    "sg:tags":[
        "designer",
        "display",
        "producer"
    ],
    "wof:name":"Designs Crafted By Dawn",
    "wof:placetype":"venue"
},
  "geometry": {"coordinates":[-93.440393,44.949328],"type":"Point"}
}