{
  "type": "Feature",
  "properties": {
    "iso:country":"US",
    "sg:address":"710 Main Ave",
    "sg:city":"Moorhead",
    "sg:classifiers":[
        {
            "category":"Manufacturing",
            "subcategory":"Printing",
            "type":"Manufacturing & Wholesale Goods"
        }
    ],
    "sg:phone":"+1 218 233 1531",
    "sg:postcode":"56560",
    "sg:province":"MN",
    "sg:tags":[
        "commercial"
    ],
    "sg:website":"www.fm-printing.com",
    "wof:name":"F M Printing",
    "wof:placetype":"venue"
},
  "geometry": {"coordinates":[-96.770214,46.873863],"type":"Point"}
}