{
  "type": "Feature",
  "properties": {
    "addr:full":"1424 E College Dr Marshall MN 56258",
    "addr:housenumber":"1424",
    "addr:postcode":"56258",
    "addr:street":"E College Dr",
    "iso:country":"US",
    "sg:address":"1424 E College Dr",
    "sg:city":"Marshall",
    "sg:classifiers":[
        {
            "category":"Banks & Credit Unions",
            "subcategory":"Investment Brokerage",
            "type":"Services"
        }
    ],
    "sg:phone":"+1 507 401 1060",
    "sg:postcode":"56258",
    "sg:province":"MN",
    "sg:tags":[
        "advisory"
    ],
    "wof:name":"Quest Resources",
    "wof:placetype":"venue"
},
  "geometry": {"coordinates":[-95.761083,44.450453],"type":"Point"}
}