{
  "type": "Feature",
  "properties": {
    "iso:country":"US",
    "sg:address":"2015 1st St S",
    "sg:city":"Willmar",
    "sg:classifiers":[
        {
            "category":"Insurance",
            "subcategory":"Insurance Agent",
            "type":"Services"
        }
    ],
    "sg:phone":"+1 320 235 2725",
    "sg:postcode":"56201",
    "sg:province":"MN",
    "wof:name":"American Family Insurance",
    "wof:placetype":"venue"
},
  "geometry": {"coordinates":[-95.042575,45.102425],"type":"Point"}
}