{
  "type": "Feature",
  "properties": {
    "addr:full":"529 Sisler Ave Grand Rapids MN 55744",
    "addr:housenumber":"529",
    "addr:postcode":"55744",
    "addr:street":"Sisler Ave",
    "iso:country":"US",
    "sg:address":"529 Sisler Ave",
    "sg:city":"Grand Rapids",
    "sg:classifiers":[
        {
            "category":"Real Estate",
            "subcategory":"Real Estate Operator",
            "type":"Services"
        }
    ],
    "sg:phone":"+1 218 326 0731",
    "sg:postcode":"55744",
    "sg:province":"MN",
    "sg:tags":[
        "building",
        "nonresidential"
    ],
    "wof:name":"Dale & Dorothy Nordin",
    "wof:placetype":"venue"
},
  "geometry": {"coordinates":[-93.486206,47.227703],"type":"Point"}
}