{
  "type": "Feature",
  "properties": {
    "iso:country":"US",
    "sg:address":"1890 350th St",
    "sg:city":"Minneota",
    "sg:classifiers":[
        {
            "category":"Farming",
            "subcategory":"Livestock Farm",
            "type":"Manufacturing & Wholesale Goods"
        },
        {
            "category":"Farming",
            "subcategory":"Farm",
            "type":"Manufacturing & Wholesale Goods"
        }
    ],
    "sg:phone":"+1 507 428 3549",
    "sg:postcode":"56264",
    "sg:province":"MN",
    "wof:name":"Van Uden, Gordon",
    "wof:placetype":"venue"
},
  "geometry": {"coordinates":[-95.863938,44.557961],"type":"Point"}
}