{
  "type": "Feature",
  "properties": {
    "addr:full":"1230 E Main St Mankato MN 56001",
    "addr:housenumber":"1230",
    "addr:postcode":"56001",
    "addr:street":"E Main St",
    "iso:country":"US",
    "sg:address":"1230 E Main St",
    "sg:city":"Mankato",
    "sg:classifiers":[
        {
            "category":"Health Services",
            "subcategory":"Doctor",
            "type":"Services"
        }
    ],
    "sg:phone":"+1 507 389 8522",
    "sg:postcode":"56001",
    "sg:province":"MN",
    "sg:tags":[
        "medicine",
        "physician",
        "practice",
        "surgeons",
        "family"
    ],
    "wof:name":"Mark P Taylor Md",
    "wof:placetype":"venue"
},
  "geometry": {"coordinates":[-93.984036,44.161033],"type":"Point"}
}