{
  "type": "Feature",
  "properties": {
    "addr:full":"11888 Aberdeen St NE Minneapolis MN 55449",
    "addr:housenumber":"11888",
    "addr:postcode":"55449",
    "addr:street":"Aberdeen St Ne",
    "iso:country":"US",
    "sg:address":"11888 Aberdeen St NE",
    "sg:city":"Minneapolis",
    "sg:classifiers":[
        {
            "category":"Restaurant",
            "type":"Food & Drink"
        }
    ],
    "sg:phone":"+1 763 757 9900",
    "sg:postcode":"55449",
    "sg:province":"MN",
    "wof:name":"Vintage Rose The",
    "wof:placetype":"venue"
},
  "geometry": {"coordinates":[-93.23281299999999,45.185266],"type":"Point"}
}