{
  "type": "Feature",
  "properties": {
    "addr:full":"37113 Loon Dr Cohasset MN 55721",
    "addr:housenumber":"37113",
    "addr:postcode":"55721",
    "addr:street":"Loon Dr",
    "iso:country":"US",
    "sg:address":"37113 Loon Dr",
    "sg:city":"Cohasset",
    "sg:classifiers":[
        {
            "category":"Manufacturing",
            "subcategory":"Rubber & Plastics",
            "type":"Manufacturing & Wholesale Goods"
        }
    ],
    "sg:phone":"+1 218 328 0220",
    "sg:postcode":"55721",
    "sg:province":"MN",
    "sg:tags":[
        "pipe",
        "mfg"
    ],
    "wof:name":"Valley Creek Plastics",
    "wof:placetype":"venue"
},
  "geometry": {"coordinates":[-93.652033,47.238214],"type":"Point"}
}