{
  "type": "Feature",
  "properties": {
    "iso:country":"US",
    "sg:address":"17815 Isle Ave",
    "sg:city":"Lakeville",
    "sg:classifiers":[
        {
            "category":"Professional",
            "subcategory":"Business Services",
            "type":"Services"
        }
    ],
    "sg:phone":"+1 952 898 5120",
    "sg:postcode":"55044",
    "sg:province":"MN",
    "sg:tags":[
        "planning",
        "meeting",
        "convention"
    ],
    "wof:name":"Meetingvelocitycom Inc",
    "wof:placetype":"venue"
},
  "geometry": {"coordinates":[-93.260733,44.691314],"type":"Point"}
}