{
  "type": "Feature",
  "properties": {
    "addr:full":"2154 3rd St Saint Paul MN 55110",
    "addr:housenumber":"2154",
    "addr:postcode":"55110",
    "addr:street":"3Rd St",
    "iso:country":"US",
    "sg:address":"2154 3rd St",
    "sg:city":"Saint Paul",
    "sg:classifiers":[
        {
            "category":"Shopping",
            "type":"Retail Goods"
        }
    ],
    "sg:phone":"+1 651 429 2844",
    "sg:postcode":"55110",
    "sg:province":"MN",
    "sg:tags":[
        "art",
        "gallery",
        "merchandise",
        "dealer"
    ],
    "wof:name":"Uptown Images",
    "wof:placetype":"venue"
},
  "geometry": {"coordinates":[-93.010442,45.084261],"type":"Point"}
}