{
  "type": "Feature",
  "properties": {
    "addr:full":"407 3rd St Prinsburg MN 56281",
    "addr:housenumber":"407",
    "addr:postcode":"56281",
    "addr:street":"3Rd St",
    "iso:country":"US",
    "sg:address":"407 3rd St",
    "sg:city":"Prinsburg",
    "sg:classifiers":[
        {
            "category":"Building & Trades",
            "subcategory":"Electrical",
            "type":"Services"
        }
    ],
    "sg:phone":"+1 320 978 6841",
    "sg:postcode":"56281",
    "sg:province":"MN",
    "sg:tags":[
        "electric",
        "contractor"
    ],
    "wof:name":"Kim's Electric",
    "wof:placetype":"venue"
},
  "geometry": {"coordinates":[-95.1919,44.939199],"type":"Point"}
}