{
  "type": "Feature",
  "properties": {
    "iso:country":"US",
    "sg:address":"2825 13th Ave S",
    "sg:city":"Minneapolis",
    "sg:classifiers":[
        {
            "category":"Autos & Motor Vehicles",
            "subcategory":"Automobile Sales",
            "type":"Retail Goods"
        }
    ],
    "sg:phone":"+1 612 722 0065",
    "sg:postcode":"55407",
    "sg:province":"MN",
    "sg:tags":[
        "equipment",
        "aircraft",
        "parts",
        "supply"
    ],
    "sg:website":"www.wentworthaircraft.com",
    "wof:name":"Wentworth Aircraft Inc",
    "wof:placetype":"venue"
},
  "geometry": {"coordinates":[-93.256219,44.950058],"type":"Point"}
}