{
  "type": "Feature",
  "properties": {
    "addr:full":"10958 Xylon Ct Champlin MN 55316",
    "addr:housenumber":"10958",
    "addr:postcode":"55316",
    "addr:street":"Xylon Ct",
    "iso:country":"US",
    "sg:address":"10958 Xylon Ct",
    "sg:city":"Champlin",
    "sg:classifiers":[
        {
            "category":"Professional",
            "subcategory":"Business Services",
            "type":"Services"
        }
    ],
    "sg:phone":"+1 763 425 3805",
    "sg:postcode":"55316",
    "sg:province":"MN",
    "sg:tags":[
        "foster",
        "agency",
        "care"
    ],
    "wof:name":"Genesis Group Home",
    "wof:placetype":"venue"
},
  "geometry": {"coordinates":[-93.386308,45.153877],"type":"Point"}
}