{
  "type": "Feature",
  "properties": {
    "iso:country":"US",
    "sg:address":"19791 Wendigo Rd",
    "sg:city":"Grand Rapids",
    "sg:classifiers":[
        {
            "category":"Professional",
            "subcategory":"Computer Services",
            "type":"Services"
        }
    ],
    "sg:phone":"+1 218 326 4323",
    "sg:postcode":"55744",
    "sg:province":"MN",
    "sg:tags":[
        "prepackaged",
        "software"
    ],
    "wof:name":"Bp Design & Development Inc",
    "wof:placetype":"venue"
},
  "geometry": {"coordinates":[-93.45411900000001,47.15461],"type":"Point"}
}