{
  "type": "Feature",
  "properties": {
    "iso:country":"US",
    "sg:address":"410 Mill St",
    "sg:city":"Peterson",
    "sg:classifiers":[
        {
            "category":"Organizations",
            "subcategory":"Community Association",
            "type":"Services"
        }
    ],
    "sg:phone":"+1 507 875 2235",
    "sg:postcode":"55962",
    "sg:province":"MN",
    "sg:tags":[
        "military"
    ],
    "wof:name":"American Legion",
    "wof:placetype":"venue"
},
  "geometry": {"coordinates":[-91.83438099999999,43.78644],"type":"Point"}
}