{
  "type": "Feature",
  "properties": {
    "iso:country":"US",
    "sg:address":"611 4th St NW",
    "sg:city":"Faribault",
    "sg:classifiers":[
        {
            "category":"Cinema",
            "subcategory":"Movie Rental",
            "type":"Entertainment"
        }
    ],
    "sg:phone":"+1 507 332 8140",
    "sg:postcode":"55021",
    "sg:province":"MN",
    "sg:tags":[
        "shop",
        "salon",
        "gift",
        "tape",
        "internet",
        "video",
        "tanning"
    ],
    "wof:name":"Total Entertainment Center",
    "wof:placetype":"venue"
},
  "geometry": {"coordinates":[-93.279578,44.294573],"type":"Point"}
}