{
  "type": "Feature",
  "properties": {
    "addr:full":"6623 Jonquil Way Osseo MN 55369",
    "addr:housenumber":"6623",
    "addr:postcode":"55369",
    "addr:street":"Jonquil Way",
    "iso:country":"US",
    "sg:address":"6623 Jonquil Way",
    "sg:city":"Osseo",
    "sg:classifiers":[
        {
            "category":"Shopping",
            "type":"Retail Goods"
        }
    ],
    "sg:phone":"+1 763 493 2048",
    "sg:postcode":"55369",
    "sg:province":"MN",
    "sg:tags":[
        "merchandise"
    ],
    "wof:name":"European Glass & Crystal",
    "wof:placetype":"venue"
},
  "geometry": {"coordinates":[-93.435304,45.075932],"type":"Point"}
}