{
  "type": "Feature",
  "properties": {
    "iso:country":"US",
    "sg:address":"9321 5th St NE",
    "sg:city":"Minneapolis",
    "sg:classifiers":[
        {
            "category":"Retail",
            "subcategory":"Portrait Studio",
            "type":"Services"
        }
    ],
    "sg:phone":"+1 763 780 6347",
    "sg:postcode":"55434",
    "sg:province":"MN",
    "sg:tags":[
        "photography"
    ],
    "wof:name":"Joel Sheagren Photography",
    "wof:placetype":"venue"
},
  "geometry": {"coordinates":[-93.26322999999999,45.139966],"type":"Point"}
}