{
  "type": "Feature",
  "properties": {
    "iso:country":"US",
    "sg:address":"1890 Woodale Dr",
    "sg:city":"St Paul",
    "sg:classifiers":[
        {
            "category":"Wholesale",
            "subcategory":"Machinery & Supplies",
            "type":"Manufacturing & Wholesale Goods"
        }
    ],
    "sg:phone":"+1 651 730 4090",
    "sg:postcode":"55125",
    "sg:province":"MN",
    "sg:tags":[
        "inspection",
        "devices"
    ],
    "wof:name":"Dr Schenk Of America",
    "wof:placetype":"venue"
},
  "geometry": {"coordinates":[-92.970319,44.921549],"type":"Point"}
}