{
  "type": "Feature",
  "properties": {
    "iso:country":"US",
    "sg:address":"329 Norman Ridge Dr",
    "sg:city":"Minneapolis",
    "sg:classifiers":[
        {
            "category":"Manufacturing",
            "subcategory":"Textiles",
            "type":"Manufacturing & Wholesale Goods"
        },
        {
            "category":"Building & Trades",
            "subcategory":"Construction",
            "type":"Services"
        }
    ],
    "sg:phone":"+1 952 835 5328",
    "sg:postcode":"55437",
    "sg:province":"MN",
    "sg:tags":[
        "tile-wholesale",
        "manufacturer",
        "tile-contractors"
    ],
    "wof:name":"Tile Network",
    "wof:placetype":"venue"
},
  "geometry": {"coordinates":[-93.351485,44.83928],"type":"Point"}
}