{
  "type": "Feature",
  "properties": {
    "addr:full":"801 1st St Grand Marais MN 55604",
    "addr:housenumber":"801",
    "addr:postcode":"55604",
    "addr:street":"1St St",
    "iso:country":"US",
    "sg:address":"801 1st St",
    "sg:city":"Grand Marais",
    "sg:classifiers":[
        {
            "category":"Building & Trades",
            "subcategory":"Construction",
            "type":"Services"
        }
    ],
    "sg:phone":"+1 218 387 1773",
    "sg:postcode":"55604",
    "sg:province":"MN",
    "wof:name":"Pedersen David Construction",
    "wof:placetype":"venue"
},
  "geometry": {"coordinates":[-90.34566599999999,47.750631],"type":"Point"}
}