{
  "type": "Feature",
  "properties": {
    "iso:country":"US",
    "sg:address":"440 Hayward Ave N",
    "sg:city":"St Paul",
    "sg:classifiers":[
        {
            "category":"Professional",
            "subcategory":"Advertising",
            "type":"Services"
        }
    ],
    "sg:phone":"+1 651 714 8402",
    "sg:postcode":"55128",
    "sg:province":"MN",
    "sg:tags":[
        "distribution"
    ],
    "wof:name":"Schmid Systems Inc",
    "wof:placetype":"venue"
},
  "geometry": {"coordinates":[-92.956813,44.956891],"type":"Point"}
}