{
  "type": "Feature",
  "properties": {
    "addr:full":"1221 E. 4th Ave Ste 195 Shakopee MN 55379",
    "addr:housenumber":"1221",
    "addr:postcode":"55379",
    "addr:street":"E. 4Th Ave Ste 195",
    "iso:country":"US",
    "sg:address":"1221 E. 4th Ave Ste 195",
    "sg:city":"Shakopee",
    "sg:classifiers":[
        {
            "category":"Personal",
            "subcategory":"Beauty Salon",
            "type":"Services"
        }
    ],
    "sg:phone":"+1 952 913 7778",
    "sg:postcode":"55379",
    "sg:province":"MN",
    "sg:tags":[
        "spa"
    ],
    "wof:name":"Pure & Simple Therapeutic Massage",
    "wof:placetype":"venue"
},
  "geometry": {"coordinates":[-93.50932400000001,44.797766],"type":"Point"}
}