{
  "type": "Feature",
  "properties": {
    "iso:country":"US",
    "sg:address":"6188 Olson Memorial Hwy",
    "sg:city":"Minneapolis",
    "sg:classifiers":[
        {
            "category":"Shopping",
            "subcategory":"Stationery & Office Supplies",
            "type":"Retail Goods"
        }
    ],
    "sg:phone":"+1 763 544 0365",
    "sg:postcode":"55422",
    "sg:province":"MN",
    "sg:tags":[
        "partition"
    ],
    "wof:name":"Hufcor Minnesota",
    "wof:placetype":"venue"
},
  "geometry": {"coordinates":[-93.360618,44.984212],"type":"Point"}
}