{
  "type": "Feature",
  "properties": {
    "iso:country":"US",
    "sg:address":"20 Thompson Ave W",
    "sg:city":"Saint Paul",
    "sg:classifiers":[
        {
            "category":"Professional",
            "subcategory":"Management & Consulting",
            "type":"Services"
        }
    ],
    "sg:phone":"+1 651 554 0643",
    "sg:postcode":"55118",
    "sg:province":"MN",
    "wof:name":"Money Axa Financial Co",
    "wof:placetype":"venue"
},
  "geometry": {"coordinates":[-93.087125,44.89997],"type":"Point"}
}