{
  "type": "Feature",
  "properties": {
    "iso:country":"US",
    "sg:address":"1224 Foster Ave",
    "sg:city":"Duluth",
    "sg:classifiers":[
        {
            "category":"Social Services",
            "type":"Services"
        }
    ],
    "sg:phone":"+1 218 728 6224",
    "sg:postcode":"55811",
    "sg:province":"MN",
    "sg:tags":[
        "organization",
        "welfare"
    ],
    "wof:name":"Rem Mn Community Svc Inc",
    "wof:placetype":"venue"
},
  "geometry": {"coordinates":[-92.15047800000001,46.810926],"type":"Point"}
}