{
  "type": "Feature",
  "properties": {
    "iso:country":"US",
    "sg:address":"3600 S Broadway",
    "sg:city":"Rochester",
    "sg:classifiers":[
        {
            "category":"Professional",
            "type":"Services"
        }
    ],
    "sg:phone":"+1 507 288 3398",
    "sg:postcode":"55904",
    "sg:province":"MN",
    "sg:tags":[
        "establishment"
    ],
    "wof:name":"Timeless Treasures",
    "wof:placetype":"venue"
},
  "geometry": {"coordinates":[-92.463353,43.968203],"type":"Point"}
}