{
  "type": "Feature",
  "properties": {
    "addr:full":"33138 Co Rd 15 Fulda MN 56131",
    "addr:housenumber":"33138;15",
    "addr:postcode":"56131",
    "addr:street":"Co Rd",
    "iso:country":"US",
    "sg:address":"33138 Co Rd 15",
    "sg:city":"Fulda",
    "sg:classifiers":[
        {
            "category":"Real Estate",
            "subcategory":"Real Estate Operator",
            "type":"Services"
        }
    ],
    "sg:phone":"+1 507 468 2724",
    "sg:postcode":"56131",
    "sg:province":"MN",
    "sg:tags":[
        "property",
        "lessor"
    ],
    "wof:name":"Gene Paplow",
    "wof:placetype":"venue"
},
  "geometry": {"coordinates":[-95.418194,43.905855],"type":"Point"}
}