{
  "type": "Feature",
  "properties": {
    "addr:full":"22115 Co Rd 10 Sleepy Eye MN 56085",
    "addr:housenumber":"22115;10",
    "addr:postcode":"56085",
    "addr:street":"Co Rd;Eye",
    "iso:country":"US",
    "sg:address":"22115 Co Rd 10",
    "sg:city":"Sleepy Eye",
    "sg:classifiers":[
        {
            "category":"Farming",
            "subcategory":"Farm",
            "type":"Manufacturing & Wholesale Goods"
        }
    ],
    "sg:phone":"+1 507 794 7129",
    "sg:postcode":"56085",
    "sg:province":"MN",
    "sg:tags":[
        "crop",
        "general"
    ],
    "wof:name":"Mark Marti",
    "wof:placetype":"venue"
},
  "geometry": {"coordinates":[-94.68048,44.285815],"type":"Point"}
}