{
  "type": "Feature",
  "properties": {
    "iso:country":"US",
    "sg:address":"201 Church St",
    "sg:city":"Claremont",
    "sg:classifiers":[
        {
            "category":"Retail",
            "subcategory":"Repair Shop",
            "type":"Services"
        }
    ],
    "sg:phone":"+1 507 528 2250",
    "sg:postcode":"55924",
    "sg:province":"MN",
    "wof:name":"Final Touch Cleanups",
    "wof:placetype":"venue"
},
  "geometry": {"coordinates":[-92.99315199999999,44.044664],"type":"Point"}
}