{
  "type": "Feature",
  "properties": {
    "addr:full":"408 Fillmore St SE Chatfield MN 55923",
    "addr:housenumber":"408",
    "addr:postcode":"55923",
    "addr:street":"Fillmore St Se",
    "iso:country":"US",
    "sg:address":"408 Fillmore St SE",
    "sg:city":"Chatfield",
    "sg:classifiers":[
        {
            "category":"Home & Garden",
            "subcategory":"Home Furnishings",
            "type":"Retail Goods"
        }
    ],
    "sg:phone":"+1 507 867 3519",
    "sg:postcode":"55923",
    "sg:province":"MN",
    "wof:name":"Window Fashions",
    "wof:placetype":"venue"
},
  "geometry": {"coordinates":[-92.18601,43.844726],"type":"Point"}
}