{
  "type": "Feature",
  "properties": {
    "iso:country":"US",
    "sg:address":"255 E Roselawn Ave",
    "sg:city":"St Paul",
    "sg:classifiers":[
        {
            "category":"Wholesale",
            "subcategory":"Durable Goods & Equipment",
            "type":"Manufacturing & Wholesale Goods"
        },
        {
            "category":"Wholesale",
            "subcategory":"Non-durable Goods",
            "type":"Manufacturing & Wholesale Goods"
        }
    ],
    "sg:phone":"+1 651 488 3557",
    "sg:postcode":"55117",
    "sg:province":"MN",
    "sg:tags":[
        "stationery",
        "item",
        "representative",
        "gift",
        "manufacturer"
    ],
    "wof:name":"Bill Parranto & Associates",
    "wof:placetype":"venue"
},
  "geometry": {"coordinates":[-93.090614,44.999125],"type":"Point"}
}