{
  "type": "Feature",
  "properties": {
    "iso:country":"US",
    "sg:address":"8026 Highway 55",
    "sg:city":"Minneapolis",
    "sg:classifiers":[
        {
            "category":"Personal",
            "type":"Services"
        },
        {
            "category":"Sports & Exercise",
            "subcategory":"Gym",
            "type":"Entertainment"
        },
        {
            "category":"Health Services",
            "subcategory":"Health Practitioner",
            "type":"Services"
        },
        {
            "category":"Arena",
            "subcategory":"Sports Club",
            "type":"Entertainment"
        }
    ],
    "sg:phone":"+1 800 615 7352",
    "sg:postcode":"55427",
    "sg:province":"MN",
    "sg:tags":[
        "control",
        "weight",
        "consultant",
        "trainer",
        "program",
        "fitness",
        "physical"
    ],
    "sg:website":"http://twincities.citysearch.com/profile/external/36505901/golden_valley_mn/curves.html?publisher=yellowpages&reference_id=1&placement=ypwebsitemip",
    "wof:name":"Curves",
    "wof:placetype":"venue"
},
  "geometry": {"coordinates":[-93.381629,44.984072],"type":"Point"}
}