{
  "type": "Feature",
  "properties": {
    "addr:full":"770 52nd Ave Winona MN 55987",
    "addr:housenumber":"770",
    "addr:postcode":"55987",
    "addr:street":"52Nd Ave",
    "iso:country":"US",
    "sg:address":"770 52nd Ave",
    "sg:city":"Winona",
    "sg:classifiers":[
        {
            "category":"Real Estate",
            "subcategory":"Real Estate Operator",
            "type":"Services"
        }
    ],
    "sg:phone":"+1 507 454 5706",
    "sg:postcode":"55987",
    "sg:province":"MN",
    "sg:tags":[
        "property",
        "lessor"
    ],
    "wof:name":"Alton Block",
    "wof:placetype":"venue"
},
  "geometry": {"coordinates":[-91.709248,44.067161],"type":"Point"}
}