{
  "type": "Feature",
  "properties": {
    "iso:country":"US",
    "sg:address":"500 Dellwood Dr N",
    "sg:city":"Baxter",
    "sg:classifiers":[
        {
            "category":"Home & Garden",
            "subcategory":"Home Furnishings",
            "type":"Retail Goods"
        }
    ],
    "sg:phone":"+1 218 829 4738",
    "sg:postcode":"56425",
    "sg:province":"MN",
    "sg:tags":[
        "curtain",
        "made",
        "drapery"
    ],
    "wof:name":"Floor To Ceiling Store",
    "wof:placetype":"venue"
},
  "geometry": {"coordinates":[-94.243891,46.357605],"type":"Point"}
}