{
  "type": "Feature",
  "properties": {
    "iso:country":"US",
    "sg:address":"6805 20th Ave Ste 100",
    "sg:city":"Hugo",
    "sg:classifiers":[
        {
            "category":"Retail",
            "subcategory":"Pet Boarding",
            "type":"Services"
        }
    ],
    "sg:phone":"+1 651 765 8901",
    "sg:postcode":"55038",
    "sg:province":"MN",
    "sg:tags":[
        "packing",
        "crating"
    ],
    "sg:website":"http://www.midwestcrating.com",
    "wof:name":"Midwest Crating Unlimited Corp.",
    "wof:placetype":"venue"
},
  "geometry": {"coordinates":[-93.04078699999999,45.153065],"type":"Point"}
}