{
  "type": "Feature",
  "properties": {
    "iso:country":"US",
    "sg:address":"2273 75th Ave",
    "sg:city":"Princeton",
    "sg:classifiers":[
        {
            "category":"Shopping",
            "subcategory":"Computers & Home Electronics",
            "type":"Retail Goods"
        }
    ],
    "sg:phone":"+1 763 389 3817",
    "sg:postcode":"55371",
    "sg:province":"MN",
    "wof:name":"Peter Lendway Electronics",
    "wof:placetype":"venue"
},
  "geometry": {"coordinates":[-93.57323100000001,45.575287],"type":"Point"}
}