{
  "type": "Feature",
  "properties": {
    "iso:country":"US",
    "sg:address":"23059 Birkett Ave",
    "sg:city":"Magnolia",
    "sg:classifiers":[
        {
            "category":"Farming",
            "subcategory":"Farm",
            "type":"Manufacturing & Wholesale Goods"
        }
    ],
    "sg:phone":"+1 507 483 2074",
    "sg:postcode":"56158",
    "sg:province":"MN",
    "sg:tags":[
        "crop",
        "general"
    ],
    "wof:name":"Shirley Reisdorfer",
    "wof:placetype":"venue"
},
  "geometry": {"coordinates":[-96.013108,43.658916],"type":"Point"}
}