{
  "type": "Feature",
  "properties": {
    "addr:full":"301 West Ave Zumbrota MN 55992",
    "addr:housenumber":"301",
    "addr:postcode":"55992",
    "addr:street":"West Ave",
    "iso:country":"US",
    "sg:address":"301 West Ave",
    "sg:city":"Zumbrota",
    "sg:classifiers":[
        {
            "category":"Cinema",
            "subcategory":"Movie Rental",
            "type":"Entertainment"
        }
    ],
    "sg:phone":"+1 507 732 7234",
    "sg:postcode":"55992",
    "sg:province":"MN",
    "sg:tags":[
        "video",
        "tape"
    ],
    "wof:name":"Zumbro Video",
    "wof:placetype":"venue"
},
  "geometry": {"coordinates":[-92.67038599999999,44.294106],"type":"Point"}
}