{
  "type": "Feature",
  "properties": {
    "addr:full":"814 Center Ave W Dilworth MN 56529",
    "addr:housenumber":"814",
    "addr:postcode":"56529",
    "addr:street":"Center Ave W",
    "iso:country":"US",
    "sg:address":"814 Center Ave W",
    "sg:city":"Dilworth",
    "sg:classifiers":[
        {
            "category":"Health Services",
            "subcategory":"Chiropractor",
            "type":"Services"
        }
    ],
    "sg:phone":"+1 218 284 6040",
    "sg:postcode":"56529",
    "sg:province":"MN",
    "wof:name":"Derosier Chropractic Clinic PC",
    "wof:placetype":"venue"
},
  "geometry": {"coordinates":[-96.71472199999999,46.87659],"type":"Point"}
}