{
  "type": "Feature",
  "properties": {
    "iso:country":"US",
    "sg:address":"600 E Travelers Trl",
    "sg:city":"Burnsville",
    "sg:classifiers":[
        {
            "category":"Retail",
            "subcategory":"Auto Repair",
            "type":"Services"
        }
    ],
    "sg:phone":"+1 952 895 4968",
    "sg:postcode":"55337",
    "sg:province":"MN",
    "sg:tags":[
        "automotive"
    ],
    "wof:name":"Olson Don Tire & Auto Centers",
    "wof:placetype":"venue"
},
  "geometry": {"coordinates":[-93.268851,44.779572],"type":"Point"}
}