{
  "type": "Feature",
  "properties": {
    "addr:full":"510 22nd Ave E Alexandria MN 56308",
    "addr:housenumber":"510",
    "addr:postcode":"56308",
    "addr:street":"22Nd Ave E",
    "iso:country":"US",
    "sg:address":"510 22nd Ave E",
    "sg:city":"Alexandria",
    "sg:classifiers":[
        {
            "category":"Professional",
            "subcategory":"Management & Consulting",
            "type":"Services"
        }
    ],
    "sg:phone":"+1 320 762 2077",
    "sg:postcode":"56308",
    "sg:province":"MN",
    "sg:tags":[
        "construction"
    ],
    "wof:name":"Orb Management Corp",
    "wof:placetype":"venue"
},
  "geometry": {"coordinates":[-95.37326899999999,45.867373],"type":"Point"}
}