{
  "type": "Feature",
  "properties": {
    "addr:full":"424 Hayward Ave N St Paul MN 55128",
    "addr:housenumber":"424",
    "addr:postcode":"55128",
    "addr:street":"Hayward Ave N",
    "iso:country":"US",
    "sg:address":"424 Hayward Ave N",
    "sg:city":"St Paul",
    "sg:classifiers":[
        {
            "category":"Banks & Credit Unions",
            "subcategory":"Investment Brokerage",
            "type":"Services"
        }
    ],
    "sg:phone":"+1 651 203 1201",
    "sg:postcode":"55128",
    "sg:province":"MN",
    "sg:tags":[
        "advisory",
        "financial"
    ],
    "wof:name":"GMA Financial",
    "wof:placetype":"venue"
},
  "geometry": {"coordinates":[-92.95623399999999,44.957119],"type":"Point"}
}