{
  "type": "Feature",
  "properties": {
    "iso:country":"US",
    "sg:address":"191 Water St",
    "sg:city":"Alden",
    "sg:classifiers":[
        {
            "category":"Professional",
            "subcategory":"Detective & Security Services",
            "type":"Services"
        }
    ],
    "sg:phone":"+1 507 377 3683",
    "sg:postcode":"56009",
    "sg:province":"MN",
    "sg:tags":[
        "information",
        "bureau"
    ],
    "wof:name":"Alden Area Food Shelf",
    "wof:placetype":"venue"
},
  "geometry": {"coordinates":[-93.574066,43.671823],"type":"Point"}
}