{
  "type": "Feature",
  "properties": {
    "iso:country":"US",
    "sg:address":"14563 100th St",
    "sg:city":"Foreston",
    "sg:classifiers":[
        {
            "category":"Building & Trades",
            "subcategory":"Construction",
            "type":"Services"
        }
    ],
    "sg:phone":"+1 320 294 5125",
    "sg:postcode":"56330",
    "sg:province":"MN",
    "sg:tags":[
        "carpentry",
        "contractor"
    ],
    "wof:name":"Mels Woodworking",
    "wof:placetype":"venue"
},
  "geometry": {"coordinates":[-93.713459,45.692506],"type":"Point"}
}