{
  "type": "Feature",
  "properties": {
    "iso:country":"US",
    "sg:address":"1418 S Riverfront Dr",
    "sg:city":"Mankato",
    "sg:classifiers":[
        {
            "category":"Autos & Motor Vehicles",
            "subcategory":"Auto Supplies",
            "type":"Retail Goods"
        }
    ],
    "sg:phone":"+1 507 345 8863",
    "sg:postcode":"56001",
    "sg:province":"MN",
    "sg:tags":[
        "automobile",
        "stereo",
        "radio"
    ],
    "sg:website":"www.sweetsounds.com",
    "wof:name":"Sweet Sounds",
    "wof:placetype":"venue"
},
  "geometry": {"coordinates":[-94.020158,44.159983],"type":"Point"}
}