{
  "type": "Feature",
  "properties": {
    "iso:country":"US",
    "sg:address":"15600 Wayzata Blvd",
    "sg:city":"Wayzata",
    "sg:classifiers":[
        {
            "category":"Real Estate",
            "subcategory":"Developer",
            "type":"Services"
        }
    ],
    "sg:phone":"+1 952 476 9400",
    "sg:postcode":"55391",
    "sg:province":"MN",
    "wof:name":"Hj Development LLP",
    "wof:placetype":"venue"
},
  "geometry": {"coordinates":[-93.48177200000001,44.971394],"type":"Point"}
}