{
  "type": "Feature",
  "properties": {
    "addr:full":"1336 Baker Rd SW Alexandria MN 56308",
    "addr:housenumber":"1336",
    "addr:postcode":"56308",
    "addr:street":"Baker Rd Sw",
    "iso:country":"US",
    "sg:address":"1336 Baker Rd SW",
    "sg:city":"Alexandria",
    "sg:classifiers":[
        {
            "category":"Farming",
            "subcategory":"Livestock Farm",
            "type":"Manufacturing & Wholesale Goods"
        }
    ],
    "sg:phone":"+1 320 762 7081",
    "sg:postcode":"56308",
    "sg:province":"MN",
    "sg:tags":[
        "equine"
    ],
    "wof:name":"Rolling Meadows Stables",
    "wof:placetype":"venue"
},
  "geometry": {"coordinates":[-95.469219,45.876614],"type":"Point"}
}