{
  "type": "Feature",
  "properties": {
    "addr:full":"31394 130th St Winnebago MN 56098",
    "addr:housenumber":"31394",
    "addr:postcode":"56098",
    "addr:street":"130Th St",
    "iso:country":"US",
    "sg:address":"31394 130th St",
    "sg:city":"Winnebago",
    "sg:classifiers":[
        {
            "category":"Farming",
            "subcategory":"Farm",
            "type":"Manufacturing & Wholesale Goods"
        }
    ],
    "sg:phone":"+1 507 464 3334",
    "sg:postcode":"56098",
    "sg:province":"MN",
    "sg:tags":[
        "corn",
        "crop",
        "soybean",
        "general"
    ],
    "wof:name":"Bruce Helland",
    "wof:placetype":"venue"
},
  "geometry": {"coordinates":[-94.234229,43.673667],"type":"Point"}
}