{
  "type": "Feature",
  "properties": {
    "iso:country":"US",
    "sg:address":"1736 320th St",
    "sg:city":"Bellingham",
    "sg:phone":"+1 320 568 2242",
    "sg:postcode":"56239",
    "sg:province":"MN",
    "sg:tags":[
        "farm",
        "corn",
        "soybean"
    ],
    "wof:name":"Larry Weber",
    "wof:placetype":"venue"
},
  "geometry": {"coordinates":[-95.951098,44.516375],"type":"Point"}
}