{
  "type": "Feature",
  "properties": {
    "addr:full":"9624 Palmer Rd Minneapolis MN 55437",
    "addr:housenumber":"9624",
    "addr:postcode":"55437",
    "addr:street":"Palmer Rd",
    "iso:country":"US",
    "sg:address":"9624 Palmer Rd",
    "sg:city":"Minneapolis",
    "sg:classifiers":[
        {
            "category":"Professional",
            "subcategory":"Business Services",
            "type":"Services"
        }
    ],
    "sg:phone":"+1 952 831 5325",
    "sg:postcode":"55437",
    "sg:province":"MN",
    "wof:name":"Nelson Commercial Properties",
    "wof:placetype":"venue"
},
  "geometry": {"coordinates":[-93.342286,44.827654],"type":"Point"}
}