{
  "type": "Feature",
  "properties": {
    "iso:country":"US",
    "sg:address":"2170 280th St",
    "sg:city":"Madison",
    "sg:classifiers":[
        {
            "category":"Social Services",
            "subcategory":"Child Care",
            "type":"Services"
        }
    ],
    "sg:phone":"+1 320 598 7714",
    "sg:postcode":"56258",
    "sg:province":"MN",
    "sg:tags":[
        "day",
        "provider"
    ],
    "wof:name":"Country Care",
    "wof:placetype":"venue"
},
  "geometry": {"coordinates":[-95.86238,44.45775],"type":"Point"}
}