{
  "type": "Feature",
  "properties": {
    "addr:full":"1143 Riverwood Dr Burnsville MN 55337",
    "addr:housenumber":"1143",
    "addr:postcode":"55337",
    "addr:street":"Riverwood Dr",
    "iso:country":"US",
    "sg:address":"1143 Riverwood Dr",
    "sg:city":"Burnsville",
    "sg:classifiers":[
        {
            "category":"Autos & Motor Vehicles",
            "subcategory":"Automobile Sales",
            "type":"Retail Goods"
        },
        {
            "category":"Wholesale",
            "subcategory":"Motor Vehicles",
            "type":"Manufacturing & Wholesale Goods"
        }
    ],
    "sg:phone":"+1 952 707 8676",
    "sg:postcode":"55337",
    "sg:province":"MN",
    "sg:tags":[
        "performance",
        "race",
        "dealer"
    ],
    "wof:name":"Peregrine Motor Sports",
    "wof:placetype":"venue"
},
  "geometry": {"coordinates":[-93.258646,44.785186],"type":"Point"}
}