{
  "type": "Feature",
  "properties": {
    "iso:country":"US",
    "sg:address":"174 Main St",
    "sg:city":"Winona",
    "sg:classifiers":[
        {
            "category":"Professional",
            "subcategory":"Lawyer & Legal Services",
            "type":"Services"
        }
    ],
    "sg:phone":"+1 507 454 3752",
    "sg:postcode":"55987",
    "sg:province":"MN",
    "wof:name":"Benson & Merchlewitz",
    "wof:placetype":"venue"
},
  "geometry": {"coordinates":[-91.63815,44.052289],"type":"Point"}
}