{
  "type": "Feature",
  "properties": {
    "iso:country":"US",
    "sg:address":"81985 380th St",
    "sg:city":"Bird Island",
    "sg:phone":"+1 320 365 3322",
    "sg:postcode":"55310",
    "sg:province":"MN",
    "sg:tags":[
        "farm",
        "beet"
    ],
    "wof:name":"Prokosch Farm Inc",
    "wof:placetype":"venue"
},
  "geometry": {"coordinates":[-94.915469,44.771822],"type":"Point"}
}