{
  "type": "Feature",
  "properties": {
    "addr:full":"1850 Adams St Mankato MN 56001",
    "addr:housenumber":"1850",
    "addr:postcode":"56001",
    "addr:street":"Adams St",
    "iso:country":"US",
    "sg:address":"1850 Adams St",
    "sg:city":"Mankato",
    "sg:classifiers":[
        {
            "category":"Shopping",
            "subcategory":"Clothing, Apparel, & Fashions",
            "type":"Retail Goods"
        }
    ],
    "sg:phone":"+1 507 345 3895",
    "sg:postcode":"56001",
    "sg:province":"MN",
    "sg:tags":[
        "leather"
    ],
    "wof:name":"Wilsons Leather",
    "wof:placetype":"venue"
},
  "geometry": {"coordinates":[-93.953412,44.170412],"type":"Point"}
}