{
  "type": "Feature",
  "properties": {
    "iso:country":"US",
    "sg:address":"714 W College St",
    "sg:city":"Duluth",
    "sg:classifiers":[
        {
            "category":"Social Services",
            "subcategory":"Adult Care",
            "type":"Services"
        }
    ],
    "sg:phone":"+1 218 724 8815",
    "sg:postcode":"55811",
    "sg:province":"MN",
    "sg:tags":[
        "residential"
    ],
    "wof:name":"Northwood Childrens Services",
    "wof:placetype":"venue"
},
  "geometry": {"coordinates":[-92.09435499999999,46.814897],"type":"Point"}
}