{
  "type": "Feature",
  "properties": {
    "addr:full":"4409 Oakmede Ln Saint Paul MN 55110",
    "addr:housenumber":"4409",
    "addr:postcode":"55110",
    "addr:street":"Oakmede Ln",
    "iso:country":"US",
    "sg:address":"4409 Oakmede Ln",
    "sg:city":"Saint Paul",
    "sg:classifiers":[
        {
            "category":"Professional",
            "type":"Services"
        }
    ],
    "sg:phone":"+1 651 653 6466",
    "sg:postcode":"55110",
    "sg:province":"MN",
    "wof:name":"Monte Lindahl",
    "wof:placetype":"venue"
},
  "geometry": {"coordinates":[-93.04468900000001,45.074854],"type":"Point"}
}