{
  "type": "Feature",
  "properties": {
    "addr:full":"5322 Frost Point Cir SE Prior Lake MN 55372",
    "addr:housenumber":"5322",
    "addr:postcode":"55372",
    "addr:street":"Frost Point Cir Se",
    "iso:country":"US",
    "sg:address":"5322 Frost Point Cir SE",
    "sg:city":"Prior Lake",
    "sg:classifiers":[
        {
            "category":"Professional",
            "type":"Services"
        }
    ],
    "sg:phone":"+1 952 447 4542",
    "sg:postcode":"55372",
    "sg:province":"MN",
    "wof:name":"Ayrton Corp",
    "wof:placetype":"venue"
},
  "geometry": {"coordinates":[-93.413449,44.731367],"type":"Point"}
}