{
  "type": "Feature",
  "properties": {
    "addr:full":"2600 7th St N Saint Cloud MN 56303",
    "addr:housenumber":"2600",
    "addr:postcode":"56303",
    "addr:street":"7Th St N",
    "iso:country":"US",
    "sg:address":"2600 7th St N",
    "sg:city":"Saint Cloud",
    "sg:classifiers":[
        {
            "category":"Freight",
            "type":"Transportation"
        }
    ],
    "sg:phone":"+1 320 251 5050",
    "sg:postcode":"56303",
    "sg:province":"MN",
    "sg:tags":[
        "operator",
        "local",
        "trucking"
    ],
    "wof:name":"Yellow Cab",
    "wof:placetype":"venue"
},
  "geometry": {"coordinates":[-94.18979899999999,45.564],"type":"Point"}
}