{
  "type": "Feature",
  "properties": {
    "iso:country":"US",
    "sg:address":"3011 Country Dr",
    "sg:city":"Little Canada",
    "sg:classifiers":[
        {
            "category":"Retail",
            "subcategory":"Auto Repair",
            "type":"Services"
        },
        {
            "category":"Wholesale",
            "subcategory":"Auto Parts",
            "type":"Manufacturing & Wholesale Goods"
        }
    ],
    "sg:phone":"+1 651 482 1267",
    "sg:postcode":"55117",
    "sg:province":"MN",
    "sg:tags":[
        "repairing",
        "automobile",
        "general",
        "re",
        "supply"
    ],
    "wof:name":"Best Auto & Tire Center Inc",
    "wof:placetype":"venue"
},
  "geometry": {"coordinates":[-93.091808,45.033783],"type":"Point"}
}