{
  "type": "Feature",
  "properties": {
    "addr:full":"506 7th St SE Minneapolis MN 55414",
    "addr:housenumber":"506",
    "addr:postcode":"55414",
    "addr:street":"7Th St Se",
    "iso:country":"US",
    "sg:address":"506 7th St SE",
    "sg:city":"Minneapolis",
    "sg:classifiers":[
        {
            "category":"Building & Trades",
            "subcategory":"Locksmith",
            "type":"Services"
        }
    ],
    "sg:phone":"+1 612 676 0222",
    "sg:postcode":"55414",
    "sg:province":"MN",
    "sg:tags":[
        "locksmiths-commercial",
        "industrial",
        "lock"
    ],
    "wof:name":"All Auto Locksmiths",
    "wof:placetype":"venue"
},
  "geometry": {"coordinates":[-93.245842,44.988373],"type":"Point"}
}