{
  "type": "Feature",
  "properties": {
    "iso:country":"US",
    "sg:address":"4001 Hiawatha Ave",
    "sg:city":"Minneapolis",
    "sg:classifiers":[
        {
            "category":"Shopping",
            "subcategory":"Gifts & Souvenirs",
            "type":"Retail Goods"
        },
        {
            "category":"Manufacturing",
            "subcategory":"Retail Goods",
            "type":"Manufacturing & Wholesale Goods"
        }
    ],
    "sg:phone":"+1 612 724 7244",
    "sg:postcode":"55406",
    "sg:province":"MN",
    "sg:tags":[
        "shop",
        "giftware's-wholesale",
        "manufacturer"
    ],
    "sg:website":"http://www.iacinternational.com",
    "wof:name":"Iac International",
    "wof:placetype":"venue"
},
  "geometry": {"coordinates":[-93.226067,44.9305],"type":"Point"}
}