{
  "type": "Feature",
  "properties": {
    "addr:full":"200 Main St E Sleepy Eye MN 56085",
    "addr:housenumber":"200",
    "addr:postcode":"56085",
    "addr:street":"Main St E",
    "iso:country":"US",
    "sg:address":"200 Main St E",
    "sg:city":"Sleepy Eye",
    "sg:classifiers":[
        {
            "category":"Food & Beverages",
            "subcategory":"Liquor & Beverages",
            "type":"Retail Goods"
        }
    ],
    "sg:phone":"+1 507 794 4040",
    "sg:postcode":"56085",
    "sg:province":"MN",
    "wof:name":"Sleepy Eye Off Sale",
    "wof:placetype":"venue"
},
  "geometry": {"coordinates":[-94.72138099999999,44.29727],"type":"Point"}
}