{
  "type": "Feature",
  "properties": {
    "addr:full":"200 Central Ave Osseo MN 55369",
    "addr:housenumber":"200",
    "addr:postcode":"55369",
    "addr:street":"Central Ave",
    "iso:country":"US",
    "sg:address":"200 Central Ave",
    "sg:city":"Osseo",
    "sg:classifiers":[
        {
            "category":"Shopping",
            "subcategory":"Clothing, Apparel, & Fashions",
            "type":"Retail Goods"
        },
        {
            "category":"Wholesale",
            "subcategory":"Apparel",
            "type":"Manufacturing & Wholesale Goods"
        },
        {
            "category":"Professional",
            "subcategory":"Printing & Photocopies",
            "type":"Services"
        }
    ],
    "sg:phone":"+1 763 424 6556",
    "sg:postcode":"55369",
    "sg:province":"MN",
    "sg:tags":[
        "screen",
        "sportswear-wholesale",
        "merchandise",
        "racing",
        "sportswear",
        "manufacturer"
    ],
    "wof:name":"Design Wear Apparel, Inc.",
    "wof:placetype":"venue"
},
  "geometry": {"coordinates":[-93.402168,45.118179],"type":"Point"}
}