{
  "type": "Feature",
  "properties": {
    "addr:full":"29458 Co Rd 19 Glenwood MN 56334",
    "addr:housenumber":"29458;19",
    "addr:postcode":"56334",
    "addr:street":"Co Rd",
    "iso:country":"US",
    "sg:address":"29458 Co Rd 19",
    "sg:city":"Glenwood",
    "sg:phone":"+1 320 634 3807",
    "sg:postcode":"56334",
    "sg:province":"MN",
    "sg:tags":[
        "farm",
        "grain",
        "cash"
    ],
    "wof:name":"Gary Gravely",
    "wof:placetype":"venue"
},
  "geometry": {"coordinates":[-95.392769,45.48092],"type":"Point"}
}