{
  "type": "Feature",
  "properties": {
    "addr:full":"633 N Wabasha St Plainview MN 55964",
    "addr:housenumber":"633",
    "addr:postcode":"55964",
    "addr:street":"N Wabasha St",
    "iso:country":"US",
    "sg:address":"633 N Wabasha St",
    "sg:city":"Plainview",
    "sg:classifiers":[
        {
            "category":"Manufacturing",
            "subcategory":"Retail Goods",
            "type":"Manufacturing & Wholesale Goods"
        }
    ],
    "sg:phone":"+1 507 534 1230",
    "sg:postcode":"55964",
    "sg:province":"MN",
    "sg:tags":[
        "assembly",
        "fabricating"
    ],
    "wof:name":"Plainview Assembly Of God",
    "wof:placetype":"venue"
},
  "geometry": {"coordinates":[-92.16554600000001,44.170808],"type":"Point"}
}