{
  "type": "Feature",
  "properties": {
    "iso:country":"US",
    "sg:address":"13903 Leaf River Rd",
    "sg:city":"Wadena",
    "sg:classifiers":[
        {
            "category":"Building & Trades",
            "subcategory":"Plumbing",
            "type":"Services"
        }
    ],
    "sg:phone":"+1 218 631 1111",
    "sg:postcode":"56482",
    "sg:province":"MN",
    "sg:tags":[
        "plumbing",
        "contractor"
    ],
    "wof:name":"Silvers Plumbing & Heating",
    "wof:placetype":"venue"
},
  "geometry": {"coordinates":[-95.073517,46.487061],"type":"Point"}
}