{
  "type": "Feature",
  "properties": {
    "iso:country":"US",
    "sg:address":"33395 370 St",
    "sg:city":"Ogema",
    "sg:classifiers":[
        {
            "category":"Building & Trades",
            "subcategory":"Construction",
            "type":"Services"
        }
    ],
    "sg:phone":"+1 218 983 3821",
    "sg:postcode":"56569",
    "sg:province":"MN",
    "sg:tags":[
        "excavation",
        "contractor"
    ],
    "wof:name":"Bobs Excavation",
    "wof:placetype":"venue"
},
  "geometry": {"coordinates":[-95.68424,47.107212],"type":"Point"}
}