{
  "type": "Feature",
  "properties": {
    "addr:full":"900 W 128th St Burnsville MN 55337",
    "addr:housenumber":"900",
    "addr:postcode":"55337",
    "addr:street":"W 128Th St",
    "iso:country":"US",
    "sg:address":"900 W 128th St",
    "sg:city":"Burnsville",
    "sg:classifiers":[
        {
            "category":"Banks & Credit Unions",
            "subcategory":"Financial Services",
            "type":"Services"
        }
    ],
    "sg:phone":"+1 952 890 2446",
    "sg:postcode":"55337",
    "sg:province":"MN",
    "sg:tags":[
        "broker",
        "mortgage"
    ],
    "wof:name":"Diversified Mortgage",
    "wof:placetype":"venue"
},
  "geometry": {"coordinates":[-93.30059799999999,44.762299],"type":"Point"}
}