{
  "type": "Feature",
  "properties": {
    "addr:full":"33534 State Hwy 68 Redwood Falls MN 56283",
    "addr:housenumber":"33534",
    "addr:postcode":"56283",
    "addr:street":"State Hwy 68",
    "iso:country":"US",
    "sg:address":"33534 State Hwy 68",
    "sg:city":"Redwood Falls",
    "sg:phone":"+1 507 644 2489",
    "sg:postcode":"56283",
    "sg:province":"MN",
    "sg:tags":[
        "farm",
        "field",
        "crop"
    ],
    "wof:name":"Parker John",
    "wof:placetype":"venue"
},
  "geometry": {"coordinates":[-95.126722,44.412735],"type":"Point"}
}