{
  "type": "Feature",
  "properties": {
    "iso:country":"US",
    "sg:address":"20339 600th Ave",
    "sg:city":"Litchfield",
    "sg:classifiers":[
        {
            "category":"Farming",
            "subcategory":"Farm",
            "type":"Manufacturing & Wholesale Goods"
        }
    ],
    "sg:phone":"+1 320 693 6642",
    "sg:postcode":"55355",
    "sg:province":"MN",
    "sg:tags":[
        "crop",
        "general"
    ],
    "wof:name":"Nygaard Farm Roy",
    "wof:placetype":"venue"
},
  "geometry": {"coordinates":[-94.56372,45.030403],"type":"Point"}
}