{
  "type": "Feature",
  "properties": {
    "iso:country":"US",
    "sg:address":"3107 Sibley Memorial Hwy",
    "sg:city":"Eagan",
    "sg:classifiers":[
        {
            "category":"Manufacturing",
            "subcategory":"Tools & Machinery",
            "type":"Manufacturing & Wholesale Goods"
        }
    ],
    "sg:phone":"+1 651 688 8827",
    "sg:postcode":"55121",
    "sg:province":"MN",
    "sg:tags":[
        "water",
        "heater",
        "mfg"
    ],
    "sg:website":"www.marathonheaters.com",
    "wof:name":"Water Heater Innovations Inc",
    "wof:placetype":"venue"
},
  "geometry": {"coordinates":[-93.184606,44.84504],"type":"Point"}
}