{
  "type": "Feature",
  "properties": {
    "addr:full":"420 N 5th St Ste 312 Minneapolis MN 55401",
    "addr:housenumber":"420",
    "addr:postcode":"55401",
    "addr:street":"N 5Th St Ste 312",
    "iso:country":"US",
    "sg:address":"420 N 5th St Ste 312",
    "sg:city":"Minneapolis",
    "sg:classifiers":[
        {
            "category":"Community Center",
            "type":"Public Place"
        },
        {
            "category":"Arts & Performance",
            "subcategory":"Theater",
            "type":"Entertainment"
        }
    ],
    "sg:phone":"+1 612 332 6858",
    "sg:postcode":"55401",
    "sg:province":"MN",
    "sg:tags":[
        "theatrical",
        "agency",
        "casting",
        "director"
    ],
    "wof:name":"Babs Casting",
    "wof:placetype":"venue"
},
  "geometry": {"coordinates":[-93.277576,44.983211],"type":"Point"}
}