{
  "type": "Feature",
  "properties": {
    "iso:country":"US",
    "sg:address":"9731 Meadowlark Ln",
    "sg:city":"Chanhassen",
    "sg:classifiers":[
        {
            "category":"Building & Trades",
            "subcategory":"Construction",
            "type":"Services"
        }
    ],
    "sg:phone":"+1 952 445 8524",
    "sg:postcode":"55317",
    "sg:province":"MN",
    "sg:tags":[
        "house"
    ],
    "wof:name":"Neil Klingelhutz Cnstr Inc",
    "wof:placetype":"venue"
},
  "geometry": {"coordinates":[-93.523635,44.827844],"type":"Point"}
}