{
  "type": "Feature",
  "properties": {
    "iso:country":"US",
    "sg:address":"309 Holden Ave",
    "sg:city":"Henning",
    "sg:classifiers":[
        {
            "category":"Organizations",
            "subcategory":"Religious Organization",
            "type":"Services"
        }
    ],
    "sg:phone":"+1 218 583 2161",
    "sg:postcode":"56551",
    "sg:province":"MN",
    "sg:tags":[
        "church"
    ],
    "sg:website":"www.fellowshipofgrace.us",
    "wof:name":"First Baptist Church",
    "wof:placetype":"venue"
},
  "geometry": {"coordinates":[-95.447372,46.324072],"type":"Point"}
}