{
  "type": "Feature",
  "properties": {
    "addr:full":"1301 E College Dr Marshall MN 56258",
    "addr:housenumber":"1301",
    "addr:postcode":"56258",
    "addr:street":"E College Dr",
    "iso:country":"US",
    "sg:address":"1301 E College Dr",
    "sg:city":"Marshall",
    "sg:classifiers":[
        {
            "category":"Building & Trades",
            "subcategory":"Cleaning & Sanitation",
            "type":"Services"
        }
    ],
    "sg:phone":"+1 507 532 3552",
    "sg:postcode":"56258",
    "sg:province":"MN",
    "sg:tags":[
        "janitor"
    ],
    "wof:name":"Quality Cleaning Co",
    "wof:placetype":"venue"
},
  "geometry": {"coordinates":[-95.7692,44.450379],"type":"Point"}
}