{
  "type": "Feature",
  "properties": {
    "addr:full":"15887 Dakota Shores Dr Park Rapids MN 56470",
    "addr:housenumber":"15887",
    "addr:postcode":"56470",
    "addr:street":"Dakota Shores Dr",
    "iso:country":"US",
    "sg:address":"15887 Dakota Shores Dr",
    "sg:city":"Park Rapids",
    "sg:classifiers":[
        {
            "category":"Manufacturing",
            "subcategory":"Glass & Minerals",
            "type":"Manufacturing & Wholesale Goods"
        }
    ],
    "sg:phone":"+1 218 732 8068",
    "sg:postcode":"56470",
    "sg:province":"MN",
    "sg:tags":[
        "prod",
        "made"
    ],
    "wof:name":"W Heinzen Co",
    "wof:placetype":"venue"
},
  "geometry": {"coordinates":[-94.992615,46.885535],"type":"Point"}
}