{
  "type": "Feature",
  "properties": {
    "addr:full":"2245 Kessler Ct Chaska MN 55318",
    "addr:housenumber":"2245",
    "addr:postcode":"55318",
    "addr:street":"Kessler Ct",
    "iso:country":"US",
    "sg:address":"2245 Kessler Ct",
    "sg:city":"Chaska",
    "sg:classifiers":[
        {
            "category":"Restaurant",
            "type":"Food & Drink"
        }
    ],
    "sg:phone":"+1 952 448 2059",
    "sg:postcode":"55318",
    "sg:province":"MN",
    "sg:tags":[
        "photofinishing",
        "eating",
        "laboratory"
    ],
    "wof:name":"Photo Evance USA",
    "wof:placetype":"venue"
},
  "geometry": {"coordinates":[-93.622196,44.816653],"type":"Point"}
}