{
  "type": "Feature",
  "properties": {
    "addr:full":"4869 Miller Trunk Hwy Duluth MN 55811",
    "addr:housenumber":"4869",
    "addr:postcode":"55811",
    "addr:street":"Miller Trunk Hwy",
    "iso:country":"US",
    "sg:address":"4869 Miller Trunk Hwy",
    "sg:city":"Duluth",
    "sg:classifiers":[
        {
            "category":"Building & Trades",
            "subcategory":"Construction",
            "type":"Services"
        }
    ],
    "sg:phone":"+1 218 722 1662",
    "sg:postcode":"55811",
    "sg:province":"MN",
    "sg:tags":[
        "concrete",
        "contractor"
    ],
    "wof:name":"Hovland Inc",
    "wof:placetype":"venue"
},
  "geometry": {"coordinates":[-92.19219,46.825545],"type":"Point"}
}