{
  "type": "Feature",
  "properties": {
    "iso:country":"US",
    "sg:address":"2221 Middle School Ave NW",
    "sg:city":"Bemidji",
    "sg:classifiers":[
        {
            "category":"Recreation",
            "type":"Entertainment"
        }
    ],
    "sg:phone":"+1 218 444 2952",
    "sg:postcode":"56601",
    "sg:province":"MN",
    "sg:tags":[
        "club",
        "baseball"
    ],
    "wof:name":"Bemidji Youth League Baseball",
    "wof:placetype":"venue"
},
  "geometry": {"coordinates":[-94.912166,47.485892],"type":"Point"}
}