{
  "type": "Feature",
  "properties": {
    "addr:full":"31996 742nd Ave South Haven MN 55382",
    "addr:housenumber":"31996",
    "addr:postcode":"55382",
    "addr:street":"742Nd Ave",
    "iso:country":"US",
    "sg:address":"31996 742nd Ave",
    "sg:city":"South Haven",
    "sg:classifiers":[
        {
            "category":"Personal",
            "type":"Services"
        }
    ],
    "sg:phone":"+1 320 398 2525",
    "sg:postcode":"55382",
    "sg:province":"MN",
    "sg:tags":[
        "therapist",
        "massage"
    ],
    "wof:name":"Holiday Beach Massage",
    "wof:placetype":"venue"
},
  "geometry": {"coordinates":[-94.272284,45.209916],"type":"Point"}
}