{
  "type": "Feature",
  "properties": {
    "addr:full":"14546 Dellwood Dr Baxter MN 56425",
    "addr:housenumber":"14546",
    "addr:postcode":"56425",
    "addr:street":"Dellwood Dr",
    "iso:country":"US",
    "sg:address":"14546 Dellwood Dr",
    "sg:city":"Baxter",
    "sg:classifiers":[
        {
            "category":"Utilities",
            "subcategory":"Mobile Phone",
            "type":"Services"
        },
        {
            "category":"Shopping",
            "subcategory":"Mobile Phones",
            "type":"Retail Goods"
        },
        {
            "category":"Utilities",
            "subcategory":"Telephone",
            "type":"Services"
        },
        {
            "category":"Professional",
            "subcategory":"Computer Services",
            "type":"Services"
        }
    ],
    "sg:phone":"+1 218 828 3535",
    "sg:postcode":"56425",
    "sg:province":"MN",
    "sg:tags":[
        "telecommunication",
        "supply",
        "communication",
        "system",
        "wireless",
        "equipment",
        "cellular"
    ],
    "sg:website":"http://clickserve.dartsearch.net/link/click?lid=43000000308049899",
    "wof:name":"T-Mobile",
    "wof:placetype":"venue"
},
  "geometry": {"coordinates":[-94.24365299999999,46.361913],"type":"Point"}
}