{
  "type": "Feature",
  "properties": {
    "iso:country":"US",
    "sg:address":"2700 Rice St",
    "sg:city":"St Paul",
    "sg:classifiers":[
        {
            "category":"Insurance",
            "subcategory":"Insurance Agent",
            "type":"Services"
        }
    ],
    "sg:phone":"+1 651 483 5303",
    "sg:postcode":"55113",
    "sg:province":"MN",
    "wof:name":"Haram Insurance",
    "wof:placetype":"venue"
},
  "geometry": {"coordinates":[-93.106027,45.021678],"type":"Point"}
}