{
  "type": "Feature",
  "properties": {
    "addr:full":"333 Main St N Stillwater MN 55082",
    "addr:housenumber":"333",
    "addr:postcode":"55082",
    "addr:street":"Main St N",
    "iso:country":"US",
    "sg:address":"333 Main St N",
    "sg:city":"Stillwater",
    "sg:classifiers":[
        {
            "category":"Health Services",
            "subcategory":"Doctor",
            "type":"Services"
        }
    ],
    "sg:phone":"+1 651 439 6125",
    "sg:postcode":"55082",
    "sg:province":"MN",
    "sg:tags":[
        "dentist"
    ],
    "wof:name":"John F Reardon DDS",
    "wof:placetype":"venue"
},
  "geometry": {"coordinates":[-92.806979,45.058846],"type":"Point"}
}