{
  "type": "Feature",
  "properties": {
    "iso:country":"US",
    "sg:address":"612 N Victory Dr",
    "sg:city":"Mankato",
    "sg:classifiers":[
        {
            "category":"Insurance",
            "subcategory":"Insurance Agent",
            "type":"Services"
        },
        {
            "category":"Insurance",
            "subcategory":"Hazard Insurance",
            "type":"Services"
        },
        {
            "category":"Insurance",
            "subcategory":"Title Insurance",
            "type":"Services"
        },
        {
            "category":"Insurance",
            "subcategory":"Life Insurance",
            "type":"Services"
        }
    ],
    "sg:phone":"+1 507 385 1855",
    "sg:postcode":"56001",
    "sg:province":"MN",
    "sg:tags":[
        "business",
        "auto",
        "commercial",
        "homeowner",
        "motorcycle",
        "renter"
    ],
    "wof:name":"Allstate Insurance Company - David Stougaard",
    "wof:placetype":"venue"
},
  "geometry": {"coordinates":[-93.969595,44.167017],"type":"Point"}
}