{
  "type": "Feature",
  "properties": {
    "addr:full":"671 Co Rd 18 Kellogg MN 55945",
    "addr:housenumber":"671;18",
    "addr:postcode":"55945",
    "addr:street":"Co Rd",
    "iso:country":"US",
    "sg:address":"671 Co Rd 18",
    "sg:city":"Kellogg",
    "sg:classifiers":[
        {
            "category":"Building & Trades",
            "subcategory":"Electrical",
            "type":"Services"
        }
    ],
    "sg:phone":"+1 507 767 4572",
    "sg:postcode":"55945",
    "sg:province":"MN",
    "sg:tags":[
        "electrical",
        "electric",
        "contractor"
    ],
    "wof:name":"Hall Electric Inc",
    "wof:placetype":"venue"
},
  "geometry": {"coordinates":[-91.995531,44.303078],"type":"Point"}
}