{
  "type": "Feature",
  "properties": {
    "addr:full":"204 N Litchfield Ave Litchfield MN 55355",
    "addr:housenumber":"204",
    "addr:postcode":"55355",
    "addr:street":"N Litchfield Ave",
    "iso:country":"US",
    "sg:address":"204 N Litchfield Ave",
    "sg:city":"Litchfield",
    "sg:classifiers":[
        {
            "category":"Autos & Motor Vehicles",
            "subcategory":"Automobile Sales",
            "type":"Retail Goods"
        }
    ],
    "sg:phone":"+1 320 235 0826",
    "sg:postcode":"55355",
    "sg:province":"MN",
    "wof:name":"Mills Jeep Nissan",
    "wof:placetype":"venue"
},
  "geometry": {"coordinates":[-94.520959,45.128618],"type":"Point"}
}