{
  "type": "Feature",
  "properties": {
    "addr:full":"825 N Central St Warren MN 56762",
    "addr:housenumber":"825",
    "addr:postcode":"56762",
    "addr:street":"N Central St",
    "iso:country":"US",
    "sg:address":"825 N Central St",
    "sg:city":"Warren",
    "sg:classifiers":[
        {
            "category":"Social Services",
            "subcategory":"Child Care",
            "type":"Services"
        }
    ],
    "sg:phone":"+1 218 201 1540",
    "sg:postcode":"56762",
    "sg:province":"MN",
    "sg:tags":[
        "nursery",
        "day"
    ],
    "wof:name":"Lil Bear Child Care",
    "wof:placetype":"venue"
},
  "geometry": {"coordinates":[-96.780006,48.199811],"type":"Point"}
}