{
  "type": "Feature",
  "properties": {
    "iso:country":"US",
    "sg:address":"3137 Oakland Ave S",
    "sg:city":"Minneapolis",
    "sg:classifiers":[
        {
            "category":"Wholesale",
            "subcategory":"Durable Goods & Equipment",
            "type":"Manufacturing & Wholesale Goods"
        }
    ],
    "sg:phone":"+1 612 822 1321",
    "sg:postcode":"55407",
    "sg:province":"MN",
    "wof:name":"Auro Brokers",
    "wof:placetype":"venue"
},
  "geometry": {"coordinates":[-93.26638800000001,44.945608],"type":"Point"}
}