{
  "type": "Feature",
  "properties": {
    "addr:full":"12001 175th St W Lakeville MN 55044",
    "addr:housenumber":"12001",
    "addr:postcode":"55044",
    "addr:street":"175Th St W",
    "iso:country":"US",
    "sg:address":"12001 175th St W",
    "sg:city":"Lakeville",
    "sg:classifiers":[
        {
            "category":"Professional",
            "subcategory":"Business Services",
            "type":"Services"
        }
    ],
    "sg:phone":"+1 952 892 1252",
    "sg:postcode":"55044",
    "sg:province":"MN",
    "wof:name":"Wech Enterprises",
    "wof:placetype":"venue"
},
  "geometry": {"coordinates":[-93.309257,44.695046],"type":"Point"}
}