{
  "type": "Feature",
  "properties": {
    "iso:country":"US",
    "sg:address":"25145 Durant St NE",
    "sg:city":"Isanti",
    "sg:classifiers":[
        {
            "category":"Building & Trades",
            "subcategory":"Construction",
            "type":"Services"
        }
    ],
    "sg:phone":"+1 763 444 6328",
    "sg:postcode":"55040",
    "sg:province":"MN",
    "sg:tags":[
        "house"
    ],
    "wof:name":"Woodsman Construction",
    "wof:placetype":"venue"
},
  "geometry": {"coordinates":[-93.163048,45.424349],"type":"Point"}
}