{
  "type": "Feature",
  "properties": {
    "addr:full":"300 N Broadway Ave Spring Valley MN 55975",
    "addr:housenumber":"300",
    "addr:postcode":"55975",
    "addr:street":"N Broadway Ave",
    "iso:country":"US",
    "sg:address":"300 N Broadway Ave",
    "sg:city":"Spring Valley",
    "sg:classifiers":[
        {
            "category":"Building & Trades",
            "subcategory":"Plumbing",
            "type":"Services"
        }
    ],
    "sg:phone":"+1 507 346 2822",
    "sg:postcode":"55975",
    "sg:province":"MN",
    "sg:tags":[
        "plumbing",
        "contractor"
    ],
    "wof:name":"Stender Enterprises",
    "wof:placetype":"venue"
},
  "geometry": {"coordinates":[-92.39088,43.68916],"type":"Point"}
}