{
  "type": "Feature",
  "properties": {
    "addr:full":"212 2nd St NW Waseca MN 56093",
    "addr:housenumber":"212",
    "addr:postcode":"56093",
    "addr:street":"2Nd St Nw",
    "iso:country":"US",
    "sg:address":"212 2nd St NW",
    "sg:city":"Waseca",
    "sg:classifiers":[
        {
            "category":"Retail",
            "subcategory":"Car Wash",
            "type":"Services"
        }
    ],
    "sg:phone":"+1 507 835 7374",
    "sg:postcode":"56093",
    "sg:province":"MN",
    "sg:tags":[
        "polishing",
        "washing"
    ],
    "wof:name":"Neste's Car Care Ctr",
    "wof:placetype":"venue"
},
  "geometry": {"coordinates":[-93.50873300000001,44.079393],"type":"Point"}
}