{
  "type": "Feature",
  "properties": {
    "addr:full":"698 Co Rd B W Roseville MN 55113",
    "addr:housenumber":"698",
    "addr:postcode":"55113",
    "addr:street":"Co Rd",
    "iso:country":"US",
    "sg:address":"698 Co Rd B W",
    "sg:city":"Roseville",
    "sg:classifiers":[
        {
            "category":"Retail",
            "subcategory":"Laundry & Dry Cleaning",
            "type":"Services"
        }
    ],
    "sg:phone":"+1 651 488 0387",
    "sg:postcode":"55113",
    "sg:province":"MN",
    "sg:tags":[
        "drycleaning",
        "plant",
        "cleaners"
    ],
    "wof:name":"One Hour Martinizing",
    "wof:placetype":"venue"
},
  "geometry": {"coordinates":[-93.12885799999999,45.006097],"type":"Point"}
}