{
  "type": "Feature",
  "properties": {
    "addr:full":"1791 Mary Ln North Mankato MN 56003",
    "addr:housenumber":"1791",
    "addr:postcode":"56003",
    "addr:street":"Mary Ln North",
    "iso:country":"US",
    "sg:address":"1791 Mary Ln",
    "sg:city":"North Mankato",
    "sg:classifiers":[
        {
            "category":"Banks & Credit Unions",
            "subcategory":"Bank",
            "type":"Services"
        }
    ],
    "sg:phone":"+1 507 386 7177",
    "sg:postcode":"56003",
    "sg:province":"MN",
    "wof:name":"Cobank",
    "wof:placetype":"venue"
},
  "geometry": {"coordinates":[-94.02363200000001,44.178644],"type":"Point"}
}