{
  "type": "Feature",
  "properties": {
    "iso:country":"US",
    "sg:address":"23677 Arcade Loop",
    "sg:city":"Menahga",
    "sg:classifiers":[
        {
            "category":"Manufacturing",
            "subcategory":"Buildings",
            "type":"Manufacturing & Wholesale Goods"
        },
        {
            "category":"Building & Trades",
            "subcategory":"Construction",
            "type":"Services"
        }
    ],
    "sg:phone":"+1 218 732 8073",
    "sg:postcode":"56464",
    "sg:province":"MN",
    "sg:tags":[
        "home",
        "builder",
        "contractor"
    ],
    "wof:name":"Hed Const",
    "wof:placetype":"venue"
},
  "geometry": {"coordinates":[-94.877414,46.823471],"type":"Point"}
}