{
  "type": "Feature",
  "properties": {
    "iso:country":"US",
    "sg:address":"612 11th Ave S",
    "sg:city":"Hopkins",
    "sg:classifiers":[
        {
            "category":"Retail",
            "subcategory":"Laundry & Dry Cleaning",
            "type":"Services"
        }
    ],
    "sg:phone":"+1 952 935 5055",
    "sg:postcode":"55343",
    "sg:province":"MN",
    "sg:tags":[
        "plant"
    ],
    "wof:name":"Town & Country Cleaners LTD",
    "wof:placetype":"venue"
},
  "geometry": {"coordinates":[-93.41435300000001,44.915092],"type":"Point"}
}