{
  "type": "Feature",
  "properties": {
    "addr:full":"675 Bolton Ave SW Buffalo MN 55313",
    "addr:housenumber":"675",
    "addr:postcode":"55313",
    "addr:street":"Bolton Ave Sw",
    "iso:country":"US",
    "sg:address":"675 Bolton Ave SW",
    "sg:city":"Buffalo",
    "sg:classifiers":[
        {
            "category":"Utilities",
            "subcategory":"Refuse",
            "type":"Services"
        }
    ],
    "sg:phone":"+1 763 682 3120",
    "sg:postcode":"55313",
    "sg:province":"MN",
    "sg:tags":[
        "system"
    ],
    "wof:name":"Can Man II Recycling",
    "wof:placetype":"venue"
},
  "geometry": {"coordinates":[-93.925939,45.142271],"type":"Point"}
}