{
  "type": "Feature",
  "properties": {
    "iso:country":"US",
    "sg:address":"3225 Skycroft Dr",
    "sg:city":"Minneapolis",
    "sg:classifiers":[
        {
            "category":"Social Services",
            "subcategory":"Retirement Home",
            "type":"Services"
        }
    ],
    "sg:phone":"+1 612 788 1181",
    "sg:postcode":"55418",
    "sg:province":"MN",
    "sg:tags":[
        "convalescent",
        "nursing"
    ],
    "wof:name":"Wingspan",
    "wof:placetype":"venue"
},
  "geometry": {"coordinates":[-93.211748,45.026434],"type":"Point"}
}