{
  "type": "Feature",
  "properties": {
    "iso:country":"US",
    "sg:address":"4345 Buckingham Ct",
    "sg:city":"St Paul",
    "sg:classifiers":[
        {
            "category":"Building & Trades",
            "subcategory":"Cleaning & Sanitation",
            "type":"Services"
        }
    ],
    "sg:phone":"+1 651 407 1339",
    "sg:postcode":"55127",
    "sg:province":"MN",
    "sg:tags":[
        "janitor"
    ],
    "wof:name":"No 1 Dustbusters",
    "wof:placetype":"venue"
},
  "geometry": {"coordinates":[-93.058165,45.072937],"type":"Point"}
}