{
  "type": "Feature",
  "properties": {
    "iso:country":"US",
    "sg:address":"10500 44th St",
    "sg:city":"Clear Lake",
    "sg:classifiers":[
        {
            "category":"Building & Trades",
            "subcategory":"Construction",
            "type":"Services"
        }
    ],
    "sg:phone":"+1 320 743 2146",
    "sg:postcode":"55319",
    "sg:province":"MN",
    "sg:tags":[
        "house"
    ],
    "wof:name":"Sandberg Construction Co",
    "wof:placetype":"venue"
},
  "geometry": {"coordinates":[-93.94323199999999,45.505807],"type":"Point"}
}