{
  "type": "Feature",
  "properties": {
    "iso:country":"US",
    "sg:address":"341 William Ave E",
    "sg:city":"Dassel",
    "sg:classifiers":[
        {
            "category":"Social Services",
            "subcategory":"Child Care",
            "type":"Services"
        }
    ],
    "sg:phone":"+1 320 275 4911",
    "sg:postcode":"55325",
    "sg:province":"MN",
    "wof:name":"Stay N' Play",
    "wof:placetype":"venue"
},
  "geometry": {"coordinates":[-94.302385,45.082975],"type":"Point"}
}