{
  "type": "Feature",
  "properties": {
    "iso:country":"US",
    "sg:address":"950 State Hwy 10",
    "sg:city":"Minneapolis",
    "sg:classifiers":[
        {
            "category":"Building & Trades",
            "subcategory":"Construction",
            "type":"Services"
        }
    ],
    "sg:phone":"+1 763 717 1246",
    "sg:postcode":"55432",
    "sg:province":"MN",
    "sg:tags":[
        "site",
        "clean"
    ],
    "wof:name":"Complete Clean",
    "wof:placetype":"venue"
},
  "geometry": {"coordinates":[-93.24567500000001,45.122816],"type":"Point"}
}