{
  "type": "Feature",
  "properties": {
    "addr:full":"7740 Flying Cloud Dr Eden Prairie MN 55344",
    "addr:housenumber":"7740",
    "addr:postcode":"55344",
    "addr:street":"Flying Cloud Dr",
    "iso:country":"US",
    "sg:address":"7740 Flying Cloud Dr",
    "sg:city":"Eden Prairie",
    "sg:classifiers":[
        {
            "category":"Travel",
            "subcategory":"Hotels & Motels",
            "type":"Entertainment"
        }
    ],
    "sg:phone":"+1 952 942 9000",
    "sg:postcode":"55344",
    "sg:province":"MN",
    "sg:tags":[
        "operation"
    ],
    "sg:website":"www.hamptoninn.com",
    "wof:name":"Hampton Inn",
    "wof:placetype":"venue"
},
  "geometry": {"coordinates":[-93.42205199999999,44.864747],"type":"Point"}
}