{
  "type": "Feature",
  "properties": {
    "addr:full":"402 Red River Ave N Cold Spring MN 56320",
    "addr:housenumber":"402",
    "addr:postcode":"56320",
    "addr:street":"Red River Ave N",
    "iso:country":"US",
    "sg:address":"402 Red River Ave N",
    "sg:city":"Cold Spring",
    "sg:classifiers":[
        {
            "category":"Health Services",
            "subcategory":"Doctor",
            "type":"Services"
        }
    ],
    "sg:phone":"+1 320 685 8641",
    "sg:postcode":"56320",
    "sg:province":"MN",
    "sg:tags":[
        "physician",
        "clinic",
        "practice",
        "surgeon",
        "family"
    ],
    "wof:name":"Cold Spring Medical Clinic",
    "wof:placetype":"venue"
},
  "geometry": {"coordinates":[-94.428197,45.460939],"type":"Point"}
}