{
  "type": "Feature",
  "properties": {
    "iso:country":"US",
    "sg:address":"700 N Chestnut St",
    "sg:city":"Chaska",
    "sg:classifiers":[
        {
            "category":"Shopping",
            "subcategory":"Bicycles & Sporting Goods",
            "type":"Retail Goods"
        }
    ],
    "sg:phone":"+1 952 448 9911",
    "sg:postcode":"55318",
    "sg:province":"MN",
    "sg:tags":[
        "bike"
    ],
    "wof:name":"Brickyard Bikes Boards & Skis",
    "wof:placetype":"venue"
},
  "geometry": {"coordinates":[-93.601917,44.79075],"type":"Point"}
}