{
  "type": "Feature",
  "properties": {
    "addr:full":"3025 310th Ave Brook Park MN 55007",
    "addr:housenumber":"3025",
    "addr:postcode":"55007",
    "addr:street":"310Th Ave",
    "iso:country":"US",
    "sg:address":"3025 310th Ave",
    "sg:city":"Brook Park",
    "sg:classifiers":[
        {
            "category":"Utilities",
            "subcategory":"Refuse",
            "type":"Services"
        }
    ],
    "sg:phone":"+1 320 384 6664",
    "sg:postcode":"55007",
    "sg:province":"MN",
    "sg:tags":[
        "system"
    ],
    "wof:name":"Rons Roll-Off Service",
    "wof:placetype":"venue"
},
  "geometry": {"coordinates":[-93.082402,46.039399],"type":"Point"}
}