{
  "type": "Feature",
  "properties": {
    "addr:full":"370 Maple Island Rd Burnsville MN 55306",
    "addr:housenumber":"370",
    "addr:postcode":"55306",
    "addr:street":"Maple Island Rd",
    "iso:country":"US",
    "sg:address":"370 Maple Island Rd",
    "sg:city":"Burnsville",
    "sg:classifiers":[
        {
            "category":"Professional",
            "subcategory":"Advertising",
            "type":"Services"
        }
    ],
    "sg:phone":"+1 952 898 2164",
    "sg:postcode":"55306",
    "sg:province":"MN",
    "sg:tags":[
        "counselor"
    ],
    "wof:name":"C Spot Create",
    "wof:placetype":"venue"
},
  "geometry": {"coordinates":[-93.27075499999999,44.718852],"type":"Point"}
}