{
  "type": "Feature",
  "properties": {
    "addr:full":"1630 New Brighton Blvd Minneapolis MN 55413",
    "addr:housenumber":"1630",
    "addr:postcode":"55413",
    "addr:street":"New Brighton Blvd",
    "iso:country":"US",
    "sg:address":"1630 New Brighton Blvd",
    "sg:city":"Minneapolis",
    "sg:classifiers":[
        {
            "category":"Shopping",
            "subcategory":"Clothing, Apparel, & Fashions",
            "type":"Retail Goods"
        }
    ],
    "sg:phone":"+1 612 781 9025",
    "sg:postcode":"55413",
    "sg:province":"MN",
    "sg:tags":[
        "personal",
        "costume"
    ],
    "sg:website":"www.partycity.com",
    "wof:name":"Party City",
    "wof:placetype":"venue"
},
  "geometry": {"coordinates":[-93.228104,45.0042],"type":"Point"}
}