{
  "type": "Feature",
  "properties": {
    "iso:country":"US",
    "sg:address":"1785 Howard Ave",
    "sg:city":"Maple Plain",
    "sg:classifiers":[
        {
            "category":"Professional",
            "subcategory":"Business Services",
            "type":"Services"
        }
    ],
    "sg:phone":"+1 763 479 2787",
    "sg:postcode":"55359",
    "sg:province":"MN",
    "sg:tags":[
        "devices",
        "mfg"
    ],
    "wof:name":"Sunset Tool",
    "wof:placetype":"venue"
},
  "geometry": {"coordinates":[-93.649886,45.008914],"type":"Point"}
}