{
  "type": "Feature",
  "properties": {
    "iso:country":"US",
    "sg:address":"750 2nd St NE",
    "sg:city":"Hopkins",
    "sg:classifiers":[
        {
            "category":"Professional",
            "subcategory":"Computer Services",
            "type":"Services"
        }
    ],
    "sg:phone":"+1 952 939 6037",
    "sg:postcode":"55343",
    "sg:province":"MN",
    "sg:tags":[
        "development",
        "software"
    ],
    "wof:name":"Entreon Corporation",
    "wof:placetype":"venue"
},
  "geometry": {"coordinates":[-93.392087,44.92775],"type":"Point"}
}