{
  "type": "Feature",
  "properties": {
    "addr:full":"11967 New Prague Blvd New Prague MN 56071",
    "addr:housenumber":"11967",
    "addr:postcode":"56071",
    "addr:street":"New Prague Blvd",
    "iso:country":"US",
    "sg:address":"11967 New Prague Blvd",
    "sg:city":"New Prague",
    "sg:classifiers":[
        {
            "category":"Building & Trades",
            "subcategory":"Construction",
            "type":"Services"
        }
    ],
    "sg:phone":"+1 952 758 6619",
    "sg:postcode":"56071",
    "sg:province":"MN",
    "sg:tags":[
        "excavation",
        "contractor"
    ],
    "wof:name":"Clays Bobcat Service Inc",
    "wof:placetype":"venue"
},
  "geometry": {"coordinates":[-93.498183,44.543658],"type":"Point"}
}