{
  "type": "Feature",
  "properties": {
    "iso:country":"US",
    "sg:address":"320 Delaware Ave",
    "sg:city":"Adrian",
    "sg:classifiers":[
        {
            "category":"Building & Trades",
            "subcategory":"Electrical",
            "type":"Services"
        }
    ],
    "sg:phone":"+1 507 483 2857",
    "sg:postcode":"56110",
    "sg:province":"MN",
    "sg:tags":[
        "electrical",
        "contractor"
    ],
    "wof:name":"Pat S Electric",
    "wof:placetype":"venue"
},
  "geometry": {"coordinates":[-95.93879099999999,43.633876],"type":"Point"}
}