{
  "type": "Feature",
  "properties": {
    "addr:full":"74187 US Hwy 71 Jackson MN 56143",
    "addr:postcode":"74187;56143",
    "addr:street":"Us Hwy 71",
    "iso:country":"US",
    "sg:address":"74187 US Hwy 71",
    "sg:city":"Jackson",
    "sg:classifiers":[
        {
            "category":"Autos & Motor Vehicles",
            "subcategory":"Automobile Sales",
            "type":"Retail Goods"
        }
    ],
    "sg:phone":"+1 507 847 2816",
    "sg:postcode":"56143",
    "sg:province":"MN",
    "sg:tags":[
        "repair"
    ],
    "wof:name":"Sadusky Sales and Service",
    "wof:placetype":"venue"
},
  "geometry": {"coordinates":[-94.994696,43.562593],"type":"Point"}
}