{
  "type": "Feature",
  "properties": {
    "iso:country":"US",
    "sg:address":"4745 Co Rd 37 NW",
    "sg:city":"Maple Lake",
    "sg:classifiers":[
        {
            "category":"Building & Trades",
            "subcategory":"Equipment Rental",
            "type":"Services"
        }
    ],
    "sg:phone":"+1 320 963 5094",
    "sg:postcode":"55358",
    "sg:province":"MN",
    "sg:tags":[
        "aircraft",
        "leasing",
        "charter"
    ],
    "wof:name":"Wright Aero Inc",
    "wof:placetype":"venue"
},
  "geometry": {"coordinates":[-93.98645399999999,45.238206],"type":"Point"}
}