{
  "type": "Feature",
  "properties": {
    "iso:country":"US",
    "sg:address":"30475 Vasa Trl",
    "sg:city":"Welch",
    "sg:classifiers":[
        {
            "category":"Farming",
            "subcategory":"Livestock Farm",
            "type":"Manufacturing & Wholesale Goods"
        }
    ],
    "sg:phone":"+1 651 258 4164",
    "sg:postcode":"55089",
    "sg:province":"MN",
    "sg:tags":[
        "dairy",
        "beef",
        "feedlot",
        "cattle"
    ],
    "wof:name":"Tim Carlson",
    "wof:placetype":"venue"
},
  "geometry": {"coordinates":[-92.716885,44.508751],"type":"Point"}
}