{
  "type": "Feature",
  "properties": {
    "iso:country":"US",
    "sg:address":"8872 Inverness Ter",
    "sg:city":"Minneapolis",
    "sg:classifiers":[
        {
            "category":"Professional",
            "subcategory":"Engineering",
            "type":"Services"
        }
    ],
    "sg:phone":"+1 612 790 1784",
    "sg:postcode":"55443",
    "sg:province":"MN",
    "wof:name":"Strzala Consulting",
    "wof:placetype":"venue"
},
  "geometry": {"coordinates":[-93.336337,45.114893],"type":"Point"}
}