{
  "type": "Feature",
  "properties": {
    "addr:full":"33378 120th St Farwell MN 56327",
    "addr:housenumber":"33378",
    "addr:postcode":"56327",
    "addr:street":"120Th St",
    "iso:country":"US",
    "sg:address":"33378 120th St",
    "sg:city":"Farwell",
    "sg:phone":"+1 320 283 5155",
    "sg:postcode":"56327",
    "sg:province":"MN",
    "sg:tags":[
        "farm",
        "wheat",
        "soybean"
    ],
    "wof:name":"James Lange",
    "wof:placetype":"venue"
},
  "geometry": {"coordinates":[-95.621825,45.730604],"type":"Point"}
}