{
  "type": "Feature",
  "properties": {
    "addr:full":"16486 Black Creek Ln NE Bemidji MN 56601",
    "addr:housenumber":"16486",
    "addr:postcode":"56601",
    "addr:street":"Black Creek Ln Ne",
    "iso:country":"US",
    "sg:address":"16486 Black Creek Ln NE",
    "sg:city":"Bemidji",
    "sg:classifiers":[
        {
            "category":"Food & Beverages",
            "subcategory":"Fruits & Vegetables",
            "type":"Retail Goods"
        }
    ],
    "sg:phone":"+1 218 586 2054",
    "sg:postcode":"56601",
    "sg:province":"MN",
    "sg:tags":[
        "wholesale"
    ],
    "wof:name":"Double B Produce & Supply",
    "wof:placetype":"venue"
},
  "geometry": {"coordinates":[-94.825332,47.62606],"type":"Point"}
}