{
  "type": "Feature",
  "properties": {
    "addr:full":"365 4th St SE Medford MN 55049",
    "addr:housenumber":"365",
    "addr:postcode":"55049",
    "addr:street":"4Th St Se",
    "iso:country":"US",
    "sg:address":"365 4th St SE",
    "sg:city":"Medford",
    "sg:classifiers":[
        {
            "category":"Transit Center",
            "subcategory":"Freight",
            "type":"Transportation"
        },
        {
            "category":"Freight",
            "type":"Transportation"
        }
    ],
    "sg:phone":"+1 507 446 0508",
    "sg:postcode":"55049",
    "sg:province":"MN",
    "sg:tags":[
        "local",
        "trucking-motor",
        "trucking"
    ],
    "wof:name":"Advantage Lime And Trucking",
    "wof:placetype":"venue"
},
  "geometry": {"coordinates":[-93.24140300000001,44.17031],"type":"Point"}
}