{
  "type": "Feature",
  "properties": {
    "iso:country":"US",
    "sg:address":"1618 2nd Ave SE",
    "sg:city":"Austin",
    "sg:classifiers":[
        {
            "category":"Social Services",
            "subcategory":"Child Care",
            "type":"Services"
        }
    ],
    "sg:phone":"+1 507 433 2819",
    "sg:postcode":"55912",
    "sg:province":"MN",
    "sg:tags":[
        "day",
        "provider"
    ],
    "wof:name":"Rebecca Condit",
    "wof:placetype":"venue"
},
  "geometry": {"coordinates":[-92.953744,43.664823],"type":"Point"}
}