{
  "type": "Feature",
  "properties": {
    "addr:full":"2189 Snelling Ave N Saint Paul MN 55113",
    "addr:housenumber":"2189",
    "addr:postcode":"55113",
    "addr:street":"Snelling Ave N",
    "iso:country":"US",
    "sg:address":"2189 Snelling Ave N",
    "sg:city":"Saint Paul",
    "sg:classifiers":[
        {
            "category":"Shopping",
            "subcategory":"Bicycles & Sporting Goods",
            "type":"Retail Goods"
        }
    ],
    "sg:phone":"+1 651 633 3110",
    "sg:postcode":"55113",
    "sg:province":"MN",
    "wof:name":"2nd Wind",
    "wof:placetype":"venue"
},
  "geometry": {"coordinates":[-93.166658,45.007219],"type":"Point"}
}