{
  "type": "Feature",
  "properties": {
    "iso:country":"US",
    "sg:address":"1600 11th Ave NE",
    "sg:city":"Willmar",
    "sg:classifiers":[
        {
            "category":"Shopping",
            "subcategory":"Bicycles & Sporting Goods",
            "type":"Retail Goods"
        }
    ],
    "sg:phone":"+1 320 979 6327",
    "sg:postcode":"56201",
    "sg:province":"MN",
    "sg:tags":[
        "snowboard"
    ],
    "wof:name":"Prophecy Snowboard Shop",
    "wof:placetype":"venue"
},
  "geometry": {"coordinates":[-95.022086,45.136345],"type":"Point"}
}