{
  "type": "Feature",
  "properties": {
    "iso:country":"US",
    "sg:address":"36290 US Hwy 71",
    "sg:city":"Redwood Falls",
    "sg:classifiers":[
        {
            "category":"Retail",
            "subcategory":"Auto Repair",
            "type":"Services"
        }
    ],
    "sg:phone":"+1 507 644 3644",
    "sg:postcode":"56283",
    "sg:province":"MN",
    "sg:tags":[
        "body"
    ],
    "wof:name":"Thomas Guetter",
    "wof:placetype":"venue"
},
  "geometry": {"coordinates":[-95.06472599999999,44.541302],"type":"Point"}
}