{
  "type": "Feature",
  "properties": {
    "iso:country":"US",
    "sg:address":"3300 Co Rd 10",
    "sg:city":"Minneapolis",
    "sg:classifiers":[
        {
            "category":"Professional",
            "type":"Services"
        }
    ],
    "sg:phone":"+1 763 561 3046",
    "sg:postcode":"55429",
    "sg:province":"MN",
    "wof:name":"P & N Services Inc",
    "wof:placetype":"venue"
},
  "geometry": {"coordinates":[-93.324246,45.060319],"type":"Point"}
}