{
  "type": "Feature",
  "properties": {
    "iso:country":"US",
    "sg:address":"399 Silver Lake Rd SW",
    "sg:city":"Saint Paul",
    "sg:classifiers":[
        {
            "category":"Retail",
            "subcategory":"Laundry & Dry Cleaning",
            "type":"Services"
        }
    ],
    "sg:phone":"+1 651 628 0777",
    "sg:postcode":"55112",
    "sg:province":"MN",
    "wof:name":"Silver Lake Cleaners",
    "wof:placetype":"venue"
},
  "geometry": {"coordinates":[-93.218102,45.043301],"type":"Point"}
}