{
  "type": "Feature",
  "properties": {
    "addr:full":"17196 Hamilton Dr Lakeville MN 55044",
    "addr:housenumber":"17196",
    "addr:postcode":"55044",
    "addr:street":"Hamilton Dr",
    "iso:country":"US",
    "sg:address":"17196 Hamilton Dr",
    "sg:city":"Lakeville",
    "sg:classifiers":[
        {
            "category":"Banks & Credit Unions",
            "subcategory":"Financial Services",
            "type":"Services"
        }
    ],
    "sg:phone":"+1 952 997 7560",
    "sg:postcode":"55044",
    "sg:province":"MN",
    "sg:tags":[
        "investor",
        "investment",
        "closed"
    ],
    "wof:name":"Terrapin Investments",
    "wof:placetype":"venue"
},
  "geometry": {"coordinates":[-93.22680099999999,44.702264],"type":"Point"}
}