{
  "type": "Feature",
  "properties": {
    "iso:country":"US",
    "sg:address":"12098 Co Rd 150",
    "sg:city":"Kimball",
    "sg:classifiers":[
        {
            "category":"Wholesale",
            "subcategory":"Construction Materials",
            "type":"Manufacturing & Wholesale Goods"
        },
        {
            "category":"Manufacturing",
            "subcategory":"Metals",
            "type":"Manufacturing & Wholesale Goods"
        }
    ],
    "sg:phone":"+1 320 398 2002",
    "sg:postcode":"55353",
    "sg:province":"MN",
    "sg:tags":[
        "building",
        "fabrication",
        "structural"
    ],
    "wof:name":"Total Steel Solutions LLC",
    "wof:placetype":"venue"
},
  "geometry": {"coordinates":[-94.2946,45.303282],"type":"Point"}
}