{
  "type": "Feature",
  "properties": {
    "iso:country":"US",
    "sg:address":"5875 Kitkerry Ct S",
    "sg:city":"Shoreview",
    "sg:classifiers":[
        {
            "category":"Home & Garden",
            "subcategory":"Home Furnishings",
            "type":"Retail Goods"
        }
    ],
    "sg:phone":"+1 651 415 2728",
    "sg:postcode":"55126",
    "sg:province":"MN",
    "sg:tags":[
        "curtain",
        "made",
        "drapery"
    ],
    "wof:name":"Interior Outlook",
    "wof:placetype":"venue"
},
  "geometry": {"coordinates":[-93.124112,45.118975],"type":"Point"}
}