{
  "type": "Feature",
  "properties": {
    "addr:full":"306 Mondale St Elmore MN 56027",
    "addr:housenumber":"306",
    "addr:postcode":"56027",
    "addr:street":"Mondale St",
    "iso:country":"US",
    "sg:address":"306 Mondale St",
    "sg:city":"Elmore",
    "sg:classifiers":[
        {
            "category":"Personal",
            "subcategory":"Beauty Salon",
            "type":"Services"
        }
    ],
    "sg:phone":"+1 507 943 3556",
    "sg:postcode":"56027",
    "sg:province":"MN",
    "wof:name":"Shear Perfection",
    "wof:placetype":"venue"
},
  "geometry": {"coordinates":[-94.085067,43.505718],"type":"Point"}
}