{
  "type": "Feature",
  "properties": {
    "addr:full":"336 W Bridge St Owatonna MN 55060",
    "addr:housenumber":"336",
    "addr:postcode":"55060",
    "addr:street":"W Bridge St",
    "iso:country":"US",
    "sg:address":"336 W Bridge St",
    "sg:city":"Owatonna",
    "sg:classifiers":[
        {
            "category":"Personal",
            "subcategory":"Beauty Salon",
            "type":"Services"
        }
    ],
    "sg:phone":"+1 507 455 1580",
    "sg:postcode":"55060",
    "sg:province":"MN",
    "sg:tags":[
        "shop"
    ],
    "wof:name":"Westbridge Hair Stylist",
    "wof:placetype":"venue"
},
  "geometry": {"coordinates":[-93.23197399999999,44.084395],"type":"Point"}
}