{
  "type": "Feature",
  "properties": {
    "addr:full":"4218 Viking Blvd NW Anoka MN 55303",
    "addr:housenumber":"4218",
    "addr:postcode":"55303",
    "addr:street":"Viking Blvd Nw",
    "iso:country":"US",
    "sg:address":"4218 Viking Blvd NW",
    "sg:city":"Anoka",
    "sg:classifiers":[
        {
            "category":"Professional",
            "type":"Services"
        }
    ],
    "sg:phone":"+1 763 753 3373",
    "sg:postcode":"55303",
    "sg:province":"MN",
    "wof:name":"Oak Grove Sewer Water Co",
    "wof:placetype":"venue"
},
  "geometry": {"coordinates":[-93.37585,45.327474],"type":"Point"}
}