{
  "type": "Feature",
  "properties": {
    "iso:country":"US",
    "sg:address":"7300 Northland Dr N",
    "sg:city":"Minneapolis",
    "sg:classifiers":[
        {
            "category":"Wholesale",
            "subcategory":"Hardware",
            "type":"Manufacturing & Wholesale Goods"
        }
    ],
    "sg:phone":"+1 763 315 0100",
    "sg:postcode":"55428",
    "sg:province":"MN",
    "sg:tags":[
        "plumbing",
        "c"
    ],
    "wof:name":"Hajoca Corporation",
    "wof:placetype":"venue"
},
  "geometry": {"coordinates":[-93.39570500000001,45.087413],"type":"Point"}
}