{
  "type": "Feature",
  "properties": {
    "iso:country":"US",
    "sg:address":"224 Pioneer Trl",
    "sg:city":"Chaska",
    "sg:classifiers":[
        {
            "category":"Restaurant",
            "type":"Food & Drink"
        }
    ],
    "sg:phone":"+1 952 361 9573",
    "sg:postcode":"55318",
    "sg:province":"MN",
    "sg:tags":[
        "pizza"
    ],
    "sg:website":"www.papajohns.com",
    "wof:name":"Papa John's Pizza",
    "wof:placetype":"venue"
},
  "geometry": {"coordinates":[-93.573601,44.826199],"type":"Point"}
}