{
  "type": "Feature",
  "properties": {
    "addr:full":"4800 Chicago Ave Minneapolis MN 55417",
    "addr:housenumber":"4800",
    "addr:postcode":"55417",
    "addr:street":"Chicago Ave",
    "iso:country":"US",
    "sg:address":"4800 Chicago Ave",
    "sg:city":"Minneapolis",
    "sg:classifiers":[
        {
            "category":"Restaurant",
            "type":"Food & Drink"
        }
    ],
    "sg:postcode":"55417",
    "sg:province":"MN",
    "sg:tags":[
        "pizza"
    ],
    "sg:website":"www.pizzahut.com",
    "wof:name":"Pizza Hut",
    "wof:placetype":"venue"
},
  "geometry": {"coordinates":[-93.262646,44.91607],"type":"Point"}
}