{
  "type": "Feature",
  "properties": {
    "addr:full":"16048 Gap Dr Caledonia MN 55921",
    "addr:postcode":"16048;55921",
    "addr:street":"Gap Dr",
    "iso:country":"US",
    "sg:address":"16048 Gap Dr",
    "sg:city":"Caledonia",
    "sg:phone":"+1 507 724 2302",
    "sg:postcode":"55921",
    "sg:province":"MN",
    "sg:tags":[
        "farm",
        "corn",
        "beef",
        "feedlot",
        "cattle"
    ],
    "wof:name":"Edward Voight Farm",
    "wof:placetype":"venue"
},
  "geometry": {"coordinates":[-91.572861,43.601754],"type":"Point"}
}