{
  "type": "Feature",
  "properties": {
    "addr:full":"4724 15th Ave S Minneapolis MN 55407",
    "addr:housenumber":"4724",
    "addr:postcode":"55407",
    "addr:street":"15Th Ave S",
    "iso:country":"US",
    "sg:address":"4724 15th Ave S",
    "sg:city":"Minneapolis",
    "sg:classifiers":[
        {
            "category":"Arts & Performance",
            "subcategory":"Music",
            "type":"Entertainment"
        }
    ],
    "sg:phone":"+1 651 287 1000",
    "sg:postcode":"55407",
    "sg:province":"MN",
    "sg:tags":[
        "dj"
    ],
    "sg:website":"www.sounds-great.com",
    "wof:name":"Sounds Great",
    "wof:placetype":"venue"
},
  "geometry": {"coordinates":[-93.25405499999999,44.917106],"type":"Point"}
}