{
  "type": "Feature",
  "properties": {
    "addr:full":"26 W 10th St Waconia MN 55387",
    "addr:housenumber":"26",
    "addr:postcode":"55387",
    "addr:street":"W 10Th St",
    "iso:country":"US",
    "sg:address":"26 W 10th St",
    "sg:city":"Waconia",
    "sg:classifiers":[
        {
            "category":"Building & Trades",
            "subcategory":"Construction",
            "type":"Services"
        }
    ],
    "sg:phone":"+1 952 442 4657",
    "sg:postcode":"55387",
    "sg:province":"MN",
    "sg:tags":[
        "residential",
        "commercial"
    ],
    "wof:name":"Tdj Construction Inc",
    "wof:placetype":"venue"
},
  "geometry": {"coordinates":[-93.78886199999999,44.840162],"type":"Point"}
}