{
  "type": "Feature",
  "properties": {
    "addr:full":"14360 92nd Ave N Osseo MN 55369",
    "addr:housenumber":"14360",
    "addr:postcode":"55369",
    "addr:street":"92Nd Ave N",
    "iso:country":"US",
    "sg:address":"14360 92nd Ave N",
    "sg:city":"Osseo",
    "sg:classifiers":[
        {
            "category":"Building & Trades",
            "subcategory":"Construction",
            "type":"Services"
        }
    ],
    "sg:phone":"+1 763 420 9737",
    "sg:postcode":"55369",
    "sg:province":"MN",
    "sg:tags":[
        "hanging",
        "contractor"
    ],
    "wof:name":"Tj Painting",
    "wof:placetype":"venue"
},
  "geometry": {"coordinates":[-93.462553,45.122046],"type":"Point"}
}