{
  "type": "Feature",
  "properties": {
    "addr:full":"1831 Minnehaha Ave E St Paul MN 55119",
    "addr:housenumber":"1831",
    "addr:postcode":"55119",
    "addr:street":"Minnehaha Ave E",
    "iso:country":"US",
    "sg:address":"1831 Minnehaha Ave E",
    "sg:city":"St Paul",
    "sg:classifiers":[
        {
            "category":"Organizations",
            "subcategory":"Religious Organization",
            "type":"Services"
        }
    ],
    "sg:phone":"+1 651 735 2555",
    "sg:postcode":"55119",
    "sg:province":"MN",
    "sg:tags":[
        "church"
    ],
    "wof:name":"Hazel Prk Congregational Churc",
    "wof:placetype":"venue"
},
  "geometry": {"coordinates":[-93.024387,44.963157],"type":"Point"}
}