{
  "type": "Feature",
  "properties": {
    "iso:country":"US",
    "sg:address":"507 Carleton Ave",
    "sg:city":"Morgan",
    "sg:classifiers":[
        {
            "category":"Bars & Pubs",
            "type":"Food & Drink"
        }
    ],
    "sg:phone":"+1 507 249 3345",
    "sg:postcode":"56266",
    "sg:province":"MN",
    "wof:name":"June Haubrick-Business",
    "wof:placetype":"venue"
},
  "geometry": {"coordinates":[-94.926687,44.420879],"type":"Point"}
}