{
  "type": "Feature",
  "properties": {
    "iso:country":"US",
    "sg:address":"501 S Lake Ave",
    "sg:city":"Duluth",
    "sg:classifiers":[
        {
            "category":"Real Estate",
            "subcategory":"Real Estate Services",
            "type":"Services"
        }
    ],
    "sg:phone":"+1 218 625 5320",
    "sg:postcode":"55802",
    "sg:province":"MN",
    "sg:tags":[
        "abstract",
        "title"
    ],
    "wof:name":"Lakeview Title",
    "wof:placetype":"venue"
},
  "geometry": {"coordinates":[-92.09313400000001,46.779299],"type":"Point"}
}