{
  "type": "Feature",
  "properties": {
    "addr:full":"232 2nd St NW Cass Lake MN 56633",
    "addr:housenumber":"232",
    "addr:postcode":"56633",
    "addr:street":"2Nd St Nw Cass",
    "iso:country":"US",
    "sg:address":"232 2nd St NW",
    "sg:city":"Cass Lake",
    "sg:classifiers":[
        {
            "category":"Professional",
            "subcategory":"Business Services",
            "type":"Services"
        }
    ],
    "sg:phone":"+1 218 335 3903",
    "sg:postcode":"56633",
    "sg:province":"MN",
    "sg:tags":[
        "statistical"
    ],
    "wof:name":"Healing Pathways",
    "wof:placetype":"venue"
},
  "geometry": {"coordinates":[-94.607153,47.379162],"type":"Point"}
}