{
  "type": "Feature",
  "properties": {
    "addr:full":"8024 50th Ave N Minneapolis MN 55428",
    "addr:housenumber":"8024",
    "addr:postcode":"55428",
    "addr:street":"50Th Ave N",
    "iso:country":"US",
    "sg:address":"8024 50th Ave N",
    "sg:city":"Minneapolis",
    "sg:classifiers":[
        {
            "category":"Shopping",
            "subcategory":"Bicycles & Sporting Goods",
            "type":"Retail Goods"
        }
    ],
    "sg:phone":"+1 763 537 6231",
    "sg:postcode":"55428",
    "sg:province":"MN",
    "wof:name":"C & R Ander Four",
    "wof:placetype":"venue"
},
  "geometry": {"coordinates":[-93.382858,45.046039],"type":"Point"}
}