{
  "type": "Feature",
  "properties": {
    "addr:full":"707 2nd Ave SE Roseau MN 56751",
    "addr:housenumber":"707",
    "addr:postcode":"56751",
    "addr:street":"2Nd Ave Se",
    "iso:country":"US",
    "sg:address":"707 2nd Ave SE",
    "sg:city":"Roseau",
    "sg:classifiers":[
        {
            "category":"Organizations",
            "subcategory":"Community Association",
            "type":"Services"
        }
    ],
    "sg:phone":"+1 218 463 1865",
    "sg:postcode":"56751",
    "sg:province":"MN",
    "sg:tags":[
        "fraternal"
    ],
    "wof:name":"Fraternal Order Of Eagles",
    "wof:placetype":"venue"
},
  "geometry": {"coordinates":[-95.761813,48.839776],"type":"Point"}
}