{
  "type": "Feature",
  "properties": {
    "addr:full":"1740 Highway 65 Mora MN 55051",
    "addr:housenumber":"1740",
    "addr:postcode":"55051",
    "addr:street":"Highway 65",
    "iso:country":"US",
    "sg:address":"1740 Highway 65",
    "sg:city":"Mora",
    "sg:classifiers":[
        {
            "category":"Professional",
            "subcategory":"Lawyer & Legal Services",
            "type":"Services"
        }
    ],
    "sg:phone":"+1 320 679 0546",
    "sg:postcode":"55051",
    "sg:province":"MN",
    "sg:tags":[
        "attorney"
    ],
    "wof:name":"Wallcrafte Llp",
    "wof:placetype":"venue"
},
  "geometry": {"coordinates":[-93.296813,45.838354],"type":"Point"}
}