{
  "type": "Feature",
  "properties": {
    "iso:country":"US",
    "sg:address":"3026 110th Ave",
    "sg:city":"Borup",
    "sg:classifiers":[
        {
            "category":"Farming",
            "subcategory":"Dairy Farm",
            "type":"Manufacturing & Wholesale Goods"
        }
    ],
    "sg:phone":"+1 218 582 3265",
    "sg:postcode":"56519",
    "sg:province":"MN",
    "wof:name":"Norman Dahl",
    "wof:placetype":"venue"
},
  "geometry": {"coordinates":[-96.428558,47.165639],"type":"Point"}
}