{
  "type": "Feature",
  "properties": {
    "addr:full":"18271 Territorial Rd Osseo MN 55369",
    "addr:housenumber":"18271",
    "addr:postcode":"55369",
    "addr:street":"Territorial Rd",
    "iso:country":"US",
    "sg:address":"18271 Territorial Rd",
    "sg:city":"Osseo",
    "sg:classifiers":[
        {
            "category":"Professional",
            "type":"Services"
        }
    ],
    "sg:phone":"+1 763 428 7330",
    "sg:postcode":"55369",
    "sg:province":"MN",
    "wof:name":"Nomis Nautical Works Ltd",
    "wof:placetype":"venue"
},
  "geometry": {"coordinates":[-93.50870999999999,45.160032],"type":"Point"}
}