{
  "type": "Feature",
  "properties": {
    "iso:country":"US",
    "sg:address":"1032 Aldrich Ave N # 101",
    "sg:city":"Minneapolis",
    "sg:classifiers":[
        {
            "category":"Health Services",
            "subcategory":"Clinic",
            "type":"Services"
        }
    ],
    "sg:phone":"+1 612 377 4815",
    "sg:postcode":"55411",
    "sg:province":"MN",
    "sg:tags":[
        "welfare"
    ],
    "wof:name":"Sisterly Love Healthcare Agcy",
    "wof:placetype":"venue"
},
  "geometry": {"coordinates":[-93.289491,44.990633],"type":"Point"}
}