{
  "type": "Feature",
  "properties": {
    "iso:country":"US",
    "sg:address":"14053 Crestone Cir",
    "sg:city":"Rosemount",
    "sg:classifiers":[
        {
            "category":"Restaurant",
            "type":"Food & Drink"
        }
    ],
    "sg:menulink":"http://www.allmenus.com/mn/rosemount/56560-papa-murphys/menu/",
    "sg:phone":"+1 651 423 2453",
    "sg:postcode":"55068",
    "sg:province":"MN",
    "sg:tags":[
        "american",
        "pizza"
    ],
    "wof:name":"Papa Murphy's",
    "wof:placetype":"venue"
},
  "geometry": {"coordinates":[-93.14424,44.729248],"type":"Point"}
}