{
  "type": "Feature",
  "properties": {
    "addr:full":"140 Center St E Harmony MN 55939",
    "addr:housenumber":"140",
    "addr:postcode":"55939",
    "addr:street":"Center St E",
    "iso:country":"US",
    "sg:address":"140 Center St E",
    "sg:city":"Harmony",
    "sg:classifiers":[
        {
            "category":"Travel",
            "subcategory":"Hotels & Motels",
            "type":"Entertainment"
        }
    ],
    "sg:phone":"+1 507 886 2200",
    "sg:postcode":"55939",
    "sg:province":"MN",
    "sg:tags":[
        "breakfast",
        "accommodation",
        "bed"
    ],
    "sg:website":"www.selvighouse.com",
    "wof:name":"Selvig House Bed & Breakfast",
    "wof:placetype":"venue"
},
  "geometry": {"coordinates":[-92.008315,43.554408],"type":"Point"}
}