{
  "type": "Feature",
  "properties": {
    "iso:country":"US",
    "sg:address":"800 Washington Ave N",
    "sg:city":"Minneapolis",
    "sg:classifiers":[
        {
            "category":"Restaurant",
            "type":"Food & Drink"
        }
    ],
    "sg:menulink":"http://www.allmenus.com/mn/minneapolis/267687-babalu/menu/",
    "sg:phone":"+1 612 746 3158",
    "sg:postcode":"55401",
    "sg:province":"MN",
    "sg:tags":[
        "caribbean"
    ],
    "wof:name":"Babalu",
    "wof:placetype":"venue"
},
  "geometry": {"coordinates":[-93.278634,44.989487],"type":"Point"}
}