{
  "type": "Feature",
  "properties": {
    "iso:country":"US",
    "sg:address":"559 Hwy 10 S",
    "sg:city":"Saint Cloud",
    "sg:classifiers":[
        {
            "category":"Retail",
            "subcategory":"Auto Repair",
            "type":"Services"
        }
    ],
    "sg:phone":"+1 320 229 1900",
    "sg:postcode":"56304",
    "sg:province":"MN",
    "sg:tags":[
        "general"
    ],
    "wof:name":"Central MN Auto Connecti",
    "wof:placetype":"venue"
},
  "geometry": {"coordinates":[-94.131468,45.559381],"type":"Point"}
}