{
  "type": "Feature",
  "properties": {
    "iso:country":"US",
    "sg:address":"5517 Harriet Ave S",
    "sg:city":"Minneapolis",
    "sg:classifiers":[
        {
            "category":"Professional",
            "type":"Services"
        }
    ],
    "sg:phone":"+1 952 469 3962",
    "sg:postcode":"55419",
    "sg:province":"MN",
    "sg:tags":[
        "establishment"
    ],
    "wof:name":"CEL",
    "wof:placetype":"venue"
},
  "geometry": {"coordinates":[-93.285669,44.901777],"type":"Point"}
}