{
  "type": "Feature",
  "properties": {
    "addr:full":"6317 Oak Meadow Dr NW Rochester MN 55901",
    "addr:housenumber":"6317",
    "addr:postcode":"55901",
    "addr:street":"Oak Meadow Dr Nw",
    "iso:country":"US",
    "sg:address":"6317 Oak Meadow Dr NW",
    "sg:city":"Rochester",
    "sg:classifiers":[
        {
            "category":"Professional",
            "subcategory":"Management & Consulting",
            "type":"Services"
        }
    ],
    "sg:phone":"+1 507 280 0217",
    "sg:postcode":"55901",
    "sg:province":"MN",
    "sg:tags":[
        "a",
        "consultant",
        "as",
        "training",
        "operates"
    ],
    "wof:name":"Nancy Knowland",
    "wof:placetype":"venue"
},
  "geometry": {"coordinates":[-92.47163500000001,44.086203],"type":"Point"}
}