{
  "type": "Feature",
  "properties": {
    "addr:full":"6900 Ridgeview Dr Minneapolis MN 55439",
    "addr:housenumber":"6900",
    "addr:postcode":"55439",
    "addr:street":"Ridgeview Dr",
    "iso:country":"US",
    "sg:address":"6900 Ridgeview Dr",
    "sg:city":"Minneapolis",
    "sg:classifiers":[
        {
            "category":"Professional",
            "type":"Services"
        }
    ],
    "sg:phone":"+1 612 348 4153",
    "sg:postcode":"55439",
    "sg:province":"MN",
    "wof:name":"Carol J Kneeskern",
    "wof:placetype":"venue"
},
  "geometry": {"coordinates":[-93.35915300000001,44.877872],"type":"Point"}
}