{
  "type": "Feature",
  "properties": {
    "addr:full":"1090 2nd St S Sartell MN 56377",
    "addr:housenumber":"1090",
    "addr:postcode":"56377",
    "addr:street":"2Nd St S",
    "iso:country":"US",
    "sg:address":"1090 2nd St S",
    "sg:city":"Sartell",
    "sg:classifiers":[
        {
            "category":"Professional",
            "subcategory":"Advertising",
            "type":"Services"
        }
    ],
    "sg:phone":"+1 320 230 6060",
    "sg:postcode":"56377",
    "sg:province":"MN",
    "sg:website":"www.sun.com",
    "wof:name":"SUN.COM",
    "wof:placetype":"venue"
},
  "geometry": {"coordinates":[-94.225932,45.615555],"type":"Point"}
}