{
  "type": "Feature",
  "properties": {
    "addr:full":"305 E 77th St Minneapolis MN 55423",
    "addr:housenumber":"305",
    "addr:postcode":"55423",
    "addr:street":"E 77Th St",
    "iso:country":"US",
    "sg:address":"305 E 77th St",
    "sg:city":"Minneapolis",
    "sg:classifiers":[
        {
            "category":"Education",
            "subcategory":"School",
            "type":"Public Place"
        }
    ],
    "sg:phone":"+1 612 866 3630",
    "sg:postcode":"55423",
    "sg:province":"MN",
    "wof:name":"Partnership Academy Charter",
    "wof:placetype":"venue"
},
  "geometry": {"coordinates":[-93.272673,44.863632],"type":"Point"}
}