{
  "type": "Feature",
  "properties": {
    "addr:full":"604 25th St SE Willmar MN 56201",
    "addr:housenumber":"604",
    "addr:postcode":"56201",
    "addr:street":"25Th St Se",
    "iso:country":"US",
    "sg:address":"604 25th St SE",
    "sg:city":"Willmar",
    "sg:classifiers":[
        {
            "category":"Real Estate",
            "subcategory":"Real Estate Operator",
            "type":"Services"
        }
    ],
    "sg:phone":"+1 320 235 3479",
    "sg:postcode":"56201",
    "sg:province":"MN",
    "sg:tags":[
        "apartment"
    ],
    "wof:name":"Gail Quale",
    "wof:placetype":"venue"
},
  "geometry": {"coordinates":[-95.00947499999999,45.119883],"type":"Point"}
}