{
  "type": "Feature",
  "properties": {
    "iso:country":"US",
    "sg:address":"610 Broadway St S",
    "sg:city":"Stillwater",
    "sg:classifiers":[
        {
            "category":"Professional",
            "type":"Services"
        }
    ],
    "sg:phone":"+1 651 439 0932",
    "sg:postcode":"55082",
    "sg:province":"MN",
    "wof:name":"Noble Works LLC",
    "wof:placetype":"venue"
},
  "geometry": {"coordinates":[-92.803766,45.050935],"type":"Point"}
}