{
  "type": "Feature",
  "properties": {
    "iso:country":"US",
    "sg:address":"11257 Ironwood Ct N",
    "sg:city":"Champlin",
    "sg:classifiers":[
        {
            "category":"Wholesale",
            "subcategory":"Machinery & Supplies",
            "type":"Manufacturing & Wholesale Goods"
        },
        {
            "category":"Home & Garden",
            "subcategory":"Garden Supply",
            "type":"Retail Goods"
        }
    ],
    "sg:phone":"+1 763 506 0358",
    "sg:postcode":"55316",
    "sg:province":"MN",
    "sg:tags":[
        "sprinkler"
    ],
    "wof:name":"Down To Earth Technologies Inc",
    "wof:placetype":"venue"
},
  "geometry": {"coordinates":[-93.405676,45.157969],"type":"Point"}
}