{
  "type": "Feature",
  "properties": {
    "iso:country":"US",
    "sg:address":"117 85th Ave NW",
    "sg:city":"Coon Rapids",
    "sg:classifiers":[
        {
            "category":"Shopping",
            "subcategory":"Discount & Variety Stores",
            "type":"Retail Goods"
        }
    ],
    "sg:phone":"+1 763 783 9020",
    "sg:postcode":"55433",
    "sg:province":"MN",
    "wof:name":"Big Dollar Store",
    "wof:placetype":"venue"
},
  "geometry": {"coordinates":[-93.27153,45.124615],"type":"Point"}
}