{
  "type": "Feature",
  "properties": {
    "iso:country":"US",
    "sg:address":"3192 139th Ave NW",
    "sg:city":"Andover",
    "sg:classifiers":[
        {
            "category":"Social Services",
            "type":"Services"
        }
    ],
    "sg:phone":"+1 763 427 4141",
    "sg:postcode":"55304",
    "sg:province":"MN",
    "sg:tags":[
        "guidance",
        "child"
    ],
    "wof:name":"Rascals & Rainbows",
    "wof:placetype":"venue"
},
  "geometry": {"coordinates":[-93.34679800000001,45.222952],"type":"Point"}
}