{
  "type": "Feature",
  "properties": {
    "addr:full":"1148 Grand Ave St Paul MN 55105",
    "addr:housenumber":"1148",
    "addr:postcode":"55105",
    "addr:street":"Grand Ave",
    "iso:country":"US",
    "sg:address":"1148 Grand Ave",
    "sg:city":"St Paul",
    "sg:classifiers":[
        {
            "category":"Health Services",
            "subcategory":"Doctor",
            "type":"Services"
        }
    ],
    "sg:phone":"+1 651 224 0001",
    "sg:postcode":"55105",
    "sg:province":"MN",
    "sg:tags":[
        "dentist"
    ],
    "wof:name":"Robert J Maley DDS",
    "wof:placetype":"venue"
},
  "geometry": {"coordinates":[-93.14766,44.939924],"type":"Point"}
}