{
  "type": "Feature",
  "properties": {
    "iso:country":"US",
    "sg:address":"438 N 57th Ave W",
    "sg:city":"Duluth",
    "sg:classifiers":[
        {
            "category":"Health Services",
            "subcategory":"Chiropractor",
            "type":"Services"
        }
    ],
    "sg:phone":"+1 218 624 5759",
    "sg:postcode":"55807",
    "sg:province":"MN",
    "sg:tags":[
        "clinic"
    ],
    "wof:name":"Audette Chiropractic Clinic PA",
    "wof:placetype":"venue"
},
  "geometry": {"coordinates":[-92.169157,46.739774],"type":"Point"}
}