{
  "type": "Feature",
  "properties": {
    "addr:full":"3100 W Lake St Minneapolis MN 55416",
    "addr:housenumber":"3100",
    "addr:postcode":"55416",
    "addr:street":"W Lake St",
    "iso:country":"US",
    "sg:address":"3100 W Lake St",
    "sg:city":"Minneapolis",
    "sg:classifiers":[
        {
            "category":"Professional",
            "subcategory":"Business Services",
            "type":"Services"
        }
    ],
    "sg:phone":"+1 952 915 1122",
    "sg:postcode":"55416",
    "sg:province":"MN",
    "wof:name":"Virtual Technology Corporation",
    "wof:placetype":"venue"
},
  "geometry": {"coordinates":[-93.322823,44.948483],"type":"Point"}
}