{
  "type": "Feature",
  "properties": {
    "iso:country":"US",
    "sg:address":"12322 Drake St NW",
    "sg:city":"Minneapolis",
    "sg:classifiers":[
        {
            "category":"Professional",
            "subcategory":"Lawyer & Legal Services",
            "type":"Services"
        }
    ],
    "sg:phone":"+1 763 862 1105",
    "sg:postcode":"55448",
    "sg:province":"MN",
    "wof:name":"Oasis Information Svc",
    "wof:placetype":"venue"
},
  "geometry": {"coordinates":[-93.303731,45.193956],"type":"Point"}
}