{
  "type": "Feature",
  "properties": {
    "addr:full":"12701 220th St E Hastings MN 55033",
    "addr:housenumber":"12701",
    "addr:postcode":"55033",
    "addr:street":"220Th St E",
    "iso:country":"US",
    "sg:address":"12701 220th St E",
    "sg:city":"Hastings",
    "sg:phone":"+1 651 437 4445",
    "sg:postcode":"55033",
    "sg:province":"MN",
    "sg:tags":[
        "farm",
        "corn",
        "soybean"
    ],
    "wof:name":"Roger Kimmes",
    "wof:placetype":"venue"
},
  "geometry": {"coordinates":[-92.83571999999999,44.629906],"type":"Point"}
}