{
  "type": "Feature",
  "properties": {
    "addr:full":"803 A Ave Eveleth MN 55734",
    "addr:housenumber":"803 a",
    "addr:postcode":"55734",
    "addr:street":"Ave Eveleth",
    "iso:country":"US",
    "sg:address":"803 A Ave",
    "sg:city":"Eveleth",
    "sg:classifiers":[
        {
            "category":"Wholesale",
            "subcategory":"Books, Periodicals, & Newspapers",
            "type":"Manufacturing & Wholesale Goods"
        }
    ],
    "sg:phone":"+1 218 744 1217",
    "sg:postcode":"55734",
    "sg:province":"MN",
    "wof:name":"Ortell Enterprises",
    "wof:placetype":"venue"
},
  "geometry": {"coordinates":[-92.537359,47.467888],"type":"Point"}
}