{
  "type": "Feature",
  "properties": {
    "iso:country":"US",
    "sg:address":"16350 96th Ave N",
    "sg:city":"Osseo",
    "sg:classifiers":[
        {
            "category":"Food & Beverages",
            "subcategory":"Groceries & Convenience Stores",
            "type":"Retail Goods"
        }
    ],
    "sg:phone":"+1 763 420 9909",
    "sg:postcode":"55311",
    "sg:province":"MN",
    "wof:name":"Holiday Station Store 319",
    "wof:placetype":"venue"
},
  "geometry": {"coordinates":[-93.488297,45.1273],"type":"Point"}
}