{
  "type": "Feature",
  "properties": {
    "addr:full":"1011 Nicollet Ave Minneapolis MN 55403",
    "addr:housenumber":"1011",
    "addr:postcode":"55403",
    "addr:street":"Nicollet Ave",
    "iso:country":"US",
    "sg:address":"1011 Nicollet Ave",
    "sg:city":"Minneapolis",
    "sg:classifiers":[
        {
            "category":"Organizations",
            "subcategory":"Religious Organization",
            "type":"Services"
        }
    ],
    "sg:phone":"+1 612 338 4745",
    "sg:postcode":"55403",
    "sg:province":"MN",
    "sg:tags":[
        "foundation",
        "book",
        "store"
    ],
    "wof:name":"Scientology Bookstore",
    "wof:placetype":"venue"
},
  "geometry": {"coordinates":[-93.275419,44.973027],"type":"Point"}
}