{
  "type": "Feature",
  "properties": {
    "iso:country":"US",
    "sg:address":"1205 2nd Ave NW",
    "sg:city":"Stewartville",
    "sg:classifiers":[
        {
            "category":"Manufacturing",
            "subcategory":"Tools & Machinery",
            "type":"Manufacturing & Wholesale Goods"
        }
    ],
    "sg:phone":"+1 507 254 0236",
    "sg:postcode":"55976",
    "sg:province":"MN",
    "sg:tags":[
        "lighting",
        "commercial"
    ],
    "wof:name":"Lightcon Corp",
    "wof:placetype":"venue"
},
  "geometry": {"coordinates":[-92.489991,43.864523],"type":"Point"}
}