{
  "type": "Feature",
  "properties": {
    "addr:full":"43056 Co Hwy 137 New York Mills MN 56567",
    "addr:housenumber":"43056",
    "addr:postcode":"56567",
    "addr:street":"Co Hwy 137",
    "iso:country":"US",
    "sg:address":"43056 Co Hwy 137",
    "sg:city":"New York Mills",
    "sg:classifiers":[
        {
            "category":"Building & Trades",
            "subcategory":"Construction",
            "type":"Services"
        }
    ],
    "sg:phone":"+1 218 385 2062",
    "sg:postcode":"56567",
    "sg:province":"MN",
    "sg:tags":[
        "general",
        "contractor"
    ],
    "wof:name":"Gunderson Construction",
    "wof:placetype":"venue"
},
  "geometry": {"coordinates":[-95.426078,46.585787],"type":"Point"}
}