{
  "type": "Feature",
  "properties": {
    "iso:country":"US",
    "sg:address":"112370 Eitel Cir",
    "sg:city":"Chaska",
    "sg:classifiers":[
        {
            "category":"Social Services",
            "subcategory":"Child Care",
            "type":"Services"
        }
    ],
    "sg:phone":"+1 952 368 9588",
    "sg:postcode":"55318",
    "sg:province":"MN",
    "sg:tags":[
        "day"
    ],
    "wof:name":"Denise M Hedtke",
    "wof:placetype":"venue"
},
  "geometry": {"coordinates":[-93.624476,44.82295],"type":"Point"}
}