{
  "type": "Feature",
  "properties": {
    "addr:full":"110 3rd Ave Spicer MN 56288",
    "addr:housenumber":"110",
    "addr:postcode":"56288",
    "addr:street":"3Rd Ave",
    "iso:country":"US",
    "sg:address":"110 3rd Ave",
    "sg:city":"Spicer",
    "sg:classifiers":[
        {
            "category":"Building & Trades",
            "subcategory":"Construction",
            "type":"Services"
        }
    ],
    "sg:phone":"+1 320 796 0541",
    "sg:postcode":"56288",
    "sg:province":"MN",
    "sg:tags":[
        "home",
        "builder"
    ],
    "wof:name":"Spiritwood Home",
    "wof:placetype":"venue"
},
  "geometry": {"coordinates":[-94.942244,45.233428],"type":"Point"}
}