{
  "type": "Feature",
  "properties": {
    "iso:country":"US",
    "sg:address":"101 4th St SE",
    "sg:city":"Rochester",
    "sg:classifiers":[
        {
            "category":"Government",
            "subcategory":"Jail",
            "type":"Public Place"
        }
    ],
    "sg:phone":"+1 507 285 8320",
    "sg:postcode":"55904",
    "sg:province":"MN",
    "sg:tags":[
        "correctional",
        "institution"
    ],
    "wof:name":"Olmsted Cnty Adult Dtntion Ctr",
    "wof:placetype":"venue"
},
  "geometry": {"coordinates":[-92.4609,44.01929],"type":"Point"}
}