{
  "type": "Feature",
  "properties": {
    "iso:country":"US",
    "sg:address":"5637 Brooklyn Blvd",
    "sg:city":"Minneapolis",
    "sg:classifiers":[
        {
            "category":"Banks & Credit Unions",
            "subcategory":"Bank",
            "type":"Services"
        }
    ],
    "sg:phone":"+1 763 535 6250",
    "sg:postcode":"55429",
    "sg:province":"MN",
    "sg:tags":[
        "loan",
        "mortgage",
        "real estate"
    ],
    "wof:name":"L J & L Jones Mortgage",
    "wof:placetype":"venue"
},
  "geometry": {"coordinates":[-93.32458800000001,45.057886],"type":"Point"}
}