{
  "type": "Feature",
  "properties": {
    "addr:full":"1611 Rice St Saint Paul MN 55117",
    "addr:housenumber":"1611",
    "addr:postcode":"55117",
    "addr:street":"Rice St",
    "iso:country":"US",
    "sg:address":"1611 Rice St",
    "sg:city":"Saint Paul",
    "sg:classifiers":[
        {
            "category":"Restaurant",
            "type":"Food & Drink"
        }
    ],
    "sg:phone":"+1 651 489 4036",
    "sg:postcode":"55117",
    "sg:province":"MN",
    "sg:tags":[
        "eating"
    ],
    "wof:name":"Wong Cafe Inc",
    "wof:placetype":"venue"
},
  "geometry": {"coordinates":[-93.105948,44.989325],"type":"Point"}
}