{
  "type": "Feature",
  "properties": {
    "iso:country":"US",
    "sg:address":"134 Columbia Ct",
    "sg:city":"Chaska",
    "sg:classifiers":[
        {
            "category":"Retail",
            "subcategory":"Storage",
            "type":"Services"
        }
    ],
    "sg:phone":"+1 952 227 3000",
    "sg:postcode":"55318",
    "sg:province":"MN",
    "sg:tags":[
        "self",
        "commercial",
        "household"
    ],
    "wof:name":"Apex International",
    "wof:placetype":"venue"
},
  "geometry": {"coordinates":[-93.591684,44.845488],"type":"Point"}
}