{
  "type": "Feature",
  "properties": {
    "addr:full":"9982 Co Rd 81 Maple Grove MN 55369",
    "addr:housenumber":"81",
    "addr:postcode":"9982;55369",
    "addr:street":"Co Rd",
    "iso:country":"US",
    "sg:address":"9982 Co Rd 81",
    "sg:city":"Maple Grove",
    "sg:classifiers":[
        {
            "category":"Travel",
            "subcategory":"Travel Agent",
            "type":"Entertainment"
        }
    ],
    "sg:phone":"+1 763 424 3975",
    "sg:postcode":"55369",
    "sg:province":"MN",
    "sg:tags":[
        "bureau",
        "passenger",
        "agency",
        "transportation",
        "arrangement"
    ],
    "wof:name":"Lindberg Travel Inc",
    "wof:placetype":"venue"
},
  "geometry": {"coordinates":[-93.41074999999999,45.118962],"type":"Point"}
}