{
  "type": "Feature",
  "properties": {
    "addr:full":"53737 430th St Courtland MN 56021",
    "addr:housenumber":"53737",
    "addr:postcode":"56021",
    "addr:street":"430Th St",
    "iso:country":"US",
    "sg:address":"53737 430th St",
    "sg:city":"Courtland",
    "sg:classifiers":[
        {
            "category":"Farming",
            "subcategory":"Dairy Farm",
            "type":"Manufacturing & Wholesale Goods"
        }
    ],
    "sg:phone":"+1 507 359 2815",
    "sg:postcode":"56021",
    "sg:province":"MN",
    "wof:name":"Brandes Farms Inc",
    "wof:placetype":"venue"
},
  "geometry": {"coordinates":[-94.34831200000001,44.326211],"type":"Point"}
}