{
  "type": "Feature",
  "properties": {
    "iso:country":"US",
    "sg:address":"445 Broadway Ave",
    "sg:city":"St Paul Park",
    "sg:classifiers":[
        {
            "category":"Building & Trades",
            "subcategory":"Construction",
            "type":"Services"
        }
    ],
    "sg:phone":"+1 651 768 0140",
    "sg:postcode":"55071",
    "sg:province":"MN",
    "sg:tags":[
        "painter"
    ],
    "wof:name":"G Q Painting",
    "wof:placetype":"venue"
},
  "geometry": {"coordinates":[-92.995779,44.847955],"type":"Point"}
}