{
  "type": "Feature",
  "properties": {
    "addr:full":"5745 Annapolis Ln N Minneapolis MN 55446",
    "addr:housenumber":"5745",
    "addr:postcode":"55446",
    "addr:street":"Annapolis Ln N",
    "iso:country":"US",
    "sg:address":"5745 Annapolis Ln N",
    "sg:city":"Minneapolis",
    "sg:classifiers":[
        {
            "category":"Banks & Credit Unions",
            "subcategory":"Bank",
            "type":"Services"
        }
    ],
    "sg:phone":"+1 763 694 6096",
    "sg:postcode":"55446",
    "sg:province":"MN",
    "sg:tags":[
        "broker",
        "mortgage"
    ],
    "wof:name":"Horizon Mortgage Solutions LLC",
    "wof:placetype":"venue"
},
  "geometry": {"coordinates":[-93.455091,45.05815],"type":"Point"}
}