{
  "type": "Feature",
  "properties": {
    "addr:full":"6348 89th Ave SW Staples MN 56479",
    "addr:housenumber":"6348",
    "addr:postcode":"56479",
    "addr:street":"89Th Ave Sw",
    "iso:country":"US",
    "sg:address":"6348 89th Ave SW",
    "sg:city":"Staples",
    "sg:phone":"+1 218 397 2360",
    "sg:postcode":"56479",
    "sg:province":"MN",
    "sg:tags":[
        "farm",
        "corn"
    ],
    "wof:name":"Robert Dailey",
    "wof:placetype":"venue"
},
  "geometry": {"coordinates":[-94.750435,46.582148],"type":"Point"}
}