{
  "type": "Feature",
  "properties": {
    "addr:full":"14082 210th St Little Falls MN 56345",
    "addr:housenumber":"14082",
    "addr:postcode":"56345",
    "addr:street":"210Th St",
    "iso:country":"US",
    "sg:address":"14082 210th St",
    "sg:city":"Little Falls",
    "sg:classifiers":[
        {
            "category":"Professional",
            "subcategory":"Engineering",
            "type":"Services"
        }
    ],
    "sg:phone":"+1 320 632 5590",
    "sg:postcode":"56345",
    "sg:province":"MN",
    "wof:name":"North Country Ind",
    "wof:placetype":"venue"
},
  "geometry": {"coordinates":[-94.350767,46.064067],"type":"Point"}
}