{
  "type": "Feature",
  "properties": {
    "iso:country":"US",
    "sg:address":"4930 W 77th St 203",
    "sg:city":"Minneapolis",
    "sg:classifiers":[
        {
            "category":"Personal",
            "subcategory":"Massage",
            "type":"Services"
        }
    ],
    "sg:phone":"+1 952 832 0111",
    "sg:postcode":"55435",
    "sg:province":"MN",
    "wof:name":"Hara Center",
    "wof:placetype":"venue"
},
  "geometry": {"coordinates":[-93.347143,44.864074],"type":"Point"}
}