{
  "type": "Feature",
  "properties": {
    "addr:full":"33536 Labrador Dr Clarissa MN 56440",
    "addr:postcode":"33536;56440",
    "addr:street":"Labrador Dr",
    "iso:country":"US",
    "sg:address":"33536 Labrador Dr",
    "sg:city":"Clarissa",
    "sg:classifiers":[
        {
            "category":"Manufacturing",
            "subcategory":"Metals",
            "type":"Manufacturing & Wholesale Goods"
        }
    ],
    "sg:phone":"+1 218 756 3370",
    "sg:postcode":"56440",
    "sg:province":"MN",
    "sg:tags":[
        "plate",
        "work",
        "fabricated",
        "mfg"
    ],
    "wof:name":"Eckland Mfg Inc",
    "wof:placetype":"venue"
},
  "geometry": {"coordinates":[-94.974737,46.119566],"type":"Point"}
}