{
  "type": "Feature",
  "properties": {
    "addr:full":"1318 W 47th St Minneapolis MN 55419",
    "addr:housenumber":"1318",
    "addr:postcode":"55419",
    "addr:street":"W 47Th St",
    "iso:country":"US",
    "sg:address":"1318 W 47th St",
    "sg:city":"Minneapolis",
    "sg:classifiers":[
        {
            "category":"Professional",
            "subcategory":"Computer Services",
            "type":"Services"
        }
    ],
    "sg:phone":"+1 612 823 2510",
    "sg:postcode":"55419",
    "sg:province":"MN",
    "sg:tags":[
        "software",
        "programing",
        "custom"
    ],
    "wof:name":"James R Teter",
    "wof:placetype":"venue"
},
  "geometry": {"coordinates":[-93.296184,44.91774],"type":"Point"}
}