{
  "type": "Feature",
  "properties": {
    "addr:full":"17948 Jaguar Path Lakeville MN 55044",
    "addr:housenumber":"17948",
    "addr:postcode":"55044",
    "addr:street":"Jaguar Path",
    "iso:country":"US",
    "sg:address":"17948 Jaguar Path",
    "sg:city":"Lakeville",
    "sg:classifiers":[
        {
            "category":"Airline",
            "type":"Transportation"
        }
    ],
    "sg:phone":"+1 952 892 3467",
    "sg:postcode":"55044",
    "sg:province":"MN",
    "sg:tags":[
        "nonscheduled",
        "air"
    ],
    "wof:name":"D&M Taildraggers Ltd",
    "wof:placetype":"venue"
},
  "geometry": {"coordinates":[-93.271906,44.689501],"type":"Point"}
}