{
  "type": "Feature",
  "properties": {
    "iso:country":"US",
    "sg:address":"13981 Industry Ave",
    "sg:city":"Becker",
    "sg:classifiers":[
        {
            "category":"Home & Garden",
            "subcategory":"Furniture",
            "type":"Retail Goods"
        }
    ],
    "sg:phone":"+1 763 261 5466",
    "sg:postcode":"55308",
    "sg:province":"MN",
    "sg:tags":[
        "cabinet"
    ],
    "sg:website":"www.goldenwoodcabinetry.com",
    "wof:name":"Goldenwood Cabinetry Inc",
    "wof:placetype":"venue"
},
  "geometry": {"coordinates":[-93.87655700000001,45.387173],"type":"Point"}
}