{
  "type": "Feature",
  "properties": {
    "addr:full":"516 Water St S Northfield MN 55057",
    "addr:housenumber":"516",
    "addr:postcode":"55057",
    "addr:street":"Water St S",
    "iso:country":"US",
    "sg:address":"516 Water St S",
    "sg:city":"Northfield",
    "sg:classifiers":[
        {
            "category":"Professional",
            "subcategory":"Lawyer & Legal Services",
            "type":"Services"
        }
    ],
    "sg:phone":"+1 507 645 0002",
    "sg:postcode":"55057",
    "sg:province":"MN",
    "sg:tags":[
        "attorney",
        "criminal",
        "business",
        "personal",
        "automobile",
        "practice",
        "damage",
        "accident",
        "injury",
        "property",
        "law"
    ],
    "sg:website":"http://www.fossumlaw.com",
    "wof:name":"Fossum Law Office",
    "wof:placetype":"venue"
},
  "geometry": {"coordinates":[-93.161671,44.454954],"type":"Point"}
}