{
  "type": "Feature",
  "properties": {
    "addr:full":"1607 E US Hwy 169 Grand Rapids MN 55744",
    "addr:housenumber":"1607",
    "addr:postcode":"55744",
    "addr:street":"E Us Hwy 169",
    "iso:country":"US",
    "sg:address":"1607 E US Hwy 169",
    "sg:city":"Grand Rapids",
    "sg:classifiers":[
        {
            "category":"Real Estate",
            "subcategory":"Real Estate Operator",
            "type":"Services"
        }
    ],
    "sg:phone":"+1 218 326 1898",
    "sg:postcode":"55744",
    "sg:province":"MN",
    "sg:tags":[
        "building",
        "apartment"
    ],
    "wof:name":"Wannigan Apartments",
    "wof:placetype":"venue"
},
  "geometry": {"coordinates":[-93.51811499999999,47.214759],"type":"Point"}
}