{
  "type": "Feature",
  "properties": {
    "iso:country":"US",
    "sg:address":"14000 Fairview Dr",
    "sg:city":"Burnsville",
    "sg:classifiers":[
        {
            "category":"Health Services",
            "subcategory":"Doctor",
            "type":"Services"
        }
    ],
    "sg:phone":"+1 952 993 8533",
    "sg:postcode":"55337",
    "sg:province":"MN",
    "sg:tags":[
        "physician",
        "surgeon"
    ],
    "wof:name":"Health Systems Park Nicollet",
    "wof:placetype":"venue"
},
  "geometry": {"coordinates":[-93.27460600000001,44.746499],"type":"Point"}
}