{
  "type": "Feature",
  "properties": {
    "addr:full":"2926 Oak Lea Dr Wayzata MN 55391",
    "addr:housenumber":"2926",
    "addr:postcode":"55391",
    "addr:street":"Oak Lea Dr",
    "iso:country":"US",
    "sg:address":"2926 Oak Lea Dr",
    "sg:city":"Wayzata",
    "sg:classifiers":[
        {
            "category":"Wholesale",
            "subcategory":"Electrical",
            "type":"Manufacturing & Wholesale Goods"
        }
    ],
    "sg:phone":"+1 952 938 7796",
    "sg:postcode":"55391",
    "sg:province":"MN",
    "sg:tags":[
        "measuring",
        "control",
        "security",
        "device",
        "system"
    ],
    "sg:website":"www.golfcst.com",
    "wof:name":"Golf Coast Products",
    "wof:placetype":"venue"
},
  "geometry": {"coordinates":[-93.464235,44.947829],"type":"Point"}
}