{
  "type": "Feature",
  "properties": {
    "addr:full":"333 Walker St Belgrade MN 56312",
    "addr:housenumber":"333",
    "addr:postcode":"56312",
    "addr:street":"Walker St",
    "iso:country":"US",
    "sg:address":"333 Walker St",
    "sg:city":"Belgrade",
    "sg:classifiers":[
        {
            "category":"Food & Beverages",
            "subcategory":"Groceries & Convenience Stores",
            "type":"Retail Goods"
        }
    ],
    "sg:phone":"+1 320 254 3422",
    "sg:postcode":"56312",
    "sg:province":"MN",
    "sg:tags":[
        "grocer"
    ],
    "wof:name":"L & L Family Foods",
    "wof:placetype":"venue"
},
  "geometry": {"coordinates":[-95.00176,45.453714],"type":"Point"}
}