{
  "type": "Feature",
  "properties": {
    "addr:full":"15491 225th Ave NE Hawick MN 56273",
    "addr:housenumber":"15491",
    "addr:postcode":"56273",
    "addr:street":"225Th Ave Ne",
    "iso:country":"US",
    "sg:address":"15491 225th Ave NE",
    "sg:city":"Hawick",
    "sg:classifiers":[
        {
            "category":"Farming",
            "subcategory":"Farm",
            "type":"Manufacturing & Wholesale Goods"
        }
    ],
    "sg:phone":"+1 320 276 8741",
    "sg:postcode":"56273",
    "sg:province":"MN",
    "wof:name":"Lost Valley Farms",
    "wof:placetype":"venue"
},
  "geometry": {"coordinates":[-94.83221899999999,45.340551],"type":"Point"}
}