{
  "type": "Feature",
  "properties": {
    "addr:full":"17248 80th Ave N Osseo MN 55311",
    "addr:housenumber":"17248",
    "addr:postcode":"55311",
    "addr:street":"80Th Ave N",
    "iso:country":"US",
    "sg:address":"17248 80th Ave N",
    "sg:city":"Osseo",
    "sg:classifiers":[
        {
            "category":"Manufacturing",
            "subcategory":"Glass & Minerals",
            "type":"Manufacturing & Wholesale Goods"
        }
    ],
    "sg:phone":"+1 763 416 1771",
    "sg:postcode":"55311",
    "sg:province":"MN",
    "sg:tags":[
        "ready",
        "concrete",
        "mfg"
    ],
    "wof:name":"Digital Mix",
    "wof:placetype":"venue"
},
  "geometry": {"coordinates":[-93.49973199999999,45.100536],"type":"Point"}
}