{
  "type": "Feature",
  "properties": {
    "iso:country":"US",
    "sg:address":"700 Cedar St",
    "sg:city":"Alexandria",
    "sg:classifiers":[
        {
            "category":"Social Services",
            "type":"Services"
        }
    ],
    "sg:phone":"+1 320 763 3538",
    "sg:postcode":"56308",
    "sg:province":"MN",
    "wof:name":"Catholic Charities",
    "wof:placetype":"venue"
},
  "geometry": {"coordinates":[-95.383731,45.884812],"type":"Point"}
}