{
  "type": "Feature",
  "properties": {
    "addr:full":"2451 160th St Granada MN 56039",
    "addr:housenumber":"2451",
    "addr:postcode":"56039",
    "addr:street":"160Th St",
    "iso:country":"US",
    "sg:address":"2451 160th St",
    "sg:city":"Granada",
    "sg:classifiers":[
        {
            "category":"Farming",
            "subcategory":"Livestock Farm",
            "type":"Manufacturing & Wholesale Goods"
        }
    ],
    "sg:phone":"+1 507 447 2219",
    "sg:postcode":"56039",
    "sg:province":"MN",
    "sg:tags":[
        "hog",
        "or",
        "feedlot"
    ],
    "wof:name":"Royce Abel",
    "wof:placetype":"venue"
},
  "geometry": {"coordinates":[-94.38122199999999,43.716905],"type":"Point"}
}