{
  "type": "Feature",
  "properties": {
    "addr:full":"38687 Co Rd 152 Albany MN 56307",
    "addr:housenumber":"152",
    "addr:postcode":"38687;56307",
    "addr:street":"Co Rd",
    "iso:country":"US",
    "sg:address":"38687 Co Rd 152",
    "sg:city":"Albany",
    "sg:phone":"+1 320 845 2904",
    "sg:postcode":"56307",
    "sg:province":"MN",
    "sg:tags":[
        "farm",
        "field",
        "crop"
    ],
    "wof:name":"Loren Lehner Farm",
    "wof:placetype":"venue"
},
  "geometry": {"coordinates":[-94.552415,45.680437],"type":"Point"}
}