{
  "type": "Feature",
  "properties": {
    "addr:full":"4525 Airport Rd Duluth MN 55811",
    "addr:housenumber":"4525",
    "addr:postcode":"55811",
    "addr:street":"Airport Rd",
    "iso:country":"US",
    "sg:address":"4525 Airport Rd",
    "sg:city":"Duluth",
    "sg:classifiers":[
        {
            "category":"Government",
            "subcategory":"Office",
            "type":"Public Place"
        }
    ],
    "sg:phone":"+1 218 722 7326",
    "sg:postcode":"55811",
    "sg:province":"MN",
    "sg:tags":[
        "federal",
        "aviation",
        "traffic"
    ],
    "wof:name":"Airport Traffic Control Tower",
    "wof:placetype":"venue"
},
  "geometry": {"coordinates":[-92.16971700000001,46.836581],"type":"Point"}
}