{
  "type": "Feature",
  "properties": {
    "addr:full":"1828 Marshall St NE Minneapolis MN 55418",
    "addr:housenumber":"1828",
    "addr:postcode":"55418",
    "addr:street":"Marshall St Ne",
    "iso:country":"US",
    "sg:address":"1828 Marshall St NE",
    "sg:city":"Minneapolis",
    "sg:classifiers":[
        {
            "category":"Shopping",
            "subcategory":"Florist",
            "type":"Retail Goods"
        }
    ],
    "sg:phone":"+1 612 788 8005",
    "sg:postcode":"55418",
    "sg:province":"MN",
    "wof:name":"Flower Outlet",
    "wof:placetype":"venue"
},
  "geometry": {"coordinates":[-93.271591,45.006843],"type":"Point"}
}