{
  "type": "Feature",
  "properties": {
    "addr:full":"10490 Lancaster Ln N Osseo MN 55369",
    "addr:housenumber":"10490",
    "addr:postcode":"55369",
    "addr:street":"Lancaster Ln N",
    "iso:country":"US",
    "sg:address":"10490 Lancaster Ln N",
    "sg:city":"Osseo",
    "sg:classifiers":[
        {
            "category":"Personal",
            "subcategory":"Beauty Salon",
            "type":"Services"
        }
    ],
    "sg:phone":"+1 763 424 8355",
    "sg:postcode":"55369",
    "sg:province":"MN",
    "sg:tags":[
        "shop"
    ],
    "wof:name":"Victorias Nailtique",
    "wof:placetype":"venue"
},
  "geometry": {"coordinates":[-93.402404,45.143321],"type":"Point"}
}