{
  "type": "Feature",
  "properties": {
    "addr:full":"100 2nd Ave N Sauk Rapids MN 56379",
    "addr:housenumber":"100",
    "addr:postcode":"56379",
    "addr:street":"2Nd Ave N Sauk",
    "iso:country":"US",
    "sg:address":"100 2nd Ave N",
    "sg:city":"Sauk Rapids",
    "sg:classifiers":[
        {
            "category":"Real Estate",
            "subcategory":"Real Estate Agent",
            "type":"Services"
        }
    ],
    "sg:phone":"+1 320 255 1911",
    "sg:postcode":"56379",
    "sg:province":"MN",
    "wof:name":"Century 21 Haller Realty",
    "wof:placetype":"venue"
},
  "geometry": {"coordinates":[-94.16707599999999,45.591221],"type":"Point"}
}