{
  "type": "Feature",
  "properties": {
    "iso:country":"US",
    "sg:address":"222 1st Ave NE",
    "sg:city":"Minneapolis",
    "sg:classifiers":[
        {
            "category":"Professional",
            "subcategory":"Business Services",
            "type":"Services"
        }
    ],
    "sg:phone":"+1 612 331 1972",
    "sg:postcode":"55413",
    "sg:province":"MN",
    "sg:tags":[
        "event"
    ],
    "wof:name":"Fire Barn Events Centre LLC",
    "wof:placetype":"venue"
},
  "geometry": {"coordinates":[-93.25724599999999,44.988835],"type":"Point"}
}