{
  "type": "Feature",
  "properties": {
    "addr:full":"11713 180th St Milaca MN 56353",
    "addr:housenumber":"11713",
    "addr:postcode":"56353",
    "addr:street":"180Th St",
    "iso:country":"US",
    "sg:address":"11713 180th St",
    "sg:city":"Milaca",
    "sg:classifiers":[
        {
            "category":"Retail",
            "subcategory":"Repair Shop",
            "type":"Services"
        },
        {
            "category":"Marine",
            "type":"Transportation"
        }
    ],
    "sg:phone":"+1 320 983 2970",
    "sg:postcode":"56353",
    "sg:province":"MN",
    "sg:tags":[
        "towing"
    ],
    "wof:name":"Mille Lacs Power Sports Inc",
    "wof:placetype":"venue"
},
  "geometry": {"coordinates":[-93.65412999999999,45.807674],"type":"Point"}
}