{
  "type": "Feature",
  "properties": {
    "addr:full":"229 2nd Ave W Halstad MN 56548",
    "addr:housenumber":"229",
    "addr:postcode":"56548",
    "addr:street":"2Nd Ave W",
    "iso:country":"US",
    "sg:address":"229 2nd Ave W",
    "sg:city":"Halstad",
    "sg:classifiers":[
        {
            "category":"Government",
            "subcategory":"Post Office",
            "type":"Public Place"
        }
    ],
    "sg:phone":"+1 218 456 2616",
    "sg:postcode":"56548",
    "sg:province":"MN",
    "wof:name":"US Post Office",
    "wof:placetype":"venue"
},
  "geometry": {"coordinates":[-96.82871400000001,47.352413],"type":"Point"}
}