{
  "type": "Feature",
  "properties": {
    "iso:country":"US",
    "sg:address":"29703 Lais Ave",
    "sg:city":"Rushmore",
    "sg:phone":"+1 507 683 2452",
    "sg:postcode":"56168",
    "sg:province":"MN",
    "sg:tags":[
        "farm",
        "corn",
        "soybean"
    ],
    "wof:name":"Gerrit Drost",
    "wof:placetype":"venue"
},
  "geometry": {"coordinates":[-95.73368000000001,43.562293],"type":"Point"}
}