{
  "type": "Feature",
  "properties": {
    "iso:country":"US",
    "sg:address":"2201 1st Ave N",
    "sg:city":"Moorhead",
    "sg:classifiers":[
        {
            "category":"Organizations",
            "subcategory":"Community Association",
            "type":"Services"
        }
    ],
    "sg:phone":"+1 218 233 6100",
    "sg:postcode":"56560",
    "sg:province":"MN",
    "sg:tags":[
        "military"
    ],
    "wof:name":"Veterans Of Foreign Wars",
    "wof:placetype":"venue"
},
  "geometry": {"coordinates":[-96.74688399999999,46.876223],"type":"Point"}
}