{
  "type": "Feature",
  "properties": {
    "addr:full":"840 Pioneer Dr Milaca MN 56353",
    "addr:housenumber":"840",
    "addr:postcode":"56353",
    "addr:street":"Pioneer Dr",
    "iso:country":"US",
    "sg:address":"840 Pioneer Dr",
    "sg:city":"Milaca",
    "sg:classifiers":[
        {
            "category":"Shopping",
            "type":"Retail Goods"
        },
        {
            "category":"Professional",
            "subcategory":"Business Services",
            "type":"Services"
        }
    ],
    "sg:phone":"+1 320 983 6007",
    "sg:postcode":"56353",
    "sg:province":"MN",
    "sg:tags":[
        "merchandise",
        "auctioneer"
    ],
    "wof:name":"Dutchman Auction Company",
    "wof:placetype":"venue"
},
  "geometry": {"coordinates":[-93.63719,45.750153],"type":"Point"}
}