{
  "type": "Feature",
  "properties": {
    "addr:full":"10860 Co Rd 118 Nisswa MN 56468",
    "addr:housenumber":"10860",
    "addr:postcode":"56468",
    "addr:street":"Co Rd 118",
    "iso:country":"US",
    "sg:address":"10860 Co Rd 118",
    "sg:city":"Nisswa",
    "sg:classifiers":[
        {
            "category":"Travel",
            "subcategory":"Campground",
            "type":"Entertainment"
        }
    ],
    "sg:phone":"+1 218 963 2222",
    "sg:postcode":"56468",
    "sg:province":"MN",
    "wof:name":"Minnesota Elk's Youth Camp",
    "wof:placetype":"venue"
},
  "geometry": {"coordinates":[-94.169532,46.533697],"type":"Point"}
}