{
  "type": "Feature",
  "properties": {
    "iso:country":"US",
    "sg:address":"1200 Main St NE",
    "sg:city":"Minneapolis",
    "sg:classifiers":[
        {
            "category":"Professional",
            "subcategory":"Computer Services",
            "type":"Services"
        }
    ],
    "sg:phone":"+1 952 933 2331",
    "sg:postcode":"55413",
    "sg:province":"MN",
    "sg:tags":[
        "planning",
        "disaster"
    ],
    "wof:name":"Constant Data Inc",
    "wof:placetype":"venue"
},
  "geometry": {"coordinates":[-93.267662,45.000876],"type":"Point"}
}