{
  "type": "Feature",
  "properties": {
    "iso:country":"US",
    "sg:address":"261 Elm Dr",
    "sg:city":"Foley",
    "sg:classifiers":[
        {
            "category":"Professional",
            "subcategory":"Management & Consulting",
            "type":"Services"
        }
    ],
    "sg:phone":"+1 320 968 4067",
    "sg:postcode":"56329",
    "sg:province":"MN",
    "sg:tags":[
        "business"
    ],
    "wof:name":"Analysis & Forensic Consulting",
    "wof:placetype":"venue"
},
  "geometry": {"coordinates":[-93.91367200000001,45.65645],"type":"Point"}
}