{
  "type": "Feature",
  "properties": {
    "addr:full":"11280 Dayton River Rd Dayton MN 55316",
    "addr:housenumber":"11280",
    "addr:postcode":"55316",
    "addr:street":"Dayton River Rd",
    "iso:country":"US",
    "sg:address":"11280 Dayton River Rd",
    "sg:city":"Dayton",
    "sg:classifiers":[
        {
            "category":"Building & Trades",
            "subcategory":"Plumbing",
            "type":"Services"
        }
    ],
    "sg:phone":"+1 763 323 0059",
    "sg:postcode":"55316",
    "sg:province":"MN",
    "sg:tags":[
        "contractor"
    ],
    "wof:name":"Heating & Air Conditioning Spe",
    "wof:placetype":"venue"
},
  "geometry": {"coordinates":[-93.422636,45.201583],"type":"Point"}
}