{
  "type": "Feature",
  "properties": {
    "iso:country":"US",
    "sg:address":"619 3rd Ave S",
    "sg:city":"St James",
    "sg:classifiers":[
        {
            "category":"Building & Trades",
            "subcategory":"Construction",
            "type":"Services"
        }
    ],
    "sg:phone":"+1 507 375 4738",
    "sg:postcode":"56081",
    "sg:province":"MN",
    "sg:tags":[
        "house",
        "general",
        "contractor"
    ],
    "wof:name":"Dorschner Construction",
    "wof:placetype":"venue"
},
  "geometry": {"coordinates":[-94.626002,43.980656],"type":"Point"}
}