{
  "type": "Feature",
  "properties": {
    "iso:country":"US",
    "sg:address":"807 18th Ave S",
    "sg:city":"St Cloud",
    "sg:classifiers":[
        {
            "category":"Wholesale",
            "subcategory":"Machinery & Supplies",
            "type":"Manufacturing & Wholesale Goods"
        }
    ],
    "sg:phone":"+1 320 255 1580",
    "sg:postcode":"56301",
    "sg:province":"MN",
    "sg:tags":[
        "janitor"
    ],
    "wof:name":"Minnesota Maintenance Supply",
    "wof:placetype":"venue"
},
  "geometry": {"coordinates":[-94.17508100000001,45.550747],"type":"Point"}
}