{
  "type": "Feature",
  "properties": {
    "iso:country":"US",
    "sg:address":"1034 1st Ave",
    "sg:city":"Worthington",
    "sg:classifiers":[
        {
            "category":"Railroad",
            "type":"Transportation"
        }
    ],
    "sg:phone":"+1 507 376 3160",
    "sg:postcode":"56187",
    "sg:province":"MN",
    "sg:tags":[
        "line"
    ],
    "wof:name":"Chicago & Northwestern Rr CO",
    "wof:placetype":"venue"
},
  "geometry": {"coordinates":[-95.59407299999999,43.61878],"type":"Point"}
}