{
  "type": "Feature",
  "properties": {
    "addr:full":"302 Edward St N Pierz MN 56364",
    "addr:housenumber":"302",
    "addr:postcode":"56364",
    "addr:street":"Edward St N",
    "iso:country":"US",
    "sg:address":"302 Edward St N",
    "sg:city":"Pierz",
    "sg:classifiers":[
        {
            "category":"Retail",
            "subcategory":"Auto Repair",
            "type":"Services"
        }
    ],
    "sg:phone":"+1 320 468 2419",
    "sg:postcode":"56364",
    "sg:province":"MN",
    "sg:tags":[
        "general"
    ],
    "wof:name":"Bills Auto & Small Engine",
    "wof:placetype":"venue"
},
  "geometry": {"coordinates":[-94.10249399999999,45.983373],"type":"Point"}
}