{
  "type": "Feature",
  "properties": {
    "iso:country":"US",
    "sg:address":"701 4th Ave S",
    "sg:city":"Minneapolis",
    "sg:classifiers":[
        {
            "category":"Professional",
            "subcategory":"Lawyer & Legal Services",
            "type":"Services"
        }
    ],
    "sg:phone":"+1 612 573 2000",
    "sg:postcode":"55415",
    "sg:province":"MN",
    "sg:tags":[
        "attorney"
    ],
    "sg:website":"www.dbclaw.com",
    "wof:name":"Dicke Billig & Czaja",
    "wof:placetype":"venue"
},
  "geometry": {"coordinates":[-93.26759199999999,44.973621],"type":"Point"}
}