{
  "type": "Feature",
  "properties": {
    "addr:full":"24375 170th Ave NW Viking MN 56760",
    "addr:housenumber":"24375",
    "addr:postcode":"56760",
    "addr:street":"170Th Ave Nw Viking",
    "iso:country":"US",
    "sg:address":"24375 170th Ave NW",
    "sg:city":"Viking",
    "sg:classifiers":[
        {
            "category":"Farming",
            "subcategory":"Farm & Veterinary Services",
            "type":"Manufacturing & Wholesale Goods"
        }
    ],
    "sg:phone":"+1 218 523 3363",
    "sg:postcode":"56760",
    "sg:province":"MN",
    "sg:tags":[
        "crop",
        "harvesting"
    ],
    "wof:name":"Gene Nelson Farm",
    "wof:placetype":"venue"
},
  "geometry": {"coordinates":[-96.412041,48.22854],"type":"Point"}
}