{
  "type": "Feature",
  "properties": {
    "iso:country":"US",
    "sg:address":"100 Co Rd 35",
    "sg:city":"Adrian",
    "sg:classifiers":[
        {
            "category":"Building & Trades",
            "subcategory":"Construction",
            "type":"Services"
        }
    ],
    "sg:phone":"+1 507 483 2690",
    "sg:postcode":"56110",
    "sg:province":"MN",
    "sg:tags":[
        "concrete",
        "contractor"
    ],
    "wof:name":"Adrian Ready Mix",
    "wof:placetype":"venue"
},
  "geometry": {"coordinates":[-95.93312899999999,43.637999],"type":"Point"}
}