{
  "type": "Feature",
  "properties": {
    "addr:full":"10116 Zenith Rd Minneapolis MN 55431",
    "addr:housenumber":"10116",
    "addr:postcode":"55431",
    "addr:street":"Zenith Rd",
    "iso:country":"US",
    "sg:address":"10116 Zenith Rd",
    "sg:city":"Minneapolis",
    "sg:classifiers":[
        {
            "category":"Professional",
            "subcategory":"Accounting & Tax Preparation",
            "type":"Services"
        }
    ],
    "sg:phone":"+1 952 893 0205",
    "sg:postcode":"55431",
    "sg:province":"MN",
    "wof:name":"Jes Accounting",
    "wof:placetype":"venue"
},
  "geometry": {"coordinates":[-93.322335,44.820175],"type":"Point"}
}