{
  "type": "Feature",
  "properties": {
    "iso:country":"US",
    "sg:address":"25525 Orchard Cir",
    "sg:city":"Excelsior",
    "sg:classifiers":[
        {
            "category":"Wholesale",
            "subcategory":"Wine & Distilled Alcoholic Beverages",
            "type":"Manufacturing & Wholesale Goods"
        }
    ],
    "sg:phone":"+1 952 470 4952",
    "sg:postcode":"55331",
    "sg:province":"MN",
    "wof:name":"Village Wine Imports LLC",
    "wof:placetype":"venue"
},
  "geometry": {"coordinates":[-93.60402000000001,44.907007],"type":"Point"}
}