{
  "type": "Feature",
  "properties": {
    "addr:full":"21405 Hamburg Ave Lakeville MN 55044",
    "addr:postcode":"21405;55044",
    "addr:street":"Hamburg Ave",
    "iso:country":"US",
    "sg:address":"21405 Hamburg Ave",
    "sg:city":"Lakeville",
    "sg:classifiers":[
        {
            "category":"Manufacturing",
            "subcategory":"Rubber & Plastics",
            "type":"Manufacturing & Wholesale Goods"
        }
    ],
    "sg:phone":"+1 952 469 5474",
    "sg:postcode":"55044",
    "sg:province":"MN",
    "sg:tags":[
        "product",
        "mfg"
    ],
    "wof:name":"Acrylic Technology Inc",
    "wof:placetype":"venue"
},
  "geometry": {"coordinates":[-93.227802,44.638135],"type":"Point"}
}