{
  "type": "Feature",
  "properties": {
    "iso:country":"US",
    "sg:address":"210 Wright St",
    "sg:city":"Monticello",
    "sg:classifiers":[
        {
            "category":"Building & Trades",
            "subcategory":"Construction",
            "type":"Services"
        }
    ],
    "sg:phone":"+1 763 295 2443",
    "sg:postcode":"55362",
    "sg:province":"MN",
    "sg:tags":[
        "maker",
        "cabinet"
    ],
    "wof:name":"Walters Cabinet Shop",
    "wof:placetype":"venue"
},
  "geometry": {"coordinates":[-93.78791099999999,45.303415],"type":"Point"}
}