{
  "type": "Feature",
  "properties": {
    "iso:country":"US",
    "sg:address":"555 30th Ave W",
    "sg:city":"Alexandria",
    "sg:classifiers":[
        {
            "category":"Manufacturing",
            "subcategory":"Glass & Minerals",
            "type":"Manufacturing & Wholesale Goods"
        },
        {
            "category":"Retail",
            "subcategory":"Auto Repair",
            "type":"Services"
        }
    ],
    "sg:phone":"+1 888 668 1837",
    "sg:postcode":"56308",
    "sg:province":"MN",
    "sg:tags":[
        "plate",
        "window",
        "windshield",
        "glass-auto"
    ],
    "sg:website":"http://local.ingenio.com/Listings/Details.aspx?NUM=a%3a9247697%3a13%3a4859924%3a14%3a0%3a7",
    "wof:name":"Interstate Auto Glass",
    "wof:placetype":"venue"
},
  "geometry": {"coordinates":[-95.383866,45.862873],"type":"Point"}
}