{
  "type": "Feature",
  "properties": {
    "addr:full":"41776 200th St East Grand Forks MN 56751",
    "addr:housenumber":"41776",
    "addr:postcode":"56751",
    "addr:street":"200Th St",
    "iso:country":"US",
    "sg:address":"41776 200th St",
    "sg:city":"East Grand Forks",
    "sg:classifiers":[
        {
            "category":"Professional",
            "subcategory":"Engineering",
            "type":"Services"
        }
    ],
    "sg:phone":"+1 218 773 3621",
    "sg:postcode":"56751",
    "sg:province":"MN",
    "sg:tags":[
        "consulting",
        "engineer"
    ],
    "wof:name":"Jack and Faiths",
    "wof:placetype":"venue"
},
  "geometry": {"coordinates":[-95.696251,48.68475],"type":"Point"}
}