{
  "type": "Feature",
  "properties": {
    "iso:country":"US",
    "sg:address":"13654 90th St S",
    "sg:city":"Hastings",
    "sg:classifiers":[
        {
            "category":"Wholesale",
            "subcategory":"Auto Parts",
            "type":"Manufacturing & Wholesale Goods"
        }
    ],
    "sg:phone":"+1 651 436 8121",
    "sg:postcode":"55033",
    "sg:province":"MN",
    "sg:tags":[
        "used"
    ],
    "wof:name":"Brede Auto Salvage",
    "wof:placetype":"venue"
},
  "geometry": {"coordinates":[-92.827488,44.818876],"type":"Point"}
}