{
  "type": "Feature",
  "properties": {
    "iso:country":"US",
    "sg:address":"1308 9th Ave S",
    "sg:city":"South Saint Paul",
    "sg:classifiers":[
        {
            "category":"Social Services",
            "subcategory":"Child Care",
            "type":"Services"
        }
    ],
    "sg:phone":"+1 651 455 4191",
    "sg:postcode":"55075",
    "sg:province":"MN",
    "sg:tags":[
        "day"
    ],
    "wof:name":"Dolores Willenbring",
    "wof:placetype":"venue"
},
  "geometry": {"coordinates":[-93.04501999999999,44.867448],"type":"Point"}
}