{
  "type": "Feature",
  "properties": {
    "iso:country":"US",
    "sg:address":"2728 118th Ct NE",
    "sg:city":"Minneapolis",
    "sg:classifiers":[
        {
            "category":"Banks & Credit Unions",
            "subcategory":"Financial Services",
            "type":"Services"
        }
    ],
    "sg:phone":"+1 763 205 3388",
    "sg:postcode":"55449",
    "sg:province":"MN",
    "sg:tags":[
        "loan"
    ],
    "sg:website":"http://www.btkroll.com",
    "wof:name":"Win Win Home Loans Inc",
    "wof:placetype":"venue"
},
  "geometry": {"coordinates":[-93.202214,45.183261],"type":"Point"}
}