{
  "type": "Feature",
  "properties": {
    "addr:full":"9334 Ensign Ave S Minneapolis MN 55438",
    "addr:housenumber":"9334",
    "addr:postcode":"55438",
    "addr:street":"Ensign Ave S",
    "iso:country":"US",
    "sg:address":"9334 Ensign Ave S",
    "sg:city":"Minneapolis",
    "sg:classifiers":[
        {
            "category":"Personal",
            "subcategory":"Massage",
            "type":"Services"
        },
        {
            "category":"Personal",
            "subcategory":"Beauty Salon",
            "type":"Services"
        },
        {
            "category":"Personal",
            "subcategory":"Day Spa",
            "type":"Services"
        },
        {
            "category":"Personal",
            "subcategory":"Skin Care",
            "type":"Services"
        },
        {
            "category":"Personal",
            "subcategory":"Nail Salon",
            "type":"Services"
        }
    ],
    "sg:phone":"+1 952 941 6804",
    "sg:postcode":"55438",
    "sg:province":"MN",
    "sg:tags":[
        "therapist"
    ],
    "sg:website":"http://www.vogue-salon.com",
    "wof:name":"Vogue Salons",
    "wof:placetype":"venue"
},
  "geometry": {"coordinates":[-93.397648,44.832461],"type":"Point"}
}