{
  "type": "Feature",
  "properties": {
    "iso:country":"US",
    "sg:address":"11678 Springbrook Dr",
    "sg:city":"Swanville",
    "sg:classifiers":[
        {
            "category":"Farming",
            "subcategory":"Poultry Farm",
            "type":"Manufacturing & Wholesale Goods"
        }
    ],
    "sg:phone":"+1 320 547 2336",
    "sg:postcode":"56382",
    "sg:province":"MN",
    "sg:tags":[
        "turkey"
    ],
    "wof:name":"Gessell Turkey Farms",
    "wof:placetype":"venue"
},
  "geometry": {"coordinates":[-94.634103,45.930545],"type":"Point"}
}