{
  "type": "Feature",
  "properties": {
    "addr:full":"6442 Lyndale Ave S Minneapolis MN 55423",
    "addr:housenumber":"6442",
    "addr:postcode":"55423",
    "addr:street":"Lyndale Ave S",
    "iso:country":"US",
    "sg:address":"6442 Lyndale Ave S",
    "sg:city":"Minneapolis",
    "sg:classifiers":[
        {
            "category":"Shopping",
            "type":"Retail Goods"
        }
    ],
    "sg:phone":"+1 612 869 4445",
    "sg:postcode":"55423",
    "sg:province":"MN",
    "sg:tags":[
        "equipment",
        "beer",
        "supply"
    ],
    "wof:name":"Barkingside Co",
    "wof:placetype":"venue"
},
  "geometry": {"coordinates":[-93.286874,44.885898],"type":"Point"}
}