{
  "type": "Feature",
  "properties": {
    "addr:full":"1061 Bluff Pass S Chaska MN 55318",
    "addr:housenumber":"1061",
    "addr:postcode":"55318",
    "addr:street":"Bluff Pass S Chaska",
    "iso:country":"US",
    "sg:address":"1061 Bluff Pass S",
    "sg:city":"Chaska",
    "sg:classifiers":[
        {
            "category":"Manufacturing",
            "subcategory":"Printing",
            "type":"Manufacturing & Wholesale Goods"
        }
    ],
    "sg:phone":"+1 612 718 2399",
    "sg:postcode":"55318",
    "sg:province":"MN",
    "sg:tags":[
        "publishing",
        "desktop"
    ],
    "wof:name":"Sight Bytes",
    "wof:placetype":"venue"
},
  "geometry": {"coordinates":[-93.575294,44.81533],"type":"Point"}
}