{
  "type": "Feature",
  "properties": {
    "addr:full":"317 Main St Lakefield MN 56150",
    "addr:housenumber":"317",
    "addr:postcode":"56150",
    "addr:street":"Main St",
    "iso:country":"US",
    "sg:address":"317 Main St",
    "sg:city":"Lakefield",
    "sg:classifiers":[
        {
            "category":"Professional",
            "subcategory":"Lawyer & Legal Services",
            "type":"Services"
        }
    ],
    "sg:phone":"+1 507 662 5852",
    "sg:postcode":"56150",
    "sg:province":"MN",
    "sg:tags":[
        "attorney"
    ],
    "wof:name":"Handevidt & Anderson Law Ofc",
    "wof:placetype":"venue"
},
  "geometry": {"coordinates":[-95.172113,43.678355],"type":"Point"}
}