{
  "type": "Feature",
  "properties": {
    "addr:full":"25645 Valley Wood Ln Excelsior MN 55331",
    "addr:housenumber":"25645",
    "addr:postcode":"55331",
    "addr:street":"Valley Wood Ln",
    "iso:country":"US",
    "sg:address":"25645 Valley Wood Ln",
    "sg:city":"Excelsior",
    "sg:classifiers":[
        {
            "category":"Manufacturing",
            "subcategory":"Printing",
            "type":"Manufacturing & Wholesale Goods"
        }
    ],
    "sg:phone":"+1 952 474 4156",
    "sg:postcode":"55331",
    "sg:province":"MN",
    "sg:tags":[
        "lithographic",
        "commercial"
    ],
    "wof:name":"Konicki Custom Imprints",
    "wof:placetype":"venue"
},
  "geometry": {"coordinates":[-93.60686800000001,44.904221],"type":"Point"}
}