{
  "type": "Feature",
  "properties": {
    "iso:country":"US",
    "sg:address":"20168 Little Bear Lake Rd",
    "sg:city":"Cook",
    "sg:classifiers":[
        {
            "category":"Wholesale",
            "subcategory":"Machinery & Supplies",
            "type":"Manufacturing & Wholesale Goods"
        }
    ],
    "sg:phone":"+1 218 777 4263",
    "sg:postcode":"55723",
    "sg:province":"MN",
    "sg:tags":[
        "equipment",
        "establishment"
    ],
    "wof:name":"Game Preserve Taxidermy Studio",
    "wof:placetype":"venue"
},
  "geometry": {"coordinates":[-93.28362799999999,47.69904],"type":"Point"}
}