{
  "type": "Feature",
  "properties": {
    "iso:country":"US",
    "sg:address":"19841 State 226",
    "sg:city":"Park Rapids",
    "sg:classifiers":[
        {
            "category":"Shopping",
            "subcategory":"Gifts & Souvenirs",
            "type":"Retail Goods"
        }
    ],
    "sg:phone":"+1 218 732 1192",
    "sg:postcode":"56470",
    "sg:province":"MN",
    "sg:tags":[
        "shop"
    ],
    "wof:name":"Moose Crossing",
    "wof:placetype":"venue"
},
  "geometry": {"coordinates":[-94.952932,46.947016],"type":"Point"}
}