{
  "type": "Feature",
  "properties": {
    "addr:full":"2252 Tower Ct Saint Paul MN 55125",
    "addr:housenumber":"2252",
    "addr:postcode":"55125",
    "addr:street":"Tower Ct",
    "iso:country":"US",
    "sg:address":"2252 Tower Ct",
    "sg:city":"Saint Paul",
    "sg:classifiers":[
        {
            "category":"Building & Trades",
            "subcategory":"Construction",
            "type":"Services"
        }
    ],
    "sg:phone":"+1 651 738 3959",
    "sg:postcode":"55125",
    "sg:province":"MN",
    "sg:tags":[
        "house"
    ],
    "wof:name":"Chad Olson Construction",
    "wof:placetype":"venue"
},
  "geometry": {"coordinates":[-92.945618,44.916468],"type":"Point"}
}