{
  "type": "Feature",
  "properties": {
    "addr:full":"1535 Livingston Ave Saint Paul MN 55118",
    "addr:housenumber":"1535",
    "addr:postcode":"55118",
    "addr:street":"Livingston Ave",
    "iso:country":"US",
    "sg:address":"1535 Livingston Ave",
    "sg:city":"Saint Paul",
    "sg:classifiers":[
        {
            "category":"Personal",
            "type":"Services"
        }
    ],
    "sg:phone":"+1 651 455 0473",
    "sg:postcode":"55118",
    "sg:province":"MN",
    "wof:name":"Center For A Balanced Life",
    "wof:placetype":"venue"
},
  "geometry": {"coordinates":[-93.08242,44.899682],"type":"Point"}
}