{
  "type": "Feature",
  "properties": {
    "iso:country":"US",
    "sg:address":"30300 Mower Freeborn Rd",
    "sg:city":"Austin",
    "sg:classifiers":[
        {
            "category":"Farming",
            "subcategory":"Farm",
            "type":"Manufacturing & Wholesale Goods"
        }
    ],
    "sg:phone":"+1 507 433 4036",
    "sg:postcode":"55912",
    "sg:province":"MN",
    "sg:tags":[
        "crop",
        "general"
    ],
    "wof:name":"Orville Thompson",
    "wof:placetype":"venue"
},
  "geometry": {"coordinates":[-93.049504,43.795842],"type":"Point"}
}