{
  "type": "Feature",
  "properties": {
    "iso:country":"US",
    "sg:address":"3324 Promenade Ave",
    "sg:city":"Eagan",
    "sg:classifiers":[
        {
            "category":"Shopping",
            "subcategory":"Clothing, Apparel, & Fashions",
            "type":"Retail Goods"
        }
    ],
    "sg:phone":"+1 651 994 9382",
    "sg:postcode":"55121",
    "sg:province":"MN",
    "sg:tags":[
        "item",
        "boutique"
    ],
    "wof:name":"Claire's Boutiques",
    "wof:placetype":"venue"
},
  "geometry": {"coordinates":[-93.15422700000001,44.838289],"type":"Point"}
}