{
  "type": "Feature",
  "properties": {
    "iso:country":"US",
    "sg:address":"8313 Quadrant Ave S",
    "sg:city":"Hastings",
    "sg:classifiers":[
        {
            "category":"Professional",
            "subcategory":"Art Services",
            "type":"Services"
        }
    ],
    "sg:phone":"+1 651 998 0806",
    "sg:postcode":"55033",
    "sg:province":"MN",
    "sg:tags":[
        "designer",
        "display",
        "producer"
    ],
    "wof:name":"St Croix Design",
    "wof:placetype":"venue"
},
  "geometry": {"coordinates":[-92.78023,44.823498],"type":"Point"}
}