{
  "type": "Feature",
  "properties": {
    "addr:full":"1405 Mayflower Dr Northfield MN 55057",
    "addr:housenumber":"1405",
    "addr:postcode":"55057",
    "addr:street":"Mayflower Dr",
    "iso:country":"US",
    "sg:address":"1405 Mayflower Dr",
    "sg:city":"Northfield",
    "sg:classifiers":[
        {
            "category":"Professional",
            "type":"Services"
        }
    ],
    "sg:phone":"+1 507 645 5110",
    "sg:postcode":"55057",
    "sg:province":"MN",
    "wof:name":"Pams Collection",
    "wof:placetype":"venue"
},
  "geometry": {"coordinates":[-93.13796499999999,44.452379],"type":"Point"}
}