{
  "type": "Feature",
  "properties": {
    "addr:full":"1049 89th Ave NW Minneapolis MN 55433",
    "addr:housenumber":"1049",
    "addr:postcode":"55433",
    "addr:street":"89Th Ave Nw",
    "iso:country":"US",
    "sg:address":"1049 89th Ave NW",
    "sg:city":"Minneapolis",
    "sg:classifiers":[
        {
            "category":"Retail",
            "subcategory":"Repair Shop",
            "type":"Services"
        }
    ],
    "sg:phone":"+1 763 784 5625",
    "sg:postcode":"55433",
    "sg:province":"MN",
    "sg:tags":[
        "sporting"
    ],
    "wof:name":"Apache Lock & Key Shop",
    "wof:placetype":"venue"
},
  "geometry": {"coordinates":[-93.29364099999999,45.131738],"type":"Point"}
}