{
  "type": "Feature",
  "properties": {
    "iso:country":"US",
    "sg:address":"414 W Forest Ave",
    "sg:city":"Warren",
    "sg:phone":"+1 218 745 4018",
    "sg:postcode":"56762",
    "sg:province":"MN",
    "sg:tags":[
        "food",
        "farm",
        "product",
        "wheat",
        "soybean"
    ],
    "wof:name":"Gerald Jevning",
    "wof:placetype":"venue"
},
  "geometry": {"coordinates":[-96.78107300000001,48.194146],"type":"Point"}
}