{
  "type": "Feature",
  "properties": {
    "addr:full":"150 S 5th St Minneapolis MN 55402",
    "addr:housenumber":"150",
    "addr:postcode":"55402",
    "addr:street":"S 5Th St",
    "iso:country":"US",
    "sg:address":"150 S 5th St",
    "sg:city":"Minneapolis",
    "sg:classifiers":[
        {
            "category":"Professional",
            "subcategory":"Lawyer & Legal Services",
            "type":"Services"
        }
    ],
    "sg:phone":"+1 612 672 3604",
    "sg:postcode":"55402",
    "sg:province":"MN",
    "sg:tags":[
        "plan"
    ],
    "wof:name":"Nathan J Nelson Atty",
    "wof:placetype":"venue"
},
  "geometry": {"coordinates":[-93.268174,44.977762],"type":"Point"}
}