{
  "type": "Feature",
  "properties": {
    "addr:full":"22 E 15th St Minneapolis MN 55403",
    "addr:housenumber":"22",
    "addr:postcode":"55403",
    "addr:street":"E 15Th St",
    "iso:country":"US",
    "sg:address":"22 E 15th St",
    "sg:city":"Minneapolis",
    "sg:classifiers":[
        {
            "category":"Organizations",
            "subcategory":"Religious Organization",
            "type":"Services"
        }
    ],
    "sg:phone":"+1 612 871 6146",
    "sg:postcode":"55403",
    "sg:province":"MN",
    "wof:name":"Minnesota Minneapolis Mission",
    "wof:placetype":"venue"
},
  "geometry": {"coordinates":[-93.276652,44.968174],"type":"Point"}
}