{
  "type": "Feature",
  "properties": {
    "iso:country":"US",
    "sg:address":"81 9th St S",
    "sg:city":"Minneapolis",
    "sg:classifiers":[
        {
            "category":"Professional",
            "subcategory":"Lawyer & Legal Services",
            "type":"Services"
        }
    ],
    "sg:phone":"+1 612 339 3500",
    "sg:postcode":"55402",
    "sg:province":"MN",
    "sg:tags":[
        "attorney"
    ],
    "wof:name":"Arthur Chapman Kettering",
    "wof:placetype":"venue"
},
  "geometry": {"coordinates":[-93.273027,44.974538],"type":"Point"}
}