{
  "type": "Feature",
  "properties": {
    "iso:country":"US",
    "sg:address":"15033 330th Ave",
    "sg:city":"Winnebago",
    "sg:classifiers":[
        {
            "category":"Real Estate",
            "subcategory":"Real Estate Operator",
            "type":"Services"
        }
    ],
    "sg:phone":"+1 507 866 4632",
    "sg:postcode":"56098",
    "sg:province":"MN",
    "sg:tags":[
        "property",
        "lessor"
    ],
    "wof:name":"Charles Nilson",
    "wof:placetype":"venue"
},
  "geometry": {"coordinates":[-94.20736100000001,43.702992],"type":"Point"}
}