{
  "type": "Feature",
  "properties": {
    "addr:full":"520 Walnut St Monticello MN 55362",
    "addr:housenumber":"520",
    "addr:postcode":"55362",
    "addr:street":"Walnut St",
    "iso:country":"US",
    "sg:address":"520 Walnut St",
    "sg:city":"Monticello",
    "sg:classifiers":[
        {
            "category":"Real Estate",
            "subcategory":"Real Estate Services",
            "type":"Services"
        }
    ],
    "sg:phone":"+1 763 295 9505",
    "sg:postcode":"55362",
    "sg:province":"MN",
    "sg:tags":[
        "company",
        "title"
    ],
    "wof:name":"American Hometown Title",
    "wof:placetype":"venue"
},
  "geometry": {"coordinates":[-93.798311,45.302155],"type":"Point"}
}