{
  "type": "Feature",
  "properties": {
    "addr:full":"5701 Kentucky Ave N Crystal MN 55428",
    "addr:housenumber":"5701",
    "addr:postcode":"55428",
    "addr:street":"Kentucky Ave N",
    "iso:country":"US",
    "sg:address":"5701 Kentucky Ave N",
    "sg:city":"Crystal",
    "sg:classifiers":[
        {
            "category":"Professional",
            "subcategory":"Business Services",
            "type":"Services"
        }
    ],
    "sg:phone":"+1 763 531 9110",
    "sg:postcode":"55428",
    "sg:province":"MN",
    "sg:tags":[
        "telemarketing"
    ],
    "wof:name":"Lead Store Inc",
    "wof:placetype":"venue"
},
  "geometry": {"coordinates":[-93.369072,45.058215],"type":"Point"}
}