{
  "type": "Feature",
  "properties": {
    "addr:full":"35132 Kestrel Ave Mc Gregor MN 55760",
    "addr:housenumber":"35132",
    "addr:postcode":"55760",
    "addr:street":"Kestrel Ave",
    "iso:country":"US",
    "sg:address":"35132 Kestrel Ave",
    "sg:city":"Mc Gregor",
    "sg:classifiers":[
        {
            "category":"Farming",
            "subcategory":"Nursery",
            "type":"Manufacturing & Wholesale Goods"
        }
    ],
    "sg:phone":"+1 218 768 4144",
    "sg:postcode":"55760",
    "sg:province":"MN",
    "sg:tags":[
        "ornamental"
    ],
    "wof:name":"Beldens Nursery Green House",
    "wof:placetype":"venue"
},
  "geometry": {"coordinates":[-93.166326,46.520495],"type":"Point"}
}