{
  "type": "Feature",
  "properties": {
    "iso:country":"US",
    "sg:address":"1422 S Minnesota St",
    "sg:city":"New Ulm",
    "sg:classifiers":[
        {
            "category":"Wholesale",
            "subcategory":"Machinery & Supplies",
            "type":"Manufacturing & Wholesale Goods"
        }
    ],
    "sg:phone":"+1 507 354 4216",
    "sg:postcode":"56073",
    "sg:province":"MN",
    "sg:tags":[
        "contractor"
    ],
    "wof:name":"Carroll Distributing Co",
    "wof:placetype":"venue"
},
  "geometry": {"coordinates":[-94.445761,44.299318],"type":"Point"}
}