{
  "type": "Feature",
  "properties": {
    "addr:full":"123 1st Ave Jackson MN 56143",
    "addr:housenumber":"123",
    "addr:postcode":"56143",
    "addr:street":"1St Ave",
    "iso:country":"US",
    "sg:address":"123 1st Ave",
    "sg:city":"Jackson",
    "sg:classifiers":[
        {
            "category":"Professional",
            "subcategory":"Management & Consulting",
            "type":"Services"
        }
    ],
    "sg:phone":"+1 507 847 4112",
    "sg:postcode":"56143",
    "sg:province":"MN",
    "sg:tags":[
        "business"
    ],
    "wof:name":"BJ Pursuits Inc",
    "wof:placetype":"venue"
},
  "geometry": {"coordinates":[-94.97942,43.616524],"type":"Point"}
}