{
  "type": "Feature",
  "properties": {
    "iso:country":"US",
    "sg:address":"7225 132nd St W",
    "sg:city":"Saint Paul",
    "sg:classifiers":[
        {
            "category":"Building & Trades",
            "subcategory":"Landscaping Services",
            "type":"Services"
        }
    ],
    "sg:phone":"+1 952 891 3483",
    "sg:postcode":"55124",
    "sg:province":"MN",
    "wof:name":"Steelsman Lawn Service",
    "wof:placetype":"venue"
},
  "geometry": {"coordinates":[-93.21209500000001,44.757379],"type":"Point"}
}