{
  "type": "Feature",
  "properties": {
    "iso:country":"US",
    "sg:address":"28375 710th Ave",
    "sg:city":"Redwood Falls",
    "sg:classifiers":[
        {
            "category":"Farming",
            "subcategory":"Farm",
            "type":"Manufacturing & Wholesale Goods"
        }
    ],
    "sg:phone":"+1 507 641 5903",
    "sg:postcode":"56283",
    "sg:province":"MN",
    "sg:tags":[
        "crop",
        "general"
    ],
    "wof:name":"Mor-Pork Inc",
    "wof:placetype":"venue"
},
  "geometry": {"coordinates":[-95.1097,44.614107],"type":"Point"}
}