{
  "type": "Feature",
  "properties": {
    "iso:country":"US",
    "sg:address":"1200 Glenwood Ave",
    "sg:city":"Minneapolis",
    "sg:classifiers":[
        {
            "category":"Autos & Motor Vehicles",
            "subcategory":"Auto Supplies",
            "type":"Retail Goods"
        }
    ],
    "sg:phone":"+1 612 377 4900",
    "sg:postcode":"55405",
    "sg:province":"MN",
    "sg:tags":[
        "tire"
    ],
    "wof:name":"NW Tire Co Inc of Mpls",
    "wof:placetype":"venue"
},
  "geometry": {"coordinates":[-93.296097,44.980598],"type":"Point"}
}