{
  "type": "Feature",
  "properties": {
    "iso:country":"US",
    "sg:address":"26154 State Hwy 13",
    "sg:city":"Albert Lea",
    "sg:classifiers":[
        {
            "category":"Building & Trades",
            "subcategory":"Cleaning & Sanitation",
            "type":"Services"
        },
        {
            "category":"Utilities",
            "type":"Services"
        }
    ],
    "sg:phone":"+1 507 826 3358",
    "sg:postcode":"56007",
    "sg:province":"MN",
    "sg:tags":[
        "sanitary",
        "snow",
        "removal"
    ],
    "wof:name":"Mark's Snowplowing",
    "wof:placetype":"venue"
},
  "geometry": {"coordinates":[-93.44880999999999,43.727672],"type":"Point"}
}