{
  "type": "Feature",
  "properties": {
    "addr:full":"4101 W Division St St Cloud MN 56301",
    "addr:housenumber":"4101",
    "addr:postcode":"56301",
    "addr:street":"W Division St",
    "iso:country":"US",
    "sg:address":"4101 W Division St",
    "sg:city":"St Cloud",
    "sg:classifiers":[
        {
            "category":"Utilities",
            "subcategory":"Mobile Phone",
            "type":"Services"
        }
    ],
    "sg:phone":"+1 320 255 9388",
    "sg:postcode":"56301",
    "sg:province":"MN",
    "sg:tags":[
        "telephone",
        "cellular"
    ],
    "wof:name":"Radio Shack",
    "wof:placetype":"venue"
},
  "geometry": {"coordinates":[-94.21331499999999,45.553492],"type":"Point"}
}