{
  "type": "Feature",
  "properties": {
    "iso:country":"US",
    "sg:address":"5048 Clear Spring Rd",
    "sg:city":"Minnetonka",
    "sg:classifiers":[
        {
            "category":"Real Estate",
            "subcategory":"Architect",
            "type":"Services"
        }
    ],
    "sg:phone":"+1 952 933 0684",
    "sg:postcode":"55345",
    "sg:province":"MN",
    "sg:tags":[
        "architectural"
    ],
    "wof:name":"Design Plus",
    "wof:placetype":"venue"
},
  "geometry": {"coordinates":[-93.49611400000001,44.913959],"type":"Point"}
}