{
  "type": "Feature",
  "properties": {
    "iso:country":"US",
    "sg:address":"2899 50th St S",
    "sg:city":"Moorhead",
    "sg:classifiers":[
        {
            "category":"Social Services",
            "subcategory":"Child Care",
            "type":"Services"
        }
    ],
    "sg:phone":"+1 218 233 1133",
    "sg:postcode":"56560",
    "sg:province":"MN",
    "sg:tags":[
        "day",
        "provider"
    ],
    "wof:name":"Candice R Christman",
    "wof:placetype":"venue"
},
  "geometry": {"coordinates":[-96.693949,46.845928],"type":"Point"}
}