{
  "type": "Feature",
  "properties": {
    "iso:country":"US",
    "sg:address":"17845 Powderhorn Dr",
    "sg:city":"Minnetonka",
    "sg:classifiers":[
        {
            "category":"Insurance",
            "subcategory":"Insurance Agent",
            "type":"Services"
        }
    ],
    "sg:phone":"+1 952 474 0823",
    "sg:postcode":"55345",
    "sg:province":"MN",
    "sg:tags":[
        "security"
    ],
    "wof:name":"Moen",
    "wof:placetype":"venue"
},
  "geometry": {"coordinates":[-93.505489,44.928726],"type":"Point"}
}