{
  "type": "Feature",
  "properties": {
    "addr:full":"111 E 7th St N Melrose MN 56352",
    "addr:housenumber":"111",
    "addr:postcode":"56352",
    "addr:street":"E 7Th St N",
    "iso:country":"US",
    "sg:address":"111 E 7th St N",
    "sg:city":"Melrose",
    "sg:classifiers":[
        {
            "category":"Freight",
            "type":"Transportation"
        }
    ],
    "sg:phone":"+1 320 256 3188",
    "sg:postcode":"56352",
    "sg:province":"MN",
    "sg:tags":[
        "operator",
        "trucking"
    ],
    "wof:name":"Randy Daneil Ostendorf",
    "wof:placetype":"venue"
},
  "geometry": {"coordinates":[-94.812916,45.682074],"type":"Point"}
}