{
  "type": "Feature",
  "properties": {
    "addr:full":"1975 Oakcrest Ave Saint Paul MN 55113",
    "addr:housenumber":"1975",
    "addr:postcode":"55113",
    "addr:street":"Oakcrest Ave",
    "iso:country":"US",
    "sg:address":"1975 Oakcrest Ave",
    "sg:city":"Saint Paul",
    "sg:classifiers":[
        {
            "category":"Shopping",
            "subcategory":"Music",
            "type":"Retail Goods"
        }
    ],
    "sg:phone":"+1 612 782 8200",
    "sg:postcode":"55113",
    "sg:province":"MN",
    "sg:tags":[
        "dvd's"
    ],
    "wof:name":"Cool International",
    "wof:placetype":"venue"
},
  "geometry": {"coordinates":[-93.18214999999999,45.017997],"type":"Point"}
}