{
  "type": "Feature",
  "properties": {
    "addr:full":"7196 27th St SE Buffalo MN 55313",
    "addr:housenumber":"7196",
    "addr:postcode":"55313",
    "addr:street":"27Th St Se",
    "iso:country":"US",
    "sg:address":"7196 27th St SE",
    "sg:city":"Buffalo",
    "sg:phone":"+1 763 477 6650",
    "sg:postcode":"55313",
    "sg:province":"MN",
    "sg:tags":[
        "farm",
        "corn",
        "soybean"
    ],
    "wof:name":"George Leerssen",
    "wof:placetype":"venue"
},
  "geometry": {"coordinates":[-93.74410399999999,45.111649],"type":"Point"}
}