{
  "type": "Feature",
  "properties": {
    "iso:country":"US",
    "sg:address":"309 Northtown Dr NE",
    "sg:city":"Blaine",
    "sg:classifiers":[
        {
            "category":"Shopping",
            "subcategory":"Jewelry",
            "type":"Retail Goods"
        }
    ],
    "sg:phone":"+1 763 786 7786",
    "sg:postcode":"55434",
    "sg:province":"MN",
    "sg:tags":[
        "jeweler"
    ],
    "sg:website":"www.helzberg.com",
    "wof:name":"Helzberg Diamonds",
    "wof:placetype":"venue"
},
  "geometry": {"coordinates":[-93.26000500000001,45.128319],"type":"Point"}
}