{
  "type": "Feature",
  "properties": {
    "iso:country":"US",
    "sg:address":"1343 Gentry Ave N",
    "sg:city":"Oakdale",
    "sg:classifiers":[
        {
            "category":"Real Estate",
            "subcategory":"Real Estate Operator",
            "type":"Services"
        }
    ],
    "sg:phone":"+1 651 739 9490",
    "sg:postcode":"55128",
    "sg:province":"MN",
    "sg:tags":[
        "apartment"
    ],
    "wof:name":"Gentry Place",
    "wof:placetype":"venue"
},
  "geometry": {"coordinates":[-92.98314499999999,44.967969],"type":"Point"}
}