{
  "type": "Feature",
  "properties": {
    "addr:full":"11786 Quail Rd Avon MN 56310",
    "addr:housenumber":"11786",
    "addr:postcode":"56310",
    "addr:street":"Quail Rd",
    "iso:country":"US",
    "sg:address":"11786 Quail Rd",
    "sg:city":"Avon",
    "sg:classifiers":[
        {
            "category":"Bars & Pubs",
            "type":"Food & Drink"
        }
    ],
    "sg:phone":"+1 320 980 4896",
    "sg:postcode":"56310",
    "sg:province":"MN",
    "sg:tags":[
        "drinking"
    ],
    "wof:name":"Funkys Bar",
    "wof:placetype":"venue"
},
  "geometry": {"coordinates":[-94.349997,45.643403],"type":"Point"}
}