{
  "type": "Feature",
  "properties": {
    "iso:country":"US",
    "sg:address":"800 Lasalle Ave Ste 2800",
    "sg:city":"Minneapolis",
    "sg:classifiers":[
        {
            "category":"Building & Trades",
            "subcategory":"Plumbing",
            "type":"Services"
        }
    ],
    "sg:phone":"+1 952 474 6153",
    "sg:postcode":"55402",
    "sg:province":"MN",
    "sg:tags":[
        "plumber",
        "industrial",
        "contractors-commercial"
    ],
    "wof:name":"O'connor's Plumbing Heating",
    "wof:placetype":"venue"
},
  "geometry": {"coordinates":[-93.27454400000001,44.976551],"type":"Point"}
}