{
  "type": "Feature",
  "properties": {
    "iso:country":"US",
    "sg:address":"212 Colfax Ave N",
    "sg:city":"Minneapolis",
    "sg:classifiers":[
        {
            "category":"Manufacturing",
            "subcategory":"Tools & Machinery",
            "type":"Manufacturing & Wholesale Goods"
        },
        {
            "category":"Building & Trades",
            "subcategory":"Electrical",
            "type":"Services"
        }
    ],
    "sg:phone":"+1 612 374 2150",
    "sg:postcode":"55405",
    "sg:province":"MN",
    "sg:tags":[
        "transmission",
        "equipment",
        "cutting",
        "gear",
        "power"
    ],
    "sg:website":"http://www.daltongear.com",
    "wof:name":"Dalton Gear Company",
    "wof:placetype":"venue"
},
  "geometry": {"coordinates":[-93.291584,44.978113],"type":"Point"}
}