{
  "type": "Feature",
  "properties": {
    "addr:full":"1200 Nicollet Ave Suite #412 Minneapolis MN 55403",
    "addr:housenumber":"1200",
    "addr:postcode":"55403",
    "addr:street":"Nicollet Ave Suite # 412",
    "iso:country":"US",
    "sg:address":"1200 Nicollet Ave Suite #412",
    "sg:city":"Minneapolis",
    "sg:phone":"+1 612 852 8408",
    "sg:postcode":"55403",
    "sg:province":"MN",
    "wof:name":"Tyson Enterprises",
    "wof:placetype":"venue"
},
  "geometry": {"coordinates":[-93.276352,44.972019],"type":"Point"}
}