{
  "type": "Feature",
  "properties": {
    "iso:country":"US",
    "sg:address":"14314 Co Hwy 4",
    "sg:city":"Lake Park",
    "sg:classifiers":[
        {
            "category":"Organizations",
            "subcategory":"Religious Organization",
            "type":"Services"
        }
    ],
    "sg:phone":"+1 218 532 2694",
    "sg:postcode":"56554",
    "sg:province":"MN",
    "sg:website":"www.cormorantlutheran.org",
    "wof:name":"Cormorant Lutheran Church",
    "wof:placetype":"venue"
},
  "geometry": {"coordinates":[-96.113411,46.75016],"type":"Point"}
}