{
  "type": "Feature",
  "properties": {
    "iso:country":"US",
    "sg:address":"4150 Pilot Knob Rd",
    "sg:city":"Eagan",
    "sg:classifiers":[
        {
            "category":"Organizations",
            "subcategory":"Religious Organization",
            "type":"Services"
        }
    ],
    "sg:phone":"+1 651 452 2114",
    "sg:postcode":"55122",
    "sg:province":"MN",
    "sg:tags":[
        "church"
    ],
    "wof:name":"Beautiful Savior Lutheran Chr",
    "wof:placetype":"venue"
},
  "geometry": {"coordinates":[-93.167118,44.805279],"type":"Point"}
}