{
  "type": "Feature",
  "properties": {
    "addr:full":"2026 Brookhaven Dr Shakopee MN 55379",
    "addr:housenumber":"2026",
    "addr:postcode":"55379",
    "addr:street":"Brookhaven Dr",
    "iso:country":"US",
    "sg:address":"2026 Brookhaven Dr",
    "sg:city":"Shakopee",
    "sg:classifiers":[
        {
            "category":"Professional",
            "type":"Services"
        }
    ],
    "sg:phone":"+1 952 496 0339",
    "sg:postcode":"55379",
    "sg:province":"MN",
    "wof:name":"Mark Kemplin",
    "wof:placetype":"venue"
},
  "geometry": {"coordinates":[-93.566379,44.757122],"type":"Point"}
}