{
  "type": "Feature",
  "properties": {
    "addr:full":"15185 Carrousel Way Rosemount MN 55068",
    "addr:postcode":"15185;55068",
    "addr:street":"Carrousel Way",
    "iso:country":"US",
    "sg:address":"15185 Carrousel Way",
    "sg:city":"Rosemount",
    "sg:classifiers":[
        {
            "category":"Retail",
            "subcategory":"Auto Repair",
            "type":"Services"
        }
    ],
    "sg:phone":"+1 651 322 1919",
    "sg:postcode":"55068",
    "sg:province":"MN",
    "sg:tags":[
        "repairing",
        "automobile"
    ],
    "wof:name":"ELM Automotive",
    "wof:placetype":"venue"
},
  "geometry": {"coordinates":[-93.135724,44.727837],"type":"Point"}
}