{
  "type": "Feature",
  "properties": {
    "iso:country":"US",
    "sg:address":"615 13th St W",
    "sg:city":"Glencoe",
    "sg:classifiers":[
        {
            "category":"Insurance",
            "subcategory":"Insurance Agent",
            "type":"Services"
        }
    ],
    "sg:phone":"+1 320 864 3069",
    "sg:postcode":"55336",
    "sg:province":"MN",
    "wof:name":"Young America Mutual Ins Inc",
    "wof:placetype":"venue"
},
  "geometry": {"coordinates":[-94.168404,44.771936],"type":"Point"}
}