{
  "type": "Feature",
  "properties": {
    "iso:country":"US",
    "sg:address":"416 E Hennepin Ave",
    "sg:city":"Minneapolis",
    "sg:classifiers":[
        {
            "category":"Professional",
            "subcategory":"Computer Services",
            "type":"Services"
        }
    ],
    "sg:phone":"+1 612 379 5334",
    "sg:postcode":"55414",
    "sg:province":"MN",
    "sg:tags":[
        "home",
        "consulting",
        "page",
        "dev",
        "internet"
    ],
    "sg:website":"www.agilemfg.com",
    "wof:name":"Agile Manufacturing Inc",
    "wof:placetype":"venue"
},
  "geometry": {"coordinates":[-93.25348700000001,44.988968],"type":"Point"}
}