{
  "type": "Feature",
  "properties": {
    "iso:country":"US",
    "sg:address":"18304 Minnetonka Blvd",
    "sg:city":"Wayzata",
    "sg:classifiers":[
        {
            "category":"Professional",
            "subcategory":"Business Services",
            "type":"Services"
        }
    ],
    "sg:phone":"+1 952 653 6300",
    "sg:postcode":"55391",
    "sg:province":"MN",
    "sg:tags":[
        "architectural"
    ],
    "wof:name":"Eclipse An Architural Group",
    "wof:placetype":"venue"
},
  "geometry": {"coordinates":[-93.512567,44.940024],"type":"Point"}
}