{
  "type": "Feature",
  "properties": {
    "iso:country":"US",
    "sg:address":"403 12th St SE",
    "sg:city":"Austin",
    "sg:classifiers":[
        {
            "category":"Real Estate",
            "subcategory":"Real Estate Operator",
            "type":"Services"
        }
    ],
    "sg:phone":"+1 507 437 4264",
    "sg:postcode":"55912",
    "sg:province":"MN",
    "sg:tags":[
        "building",
        "apartment"
    ],
    "wof:name":"Webster Apts",
    "wof:placetype":"venue"
},
  "geometry": {"coordinates":[-92.957144,43.663866],"type":"Point"}
}