{
  "type": "Feature",
  "properties": {
    "addr:full":"220 E Hickory St Mankato MN 56001",
    "addr:housenumber":"220",
    "addr:postcode":"56001",
    "addr:street":"E Hickory St",
    "iso:country":"US",
    "sg:address":"220 E Hickory St",
    "sg:city":"Mankato",
    "sg:classifiers":[
        {
            "category":"Organizations",
            "subcategory":"Religious Organization",
            "type":"Services"
        }
    ],
    "sg:phone":"+1 507 387 2160",
    "sg:postcode":"56001",
    "sg:province":"MN",
    "sg:tags":[
        "church"
    ],
    "sg:website":"www.fpcmankato.org",
    "wof:name":"First Presbyterian Church",
    "wof:placetype":"venue"
},
  "geometry": {"coordinates":[-94.00301899999999,44.164884],"type":"Point"}
}