{
  "type": "Feature",
  "properties": {
    "addr:full":"380 Roslyn Pl Minneapolis MN 55419",
    "addr:housenumber":"380",
    "addr:postcode":"55419",
    "addr:street":"Roslyn Pl",
    "iso:country":"US",
    "sg:address":"380 Roslyn Pl",
    "sg:city":"Minneapolis",
    "sg:classifiers":[
        {
            "category":"Home & Garden",
            "subcategory":"Home Furnishings",
            "type":"Retail Goods"
        }
    ],
    "sg:phone":"+1 612 866 8158",
    "sg:postcode":"55419",
    "sg:province":"MN",
    "sg:tags":[
        "venetian",
        "blind"
    ],
    "wof:name":"Budget Blinds Of Bloomington",
    "wof:placetype":"venue"
},
  "geometry": {"coordinates":[-93.270219,44.894925],"type":"Point"}
}