{
  "type": "Feature",
  "properties": {
    "iso:country":"US",
    "sg:address":"4225 Daniel Dr",
    "sg:city":"Saint Paul",
    "sg:classifiers":[
        {
            "category":"Personal",
            "subcategory":"Beauty Salon",
            "type":"Services"
        }
    ],
    "sg:phone":"+1 651 905 0943",
    "sg:postcode":"55123",
    "sg:province":"MN",
    "sg:tags":[
        "shop"
    ],
    "wof:name":"Twin Cities Event Planning",
    "wof:placetype":"venue"
},
  "geometry": {"coordinates":[-93.136551,44.804266],"type":"Point"}
}