{
  "type": "Feature",
  "properties": {
    "iso:country":"US",
    "sg:address":"1501 University Ave SE",
    "sg:city":"Minneapolis",
    "sg:classifiers":[
        {
            "category":"Food & Beverages",
            "subcategory":"Specialty",
            "type":"Retail Goods"
        }
    ],
    "sg:phone":"+1 612 378 9555",
    "sg:postcode":"55414",
    "sg:province":"MN",
    "sg:tags":[
        "tea",
        "coffee"
    ],
    "wof:name":"Espresso 22",
    "wof:placetype":"venue"
},
  "geometry": {"coordinates":[-93.23491,44.978867],"type":"Point"}
}