{
  "type": "Feature",
  "properties": {
    "addr:full":"401 Douglas Ave Eveleth MN 55734",
    "addr:housenumber":"401",
    "addr:postcode":"55734",
    "addr:street":"Douglas Ave",
    "iso:country":"US",
    "sg:address":"401 Douglas Ave",
    "sg:city":"Eveleth",
    "sg:classifiers":[
        {
            "category":"Utilities",
            "subcategory":"Electric",
            "type":"Services"
        }
    ],
    "sg:phone":"+1 218 744 5584",
    "sg:postcode":"55734",
    "sg:province":"MN",
    "sg:tags":[
        "company"
    ],
    "wof:name":"Minnesota Power",
    "wof:placetype":"venue"
},
  "geometry": {"coordinates":[-92.54132799999999,47.464214],"type":"Point"}
}