{
  "type": "Feature",
  "properties": {
    "iso:country":"US",
    "sg:address":"2160 Wayzata Blvd",
    "sg:city":"Long Lake",
    "sg:classifiers":[
        {
            "category":"Real Estate",
            "subcategory":"Real Estate Operator",
            "type":"Services"
        }
    ],
    "sg:phone":"+1 952 473 7047",
    "sg:postcode":"55356",
    "sg:province":"MN",
    "sg:tags":[
        "mall",
        "shopping",
        "center"
    ],
    "wof:name":"Hilloway Shopping Ctr",
    "wof:placetype":"venue"
},
  "geometry": {"coordinates":[-93.581051,44.989252],"type":"Point"}
}