{
  "type": "Feature",
  "properties": {
    "addr:full":"10648 W River Rd Minneapolis MN 55443",
    "addr:housenumber":"10648",
    "addr:postcode":"55443",
    "addr:street":"W River Rd",
    "iso:country":"US",
    "sg:address":"10648 W River Rd",
    "sg:city":"Minneapolis",
    "sg:classifiers":[
        {
            "category":"Building & Trades",
            "subcategory":"Landscaping Services",
            "type":"Services"
        }
    ],
    "sg:phone":"+1 763 422 6802",
    "sg:postcode":"55443",
    "sg:province":"MN",
    "sg:tags":[
        "aged",
        "homes-institutional"
    ],
    "wof:name":"Marge Schwab",
    "wof:placetype":"venue"
},
  "geometry": {"coordinates":[-93.32831299999999,45.14804],"type":"Point"}
}