{
  "type": "Feature",
  "properties": {
    "iso:country":"US",
    "sg:address":"302 1st Ave NW Suite 5",
    "sg:city":"Byron",
    "sg:classifiers":[
        {
            "category":"Building & Trades",
            "subcategory":"Plumbing",
            "type":"Services"
        },
        {
            "category":"Building & Trades",
            "subcategory":"Construction",
            "type":"Services"
        },
        {
            "category":"Utilities",
            "subcategory":"Sewage",
            "type":"Services"
        }
    ],
    "sg:phone":"+1 507 208 2068",
    "sg:postcode":"55920",
    "sg:province":"MN",
    "sg:tags":[
        "tank",
        "septic",
        "grading",
        "excavation",
        "system",
        "contractor",
        "sewer",
        "demolition"
    ],
    "sg:website":"http://www.decookexcavating.com",
    "wof:name":"DeCook Excavating Inc",
    "wof:placetype":"venue"
},
  "geometry": {"coordinates":[-92.64692700000001,44.031966],"type":"Point"}
}