{
  "type": "Feature",
  "properties": {
    "iso:country":"US",
    "sg:address":"5051 Jackson St NE",
    "sg:city":"Minneapolis",
    "sg:classifiers":[
        {
            "category":"Real Estate",
            "subcategory":"Real Estate Agent",
            "type":"Services"
        }
    ],
    "sg:phone":"+1 763 586 0481",
    "sg:postcode":"55421",
    "sg:province":"MN",
    "wof:name":"Lipa Appraisals Inc",
    "wof:placetype":"venue"
},
  "geometry": {"coordinates":[-93.249291,45.060557],"type":"Point"}
}