{
  "type": "Feature",
  "properties": {
    "addr:full":"804 Laurel St W Stillwater MN 55082",
    "addr:housenumber":"804",
    "addr:postcode":"55082",
    "addr:street":"Laurel St W",
    "iso:country":"US",
    "sg:address":"804 Laurel St W",
    "sg:city":"Stillwater",
    "sg:classifiers":[
        {
            "category":"Retail",
            "subcategory":"Auto Repair",
            "type":"Services"
        }
    ],
    "sg:phone":"+1 651 430 2381",
    "sg:postcode":"55082",
    "sg:province":"MN",
    "sg:tags":[
        "brake"
    ],
    "wof:name":"Best Brake & Exhaust Svc",
    "wof:placetype":"venue"
},
  "geometry": {"coordinates":[-92.820452,45.060254],"type":"Point"}
}