{
  "type": "Feature",
  "properties": {
    "addr:full":"6401 France Ave S Minneapolis MN 55435",
    "addr:housenumber":"6401",
    "addr:postcode":"55435",
    "addr:street":"France Ave S",
    "iso:country":"US",
    "sg:address":"6401 France Ave S",
    "sg:city":"Minneapolis",
    "sg:classifiers":[
        {
            "category":"Health Services",
            "subcategory":"Doctor",
            "type":"Services"
        }
    ],
    "sg:phone":"+1 952 924 5187",
    "sg:postcode":"55435",
    "sg:province":"MN",
    "sg:tags":[
        "physician",
        "surgeon",
        "anesthesiology",
        "surgeons"
    ],
    "wof:name":"Southdale Anesthesiologists",
    "wof:placetype":"venue"
},
  "geometry": {"coordinates":[-93.328873,44.886471],"type":"Point"}
}