{
  "type": "Feature",
  "properties": {
    "addr:full":"316 Westover Rd Hoyt Lakes MN 55750",
    "addr:housenumber":"316",
    "addr:postcode":"55750",
    "addr:street":"Westover Rd",
    "iso:country":"US",
    "sg:address":"316 Westover Rd",
    "sg:city":"Hoyt Lakes",
    "sg:classifiers":[
        {
            "category":"Food & Beverages",
            "subcategory":"Liquor & Beverages",
            "type":"Retail Goods"
        }
    ],
    "sg:phone":"+1 218 225 2090",
    "sg:postcode":"55750",
    "sg:province":"MN",
    "sg:tags":[
        "alcoholic"
    ],
    "wof:name":"Friendly Liquor Store",
    "wof:placetype":"venue"
},
  "geometry": {"coordinates":[-92.14373999999999,47.522036],"type":"Point"}
}