{
  "type": "Feature",
  "properties": {
    "addr:full":"14760 Robert Trl S Rosemount MN 55068",
    "addr:housenumber":"14760",
    "addr:postcode":"55068",
    "addr:street":"Robert Trl S",
    "iso:country":"US",
    "sg:address":"14760 Robert Trl S",
    "sg:city":"Rosemount",
    "sg:classifiers":[
        {
            "category":"Professional",
            "type":"Services"
        }
    ],
    "sg:phone":"+1 651 423 0555",
    "sg:postcode":"55068",
    "sg:province":"MN",
    "wof:name":"Steddy Inc",
    "wof:placetype":"venue"
},
  "geometry": {"coordinates":[-93.126079,44.735349],"type":"Point"}
}