{
  "type": "Feature",
  "properties": {
    "addr:full":"520 9th St N New Ulm MN 56073",
    "addr:housenumber":"520",
    "addr:postcode":"56073",
    "addr:street":"9Th St N",
    "iso:country":"US",
    "sg:address":"520 9th St N",
    "sg:city":"New Ulm",
    "sg:classifiers":[
        {
            "category":"Farming",
            "subcategory":"Farm",
            "type":"Manufacturing & Wholesale Goods"
        }
    ],
    "sg:phone":"+1 507 354 2703",
    "sg:postcode":"56073",
    "sg:province":"MN",
    "sg:tags":[
        "crop",
        "general"
    ],
    "wof:name":"Harlan Schulz",
    "wof:placetype":"venue"
},
  "geometry": {"coordinates":[-94.46762200000001,44.322055],"type":"Point"}
}