{
  "type": "Feature",
  "properties": {
    "iso:country":"US",
    "sg:address":"346 Campbell Dr",
    "sg:city":"Hopkins",
    "sg:classifiers":[
        {
            "category":"Real Estate",
            "subcategory":"Real Estate Agent",
            "type":"Services"
        }
    ],
    "sg:phone":"+1 952 936 0750",
    "sg:postcode":"55343",
    "sg:province":"MN",
    "wof:name":"Real Estate Specialists Inc",
    "wof:placetype":"venue"
},
  "geometry": {"coordinates":[-93.40302200000001,44.931877],"type":"Point"}
}