{
  "type": "Feature",
  "properties": {
    "iso:country":"US",
    "sg:address":"410 2nd St SE",
    "sg:city":"Elbow Lake",
    "sg:classifiers":[
        {
            "category":"Sports & Exercise",
            "subcategory":"Bowling",
            "type":"Entertainment"
        }
    ],
    "sg:phone":"+1 218 685 4746",
    "sg:postcode":"56531",
    "sg:province":"MN",
    "sg:tags":[
        "center"
    ],
    "wof:name":"Joe Jos",
    "wof:placetype":"venue"
},
  "geometry": {"coordinates":[-95.970663,45.989814],"type":"Point"}
}