{
  "type": "Feature",
  "properties": {
    "iso:country":"US",
    "sg:address":"2900 Piedmont Ave",
    "sg:city":"Duluth",
    "sg:classifiers":[
        {
            "category":"Health Services",
            "subcategory":"Doctor",
            "type":"Services"
        }
    ],
    "sg:phone":"+1 218 727 8288",
    "sg:postcode":"55811",
    "sg:province":"MN",
    "sg:tags":[
        "clinic",
        "practice",
        "family"
    ],
    "wof:name":"Skyline Family Medical Center",
    "wof:placetype":"venue"
},
  "geometry": {"coordinates":[-92.16400400000001,46.784907],"type":"Point"}
}