{
  "type": "Feature",
  "properties": {
    "addr:full":"4500 18th Ave NW Rochester MN 55901",
    "addr:housenumber":"4500",
    "addr:postcode":"55901",
    "addr:street":"18Th Ave Nw",
    "iso:country":"US",
    "sg:address":"4500 18th Ave NW",
    "sg:city":"Rochester",
    "sg:classifiers":[
        {
            "category":"Restaurant",
            "type":"Food & Drink"
        }
    ],
    "sg:menulink":"http://www.allmenus.com/mn/rochester/225600-caseys-general-store/menu/",
    "sg:phone":"+1 507 287 9820",
    "sg:postcode":"55901",
    "sg:province":"MN",
    "sg:tags":[
        "american",
        "pizza"
    ],
    "wof:name":"Casey's General Store",
    "wof:placetype":"venue"
},
  "geometry": {"coordinates":[-92.488907,44.069463],"type":"Point"}
}