{
  "type": "Feature",
  "properties": {
    "iso:country":"US",
    "sg:address":"24 Mort Meadows",
    "sg:city":"Grand Marais",
    "sg:classifiers":[
        {
            "category":"Professional",
            "subcategory":"Business Services",
            "type":"Services"
        }
    ],
    "sg:phone":"+1 218 387 2140",
    "sg:postcode":"55604",
    "sg:province":"MN",
    "wof:name":"Millers Enterprises",
    "wof:placetype":"venue"
},
  "geometry": {"coordinates":[-90.318939,47.788043],"type":"Point"}
}