{
  "type": "Feature",
  "properties": {
    "iso:country":"US",
    "sg:address":"125 Jackson Ave N",
    "sg:city":"Hopkins",
    "sg:classifiers":[
        {
            "category":"Manufacturing",
            "subcategory":"Food",
            "type":"Manufacturing & Wholesale Goods"
        }
    ],
    "sg:phone":"+1 952 935 0410",
    "sg:postcode":"55343",
    "sg:province":"MN",
    "sg:tags":[
        "manufacture",
        "juice"
    ],
    "sg:website":"www.citrussystems.com",
    "wof:name":"Citrus Systems Inc",
    "wof:placetype":"venue"
},
  "geometry": {"coordinates":[-93.394437,44.926369],"type":"Point"}
}