{
  "type": "Feature",
  "properties": {
    "addr:full":"1980 15th Ave SE Saint Cloud MN 56304",
    "addr:housenumber":"1980",
    "addr:postcode":"56304",
    "addr:street":"15Th Ave Se",
    "iso:country":"US",
    "sg:address":"1980 15th Ave SE",
    "sg:city":"Saint Cloud",
    "sg:classifiers":[
        {
            "category":"Professional",
            "type":"Services"
        }
    ],
    "sg:phone":"+1 320 252 1795",
    "sg:postcode":"56304",
    "sg:province":"MN",
    "wof:name":"Mary Schmidt",
    "wof:placetype":"venue"
},
  "geometry": {"coordinates":[-94.131897,45.541363],"type":"Point"}
}