{
  "type": "Feature",
  "properties": {
    "addr:full":"26468 150th Ave NE Thief River Falls MN 56701",
    "addr:housenumber":"26468",
    "addr:postcode":"56701",
    "addr:street":"150Th Ave Ne",
    "iso:country":"US",
    "sg:address":"26468 150th Ave NE",
    "sg:city":"Thief River Falls",
    "sg:classifiers":[
        {
            "category":"Farming",
            "subcategory":"Farm",
            "type":"Manufacturing & Wholesale Goods"
        }
    ],
    "sg:phone":"+1 218 449 4825",
    "sg:postcode":"56701",
    "sg:province":"MN",
    "sg:tags":[
        "crop",
        "general"
    ],
    "wof:name":"Walter Steinhauer Farm Inc",
    "wof:placetype":"venue"
},
  "geometry": {"coordinates":[-96.15199800000001,48.262235],"type":"Point"}
}