{
  "type": "Feature",
  "properties": {
    "iso:country":"US",
    "sg:address":"777 S Victory Dr",
    "sg:city":"Mankato",
    "sg:classifiers":[
        {
            "category":"Shopping",
            "subcategory":"Bicycles & Sporting Goods",
            "type":"Retail Goods"
        }
    ],
    "sg:phone":"+1 507 625 7897",
    "sg:postcode":"56001",
    "sg:province":"MN",
    "wof:name":"Southern Archery North",
    "wof:placetype":"venue"
},
  "geometry": {"coordinates":[-93.967811,44.150779],"type":"Point"}
}