{
  "type": "Feature",
  "properties": {
    "addr:full":"3335 142nd St W Rosemount MN 55068",
    "addr:housenumber":"3335",
    "addr:postcode":"55068",
    "addr:street":"142Nd St W",
    "iso:country":"US",
    "sg:address":"3335 142nd St W",
    "sg:city":"Rosemount",
    "sg:classifiers":[
        {
            "category":"Education",
            "subcategory":"School",
            "type":"Public Place"
        }
    ],
    "sg:phone":"+1 651 423 7501",
    "sg:postcode":"55068",
    "sg:province":"MN",
    "sg:website":"www.district196.org",
    "wof:name":"Rosemount High School",
    "wof:placetype":"venue"
},
  "geometry": {"coordinates":[-93.12860999999999,44.744169],"type":"Point"}
}