{
  "type": "Feature",
  "properties": {
    "iso:country":"US",
    "sg:address":"5102 S Cant Rd",
    "sg:city":"Duluth",
    "sg:classifiers":[
        {
            "category":"Freight",
            "type":"Transportation"
        }
    ],
    "sg:phone":"+1 218 525 6681",
    "sg:postcode":"55804",
    "sg:province":"MN",
    "sg:tags":[
        "over",
        "road",
        "trucking"
    ],
    "wof:name":"Monson Trucking Inc",
    "wof:placetype":"venue"
},
  "geometry": {"coordinates":[-91.94176400000001,46.890475],"type":"Point"}
}