{
  "type": "Feature",
  "properties": {
    "iso:country":"US",
    "sg:address":"1525 Division St W",
    "sg:city":"Faribault",
    "sg:classifiers":[
        {
            "category":"Restaurant",
            "type":"Food & Drink"
        }
    ],
    "sg:phone":"+1 507 334 9892",
    "sg:postcode":"55021",
    "sg:province":"MN",
    "sg:tags":[
        "a",
        "as",
        "bar",
        "operates"
    ],
    "wof:name":"Spikes Bar & Grill",
    "wof:placetype":"venue"
},
  "geometry": {"coordinates":[-93.29052799999999,44.290494],"type":"Point"}
}