{
  "type": "Feature",
  "properties": {
    "iso:country":"US",
    "sg:address":"700 Dodge Ave NW",
    "sg:city":"Elk River",
    "sg:classifiers":[
        {
            "category":"Restaurant",
            "type":"Food & Drink"
        }
    ],
    "sg:menulink":"http://www.allmenus.com/mn/elk-river/193939-mcdonalds/menu/",
    "sg:postcode":"55330",
    "sg:province":"MN",
    "sg:tags":[
        "burger",
        "american"
    ],
    "wof:name":"McDonald's",
    "wof:placetype":"venue"
},
  "geometry": {"coordinates":[-93.556702,45.314589],"type":"Point"}
}