{
  "type": "Feature",
  "properties": {
    "addr:full":"14717 State Hwy 210 Hewitt MN 56453",
    "addr:housenumber":"14717",
    "addr:postcode":"56453",
    "addr:street":"State Hwy 210",
    "iso:country":"US",
    "sg:address":"14717 State Hwy 210",
    "sg:city":"Hewitt",
    "sg:classifiers":[
        {
            "category":"Professional",
            "type":"Services"
        }
    ],
    "sg:phone":"+1 218 924 4356",
    "sg:postcode":"56453",
    "sg:province":"MN",
    "sg:tags":[
        "establishment"
    ],
    "wof:name":"Dixon & Dixon",
    "wof:placetype":"venue"
},
  "geometry": {"coordinates":[-95.054586,46.325295],"type":"Point"}
}