{
  "type": "Feature",
  "properties": {
    "addr:full":"801 Nicollet Ave Minneapolis MN 55402",
    "addr:housenumber":"801",
    "addr:postcode":"55402",
    "addr:street":"Nicollet Ave",
    "iso:country":"US",
    "sg:address":"801 Nicollet Ave",
    "sg:city":"Minneapolis",
    "sg:classifiers":[
        {
            "category":"Professional",
            "subcategory":"Management & Consulting",
            "type":"Services"
        }
    ],
    "sg:phone":"+1 612 376 9376",
    "sg:postcode":"55402",
    "sg:province":"MN",
    "sg:tags":[
        "business"
    ],
    "wof:name":"Family Business Group",
    "wof:placetype":"venue"
},
  "geometry": {"coordinates":[-93.27387899999999,44.97493],"type":"Point"}
}