{
  "type": "Feature",
  "properties": {
    "iso:country":"US",
    "sg:address":"3700 Cedar Lake Ave",
    "sg:city":"Minneapolis",
    "sg:classifiers":[
        {
            "category":"Health Services",
            "subcategory":"Nursing And Care Facility",
            "type":"Services"
        }
    ],
    "sg:phone":"+1 612 920 2030",
    "sg:postcode":"55416",
    "sg:province":"MN",
    "sg:tags":[
        "living",
        "assisted",
        "skilled",
        "home"
    ],
    "sg:website":"www.jones-harrison.org",
    "wof:name":"Jones-Harrison Residence",
    "wof:placetype":"venue"
},
  "geometry": {"coordinates":[-93.326172,44.953602],"type":"Point"}
}