{
  "type": "Feature",
  "properties": {
    "iso:country":"US",
    "sg:address":"11300 Club West Pkwy",
    "sg:city":"Minneapolis",
    "sg:classifiers":[
        {
            "category":"Cafe",
            "type":"Food & Drink"
        }
    ],
    "sg:menulink":"http://www.allmenus.com/mn/blaine/54014-majors-sports-cafe/menu/",
    "sg:phone":"+1 763 746 2774",
    "sg:postcode":"55449",
    "sg:province":"MN",
    "sg:tags":[
        "american"
    ],
    "wof:name":"Majors Sports Cafe",
    "wof:placetype":"venue"
},
  "geometry": {"coordinates":[-93.231756,45.17667],"type":"Point"}
}