{
  "type": "Feature",
  "properties": {
    "addr:full":"2670 Commerce Blvd Mound MN 55364",
    "addr:housenumber":"2670",
    "addr:postcode":"55364",
    "addr:street":"Commerce Blvd",
    "iso:country":"US",
    "sg:address":"2670 Commerce Blvd",
    "sg:city":"Mound",
    "sg:classifiers":[
        {
            "category":"Professional",
            "subcategory":"Accounting & Tax Preparation",
            "type":"Services"
        }
    ],
    "sg:phone":"+1 952 472 6759",
    "sg:postcode":"55364",
    "sg:province":"MN",
    "wof:name":"Charles J Stanisich CPA",
    "wof:placetype":"venue"
},
  "geometry": {"coordinates":[-93.669348,44.930328],"type":"Point"}
}