{
  "type": "Feature",
  "properties": {
    "iso:country":"US",
    "sg:address":"6667 W Old Shakopee Rd",
    "sg:city":"Minneapolis",
    "sg:classifiers":[
        {
            "category":"Wholesale",
            "subcategory":"Groceries",
            "type":"Manufacturing & Wholesale Goods"
        }
    ],
    "sg:phone":"+1 952 746 6099",
    "sg:postcode":"55438",
    "sg:province":"MN",
    "wof:name":"Markdown International  LLC",
    "wof:placetype":"venue"
},
  "geometry": {"coordinates":[-93.373355,44.807927],"type":"Point"}
}