{
  "type": "Feature",
  "properties": {
    "addr:full":"902 E 6th St St Paul MN 55106",
    "addr:housenumber":"902",
    "addr:postcode":"55106",
    "addr:street":"E 6Th St",
    "iso:country":"US",
    "sg:address":"902 E 6th St",
    "sg:city":"St Paul",
    "sg:classifiers":[
        {
            "category":"Social Services",
            "subcategory":"Child Care",
            "type":"Services"
        }
    ],
    "sg:phone":"+1 651 793 0015",
    "sg:postcode":"55106",
    "sg:province":"MN",
    "wof:name":"Momma L's Lullabies Child Care",
    "wof:placetype":"venue"
},
  "geometry": {"coordinates":[-93.061618,44.960275],"type":"Point"}
}