{
  "type": "Feature",
  "properties": {
    "iso:country":"US",
    "sg:address":"1815 Radio Dr",
    "sg:city":"Saint Paul",
    "sg:classifiers":[
        {
            "category":"Health Services",
            "subcategory":"Doctor",
            "type":"Services"
        }
    ],
    "sg:phone":"+1 651 578 8401",
    "sg:postcode":"55125",
    "sg:province":"MN",
    "wof:name":"Oca",
    "wof:placetype":"venue"
},
  "geometry": {"coordinates":[-92.934027,44.92065],"type":"Point"}
}