{
  "type": "Feature",
  "properties": {
    "addr:full":"7953 Main St NE Minneapolis MN 55432",
    "addr:housenumber":"7953",
    "addr:postcode":"55432",
    "addr:street":"Main St Ne",
    "iso:country":"US",
    "sg:address":"7953 Main St NE",
    "sg:city":"Minneapolis",
    "sg:classifiers":[
        {
            "category":"Restaurant",
            "type":"Food & Drink"
        },
        {
            "category":"Ice Cream",
            "type":"Food & Drink"
        }
    ],
    "sg:phone":"+1 763 784 6690",
    "sg:postcode":"55432",
    "sg:province":"MN",
    "sg:tags":[
        "frozen",
        "dessert"
    ],
    "wof:name":"Artic Glacier Ice Inc",
    "wof:placetype":"venue"
},
  "geometry": {"coordinates":[-93.268868,45.112212],"type":"Point"}
}