{
  "type": "Feature",
  "properties": {
    "iso:country":"US",
    "sg:address":"1320 W Lake St",
    "sg:city":"Minneapolis",
    "sg:classifiers":[
        {
            "category":"Restaurant",
            "type":"Food & Drink"
        }
    ],
    "sg:phone":"+1 612 353 5156",
    "sg:postcode":"55408",
    "sg:province":"MN",
    "sg:tags":[
        "tex-mex"
    ],
    "wof:name":"Cowboy Slim's",
    "wof:placetype":"venue"
},
  "geometry": {"coordinates":[-93.296661,44.948378],"type":"Point"}
}