{
  "type": "Feature",
  "properties": {
    "addr:full":"51 E 4th St Winona MN 55987",
    "addr:housenumber":"51",
    "addr:postcode":"55987",
    "addr:street":"E 4Th St",
    "iso:country":"US",
    "sg:address":"51 E 4th St",
    "sg:city":"Winona",
    "sg:classifiers":[
        {
            "category":"Shopping",
            "subcategory":"Clothing, Apparel, & Fashions",
            "type":"Retail Goods"
        }
    ],
    "sg:phone":"+1 507 452 7142",
    "sg:postcode":"55987",
    "sg:province":"MN",
    "sg:tags":[
        "tailor"
    ],
    "wof:name":"Tailor Maid",
    "wof:placetype":"venue"
},
  "geometry": {"coordinates":[-91.63646199999999,44.051141],"type":"Point"}
}