{
  "type": "Feature",
  "properties": {
    "addr:full":"1321 Duckwood Dr Eagan MN 55123",
    "addr:housenumber":"1321",
    "addr:postcode":"55123",
    "addr:street":"Duckwood Dr",
    "iso:country":"US",
    "sg:address":"1321 Duckwood Dr",
    "sg:city":"Eagan",
    "sg:classifiers":[
        {
            "category":"Retail",
            "subcategory":"Veterinary Services",
            "type":"Services"
        }
    ],
    "sg:phone":"+1 651 456 5665",
    "sg:postcode":"55123",
    "sg:province":"MN",
    "sg:tags":[
        "veterinarian"
    ],
    "wof:name":"VCA Companion Animal Hospital",
    "wof:placetype":"venue"
},
  "geometry": {"coordinates":[-93.161894,44.827429],"type":"Point"}
}