{
  "type": "Feature",
  "properties": {
    "addr:full":"4620 Beacon Hill Rd St Paul MN 55122",
    "addr:housenumber":"4620",
    "addr:postcode":"55122",
    "addr:street":"Beacon Hill Rd",
    "iso:country":"US",
    "sg:address":"4620 Beacon Hill Rd",
    "sg:city":"St Paul",
    "sg:classifiers":[
        {
            "category":"Professional",
            "subcategory":"Computer Services",
            "type":"Services"
        }
    ],
    "sg:phone":"+1 651 452 1971",
    "sg:postcode":"55122",
    "sg:province":"MN",
    "sg:tags":[
        "consultant",
        "designer"
    ],
    "sg:website":"www.staneksoftware.com",
    "wof:name":"Stanek Software Dev Inc",
    "wof:placetype":"venue"
},
  "geometry": {"coordinates":[-93.181135,44.789928],"type":"Point"}
}