{
  "type": "Feature",
  "properties": {
    "addr:full":"6084 12th St N St Paul MN 55128",
    "addr:housenumber":"6084",
    "addr:postcode":"55128",
    "addr:street":"12Th St N",
    "iso:country":"US",
    "sg:address":"6084 12th St N",
    "sg:city":"St Paul",
    "sg:classifiers":[
        {
            "category":"Shopping",
            "subcategory":"Tobacco",
            "type":"Retail Goods"
        }
    ],
    "sg:phone":"+1 651 739 1871",
    "sg:postcode":"55128",
    "sg:province":"MN",
    "sg:tags":[
        "shop",
        "product",
        "smoke",
        "supply"
    ],
    "wof:name":"Smokers Oasis",
    "wof:placetype":"venue"
},
  "geometry": {"coordinates":[-92.983847,44.965738],"type":"Point"}
}