{
  "type": "Feature",
  "properties": {
    "iso:country":"US",
    "sg:address":"306 3rd Ave NE",
    "sg:city":"Dodge Center",
    "sg:classifiers":[
        {
            "category":"Professional",
            "type":"Services"
        }
    ],
    "sg:phone":"+1 507 374 6861",
    "sg:postcode":"55927",
    "sg:province":"MN",
    "wof:name":"Lynn Shaw",
    "wof:placetype":"venue"
},
  "geometry": {"coordinates":[-92.850972,44.030376],"type":"Point"}
}