{
  "type": "Feature",
  "properties": {
    "iso:country":"US",
    "sg:address":"654 S Shore Dr",
    "sg:city":"Windom",
    "sg:classifiers":[
        {
            "category":"Organizations",
            "subcategory":"Non-profit Organization",
            "type":"Services"
        }
    ],
    "sg:phone":"+1 507 831 2159",
    "sg:postcode":"56101",
    "sg:province":"MN",
    "sg:tags":[
        "fund",
        "counselor",
        "raising"
    ],
    "wof:name":"Rangeway Marketing",
    "wof:placetype":"venue"
},
  "geometry": {"coordinates":[-95.054698,43.837591],"type":"Point"}
}