{
  "type": "Feature",
  "properties": {
    "iso:country":"US",
    "sg:address":"1337 Madison St",
    "sg:city":"Hastings",
    "sg:classifiers":[
        {
            "category":"Building & Trades",
            "subcategory":"Construction",
            "type":"Services"
        }
    ],
    "sg:phone":"+1 651 437 6496",
    "sg:postcode":"55033",
    "sg:province":"MN",
    "sg:tags":[
        "house"
    ],
    "wof:name":"Bob Kruse Construction",
    "wof:placetype":"venue"
},
  "geometry": {"coordinates":[-92.88215599999999,44.751065],"type":"Point"}
}