{
  "type": "Feature",
  "properties": {
    "addr:full":"831 Main St NW Elk River MN 55330",
    "addr:housenumber":"831",
    "addr:postcode":"55330",
    "addr:street":"Main St Nw",
    "iso:country":"US",
    "sg:address":"831 Main St NW",
    "sg:city":"Elk River",
    "sg:classifiers":[
        {
            "category":"Professional",
            "subcategory":"Accounting & Tax Preparation",
            "type":"Services"
        }
    ],
    "sg:phone":"+1 763 441 5060",
    "sg:postcode":"55330",
    "sg:province":"MN",
    "wof:name":"Lawrence E Vaske",
    "wof:placetype":"venue"
},
  "geometry": {"coordinates":[-93.552516,45.312712],"type":"Point"}
}