{
  "type": "Feature",
  "properties": {
    "iso:country":"US",
    "sg:address":"2608 W 102nd St",
    "sg:city":"Minneapolis",
    "sg:classifiers":[
        {
            "category":"Professional",
            "subcategory":"Employment Agencies",
            "type":"Services"
        }
    ],
    "sg:phone":"+1 952 948 1948",
    "sg:postcode":"55431",
    "sg:province":"MN",
    "sg:tags":[
        "placement"
    ],
    "wof:name":"Schalekamp & Associates Inc",
    "wof:placetype":"venue"
},
  "geometry": {"coordinates":[-93.31349899999999,44.819199],"type":"Point"}
}