{
  "type": "Feature",
  "properties": {
    "addr:full":"11715 177th St W Lakeville MN 55044",
    "addr:housenumber":"11715",
    "addr:postcode":"55044",
    "addr:street":"177Th St W",
    "iso:country":"US",
    "sg:address":"11715 177th St W",
    "sg:city":"Lakeville",
    "sg:classifiers":[
        {
            "category":"Shopping",
            "subcategory":"Computers & Home Electronics",
            "type":"Retail Goods"
        }
    ],
    "sg:phone":"+1 952 435 3481",
    "sg:postcode":"55044",
    "sg:province":"MN",
    "wof:name":"AGF Assoc Inc",
    "wof:placetype":"venue"
},
  "geometry": {"coordinates":[-93.302374,44.692837],"type":"Point"}
}