{
  "type": "Feature",
  "properties": {
    "iso:country":"US",
    "sg:address":"1018 Sibley St",
    "sg:city":"Hastings",
    "sg:classifiers":[
        {
            "category":"Personal",
            "subcategory":"Beauty Salon",
            "type":"Services"
        }
    ],
    "sg:phone":"+1 651 437 5165",
    "sg:postcode":"55033",
    "sg:province":"MN",
    "sg:tags":[
        "shop"
    ],
    "wof:name":"Hair Cuttery",
    "wof:placetype":"venue"
},
  "geometry": {"coordinates":[-92.851285,44.735228],"type":"Point"}
}