{
  "type": "Feature",
  "properties": {
    "addr:full":"1744 Walnut St Saint Paul MN 55113",
    "addr:housenumber":"1744",
    "addr:postcode":"55113",
    "addr:street":"Walnut St",
    "iso:country":"US",
    "sg:address":"1744 Walnut St",
    "sg:city":"Saint Paul",
    "sg:classifiers":[
        {
            "category":"Organizations",
            "subcategory":"Religious Organization",
            "type":"Services"
        }
    ],
    "sg:phone":"+1 651 644 5440",
    "sg:postcode":"55113",
    "sg:province":"MN",
    "wof:name":"Evanglcal Lthern Chrch In Amer",
    "wof:placetype":"venue"
},
  "geometry": {"coordinates":[-93.20495200000001,44.994498],"type":"Point"}
}