{
  "type": "Feature",
  "properties": {
    "addr:full":"211 S Main Ave Hills MN 56138",
    "addr:housenumber":"211",
    "addr:postcode":"56138",
    "addr:street":"S Main Ave",
    "iso:country":"US",
    "sg:address":"211 S Main Ave",
    "sg:city":"Hills",
    "sg:classifiers":[
        {
            "category":"Professional",
            "subcategory":"Business Services",
            "type":"Services"
        }
    ],
    "sg:phone":"+1 507 962 3433",
    "sg:postcode":"56138",
    "sg:province":"MN",
    "sg:tags":[
        "auctioneer"
    ],
    "wof:name":"Elbers Auction Service",
    "wof:placetype":"venue"
},
  "geometry": {"coordinates":[-96.358942,43.528044],"type":"Point"}
}