{
  "type": "Feature",
  "properties": {
    "addr:full":"14345 100th St N Stillwater MN 55082",
    "addr:housenumber":"14345",
    "addr:postcode":"55082",
    "addr:street":"100Th St N",
    "iso:country":"US",
    "sg:address":"14345 100th St N",
    "sg:city":"Stillwater",
    "sg:classifiers":[
        {
            "category":"Communications",
            "subcategory":"Film & Video Production",
            "type":"Services"
        }
    ],
    "sg:phone":"+1 651 351 0511",
    "sg:postcode":"55082",
    "sg:province":"MN",
    "sg:tags":[
        "motion"
    ],
    "wof:name":"Quest Productions",
    "wof:placetype":"venue"
},
  "geometry": {"coordinates":[-92.814758,45.09364],"type":"Point"}
}