{
  "type": "Feature",
  "properties": {
    "addr:full":"1721 Viking Rd Worthington MN 56187",
    "addr:housenumber":"1721",
    "addr:postcode":"56187",
    "addr:street":"Viking Rd",
    "iso:country":"US",
    "sg:address":"1721 Viking Rd",
    "sg:city":"Worthington",
    "sg:classifiers":[
        {
            "category":"Professional",
            "subcategory":"Computer Services",
            "type":"Services"
        }
    ],
    "sg:phone":"+1 507 376 5910",
    "sg:postcode":"56187",
    "sg:province":"MN",
    "sg:tags":[
        "prepackaged",
        "software"
    ],
    "wof:name":"Star City Word Processing",
    "wof:placetype":"venue"
},
  "geometry": {"coordinates":[-95.619021,43.633327],"type":"Point"}
}