{
  "type": "Feature",
  "properties": {
    "addr:full":"10540 Abbott Ave S Minneapolis MN 55431",
    "addr:housenumber":"10540",
    "addr:postcode":"55431",
    "addr:street":"Abbott Ave S",
    "iso:country":"US",
    "sg:address":"10540 Abbott Ave S",
    "sg:city":"Minneapolis",
    "sg:classifiers":[
        {
            "category":"Professional",
            "subcategory":"Accounting & Tax Preparation",
            "type":"Services"
        }
    ],
    "sg:phone":"+1 952 886 0106",
    "sg:postcode":"55431",
    "sg:province":"MN",
    "sg:tags":[
        "return"
    ],
    "wof:name":"Dawn Mould",
    "wof:placetype":"venue"
},
  "geometry": {"coordinates":[-93.32317399999999,44.813993],"type":"Point"}
}