{
  "type": "Feature",
  "properties": {
    "iso:country":"US",
    "sg:address":"2720 W 43rd St",
    "sg:city":"Minneapolis",
    "sg:classifiers":[
        {
            "category":"Health Services",
            "subcategory":"Health Practitioner",
            "type":"Services"
        },
        {
            "category":"Health Services",
            "subcategory":"Doctor",
            "type":"Services"
        }
    ],
    "sg:phone":"+1 952 920 9550",
    "sg:postcode":"55410",
    "sg:province":"MN",
    "sg:tags":[
        "psychotherapist",
        "medical"
    ],
    "wof:name":"Jungian Psychoanalytic Practic",
    "wof:placetype":"venue"
},
  "geometry": {"coordinates":[-93.313395,44.924447],"type":"Point"}
}