{
  "type": "Feature",
  "properties": {
    "addr:full":"2031 14th St NW Rochester MN 55901",
    "addr:housenumber":"2031",
    "addr:postcode":"55901",
    "addr:street":"14Th St Nw",
    "iso:country":"US",
    "sg:address":"2031 14th St NW",
    "sg:city":"Rochester",
    "sg:classifiers":[
        {
            "category":"Freight",
            "type":"Transportation"
        }
    ],
    "sg:phone":"+1 507 281 4011",
    "sg:postcode":"55901",
    "sg:province":"MN",
    "sg:tags":[
        "operator",
        "trucking"
    ],
    "sg:website":"www.lakevillemotorexpress.com",
    "wof:name":"Lakeville Motor Express",
    "wof:placetype":"venue"
},
  "geometry": {"coordinates":[-92.494367,44.036281],"type":"Point"}
}