{
  "type": "Feature",
  "properties": {
    "addr:full":"2855 Grand St NE Minneapolis MN 55418",
    "addr:housenumber":"2855",
    "addr:postcode":"55418",
    "addr:street":"Grand St Ne",
    "iso:country":"US",
    "sg:address":"2855 Grand St NE",
    "sg:city":"Minneapolis",
    "sg:classifiers":[
        {
            "category":"Health Services",
            "subcategory":"Clinic",
            "type":"Services"
        }
    ],
    "sg:phone":"+1 612 782 0835",
    "sg:postcode":"55418",
    "sg:province":"MN",
    "sg:tags":[
        "information",
        "alcoholism",
        "treatment"
    ],
    "wof:name":"Massage Therapy By Yogamary",
    "wof:placetype":"venue"
},
  "geometry": {"coordinates":[-93.270133,45.019637],"type":"Point"}
}