{
  "type": "Feature",
  "properties": {
    "iso:country":"US",
    "sg:address":"18076 Wellington Ave",
    "sg:city":"Prior Lake",
    "sg:classifiers":[
        {
            "category":"Building & Trades",
            "subcategory":"Landscaping Services",
            "type":"Services"
        }
    ],
    "sg:phone":"+1 952 447 8450",
    "sg:postcode":"55372",
    "sg:province":"MN",
    "sg:tags":[
        "lawn",
        "maintenance",
        "grounds"
    ],
    "wof:name":"Laker Lawn Svc",
    "wof:placetype":"venue"
},
  "geometry": {"coordinates":[-93.416076,44.686511],"type":"Point"}
}