{
  "type": "Feature",
  "properties": {
    "addr:full":"1698 Vierling Dr E Shakopee MN 55379",
    "addr:housenumber":"1698",
    "addr:postcode":"55379",
    "addr:street":"Vierling Dr E",
    "iso:country":"US",
    "sg:address":"1698 Vierling Dr E",
    "sg:city":"Shakopee",
    "sg:phone":"+1 952 230 5700",
    "sg:postcode":"55379",
    "sg:province":"MN",
    "sg:website":"http://www.goldsgym.com",
    "wof:name":"Gold's Gym",
    "wof:placetype":"venue"
},
  "geometry": {"coordinates":[-93.501007,44.780918],"type":"Point"}
}