{
  "type": "Feature",
  "properties": {
    "addr:full":"144 McKinley St Manchester MN 56007",
    "addr:housenumber":"144",
    "addr:postcode":"56007",
    "addr:street":"Mckinley St",
    "iso:country":"US",
    "sg:address":"144 McKinley St",
    "sg:city":"Manchester",
    "sg:classifiers":[
        {
            "category":"Government",
            "subcategory":"Post Office",
            "type":"Public Place"
        }
    ],
    "sg:phone":"+1 507 826 3395",
    "sg:postcode":"56007",
    "sg:province":"MN",
    "wof:name":"US Post Office",
    "wof:placetype":"venue"
},
  "geometry": {"coordinates":[-93.453371,43.724353],"type":"Point"}
}