{
  "type": "Feature",
  "properties": {
    "iso:country":"US",
    "sg:address":"1438 Kingswood Rd",
    "sg:city":"Saint Paul",
    "sg:classifiers":[
        {
            "category":"Travel",
            "subcategory":"Travel Agent",
            "type":"Entertainment"
        }
    ],
    "sg:phone":"+1 651 688 0113",
    "sg:postcode":"55122",
    "sg:province":"MN",
    "sg:tags":[
        "operator",
        "tour",
        "agency"
    ],
    "wof:name":"American Cruises Tours",
    "wof:placetype":"venue"
},
  "geometry": {"coordinates":[-93.167911,44.816716],"type":"Point"}
}