{
  "type": "Feature",
  "properties": {
    "addr:full":"1516 3rd St N Saint Cloud MN 56303",
    "addr:housenumber":"1516",
    "addr:postcode":"56303",
    "addr:street":"3Rd St N",
    "iso:country":"US",
    "sg:address":"1516 3rd St N",
    "sg:city":"Saint Cloud",
    "sg:classifiers":[
        {
            "category":"Wholesale",
            "subcategory":"Drugs",
            "type":"Manufacturing & Wholesale Goods"
        }
    ],
    "sg:phone":"+1 320 251 3175",
    "sg:postcode":"56303",
    "sg:province":"MN",
    "sg:tags":[
        "food"
    ],
    "wof:name":"Bernadine Chrstman Shklee Dist",
    "wof:placetype":"venue"
},
  "geometry": {"coordinates":[-94.172946,45.558614],"type":"Point"}
}