{
  "type": "Feature",
  "properties": {
    "iso:country":"US",
    "sg:address":"11118 Stanley Cir",
    "sg:city":"Minneapolis",
    "sg:classifiers":[
        {
            "category":"Professional",
            "subcategory":"Computer Services",
            "type":"Services"
        }
    ],
    "sg:phone":"+1 952 886 0933",
    "sg:postcode":"55437",
    "sg:province":"MN",
    "wof:name":"Ballinger Services",
    "wof:placetype":"venue"
},
  "geometry": {"coordinates":[-93.345913,44.801212],"type":"Point"}
}