{
  "type": "Feature",
  "properties": {
    "addr:full":"1819 3rd Ave NW East Grand Forks MN 56721",
    "addr:housenumber":"1819",
    "addr:postcode":"56721",
    "addr:street":"3Rd Ave Nw",
    "iso:country":"US",
    "sg:address":"1819 3rd Ave NW",
    "sg:city":"East Grand Forks",
    "sg:classifiers":[
        {
            "category":"Real Estate",
            "subcategory":"Real Estate Operator",
            "type":"Services"
        }
    ],
    "sg:phone":"+1 218 773 1871",
    "sg:postcode":"56721",
    "sg:province":"MN",
    "sg:tags":[
        "apartment"
    ],
    "wof:name":"Northwood Park Townhomes",
    "wof:placetype":"venue"
},
  "geometry": {"coordinates":[-97.023067,47.944024],"type":"Point"}
}