{
  "type": "Feature",
  "properties": {
    "addr:full":"4635 Nicols Rd Saint Paul MN 55122",
    "addr:housenumber":"4635",
    "addr:postcode":"55122",
    "addr:street":"Nicols Rd",
    "iso:country":"US",
    "sg:address":"4635 Nicols Rd",
    "sg:city":"Saint Paul",
    "sg:classifiers":[
        {
            "category":"Banks & Credit Unions",
            "subcategory":"Bank",
            "type":"Services"
        }
    ],
    "sg:phone":"+1 651 681 8500",
    "sg:postcode":"55122",
    "sg:province":"MN",
    "sg:tags":[
        "depository",
        "banking"
    ],
    "wof:name":"Monarch Atm Management",
    "wof:placetype":"venue"
},
  "geometry": {"coordinates":[-93.217924,44.788301],"type":"Point"}
}