{
  "type": "Feature",
  "properties": {
    "iso:country":"US",
    "sg:address":"1741 2nd St SW",
    "sg:city":"Rochester",
    "sg:classifiers":[
        {
            "category":"Real Estate",
            "subcategory":"Real Estate Services",
            "type":"Services"
        }
    ],
    "sg:phone":"+1 507 288 4355",
    "sg:postcode":"55902",
    "sg:province":"MN",
    "sg:tags":[
        "company",
        "title"
    ],
    "wof:name":"Title Insurance",
    "wof:placetype":"venue"
},
  "geometry": {"coordinates":[-92.489873,44.021602],"type":"Point"}
}