{
  "type": "Feature",
  "properties": {
    "addr:full":"7320 Oakland Ave S Minneapolis MN 55423",
    "addr:housenumber":"7320",
    "addr:postcode":"55423",
    "addr:street":"Oakland Ave S",
    "iso:country":"US",
    "sg:address":"7320 Oakland Ave S",
    "sg:city":"Minneapolis",
    "sg:classifiers":[
        {
            "category":"Professional",
            "type":"Services"
        }
    ],
    "sg:phone":"+1 612 869 4521",
    "sg:postcode":"55423",
    "sg:province":"MN",
    "wof:name":"Jason & Associates Inc",
    "wof:placetype":"venue"
},
  "geometry": {"coordinates":[-93.26688,44.869466],"type":"Point"}
}