{
  "type": "Feature",
  "properties": {
    "iso:country":"US",
    "sg:address":"5785 Hunters Rd",
    "sg:city":"Chaska",
    "sg:classifiers":[
        {
            "category":"Recreation",
            "type":"Entertainment"
        }
    ],
    "sg:phone":"+1 952 443 2082",
    "sg:postcode":"55318",
    "sg:province":"MN",
    "sg:tags":[
        "preserve",
        "boarding",
        "kennel",
        "hunting"
    ],
    "wof:name":"Marsh Lake Hunting Preserve",
    "wof:placetype":"venue"
},
  "geometry": {"coordinates":[-93.66750999999999,44.827595],"type":"Point"}
}