{
  "type": "Feature",
  "properties": {
    "iso:country":"US",
    "sg:address":"530 S Main St",
    "sg:city":"Holdingford",
    "sg:classifiers":[
        {
            "category":"Restaurant",
            "type":"Food & Drink"
        }
    ],
    "sg:phone":"+1 320 746 2401",
    "sg:postcode":"56340",
    "sg:province":"MN",
    "wof:name":"Mary's Family Restaurant",
    "wof:placetype":"venue"
},
  "geometry": {"coordinates":[-94.475615,45.729939],"type":"Point"}
}