{
  "type": "Feature",
  "properties": {
    "addr:full":"2660 Ann Dr Shakopee MN 55379",
    "addr:housenumber":"2660",
    "addr:postcode":"55379",
    "addr:street":"Ann Dr",
    "iso:country":"US",
    "sg:address":"2660 Ann Dr",
    "sg:city":"Shakopee",
    "sg:classifiers":[
        {
            "category":"Utilities",
            "type":"Services"
        }
    ],
    "sg:phone":"+1 952 445 9507",
    "sg:postcode":"55379",
    "sg:province":"MN",
    "sg:tags":[
        "sanitary"
    ],
    "wof:name":"Rons Snow Removal",
    "wof:placetype":"venue"
},
  "geometry": {"coordinates":[-93.57277499999999,44.756248],"type":"Point"}
}