{
  "type": "Feature",
  "properties": {
    "iso:country":"US",
    "sg:address":"1287 2nd St N",
    "sg:city":"Sauk Rapids",
    "sg:classifiers":[
        {
            "category":"Professional",
            "subcategory":"Lawyer & Legal Services",
            "type":"Services"
        }
    ],
    "sg:phone":"+1 320 251 7381",
    "sg:postcode":"56379",
    "sg:province":"MN",
    "sg:tags":[
        "attorney"
    ],
    "wof:name":"Jessica J Smith",
    "wof:placetype":"venue"
},
  "geometry": {"coordinates":[-94.153673,45.598229],"type":"Point"}
}