{
  "type": "Feature",
  "properties": {
    "iso:country":"US",
    "sg:address":"4000 Valley Industrial Blvd S",
    "sg:city":"Shakopee",
    "sg:classifiers":[
        {
            "category":"Building & Trades",
            "subcategory":"Construction",
            "type":"Services"
        }
    ],
    "sg:phone":"+1 952 934 4695",
    "sg:postcode":"55379",
    "sg:province":"MN",
    "sg:tags":[
        "contractor"
    ],
    "wof:name":"R T L Construction Inc",
    "wof:placetype":"venue"
},
  "geometry": {"coordinates":[-93.46244299999999,44.793217],"type":"Point"}
}