{
  "type": "Feature",
  "properties": {
    "iso:country":"US",
    "sg:address":"2500 23rd Ave S",
    "sg:city":"Minneapolis",
    "sg:classifiers":[
        {
            "category":"Utilities",
            "subcategory":"Natural Gas",
            "type":"Services"
        }
    ],
    "sg:phone":"+1 612 721 4112",
    "sg:postcode":"55404",
    "sg:province":"MN",
    "sg:tags":[
        "cylinders-air",
        "hydraulic"
    ],
    "sg:website":"http://www.mycylinderheadservice.com",
    "wof:name":"Cylinder Head Service Inc",
    "wof:placetype":"venue"
},
  "geometry": {"coordinates":[-93.239288,44.957352],"type":"Point"}
}