{
  "type": "Feature",
  "properties": {
    "addr:full":"5192 Central Ave NE Minneapolis MN 55421",
    "addr:housenumber":"5192",
    "addr:postcode":"55421",
    "addr:street":"Central Ave Ne",
    "iso:country":"US",
    "sg:address":"5192 Central Ave NE",
    "sg:city":"Minneapolis",
    "sg:classifiers":[
        {
            "category":"Government",
            "subcategory":"Office",
            "type":"Public Place"
        }
    ],
    "sg:phone":"+1 612 334 4000",
    "sg:postcode":"55421",
    "sg:province":"MN",
    "sg:tags":[
        "guard",
        "station",
        "recruiting",
        "coast"
    ],
    "wof:name":"Coast Guard Recruiting Office",
    "wof:placetype":"venue"
},
  "geometry": {"coordinates":[-93.24779599999999,45.06193],"type":"Point"}
}