{
  "type": "Feature",
  "properties": {
    "addr:full":"1155 US Hwy 10 E Detroit Lakes MN 56501",
    "addr:housenumber":"1155",
    "addr:postcode":"56501",
    "addr:street":"Us Hwy 10 E",
    "iso:country":"US",
    "sg:address":"1155 US Hwy 10 E",
    "sg:city":"Detroit Lakes",
    "sg:classifiers":[
        {
            "category":"Travel",
            "subcategory":"Hotels & Motels",
            "type":"Entertainment"
        }
    ],
    "sg:phone":"+1 218 847 2121",
    "sg:postcode":"56501",
    "sg:province":"MN",
    "sg:tags":[
        "personal",
        "operation",
        "eating"
    ],
    "wof:name":"Holiday Inn",
    "wof:placetype":"venue"
},
  "geometry": {"coordinates":[-95.81536699999999,46.805708],"type":"Point"}
}