{
  "type": "Feature",
  "properties": {
    "addr:full":"2104 Mississippi St Saint Paul MN 55117",
    "addr:housenumber":"2104",
    "addr:postcode":"55117",
    "addr:street":"Mississippi St",
    "iso:country":"US",
    "sg:address":"2104 Mississippi St",
    "sg:city":"Saint Paul",
    "sg:classifiers":[
        {
            "category":"Professional",
            "type":"Services"
        }
    ],
    "sg:phone":"+1 651 772 4368",
    "sg:postcode":"55117",
    "sg:province":"MN",
    "wof:name":"V Temp Service",
    "wof:placetype":"venue"
},
  "geometry": {"coordinates":[-93.088702,45.00436],"type":"Point"}
}