{
  "type": "Feature",
  "properties": {
    "addr:full":"34 6th Ave S Sauk Rapids MN 56379",
    "addr:housenumber":"34",
    "addr:postcode":"56379",
    "addr:street":"6Th Ave S Sauk",
    "iso:country":"US",
    "sg:address":"34 6th Ave S",
    "sg:city":"Sauk Rapids",
    "sg:classifiers":[
        {
            "category":"Home & Garden",
            "subcategory":"Home Furnishings",
            "type":"Retail Goods"
        }
    ],
    "sg:phone":"+1 320 259 8854",
    "sg:postcode":"56379",
    "sg:province":"MN",
    "sg:tags":[
        "lighting",
        "fixture"
    ],
    "wof:name":"J & P Enterprises",
    "wof:placetype":"venue"
},
  "geometry": {"coordinates":[-94.15922399999999,45.590872],"type":"Point"}
}