{
  "type": "Feature",
  "properties": {
    "iso:country":"US",
    "sg:address":"13366 Lake Dr NE",
    "sg:city":"Forest Lake",
    "sg:classifiers":[
        {
            "category":"Wholesale",
            "subcategory":"Durable Goods & Equipment",
            "type":"Manufacturing & Wholesale Goods"
        }
    ],
    "sg:phone":"+1 651 982 9802",
    "sg:postcode":"55025",
    "sg:province":"MN",
    "sg:tags":[
        "representative",
        "manufacturer"
    ],
    "wof:name":"Bongard Corp",
    "wof:placetype":"venue"
},
  "geometry": {"coordinates":[-93.093519,45.212861],"type":"Point"}
}