{
  "type": "Feature",
  "properties": {
    "iso:country":"US",
    "sg:address":"525 Kasota Ave SE",
    "sg:city":"Minneapolis",
    "sg:classifiers":[
        {
            "category":"Transit Center",
            "subcategory":"Freight",
            "type":"Transportation"
        },
        {
            "category":"Freight",
            "type":"Transportation"
        }
    ],
    "sg:phone":"+1 612 379 8170",
    "sg:postcode":"55414",
    "sg:province":"MN",
    "sg:tags":[
        "local",
        "trucking-motor",
        "trucking"
    ],
    "sg:website":"http://www.crownassociates.com",
    "wof:name":"Triple Crown Services Company",
    "wof:placetype":"venue"
},
  "geometry": {"coordinates":[-93.20782,44.977238],"type":"Point"}
}