{
  "type": "Feature",
  "properties": {
    "iso:country":"US",
    "sg:address":"908 2nd Ave",
    "sg:city":"Proctor",
    "sg:classifiers":[
        {
            "category":"Wholesale",
            "subcategory":"Office Equipment",
            "type":"Manufacturing & Wholesale Goods"
        }
    ],
    "sg:phone":"+1 218 624 3231",
    "sg:postcode":"55810",
    "sg:province":"MN",
    "sg:tags":[
        "credit"
    ],
    "wof:name":"Heartland Payment Systems",
    "wof:placetype":"venue"
},
  "geometry": {"coordinates":[-92.22222499999999,46.752298],"type":"Point"}
}