{
  "type": "Feature",
  "properties": {
    "iso:country":"US",
    "sg:address":"1687 Manning Ave N",
    "sg:city":"Lake Elmo",
    "sg:classifiers":[
        {
            "category":"Building & Trades",
            "subcategory":"Plumbing",
            "type":"Services"
        }
    ],
    "sg:phone":"+1 651 436 7085",
    "sg:postcode":"55042",
    "sg:province":"MN",
    "sg:tags":[
        "contractor",
        "mechanical"
    ],
    "wof:name":"Elektro Mechanical Services",
    "wof:placetype":"venue"
},
  "geometry": {"coordinates":[-92.854906,44.971927],"type":"Point"}
}