{
  "type": "Feature",
  "properties": {
    "addr:full":"2844 Johnson St NE Minneapolis MN 55418",
    "addr:housenumber":"2844",
    "addr:postcode":"55418",
    "addr:street":"Johnson St Ne",
    "iso:country":"US",
    "sg:address":"2844 Johnson St NE",
    "sg:city":"Minneapolis",
    "sg:classifiers":[
        {
            "category":"Real Estate",
            "subcategory":"Real Estate Agent",
            "type":"Services"
        }
    ],
    "sg:phone":"+1 612 256 4889",
    "sg:postcode":"55418",
    "sg:province":"MN",
    "sg:website":"http://www.judlauzon.com",
    "wof:name":"IBR Realty Minneapolis-St Paul",
    "wof:placetype":"venue"
},
  "geometry": {"coordinates":[-93.23711900000001,45.019447],"type":"Point"}
}