{
  "type": "Feature",
  "properties": {
    "iso:country":"US",
    "sg:address":"226 Main St S",
    "sg:city":"Stillwater",
    "sg:classifiers":[
        {
            "category":"Shopping",
            "subcategory":"Clothing, Apparel, & Fashions",
            "type":"Retail Goods"
        }
    ],
    "sg:phone":"+1 763 757 3835",
    "sg:postcode":"55082",
    "sg:province":"MN",
    "sg:tags":[
        "infant",
        "wear"
    ],
    "wof:name":"Heaven Sent",
    "wof:placetype":"venue"
},
  "geometry": {"coordinates":[-92.805616,45.055122],"type":"Point"}
}