{
  "type": "Feature",
  "properties": {
    "iso:country":"US",
    "sg:address":"1 Sunrise Dr",
    "sg:city":"Virginia",
    "sg:classifiers":[
        {
            "category":"Organizations",
            "subcategory":"Religious Organization",
            "type":"Services"
        }
    ],
    "sg:phone":"+1 218 741 2124",
    "sg:postcode":"55792",
    "sg:province":"MN",
    "sg:tags":[
        "church"
    ],
    "sg:website":"www.true-hope.com",
    "wof:name":"Virginia Assembly Of God Chr",
    "wof:placetype":"venue"
},
  "geometry": {"coordinates":[-92.52327099999999,47.490142],"type":"Point"}
}