{
  "type": "Feature",
  "properties": {
    "iso:country":"US",
    "sg:address":"2407 33rd Ave NE",
    "sg:city":"Minneapolis",
    "sg:classifiers":[
        {
            "category":"Professional",
            "type":"Services"
        }
    ],
    "sg:phone":"+1 651 450 1316",
    "sg:postcode":"55418",
    "sg:province":"MN",
    "wof:name":"Godes String Instrument L",
    "wof:placetype":"venue"
},
  "geometry": {"coordinates":[-93.225526,45.027793],"type":"Point"}
}