{
  "type": "Feature",
  "properties": {
    "addr:full":"304 N Fairview Dr Luverne MN 56156",
    "addr:housenumber":"304",
    "addr:postcode":"56156",
    "addr:street":"N Fairview Dr",
    "iso:country":"US",
    "sg:address":"304 N Fairview Dr",
    "sg:city":"Luverne",
    "sg:classifiers":[
        {
            "category":"Organizations",
            "subcategory":"Religious Organization",
            "type":"Services"
        }
    ],
    "sg:phone":"+1 507 283 8600",
    "sg:postcode":"56156",
    "sg:province":"MN",
    "wof:name":"American Reformed Church",
    "wof:placetype":"venue"
},
  "geometry": {"coordinates":[-96.212653,43.66698],"type":"Point"}
}