{
  "type": "Feature",
  "properties": {
    "iso:country":"US",
    "sg:address":"100 Roosevelt Rd",
    "sg:city":"St Cloud",
    "sg:phone":"+1 320 252 2977",
    "sg:postcode":"56301",
    "sg:province":"MN",
    "sg:tags":[
        "equipment",
        "supply"
    ],
    "wof:name":"Strategic Equipment & Supply",
    "wof:placetype":"venue"
},
  "geometry": {"coordinates":[-94.188729,45.549789],"type":"Point"}
}