{
  "type": "Feature",
  "properties": {
    "iso:country":"US",
    "sg:address":"7900 International Dr",
    "sg:city":"Minneapolis",
    "sg:classifiers":[
        {
            "category":"Insurance",
            "subcategory":"Health Insurance",
            "type":"Services"
        }
    ],
    "sg:phone":"+1 952 883 3133",
    "sg:postcode":"55425",
    "sg:province":"MN",
    "sg:tags":[
        "medical",
        "plan"
    ],
    "wof:name":"Minnesota Halthcare Netwrk LLC",
    "wof:placetype":"venue"
},
  "geometry": {"coordinates":[-93.22612700000001,44.860221],"type":"Point"}
}