{
  "type": "Feature",
  "properties": {
    "iso:country":"US",
    "sg:address":"7351 Kirkwood Ln N",
    "sg:city":"Osseo",
    "sg:classifiers":[
        {
            "category":"Manufacturing",
            "subcategory":"Tools & Machinery",
            "type":"Manufacturing & Wholesale Goods"
        }
    ],
    "sg:phone":"+1 763 315 8080",
    "sg:postcode":"55369",
    "sg:province":"MN",
    "sg:tags":[
        "computer",
        "photographic",
        "mfg"
    ],
    "wof:name":"Symbology Inc",
    "wof:placetype":"venue"
},
  "geometry": {"coordinates":[-93.43454699999999,45.08757],"type":"Point"}
}