{
  "type": "Feature",
  "properties": {
    "addr:full":"45105 220th St Springfield MN 56087",
    "addr:housenumber":"45105",
    "addr:postcode":"56087",
    "addr:street":"220Th St",
    "iso:country":"US",
    "sg:address":"45105 220th St",
    "sg:city":"Springfield",
    "sg:phone":"+1 507 723 9956",
    "sg:postcode":"56087",
    "sg:province":"MN",
    "sg:tags":[
        "farm",
        "corn",
        "soybean"
    ],
    "wof:name":"Dale Roiger",
    "wof:placetype":"venue"
},
  "geometry": {"coordinates":[-94.889134,44.282351],"type":"Point"}
}