{
  "type": "Feature",
  "properties": {
    "addr:full":"2780 10th Ave NE Sauk Rapids MN 56379",
    "addr:housenumber":"2780",
    "addr:postcode":"56379",
    "addr:street":"10Th Ave Ne",
    "iso:country":"US",
    "sg:address":"2780 10th Ave NE",
    "sg:city":"Sauk Rapids",
    "sg:classifiers":[
        {
            "category":"Freight",
            "type":"Transportation"
        }
    ],
    "sg:phone":"+1 320 253 8471",
    "sg:postcode":"56379",
    "sg:province":"MN",
    "sg:tags":[
        "operator",
        "local",
        "trucking"
    ],
    "wof:name":"John Kiley and Son",
    "wof:placetype":"venue"
},
  "geometry": {"coordinates":[-94.143636,45.608024],"type":"Point"}
}