{
  "type": "Feature",
  "properties": {
    "iso:country":"US",
    "sg:address":"82 Ramsey Cir NE",
    "sg:city":"Minneapolis",
    "sg:classifiers":[
        {
            "category":"Communications",
            "subcategory":"Film & Video Production",
            "type":"Services"
        }
    ],
    "sg:phone":"+1 612 379 2339",
    "sg:postcode":"55413",
    "sg:province":"MN",
    "sg:tags":[
        "motion"
    ],
    "wof:name":"Its Productions",
    "wof:placetype":"venue"
},
  "geometry": {"coordinates":[-93.266504,44.993194],"type":"Point"}
}