{
  "type": "Feature",
  "properties": {
    "iso:country":"US",
    "sg:address":"12825 Falcon Dr",
    "sg:city":"Saint Paul",
    "sg:classifiers":[
        {
            "category":"Real Estate",
            "subcategory":"Real Estate Operator",
            "type":"Services"
        }
    ],
    "sg:phone":"+1 952 432 8957",
    "sg:postcode":"55124",
    "sg:province":"MN",
    "sg:tags":[
        "property",
        "lessor"
    ],
    "wof:name":"Jim Knecht",
    "wof:placetype":"venue"
},
  "geometry": {"coordinates":[-93.192241,44.763082],"type":"Point"}
}