{
  "type": "Feature",
  "properties": {
    "addr:full":"312 Central Ave SE Ste 526 Minneapolis MN 55414",
    "addr:housenumber":"312",
    "addr:postcode":"55414",
    "addr:street":"Central Ave Se Ste 526",
    "iso:country":"US",
    "sg:address":"312 Central Ave SE Ste 526",
    "sg:city":"Minneapolis",
    "sg:classifiers":[
        {
            "category":"Communications",
            "subcategory":"Newspaper",
            "type":"Services"
        }
    ],
    "sg:phone":"+1 612 379 4725",
    "sg:postcode":"55414",
    "sg:province":"MN",
    "sg:tags":[
        "print",
        "medium"
    ],
    "wof:name":"Mpls Labor Review Newspaper",
    "wof:placetype":"venue"
},
  "geometry": {"coordinates":[-93.2547,44.9869],"type":"Point"}
}