{
  "type": "Feature",
  "properties": {
    "iso:country":"US",
    "sg:address":"3625 E 43rd St",
    "sg:city":"Minneapolis",
    "sg:classifiers":[
        {
            "category":"Real Estate",
            "subcategory":"Real Estate Operator",
            "type":"Services"
        }
    ],
    "sg:phone":"+1 866 637 6676",
    "sg:postcode":"55406",
    "sg:province":"MN",
    "sg:tags":[
        "apartment"
    ],
    "sg:website":"http://local.ingenio.com/Listings/Details.aspx?NUM=a%3a10338805%3a13%3a4859924%3a14%3a0%3a7",
    "wof:name":"Hiawatha Flats Apartments",
    "wof:placetype":"venue"
},
  "geometry": {"coordinates":[-93.220102,44.925121],"type":"Point"}
}