{
  "type": "Feature",
  "properties": {
    "addr:full":"10600 Wayzata Blvd Minneapolis MN 55401",
    "addr:housenumber":"10600",
    "addr:postcode":"55401",
    "addr:street":"Wayzata Blvd",
    "iso:country":"US",
    "sg:address":"10600 Wayzata Blvd",
    "sg:city":"Minneapolis",
    "sg:classifiers":[
        {
            "category":"Restaurant",
            "type":"Food & Drink"
        },
        {
            "category":"Bars & Pubs",
            "subcategory":"Nightclub",
            "type":"Food & Drink"
        }
    ],
    "sg:phone":"+1 952 541 1430",
    "sg:postcode":"55401",
    "sg:province":"MN",
    "sg:tags":[
        "steakhouse",
        "nightlife"
    ],
    "wof:name":"Cattle Company Restaurant Stuart Anderson's",
    "wof:placetype":"venue"
},
  "geometry": {"coordinates":[-93.269997,44.984501],"type":"Point"}
}