{
  "type": "Feature",
  "properties": {
    "iso:country":"US",
    "sg:address":"900 2nd Ave S Ste 410",
    "sg:city":"Minneapolis",
    "sg:classifiers":[
        {
            "category":"Wholesale",
            "subcategory":"Stationery",
            "type":"Manufacturing & Wholesale Goods"
        }
    ],
    "sg:phone":"+1 612 673 9202",
    "sg:postcode":"55402",
    "sg:province":"MN",
    "sg:tags":[
        "card"
    ],
    "sg:website":"www.papermagic.com",
    "wof:name":"Paper Magic Group",
    "wof:placetype":"venue"
},
  "geometry": {"coordinates":[-93.271218,44.973878],"type":"Point"}
}