{
  "type": "Feature",
  "properties": {
    "addr:full":"16948 S Big Cormorant Rd Audubon MN 56511",
    "addr:housenumber":"16948",
    "addr:postcode":"56511",
    "addr:street":"S Big Cormorant Rd",
    "iso:country":"US",
    "sg:address":"16948 S Big Cormorant Rd",
    "sg:city":"Audubon",
    "sg:classifiers":[
        {
            "category":"Building & Trades",
            "subcategory":"Construction",
            "type":"Services"
        }
    ],
    "sg:phone":"+1 218 439 6709",
    "sg:postcode":"56511",
    "sg:province":"MN",
    "sg:tags":[
        "hanging",
        "contractor"
    ],
    "wof:name":"Northwest Painting",
    "wof:placetype":"venue"
},
  "geometry": {"coordinates":[-96.04922000000001,46.741557],"type":"Point"}
}