{
  "type": "Feature",
  "properties": {
    "addr:full":"222 3rd St NE Faribault MN 55021",
    "addr:housenumber":"222",
    "addr:postcode":"55021",
    "addr:street":"3Rd St Ne",
    "iso:country":"US",
    "sg:address":"222 3rd St NE",
    "sg:city":"Faribault",
    "sg:classifiers":[
        {
            "category":"Food & Beverages",
            "subcategory":"Dairy",
            "type":"Retail Goods"
        }
    ],
    "sg:phone":"+1 507 334 5260",
    "sg:postcode":"55021",
    "sg:province":"MN",
    "sg:tags":[
        "product"
    ],
    "wof:name":"Faribault Dairy Co Inc",
    "wof:placetype":"venue"
},
  "geometry": {"coordinates":[-93.264838,44.293652],"type":"Point"}
}