{
  "type": "Feature",
  "properties": {
    "addr:full":"15679 10th St Brownton MN 55312",
    "addr:housenumber":"15679",
    "addr:postcode":"55312",
    "addr:street":"10Th St",
    "iso:country":"US",
    "sg:address":"15679 10th St",
    "sg:city":"Brownton",
    "sg:phone":"+1 320 328 5774",
    "sg:postcode":"55312",
    "sg:province":"MN",
    "sg:tags":[
        "farm",
        "corn"
    ],
    "wof:name":"Charles Schiller",
    "wof:placetype":"venue"
},
  "geometry": {"coordinates":[-94.30927200000001,44.630324],"type":"Point"}
}