{
  "type": "Feature",
  "properties": {
    "iso:country":"US",
    "sg:address":"14249 300th Ave",
    "sg:city":"Waseca",
    "sg:classifiers":[
        {
            "category":"Farming",
            "subcategory":"Farm",
            "type":"Manufacturing & Wholesale Goods"
        }
    ],
    "sg:phone":"+1 507 835 2472",
    "sg:postcode":"56093",
    "sg:province":"MN",
    "wof:name":"Jerry Raetz",
    "wof:placetype":"venue"
},
  "geometry": {"coordinates":[-93.482479,43.993643],"type":"Point"}
}