{
  "type": "Feature",
  "properties": {
    "addr:full":"631 S Main St Holdingford MN 56340",
    "addr:housenumber":"631",
    "addr:postcode":"56340",
    "addr:street":"S Main St",
    "iso:country":"US",
    "sg:address":"631 S Main St",
    "sg:city":"Holdingford",
    "sg:classifiers":[
        {
            "category":"Retail",
            "subcategory":"Funeral Services",
            "type":"Services"
        }
    ],
    "sg:phone":"+1 320 746 9994",
    "sg:postcode":"56340",
    "sg:province":"MN",
    "wof:name":"Brenny Funeral Home",
    "wof:placetype":"venue"
},
  "geometry": {"coordinates":[-94.475757,45.730903],"type":"Point"}
}