{
  "type": "Feature",
  "properties": {
    "iso:country":"US",
    "sg:address":"14020 236th St N",
    "sg:city":"Scandia",
    "sg:classifiers":[
        {
            "category":"Building & Trades",
            "subcategory":"Construction",
            "type":"Services"
        }
    ],
    "sg:phone":"+1 651 433 5110",
    "sg:postcode":"55073",
    "sg:province":"MN",
    "sg:tags":[
        "excavation",
        "contractor"
    ],
    "wof:name":"Jeff Anderson Excavating Inc",
    "wof:placetype":"venue"
},
  "geometry": {"coordinates":[-92.82404699999999,45.291457],"type":"Point"}
}