{
  "type": "Feature",
  "properties": {
    "addr:full":"15885 Market Ave Carver MN 55315",
    "addr:housenumber":"15885",
    "addr:postcode":"55315",
    "addr:street":"Market Ave",
    "iso:country":"US",
    "sg:address":"15885 Market Ave",
    "sg:city":"Carver",
    "sg:phone":"+1 952 466 5977",
    "sg:postcode":"55315",
    "sg:province":"MN",
    "sg:tags":[
        "farm",
        "wheat"
    ],
    "wof:name":"Jonathan Mellgrem",
    "wof:placetype":"venue"
},
  "geometry": {"coordinates":[-93.76812,44.711061],"type":"Point"}
}