{
  "type": "Feature",
  "properties": {
    "addr:full":"604 Broadway St Alexandria MN 56308",
    "addr:housenumber":"604",
    "addr:postcode":"56308",
    "addr:street":"Broadway St",
    "iso:country":"US",
    "sg:address":"604 Broadway St",
    "sg:city":"Alexandria",
    "sg:classifiers":[
        {
            "category":"Shopping",
            "subcategory":"Gifts & Souvenirs",
            "type":"Retail Goods"
        }
    ],
    "sg:phone":"+1 320 763 6363",
    "sg:postcode":"56308",
    "sg:province":"MN",
    "sg:tags":[
        "shop"
    ],
    "sg:website":"www.scandinaviangifts.com",
    "wof:name":"Scandinavian Gift Shop",
    "wof:placetype":"venue"
},
  "geometry": {"coordinates":[-95.377717,45.885902],"type":"Point"}
}