{
  "type": "Feature",
  "properties": {
    "iso:country":"US",
    "sg:address":"4500 Brookside Ave",
    "sg:city":"Minneapolis",
    "sg:classifiers":[
        {
            "category":"Travel",
            "subcategory":"Campground",
            "type":"Entertainment"
        }
    ],
    "sg:phone":"+1 952 922 2218",
    "sg:postcode":"55436",
    "sg:province":"MN",
    "sg:tags":[
        "trailer"
    ],
    "wof:name":"Sissebagamah Rv Resort",
    "wof:placetype":"venue"
},
  "geometry": {"coordinates":[-93.353844,44.916534],"type":"Point"}
}