{
  "type": "Feature",
  "properties": {
    "addr:full":"1114 Valley View Rd Lake City MN 55041",
    "addr:housenumber":"1114",
    "addr:postcode":"55041",
    "addr:street":"Valley View Rd",
    "iso:country":"US",
    "sg:address":"1114 Valley View Rd",
    "sg:city":"Lake City",
    "sg:classifiers":[
        {
            "category":"Professional",
            "subcategory":"Management & Consulting",
            "type":"Services"
        }
    ],
    "sg:phone":"+1 651 345 4976",
    "sg:postcode":"55041",
    "sg:province":"MN",
    "sg:tags":[
        "business"
    ],
    "wof:name":"Heartwood Forestry",
    "wof:placetype":"venue"
},
  "geometry": {"coordinates":[-92.266069,44.433912],"type":"Point"}
}