{
  "type": "Feature",
  "properties": {
    "addr:full":"13720 E Wellington Cres Burnsville MN 55337",
    "addr:housenumber":"13720",
    "addr:postcode":"55337",
    "addr:street":"E Wellington Cres",
    "iso:country":"US",
    "sg:address":"13720 E Wellington Cres",
    "sg:city":"Burnsville",
    "sg:classifiers":[
        {
            "category":"Shopping",
            "subcategory":"Gifts & Souvenirs",
            "type":"Retail Goods"
        }
    ],
    "sg:phone":"+1 952 890 1066",
    "sg:postcode":"55337",
    "sg:province":"MN",
    "wof:name":"Wellington House",
    "wof:placetype":"venue"
},
  "geometry": {"coordinates":[-93.28734900000001,44.753353],"type":"Point"}
}