{
  "type": "Feature",
  "properties": {
    "addr:full":"430 Old Hwy 8 SW Saint Paul MN 55112",
    "addr:housenumber":"430",
    "addr:postcode":"55112",
    "addr:street":"Old Hwy 8 Sw",
    "iso:country":"US",
    "sg:address":"430 Old Hwy 8 SW",
    "sg:city":"Saint Paul",
    "sg:classifiers":[
        {
            "category":"Professional",
            "subcategory":"Business Services",
            "type":"Services"
        }
    ],
    "sg:phone":"+1 651 639 1217",
    "sg:postcode":"55112",
    "sg:province":"MN",
    "wof:name":"Wongs Interior Finishing",
    "wof:placetype":"venue"
},
  "geometry": {"coordinates":[-93.19800499999999,45.041948],"type":"Point"}
}