{
  "type": "Feature",
  "properties": {
    "iso:country":"US",
    "sg:address":"18202 Minnetonka Blvd",
    "sg:city":"Wayzata",
    "sg:classifiers":[
        {
            "category":"Professional",
            "subcategory":"Management & Consulting",
            "type":"Services"
        }
    ],
    "sg:phone":"+1 952 249 0541",
    "sg:postcode":"55391",
    "sg:province":"MN",
    "sg:tags":[
        "telecommunication"
    ],
    "wof:name":"Orion Communication Services",
    "wof:placetype":"venue"
},
  "geometry": {"coordinates":[-93.512587,44.942119],"type":"Point"}
}