{
  "type": "Feature",
  "properties": {
    "iso:country":"US",
    "sg:address":"7451 Brooklyn Blvd",
    "sg:city":"Brooklyn Park",
    "sg:classifiers":[
        {
            "category":"Real Estate",
            "subcategory":"Real Estate Operator",
            "type":"Services"
        }
    ],
    "sg:phone":"+1 763 560 2611",
    "sg:postcode":"55443",
    "sg:province":"MN",
    "sg:tags":[
        "apartment"
    ],
    "wof:name":"Huntington Place Apartment",
    "wof:placetype":"venue"
},
  "geometry": {"coordinates":[-93.349943,45.090383],"type":"Point"}
}