{
  "type": "Feature",
  "properties": {
    "addr:full":"8222 132nd St NW Annandale MN 55302",
    "addr:housenumber":"8222",
    "addr:postcode":"55302",
    "addr:street":"132Nd St Nw",
    "iso:country":"US",
    "sg:address":"8222 132nd St NW",
    "sg:city":"Annandale",
    "sg:classifiers":[
        {
            "category":"Social Services",
            "type":"Services"
        }
    ],
    "sg:phone":"+1 320 274 8881",
    "sg:postcode":"55302",
    "sg:province":"MN",
    "wof:name":"Wee Care We Share",
    "wof:placetype":"venue"
},
  "geometry": {"coordinates":[-94.063884,45.343901],"type":"Point"}
}