{
  "type": "Feature",
  "properties": {
    "iso:country":"US",
    "sg:address":"7222 Washington Ave S",
    "sg:city":"Eden Prairie",
    "sg:classifiers":[
        {
            "category":"Retail",
            "subcategory":"Auto Repair",
            "type":"Services"
        }
    ],
    "sg:phone":"+1 952 944 4011",
    "sg:postcode":"55344",
    "sg:province":"MN",
    "sg:tags":[
        "body",
        "automobile",
        "customizing",
        "trad"
    ],
    "wof:name":"Auto Visions",
    "wof:placetype":"venue"
},
  "geometry": {"coordinates":[-93.398438,44.86911],"type":"Point"}
}