{
  "type": "Feature",
  "properties": {
    "iso:country":"US",
    "sg:address":"26792 153rd St",
    "sg:city":"Pierz",
    "sg:classifiers":[
        {
            "category":"Personal",
            "subcategory":"Beauty Salon",
            "type":"Services"
        }
    ],
    "sg:phone":"+1 320 277 3277",
    "sg:postcode":"56364",
    "sg:province":"MN",
    "wof:name":"Loose Cannon Enterprises",
    "wof:placetype":"venue"
},
  "geometry": {"coordinates":[-94.097655,45.983341],"type":"Point"}
}