{
  "type": "Feature",
  "properties": {
    "addr:full":"3940 W 50th St Edina MN 55424",
    "addr:housenumber":"3940",
    "addr:postcode":"55424",
    "addr:street":"W 50Th St",
    "iso:country":"US",
    "sg:address":"3940 W 50th St",
    "sg:city":"Edina",
    "sg:classifiers":[
        {
            "category":"Restaurant",
            "type":"Food & Drink"
        }
    ],
    "sg:phone":"+1 952 848 1655",
    "sg:postcode":"55424",
    "sg:province":"MN",
    "wof:name":"Cafe Thai",
    "wof:placetype":"venue"
},
  "geometry": {"coordinates":[-93.33127500000001,44.912606],"type":"Point"}
}