{
  "type": "Feature",
  "properties": {
    "addr:full":"11827 Clementa Ave SW Montrose MN 55363",
    "addr:housenumber":"11827",
    "addr:postcode":"55363",
    "addr:street":"Clementa Ave Sw",
    "iso:country":"US",
    "sg:address":"11827 Clementa Ave SW",
    "sg:city":"Montrose",
    "sg:classifiers":[
        {
            "category":"Farming",
            "subcategory":"Dairy Farm",
            "type":"Manufacturing & Wholesale Goods"
        }
    ],
    "sg:phone":"+1 952 955 1181",
    "sg:postcode":"55363",
    "sg:province":"MN",
    "sg:tags":[
        "feedlot",
        "or",
        "beef"
    ],
    "wof:name":"Kenneth Pawelk Farms",
    "wof:placetype":"venue"
},
  "geometry": {"coordinates":[-93.930954,44.981371],"type":"Point"}
}