{
  "type": "Feature",
  "properties": {
    "iso:country":"US",
    "sg:address":"3001 Harbor Ln N",
    "sg:city":"Plymouth",
    "sg:classifiers":[
        {
            "category":"Professional",
            "subcategory":"Management & Consulting",
            "type":"Services"
        }
    ],
    "sg:phone":"+1 763 694 8810",
    "sg:postcode":"55447",
    "sg:province":"MN",
    "sg:tags":[
        "consultant"
    ],
    "wof:name":"Hanover Advisors Inc",
    "wof:placetype":"venue"
},
  "geometry": {"coordinates":[-93.461456,45.014137],"type":"Point"}
}