{
  "type": "Feature",
  "properties": {
    "addr:full":"417 Medayto Dr Spicer MN 56288",
    "addr:housenumber":"417",
    "addr:postcode":"56288",
    "addr:street":"Medayto Dr Spicer",
    "iso:country":"US",
    "sg:address":"417 Medayto Dr",
    "sg:city":"Spicer",
    "sg:classifiers":[
        {
            "category":"Social Services",
            "subcategory":"Child Care",
            "type":"Services"
        }
    ],
    "sg:phone":"+1 320 796 6101",
    "sg:postcode":"56288",
    "sg:province":"MN",
    "sg:tags":[
        "day",
        "provides"
    ],
    "wof:name":"Cathy Tebben",
    "wof:placetype":"venue"
},
  "geometry": {"coordinates":[-94.946287,45.238341],"type":"Point"}
}