{
  "type": "Feature",
  "properties": {
    "addr:full":"3904 Beau D Rue Dr Eagan MN 55122",
    "addr:housenumber":"3904;d",
    "addr:postcode":"55122",
    "addr:street":"Beau;Rue Dr",
    "iso:country":"US",
    "sg:address":"3904 Beau D Rue Dr",
    "sg:city":"Eagan",
    "sg:classifiers":[
        {
            "category":"Food & Beverages",
            "subcategory":"Groceries & Convenience Stores",
            "type":"Retail Goods"
        }
    ],
    "sg:phone":"+1 651 454 0390",
    "sg:postcode":"55122",
    "sg:province":"MN",
    "sg:tags":[
        "grocer"
    ],
    "wof:name":"Oriental Foods",
    "wof:placetype":"venue"
},
  "geometry": {"coordinates":[-93.21457700000001,44.813441],"type":"Point"}
}