{
  "type": "Feature",
  "properties": {
    "iso:country":"US",
    "sg:address":"5037 Gladstone Ave",
    "sg:city":"Minneapolis",
    "sg:classifiers":[
        {
            "category":"Home & Garden",
            "subcategory":"Carpets & Floor Coverings",
            "type":"Retail Goods"
        }
    ],
    "sg:phone":"+1 612 822 1012",
    "sg:postcode":"55419",
    "sg:province":"MN",
    "sg:tags":[
        "mosaic"
    ],
    "wof:name":"Mosaic Gallery Inc",
    "wof:placetype":"venue"
},
  "geometry": {"coordinates":[-93.282669,44.911411],"type":"Point"}
}