{
  "type": "Feature",
  "properties": {
    "iso:country":"US",
    "sg:address":"506 Paul Ave S",
    "sg:city":"Cologne",
    "sg:classifiers":[
        {
            "category":"Transit Center",
            "subcategory":"Freight",
            "type":"Transportation"
        },
        {
            "category":"Freight",
            "type":"Transportation"
        }
    ],
    "sg:phone":"+1 952 466 2635",
    "sg:postcode":"55322",
    "sg:province":"MN",
    "sg:tags":[
        "local",
        "trucking-motor",
        "trucking"
    ],
    "wof:name":"Traver Trucking",
    "wof:placetype":"venue"
},
  "geometry": {"coordinates":[-93.781323,44.766551],"type":"Point"}
}