{
  "type": "Feature",
  "properties": {
    "addr:full":"1824 Country View Blvd Burnsville MN 55337",
    "addr:housenumber":"1824",
    "addr:postcode":"55337",
    "addr:street":"Country View Blvd",
    "iso:country":"US",
    "sg:address":"1824 Country View Blvd",
    "sg:city":"Burnsville",
    "sg:classifiers":[
        {
            "category":"Communications",
            "type":"Services"
        }
    ],
    "sg:phone":"+1 952 894 9553",
    "sg:postcode":"55337",
    "sg:province":"MN",
    "sg:website":"http://www.vortexone.com",
    "wof:name":"Vortex One Corp",
    "wof:placetype":"venue"
},
  "geometry": {"coordinates":[-93.24996299999999,44.772049],"type":"Point"}
}