{
  "type": "Feature",
  "properties": {
    "addr:full":"1145 Shakopee Ave E Shakopee MN 55379",
    "addr:housenumber":"1145",
    "addr:postcode":"55379",
    "addr:street":"Shakopee Ave E",
    "iso:country":"US",
    "sg:address":"1145 Shakopee Ave E",
    "sg:city":"Shakopee",
    "sg:classifiers":[
        {
            "category":"Shopping",
            "subcategory":"Hobbies, Toys, & Games",
            "type":"Retail Goods"
        }
    ],
    "sg:phone":"+1 952 402 0291",
    "sg:postcode":"55379",
    "sg:province":"MN",
    "wof:name":"Phantasy Hobbies",
    "wof:placetype":"venue"
},
  "geometry": {"coordinates":[-93.507797,44.789997],"type":"Point"}
}