{
  "type": "Feature",
  "properties": {
    "iso:country":"US",
    "sg:address":"160 Loretto St",
    "sg:city":"Loretto",
    "sg:classifiers":[
        {
            "category":"Banks & Credit Unions",
            "subcategory":"Bank",
            "type":"Services"
        },
        {
            "category":"Shopping",
            "subcategory":"Antiques",
            "type":"Retail Goods"
        },
        {
            "category":"Shopping",
            "subcategory":"Used Merchandise",
            "type":"Retail Goods"
        }
    ],
    "sg:phone":"+1 763 479 1935",
    "sg:postcode":"55357",
    "sg:province":"MN",
    "sg:tags":[
        "shop",
        "resale",
        "second",
        "hand"
    ],
    "wof:name":"Antique Clockworks",
    "wof:placetype":"venue"
},
  "geometry": {"coordinates":[-93.633551,45.054292],"type":"Point"}
}