{
  "type": "Feature",
  "properties": {
    "iso:country":"US",
    "sg:address":"10405 Bass Lake Rd",
    "sg:city":"Minneapolis",
    "sg:classifiers":[
        {
            "category":"Manufacturing",
            "subcategory":"Signs",
            "type":"Manufacturing & Wholesale Goods"
        }
    ],
    "sg:phone":"+1 763 559 0163",
    "sg:postcode":"55442",
    "sg:province":"MN",
    "sg:tags":[
        "specialty",
        "mfg"
    ],
    "wof:name":"Gove Sign Co",
    "wof:placetype":"venue"
},
  "geometry": {"coordinates":[-93.412274,45.058336],"type":"Point"}
}