{
  "type": "Feature",
  "properties": {
    "iso:country":"US",
    "sg:address":"2267 125th St NW",
    "sg:city":"Rice",
    "sg:classifiers":[
        {
            "category":"Autos & Motor Vehicles",
            "subcategory":"Automobile Sales",
            "type":"Retail Goods"
        }
    ],
    "sg:phone":"+1 320 251 6169",
    "sg:postcode":"56367",
    "sg:province":"MN",
    "sg:tags":[
        "car",
        "dealer"
    ],
    "wof:name":"Kent's KARS",
    "wof:placetype":"venue"
},
  "geometry": {"coordinates":[-94.209558,45.750011],"type":"Point"}
}