{
  "type": "Feature",
  "properties": {
    "iso:country":"US",
    "sg:address":"705 Mill St",
    "sg:city":"Zumbrota",
    "sg:classifiers":[
        {
            "category":"Education",
            "subcategory":"School",
            "type":"Public Place"
        }
    ],
    "sg:phone":"+1 507 732 7395",
    "sg:postcode":"55992",
    "sg:province":"MN",
    "sg:website":"www.zmsch.k12.mn.us",
    "wof:name":"Zumbrota Mazeppa High School",
    "wof:placetype":"venue"
},
  "geometry": {"coordinates":[-92.67394,44.290492],"type":"Point"}
}