{
  "type": "Feature",
  "properties": {
    "iso:country":"US",
    "sg:address":"525 N Lundys Ln",
    "sg:city":"Fergus Falls",
    "sg:classifiers":[
        {
            "category":"Freight",
            "type":"Transportation"
        }
    ],
    "sg:phone":"+1 218 739 4833",
    "sg:postcode":"56537",
    "sg:province":"MN",
    "sg:tags":[
        "commercial",
        "storage"
    ],
    "wof:name":"Washington Ave Self Storage",
    "wof:placetype":"venue"
},
  "geometry": {"coordinates":[-96.060243,46.288514],"type":"Point"}
}