{
  "type": "Feature",
  "properties": {
    "iso:country":"US",
    "sg:address":"5010 Miller Trunk Hwy",
    "sg:city":"Duluth",
    "sg:classifiers":[
        {
            "category":"Building & Trades",
            "subcategory":"Construction",
            "type":"Services"
        }
    ],
    "sg:phone":"+1 218 729 7570",
    "sg:postcode":"55811",
    "sg:province":"MN",
    "sg:tags":[
        "home",
        "builder",
        "commercial",
        "family",
        "contractor"
    ],
    "wof:name":"Billmans Construction Inc",
    "wof:placetype":"venue"
},
  "geometry": {"coordinates":[-92.205209,46.833562],"type":"Point"}
}