{
  "type": "Feature",
  "properties": {
    "iso:country":"US",
    "sg:address":"30872 Nature Rd",
    "sg:city":"Royalton",
    "sg:classifiers":[
        {
            "category":"Professional",
            "subcategory":"Business Services",
            "type":"Services"
        }
    ],
    "sg:phone":"+1 320 355 2580",
    "sg:postcode":"56373",
    "sg:province":"MN",
    "wof:name":"Royal Home Inspections",
    "wof:placetype":"venue"
},
  "geometry": {"coordinates":[-94.01637599999999,45.829421],"type":"Point"}
}