{
  "type": "Feature",
  "properties": {
    "iso:country":"US",
    "sg:address":"3844 Quail Ave N",
    "sg:city":"Minneapolis",
    "sg:classifiers":[
        {
            "category":"Wholesale",
            "subcategory":"Vending Machines",
            "type":"Manufacturing & Wholesale Goods"
        }
    ],
    "sg:phone":"+1 763 300 5915",
    "sg:postcode":"55422",
    "sg:province":"MN",
    "sg:tags":[
        "operator"
    ],
    "wof:name":"Sundquist Vending",
    "wof:placetype":"venue"
},
  "geometry": {"coordinates":[-93.34278,45.025114],"type":"Point"}
}