{
  "type": "Feature",
  "properties": {
    "addr:full":"8690 Flamingo Dr Chanhassen MN 55317",
    "addr:housenumber":"8690",
    "addr:postcode":"55317",
    "addr:street":"Flamingo Dr",
    "iso:country":"US",
    "sg:address":"8690 Flamingo Dr",
    "sg:city":"Chanhassen",
    "sg:classifiers":[
        {
            "category":"Professional",
            "subcategory":"Accounting & Tax Preparation",
            "type":"Services"
        }
    ],
    "sg:phone":"+1 952 361 3131",
    "sg:postcode":"55317",
    "sg:province":"MN",
    "wof:name":"Nancy S Lipinski CPA",
    "wof:placetype":"venue"
},
  "geometry": {"coordinates":[-93.55502,44.846007],"type":"Point"}
}