{
  "type": "Feature",
  "properties": {
    "addr:full":"49252 340th St Ottertail MN 56571",
    "addr:housenumber":"49252",
    "addr:postcode":"56571",
    "addr:street":"340Th St",
    "iso:country":"US",
    "sg:address":"49252 340th St",
    "sg:city":"Ottertail",
    "sg:phone":"+1 218 385 3098",
    "sg:postcode":"56571",
    "sg:province":"MN",
    "sg:tags":[
        "farm",
        "corn"
    ],
    "wof:name":"Peter Bakka",
    "wof:placetype":"venue"
},
  "geometry": {"coordinates":[-95.460323,46.455657],"type":"Point"}
}