{
  "type": "Feature",
  "properties": {
    "addr:full":"859 Village Center Dr Saint Paul MN 55127",
    "addr:housenumber":"859",
    "addr:postcode":"55127",
    "addr:street":"Village Center Dr",
    "iso:country":"US",
    "sg:address":"859 Village Center Dr",
    "sg:city":"Saint Paul",
    "sg:classifiers":[
        {
            "category":"Food & Beverages",
            "subcategory":"Liquor & Beverages",
            "type":"Retail Goods"
        }
    ],
    "sg:phone":"+1 651 483 1767",
    "sg:postcode":"55127",
    "sg:province":"MN",
    "sg:tags":[
        "alcoholic"
    ],
    "wof:name":"Winestreet Spirits Inc",
    "wof:placetype":"venue"
},
  "geometry": {"coordinates":[-93.117227,45.08137],"type":"Point"}
}