{
  "type": "Feature",
  "properties": {
    "iso:country":"US",
    "sg:address":"118 Main Ave S",
    "sg:city":"New York Mills",
    "sg:classifiers":[
        {
            "category":"Government",
            "subcategory":"Office",
            "type":"Public Place"
        }
    ],
    "sg:phone":"+1 218 385 3000",
    "sg:postcode":"56567",
    "sg:province":"MN",
    "wof:name":"Otter Tail County Extension",
    "wof:placetype":"venue"
},
  "geometry": {"coordinates":[-95.37717000000001,46.517109],"type":"Point"}
}