{
  "type": "Feature",
  "properties": {
    "iso:country":"US",
    "sg:address":"111 E Kellogg Blvd",
    "sg:city":"St Paul",
    "sg:classifiers":[
        {
            "category":"Health Services",
            "subcategory":"Podiatrist",
            "type":"Services"
        }
    ],
    "sg:phone":"+1 651 224 0351",
    "sg:postcode":"55105",
    "sg:province":"MN",
    "wof:name":"Downtown Foot Clinic",
    "wof:placetype":"venue"
},
  "geometry": {"coordinates":[-93.089921,44.94532],"type":"Point"}
}