{
  "type": "Feature",
  "properties": {
    "iso:country":"US",
    "sg:address":"1106 Broadway St",
    "sg:city":"Alexandria",
    "sg:classifiers":[
        {
            "category":"Professional",
            "type":"Services"
        }
    ],
    "sg:phone":"+1 320 763 5407",
    "sg:postcode":"56308",
    "sg:province":"MN",
    "wof:name":"Dfl Headquarters",
    "wof:placetype":"venue"
},
  "geometry": {"coordinates":[-95.37779,45.880028],"type":"Point"}
}