{
  "type": "Feature",
  "properties": {
    "addr:full":"210 Elizabeth St Edgerton MN 56128",
    "addr:housenumber":"210",
    "addr:postcode":"56128",
    "addr:street":"Elizabeth St",
    "iso:country":"US",
    "sg:address":"210 Elizabeth St",
    "sg:city":"Edgerton",
    "sg:classifiers":[
        {
            "category":"Education",
            "subcategory":"School",
            "type":"Public Place"
        }
    ],
    "sg:phone":"+1 507 442 6181",
    "sg:postcode":"56128",
    "sg:province":"MN",
    "wof:name":"Edgerton Christian Elementary",
    "wof:placetype":"venue"
},
  "geometry": {"coordinates":[-96.12775499999999,43.875873],"type":"Point"}
}