{
  "type": "Feature",
  "properties": {
    "addr:full":"121 Broadway E Little Falls MN 56345",
    "addr:housenumber":"121",
    "addr:postcode":"56345",
    "addr:street":"Broadway E",
    "iso:country":"US",
    "sg:address":"121 Broadway E",
    "sg:city":"Little Falls",
    "sg:classifiers":[
        {
            "category":"Food & Beverages",
            "subcategory":"Bakery",
            "type":"Retail Goods"
        }
    ],
    "sg:phone":"+1 320 632 6388",
    "sg:postcode":"56345",
    "sg:province":"MN",
    "wof:name":"Pete & Joys Bakery Inc",
    "wof:placetype":"venue"
},
  "geometry": {"coordinates":[-94.36219699999999,45.976477],"type":"Point"}
}