{
  "type": "Feature",
  "properties": {
    "addr:full":"9512 270th St E Medford MN 55049",
    "addr:housenumber":"9512",
    "addr:postcode":"55049",
    "addr:street":"270Th St E",
    "iso:country":"US",
    "sg:address":"9512 270th St E",
    "sg:city":"Medford",
    "sg:phone":"+1 507 451 8816",
    "sg:postcode":"55049",
    "sg:province":"MN",
    "sg:tags":[
        "farm",
        "corn",
        "soybean"
    ],
    "wof:name":"Dressel Brothers",
    "wof:placetype":"venue"
},
  "geometry": {"coordinates":[-93.119511,44.196726],"type":"Point"}
}