{
  "type": "Feature",
  "properties": {
    "addr:full":"25882 State Hwy 47 Isanti MN 55040",
    "addr:housenumber":"25882",
    "addr:postcode":"55040",
    "addr:street":"State Hwy 47",
    "iso:country":"US",
    "sg:address":"25882 State Hwy 47",
    "sg:city":"Isanti",
    "sg:classifiers":[
        {
            "category":"Building & Trades",
            "subcategory":"Construction",
            "type":"Services"
        }
    ],
    "sg:phone":"+1 763 444 4223",
    "sg:postcode":"55040",
    "sg:province":"MN",
    "sg:tags":[
        "carpentry",
        "contractor"
    ],
    "wof:name":"Kerners Specialty Cabinets",
    "wof:placetype":"venue"
},
  "geometry": {"coordinates":[-93.367771,45.435518],"type":"Point"}
}