{
  "type": "Feature",
  "properties": {
    "iso:country":"US",
    "sg:address":"223 E Front St",
    "sg:city":"Callaway",
    "sg:classifiers":[
        {
            "category":"Professional",
            "type":"Services"
        }
    ],
    "sg:phone":"+1 218 375 3323",
    "sg:postcode":"56552",
    "sg:province":"MN",
    "wof:name":"Service King",
    "wof:placetype":"venue"
},
  "geometry": {"coordinates":[-96.256626,46.977238],"type":"Point"}
}