{
  "type": "Feature",
  "properties": {
    "iso:country":"US",
    "sg:address":"915 4th Ave",
    "sg:city":"Worthington",
    "sg:classifiers":[
        {
            "category":"Professional",
            "subcategory":"Lawyer & Legal Services",
            "type":"Services"
        }
    ],
    "sg:phone":"+1 507 372 7542",
    "sg:postcode":"56187",
    "sg:province":"MN",
    "sg:tags":[
        "farm",
        "corn"
    ],
    "wof:name":"Frank Riley",
    "wof:placetype":"venue"
},
  "geometry": {"coordinates":[-95.59756400000001,43.62025],"type":"Point"}
}