{
  "type": "Feature",
  "properties": {
    "addr:full":"1419 Paddock Cir Stillwater MN 55082",
    "addr:housenumber":"1419",
    "addr:postcode":"55082",
    "addr:street":"Paddock Cir",
    "iso:country":"US",
    "sg:address":"1419 Paddock Cir",
    "sg:city":"Stillwater",
    "sg:classifiers":[
        {
            "category":"Manufacturing",
            "subcategory":"Tools & Machinery",
            "type":"Manufacturing & Wholesale Goods"
        }
    ],
    "sg:phone":"+1 651 439 5923",
    "sg:postcode":"55082",
    "sg:province":"MN",
    "sg:tags":[
        "water",
        "mfg",
        "system",
        "purification"
    ],
    "wof:name":"Innovative Turnkey Systems",
    "wof:placetype":"venue"
},
  "geometry": {"coordinates":[-92.82614599999999,45.044463],"type":"Point"}
}