{
  "type": "Feature",
  "properties": {
    "addr:full":"32772 30th St Elmore MN 56027",
    "addr:housenumber":"32772",
    "addr:postcode":"56027",
    "addr:street":"30Th St",
    "iso:country":"US",
    "sg:address":"32772 30th St",
    "sg:city":"Elmore",
    "sg:phone":"+1 507 943 3628",
    "sg:postcode":"56027",
    "sg:province":"MN",
    "sg:tags":[
        "farm",
        "corn",
        "soybean"
    ],
    "wof:name":"James Smith",
    "wof:placetype":"venue"
},
  "geometry": {"coordinates":[-94.219679,43.529098],"type":"Point"}
}