{
  "type": "Feature",
  "properties": {
    "addr:full":"13785 Bass Lake Rd Osseo MN 55311",
    "addr:housenumber":"13785",
    "addr:postcode":"55311",
    "addr:street":"Bass Lake Rd",
    "iso:country":"US",
    "sg:address":"13785 Bass Lake Rd",
    "sg:city":"Osseo",
    "sg:classifiers":[
        {
            "category":"Local Transit",
            "type":"Transportation"
        }
    ],
    "sg:phone":"+1 763 519 1441",
    "sg:postcode":"55311",
    "sg:province":"MN",
    "sg:tags":[
        "passenger"
    ],
    "wof:name":"Blue Knight Limousine Service",
    "wof:placetype":"venue"
},
  "geometry": {"coordinates":[-93.45523300000001,45.072315],"type":"Point"}
}