{
  "type": "Feature",
  "properties": {
    "iso:country":"US",
    "sg:address":"16781 58th St",
    "sg:city":"Royalton",
    "sg:classifiers":[
        {
            "category":"Professional",
            "type":"Services"
        }
    ],
    "sg:phone":"+1 320 584 5786",
    "sg:postcode":"56373",
    "sg:province":"MN",
    "wof:name":"Rodney Crowe",
    "wof:placetype":"venue"
},
  "geometry": {"coordinates":[-94.321001,45.844293],"type":"Point"}
}