{
  "type": "Feature",
  "properties": {
    "addr:full":"5032 Edgewater Dr Mound MN 55364",
    "addr:housenumber":"5032",
    "addr:postcode":"55364",
    "addr:street":"Edgewater Dr Mound",
    "iso:country":"US",
    "sg:address":"5032 Edgewater Dr",
    "sg:city":"Mound",
    "sg:classifiers":[
        {
            "category":"Building & Trades",
            "subcategory":"Construction",
            "type":"Services"
        }
    ],
    "sg:phone":"+1 952 936 0556",
    "sg:postcode":"55364",
    "sg:province":"MN",
    "sg:tags":[
        "contractor"
    ],
    "wof:name":"Anderson Systems",
    "wof:placetype":"venue"
},
  "geometry": {"coordinates":[-93.650954,44.938608],"type":"Point"}
}