{
  "type": "Feature",
  "properties": {
    "iso:country":"US",
    "sg:address":"126 N High Dr NE",
    "sg:city":"Hutchinson",
    "sg:classifiers":[
        {
            "category":"Professional",
            "subcategory":"Employment Agencies",
            "type":"Services"
        }
    ],
    "sg:phone":"+1 320 587 9728",
    "sg:postcode":"55350",
    "sg:province":"MN",
    "wof:name":"Kirsten Kinzer",
    "wof:placetype":"venue"
},
  "geometry": {"coordinates":[-94.36490999999999,44.906788],"type":"Point"}
}