{
  "type": "Feature",
  "properties": {
    "addr:full":"670 Humbolt Dr NW Big Lake MN 55309",
    "addr:housenumber":"670",
    "addr:postcode":"55309",
    "addr:street":"Humbolt Dr Nw",
    "iso:country":"US",
    "sg:address":"670 Humbolt Dr NW",
    "sg:city":"Big Lake",
    "sg:classifiers":[
        {
            "category":"Personal",
            "type":"Services"
        }
    ],
    "sg:phone":"+1 763 241 1434",
    "sg:postcode":"55309",
    "sg:province":"MN",
    "wof:name":"Caring Touch",
    "wof:placetype":"venue"
},
  "geometry": {"coordinates":[-93.734925,45.332041],"type":"Point"}
}