{
  "type": "Feature",
  "properties": {
    "addr:full":"801 S Minnesota St New Ulm MN 56073",
    "addr:housenumber":"801",
    "addr:postcode":"56073",
    "addr:street":"S Minnesota St",
    "iso:country":"US",
    "sg:address":"801 S Minnesota St",
    "sg:city":"New Ulm",
    "sg:classifiers":[
        {
            "category":"Manufacturing",
            "subcategory":"Pottery",
            "type":"Manufacturing & Wholesale Goods"
        }
    ],
    "sg:phone":"+1 507 354 2414",
    "sg:postcode":"56073",
    "sg:province":"MN",
    "sg:tags":[
        "product",
        "mfg"
    ],
    "wof:name":"Sandhurst Creations",
    "wof:placetype":"venue"
},
  "geometry": {"coordinates":[-94.451475,44.305431],"type":"Point"}
}