{
  "type": "Feature",
  "properties": {
    "iso:country":"US",
    "sg:address":"402 8th St NW",
    "sg:city":"Austin",
    "sg:classifiers":[
        {
            "category":"Social Services",
            "subcategory":"Child Care",
            "type":"Services"
        }
    ],
    "sg:phone":"+1 507 437 1293",
    "sg:postcode":"55912",
    "sg:province":"MN",
    "sg:tags":[
        "day",
        "provider"
    ],
    "wof:name":"Judith Childcare",
    "wof:placetype":"venue"
},
  "geometry": {"coordinates":[-92.98471600000001,43.67029],"type":"Point"}
}