{
  "type": "Feature",
  "properties": {
    "iso:country":"US",
    "sg:address":"108 N 1st Ave W",
    "sg:city":"Duluth",
    "sg:classifiers":[
        {
            "category":"Manufacturing",
            "subcategory":"Printing",
            "type":"Manufacturing & Wholesale Goods"
        }
    ],
    "sg:phone":"+1 218 722 1048",
    "sg:postcode":"55802",
    "sg:province":"MN",
    "sg:tags":[
        "work"
    ],
    "wof:name":"Duluth Ruling & Binding Co",
    "wof:placetype":"venue"
},
  "geometry": {"coordinates":[-92.101529,46.787325],"type":"Point"}
}