{
  "type": "Feature",
  "properties": {
    "iso:country":"US",
    "sg:address":"45678 162nd St",
    "sg:city":"Glencoe",
    "sg:phone":"+1 320 864 3488",
    "sg:postcode":"55336",
    "sg:province":"MN",
    "sg:tags":[
        "farm",
        "corn",
        "soybean"
    ],
    "wof:name":"Kenneth Ortloff",
    "wof:placetype":"venue"
},
  "geometry": {"coordinates":[-94.185327,44.71366],"type":"Point"}
}