{
  "type": "Feature",
  "properties": {
    "addr:full":"28403 40th St Janesville MN 56048",
    "addr:housenumber":"28403",
    "addr:postcode":"56048",
    "addr:street":"40Th St",
    "iso:country":"US",
    "sg:address":"28403 40th St",
    "sg:city":"Janesville",
    "sg:classifiers":[
        {
            "category":"Farming",
            "subcategory":"Farm",
            "type":"Manufacturing & Wholesale Goods"
        }
    ],
    "sg:phone":"+1 507 239 2209",
    "sg:postcode":"56048",
    "sg:province":"MN",
    "sg:tags":[
        "crop",
        "general"
    ],
    "wof:name":"Gerald Holmes",
    "wof:placetype":"venue"
},
  "geometry": {"coordinates":[-93.68745699999999,43.965573],"type":"Point"}
}