{
  "type": "Feature",
  "properties": {
    "addr:full":"23511 Aspen Dr Rogers MN 55374",
    "addr:housenumber":"23511",
    "addr:postcode":"55374",
    "addr:street":"Aspen Dr",
    "iso:country":"US",
    "sg:address":"23511 Aspen Dr",
    "sg:city":"Rogers",
    "sg:classifiers":[
        {
            "category":"Building & Trades",
            "subcategory":"Construction",
            "type":"Services"
        }
    ],
    "sg:phone":"+1 763 428 7875",
    "sg:postcode":"55374",
    "sg:province":"MN",
    "sg:tags":[
        "wallcoverings-installation",
        "wallpaper",
        "painting",
        "contractor"
    ],
    "wof:name":"Craig Walter Painting",
    "wof:placetype":"venue"
},
  "geometry": {"coordinates":[-93.57811700000001,45.201775],"type":"Point"}
}