{
  "type": "Feature",
  "properties": {
    "addr:full":"705 Schifsky Rd Saint Paul MN 55126",
    "addr:housenumber":"705",
    "addr:postcode":"55126",
    "addr:street":"Schifsky Rd",
    "iso:country":"US",
    "sg:address":"705 Schifsky Rd",
    "sg:city":"Saint Paul",
    "sg:classifiers":[
        {
            "category":"Social Services",
            "type":"Services"
        }
    ],
    "sg:phone":"+1 651 765 0733",
    "sg:postcode":"55126",
    "sg:province":"MN",
    "wof:name":"Eecf",
    "wof:placetype":"venue"
},
  "geometry": {"coordinates":[-93.129575,45.091],"type":"Point"}
}