{
  "type": "Feature",
  "properties": {
    "addr:full":"102 E Central Entrance Duluth MN 55811",
    "addr:housenumber":"102",
    "addr:postcode":"55811",
    "addr:street":"E Central Entrance",
    "iso:country":"US",
    "sg:address":"102 E Central Entrance",
    "sg:city":"Duluth",
    "sg:classifiers":[
        {
            "category":"Banks & Credit Unions",
            "subcategory":"Bank",
            "type":"Services"
        }
    ],
    "sg:phone":"+1 218 722 2773",
    "sg:postcode":"55811",
    "sg:province":"MN",
    "sg:tags":[
        "loan",
        "correspondent",
        "banker",
        "mortgage"
    ],
    "sg:website":"www.independentmc.com",
    "wof:name":"Fairway Independent Mortgage",
    "wof:placetype":"venue"
},
  "geometry": {"coordinates":[-92.13042,46.800298],"type":"Point"}
}