{
  "type": "Feature",
  "properties": {
    "addr:full":"1221 E Main St Marshall MN 56258",
    "addr:housenumber":"1221",
    "addr:postcode":"56258",
    "addr:street":"E Main St",
    "iso:country":"US",
    "sg:address":"1221 E Main St",
    "sg:city":"Marshall",
    "sg:classifiers":[
        {
            "category":"Shopping",
            "subcategory":"Department Store",
            "type":"Retail Goods"
        },
        {
            "category":"Shopping",
            "subcategory":"Clothing, Apparel, & Fashions",
            "type":"Retail Goods"
        },
        {
            "category":"Shopping",
            "subcategory":"Discount & Variety Stores",
            "type":"Retail Goods"
        },
        {
            "category":"Food & Beverages",
            "subcategory":"Supermarket",
            "type":"Retail Goods"
        },
        {
            "category":"Shopping",
            "type":"Retail Goods"
        }
    ],
    "sg:phone":"+1 507 532 9383",
    "sg:postcode":"56258",
    "sg:province":"MN",
    "sg:tags":[
        "clothing",
        "super",
        "merchandise"
    ],
    "sg:website":"http://www.walmart.com",
    "wof:name":"Wal-Mart Supercenter",
    "wof:placetype":"venue"
},
  "geometry": {"coordinates":[-95.77116599999999,44.433893],"type":"Point"}
}