{
  "type": "Feature",
  "properties": {
    "addr:full":"70305 US Hwy 71 Morton MN 56270",
    "addr:postcode":"70305;56270",
    "addr:street":"Us Hwy 71",
    "iso:country":"US",
    "sg:address":"70305 US Hwy 71",
    "sg:city":"Morton",
    "sg:classifiers":[
        {
            "category":"Farming",
            "subcategory":"Farm",
            "type":"Manufacturing & Wholesale Goods"
        }
    ],
    "sg:phone":"+1 507 697 6102",
    "sg:postcode":"56270",
    "sg:province":"MN",
    "wof:name":"Winter Creek Farms",
    "wof:placetype":"venue"
},
  "geometry": {"coordinates":[-94.994455,44.60269],"type":"Point"}
}