{
  "type": "Feature",
  "properties": {
    "iso:country":"US",
    "sg:address":"2000 Plymouth Rd",
    "sg:city":"Hopkins",
    "sg:classifiers":[
        {
            "category":"Shopping",
            "type":"Retail Goods"
        }
    ],
    "sg:phone":"+1 952 470 9063",
    "sg:postcode":"55305",
    "sg:province":"MN",
    "sg:tags":[
        "surgical",
        "appliance",
        "merchandise",
        "mfg"
    ],
    "wof:name":"Teratech Products",
    "wof:placetype":"venue"
},
  "geometry": {"coordinates":[-93.442291,44.961963],"type":"Point"}
}