{
  "type": "Feature",
  "properties": {
    "addr:full":"12401 Minnetonka Blvd Hopkins MN 55305",
    "addr:housenumber":"12401",
    "addr:postcode":"55305",
    "addr:street":"Minnetonka Blvd",
    "iso:country":"US",
    "sg:address":"12401 Minnetonka Blvd",
    "sg:city":"Hopkins",
    "sg:classifiers":[
        {
            "category":"Real Estate",
            "subcategory":"Developer",
            "type":"Services"
        }
    ],
    "sg:phone":"+1 952 593 7620",
    "sg:postcode":"55305",
    "sg:province":"MN",
    "wof:name":"Arrowwood Development",
    "wof:placetype":"venue"
},
  "geometry": {"coordinates":[-93.437302,44.942829],"type":"Point"}
}