{
  "type": "Feature",
  "properties": {
    "iso:country":"US",
    "sg:address":"669 2nd Ave",
    "sg:city":"Brewster",
    "sg:classifiers":[
        {
            "category":"Professional",
            "subcategory":"Management & Consulting",
            "type":"Services"
        }
    ],
    "sg:phone":"+1 507 842 5680",
    "sg:postcode":"56119",
    "sg:province":"MN",
    "wof:name":"Applied Science Mktg",
    "wof:placetype":"venue"
},
  "geometry": {"coordinates":[-95.464235,43.701257],"type":"Point"}
}