{
  "type": "Feature",
  "properties": {
    "iso:country":"US",
    "sg:address":"4920 Penn Ave S",
    "sg:city":"Minneapolis",
    "sg:classifiers":[
        {
            "category":"Professional",
            "subcategory":"Business Services",
            "type":"Services"
        }
    ],
    "sg:phone":"+1 612 925 5058",
    "sg:postcode":"55419",
    "sg:province":"MN",
    "wof:name":"Council Oak Assoc",
    "wof:placetype":"venue"
},
  "geometry": {"coordinates":[-93.30877099999999,44.912733],"type":"Point"}
}