{
  "type": "Feature",
  "properties": {
    "addr:full":"15512 Co Hwy 17 Holdingford MN 56340",
    "addr:housenumber":"15512",
    "addr:postcode":"56340",
    "addr:street":"Co Hwy 17 Holdingford",
    "iso:country":"US",
    "sg:address":"15512 Co Hwy 17",
    "sg:city":"Holdingford",
    "sg:classifiers":[
        {
            "category":"Building & Trades",
            "subcategory":"Plumbing",
            "type":"Services"
        }
    ],
    "sg:phone":"+1 320 746 2309",
    "sg:postcode":"56340",
    "sg:province":"MN",
    "sg:tags":[
        "contractor"
    ],
    "wof:name":"Durene Heating",
    "wof:placetype":"venue"
},
  "geometry": {"coordinates":[-94.432484,45.745864],"type":"Point"}
}