{
  "type": "Feature",
  "properties": {
    "addr:full":"23138 270th St NE Brooks MN 56725",
    "addr:housenumber":"23138",
    "addr:postcode":"56725",
    "addr:street":"270Th St Ne",
    "iso:country":"US",
    "sg:address":"23138 270th St NE",
    "sg:city":"Brooks",
    "sg:classifiers":[
        {
            "category":"Farming",
            "subcategory":"Farm",
            "type":"Manufacturing & Wholesale Goods"
        }
    ],
    "sg:phone":"+1 218 698 4457",
    "sg:postcode":"56725",
    "sg:province":"MN",
    "sg:tags":[
        "crop",
        "general"
    ],
    "wof:name":"Berberich Farms",
    "wof:placetype":"venue"
},
  "geometry": {"coordinates":[-95.978719,48.265525],"type":"Point"}
}