{
  "type": "Feature",
  "properties": {
    "iso:country":"US",
    "sg:address":"10001 Xerxes Ave S",
    "sg:city":"Minneapolis",
    "sg:classifiers":[
        {
            "category":"Government",
            "subcategory":"Fire Station",
            "type":"Public Place"
        }
    ],
    "sg:phone":"+1 952 881 5060",
    "sg:postcode":"55431",
    "sg:province":"MN",
    "sg:tags":[
        "department"
    ],
    "wof:name":"Fire Station Six",
    "wof:placetype":"venue"
},
  "geometry": {"coordinates":[-93.319092,44.823151],"type":"Point"}
}