{
  "type": "Feature",
  "properties": {
    "iso:country":"US",
    "sg:address":"29218 State Hwy 58",
    "sg:city":"Red Wing",
    "sg:classifiers":[
        {
            "category":"Health Services",
            "subcategory":"Chiropractor",
            "type":"Services"
        }
    ],
    "sg:phone":"+1 651 388 8294",
    "sg:postcode":"55066",
    "sg:province":"MN",
    "sg:tags":[
        "medical"
    ],
    "wof:name":"Red Wing Chiropractic Clinic",
    "wof:placetype":"venue"
},
  "geometry": {"coordinates":[-92.523113,44.523483],"type":"Point"}
}