{
  "type": "Feature",
  "properties": {
    "iso:country":"US",
    "sg:address":"7340 Co Rd 19 SE",
    "sg:city":"Rochester",
    "sg:classifiers":[
        {
            "category":"Retail",
            "subcategory":"Repair Shop",
            "type":"Services"
        }
    ],
    "sg:phone":"+1 507 282 8839",
    "sg:postcode":"55904",
    "sg:province":"MN",
    "wof:name":"A Way Sewer Drain",
    "wof:placetype":"venue"
},
  "geometry": {"coordinates":[-92.330778,43.915423],"type":"Point"}
}