{
  "type": "Feature",
  "properties": {
    "addr:full":"60 N Kent St St Paul MN 55102",
    "addr:housenumber":"60",
    "addr:postcode":"55102",
    "addr:street":"N Kent St",
    "iso:country":"US",
    "sg:address":"60 N Kent St",
    "sg:city":"St Paul",
    "sg:classifiers":[
        {
            "category":"Social Services",
            "type":"Services"
        }
    ],
    "sg:phone":"+1 651 221 9011",
    "sg:postcode":"55102",
    "sg:province":"MN",
    "sg:tags":[
        "organization",
        "welfare"
    ],
    "wof:name":"Family Resource Ctr",
    "wof:placetype":"venue"
},
  "geometry": {"coordinates":[-93.123555,44.942677],"type":"Point"}
}