{
  "type": "Feature",
  "properties": {
    "iso:country":"US",
    "sg:address":"20213 680th St",
    "sg:city":"Dodge Center",
    "sg:classifiers":[
        {
            "category":"Farming",
            "subcategory":"Farm",
            "type":"Manufacturing & Wholesale Goods"
        }
    ],
    "sg:phone":"+1 507 374 6620",
    "sg:postcode":"55927",
    "sg:province":"MN",
    "sg:tags":[
        "crop",
        "general"
    ],
    "wof:name":"Mc Colley Farms",
    "wof:placetype":"venue"
},
  "geometry": {"coordinates":[-92.836065,43.964674],"type":"Point"}
}