{
  "type": "Feature",
  "properties": {
    "iso:country":"US",
    "sg:address":"112 Industry Rd",
    "sg:city":"Finley",
    "sg:classifiers":[
        {
            "category":"Retail",
            "subcategory":"Auto Repair",
            "type":"Services"
        }
    ],
    "sg:phone":"+1 701 524 2520",
    "sg:postcode":"58276",
    "sg:province":"MN",
    "sg:tags":[
        "truck"
    ],
    "wof:name":"Peterson Enterprises",
    "wof:placetype":"venue"
},
  "geometry": {"coordinates":[-97.446341,48.622227],"type":"Point"}
}