{
  "type": "Feature",
  "properties": {
    "addr:full":"5200 Dundee Rd Minneapolis MN 55436",
    "addr:housenumber":"5200",
    "addr:postcode":"55436",
    "addr:street":"Dundee Rd",
    "iso:country":"US",
    "sg:address":"5200 Dundee Rd",
    "sg:city":"Minneapolis",
    "sg:classifiers":[
        {
            "category":"Professional",
            "type":"Services"
        }
    ],
    "sg:phone":"+1 952 929 7311",
    "sg:postcode":"55436",
    "sg:province":"MN",
    "wof:name":"Charles G Schiess",
    "wof:placetype":"venue"
},
  "geometry": {"coordinates":[-93.375023,44.90947],"type":"Point"}
}