{
  "type": "Feature",
  "properties": {
    "addr:full":"3404 Lyndale Ave S Minneapolis MN 55408",
    "addr:housenumber":"3404",
    "addr:postcode":"55408",
    "addr:street":"Lyndale Ave S",
    "iso:country":"US",
    "sg:address":"3404 Lyndale Ave S",
    "sg:city":"Minneapolis",
    "sg:classifiers":[
        {
            "category":"Shopping",
            "subcategory":"Jewelry",
            "type":"Retail Goods"
        },
        {
            "category":"Home & Garden",
            "subcategory":"Home Furnishings",
            "type":"Retail Goods"
        },
        {
            "category":"Wholesale",
            "subcategory":"Stationery",
            "type":"Manufacturing & Wholesale Goods"
        }
    ],
    "sg:phone":"+1 612 825 2909",
    "sg:postcode":"55408",
    "sg:province":"MN",
    "sg:tags":[
        "decor",
        "card"
    ],
    "sg:website":"www.shopbelleweather.com",
    "wof:name":"Belle Weather",
    "wof:placetype":"venue"
},
  "geometry": {"coordinates":[-93.288203,44.94121],"type":"Point"}
}