{
  "type": "Feature",
  "properties": {
    "iso:country":"US",
    "sg:address":"1707 Selmser Ave",
    "sg:city":"Cloquet",
    "sg:classifiers":[
        {
            "category":"Wholesale",
            "subcategory":"Medical Equipment & Supplies",
            "type":"Manufacturing & Wholesale Goods"
        }
    ],
    "sg:phone":"+1 218 879 6996",
    "sg:postcode":"55720",
    "sg:province":"MN",
    "wof:name":"R D G & Assoc",
    "wof:placetype":"venue"
},
  "geometry": {"coordinates":[-92.445628,46.716024],"type":"Point"}
}