{
  "type": "Feature",
  "properties": {
    "addr:full":"5716 Travers Ln Granite Falls MN 56241",
    "addr:housenumber":"5716",
    "addr:postcode":"56241",
    "addr:street":"Travers Ln",
    "iso:country":"US",
    "sg:address":"5716 Travers Ln",
    "sg:city":"Granite Falls",
    "sg:classifiers":[
        {
            "category":"Social Services",
            "type":"Services"
        }
    ],
    "sg:phone":"+1 320 564 1264",
    "sg:postcode":"56241",
    "sg:province":"MN",
    "sg:tags":[
        "organization",
        "welfare"
    ],
    "wof:name":"Upper Sioux Community Rec",
    "wof:placetype":"venue"
},
  "geometry": {"coordinates":[-95.495662,44.745912],"type":"Point"}
}