{
  "type": "Feature",
  "properties": {
    "iso:country":"US",
    "sg:address":"700 Washington Avenue North Suite 210",
    "sg:city":"Minneapolis",
    "sg:classifiers":[
        {
            "category":"Arts & Performance",
            "subcategory":"Arts Center",
            "type":"Entertainment"
        },
        {
            "category":"Professional",
            "subcategory":"Employment Agencies",
            "type":"Services"
        }
    ],
    "sg:phone":"+1 612 664 1174",
    "sg:postcode":"55401",
    "sg:province":"MN",
    "sg:tags":[
        "modeling",
        "performing"
    ],
    "sg:website":"www.agencymodelsandtalent.com",
    "wof:name":"Agency Model & Talent",
    "wof:placetype":"venue"
},
  "geometry": {"coordinates":[-93.27664799999999,44.987985],"type":"Point"}
}