{
  "type": "Feature",
  "properties": {
    "addr:full":"502 W 6th St Monticello MN 55362",
    "addr:housenumber":"502",
    "addr:postcode":"55362",
    "addr:street":"W 6Th St",
    "iso:country":"US",
    "sg:address":"502 W 6th St",
    "sg:city":"Monticello",
    "sg:classifiers":[
        {
            "category":"Health Services",
            "subcategory":"Chiropractor",
            "type":"Services"
        }
    ],
    "sg:phone":"+1 763 295 2476",
    "sg:postcode":"55362",
    "sg:province":"MN",
    "wof:name":"D & C Contractors",
    "wof:placetype":"venue"
},
  "geometry": {"coordinates":[-93.804243,45.304005],"type":"Point"}
}