{
  "type": "Feature",
  "properties": {
    "iso:country":"US",
    "sg:address":"232 Ann Dr",
    "sg:city":"Eagle Lake",
    "sg:classifiers":[
        {
            "category":"Building & Trades",
            "subcategory":"Construction",
            "type":"Services"
        }
    ],
    "sg:phone":"+1 507 257 2214",
    "sg:postcode":"56024",
    "sg:province":"MN",
    "sg:tags":[
        "house"
    ],
    "wof:name":"Hansen Dj Construction",
    "wof:placetype":"venue"
},
  "geometry": {"coordinates":[-93.88265199999999,44.160889],"type":"Point"}
}