{
  "type": "Feature",
  "properties": {
    "addr:full":"2508 Riverside Ave Minneapolis MN 55454",
    "addr:housenumber":"2508",
    "addr:postcode":"55454",
    "addr:street":"Riverside Ave",
    "iso:country":"US",
    "sg:address":"2508 Riverside Ave",
    "sg:city":"Minneapolis",
    "sg:classifiers":[
        {
            "category":"Shopping",
            "subcategory":"Florist",
            "type":"Retail Goods"
        }
    ],
    "sg:phone":"+1 612 332 7441",
    "sg:postcode":"55454",
    "sg:province":"MN",
    "wof:name":"Riverside Florist",
    "wof:placetype":"venue"
},
  "geometry": {"coordinates":[-93.235703,44.965199],"type":"Point"}
}