{
  "type": "Feature",
  "properties": {
    "addr:full":"12687 Echo Ave Lonsdale MN 55046",
    "addr:housenumber":"12687",
    "addr:postcode":"55046",
    "addr:street":"Echo Ave",
    "iso:country":"US",
    "sg:address":"12687 Echo Ave",
    "sg:city":"Lonsdale",
    "sg:classifiers":[
        {
            "category":"Transit Center",
            "subcategory":"Freight",
            "type":"Transportation"
        },
        {
            "category":"Freight",
            "type":"Transportation"
        }
    ],
    "sg:phone":"+1 507 291 0752",
    "sg:postcode":"55046",
    "sg:province":"MN",
    "sg:tags":[
        "local",
        "trucking-motor",
        "trucking"
    ],
    "wof:name":"L And J Trucking",
    "wof:placetype":"venue"
},
  "geometry": {"coordinates":[-93.362497,44.40175],"type":"Point"}
}