{
  "type": "Feature",
  "properties": {
    "addr:full":"1117 Xerxes Ave S Minneapolis MN 55405",
    "addr:housenumber":"1117",
    "addr:postcode":"55405",
    "addr:street":"Xerxes Ave S",
    "iso:country":"US",
    "sg:address":"1117 Xerxes Ave S",
    "sg:city":"Minneapolis",
    "sg:classifiers":[
        {
            "category":"Professional",
            "subcategory":"Art Services",
            "type":"Services"
        }
    ],
    "sg:phone":"+1 612 377 4838",
    "sg:postcode":"55405",
    "sg:province":"MN",
    "sg:tags":[
        "commercial",
        "design",
        "artist"
    ],
    "sg:website":"http://www.jodywinger.com",
    "wof:name":"Jody Winger Co",
    "wof:placetype":"venue"
},
  "geometry": {"coordinates":[-93.318547,44.968916],"type":"Point"}
}