{
  "type": "Feature",
  "properties": {
    "addr:full":"3813 Chandler Dr NE Minneapolis MN 55421",
    "addr:housenumber":"3813",
    "addr:postcode":"55421",
    "addr:street":"Chandler Dr Ne",
    "iso:country":"US",
    "sg:address":"3813 Chandler Dr NE",
    "sg:city":"Minneapolis",
    "sg:classifiers":[
        {
            "category":"Manufacturing",
            "subcategory":"Printing",
            "type":"Manufacturing & Wholesale Goods"
        }
    ],
    "sg:phone":"+1 612 788 2331",
    "sg:postcode":"55421",
    "sg:province":"MN",
    "sg:tags":[
        "lithographic",
        "b",
        "commercial",
        "typesetting"
    ],
    "wof:name":"Tracy Printing Inc",
    "wof:placetype":"venue"
},
  "geometry": {"coordinates":[-93.211382,45.039272],"type":"Point"}
}