{
  "type": "Feature",
  "properties": {
    "addr:full":"2625 Brookdale Rd Moorhead MN 56560",
    "addr:housenumber":"2625",
    "addr:postcode":"56560",
    "addr:street":"Brookdale Rd",
    "iso:country":"US",
    "sg:address":"2625 Brookdale Rd",
    "sg:city":"Moorhead",
    "sg:classifiers":[
        {
            "category":"Shopping",
            "subcategory":"Gifts & Souvenirs",
            "type":"Retail Goods"
        }
    ],
    "sg:phone":"+1 218 233 3606",
    "sg:postcode":"56560",
    "sg:province":"MN",
    "wof:name":"Rubys Mom Crafts Gifts",
    "wof:placetype":"venue"
},
  "geometry": {"coordinates":[-96.770758,46.848738],"type":"Point"}
}