{
  "type": "Feature",
  "properties": {
    "iso:country":"US",
    "sg:address":"1500 1st Ave NE",
    "sg:city":"Rochester",
    "sg:classifiers":[
        {
            "category":"Professional",
            "subcategory":"Detective & Security Services",
            "type":"Services"
        }
    ],
    "sg:phone":"+1 507 281 9646",
    "sg:postcode":"55906",
    "sg:province":"MN",
    "sg:tags":[
        "system"
    ],
    "wof:name":"General Security Services",
    "wof:placetype":"venue"
},
  "geometry": {"coordinates":[-92.460536,44.037915],"type":"Point"}
}