{
  "type": "Feature",
  "properties": {
    "iso:country":"US",
    "sg:address":"8118 Hadley Ave S",
    "sg:city":"Cottage Grove",
    "sg:classifiers":[
        {
            "category":"Retail",
            "subcategory":"Auto Repair",
            "type":"Services"
        }
    ],
    "sg:phone":"+1 651 459 9748",
    "sg:postcode":"55016",
    "sg:province":"MN",
    "sg:tags":[
        "repairing",
        "automobile"
    ],
    "wof:name":"Hansen's Auto Care",
    "wof:placetype":"venue"
},
  "geometry": {"coordinates":[-92.96768400000001,44.83209],"type":"Point"}
}