{
  "type": "Feature",
  "properties": {
    "iso:country":"US",
    "sg:address":"808 Washington Ave",
    "sg:city":"Detroit Lakes",
    "sg:classifiers":[
        {
            "category":"Personal",
            "subcategory":"Beauty Salon",
            "type":"Services"
        }
    ],
    "sg:phone":"+1 218 847 9200",
    "sg:postcode":"56501",
    "sg:province":"MN",
    "sg:tags":[
        "manicuring"
    ],
    "wof:name":"Personal Fx Your Place-Nails",
    "wof:placetype":"venue"
},
  "geometry": {"coordinates":[-95.845366,46.818327],"type":"Point"}
}