{
  "type": "Feature",
  "properties": {
    "addr:full":"629 E Sheridan St Ely MN 55731",
    "addr:housenumber":"629",
    "addr:postcode":"55731",
    "addr:street":"E Sheridan St",
    "iso:country":"US",
    "sg:address":"629 E Sheridan St",
    "sg:city":"Ely",
    "sg:classifiers":[
        {
            "category":"Professional",
            "type":"Services"
        }
    ],
    "sg:phone":"+1 218 365 5832",
    "sg:postcode":"55731",
    "sg:province":"MN",
    "sg:tags":[
        "establishment"
    ],
    "wof:name":"Moose Lake Landing",
    "wof:placetype":"venue"
},
  "geometry": {"coordinates":[-91.856911,47.903113],"type":"Point"}
}