{
  "type": "Feature",
  "properties": {
    "iso:country":"US",
    "sg:address":"Moore Lake Cmns",
    "sg:city":"Minneapolis",
    "sg:classifiers":[
        {
            "category":"Social Services",
            "subcategory":"Child Care",
            "type":"Services"
        }
    ],
    "sg:phone":"+1 763 574 7450",
    "sg:postcode":"55421",
    "sg:province":"MN",
    "sg:tags":[
        "day"
    ],
    "wof:name":"New Horizon Child Care",
    "wof:placetype":"venue"
},
  "geometry": {"coordinates":[-93.244499,45.047298],"type":"Point"}
}