{
  "type": "Feature",
  "properties": {
    "addr:full":"568 Oak St NE Mazeppa MN 55956",
    "addr:housenumber":"568",
    "addr:postcode":"55956",
    "addr:street":"Oak St Ne",
    "iso:country":"US",
    "sg:address":"568 Oak St NE",
    "sg:city":"Mazeppa",
    "sg:classifiers":[
        {
            "category":"Manufacturing",
            "subcategory":"Pet Food",
            "type":"Manufacturing & Wholesale Goods"
        },
        {
            "category":"Farming",
            "subcategory":"Farm",
            "type":"Manufacturing & Wholesale Goods"
        }
    ],
    "sg:phone":"+1 507 843 4515",
    "sg:postcode":"55956",
    "sg:province":"MN",
    "sg:tags":[
        "hay"
    ],
    "wof:name":"Ernest Arnedt",
    "wof:placetype":"venue"
},
  "geometry": {"coordinates":[-92.537204,44.279099],"type":"Point"}
}