{
  "type": "Feature",
  "properties": {
    "iso:country":"US",
    "sg:address":"910 Central Ave NE",
    "sg:city":"East Grand Forks",
    "sg:classifiers":[
        {
            "category":"Shopping",
            "subcategory":"Optical Goods",
            "type":"Retail Goods"
        }
    ],
    "sg:phone":"+1 218 773 7518",
    "sg:postcode":"56721",
    "sg:province":"MN",
    "wof:name":"Midwest Vision Centers",
    "wof:placetype":"venue"
},
  "geometry": {"coordinates":[-97.02009200000001,47.933997],"type":"Point"}
}