{
  "type": "Feature",
  "properties": {
    "iso:country":"US",
    "sg:address":"3900 Park Nicollet Blvd",
    "sg:city":"Minneapolis",
    "sg:classifiers":[
        {
            "category":"Shopping",
            "subcategory":"Optician",
            "type":"Retail Goods"
        }
    ],
    "sg:phone":"+1 952 993 1940",
    "sg:postcode":"55416",
    "sg:province":"MN",
    "sg:tags":[
        "eyewear"
    ],
    "sg:website":"www.parknicollet.com",
    "wof:name":"Optical Store @ Park Nicollet",
    "wof:placetype":"venue"
},
  "geometry": {"coordinates":[-93.346653,44.933047],"type":"Point"}
}