{
  "type": "Feature",
  "properties": {
    "addr:full":"113 E 4th St Blue Earth MN 56013",
    "addr:housenumber":"113",
    "addr:postcode":"56013",
    "addr:street":"E 4Th St",
    "iso:country":"US",
    "sg:address":"113 E 4th St",
    "sg:city":"Blue Earth",
    "sg:classifiers":[
        {
            "category":"Professional",
            "subcategory":"Accounting & Tax Preparation",
            "type":"Services"
        }
    ],
    "sg:phone":"+1 507 526 2866",
    "sg:postcode":"56013",
    "sg:province":"MN",
    "sg:tags":[
        "accountant"
    ],
    "wof:name":"Williams Accounting & Ins",
    "wof:placetype":"venue"
},
  "geometry": {"coordinates":[-94.10236,43.6408],"type":"Point"}
}