{
  "type": "Feature",
  "properties": {
    "iso:country":"US",
    "sg:address":"8030 Rhode Island Cir",
    "sg:city":"Minneapolis",
    "sg:classifiers":[
        {
            "category":"Shopping",
            "subcategory":"Pets & Pet Supplies",
            "type":"Retail Goods"
        }
    ],
    "sg:phone":"+1 952 944 9847",
    "sg:postcode":"55438",
    "sg:province":"MN",
    "sg:tags":[
        "product",
        "health",
        "animal"
    ],
    "wof:name":"Charles Immel Associates Inc",
    "wof:placetype":"venue"
},
  "geometry": {"coordinates":[-93.38229200000001,44.857016],"type":"Point"}
}