{
  "type": "Feature",
  "properties": {
    "addr:full":"1851 Central Ave NE Minneapolis MN 55418",
    "addr:housenumber":"1851",
    "addr:postcode":"55418",
    "addr:street":"Central Ave Ne",
    "iso:country":"US",
    "sg:address":"1851 Central Ave NE",
    "sg:city":"Minneapolis",
    "sg:classifiers":[
        {
            "category":"Restaurant",
            "type":"Food & Drink"
        },
        {
            "category":"Bars & Pubs",
            "subcategory":"Nightclub",
            "type":"Food & Drink"
        }
    ],
    "sg:phone":"+1 612 788 4122",
    "sg:postcode":"55418",
    "sg:province":"MN",
    "sg:tags":[
        "club",
        "night"
    ],
    "wof:name":"King Falafel",
    "wof:placetype":"venue"
},
  "geometry": {"coordinates":[-93.24736799999999,45.007088],"type":"Point"}
}