{
  "type": "Feature",
  "properties": {
    "iso:country":"US",
    "sg:address":"1004 10th Ave",
    "sg:city":"Clarkfield",
    "sg:classifiers":[
        {
            "category":"Government",
            "subcategory":"Office",
            "type":"Public Place"
        }
    ],
    "sg:phone":"+1 320 669 4471",
    "sg:postcode":"56223",
    "sg:province":"MN",
    "wof:name":"Yellow Medicine County Ext Svc",
    "wof:placetype":"venue"
},
  "geometry": {"coordinates":[-95.804863,44.790761],"type":"Point"}
}