{
  "type": "Feature",
  "properties": {
    "iso:country":"US",
    "sg:address":"105 Main Ave S",
    "sg:city":"Roseau",
    "sg:classifiers":[
        {
            "category":"Retail",
            "subcategory":"Photofinishing",
            "type":"Services"
        }
    ],
    "sg:phone":"+1 218 463 2550",
    "sg:postcode":"56751",
    "sg:province":"MN",
    "sg:tags":[
        "laboratory",
        "finishing",
        "photo"
    ],
    "wof:name":"Dean's Photo Express",
    "wof:placetype":"venue"
},
  "geometry": {"coordinates":[-95.762933,48.845252],"type":"Point"}
}