{
  "type": "Feature",
  "properties": {
    "addr:full":"207 N 1st St Montevideo MN 56265",
    "addr:housenumber":"207",
    "addr:postcode":"56265",
    "addr:street":"N 1St St",
    "iso:country":"US",
    "sg:address":"207 N 1st St",
    "sg:city":"Montevideo",
    "sg:classifiers":[
        {
            "category":"Restaurant",
            "type":"Food & Drink"
        }
    ],
    "sg:phone":"+1 320 269 6888",
    "sg:postcode":"56265",
    "sg:province":"MN",
    "sg:tags":[
        "eating"
    ],
    "wof:name":"Grand Buffet",
    "wof:placetype":"venue"
},
  "geometry": {"coordinates":[-95.724908,44.947167],"type":"Point"}
}