{
  "type": "Feature",
  "properties": {
    "iso:country":"US",
    "sg:address":"2600 S Pokegama Ave",
    "sg:city":"Grand Rapids",
    "sg:classifiers":[
        {
            "category":"Home & Garden",
            "subcategory":"Building Materials",
            "type":"Retail Goods"
        }
    ],
    "sg:phone":"+1 218 327 9791",
    "sg:postcode":"55744",
    "sg:province":"MN",
    "sg:tags":[
        "center"
    ],
    "sg:website":"www.homedepot.com",
    "wof:name":"Home Depot",
    "wof:placetype":"venue"
},
  "geometry": {"coordinates":[-93.528704,47.208119],"type":"Point"}
}