{
  "type": "Feature",
  "properties": {
    "addr:full":"3908 19th Ave NW Rochester MN 55901",
    "addr:housenumber":"3908",
    "addr:postcode":"55901",
    "addr:street":"19Th Ave Nw",
    "iso:country":"US",
    "sg:address":"3908 19th Ave NW",
    "sg:city":"Rochester",
    "sg:classifiers":[
        {
            "category":"Real Estate",
            "subcategory":"Real Estate Operator",
            "type":"Services"
        }
    ],
    "sg:phone":"+1 507 288 6559",
    "sg:postcode":"55901",
    "sg:province":"MN",
    "sg:tags":[
        "apartment",
        "complex"
    ],
    "wof:name":"Winchester Apartments",
    "wof:placetype":"venue"
},
  "geometry": {"coordinates":[-92.49250000000001,44.06422],"type":"Point"}
}