{
  "type": "Feature",
  "properties": {
    "iso:country":"US",
    "sg:address":"15249 Spring Lake Rd NW",
    "sg:city":"Miltona",
    "sg:classifiers":[
        {
            "category":"Travel",
            "subcategory":"Hotels & Motels",
            "type":"Entertainment"
        }
    ],
    "sg:phone":"+1 218 267 2541",
    "sg:postcode":"56354",
    "sg:province":"MN",
    "sg:tags":[
        "resort",
        "electrical",
        "contractor"
    ],
    "wof:name":"Country Bay Resort",
    "wof:placetype":"venue"
},
  "geometry": {"coordinates":[-95.432478,46.051708],"type":"Point"}
}