{
  "type": "Feature",
  "properties": {
    "addr:full":"115 Pacific Ave Waverly MN 55390",
    "addr:housenumber":"115",
    "addr:postcode":"55390",
    "addr:street":"Pacific Ave",
    "iso:country":"US",
    "sg:address":"115 Pacific Ave",
    "sg:city":"Waverly",
    "sg:classifiers":[
        {
            "category":"Retail",
            "subcategory":"Auto Repair",
            "type":"Services"
        }
    ],
    "sg:phone":"+1 763 658 4501",
    "sg:postcode":"55390",
    "sg:province":"MN",
    "sg:tags":[
        "repairing",
        "automobile"
    ],
    "wof:name":"J & T Motors",
    "wof:placetype":"venue"
},
  "geometry": {"coordinates":[-93.96193700000001,45.066119],"type":"Point"}
}