{
  "type": "Feature",
  "properties": {
    "iso:country":"US",
    "sg:address":"3033 Excelsior Blvd",
    "sg:city":"Minneapolis",
    "sg:classifiers":[
        {
            "category":"Health Services",
            "subcategory":"Nursing And Care Facility",
            "type":"Services"
        }
    ],
    "sg:phone":"+1 612 827 4751",
    "sg:postcode":"55416",
    "sg:province":"MN",
    "sg:tags":[
        "nurse",
        "practice-arnp",
        "nurses-advanced"
    ],
    "wof:name":"Kringle Vicki",
    "wof:placetype":"venue"
},
  "geometry": {"coordinates":[-93.32061,44.947498],"type":"Point"}
}