{
  "type": "Feature",
  "properties": {
    "addr:full":"1536 13th Ave E Hibbing MN 55746",
    "addr:housenumber":"1536",
    "addr:postcode":"55746",
    "addr:street":"13Th Ave E Hibbing",
    "iso:country":"US",
    "sg:address":"1536 13th Ave E",
    "sg:city":"Hibbing",
    "sg:classifiers":[
        {
            "category":"Manufacturing",
            "subcategory":"Apparel",
            "type":"Manufacturing & Wholesale Goods"
        }
    ],
    "sg:phone":"+1 218 262 4849",
    "sg:postcode":"55746",
    "sg:province":"MN",
    "wof:name":"Noor Embroidery Services",
    "wof:placetype":"venue"
},
  "geometry": {"coordinates":[-92.92631900000001,47.432361],"type":"Point"}
}