{
  "type": "Feature",
  "properties": {
    "addr:full":"1601 County Road 42 W Burnsville MN 55306",
    "addr:housenumber":"1601",
    "addr:postcode":"55306",
    "addr:street":"County Road 42 W",
    "iso:country":"US",
    "sg:address":"1601 County Road 42 W",
    "sg:city":"Burnsville",
    "sg:classifiers":[
        {
            "category":"Deli",
            "type":"Food & Drink"
        },
        {
            "category":"Bagels",
            "type":"Food & Drink"
        },
        {
            "category":"Coffee & Tea",
            "type":"Food & Drink"
        }
    ],
    "sg:menulink":"http://www.allmenus.com/mn/burnsville/40971-brueggers/menu/",
    "sg:phone":"+1 952 898 1999",
    "sg:postcode":"55306",
    "sg:province":"MN",
    "sg:tags":[
        "wrap",
        "soup",
        "american",
        "sandwich",
        "salad"
    ],
    "wof:name":"Bruegger's",
    "wof:placetype":"venue"
},
  "geometry": {"coordinates":[-93.25364,44.733429],"type":"Point"}
}