{
  "type": "Feature",
  "properties": {
    "iso:country":"US",
    "sg:address":"20600 Manor Rd",
    "sg:city":"Excelsior",
    "sg:classifiers":[
        {
            "category":"Real Estate",
            "subcategory":"Real Estate Operator",
            "type":"Services"
        }
    ],
    "sg:phone":"+1 952 401 1620",
    "sg:postcode":"55331",
    "sg:province":"MN",
    "sg:tags":[
        "apartment"
    ],
    "wof:name":"Manor Park",
    "wof:placetype":"venue"
},
  "geometry": {"coordinates":[-93.541397,44.9105],"type":"Point"}
}