{
  "type": "Feature",
  "properties": {
    "addr:full":"10929 Scandia Trl N Scandia MN 55073",
    "addr:housenumber":"10929",
    "addr:postcode":"55073",
    "addr:street":"Scandia Trl N Scandia",
    "iso:country":"US",
    "sg:address":"10929 Scandia Trl N",
    "sg:city":"Scandia",
    "sg:classifiers":[
        {
            "category":"Manufacturing",
            "subcategory":"Food",
            "type":"Manufacturing & Wholesale Goods"
        },
        {
            "category":"Farming",
            "subcategory":"Farm",
            "type":"Manufacturing & Wholesale Goods"
        }
    ],
    "sg:phone":"+1 651 433 2998",
    "sg:postcode":"55073",
    "sg:province":"MN",
    "sg:tags":[
        "corn",
        "product"
    ],
    "wof:name":"George Lindgren",
    "wof:placetype":"venue"
},
  "geometry": {"coordinates":[-92.889574,45.253478],"type":"Point"}
}