{
  "type": "Feature",
  "properties": {
    "addr:full":"19175 Market Ave Belle Plaine MN 56011",
    "addr:housenumber":"19175",
    "addr:postcode":"56011",
    "addr:street":"Market Ave Belle Plaine",
    "iso:country":"US",
    "sg:address":"19175 Market Ave",
    "sg:city":"Belle Plaine",
    "sg:classifiers":[
        {
            "category":"Banks & Credit Unions",
            "subcategory":"Financial Services",
            "type":"Services"
        }
    ],
    "sg:phone":"+1 952 873 2873",
    "sg:postcode":"56011",
    "sg:province":"MN",
    "sg:tags":[
        "company",
        "holding"
    ],
    "wof:name":"Rmk Holdings Inc",
    "wof:placetype":"venue"
},
  "geometry": {"coordinates":[-93.768095,44.656639],"type":"Point"}
}