{
  "type": "Feature",
  "properties": {
    "addr:full":"6044 W Broadway Ave Minneapolis MN 55428",
    "addr:housenumber":"6044",
    "addr:postcode":"55428",
    "addr:street":"W Broadway Ave",
    "iso:country":"US",
    "sg:address":"6044 W Broadway Ave",
    "sg:city":"Minneapolis",
    "sg:classifiers":[
        {
            "category":"Professional",
            "subcategory":"Business Services",
            "type":"Services"
        }
    ],
    "sg:phone":"+1 763 531 2429",
    "sg:postcode":"55428",
    "sg:province":"MN",
    "sg:tags":[
        "distribution"
    ],
    "wof:name":"Braziel Enterprises",
    "wof:placetype":"venue"
},
  "geometry": {"coordinates":[-93.375061,45.064745],"type":"Point"}
}