{
  "type": "Feature",
  "properties": {
    "addr:full":"410 9th Ave SW Wells MN 56097",
    "addr:housenumber":"410",
    "addr:postcode":"56097",
    "addr:street":"9Th Ave Sw",
    "iso:country":"US",
    "sg:address":"410 9th Ave SW",
    "sg:city":"Wells",
    "sg:classifiers":[
        {
            "category":"Building & Trades",
            "subcategory":"Landscaping Services",
            "type":"Services"
        }
    ],
    "sg:phone":"+1 507 553 3253",
    "sg:postcode":"56097",
    "sg:province":"MN",
    "wof:name":"Weber Lawn & Snowblowing Svc",
    "wof:placetype":"venue"
},
  "geometry": {"coordinates":[-93.737675,43.740926],"type":"Point"}
}