{
  "type": "Feature",
  "properties": {
    "iso:country":"US",
    "sg:address":"4430 Haines Rd",
    "sg:city":"Duluth",
    "sg:classifiers":[
        {
            "category":"Wholesale",
            "subcategory":"Medical Equipment & Supplies",
            "type":"Manufacturing & Wholesale Goods"
        }
    ],
    "sg:phone":"+1 218 722 7436",
    "sg:postcode":"55811",
    "sg:province":"MN",
    "sg:tags":[
        "hospital"
    ],
    "wof:name":"KCI",
    "wof:placetype":"venue"
},
  "geometry": {"coordinates":[-92.174722,46.830693],"type":"Point"}
}