{
  "type": "Feature",
  "properties": {
    "addr:full":"1630 White Bear Ave N St Paul MN 55106",
    "addr:housenumber":"1630",
    "addr:postcode":"55106",
    "addr:street":"White Bear Ave N",
    "iso:country":"US",
    "sg:address":"1630 White Bear Ave N",
    "sg:city":"St Paul",
    "sg:classifiers":[
        {
            "category":"Personal",
            "subcategory":"Beauty Salon",
            "type":"Services"
        }
    ],
    "sg:phone":"+1 651 772 6850",
    "sg:postcode":"55106",
    "sg:province":"MN",
    "sg:tags":[
        "manicuring"
    ],
    "wof:name":"Pro Nail",
    "wof:placetype":"venue"
},
  "geometry": {"coordinates":[-93.025148,44.990781],"type":"Point"}
}