{
  "type": "Feature",
  "properties": {
    "iso:country":"US",
    "sg:address":"16 Bedford St SE",
    "sg:city":"Minneapolis",
    "sg:classifiers":[
        {
            "category":"Retail",
            "subcategory":"Auto Repair",
            "type":"Services"
        }
    ],
    "sg:phone":"+1 612 379 4232",
    "sg:postcode":"55414",
    "sg:province":"MN",
    "wof:name":"Hondaworks",
    "wof:placetype":"venue"
},
  "geometry": {"coordinates":[-93.208282,44.968719],"type":"Point"}
}