{
  "type": "Feature",
  "properties": {
    "addr:full":"12008 Co Rd 11 Burnsville MN 55337",
    "addr:housenumber":"12008;11",
    "addr:postcode":"55337",
    "addr:street":"Co Rd",
    "iso:country":"US",
    "sg:address":"12008 Co Rd 11",
    "sg:city":"Burnsville",
    "sg:classifiers":[
        {
            "category":"Real Estate",
            "subcategory":"Real Estate Agent",
            "type":"Services"
        }
    ],
    "sg:phone":"+1 952 746 7570",
    "sg:postcode":"55337",
    "sg:province":"MN",
    "wof:name":"Help U Sell Choice Real Estate",
    "wof:placetype":"venue"
},
  "geometry": {"coordinates":[-93.24816199999999,44.78677],"type":"Point"}
}