{
  "type": "Feature",
  "properties": {
    "addr:full":"5000 Green Farms Rd Minneapolis MN 55436",
    "addr:housenumber":"5000",
    "addr:postcode":"55436",
    "addr:street":"Green Farms Rd",
    "iso:country":"US",
    "sg:address":"5000 Green Farms Rd",
    "sg:city":"Minneapolis",
    "sg:classifiers":[
        {
            "category":"Organizations",
            "subcategory":"Labor Organization",
            "type":"Services"
        }
    ],
    "sg:phone":"+1 612 725 0933",
    "sg:postcode":"55436",
    "sg:province":"MN",
    "wof:name":"Mail Handlers Union Office",
    "wof:placetype":"venue"
},
  "geometry": {"coordinates":[-93.39127999999999,44.913456],"type":"Point"}
}