{
  "type": "Feature",
  "properties": {
    "addr:full":"965 Rice St St Paul MN 55117",
    "addr:housenumber":"965",
    "addr:postcode":"55117",
    "addr:street":"Rice St",
    "iso:country":"US",
    "sg:address":"965 Rice St",
    "sg:city":"St Paul",
    "sg:classifiers":[
        {
            "category":"Personal",
            "subcategory":"Beauty Salon",
            "type":"Services"
        }
    ],
    "sg:phone":"+1 651 489 2583",
    "sg:postcode":"55117",
    "sg:province":"MN",
    "wof:name":"Bamba Hair Braiding",
    "wof:placetype":"venue"
},
  "geometry": {"coordinates":[-93.106037,44.970921],"type":"Point"}
}