{
  "type": "Feature",
  "properties": {
    "addr:full":"9640 Xylon Ave S Minneapolis MN 55438",
    "addr:postcode":"9640;55438",
    "addr:street":"Xylon Ave S",
    "iso:country":"US",
    "sg:address":"9640 Xylon Ave S",
    "sg:city":"Minneapolis",
    "sg:classifiers":[
        {
            "category":"Real Estate",
            "subcategory":"Real Estate Services",
            "type":"Services"
        }
    ],
    "sg:phone":"+1 952 941 1822",
    "sg:postcode":"55438",
    "sg:province":"MN",
    "sg:tags":[
        "commercial"
    ],
    "wof:name":"Peterson Real Estate Services",
    "wof:placetype":"venue"
},
  "geometry": {"coordinates":[-93.389651,44.828581],"type":"Point"}
}