{
  "type": "Feature",
  "properties": {
    "addr:full":"33 Hays Cir Silver Bay MN 55614",
    "addr:housenumber":"33",
    "addr:postcode":"55614",
    "addr:street":"Hays Cir",
    "iso:country":"US",
    "sg:address":"33 Hays Cir",
    "sg:city":"Silver Bay",
    "sg:classifiers":[
        {
            "category":"Building & Trades",
            "subcategory":"Construction",
            "type":"Services"
        }
    ],
    "sg:phone":"+1 218 226 3743",
    "sg:postcode":"55614",
    "sg:province":"MN",
    "sg:tags":[
        "residential"
    ],
    "wof:name":"Thompson Construction",
    "wof:placetype":"venue"
},
  "geometry": {"coordinates":[-91.290443,47.290659],"type":"Point"}
}