{
  "type": "Feature",
  "properties": {
    "iso:country":"US",
    "sg:address":"18 Railway St",
    "sg:city":"Kensington",
    "sg:classifiers":[
        {
            "category":"Manufacturing",
            "subcategory":"Toys & Sporting Goods",
            "type":"Manufacturing & Wholesale Goods"
        }
    ],
    "sg:phone":"+1 320 965 2242",
    "sg:postcode":"56343",
    "sg:province":"MN",
    "sg:tags":[
        "athletic"
    ],
    "wof:name":"Runestone Manufacturing",
    "wof:placetype":"venue"
},
  "geometry": {"coordinates":[-95.697953,45.778507],"type":"Point"}
}