{
  "type": "Feature",
  "properties": {
    "addr:full":"213 Summit St SW Sleepy Eye MN 56085",
    "addr:housenumber":"213",
    "addr:postcode":"56085",
    "addr:street":"Summit St Sw Sleepy",
    "iso:country":"US",
    "sg:address":"213 Summit St SW",
    "sg:city":"Sleepy Eye",
    "sg:classifiers":[
        {
            "category":"Social Services",
            "subcategory":"Child Care",
            "type":"Services"
        }
    ],
    "sg:phone":"+1 507 794 6477",
    "sg:postcode":"56085",
    "sg:province":"MN",
    "sg:tags":[
        "daycare",
        "provider"
    ],
    "wof:name":"Sharon Remus",
    "wof:placetype":"venue"
},
  "geometry": {"coordinates":[-94.725555,44.291997],"type":"Point"}
}