{
  "type": "Feature",
  "properties": {
    "addr:full":"13833 Shenandoah St NE Anoka MN 55304",
    "addr:housenumber":"13833",
    "addr:postcode":"55304",
    "addr:street":"Shenandoah St Ne",
    "iso:country":"US",
    "sg:address":"13833 Shenandoah St NE",
    "sg:city":"Anoka",
    "sg:classifiers":[
        {
            "category":"Professional",
            "subcategory":"Business Services",
            "type":"Services"
        }
    ],
    "sg:phone":"+1 763 862 2590",
    "sg:postcode":"55304",
    "sg:province":"MN",
    "wof:name":"Water Logic Inc",
    "wof:placetype":"venue"
},
  "geometry": {"coordinates":[-93.17502399999999,45.221429],"type":"Point"}
}