{
  "type": "Feature",
  "properties": {
    "addr:full":"4613 Lakeside Ln Mound MN 55364",
    "addr:housenumber":"4613",
    "addr:postcode":"55364",
    "addr:street":"Lakeside Ln",
    "iso:country":"US",
    "sg:address":"4613 Lakeside Ln",
    "sg:city":"Mound",
    "sg:classifiers":[
        {
            "category":"Professional",
            "subcategory":"Management & Consulting",
            "type":"Services"
        },
        {
            "category":"Professional",
            "subcategory":"Advertising",
            "type":"Services"
        }
    ],
    "sg:phone":"+1 952 472 1763",
    "sg:postcode":"55364",
    "sg:province":"MN",
    "sg:tags":[
        "marketing",
        "program",
        "consultant"
    ],
    "wof:name":"Aerotech Marketing Ltd",
    "wof:placetype":"venue"
},
  "geometry": {"coordinates":[-93.64073399999999,44.941505],"type":"Point"}
}