{
  "type": "Feature",
  "properties": {
    "iso:country":"US",
    "sg:address":"912 Main St",
    "sg:city":"Red Wing",
    "sg:classifiers":[
        {
            "category":"Cinema",
            "subcategory":"Movie Rental",
            "type":"Entertainment"
        }
    ],
    "sg:phone":"+1 651 388 9411",
    "sg:postcode":"55066",
    "sg:province":"MN",
    "sg:tags":[
        "leasing",
        "video",
        "disc",
        "tape"
    ],
    "wof:name":"Mr Movies",
    "wof:placetype":"venue"
},
  "geometry": {"coordinates":[-92.54077599999999,44.563594],"type":"Point"}
}