{
  "type": "Feature",
  "properties": {
    "iso:country":"US",
    "sg:address":"1819 Valley Curve Rd",
    "sg:city":"Saint Paul",
    "sg:classifiers":[
        {
            "category":"Real Estate",
            "subcategory":"Real Estate Agent",
            "type":"Services"
        }
    ],
    "sg:phone":"+1 651 454 1933",
    "sg:postcode":"55118",
    "sg:province":"MN",
    "wof:name":"WE Holding Co Ltd",
    "wof:placetype":"venue"
},
  "geometry": {"coordinates":[-93.12821700000001,44.889365],"type":"Point"}
}