{
  "type": "Feature",
  "properties": {
    "iso:country":"US",
    "sg:address":"1293 Wood Duck Trl",
    "sg:city":"Shakopee",
    "sg:classifiers":[
        {
            "category":"Professional",
            "subcategory":"Management & Consulting",
            "type":"Services"
        }
    ],
    "sg:phone":"+1 952 403 1098",
    "sg:postcode":"55379",
    "sg:province":"MN",
    "sg:tags":[
        "publishing",
        "desktop"
    ],
    "wof:name":"Darcee Desktop Publishing",
    "wof:placetype":"venue"
},
  "geometry": {"coordinates":[-93.507578,44.752878],"type":"Point"}
}