{
  "type": "Feature",
  "properties": {
    "addr:full":"118 1st St NW Ulen MN 56585",
    "addr:housenumber":"118",
    "addr:postcode":"56585",
    "addr:street":"1St St Nw",
    "iso:country":"US",
    "sg:address":"118 1st St NW",
    "sg:city":"Ulen",
    "sg:classifiers":[
        {
            "category":"Retail",
            "subcategory":"Auto Repair",
            "type":"Services"
        }
    ],
    "sg:phone":"+1 218 596 8817",
    "sg:postcode":"56585",
    "sg:province":"MN",
    "sg:tags":[
        "repairing",
        "automobile"
    ],
    "wof:name":"Ulen Standard",
    "wof:placetype":"venue"
},
  "geometry": {"coordinates":[-96.259111,47.080641],"type":"Point"}
}