{
  "type": "Feature",
  "properties": {
    "addr:full":"608 University Ave W St Paul MN 55103",
    "addr:housenumber":"608",
    "addr:postcode":"55103",
    "addr:street":"University Ave W",
    "iso:country":"US",
    "sg:address":"608 University Ave W",
    "sg:city":"St Paul",
    "sg:classifiers":[
        {
            "category":"Wholesale",
            "subcategory":"Machinery & Supplies",
            "type":"Manufacturing & Wholesale Goods"
        }
    ],
    "sg:phone":"+1 651 290 2836",
    "sg:postcode":"55103",
    "sg:province":"MN",
    "sg:tags":[
        "salon",
        "establishment",
        "merchandise",
        "beauty"
    ],
    "wof:name":"Earth's Beauty Supply",
    "wof:placetype":"venue"
},
  "geometry": {"coordinates":[-93.124849,44.955652],"type":"Point"}
}