{
  "type": "Feature",
  "properties": {
    "iso:country":"US",
    "sg:address":"26 E Exchange St",
    "sg:city":"St Paul",
    "sg:classifiers":[
        {
            "category":"Professional",
            "subcategory":"Lawyer & Legal Services",
            "type":"Services"
        }
    ],
    "sg:phone":"+1 651 227 0220",
    "sg:postcode":"55101",
    "sg:province":"MN",
    "sg:tags":[
        "attorney"
    ],
    "wof:name":"Montgomery Law Office",
    "wof:placetype":"venue"
},
  "geometry": {"coordinates":[-93.096667,44.949429],"type":"Point"}
}