{
  "type": "Feature",
  "properties": {
    "iso:country":"US",
    "sg:address":"130 13th Ave SE",
    "sg:city":"Rochester",
    "sg:classifiers":[
        {
            "category":"Retail",
            "subcategory":"Animal Services",
            "type":"Services"
        }
    ],
    "sg:phone":"+1 507 292 1901",
    "sg:postcode":"55904",
    "sg:province":"MN",
    "sg:tags":[
        "pet",
        "grooming",
        "washing"
    ],
    "wof:name":"Rochester Grooming Center",
    "wof:placetype":"venue"
},
  "geometry": {"coordinates":[-92.446432,44.02186],"type":"Point"}
}