{
  "type": "Feature",
  "properties": {
    "iso:country":"US",
    "sg:address":"4902 222nd St E",
    "sg:city":"Hampton",
    "sg:phone":"+1 651 437 6348",
    "sg:postcode":"55031",
    "sg:province":"MN",
    "sg:tags":[
        "farm",
        "grain",
        "cash"
    ],
    "wof:name":"Marcus Halepeska",
    "wof:placetype":"venue"
},
  "geometry": {"coordinates":[-93.010167,44.626555],"type":"Point"}
}