{
  "type": "Feature",
  "properties": {
    "iso:country":"US",
    "sg:address":"720 5th St N",
    "sg:city":"Breckenridge",
    "sg:classifiers":[
        {
            "category":"Health Services",
            "subcategory":"Nursing And Care Facility",
            "type":"Services"
        }
    ],
    "sg:phone":"+1 218 641 1140",
    "sg:postcode":"56520",
    "sg:province":"MN",
    "sg:tags":[
        "home",
        "retirement",
        "community"
    ],
    "wof:name":"Spectrum Employee Benefits",
    "wof:placetype":"venue"
},
  "geometry": {"coordinates":[-96.58747,46.270825],"type":"Point"}
}