{
  "type": "Feature",
  "properties": {
    "iso:country":"US",
    "sg:address":"1002 Mainstreet",
    "sg:city":"Hopkins",
    "sg:classifiers":[
        {
            "category":"Shopping",
            "subcategory":"Clothing, Apparel, & Fashions",
            "type":"Retail Goods"
        }
    ],
    "sg:phone":"+1 952 933 5201",
    "sg:postcode":"55343",
    "sg:province":"MN",
    "sg:tags":[
        "western"
    ],
    "wof:name":"El Potro Western Wear",
    "wof:placetype":"venue"
},
  "geometry": {"coordinates":[-93.413944,44.924294],"type":"Point"}
}