{
  "type": "Feature",
  "properties": {
    "addr:full":"4235 5th Ave S Minneapolis MN 55409",
    "addr:housenumber":"4235",
    "addr:postcode":"55409",
    "addr:street":"5Th Ave S",
    "iso:country":"US",
    "sg:address":"4235 5th Ave S",
    "sg:city":"Minneapolis",
    "sg:classifiers":[
        {
            "category":"Building & Trades",
            "subcategory":"Construction",
            "type":"Services"
        }
    ],
    "sg:phone":"+1 612 825 4757",
    "sg:postcode":"55409",
    "sg:province":"MN",
    "sg:tags":[
        "house"
    ],
    "wof:name":"Ru Remodeling",
    "wof:placetype":"venue"
},
  "geometry": {"coordinates":[-93.268799,44.925754],"type":"Point"}
}