{
  "type": "Feature",
  "properties": {
    "addr:full":"10 E 15th St Minneapolis MN 55403",
    "addr:housenumber":"10",
    "addr:postcode":"55403",
    "addr:street":"E 15Th St",
    "iso:country":"US",
    "sg:address":"10 E 15th St",
    "sg:city":"Minneapolis",
    "sg:classifiers":[
        {
            "category":"Professional",
            "type":"Services"
        },
        {
            "category":"Utilities",
            "subcategory":"Fuel Oil & Lpg",
            "type":"Services"
        },
        {
            "category":"Wholesale",
            "subcategory":"Petroleum",
            "type":"Manufacturing & Wholesale Goods"
        }
    ],
    "sg:phone":"+1 612 879 9842",
    "sg:postcode":"55403",
    "sg:province":"MN",
    "sg:tags":[
        "field",
        "well",
        "drilling"
    ],
    "wof:name":"Cromwell",
    "wof:placetype":"venue"
},
  "geometry": {"coordinates":[-93.27774599999999,44.968029],"type":"Point"}
}