{
  "type": "Feature",
  "properties": {
    "addr:full":"135 80th St SE Maynard MN 56265",
    "addr:housenumber":"135",
    "addr:postcode":"56265",
    "addr:street":"80Th St Se",
    "iso:country":"US",
    "sg:address":"135 80th St SE",
    "sg:city":"Maynard",
    "sg:classifiers":[
        {
            "category":"Farming",
            "subcategory":"Farm",
            "type":"Manufacturing & Wholesale Goods"
        }
    ],
    "sg:phone":"+1 320 269 7578",
    "sg:postcode":"56265",
    "sg:province":"MN",
    "sg:tags":[
        "crop",
        "general"
    ],
    "wof:name":"K & W Farms Inc",
    "wof:placetype":"venue"
},
  "geometry": {"coordinates":[-95.59326,44.905711],"type":"Point"}
}