{
  "type": "Feature",
  "properties": {
    "addr:full":"2310 Como Ave St Paul MN 55108",
    "addr:housenumber":"2310",
    "addr:postcode":"55108",
    "addr:street":"Como Ave",
    "iso:country":"US",
    "sg:address":"2310 Como Ave",
    "sg:city":"St Paul",
    "sg:classifiers":[
        {
            "category":"Food & Beverages",
            "subcategory":"Groceries & Convenience Stores",
            "type":"Retail Goods"
        }
    ],
    "sg:phone":"+1 651 645 7360",
    "sg:postcode":"55108",
    "sg:province":"MN",
    "sg:tags":[
        "grocer",
        "station"
    ],
    "wof:name":"Tim & Tom's Speedy Market Inc",
    "wof:placetype":"venue"
},
  "geometry": {"coordinates":[-93.196144,44.982577],"type":"Point"}
}