{
  "type": "Feature",
  "properties": {
    "addr:full":"1501 30th Ave N Minneapolis MN 55411",
    "addr:housenumber":"1501",
    "addr:postcode":"55411",
    "addr:street":"30Th Ave N",
    "iso:country":"US",
    "sg:address":"1501 30th Ave N",
    "sg:city":"Minneapolis",
    "sg:classifiers":[
        {
            "category":"Education",
            "subcategory":"School",
            "type":"Public Place"
        }
    ],
    "sg:phone":"+1 612 668 2240",
    "sg:postcode":"55411",
    "sg:province":"MN",
    "sg:tags":[
        "high",
        "elementary",
        "middle"
    ],
    "sg:website":"www.mpls.k12.mn.us",
    "wof:name":"Jordan Park Elementary School of Extended Learning",
    "wof:placetype":"venue"
},
  "geometry": {"coordinates":[-93.298103,45.011398],"type":"Point"}
}