{
  "type": "Feature",
  "properties": {
    "addr:full":"528 Maceman St Winona MN 55987",
    "addr:housenumber":"528",
    "addr:postcode":"55987",
    "addr:street":"Maceman St",
    "iso:country":"US",
    "sg:address":"528 Maceman St",
    "sg:city":"Winona",
    "sg:classifiers":[
        {
            "category":"Real Estate",
            "subcategory":"Real Estate Operator",
            "type":"Services"
        }
    ],
    "sg:phone":"+1 507 452 2929",
    "sg:postcode":"55987",
    "sg:province":"MN",
    "sg:tags":[
        "building",
        "apartment"
    ],
    "wof:name":"Maceman Street Apartments",
    "wof:placetype":"venue"
},
  "geometry": {"coordinates":[-91.67756199999999,44.049627],"type":"Point"}
}