{
  "type": "Feature",
  "properties": {
    "iso:country":"US",
    "sg:address":"21701 John Deere Ln",
    "sg:city":"Rogers",
    "sg:classifiers":[
        {
            "category":"Insurance",
            "subcategory":"Hazard Insurance",
            "type":"Services"
        }
    ],
    "sg:phone":"+1 763 428 3595",
    "sg:postcode":"55374",
    "sg:province":"MN",
    "sg:tags":[
        "commercial",
        "business"
    ],
    "wof:name":"Allstate Peterbilt North",
    "wof:placetype":"venue"
},
  "geometry": {"coordinates":[-93.553421,45.19051],"type":"Point"}
}