{
  "type": "Feature",
  "properties": {
    "iso:country":"US",
    "sg:address":"515 Granite St",
    "sg:city":"Cloquet",
    "sg:classifiers":[
        {
            "category":"Social Services",
            "subcategory":"Child Care",
            "type":"Services"
        }
    ],
    "sg:phone":"+1 218 879 0929",
    "sg:postcode":"55720",
    "sg:province":"MN",
    "sg:tags":[
        "day"
    ],
    "wof:name":"Kids Crnr Schl Aged Child Care",
    "wof:placetype":"venue"
},
  "geometry": {"coordinates":[-92.46224100000001,46.733595],"type":"Point"}
}