{
  "type": "Feature",
  "properties": {
    "iso:country":"US",
    "sg:address":"1322 159th Ave NE",
    "sg:city":"Anoka",
    "sg:classifiers":[
        {
            "category":"Building & Trades",
            "subcategory":"Construction",
            "type":"Services"
        }
    ],
    "sg:phone":"+1 763 434 6371",
    "sg:postcode":"55304",
    "sg:province":"MN",
    "sg:tags":[
        "concrete",
        "masonry",
        "contractor"
    ],
    "wof:name":"Crosstown Masonry Inc",
    "wof:placetype":"venue"
},
  "geometry": {"coordinates":[-93.236951,45.259641],"type":"Point"}
}