{
  "type": "Feature",
  "properties": {
    "addr:full":"5901 Cedar Lake Rd S Minneapolis MN 55416",
    "addr:housenumber":"5901",
    "addr:postcode":"55416",
    "addr:street":"Cedar Lake Rd",
    "iso:country":"US",
    "sg:address":"5901 Cedar Lake Rd S",
    "sg:city":"Minneapolis",
    "sg:classifiers":[
        {
            "category":"Professional",
            "subcategory":"Lawyer & Legal Services",
            "type":"Services"
        }
    ],
    "sg:phone":"+1 952 544 5501",
    "sg:postcode":"55416",
    "sg:province":"MN",
    "sg:tags":[
        "personal",
        "attorney",
        "practice",
        "injury"
    ],
    "wof:name":"Love Brian J Atty",
    "wof:placetype":"venue"
},
  "geometry": {"coordinates":[-93.3554,44.965401],"type":"Point"}
}