{
  "type": "Feature",
  "properties": {
    "addr:full":"329 Main St S Austin MN 55912",
    "addr:housenumber":"329",
    "addr:postcode":"55912",
    "addr:street":"Main St S",
    "iso:country":"US",
    "sg:address":"329 Main St S",
    "sg:city":"Austin",
    "sg:classifiers":[
        {
            "category":"Insurance",
            "subcategory":"Insurance Agent",
            "type":"Services"
        }
    ],
    "sg:phone":"+1 507 437 4022",
    "sg:postcode":"55912",
    "sg:province":"MN",
    "wof:name":"New York Life",
    "wof:placetype":"venue"
},
  "geometry": {"coordinates":[-92.974791,43.664475],"type":"Point"}
}