{
  "type": "Feature",
  "properties": {
    "addr:full":"5066 Theater Ln NW Bemidji MN 56601",
    "addr:housenumber":"5066",
    "addr:postcode":"56601",
    "addr:street":"Theater Ln Nw",
    "iso:country":"US",
    "sg:address":"5066 Theater Ln NW",
    "sg:city":"Bemidji",
    "sg:classifiers":[
        {
            "category":"Real Estate",
            "subcategory":"Developer",
            "type":"Services"
        }
    ],
    "sg:phone":"+1 218 444 2897",
    "sg:postcode":"56601",
    "sg:province":"MN",
    "sg:tags":[
        "residential",
        "retail",
        "land"
    ],
    "wof:name":"Integrity Home Mortgage",
    "wof:placetype":"venue"
},
  "geometry": {"coordinates":[-94.95448500000001,47.506547],"type":"Point"}
}