{
  "type": "Feature",
  "properties": {
    "iso:country":"US",
    "sg:address":"13517 State Hwy 65",
    "sg:city":"Anoka",
    "sg:classifiers":[
        {
            "category":"Wholesale",
            "subcategory":"Motor Vehicles",
            "type":"Manufacturing & Wholesale Goods"
        }
    ],
    "sg:phone":"+1 763 772 0700",
    "sg:postcode":"55304",
    "sg:province":"MN",
    "wof:name":"Copart Inc",
    "wof:placetype":"venue"
},
  "geometry": {"coordinates":[-93.234697,45.218579],"type":"Point"}
}