{
  "type": "Feature",
  "properties": {
    "addr:full":"26581 Drew Ave Elko MN 55020",
    "addr:housenumber":"26581",
    "addr:postcode":"55020",
    "addr:street":"Drew Ave",
    "iso:country":"US",
    "sg:address":"26581 Drew Ave",
    "sg:city":"Elko",
    "sg:classifiers":[
        {
            "category":"Building & Trades",
            "subcategory":"Construction",
            "type":"Services"
        }
    ],
    "sg:phone":"+1 952 461 4174",
    "sg:postcode":"55020",
    "sg:province":"MN",
    "sg:tags":[
        "concrete",
        "contractor"
    ],
    "wof:name":"Sexton Concrete Masonry",
    "wof:placetype":"venue"
},
  "geometry": {"coordinates":[-93.326791,44.563545],"type":"Point"}
}