{
  "type": "Feature",
  "properties": {
    "addr:full":"21719 235th St Glenwood MN 56353",
    "addr:housenumber":"21719",
    "addr:postcode":"56353",
    "addr:street":"235Th St",
    "iso:country":"US",
    "sg:address":"21719 235th St",
    "sg:city":"Glenwood",
    "sg:classifiers":[
        {
            "category":"Building & Trades",
            "subcategory":"Plumbing",
            "type":"Services"
        }
    ],
    "sg:phone":"+1 320 634 4162",
    "sg:postcode":"56353",
    "sg:province":"MN",
    "sg:tags":[
        "tank",
        "septic"
    ],
    "wof:name":"Glacial Lakes Excavating Inc",
    "wof:placetype":"venue"
},
  "geometry": {"coordinates":[-93.685602,45.887607],"type":"Point"}
}