{
  "type": "Feature",
  "properties": {
    "addr:full":"6617 Lake Blvd Forest Lake MN 55025",
    "addr:housenumber":"6617",
    "addr:postcode":"55025",
    "addr:street":"Lake Blvd",
    "iso:country":"US",
    "sg:address":"6617 Lake Blvd",
    "sg:city":"Forest Lake",
    "sg:classifiers":[
        {
            "category":"Food & Beverages",
            "subcategory":"Groceries & Convenience Stores",
            "type":"Retail Goods"
        }
    ],
    "sg:phone":"+1 651 464 6573",
    "sg:postcode":"55025",
    "sg:province":"MN",
    "sg:website":"www.holidaystationstores.com",
    "wof:name":"Holiday Station Stores Inc",
    "wof:placetype":"venue"
},
  "geometry": {"coordinates":[-92.968549,45.302009],"type":"Point"}
}