{
  "type": "Feature",
  "properties": {
    "addr:full":"101 5th St SE Kasson MN 55944",
    "addr:housenumber":"101",
    "addr:postcode":"55944",
    "addr:street":"5Th St Se",
    "iso:country":"US",
    "sg:address":"101 5th St SE",
    "sg:city":"Kasson",
    "sg:classifiers":[
        {
            "category":"Building & Trades",
            "subcategory":"Construction",
            "type":"Services"
        }
    ],
    "sg:phone":"+1 507 634 6006",
    "sg:postcode":"55944",
    "sg:province":"MN",
    "sg:tags":[
        "insulation",
        "heat",
        "contractor"
    ],
    "wof:name":"Dave's Insulation",
    "wof:placetype":"venue"
},
  "geometry": {"coordinates":[-92.747485,44.025035],"type":"Point"}
}