{
  "type": "Feature",
  "properties": {
    "iso:country":"US",
    "sg:address":"18355 790th Ave",
    "sg:city":"Ostrander",
    "sg:classifiers":[
        {
            "category":"Farming",
            "subcategory":"Livestock Farm",
            "type":"Manufacturing & Wholesale Goods"
        }
    ],
    "sg:phone":"+1 507 657 2486",
    "sg:postcode":"55961",
    "sg:province":"MN",
    "sg:tags":[
        "beef",
        "feedlot",
        "cattle"
    ],
    "wof:name":"Drinkall Delvin",
    "wof:placetype":"venue"
},
  "geometry": {"coordinates":[-92.469403,43.617295],"type":"Point"}
}