{
  "type": "Feature",
  "properties": {
    "iso:country":"US",
    "sg:address":"1501 Northway Dr",
    "sg:city":"St Cloud",
    "sg:classifiers":[
        {
            "category":"Food & Beverages",
            "subcategory":"Groceries & Convenience Stores",
            "type":"Retail Goods"
        }
    ],
    "sg:phone":"+1 320 253 5063",
    "sg:postcode":"56303",
    "sg:province":"MN",
    "sg:tags":[
        "grocer"
    ],
    "wof:name":"Tom Thumb Food Market",
    "wof:placetype":"venue"
},
  "geometry": {"coordinates":[-94.18218899999999,45.57892],"type":"Point"}
}