{
  "type": "Feature",
  "properties": {
    "addr:full":"6697 Promontory Dr Eden Prairie MN 55346",
    "addr:housenumber":"6697",
    "addr:postcode":"55346",
    "addr:street":"Promontory Dr",
    "iso:country":"US",
    "sg:address":"6697 Promontory Dr",
    "sg:city":"Eden Prairie",
    "sg:classifiers":[
        {
            "category":"Insurance",
            "subcategory":"Insurance Agent",
            "type":"Services"
        }
    ],
    "sg:phone":"+1 612 868 7000",
    "sg:postcode":"55346",
    "sg:province":"MN",
    "wof:name":"Communication Consultants",
    "wof:placetype":"venue"
},
  "geometry": {"coordinates":[-93.44543299999999,44.883401],"type":"Point"}
}