{
  "type": "Feature",
  "properties": {
    "iso:country":"US",
    "sg:address":"10633 165th St W",
    "sg:city":"Lakeville",
    "sg:classifiers":[
        {
            "category":"Insurance",
            "subcategory":"Insurance Agent",
            "type":"Services"
        },
        {
            "category":"Insurance",
            "subcategory":"Hazard Insurance",
            "type":"Services"
        },
        {
            "category":"Insurance",
            "subcategory":"Title Insurance",
            "type":"Services"
        },
        {
            "category":"Insurance",
            "subcategory":"Life Insurance",
            "type":"Services"
        }
    ],
    "sg:phone":"+1 952 388 1600",
    "sg:postcode":"55044",
    "sg:province":"MN",
    "sg:tags":[
        "business",
        "auto",
        "commercial",
        "homeowner",
        "motorcycle",
        "renter"
    ],
    "wof:name":"Allstate Insurance Company - Dan Speegle",
    "wof:placetype":"venue"
},
  "geometry": {"coordinates":[-93.28085299999999,44.71022],"type":"Point"}
}