{
  "type": "Feature",
  "properties": {
    "iso:country":"US",
    "sg:address":"217 Tepeeotah Rd",
    "sg:city":"Tracy",
    "sg:classifiers":[
        {
            "category":"Real Estate",
            "subcategory":"Real Estate Agent",
            "type":"Services"
        }
    ],
    "sg:phone":"+1 507 829 5191",
    "sg:postcode":"56175",
    "sg:province":"MN",
    "wof:name":"Brasco Enterprises",
    "wof:placetype":"venue"
},
  "geometry": {"coordinates":[-95.680927,44.129317],"type":"Point"}
}