{
  "type": "Feature",
  "properties": {
    "iso:country":"US",
    "sg:address":"413 S Broadway",
    "sg:city":"Rochester",
    "sg:classifiers":[
        {
            "category":"Professional",
            "subcategory":"Business Services",
            "type":"Services"
        }
    ],
    "sg:phone":"+1 507 536 7969",
    "sg:postcode":"55904",
    "sg:province":"MN",
    "sg:tags":[
        "embroidery"
    ],
    "wof:name":"Blazing Needles",
    "wof:placetype":"venue"
},
  "geometry": {"coordinates":[-92.463216,44.017195],"type":"Point"}
}