{
  "type": "Feature",
  "properties": {
    "addr:full":"3552 134th Ave NW Anoka MN 55304",
    "addr:housenumber":"3552",
    "addr:postcode":"55304",
    "addr:street":"134Th Ave Nw",
    "iso:country":"US",
    "sg:address":"3552 134th Ave NW",
    "sg:city":"Anoka",
    "sg:classifiers":[
        {
            "category":"Wholesale",
            "subcategory":"Groceries",
            "type":"Manufacturing & Wholesale Goods"
        }
    ],
    "sg:phone":"+1 763 421 5552",
    "sg:postcode":"55304",
    "sg:province":"MN",
    "wof:name":"Alpha Enterprise Corporation",
    "wof:placetype":"venue"
},
  "geometry": {"coordinates":[-93.35621500000001,45.214205],"type":"Point"}
}