{
  "type": "Feature",
  "properties": {
    "iso:country":"US",
    "sg:address":"150 Lake St W",
    "sg:city":"Wayzata",
    "sg:classifiers":[
        {
            "category":"Professional",
            "type":"Services"
        }
    ],
    "sg:phone":"+1 952 404 1313",
    "sg:postcode":"55391",
    "sg:province":"MN",
    "sg:tags":[
        "establishment"
    ],
    "wof:name":"Irv Fish Office",
    "wof:placetype":"venue"
},
  "geometry": {"coordinates":[-93.524143,44.97056],"type":"Point"}
}