{
  "type": "Feature",
  "properties": {
    "addr:full":"1423 29th Avenue NE Minneapolis MN 55418",
    "addr:housenumber":"1423",
    "addr:postcode":"55418",
    "addr:street":"29Th Avenue Ne",
    "iso:country":"US",
    "sg:address":"1423 29th Avenue NE",
    "sg:city":"Minneapolis",
    "sg:phone":"+1 612 968 9484",
    "sg:postcode":"55418",
    "sg:province":"MN",
    "sg:website":"http://www.HumansWin.com",
    "wof:name":"Humans Win! Recording Studio",
    "wof:placetype":"venue"
},
  "geometry": {"coordinates":[-93.23937599999999,45.020433],"type":"Point"}
}