{
  "type": "Feature",
  "properties": {
    "iso:country":"US",
    "sg:address":"7350 Inwood Rd",
    "sg:city":"Cologne",
    "sg:classifiers":[
        {
            "category":"Farming",
            "subcategory":"Dairy Farm",
            "type":"Manufacturing & Wholesale Goods"
        }
    ],
    "sg:phone":"+1 952 448 4032",
    "sg:postcode":"55322",
    "sg:province":"MN",
    "wof:name":"Don Breeggemann",
    "wof:placetype":"venue"
},
  "geometry": {"coordinates":[-93.70605999999999,44.741563],"type":"Point"}
}