{
  "type": "Feature",
  "properties": {
    "addr:full":"10920 Kingsborough Ct S Cottage Grove MN 55016",
    "addr:housenumber":"10920",
    "addr:postcode":"55016",
    "addr:street":"Kingsborough Ct S Cottage Grove",
    "iso:country":"US",
    "sg:address":"10920 Kingsborough Ct S",
    "sg:city":"Cottage Grove",
    "sg:classifiers":[
        {
            "category":"Building & Trades",
            "subcategory":"Construction",
            "type":"Services"
        }
    ],
    "sg:phone":"+1 651 458 0868",
    "sg:postcode":"55016",
    "sg:province":"MN",
    "sg:tags":[
        "house"
    ],
    "wof:name":"Jenkins Mrgan Rsdential Design",
    "wof:placetype":"venue"
},
  "geometry": {"coordinates":[-92.892082,44.792714],"type":"Point"}
}