{
  "type": "Feature",
  "properties": {
    "addr:full":"6824 Dupont Ave N Minneapolis MN 55430",
    "addr:housenumber":"6824",
    "addr:postcode":"55430",
    "addr:street":"Dupont Ave N",
    "iso:country":"US",
    "sg:address":"6824 Dupont Ave N",
    "sg:city":"Minneapolis",
    "sg:classifiers":[
        {
            "category":"Utilities",
            "subcategory":"Telephone",
            "type":"Services"
        }
    ],
    "sg:phone":"+1 763 560 8842",
    "sg:postcode":"55430",
    "sg:province":"MN",
    "sg:tags":[
        "communications"
    ],
    "wof:name":"Sickure Systems Organization",
    "wof:placetype":"venue"
},
  "geometry": {"coordinates":[-93.29489599999999,45.077795],"type":"Point"}
}