{
  "type": "Feature",
  "properties": {
    "iso:country":"US",
    "sg:address":"4568 Schultz Rd",
    "sg:city":"Duluth",
    "sg:classifiers":[
        {
            "category":"Building & Trades",
            "subcategory":"Electrical",
            "type":"Services"
        }
    ],
    "sg:phone":"+1 218 721 3832",
    "sg:postcode":"55803",
    "sg:province":"MN",
    "sg:tags":[
        "electrical",
        "contractor"
    ],
    "wof:name":"Korkalo Electric",
    "wof:placetype":"venue"
},
  "geometry": {"coordinates":[-92.162024,46.923502],"type":"Point"}
}