{
  "type": "Feature",
  "properties": {
    "iso:country":"US",
    "sg:address":"190 E 5th St",
    "sg:city":"Saint Paul",
    "sg:classifiers":[
        {
            "category":"Professional",
            "subcategory":"Computer Services",
            "type":"Services"
        }
    ],
    "sg:phone":"+1 651 298 8111",
    "sg:postcode":"55101",
    "sg:province":"MN",
    "sg:tags":[
        "design",
        "system"
    ],
    "wof:name":"Zamba Corp",
    "wof:placetype":"venue"
},
  "geometry": {"coordinates":[-93.088792,44.948162],"type":"Point"}
}