{
  "type": "Feature",
  "properties": {
    "iso:country":"US",
    "sg:address":"9000 Penn Ave S",
    "sg:city":"Minneapolis",
    "sg:classifiers":[
        {
            "category":"Food & Beverages",
            "subcategory":"Groceries & Convenience Stores",
            "type":"Retail Goods"
        }
    ],
    "sg:phone":"+1 952 881 4738",
    "sg:postcode":"55431",
    "sg:province":"MN",
    "wof:name":"Premium Stop",
    "wof:placetype":"venue"
},
  "geometry": {"coordinates":[-93.308998,44.840199],"type":"Point"}
}