{
  "type": "Feature",
  "properties": {
    "iso:country":"US",
    "sg:address":"2275 McKnight Rd N",
    "sg:city":"Saint Paul",
    "sg:classifiers":[
        {
            "category":"Professional",
            "subcategory":"Employment Agencies",
            "type":"Services"
        }
    ],
    "sg:phone":"+1 651 777 7780",
    "sg:postcode":"55109",
    "sg:province":"MN",
    "sg:tags":[
        "operator",
        "supply",
        "help",
        "trucking"
    ],
    "wof:name":"Advanced Auto Transport Inc",
    "wof:placetype":"venue"
},
  "geometry": {"coordinates":[-93.005053,45.006696],"type":"Point"}
}