{
  "type": "Feature",
  "properties": {
    "addr:full":"1600 1st St S Willmar MN 56201",
    "addr:housenumber":"1600",
    "addr:postcode":"56201",
    "addr:street":"1St St S",
    "iso:country":"US",
    "sg:address":"1600 1st St S",
    "sg:city":"Willmar",
    "sg:classifiers":[
        {
            "category":"Shopping",
            "subcategory":"Pharmacy",
            "type":"Retail Goods"
        }
    ],
    "sg:phone":"+1 320 235 1930",
    "sg:postcode":"56201",
    "sg:province":"MN",
    "sg:tags":[
        "drug",
        "store"
    ],
    "wof:name":"Thrifty White Drug 22",
    "wof:placetype":"venue"
},
  "geometry": {"coordinates":[-95.04276,45.106919],"type":"Point"}
}