{
  "type": "Feature",
  "properties": {
    "addr:full":"116 Atlantic Ave Morris MN 56267",
    "addr:housenumber":"116",
    "addr:postcode":"56267",
    "addr:street":"Atlantic Ave",
    "iso:country":"US",
    "sg:address":"116 Atlantic Ave",
    "sg:city":"Morris",
    "sg:classifiers":[
        {
            "category":"Shopping",
            "subcategory":"Florist",
            "type":"Retail Goods"
        }
    ],
    "sg:phone":"+1 320 589 3344",
    "sg:postcode":"56267",
    "sg:province":"MN",
    "wof:name":"Morris Floral and Greenhouse",
    "wof:placetype":"venue"
},
  "geometry": {"coordinates":[-95.910826,45.58264],"type":"Point"}
}