{
  "type": "Feature",
  "properties": {
    "iso:country":"US",
    "sg:address":"1101 Center Ave W",
    "sg:city":"Dilworth",
    "sg:classifiers":[
        {
            "category":"Home & Garden",
            "subcategory":"Building Materials",
            "type":"Retail Goods"
        },
        {
            "category":"Manufacturing",
            "subcategory":"Building Materials",
            "type":"Manufacturing & Wholesale Goods"
        },
        {
            "category":"Home & Garden",
            "subcategory":"Carpets & Floor Coverings",
            "type":"Retail Goods"
        }
    ],
    "sg:phone":"+1 218 236 0747",
    "sg:postcode":"56529",
    "sg:province":"MN",
    "sg:tags":[
        "hardwood",
        "materials-wholesale",
        "rug",
        "manufacturer"
    ],
    "sg:website":"http://www.weivodacarpet.com",
    "wof:name":"Weivoda Carpet Sales",
    "wof:placetype":"venue"
},
  "geometry": {"coordinates":[-96.716171,46.87674],"type":"Point"}
}