{
  "type": "Feature",
  "properties": {
    "iso:country":"US",
    "sg:address":"1219 7th Ave",
    "sg:city":"Two Harbors",
    "sg:classifiers":[
        {
            "category":"Real Estate",
            "subcategory":"Real Estate Agent",
            "type":"Services"
        }
    ],
    "sg:phone":"+1 218 834 5050",
    "sg:postcode":"55616",
    "sg:province":"MN",
    "wof:name":"Superior 'N' Forest Real Est",
    "wof:placetype":"venue"
},
  "geometry": {"coordinates":[-91.68182299999999,47.025642],"type":"Point"}
}