{
  "type": "Feature",
  "properties": {
    "addr:full":"6059 Co Rd 11 NE Alexandria MN 56308",
    "addr:housenumber":"6059;11",
    "addr:postcode":"56308",
    "addr:street":"Co Rd;Ne",
    "iso:country":"US",
    "sg:address":"6059 Co Rd 11 NE",
    "sg:city":"Alexandria",
    "sg:classifiers":[
        {
            "category":"Building & Trades",
            "subcategory":"Construction",
            "type":"Services"
        }
    ],
    "sg:phone":"+1 320 808 7948",
    "sg:postcode":"56308",
    "sg:province":"MN",
    "sg:tags":[
        "general",
        "contractor"
    ],
    "wof:name":"Cavers Construction",
    "wof:placetype":"venue"
},
  "geometry": {"coordinates":[-95.376248,45.955281],"type":"Point"}
}