{
  "type": "Feature",
  "properties": {
    "addr:full":"1436 Valleyview Rd Chaska MN 55318",
    "addr:housenumber":"1436",
    "addr:postcode":"55318",
    "addr:street":"Valleyview Rd",
    "iso:country":"US",
    "sg:address":"1436 Valleyview Rd",
    "sg:city":"Chaska",
    "sg:classifiers":[
        {
            "category":"Social Services",
            "subcategory":"Child Care",
            "type":"Services"
        }
    ],
    "sg:phone":"+1 952 448 2116",
    "sg:postcode":"55318",
    "sg:province":"MN",
    "sg:tags":[
        "day"
    ],
    "wof:name":"Lenius Gwindolyn",
    "wof:placetype":"venue"
},
  "geometry": {"coordinates":[-93.59299,44.803437],"type":"Point"}
}