{
  "type": "Feature",
  "properties": {
    "addr:full":"23 E Ken Rue Ln Fairmont MN 56031",
    "addr:housenumber":"23",
    "addr:postcode":"56031",
    "addr:street":"E;Rue Ln",
    "iso:country":"US",
    "sg:address":"23 E Ken Rue Ln",
    "sg:city":"Fairmont",
    "sg:classifiers":[
        {
            "category":"Professional",
            "subcategory":"Business Services",
            "type":"Services"
        }
    ],
    "sg:phone":"+1 507 238 4138",
    "sg:postcode":"56031",
    "sg:province":"MN",
    "wof:name":"Schmidt Agency",
    "wof:placetype":"venue"
},
  "geometry": {"coordinates":[-94.443754,43.667876],"type":"Point"}
}