{
  "type": "Feature",
  "properties": {
    "addr:full":"2471 Angell Rd Saint Paul MN 55118",
    "addr:housenumber":"2471",
    "addr:postcode":"55118",
    "addr:street":"Angell Rd",
    "iso:country":"US",
    "sg:address":"2471 Angell Rd",
    "sg:city":"Saint Paul",
    "sg:classifiers":[
        {
            "category":"Professional",
            "subcategory":"Management & Consulting",
            "type":"Services"
        }
    ],
    "sg:phone":"+1 651 450 9900",
    "sg:postcode":"55118",
    "sg:province":"MN",
    "sg:tags":[
        "business"
    ],
    "wof:name":"Rhb Inc",
    "wof:placetype":"venue"
},
  "geometry": {"coordinates":[-93.09191300000001,44.880709],"type":"Point"}
}