{
  "type": "Feature",
  "properties": {
    "addr:full":"6809 Quantico Ln N Osseo MN 55311",
    "addr:housenumber":"6809",
    "addr:postcode":"55311",
    "addr:street":"Quantico Ln N",
    "iso:country":"US",
    "sg:address":"6809 Quantico Ln N",
    "sg:city":"Osseo",
    "sg:classifiers":[
        {
            "category":"Shopping",
            "subcategory":"Stationery & Office Supplies",
            "type":"Retail Goods"
        },
        {
            "category":"Manufacturing",
            "subcategory":"Paper Products",
            "type":"Manufacturing & Wholesale Goods"
        }
    ],
    "sg:phone":"+1 763 553 1702",
    "sg:postcode":"55311",
    "sg:province":"MN",
    "sg:tags":[
        "stationery-wholesale",
        "store",
        "manufacturer"
    ],
    "sg:website":"http://www.businessproductsandsolutions.com",
    "wof:name":"Business Products And Solutions",
    "wof:placetype":"venue"
},
  "geometry": {"coordinates":[-93.476271,45.078496],"type":"Point"}
}