{
  "type": "Feature",
  "properties": {
    "addr:full":"223 US Hwy 169 Elmore MN 56027",
    "addr:housenumber":"223",
    "addr:postcode":"56027",
    "addr:street":"Us Hwy 169",
    "iso:country":"US",
    "sg:address":"223 US Hwy 169",
    "sg:city":"Elmore",
    "sg:classifiers":[
        {
            "category":"Travel",
            "subcategory":"Hotels & Motels",
            "type":"Entertainment"
        }
    ],
    "sg:phone":"+1 507 943 3410",
    "sg:postcode":"56027",
    "sg:province":"MN",
    "sg:tags":[
        "operation",
        "business"
    ],
    "wof:name":"Hilltop Motel",
    "wof:placetype":"venue"
},
  "geometry": {"coordinates":[-94.088234,43.505548],"type":"Point"}
}