{
  "type": "Feature",
  "properties": {
    "addr:full":"600 W Railroad St Norwood MN 55368",
    "addr:housenumber":"600",
    "addr:postcode":"55368",
    "addr:street":"W Railroad St",
    "iso:country":"US",
    "sg:address":"600 W Railroad St",
    "sg:city":"Norwood",
    "sg:classifiers":[
        {
            "category":"Utilities",
            "subcategory":"Refuse",
            "type":"Services"
        }
    ],
    "sg:phone":"+1 952 467 2998",
    "sg:postcode":"55368",
    "sg:province":"MN",
    "sg:tags":[
        "system"
    ],
    "wof:name":"Waste Management",
    "wof:placetype":"venue"
},
  "geometry": {"coordinates":[-93.93281399999999,44.769681],"type":"Point"}
}