{
  "type": "Feature",
  "properties": {
    "addr:full":"205 5th St NW Saint Paul MN 55112",
    "addr:housenumber":"205",
    "addr:postcode":"55112",
    "addr:street":"5Th St Nw",
    "iso:country":"US",
    "sg:address":"205 5th St NW",
    "sg:city":"Saint Paul",
    "sg:classifiers":[
        {
            "category":"Arts & Performance",
            "subcategory":"Theater",
            "type":"Entertainment"
        }
    ],
    "sg:phone":"+1 612 879 8685",
    "sg:postcode":"55112",
    "sg:province":"MN",
    "sg:tags":[
        "group"
    ],
    "wof:name":"Brand New Very You Co St",
    "wof:placetype":"venue"
},
  "geometry": {"coordinates":[-93.190455,45.057446],"type":"Point"}
}