{
  "type": "Feature",
  "properties": {
    "addr:full":"21021 Heron Way Lakeville MN 55044",
    "addr:housenumber":"21021",
    "addr:postcode":"55044",
    "addr:street":"Heron Way",
    "iso:country":"US",
    "sg:address":"21021 Heron Way",
    "sg:city":"Lakeville",
    "sg:classifiers":[
        {
            "category":"Building & Trades",
            "subcategory":"Construction",
            "type":"Services"
        }
    ],
    "sg:phone":"+1 952 469 6904",
    "sg:postcode":"55044",
    "sg:province":"MN",
    "sg:tags":[
        "repairing",
        "house",
        "remodeling",
        "contractor"
    ],
    "wof:name":"American Remodeling Contractor",
    "wof:placetype":"venue"
},
  "geometry": {"coordinates":[-93.230312,44.644403],"type":"Point"}
}