{
  "type": "Feature",
  "properties": {
    "addr:full":"1021 15th Ave SE Rochester MN 55904",
    "addr:housenumber":"1021",
    "addr:postcode":"55904",
    "addr:street":"15Th Ave Se",
    "iso:country":"US",
    "sg:address":"1021 15th Ave SE",
    "sg:city":"Rochester",
    "sg:classifiers":[
        {
            "category":"Food & Beverages",
            "subcategory":"Liquor & Beverages",
            "type":"Retail Goods"
        }
    ],
    "sg:phone":"+1 507 289 3288",
    "sg:postcode":"55904",
    "sg:province":"MN",
    "sg:tags":[
        "alcoholic"
    ],
    "wof:name":"Bear Creek Liquor Store",
    "wof:placetype":"venue"
},
  "geometry": {"coordinates":[-92.443861,44.011045],"type":"Point"}
}