{
  "type": "Feature",
  "properties": {
    "iso:country":"US",
    "sg:address":"15114 Co Hwy 45",
    "sg:city":"South Haven",
    "sg:phone":"+1 320 236 7837",
    "sg:postcode":"55382",
    "sg:province":"MN",
    "sg:tags":[
        "farm",
        "field",
        "corn",
        "crop",
        "soybean"
    ],
    "wof:name":"Donald Rose",
    "wof:placetype":"venue"
},
  "geometry": {"coordinates":[-94.18076000000001,45.342635],"type":"Point"}
}