{
  "type": "Feature",
  "properties": {
    "addr:full":"105 W 23rd St Hastings MN 55033",
    "addr:housenumber":"105",
    "addr:postcode":"55033",
    "addr:street":"W 23Rd St",
    "iso:country":"US",
    "sg:address":"105 W 23rd St",
    "sg:city":"Hastings",
    "sg:classifiers":[
        {
            "category":"Professional",
            "type":"Services"
        }
    ],
    "sg:phone":"+1 651 438 8800",
    "sg:postcode":"55033",
    "sg:province":"MN",
    "sg:tags":[
        "establishment"
    ],
    "wof:name":"Twin Cities Global Connections",
    "wof:placetype":"venue"
},
  "geometry": {"coordinates":[-92.853095,44.72178],"type":"Point"}
}