{
  "type": "Feature",
  "properties": {
    "addr:full":"17003 County 9 Blvd Goodhue MN 55027",
    "addr:housenumber":"17003",
    "addr:postcode":"55027",
    "addr:street":"County 9 Blvd",
    "iso:country":"US",
    "sg:address":"17003 County 9 Blvd",
    "sg:city":"Goodhue",
    "sg:classifiers":[
        {
            "category":"Manufacturing",
            "subcategory":"Food",
            "type":"Manufacturing & Wholesale Goods"
        },
        {
            "category":"Farming",
            "subcategory":"Farm",
            "type":"Manufacturing & Wholesale Goods"
        }
    ],
    "sg:phone":"+1 651 923 4107",
    "sg:postcode":"55027",
    "sg:province":"MN",
    "sg:tags":[
        "corn",
        "product"
    ],
    "wof:name":"Arnie Stenlund",
    "wof:placetype":"venue"
},
  "geometry": {"coordinates":[-92.69889999999999,44.398373],"type":"Point"}
}