{
  "type": "Feature",
  "properties": {
    "iso:country":"US",
    "sg:address":"351 5th St",
    "sg:city":"Chandler",
    "sg:classifiers":[
        {
            "category":"Building & Trades",
            "subcategory":"Electrical",
            "type":"Services"
        }
    ],
    "sg:phone":"+1 507 677 2244",
    "sg:postcode":"56122",
    "sg:province":"MN",
    "sg:tags":[
        "electric",
        "contractor"
    ],
    "wof:name":"Valley Electric Of Chandler",
    "wof:placetype":"venue"
},
  "geometry": {"coordinates":[-95.94866500000001,43.934708],"type":"Point"}
}