{
  "type": "Feature",
  "properties": {
    "iso:country":"US",
    "sg:address":"2705 Bunker Lake Blvd NW Ste 202",
    "sg:city":"Andover",
    "sg:classifiers":[
        {
            "category":"Banks & Credit Unions",
            "subcategory":"Financial Services",
            "type":"Services"
        }
    ],
    "sg:phone":"+1 763 862 6000",
    "sg:postcode":"55304",
    "sg:province":"MN",
    "sg:tags":[
        "broker",
        "mortgage"
    ],
    "wof:name":"Advantage Processing",
    "wof:placetype":"venue"
},
  "geometry": {"coordinates":[-93.334541,45.219775],"type":"Point"}
}