{
  "type": "Feature",
  "properties": {
    "addr:full":"1001 S Pokegama Ave Grand Rapids MN 55744",
    "addr:housenumber":"1001",
    "addr:postcode":"55744",
    "addr:street":"S Pokegama Ave",
    "iso:country":"US",
    "sg:address":"1001 S Pokegama Ave",
    "sg:city":"Grand Rapids",
    "sg:classifiers":[
        {
            "category":"Real Estate",
            "subcategory":"Real Estate Agent",
            "type":"Services"
        }
    ],
    "sg:phone":"+1 218 326 8200",
    "sg:postcode":"55744",
    "sg:province":"MN",
    "wof:name":"Remax Thousand Lakes",
    "wof:placetype":"venue"
},
  "geometry": {"coordinates":[-93.5287,47.220099],"type":"Point"}
}