{
  "type": "Feature",
  "properties": {
    "addr:full":"1838 Olympic St Mora MN 55051",
    "addr:housenumber":"1838",
    "addr:postcode":"55051",
    "addr:street":"Olympic St",
    "iso:country":"US",
    "sg:address":"1838 Olympic St",
    "sg:city":"Mora",
    "sg:classifiers":[
        {
            "category":"Personal",
            "subcategory":"Beauty Salon",
            "type":"Services"
        }
    ],
    "sg:phone":"+1 320 679 0891",
    "sg:postcode":"55051",
    "sg:province":"MN",
    "sg:tags":[
        "shop"
    ],
    "wof:name":"Marys Bark & Beauty",
    "wof:placetype":"venue"
},
  "geometry": {"coordinates":[-93.225291,45.832671],"type":"Point"}
}