{
  "type": "Feature",
  "properties": {
    "iso:country":"US",
    "sg:address":"34102 320th St",
    "sg:city":"Climax",
    "sg:phone":"+1 218 281 2550",
    "sg:postcode":"56576",
    "sg:province":"MN",
    "sg:tags":[
        "farm",
        "grain",
        "wheat",
        "cash",
        "beet"
    ],
    "wof:name":"Dragseth Farms Inc",
    "wof:placetype":"venue"
},
  "geometry": {"coordinates":[-95.766451,46.425242],"type":"Point"}
}