{
  "type": "Feature",
  "properties": {
    "iso:country":"US",
    "sg:address":"3751 155th Ave NE",
    "sg:city":"Andover",
    "sg:classifiers":[
        {
            "category":"Professional",
            "subcategory":"Management & Consulting",
            "type":"Services"
        }
    ],
    "sg:phone":"+1 763 413 1733",
    "sg:postcode":"55304",
    "sg:province":"MN",
    "sg:tags":[
        "consultant",
        "business"
    ],
    "wof:name":"FRB Solutions",
    "wof:placetype":"venue"
},
  "geometry": {"coordinates":[-93.180814,45.250998],"type":"Point"}
}