{
  "type": "Feature",
  "properties": {
    "iso:country":"US",
    "sg:address":"12510 Fletcher Ln",
    "sg:city":"Rogers",
    "sg:classifiers":[
        {
            "category":"Manufacturing",
            "subcategory":"Metals",
            "type":"Manufacturing & Wholesale Goods"
        }
    ],
    "sg:phone":"+1 763 420 0233",
    "sg:postcode":"55374",
    "sg:province":"MN",
    "sg:tags":[
        "coating"
    ],
    "wof:name":"E2P LLC",
    "wof:placetype":"venue"
},
  "geometry": {"coordinates":[-93.54229599999999,45.18148],"type":"Point"}
}