{
  "type": "Feature",
  "properties": {
    "addr:full":"2600 E 81st St Bloomington MN 55425",
    "addr:housenumber":"2600",
    "addr:postcode":"55425",
    "addr:street":"E 81St St",
    "iso:country":"US",
    "sg:address":"2600 E 81st St",
    "sg:city":"Bloomington",
    "sg:classifiers":[
        {
            "category":"Freight",
            "type":"Transportation"
        },
        {
            "category":"Ferry",
            "type":"Transportation"
        }
    ],
    "sg:phone":"+1 952 854 4057",
    "sg:postcode":"55425",
    "sg:province":"MN",
    "sg:tags":[
        "company",
        "steamship",
        "arrangement"
    ],
    "wof:name":"Atlantic Container Line AB",
    "wof:placetype":"venue"
},
  "geometry": {"coordinates":[-93.23251999999999,44.856505],"type":"Point"}
}