{
  "type": "Feature",
  "properties": {
    "addr:full":"8023 121st Ln N Champlin MN 55316",
    "addr:housenumber":"8023",
    "addr:postcode":"55316",
    "addr:street":"121St Ln N",
    "iso:country":"US",
    "sg:address":"8023 121st Ln N",
    "sg:city":"Champlin",
    "sg:classifiers":[
        {
            "category":"Professional",
            "type":"Services"
        }
    ],
    "sg:phone":"+1 763 422 0416",
    "sg:postcode":"55316",
    "sg:province":"MN",
    "wof:name":"A Athena Charter Co",
    "wof:placetype":"venue"
},
  "geometry": {"coordinates":[-93.383522,45.173878],"type":"Point"}
}