{
  "type": "Feature",
  "properties": {
    "addr:full":"3582 Emerson Ave NW Maple Lake MN 55358",
    "addr:housenumber":"3582",
    "addr:postcode":"55358",
    "addr:street":"Emerson Ave Nw",
    "iso:country":"US",
    "sg:address":"3582 Emerson Ave NW",
    "sg:city":"Maple Lake",
    "sg:classifiers":[
        {
            "category":"Professional",
            "type":"Services"
        }
    ],
    "sg:phone":"+1 320 963 2232",
    "sg:postcode":"55358",
    "sg:province":"MN",
    "sg:tags":[
        "establishment"
    ],
    "wof:name":"RBRC",
    "wof:placetype":"venue"
},
  "geometry": {"coordinates":[-93.982827,45.204738],"type":"Point"}
}