{
  "type": "Feature",
  "properties": {
    "iso:country":"US",
    "sg:address":"319 Pintail St",
    "sg:city":"Mankato",
    "sg:classifiers":[
        {
            "category":"Retail",
            "subcategory":"Repair Shop",
            "type":"Services"
        }
    ],
    "sg:phone":"+1 507 387 3121",
    "sg:postcode":"56001",
    "sg:province":"MN",
    "sg:tags":[
        "welding"
    ],
    "wof:name":"Crawler Welding Inc",
    "wof:placetype":"venue"
},
  "geometry": {"coordinates":[-94.06405599999999,44.150607],"type":"Point"}
}