{
  "type": "Feature",
  "properties": {
    "iso:country":"US",
    "sg:address":"10587 Tagus Ave",
    "sg:city":"Brownton",
    "sg:classifiers":[
        {
            "category":"Farming",
            "subcategory":"Livestock Farm",
            "type":"Manufacturing & Wholesale Goods"
        }
    ],
    "sg:phone":"+1 320 328 5369",
    "sg:postcode":"55312",
    "sg:province":"MN",
    "sg:tags":[
        "bearing",
        "fur",
        "animal"
    ],
    "wof:name":"Petersen Fur Farm",
    "wof:placetype":"venue"
},
  "geometry": {"coordinates":[-94.396362,44.772277],"type":"Point"}
}