{
  "type": "Feature",
  "properties": {
    "addr:full":"30 6th St SW Pine City MN 55063",
    "addr:housenumber":"30",
    "addr:postcode":"55063",
    "addr:street":"6Th St Sw",
    "iso:country":"US",
    "sg:address":"30 6th St SW",
    "sg:city":"Pine City",
    "sg:classifiers":[
        {
            "category":"Wholesale",
            "subcategory":"Vending Machines",
            "type":"Manufacturing & Wholesale Goods"
        }
    ],
    "sg:phone":"+1 651 277 2653",
    "sg:postcode":"55063",
    "sg:province":"MN",
    "wof:name":"First Choice Food & Beverage",
    "wof:placetype":"venue"
},
  "geometry": {"coordinates":[-92.970426,45.829155],"type":"Point"}
}