{
  "type": "Feature",
  "properties": {
    "addr:full":"56387 220th St Austin MN 55912",
    "addr:housenumber":"56387",
    "addr:postcode":"55912",
    "addr:street":"220Th St",
    "iso:country":"US",
    "sg:address":"56387 220th St",
    "sg:city":"Austin",
    "sg:classifiers":[
        {
            "category":"Manufacturing",
            "subcategory":"Pet Food",
            "type":"Manufacturing & Wholesale Goods"
        }
    ],
    "sg:phone":"+1 507 437 3700",
    "sg:postcode":"55912",
    "sg:province":"MN",
    "sg:tags":[
        "feed",
        "mfg",
        "prepared"
    ],
    "wof:name":"Woodpecker Products Inc",
    "wof:placetype":"venue"
},
  "geometry": {"coordinates":[-92.921515,43.674121],"type":"Point"}
}