{
  "type": "Feature",
  "properties": {
    "iso:country":"US",
    "sg:address":"21731 715th Ave",
    "sg:city":"Albert Lea",
    "sg:classifiers":[
        {
            "category":"Professional",
            "type":"Services"
        }
    ],
    "sg:phone":"+1 507 377 7109",
    "sg:postcode":"56007",
    "sg:province":"MN",
    "wof:name":"Robert Killpack",
    "wof:placetype":"venue"
},
  "geometry": {"coordinates":[-93.43371500000001,43.660492],"type":"Point"}
}