{
  "type": "Feature",
  "properties": {
    "iso:country":"US",
    "sg:address":"617 S State St",
    "sg:city":"Fairmont",
    "sg:classifiers":[
        {
            "category":"Shopping",
            "subcategory":"Bicycles & Sporting Goods",
            "type":"Retail Goods"
        }
    ],
    "sg:phone":"+1 507 235 5004",
    "sg:postcode":"56031",
    "sg:province":"MN",
    "wof:name":"The Tee Box",
    "wof:placetype":"venue"
},
  "geometry": {"coordinates":[-94.447221,43.648025],"type":"Point"}
}