{
  "type": "Feature",
  "properties": {
    "addr:full":"2520 151st Ct W Rosemount MN 55068",
    "addr:housenumber":"2520",
    "addr:postcode":"55068",
    "addr:street":"151St Ct W",
    "iso:country":"US",
    "sg:address":"2520 151st Ct W",
    "sg:city":"Rosemount",
    "sg:classifiers":[
        {
            "category":"Communications",
            "type":"Services"
        },
        {
            "category":"Shopping",
            "subcategory":"Computers & Home Electronics",
            "type":"Retail Goods"
        }
    ],
    "sg:phone":"+1 651 423 6068",
    "sg:postcode":"55068",
    "sg:province":"MN",
    "sg:tags":[
        "sound",
        "television",
        "system",
        "equipment",
        "radio",
        "store"
    ],
    "wof:name":"Garrett Electronics",
    "wof:placetype":"venue"
},
  "geometry": {"coordinates":[-93.116895,44.730038],"type":"Point"}
}