{
  "type": "Feature",
  "properties": {
    "iso:country":"US",
    "sg:address":"106 Division St",
    "sg:city":"Waite Park",
    "sg:classifiers":[
        {
            "category":"Home & Garden",
            "subcategory":"Building Materials",
            "type":"Retail Goods"
        }
    ],
    "sg:phone":"+1 320 251 6620",
    "sg:postcode":"56387",
    "sg:province":"MN",
    "sg:tags":[
        "paint",
        "covering"
    ],
    "wof:name":"Sherwin-Williams Paints",
    "wof:placetype":"venue"
},
  "geometry": {"coordinates":[-94.21885899999999,45.553415],"type":"Point"}
}