{
  "type": "Feature",
  "properties": {
    "iso:country":"US",
    "sg:address":"14616 Afton Blvd S",
    "sg:city":"Afton",
    "sg:classifiers":[
        {
            "category":"Retail",
            "subcategory":"Auto Repair",
            "type":"Services"
        }
    ],
    "sg:phone":"+1 651 436 1346",
    "sg:postcode":"55001",
    "sg:province":"MN",
    "sg:tags":[
        "assembly",
        "board",
        "circuit"
    ],
    "sg:website":"http://www.rossdesigninc.com",
    "wof:name":"Ross Design Inc",
    "wof:placetype":"venue"
},
  "geometry": {"coordinates":[-92.808739,44.893478],"type":"Point"}
}