{
  "type": "Feature",
  "properties": {
    "iso:country":"US",
    "sg:address":"1845 Co Rd D E",
    "sg:city":"Maplewood",
    "sg:classifiers":[
        {
            "category":"Shopping",
            "subcategory":"Shoes",
            "type":"Retail Goods"
        }
    ],
    "sg:phone":"+1 651 779 0081",
    "sg:postcode":"55109",
    "sg:province":"MN",
    "wof:name":"Foot Ext",
    "wof:placetype":"venue"
},
  "geometry": {"coordinates":[-93.030581,45.035864],"type":"Point"}
}