{
  "type": "Feature",
  "properties": {
    "iso:country":"US",
    "sg:address":"7601 W 84th St",
    "sg:city":"Minneapolis",
    "sg:classifiers":[
        {
            "category":"Professional",
            "subcategory":"Management & Consulting",
            "type":"Services"
        }
    ],
    "sg:phone":"+1 952 943 8371",
    "sg:postcode":"55438",
    "sg:province":"MN",
    "wof:name":"Saxton Assoc",
    "wof:placetype":"venue"
},
  "geometry": {"coordinates":[-93.38254499999999,44.848934],"type":"Point"}
}