{
  "type": "Feature",
  "properties": {
    "iso:country":"US",
    "sg:address":"1700 Tullamore St",
    "sg:city":"Mankato",
    "sg:classifiers":[
        {
            "category":"Wholesale",
            "subcategory":"Farm Supplies",
            "type":"Manufacturing & Wholesale Goods"
        }
    ],
    "sg:phone":"+1 507 625 6151",
    "sg:postcode":"56001",
    "sg:province":"MN",
    "wof:name":"Tractor Supply Co",
    "wof:placetype":"venue"
},
  "geometry": {"coordinates":[-93.960516,44.16818],"type":"Point"}
}