{
  "type": "Feature",
  "properties": {
    "iso:country":"US",
    "sg:address":"4421 Abbott Ave S",
    "sg:city":"Minneapolis",
    "sg:classifiers":[
        {
            "category":"Wholesale",
            "subcategory":"Machinery & Supplies",
            "type":"Manufacturing & Wholesale Goods"
        }
    ],
    "sg:phone":"+1 952 882 9642",
    "sg:postcode":"55410",
    "sg:province":"MN",
    "sg:tags":[
        "industrial",
        "machinery-new",
        "equipment",
        "used",
        "supplies-wholesale"
    ],
    "wof:name":"Dayton Machine Products, Inc",
    "wof:placetype":"venue"
},
  "geometry": {"coordinates":[-93.32270699999999,44.922986],"type":"Point"}
}