{
  "type": "Feature",
  "properties": {
    "iso:country":"US",
    "sg:address":"6317 Welcome Ave N",
    "sg:city":"Brooklyn Park",
    "sg:classifiers":[
        {
            "category":"Retail",
            "subcategory":"Auto Repair",
            "type":"Services"
        }
    ],
    "sg:phone":"+1 763 537 3017",
    "sg:postcode":"55429",
    "sg:province":"MN",
    "sg:tags":[
        "clutches"
    ],
    "wof:name":"JPT Svc",
    "wof:placetype":"venue"
},
  "geometry": {"coordinates":[-93.351879,45.072528],"type":"Point"}
}