{
  "type": "Feature",
  "properties": {
    "iso:country":"US",
    "sg:address":"1611 Co Rd B W",
    "sg:city":"Roseville",
    "sg:classifiers":[
        {
            "category":"Professional",
            "subcategory":"Lawyer & Legal Services",
            "type":"Services"
        }
    ],
    "sg:phone":"+1 651 481 0177",
    "sg:postcode":"55113",
    "sg:province":"MN",
    "sg:tags":[
        "attorney"
    ],
    "wof:name":"Intelliware Int'l Law Firm",
    "wof:placetype":"venue"
},
  "geometry": {"coordinates":[-93.169099,45.006238],"type":"Point"}
}