{
  "type": "Feature",
  "properties": {
    "iso:country":"US",
    "sg:address":"2665 4th Ave Ste 105",
    "sg:city":"Anoka",
    "sg:classifiers":[
        {
            "category":"Shopping",
            "subcategory":"Hobbies, Toys, & Games",
            "type":"Retail Goods"
        }
    ],
    "sg:phone":"+1 763 506 0303",
    "sg:postcode":"55303",
    "sg:province":"MN",
    "sg:tags":[
        "shop",
        "hobby"
    ],
    "wof:name":"Village Games",
    "wof:placetype":"venue"
},
  "geometry": {"coordinates":[-93.385363,45.206028],"type":"Point"}
}