{
  "type": "Feature",
  "properties": {
    "iso:country":"US",
    "sg:address":"9116 Logan Ave S",
    "sg:city":"Bloomington",
    "sg:classifiers":[
        {
            "category":"Wholesale",
            "subcategory":"Machinery & Supplies",
            "type":"Manufacturing & Wholesale Goods"
        },
        {
            "category":"Manufacturing",
            "subcategory":"Printing",
            "type":"Manufacturing & Wholesale Goods"
        }
    ],
    "sg:phone":"+1 952 887 2751",
    "sg:postcode":"55431",
    "sg:province":"MN",
    "sg:tags":[
        "bookbinder",
        "bindery",
        "equipment"
    ],
    "wof:name":"Bindery Service Plus Inc",
    "wof:placetype":"venue"
},
  "geometry": {"coordinates":[-93.30359300000001,44.837677],"type":"Point"}
}