{
  "type": "Feature",
  "properties": {
    "iso:country":"US",
    "sg:address":"2400 Margaret St N",
    "sg:city":"Saint Paul",
    "sg:classifiers":[
        {
            "category":"Government",
            "subcategory":"Office",
            "type":"Public Place"
        }
    ],
    "sg:phone":"+1 651 770 4450",
    "sg:postcode":"55109",
    "sg:province":"MN",
    "sg:tags":[
        "executive"
    ],
    "wof:name":"North Saint Paul City of",
    "wof:placetype":"venue"
},
  "geometry": {"coordinates":[-92.99221799999999,45.014147],"type":"Point"}
}