{
  "type": "Feature",
  "properties": {
    "iso:country":"US",
    "sg:address":"4767 Sharon Ln",
    "sg:city":"Saint Paul",
    "sg:classifiers":[
        {
            "category":"Professional",
            "subcategory":"Business Services",
            "type":"Services"
        }
    ],
    "sg:phone":"+1 651 276 3300",
    "sg:postcode":"55110",
    "sg:province":"MN",
    "wof:name":"Elite Packaging",
    "wof:placetype":"venue"
},
  "geometry": {"coordinates":[-93.030592,45.087982],"type":"Point"}
}