{
  "type": "Feature",
  "properties": {
    "addr:full":"8623 Hwy 63 N Rochester MN 55906",
    "addr:housenumber":"8623",
    "addr:postcode":"55906",
    "addr:street":"Hwy 63 N",
    "iso:country":"US",
    "sg:address":"8623 Hwy 63 N",
    "sg:city":"Rochester",
    "sg:classifiers":[
        {
            "category":"Professional",
            "type":"Services"
        }
    ],
    "sg:phone":"+1 507 285 0798",
    "sg:postcode":"55906",
    "sg:province":"MN",
    "sg:tags":[
        "establishment"
    ],
    "wof:name":"Banitt & Banitt",
    "wof:placetype":"venue"
},
  "geometry": {"coordinates":[-92.418156,44.127476],"type":"Point"}
}