{
  "type": "Feature",
  "properties": {
    "addr:full":"11 S Marshall Ave Springfield MN 56087",
    "addr:housenumber":"11",
    "addr:postcode":"56087",
    "addr:street":"S Marshall Ave",
    "iso:country":"US",
    "sg:address":"11 S Marshall Ave",
    "sg:city":"Springfield",
    "sg:classifiers":[
        {
            "category":"Restaurant",
            "type":"Food & Drink"
        }
    ],
    "sg:phone":"+1 507 723 4716",
    "sg:postcode":"56087",
    "sg:province":"MN",
    "wof:name":"Ruby's Cafe",
    "wof:placetype":"venue"
},
  "geometry": {"coordinates":[-94.975892,44.238064],"type":"Point"}
}