{
  "type": "Feature",
  "properties": {
    "addr:full":"13476 Ferris Ave Saint Paul MN 55124",
    "addr:housenumber":"13476",
    "addr:postcode":"55124",
    "addr:street":"Ferris Ave",
    "iso:country":"US",
    "sg:address":"13476 Ferris Ave",
    "sg:city":"Saint Paul",
    "sg:classifiers":[
        {
            "category":"Professional",
            "subcategory":"Management & Consulting",
            "type":"Services"
        }
    ],
    "sg:phone":"+1 952 432 5430",
    "sg:postcode":"55124",
    "sg:province":"MN",
    "wof:name":"Applied Competitive Stratagies",
    "wof:placetype":"venue"
},
  "geometry": {"coordinates":[-93.190787,44.753966],"type":"Point"}
}