{
  "type": "Feature",
  "properties": {
    "iso:country":"US",
    "sg:address":"275 E 4th St",
    "sg:city":"Saint Paul",
    "sg:classifiers":[
        {
            "category":"Real Estate",
            "subcategory":"Architect",
            "type":"Services"
        }
    ],
    "sg:phone":"+1 651 222 5938",
    "sg:postcode":"55101",
    "sg:province":"MN",
    "sg:tags":[
        "architectural"
    ],
    "wof:name":"Jesse S Okie Art & Arch",
    "wof:placetype":"venue"
},
  "geometry": {"coordinates":[-93.085832,44.948619],"type":"Point"}
}