{
  "type": "Feature",
  "properties": {
    "addr:full":"6090 Ojibwa Rd Brainerd MN 56401",
    "addr:postcode":"6090;56401",
    "addr:street":"Ojibwa Rd",
    "iso:country":"US",
    "sg:address":"6090 Ojibwa Rd",
    "sg:city":"Brainerd",
    "sg:classifiers":[
        {
            "category":"Professional",
            "subcategory":"Engineering",
            "type":"Services"
        }
    ],
    "sg:phone":"+1 218 963 3158",
    "sg:postcode":"56401",
    "sg:province":"MN",
    "sg:tags":[
        "engineer",
        "integration",
        "system"
    ],
    "wof:name":"Charles Gorgensen",
    "wof:placetype":"venue"
},
  "geometry": {"coordinates":[-94.266366,46.45211],"type":"Point"}
}