{
  "type": "Feature",
  "properties": {
    "addr:full":"1518 13th St E Glencoe MN 55336",
    "addr:housenumber":"1518",
    "addr:postcode":"55336",
    "addr:street":"13Th St E",
    "iso:country":"US",
    "sg:address":"1518 13th St E",
    "sg:city":"Glencoe",
    "sg:classifiers":[
        {
            "category":"Retail",
            "subcategory":"Auto Repair",
            "type":"Services"
        }
    ],
    "sg:phone":"+1 320 864 3764",
    "sg:postcode":"55336",
    "sg:province":"MN",
    "sg:tags":[
        "repairing",
        "industrial",
        "mfg",
        "automobile",
        "general",
        "machinery"
    ],
    "wof:name":"Christensen's Auto Repair",
    "wof:placetype":"venue"
},
  "geometry": {"coordinates":[-94.14221000000001,44.772078],"type":"Point"}
}