{
  "type": "Feature",
  "properties": {
    "iso:country":"US",
    "sg:address":"16523 Klondike Rd",
    "sg:city":"Brownsville",
    "sg:classifiers":[
        {
            "category":"Farming",
            "subcategory":"Livestock Farm",
            "type":"Manufacturing & Wholesale Goods"
        }
    ],
    "sg:phone":"+1 507 542 4620",
    "sg:postcode":"55919",
    "sg:province":"MN",
    "sg:tags":[
        "hog",
        "or",
        "feedlot"
    ],
    "wof:name":"Wunnecka Eldora",
    "wof:placetype":"venue"
},
  "geometry": {"coordinates":[-91.297927,43.6091],"type":"Point"}
}