{
  "type": "Feature",
  "properties": {
    "addr:full":"13616 Pierce St NE Anoka MN 55304",
    "addr:housenumber":"13616",
    "addr:postcode":"55304",
    "addr:street":"Pierce St Ne",
    "iso:country":"US",
    "sg:address":"13616 Pierce St NE",
    "sg:city":"Anoka",
    "sg:classifiers":[
        {
            "category":"Building & Trades",
            "subcategory":"Construction",
            "type":"Services"
        }
    ],
    "sg:phone":"+1 763 767 1092",
    "sg:postcode":"55304",
    "sg:province":"MN",
    "sg:tags":[
        "commercial",
        "remodeling"
    ],
    "wof:name":"Domino GA Construction Inc",
    "wof:placetype":"venue"
},
  "geometry": {"coordinates":[-93.24089600000001,45.217616],"type":"Point"}
}