{
  "type": "Feature",
  "properties": {
    "iso:country":"US",
    "sg:address":"5452 Dupont Ave N",
    "sg:city":"Minneapolis",
    "sg:classifiers":[
        {
            "category":"Organizations",
            "subcategory":"Religious Organization",
            "type":"Services"
        }
    ],
    "sg:phone":"+1 763 566 2780",
    "sg:postcode":"55430",
    "sg:province":"MN",
    "wof:name":"Harron United Methodist Church",
    "wof:placetype":"venue"
},
  "geometry": {"coordinates":[-93.293904,45.053813],"type":"Point"}
}