{
  "type": "Feature",
  "properties": {
    "iso:country":"US",
    "sg:address":"49446 US 71",
    "sg:city":"Bemidji",
    "sg:classifiers":[
        {
            "category":"Personal",
            "subcategory":"Beauty Salon",
            "type":"Services"
        }
    ],
    "sg:phone":"+1 218 751 0057",
    "sg:postcode":"56601",
    "sg:province":"MN",
    "wof:name":"Terri's Nary Hairport",
    "wof:placetype":"venue"
},
  "geometry": {"coordinates":[-94.862951,47.37228],"type":"Point"}
}