{
  "type": "Feature",
  "properties": {
    "iso:country":"US",
    "sg:address":"14920 Maywood Dr",
    "sg:city":"Burnsville",
    "sg:classifiers":[
        {
            "category":"Shopping",
            "subcategory":"Computers & Home Electronics",
            "type":"Retail Goods"
        }
    ],
    "sg:phone":"+1 952 997 2384",
    "sg:postcode":"55306",
    "sg:province":"MN",
    "wof:name":"Hr Web Works",
    "wof:placetype":"venue"
},
  "geometry": {"coordinates":[-93.259342,44.733611],"type":"Point"}
}