{
  "type": "Feature",
  "properties": {
    "addr:full":"4850 Mayer Ave NE St Michael MN 55376",
    "addr:housenumber":"4850",
    "addr:postcode":"55376",
    "addr:street":"Mayer Ave Ne St",
    "iso:country":"US",
    "sg:address":"4850 Mayer Ave NE",
    "sg:city":"St Michael",
    "sg:classifiers":[
        {
            "category":"Professional",
            "type":"Services"
        }
    ],
    "sg:phone":"+1 763 493 3413",
    "sg:postcode":"55376",
    "sg:province":"MN",
    "sg:tags":[
        "establishment"
    ],
    "wof:name":"J A Mc Donald & Assoc Inc",
    "wof:placetype":"venue"
},
  "geometry": {"coordinates":[-93.632617,45.222517],"type":"Point"}
}