{
  "type": "Feature",
  "properties": {
    "iso:country":"US",
    "sg:address":"627 Belgrade Ave",
    "sg:city":"Mankato",
    "sg:classifiers":[
        {
            "category":"Professional",
            "subcategory":"Art Services",
            "type":"Services"
        }
    ],
    "sg:phone":"+1 507 388 5817",
    "sg:postcode":"56003",
    "sg:province":"MN",
    "sg:tags":[
        "commercial",
        "photography",
        "graphic",
        "design",
        "designer"
    ],
    "wof:name":"Franchise Graphics and Photogr",
    "wof:placetype":"venue"
},
  "geometry": {"coordinates":[-94.0168,44.16996],"type":"Point"}
}