{
  "type": "Feature",
  "properties": {
    "iso:country":"US",
    "sg:address":"8309 Penn Ave N",
    "sg:city":"Minneapolis",
    "sg:classifiers":[
        {
            "category":"Real Estate",
            "subcategory":"Real Estate Agent",
            "type":"Services"
        }
    ],
    "sg:phone":"+1 763 566 2709",
    "sg:postcode":"55444",
    "sg:province":"MN",
    "wof:name":"Jkcts Real Estate Co LLC",
    "wof:placetype":"venue"
},
  "geometry": {"coordinates":[-93.309844,45.106261],"type":"Point"}
}