{
  "type": "Feature",
  "properties": {
    "iso:country":"US",
    "sg:address":"1600 69th Ave N",
    "sg:city":"Minneapolis",
    "sg:classifiers":[
        {
            "category":"Building & Trades",
            "subcategory":"Construction",
            "type":"Services"
        }
    ],
    "sg:phone":"+1 612 685 3653",
    "sg:postcode":"55430",
    "sg:province":"MN",
    "sg:tags":[
        "contractor"
    ],
    "wof:name":"C & C Cable Contracting",
    "wof:placetype":"venue"
},
  "geometry": {"coordinates":[-93.30523599999999,45.080115],"type":"Point"}
}