{
  "type": "Feature",
  "properties": {
    "iso:country":"US",
    "sg:address":"111 E Jefferson St",
    "sg:city":"Spring Valley",
    "sg:classifiers":[
        {
            "category":"Insurance",
            "subcategory":"Insurance Agent",
            "type":"Services"
        }
    ],
    "sg:phone":"+1 507 346 7646",
    "sg:postcode":"55975",
    "sg:province":"MN",
    "wof:name":"Marburger Insurance Svc",
    "wof:placetype":"venue"
},
  "geometry": {"coordinates":[-92.38968,43.688779],"type":"Point"}
}