{
  "type": "Feature",
  "properties": {
    "iso:country":"US",
    "sg:address":"2530 Edgcumbe Rd",
    "sg:city":"St Paul",
    "sg:classifiers":[
        {
            "category":"Government",
            "subcategory":"Fire Station",
            "type":"Public Place"
        }
    ],
    "sg:phone":"+1 651 699 2504",
    "sg:postcode":"55116",
    "sg:province":"MN",
    "sg:tags":[
        "department"
    ],
    "wof:name":"St Paul Fire Station Res",
    "wof:placetype":"venue"
},
  "geometry": {"coordinates":[-93.177126,44.903494],"type":"Point"}
}