{
  "type": "Feature",
  "properties": {
    "iso:country":"US",
    "sg:address":"1200 Bridgeport Ln NW",
    "sg:city":"Alexandria",
    "sg:classifiers":[
        {
            "category":"Social Services",
            "subcategory":"Child Care",
            "type":"Services"
        }
    ],
    "sg:phone":"+1 320 762 1946",
    "sg:postcode":"56308",
    "sg:province":"MN",
    "sg:tags":[
        "day",
        "provider"
    ],
    "wof:name":"Janell M Gronholz",
    "wof:placetype":"venue"
},
  "geometry": {"coordinates":[-95.39643100000001,45.904616],"type":"Point"}
}