{
  "type": "Feature",
  "properties": {
    "addr:full":"653 Galtier St St Paul MN 55103",
    "addr:housenumber":"653",
    "addr:postcode":"55103",
    "addr:street":"Galtier St",
    "iso:country":"US",
    "sg:address":"653 Galtier St",
    "sg:city":"St Paul",
    "sg:classifiers":[
        {
            "category":"Shopping",
            "subcategory":"Gifts & Souvenirs",
            "type":"Retail Goods"
        }
    ],
    "sg:phone":"+1 651 489 3279",
    "sg:postcode":"55103",
    "sg:province":"MN",
    "sg:tags":[
        "shop"
    ],
    "wof:name":"Moxie Box",
    "wof:placetype":"venue"
},
  "geometry": {"coordinates":[-93.11067300000001,44.961174],"type":"Point"}
}