{
  "type": "Feature",
  "properties": {
    "addr:full":"2708 Bridge Ave Albert Lea MN 56007",
    "addr:housenumber":"2708",
    "addr:postcode":"56007",
    "addr:street":"Bridge Ave",
    "iso:country":"US",
    "sg:address":"2708 Bridge Ave",
    "sg:city":"Albert Lea",
    "sg:classifiers":[
        {
            "category":"Banks & Credit Unions",
            "subcategory":"Bank",
            "type":"Services"
        }
    ],
    "sg:phone":"+1 507 377 5002",
    "sg:postcode":"56007",
    "sg:province":"MN",
    "wof:name":"Associated Bank",
    "wof:placetype":"venue"
},
  "geometry": {"coordinates":[-93.358861,43.685626],"type":"Point"}
}