{
  "type": "Feature",
  "properties": {
    "iso:country":"US",
    "sg:address":"38168 248th St",
    "sg:city":"Arlington",
    "sg:phone":"+1 507 964 5629",
    "sg:postcode":"55307",
    "sg:province":"MN",
    "sg:tags":[
        "farm",
        "grain",
        "cash"
    ],
    "wof:name":"Bruce Lilienthal",
    "wof:placetype":"venue"
},
  "geometry": {"coordinates":[-94.031154,44.590446],"type":"Point"}
}