{
  "type": "Feature",
  "properties": {
    "addr:full":"709 11th Ave N Saint James MN 56081",
    "addr:housenumber":"709",
    "addr:postcode":"56081",
    "addr:street":"11Th Ave N",
    "iso:country":"US",
    "sg:address":"709 11th Ave N",
    "sg:city":"Saint James",
    "sg:classifiers":[
        {
            "category":"Social Services",
            "subcategory":"Child Care",
            "type":"Services"
        }
    ],
    "sg:phone":"+1 507 375 7195",
    "sg:postcode":"56081",
    "sg:province":"MN",
    "sg:tags":[
        "daycare",
        "provider"
    ],
    "wof:name":"Lori Schiller",
    "wof:placetype":"venue"
},
  "geometry": {"coordinates":[-94.629626,43.992001],"type":"Point"}
}