{
  "type": "Feature",
  "properties": {
    "addr:full":"539 Lake St E Wayzata MN 55391",
    "addr:housenumber":"539",
    "addr:postcode":"55391",
    "addr:street":"Lake St E",
    "iso:country":"US",
    "sg:address":"539 Lake St E",
    "sg:city":"Wayzata",
    "sg:classifiers":[
        {
            "category":"Professional",
            "subcategory":"Management & Consulting",
            "type":"Services"
        }
    ],
    "sg:phone":"+1 952 404 8060",
    "sg:postcode":"55391",
    "sg:province":"MN",
    "sg:tags":[
        "firm",
        "search",
        "executive",
        "employment"
    ],
    "wof:name":"Andcor Human Resources",
    "wof:placetype":"venue"
},
  "geometry": {"coordinates":[-93.51398399999999,44.969794],"type":"Point"}
}