{
  "type": "Feature",
  "properties": {
    "addr:full":"911 Hennepin Ave N Glencoe MN 55336",
    "addr:housenumber":"911",
    "addr:postcode":"55336",
    "addr:street":"Hennepin Ave N",
    "iso:country":"US",
    "sg:address":"911 Hennepin Ave N",
    "sg:city":"Glencoe",
    "sg:classifiers":[
        {
            "category":"Social Services",
            "type":"Services"
        }
    ],
    "sg:phone":"+1 320 864 3950",
    "sg:postcode":"55336",
    "sg:province":"MN",
    "sg:tags":[
        "counseling"
    ],
    "wof:name":"Family Counseling Svc",
    "wof:placetype":"venue"
},
  "geometry": {"coordinates":[-94.151794,44.768966],"type":"Point"}
}