{
  "type": "Feature",
  "properties": {
    "addr:full":"400 S Broadway Ave Rochester MN 55904",
    "addr:housenumber":"400",
    "addr:postcode":"55904",
    "addr:street":"S Broadway Ave",
    "iso:country":"US",
    "sg:address":"400 S Broadway Ave",
    "sg:city":"Rochester",
    "sg:classifiers":[
        {
            "category":"Professional",
            "subcategory":"Employment Agencies",
            "type":"Services"
        }
    ],
    "sg:phone":"+1 507 536 7130",
    "sg:postcode":"55904",
    "sg:province":"MN",
    "sg:tags":[
        "opportunity"
    ],
    "wof:name":"Aerotek",
    "wof:placetype":"venue"
},
  "geometry": {"coordinates":[-92.46314,44.01706],"type":"Point"}
}