{
  "type": "Feature",
  "properties": {
    "addr:full":"527 Marquette Ave # 1640 Minneapolis MN 55402",
    "addr:housenumber":"527",
    "addr:postcode":"55402",
    "addr:street":"Marquette Ave # 1640",
    "iso:country":"US",
    "sg:address":"527 Marquette Ave # 1640",
    "sg:city":"Minneapolis",
    "sg:classifiers":[
        {
            "category":"Professional",
            "subcategory":"Lawyer & Legal Services",
            "type":"Services"
        }
    ],
    "sg:phone":"+1 612 339 4139",
    "sg:postcode":"55402",
    "sg:province":"MN",
    "sg:tags":[
        "attorney",
        "practice"
    ],
    "wof:name":"Petricka Law Firm",
    "wof:placetype":"venue"
},
  "geometry": {"coordinates":[-93.269515,44.977969],"type":"Point"}
}