{
  "type": "Feature",
  "properties": {
    "iso:country":"US",
    "sg:address":"12718 Co Rd 128 NE",
    "sg:city":"Rochester",
    "sg:phone":"+1 507 753 2324",
    "sg:postcode":"55906",
    "sg:province":"MN",
    "sg:tags":[
        "farm",
        "hog",
        "corn",
        "or",
        "feedlot"
    ],
    "wof:name":"William Wagner",
    "wof:placetype":"venue"
},
  "geometry": {"coordinates":[-92.379058,44.183821],"type":"Point"}
}