{
  "type": "Feature",
  "properties": {
    "iso:country":"US",
    "sg:address":"18016 Bluebird St NW",
    "sg:city":"Anoka",
    "sg:classifiers":[
        {
            "category":"Professional",
            "subcategory":"Business Services",
            "type":"Services"
        }
    ],
    "sg:phone":"+1 763 323 7577",
    "sg:postcode":"55304",
    "sg:province":"MN",
    "wof:name":"Quality Surplus LLC",
    "wof:placetype":"venue"
},
  "geometry": {"coordinates":[-93.299176,45.296433],"type":"Point"}
}