{
  "type": "Feature",
  "properties": {
    "iso:country":"US",
    "sg:address":"19736 State 34",
    "sg:city":"Park Rapids",
    "sg:classifiers":[
        {
            "category":"Home & Garden",
            "subcategory":"Carpets & Floor Coverings",
            "type":"Retail Goods"
        }
    ],
    "sg:phone":"+1 218 732 8201",
    "sg:postcode":"56470",
    "sg:province":"MN",
    "sg:tags":[
        "dealer",
        "rug"
    ],
    "wof:name":"Lakeside Carpet Inc",
    "wof:placetype":"venue"
},
  "geometry": {"coordinates":[-94.957684,46.936284],"type":"Point"}
}