{
  "type": "Feature",
  "properties": {
    "iso:country":"US",
    "sg:address":"4159 Grand Ave S",
    "sg:city":"Minneapolis",
    "sg:classifiers":[
        {
            "category":"Real Estate",
            "subcategory":"Architect",
            "type":"Services"
        }
    ],
    "sg:phone":"+1 612 822 8200",
    "sg:postcode":"55409",
    "sg:province":"MN",
    "sg:website":"www.sagatarchitects.com",
    "wof:name":"Sagat Architects",
    "wof:placetype":"venue"
},
  "geometry": {"coordinates":[-93.28420300000001,44.927101],"type":"Point"}
}