{
  "type": "Feature",
  "properties": {
    "addr:full":"127 Main St N Chatfield MN 55923",
    "addr:housenumber":"127",
    "addr:postcode":"55923",
    "addr:street":"Main St N",
    "iso:country":"US",
    "sg:address":"127 Main St N",
    "sg:city":"Chatfield",
    "sg:classifiers":[
        {
            "category":"Social Services",
            "subcategory":"Child Care",
            "type":"Services"
        }
    ],
    "sg:phone":"+1 507 867 3895",
    "sg:postcode":"55923",
    "sg:province":"MN",
    "sg:tags":[
        "day",
        "provider"
    ],
    "wof:name":"Norma J Gathje",
    "wof:placetype":"venue"
},
  "geometry": {"coordinates":[-92.192347,43.848325],"type":"Point"}
}