{
  "type": "Feature",
  "properties": {
    "iso:country":"US",
    "sg:address":"166 E 8th St",
    "sg:city":"St Paul",
    "sg:classifiers":[
        {
            "category":"Retail",
            "subcategory":"Auto Rental",
            "type":"Services"
        }
    ],
    "sg:phone":"+1 651 846 2212",
    "sg:postcode":"55101",
    "sg:province":"MN",
    "sg:tags":[
        "renting",
        "automobile"
    ],
    "wof:name":"Budget Rent A Car",
    "wof:placetype":"venue"
},
  "geometry": {"coordinates":[-93.089291,44.951434],"type":"Point"}
}