{
  "type": "Feature",
  "properties": {
    "iso:country":"US",
    "sg:address":"111 6th Ave SE",
    "sg:city":"Roseau",
    "sg:classifiers":[
        {
            "category":"Social Services",
            "subcategory":"Child Care",
            "type":"Services"
        }
    ],
    "sg:phone":"+1 218 463 3760",
    "sg:postcode":"56751",
    "sg:province":"MN",
    "sg:tags":[
        "day"
    ],
    "wof:name":"Lynn M Kvidt",
    "wof:placetype":"venue"
},
  "geometry": {"coordinates":[-95.75504100000001,48.846112],"type":"Point"}
}