{
  "type": "Feature",
  "properties": {
    "addr:full":"5317 Lyndale Ave S Minneapolis MN 55419",
    "addr:housenumber":"5317",
    "addr:postcode":"55419",
    "addr:street":"Lyndale Ave S",
    "iso:country":"US",
    "sg:address":"5317 Lyndale Ave S",
    "sg:city":"Minneapolis",
    "sg:classifiers":[
        {
            "category":"Restaurant",
            "type":"Food & Drink"
        }
    ],
    "sg:phone":"+1 612 824 4877",
    "sg:postcode":"55419",
    "sg:province":"MN",
    "wof:name":"Subway Sandwiches & Salads",
    "wof:placetype":"venue"
},
  "geometry": {"coordinates":[-93.28821600000001,44.905316],"type":"Point"}
}