{
  "type": "Feature",
  "properties": {
    "iso:country":"US",
    "sg:address":"464 S Hamline Ave",
    "sg:city":"St Paul",
    "sg:classifiers":[
        {
            "category":"Professional",
            "subcategory":"Lawyer & Legal Services",
            "type":"Services"
        }
    ],
    "sg:phone":"+1 651 699 5038",
    "sg:postcode":"55105",
    "sg:province":"MN",
    "sg:tags":[
        "attorney"
    ],
    "wof:name":"Evening & Weekend Law Offices",
    "wof:placetype":"venue"
},
  "geometry": {"coordinates":[-93.156763,44.927352],"type":"Point"}
}