{
  "type": "Feature",
  "properties": {
    "addr:full":"7475 Brooklyn Blvd Minneapolis MN 55443",
    "addr:housenumber":"7475",
    "addr:postcode":"55443",
    "addr:street":"Brooklyn Blvd",
    "iso:country":"US",
    "sg:address":"7475 Brooklyn Blvd",
    "sg:city":"Minneapolis",
    "sg:classifiers":[
        {
            "category":"Organizations",
            "subcategory":"Non-profit Organization",
            "type":"Services"
        }
    ],
    "sg:phone":"+1 763 560 1347",
    "sg:postcode":"55443",
    "sg:province":"MN",
    "sg:website":"www.liberiabuiltproject.org",
    "wof:name":"Liberia Built Project Non Prft",
    "wof:placetype":"venue"
},
  "geometry": {"coordinates":[-93.34926400000001,45.089838],"type":"Point"}
}