{
  "type": "Feature",
  "properties": {
    "addr:full":"625 E Nicollet Blvd Burnsville MN 55337",
    "addr:housenumber":"625",
    "addr:postcode":"55337",
    "addr:street":"E Nicollet Blvd",
    "iso:country":"US",
    "sg:address":"625 E Nicollet Blvd",
    "sg:city":"Burnsville",
    "sg:classifiers":[
        {
            "category":"Health Services",
            "subcategory":"Doctor",
            "type":"Services"
        }
    ],
    "sg:phone":"+1 952 435 0303",
    "sg:postcode":"55337",
    "sg:province":"MN",
    "sg:tags":[
        "practice",
        "family"
    ],
    "wof:name":"Scherf Laura MD",
    "wof:placetype":"venue"
},
  "geometry": {"coordinates":[-93.270798,44.750099],"type":"Point"}
}