{
  "type": "Feature",
  "properties": {
    "addr:full":"20157 170th St Big Lake MN 55309",
    "addr:housenumber":"20157",
    "addr:postcode":"55309",
    "addr:street":"170Th St",
    "iso:country":"US",
    "sg:address":"20157 170th St",
    "sg:city":"Big Lake",
    "sg:classifiers":[
        {
            "category":"Building & Trades",
            "subcategory":"Construction",
            "type":"Services"
        }
    ],
    "sg:phone":"+1 763 263 2210",
    "sg:postcode":"55309",
    "sg:province":"MN",
    "sg:tags":[
        "contractor"
    ],
    "wof:name":"Don Deuel Construction",
    "wof:placetype":"venue"
},
  "geometry": {"coordinates":[-93.700232,45.339652],"type":"Point"}
}