{
  "type": "Feature",
  "properties": {
    "iso:country":"US",
    "sg:address":"2480 Fairview Ave N",
    "sg:city":"Saint Paul",
    "sg:classifiers":[
        {
            "category":"Shopping",
            "subcategory":"News",
            "type":"Retail Goods"
        }
    ],
    "sg:phone":"+1 651 639 0640",
    "sg:postcode":"55113",
    "sg:province":"MN",
    "sg:tags":[
        "newsstand"
    ],
    "wof:name":"Shinders New Bks Cmics Spt Cds",
    "wof:placetype":"venue"
},
  "geometry": {"coordinates":[-93.177144,45.015113],"type":"Point"}
}