{
  "type": "Feature",
  "properties": {
    "iso:country":"US",
    "sg:address":"7800 Maple Hill Rd",
    "sg:city":"Hamel",
    "sg:classifiers":[
        {
            "category":"Real Estate",
            "subcategory":"Real Estate Operator",
            "type":"Services"
        }
    ],
    "sg:phone":"+1 763 420 3679",
    "sg:postcode":"55340",
    "sg:province":"MN",
    "sg:tags":[
        "mobile",
        "home",
        "site",
        "community"
    ],
    "wof:name":"Maple Hill Estates",
    "wof:placetype":"venue"
},
  "geometry": {"coordinates":[-93.534819,45.099812],"type":"Point"}
}