{
  "type": "Feature",
  "properties": {
    "addr:full":"2450 Wilshire Blvd Mound MN 55364",
    "addr:housenumber":"2450",
    "addr:postcode":"55364",
    "addr:street":"Wilshire Blvd",
    "iso:country":"US",
    "sg:address":"2450 Wilshire Blvd",
    "sg:city":"Mound",
    "sg:classifiers":[
        {
            "category":"Education",
            "subcategory":"School",
            "type":"Public Place"
        }
    ],
    "sg:phone":"+1 952 491 8007",
    "sg:postcode":"55364",
    "sg:province":"MN",
    "wof:name":"Westonka Public School Dist",
    "wof:placetype":"venue"
},
  "geometry": {"coordinates":[-93.65787,44.93432],"type":"Point"}
}