{
  "type": "Feature",
  "properties": {
    "iso:country":"US",
    "sg:address":"815 Forest Ave",
    "sg:city":"Northfield",
    "sg:classifiers":[
        {
            "category":"Travel",
            "subcategory":"Bed & Breakfast",
            "type":"Entertainment"
        }
    ],
    "sg:phone":"+1 507 664 8845",
    "sg:postcode":"55057",
    "sg:province":"MN",
    "sg:tags":[
        "house"
    ],
    "wof:name":"Fellowship Residence",
    "wof:placetype":"venue"
},
  "geometry": {"coordinates":[-93.171271,44.456954],"type":"Point"}
}