{
  "type": "Feature",
  "properties": {
    "addr:full":"24235 Langford Ave Jordan MN 55352",
    "addr:postcode":"24235;55352",
    "addr:street":"Langford Ave",
    "iso:country":"US",
    "sg:address":"24235 Langford Ave",
    "sg:city":"Jordan",
    "sg:classifiers":[
        {
            "category":"Farming",
            "subcategory":"Livestock Farm",
            "type":"Manufacturing & Wholesale Goods"
        }
    ],
    "sg:phone":"+1 952 492 3320",
    "sg:postcode":"55352",
    "sg:province":"MN",
    "sg:tags":[
        "hog",
        "or",
        "feedlot"
    ],
    "wof:name":"Ronald Bastyr",
    "wof:placetype":"venue"
},
  "geometry": {"coordinates":[-93.50675099999999,44.590879],"type":"Point"}
}