{
  "type": "Feature",
  "properties": {
    "iso:country":"US",
    "sg:address":"2534 18th Ave",
    "sg:city":"Saint Paul",
    "sg:classifiers":[
        {
            "category":"Professional",
            "subcategory":"Lawyer & Legal Services",
            "type":"Services"
        }
    ],
    "sg:phone":"+1 651 779 4175",
    "sg:postcode":"55109",
    "sg:province":"MN",
    "sg:tags":[
        "document",
        "processing"
    ],
    "wof:name":"Anitas Prof Document Svc",
    "wof:placetype":"venue"
},
  "geometry": {"coordinates":[-92.993319,45.021997],"type":"Point"}
}