{
  "type": "Feature",
  "properties": {
    "addr:full":"3136 Donnelly Dr NW Maple Lake MN 55358",
    "addr:housenumber":"3136",
    "addr:postcode":"55358",
    "addr:street":"Donnelly Dr Nw",
    "iso:country":"US",
    "sg:address":"3136 Donnelly Dr NW",
    "sg:city":"Maple Lake",
    "sg:classifiers":[
        {
            "category":"Building & Trades",
            "subcategory":"Construction",
            "type":"Services"
        }
    ],
    "sg:phone":"+1 320 963 2400",
    "sg:postcode":"55358",
    "sg:province":"MN",
    "sg:tags":[
        "business",
        "contractor"
    ],
    "wof:name":"Mp Nexlevel LLC",
    "wof:placetype":"venue"
},
  "geometry": {"coordinates":[-93.952639,45.233305],"type":"Point"}
}