{
  "type": "Feature",
  "properties": {
    "addr:full":"509 3rd St NE Roseau MN 56751",
    "addr:housenumber":"509",
    "addr:postcode":"56751",
    "addr:street":"3Rd St Ne",
    "iso:country":"US",
    "sg:address":"509 3rd St NE",
    "sg:city":"Roseau",
    "sg:classifiers":[
        {
            "category":"Education",
            "subcategory":"School",
            "type":"Public Place"
        }
    ],
    "sg:phone":"+1 218 463 2746",
    "sg:postcode":"56751",
    "sg:province":"MN",
    "sg:tags":[
        "elementary"
    ],
    "wof:name":"Roseau Elementary School",
    "wof:placetype":"venue"
},
  "geometry": {"coordinates":[-95.75629600000001,48.848058],"type":"Point"}
}