{
  "type": "Feature",
  "properties": {
    "iso:country":"US",
    "sg:address":"3310 Brookdale Dr N",
    "sg:city":"Minneapolis",
    "sg:classifiers":[
        {
            "category":"Personal",
            "subcategory":"Tanning Parlor",
            "type":"Services"
        },
        {
            "category":"Personal",
            "type":"Services"
        }
    ],
    "sg:phone":"+1 763 560 2229",
    "sg:postcode":"55443",
    "sg:province":"MN",
    "sg:tags":[
        "salon"
    ],
    "wof:name":"Sunset Tan",
    "wof:placetype":"venue"
},
  "geometry": {"coordinates":[-93.32151500000001,45.097277],"type":"Point"}
}