{
  "type": "Feature",
  "properties": {
    "addr:full":"2549 Cornelia Trl Saint Paul MN 55125",
    "addr:housenumber":"2549",
    "addr:postcode":"55125",
    "addr:street":"Cornelia Trl",
    "iso:country":"US",
    "sg:address":"2549 Cornelia Trl",
    "sg:city":"Saint Paul",
    "sg:classifiers":[
        {
            "category":"Real Estate",
            "subcategory":"Real Estate Agent",
            "type":"Services"
        },
        {
            "category":"Real Estate",
            "subcategory":"Real Estate Operator",
            "type":"Services"
        }
    ],
    "sg:phone":"+1 651 501 2711",
    "sg:postcode":"55125",
    "sg:province":"MN",
    "sg:tags":[
        "townhouses"
    ],
    "wof:name":"West View Estates Town Homes",
    "wof:placetype":"venue"
},
  "geometry": {"coordinates":[-92.971778,44.910626],"type":"Point"}
}