{
  "type": "Feature",
  "properties": {
    "addr:full":"200 5th St SE Perham MN 56573",
    "addr:housenumber":"200",
    "addr:postcode":"56573",
    "addr:street":"5Th St Se",
    "iso:country":"US",
    "sg:address":"200 5th St SE",
    "sg:city":"Perham",
    "sg:classifiers":[
        {
            "category":"Education",
            "subcategory":"School",
            "type":"Public Place"
        }
    ],
    "sg:phone":"+1 218 346 6500",
    "sg:postcode":"56573",
    "sg:province":"MN",
    "sg:tags":[
        "high"
    ],
    "sg:website":"www.perham.k12.mn.us",
    "wof:name":"Perham Senior High School",
    "wof:placetype":"venue"
},
  "geometry": {"coordinates":[-95.575638,46.59042],"type":"Point"}
}