{
  "type": "Feature",
  "properties": {
    "addr:full":"5502 Osgood Ave N Stillwater MN 55082",
    "addr:housenumber":"5502",
    "addr:postcode":"55082",
    "addr:street":"Osgood Ave N",
    "iso:country":"US",
    "sg:address":"5502 Osgood Ave N",
    "sg:city":"Stillwater",
    "sg:classifiers":[
        {
            "category":"Home & Garden",
            "subcategory":"Building Materials",
            "type":"Retail Goods"
        }
    ],
    "sg:phone":"+1 651 430 1556",
    "sg:postcode":"55082",
    "sg:province":"MN",
    "sg:tags":[
        "glass",
        "leaded"
    ],
    "wof:name":"Stoney Lake Illusions",
    "wof:placetype":"venue"
},
  "geometry": {"coordinates":[-92.807254,45.028936],"type":"Point"}
}