{
  "type": "Feature",
  "properties": {
    "iso:country":"US",
    "sg:address":"5400 Penn Ave S",
    "sg:city":"Minneapolis",
    "sg:classifiers":[
        {
            "category":"Retail",
            "subcategory":"Auto Repair",
            "type":"Services"
        }
    ],
    "sg:phone":"+1 612 922 3834",
    "sg:postcode":"55419",
    "sg:province":"MN",
    "sg:tags":[
        "repairing",
        "automobile"
    ],
    "wof:name":"Jensen's Car Care",
    "wof:placetype":"venue"
},
  "geometry": {"coordinates":[-93.30864,44.903343],"type":"Point"}
}