{
  "type": "Feature",
  "properties": {
    "iso:country":"US",
    "sg:address":"217 S Minnesota Ave",
    "sg:city":"Saint Peter",
    "sg:classifiers":[
        {
            "category":"Manufacturing",
            "subcategory":"Toys & Sporting Goods",
            "type":"Manufacturing & Wholesale Goods"
        }
    ],
    "sg:phone":"+1 507 934 9699",
    "sg:postcode":"56082",
    "sg:province":"MN",
    "sg:tags":[
        "mfg"
    ],
    "wof:name":"Midwest Tackle",
    "wof:placetype":"venue"
},
  "geometry": {"coordinates":[-93.956525,44.324821],"type":"Point"}
}