{
  "type": "Feature",
  "properties": {
    "addr:full":"10600 282nd St Chisago City MN 55013",
    "addr:housenumber":"10600",
    "addr:postcode":"55013",
    "addr:street":"282Nd St",
    "iso:country":"US",
    "sg:address":"10600 282nd St",
    "sg:city":"Chisago City",
    "sg:classifiers":[
        {
            "category":"Real Estate",
            "subcategory":"Real Estate Operator",
            "type":"Services"
        }
    ],
    "sg:phone":"+1 651 257 0581",
    "sg:postcode":"55013",
    "sg:province":"MN",
    "sg:tags":[
        "building",
        "apartment"
    ],
    "wof:name":"Parmly Lakeview Apartments",
    "wof:placetype":"venue"
},
  "geometry": {"coordinates":[-92.883369,45.356522],"type":"Point"}
}