{
  "type": "Feature",
  "properties": {
    "addr:full":"13985 Industry Ave Becker MN 55308",
    "addr:housenumber":"13985",
    "addr:postcode":"55308",
    "addr:street":"Industry Ave",
    "iso:country":"US",
    "sg:address":"13985 Industry Ave",
    "sg:city":"Becker",
    "sg:classifiers":[
        {
            "category":"Retail",
            "subcategory":"Auto Repair",
            "type":"Services"
        }
    ],
    "sg:phone":"+1 763 262 0100",
    "sg:postcode":"55308",
    "sg:province":"MN",
    "sg:tags":[
        "truck"
    ],
    "wof:name":"Truck Technologies",
    "wof:placetype":"venue"
},
  "geometry": {"coordinates":[-93.876565,45.386928],"type":"Point"}
}