{
  "type": "Feature",
  "properties": {
    "addr:full":"1585 Homer Rd Winona MN 55987",
    "addr:housenumber":"1585",
    "addr:postcode":"55987",
    "addr:street":"Homer Rd",
    "iso:country":"US",
    "sg:address":"1585 Homer Rd",
    "sg:city":"Winona",
    "sg:classifiers":[
        {
            "category":"Real Estate",
            "subcategory":"Real Estate Operator",
            "type":"Services"
        }
    ],
    "sg:phone":"+1 507 454 1836",
    "sg:postcode":"55987",
    "sg:province":"MN",
    "sg:tags":[
        "building",
        "apartment"
    ],
    "wof:name":"Fairway Woods Apts",
    "wof:placetype":"venue"
},
  "geometry": {"coordinates":[-91.6101,44.019814],"type":"Point"}
}