{
  "type": "Feature",
  "properties": {
    "addr:full":"15899 Harwell Ave Saint Paul MN 55124",
    "addr:housenumber":"15899",
    "addr:postcode":"55124",
    "addr:street":"Harwell Ave",
    "iso:country":"US",
    "sg:address":"15899 Harwell Ave",
    "sg:city":"Saint Paul",
    "sg:classifiers":[
        {
            "category":"Professional",
            "subcategory":"Computer Services",
            "type":"Services"
        }
    ],
    "sg:phone":"+1 952 432 2158",
    "sg:postcode":"55124",
    "sg:province":"MN",
    "sg:tags":[
        "related"
    ],
    "wof:name":"Germincon Corp of Minnesota",
    "wof:placetype":"venue"
},
  "geometry": {"coordinates":[-93.23470399999999,44.717738],"type":"Point"}
}