{
  "type": "Feature",
  "properties": {
    "iso:country":"US",
    "sg:address":"6936 Oliver Ave S",
    "sg:city":"Minneapolis",
    "sg:classifiers":[
        {
            "category":"Building & Trades",
            "subcategory":"Construction",
            "type":"Services"
        }
    ],
    "sg:phone":"+1 612 869 4975",
    "sg:postcode":"55423",
    "sg:province":"MN",
    "sg:tags":[
        "nonresidential"
    ],
    "wof:name":"David Michael Swirtz",
    "wof:placetype":"venue"
},
  "geometry": {"coordinates":[-93.307402,44.876981],"type":"Point"}
}