{
  "type": "Feature",
  "properties": {
    "iso:country":"US",
    "sg:address":"7986 Brooklyn Blvd",
    "sg:city":"Minneapolis",
    "sg:classifiers":[
        {
            "category":"Food & Beverages",
            "subcategory":"Groceries & Convenience Stores",
            "type":"Retail Goods"
        }
    ],
    "sg:phone":"+1 763 315 1125",
    "sg:postcode":"55445",
    "sg:province":"MN",
    "wof:name":"Asian Pacific",
    "wof:placetype":"venue"
},
  "geometry": {"coordinates":[-93.383137,45.094614],"type":"Point"}
}