{
  "type": "Feature",
  "properties": {
    "iso:country":"US",
    "sg:address":"1801 NE Grand St",
    "sg:city":"Minneapolis",
    "sg:classifiers":[
        {
            "category":"Professional",
            "type":"Services"
        }
    ],
    "sg:phone":"+1 612 378 7060",
    "sg:postcode":"55418",
    "sg:province":"MN",
    "sg:tags":[
        "establishment"
    ],
    "wof:name":"Go Native",
    "wof:placetype":"venue"
},
  "geometry": {"coordinates":[-93.27007500000001,45.006986],"type":"Point"}
}