{
  "type": "Feature",
  "properties": {
    "addr:full":"1012 Marquette Ave Minneapolis MN 55403",
    "addr:housenumber":"1012",
    "addr:postcode":"55403",
    "addr:street":"Marquette Ave",
    "iso:country":"US",
    "sg:address":"1012 Marquette Ave",
    "sg:city":"Minneapolis",
    "sg:classifiers":[
        {
            "category":"Real Estate",
            "subcategory":"Architect",
            "type":"Services"
        }
    ],
    "sg:phone":"+1 612 338 6622",
    "sg:postcode":"55403",
    "sg:province":"MN",
    "sg:tags":[
        "architectural"
    ],
    "wof:name":"Brantingham Architects Ltd",
    "wof:placetype":"venue"
},
  "geometry": {"coordinates":[-93.274002,44.972801],"type":"Point"}
}