{
  "type": "Feature",
  "properties": {
    "iso:country":"US",
    "sg:address":"2002 London Rd",
    "sg:city":"Duluth",
    "sg:classifiers":[
        {
            "category":"Organizations",
            "subcategory":"Labor Organization",
            "type":"Services"
        }
    ],
    "sg:phone":"+1 218 724 8374",
    "sg:postcode":"55812",
    "sg:province":"MN",
    "wof:name":"Bricklayers & Tile Setters",
    "wof:placetype":"venue"
},
  "geometry": {"coordinates":[-92.069046,46.804491],"type":"Point"}
}