{
  "type": "Feature",
  "properties": {
    "iso:country":"US",
    "sg:address":"1501 Glenwood Ave",
    "sg:city":"Minneapolis",
    "sg:classifiers":[
        {
            "category":"Travel",
            "subcategory":"Travel Agent",
            "type":"Entertainment"
        }
    ],
    "sg:phone":"+1 612 374 2656",
    "sg:postcode":"55405",
    "sg:province":"MN",
    "sg:tags":[
        "agency"
    ],
    "wof:name":"Sky Travel",
    "wof:placetype":"venue"
},
  "geometry": {"coordinates":[-93.300758,44.980903],"type":"Point"}
}