{
  "type": "Feature",
  "properties": {
    "iso:country":"US",
    "sg:address":"1600 152nd Ave NE",
    "sg:city":"Anoka",
    "sg:classifiers":[
        {
            "category":"Wholesale",
            "subcategory":"Electrical",
            "type":"Manufacturing & Wholesale Goods"
        }
    ],
    "sg:phone":"+1 763 434 1855",
    "sg:postcode":"55304",
    "sg:province":"MN",
    "sg:tags":[
        "equipment"
    ],
    "wof:name":"Complete Electric Service",
    "wof:placetype":"venue"
},
  "geometry": {"coordinates":[-93.22802900000001,45.245427],"type":"Point"}
}