{
  "type": "Feature",
  "properties": {
    "addr:full":"425 US Hwy 10 S Saint Cloud MN 56304",
    "addr:housenumber":"425",
    "addr:postcode":"56304",
    "addr:street":"Us Hwy 10 S;Cloud",
    "iso:country":"US",
    "sg:address":"425 US Hwy 10 S",
    "sg:city":"Saint Cloud",
    "sg:classifiers":[
        {
            "category":"Health Services",
            "subcategory":"Clinic",
            "type":"Services"
        }
    ],
    "sg:phone":"+1 320 253 6579",
    "sg:postcode":"56304",
    "sg:province":"MN",
    "sg:tags":[
        "rehabilitation",
        "center"
    ],
    "wof:name":"Rehabilitation Cnsr CNT MN Inc",
    "wof:placetype":"venue"
},
  "geometry": {"coordinates":[-94.13746999999999,45.564537],"type":"Point"}
}