{
  "type": "Feature",
  "properties": {
    "iso:country":"US",
    "sg:address":"507 Ash Ave NW",
    "sg:city":"Wadena",
    "sg:classifiers":[
        {
            "category":"Shopping",
            "subcategory":"Computers & Home Electronics",
            "type":"Retail Goods"
        }
    ],
    "sg:phone":"+1 218 631 7455",
    "sg:postcode":"56482",
    "sg:province":"MN",
    "sg:tags":[
        "tv",
        "satellite",
        "sales",
        "internet"
    ],
    "wof:name":"Quality Installation Service",
    "wof:placetype":"venue"
},
  "geometry": {"coordinates":[-95.14506,46.44551],"type":"Point"}
}