{
  "type": "Feature",
  "properties": {
    "addr:full":"525 Cleveland Ave W Winnebago MN 56098",
    "addr:housenumber":"525",
    "addr:postcode":"56098",
    "addr:street":"Cleveland Ave W",
    "iso:country":"US",
    "sg:address":"525 Cleveland Ave W",
    "sg:city":"Winnebago",
    "sg:classifiers":[
        {
            "category":"Shopping",
            "type":"Retail Goods"
        }
    ],
    "sg:phone":"+1 507 893 4762",
    "sg:postcode":"56098",
    "sg:province":"MN",
    "sg:tags":[
        "wedding",
        "supply"
    ],
    "wof:name":"Apple Blossom Wedding Svc",
    "wof:placetype":"venue"
},
  "geometry": {"coordinates":[-94.176254,43.767844],"type":"Point"}
}