{
  "type": "Feature",
  "properties": {
    "iso:country":"US",
    "sg:address":"227 Lion Ln",
    "sg:city":"Saint Paul",
    "sg:classifiers":[
        {
            "category":"Manufacturing",
            "subcategory":"Printing",
            "type":"Manufacturing & Wholesale Goods"
        }
    ],
    "sg:phone":"+1 651 481 9297",
    "sg:postcode":"55126",
    "sg:province":"MN",
    "sg:tags":[
        "business",
        "form",
        "card"
    ],
    "wof:name":"Superior Business Products",
    "wof:placetype":"venue"
},
  "geometry": {"coordinates":[-93.109759,45.076066],"type":"Point"}
}