{
  "type": "Feature",
  "properties": {
    "addr:full":"7114 Logan Ave S Minneapolis MN 55423",
    "addr:housenumber":"7114",
    "addr:postcode":"55423",
    "addr:street":"Logan Ave S",
    "iso:country":"US",
    "sg:address":"7114 Logan Ave S",
    "sg:city":"Minneapolis",
    "sg:classifiers":[
        {
            "category":"Professional",
            "subcategory":"Management & Consulting",
            "type":"Services"
        }
    ],
    "sg:phone":"+1 612 866 3654",
    "sg:postcode":"55423",
    "sg:province":"MN",
    "sg:tags":[
        "business"
    ],
    "wof:name":"Creative Athletics",
    "wof:placetype":"venue"
},
  "geometry": {"coordinates":[-93.303636,44.872967],"type":"Point"}
}