{
  "type": "Feature",
  "properties": {
    "iso:country":"US",
    "sg:address":"6403 Cecilia Cir",
    "sg:city":"Minneapolis",
    "sg:classifiers":[
        {
            "category":"Banks & Credit Unions",
            "subcategory":"Bank",
            "type":"Services"
        }
    ],
    "sg:phone":"+1 952 746 8255",
    "sg:postcode":"55439",
    "sg:province":"MN",
    "sg:tags":[
        "loan",
        "real estate"
    ],
    "wof:name":"Rising Star Mortgage",
    "wof:placetype":"venue"
},
  "geometry": {"coordinates":[-93.365917,44.862257],"type":"Point"}
}