{
  "type": "Feature",
  "properties": {
    "iso:country":"US",
    "sg:address":"13908 Lake Dr NE",
    "sg:city":"Forest Lake",
    "sg:classifiers":[
        {
            "category":"Shopping",
            "subcategory":"Hobbies, Toys, & Games",
            "type":"Retail Goods"
        },
        {
            "category":"Shopping",
            "subcategory":"Gifts & Souvenirs",
            "type":"Retail Goods"
        }
    ],
    "sg:phone":"+1 651 464 1213",
    "sg:postcode":"55025",
    "sg:province":"MN",
    "sg:tags":[
        "craft"
    ],
    "wof:name":"Beyond The Picket Fence",
    "wof:placetype":"venue"
},
  "geometry": {"coordinates":[-93.09100599999999,45.223458],"type":"Point"}
}