{
  "type": "Feature",
  "properties": {
    "addr:full":"108 Atlantic Ave Waverly MN 55390",
    "addr:housenumber":"108",
    "addr:postcode":"55390",
    "addr:street":"Atlantic Ave",
    "iso:country":"US",
    "sg:address":"108 Atlantic Ave",
    "sg:city":"Waverly",
    "sg:classifiers":[
        {
            "category":"Retail",
            "subcategory":"Animal Services",
            "type":"Services"
        }
    ],
    "sg:phone":"+1 763 658 4434",
    "sg:postcode":"55390",
    "sg:province":"MN",
    "sg:tags":[
        "pet",
        "boarding",
        "sitting"
    ],
    "wof:name":"Spirit Bay",
    "wof:placetype":"venue"
},
  "geometry": {"coordinates":[-93.96204299999999,45.067214],"type":"Point"}
}