{
  "type": "Feature",
  "properties": {
    "iso:country":"US",
    "sg:address":"633 E Main St",
    "sg:city":"Anoka",
    "sg:classifiers":[
        {
            "category":"Personal",
            "subcategory":"Barber",
            "type":"Services"
        }
    ],
    "sg:phone":"+1 763 421 8584",
    "sg:postcode":"55303",
    "sg:province":"MN",
    "sg:tags":[
        "shop",
        "beauty"
    ],
    "wof:name":"Georges Kut N Style",
    "wof:placetype":"venue"
},
  "geometry": {"coordinates":[-93.37913500000001,45.197814],"type":"Point"}
}