{
  "type": "Feature",
  "properties": {
    "iso:country":"US",
    "sg:address":"3461 River Rapids Dr NW",
    "sg:city":"Minneapolis",
    "sg:classifiers":[
        {
            "category":"Ice Cream",
            "type":"Food & Drink"
        }
    ],
    "sg:phone":"+1 763 427 8816",
    "sg:postcode":"55448",
    "sg:province":"MN",
    "sg:tags":[
        "frozen",
        "yogurt"
    ],
    "wof:name":"Cold Stone Creamery",
    "wof:placetype":"venue"
},
  "geometry": {"coordinates":[-93.29679899999999,45.187099],"type":"Point"}
}