{
  "type": "Feature",
  "properties": {
    "iso:country":"US",
    "sg:address":"73926 Co Rd 13",
    "sg:city":"Blackduck",
    "sg:classifiers":[
        {
            "category":"Manufacturing",
            "subcategory":"Lumber",
            "type":"Manufacturing & Wholesale Goods"
        }
    ],
    "sg:phone":"+1 218 835 4969",
    "sg:postcode":"56630",
    "sg:province":"MN",
    "sg:tags":[
        "logging"
    ],
    "wof:name":"Michalicek Logging",
    "wof:placetype":"venue"
},
  "geometry": {"coordinates":[-94.41787600000001,47.730103],"type":"Point"}
}