{
  "type": "Feature",
  "properties": {
    "addr:full":"1557 US Hwy 10 W Detroit Lakes MN 56501",
    "addr:housenumber":"1557",
    "addr:postcode":"56501",
    "addr:street":"Us Hwy 10 W",
    "iso:country":"US",
    "sg:address":"1557 US Hwy 10 W",
    "sg:city":"Detroit Lakes",
    "sg:classifiers":[
        {
            "category":"Autos & Motor Vehicles",
            "subcategory":"Fuel & Gas Station",
            "type":"Retail Goods"
        }
    ],
    "sg:phone":"+1 218 846 1177",
    "sg:postcode":"56501",
    "sg:province":"MN",
    "sg:tags":[
        "station",
        "gasoline"
    ],
    "wof:name":"Murphys Oil",
    "wof:placetype":"venue"
},
  "geometry": {"coordinates":[-95.87294199999999,46.827871],"type":"Point"}
}