{
  "type": "Feature",
  "properties": {
    "iso:country":"US",
    "sg:address":"374 S Avenue",
    "sg:city":"Bloomington",
    "sg:classifiers":[
        {
            "category":"Restaurant",
            "type":"Food & Drink"
        }
    ],
    "sg:menulink":"http://www.allmenus.com/mn/bloomington/240305-panda-express/menu/",
    "sg:phone":"+1 952 858 8115",
    "sg:postcode":"55425",
    "sg:province":"MN",
    "sg:tags":[
        "asian",
        "chinese"
    ],
    "wof:name":"Panda Express",
    "wof:placetype":"venue"
},
  "geometry": {"coordinates":[-93.24355199999999,44.852778],"type":"Point"}
}