{
  "type": "Feature",
  "properties": {
    "iso:country":"US",
    "sg:address":"3025 Harbor Ln N",
    "sg:city":"Minneapolis",
    "sg:classifiers":[
        {
            "category":"Professional",
            "type":"Services"
        }
    ],
    "sg:phone":"+1 952 853 8101",
    "sg:postcode":"55447",
    "sg:province":"MN",
    "wof:name":"Blackjack Magic",
    "wof:placetype":"venue"
},
  "geometry": {"coordinates":[-93.461262,45.014061],"type":"Point"}
}