{
  "type": "Feature",
  "properties": {
    "iso:country":"US",
    "sg:address":"4717 Clark Ave",
    "sg:city":"St Paul",
    "sg:classifiers":[
        {
            "category":"Health Services",
            "subcategory":"Chiropractor",
            "type":"Services"
        },
        {
            "category":"Health Services",
            "subcategory":"Clinic",
            "type":"Services"
        }
    ],
    "sg:phone":"+1 651 762 8040",
    "sg:postcode":"55110",
    "sg:province":"MN",
    "wof:name":"Carlson Chiropractic Clinic",
    "wof:placetype":"venue"
},
  "geometry": {"coordinates":[-93.010079,45.082625],"type":"Point"}
}