{
  "type": "Feature",
  "properties": {
    "iso:country":"US",
    "sg:address":"2172 Tower Ct",
    "sg:city":"Saint Paul",
    "sg:classifiers":[
        {
            "category":"Professional",
            "subcategory":"Business Services",
            "type":"Services"
        }
    ],
    "sg:phone":"+1 651 738 8941",
    "sg:postcode":"55125",
    "sg:province":"MN",
    "wof:name":"Sundari Business & Leisure Tra",
    "wof:placetype":"venue"
},
  "geometry": {"coordinates":[-92.94741,44.916934],"type":"Point"}
}