{
  "type": "Feature",
  "properties": {
    "addr:full":"7577 175th St E Prior Lake MN 55372",
    "addr:housenumber":"7577",
    "addr:postcode":"55372",
    "addr:street":"175Th St E",
    "iso:country":"US",
    "sg:address":"7577 175th St E",
    "sg:city":"Prior Lake",
    "sg:classifiers":[
        {
            "category":"Freight",
            "type":"Transportation"
        }
    ],
    "sg:phone":"+1 952 447 6229",
    "sg:postcode":"55372",
    "sg:province":"MN",
    "sg:tags":[
        "operator",
        "local",
        "trucking"
    ],
    "wof:name":"Gottas Trucking Inc",
    "wof:placetype":"venue"
},
  "geometry": {"coordinates":[-93.366394,44.69583],"type":"Point"}
}