{
  "type": "Feature",
  "properties": {
    "iso:country":"US",
    "sg:address":"215 Elm Ave E",
    "sg:city":"Waseca",
    "sg:classifiers":[
        {
            "category":"Professional",
            "subcategory":"Lawyer & Legal Services",
            "type":"Services"
        }
    ],
    "sg:phone":"+1 507 835 5240",
    "sg:postcode":"56093",
    "sg:province":"MN",
    "sg:tags":[
        "attorney",
        "estate",
        "wills",
        "planning",
        "trust"
    ],
    "wof:name":"Zarrett, Linda P",
    "wof:placetype":"venue"
},
  "geometry": {"coordinates":[-93.505818,44.077534],"type":"Point"}
}