{
  "type": "Feature",
  "properties": {
    "iso:country":"US",
    "sg:address":"14977 223rd St N",
    "sg:city":"Scandia",
    "sg:classifiers":[
        {
            "category":"Retail",
            "subcategory":"Repair Shop",
            "type":"Services"
        }
    ],
    "sg:phone":"+1 651 433 5819",
    "sg:postcode":"55073",
    "sg:province":"MN",
    "sg:tags":[
        "welding"
    ],
    "wof:name":"Bobs Custom Welding",
    "wof:placetype":"venue"
},
  "geometry": {"coordinates":[-92.799092,45.27102],"type":"Point"}
}