{
  "type": "Feature",
  "properties": {
    "iso:country":"US",
    "sg:address":"414 6th St",
    "sg:city":"Hawley",
    "sg:classifiers":[
        {
            "category":"Professional",
            "subcategory":"Management & Consulting",
            "type":"Services"
        }
    ],
    "sg:phone":"+1 218 483 3215",
    "sg:postcode":"56549",
    "sg:province":"MN",
    "wof:name":"Dr Planning Co",
    "wof:placetype":"venue"
},
  "geometry": {"coordinates":[-96.31698799999999,46.881585],"type":"Point"}
}