{
  "type": "Feature",
  "properties": {
    "addr:full":"418 NE 6th Ave Grand Rapids MN 55744",
    "addr:housenumber":"418",
    "addr:postcode":"55744",
    "addr:street":"Ne 6Th Ave",
    "iso:country":"US",
    "sg:address":"418 NE 6th Ave",
    "sg:city":"Grand Rapids",
    "sg:classifiers":[
        {
            "category":"Retail",
            "subcategory":"Auto Repair",
            "type":"Services"
        }
    ],
    "sg:phone":"+1 218 326 0325",
    "sg:postcode":"55744",
    "sg:province":"MN",
    "sg:tags":[
        "automotive",
        "mechanical"
    ],
    "wof:name":"Glenns Automotive Center",
    "wof:placetype":"venue"
},
  "geometry": {"coordinates":[-93.519053,47.236082],"type":"Point"}
}