{
  "type": "Feature",
  "properties": {
    "iso:country":"US",
    "sg:address":"4100 66th St E",
    "sg:city":"Inver Grove Heights",
    "sg:classifiers":[
        {
            "category":"Education",
            "subcategory":"School",
            "type":"Public Place"
        }
    ],
    "sg:phone":"+1 651 457 7072",
    "sg:postcode":"55076",
    "sg:province":"MN",
    "sg:tags":[
        "elementary"
    ],
    "wof:name":"Tarek Ibn Ziyad Academy",
    "wof:placetype":"venue"
},
  "geometry": {"coordinates":[-93.024117,44.853327],"type":"Point"}
}