{
  "type": "Feature",
  "properties": {
    "addr:full":"2169 Arkwright St Saint Paul MN 55117",
    "addr:housenumber":"2169",
    "addr:postcode":"55117",
    "addr:street":"Arkwright St",
    "iso:country":"US",
    "sg:address":"2169 Arkwright St",
    "sg:city":"Saint Paul",
    "sg:classifiers":[
        {
            "category":"Professional",
            "type":"Services"
        }
    ],
    "sg:phone":"+1 651 771 7867",
    "sg:postcode":"55117",
    "sg:province":"MN",
    "wof:name":"Cjn Co Inc",
    "wof:placetype":"venue"
},
  "geometry": {"coordinates":[-93.084012,45.007249],"type":"Point"}
}