{
  "type": "Feature",
  "properties": {
    "iso:country":"US",
    "sg:address":"114 Marquette Ave",
    "sg:city":"North Mankato",
    "sg:classifiers":[
        {
            "category":"Building & Trades",
            "subcategory":"Plumbing",
            "type":"Services"
        }
    ],
    "sg:phone":"+1 507 388 6496",
    "sg:postcode":"56003",
    "sg:province":"MN",
    "sg:tags":[
        "plumbing",
        "contractor"
    ],
    "wof:name":"Trautman Plumbing & Repair",
    "wof:placetype":"venue"
},
  "geometry": {"coordinates":[-94.050774,44.170958],"type":"Point"}
}