{
  "type": "Feature",
  "properties": {
    "iso:country":"US",
    "sg:address":"1110 Hwy 55",
    "sg:city":"Hastings",
    "sg:classifiers":[
        {
            "category":"Travel",
            "subcategory":"Travel Agent",
            "type":"Entertainment"
        }
    ],
    "sg:phone":"+1 651 437 7651",
    "sg:postcode":"55033",
    "sg:province":"MN",
    "sg:tags":[
        "agency"
    ],
    "wof:name":"Travel Express Inc",
    "wof:placetype":"venue"
},
  "geometry": {"coordinates":[-92.87206399999999,44.738404],"type":"Point"}
}