{
  "type": "Feature",
  "properties": {
    "iso:country":"US",
    "sg:address":"330 21st Ave S",
    "sg:city":"Minneapolis",
    "sg:classifiers":[
        {
            "category":"Arts & Performance",
            "subcategory":"Arts Center",
            "type":"Entertainment"
        }
    ],
    "sg:phone":"+1 612 625 6699",
    "sg:postcode":"55454",
    "sg:province":"MN",
    "sg:tags":[
        "performing"
    ],
    "sg:website":"theatre.umn.edu/directions.php",
    "wof:name":"Rarig Center",
    "wof:placetype":"venue"
},
  "geometry": {"coordinates":[-93.242447,44.970222],"type":"Point"}
}