{
  "type": "Feature",
  "properties": {
    "iso:country":"US",
    "sg:address":"12100 196th st",
    "sg:city":"marine on st.croix",
    "sg:classifiers":[
        {
            "category":"Professional",
            "subcategory":"Computer Services",
            "type":"Services"
        }
    ],
    "sg:phone":"+1 651 334 8312",
    "sg:postcode":"55047",
    "sg:province":"MN",
    "sg:tags":[
        "mnlakeplace-com-minnesota-lake-homes-cabin-rentals-resorts-minnesota-lakes-mn-real-estate"
    ],
    "sg:website":"http://www.mnlakeplace.com",
    "wof:name":"mnlakeplace.com",
    "wof:placetype":"venue"
},
  "geometry": {"coordinates":[-92.85625899999999,45.23305],"type":"Point"}
}