{
  "type": "Feature",
  "properties": {
    "addr:full":"4460 Johnny Cake Ridge Rd Saint Paul MN 55122",
    "addr:housenumber":"4460",
    "addr:postcode":"55122",
    "addr:street":"Johnny Cake Ridge Rd",
    "iso:country":"US",
    "sg:address":"4460 Johnny Cake Ridge Rd",
    "sg:city":"Saint Paul",
    "sg:classifiers":[
        {
            "category":"Building & Trades",
            "subcategory":"Plumbing",
            "type":"Services"
        }
    ],
    "sg:phone":"+1 651 688 6191",
    "sg:postcode":"55122",
    "sg:province":"MN",
    "sg:tags":[
        "contractor"
    ],
    "wof:name":"Pro-Q Inc",
    "wof:placetype":"venue"
},
  "geometry": {"coordinates":[-93.186325,44.795023],"type":"Point"}
}