{
  "type": "Feature",
  "properties": {
    "addr:full":"30558 Co Rd 18 Deer River MN 56636",
    "addr:housenumber":"30558;18",
    "addr:postcode":"56636",
    "addr:street":"Co Rd;Deer River",
    "iso:country":"US",
    "sg:address":"30558 Co Rd 18",
    "sg:city":"Deer River",
    "sg:classifiers":[
        {
            "category":"Manufacturing",
            "subcategory":"Lumber",
            "type":"Manufacturing & Wholesale Goods"
        }
    ],
    "sg:phone":"+1 218 246 8959",
    "sg:postcode":"56636",
    "sg:province":"MN",
    "sg:tags":[
        "logging"
    ],
    "wof:name":"Huotari Logging",
    "wof:placetype":"venue"
},
  "geometry": {"coordinates":[-93.900868,47.319176],"type":"Point"}
}