{
  "type": "Feature",
  "properties": {
    "addr:full":"509 1st St S Long Prairie MN 56347",
    "addr:housenumber":"509",
    "addr:postcode":"56347",
    "addr:street":"1St St S",
    "iso:country":"US",
    "sg:address":"509 1st St S",
    "sg:city":"Long Prairie",
    "sg:classifiers":[
        {
            "category":"Building & Trades",
            "subcategory":"Construction",
            "type":"Services"
        }
    ],
    "sg:phone":"+1 320 732 4057",
    "sg:postcode":"56347",
    "sg:province":"MN",
    "sg:tags":[
        "contractor"
    ],
    "wof:name":"Gould Construction",
    "wof:placetype":"venue"
},
  "geometry": {"coordinates":[-94.863893,45.967335],"type":"Point"}
}