{
  "type": "Feature",
  "properties": {
    "iso:country":"US",
    "sg:address":"720 5th St S",
    "sg:city":"Hopkins",
    "sg:classifiers":[
        {
            "category":"Professional",
            "type":"Services"
        }
    ],
    "sg:phone":"+1 952 935 1721",
    "sg:postcode":"55343",
    "sg:province":"MN",
    "sg:tags":[
        "establishment"
    ],
    "wof:name":"Worldspan",
    "wof:placetype":"venue"
},
  "geometry": {"coordinates":[-93.412785,44.915272],"type":"Point"}
}