{
  "type": "Feature",
  "properties": {
    "addr:full":"20919 Huntsville Trl Lakeville MN 55044",
    "addr:housenumber":"20919",
    "addr:postcode":"55044",
    "addr:street":"Huntsville Trl",
    "iso:country":"US",
    "sg:address":"20919 Huntsville Trl",
    "sg:city":"Lakeville",
    "sg:classifiers":[
        {
            "category":"Professional",
            "subcategory":"Business Services",
            "type":"Services"
        }
    ],
    "sg:phone":"+1 952 985 5149",
    "sg:postcode":"55044",
    "sg:province":"MN",
    "wof:name":"Tony Pettit Enterprises Inc",
    "wof:placetype":"venue"
},
  "geometry": {"coordinates":[-93.248761,44.647597],"type":"Point"}
}