{
  "type": "Feature",
  "properties": {
    "iso:country":"US",
    "sg:address":"3500 W 50th St",
    "sg:city":"Minneapolis",
    "sg:classifiers":[
        {
            "category":"Retail",
            "subcategory":"Funeral Services",
            "type":"Services"
        }
    ],
    "sg:phone":"+1 952 927 8641",
    "sg:postcode":"55410",
    "sg:province":"MN",
    "sg:tags":[
        "home"
    ],
    "wof:name":"SCI",
    "wof:placetype":"venue"
},
  "geometry": {"coordinates":[-93.325226,44.912502],"type":"Point"}
}