{
  "type": "Feature",
  "properties": {
    "addr:full":"1955 W County Rd B2 Ste 6 Roseville MN 55113",
    "addr:housenumber":"1955;ste 6",
    "addr:postcode":"b2;55113",
    "addr:street":"W County Rd",
    "iso:country":"US",
    "sg:address":"1955 W County Rd B2 Ste 6",
    "sg:city":"Roseville",
    "sg:classifiers":[
        {
            "category":"Building & Trades",
            "subcategory":"Construction",
            "type":"Services"
        },
        {
            "category":"Home & Garden",
            "subcategory":"Furniture",
            "type":"Retail Goods"
        }
    ],
    "sg:phone":"+1 651 633 7042",
    "sg:postcode":"55113",
    "sg:province":"MN",
    "sg:tags":[
        "interior",
        "design",
        "store"
    ],
    "sg:website":"www.schneidermans.com",
    "wof:name":"Schneiderman's Furniture",
    "wof:placetype":"venue"
},
  "geometry": {"coordinates":[-93.181614,45.014978],"type":"Point"}
}