{
  "type": "Feature",
  "properties": {
    "addr:full":"1590 Thomas Center Dr Ste 110 Saint Paul MN 55122",
    "addr:housenumber":"1590",
    "addr:postcode":"55122",
    "addr:street":"Thomas Center Dr Ste 110",
    "iso:country":"US",
    "sg:address":"1590 Thomas Center Dr Ste 110",
    "sg:city":"Saint Paul",
    "sg:classifiers":[
        {
            "category":"Personal",
            "subcategory":"Massage",
            "type":"Services"
        },
        {
            "category":"Health Services",
            "subcategory":"Chiropractor",
            "type":"Services"
        }
    ],
    "sg:phone":"+1 651 209 9710",
    "sg:postcode":"55122",
    "sg:province":"MN",
    "sg:website":"www.cornerstonefamilychiropracti...",
    "wof:name":"Cornerstone Family Chiropractic",
    "wof:placetype":"venue"
},
  "geometry": {"coordinates":[-93.18102500000001,44.791152],"type":"Point"}
}