{
  "type": "Feature",
  "properties": {
    "iso:country":"US",
    "sg:address":"1435 E White St",
    "sg:city":"Ely",
    "sg:classifiers":[
        {
            "category":"Insurance",
            "subcategory":"Hazard Insurance",
            "type":"Services"
        }
    ],
    "sg:phone":"+1 218 365 3087",
    "sg:postcode":"55731",
    "sg:province":"MN",
    "sg:tags":[
        "pension"
    ],
    "wof:name":"Dean R Stankey",
    "wof:placetype":"venue"
},
  "geometry": {"coordinates":[-91.84560500000001,47.899604],"type":"Point"}
}