{
  "type": "Feature",
  "properties": {
    "iso:country":"US",
    "sg:address":"310 107th Ln NW",
    "sg:city":"Minneapolis",
    "sg:classifiers":[
        {
            "category":"Organizations",
            "subcategory":"Religious Organization",
            "type":"Services"
        }
    ],
    "sg:phone":"+1 763 757 4476",
    "sg:postcode":"55448",
    "sg:province":"MN",
    "wof:name":"Peace Intercessary Prayer",
    "wof:placetype":"venue"
},
  "geometry": {"coordinates":[-93.27513500000001,45.165205],"type":"Point"}
}