{
  "type": "Feature",
  "properties": {
    "iso:country":"US",
    "sg:address":"3424 Lee Ave N",
    "sg:city":"Minneapolis",
    "sg:classifiers":[
        {
            "category":"Real Estate",
            "subcategory":"Real Estate Agent",
            "type":"Services"
        }
    ],
    "sg:phone":"+1 763 588 6647",
    "sg:postcode":"55422",
    "sg:province":"MN",
    "wof:name":"Ardis Max",
    "wof:placetype":"venue"
},
  "geometry": {"coordinates":[-93.33625000000001,45.017334],"type":"Point"}
}