{
  "type": "Feature",
  "properties": {
    "addr:full":"720 Industrial Rd Moose Lake MN 55767",
    "addr:housenumber":"720",
    "addr:postcode":"55767",
    "addr:street":"Industrial Rd",
    "iso:country":"US",
    "sg:address":"720 Industrial Rd",
    "sg:city":"Moose Lake",
    "sg:classifiers":[
        {
            "category":"Retail",
            "subcategory":"Auto Repair",
            "type":"Services"
        }
    ],
    "sg:phone":"+1 218 485 8024",
    "sg:postcode":"55767",
    "sg:province":"MN",
    "sg:tags":[
        "repairing",
        "automobile",
        "general"
    ],
    "wof:name":"A & B Automotive Inc",
    "wof:placetype":"venue"
},
  "geometry": {"coordinates":[-92.758787,46.457176],"type":"Point"}
}