{
  "type": "Feature",
  "properties": {
    "iso:country":"US",
    "sg:address":"11231 49th Ave N",
    "sg:city":"Minneapolis",
    "sg:classifiers":[
        {
            "category":"Building & Trades",
            "subcategory":"Construction",
            "type":"Services"
        }
    ],
    "sg:phone":"+1 763 559 5134",
    "sg:postcode":"55442",
    "sg:province":"MN",
    "sg:tags":[
        "nonresidential"
    ],
    "wof:name":"Iyawe & Assoc",
    "wof:placetype":"venue"
},
  "geometry": {"coordinates":[-93.42339800000001,45.042386],"type":"Point"}
}