{
  "type": "Feature",
  "properties": {
    "iso:country":"US",
    "sg:address":"14310 Northdale Blvd",
    "sg:city":"Rogers",
    "sg:classifiers":[
        {
            "category":"Manufacturing",
            "subcategory":"Metals",
            "type":"Manufacturing & Wholesale Goods"
        }
    ],
    "sg:phone":"+1 763 428 9175",
    "sg:postcode":"55374",
    "sg:province":"MN",
    "sg:tags":[
        "plate",
        "refuse",
        "mfg",
        "work",
        "fabricated",
        "system"
    ],
    "wof:name":"Slick Lift",
    "wof:placetype":"venue"
},
  "geometry": {"coordinates":[-93.555713,45.214131],"type":"Point"}
}