{
  "type": "Feature",
  "properties": {
    "addr:full":"13575 Grove Dr Osseo MN 55311",
    "addr:housenumber":"13575",
    "addr:postcode":"55311",
    "addr:street":"Grove Dr",
    "iso:country":"US",
    "sg:address":"13575 Grove Dr",
    "sg:city":"Osseo",
    "sg:classifiers":[
        {
            "category":"Retail",
            "subcategory":"Photofinishing",
            "type":"Services"
        }
    ],
    "sg:phone":"+1 952 914 9412",
    "sg:postcode":"55311",
    "sg:province":"MN",
    "sg:tags":[
        "laundry",
        "developing",
        "printing",
        "operated",
        "coin",
        "film"
    ],
    "wof:name":"Pro Photo",
    "wof:placetype":"venue"
},
  "geometry": {"coordinates":[-93.452397,45.102856],"type":"Point"}
}