{
  "type": "Feature",
  "properties": {
    "iso:country":"US",
    "sg:address":"4109 Park Ave S",
    "sg:city":"Minneapolis",
    "sg:classifiers":[
        {
            "category":"Professional",
            "subcategory":"Art Services",
            "type":"Services"
        }
    ],
    "sg:phone":"+1 612 825 7897",
    "sg:postcode":"55407",
    "sg:province":"MN",
    "sg:tags":[
        "photo",
        "photography",
        "commercial",
        "studio",
        "portrait"
    ],
    "sg:website":"www.kristineheykants.com",
    "wof:name":"Kristine Heykants Photography",
    "wof:placetype":"venue"
},
  "geometry": {"coordinates":[-93.264932,44.927096],"type":"Point"}
}