{
  "type": "Feature",
  "properties": {
    "iso:country":"US",
    "sg:address":"4030 Coon Rapids Blvd NW",
    "sg:city":"Coon Rapids",
    "sg:classifiers":[
        {
            "category":"Health Services",
            "subcategory":"Doctor",
            "type":"Services"
        }
    ],
    "sg:phone":"+1 763 433 0221",
    "sg:postcode":"55433",
    "sg:province":"MN",
    "sg:tags":[
        "physician",
        "radiology",
        "pediatrics-radiology",
        "surgeons",
        "surgeon"
    ],
    "wof:name":"Mercy Radiation Therapy Center",
    "wof:placetype":"venue"
},
  "geometry": {"coordinates":[-93.368599,45.184101],"type":"Point"}
}