{
  "type": "Feature",
  "properties": {
    "iso:country":"US",
    "sg:address":"619 E 4th St",
    "sg:city":"Duluth",
    "sg:classifiers":[
        {
            "category":"Food & Beverages",
            "subcategory":"Liquor & Beverages",
            "type":"Retail Goods"
        }
    ],
    "sg:phone":"+1 218 727 6825",
    "sg:postcode":"55805",
    "sg:province":"MN",
    "sg:website":"www.lastchanceliquor.com",
    "wof:name":"Last Chance Liquor & Wine",
    "wof:placetype":"venue"
},
  "geometry": {"coordinates":[-92.094041,46.796175],"type":"Point"}
}