{
  "type": "Feature",
  "properties": {
    "addr:full":"18339 Hines Rd NE Hines MN 56647",
    "addr:housenumber":"18339",
    "addr:postcode":"56647",
    "addr:street":"Hines Rd Ne",
    "iso:country":"US",
    "sg:address":"18339 Hines Rd NE",
    "sg:city":"Hines",
    "sg:classifiers":[
        {
            "category":"Building & Trades",
            "subcategory":"Plumbing",
            "type":"Services"
        }
    ],
    "sg:phone":"+1 218 835 7198",
    "sg:postcode":"56647",
    "sg:province":"MN",
    "sg:tags":[
        "contractor"
    ],
    "wof:name":"Merrill Heating",
    "wof:placetype":"venue"
},
  "geometry": {"coordinates":[-94.56426500000001,47.642731],"type":"Point"}
}