{
  "type": "Feature",
  "properties": {
    "iso:country":"US",
    "sg:address":"446 Lake Ave SE",
    "sg:city":"Bemidji",
    "sg:classifiers":[
        {
            "category":"Organizations",
            "subcategory":"Membership Organization",
            "type":"Services"
        }
    ],
    "sg:phone":"+1 218 444 1495",
    "sg:postcode":"56601",
    "sg:province":"MN",
    "wof:name":"Citizens For Truth & Light",
    "wof:placetype":"venue"
},
  "geometry": {"coordinates":[-94.842449,47.457036],"type":"Point"}
}