{
  "type": "Feature",
  "properties": {
    "iso:country":"US",
    "sg:address":"7230 Valley Creek Rd",
    "sg:city":"St Paul",
    "sg:classifiers":[
        {
            "category":"Restaurant",
            "type":"Food & Drink"
        }
    ],
    "sg:phone":"+1 651 714 0357",
    "sg:postcode":"55125",
    "sg:province":"MN",
    "sg:tags":[
        "shop",
        "coffee",
        "eating"
    ],
    "sg:website":"www.starbucks.com",
    "wof:name":"Starbucks",
    "wof:placetype":"venue"
},
  "geometry": {"coordinates":[-92.96035999999999,44.924656],"type":"Point"}
}