{
  "type": "Feature",
  "properties": {
    "addr:full":"822 4th St Graceville MN 56240",
    "addr:housenumber":"822",
    "addr:postcode":"56240",
    "addr:street":"4Th St",
    "iso:country":"US",
    "sg:address":"822 4th St",
    "sg:city":"Graceville",
    "sg:classifiers":[
        {
            "category":"Real Estate",
            "subcategory":"Real Estate Operator",
            "type":"Services"
        }
    ],
    "sg:phone":"+1 320 748 7492",
    "sg:postcode":"56240",
    "sg:province":"MN",
    "sg:tags":[
        "property",
        "lessor"
    ],
    "wof:name":"Frank Steffan",
    "wof:placetype":"venue"
},
  "geometry": {"coordinates":[-96.435964,45.570285],"type":"Point"}
}