{
  "type": "Feature",
  "properties": {
    "iso:country":"US",
    "sg:address":"41640 State Hwy 65",
    "sg:city":"Nashwauk",
    "sg:classifiers":[
        {
            "category":"Shopping",
            "subcategory":"Gifts & Souvenirs",
            "type":"Retail Goods"
        }
    ],
    "sg:phone":"+1 218 768 2533",
    "sg:postcode":"55769",
    "sg:province":"MN",
    "sg:tags":[
        "mfg"
    ],
    "wof:name":"Minnestalgia Winery",
    "wof:placetype":"venue"
},
  "geometry": {"coordinates":[-93.19551,47.48117],"type":"Point"}
}