{
  "type": "Feature",
  "properties": {
    "iso:country":"US",
    "sg:address":"601 7th Ave",
    "sg:city":"Two Harbors",
    "sg:classifiers":[
        {
            "category":"Personal",
            "subcategory":"Beauty Salon",
            "type":"Services"
        }
    ],
    "sg:phone":"+1 218 834 5409",
    "sg:postcode":"55616",
    "sg:province":"MN",
    "sg:tags":[
        "shop"
    ],
    "wof:name":"New Hairitage",
    "wof:placetype":"venue"
},
  "geometry": {"coordinates":[-91.672939,47.025625],"type":"Point"}
}