{
  "type": "Feature",
  "properties": {
    "addr:full":"5243 Dodge St Duluth MN 55804",
    "addr:housenumber":"5243",
    "addr:postcode":"55804",
    "addr:street":"Dodge St",
    "iso:country":"US",
    "sg:address":"5243 Dodge St",
    "sg:city":"Duluth",
    "sg:classifiers":[
        {
            "category":"Building & Trades",
            "subcategory":"Plumbing",
            "type":"Services"
        }
    ],
    "sg:phone":"+1 218 525 6049",
    "sg:postcode":"55804",
    "sg:province":"MN",
    "sg:tags":[
        "plumbing",
        "contractor"
    ],
    "wof:name":"ABC Plumbing",
    "wof:placetype":"venue"
},
  "geometry": {"coordinates":[-92.021072,46.833276],"type":"Point"}
}