{
  "type": "Feature",
  "properties": {
    "addr:full":"12551 Queens Way N Stillwater MN 55082",
    "addr:housenumber":"12551",
    "addr:postcode":"55082",
    "addr:street":"Queens Way N",
    "iso:country":"US",
    "sg:address":"12551 Queens Way N",
    "sg:city":"Stillwater",
    "sg:classifiers":[
        {
            "category":"Shopping",
            "subcategory":"Gifts & Souvenirs",
            "type":"Retail Goods"
        }
    ],
    "sg:phone":"+1 651 430 2730",
    "sg:postcode":"55082",
    "sg:province":"MN",
    "sg:tags":[
        "shop"
    ],
    "wof:name":"From The Heart",
    "wof:placetype":"venue"
},
  "geometry": {"coordinates":[-92.770252,45.133123],"type":"Point"}
}