{
  "type": "Feature",
  "properties": {
    "iso:country":"US",
    "sg:address":"140 W Myrtle St",
    "sg:city":"Duluth",
    "sg:classifiers":[
        {
            "category":"Professional",
            "subcategory":"Management & Consulting",
            "type":"Services"
        }
    ],
    "sg:phone":"+1 218 727 5150",
    "sg:postcode":"55811",
    "sg:province":"MN",
    "sg:tags":[
        "consultant",
        "business"
    ],
    "wof:name":"Mary M Ruprecht & Assoc Inc",
    "wof:placetype":"venue"
},
  "geometry": {"coordinates":[-92.138689,46.801208],"type":"Point"}
}