{
  "type": "Feature",
  "properties": {
    "addr:full":"834 4th Ave NE Byron MN 55920",
    "addr:housenumber":"834",
    "addr:postcode":"55920",
    "addr:street":"4Th Ave Ne",
    "iso:country":"US",
    "sg:address":"834 4th Ave NE",
    "sg:city":"Byron",
    "sg:classifiers":[
        {
            "category":"Professional",
            "subcategory":"Art Services",
            "type":"Services"
        }
    ],
    "sg:phone":"+1 507 421 2060",
    "sg:postcode":"55920",
    "sg:province":"MN",
    "sg:tags":[
        "photographers-portrait"
    ],
    "wof:name":"Photography by Janet Johnson",
    "wof:placetype":"venue"
},
  "geometry": {"coordinates":[-92.638971,44.039376],"type":"Point"}
}