{
  "type": "Feature",
  "properties": {
    "iso:country":"US",
    "sg:address":"6601 France Ave S",
    "sg:city":"Edina",
    "sg:classifiers":[
        {
            "category":"Shopping",
            "subcategory":"Gifts & Souvenirs",
            "type":"Retail Goods"
        }
    ],
    "sg:phone":"+1 952 928 9848",
    "sg:postcode":"55435",
    "sg:province":"MN",
    "sg:tags":[
        "shop"
    ],
    "wof:name":"Crabtree & Evelyn",
    "wof:placetype":"venue"
},
  "geometry": {"coordinates":[-93.32894899999999,44.879861],"type":"Point"}
}