{
  "type": "Feature",
  "properties": {
    "addr:full":"17021 Riverwood Dr Little Falls MN 56345",
    "addr:housenumber":"17021",
    "addr:postcode":"56345",
    "addr:street":"Riverwood Dr",
    "iso:country":"US",
    "sg:address":"17021 Riverwood Dr",
    "sg:city":"Little Falls",
    "sg:classifiers":[
        {
            "category":"Social Services",
            "subcategory":"Adult Care",
            "type":"Services"
        }
    ],
    "sg:phone":"+1 320 632 1817",
    "sg:postcode":"56345",
    "sg:province":"MN",
    "sg:tags":[
        "home",
        "group"
    ],
    "wof:name":"Oakridge Homes",
    "wof:placetype":"venue"
},
  "geometry": {"coordinates":[-94.355282,46.007867],"type":"Point"}
}