{
  "type": "Feature",
  "properties": {
    "iso:country":"US",
    "sg:address":"28484 Co Hwy 145",
    "sg:city":"Battle Lake",
    "sg:classifiers":[
        {
            "category":"Travel",
            "subcategory":"Hotels & Motels",
            "type":"Entertainment"
        }
    ],
    "sg:phone":"+1 218 495 3444",
    "sg:postcode":"56515",
    "sg:province":"MN",
    "sg:tags":[
        "resort",
        "operation"
    ],
    "sg:website":"www.barkysresort.com",
    "wof:name":"Barky's Resort",
    "wof:placetype":"venue"
},
  "geometry": {"coordinates":[-95.744367,46.370074],"type":"Point"}
}