{
  "type": "Feature",
  "properties": {
    "addr:full":"501 Main Ave Moorhead MN 56560",
    "addr:housenumber":"501",
    "addr:postcode":"56560",
    "addr:street":"Main Ave",
    "iso:country":"US",
    "sg:address":"501 Main Ave",
    "sg:city":"Moorhead",
    "sg:classifiers":[
        {
            "category":"Personal",
            "type":"Services"
        }
    ],
    "sg:phone":"+1 218 236 0226",
    "sg:postcode":"56560",
    "sg:province":"MN",
    "sg:tags":[
        "health"
    ],
    "wof:name":"Theraptic Massage Wellness Ctr",
    "wof:placetype":"venue"
},
  "geometry": {"coordinates":[-96.770888,46.873791],"type":"Point"}
}