{
  "type": "Feature",
  "properties": {
    "iso:country":"US",
    "sg:address":"10084 Valley Forge Ln N",
    "sg:city":"Osseo",
    "sg:classifiers":[
        {
            "category":"Professional",
            "type":"Services"
        }
    ],
    "sg:phone":"+1 763 424 5865",
    "sg:postcode":"55369",
    "sg:province":"MN",
    "wof:name":"Handyman Service By Brian",
    "wof:placetype":"venue"
},
  "geometry": {"coordinates":[-93.417648,45.13703],"type":"Point"}
}