{
  "type": "Feature",
  "properties": {
    "addr:full":"23490 State Hwy 6 Cohasset MN 55721",
    "addr:housenumber":"23490",
    "addr:postcode":"55721",
    "addr:street":"State Hwy 6",
    "iso:country":"US",
    "sg:address":"23490 State Hwy 6",
    "sg:city":"Cohasset",
    "sg:phone":"+1 218 328 5531",
    "sg:postcode":"55721",
    "sg:province":"MN",
    "sg:tags":[
        "farm",
        "field",
        "crop"
    ],
    "wof:name":"James Skelly Farm",
    "wof:placetype":"venue"
},
  "geometry": {"coordinates":[-93.756169,47.214954],"type":"Point"}
}