{
  "type": "Feature",
  "properties": {
    "iso:country":"US",
    "sg:address":"312 8th Ave",
    "sg:city":"International Falls",
    "sg:classifiers":[
        {
            "category":"Professional",
            "subcategory":"Accounting & Tax Preparation",
            "type":"Services"
        }
    ],
    "sg:phone":"+1 218 283 8457",
    "sg:postcode":"56649",
    "sg:province":"MN",
    "wof:name":"Miller McDonald Erckson Moller",
    "wof:placetype":"venue"
},
  "geometry": {"coordinates":[-93.411311,48.601841],"type":"Point"}
}