{
  "type": "Feature",
  "properties": {
    "addr:full":"218 W Clark St Albert Lea MN 56007",
    "addr:housenumber":"218",
    "addr:postcode":"56007",
    "addr:street":"W Clark St",
    "iso:country":"US",
    "sg:address":"218 W Clark St",
    "sg:city":"Albert Lea",
    "sg:classifiers":[
        {
            "category":"Building & Trades",
            "subcategory":"Construction",
            "type":"Services"
        }
    ],
    "sg:phone":"+1 507 256 4833",
    "sg:postcode":"56007",
    "sg:province":"MN",
    "sg:tags":[
        "general",
        "contractor"
    ],
    "wof:name":"Bruce Stadheim Construction",
    "wof:placetype":"venue"
},
  "geometry": {"coordinates":[-93.37114699999999,43.649826],"type":"Point"}
}