{
  "type": "Feature",
  "properties": {
    "addr:full":"6600 France Ave S Edina MN 55435",
    "addr:housenumber":"6600",
    "addr:postcode":"55435",
    "addr:street":"France Ave S",
    "iso:country":"US",
    "sg:address":"6600 France Ave S",
    "sg:city":"Edina",
    "sg:classifiers":[
        {
            "category":"Professional",
            "subcategory":"Management & Consulting",
            "type":"Services"
        }
    ],
    "sg:phone":"+1 952 925 9566",
    "sg:postcode":"55435",
    "sg:province":"MN",
    "sg:tags":[
        "promotion",
        "sales",
        "relations",
        "public"
    ],
    "sg:website":"www.addedvalueinc.com",
    "wof:name":"Added Value Inc",
    "wof:placetype":"venue"
},
  "geometry": {"coordinates":[-93.32894899999999,44.879861],"type":"Point"}
}