{
  "type": "Feature",
  "properties": {
    "iso:country":"US",
    "sg:address":"7753 80th St S",
    "sg:city":"Cottage Grove",
    "sg:classifiers":[
        {
            "category":"Home & Garden",
            "subcategory":"Household Appliances",
            "type":"Retail Goods"
        }
    ],
    "sg:phone":"+1 651 459 8899",
    "sg:postcode":"55016",
    "sg:province":"MN",
    "wof:name":"Arlos Vac Sales-Repair Parts",
    "wof:placetype":"venue"
},
  "geometry": {"coordinates":[-92.949972,44.833483],"type":"Point"}
}