{
  "type": "Feature",
  "properties": {
    "iso:country":"US",
    "sg:address":"3812 5th Ave E",
    "sg:city":"Hibbing",
    "sg:classifiers":[
        {
            "category":"Social Services",
            "subcategory":"Child Care",
            "type":"Services"
        }
    ],
    "sg:phone":"+1 218 263 7776",
    "sg:postcode":"55746",
    "sg:province":"MN",
    "sg:tags":[
        "day",
        "provider"
    ],
    "wof:name":"Janet Lenoie",
    "wof:placetype":"venue"
},
  "geometry": {"coordinates":[-92.934044,47.405109],"type":"Point"}
}