{
  "type": "Feature",
  "properties": {
    "iso:country":"US",
    "sg:address":"13005 Riverdale Dr NW",
    "sg:city":"Minneapolis",
    "sg:classifiers":[
        {
            "category":"Restaurant",
            "type":"Food & Drink"
        }
    ],
    "sg:phone":"+1 763 421 0029",
    "sg:postcode":"55448",
    "sg:province":"MN",
    "sg:website":"www.burgerking.com",
    "wof:name":"Burger King Restaurants",
    "wof:placetype":"venue"
},
  "geometry": {"coordinates":[-93.3601,45.205399],"type":"Point"}
}