{
  "type": "Feature",
  "properties": {
    "iso:country":"US",
    "sg:address":"31686 171st Ave",
    "sg:city":"New Prague",
    "sg:classifiers":[
        {
            "category":"Building & Trades",
            "subcategory":"Construction",
            "type":"Services"
        }
    ],
    "sg:phone":"+1 952 758 2786",
    "sg:postcode":"56071",
    "sg:province":"MN",
    "sg:tags":[
        "excavating",
        "contractor"
    ],
    "wof:name":"Braith Excavating",
    "wof:placetype":"venue"
},
  "geometry": {"coordinates":[-93.605968,44.489862],"type":"Point"}
}