{
  "type": "Feature",
  "properties": {
    "addr:full":"13205 Saint Croix Ave Lindstrom MN 55045",
    "addr:housenumber":"13205",
    "addr:postcode":"55045",
    "addr:street":"Saint Croix Ave",
    "iso:country":"US",
    "sg:address":"13205 Saint Croix Ave",
    "sg:city":"Lindstrom",
    "sg:phone":"+1 651 257 1557",
    "sg:postcode":"55045",
    "sg:province":"MN",
    "wof:name":"Totally You Hair Salon Day Spa",
    "wof:placetype":"venue"
},
  "geometry": {"coordinates":[-92.83968400000001,45.390288],"type":"Point"}
}