{
  "type": "Feature",
  "properties": {
    "addr:full":"404 Adams Ave Owatonna MN 55060",
    "addr:housenumber":"404",
    "addr:postcode":"55060",
    "addr:street":"Adams Ave",
    "iso:country":"US",
    "sg:address":"404 Adams Ave",
    "sg:city":"Owatonna",
    "sg:classifiers":[
        {
            "category":"Building & Trades",
            "subcategory":"Landscaping Services",
            "type":"Services"
        }
    ],
    "sg:phone":"+1 507 455 0073",
    "sg:postcode":"55060",
    "sg:province":"MN",
    "sg:tags":[
        "horticulture"
    ],
    "wof:name":"Betty J Bjorge",
    "wof:placetype":"venue"
},
  "geometry": {"coordinates":[-93.234291,44.088607],"type":"Point"}
}