{
  "type": "Feature",
  "properties": {
    "addr:full":"1207 11th Ave N Minneapolis MN 55411",
    "addr:housenumber":"1207",
    "addr:postcode":"55411",
    "addr:street":"11Th Ave N",
    "iso:country":"US",
    "sg:address":"1207 11th Ave N",
    "sg:city":"Minneapolis",
    "sg:classifiers":[
        {
            "category":"Building & Trades",
            "subcategory":"Construction",
            "type":"Services"
        }
    ],
    "sg:phone":"+1 612 377 5527",
    "sg:postcode":"55411",
    "sg:province":"MN",
    "sg:tags":[
        "wallcoverings-installation",
        "wallpaper",
        "painting",
        "contractor"
    ],
    "wof:name":"Kringle Painting",
    "wof:placetype":"venue"
},
  "geometry": {"coordinates":[-93.294786,44.988991],"type":"Point"}
}