{
  "type": "Feature",
  "properties": {
    "iso:country":"US",
    "sg:address":"2236 172nd Ln NE",
    "sg:city":"Andover",
    "sg:classifiers":[
        {
            "category":"Real Estate",
            "subcategory":"Real Estate Operator",
            "type":"Services"
        }
    ],
    "sg:phone":"+1 763 434 3862",
    "sg:postcode":"55304",
    "sg:province":"MN",
    "sg:tags":[
        "building",
        "park",
        "nonresidential"
    ],
    "wof:name":"Kurt & Ken Lacoe Properties",
    "wof:placetype":"venue"
},
  "geometry": {"coordinates":[-93.21359699999999,45.283003],"type":"Point"}
}