{
  "type": "Feature",
  "properties": {
    "iso:country":"US",
    "sg:address":"24044 July Ave",
    "sg:city":"Chisago City",
    "sg:classifiers":[
        {
            "category":"Building & Trades",
            "subcategory":"Construction",
            "type":"Services"
        }
    ],
    "sg:phone":"+1 651 257 9469",
    "sg:postcode":"55013",
    "sg:province":"MN",
    "sg:tags":[
        "road"
    ],
    "wof:name":"Dresel Contracting Inc",
    "wof:placetype":"venue"
},
  "geometry": {"coordinates":[-92.90705,45.296661],"type":"Point"}
}