{
  "type": "Feature",
  "properties": {
    "iso:country":"US",
    "sg:address":"2400 Central Ave NE",
    "sg:city":"Minneapolis",
    "sg:classifiers":[
        {
            "category":"Food & Beverages",
            "subcategory":"Groceries & Convenience Stores",
            "type":"Retail Goods"
        }
    ],
    "sg:phone":"+1 612 781 0320",
    "sg:postcode":"55418",
    "sg:province":"MN",
    "sg:tags":[
        "grocer"
    ],
    "wof:name":"KET Grocery",
    "wof:placetype":"venue"
},
  "geometry": {"coordinates":[-93.247337,45.013161],"type":"Point"}
}