{
  "type": "Feature",
  "properties": {
    "addr:full":"520 Snelling Ave St Paul MN 55104",
    "addr:housenumber":"520",
    "addr:postcode":"55104",
    "addr:street":"Snelling Ave",
    "iso:country":"US",
    "sg:address":"520 Snelling Ave",
    "sg:city":"St Paul",
    "sg:classifiers":[
        {
            "category":"Personal",
            "subcategory":"Beauty Salon",
            "type":"Services"
        }
    ],
    "sg:phone":"+1 651 646 0520",
    "sg:postcode":"55104",
    "sg:province":"MN",
    "wof:name":"Shane Beauty Salon",
    "wof:placetype":"venue"
},
  "geometry": {"coordinates":[-93.166926,44.957199],"type":"Point"}
}