{
  "type": "Feature",
  "properties": {
    "addr:full":"386 Gironde Ct Saint Paul MN 55125",
    "addr:housenumber":"386",
    "addr:postcode":"55125",
    "addr:street":"Gironde Ct",
    "iso:country":"US",
    "sg:address":"386 Gironde Ct",
    "sg:city":"Saint Paul",
    "sg:classifiers":[
        {
            "category":"Professional",
            "type":"Services"
        }
    ],
    "sg:phone":"+1 651 739 4453",
    "sg:postcode":"55125",
    "sg:province":"MN",
    "wof:name":"Esoteric",
    "wof:placetype":"venue"
},
  "geometry": {"coordinates":[-92.949617,44.942002],"type":"Point"}
}