{
  "type": "Feature",
  "properties": {
    "addr:full":"3106 68th Ave N Brooklyn Center MN 55429",
    "addr:housenumber":"3106",
    "addr:postcode":"55429",
    "addr:street":"68Th Ave N",
    "iso:country":"US",
    "sg:address":"3106 68th Ave N",
    "sg:city":"Brooklyn Center",
    "sg:classifiers":[
        {
            "category":"Wholesale",
            "subcategory":"Auto Parts",
            "type":"Manufacturing & Wholesale Goods"
        }
    ],
    "sg:phone":"+1 763 560 3023",
    "sg:postcode":"55429",
    "sg:province":"MN",
    "sg:tags":[
        "automobile",
        "rebuilt"
    ],
    "wof:name":"B & K Towing",
    "wof:placetype":"venue"
},
  "geometry": {"coordinates":[-93.321622,45.077948],"type":"Point"}
}