{
  "type": "Feature",
  "properties": {
    "iso:country":"US",
    "sg:address":"298 Coon Rapids Blvd NW",
    "sg:city":"Coon Rapids",
    "sg:classifiers":[
        {
            "category":"Manufacturing",
            "subcategory":"Food",
            "type":"Manufacturing & Wholesale Goods"
        },
        {
            "category":"Manufacturing",
            "subcategory":"Tools & Machinery",
            "type":"Manufacturing & Wholesale Goods"
        }
    ],
    "sg:phone":"+1 763 786 2146",
    "sg:postcode":"55433",
    "sg:province":"MN",
    "sg:tags":[
        "equipment",
        "laboratory",
        "flavor",
        "supply",
        "mfg"
    ],
    "sg:website":"www.gibbcoscientific.com",
    "wof:name":"Gibbco Scientific Inc",
    "wof:placetype":"venue"
},
  "geometry": {"coordinates":[-93.274692,45.139095],"type":"Point"}
}