{
  "type": "Feature",
  "properties": {
    "addr:full":"5068 144th St W Saint Paul MN 55124",
    "addr:housenumber":"5068",
    "addr:postcode":"55124",
    "addr:street":"144Th St W",
    "iso:country":"US",
    "sg:address":"5068 144th St W",
    "sg:city":"Saint Paul",
    "sg:classifiers":[
        {
            "category":"Professional",
            "subcategory":"Computer Services",
            "type":"Services"
        }
    ],
    "sg:phone":"+1 952 423 4791",
    "sg:postcode":"55124",
    "sg:province":"MN",
    "sg:tags":[
        "programing",
        "custom"
    ],
    "wof:name":"T Marden & Associates",
    "wof:placetype":"venue"
},
  "geometry": {"coordinates":[-93.16775800000001,44.739553],"type":"Point"}
}