{
  "type": "Feature",
  "properties": {
    "addr:full":"5204 Bloomington Ave Minneapolis MN 55417",
    "addr:housenumber":"5204",
    "addr:postcode":"55417",
    "addr:street":"Bloomington Ave",
    "iso:country":"US",
    "sg:address":"5204 Bloomington Ave",
    "sg:city":"Minneapolis",
    "sg:classifiers":[
        {
            "category":"Restaurant",
            "type":"Food & Drink"
        }
    ],
    "sg:phone":"+1 612 824 4794",
    "sg:postcode":"55417",
    "sg:province":"MN",
    "sg:tags":[
        "breakfast",
        "brunch",
        "diner"
    ],
    "sg:website":"www.hotplatediner.com",
    "wof:name":"Hot Plate",
    "wof:placetype":"venue"
},
  "geometry": {"coordinates":[-93.252594,44.908703],"type":"Point"}
}