{
  "type": "Feature",
  "properties": {
    "addr:full":"102 E Main St Hardwick MN 56134",
    "addr:housenumber":"102",
    "addr:postcode":"56134",
    "addr:street":"E Main St",
    "iso:country":"US",
    "sg:address":"102 E Main St",
    "sg:city":"Hardwick",
    "sg:classifiers":[
        {
            "category":"Banks & Credit Unions",
            "subcategory":"Bank",
            "type":"Services"
        }
    ],
    "sg:phone":"+1 507 669 2150",
    "sg:postcode":"56134",
    "sg:province":"MN",
    "sg:tags":[
        "loan"
    ],
    "wof:name":"Hardwick State Bank",
    "wof:placetype":"venue"
},
  "geometry": {"coordinates":[-96.1995,43.774575],"type":"Point"}
}