{
  "type": "Feature",
  "properties": {
    "addr:full":"3200 White Bear Ave Saint Paul MN 55110",
    "addr:housenumber":"3200",
    "addr:postcode":"55110",
    "addr:street":"White Bear Ave",
    "iso:country":"US",
    "sg:address":"3200 White Bear Ave",
    "sg:city":"Saint Paul",
    "sg:classifiers":[
        {
            "category":"Bars & Pubs",
            "type":"Food & Drink"
        }
    ],
    "sg:phone":"+1 651 770 3582",
    "sg:postcode":"55110",
    "sg:province":"MN",
    "sg:tags":[
        "tavern"
    ],
    "wof:name":"Doc's Landing",
    "wof:placetype":"venue"
},
  "geometry": {"coordinates":[-93.01740100000001,45.039116],"type":"Point"}
}