{
  "type": "Feature",
  "properties": {
    "iso:country":"US",
    "sg:address":"6287 Monticello Ln N",
    "sg:city":"Maple Grove",
    "sg:classifiers":[
        {
            "category":"Retail",
            "subcategory":"Laundry & Dry Cleaning",
            "type":"Services"
        }
    ],
    "sg:phone":"+1 612 328 1543",
    "sg:postcode":"55369",
    "sg:province":"MN",
    "sg:tags":[
        "cleaners",
        "rug",
        "carpet"
    ],
    "wof:name":"Reliable Cleanings Svc",
    "wof:placetype":"venue"
},
  "geometry": {"coordinates":[-93.40451299999999,45.069234],"type":"Point"}
}