{
  "type": "Feature",
  "properties": {
    "iso:country":"US",
    "sg:address":"1060 W Laurel Ave",
    "sg:city":"Saint Paul",
    "sg:classifiers":[
        {
            "category":"Professional",
            "subcategory":"Employment Agencies",
            "type":"Services"
        }
    ],
    "sg:phone":"+1 651 222 4988",
    "sg:postcode":"55104",
    "sg:province":"MN",
    "wof:name":"Nielsen Rescource Solutions",
    "wof:placetype":"venue"
},
  "geometry": {"coordinates":[-93.146004,44.944925],"type":"Point"}
}