{
  "type": "Feature",
  "properties": {
    "addr:full":"5865 River Ridge Ct NE Rochester MN 55906",
    "addr:housenumber":"5865",
    "addr:postcode":"55906",
    "addr:street":"River Ridge Ct Ne",
    "iso:country":"US",
    "sg:address":"5865 River Ridge Ct NE",
    "sg:city":"Rochester",
    "sg:classifiers":[
        {
            "category":"Manufacturing",
            "subcategory":"Watercraft",
            "type":"Manufacturing & Wholesale Goods"
        }
    ],
    "sg:phone":"+1 507 288 2750",
    "sg:postcode":"55906",
    "sg:province":"MN",
    "sg:tags":[
        "sporting"
    ],
    "wof:name":"River Ridge Custom Canoes LLC",
    "wof:placetype":"venue"
},
  "geometry": {"coordinates":[-92.449049,44.087015],"type":"Point"}
}