{
  "type": "Feature",
  "properties": {
    "addr:full":"3119 Van Ave NE Alexandria MN 56308",
    "addr:housenumber":"3119",
    "addr:postcode":"56308",
    "addr:street":"Van Ave Ne",
    "iso:country":"US",
    "sg:address":"3119 Van Ave NE",
    "sg:city":"Alexandria",
    "sg:classifiers":[
        {
            "category":"Health Services",
            "subcategory":"Doctor",
            "type":"Services"
        }
    ],
    "sg:phone":"+1 320 762 2692",
    "sg:postcode":"56308",
    "sg:province":"MN",
    "sg:tags":[
        "physician",
        "surgeon"
    ],
    "wof:name":"P M Geiser MD",
    "wof:placetype":"venue"
},
  "geometry": {"coordinates":[-95.353364,45.925177],"type":"Point"}
}