{
  "type": "Feature",
  "properties": {
    "addr:full":"3420 46th Ave N Minneapolis MN 55422",
    "addr:housenumber":"3420",
    "addr:postcode":"55422",
    "addr:street":"46Th Ave N",
    "iso:country":"US",
    "sg:address":"3420 46th Ave N",
    "sg:city":"Minneapolis",
    "sg:classifiers":[
        {
            "category":"Real Estate",
            "subcategory":"Real Estate Operator",
            "type":"Services"
        }
    ],
    "sg:phone":"+1 763 971 5223",
    "sg:postcode":"55422",
    "sg:province":"MN",
    "sg:tags":[
        "building",
        "nonresidential"
    ],
    "wof:name":"E & F Properties LLC",
    "wof:placetype":"venue"
},
  "geometry": {"coordinates":[-93.32347799999999,45.03859],"type":"Point"}
}