{
  "type": "Feature",
  "properties": {
    "addr:full":"386 Wabasha St N St Paul MN 55102",
    "addr:housenumber":"386",
    "addr:postcode":"55102",
    "addr:street":"Wabasha St N",
    "iso:country":"US",
    "sg:address":"386 Wabasha St N",
    "sg:city":"St Paul",
    "sg:classifiers":[
        {
            "category":"Professional",
            "subcategory":"Lawyer & Legal Services",
            "type":"Services"
        }
    ],
    "sg:phone":"+1 651 291 1177",
    "sg:postcode":"55102",
    "sg:province":"MN",
    "sg:tags":[
        "attorney"
    ],
    "sg:website":"www.goklawfirm.com",
    "wof:name":"Geraghty O'Loughlin & Kenney",
    "wof:placetype":"venue"
},
  "geometry": {"coordinates":[-93.09477099999999,44.945949],"type":"Point"}
}