{
  "type": "Feature",
  "properties": {
    "addr:full":"1106 10th Dr SE Austin MN 55912",
    "addr:housenumber":"1106",
    "addr:postcode":"55912",
    "addr:street":"10Th Dr Se",
    "iso:country":"US",
    "sg:address":"1106 10th Dr SE",
    "sg:city":"Austin",
    "sg:classifiers":[
        {
            "category":"Home & Garden",
            "subcategory":"Furniture",
            "type":"Retail Goods"
        }
    ],
    "sg:phone":"+1 507 437 4891",
    "sg:postcode":"55912",
    "sg:province":"MN",
    "sg:tags":[
        "cabinet"
    ],
    "wof:name":"Gary Granle Enterprises",
    "wof:placetype":"venue"
},
  "geometry": {"coordinates":[-92.957945,43.65664],"type":"Point"}
}