{
  "type": "Feature",
  "properties": {
    "iso:country":"US",
    "sg:address":"425 13th Ave SE",
    "sg:city":"Minneapolis",
    "sg:classifiers":[
        {
            "category":"Personal",
            "subcategory":"Beauty Salon",
            "type":"Services"
        }
    ],
    "sg:phone":"+1 612 378 0842",
    "sg:postcode":"55414",
    "sg:province":"MN",
    "sg:tags":[
        "hair"
    ],
    "wof:name":"J2c2 Inc",
    "wof:placetype":"venue"
},
  "geometry": {"coordinates":[-93.236548,44.981815],"type":"Point"}
}