{
  "type": "Feature",
  "properties": {
    "iso:country":"US",
    "sg:address":"558 Pacific Ave",
    "sg:city":"Hancock",
    "sg:classifiers":[
        {
            "category":"Travel",
            "subcategory":"Bed & Breakfast",
            "type":"Entertainment"
        }
    ],
    "sg:phone":"+1 320 392 5211",
    "sg:postcode":"56244",
    "sg:province":"MN",
    "wof:name":"Williams Home",
    "wof:placetype":"venue"
},
  "geometry": {"coordinates":[-95.796707,45.496096],"type":"Point"}
}