{
  "type": "Feature",
  "properties": {
    "addr:full":"3718 Vincent Ave N Minneapolis MN 55412",
    "addr:housenumber":"3718",
    "addr:postcode":"55412",
    "addr:street":"Vincent Ave N",
    "iso:country":"US",
    "sg:address":"3718 Vincent Ave N",
    "sg:city":"Minneapolis",
    "sg:classifiers":[
        {
            "category":"Retail",
            "subcategory":"Repair Shop",
            "type":"Services"
        }
    ],
    "sg:phone":"+1 612 520 4078",
    "sg:postcode":"55412",
    "sg:province":"MN",
    "wof:name":"Instrument Repair Service",
    "wof:placetype":"venue"
},
  "geometry": {"coordinates":[-93.31589,45.023764],"type":"Point"}
}