{
  "type": "Feature",
  "properties": {
    "iso:country":"US",
    "sg:address":"612 Northwood Dr",
    "sg:city":"Redwood Falls",
    "sg:classifiers":[
        {
            "category":"Retail",
            "subcategory":"Funeral Services",
            "type":"Services"
        }
    ],
    "sg:phone":"+1 507 637 5877",
    "sg:postcode":"56283",
    "sg:province":"MN",
    "wof:name":"Redwood Valley Funeral Home",
    "wof:placetype":"venue"
},
  "geometry": {"coordinates":[-95.098225,44.547523],"type":"Point"}
}