{
  "type": "Feature",
  "properties": {
    "addr:full":"110 Century Dr Minneota MN 56264",
    "addr:housenumber":"110",
    "addr:postcode":"56264",
    "addr:street":"Century Dr Minneota",
    "iso:country":"US",
    "sg:address":"110 Century Dr",
    "sg:city":"Minneota",
    "sg:classifiers":[
        {
            "category":"Organizations",
            "subcategory":"Community Association",
            "type":"Services"
        }
    ],
    "sg:phone":"+1 507 872 6277",
    "sg:postcode":"56264",
    "sg:province":"MN",
    "sg:tags":[
        "center",
        "bowling"
    ],
    "wof:name":"Legion Lanes Bowling",
    "wof:placetype":"venue"
},
  "geometry": {"coordinates":[-95.9898,44.55668],"type":"Point"}
}