{
  "type": "Feature",
  "properties": {
    "iso:country":"US",
    "sg:address":"2521 Miller Trunk Hwy",
    "sg:city":"Duluth",
    "sg:classifiers":[
        {
            "category":"Retail",
            "subcategory":"Auto Rental",
            "type":"Services"
        }
    ],
    "sg:phone":"+1 218 722 4181",
    "sg:postcode":"55811",
    "sg:province":"MN",
    "sg:tags":[
        "car"
    ],
    "wof:name":"ACAR Auto Rental",
    "wof:placetype":"venue"
},
  "geometry": {"coordinates":[-92.170323,46.812177],"type":"Point"}
}