{
  "type": "Feature",
  "properties": {
    "addr:full":"7162 72nd Ln N Minneapolis MN 55428",
    "addr:housenumber":"7162",
    "addr:postcode":"55428",
    "addr:street":"72Nd Ln N",
    "iso:country":"US",
    "sg:address":"7162 72nd Ln N",
    "sg:city":"Minneapolis",
    "sg:classifiers":[
        {
            "category":"Professional",
            "type":"Services"
        }
    ],
    "sg:phone":"+1 763 427 1056",
    "sg:postcode":"55428",
    "sg:province":"MN",
    "wof:name":"A1 Signing Services of MN",
    "wof:placetype":"venue"
},
  "geometry": {"coordinates":[-93.37327000000001,45.084853],"type":"Point"}
}