{
  "type": "Feature",
  "properties": {
    "addr:full":"3200 Northway Dr Minneapolis MN 55429",
    "addr:housenumber":"3200",
    "addr:postcode":"55429",
    "addr:street":"Northway Dr",
    "iso:country":"US",
    "sg:address":"3200 Northway Dr",
    "sg:city":"Minneapolis",
    "sg:classifiers":[
        {
            "category":"Banks & Credit Unions",
            "subcategory":"Bank",
            "type":"Services"
        }
    ],
    "sg:phone":"+1 763 560 7000",
    "sg:postcode":"55429",
    "sg:province":"MN",
    "sg:tags":[
        "state",
        "loan",
        "broker"
    ],
    "wof:name":"Energy Family Credit Union",
    "wof:placetype":"venue"
},
  "geometry": {"coordinates":[-93.320672,45.061047],"type":"Point"}
}