{
  "type": "Feature",
  "properties": {
    "iso:country":"US",
    "sg:address":"41502 100th Ave",
    "sg:city":"Pelican Rapids",
    "sg:classifiers":[
        {
            "category":"Organizations",
            "subcategory":"Religious Organization",
            "type":"Services"
        }
    ],
    "sg:phone":"+1 218 867 2327",
    "sg:postcode":"56572",
    "sg:province":"MN",
    "wof:name":"South Immanuel Church",
    "wof:placetype":"venue"
},
  "geometry": {"coordinates":[-96.281069,46.558946],"type":"Point"}
}