{
  "type": "Feature",
  "properties": {
    "iso:country":"US",
    "sg:address":"4808 Stinson Blvd",
    "sg:city":"Minneapolis",
    "sg:classifiers":[
        {
            "category":"Health Services",
            "subcategory":"Doctor",
            "type":"Services"
        },
        {
            "category":"Health Services",
            "subcategory":"Hospital",
            "type":"Services"
        }
    ],
    "sg:phone":"+1 763 574 1603",
    "sg:postcode":"55421",
    "sg:province":"MN",
    "sg:tags":[
        "nursing",
        "consultant",
        "medical",
        "practice",
        "home"
    ],
    "wof:name":"Mn Consulting",
    "wof:placetype":"venue"
},
  "geometry": {"coordinates":[-93.22706100000001,45.056072],"type":"Point"}
}