{
  "type": "Feature",
  "properties": {
    "iso:country":"US",
    "sg:address":"3301 Labore Rd",
    "sg:city":"Saint Paul",
    "sg:classifiers":[
        {
            "category":"Manufacturing",
            "subcategory":"Tools & Machinery",
            "type":"Manufacturing & Wholesale Goods"
        }
    ],
    "sg:phone":"+1 651 486 0475",
    "sg:postcode":"55110",
    "sg:province":"MN",
    "sg:tags":[
        "screen",
        "stencil",
        "mfg"
    ],
    "wof:name":"Hybrid Screen Technologies",
    "wof:placetype":"venue"
},
  "geometry": {"coordinates":[-93.05677300000001,45.043091],"type":"Point"}
}