{
  "type": "Feature",
  "properties": {
    "addr:full":"22908 285th Ave Akeley MN 56433",
    "addr:housenumber":"22908",
    "addr:postcode":"56433",
    "addr:street":"285Th Ave",
    "iso:country":"US",
    "sg:address":"22908 285th Ave",
    "sg:city":"Akeley",
    "sg:classifiers":[
        {
            "category":"Building & Trades",
            "subcategory":"Construction",
            "type":"Services"
        }
    ],
    "sg:phone":"+1 218 652 4780",
    "sg:postcode":"56433",
    "sg:province":"MN",
    "sg:tags":[
        "resurfacing",
        "laying",
        "refinishing",
        "floor"
    ],
    "wof:name":"Ron F Massar Flooring",
    "wof:placetype":"venue"
},
  "geometry": {"coordinates":[-94.76981600000001,46.99151],"type":"Point"}
}