{
  "type": "Feature",
  "properties": {
    "iso:country":"US",
    "sg:address":"75721 350th Ave",
    "sg:city":"Round Lake",
    "sg:phone":"+1 507 945 8328",
    "sg:postcode":"56167",
    "sg:province":"MN",
    "sg:tags":[
        "farm",
        "corn",
        "grain",
        "cash"
    ],
    "wof:name":"Steven Koster",
    "wof:placetype":"venue"
},
  "geometry": {"coordinates":[-95.3749,43.579245],"type":"Point"}
}