{
  "type": "Feature",
  "properties": {
    "addr:full":"6811 Kingston Dr Eden Prairie MN 55346",
    "addr:housenumber":"6811",
    "addr:postcode":"55346",
    "addr:street":"Kingston Dr",
    "iso:country":"US",
    "sg:address":"6811 Kingston Dr",
    "sg:city":"Eden Prairie",
    "sg:classifiers":[
        {
            "category":"Building & Trades",
            "subcategory":"Construction",
            "type":"Services"
        }
    ],
    "sg:phone":"+1 952 949 3752",
    "sg:postcode":"55346",
    "sg:province":"MN",
    "sg:tags":[
        "contractor"
    ],
    "wof:name":"Mosman Inc",
    "wof:placetype":"venue"
},
  "geometry": {"coordinates":[-93.457443,44.877328],"type":"Point"}
}