{
  "type": "Feature",
  "properties": {
    "iso:country":"US",
    "sg:address":"500 Franklin St N",
    "sg:city":"Glenwood",
    "sg:classifiers":[
        {
            "category":"Real Estate",
            "subcategory":"Real Estate Operator",
            "type":"Services"
        }
    ],
    "sg:phone":"+1 320 634 0022",
    "sg:postcode":"56334",
    "sg:province":"MN",
    "sg:tags":[
        "apartment"
    ],
    "wof:name":"Glenwood Estates",
    "wof:placetype":"venue"
},
  "geometry": {"coordinates":[-95.389993,45.654403],"type":"Point"}
}