{
  "type": "Feature",
  "properties": {
    "addr:full":"5249 Green Gables Rd NW Brainerd MN 56401",
    "addr:housenumber":"5249",
    "addr:postcode":"56401",
    "addr:street":"Green Gables Rd Nw",
    "iso:country":"US",
    "sg:address":"5249 Green Gables Rd NW",
    "sg:city":"Brainerd",
    "sg:classifiers":[
        {
            "category":"Building & Trades",
            "subcategory":"Plumbing",
            "type":"Services"
        }
    ],
    "sg:phone":"+1 218 963 4889",
    "sg:postcode":"56401",
    "sg:province":"MN",
    "sg:tags":[
        "plumbing",
        "contractor"
    ],
    "wof:name":"Oaks Plumbing & Heating",
    "wof:placetype":"venue"
},
  "geometry": {"coordinates":[-94.312746,46.42752],"type":"Point"}
}