{
  "type": "Feature",
  "properties": {
    "addr:full":"807 S Rum River Dr Princeton MN 55371",
    "addr:housenumber":"807",
    "addr:postcode":"55371",
    "addr:street":"S Rum River Dr",
    "iso:country":"US",
    "sg:address":"807 S Rum River Dr",
    "sg:city":"Princeton",
    "sg:classifiers":[
        {
            "category":"Restaurant",
            "type":"Food & Drink"
        }
    ],
    "sg:menulink":"http://www.allmenus.com/mn/princeton/80109-pizza-hut/menu/",
    "sg:phone":"+1 763 389 3600",
    "sg:postcode":"55371",
    "sg:province":"MN",
    "sg:tags":[
        "american",
        "pizza"
    ],
    "wof:name":"Pizza Hut",
    "wof:placetype":"venue"
},
  "geometry": {"coordinates":[-93.58075100000001,45.560858],"type":"Point"}
}