{
  "type": "Feature",
  "properties": {
    "addr:full":"9892 260th St E Cannon Falls MN 55009",
    "addr:housenumber":"9892",
    "addr:postcode":"55009",
    "addr:street":"260Th St E",
    "iso:country":"US",
    "sg:address":"9892 260th St E",
    "sg:city":"Cannon Falls",
    "sg:classifiers":[
        {
            "category":"Farming",
            "subcategory":"Livestock Farm",
            "type":"Manufacturing & Wholesale Goods"
        }
    ],
    "sg:phone":"+1 507 263 2590",
    "sg:postcode":"55009",
    "sg:province":"MN",
    "sg:tags":[
        "beef",
        "feedlot",
        "cattle"
    ],
    "wof:name":"George Feidt",
    "wof:placetype":"venue"
},
  "geometry": {"coordinates":[-92.913928,44.572238],"type":"Point"}
}