{
  "type": "Feature",
  "properties": {
    "addr:full":"2751 Hennepin Avenue Suite 600 Minneapolis MN 55408",
    "addr:housenumber":"2751",
    "addr:postcode":"55408",
    "addr:street":"Hennepin Avenue Suite 600",
    "iso:country":"US",
    "sg:address":"2751 Hennepin Avenue Suite 600",
    "sg:city":"Minneapolis",
    "sg:classifiers":[
        {
            "category":"Restaurant",
            "type":"Food & Drink"
        }
    ],
    "sg:phone":"+1 651 204 9191",
    "sg:postcode":"55408",
    "sg:province":"MN",
    "sg:tags":[
        "chinese"
    ],
    "sg:website":"www.fooddeliveryminneapolis.com/...",
    "wof:name":"Minneapolis Food Delivery",
    "wof:placetype":"venue"
},
  "geometry": {"coordinates":[-93.297966,44.952824],"type":"Point"}
}