{
  "type": "Feature",
  "properties": {
    "iso:country":"US",
    "sg:address":"4035 Norex Dr",
    "sg:city":"Chaska",
    "sg:classifiers":[
        {
            "category":"Shopping",
            "subcategory":"Gifts & Souvenirs",
            "type":"Retail Goods"
        }
    ],
    "sg:phone":"+1 952 361 9559",
    "sg:postcode":"55318",
    "sg:province":"MN",
    "sg:tags":[
        "flower"
    ],
    "wof:name":"Rasmussen Import Company",
    "wof:placetype":"venue"
},
  "geometry": {"coordinates":[-93.611397,44.8097],"type":"Point"}
}