{
  "type": "Feature",
  "properties": {
    "addr:full":"634 2nd St Kenyon MN 55946",
    "addr:housenumber":"634",
    "addr:postcode":"55946",
    "addr:street":"2Nd St",
    "iso:country":"US",
    "sg:address":"634 2nd St",
    "sg:city":"Kenyon",
    "sg:classifiers":[
        {
            "category":"Professional",
            "subcategory":"Lawyer & Legal Services",
            "type":"Services"
        }
    ],
    "sg:phone":"+1 507 789 6667",
    "sg:postcode":"55946",
    "sg:province":"MN",
    "sg:tags":[
        "attorney",
        "trust",
        "estate",
        "wills",
        "planning",
        "plan",
        "criminal",
        "law"
    ],
    "sg:website":"http://www.davidjacobsenlaw.com/contact.html",
    "wof:name":"The Law Office of David W. Jacobsen LLC",
    "wof:placetype":"venue"
},
  "geometry": {"coordinates":[-92.987205,44.272041],"type":"Point"}
}