{
  "type": "Feature",
  "properties": {
    "addr:full":"720 4th Ave S St Cloud MN 56301",
    "addr:housenumber":"720",
    "addr:postcode":"56301",
    "addr:street":"4Th Ave S",
    "iso:country":"US",
    "sg:address":"720 4th Ave S",
    "sg:city":"St Cloud",
    "sg:classifiers":[
        {
            "category":"Education",
            "subcategory":"Library",
            "type":"Public Place"
        }
    ],
    "sg:phone":"+1 320 255 2084",
    "sg:postcode":"56301",
    "sg:province":"MN",
    "sg:tags":[
        "special",
        "interest"
    ],
    "wof:name":"Learning Resource & Tech Svc",
    "wof:placetype":"venue"
},
  "geometry": {"coordinates":[-94.15294799999999,45.552697],"type":"Point"}
}