{
  "type": "Feature",
  "properties": {
    "iso:country":"US",
    "sg:address":"574 Prairie Center Dr",
    "sg:city":"Eden Prairie",
    "sg:classifiers":[
        {
            "category":"Organizations",
            "subcategory":"Professional Association",
            "type":"Services"
        }
    ],
    "sg:phone":"+1 423 504 3816",
    "sg:postcode":"55344",
    "sg:province":"MN",
    "sg:tags":[
        "woodworker"
    ],
    "wof:name":"Cabinet Makers Association",
    "wof:placetype":"venue"
},
  "geometry": {"coordinates":[-93.430458,44.851578],"type":"Point"}
}