{
  "type": "Feature",
  "properties": {
    "addr:full":"14026 State Hwy 78 Battle Lake MN 56515",
    "addr:housenumber":"14026",
    "addr:postcode":"56515",
    "addr:street":"State Hwy 78",
    "iso:country":"US",
    "sg:address":"14026 State Hwy 78",
    "sg:city":"Battle Lake",
    "sg:classifiers":[
        {
            "category":"Professional",
            "type":"Services"
        }
    ],
    "sg:phone":"+1 218 864 8010",
    "sg:postcode":"56515",
    "sg:province":"MN",
    "wof:name":"Eagle Capital Svc",
    "wof:placetype":"venue"
},
  "geometry": {"coordinates":[-95.70835599999999,46.169339],"type":"Point"}
}