{
  "type": "Feature",
  "properties": {
    "addr:full":"6105 135th St W Lonsdale MN 55046",
    "addr:housenumber":"6105",
    "addr:postcode":"55046",
    "addr:street":"135Th St W",
    "iso:country":"US",
    "sg:address":"6105 135th St W",
    "sg:city":"Lonsdale",
    "sg:phone":"+1 507 332 7888",
    "sg:postcode":"55046",
    "sg:province":"MN",
    "sg:tags":[
        "farm",
        "corn"
    ],
    "wof:name":"Roger Ross",
    "wof:placetype":"venue"
},
  "geometry": {"coordinates":[-93.38489199999999,44.3925],"type":"Point"}
}