{
  "type": "Feature",
  "properties": {
    "addr:full":"41384 State Hwy 13 Waseca MN 56093",
    "addr:housenumber":"41384",
    "addr:postcode":"56093",
    "addr:street":"State Hwy 13",
    "iso:country":"US",
    "sg:address":"41384 State Hwy 13",
    "sg:city":"Waseca",
    "sg:classifiers":[
        {
            "category":"Retail",
            "subcategory":"Repair Shop",
            "type":"Services"
        }
    ],
    "sg:phone":"+1 507 835 7085",
    "sg:postcode":"56093",
    "sg:province":"MN",
    "sg:tags":[
        "engine",
        "locomotive",
        "maintenance"
    ],
    "wof:name":"Rail Works Inc",
    "wof:placetype":"venue"
},
  "geometry": {"coordinates":[-93.507301,44.159462],"type":"Point"}
}