{
  "type": "Feature",
  "properties": {
    "iso:country":"US",
    "sg:address":"6110 Nicollet Ave",
    "sg:city":"Minneapolis",
    "sg:classifiers":[
        {
            "category":"Professional",
            "subcategory":"Business Services",
            "type":"Services"
        },
        {
            "category":"Real Estate",
            "subcategory":"Real Estate Operator",
            "type":"Services"
        }
    ],
    "sg:phone":"+1 612 866 1178",
    "sg:postcode":"55419",
    "sg:province":"MN",
    "sg:tags":[
        "mall",
        "shopping",
        "center"
    ],
    "wof:name":"E Enterprises",
    "wof:placetype":"venue"
},
  "geometry": {"coordinates":[-93.278181,44.89086],"type":"Point"}
}