{
  "type": "Feature",
  "properties": {
    "iso:country":"US",
    "sg:address":"8206 Thomas Ave S",
    "sg:city":"Minneapolis",
    "sg:classifiers":[
        {
            "category":"Recreation",
            "subcategory":"Fishing",
            "type":"Entertainment"
        }
    ],
    "sg:phone":"+1 952 888 6554",
    "sg:postcode":"55431",
    "sg:province":"MN",
    "sg:tags":[
        "tackle",
        "tackle-wholesale",
        "manufacturer"
    ],
    "wof:name":"Hawkland Wholesale",
    "wof:placetype":"venue"
},
  "geometry": {"coordinates":[-93.314172,44.854023],"type":"Point"}
}