{
  "type": "Feature",
  "properties": {
    "addr:full":"7455 180th St E Prior Lake MN 55372",
    "addr:housenumber":"7455",
    "addr:postcode":"55372",
    "addr:street":"180Th St E",
    "iso:country":"US",
    "sg:address":"7455 180th St E",
    "sg:city":"Prior Lake",
    "sg:classifiers":[
        {
            "category":"Manufacturing",
            "subcategory":"Motor Vehicles & Parts",
            "type":"Manufacturing & Wholesale Goods"
        }
    ],
    "sg:phone":"+1 952 226 5110",
    "sg:postcode":"55372",
    "sg:province":"MN",
    "sg:tags":[
        "equipment",
        "transportation",
        "mfg"
    ],
    "wof:name":"Midwest Atv",
    "wof:placetype":"venue"
},
  "geometry": {"coordinates":[-93.375917,44.688608],"type":"Point"}
}