{
  "type": "Feature",
  "properties": {
    "addr:full":"18450 Country Squires Cir Prior Lake MN 55372",
    "addr:housenumber":"18450",
    "addr:postcode":"55372",
    "addr:street":"Country Squires Cir",
    "iso:country":"US",
    "sg:address":"18450 Country Squires Cir",
    "sg:city":"Prior Lake",
    "sg:classifiers":[
        {
            "category":"Retail",
            "subcategory":"Auto Repair",
            "type":"Services"
        }
    ],
    "sg:phone":"+1 952 447 4169",
    "sg:postcode":"55372",
    "sg:province":"MN",
    "sg:tags":[
        "equipment",
        "chassis",
        "truck",
        "alteration"
    ],
    "wof:name":"Fleury Hot Rods",
    "wof:placetype":"venue"
},
  "geometry": {"coordinates":[-93.458474,44.682276],"type":"Point"}
}