{
  "type": "Feature",
  "properties": {
    "addr:full":"708 Fremont St Anoka MN 55303",
    "addr:housenumber":"708",
    "addr:postcode":"55303",
    "addr:street":"Fremont St",
    "iso:country":"US",
    "sg:address":"708 Fremont St",
    "sg:city":"Anoka",
    "sg:classifiers":[
        {
            "category":"Professional",
            "type":"Services"
        },
        {
            "category":"Shopping",
            "subcategory":"Party Supplies",
            "type":"Retail Goods"
        }
    ],
    "sg:phone":"+1 763 421 0995",
    "sg:postcode":"55303",
    "sg:province":"MN",
    "sg:tags":[
        "caterer",
        "wedding"
    ],
    "wof:name":"Lisa's Catering",
    "wof:placetype":"venue"
},
  "geometry": {"coordinates":[-93.400961,45.198045],"type":"Point"}
}