{
  "type": "Feature",
  "properties": {
    "addr:full":"4066 Brandon Rd Brookston MN 55711",
    "addr:housenumber":"4066",
    "addr:postcode":"55711",
    "addr:street":"Brandon Rd",
    "iso:country":"US",
    "sg:address":"4066 Brandon Rd",
    "sg:city":"Brookston",
    "sg:classifiers":[
        {
            "category":"Recreation",
            "type":"Entertainment"
        }
    ],
    "sg:phone":"+1 218 878 0456",
    "sg:postcode":"55711",
    "sg:province":"MN",
    "wof:name":"Medicine Horse Riding Center",
    "wof:placetype":"venue"
},
  "geometry": {"coordinates":[-92.70155800000001,46.800363],"type":"Point"}
}