{
  "type": "Feature",
  "properties": {
    "addr:full":"117 Broadway E Little Falls MN 56345",
    "addr:housenumber":"117",
    "addr:postcode":"56345",
    "addr:street":"Broadway E",
    "iso:country":"US",
    "sg:address":"117 Broadway E",
    "sg:city":"Little Falls",
    "sg:classifiers":[
        {
            "category":"Banks & Credit Unions",
            "subcategory":"Investment Brokerage",
            "type":"Services"
        }
    ],
    "sg:phone":"+1 320 632 9475",
    "sg:postcode":"56345",
    "sg:province":"MN",
    "sg:tags":[
        "security"
    ],
    "wof:name":"Edward Jones 09080",
    "wof:placetype":"venue"
},
  "geometry": {"coordinates":[-94.362337,45.976483],"type":"Point"}
}