{
  "type": "Feature",
  "properties": {
    "iso:country":"US",
    "sg:address":"1260 120th St",
    "sg:city":"Welcome",
    "sg:classifiers":[
        {
            "category":"Building & Trades",
            "subcategory":"Construction",
            "type":"Services"
        }
    ],
    "sg:phone":"+1 507 728 8608",
    "sg:postcode":"56181",
    "sg:province":"MN",
    "sg:tags":[
        "excavating",
        "contractor"
    ],
    "wof:name":"Rosburg Construction",
    "wof:placetype":"venue"
},
  "geometry": {"coordinates":[-94.62249799999999,43.659882],"type":"Point"}
}