{
  "type": "Feature",
  "properties": {
    "addr:full":"701 Plymouth Ave N Minneapolis MN 55411",
    "addr:housenumber":"701",
    "addr:postcode":"55411",
    "addr:street":"Plymouth Ave N",
    "iso:country":"US",
    "sg:address":"701 Plymouth Ave N",
    "sg:city":"Minneapolis",
    "sg:classifiers":[
        {
            "category":"Manufacturing",
            "subcategory":"Printing",
            "type":"Manufacturing & Wholesale Goods"
        }
    ],
    "sg:phone":"+1 612 522 4406",
    "sg:postcode":"55411",
    "sg:province":"MN",
    "sg:tags":[
        "bookbinder",
        "book",
        "binding"
    ],
    "sg:website":"http://www.mbbindery.com",
    "wof:name":"Muscle Bound Bindery",
    "wof:placetype":"venue"
},
  "geometry": {"coordinates":[-93.287987,44.991928],"type":"Point"}
}