{
  "type": "Feature",
  "properties": {
    "addr:full":"418 Ash St S Browns Valley MN 56219",
    "addr:housenumber":"418",
    "addr:postcode":"56219",
    "addr:street":"Ash St S Browns",
    "iso:country":"US",
    "sg:address":"418 Ash St S",
    "sg:city":"Browns Valley",
    "sg:classifiers":[
        {
            "category":"Organizations",
            "subcategory":"Religious Organization",
            "type":"Services"
        }
    ],
    "sg:phone":"+1 320 695 2516",
    "sg:postcode":"56219",
    "sg:province":"MN",
    "sg:tags":[
        "church"
    ],
    "wof:name":"United Methodist Prsbytrn Chr",
    "wof:placetype":"venue"
},
  "geometry": {"coordinates":[-96.82804899999999,45.59047],"type":"Point"}
}