{
  "type": "Feature",
  "properties": {
    "iso:country":"US",
    "sg:address":"212 3rd Ave S",
    "sg:city":"Minneapolis",
    "sg:classifiers":[
        {
            "category":"Wholesale",
            "subcategory":"Scrap",
            "type":"Manufacturing & Wholesale Goods"
        }
    ],
    "sg:phone":"+1 612 375 9381",
    "sg:postcode":"55401",
    "sg:province":"MN",
    "sg:tags":[
        "metal"
    ],
    "wof:name":"Residual Materials Inc",
    "wof:placetype":"venue"
},
  "geometry": {"coordinates":[-93.263915,44.980409],"type":"Point"}
}