{
  "type": "Feature",
  "properties": {
    "iso:country":"US",
    "sg:address":"3015 E Medicine Lake Blvd",
    "sg:city":"Plymouth",
    "sg:classifiers":[
        {
            "category":"Professional",
            "subcategory":"Lawyer & Legal Services",
            "type":"Services"
        }
    ],
    "sg:phone":"+1 763 545 4183",
    "sg:postcode":"55441",
    "sg:province":"MN",
    "sg:tags":[
        "divorce",
        "assistance"
    ],
    "wof:name":"AN R & R Paralegal Low Cost",
    "wof:placetype":"venue"
},
  "geometry": {"coordinates":[-93.41585000000001,45.013353],"type":"Point"}
}