{
  "type": "Feature",
  "properties": {
    "iso:country":"US",
    "sg:address":"13871 Eidelweiss St NW",
    "sg:city":"Andover",
    "sg:classifiers":[
        {
            "category":"Wholesale",
            "subcategory":"Toys & Hobbies",
            "type":"Manufacturing & Wholesale Goods"
        }
    ],
    "sg:phone":"+1 763 422 0220",
    "sg:postcode":"55304",
    "sg:province":"MN",
    "sg:tags":[
        "wholesaler"
    ],
    "wof:name":"Nybeck Golf Inc",
    "wof:placetype":"venue"
},
  "geometry": {"coordinates":[-93.33981,45.223193],"type":"Point"}
}