{
  "type": "Feature",
  "properties": {
    "iso:country":"US",
    "sg:address":"5554 Nantucket Pl",
    "sg:city":"Minnetonka",
    "sg:classifiers":[
        {
            "category":"Health Services",
            "subcategory":"Clinic",
            "type":"Services"
        }
    ],
    "sg:phone":"+1 952 937 5029",
    "sg:postcode":"55345",
    "sg:province":"MN",
    "sg:tags":[
        "home",
        "care"
    ],
    "wof:name":"Simply Essence",
    "wof:placetype":"venue"
},
  "geometry": {"coordinates":[-93.49747499999999,44.903473],"type":"Point"}
}