{
  "type": "Feature",
  "properties": {
    "iso:country":"US",
    "sg:address":"102 County Road 10",
    "sg:city":"Bovey",
    "sg:classifiers":[
        {
            "category":"Building & Trades",
            "subcategory":"Landscaping Services",
            "type":"Services"
        },
        {
            "category":"Social Services",
            "subcategory":"Retirement Home",
            "type":"Services"
        }
    ],
    "sg:phone":"+1 218 245 3550",
    "sg:postcode":"55709",
    "sg:province":"MN",
    "sg:tags":[
        "convalescent",
        "aged",
        "nursing",
        "homes-institutional"
    ],
    "wof:name":"Edgewood Care Inc",
    "wof:placetype":"venue"
},
  "geometry": {"coordinates":[-93.418584,47.289707],"type":"Point"}
}