{
  "type": "Feature",
  "properties": {
    "addr:full":"717 NE 4th St Grand Rapids MN 55744",
    "addr:housenumber":"717",
    "addr:postcode":"55744",
    "addr:street":"Ne 4Th St",
    "iso:country":"US",
    "sg:address":"717 NE 4th St",
    "sg:city":"Grand Rapids",
    "sg:classifiers":[
        {
            "category":"Health Services",
            "subcategory":"Clinic",
            "type":"Services"
        }
    ],
    "sg:phone":"+1 218 327 2001",
    "sg:postcode":"55744",
    "sg:province":"MN",
    "sg:tags":[
        "specialty",
        "outpatient"
    ],
    "wof:name":"Rapids Counseling Services",
    "wof:placetype":"venue"
},
  "geometry": {"coordinates":[-93.51622999999999,47.23598],"type":"Point"}
}