{
  "type": "Feature",
  "properties": {
    "addr:full":"813 Meander Ct Hamel MN 55340",
    "addr:housenumber":"813",
    "addr:postcode":"55340",
    "addr:street":"Meander Ct",
    "iso:country":"US",
    "sg:address":"813 Meander Ct",
    "sg:city":"Hamel",
    "sg:classifiers":[
        {
            "category":"Personal",
            "type":"Services"
        },
        {
            "category":"Professional",
            "subcategory":"Art Services",
            "type":"Services"
        }
    ],
    "sg:phone":"+1 763 478 9851",
    "sg:postcode":"55340",
    "sg:province":"MN",
    "sg:tags":[
        "photographers-portrait",
        "videography",
        "photography",
        "wedding"
    ],
    "sg:website":"http://www.michellesportraitdesign.com/",
    "wof:name":"Michelle's Portrait Design",
    "wof:placetype":"venue"
},
  "geometry": {"coordinates":[-93.542592,45.052892],"type":"Point"}
}