{
  "type": "Feature",
  "properties": {
    "addr:full":"107 11th St E Canby MN 56220",
    "addr:housenumber":"107",
    "addr:postcode":"56220",
    "addr:street":"11Th St E",
    "iso:country":"US",
    "sg:address":"107 11th St E",
    "sg:city":"Canby",
    "sg:classifiers":[
        {
            "category":"Professional",
            "subcategory":"Management & Consulting",
            "type":"Services"
        }
    ],
    "sg:phone":"+1 507 223 7114",
    "sg:postcode":"56220",
    "sg:province":"MN",
    "wof:name":"American Express",
    "wof:placetype":"venue"
},
  "geometry": {"coordinates":[-96.264791,44.716986],"type":"Point"}
}