{
  "type": "Feature",
  "properties": {
    "iso:country":"US",
    "sg:address":"9635 Humboldt Ave S",
    "sg:city":"Bloomington",
    "sg:classifiers":[
        {
            "category":"Building & Trades",
            "subcategory":"Construction",
            "type":"Services"
        }
    ],
    "sg:phone":"+1 612 209 8580",
    "sg:postcode":"55431",
    "sg:province":"MN",
    "sg:tags":[
        "siding",
        "contractor"
    ],
    "wof:name":"B Johnson Siding Roofing",
    "wof:placetype":"venue"
},
  "geometry": {"coordinates":[-93.29869600000001,44.828749],"type":"Point"}
}