{
  "type": "Feature",
  "properties": {
    "iso:country":"US",
    "sg:address":"7000 Cornelia Dr",
    "sg:city":"Edina",
    "sg:classifiers":[
        {
            "category":"Education",
            "subcategory":"School",
            "type":"Public Place"
        }
    ],
    "sg:phone":"+1 952 848 4600",
    "sg:postcode":"55435",
    "sg:province":"MN",
    "wof:name":"Cornelia Elementary School",
    "wof:placetype":"venue"
},
  "geometry": {"coordinates":[-93.335838,44.875229],"type":"Point"}
}