{
  "type": "Feature",
  "properties": {
    "addr:full":"33200 390th St Le Sueur MN 56058",
    "addr:housenumber":"33200",
    "addr:postcode":"56058",
    "addr:street":"390Th St",
    "iso:country":"US",
    "sg:address":"33200 390th St",
    "sg:city":"Le Sueur",
    "sg:phone":"+1 507 665 3801",
    "sg:postcode":"56058",
    "sg:province":"MN",
    "sg:tags":[
        "farm",
        "corn",
        "soybean"
    ],
    "wof:name":"Dan Heldberg",
    "wof:placetype":"venue"
},
  "geometry": {"coordinates":[-93.942223,44.384445],"type":"Point"}
}