{
  "type": "Feature",
  "properties": {
    "addr:full":"1844 Gold Trl St Paul MN 55122",
    "addr:housenumber":"1844",
    "addr:postcode":"55122",
    "addr:street":"Gold Trl",
    "iso:country":"US",
    "sg:address":"1844 Gold Trl",
    "sg:city":"St Paul",
    "sg:classifiers":[
        {
            "category":"Professional",
            "subcategory":"Management & Consulting",
            "type":"Services"
        }
    ],
    "sg:phone":"+1 651 686 9549",
    "sg:postcode":"55122",
    "sg:province":"MN",
    "sg:tags":[
        "promotion",
        "sales"
    ],
    "wof:name":"Curtco Sales Co",
    "wof:placetype":"venue"
},
  "geometry": {"coordinates":[-93.197282,44.814917],"type":"Point"}
}