{
  "type": "Feature",
  "properties": {
    "addr:full":"128 2nd Ave SE Elgin MN 55932",
    "addr:housenumber":"128",
    "addr:postcode":"55932",
    "addr:street":"2Nd Ave Se",
    "iso:country":"US",
    "sg:address":"128 2nd Ave SE",
    "sg:city":"Elgin",
    "sg:classifiers":[
        {
            "category":"Health Services",
            "subcategory":"Chiropractor",
            "type":"Services"
        }
    ],
    "sg:phone":"+1 507 876 9997",
    "sg:postcode":"55932",
    "sg:province":"MN",
    "wof:name":"Urbain Family Chiropractic",
    "wof:placetype":"venue"
},
  "geometry": {"coordinates":[-92.24933900000001,44.128873],"type":"Point"}
}