{
  "type": "Feature",
  "properties": {
    "iso:country":"US",
    "sg:address":"730 Bunker Lake Blvd NW",
    "sg:city":"Anoka",
    "sg:classifiers":[
        {
            "category":"Building & Trades",
            "subcategory":"Construction",
            "type":"Services"
        }
    ],
    "sg:phone":"+1 763 421 1152",
    "sg:postcode":"55303",
    "sg:province":"MN",
    "sg:tags":[
        "contractor"
    ],
    "wof:name":"Reshetar Construction Inc",
    "wof:placetype":"venue"
},
  "geometry": {"coordinates":[-93.39939200000001,45.224034],"type":"Point"}
}