{
  "type": "Feature",
  "properties": {
    "addr:full":"6200 560th St Pine City MN 55063",
    "addr:housenumber":"6200",
    "addr:postcode":"55063",
    "addr:street":"560Th St",
    "iso:country":"US",
    "sg:address":"6200 560th St",
    "sg:city":"Pine City",
    "sg:classifiers":[
        {
            "category":"Farming",
            "subcategory":"Aquatic Farm",
            "type":"Manufacturing & Wholesale Goods"
        }
    ],
    "sg:phone":"+1 320 629 7140",
    "sg:postcode":"55063",
    "sg:province":"MN",
    "wof:name":"Douglas Johnson",
    "wof:placetype":"venue"
},
  "geometry": {"coordinates":[-92.983318,45.75927],"type":"Point"}
}