{
  "type": "Feature",
  "properties": {
    "iso:country":"US",
    "sg:address":"4600 W 77th St Ste 305",
    "sg:city":"Minneapolis",
    "sg:classifiers":[
        {
            "category":"Wholesale",
            "subcategory":"Farm Supplies",
            "type":"Manufacturing & Wholesale Goods"
        }
    ],
    "sg:phone":"+1 952 830 0058",
    "sg:postcode":"55435",
    "sg:province":"MN",
    "sg:tags":[
        "equipment"
    ],
    "wof:name":"Lost Creek Farms Inc",
    "wof:placetype":"venue"
},
  "geometry": {"coordinates":[-93.343681,44.863171],"type":"Point"}
}