{
  "type": "Feature",
  "properties": {
    "addr:full":"623 3rd St Madison MN 56256",
    "addr:housenumber":"623",
    "addr:postcode":"56256",
    "addr:street":"3Rd St",
    "iso:country":"US",
    "sg:address":"623 3rd St",
    "sg:city":"Madison",
    "sg:classifiers":[
        {
            "category":"Communications",
            "subcategory":"Radio Station",
            "type":"Services"
        }
    ],
    "sg:phone":"+1 320 598 7301",
    "sg:postcode":"56256",
    "sg:province":"MN",
    "sg:tags":[
        "company",
        "broadcasting"
    ],
    "wof:name":"KLQP",
    "wof:placetype":"venue"
},
  "geometry": {"coordinates":[-96.19364299999999,45.011204],"type":"Point"}
}