{
  "type": "Feature",
  "properties": {
    "iso:country":"US",
    "sg:address":"1135 W Main St Ste 104",
    "sg:city":"Anoka",
    "sg:classifiers":[
        {
            "category":"Personal",
            "subcategory":"Beauty Salon",
            "type":"Services"
        }
    ],
    "sg:phone":"+1 763 755 0373",
    "sg:postcode":"55303",
    "sg:province":"MN",
    "wof:name":"Looking Good Hair Salon",
    "wof:placetype":"venue"
},
  "geometry": {"coordinates":[-93.36489400000001,45.197571],"type":"Point"}
}