{
  "type": "Feature",
  "properties": {
    "addr:full":"8545 Upper 206th St W Lakeville MN 55044",
    "addr:housenumber":"8545",
    "addr:postcode":"55044",
    "addr:street":"Upper 206Th St W",
    "iso:country":"US",
    "sg:address":"8545 Upper 206th St W",
    "sg:city":"Lakeville",
    "sg:classifiers":[
        {
            "category":"Freight",
            "type":"Transportation"
        }
    ],
    "sg:phone":"+1 952 469 5211",
    "sg:postcode":"55044",
    "sg:province":"MN",
    "sg:tags":[
        "operator",
        "local",
        "trucking"
    ],
    "wof:name":"P & L Trucking Inc",
    "wof:placetype":"venue"
},
  "geometry": {"coordinates":[-93.23902099999999,44.650693],"type":"Point"}
}