{
  "type": "Feature",
  "properties": {
    "addr:full":"8901 Lyndale Ave S Minneapolis MN 55420",
    "addr:housenumber":"8901",
    "addr:postcode":"55420",
    "addr:street":"Lyndale Ave S",
    "iso:country":"US",
    "sg:address":"8901 Lyndale Ave S",
    "sg:city":"Minneapolis",
    "sg:classifiers":[
        {
            "category":"Shopping",
            "subcategory":"Used Merchandise",
            "type":"Retail Goods"
        },
        {
            "category":"Professional",
            "type":"Services"
        }
    ],
    "sg:phone":"+1 952 703 5800",
    "sg:postcode":"55420",
    "sg:province":"MN",
    "sg:tags":[
        "shop",
        "consignment"
    ],
    "wof:name":"Netconsign",
    "wof:placetype":"venue"
},
  "geometry": {"coordinates":[-93.28850300000001,44.841956],"type":"Point"}
}