{
  "type": "Feature",
  "properties": {
    "addr:full":"460 Lake St SW Hutchinson MN 55350",
    "addr:housenumber":"460",
    "addr:postcode":"55350",
    "addr:street":"Lake St Sw",
    "iso:country":"US",
    "sg:address":"460 Lake St SW",
    "sg:city":"Hutchinson",
    "sg:classifiers":[
        {
            "category":"Organizations",
            "subcategory":"Religious Organization",
            "type":"Services"
        }
    ],
    "sg:phone":"+1 320 587 6507",
    "sg:postcode":"55350",
    "sg:province":"MN",
    "wof:name":"St Anastasia Catholic Church",
    "wof:placetype":"venue"
},
  "geometry": {"coordinates":[-94.385938,44.88542],"type":"Point"}
}