{
  "type": "Feature",
  "properties": {
    "addr:full":"194 N Garden Minneapolis MN 55425",
    "addr:housenumber":"194",
    "addr:postcode":"55425",
    "addr:street":"N Garden",
    "iso:country":"US",
    "sg:address":"194 N Garden",
    "sg:city":"Minneapolis",
    "sg:phone":"+1 952 854 2501",
    "sg:postcode":"55425",
    "sg:province":"MN",
    "sg:website":"http://www.cariboucoffee.com",
    "wof:name":"Caribou Coffee Company",
    "wof:placetype":"venue"
},
  "geometry": {"coordinates":[-93.24069799999999,44.856043],"type":"Point"}
}