{
  "type": "Feature",
  "properties": {
    "addr:full":"312 Beltrami Ave NW Bemidji MN 56601",
    "addr:housenumber":"312",
    "addr:postcode":"56601",
    "addr:street":"Beltrami Ave Nw",
    "iso:country":"US",
    "sg:address":"312 Beltrami Ave NW",
    "sg:city":"Bemidji",
    "sg:classifiers":[
        {
            "category":"Shopping",
            "subcategory":"Jewelry",
            "type":"Retail Goods"
        }
    ],
    "sg:phone":"+1 218 751 8663",
    "sg:postcode":"56601",
    "sg:province":"MN",
    "sg:tags":[
        "stone"
    ],
    "wof:name":"Kelseys Jewelry",
    "wof:placetype":"venue"
},
  "geometry": {"coordinates":[-94.881108,47.471462],"type":"Point"}
}