{
  "type": "Feature",
  "properties": {
    "addr:full":"64 Birnamwood Dr Burnsville MN 55337",
    "addr:housenumber":"64",
    "addr:postcode":"55337",
    "addr:street":"Birnamwood Dr",
    "iso:country":"US",
    "sg:address":"64 Birnamwood Dr",
    "sg:city":"Burnsville",
    "sg:classifiers":[
        {
            "category":"Professional",
            "subcategory":"Management & Consulting",
            "type":"Services"
        }
    ],
    "sg:phone":"+1 952 707 1997",
    "sg:postcode":"55337",
    "sg:province":"MN",
    "sg:tags":[
        "retail",
        "direct",
        "sales"
    ],
    "wof:name":"Derscheid Diamonds",
    "wof:placetype":"venue"
},
  "geometry": {"coordinates":[-93.258084,44.777883],"type":"Point"}
}