{
  "type": "Feature",
  "properties": {
    "iso:country":"US",
    "sg:address":"225 W Lincoln Ave",
    "sg:city":"Fergus Falls",
    "sg:classifiers":[
        {
            "category":"Insurance",
            "subcategory":"Insurance Agent",
            "type":"Services"
        }
    ],
    "sg:phone":"+1 218 998 0582",
    "sg:postcode":"56537",
    "sg:province":"MN",
    "wof:name":"Wilson L T C Insurance Service",
    "wof:placetype":"venue"
},
  "geometry": {"coordinates":[-96.07749099999999,46.283422],"type":"Point"}
}