{
  "type": "Feature",
  "properties": {
    "iso:country":"US",
    "sg:address":"20560 Linden Rd",
    "sg:city":"Excelsior",
    "sg:classifiers":[
        {
            "category":"Banks & Credit Unions",
            "subcategory":"Financial Services",
            "type":"Services"
        }
    ],
    "sg:phone":"+1 952 470 5376",
    "sg:postcode":"55331",
    "sg:province":"MN",
    "sg:tags":[
        "investor"
    ],
    "wof:name":"Investments 2 Schlesinger",
    "wof:placetype":"venue"
},
  "geometry": {"coordinates":[-93.54223,44.922466],"type":"Point"}
}