{
  "type": "Feature",
  "properties": {
    "iso:country":"US",
    "sg:address":"324 South St",
    "sg:city":"Tracy",
    "sg:classifiers":[
        {
            "category":"Health Services",
            "subcategory":"Chiropractor",
            "type":"Services"
        }
    ],
    "sg:phone":"+1 507 629 3664",
    "sg:postcode":"56175",
    "sg:province":"MN",
    "sg:tags":[
        "chiropractic"
    ],
    "wof:name":"Lane Horn Dc",
    "wof:placetype":"venue"
},
  "geometry": {"coordinates":[-95.620451,44.232248],"type":"Point"}
}