{
  "type": "Feature",
  "properties": {
    "iso:country":"US",
    "sg:address":"31768 830th St",
    "sg:city":"Brewster",
    "sg:classifiers":[
        {
            "category":"Manufacturing",
            "subcategory":"Food",
            "type":"Manufacturing & Wholesale Goods"
        },
        {
            "category":"Farming",
            "subcategory":"Farm",
            "type":"Manufacturing & Wholesale Goods"
        }
    ],
    "sg:phone":"+1 507 842 5618",
    "sg:postcode":"56119",
    "sg:province":"MN",
    "sg:tags":[
        "corn",
        "product"
    ],
    "wof:name":"Larry Schmitz",
    "wof:placetype":"venue"
},
  "geometry": {"coordinates":[-95.438866,43.688389],"type":"Point"}
}