{
  "type": "Feature",
  "properties": {
    "addr:full":"112 Holmes St S Shakopee MN 55379",
    "addr:housenumber":"112",
    "addr:postcode":"55379",
    "addr:street":"Holmes St S",
    "iso:country":"US",
    "sg:address":"112 Holmes St S",
    "sg:city":"Shakopee",
    "sg:classifiers":[
        {
            "category":"Retail",
            "subcategory":"Animal Services",
            "type":"Services"
        }
    ],
    "sg:phone":"+1 952 445 5262",
    "sg:postcode":"55379",
    "sg:province":"MN",
    "sg:tags":[
        "pet",
        "grooming",
        "washing",
        "boarding/pet",
        "sitting"
    ],
    "wof:name":"Doggie Doo's Inc",
    "wof:placetype":"venue"
},
  "geometry": {"coordinates":[-93.526901,44.798401],"type":"Point"}
}