{
  "type": "Feature",
  "properties": {
    "addr:full":"727 Front Ave St Paul MN 55103",
    "addr:housenumber":"727",
    "addr:postcode":"55103",
    "addr:street":"Front Ave",
    "iso:country":"US",
    "sg:address":"727 Front Ave",
    "sg:city":"St Paul",
    "sg:classifiers":[
        {
            "category":"Social Services",
            "type":"Services"
        }
    ],
    "sg:phone":"+1 651 487 5135",
    "sg:postcode":"55103",
    "sg:province":"MN",
    "sg:tags":[
        "senior",
        "citizen"
    ],
    "wof:name":"Living At Home Block Nurse Inc",
    "wof:placetype":"venue"
},
  "geometry": {"coordinates":[-93.128891,44.970172],"type":"Point"}
}