{
  "type": "Feature",
  "properties": {
    "addr:full":"525 Portland Ave Fl 4 Minneapolis MN 55415",
    "addr:housenumber":"525;4",
    "addr:postcode":"55415",
    "addr:street":"Portland Ave Fl",
    "iso:country":"US",
    "sg:address":"525 Portland Ave Fl 4",
    "sg:city":"Minneapolis",
    "sg:classifiers":[
        {
            "category":"Health Services",
            "subcategory":"Clinic",
            "type":"Services"
        }
    ],
    "sg:phone":"+1 612 348 6363",
    "sg:postcode":"55415",
    "sg:province":"MN",
    "sg:tags":[
        "welfare"
    ],
    "wof:name":"Red Door Clinic",
    "wof:placetype":"venue"
},
  "geometry": {"coordinates":[-93.262657,44.975125],"type":"Point"}
}