{
  "type": "Feature",
  "properties": {
    "iso:country":"US",
    "sg:address":"5814 Blackshire Path",
    "sg:city":"Inver Grove Heights",
    "sg:classifiers":[
        {
            "category":"Professional",
            "subcategory":"Art Services",
            "type":"Services"
        }
    ],
    "sg:phone":"+1 952 948 9234",
    "sg:postcode":"55076",
    "sg:province":"MN",
    "sg:tags":[
        "commercial",
        "design"
    ],
    "wof:name":"Ecra Inc",
    "wof:placetype":"venue"
},
  "geometry": {"coordinates":[-93.05327800000001,44.864692],"type":"Point"}
}