{
  "type": "Feature",
  "properties": {
    "addr:full":"917 Winnebago Ave Fairmont MN 56031",
    "addr:housenumber":"917",
    "addr:postcode":"56031",
    "addr:street":"Winnebago Ave",
    "iso:country":"US",
    "sg:address":"917 Winnebago Ave",
    "sg:city":"Fairmont",
    "sg:classifiers":[
        {
            "category":"Wholesale",
            "subcategory":"Meat",
            "type":"Manufacturing & Wholesale Goods"
        }
    ],
    "sg:phone":"+1 507 238 2563",
    "sg:postcode":"56031",
    "sg:province":"MN",
    "wof:name":"Olson Locker Inc",
    "wof:placetype":"venue"
},
  "geometry": {"coordinates":[-94.450174,43.666745],"type":"Point"}
}