{
  "type": "Feature",
  "properties": {
    "iso:country":"US",
    "sg:address":"22272 Co Rd 75",
    "sg:city":"Big Lake",
    "sg:classifiers":[
        {
            "category":"Building & Trades",
            "subcategory":"Electrical",
            "type":"Services"
        }
    ],
    "sg:phone":"+1 763 263 5169",
    "sg:postcode":"55309",
    "sg:province":"MN",
    "sg:tags":[
        "electrical",
        "contractor"
    ],
    "wof:name":"Notch Electric",
    "wof:placetype":"venue"
},
  "geometry": {"coordinates":[-93.754683,45.37551],"type":"Point"}
}