{
  "type": "Feature",
  "properties": {
    "iso:country":"US",
    "sg:address":"1981 Arlington Ave E",
    "sg:city":"St Paul",
    "sg:classifiers":[
        {
            "category":"Building & Trades",
            "subcategory":"Construction",
            "type":"Services"
        }
    ],
    "sg:phone":"+1 651 772 0156",
    "sg:postcode":"55119",
    "sg:province":"MN",
    "sg:tags":[
        "sewer",
        "contractor"
    ],
    "wof:name":"A A Drain Svc",
    "wof:placetype":"venue"
},
  "geometry": {"coordinates":[-93.01855399999999,44.984804],"type":"Point"}
}