{
  "type": "Feature",
  "properties": {
    "iso:country":"US",
    "sg:address":"211 2nd Ave",
    "sg:city":"Clearbrook",
    "sg:classifiers":[
        {
            "category":"Food & Beverages",
            "subcategory":"Bakery",
            "type":"Retail Goods"
        }
    ],
    "sg:phone":"+1 218 776 2833",
    "sg:postcode":"56634",
    "sg:province":"MN",
    "sg:tags":[
        "baker"
    ],
    "wof:name":"Mom's Cakes",
    "wof:placetype":"venue"
},
  "geometry": {"coordinates":[-95.425831,47.692781],"type":"Point"}
}