{
  "type": "Feature",
  "properties": {
    "addr:full":"17573 Co Rd 27 Spring Grove MN 55974",
    "addr:housenumber":"17573;27",
    "addr:postcode":"55974",
    "addr:street":"Co Rd",
    "iso:country":"US",
    "sg:address":"17573 Co Rd 27",
    "sg:city":"Spring Grove",
    "sg:classifiers":[
        {
            "category":"Farming",
            "subcategory":"Farm",
            "type":"Manufacturing & Wholesale Goods"
        }
    ],
    "sg:phone":"+1 507 498 5588",
    "sg:postcode":"55974",
    "sg:province":"MN",
    "sg:tags":[
        "crop",
        "general"
    ],
    "wof:name":"Gerard Farms",
    "wof:placetype":"venue"
},
  "geometry": {"coordinates":[-91.606075,43.542765],"type":"Point"}
}