{
  "type": "Feature",
  "properties": {
    "addr:full":"450 N Pine Lake Rd Harris MN 55032",
    "addr:housenumber":"450",
    "addr:postcode":"55032",
    "addr:street":"N Pine Lake Rd",
    "iso:country":"US",
    "sg:address":"450 N Pine Lake Rd",
    "sg:city":"Harris",
    "sg:classifiers":[
        {
            "category":"Professional",
            "subcategory":"Management & Consulting",
            "type":"Services"
        }
    ],
    "sg:phone":"+1 763 689 5965",
    "sg:postcode":"55032",
    "sg:province":"MN",
    "wof:name":"OKeefe Enterprises LLP",
    "wof:placetype":"venue"
},
  "geometry": {"coordinates":[-93.103847,45.564004],"type":"Point"}
}