{
  "type": "Feature",
  "properties": {
    "iso:country":"US",
    "sg:address":"311 W Main St",
    "sg:city":"Caledonia",
    "sg:classifiers":[
        {
            "category":"Shopping",
            "subcategory":"Clothing, Apparel, & Fashions",
            "type":"Retail Goods"
        }
    ],
    "sg:phone":"+1 507 725 8641",
    "sg:postcode":"55921",
    "sg:province":"MN",
    "wof:name":"Family Fashions",
    "wof:placetype":"venue"
},
  "geometry": {"coordinates":[-91.50029499999999,43.634567],"type":"Point"}
}