{
  "type": "Feature",
  "properties": {
    "iso:country":"US",
    "sg:address":"3832 Chicago Ave",
    "sg:city":"Minneapolis",
    "sg:classifiers":[
        {
            "category":"Real Estate",
            "subcategory":"Real Estate Services",
            "type":"Services"
        },
        {
            "category":"Real Estate",
            "subcategory":"Real Estate Agent",
            "type":"Services"
        }
    ],
    "sg:phone":"+1 612 366 0808",
    "sg:postcode":"55407",
    "sg:province":"MN",
    "sg:tags":[
        "buyer",
        "broker"
    ],
    "wof:name":"2 Cities Real Estate",
    "wof:placetype":"venue"
},
  "geometry": {"coordinates":[-93.26248200000001,44.933572],"type":"Point"}
}