{
  "type": "Feature",
  "properties": {
    "addr:full":"317 1st St W Park Rapids MN 56470",
    "addr:housenumber":"317",
    "addr:postcode":"56470",
    "addr:street":"1St St W",
    "iso:country":"US",
    "sg:address":"317 1st St W",
    "sg:city":"Park Rapids",
    "sg:classifiers":[
        {
            "category":"Professional",
            "subcategory":"Lawyer & Legal Services",
            "type":"Services"
        }
    ],
    "sg:phone":"+1 218 732 1456",
    "sg:postcode":"56470",
    "sg:province":"MN",
    "sg:tags":[
        "attorney"
    ],
    "wof:name":"Bolton Law Office",
    "wof:placetype":"venue"
},
  "geometry": {"coordinates":[-95.0616,46.922119],"type":"Point"}
}