{
  "type": "Feature",
  "properties": {
    "addr:full":"7600 France Ave S Minneapolis MN 55435",
    "addr:housenumber":"7600",
    "addr:postcode":"55435",
    "addr:street":"France Ave S",
    "iso:country":"US",
    "sg:address":"7600 France Ave S",
    "sg:city":"Minneapolis",
    "sg:classifiers":[
        {
            "category":"Health Services",
            "subcategory":"Doctor",
            "type":"Services"
        }
    ],
    "sg:phone":"+1 952 925 2425",
    "sg:postcode":"55435",
    "sg:province":"MN",
    "sg:tags":[
        "physician",
        "surgeon"
    ],
    "wof:name":"Cervical Spine Specialists",
    "wof:placetype":"venue"
},
  "geometry": {"coordinates":[-93.328812,44.861897],"type":"Point"}
}