{
  "type": "Feature",
  "properties": {
    "addr:full":"1255 Old Hwy 8 NW Saint Paul MN 55112",
    "addr:housenumber":"1255",
    "addr:postcode":"55112",
    "addr:street":"Old Hwy 8 Nw",
    "iso:country":"US",
    "sg:address":"1255 Old Hwy 8 NW",
    "sg:city":"Saint Paul",
    "sg:classifiers":[
        {
            "category":"Government",
            "subcategory":"Post Office",
            "type":"Public Place"
        }
    ],
    "sg:phone":"+1 651 633 2433",
    "sg:postcode":"55112",
    "sg:province":"MN",
    "sg:tags":[
        "postal",
        "us"
    ],
    "wof:name":"United States Postal Service",
    "wof:placetype":"venue"
},
  "geometry": {"coordinates":[-93.192779,45.07005],"type":"Point"}
}