{
  "type": "Feature",
  "properties": {
    "iso:country":"US",
    "sg:address":"40686 Co Hwy 60",
    "sg:city":"Perham",
    "sg:classifiers":[
        {
            "category":"Building & Trades",
            "subcategory":"Landscaping Services",
            "type":"Services"
        }
    ],
    "sg:phone":"+1 218 346 4511",
    "sg:postcode":"56573",
    "sg:province":"MN",
    "wof:name":"Cutting Edge Lawn Service",
    "wof:placetype":"venue"
},
  "geometry": {"coordinates":[-95.64265899999999,46.661917],"type":"Point"}
}