{
  "type": "Feature",
  "properties": {
    "iso:country":"US",
    "sg:address":"2728 Stillwater Rd",
    "sg:city":"St Paul",
    "sg:classifiers":[
        {
            "category":"Food & Beverages",
            "subcategory":"Liquor & Beverages",
            "type":"Retail Goods"
        }
    ],
    "sg:phone":"+1 651 714 8633",
    "sg:postcode":"55119",
    "sg:province":"MN",
    "sg:tags":[
        "alcoholic"
    ],
    "wof:name":"Princess Liquor & Tobacco",
    "wof:placetype":"venue"
},
  "geometry": {"coordinates":[-92.98960700000001,44.973328],"type":"Point"}
}