{
  "type": "Feature",
  "properties": {
    "addr:full":"25066 525th St Pine Island MN 55963",
    "addr:housenumber":"25066",
    "addr:postcode":"55963",
    "addr:street":"525Th St",
    "iso:country":"US",
    "sg:address":"25066 525th St",
    "sg:city":"Pine Island",
    "sg:classifiers":[
        {
            "category":"Farming",
            "subcategory":"Farm",
            "type":"Manufacturing & Wholesale Goods"
        }
    ],
    "sg:phone":"+1 507 356 4349",
    "sg:postcode":"55963",
    "sg:province":"MN",
    "sg:tags":[
        "crop",
        "general"
    ],
    "wof:name":"Joe Heimberg",
    "wof:placetype":"venue"
},
  "geometry": {"coordinates":[-92.734263,44.188832],"type":"Point"}
}