{
  "type": "Feature",
  "properties": {
    "iso:country":"US",
    "sg:address":"14777 Lake Dr NE",
    "sg:city":"Forest Lake",
    "sg:classifiers":[
        {
            "category":"Building & Trades",
            "subcategory":"Construction",
            "type":"Services"
        }
    ],
    "sg:phone":"+1 651 464 4500",
    "sg:postcode":"55025",
    "sg:province":"MN",
    "sg:tags":[
        "street",
        "road",
        "highway",
        "contractor"
    ],
    "wof:name":"Forest Lake Contracting Inc",
    "wof:placetype":"venue"
},
  "geometry": {"coordinates":[-93.080513,45.23788],"type":"Point"}
}