{
  "type": "Feature",
  "properties": {
    "addr:full":"12045 Hanson Blvd NW Minneapolis MN 55448",
    "addr:housenumber":"12045",
    "addr:postcode":"55448",
    "addr:street":"Hanson Blvd Nw",
    "iso:country":"US",
    "sg:address":"12045 Hanson Blvd NW",
    "sg:city":"Minneapolis",
    "sg:classifiers":[
        {
            "category":"Health Services",
            "subcategory":"Chiropractor",
            "type":"Services"
        }
    ],
    "sg:phone":"+1 763 754 2573",
    "sg:postcode":"55448",
    "sg:province":"MN",
    "wof:name":"Tollefson Richard R Chiropractor",
    "wof:placetype":"venue"
},
  "geometry": {"coordinates":[-93.30999799999999,45.189098],"type":"Point"}
}