{
  "type": "Feature",
  "properties": {
    "addr:full":"1209 Black Oak Ave Montevideo MN 56265",
    "addr:housenumber":"1209",
    "addr:postcode":"56265",
    "addr:street":"Black Oak Ave",
    "iso:country":"US",
    "sg:address":"1209 Black Oak Ave",
    "sg:city":"Montevideo",
    "sg:classifiers":[
        {
            "category":"Retail",
            "subcategory":"Animal Services",
            "type":"Services"
        }
    ],
    "sg:phone":"+1 320 269 3223",
    "sg:postcode":"56265",
    "sg:province":"MN",
    "wof:name":"Perfect Paws Pet Grooming",
    "wof:placetype":"venue"
},
  "geometry": {"coordinates":[-95.712024,44.948962],"type":"Point"}
}