{
  "type": "Feature",
  "properties": {
    "iso:country":"US",
    "sg:address":"601 Nelson St NE",
    "sg:city":"Warroad",
    "sg:classifiers":[
        {
            "category":"Real Estate",
            "subcategory":"Real Estate Operator",
            "type":"Services"
        }
    ],
    "sg:phone":"+1 218 386 2959",
    "sg:postcode":"56763",
    "sg:province":"MN",
    "sg:tags":[
        "apartment"
    ],
    "wof:name":"Warroad Town Homes",
    "wof:placetype":"venue"
},
  "geometry": {"coordinates":[-95.31313900000001,48.908585],"type":"Point"}
}