{
  "type": "Feature",
  "properties": {
    "iso:country":"US",
    "sg:address":"4402 Nathan Ln N",
    "sg:city":"Minneapolis",
    "sg:classifiers":[
        {
            "category":"Personal",
            "subcategory":"Beauty Salon",
            "type":"Services"
        },
        {
            "category":"Personal",
            "subcategory":"Barber",
            "type":"Services"
        }
    ],
    "sg:phone":"+1 763 559 2161",
    "sg:postcode":"55442",
    "sg:province":"MN",
    "sg:tags":[
        "hair",
        "accessory",
        "stylist",
        "supply"
    ],
    "sg:website":"http://www.greatclips.com/",
    "wof:name":"Great Clips",
    "wof:placetype":"venue"
},
  "geometry": {"coordinates":[-93.40857200000001,45.0341],"type":"Point"}
}