{
  "type": "Feature",
  "properties": {
    "iso:country":"US",
    "sg:address":"14430 Dayton River Rd",
    "sg:city":"Dayton",
    "sg:classifiers":[
        {
            "category":"Farming",
            "subcategory":"Livestock Farm",
            "type":"Manufacturing & Wholesale Goods"
        }
    ],
    "sg:phone":"+1 763 421 1548",
    "sg:postcode":"55327",
    "sg:province":"MN",
    "sg:tags":[
        "equine"
    ],
    "wof:name":"Winfield Farms",
    "wof:placetype":"venue"
},
  "geometry": {"coordinates":[-93.45412899999999,45.213055],"type":"Point"}
}