{
  "type": "Feature",
  "properties": {
    "iso:country":"US",
    "sg:address":"2356 University Ave W",
    "sg:city":"Saint Paul",
    "sg:classifiers":[
        {
            "category":"Professional",
            "subcategory":"Lawyer & Legal Services",
            "type":"Services"
        }
    ],
    "sg:phone":"+1 651 641 1500",
    "sg:postcode":"55114",
    "sg:province":"MN",
    "wof:name":"Faris & Faris",
    "wof:placetype":"venue"
},
  "geometry": {"coordinates":[-93.197306,44.963694],"type":"Point"}
}