{
  "type": "Feature",
  "properties": {
    "iso:country":"US",
    "sg:address":"8275 110th St S",
    "sg:city":"Cottage Grove",
    "sg:classifiers":[
        {
            "category":"Building & Trades",
            "subcategory":"Construction",
            "type":"Services"
        }
    ],
    "sg:phone":"+1 651 459 1596",
    "sg:postcode":"55016",
    "sg:province":"MN",
    "sg:tags":[
        "insulation",
        "contractor"
    ],
    "wof:name":"Petrich Insulation Inc",
    "wof:placetype":"venue"
},
  "geometry": {"coordinates":[-92.938288,44.790036],"type":"Point"}
}