{
  "type": "Feature",
  "properties": {
    "iso:country":"US",
    "sg:address":"20421 15th St SE",
    "sg:city":"Blomkest",
    "sg:classifiers":[
        {
            "category":"Manufacturing",
            "subcategory":"Tools & Machinery",
            "type":"Manufacturing & Wholesale Goods"
        }
    ],
    "sg:phone":"+1 320 995 6141",
    "sg:postcode":"56216",
    "sg:province":"MN",
    "sg:tags":[
        "equipment",
        "conveyor",
        "conveying"
    ],
    "sg:website":"www.christianson.com",
    "wof:name":"Christianson Systems Inc",
    "wof:placetype":"venue"
},
  "geometry": {"coordinates":[-95.023477,44.926553],"type":"Point"}
}