{
  "type": "Feature",
  "properties": {
    "addr:full":"14086 Rice Lake Cir Osseo MN 55369",
    "addr:housenumber":"14086",
    "addr:postcode":"55369",
    "addr:street":"Rice Lake Cir",
    "iso:country":"US",
    "sg:address":"14086 Rice Lake Cir",
    "sg:city":"Osseo",
    "sg:classifiers":[
        {
            "category":"Professional",
            "subcategory":"Management & Consulting",
            "type":"Services"
        }
    ],
    "sg:phone":"+1 763 420 7583",
    "sg:postcode":"55369",
    "sg:province":"MN",
    "wof:name":"Jem Management Inc",
    "wof:placetype":"venue"
},
  "geometry": {"coordinates":[-93.45667400000001,45.112347],"type":"Point"}
}