{
  "type": "Feature",
  "properties": {
    "addr:full":"4543 W Bay View Ln Duluth MN 55803",
    "addr:housenumber":"4543",
    "addr:postcode":"55803",
    "addr:street":"W Bay View Ln",
    "iso:country":"US",
    "sg:address":"4543 W Bay View Ln",
    "sg:city":"Duluth",
    "sg:classifiers":[
        {
            "category":"Building & Trades",
            "subcategory":"Equipment Rental",
            "type":"Services"
        }
    ],
    "sg:phone":"+1 218 721 3117",
    "sg:postcode":"55803",
    "sg:province":"MN",
    "sg:tags":[
        "yard",
        "leasing",
        "store"
    ],
    "wof:name":"Hall S Cabin Rentals",
    "wof:placetype":"venue"
},
  "geometry": {"coordinates":[-92.155169,47.012022],"type":"Point"}
}