{
  "type": "Feature",
  "properties": {
    "iso:country":"US",
    "sg:address":"27549 128th St NW",
    "sg:city":"Zimmerman",
    "sg:classifiers":[
        {
            "category":"Professional",
            "subcategory":"Engineering",
            "type":"Services"
        },
        {
            "category":"Building & Trades",
            "subcategory":"Electrical",
            "type":"Services"
        }
    ],
    "sg:phone":"+1 763 856 2455",
    "sg:postcode":"55398",
    "sg:province":"MN",
    "sg:tags":[
        "engineer",
        "industrial",
        "electrician",
        "electric",
        "contractors-commercial"
    ],
    "wof:name":"Hannay Electric Inc",
    "wof:placetype":"venue"
},
  "geometry": {"coordinates":[-93.59314999999999,45.469848],"type":"Point"}
}