{
  "type": "Feature",
  "properties": {
    "iso:country":"US",
    "sg:address":"1122 16th Ave SE",
    "sg:city":"Minneapolis",
    "sg:classifiers":[
        {
            "category":"Professional",
            "type":"Services"
        }
    ],
    "sg:phone":"+1 612 378 3884",
    "sg:postcode":"55414",
    "sg:province":"MN",
    "wof:name":"Paper & Stone",
    "wof:placetype":"venue"
},
  "geometry": {"coordinates":[-93.229432,44.992707],"type":"Point"}
}