{
  "type": "Feature",
  "properties": {
    "addr:full":"17718 Co Hwy 1 Lake Park MN 56554",
    "addr:housenumber":"17718",
    "addr:postcode":"56554",
    "addr:street":"Co Hwy 1;Park",
    "iso:country":"US",
    "sg:address":"17718 Co Hwy 1",
    "sg:city":"Lake Park",
    "sg:classifiers":[
        {
            "category":"Home & Garden",
            "subcategory":"Home Furnishings",
            "type":"Retail Goods"
        }
    ],
    "sg:phone":"+1 218 238 6758",
    "sg:postcode":"56554",
    "sg:province":"MN",
    "wof:name":"Pine Hill Pottery",
    "wof:placetype":"venue"
},
  "geometry": {"coordinates":[-96.134297,46.829534],"type":"Point"}
}