{
  "type": "Feature",
  "properties": {
    "addr:full":"512 Ash Ave NW Wadena MN 56482",
    "addr:housenumber":"512",
    "addr:postcode":"56482",
    "addr:street":"Ash Ave Nw",
    "iso:country":"US",
    "sg:address":"512 Ash Ave NW",
    "sg:city":"Wadena",
    "sg:classifiers":[
        {
            "category":"Personal",
            "subcategory":"Beauty Salon",
            "type":"Services"
        }
    ],
    "sg:phone":"+1 218 631 3112",
    "sg:postcode":"56482",
    "sg:province":"MN",
    "sg:tags":[
        "shop"
    ],
    "wof:name":"Lois' Coiffures",
    "wof:placetype":"venue"
},
  "geometry": {"coordinates":[-95.14615999999999,46.445899],"type":"Point"}
}