{
  "type": "Feature",
  "properties": {
    "addr:full":"162 Annapolis St E Saint Paul MN 55118",
    "addr:housenumber":"162",
    "addr:postcode":"55118",
    "addr:street":"Annapolis St E",
    "iso:country":"US",
    "sg:address":"162 Annapolis St E",
    "sg:city":"Saint Paul",
    "sg:classifiers":[
        {
            "category":"Retail",
            "subcategory":"Auto Repair",
            "type":"Services"
        }
    ],
    "sg:phone":"+1 651 493 8697",
    "sg:postcode":"55118",
    "sg:province":"MN",
    "sg:tags":[
        "automotive"
    ],
    "wof:name":"Brooks Towing",
    "wof:placetype":"venue"
},
  "geometry": {"coordinates":[-93.07848799999999,44.919528],"type":"Point"}
}