{
  "type": "Feature",
  "properties": {
    "addr:full":"5895 Otter Ridge Cir Saint Paul MN 55110",
    "addr:housenumber":"5895",
    "addr:postcode":"55110",
    "addr:street":"Otter Ridge Cir",
    "iso:country":"US",
    "sg:address":"5895 Otter Ridge Cir",
    "sg:city":"Saint Paul",
    "sg:classifiers":[
        {
            "category":"Professional",
            "subcategory":"Management & Consulting",
            "type":"Services"
        }
    ],
    "sg:phone":"+1 612 803 4205",
    "sg:postcode":"55110",
    "sg:province":"MN",
    "wof:name":"Mpn Consulting",
    "wof:placetype":"venue"
},
  "geometry": {"coordinates":[-93.045986,45.119879],"type":"Point"}
}