{
  "type": "Feature",
  "properties": {
    "iso:country":"US",
    "sg:address":"605 Main St W",
    "sg:city":"Baudette",
    "sg:classifiers":[
        {
            "category":"Banks & Credit Unions",
            "subcategory":"Bank",
            "type":"Services"
        }
    ],
    "sg:phone":"+1 218 634 3300",
    "sg:postcode":"56623",
    "sg:province":"MN",
    "sg:website":"www.borderstatebank.com",
    "wof:name":"Border State Bank",
    "wof:placetype":"venue"
},
  "geometry": {"coordinates":[-94.757879,48.710158],"type":"Point"}
}