{
  "type": "Feature",
  "properties": {
    "addr:full":"26290 162nd St Sleepy Eye MN 56085",
    "addr:housenumber":"26290",
    "addr:postcode":"56085",
    "addr:street":"162Nd St",
    "iso:country":"US",
    "sg:address":"26290 162nd St",
    "sg:city":"Sleepy Eye",
    "sg:phone":"+1 507 794 4604",
    "sg:postcode":"56085",
    "sg:province":"MN",
    "sg:tags":[
        "farm",
        "corn",
        "soybean"
    ],
    "wof:name":"Brian Aschenbrenne",
    "wof:placetype":"venue"
},
  "geometry": {"coordinates":[-94.700532,44.199464],"type":"Point"}
}