{
  "type": "Feature",
  "properties": {
    "addr:full":"5457 Morris Thomas Rd Hermantown MN 55810",
    "addr:housenumber":"5457",
    "addr:postcode":"55810",
    "addr:street":"Morris Thomas Rd",
    "iso:country":"US",
    "sg:address":"5457 Morris Thomas Rd",
    "sg:city":"Hermantown",
    "sg:classifiers":[
        {
            "category":"Freight",
            "type":"Transportation"
        }
    ],
    "sg:phone":"+1 218 628 1805",
    "sg:postcode":"55810",
    "sg:province":"MN",
    "sg:tags":[
        "commercial",
        "storage"
    ],
    "wof:name":"All Around Storage",
    "wof:placetype":"venue"
},
  "geometry": {"coordinates":[-92.254009,46.778575],"type":"Point"}
}