{
  "type": "Feature",
  "properties": {
    "addr:full":"17616 State Hwy 65 Anoka MN 55304",
    "addr:housenumber":"17616",
    "addr:postcode":"55304",
    "addr:street":"State Hwy 65",
    "iso:country":"US",
    "sg:address":"17616 State Hwy 65",
    "sg:city":"Anoka",
    "sg:classifiers":[
        {
            "category":"Retail",
            "subcategory":"Repair Shop",
            "type":"Services"
        }
    ],
    "sg:phone":"+1 763 434 8587",
    "sg:postcode":"55304",
    "sg:province":"MN",
    "wof:name":"A Ruppert & Son Well Drilling",
    "wof:placetype":"venue"
},
  "geometry": {"coordinates":[-93.23447299999999,45.290179],"type":"Point"}
}