{
  "type": "Feature",
  "properties": {
    "addr:full":"5801 Co Rd 108 SW Stewartville MN 55976",
    "addr:housenumber":"5801",
    "addr:postcode":"55976",
    "addr:street":"Co Rd 108 Sw",
    "iso:country":"US",
    "sg:address":"5801 Co Rd 108 SW",
    "sg:city":"Stewartville",
    "sg:classifiers":[
        {
            "category":"Building & Trades",
            "subcategory":"Electrical",
            "type":"Services"
        }
    ],
    "sg:phone":"+1 507 533 4155",
    "sg:postcode":"55976",
    "sg:province":"MN",
    "sg:tags":[
        "electrical",
        "contractor"
    ],
    "wof:name":"Voll Electric",
    "wof:placetype":"venue"
},
  "geometry": {"coordinates":[-92.556528,43.85559],"type":"Point"}
}