{
  "type": "Feature",
  "properties": {
    "iso:country":"US",
    "sg:address":"330 N 12th Ave E",
    "sg:city":"Duluth",
    "sg:classifiers":[
        {
            "category":"Education",
            "subcategory":"Dance Studio",
            "type":"Public Place"
        }
    ],
    "sg:phone":"+1 218 628 1872",
    "sg:postcode":"55805",
    "sg:province":"MN",
    "wof:name":"Dance Escape",
    "wof:placetype":"venue"
},
  "geometry": {"coordinates":[-92.087264,46.800914],"type":"Point"}
}