{
  "type": "Feature",
  "properties": {
    "addr:full":"27383 120th St New Richland MN 56072",
    "addr:housenumber":"27383",
    "addr:postcode":"56072",
    "addr:street":"120Th St",
    "iso:country":"US",
    "sg:address":"27383 120th St",
    "sg:city":"New Richland",
    "sg:classifiers":[
        {
            "category":"Farming",
            "subcategory":"Farm",
            "type":"Manufacturing & Wholesale Goods"
        }
    ],
    "sg:phone":"+1 507 465 3302",
    "sg:postcode":"56072",
    "sg:province":"MN",
    "sg:tags":[
        "crop",
        "general"
    ],
    "wof:name":"Keith Root",
    "wof:placetype":"venue"
},
  "geometry": {"coordinates":[-93.526596,43.956442],"type":"Point"}
}