{
  "type": "Feature",
  "properties": {
    "addr:full":"5551 W Lake St Minneapolis MN 55416",
    "addr:housenumber":"5551",
    "addr:postcode":"55416",
    "addr:street":"W Lake St",
    "iso:country":"US",
    "sg:address":"5551 W Lake St",
    "sg:city":"Minneapolis",
    "sg:classifiers":[
        {
            "category":"Coffee & Tea",
            "type":"Food & Drink"
        }
    ],
    "sg:menulink":"http://www.allmenus.com/mn/st-louis-park/58716-caribou-coffee/menu/",
    "sg:phone":"+1 952 929 9536",
    "sg:postcode":"55416",
    "sg:province":"MN",
    "sg:tags":[
        "american"
    ],
    "wof:name":"Caribou Coffee",
    "wof:placetype":"venue"
},
  "geometry": {"coordinates":[-93.35001,44.948041],"type":"Point"}
}