{
  "type": "Feature",
  "properties": {
    "addr:full":"104 6th St SW Pine Island MN 55963",
    "addr:housenumber":"104",
    "addr:postcode":"55963",
    "addr:street":"6Th St Sw",
    "iso:country":"US",
    "sg:address":"104 6th St SW",
    "sg:city":"Pine Island",
    "sg:classifiers":[
        {
            "category":"Organizations",
            "subcategory":"Religious Organization",
            "type":"Services"
        }
    ],
    "sg:phone":"+1 507 356 8622",
    "sg:postcode":"55963",
    "sg:province":"MN",
    "wof:name":"Pine Island Assmbly God Church",
    "wof:placetype":"venue"
},
  "geometry": {"coordinates":[-92.646367,44.197229],"type":"Point"}
}