{
  "type": "Feature",
  "properties": {
    "addr:full":"3800 American Blvd W Minneapolis MN 55431",
    "addr:housenumber":"3800",
    "addr:postcode":"55431",
    "addr:street":"American Blvd W",
    "iso:country":"US",
    "sg:address":"3800 American Blvd W",
    "sg:city":"Minneapolis",
    "sg:classifiers":[
        {
            "category":"Personal",
            "subcategory":"Beauty Salon",
            "type":"Services"
        },
        {
            "category":"Personal",
            "subcategory":"Barber",
            "type":"Services"
        }
    ],
    "sg:phone":"+1 952 844 3413",
    "sg:postcode":"55431",
    "sg:province":"MN",
    "sg:tags":[
        "hair",
        "accessory",
        "stylist",
        "supply"
    ],
    "sg:website":"http://www.greatclips.com/",
    "wof:name":"Great Clips",
    "wof:placetype":"venue"
},
  "geometry": {"coordinates":[-93.32730100000001,44.855789],"type":"Point"}
}