{
  "type": "Feature",
  "properties": {
    "addr:full":"6700 France Ave S Ste 141 Minneapolis MN 55435",
    "addr:housenumber":"6700",
    "addr:postcode":"55435",
    "addr:street":"France Ave S Ste 141",
    "iso:country":"US",
    "sg:address":"6700 France Ave S Ste 141",
    "sg:city":"Minneapolis",
    "sg:classifiers":[
        {
            "category":"Shopping",
            "subcategory":"Gifts & Souvenirs",
            "type":"Retail Goods"
        }
    ],
    "sg:phone":"+1 952 929 6269",
    "sg:postcode":"55435",
    "sg:province":"MN",
    "sg:tags":[
        "shop"
    ],
    "wof:name":"Dale Center Shoppe",
    "wof:placetype":"venue"
},
  "geometry": {"coordinates":[-93.329058,44.881683],"type":"Point"}
}