{
  "type": "Feature",
  "properties": {
    "iso:country":"US",
    "sg:address":"2301 130th St E",
    "sg:city":"Dundas",
    "sg:classifiers":[
        {
            "category":"Farming",
            "subcategory":"Farm",
            "type":"Manufacturing & Wholesale Goods"
        }
    ],
    "sg:phone":"+1 507 645 9234",
    "sg:postcode":"55019",
    "sg:province":"MN",
    "sg:tags":[
        "crop",
        "general"
    ],
    "wof:name":"Lynn Hutton",
    "wof:placetype":"venue"
},
  "geometry": {"coordinates":[-93.255413,44.399492],"type":"Point"}
}