{
  "type": "Feature",
  "properties": {
    "iso:country":"US",
    "sg:address":"6525 France Ave S Ste 325",
    "sg:city":"Minneapolis",
    "sg:classifiers":[
        {
            "category":"Health Services",
            "subcategory":"Doctor",
            "type":"Services"
        }
    ],
    "sg:phone":"+1 952 920 7580",
    "sg:postcode":"55435",
    "sg:province":"MN",
    "sg:tags":[
        "physician",
        "pediatrics-otorhinolaryngology",
        "surgeons",
        "otorhinolaryngology",
        "nose",
        "throat",
        "surgeon",
        "ear"
    ],
    "wof:name":"Minneapolis Otolarynogology Head And Neck Surgery Pa",
    "wof:placetype":"venue"
},
  "geometry": {"coordinates":[-93.328846,44.885036],"type":"Point"}
}