{
  "type": "Feature",
  "properties": {
    "addr:full":"25 1st St NW Madelia MN 56062",
    "addr:housenumber":"25",
    "addr:postcode":"56062",
    "addr:street":"1St St Nw Madelia",
    "iso:country":"US",
    "sg:address":"25 1st St NW",
    "sg:city":"Madelia",
    "sg:classifiers":[
        {
            "category":"Building & Trades",
            "subcategory":"Plumbing",
            "type":"Services"
        }
    ],
    "sg:phone":"+1 507 642 3415",
    "sg:postcode":"56062",
    "sg:province":"MN",
    "sg:tags":[
        "work",
        "well",
        "heating",
        "air",
        "conditioning",
        "plumbing"
    ],
    "wof:name":"Anderson Duane Plbg Htg & A Co",
    "wof:placetype":"venue"
},
  "geometry": {"coordinates":[-94.41886599999999,44.051867],"type":"Point"}
}