{
  "type": "Feature",
  "properties": {
    "iso:country":"US",
    "sg:address":"35200 County 24 Blvd",
    "sg:city":"Cannon Falls",
    "sg:phone":"+1 507 263 4007",
    "sg:postcode":"55009",
    "sg:province":"MN",
    "sg:tags":[
        "farm",
        "corn",
        "soybean"
    ],
    "wof:name":"Ebbie Makarius",
    "wof:placetype":"venue"
},
  "geometry": {"coordinates":[-92.95989899999999,44.438609],"type":"Point"}
}