{
  "type": "Feature",
  "properties": {
    "addr:full":"444 Hwy 96 E Vadnais Heights MN 55127",
    "addr:housenumber":"444",
    "addr:postcode":"55127",
    "addr:street":"Hwy 96 E",
    "iso:country":"US",
    "sg:address":"444 Hwy 96 E",
    "sg:city":"Vadnais Heights",
    "sg:classifiers":[
        {
            "category":"Professional",
            "subcategory":"Credit Reporting & Collection",
            "type":"Services"
        }
    ],
    "sg:phone":"+1 651 483 8201",
    "sg:postcode":"55127",
    "sg:province":"MN",
    "sg:tags":[
        "agency"
    ],
    "wof:name":"I C System Inc",
    "wof:placetype":"venue"
},
  "geometry": {"coordinates":[-93.083664,45.079148],"type":"Point"}
}