{
  "type": "Feature",
  "properties": {
    "iso:country":"US",
    "sg:address":"67606 Co Rd 3",
    "sg:city":"Fairfax",
    "sg:classifiers":[
        {
            "category":"Farming",
            "subcategory":"Farm",
            "type":"Manufacturing & Wholesale Goods"
        }
    ],
    "sg:phone":"+1 507 557 8357",
    "sg:postcode":"55332",
    "sg:province":"MN",
    "sg:tags":[
        "crop"
    ],
    "wof:name":"Paul Simonsen",
    "wof:placetype":"venue"
},
  "geometry": {"coordinates":[-94.812338,44.556443],"type":"Point"}
}