{
  "type": "Feature",
  "properties": {
    "addr:full":"14339 Xebec St NE Anoka MN 55304",
    "addr:housenumber":"14339",
    "addr:postcode":"55304",
    "addr:street":"Xebec St Ne",
    "iso:country":"US",
    "sg:address":"14339 Xebec St NE",
    "sg:city":"Anoka",
    "sg:classifiers":[
        {
            "category":"Building & Trades",
            "subcategory":"Landscaping Services",
            "type":"Services"
        }
    ],
    "sg:phone":"+1 763 785 2931",
    "sg:postcode":"55304",
    "sg:province":"MN",
    "sg:tags":[
        "design",
        "installation",
        "landscape",
        "contractor"
    ],
    "wof:name":"Kline Design & Landscapins Inc",
    "wof:placetype":"venue"
},
  "geometry": {"coordinates":[-93.17051499999999,45.22966],"type":"Point"}
}