{
  "type": "Feature",
  "properties": {
    "iso:country":"US",
    "sg:address":"3715 21st Ave S",
    "sg:city":"Minneapolis",
    "sg:classifiers":[
        {
            "category":"Retail",
            "subcategory":"Repair Shop",
            "type":"Services"
        }
    ],
    "sg:phone":"+1 612 722 2470",
    "sg:postcode":"55407",
    "sg:province":"MN",
    "sg:tags":[
        "plumbing",
        "drain",
        "cleaning",
        "sewer"
    ],
    "wof:name":"Drain Busters",
    "wof:placetype":"venue"
},
  "geometry": {"coordinates":[-93.24219600000001,44.934373],"type":"Point"}
}