{
  "type": "Feature",
  "properties": {
    "iso:country":"US",
    "sg:address":"1527 Grand Ave",
    "sg:city":"St Paul",
    "sg:classifiers":[
        {
            "category":"Shopping",
            "subcategory":"Computers & Home Electronics",
            "type":"Retail Goods"
        }
    ],
    "sg:phone":"+1 651 228 3000",
    "sg:postcode":"55105",
    "sg:province":"MN",
    "sg:tags":[
        "equipment",
        "dealer"
    ],
    "wof:name":"Abbai Computer Svc",
    "wof:placetype":"venue"
},
  "geometry": {"coordinates":[-93.166815,44.940139],"type":"Point"}
}