{
  "type": "Feature",
  "properties": {
    "addr:full":"7068 126th St SW Motley MN 56466",
    "addr:housenumber":"7068",
    "addr:postcode":"56466",
    "addr:street":"126Th St Sw",
    "iso:country":"US",
    "sg:address":"7068 126th St SW",
    "sg:city":"Motley",
    "sg:classifiers":[
        {
            "category":"Social Services",
            "subcategory":"Child Care",
            "type":"Services"
        }
    ],
    "sg:phone":"+1 218 352 9203",
    "sg:postcode":"56466",
    "sg:province":"MN",
    "sg:tags":[
        "day",
        "provides"
    ],
    "wof:name":"Kathy Ackerman",
    "wof:placetype":"venue"
},
  "geometry": {"coordinates":[-94.64564300000001,46.347888],"type":"Point"}
}