{
  "type": "Feature",
  "properties": {
    "addr:full":"777 Woodridge Ct Saint Paul MN 55115",
    "addr:housenumber":"777",
    "addr:postcode":"55115",
    "addr:street":"Woodridge Ct",
    "iso:country":"US",
    "sg:address":"777 Woodridge Ct",
    "sg:city":"Saint Paul",
    "sg:classifiers":[
        {
            "category":"Professional",
            "subcategory":"Business Services",
            "type":"Services"
        }
    ],
    "sg:phone":"+1 651 770 7139",
    "sg:postcode":"55115",
    "sg:province":"MN",
    "wof:name":"Imagine That A Visual Design",
    "wof:placetype":"venue"
},
  "geometry": {"coordinates":[-92.966908,45.045541],"type":"Point"}
}