{
  "type": "Feature",
  "properties": {
    "iso:country":"US",
    "sg:address":"26962 Hwy 72 NE",
    "sg:city":"Blackduck",
    "sg:classifiers":[
        {
            "category":"Farming",
            "subcategory":"Dairy Farm",
            "type":"Manufacturing & Wholesale Goods"
        }
    ],
    "sg:phone":"+1 218 835 7539",
    "sg:postcode":"56630",
    "sg:province":"MN",
    "wof:name":"Blackduck Country Dairy Inc",
    "wof:placetype":"venue"
},
  "geometry": {"coordinates":[-94.54741799999999,47.746528],"type":"Point"}
}