{
  "type": "Feature",
  "properties": {
    "addr:full":"2192 Co Rd 10 Cottonwood MN 56229",
    "addr:housenumber":"2192;10",
    "addr:postcode":"56229",
    "addr:street":"Co Rd",
    "iso:country":"US",
    "sg:address":"2192 Co Rd 10",
    "sg:city":"Cottonwood",
    "sg:classifiers":[
        {
            "category":"Social Services",
            "subcategory":"Child Care",
            "type":"Services"
        }
    ],
    "sg:phone":"+1 507 872 6736",
    "sg:postcode":"56229",
    "sg:province":"MN",
    "sg:tags":[
        "day",
        "provider"
    ],
    "wof:name":"Cheryl Nuese",
    "wof:placetype":"venue"
},
  "geometry": {"coordinates":[-95.85046,44.61615],"type":"Point"}
}