{
  "type": "Feature",
  "properties": {
    "addr:full":"800 E Main St Marshall MN 56258",
    "addr:housenumber":"800",
    "addr:postcode":"56258",
    "addr:street":"E Main St",
    "iso:country":"US",
    "sg:address":"800 E Main St",
    "sg:city":"Marshall",
    "sg:classifiers":[
        {
            "category":"Insurance",
            "subcategory":"Insurance Agent",
            "type":"Services"
        }
    ],
    "sg:phone":"+1 507 532 7538",
    "sg:postcode":"56258",
    "sg:province":"MN",
    "wof:name":"Blue Cross & Blue Shield",
    "wof:placetype":"venue"
},
  "geometry": {"coordinates":[-95.777552,44.439028],"type":"Point"}
}