{
  "type": "Feature",
  "properties": {
    "iso:country":"US",
    "sg:address":"4996 Hazelwood Ave",
    "sg:city":"Northfield",
    "sg:classifiers":[
        {
            "category":"Organizations",
            "subcategory":"Religious Organization",
            "type":"Services"
        }
    ],
    "sg:phone":"+1 952 652 2625",
    "sg:postcode":"55057",
    "sg:province":"MN",
    "sg:tags":[
        "church"
    ],
    "wof:name":"Church of Annunciation",
    "wof:placetype":"venue"
},
  "geometry": {"coordinates":[-93.28478200000001,44.515758],"type":"Point"}
}