{
  "type": "Feature",
  "properties": {
    "iso:country":"US",
    "sg:address":"217 Main St W",
    "sg:city":"Sleepy Eye",
    "sg:classifiers":[
        {
            "category":"Health Services",
            "subcategory":"Doctor",
            "type":"Services"
        }
    ],
    "sg:phone":"+1 507 794 4361",
    "sg:postcode":"56085",
    "sg:province":"MN",
    "wof:name":"Robert H Rubey DDS",
    "wof:placetype":"venue"
},
  "geometry": {"coordinates":[-94.72549600000001,44.297193],"type":"Point"}
}