{
  "type": "Feature",
  "properties": {
    "addr:full":"4186 Centerville Rd St Paul MN 55127",
    "addr:housenumber":"4186",
    "addr:postcode":"55127",
    "addr:street":"Centerville Rd",
    "iso:country":"US",
    "sg:address":"4186 Centerville Rd",
    "sg:city":"St Paul",
    "sg:classifiers":[
        {
            "category":"Building & Trades",
            "subcategory":"Landscaping Services",
            "type":"Services"
        }
    ],
    "sg:phone":"+1 651 426 1330",
    "sg:postcode":"55127",
    "sg:province":"MN",
    "sg:tags":[
        "tree"
    ],
    "wof:name":"Langer's Tree Svc",
    "wof:placetype":"venue"
},
  "geometry": {"coordinates":[-93.056073,45.069508],"type":"Point"}
}