{
  "type": "Feature",
  "properties": {
    "addr:full":"2300 University Ave NE Minneapolis MN 55418",
    "addr:housenumber":"2300",
    "addr:postcode":"55418",
    "addr:street":"University Ave Ne",
    "iso:country":"US",
    "sg:address":"2300 University Ave NE",
    "sg:city":"Minneapolis",
    "sg:classifiers":[
        {
            "category":"Bars & Pubs",
            "type":"Food & Drink"
        },
        {
            "category":"Restaurant",
            "type":"Food & Drink"
        }
    ],
    "sg:phone":"+1 612 781 3860",
    "sg:postcode":"55418",
    "sg:province":"MN",
    "sg:tags":[
        "german",
        "brew"
    ],
    "sg:website":"www.gasthofzg.com/",
    "wof:name":"Gasthof Zur Gemutlichkeit",
    "wof:placetype":"venue"
},
  "geometry": {"coordinates":[-93.26309999999999,45.011101],"type":"Point"}
}