{
  "type": "Feature",
  "properties": {
    "addr:full":"12860 Fremont Ave Zimmerman MN 55398",
    "addr:housenumber":"12860",
    "addr:postcode":"55398",
    "addr:street":"Fremont Ave",
    "iso:country":"US",
    "sg:address":"12860 Fremont Ave",
    "sg:city":"Zimmerman",
    "sg:classifiers":[
        {
            "category":"Retail",
            "subcategory":"Auto Rental",
            "type":"Services"
        }
    ],
    "sg:phone":"+1 763 856 4979",
    "sg:postcode":"55398",
    "sg:province":"MN",
    "sg:tags":[
        "renting",
        "truck",
        "leasing"
    ],
    "wof:name":"U-Haul Co",
    "wof:placetype":"venue"
},
  "geometry": {"coordinates":[-93.594871,45.443311],"type":"Point"}
}