{
  "type": "Feature",
  "properties": {
    "addr:full":"9140 E River Rd Coon Rapids MN 55433",
    "addr:housenumber":"9140",
    "addr:postcode":"55433",
    "addr:street":"E River Rd",
    "iso:country":"US",
    "sg:address":"9140 E River Rd",
    "sg:city":"Coon Rapids",
    "sg:classifiers":[
        {
            "category":"Organizations",
            "subcategory":"Religious Organization",
            "type":"Services"
        }
    ],
    "sg:phone":"+1 763 785 1071",
    "sg:postcode":"55433",
    "sg:province":"MN",
    "sg:tags":[
        "church"
    ],
    "wof:name":"Jehovah's Witnesses",
    "wof:placetype":"venue"
},
  "geometry": {"coordinates":[-93.28942499999999,45.136378],"type":"Point"}
}