{
  "type": "Feature",
  "properties": {
    "iso:country":"US",
    "sg:address":"17380 Kenrick Ave",
    "sg:city":"Lakeville",
    "sg:classifiers":[
        {
            "category":"Autos & Motor Vehicles",
            "subcategory":"Fuel & Gas Station",
            "type":"Retail Goods"
        }
    ],
    "sg:phone":"+1 952 892 7112",
    "sg:postcode":"55044",
    "sg:province":"MN",
    "sg:tags":[
        "oil"
    ],
    "wof:name":"Sinclair Oil Corp",
    "wof:placetype":"venue"
},
  "geometry": {"coordinates":[-93.286675,44.697142],"type":"Point"}
}