{
  "type": "Feature",
  "properties": {
    "iso:country":"US",
    "sg:address":"4340 Central Ave NE",
    "sg:city":"Minneapolis",
    "sg:classifiers":[
        {
            "category":"Home & Garden",
            "subcategory":"Hardware",
            "type":"Retail Goods"
        }
    ],
    "sg:phone":"+1 612 238 3719",
    "sg:postcode":"55421",
    "sg:province":"MN",
    "sg:tags":[
        "store"
    ],
    "sg:website":"www.acehardware.com",
    "wof:name":"Frattallone's-Ace Hardware",
    "wof:placetype":"venue"
},
  "geometry": {"coordinates":[-93.247641,45.047125],"type":"Point"}
}