{
  "type": "Feature",
  "properties": {
    "addr:full":"13750 County Rd 11 Burnsville MN 55337",
    "addr:housenumber":"13750;11",
    "addr:postcode":"55337",
    "addr:street":"County Rd",
    "iso:country":"US",
    "sg:address":"13750 County Rd 11",
    "sg:city":"Burnsville",
    "sg:classifiers":[
        {
            "category":"Deli",
            "type":"Food & Drink"
        },
        {
            "category":"Insurance",
            "subcategory":"Health Insurance",
            "type":"Services"
        },
        {
            "category":"Food & Beverages",
            "subcategory":"Groceries & Convenience Stores",
            "type":"Retail Goods"
        }
    ],
    "sg:phone":"+1 952 891 1212",
    "sg:postcode":"55337",
    "sg:province":"MN",
    "sg:tags":[
        "market"
    ],
    "sg:website":"www.valleynaturalfoods.com",
    "wof:name":"Valley Natural Foods",
    "wof:placetype":"venue"
},
  "geometry": {"coordinates":[-93.248169,44.755941],"type":"Point"}
}