{
  "type": "Feature",
  "properties": {
    "iso:country":"US",
    "sg:address":"12700 Pioneer Trl",
    "sg:city":"Eden Prairie",
    "sg:classifiers":[
        {
            "category":"Real Estate",
            "subcategory":"Real Estate Agent",
            "type":"Services"
        }
    ],
    "sg:phone":"+1 952 943 1800",
    "sg:postcode":"55347",
    "sg:province":"MN",
    "wof:name":"Action Center Realty Inc",
    "wof:placetype":"venue"
},
  "geometry": {"coordinates":[-93.437393,44.829406],"type":"Point"}
}