{
  "type": "Feature",
  "properties": {
    "addr:full":"17190 15th Ave NE Rice MN 56367",
    "addr:housenumber":"17190",
    "addr:postcode":"56367",
    "addr:street":"15Th Ave Ne",
    "iso:country":"US",
    "sg:address":"17190 15th Ave NE",
    "sg:city":"Rice",
    "sg:classifiers":[
        {
            "category":"Farming",
            "subcategory":"Farm",
            "type":"Manufacturing & Wholesale Goods"
        }
    ],
    "sg:phone":"+1 320 393 2689",
    "sg:postcode":"56367",
    "sg:province":"MN",
    "wof:name":"Bunker Hill Creek Farm",
    "wof:placetype":"venue"
},
  "geometry": {"coordinates":[-94.135198,45.821685],"type":"Point"}
}