{
  "type": "Feature",
  "properties": {
    "addr:full":"1111 Rice St W Stillwater MN 55082",
    "addr:housenumber":"1111",
    "addr:postcode":"55082",
    "addr:street":"Rice St W",
    "iso:country":"US",
    "sg:address":"1111 Rice St W",
    "sg:city":"Stillwater",
    "sg:classifiers":[
        {
            "category":"Building & Trades",
            "subcategory":"Construction",
            "type":"Services"
        }
    ],
    "sg:phone":"+1 651 439 5104",
    "sg:postcode":"55082",
    "sg:province":"MN",
    "sg:tags":[
        "home",
        "remodeling",
        "family"
    ],
    "wof:name":"Ronning Design Build Inc",
    "wof:placetype":"venue"
},
  "geometry": {"coordinates":[-92.821659,45.055856],"type":"Point"}
}