{
  "type": "Feature",
  "properties": {
    "iso:country":"US",
    "sg:address":"8061 Flying Cloud Dr",
    "sg:city":"Eden Prairie",
    "sg:classifiers":[
        {
            "category":"Restaurant",
            "type":"Food & Drink"
        }
    ],
    "sg:menulink":"http://www.allmenus.com/mn/eden-prairie/56720-davannis/menu/",
    "sg:phone":"+1 952 941 4444",
    "sg:postcode":"55344",
    "sg:province":"MN",
    "sg:tags":[
        "wrap",
        "american",
        "sandwich"
    ],
    "wof:name":"Davanni's",
    "wof:placetype":"venue"
},
  "geometry": {"coordinates":[-93.425983,44.857733],"type":"Point"}
}