{
  "type": "Feature",
  "properties": {
    "addr:full":"20969 Clayton Ave Farmington MN 55024",
    "addr:housenumber":"20969",
    "addr:postcode":"55024",
    "addr:street":"Clayton Ave",
    "iso:country":"US",
    "sg:address":"20969 Clayton Ave",
    "sg:city":"Farmington",
    "sg:classifiers":[
        {
            "category":"Building & Trades",
            "subcategory":"Construction",
            "type":"Services"
        }
    ],
    "sg:phone":"+1 651 463 2139",
    "sg:postcode":"55024",
    "sg:province":"MN",
    "sg:tags":[
        "project"
    ],
    "wof:name":"Scott Johnson Construction Svc",
    "wof:placetype":"venue"
},
  "geometry": {"coordinates":[-93.035048,44.64503],"type":"Point"}
}