{
  "type": "Feature",
  "properties": {
    "addr:full":"4339 280th Ave Gary MN 56545",
    "addr:housenumber":"4339",
    "addr:postcode":"56545",
    "addr:street":"280Th Ave",
    "iso:country":"US",
    "sg:address":"4339 280th Ave",
    "sg:city":"Gary",
    "sg:classifiers":[
        {
            "category":"Wholesale",
            "subcategory":"Farm Supplies",
            "type":"Manufacturing & Wholesale Goods"
        },
        {
            "category":"Farming",
            "subcategory":"Farm",
            "type":"Manufacturing & Wholesale Goods"
        }
    ],
    "sg:phone":"+1 218 356 8245",
    "sg:postcode":"56545",
    "sg:province":"MN",
    "sg:tags":[
        "grain"
    ],
    "wof:name":"Carman Dahl",
    "wof:placetype":"venue"
},
  "geometry": {"coordinates":[-96.152041,47.41256],"type":"Point"}
}