{
  "type": "Feature",
  "properties": {
    "addr:full":"24584 Co Hwy 39 Osage MN 56570",
    "addr:housenumber":"24584",
    "addr:postcode":"56570",
    "addr:street":"Co Hwy 39",
    "iso:country":"US",
    "sg:address":"24584 Co Hwy 39",
    "sg:city":"Osage",
    "sg:classifiers":[
        {
            "category":"Government",
            "subcategory":"Office",
            "type":"Public Place"
        }
    ],
    "sg:phone":"+1 218 573 3286",
    "sg:postcode":"56570",
    "sg:province":"MN",
    "sg:tags":[
        "executive"
    ],
    "wof:name":"Shell Lake Township",
    "wof:placetype":"venue"
},
  "geometry": {"coordinates":[-95.413769,46.932172],"type":"Point"}
}