{
  "type": "Feature",
  "properties": {
    "iso:country":"US",
    "sg:address":"216 N Tower Rd",
    "sg:city":"Fergus Falls",
    "sg:classifiers":[
        {
            "category":"Wholesale",
            "subcategory":"Apparel",
            "type":"Manufacturing & Wholesale Goods"
        }
    ],
    "sg:phone":"+1 218 739 2650",
    "sg:postcode":"56537",
    "sg:province":"MN",
    "sg:tags":[
        "fabric"
    ],
    "wof:name":"R S & M",
    "wof:placetype":"venue"
},
  "geometry": {"coordinates":[-96.102436,46.28472],"type":"Point"}
}