{
  "type": "Feature",
  "properties": {
    "iso:country":"US",
    "sg:address":"1417 Sundby Rd",
    "sg:city":"Duluth",
    "sg:classifiers":[
        {
            "category":"Personal",
            "type":"Services"
        }
    ],
    "sg:phone":"+1 218 625 2353",
    "sg:postcode":"55811",
    "sg:province":"MN",
    "sg:tags":[
        "parlor",
        "massage"
    ],
    "wof:name":"Eagles Nest Massage Therapy",
    "wof:placetype":"venue"
},
  "geometry": {"coordinates":[-92.170068,46.817724],"type":"Point"}
}