{
  "type": "Feature",
  "properties": {
    "iso:country":"US",
    "sg:address":"6989 55th St N",
    "sg:city":"St Paul",
    "sg:classifiers":[
        {
            "category":"Wholesale",
            "subcategory":"Computers",
            "type":"Manufacturing & Wholesale Goods"
        },
        {
            "category":"Wholesale",
            "subcategory":"Electrical",
            "type":"Manufacturing & Wholesale Goods"
        }
    ],
    "sg:phone":"+1 651 779 1022",
    "sg:postcode":"55128",
    "sg:province":"MN",
    "sg:tags":[
        "communications",
        "datum",
        "telecommunication",
        "supply"
    ],
    "sg:website":"www.best-ent.com",
    "wof:name":"Best Enterprises LLC",
    "wof:placetype":"venue"
},
  "geometry": {"coordinates":[-92.96925299999999,45.027411],"type":"Point"}
}