{
  "type": "Feature",
  "properties": {
    "iso:country":"US",
    "sg:address":"403 1st St N",
    "sg:city":"Virginia",
    "sg:classifiers":[
        {
            "category":"Professional",
            "subcategory":"Accounting & Tax Preparation",
            "type":"Services"
        }
    ],
    "sg:phone":"+1 218 741 0254",
    "sg:postcode":"55792",
    "sg:province":"MN",
    "sg:tags":[
        "accountant"
    ],
    "wof:name":"James Q Forsman CPA",
    "wof:placetype":"venue"
},
  "geometry": {"coordinates":[-92.538659,47.524119],"type":"Point"}
}