{
  "type": "Feature",
  "properties": {
    "addr:full":"490 West St Taylors Falls MN 55084",
    "addr:housenumber":"490",
    "addr:postcode":"55084",
    "addr:street":"West St",
    "iso:country":"US",
    "sg:address":"490 West St",
    "sg:city":"Taylors Falls",
    "sg:classifiers":[
        {
            "category":"Professional",
            "type":"Services"
        }
    ],
    "sg:phone":"+1 651 465 4310",
    "sg:postcode":"55084",
    "sg:province":"MN",
    "sg:tags":[
        "writer"
    ],
    "wof:name":"J F Thibodeau Inc",
    "wof:placetype":"venue"
},
  "geometry": {"coordinates":[-92.656738,45.403648],"type":"Point"}
}