{
  "type": "Feature",
  "properties": {
    "iso:country":"US",
    "sg:address":"11903 Larc Industrial Blvd",
    "sg:city":"Burnsville",
    "sg:classifiers":[
        {
            "category":"Manufacturing",
            "subcategory":"Petroleum Products",
            "type":"Manufacturing & Wholesale Goods"
        }
    ],
    "sg:phone":"+1 952 445 4333",
    "sg:postcode":"55337",
    "sg:province":"MN",
    "sg:tags":[
        "candles-wholesale",
        "manufacturer"
    ],
    "sg:website":"http://www.diannescc.com",
    "wof:name":"Dianne's Custom Candles",
    "wof:placetype":"venue"
},
  "geometry": {"coordinates":[-93.25428599999999,44.78868],"type":"Point"}
}