{
  "type": "Feature",
  "properties": {
    "iso:country":"US",
    "sg:address":"13681 Grove Dr",
    "sg:city":"Osseo",
    "sg:classifiers":[
        {
            "category":"Personal",
            "subcategory":"Beauty Salon",
            "type":"Services"
        }
    ],
    "sg:phone":"+1 763 416 3852",
    "sg:postcode":"55311",
    "sg:province":"MN",
    "sg:tags":[
        "shop"
    ],
    "wof:name":"K Nails",
    "wof:placetype":"venue"
},
  "geometry": {"coordinates":[-93.45313400000001,45.103916],"type":"Point"}
}