{
  "type": "Feature",
  "properties": {
    "addr:full":"1180 50th Ave NE Columbia Heights MN 55421",
    "addr:housenumber":"1180",
    "addr:postcode":"55421",
    "addr:street":"50Th Ave Ne;Heights",
    "iso:country":"US",
    "sg:address":"1180 50th Ave NE",
    "sg:city":"Columbia Heights",
    "sg:classifiers":[
        {
            "category":"Professional",
            "subcategory":"Engineering",
            "type":"Services"
        }
    ],
    "sg:phone":"+1 763 586 0820",
    "sg:postcode":"55421",
    "sg:province":"MN",
    "sg:tags":[
        "development",
        "f",
        "support",
        "design",
        "circuit",
        "integrated",
        "engineer"
    ],
    "sg:website":"www.asicsystems.com",
    "wof:name":"A Sic Systems Inc",
    "wof:placetype":"venue"
},
  "geometry": {"coordinates":[-93.243219,45.05845],"type":"Point"}
}