{
  "type": "Feature",
  "properties": {
    "iso:country":"US",
    "sg:address":"401 S Co Rd 5",
    "sg:city":"Springfield",
    "sg:classifiers":[
        {
            "category":"Real Estate",
            "subcategory":"Real Estate Agent",
            "type":"Services"
        }
    ],
    "sg:phone":"+1 507 723 5111",
    "sg:postcode":"56087",
    "sg:province":"MN",
    "sg:tags":[
        "cooperative"
    ],
    "wof:name":"Riverview Homestead Co-Op",
    "wof:placetype":"venue"
},
  "geometry": {"coordinates":[-94.967123,44.238312],"type":"Point"}
}