{
  "type": "Feature",
  "properties": {
    "iso:country":"US",
    "sg:address":"8391 US Hwy 169",
    "sg:city":"Garrison",
    "sg:classifiers":[
        {
            "category":"Travel",
            "subcategory":"Hotels & Motels",
            "type":"Entertainment"
        }
    ],
    "sg:phone":"+1 320 692 4349",
    "sg:postcode":"56450",
    "sg:province":"MN",
    "wof:name":"Mille Lacs Motel",
    "wof:placetype":"venue"
},
  "geometry": {"coordinates":[-93.822626,46.286037],"type":"Point"}
}