{
  "type": "Feature",
  "properties": {
    "iso:country":"US",
    "sg:address":"216 3rd Ave S",
    "sg:city":"Sauk Rapids",
    "sg:classifiers":[
        {
            "category":"Manufacturing",
            "subcategory":"Buildings",
            "type":"Manufacturing & Wholesale Goods"
        }
    ],
    "sg:phone":"+1 320 267 9864",
    "sg:postcode":"56379",
    "sg:province":"MN",
    "sg:tags":[
        "prefab"
    ],
    "wof:name":"Cloverleaf Realty",
    "wof:placetype":"venue"
},
  "geometry": {"coordinates":[-94.161531,45.587831],"type":"Point"}
}