{
  "type": "Feature",
  "properties": {
    "iso:country":"US",
    "sg:address":"520 S Elm St",
    "sg:city":"Belle Plaine",
    "sg:classifiers":[
        {
            "category":"Shopping",
            "subcategory":"Florist",
            "type":"Retail Goods"
        }
    ],
    "sg:phone":"+1 952 873 2970",
    "sg:postcode":"56011",
    "sg:province":"MN",
    "wof:name":"Emma Krumbee's Floral",
    "wof:placetype":"venue"
},
  "geometry": {"coordinates":[-93.76250400000001,44.61796],"type":"Point"}
}