{
  "type": "Feature",
  "properties": {
    "addr:full":"23634 Co Hwy 22 Detroit Lakes MN 56501",
    "addr:housenumber":"23634",
    "addr:postcode":"56501",
    "addr:street":"Co Hwy 22",
    "iso:country":"US",
    "sg:address":"23634 Co Hwy 22",
    "sg:city":"Detroit Lakes",
    "sg:classifiers":[
        {
            "category":"Restaurant",
            "type":"Food & Drink"
        }
    ],
    "sg:phone":"+1 218 847 9894",
    "sg:postcode":"56501",
    "sg:province":"MN",
    "wof:name":"Hotel Shoreham Pizza Bar/Grill",
    "wof:placetype":"venue"
},
  "geometry": {"coordinates":[-95.902371,46.755858],"type":"Point"}
}