{
  "type": "Feature",
  "properties": {
    "addr:full":"410 4th Ave SE Long Prairie MN 56347",
    "addr:housenumber":"410",
    "addr:postcode":"56347",
    "addr:street":"4Th Ave Se",
    "iso:country":"US",
    "sg:address":"410 4th Ave SE",
    "sg:city":"Long Prairie",
    "sg:classifiers":[
        {
            "category":"Real Estate",
            "subcategory":"Real Estate Operator",
            "type":"Services"
        }
    ],
    "sg:phone":"+1 320 732 6940",
    "sg:postcode":"56347",
    "sg:province":"MN",
    "sg:tags":[
        "apartment"
    ],
    "wof:name":"Prairie View 400 Office",
    "wof:placetype":"venue"
},
  "geometry": {"coordinates":[-94.85887,45.969402],"type":"Point"}
}