{
  "type": "Feature",
  "properties": {
    "iso:country":"US",
    "sg:address":"1618 160th Ave",
    "sg:city":"Lake Benton",
    "sg:phone":"+1 507 368 4386",
    "sg:postcode":"56172",
    "sg:province":"MN",
    "sg:tags":[
        "beef",
        "farm",
        "cash",
        "grain",
        "cattle",
        "feedlot"
    ],
    "wof:name":"Kevin Willert",
    "wof:placetype":"venue"
},
  "geometry": {"coordinates":[-95.743256,44.082063],"type":"Point"}
}