{
  "type": "Feature",
  "properties": {
    "addr:full":"6519 Central Ave NE Fridley MN 55432",
    "addr:housenumber":"6519",
    "addr:postcode":"55432",
    "addr:street":"Central Ave Ne",
    "iso:country":"US",
    "sg:address":"6519 Central Ave NE",
    "sg:city":"Fridley",
    "sg:classifiers":[
        {
            "category":"Retail",
            "subcategory":"Auto Repair",
            "type":"Services"
        }
    ],
    "sg:phone":"+1 763 571 2660",
    "sg:postcode":"55432",
    "sg:province":"MN",
    "sg:tags":[
        "wrecker"
    ],
    "wof:name":"Northeast Towing Svc",
    "wof:placetype":"venue"
},
  "geometry": {"coordinates":[-93.23773300000001,45.086613],"type":"Point"}
}