{
  "type": "Feature",
  "properties": {
    "iso:country":"US",
    "sg:address":"830 W Main St",
    "sg:city":"Anoka",
    "sg:classifiers":[
        {
            "category":"Building & Trades",
            "subcategory":"Construction",
            "type":"Services"
        }
    ],
    "sg:phone":"+1 763 533 3752",
    "sg:postcode":"55303",
    "sg:province":"MN",
    "sg:tags":[
        "contractor"
    ],
    "wof:name":"Family Owner Builders",
    "wof:placetype":"venue"
},
  "geometry": {"coordinates":[-93.4076,45.208599],"type":"Point"}
}