{
  "type": "Feature",
  "properties": {
    "addr:full":"19181 180th Ave Big Lake MN 55309",
    "addr:housenumber":"19181",
    "addr:postcode":"55309",
    "addr:street":"180Th Ave",
    "iso:country":"US",
    "sg:address":"19181 180th Ave",
    "sg:city":"Big Lake",
    "sg:classifiers":[
        {
            "category":"Professional",
            "subcategory":"Computer Services",
            "type":"Services"
        }
    ],
    "sg:phone":"+1 763 263 6321",
    "sg:postcode":"55309",
    "sg:province":"MN",
    "sg:tags":[
        "prepackaged",
        "software"
    ],
    "wof:name":"Rogerware",
    "wof:placetype":"venue"
},
  "geometry": {"coordinates":[-93.750105,45.298065],"type":"Point"}
}