{
  "type": "Feature",
  "properties": {
    "iso:country":"US",
    "sg:address":"205 Main St",
    "sg:city":"Lakefield",
    "sg:classifiers":[
        {
            "category":"Retail",
            "subcategory":"Auto Repair",
            "type":"Services"
        }
    ],
    "sg:phone":"+1 507 662 6451",
    "sg:postcode":"56150",
    "sg:province":"MN",
    "sg:tags":[
        "repairing",
        "automobile"
    ],
    "wof:name":"Bannister Repair",
    "wof:placetype":"venue"
},
  "geometry": {"coordinates":[-95.172138,43.677425],"type":"Point"}
}