{
  "type": "Feature",
  "properties": {
    "iso:country":"US",
    "sg:address":"1222 Main St W",
    "sg:city":"Baudette",
    "sg:classifiers":[
        {
            "category":"Travel",
            "subcategory":"Hotels & Motels",
            "type":"Entertainment"
        }
    ],
    "sg:phone":"+1 218 634 2869",
    "sg:postcode":"56623",
    "sg:province":"MN",
    "wof:name":"Country Bunk-Ins",
    "wof:placetype":"venue"
},
  "geometry": {"coordinates":[-94.757828,48.709722],"type":"Point"}
}