{
  "type": "Feature",
  "properties": {
    "addr:full":"9701 Data Park Hopkins MN 55343",
    "addr:housenumber":"9701",
    "addr:postcode":"55343",
    "addr:street":"Data Park",
    "iso:country":"US",
    "sg:address":"9701 Data Park",
    "sg:city":"Hopkins",
    "sg:classifiers":[
        {
            "category":"Manufacturing",
            "subcategory":"Tools & Machinery",
            "type":"Manufacturing & Wholesale Goods"
        }
    ],
    "sg:phone":"+1 952 932 8000",
    "sg:postcode":"55343",
    "sg:province":"MN",
    "sg:tags":[
        "equipment",
        "peripheral",
        "computer",
        "mfg"
    ],
    "wof:name":"Multimdia Cmmnications Systems",
    "wof:placetype":"venue"
},
  "geometry": {"coordinates":[-93.403786,44.895267],"type":"Point"}
}