{
  "type": "Feature",
  "properties": {
    "iso:country":"US",
    "sg:address":"21565 255th Ave",
    "sg:city":"Starbuck",
    "sg:classifiers":[
        {
            "category":"Farming",
            "subcategory":"Livestock Farm",
            "type":"Manufacturing & Wholesale Goods"
        }
    ],
    "sg:phone":"+1 320 239 2130",
    "sg:postcode":"56381",
    "sg:province":"MN",
    "sg:tags":[
        "beef",
        "feedlot",
        "cattle"
    ],
    "wof:name":"Timothy Thomas",
    "wof:placetype":"venue"
},
  "geometry": {"coordinates":[-95.45933100000001,45.585552],"type":"Point"}
}