{
  "type": "Feature",
  "properties": {
    "addr:full":"6495 S Saunders Lake Dr Mound MN 55364",
    "addr:housenumber":"6495",
    "addr:postcode":"55364",
    "addr:street":"S Saunders Lake Dr Mound",
    "iso:country":"US",
    "sg:address":"6495 S Saunders Lake Dr",
    "sg:city":"Mound",
    "sg:classifiers":[
        {
            "category":"Retail",
            "subcategory":"Veterinary Services",
            "type":"Services"
        }
    ],
    "sg:phone":"+1 952 472 3469",
    "sg:postcode":"55364",
    "sg:province":"MN",
    "sg:tags":[
        "clinic",
        "hospital"
    ],
    "wof:name":"Saunders Lk Veterinary Svcs",
    "wof:placetype":"venue"
},
  "geometry": {"coordinates":[-93.688408,44.927361],"type":"Point"}
}