{
  "type": "Feature",
  "properties": {
    "addr:full":"19285 State Hwy 7 Excelsior MN 55331",
    "addr:housenumber":"19285",
    "addr:postcode":"55331",
    "addr:street":"State Hwy 7",
    "iso:country":"US",
    "sg:address":"19285 State Hwy 7",
    "sg:city":"Excelsior",
    "sg:classifiers":[
        {
            "category":"Professional",
            "subcategory":"Art Services",
            "type":"Services"
        }
    ],
    "sg:phone":"+1 952 474 4442",
    "sg:postcode":"55331",
    "sg:province":"MN",
    "sg:tags":[
        "commercial",
        "design"
    ],
    "wof:name":"Janson Graphics",
    "wof:placetype":"venue"
},
  "geometry": {"coordinates":[-93.523796,44.911189],"type":"Point"}
}