{
  "type": "Feature",
  "properties": {
    "addr:full":"11606 220th St Magnolia MN 56158",
    "addr:housenumber":"11606",
    "addr:postcode":"56158",
    "addr:street":"220Th St",
    "iso:country":"US",
    "sg:address":"11606 220th St",
    "sg:city":"Magnolia",
    "sg:classifiers":[
        {
            "category":"Farming",
            "subcategory":"Farm",
            "type":"Manufacturing & Wholesale Goods"
        }
    ],
    "sg:phone":"+1 507 472 8708",
    "sg:postcode":"56158",
    "sg:province":"MN",
    "wof:name":"Heeren & Sons",
    "wof:placetype":"venue"
},
  "geometry": {"coordinates":[-96.0204,43.673767],"type":"Point"}
}