{
  "type": "Feature",
  "properties": {
    "iso:country":"US",
    "sg:address":"1117 2nd St SW",
    "sg:city":"Rochester",
    "sg:classifiers":[
        {
            "category":"Wholesale",
            "subcategory":"Medical Equipment & Supplies",
            "type":"Manufacturing & Wholesale Goods"
        },
        {
            "category":"Shopping",
            "type":"Retail Goods"
        }
    ],
    "sg:phone":"+1 507 288 0113",
    "sg:postcode":"55902",
    "sg:province":"MN",
    "sg:tags":[
        "wheelchair",
        "hospital"
    ],
    "wof:name":"Anderson's Wheelchairs",
    "wof:placetype":"venue"
},
  "geometry": {"coordinates":[-92.480979,44.021706],"type":"Point"}
}