{
  "type": "Feature",
  "properties": {
    "iso:country":"US",
    "sg:address":"5235 W Frontage Rd",
    "sg:city":"Rochester",
    "sg:classifiers":[
        {
            "category":"Shopping",
            "type":"Retail Goods"
        }
    ],
    "sg:phone":"+1 507 252 9463",
    "sg:postcode":"55901",
    "sg:province":"MN",
    "sg:tags":[
        "equipment",
        "beer",
        "supply"
    ],
    "wof:name":"Pine Cheese Mart",
    "wof:placetype":"venue"
},
  "geometry": {"coordinates":[-92.51034199999999,44.078265],"type":"Point"}
}