{
  "type": "Feature",
  "properties": {
    "iso:country":"US",
    "sg:address":"702 3rd Ave",
    "sg:city":"Goodhue",
    "sg:classifiers":[
        {
            "category":"Place Of Worship",
            "subcategory":"Church",
            "type":"Public Place"
        },
        {
            "category":"Place Of Worship",
            "type":"Public Place"
        }
    ],
    "sg:phone":"+1 651 923 4969",
    "sg:postcode":"55027",
    "sg:province":"MN",
    "sg:tags":[
        "lutheran",
        "america",
        "churches-lutheran",
        "churches-lutheran-evangelical"
    ],
    "wof:name":"Randall Kuznicki",
    "wof:placetype":"venue"
},
  "geometry": {"coordinates":[-92.631168,44.401293],"type":"Point"}
}