{
  "type": "Feature",
  "properties": {
    "iso:country":"US",
    "sg:address":"218 W Main St",
    "sg:city":"Crosby",
    "sg:classifiers":[
        {
            "category":"Sports & Exercise",
            "subcategory":"Bowling",
            "type":"Entertainment"
        }
    ],
    "sg:phone":"+1 218 546 5027",
    "sg:postcode":"56441",
    "sg:province":"MN",
    "sg:tags":[
        "center"
    ],
    "wof:name":"Cuyuna Lanes",
    "wof:placetype":"venue"
},
  "geometry": {"coordinates":[-93.957374,46.482345],"type":"Point"}
}