{
  "type": "Feature",
  "properties": {
    "addr:full":"6444 Lyndale Ave S Richfield MN 55423",
    "addr:housenumber":"6444",
    "addr:postcode":"55423",
    "addr:street":"Lyndale Ave S",
    "iso:country":"US",
    "sg:address":"6444 Lyndale Ave S",
    "sg:city":"Richfield",
    "sg:classifiers":[
        {
            "category":"Food & Beverages",
            "subcategory":"Liquor & Beverages",
            "type":"Retail Goods"
        }
    ],
    "sg:phone":"+1 612 861 9375",
    "sg:postcode":"55423",
    "sg:province":"MN",
    "wof:name":"Richfield Municipal Liquor",
    "wof:placetype":"venue"
},
  "geometry": {"coordinates":[-93.286907,44.885933],"type":"Point"}
}