{
  "type": "Feature",
  "properties": {
    "addr:full":"609 S 10th St Minneapolis MN 55404",
    "addr:housenumber":"609",
    "addr:postcode":"55404",
    "addr:street":"S 10Th St",
    "iso:country":"US",
    "sg:address":"609 S 10th St",
    "sg:city":"Minneapolis",
    "sg:classifiers":[
        {
            "category":"Organizations",
            "subcategory":"Non-profit Organization",
            "type":"Services"
        }
    ],
    "sg:phone":"+1 612 359 0601",
    "sg:postcode":"55404",
    "sg:province":"MN",
    "sg:tags":[
        "service/non-profit",
        "community"
    ],
    "wof:name":"East Downtown Council",
    "wof:placetype":"venue"
},
  "geometry": {"coordinates":[-93.266447,44.970375],"type":"Point"}
}