{
  "type": "Feature",
  "properties": {
    "iso:country":"US",
    "sg:address":"1135 W Main St",
    "sg:city":"Anoka",
    "sg:classifiers":[
        {
            "category":"Social Services",
            "subcategory":"Child Care",
            "type":"Services"
        },
        {
            "category":"Education",
            "subcategory":"Preschool",
            "type":"Public Place"
        },
        {
            "category":"Education",
            "subcategory":"School",
            "type":"Public Place"
        }
    ],
    "sg:phone":"+1 763 323 4067",
    "sg:postcode":"55303",
    "sg:province":"MN",
    "sg:tags":[
        "elementary",
        "day"
    ],
    "sg:website":"www.creativekidschildcarecenter.com",
    "wof:name":"Creative Kids Childcare Center",
    "wof:placetype":"venue"
},
  "geometry": {"coordinates":[-93.41089599999999,45.211201],"type":"Point"}
}