{
  "type": "Feature",
  "properties": {
    "addr:full":"110 E Elm Ave Upsala MN 56384",
    "addr:housenumber":"110",
    "addr:postcode":"56384",
    "addr:street":"E Elm Ave",
    "iso:country":"US",
    "sg:address":"110 E Elm Ave",
    "sg:city":"Upsala",
    "sg:classifiers":[
        {
            "category":"Government",
            "subcategory":"Office",
            "type":"Public Place"
        }
    ],
    "sg:phone":"+1 320 573 4950",
    "sg:postcode":"56384",
    "sg:province":"MN",
    "sg:tags":[
        "city"
    ],
    "wof:name":"City of Upsala",
    "wof:placetype":"venue"
},
  "geometry": {"coordinates":[-94.571496,45.808591],"type":"Point"}
}