{
  "type": "Feature",
  "properties": {
    "iso:country":"US",
    "sg:address":"275 33rd St W",
    "sg:city":"Hastings",
    "sg:classifiers":[
        {
            "category":"Food & Beverages",
            "subcategory":"Liquor & Beverages",
            "type":"Retail Goods"
        }
    ],
    "sg:phone":"+1 651 438 2807",
    "sg:postcode":"55033",
    "sg:province":"MN",
    "wof:name":"Short Stop Liquor",
    "wof:placetype":"venue"
},
  "geometry": {"coordinates":[-92.84840699999999,44.715228],"type":"Point"}
}