{
  "type": "Feature",
  "properties": {
    "addr:full":"701 Xenia Ave S Minneapolis MN 55416",
    "addr:housenumber":"701",
    "addr:postcode":"55416",
    "addr:street":"Xenia Ave S",
    "iso:country":"US",
    "sg:address":"701 Xenia Ave S",
    "sg:city":"Minneapolis",
    "sg:classifiers":[
        {
            "category":"Autos & Motor Vehicles",
            "subcategory":"Automobile Sales",
            "type":"Retail Goods"
        }
    ],
    "sg:phone":"+1 763 512 1316",
    "sg:postcode":"55416",
    "sg:province":"MN",
    "sg:tags":[
        "car"
    ],
    "wof:name":"Two Grey Hills Auto Sales",
    "wof:placetype":"venue"
},
  "geometry": {"coordinates":[-93.352203,44.974602],"type":"Point"}
}