{
  "type": "Feature",
  "properties": {
    "iso:country":"US",
    "sg:address":"2909 Bryant Ave S",
    "sg:city":"Minneapolis",
    "sg:classifiers":[
        {
            "category":"Retail",
            "subcategory":"Repair Shop",
            "type":"Services"
        }
    ],
    "sg:phone":"+1 612 827 1744",
    "sg:postcode":"55408",
    "sg:province":"MN",
    "sg:tags":[
        "reupholstery",
        "furniture"
    ],
    "sg:website":"www.furnitureindustries.com",
    "wof:name":"Furniture Industries Inc",
    "wof:placetype":"venue"
},
  "geometry": {"coordinates":[-93.290497,44.949501],"type":"Point"}
}