{
  "type": "Feature",
  "properties": {
    "iso:country":"US",
    "sg:address":"425 S Lake Ave",
    "sg:city":"Duluth",
    "sg:classifiers":[
        {
            "category":"Restaurant",
            "type":"Food & Drink"
        }
    ],
    "sg:menulink":"http://www.allmenus.com/mn/duluth/243987-grandmas-sports-garden/menu/",
    "sg:phone":"+1 218 722 4724",
    "sg:postcode":"55802",
    "sg:province":"MN",
    "sg:tags":[
        "american"
    ],
    "wof:name":"Grandma's Sports Garden",
    "wof:placetype":"venue"
},
  "geometry": {"coordinates":[-92.094464,46.781349],"type":"Point"}
}