{
  "type": "Feature",
  "properties": {
    "addr:full":"6500 Parnell Ave Minneapolis MN 55435",
    "addr:housenumber":"6500",
    "addr:postcode":"55435",
    "addr:street":"Parnell Ave",
    "iso:country":"US",
    "sg:address":"6500 Parnell Ave",
    "sg:city":"Minneapolis",
    "sg:classifiers":[
        {
            "category":"Professional",
            "type":"Services"
        }
    ],
    "sg:phone":"+1 952 929 6774",
    "sg:postcode":"55435",
    "sg:province":"MN",
    "wof:name":"Orchard Psyd Ann",
    "wof:placetype":"venue"
},
  "geometry": {"coordinates":[-93.346565,44.884147],"type":"Point"}
}