{
  "type": "Feature",
  "properties": {
    "iso:country":"US",
    "sg:address":"927 N Armstrong Ave",
    "sg:city":"Litchfield",
    "sg:classifiers":[
        {
            "category":"Government",
            "subcategory":"Office",
            "type":"Public Place"
        }
    ],
    "sg:phone":"+1 320 693 8191",
    "sg:postcode":"55355",
    "sg:province":"MN",
    "wof:name":"Meeker Highway Shop",
    "wof:placetype":"venue"
},
  "geometry": {"coordinates":[-94.52397000000001,45.136788],"type":"Point"}
}