{
  "type": "Feature",
  "properties": {
    "iso:country":"US",
    "sg:address":"43572 W Paul Lake Dr",
    "sg:city":"Perham",
    "sg:classifiers":[
        {
            "category":"Professional",
            "type":"Services"
        }
    ],
    "sg:phone":"+1 218 346 6059",
    "sg:postcode":"56573",
    "sg:province":"MN",
    "sg:tags":[
        "establishment"
    ],
    "wof:name":"Janisch & Janisch",
    "wof:placetype":"venue"
},
  "geometry": {"coordinates":[-95.709305,46.593542],"type":"Point"}
}