{
  "type": "Feature",
  "properties": {
    "iso:country":"US",
    "sg:address":"6045 Lark Rd NW",
    "sg:city":"Sauk Rapids",
    "sg:classifiers":[
        {
            "category":"Building & Trades",
            "subcategory":"Construction",
            "type":"Services"
        }
    ],
    "sg:phone":"+1 320 203 7617",
    "sg:postcode":"56379",
    "sg:province":"MN",
    "sg:tags":[
        "contractor"
    ],
    "wof:name":"Rapid Container Services",
    "wof:placetype":"venue"
},
  "geometry": {"coordinates":[-94.17983700000001,45.656207],"type":"Point"}
}