{
  "type": "Feature",
  "properties": {
    "addr:full":"470 Cleveland Ave N St Paul MN 55104",
    "addr:housenumber":"470",
    "addr:postcode":"55104",
    "addr:street":"Cleveland Ave N",
    "iso:country":"US",
    "sg:address":"470 Cleveland Ave N",
    "sg:city":"St Paul",
    "sg:classifiers":[
        {
            "category":"Sports & Exercise",
            "subcategory":"Gym",
            "type":"Entertainment"
        }
    ],
    "sg:phone":"+1 571 243 2981",
    "sg:postcode":"55104",
    "sg:province":"MN",
    "sg:website":"crossfitstpaul.com",
    "wof:name":"CrossFit St Paul",
    "wof:placetype":"venue"
},
  "geometry": {"coordinates":[-93.186925,44.955036],"type":"Point"}
}