{
  "type": "Feature",
  "properties": {
    "addr:full":"2922 Lyndale Ave S Minneapolis MN 55408",
    "addr:housenumber":"2922",
    "addr:postcode":"55408",
    "addr:street":"Lyndale Ave S",
    "iso:country":"US",
    "sg:address":"2922 Lyndale Ave S",
    "sg:city":"Minneapolis",
    "sg:classifiers":[
        {
            "category":"Bars & Pubs",
            "type":"Food & Drink"
        },
        {
            "category":"Brewery",
            "type":"Food & Drink"
        }
    ],
    "sg:phone":"+1 612 821 0101",
    "sg:postcode":"55408",
    "sg:province":"MN",
    "sg:website":"www.theherkimer.com",
    "wof:name":"Herkimer the Pub and Brewery",
    "wof:placetype":"venue"
},
  "geometry": {"coordinates":[-93.2882,44.949501],"type":"Point"}
}