{
  "type": "Feature",
  "properties": {
    "addr:full":"227 McKinley Ave Eveleth MN 55734",
    "addr:housenumber":"227",
    "addr:postcode":"55734",
    "addr:street":"Mckinley Ave",
    "iso:country":"US",
    "sg:address":"227 McKinley Ave",
    "sg:city":"Eveleth",
    "sg:classifiers":[
        {
            "category":"Health Services",
            "subcategory":"Hospital",
            "type":"Services"
        }
    ],
    "sg:phone":"+1 218 744 3226",
    "sg:postcode":"55734",
    "sg:province":"MN",
    "wof:name":"Fresenius Medical Care",
    "wof:placetype":"venue"
},
  "geometry": {"coordinates":[-92.534925,47.46217],"type":"Point"}
}