{
  "type": "Feature",
  "properties": {
    "iso:country":"US",
    "sg:address":"1 Burns Dr",
    "sg:city":"Osseo",
    "sg:classifiers":[
        {
            "category":"Building & Trades",
            "subcategory":"Construction",
            "type":"Services"
        }
    ],
    "sg:phone":"+1 763 428 7519",
    "sg:postcode":"55369",
    "sg:province":"MN",
    "sg:tags":[
        "hanging",
        "contractor"
    ],
    "wof:name":"Jerry L McDearmon",
    "wof:placetype":"venue"
},
  "geometry": {"coordinates":[-93.517532,45.169678],"type":"Point"}
}