{
  "type": "Feature",
  "properties": {
    "addr:full":"50243 224th St Lake Crystal MN 56055",
    "addr:housenumber":"50243",
    "addr:postcode":"56055",
    "addr:street":"224Th St",
    "iso:country":"US",
    "sg:address":"50243 224th St",
    "sg:city":"Lake Crystal",
    "sg:classifiers":[
        {
            "category":"Professional",
            "type":"Services"
        }
    ],
    "sg:phone":"+1 507 947 3747",
    "sg:postcode":"56055",
    "sg:province":"MN",
    "wof:name":"Engles John",
    "wof:placetype":"venue"
},
  "geometry": {"coordinates":[-94.257608,44.188376],"type":"Point"}
}