{
  "type": "Feature",
  "properties": {
    "addr:full":"2236 116th St NE Monticello MN 55362",
    "addr:housenumber":"2236",
    "addr:postcode":"55362",
    "addr:street":"116Th St Ne",
    "iso:country":"US",
    "sg:address":"2236 116th St NE",
    "sg:city":"Monticello",
    "sg:classifiers":[
        {
            "category":"Sports & Exercise",
            "subcategory":"Sports Center",
            "type":"Entertainment"
        }
    ],
    "sg:phone":"+1 763 295 0090",
    "sg:postcode":"55362",
    "sg:province":"MN",
    "sg:tags":[
        "club",
        "football"
    ],
    "wof:name":"Monticello Youth Football Association In",
    "wof:placetype":"venue"
},
  "geometry": {"coordinates":[-93.845595,45.31906],"type":"Point"}
}