{
  "type": "Feature",
  "properties": {
    "addr:full":"4848 Gershwin Ave N St Paul MN 55128",
    "addr:housenumber":"4848",
    "addr:postcode":"55128",
    "addr:street":"Gershwin Ave N",
    "iso:country":"US",
    "sg:address":"4848 Gershwin Ave N",
    "sg:city":"St Paul",
    "sg:classifiers":[
        {
            "category":"Professional",
            "subcategory":"Computer Services",
            "type":"Services"
        }
    ],
    "sg:phone":"+1 651 770 2757",
    "sg:postcode":"55128",
    "sg:province":"MN",
    "sg:tags":[
        "consultant",
        "designer"
    ],
    "wof:name":"KDR Inc",
    "wof:placetype":"venue"
},
  "geometry": {"coordinates":[-92.982321,45.018659],"type":"Point"}
}