{
  "type": "Feature",
  "properties": {
    "addr:full":"4200 Minnetonka Blvd St Louis Park MN 55416",
    "addr:housenumber":"4200",
    "addr:postcode":"55416",
    "addr:street":"Minnetonka Blvd",
    "iso:country":"US",
    "sg:address":"4200 Minnetonka Blvd",
    "sg:city":"St Louis Park",
    "sg:classifiers":[
        {
            "category":"Personal",
            "subcategory":"Massage",
            "type":"Services"
        },
        {
            "category":"Shopping",
            "subcategory":"Beauty & Cosmetics",
            "type":"Retail Goods"
        },
        {
            "category":"Health Services",
            "subcategory":"Health Practitioner",
            "type":"Services"
        }
    ],
    "sg:phone":"+1 651 334 8380",
    "sg:postcode":"55416",
    "sg:province":"MN",
    "sg:tags":[
        "acupuncture",
        "supply"
    ],
    "sg:website":"www.yogacentermpls.com/",
    "wof:name":"Sara Bublitz",
    "wof:placetype":"venue"
},
  "geometry": {"coordinates":[-93.332712,44.948492],"type":"Point"}
}