{
  "type": "Feature",
  "properties": {
    "iso:country":"US",
    "sg:address":"921 Greeley St S",
    "sg:city":"Stillwater",
    "sg:classifiers":[
        {
            "category":"Health Services",
            "subcategory":"Doctor",
            "type":"Services"
        }
    ],
    "sg:phone":"+1 651 439 3023",
    "sg:postcode":"55082",
    "sg:province":"MN",
    "sg:tags":[
        "physician",
        "surgeon"
    ],
    "wof:name":"Stillwater Medical",
    "wof:placetype":"venue"
},
  "geometry": {"coordinates":[-92.819191,45.047945],"type":"Point"}
}