{
  "type": "Feature",
  "properties": {
    "iso:country":"US",
    "sg:address":"1340 Duckwood Dr",
    "sg:city":"Eagan",
    "sg:classifiers":[
        {
            "category":"Retail",
            "subcategory":"Auto Rental",
            "type":"Services"
        }
    ],
    "sg:phone":"+1 651 452 0977",
    "sg:postcode":"55123",
    "sg:province":"MN",
    "sg:tags":[
        "renting",
        "automobile",
        "passenger",
        "car"
    ],
    "sg:website":"www.enterprise.com",
    "wof:name":"Enterprise Rent-A-Car",
    "wof:placetype":"venue"
},
  "geometry": {"coordinates":[-93.16268100000001,44.8276],"type":"Point"}
}