{
  "type": "Feature",
  "properties": {
    "iso:country":"US",
    "sg:address":"1601 39th Ave NE",
    "sg:city":"Minneapolis",
    "sg:classifiers":[
        {
            "category":"Home & Garden",
            "subcategory":"Home Furnishings",
            "type":"Retail Goods"
        }
    ],
    "sg:phone":"+1 763 781 1209",
    "sg:postcode":"55421",
    "sg:province":"MN",
    "wof:name":"Tupperware Cnsltnt-Lnda Glbert",
    "wof:placetype":"venue"
},
  "geometry": {"coordinates":[-93.235834,45.038253],"type":"Point"}
}