{
  "type": "Feature",
  "properties": {
    "iso:country":"US",
    "sg:address":"307 N Hwy 86",
    "sg:city":"Lakefield",
    "sg:classifiers":[
        {
            "category":"Museum",
            "type":"Entertainment"
        }
    ],
    "sg:phone":"+1 507 662 5505",
    "sg:postcode":"56150",
    "sg:province":"MN",
    "sg:tags":[
        "gallery"
    ],
    "wof:name":"Jackson County Historical Soc",
    "wof:placetype":"venue"
},
  "geometry": {"coordinates":[-95.174683,43.678562],"type":"Point"}
}