{
  "type": "Feature",
  "properties": {
    "addr:full":"149 Lime Valley Ln Mankato MN 56001",
    "addr:housenumber":"149",
    "addr:postcode":"56001",
    "addr:street":"Lime Valley Ln",
    "iso:country":"US",
    "sg:address":"149 Lime Valley Ln",
    "sg:city":"Mankato",
    "sg:classifiers":[
        {
            "category":"Professional",
            "subcategory":"Art Services",
            "type":"Services"
        }
    ],
    "sg:phone":"+1 507 625 1481",
    "sg:postcode":"56001",
    "sg:province":"MN",
    "sg:tags":[
        "photography",
        "commercial"
    ],
    "wof:name":"Lasting Memories Photography",
    "wof:placetype":"venue"
},
  "geometry": {"coordinates":[-93.97859099999999,44.202017],"type":"Point"}
}