{
  "type": "Feature",
  "properties": {
    "iso:country":"US",
    "sg:address":"1306 Kenneth Dr",
    "sg:city":"Cloquet",
    "sg:classifiers":[
        {
            "category":"Organizations",
            "subcategory":"Religious Organization",
            "type":"Services"
        }
    ],
    "sg:phone":"+1 218 879 7757",
    "sg:postcode":"55720",
    "sg:province":"MN",
    "wof:name":"Ur Savior Lutheran Church Elca",
    "wof:placetype":"venue"
},
  "geometry": {"coordinates":[-92.444737,46.733921],"type":"Point"}
}