{
  "type": "Feature",
  "properties": {
    "iso:country":"US",
    "sg:address":"1100 E Main St",
    "sg:city":"Anoka",
    "sg:classifiers":[
        {
            "category":"Banks & Credit Unions",
            "subcategory":"Bank",
            "type":"Services"
        }
    ],
    "sg:phone":"+1 763 422 6630",
    "sg:postcode":"55303",
    "sg:province":"MN",
    "sg:tags":[
        "national"
    ],
    "wof:name":"First Bank Anoka",
    "wof:placetype":"venue"
},
  "geometry": {"coordinates":[-93.36795600000001,45.197573],"type":"Point"}
}