{
  "type": "Feature",
  "properties": {
    "addr:full":"122 2nd Ave Madison MN 56256",
    "addr:housenumber":"122",
    "addr:postcode":"56256",
    "addr:street":"2Nd Ave",
    "iso:country":"US",
    "sg:address":"122 2nd Ave",
    "sg:city":"Madison",
    "sg:classifiers":[
        {
            "category":"Home & Garden",
            "subcategory":"Carpets & Floor Coverings",
            "type":"Retail Goods"
        },
        {
            "category":"Building & Trades",
            "subcategory":"Construction",
            "type":"Services"
        }
    ],
    "sg:phone":"+1 320 598 3098",
    "sg:postcode":"56256",
    "sg:province":"MN",
    "sg:tags":[
        "dealer",
        "laying",
        "rug",
        "contractor"
    ],
    "wof:name":"Carpets N More Inc",
    "wof:placetype":"venue"
},
  "geometry": {"coordinates":[-96.187297,45.010013],"type":"Point"}
}