{
  "type": "Feature",
  "properties": {
    "addr:full":"11269 Jefferson Hwy Anoka MN 55303",
    "addr:housenumber":"11269",
    "addr:postcode":"55303",
    "addr:street":"Jefferson Hwy",
    "iso:country":"US",
    "sg:address":"11269 Jefferson Hwy",
    "sg:city":"Anoka",
    "sg:classifiers":[
        {
            "category":"Health Services",
            "subcategory":"Doctor",
            "type":"Services"
        }
    ],
    "sg:phone":"+1 763 236 0600",
    "sg:postcode":"55303",
    "sg:province":"MN",
    "wof:name":"Allina Hospitals & Clinics",
    "wof:placetype":"venue"
},
  "geometry": {"coordinates":[-93.41439800000001,45.240501],"type":"Point"}
}