{
  "type": "Feature",
  "properties": {
    "addr:full":"1605 N Riverfront Dr Mankato MN 56001",
    "addr:housenumber":"1605",
    "addr:postcode":"56001",
    "addr:street":"N Riverfront Dr",
    "iso:country":"US",
    "sg:address":"1605 N Riverfront Dr",
    "sg:city":"Mankato",
    "sg:classifiers":[
        {
            "category":"Building & Trades",
            "subcategory":"Construction",
            "type":"Services"
        }
    ],
    "sg:phone":"+1 507 388 7476",
    "sg:postcode":"56001",
    "sg:province":"MN",
    "sg:tags":[
        "home",
        "builder"
    ],
    "wof:name":"P C Builders",
    "wof:placetype":"venue"
},
  "geometry": {"coordinates":[-93.988328,44.182185],"type":"Point"}
}