{
  "type": "Feature",
  "properties": {
    "addr:full":"413 Vermillion St Hastings MN 55033",
    "addr:housenumber":"413",
    "addr:postcode":"55033",
    "addr:street":"Vermillion St",
    "iso:country":"US",
    "sg:address":"413 Vermillion St",
    "sg:city":"Hastings",
    "sg:classifiers":[
        {
            "category":"Autos & Motor Vehicles",
            "subcategory":"Boat Sales",
            "type":"Retail Goods"
        }
    ],
    "sg:phone":"+1 651 480 8300",
    "sg:postcode":"55033",
    "sg:province":"MN",
    "sg:tags":[
        "dealer",
        "sales"
    ],
    "wof:name":"Crystal-Pierz Marine",
    "wof:placetype":"venue"
},
  "geometry": {"coordinates":[-92.85231400000001,44.741403],"type":"Point"}
}