{
  "type": "Feature",
  "properties": {
    "iso:country":"US",
    "sg:address":"320 3rd Ave",
    "sg:city":"Albany",
    "sg:classifiers":[
        {
            "category":"Health Services",
            "subcategory":"Doctor",
            "type":"Services"
        }
    ],
    "sg:phone":"+1 320 845 2157",
    "sg:postcode":"56307",
    "sg:province":"MN",
    "sg:tags":[
        "clinic"
    ],
    "wof:name":"Albany Medical Center",
    "wof:placetype":"venue"
},
  "geometry": {"coordinates":[-94.567617,45.638849],"type":"Point"}
}