{
  "type": "Feature",
  "properties": {
    "iso:country":"US",
    "sg:address":"512 49th Ave N",
    "sg:city":"Minneapolis",
    "sg:classifiers":[
        {
            "category":"Professional",
            "subcategory":"Management & Consulting",
            "type":"Services"
        }
    ],
    "sg:phone":"+1 612 521 4465",
    "sg:postcode":"55430",
    "sg:province":"MN",
    "sg:tags":[
        "personnel",
        "consultant"
    ],
    "wof:name":"Star Med Staffing Minnesota",
    "wof:placetype":"venue"
},
  "geometry": {"coordinates":[-93.286427,45.044005],"type":"Point"}
}