{
  "type": "Feature",
  "properties": {
    "addr:full":"16348 60th Ave NW Cass Lake MN 56633",
    "addr:housenumber":"16348",
    "addr:postcode":"56633",
    "addr:street":"60Th Ave Nw Cass",
    "iso:country":"US",
    "sg:address":"16348 60th Ave NW",
    "sg:city":"Cass Lake",
    "sg:classifiers":[
        {
            "category":"Travel",
            "subcategory":"Hotels & Motels",
            "type":"Entertainment"
        }
    ],
    "sg:phone":"+1 218 335 2424",
    "sg:postcode":"56633",
    "sg:province":"MN",
    "sg:tags":[
        "resort",
        "operation"
    ],
    "sg:website":"www.sahkahtay.com",
    "wof:name":"Sah-Kah-Tay Beach Resort LLC",
    "wof:placetype":"venue"
},
  "geometry": {"coordinates":[-94.60005,47.392456],"type":"Point"}
}