{
  "type": "Feature",
  "properties": {
    "iso:country":"US",
    "sg:address":"711 Hennepin Ave",
    "sg:city":"Minneapolis",
    "sg:classifiers":[
        {
            "category":"Cinema",
            "subcategory":"Movie Theater",
            "type":"Entertainment"
        }
    ],
    "sg:phone":"+1 612 332 3303",
    "sg:postcode":"55403",
    "sg:province":"MN",
    "wof:name":"Mann Theatres Inc",
    "wof:placetype":"venue"
},
  "geometry": {"coordinates":[-93.274902,44.977901],"type":"Point"}
}