{
  "type": "Feature",
  "properties": {
    "addr:full":"3007 Newton Ave N Minneapolis MN 55411",
    "addr:housenumber":"3007",
    "addr:postcode":"55411",
    "addr:street":"Newton Ave N",
    "iso:country":"US",
    "sg:address":"3007 Newton Ave N",
    "sg:city":"Minneapolis",
    "sg:classifiers":[
        {
            "category":"Arts & Performance",
            "subcategory":"Theater",
            "type":"Entertainment"
        }
    ],
    "sg:phone":"+1 612 521 4488",
    "sg:postcode":"55411",
    "sg:province":"MN",
    "sg:tags":[
        "group"
    ],
    "wof:name":"Knight Sounds Entertainment",
    "wof:placetype":"venue"
},
  "geometry": {"coordinates":[-93.305702,45.013222],"type":"Point"}
}