{
  "type": "Feature",
  "properties": {
    "iso:country":"US",
    "sg:address":"20885 Georgia Ave N",
    "sg:city":"Forest Lake",
    "sg:classifiers":[
        {
            "category":"Manufacturing",
            "subcategory":"Metals",
            "type":"Manufacturing & Wholesale Goods"
        }
    ],
    "sg:phone":"+1 651 464 5433",
    "sg:postcode":"55025",
    "sg:province":"MN",
    "sg:tags":[
        "ornamental",
        "work"
    ],
    "wof:name":"Michael's Custom Metal Artwork",
    "wof:placetype":"venue"
},
  "geometry": {"coordinates":[-92.980918,45.251371],"type":"Point"}
}