{
  "type": "Feature",
  "properties": {
    "addr:full":"24505 Tucker Rd Rogers MN 55374",
    "addr:housenumber":"24505",
    "addr:postcode":"55374",
    "addr:street":"Tucker Rd",
    "iso:country":"US",
    "sg:address":"24505 Tucker Rd",
    "sg:city":"Rogers",
    "sg:classifiers":[
        {
            "category":"Building & Trades",
            "subcategory":"Landscaping Services",
            "type":"Services"
        }
    ],
    "sg:phone":"+1 763 428 3899",
    "sg:postcode":"55374",
    "sg:province":"MN",
    "sg:tags":[
        "landscape",
        "contractor"
    ],
    "wof:name":"Dehns Landscaping Inc",
    "wof:placetype":"venue"
},
  "geometry": {"coordinates":[-93.58976199999999,45.172435],"type":"Point"}
}