{
  "type": "Feature",
  "properties": {
    "addr:full":"1 N 4th St Apt B Minneapolis MN 55401",
    "addr:housenumber":"1",
    "addr:postcode":"55401",
    "addr:street":"N 4Th St Apt B",
    "iso:country":"US",
    "sg:address":"1 N 4th St Apt B",
    "sg:city":"Minneapolis",
    "sg:classifiers":[
        {
            "category":"Professional",
            "subcategory":"Engineering",
            "type":"Services"
        },
        {
            "category":"Wholesale",
            "subcategory":"Construction Materials",
            "type":"Manufacturing & Wholesale Goods"
        }
    ],
    "sg:phone":"+1 612 332 9529",
    "sg:postcode":"55401",
    "sg:province":"MN",
    "sg:tags":[
        "passenger-commercial",
        "industrial",
        "elevators-freight",
        "elevator"
    ],
    "wof:name":"Furmart Elevator Line",
    "wof:placetype":"venue"
},
  "geometry": {"coordinates":[-93.27137,44.980438],"type":"Point"}
}