{
  "type": "Feature",
  "properties": {
    "iso:country":"US",
    "sg:address":"3260 Fanum Rd",
    "sg:city":"St Paul",
    "sg:classifiers":[
        {
            "category":"Building & Trades",
            "subcategory":"Plumbing",
            "type":"Services"
        }
    ],
    "sg:phone":"+1 651 704 9366",
    "sg:postcode":"55110",
    "sg:province":"MN",
    "sg:tags":[
        "sheet",
        "work",
        "metal",
        "contractor"
    ],
    "wof:name":"Metro Sheet Metal",
    "wof:placetype":"venue"
},
  "geometry": {"coordinates":[-93.036749,45.040468],"type":"Point"}
}