{
  "type": "Feature",
  "properties": {
    "iso:country":"US",
    "sg:address":"11070 Cedar Beach Dr NW",
    "sg:city":"Oronoco",
    "sg:classifiers":[
        {
            "category":"Building & Trades",
            "subcategory":"Construction",
            "type":"Services"
        }
    ],
    "sg:phone":"+1 507 367 2246",
    "sg:postcode":"55960",
    "sg:province":"MN",
    "sg:tags":[
        "roofing",
        "contractor"
    ],
    "wof:name":"Tom Kline Roofing",
    "wof:placetype":"venue"
},
  "geometry": {"coordinates":[-92.47557999999999,44.1655],"type":"Point"}
}