{
  "type": "Feature",
  "properties": {
    "iso:country":"US",
    "sg:address":"208 2nd St E",
    "sg:city":"Hastings",
    "sg:classifiers":[
        {
            "category":"Home & Garden",
            "subcategory":"Household Appliances",
            "type":"Retail Goods"
        }
    ],
    "sg:phone":"+1 651 437 4186",
    "sg:postcode":"55033",
    "sg:province":"MN",
    "sg:tags":[
        "repair",
        "electrical"
    ],
    "wof:name":"Bathrick's Appliances Inc",
    "wof:placetype":"venue"
},
  "geometry": {"coordinates":[-92.850024,44.744269],"type":"Point"}
}