{
  "type": "Feature",
  "properties": {
    "iso:country":"US",
    "sg:address":"12564 Goodview Ave N",
    "sg:city":"Saint Paul",
    "sg:classifiers":[
        {
            "category":"Manufacturing",
            "subcategory":"Rubber & Plastics",
            "type":"Manufacturing & Wholesale Goods"
        }
    ],
    "sg:phone":"+1 651 426 1626",
    "sg:postcode":"55110",
    "sg:province":"MN",
    "sg:tags":[
        "product",
        "mfg"
    ],
    "wof:name":"Quality Molding & Trim",
    "wof:placetype":"venue"
},
  "geometry": {"coordinates":[-92.97910400000001,45.132059],"type":"Point"}
}