{
  "type": "Feature",
  "properties": {
    "addr:full":"1507 Woodland Cir Mora MN 55051",
    "addr:housenumber":"1507",
    "addr:postcode":"55051",
    "addr:street":"Woodland Cir",
    "iso:country":"US",
    "sg:address":"1507 Woodland Cir",
    "sg:city":"Mora",
    "sg:classifiers":[
        {
            "category":"Professional",
            "type":"Services"
        }
    ],
    "sg:phone":"+1 320 679 2573",
    "sg:postcode":"55051",
    "sg:province":"MN",
    "wof:name":"Northland BUIlders&remodelers",
    "wof:placetype":"venue"
},
  "geometry": {"coordinates":[-93.40931999999999,45.920825],"type":"Point"}
}