{
  "type": "Feature",
  "properties": {
    "addr:full":"9625 Zebra Ave Young America MN 55397",
    "addr:housenumber":"9625",
    "addr:postcode":"55397",
    "addr:street":"Zebra Ave",
    "iso:country":"US",
    "sg:address":"9625 Zebra Ave",
    "sg:city":"Young America",
    "sg:classifiers":[
        {
            "category":"Real Estate",
            "subcategory":"Real Estate Operator",
            "type":"Services"
        }
    ],
    "sg:phone":"+1 952 467 2844",
    "sg:postcode":"55397",
    "sg:province":"MN",
    "sg:tags":[
        "property",
        "lessor"
    ],
    "wof:name":"Elmer Fritz",
    "wof:placetype":"venue"
},
  "geometry": {"coordinates":[-94.009957,44.820691],"type":"Point"}
}