{
  "type": "Feature",
  "properties": {
    "addr:full":"1601 N Innsbruck Dr Minneapolis MN 55432",
    "addr:housenumber":"1601",
    "addr:postcode":"55432",
    "addr:street":"N Innsbruck Dr",
    "iso:country":"US",
    "sg:address":"1601 N Innsbruck Dr",
    "sg:city":"Minneapolis",
    "sg:classifiers":[
        {
            "category":"Professional",
            "subcategory":"Business Services",
            "type":"Services"
        }
    ],
    "sg:phone":"+1 763 571 9544",
    "sg:postcode":"55432",
    "sg:province":"MN",
    "wof:name":"Bridled Tongue & Logo Design",
    "wof:placetype":"venue"
},
  "geometry": {"coordinates":[-93.22758899999999,45.069576],"type":"Point"}
}