{
  "type": "Feature",
  "properties": {
    "iso:country":"US",
    "sg:address":"233 2nd St NW",
    "sg:city":"Ortonville",
    "sg:classifiers":[
        {
            "category":"Professional",
            "subcategory":"Accounting & Tax Preparation",
            "type":"Services"
        }
    ],
    "sg:phone":"+1 320 839 3459",
    "sg:postcode":"56278",
    "sg:province":"MN",
    "sg:tags":[
        "accountant"
    ],
    "wof:name":"Blair Johnson CPA PA",
    "wof:placetype":"venue"
},
  "geometry": {"coordinates":[-96.445893,45.305661],"type":"Point"}
}