{
  "type": "Feature",
  "properties": {
    "addr:full":"218 3rd St NW Faribault MN 55021",
    "addr:housenumber":"218",
    "addr:postcode":"55021",
    "addr:street":"3Rd St Nw",
    "iso:country":"US",
    "sg:address":"218 3rd St NW",
    "sg:city":"Faribault",
    "sg:classifiers":[
        {
            "category":"Professional",
            "subcategory":"Lawyer & Legal Services",
            "type":"Services"
        },
        {
            "category":"Government",
            "subcategory":"Court House",
            "type":"Public Place"
        }
    ],
    "sg:phone":"+1 507 332 6103",
    "sg:postcode":"55021",
    "sg:province":"MN",
    "sg:tags":[
        "county",
        "counsel",
        "executive"
    ],
    "wof:name":"Rice County Attorneys Office",
    "wof:placetype":"venue"
},
  "geometry": {"coordinates":[-93.27168,44.293677],"type":"Point"}
}