{
  "type": "Feature",
  "properties": {
    "addr:full":"8405 Adair Ave N Minneapolis MN 55443",
    "addr:housenumber":"8405",
    "addr:postcode":"55443",
    "addr:street":"Adair Ave N",
    "iso:country":"US",
    "sg:address":"8405 Adair Ave N",
    "sg:city":"Minneapolis",
    "sg:classifiers":[
        {
            "category":"Professional",
            "subcategory":"Engineering",
            "type":"Services"
        }
    ],
    "sg:phone":"+1 763 424 4913",
    "sg:postcode":"55443",
    "sg:province":"MN",
    "sg:tags":[
        "consulting",
        "engineer"
    ],
    "wof:name":"Spear Engineering Inc",
    "wof:placetype":"venue"
},
  "geometry": {"coordinates":[-93.35659,45.10686],"type":"Point"}
}