{
  "type": "Feature",
  "properties": {
    "addr:full":"2 E Sheridan St Ely MN 55731",
    "addr:housenumber":"2",
    "addr:postcode":"55731",
    "addr:street":"E Sheridan St",
    "iso:country":"US",
    "sg:address":"2 E Sheridan St",
    "sg:city":"Ely",
    "sg:classifiers":[
        {
            "category":"Shopping",
            "subcategory":"Bicycles & Sporting Goods",
            "type":"Retail Goods"
        }
    ],
    "sg:phone":"+1 218 365 2155",
    "sg:postcode":"55731",
    "sg:province":"MN",
    "sg:tags":[
        "surfboard"
    ],
    "wof:name":"Ely Surf Shop Inc",
    "wof:placetype":"venue"
},
  "geometry": {"coordinates":[-91.86689,47.90322],"type":"Point"}
}