{
  "type": "Feature",
  "properties": {
    "addr:full":"4035 140th Ave SE Clara City MN 56222",
    "addr:housenumber":"4035",
    "addr:postcode":"56222",
    "addr:street":"140Th Ave Se",
    "iso:country":"US",
    "sg:address":"4035 140th Ave SE",
    "sg:city":"Clara City",
    "sg:phone":"+1 320 847 2519",
    "sg:postcode":"56222",
    "sg:province":"MN",
    "sg:tags":[
        "farm",
        "grain",
        "cash"
    ],
    "wof:name":"Ammermann Farms",
    "wof:placetype":"venue"
},
  "geometry": {"coordinates":[-95.30994099999999,44.963048],"type":"Point"}
}