{
  "type": "Feature",
  "properties": {
    "iso:country":"US",
    "sg:address":"2354 7th Ave",
    "sg:city":"Anoka",
    "sg:classifiers":[
        {
            "category":"Health Services",
            "subcategory":"Medical Lab",
            "type":"Services"
        }
    ],
    "sg:phone":"+1 763 712 0702",
    "sg:postcode":"55303",
    "sg:province":"MN",
    "sg:tags":[
        "laboratory"
    ],
    "wof:name":"Millenium Dental Lab Inc",
    "wof:placetype":"venue"
},
  "geometry": {"coordinates":[-93.378292,45.203148],"type":"Point"}
}