{
  "type": "Feature",
  "properties": {
    "addr:full":"429 Cindy Ln Owatonna MN 55060",
    "addr:housenumber":"429",
    "addr:postcode":"55060",
    "addr:street":"Cindy Ln",
    "iso:country":"US",
    "sg:address":"429 Cindy Ln",
    "sg:city":"Owatonna",
    "sg:classifiers":[
        {
            "category":"Real Estate",
            "subcategory":"Real Estate Operator",
            "type":"Services"
        }
    ],
    "sg:phone":"+1 507 451 0600",
    "sg:postcode":"55060",
    "sg:province":"MN",
    "sg:tags":[
        "building",
        "apartment"
    ],
    "wof:name":"Park View Heights Townhomes",
    "wof:placetype":"venue"
},
  "geometry": {"coordinates":[-93.244435,44.07969],"type":"Point"}
}