{
  "type": "Feature",
  "properties": {
    "iso:country":"US",
    "sg:address":"5115 Excelsior Blvd 317",
    "sg:city":"Minneapolis",
    "sg:classifiers":[
        {
            "category":"Building & Trades",
            "subcategory":"Construction",
            "type":"Services"
        },
        {
            "category":"Home & Garden",
            "subcategory":"Furniture",
            "type":"Retail Goods"
        }
    ],
    "sg:phone":"+1 763 531 9191",
    "sg:postcode":"55416",
    "sg:province":"MN",
    "sg:tags":[
        "maker",
        "cabinet"
    ],
    "wof:name":"Creative Woodworking International",
    "wof:placetype":"venue"
},
  "geometry": {"coordinates":[-93.34559,44.931533],"type":"Point"}
}