{
  "type": "Feature",
  "properties": {
    "addr:full":"2024 Paul Bunyan Dr NW Bemidji MN 56601",
    "addr:housenumber":"2024",
    "addr:postcode":"56601",
    "addr:street":"Paul Bunyan Dr Nw",
    "iso:country":"US",
    "sg:address":"2024 Paul Bunyan Dr NW",
    "sg:city":"Bemidji",
    "sg:classifiers":[
        {
            "category":"Banks & Credit Unions",
            "subcategory":"Bank",
            "type":"Services"
        }
    ],
    "sg:phone":"+1 218 751 3757",
    "sg:postcode":"56601",
    "sg:province":"MN",
    "sg:website":"www.wellsfargo.com",
    "wof:name":"Wells Fargo Bank",
    "wof:placetype":"venue"
},
  "geometry": {"coordinates":[-94.90933699999999,47.495175],"type":"Point"}
}