{
  "type": "Feature",
  "properties": {
    "iso:country":"US",
    "sg:address":"16445 Co Rd 30",
    "sg:city":"Maple Grove",
    "sg:classifiers":[
        {
            "category":"Shopping",
            "type":"Retail Goods"
        },
        {
            "category":"Wholesale",
            "subcategory":"Sporting Goods",
            "type":"Manufacturing & Wholesale Goods"
        }
    ],
    "sg:phone":"+1 763 494 9934",
    "sg:postcode":"55311",
    "sg:province":"MN",
    "sg:tags":[
        "equipment",
        "merchandise",
        "pool",
        "swimming"
    ],
    "wof:name":"Second Wind Pool N Spa",
    "wof:placetype":"venue"
},
  "geometry": {"coordinates":[-93.48729,45.12539],"type":"Point"}
}