{
  "type": "Feature",
  "properties": {
    "addr:full":"30 Main St Soudan MN 55782",
    "addr:housenumber":"30",
    "addr:postcode":"55782",
    "addr:street":"Main St",
    "iso:country":"US",
    "sg:address":"30 Main St",
    "sg:city":"Soudan",
    "sg:classifiers":[
        {
            "category":"Shopping",
            "subcategory":"Bicycles & Sporting Goods",
            "type":"Retail Goods"
        }
    ],
    "sg:phone":"+1 218 753 8070",
    "sg:postcode":"55782",
    "sg:province":"MN",
    "sg:tags":[
        "bait",
        "fishing"
    ],
    "wof:name":"Bite-Em Bait N Tackle",
    "wof:placetype":"venue"
},
  "geometry": {"coordinates":[-92.245486,47.816564],"type":"Point"}
}