{
  "type": "Feature",
  "properties": {
    "iso:country":"US",
    "sg:address":"362 Juniper St",
    "sg:city":"Saint Paul",
    "sg:classifiers":[
        {
            "category":"Building & Trades",
            "subcategory":"Construction",
            "type":"Services"
        }
    ],
    "sg:phone":"+1 651 779 0850",
    "sg:postcode":"55115",
    "sg:province":"MN",
    "sg:tags":[
        "carpentry",
        "contractor"
    ],
    "wof:name":"Dovetail Carpentry",
    "wof:placetype":"venue"
},
  "geometry": {"coordinates":[-92.948612,45.068538],"type":"Point"}
}