{
  "type": "Feature",
  "properties": {
    "addr:full":"7000 Rolling Acres Rd Excelsior MN 55331",
    "addr:housenumber":"7000",
    "addr:postcode":"55331",
    "addr:street":"Rolling Acres Rd",
    "iso:country":"US",
    "sg:address":"7000 Rolling Acres Rd",
    "sg:city":"Excelsior",
    "sg:classifiers":[
        {
            "category":"Real Estate",
            "subcategory":"Architect",
            "type":"Services"
        }
    ],
    "sg:phone":"+1 952 474 6696",
    "sg:postcode":"55331",
    "sg:province":"MN",
    "sg:tags":[
        "architectural",
        "mfg"
    ],
    "wof:name":"Vosejpka Associates Inc",
    "wof:placetype":"venue"
},
  "geometry": {"coordinates":[-93.641446,44.877882],"type":"Point"}
}