{
  "type": "Feature",
  "properties": {
    "addr:full":"19 E Pleasant Lake Rd Saint Paul MN 55127",
    "addr:housenumber":"19",
    "addr:postcode":"55127",
    "addr:street":"E Pleasant Lake Rd",
    "iso:country":"US",
    "sg:address":"19 E Pleasant Lake Rd",
    "sg:city":"Saint Paul",
    "sg:classifiers":[
        {
            "category":"Building & Trades",
            "subcategory":"Construction",
            "type":"Services"
        }
    ],
    "sg:phone":"+1 651 631 1122",
    "sg:postcode":"55127",
    "sg:province":"MN",
    "sg:tags":[
        "contractor"
    ],
    "wof:name":"Anderson Fireplaces",
    "wof:placetype":"venue"
},
  "geometry": {"coordinates":[-93.09135000000001,45.089149],"type":"Point"}
}