{
  "type": "Feature",
  "properties": {
    "addr:full":"61289 Meeker Stearns St Eden Valley MN 55329",
    "addr:housenumber":"61289",
    "addr:postcode":"55329",
    "addr:street":"St",
    "iso:country":"US",
    "sg:address":"61289 Meeker Stearns St",
    "sg:city":"Eden Valley",
    "sg:classifiers":[
        {
            "category":"Retail",
            "subcategory":"Repair Shop",
            "type":"Services"
        }
    ],
    "sg:phone":"+1 320 453 7268",
    "sg:postcode":"55329",
    "sg:province":"MN",
    "wof:name":"Neumans Jim Small Engine",
    "wof:placetype":"venue"
},
  "geometry": {"coordinates":[-94.529213,45.326089],"type":"Point"}
}