{
  "type": "Feature",
  "properties": {
    "addr:full":"23247 350th St Albany MN 56307",
    "addr:housenumber":"23247",
    "addr:postcode":"56307",
    "addr:street":"350Th St",
    "iso:country":"US",
    "sg:address":"23247 350th St",
    "sg:city":"Albany",
    "sg:classifiers":[
        {
            "category":"Farming",
            "subcategory":"Livestock Farm",
            "type":"Manufacturing & Wholesale Goods"
        }
    ],
    "sg:phone":"+1 320 845 2857",
    "sg:postcode":"56307",
    "sg:province":"MN",
    "sg:tags":[
        "feedlot",
        "hog",
        "or",
        "beef",
        "cattle"
    ],
    "wof:name":"George Reber",
    "wof:placetype":"venue"
},
  "geometry": {"coordinates":[-94.603042,45.628611],"type":"Point"}
}