{
  "type": "Feature",
  "properties": {
    "addr:full":"410 Bridge Ave Albert Lea MN 56007",
    "addr:housenumber":"410",
    "addr:postcode":"56007",
    "addr:street":"Bridge Ave",
    "iso:country":"US",
    "sg:address":"410 Bridge Ave",
    "sg:city":"Albert Lea",
    "sg:classifiers":[
        {
            "category":"Shopping",
            "subcategory":"Florist",
            "type":"Retail Goods"
        }
    ],
    "sg:phone":"+1 507 373 8523",
    "sg:postcode":"56007",
    "sg:province":"MN",
    "wof:name":"Ben's Floral & Frame Designs",
    "wof:placetype":"venue"
},
  "geometry": {"coordinates":[-93.360415,43.652177],"type":"Point"}
}