{
  "type": "Feature",
  "properties": {
    "addr:full":"1316 4th St SE Minneapolis MN 55414",
    "addr:housenumber":"1316",
    "addr:postcode":"55414",
    "addr:street":"4Th St Se",
    "iso:country":"US",
    "sg:address":"1316 4th St SE",
    "sg:city":"Minneapolis",
    "sg:classifiers":[
        {
            "category":"Shopping",
            "subcategory":"Bicycles & Sporting Goods",
            "type":"Retail Goods"
        }
    ],
    "sg:phone":"+1 612 623 0990",
    "sg:postcode":"55414",
    "sg:province":"MN",
    "sg:tags":[
        "bike"
    ],
    "sg:website":"www.varsitybike.com",
    "wof:name":"Varsity Bike Shop",
    "wof:placetype":"venue"
},
  "geometry": {"coordinates":[-93.236288,44.980702],"type":"Point"}
}