{
  "type": "Feature",
  "properties": {
    "addr:full":"1 Main St N Kimball MN 55353",
    "addr:housenumber":"1",
    "addr:postcode":"55353",
    "addr:street":"Main St N",
    "iso:country":"US",
    "sg:address":"1 Main St N",
    "sg:city":"Kimball",
    "sg:classifiers":[
        {
            "category":"Government",
            "subcategory":"Police Station",
            "type":"Public Place"
        }
    ],
    "sg:phone":"+1 320 398 2871",
    "sg:postcode":"55353",
    "sg:province":"MN",
    "sg:tags":[
        "department"
    ],
    "wof:name":"Kimball Police Dept",
    "wof:placetype":"venue"
},
  "geometry": {"coordinates":[-94.30036,45.31415],"type":"Point"}
}