{
  "type": "Feature",
  "properties": {
    "addr:full":"4755 Miller Trunk Hwy Hermantown MN 55811",
    "addr:housenumber":"4755",
    "addr:postcode":"55811",
    "addr:street":"Miller Trunk Hwy",
    "iso:country":"US",
    "sg:address":"4755 Miller Trunk Hwy",
    "sg:city":"Hermantown",
    "sg:phone":"+1 218 720 6123",
    "sg:postcode":"55811",
    "sg:province":"MN",
    "sg:website":"http://www.duluthdodge.com",
    "wof:name":"Duluth Suzuki",
    "wof:placetype":"venue"
},
  "geometry": {"coordinates":[-92.179847,46.818004],"type":"Point"}
}