{
  "type": "Feature",
  "properties": {
    "iso:country":"US",
    "sg:address":"2160 108th Ln NE",
    "sg:city":"Minneapolis",
    "sg:classifiers":[
        {
            "category":"Building & Trades",
            "subcategory":"Construction",
            "type":"Services"
        }
    ],
    "sg:phone":"+1 763 784 6910",
    "sg:postcode":"55449",
    "sg:province":"MN",
    "sg:tags":[
        "house",
        "nonresidential"
    ],
    "wof:name":"Socon",
    "wof:placetype":"venue"
},
  "geometry": {"coordinates":[-93.215576,45.167068],"type":"Point"}
}