{
  "type": "Feature",
  "properties": {
    "addr:full":"823 University Ave W St Paul MN 55104",
    "addr:housenumber":"823",
    "addr:postcode":"55104",
    "addr:street":"University Ave W",
    "iso:country":"US",
    "sg:address":"823 University Ave W",
    "sg:city":"St Paul",
    "sg:classifiers":[
        {
            "category":"Restaurant",
            "type":"Food & Drink"
        },
        {
            "category":"Wholesale",
            "subcategory":"Groceries",
            "type":"Manufacturing & Wholesale Goods"
        }
    ],
    "sg:phone":"+1 651 291 2661",
    "sg:postcode":"55104",
    "sg:province":"MN",
    "sg:tags":[
        "bakery",
        "retail"
    ],
    "wof:name":"Ala Francaise",
    "wof:placetype":"venue"
},
  "geometry": {"coordinates":[-93.135801,44.955798],"type":"Point"}
}