{
  "type": "Feature",
  "properties": {
    "iso:country":"US",
    "sg:address":"1831 Alameda St",
    "sg:city":"Saint Paul",
    "sg:classifiers":[
        {
            "category":"Professional",
            "subcategory":"Management & Consulting",
            "type":"Services"
        }
    ],
    "sg:phone":"+1 651 488 2356",
    "sg:postcode":"55113",
    "sg:province":"MN",
    "wof:name":"Solutions International Inc",
    "wof:placetype":"venue"
},
  "geometry": {"coordinates":[-93.130937,44.996986],"type":"Point"}
}