{
  "type": "Feature",
  "properties": {
    "addr:full":"204 Adams St Morgan MN 56266",
    "addr:housenumber":"204",
    "addr:postcode":"56266",
    "addr:street":"Adams St",
    "iso:country":"US",
    "sg:address":"204 Adams St",
    "sg:city":"Morgan",
    "sg:classifiers":[
        {
            "category":"Farming",
            "subcategory":"Dairy Farm",
            "type":"Manufacturing & Wholesale Goods"
        }
    ],
    "sg:phone":"+1 507 249 3360",
    "sg:postcode":"56266",
    "sg:province":"MN",
    "sg:tags":[
        "field",
        "corn",
        "crop"
    ],
    "wof:name":"Thomas Hoffmann",
    "wof:placetype":"venue"
},
  "geometry": {"coordinates":[-94.92362300000001,44.410908],"type":"Point"}
}