{
  "type": "Feature",
  "properties": {
    "iso:country":"US",
    "sg:address":"821 N Front St",
    "sg:city":"New Ulm",
    "sg:classifiers":[
        {
            "category":"Retail",
            "subcategory":"Auto Repair",
            "type":"Services"
        }
    ],
    "sg:phone":"+1 507 354 7700",
    "sg:postcode":"56073",
    "sg:province":"MN",
    "sg:tags":[
        "truck"
    ],
    "wof:name":"New Ulm Truck & Trailer",
    "wof:placetype":"venue"
},
  "geometry": {"coordinates":[-94.464324,44.32723],"type":"Point"}
}