{
  "type": "Feature",
  "properties": {
    "iso:country":"US",
    "sg:address":"9477 585th Ave",
    "sg:city":"Wells",
    "sg:classifiers":[
        {
            "category":"Manufacturing",
            "subcategory":"Food",
            "type":"Manufacturing & Wholesale Goods"
        },
        {
            "category":"Wholesale",
            "subcategory":"Fruits & Vegetables",
            "type":"Manufacturing & Wholesale Goods"
        },
        {
            "category":"Farming",
            "subcategory":"Farm",
            "type":"Manufacturing & Wholesale Goods"
        }
    ],
    "sg:phone":"+1 507 294 3379",
    "sg:postcode":"56097",
    "sg:province":"MN",
    "sg:tags":[
        "corn",
        "bean",
        "product"
    ],
    "wof:name":"David Strehlow",
    "wof:placetype":"venue"
},
  "geometry": {"coordinates":[-93.698194,43.626014],"type":"Point"}
}