{
  "type": "Feature",
  "properties": {
    "addr:full":"2303 Kennedy St NE Minneapolis MN 55413",
    "addr:housenumber":"2303",
    "addr:postcode":"55413",
    "addr:street":"Kennedy St Ne",
    "iso:country":"US",
    "sg:address":"2303 Kennedy St NE",
    "sg:city":"Minneapolis",
    "sg:classifiers":[
        {
            "category":"Manufacturing",
            "subcategory":"Lumber",
            "type":"Manufacturing & Wholesale Goods"
        }
    ],
    "sg:phone":"+1 612 617 0446",
    "sg:postcode":"55413",
    "sg:province":"MN",
    "sg:tags":[
        "mfg",
        "custom",
        "furniture"
    ],
    "wof:name":"Erik Wyckoff Artworks",
    "wof:placetype":"venue"
},
  "geometry": {"coordinates":[-93.22726,44.99515],"type":"Point"}
}