{
  "type": "Feature",
  "properties": {
    "addr:full":"13694 Grove Dr Osseo MN 55311",
    "addr:housenumber":"13694",
    "addr:postcode":"55311",
    "addr:street":"Grove Dr",
    "iso:country":"US",
    "sg:address":"13694 Grove Dr",
    "sg:city":"Osseo",
    "sg:classifiers":[
        {
            "category":"Shopping",
            "subcategory":"Clothing, Apparel, & Fashions",
            "type":"Retail Goods"
        }
    ],
    "sg:phone":"+1 763 494 9499",
    "sg:postcode":"55311",
    "sg:province":"MN",
    "sg:tags":[
        "tailor"
    ],
    "wof:name":"Magic Needle",
    "wof:placetype":"venue"
},
  "geometry": {"coordinates":[-93.45315600000001,45.104127],"type":"Point"}
}