{
  "type": "Feature",
  "properties": {
    "iso:country":"US",
    "sg:address":"1149 Riverwood Dr",
    "sg:city":"Burnsville",
    "sg:classifiers":[
        {
            "category":"Professional",
            "type":"Services"
        }
    ],
    "sg:phone":"+1 952 736 7725",
    "sg:postcode":"55337",
    "sg:province":"MN",
    "wof:name":"Commerical Door",
    "wof:placetype":"venue"
},
  "geometry": {"coordinates":[-93.258703,44.785186],"type":"Point"}
}