{
  "type": "Feature",
  "properties": {
    "iso:country":"US",
    "sg:address":"3949 133rd Ct W",
    "sg:city":"Rosemount",
    "sg:classifiers":[
        {
            "category":"Professional",
            "subcategory":"Business Services",
            "type":"Services"
        }
    ],
    "sg:phone":"+1 651 503 6081",
    "sg:postcode":"55068",
    "sg:province":"MN",
    "wof:name":"A Gal I Know",
    "wof:placetype":"venue"
},
  "geometry": {"coordinates":[-93.146095,44.756889],"type":"Point"}
}