{
  "type": "Feature",
  "properties": {
    "iso:country":"US",
    "sg:address":"5815 E Superior St",
    "sg:city":"Duluth",
    "sg:classifiers":[
        {
            "category":"Retail",
            "subcategory":"Car Wash",
            "type":"Services"
        }
    ],
    "sg:phone":"+1 218 625 0290",
    "sg:postcode":"55804",
    "sg:province":"MN",
    "sg:tags":[
        "polishing",
        "washing"
    ],
    "wof:name":"Self Service Car Washes",
    "wof:placetype":"venue"
},
  "geometry": {"coordinates":[-92.00943700000001,46.838454],"type":"Point"}
}