{
  "type": "Feature",
  "properties": {
    "addr:full":"15 1st Ave S Buffalo MN 55313",
    "addr:housenumber":"15",
    "addr:postcode":"55313",
    "addr:street":"1St Ave S Buffalo",
    "iso:country":"US",
    "sg:address":"15 1st Ave S",
    "sg:city":"Buffalo",
    "sg:classifiers":[
        {
            "category":"Banks & Credit Unions",
            "subcategory":"Bank",
            "type":"Services"
        }
    ],
    "sg:phone":"+1 763 682 9470",
    "sg:postcode":"55313",
    "sg:province":"MN",
    "sg:tags":[
        "loan"
    ],
    "wof:name":"Brunworth Home Loans",
    "wof:placetype":"venue"
},
  "geometry": {"coordinates":[-93.87488399999999,45.171891],"type":"Point"}
}