{
  "type": "Feature",
  "properties": {
    "addr:full":"1849 200th St Truman MN 56088",
    "addr:housenumber":"1849",
    "addr:postcode":"56088",
    "addr:street":"200Th St",
    "iso:country":"US",
    "sg:address":"1849 200th St",
    "sg:city":"Truman",
    "sg:phone":"+1 507 776 4377",
    "sg:postcode":"56088",
    "sg:province":"MN",
    "sg:tags":[
        "farm",
        "corn"
    ],
    "wof:name":"Peterson Pork",
    "wof:placetype":"venue"
},
  "geometry": {"coordinates":[-94.50244000000001,43.774824],"type":"Point"}
}