{
  "type": "Feature",
  "properties": {
    "addr:full":"619 W Prairie St Le Center MN 56057",
    "addr:housenumber":"619",
    "addr:postcode":"56057",
    "addr:street":"W Prairie St",
    "iso:country":"US",
    "sg:address":"619 W Prairie St",
    "sg:city":"Le Center",
    "sg:phone":"+1 507 357 4952",
    "sg:postcode":"56057",
    "sg:province":"MN",
    "sg:tags":[
        "farm",
        "corn"
    ],
    "wof:name":"Henry Macho",
    "wof:placetype":"venue"
},
  "geometry": {"coordinates":[-93.740696,44.398819],"type":"Point"}
}