{
  "type": "Feature",
  "properties": {
    "addr:full":"6040 Main St Rockford MN 55373",
    "addr:housenumber":"6040",
    "addr:postcode":"55373",
    "addr:street":"Main St",
    "iso:country":"US",
    "sg:address":"6040 Main St",
    "sg:city":"Rockford",
    "sg:classifiers":[
        {
            "category":"Professional",
            "subcategory":"Lawyer & Legal Services",
            "type":"Services"
        }
    ],
    "sg:phone":"+1 763 477 4677",
    "sg:postcode":"55373",
    "sg:province":"MN",
    "wof:name":"Schirdo Law",
    "wof:placetype":"venue"
},
  "geometry": {"coordinates":[-93.734506,45.088246],"type":"Point"}
}