{
  "type": "Feature",
  "properties": {
    "addr:full":"3759 31st St SE St Cloud MN 56304",
    "addr:housenumber":"3759",
    "addr:postcode":"56304",
    "addr:street":"31St St Se",
    "iso:country":"US",
    "sg:address":"3759 31st St SE",
    "sg:city":"St Cloud",
    "sg:classifiers":[
        {
            "category":"Building & Trades",
            "subcategory":"Construction",
            "type":"Services"
        }
    ],
    "sg:phone":"+1 320 203 7145",
    "sg:postcode":"56304",
    "sg:province":"MN",
    "sg:tags":[
        "underground",
        "wire",
        "laying",
        "cable",
        "utility"
    ],
    "wof:name":"Walker & Son Construction",
    "wof:placetype":"venue"
},
  "geometry": {"coordinates":[-94.081937,45.523365],"type":"Point"}
}