{
  "type": "Feature",
  "properties": {
    "addr:full":"6205 214th St W Jordan MN 55352",
    "addr:housenumber":"6205",
    "addr:postcode":"55352",
    "addr:street":"214Th St W",
    "iso:country":"US",
    "sg:address":"6205 214th St W",
    "sg:city":"Jordan",
    "sg:classifiers":[
        {
            "category":"Building & Trades",
            "subcategory":"Construction",
            "type":"Services"
        }
    ],
    "sg:phone":"+1 952 492 3296",
    "sg:postcode":"55352",
    "sg:province":"MN",
    "sg:tags":[
        "contractor"
    ],
    "wof:name":"Otto Construction",
    "wof:placetype":"venue"
},
  "geometry": {"coordinates":[-93.647442,44.639616],"type":"Point"}
}