{
  "type": "Feature",
  "properties": {
    "addr:full":"6116 Parnell Ave Minneapolis MN 55424",
    "addr:housenumber":"6116",
    "addr:postcode":"55424",
    "addr:street":"Parnell Ave",
    "iso:country":"US",
    "sg:address":"6116 Parnell Ave",
    "sg:city":"Minneapolis",
    "sg:classifiers":[
        {
            "category":"Professional",
            "subcategory":"Management & Consulting",
            "type":"Services"
        }
    ],
    "sg:phone":"+1 612 720 4888",
    "sg:postcode":"55424",
    "sg:province":"MN",
    "sg:tags":[
        "town",
        "city",
        "regional",
        "planner"
    ],
    "wof:name":"Brauer Group",
    "wof:placetype":"venue"
},
  "geometry": {"coordinates":[-93.346833,44.891236],"type":"Point"}
}