{
  "type": "Feature",
  "properties": {
    "iso:country":"US",
    "sg:address":"5759 US Hwy 14",
    "sg:city":"Janesville",
    "sg:phone":"+1 507 234 5766",
    "sg:postcode":"56048",
    "sg:province":"MN",
    "sg:tags":[
        "farm",
        "grain",
        "cash"
    ],
    "wof:name":"Guse Eldo",
    "wof:placetype":"venue"
},
  "geometry": {"coordinates":[-93.64688599999999,44.111354],"type":"Point"}
}