{
  "type": "Feature",
  "properties": {
    "iso:country":"US",
    "sg:address":"4300 Park Glen Rd",
    "sg:city":"Minneapolis",
    "sg:classifiers":[
        {
            "category":"Professional",
            "subcategory":"Management & Consulting",
            "type":"Services"
        }
    ],
    "sg:phone":"+1 952 927 9716",
    "sg:postcode":"55416",
    "sg:province":"MN",
    "sg:tags":[
        "sound",
        "system",
        "consultant"
    ],
    "sg:website":"http://www.archoustics-midwest.com",
    "wof:name":"Acoustics Midwest",
    "wof:placetype":"venue"
},
  "geometry": {"coordinates":[-93.33793,44.943323],"type":"Point"}
}