{
  "type": "Feature",
  "properties": {
    "addr:full":"2009 11th Ave NE Austin MN 55912",
    "addr:housenumber":"2009",
    "addr:postcode":"55912",
    "addr:street":"11Th Ave Ne",
    "iso:country":"US",
    "sg:address":"2009 11th Ave NE",
    "sg:city":"Austin",
    "sg:classifiers":[
        {
            "category":"Professional",
            "subcategory":"Business Services",
            "type":"Services"
        }
    ],
    "sg:phone":"+1 507 437 6977",
    "sg:postcode":"55912",
    "sg:province":"MN",
    "wof:name":"Meadow Brook Soft Water Svc",
    "wof:placetype":"venue"
},
  "geometry": {"coordinates":[-92.941912,43.677218],"type":"Point"}
}