{
  "type": "Feature",
  "properties": {
    "addr:full":"1433 Utica Ave S Ste 57 Minneapolis MN 55416",
    "addr:housenumber":"1433",
    "addr:postcode":"55416",
    "addr:street":"Utica Ave S Ste 57",
    "iso:country":"US",
    "sg:address":"1433 Utica Ave S Ste 57",
    "sg:city":"Minneapolis",
    "sg:classifiers":[
        {
            "category":"Education",
            "subcategory":"Special Training",
            "type":"Public Place"
        }
    ],
    "sg:phone":"+1 952 593 0369",
    "sg:postcode":"55416",
    "sg:province":"MN",
    "sg:tags":[
        "tutoring"
    ],
    "wof:name":"Halpern Sheryl Newman Learning Specialist Prp Schl",
    "wof:placetype":"venue"
},
  "geometry": {"coordinates":[-93.345299,44.969601],"type":"Point"}
}