{
  "type": "Feature",
  "properties": {
    "addr:full":"6120 Blue Circle Dr Hopkins MN 55343",
    "addr:housenumber":"6120",
    "addr:postcode":"55343",
    "addr:street":"Blue Circle Dr",
    "iso:country":"US",
    "sg:address":"6120 Blue Circle Dr",
    "sg:city":"Hopkins",
    "sg:classifiers":[
        {
            "category":"Real Estate",
            "subcategory":"Real Estate Services",
            "type":"Services"
        },
        {
            "category":"Insurance",
            "subcategory":"Hazard Insurance",
            "type":"Services"
        },
        {
            "category":"Insurance",
            "subcategory":"Health Insurance",
            "type":"Services"
        },
        {
            "category":"Insurance",
            "subcategory":"Life Insurance",
            "type":"Services"
        }
    ],
    "sg:phone":"+1 952 938 4646",
    "sg:postcode":"55343",
    "sg:province":"MN",
    "sg:tags":[
        "fire",
        "management",
        "commercial",
        "business"
    ],
    "sg:website":"http://www.emcins.com",
    "wof:name":"Employers Mutual Insurance",
    "wof:placetype":"venue"
},
  "geometry": {"coordinates":[-93.408089,44.892239],"type":"Point"}
}