{
  "type": "Feature",
  "properties": {
    "addr:full":"734 7th St Westbrook MN 56183",
    "addr:housenumber":"734",
    "addr:postcode":"56183",
    "addr:street":"7Th St",
    "iso:country":"US",
    "sg:address":"734 7th St",
    "sg:city":"Westbrook",
    "sg:classifiers":[
        {
            "category":"Insurance",
            "subcategory":"Insurance Agent",
            "type":"Services"
        }
    ],
    "sg:phone":"+1 507 274 5962",
    "sg:postcode":"56183",
    "sg:province":"MN",
    "wof:name":"Knakmuhs Agency",
    "wof:placetype":"venue"
},
  "geometry": {"coordinates":[-95.43557199999999,44.043169],"type":"Point"}
}