{
  "type": "Feature",
  "properties": {
    "iso:country":"US",
    "sg:address":"2879 Fairview Ln",
    "sg:city":"Long Lake",
    "sg:classifiers":[
        {
            "category":"Banks & Credit Unions",
            "subcategory":"Financial Services",
            "type":"Services"
        }
    ],
    "sg:phone":"+1 952 473 9777",
    "sg:postcode":"55356",
    "sg:province":"MN",
    "sg:tags":[
        "company",
        "holding"
    ],
    "wof:name":"Bremer Capital Holdings LLC",
    "wof:placetype":"venue"
},
  "geometry": {"coordinates":[-93.600078,44.965305],"type":"Point"}
}