{
  "type": "Feature",
  "properties": {
    "iso:country":"US",
    "sg:address":"224 S Avenue",
    "sg:city":"Minneapolis",
    "sg:classifiers":[
        {
            "category":"Shopping",
            "subcategory":"Clothing, Apparel, & Fashions",
            "type":"Retail Goods"
        },
        {
            "category":"Manufacturing",
            "subcategory":"Jewelry",
            "type":"Manufacturing & Wholesale Goods"
        },
        {
            "category":"Shopping",
            "type":"Retail Goods"
        }
    ],
    "sg:phone":"+1 952 854 8043",
    "sg:postcode":"55425",
    "sg:province":"MN",
    "sg:tags":[
        "handbag",
        "collectible",
        "accessory",
        "novelty",
        "women's"
    ],
    "sg:website":"http://www.brighton.com",
    "wof:name":"Brighton Collectibles",
    "wof:placetype":"venue"
},
  "geometry": {"coordinates":[-93.243201,44.853714],"type":"Point"}
}