{
  "type": "Feature",
  "properties": {
    "iso:country":"US",
    "sg:address":"24197 Jade Ave",
    "sg:city":"Silver Lake",
    "sg:phone":"+1 320 327 2411",
    "sg:postcode":"55381",
    "sg:province":"MN",
    "sg:tags":[
        "farm",
        "corn"
    ],
    "wof:name":"John Shimanski",
    "wof:placetype":"venue"
},
  "geometry": {"coordinates":[-94.215575,44.968554],"type":"Point"}
}