{
  "type": "Feature",
  "properties": {
    "addr:full":"115 5th St NW Bemidji MN 56601",
    "addr:housenumber":"115",
    "addr:postcode":"56601",
    "addr:street":"5Th St Nw",
    "iso:country":"US",
    "sg:address":"115 5th St NW",
    "sg:city":"Bemidji",
    "sg:classifiers":[
        {
            "category":"Professional",
            "subcategory":"Lawyer & Legal Services",
            "type":"Services"
        }
    ],
    "sg:phone":"+1 218 751 3130",
    "sg:postcode":"56601",
    "sg:province":"MN",
    "sg:tags":[
        "attorney"
    ],
    "wof:name":"Smith Law Firm PA",
    "wof:placetype":"venue"
},
  "geometry": {"coordinates":[-94.881141,47.472707],"type":"Point"}
}