{
  "type": "Feature",
  "properties": {
    "addr:full":"1930 20th St SW Appleton MN 56208",
    "addr:housenumber":"1930",
    "addr:postcode":"56208",
    "addr:street":"20Th St Sw",
    "iso:country":"US",
    "sg:address":"1930 20th St SW",
    "sg:city":"Appleton",
    "sg:phone":"+1 320 394 2242",
    "sg:postcode":"56208",
    "sg:province":"MN",
    "sg:tags":[
        "farm",
        "corn",
        "wheat"
    ],
    "wof:name":"Ascheman Farm",
    "wof:placetype":"venue"
},
  "geometry": {"coordinates":[-95.99014699999999,45.29718],"type":"Point"}
}