{
  "type": "Feature",
  "properties": {
    "addr:full":"1700 Hwy 25 N Buffalo MN 55313",
    "addr:housenumber":"1700",
    "addr:postcode":"55313",
    "addr:street":"Hwy 25 N",
    "iso:country":"US",
    "sg:address":"1700 Hwy 25 N",
    "sg:city":"Buffalo",
    "sg:classifiers":[
        {
            "category":"Health Services",
            "subcategory":"Doctor",
            "type":"Services"
        }
    ],
    "sg:phone":"+1 763 682 9241",
    "sg:postcode":"55313",
    "sg:province":"MN",
    "sg:tags":[
        "medical"
    ],
    "wof:name":"Charles M Yancey MD",
    "wof:placetype":"venue"
},
  "geometry": {"coordinates":[-93.871061,45.197295],"type":"Point"}
}