{
  "type": "Feature",
  "properties": {
    "iso:country":"US",
    "sg:address":"4133 32nd Ave S",
    "sg:city":"Moorhead",
    "sg:classifiers":[
        {
            "category":"Home & Garden",
            "subcategory":"Hardware",
            "type":"Retail Goods"
        }
    ],
    "sg:phone":"+1 218 236 7099",
    "sg:postcode":"56560",
    "sg:province":"MN",
    "sg:tags":[
        "equipment"
    ],
    "wof:name":"Olsen Chain & Cable Inc",
    "wof:placetype":"venue"
},
  "geometry": {"coordinates":[-96.709464,46.841412],"type":"Point"}
}