{
  "type": "Feature",
  "properties": {
    "addr:full":"73504 200th St Dassel MN 55325",
    "addr:housenumber":"73504",
    "addr:postcode":"55325",
    "addr:street":"200Th St",
    "iso:country":"US",
    "sg:address":"73504 200th St",
    "sg:city":"Dassel",
    "sg:classifiers":[
        {
            "category":"Home & Garden",
            "subcategory":"Garden Supply",
            "type":"Retail Goods"
        }
    ],
    "sg:phone":"+1 320 275 2527",
    "sg:postcode":"55325",
    "sg:province":"MN",
    "sg:tags":[
        "bulb",
        "seed"
    ],
    "wof:name":"Dahlman Seed Co",
    "wof:placetype":"venue"
},
  "geometry": {"coordinates":[-94.27955799999999,45.035945],"type":"Point"}
}