{
  "type": "Feature",
  "properties": {
    "addr:full":"416 S Front St New Ulm MN 56073",
    "addr:housenumber":"416",
    "addr:postcode":"56073",
    "addr:street":"S Front St",
    "iso:country":"US",
    "sg:address":"416 S Front St",
    "sg:city":"New Ulm",
    "sg:classifiers":[
        {
            "category":"Retail",
            "subcategory":"Repair Shop",
            "type":"Services"
        }
    ],
    "sg:phone":"+1 507 359 9505",
    "sg:postcode":"56073",
    "sg:province":"MN",
    "wof:name":"Dianes Upholstery",
    "wof:placetype":"venue"
},
  "geometry": {"coordinates":[-94.449138,44.311393],"type":"Point"}
}