{
  "type": "Feature",
  "properties": {
    "iso:country":"US",
    "sg:address":"14735 93rd Ave",
    "sg:city":"Kimball",
    "sg:classifiers":[
        {
            "category":"Wholesale",
            "subcategory":"Construction Materials",
            "type":"Manufacturing & Wholesale Goods"
        }
    ],
    "sg:phone":"+1 320 398 7625",
    "sg:postcode":"55353",
    "sg:province":"MN",
    "sg:tags":[
        "sand",
        "gravel"
    ],
    "wof:name":"Stearns Aggregate",
    "wof:placetype":"venue"
},
  "geometry": {"coordinates":[-94.30278800000001,45.33557],"type":"Point"}
}