{
  "type": "Feature",
  "properties": {
    "addr:full":"4148 Meadow Pkwy Duluth MN 55811",
    "addr:housenumber":"4148",
    "addr:postcode":"55811",
    "addr:street":"Meadow Pkwy",
    "iso:country":"US",
    "sg:address":"4148 Meadow Pkwy",
    "sg:city":"Duluth",
    "sg:classifiers":[
        {
            "category":"Health Services",
            "subcategory":"Health Practitioner",
            "type":"Services"
        }
    ],
    "sg:phone":"+1 218 428 8004",
    "sg:postcode":"55811",
    "sg:province":"MN",
    "wof:name":"Ann Camenga",
    "wof:placetype":"venue"
},
  "geometry": {"coordinates":[-92.19418,46.808132],"type":"Point"}
}