{
  "type": "Feature",
  "properties": {
    "addr:full":"1108 Scanlon Way Cloquet MN 55720",
    "addr:housenumber":"1108",
    "addr:postcode":"55720",
    "addr:street":"Scanlon Way",
    "iso:country":"US",
    "sg:address":"1108 Scanlon Way",
    "sg:city":"Cloquet",
    "sg:classifiers":[
        {
            "category":"Shopping",
            "subcategory":"Pets & Pet Supplies",
            "type":"Retail Goods"
        },
        {
            "category":"Retail",
            "subcategory":"Veterinary Services",
            "type":"Services"
        }
    ],
    "sg:phone":"+1 218 879 5356",
    "sg:postcode":"55720",
    "sg:province":"MN",
    "sg:tags":[
        "hospital",
        "specialty",
        "dog",
        "clinic",
        "veterinarian",
        "furnishing",
        "cat",
        "store"
    ],
    "wof:name":"Goebel Crow Veterinary Clinic",
    "wof:placetype":"venue"
},
  "geometry": {"coordinates":[-92.426355,46.706761],"type":"Point"}
}