{
  "type": "Feature",
  "properties": {
    "addr:full":"14566 Chrome Ave Rosemount MN 55068",
    "addr:housenumber":"14566",
    "addr:postcode":"55068",
    "addr:street":"Chrome Ave",
    "iso:country":"US",
    "sg:address":"14566 Chrome Ave",
    "sg:city":"Rosemount",
    "sg:classifiers":[
        {
            "category":"Retail",
            "subcategory":"Auto Repair",
            "type":"Services"
        }
    ],
    "sg:phone":"+1 651 423 2270",
    "sg:postcode":"55068",
    "sg:province":"MN",
    "sg:tags":[
        "general"
    ],
    "wof:name":"Engine Service",
    "wof:placetype":"venue"
},
  "geometry": {"coordinates":[-93.137612,44.737225],"type":"Point"}
}