{
  "type": "Feature",
  "properties": {
    "addr:full":"3189 Fernbrook Ln N Minneapolis MN 55447",
    "addr:housenumber":"3189",
    "addr:postcode":"55447",
    "addr:street":"Fernbrook Ln N",
    "iso:country":"US",
    "sg:address":"3189 Fernbrook Ln N",
    "sg:city":"Minneapolis",
    "sg:classifiers":[
        {
            "category":"Manufacturing",
            "subcategory":"Tools & Machinery",
            "type":"Manufacturing & Wholesale Goods"
        }
    ],
    "sg:phone":"+1 763 753 8157",
    "sg:postcode":"55447",
    "sg:province":"MN",
    "sg:tags":[
        "outdoor",
        "lighting",
        "other",
        "provides"
    ],
    "wof:name":"Signature Lighting Inc",
    "wof:placetype":"venue"
},
  "geometry": {"coordinates":[-93.461505,45.016362],"type":"Point"}
}