{
  "type": "Feature",
  "properties": {
    "addr:full":"3505 8th St S Moorhead MN 56560",
    "addr:housenumber":"3505",
    "addr:postcode":"56560",
    "addr:street":"8Th St S",
    "iso:country":"US",
    "sg:address":"3505 8th St S",
    "sg:city":"Moorhead",
    "sg:classifiers":[
        {
            "category":"Personal",
            "subcategory":"Beauty Salon",
            "type":"Services"
        }
    ],
    "sg:phone":"+1 218 233 6939",
    "sg:postcode":"56560",
    "sg:province":"MN",
    "sg:tags":[
        "shop"
    ],
    "wof:name":"Holiday Barber Stylist",
    "wof:placetype":"venue"
},
  "geometry": {"coordinates":[-96.768051,46.836809],"type":"Point"}
}