{
  "type": "Feature",
  "properties": {
    "iso:country":"US",
    "sg:address":"1175 Co Rd D E",
    "sg:city":"St Paul",
    "sg:classifiers":[
        {
            "category":"Real Estate",
            "subcategory":"Real Estate Operator",
            "type":"Services"
        },
        {
            "category":"Building & Trades",
            "subcategory":"Landscaping Services",
            "type":"Services"
        }
    ],
    "sg:phone":"+1 651 483 2659",
    "sg:postcode":"55109",
    "sg:province":"MN",
    "sg:tags":[
        "apartment"
    ],
    "wof:name":"Shadow Lawn Estates",
    "wof:placetype":"venue"
},
  "geometry": {"coordinates":[-93.05645199999999,45.035951],"type":"Point"}
}