{
  "type": "Feature",
  "properties": {
    "iso:country":"US",
    "sg:address":"14964 Pixie Point Cir SE",
    "sg:city":"Prior Lake",
    "sg:classifiers":[
        {
            "category":"Communications",
            "type":"Services"
        }
    ],
    "sg:phone":"+1 952 447 7784",
    "sg:postcode":"55372",
    "sg:province":"MN",
    "sg:tags":[
        "communication"
    ],
    "wof:name":"Database Marketing Resources",
    "wof:placetype":"venue"
},
  "geometry": {"coordinates":[-93.40175000000001,44.732468],"type":"Point"}
}