{
  "type": "Feature",
  "properties": {
    "iso:country":"US",
    "sg:address":"1049 Oregon Ave",
    "sg:city":"Breckenridge",
    "sg:classifiers":[
        {
            "category":"Social Services",
            "subcategory":"Child Care",
            "type":"Services"
        }
    ],
    "sg:phone":"+1 218 643 3701",
    "sg:postcode":"56520",
    "sg:province":"MN",
    "sg:tags":[
        "daycare",
        "provider"
    ],
    "wof:name":"Darcy Tolbert",
    "wof:placetype":"venue"
},
  "geometry": {"coordinates":[-96.579266,46.259545],"type":"Point"}
}