{
  "type": "Feature",
  "properties": {
    "iso:country":"US",
    "sg:address":"5625 Xerxes Ave N",
    "sg:city":"Brooklyn Center",
    "sg:classifiers":[
        {
            "category":"Food & Beverages",
            "subcategory":"Liquor & Beverages",
            "type":"Retail Goods"
        }
    ],
    "sg:phone":"+1 763 561 2420",
    "sg:postcode":"55430",
    "sg:province":"MN",
    "wof:name":"Brooklyn Center Municipal Lqr",
    "wof:placetype":"venue"
},
  "geometry": {"coordinates":[-93.320679,45.058883],"type":"Point"}
}