{
  "type": "Feature",
  "properties": {
    "addr:full":"2618 17th Ave North St Paul MN 55109",
    "addr:housenumber":"2618",
    "addr:postcode":"55109",
    "addr:street":"17Th Ave",
    "iso:country":"US",
    "sg:address":"2618 17th Ave",
    "sg:city":"North St Paul",
    "sg:classifiers":[
        {
            "category":"Food & Beverages",
            "subcategory":"Groceries & Convenience Stores",
            "type":"Retail Goods"
        }
    ],
    "sg:phone":"+1 651 777 0810",
    "sg:postcode":"55109",
    "sg:province":"MN",
    "sg:tags":[
        "grocer"
    ],
    "wof:name":"Silver Lake Market",
    "wof:placetype":"venue"
},
  "geometry": {"coordinates":[-92.99133,45.021023],"type":"Point"}
}