{
  "type": "Feature",
  "properties": {
    "addr:full":"7931 Penn Ave S Bloomington MN 55431",
    "addr:housenumber":"7931",
    "addr:postcode":"55431",
    "addr:street":"Penn Ave S",
    "iso:country":"US",
    "sg:address":"7931 Penn Ave S",
    "sg:city":"Bloomington",
    "sg:classifiers":[
        {
            "category":"Shopping",
            "subcategory":"Department Store",
            "type":"Retail Goods"
        }
    ],
    "sg:phone":"+1 952 881 8861",
    "sg:postcode":"55431",
    "sg:province":"MN",
    "wof:name":"Kohl's",
    "wof:placetype":"venue"
},
  "geometry": {"coordinates":[-93.308634,44.86049],"type":"Point"}
}