{
  "type": "Feature",
  "properties": {
    "iso:country":"US",
    "sg:address":"3220 W Calhoun Pkwy",
    "sg:city":"Minneapolis",
    "sg:classifiers":[
        {
            "category":"Banks & Credit Unions",
            "subcategory":"Financial Services",
            "type":"Services"
        }
    ],
    "sg:phone":"+1 612 799 6962",
    "sg:postcode":"55416",
    "sg:province":"MN",
    "sg:tags":[
        "investor"
    ],
    "wof:name":"Rubin Family Investments",
    "wof:placetype":"venue"
},
  "geometry": {"coordinates":[-93.32028099999999,44.942223],"type":"Point"}
}