{
  "type": "Feature",
  "properties": {
    "addr:full":"201 2nd Ave SW Wells MN 56097",
    "addr:housenumber":"201",
    "addr:postcode":"56097",
    "addr:street":"2Nd Ave Sw",
    "iso:country":"US",
    "sg:address":"201 2nd Ave SW",
    "sg:city":"Wells",
    "sg:classifiers":[
        {
            "category":"Organizations",
            "subcategory":"Religious Organization",
            "type":"Services"
        }
    ],
    "sg:phone":"+1 507 553 5165",
    "sg:postcode":"56097",
    "sg:province":"MN",
    "wof:name":"Calvary Baptist Church",
    "wof:placetype":"venue"
},
  "geometry": {"coordinates":[-93.72832699999999,43.7431],"type":"Point"}
}