{
  "type": "Feature",
  "properties": {
    "addr:full":"118 SE 10th St Grand Rapids MN 55744",
    "addr:housenumber":"118",
    "addr:postcode":"55744",
    "addr:street":"Se 10Th St",
    "iso:country":"US",
    "sg:address":"118 SE 10th St",
    "sg:city":"Grand Rapids",
    "sg:classifiers":[
        {
            "category":"Retail",
            "subcategory":"Auto Repair",
            "type":"Services"
        }
    ],
    "sg:phone":"+1 218 326 0363",
    "sg:postcode":"55744",
    "sg:province":"MN",
    "sg:tags":[
        "repairing",
        "automobile",
        "general",
        "supply"
    ],
    "wof:name":"Bob's Southside Tire & Auto",
    "wof:placetype":"venue"
},
  "geometry": {"coordinates":[-93.52687899999999,47.221074],"type":"Point"}
}