{
  "type": "Feature",
  "properties": {
    "iso:country":"US",
    "sg:address":"25818 Island Lake Rd",
    "sg:city":"Cold Spring",
    "sg:classifiers":[
        {
            "category":"Banks & Credit Unions",
            "subcategory":"Bank",
            "type":"Services"
        }
    ],
    "sg:phone":"+1 320 685 7074",
    "sg:postcode":"56320",
    "sg:province":"MN",
    "sg:tags":[
        "personal",
        "institution"
    ],
    "wof:name":"Newcourt Financial",
    "wof:placetype":"venue"
},
  "geometry": {"coordinates":[-94.404433,45.49141],"type":"Point"}
}