{
  "type": "Feature",
  "properties": {
    "addr:full":"2000 Cliff Lake Rd Saint Paul MN 55122",
    "addr:housenumber":"2000",
    "addr:postcode":"55122",
    "addr:street":"Cliff Lake Rd",
    "iso:country":"US",
    "sg:address":"2000 Cliff Lake Rd",
    "sg:city":"Saint Paul",
    "sg:classifiers":[
        {
            "category":"Shopping",
            "subcategory":"Department Store",
            "type":"Retail Goods"
        }
    ],
    "sg:phone":"+1 651 688 8706",
    "sg:postcode":"55122",
    "sg:province":"MN",
    "wof:name":"Target Stores",
    "wof:placetype":"venue"
},
  "geometry": {"coordinates":[-93.201103,44.795502],"type":"Point"}
}