{
  "type": "Feature",
  "properties": {
    "addr:full":"47 Little Canada Rd E Little Canada MN 55117",
    "addr:housenumber":"47",
    "addr:postcode":"55117",
    "addr:street":"Little Canada Rd E",
    "iso:country":"US",
    "sg:address":"47 Little Canada Rd E",
    "sg:city":"Little Canada",
    "sg:classifiers":[
        {
            "category":"Shopping",
            "type":"Retail Goods"
        }
    ],
    "sg:phone":"+1 651 483 5768",
    "sg:postcode":"55117",
    "sg:province":"MN",
    "sg:tags":[
        "hearing",
        "equipment",
        "supply",
        "merchandise",
        "impaired"
    ],
    "wof:name":"All Hear-World Wide",
    "wof:placetype":"venue"
},
  "geometry": {"coordinates":[-93.099756,45.025621],"type":"Point"}
}