{
  "type": "Feature",
  "properties": {
    "iso:country":"US",
    "sg:address":"3619 Oakton Ridge",
    "sg:city":"Hopkins",
    "sg:classifiers":[
        {
            "category":"Wholesale",
            "subcategory":"Farm Supplies",
            "type":"Manufacturing & Wholesale Goods"
        }
    ],
    "sg:phone":"+1 952 938 7680",
    "sg:postcode":"55305",
    "sg:province":"MN",
    "sg:tags":[
        "livestock"
    ],
    "wof:name":"Frontier Livestock",
    "wof:placetype":"venue"
},
  "geometry": {"coordinates":[-93.42,44.937692],"type":"Point"}
}