{
  "type": "Feature",
  "properties": {
    "iso:country":"US",
    "sg:address":"1103 Industry Ave",
    "sg:city":"Cloquet",
    "sg:classifiers":[
        {
            "category":"Wholesale",
            "subcategory":"Scrap",
            "type":"Manufacturing & Wholesale Goods"
        }
    ],
    "sg:phone":"+1 218 879 4332",
    "sg:postcode":"55720",
    "sg:province":"MN",
    "sg:tags":[
        "recycling",
        "center"
    ],
    "wof:name":"Cloquet Riverside Recycling Inc",
    "wof:placetype":"venue"
},
  "geometry": {"coordinates":[-92.449994,46.724915],"type":"Point"}
}