{
  "type": "Feature",
  "properties": {
    "addr:full":"24276 Smiley Rd Nisswa MN 56468",
    "addr:housenumber":"24276",
    "addr:postcode":"56468",
    "addr:street":"Smiley Rd",
    "iso:country":"US",
    "sg:address":"24276 Smiley Rd",
    "sg:city":"Nisswa",
    "sg:classifiers":[
        {
            "category":"Retail",
            "subcategory":"Car Wash",
            "type":"Services"
        }
    ],
    "sg:phone":"+1 218 963 1204",
    "sg:postcode":"56468",
    "sg:province":"MN",
    "sg:tags":[
        "carwash"
    ],
    "wof:name":"Liquid Reflektions Inc",
    "wof:placetype":"venue"
},
  "geometry": {"coordinates":[-94.29755,46.504419],"type":"Point"}
}