{
  "type": "Feature",
  "properties": {
    "iso:country":"US",
    "sg:address":"4750 Maple St",
    "sg:city":"Rockford",
    "sg:classifiers":[
        {
            "category":"Building & Trades",
            "subcategory":"Construction",
            "type":"Services"
        }
    ],
    "sg:phone":"+1 763 477 5077",
    "sg:postcode":"55373",
    "sg:province":"MN",
    "sg:tags":[
        "excavation",
        "excavating",
        "contractor"
    ],
    "wof:name":"Quickway Excavating Co",
    "wof:placetype":"venue"
},
  "geometry": {"coordinates":[-93.750378,45.081682],"type":"Point"}
}