{
  "type": "Feature",
  "properties": {
    "iso:country":"US",
    "sg:address":"3101 S Frontage Rd",
    "sg:city":"Moorhead",
    "sg:classifiers":[
        {
            "category":"Insurance",
            "subcategory":"Hazard Insurance",
            "type":"Services"
        },
        {
            "category":"Insurance",
            "subcategory":"Insurance Agent",
            "type":"Services"
        },
        {
            "category":"Insurance",
            "subcategory":"Life Insurance",
            "type":"Services"
        },
        {
            "category":"Insurance",
            "subcategory":"Title Insurance",
            "type":"Services"
        }
    ],
    "sg:phone":"+1 218 233 1216",
    "sg:postcode":"56560",
    "sg:province":"MN",
    "sg:tags":[
        "property",
        "casualty",
        "homeowner"
    ],
    "sg:website":"http://www.amfam.com/agentlocator/BBERG?sourceid=yp9",
    "wof:name":"American Family Insurance- Brent Berg",
    "wof:placetype":"venue"
},
  "geometry": {"coordinates":[-96.730755,46.875503],"type":"Point"}
}