{
  "type": "Feature",
  "properties": {
    "iso:country":"US",
    "sg:address":"1291 W 2nd St",
    "sg:city":"Winona",
    "sg:classifiers":[
        {
            "category":"Shopping",
            "subcategory":"Used Merchandise",
            "type":"Retail Goods"
        }
    ],
    "sg:phone":"+1 507 454 6675",
    "sg:postcode":"55987",
    "sg:province":"MN",
    "wof:name":"Cheryls Antiques",
    "wof:placetype":"venue"
},
  "geometry": {"coordinates":[-91.670501,44.05663],"type":"Point"}
}