{
  "type": "Feature",
  "properties": {
    "iso:country":"US",
    "sg:address":"6305 Cambridge St",
    "sg:city":"Minneapolis",
    "sg:classifiers":[
        {
            "category":"Building & Trades",
            "subcategory":"Construction",
            "type":"Services"
        }
    ],
    "sg:phone":"+1 952 925 6156",
    "sg:postcode":"55416",
    "sg:province":"MN",
    "sg:tags":[
        "house"
    ],
    "wof:name":"John Haley 1 Roofer",
    "wof:placetype":"venue"
},
  "geometry": {"coordinates":[-93.35836,44.933353],"type":"Point"}
}