{
  "type": "Feature",
  "properties": {
    "addr:full":"400 Main St New Ulm MN 56073",
    "addr:housenumber":"400",
    "addr:postcode":"56073",
    "addr:street":"Main St",
    "iso:country":"US",
    "sg:address":"400 Main St",
    "sg:city":"New Ulm",
    "sg:classifiers":[
        {
            "category":"Restaurant",
            "type":"Food & Drink"
        }
    ],
    "sg:phone":"+1 507 354 1228",
    "sg:postcode":"56073",
    "sg:province":"MN",
    "sg:tags":[
        "eating"
    ],
    "wof:name":"Main Jiang House",
    "wof:placetype":"venue"
},
  "geometry": {"coordinates":[-94.433486,44.228615],"type":"Point"}
}