{
  "type": "Feature",
  "properties": {
    "iso:country":"US",
    "sg:address":"201 Crestway Ln",
    "sg:city":"Saint Paul",
    "sg:classifiers":[
        {
            "category":"Professional",
            "subcategory":"Management & Consulting",
            "type":"Services"
        }
    ],
    "sg:phone":"+1 651 451 0063",
    "sg:postcode":"55118",
    "sg:province":"MN",
    "wof:name":"Pearson Consulting Inc",
    "wof:placetype":"venue"
},
  "geometry": {"coordinates":[-93.09439500000001,44.889061],"type":"Point"}
}