{
  "type": "Feature",
  "properties": {
    "addr:full":"14888 Natchez Ave Savage MN 55378",
    "addr:housenumber":"14888",
    "addr:postcode":"55378",
    "addr:street":"Natchez Ave",
    "iso:country":"US",
    "sg:address":"14888 Natchez Ave",
    "sg:city":"Savage",
    "sg:classifiers":[
        {
            "category":"Health Services",
            "subcategory":"Doctor",
            "type":"Services"
        }
    ],
    "sg:phone":"+1 952 447 5082",
    "sg:postcode":"55378",
    "sg:province":"MN",
    "sg:tags":[
        "physician",
        "surgeon"
    ],
    "wof:name":"Hartland Surgical Svc Inc",
    "wof:placetype":"venue"
},
  "geometry": {"coordinates":[-93.339353,44.736433],"type":"Point"}
}