{
  "type": "Feature",
  "properties": {
    "addr:full":"14563 Ymca Ln Lake Park MN 56554",
    "addr:housenumber":"14563",
    "addr:postcode":"56554",
    "addr:street":"Ymca Ln",
    "iso:country":"US",
    "sg:address":"14563 Ymca Ln",
    "sg:city":"Lake Park",
    "sg:classifiers":[
        {
            "category":"Travel",
            "subcategory":"Campground",
            "type":"Entertainment"
        }
    ],
    "sg:phone":"+1 218 532 2570",
    "sg:postcode":"56554",
    "sg:province":"MN",
    "sg:tags":[
        "camp"
    ],
    "sg:website":"www.fmymca.org",
    "wof:name":"Camp Cormorant",
    "wof:placetype":"venue"
},
  "geometry": {"coordinates":[-96.06811399999999,46.788043],"type":"Point"}
}