{
  "type": "Feature",
  "properties": {
    "addr:full":"2715 Upper Afton Rd St Paul MN 55119",
    "addr:housenumber":"2715",
    "addr:postcode":"55119",
    "addr:street":"Upper Afton Rd",
    "iso:country":"US",
    "sg:address":"2715 Upper Afton Rd",
    "sg:city":"St Paul",
    "sg:classifiers":[
        {
            "category":"Building & Trades",
            "subcategory":"Landscaping Services",
            "type":"Services"
        }
    ],
    "sg:phone":"+1 651 735 9404",
    "sg:postcode":"55119",
    "sg:province":"MN",
    "sg:tags":[
        "lawn",
        "maintenance",
        "grounds"
    ],
    "wof:name":"Thomson Grass Valley",
    "wof:placetype":"venue"
},
  "geometry": {"coordinates":[-92.98469799999999,44.941494],"type":"Point"}
}