{
  "type": "Feature",
  "properties": {
    "addr:full":"900 S Broadway Rochester MN 55904",
    "addr:housenumber":"900",
    "addr:postcode":"55904",
    "addr:street":"S Broadway",
    "iso:country":"US",
    "sg:address":"900 S Broadway",
    "sg:city":"Rochester",
    "sg:classifiers":[
        {
            "category":"Autos & Motor Vehicles",
            "subcategory":"Automobile Sales",
            "type":"Retail Goods"
        }
    ],
    "sg:phone":"+1 507 536 0006",
    "sg:postcode":"55904",
    "sg:province":"MN",
    "sg:tags":[
        "car",
        "dealer"
    ],
    "wof:name":"Soldier's Field Motors",
    "wof:placetype":"venue"
},
  "geometry": {"coordinates":[-92.46311900000001,44.007999],"type":"Point"}
}