{
  "type": "Feature",
  "properties": {
    "iso:country":"US",
    "sg:address":"75903 230th St",
    "sg:city":"Albert Lea",
    "sg:classifiers":[
        {
            "category":"Wholesale",
            "subcategory":"Machinery & Supplies",
            "type":"Manufacturing & Wholesale Goods"
        }
    ],
    "sg:phone":"+1 507 373 0669",
    "sg:postcode":"56007",
    "sg:province":"MN",
    "sg:tags":[
        "farm",
        "equipment"
    ],
    "wof:name":"Budach Implement Albert Lea",
    "wof:placetype":"venue"
},
  "geometry": {"coordinates":[-93.351333,43.687509],"type":"Point"}
}