{
  "type": "Feature",
  "properties": {
    "iso:country":"US",
    "sg:address":"227 Main St",
    "sg:city":"Wanamingo",
    "sg:classifiers":[
        {
            "category":"Retail",
            "subcategory":"Auto Repair",
            "type":"Services"
        }
    ],
    "sg:phone":"+1 507 824 2247",
    "sg:postcode":"55983",
    "sg:province":"MN",
    "sg:tags":[
        "repairing",
        "automobile"
    ],
    "wof:name":"Romness Garage",
    "wof:placetype":"venue"
},
  "geometry": {"coordinates":[-92.79069,44.303968],"type":"Point"}
}