{
  "type": "Feature",
  "properties": {
    "addr:full":"6715 Featherstone Dr Savage MN 55378",
    "addr:housenumber":"6715",
    "addr:postcode":"55378",
    "addr:street":"Featherstone Dr",
    "iso:country":"US",
    "sg:address":"6715 Featherstone Dr",
    "sg:city":"Savage",
    "sg:classifiers":[
        {
            "category":"Building & Trades",
            "subcategory":"Construction",
            "type":"Services"
        }
    ],
    "sg:phone":"+1 952 447 6004",
    "sg:postcode":"55378",
    "sg:province":"MN",
    "sg:tags":[
        "home",
        "builder"
    ],
    "wof:name":"Merlyn Olson Homes",
    "wof:placetype":"venue"
},
  "geometry": {"coordinates":[-93.364831,44.743265],"type":"Point"}
}