{
  "type": "Feature",
  "properties": {
    "iso:country":"US",
    "sg:address":"485 Westfield Ln",
    "sg:city":"Saint Paul",
    "sg:classifiers":[
        {
            "category":"Social Services",
            "subcategory":"Child Care",
            "type":"Services"
        }
    ],
    "sg:phone":"+1 651 429 6889",
    "sg:postcode":"55127",
    "sg:province":"MN",
    "sg:tags":[
        "day"
    ],
    "wof:name":"Kathy M Parsons",
    "wof:placetype":"venue"
},
  "geometry": {"coordinates":[-93.076448,45.073576],"type":"Point"}
}