{
  "type": "Feature",
  "properties": {
    "iso:country":"US",
    "sg:address":"560 Indian Mound St E",
    "sg:city":"Wayzata",
    "sg:classifiers":[
        {
            "category":"Professional",
            "subcategory":"Lawyer & Legal Services",
            "type":"Services"
        }
    ],
    "sg:phone":"+1 952 473 3434",
    "sg:postcode":"55391",
    "sg:province":"MN",
    "sg:tags":[
        "attorney"
    ],
    "wof:name":"Howard Robe Alton",
    "wof:placetype":"venue"
},
  "geometry": {"coordinates":[-93.51379900000001,44.970794],"type":"Point"}
}