{
  "type": "Feature",
  "properties": {
    "addr:full":"17339 State Hwy 34 Park Rapids MN 56470",
    "addr:housenumber":"17339",
    "addr:postcode":"56470",
    "addr:street":"State Hwy 34",
    "iso:country":"US",
    "sg:address":"17339 State Hwy 34",
    "sg:city":"Park Rapids",
    "sg:classifiers":[
        {
            "category":"Arts & Performance",
            "subcategory":"Theater",
            "type":"Entertainment"
        }
    ],
    "sg:phone":"+1 218 237 4333",
    "sg:postcode":"56470",
    "sg:province":"MN",
    "sg:tags":[
        "live",
        "music"
    ],
    "wof:name":"Jasper's Jubilee Theater",
    "wof:placetype":"venue"
},
  "geometry": {"coordinates":[-94.998034,46.929291],"type":"Point"}
}