{
  "type": "Feature",
  "properties": {
    "iso:country":"US",
    "sg:address":"3318 Highway 10 E",
    "sg:city":"Moorhead",
    "sg:classifiers":[
        {
            "category":"Retail",
            "subcategory":"Laundry & Dry Cleaning",
            "type":"Services"
        }
    ],
    "sg:phone":"+1 218 233 3110",
    "sg:postcode":"56560",
    "sg:province":"MN",
    "sg:tags":[
        "laundries-self",
        "operated",
        "washer",
        "dryer",
        "coin"
    ],
    "wof:name":"Moorhead Maytag Laundry",
    "wof:placetype":"venue"
},
  "geometry": {"coordinates":[-96.737472,46.876492],"type":"Point"}
}