{
  "type": "Feature",
  "properties": {
    "iso:country":"US",
    "sg:address":"8300 Norman Center Dr",
    "sg:city":"Minneapolis",
    "sg:classifiers":[
        {
            "category":"Wholesale",
            "subcategory":"Electrical",
            "type":"Manufacturing & Wholesale Goods"
        }
    ],
    "sg:phone":"+1 952 921 8300",
    "sg:postcode":"55437",
    "sg:province":"MN",
    "sg:tags":[
        "engineering",
        "electronic"
    ],
    "wof:name":"LSI Logic",
    "wof:placetype":"venue"
},
  "geometry": {"coordinates":[-93.352211,44.854015],"type":"Point"}
}