{
  "type": "Feature",
  "properties": {
    "addr:full":"6429 W 218th St Jordan MN 55352",
    "addr:housenumber":"6429",
    "addr:postcode":"55352",
    "addr:street":"W 218Th St",
    "iso:country":"US",
    "sg:address":"6429 W 218th St",
    "sg:city":"Jordan",
    "sg:classifiers":[
        {
            "category":"Building & Trades",
            "subcategory":"Construction",
            "type":"Services"
        }
    ],
    "sg:phone":"+1 952 492 5039",
    "sg:postcode":"55352",
    "sg:province":"MN",
    "sg:tags":[
        "system",
        "contractor",
        "air conditioning"
    ],
    "wof:name":"Zahler Heating And Air Conditioning Inc",
    "wof:placetype":"venue"
},
  "geometry": {"coordinates":[-93.652981,44.63415],"type":"Point"}
}