{
  "type": "Feature",
  "properties": {
    "iso:country":"US",
    "sg:address":"425 E River Pkwy Ste 347",
    "sg:city":"Minneapolis",
    "sg:classifiers":[
        {
            "category":"Health Services",
            "subcategory":"Doctor",
            "type":"Services"
        }
    ],
    "sg:phone":"+1 800 433 3243",
    "sg:postcode":"55455",
    "sg:province":"MN",
    "sg:tags":[
        "physician",
        "cardiology",
        "surgeons",
        "surgeon",
        "surgery-general"
    ],
    "wof:name":"University of Minnesota-Srgry",
    "wof:placetype":"venue"
},
  "geometry": {"coordinates":[-93.233887,44.971031],"type":"Point"}
}