{
  "type": "Feature",
  "properties": {
    "iso:country":"US",
    "sg:address":"440 Guernsey Ln",
    "sg:city":"Red Wing",
    "sg:classifiers":[
        {
            "category":"Retail",
            "subcategory":"Auto Repair",
            "type":"Services"
        }
    ],
    "sg:phone":"+1 651 388 1406",
    "sg:postcode":"55066",
    "sg:province":"MN",
    "sg:tags":[
        "automotive",
        "general"
    ],
    "wof:name":"Dodes Raidiator Repair Welding",
    "wof:placetype":"venue"
},
  "geometry": {"coordinates":[-92.517647,44.537504],"type":"Point"}
}