{
  "type": "Feature",
  "properties": {
    "addr:full":"221 Church St Watkins MN 55389",
    "addr:housenumber":"221",
    "addr:postcode":"55389",
    "addr:street":"Church St",
    "iso:country":"US",
    "sg:address":"221 Church St",
    "sg:city":"Watkins",
    "sg:classifiers":[
        {
            "category":"Retail",
            "subcategory":"Funeral Services",
            "type":"Services"
        }
    ],
    "sg:phone":"+1 320 764 2800",
    "sg:postcode":"55389",
    "sg:province":"MN",
    "sg:tags":[
        "director"
    ],
    "wof:name":"Ertl Funeral Home",
    "wof:placetype":"venue"
},
  "geometry": {"coordinates":[-94.408018,45.314178],"type":"Point"}
}