{
  "type": "Feature",
  "properties": {
    "iso:country":"US",
    "sg:address":"2024 Co Rd 45",
    "sg:city":"Owatonna",
    "sg:classifiers":[
        {
            "category":"Building & Trades",
            "subcategory":"Cleaning & Sanitation",
            "type":"Services"
        }
    ],
    "sg:phone":"+1 507 451 4138",
    "sg:postcode":"55060",
    "sg:province":"MN",
    "sg:tags":[
        "janitor"
    ],
    "wof:name":"Superb Building Maintenance",
    "wof:placetype":"venue"
},
  "geometry": {"coordinates":[-93.24165499999999,44.108125],"type":"Point"}
}