{
  "type": "Feature",
  "properties": {
    "iso:country":"US",
    "sg:address":"820 E Court St",
    "sg:city":"Belle Plaine",
    "sg:classifiers":[
        {
            "category":"Home & Garden",
            "subcategory":"Furniture",
            "type":"Retail Goods"
        }
    ],
    "sg:phone":"+1 952 873 6949",
    "sg:postcode":"56011",
    "sg:province":"MN",
    "sg:tags":[
        "shop",
        "custom",
        "kitchen",
        "cabinet"
    ],
    "wof:name":"Hartman Cabinets & Customs",
    "wof:placetype":"venue"
},
  "geometry": {"coordinates":[-93.756229,44.626165],"type":"Point"}
}