{
  "type": "Feature",
  "properties": {
    "iso:country":"US",
    "sg:address":"105 Jake St",
    "sg:city":"Perham",
    "sg:classifiers":[
        {
            "category":"Building & Trades",
            "subcategory":"Pest Control",
            "type":"Services"
        }
    ],
    "sg:phone":"+1 218 346 7378",
    "sg:postcode":"56573",
    "sg:province":"MN",
    "wof:name":"Pest Solutions Inc",
    "wof:placetype":"venue"
},
  "geometry": {"coordinates":[-95.57496,46.583589],"type":"Point"}
}