{
  "type": "Feature",
  "properties": {
    "iso:country":"US",
    "sg:address":"768 State 6 NE",
    "sg:city":"Outing",
    "sg:classifiers":[
        {
            "category":"Manufacturing",
            "subcategory":"Tools & Machinery",
            "type":"Manufacturing & Wholesale Goods"
        },
        {
            "category":"Retail",
            "subcategory":"Repair Shop",
            "type":"Services"
        },
        {
            "category":"Retail",
            "subcategory":"Auto Repair",
            "type":"Services"
        }
    ],
    "sg:phone":"+1 218 792 5816",
    "sg:postcode":"56662",
    "sg:province":"MN",
    "sg:tags":[
        "machine",
        "automobile",
        "machinery-rebuild"
    ],
    "wof:name":"Best Engineering Res Group",
    "wof:placetype":"venue"
},
  "geometry": {"coordinates":[-93.94379000000001,46.830682],"type":"Point"}
}