{
  "type": "Feature",
  "properties": {
    "addr:full":"55 Sherburne Ave Saint Paul MN 55103",
    "addr:housenumber":"55",
    "addr:postcode":"55103",
    "addr:street":"Sherburne Ave",
    "iso:country":"US",
    "sg:address":"55 Sherburne Ave",
    "sg:city":"Saint Paul",
    "sg:classifiers":[
        {
            "category":"Organizations",
            "subcategory":"Labor Organization",
            "type":"Services"
        }
    ],
    "sg:phone":"+1 651 228 0575",
    "sg:postcode":"55103",
    "sg:province":"MN",
    "wof:name":"United Tchncal Cllege Edcators",
    "wof:placetype":"venue"
},
  "geometry": {"coordinates":[-93.10150400000001,44.956917],"type":"Point"}
}