{
  "type": "Feature",
  "properties": {
    "iso:country":"US",
    "sg:address":"5208 3rd Ave S",
    "sg:city":"Minneapolis",
    "sg:classifiers":[
        {
            "category":"Professional",
            "type":"Services"
        }
    ],
    "sg:phone":"+1 612 824 6290",
    "sg:postcode":"55419",
    "sg:province":"MN",
    "wof:name":"Northern Craftsman",
    "wof:placetype":"venue"
},
  "geometry": {"coordinates":[-93.272974,44.907153],"type":"Point"}
}