{
  "type": "Feature",
  "properties": {
    "addr:full":"8000 Flour Exchange Bldg 310 4th Ave S Minneapolis MN 55415",
    "addr:housenumber":"310",
    "addr:postcode":"8000;55415",
    "addr:street":"4Th Ave S",
    "iso:country":"US",
    "sg:address":"8000 Flour Exchange Bldg 310 4th Ave S",
    "sg:city":"Minneapolis",
    "sg:classifiers":[
        {
            "category":"Professional",
            "subcategory":"Lawyer & Legal Services",
            "type":"Services"
        }
    ],
    "sg:phone":"+1 612 333 1500",
    "sg:postcode":"55415",
    "sg:province":"MN",
    "sg:website":"www.Mpls-Criminal-Lawyer.com",
    "wof:name":"Gallagher Thomas C Atty",
    "wof:placetype":"venue"
},
  "geometry": {"coordinates":[-93.264049,44.978262],"type":"Point"}
}