{
  "type": "Feature",
  "properties": {
    "iso:country":"US",
    "sg:address":"31713 243rd St",
    "sg:city":"Pierz",
    "sg:classifiers":[
        {
            "category":"Transit Center",
            "subcategory":"Freight",
            "type":"Transportation"
        },
        {
            "category":"Freight",
            "type":"Transportation"
        }
    ],
    "sg:phone":"+1 320 277 3103",
    "sg:postcode":"56364",
    "sg:province":"MN",
    "sg:tags":[
        "local",
        "trucking-motor",
        "trucking"
    ],
    "wof:name":"Donek Trucking",
    "wof:placetype":"venue"
},
  "geometry": {"coordinates":[-94.006017,46.11362],"type":"Point"}
}