{
  "type": "Feature",
  "properties": {
    "addr:full":"30997 410th St Melrose MN 56352",
    "addr:housenumber":"30997",
    "addr:postcode":"56352",
    "addr:street":"410Th St",
    "iso:country":"US",
    "sg:address":"30997 410th St",
    "sg:city":"Melrose",
    "sg:classifiers":[
        {
            "category":"Fast Food",
            "type":"Food & Drink"
        },
        {
            "category":"Restaurant",
            "type":"Food & Drink"
        },
        {
            "category":"Ice Cream",
            "type":"Food & Drink"
        }
    ],
    "sg:phone":"+1 320 256 3399",
    "sg:postcode":"56352",
    "sg:province":"MN",
    "sg:tags":[
        "frozen",
        "take",
        "dessert"
    ],
    "sg:website":"http://www.dairyqueen.com",
    "wof:name":"Dairy Queen",
    "wof:placetype":"venue"
},
  "geometry": {"coordinates":[-94.750952,45.716441],"type":"Point"}
}