{
  "type": "Feature",
  "properties": {
    "iso:country":"US",
    "sg:address":"217 8th Ave SE",
    "sg:city":"Pipestone",
    "sg:classifiers":[
        {
            "category":"Banks & Credit Unions",
            "subcategory":"Bank",
            "type":"Services"
        }
    ],
    "sg:phone":"+1 507 825 4997",
    "sg:postcode":"56164",
    "sg:province":"MN",
    "sg:tags":[
        "commercial"
    ],
    "wof:name":"Home Federal Savings",
    "wof:placetype":"venue"
},
  "geometry": {"coordinates":[-96.307406,43.999282],"type":"Point"}
}