{
  "type": "Feature",
  "properties": {
    "iso:country":"US",
    "sg:address":"6613 Canterbury Ln",
    "sg:city":"Eden Prairie",
    "sg:classifiers":[
        {
            "category":"Building & Trades",
            "subcategory":"Locksmith",
            "type":"Services"
        }
    ],
    "sg:phone":"+1 952 562 0082",
    "sg:postcode":"55346",
    "sg:province":"MN",
    "sg:tags":[
        "key"
    ],
    "wof:name":"0 A A A 24 A Locksmith",
    "wof:placetype":"venue"
},
  "geometry": {"coordinates":[-93.459676,44.883437],"type":"Point"}
}