{
  "type": "Feature",
  "properties": {
    "addr:full":"207 E Dodge St Luverne MN 56156",
    "addr:housenumber":"207",
    "addr:postcode":"56156",
    "addr:street":"E Dodge St",
    "iso:country":"US",
    "sg:address":"207 E Dodge St",
    "sg:city":"Luverne",
    "sg:classifiers":[
        {
            "category":"Sports & Exercise",
            "subcategory":"Bowling",
            "type":"Entertainment"
        }
    ],
    "sg:phone":"+1 507 283 8336",
    "sg:postcode":"56156",
    "sg:province":"MN",
    "wof:name":"Bowling Association",
    "wof:placetype":"venue"
},
  "geometry": {"coordinates":[-96.207651,43.65996],"type":"Point"}
}