{
  "type": "Feature",
  "properties": {
    "iso:country":"US",
    "sg:address":"30327 Old Hwy 371",
    "sg:city":"Pequot Lakes",
    "sg:classifiers":[
        {
            "category":"Social Services",
            "subcategory":"Child Care",
            "type":"Services"
        }
    ],
    "sg:phone":"+1 218 568 8262",
    "sg:postcode":"56472",
    "sg:province":"MN",
    "sg:tags":[
        "day"
    ],
    "wof:name":"Kids Clubhouse Daycare",
    "wof:placetype":"venue"
},
  "geometry": {"coordinates":[-94.30939100000001,46.592907],"type":"Point"}
}