{
  "type": "Feature",
  "properties": {
    "addr:full":"16780 2nd St N Lakeland MN 55043",
    "addr:housenumber":"16780",
    "addr:postcode":"55043",
    "addr:street":"2Nd St N",
    "iso:country":"US",
    "sg:address":"16780 2nd St N",
    "sg:city":"Lakeland",
    "sg:classifiers":[
        {
            "category":"Building & Trades",
            "subcategory":"Construction",
            "type":"Services"
        }
    ],
    "sg:phone":"+1 651 436 3491",
    "sg:postcode":"55043",
    "sg:province":"MN",
    "sg:tags":[
        "work",
        "laying",
        "floor"
    ],
    "wof:name":"Konchal Floor Covering",
    "wof:placetype":"venue"
},
  "geometry": {"coordinates":[-92.765857,44.95169],"type":"Point"}
}