{
  "type": "Feature",
  "properties": {
    "addr:full":"660 Brockton Curve St Paul MN 55123",
    "addr:housenumber":"660",
    "addr:postcode":"55123",
    "addr:street":"Brockton Curve",
    "iso:country":"US",
    "sg:address":"660 Brockton Curve",
    "sg:city":"St Paul",
    "sg:classifiers":[
        {
            "category":"Professional",
            "subcategory":"Business Services",
            "type":"Services"
        }
    ],
    "sg:phone":"+1 651 687 0662",
    "sg:postcode":"55123",
    "sg:province":"MN",
    "sg:tags":[
        "embroidery"
    ],
    "wof:name":"Golden Needles",
    "wof:placetype":"venue"
},
  "geometry": {"coordinates":[-93.112866,44.814956],"type":"Point"}
}