{
  "type": "Feature",
  "properties": {
    "addr:full":"4151 State Hwy 7 Excelsior MN 55331",
    "addr:housenumber":"4151",
    "addr:postcode":"55331",
    "addr:street":"State Hwy 7",
    "iso:country":"US",
    "sg:address":"4151 State Hwy 7",
    "sg:city":"Excelsior",
    "sg:classifiers":[
        {
            "category":"Organizations",
            "subcategory":"Religious Organization",
            "type":"Services"
        }
    ],
    "sg:phone":"+1 952 474 9242",
    "sg:postcode":"55331",
    "sg:province":"MN",
    "sg:tags":[
        "church"
    ],
    "wof:name":"Holy Cross Lutheran Church",
    "wof:placetype":"venue"
},
  "geometry": {"coordinates":[-93.626062,44.883322],"type":"Point"}
}