{
  "type": "Feature",
  "properties": {
    "iso:country":"US",
    "sg:address":"2760 Juniper Ave",
    "sg:city":"Slayton",
    "sg:classifiers":[
        {
            "category":"Health Services",
            "subcategory":"Clinic",
            "type":"Services"
        }
    ],
    "sg:phone":"+1 507 836 6439",
    "sg:postcode":"56172",
    "sg:province":"MN",
    "sg:tags":[
        "home"
    ],
    "wof:name":"Our House Of Murray County",
    "wof:placetype":"venue"
},
  "geometry": {"coordinates":[-95.759314,43.985766],"type":"Point"}
}