{
  "type": "Feature",
  "properties": {
    "addr:full":"1018 Lambert Ave SE Bemidji MN 56601",
    "addr:housenumber":"1018",
    "addr:postcode":"56601",
    "addr:street":"Lambert Ave Se",
    "iso:country":"US",
    "sg:address":"1018 Lambert Ave SE",
    "sg:city":"Bemidji",
    "sg:classifiers":[
        {
            "category":"Professional",
            "type":"Services"
        }
    ],
    "sg:phone":"+1 218 755 4595",
    "sg:postcode":"56601",
    "sg:province":"MN",
    "sg:tags":[
        "establishment"
    ],
    "wof:name":"North Country STW Partnershp",
    "wof:placetype":"venue"
},
  "geometry": {"coordinates":[-94.856021,47.451751],"type":"Point"}
}