{
  "type": "Feature",
  "properties": {
    "iso:country":"US",
    "sg:address":"4874 Grover Ave NW",
    "sg:city":"Maple Lake",
    "sg:classifiers":[
        {
            "category":"Real Estate",
            "subcategory":"Real Estate Agent",
            "type":"Services"
        }
    ],
    "sg:phone":"+1 320 963 5481",
    "sg:postcode":"55358",
    "sg:province":"MN",
    "wof:name":"Steve Neslund",
    "wof:placetype":"venue"
},
  "geometry": {"coordinates":[-94.02326600000001,45.223647],"type":"Point"}
}