{
  "type": "Feature",
  "properties": {
    "iso:country":"US",
    "sg:address":"200 Ontario St SE",
    "sg:city":"Minneapolis",
    "sg:classifiers":[
        {
            "category":"Government",
            "subcategory":"Fire Station",
            "type":"Public Place"
        }
    ],
    "sg:phone":"+1 612 673 5369",
    "sg:postcode":"55414",
    "sg:province":"MN",
    "sg:tags":[
        "department"
    ],
    "wof:name":"Minneapolis Fire Dept",
    "wof:placetype":"venue"
},
  "geometry": {"coordinates":[-93.22567600000001,44.973547],"type":"Point"}
}