{
  "type": "Feature",
  "properties": {
    "addr:full":"14808 Oakhill Rd N Scandia MN 55073",
    "addr:housenumber":"14808",
    "addr:postcode":"55073",
    "addr:street":"Oakhill Rd N Scandia",
    "iso:country":"US",
    "sg:address":"14808 Oakhill Rd N",
    "sg:city":"Scandia",
    "sg:classifiers":[
        {
            "category":"Restaurant",
            "type":"Food & Drink"
        },
        {
            "category":"Bars & Pubs",
            "type":"Food & Drink"
        }
    ],
    "sg:phone":"+1 651 433 5230",
    "sg:postcode":"55073",
    "sg:province":"MN",
    "sg:tags":[
        "drinking",
        "eating"
    ],
    "wof:name":"Meister's Bar & Grill",
    "wof:placetype":"venue"
},
  "geometry": {"coordinates":[-92.804171,45.252627],"type":"Point"}
}