{
  "type": "Feature",
  "properties": {
    "iso:country":"US",
    "sg:address":"4430 165th Ave NE",
    "sg:city":"New London",
    "sg:classifiers":[
        {
            "category":"Professional",
            "type":"Services"
        }
    ],
    "sg:phone":"+1 320 354 2005",
    "sg:postcode":"56273",
    "sg:province":"MN",
    "wof:name":"Whitney Music",
    "wof:placetype":"venue"
},
  "geometry": {"coordinates":[-94.982409,45.282133],"type":"Point"}
}