{
  "type": "Feature",
  "properties": {
    "iso:country":"US",
    "sg:address":"6700 Industry Ave",
    "sg:city":"Ramsey",
    "sg:classifiers":[
        {
            "category":"Manufacturing",
            "subcategory":"Electronics",
            "type":"Manufacturing & Wholesale Goods"
        }
    ],
    "sg:phone":"+1 763 427 7735",
    "sg:postcode":"55303",
    "sg:province":"MN",
    "sg:tags":[
        "equipment",
        "electronic",
        "supply"
    ],
    "sg:website":"www.altronmfg.com",
    "wof:name":"Altron Inc",
    "wof:placetype":"venue"
},
  "geometry": {"coordinates":[-93.43722699999999,45.232413],"type":"Point"}
}