{
  "type": "Feature",
  "properties": {
    "addr:full":"5671 Miller Trunk Hwy Duluth MN 55811",
    "addr:housenumber":"5671",
    "addr:postcode":"55811",
    "addr:street":"Miller Trunk Hwy",
    "iso:country":"US",
    "sg:address":"5671 Miller Trunk Hwy",
    "sg:city":"Duluth",
    "sg:classifiers":[
        {
            "category":"Restaurant",
            "type":"Food & Drink"
        }
    ],
    "sg:phone":"+1 218 729 8207",
    "sg:postcode":"55811",
    "sg:province":"MN",
    "sg:website":"www.bettyspies.com",
    "wof:name":"Betty's Pies Pike Lake",
    "wof:placetype":"venue"
},
  "geometry": {"coordinates":[-92.279273,46.852804],"type":"Point"}
}