{
  "type": "Feature",
  "properties": {
    "addr:full":"7704 160th St W Lakeville MN 55068",
    "addr:housenumber":"7704",
    "addr:postcode":"55068",
    "addr:street":"160Th St W",
    "iso:country":"US",
    "sg:address":"7704 160th St W",
    "sg:city":"Lakeville",
    "sg:classifiers":[
        {
            "category":"Restaurant",
            "type":"Food & Drink"
        }
    ],
    "sg:phone":"+1 952 431 1227",
    "sg:postcode":"55068",
    "sg:province":"MN",
    "wof:name":"Pierre Cafe",
    "wof:placetype":"venue"
},
  "geometry": {"coordinates":[-93.22232700000001,44.717428],"type":"Point"}
}