{
  "type": "Feature",
  "properties": {
    "iso:country":"US",
    "sg:address":"2985 Centre Pointe Dr",
    "sg:city":"Saint Paul",
    "sg:classifiers":[
        {
            "category":"Travel",
            "subcategory":"Hotels & Motels",
            "type":"Entertainment"
        }
    ],
    "sg:phone":"+1 651 636 1364",
    "sg:postcode":"55113",
    "sg:province":"MN",
    "sg:website":"www.residenceinn.com",
    "wof:name":"Residence Inn by Marriott",
    "wof:placetype":"venue"
},
  "geometry": {"coordinates":[-93.18890399999999,45.030602],"type":"Point"}
}