{
  "type": "Feature",
  "properties": {
    "addr:full":"2383 Linwood Ave E Saint Paul MN 55119",
    "addr:housenumber":"2383",
    "addr:postcode":"55119",
    "addr:street":"Linwood Ave E",
    "iso:country":"US",
    "sg:address":"2383 Linwood Ave E",
    "sg:city":"Saint Paul",
    "sg:classifiers":[
        {
            "category":"Shopping",
            "subcategory":"Used Merchandise",
            "type":"Retail Goods"
        }
    ],
    "sg:phone":"+1 651 739 0308",
    "sg:postcode":"55119",
    "sg:province":"MN",
    "wof:name":"Better Than New Antiques",
    "wof:placetype":"venue"
},
  "geometry": {"coordinates":[-92.9961,44.919568],"type":"Point"}
}