{
  "type": "Feature",
  "properties": {
    "iso:country":"US",
    "sg:address":"7733 Comstock Ln N",
    "sg:city":"Osseo",
    "sg:classifiers":[
        {
            "category":"Shopping",
            "subcategory":"Gifts & Souvenirs",
            "type":"Retail Goods"
        }
    ],
    "sg:phone":"+1 763 416 7718",
    "sg:postcode":"55311",
    "sg:province":"MN",
    "wof:name":"Heartstrings",
    "wof:placetype":"venue"
},
  "geometry": {"coordinates":[-93.491232,45.095192],"type":"Point"}
}