{
  "type": "Feature",
  "properties": {
    "addr:full":"6659 Moorland Dr Eden Prairie MN 55346",
    "addr:housenumber":"6659",
    "addr:postcode":"55346",
    "addr:street":"Moorland Dr",
    "iso:country":"US",
    "sg:address":"6659 Moorland Dr",
    "sg:city":"Eden Prairie",
    "sg:classifiers":[
        {
            "category":"Professional",
            "subcategory":"Management & Consulting",
            "type":"Services"
        }
    ],
    "sg:phone":"+1 952 906 1852",
    "sg:postcode":"55346",
    "sg:province":"MN",
    "sg:tags":[
        "consultant"
    ],
    "wof:name":"Collective Consciousness",
    "wof:placetype":"venue"
},
  "geometry": {"coordinates":[-93.48057900000001,44.883053],"type":"Point"}
}