{
  "type": "Feature",
  "properties": {
    "iso:country":"US",
    "sg:address":"5241 Saint John Dr",
    "sg:city":"Orr",
    "sg:classifiers":[
        {
            "category":"Place Of Worship",
            "subcategory":"Church",
            "type":"Public Place"
        },
        {
            "category":"Place Of Worship",
            "type":"Public Place"
        }
    ],
    "sg:phone":"+1 218 757 3188",
    "sg:postcode":"55771",
    "sg:province":"MN",
    "sg:tags":[
        "churches-baptist-general",
        "churches-baptist"
    ],
    "wof:name":"Lake Nett Baptist Church",
    "wof:placetype":"venue"
},
  "geometry": {"coordinates":[-93.096542,48.110203],"type":"Point"}
}