{
  "type": "Feature",
  "properties": {
    "addr:full":"5115 State Hwy 47 Dalbo MN 55017",
    "addr:housenumber":"5115",
    "addr:postcode":"55017",
    "addr:street":"State Hwy 47",
    "iso:country":"US",
    "sg:address":"5115 State Hwy 47",
    "sg:city":"Dalbo",
    "sg:classifiers":[
        {
            "category":"Manufacturing",
            "subcategory":"Food",
            "type":"Manufacturing & Wholesale Goods"
        }
    ],
    "sg:phone":"+1 763 689 0270",
    "sg:postcode":"55017",
    "sg:province":"MN",
    "sg:tags":[
        "cheese",
        "mfg"
    ],
    "sg:website":"www.rochestercheese.com",
    "wof:name":"Rochester Cheese",
    "wof:placetype":"venue"
},
  "geometry": {"coordinates":[-93.39737100000001,45.65886],"type":"Point"}
}