{
  "type": "Feature",
  "properties": {
    "addr:full":"12800 Arbor Lakes Pkwy N Maple Grove MN 55369",
    "addr:housenumber":"12800",
    "addr:postcode":"55369",
    "addr:street":"Arbor Lakes Pkwy N",
    "iso:country":"US",
    "sg:address":"12800 Arbor Lakes Pkwy N",
    "sg:city":"Maple Grove",
    "sg:classifiers":[
        {
            "category":"Government",
            "subcategory":"Office",
            "type":"Public Place"
        }
    ],
    "sg:phone":"+1 763 494 6015",
    "sg:postcode":"55369",
    "sg:province":"MN",
    "sg:tags":[
        "village"
    ],
    "wof:name":"Maple Grove Human Resources",
    "wof:placetype":"venue"
},
  "geometry": {"coordinates":[-93.442345,45.098387],"type":"Point"}
}