{
  "type": "Feature",
  "properties": {
    "iso:country":"US",
    "sg:address":"7538 3rd Ave S",
    "sg:city":"Minneapolis",
    "sg:classifiers":[
        {
            "category":"Professional",
            "subcategory":"Management & Consulting",
            "type":"Services"
        }
    ],
    "sg:phone":"+1 612 869 9494",
    "sg:postcode":"55423",
    "sg:province":"MN",
    "sg:tags":[
        "equipment-wholesale",
        "manufacturer",
        "business",
        "furniture"
    ],
    "wof:name":"F C Flanagan Consulting",
    "wof:placetype":"venue"
},
  "geometry": {"coordinates":[-93.273173,44.866604],"type":"Point"}
}