{
  "type": "Feature",
  "properties": {
    "addr:full":"2120 20th St Slayton MN 56172",
    "addr:housenumber":"2120",
    "addr:postcode":"56172",
    "addr:street":"20Th St",
    "iso:country":"US",
    "sg:address":"2120 20th St",
    "sg:city":"Slayton",
    "sg:classifiers":[
        {
            "category":"Insurance",
            "subcategory":"Insurance Agent",
            "type":"Services"
        }
    ],
    "sg:phone":"+1 507 836 6166",
    "sg:postcode":"56172",
    "sg:province":"MN",
    "wof:name":"State Farm Insurance",
    "wof:placetype":"venue"
},
  "geometry": {"coordinates":[-95.76209299999999,43.993025],"type":"Point"}
}