{
  "type": "Feature",
  "properties": {
    "addr:full":"712 Lincoln Loop Sauk Centre MN 56378",
    "addr:housenumber":"712",
    "addr:postcode":"56378",
    "addr:street":"Lincoln Loop",
    "iso:country":"US",
    "sg:address":"712 Lincoln Loop",
    "sg:city":"Sauk Centre",
    "sg:classifiers":[
        {
            "category":"Social Services",
            "subcategory":"Job Training",
            "type":"Services"
        }
    ],
    "sg:phone":"+1 320 352 6759",
    "sg:postcode":"56378",
    "sg:province":"MN",
    "sg:tags":[
        "rehabilitation"
    ],
    "wof:name":"Wacosa",
    "wof:placetype":"venue"
},
  "geometry": {"coordinates":[-94.961738,45.731716],"type":"Point"}
}