{
  "type": "Feature",
  "properties": {
    "addr:full":"18637 Smith Rd Brainerd MN 56401",
    "addr:housenumber":"18637",
    "addr:postcode":"56401",
    "addr:street":"Smith Rd",
    "iso:country":"US",
    "sg:address":"18637 Smith Rd",
    "sg:city":"Brainerd",
    "sg:classifiers":[
        {
            "category":"Retail",
            "subcategory":"Repair Shop",
            "type":"Services"
        }
    ],
    "sg:phone":"+1 218 828 8763",
    "sg:postcode":"56401",
    "sg:province":"MN",
    "wof:name":"Bob Severson Mobile Locksmith",
    "wof:placetype":"venue"
},
  "geometry": {"coordinates":[-94.19186999999999,46.422879],"type":"Point"}
}