{
  "type": "Feature",
  "properties": {
    "addr:full":"700 Nicollet Mall Minneapolis MN 55402",
    "addr:housenumber":"700",
    "addr:postcode":"55402",
    "addr:street":"Nicollet Mall",
    "iso:country":"US",
    "sg:address":"700 Nicollet Mall",
    "sg:city":"Minneapolis",
    "sg:classifiers":[
        {
            "category":"Utilities",
            "subcategory":"Mobile Phone",
            "type":"Services"
        },
        {
            "category":"Coffee & Tea",
            "type":"Food & Drink"
        }
    ],
    "sg:phone":"+1 612 375 2077",
    "sg:postcode":"55402",
    "sg:province":"MN",
    "sg:tags":[
        "shop",
        "wi-fi",
        "espresso",
        "hotspot",
        "restaurant"
    ],
    "sg:website":"http://www.starbuckscoffee.com",
    "wof:name":"Starbucks Coffee",
    "wof:placetype":"venue"
},
  "geometry": {"coordinates":[-93.27224,44.97691],"type":"Point"}
}