{
  "type": "Feature",
  "properties": {
    "addr:full":"4304 Nicollet Ave Minneapolis MN 55409",
    "addr:housenumber":"4304",
    "addr:postcode":"55409",
    "addr:street":"Nicollet Ave",
    "iso:country":"US",
    "sg:address":"4304 Nicollet Ave",
    "sg:city":"Minneapolis",
    "sg:classifiers":[
        {
            "category":"Shopping",
            "subcategory":"Music",
            "type":"Retail Goods"
        }
    ],
    "sg:phone":"+1 612 822 0613",
    "sg:postcode":"55409",
    "sg:province":"MN",
    "sg:tags":[
        "record",
        "vinyl",
        "dvd's"
    ],
    "sg:website":"www.landspeedrecords.com",
    "wof:name":"Roadrunner Record Exchange",
    "wof:placetype":"venue"
},
  "geometry": {"coordinates":[-93.278099,44.924599],"type":"Point"}
}