{
  "type": "Feature",
  "properties": {
    "iso:country":"US",
    "sg:address":"9851 Humboldt Ave S",
    "sg:city":"Minneapolis",
    "sg:classifiers":[
        {
            "category":"Shopping",
            "subcategory":"Catalog Store",
            "type":"Retail Goods"
        }
    ],
    "sg:phone":"+1 952 884 6850",
    "sg:postcode":"55431",
    "sg:province":"MN",
    "sg:tags":[
        "product",
        "sales",
        "promotional"
    ],
    "wof:name":"Brands Promotional Products",
    "wof:placetype":"venue"
},
  "geometry": {"coordinates":[-93.298649,44.823214],"type":"Point"}
}