{
  "type": "Feature",
  "properties": {
    "addr:full":"3008 Highland Blvd Mound MN 55364",
    "addr:housenumber":"3008",
    "addr:postcode":"55364",
    "addr:street":"Highland Blvd",
    "iso:country":"US",
    "sg:address":"3008 Highland Blvd",
    "sg:city":"Mound",
    "sg:classifiers":[
        {
            "category":"Autos & Motor Vehicles",
            "subcategory":"Boat Sales",
            "type":"Retail Goods"
        }
    ],
    "sg:phone":"+1 952 472 1172",
    "sg:postcode":"55364",
    "sg:province":"MN",
    "sg:tags":[
        "mfg"
    ],
    "wof:name":"Fineline Lakeshore Service",
    "wof:placetype":"venue"
},
  "geometry": {"coordinates":[-93.67126500000001,44.923744],"type":"Point"}
}