{
  "type": "Feature",
  "properties": {
    "iso:country":"US",
    "sg:address":"159 18th St SW",
    "sg:city":"Owatonna",
    "sg:classifiers":[
        {
            "category":"Health Services",
            "subcategory":"Doctor",
            "type":"Services"
        }
    ],
    "sg:phone":"+1 507 455 1000",
    "sg:postcode":"55060",
    "sg:province":"MN",
    "sg:tags":[
        "dentist"
    ],
    "wof:name":"Main Street Dental Clinic",
    "wof:placetype":"venue"
},
  "geometry": {"coordinates":[-93.228308,44.066139],"type":"Point"}
}