{
  "type": "Feature",
  "properties": {
    "iso:country":"US",
    "sg:address":"5001 W 80th St",
    "sg:city":"Minneapolis",
    "sg:classifiers":[
        {
            "category":"Professional",
            "type":"Services"
        }
    ],
    "sg:phone":"+1 952 835 8500",
    "sg:postcode":"55437",
    "sg:province":"MN",
    "sg:tags":[
        "establishment"
    ],
    "wof:name":"Elgethun David S King Kurt J",
    "wof:placetype":"venue"
},
  "geometry": {"coordinates":[-93.349749,44.856458],"type":"Point"}
}