{
  "type": "Feature",
  "properties": {
    "addr:full":"53 Woodlynn Ave Saint Paul MN 55113",
    "addr:housenumber":"53",
    "addr:postcode":"55113",
    "addr:street":"Woodlynn Ave",
    "iso:country":"US",
    "sg:address":"53 Woodlynn Ave",
    "sg:city":"Saint Paul",
    "sg:classifiers":[
        {
            "category":"Wholesale",
            "subcategory":"Machinery & Supplies",
            "type":"Manufacturing & Wholesale Goods"
        }
    ],
    "sg:phone":"+1 651 482 1234",
    "sg:postcode":"55113",
    "sg:province":"MN",
    "sg:tags":[
        "tool",
        "pneumatic",
        "fastener"
    ],
    "wof:name":"American Fastening Systems",
    "wof:placetype":"venue"
},
  "geometry": {"coordinates":[-93.104827,45.034924],"type":"Point"}
}