{
  "type": "Feature",
  "properties": {
    "addr:full":"8541 Interlachen Rd Nisswa MN 56468",
    "addr:housenumber":"8541",
    "addr:postcode":"56468",
    "addr:street":"Interlachen Rd",
    "iso:country":"US",
    "sg:address":"8541 Interlachen Rd",
    "sg:city":"Nisswa",
    "sg:classifiers":[
        {
            "category":"Building & Trades",
            "subcategory":"Construction",
            "type":"Services"
        }
    ],
    "sg:phone":"+1 218 963 0104",
    "sg:postcode":"56468",
    "sg:province":"MN",
    "sg:tags":[
        "hanging",
        "contractor"
    ],
    "wof:name":"Northland Striping Co",
    "wof:placetype":"venue"
},
  "geometry": {"coordinates":[-94.35604600000001,46.495333],"type":"Point"}
}