{
  "type": "Feature",
  "properties": {
    "addr:full":"17170 160th Ave S Barnesville MN 56514",
    "addr:housenumber":"17170",
    "addr:postcode":"56514",
    "addr:street":"160Th Ave S Barnesville",
    "iso:country":"US",
    "sg:address":"17170 160th Ave S",
    "sg:city":"Barnesville",
    "sg:phone":"+1 218 493 4689",
    "sg:postcode":"56514",
    "sg:province":"MN",
    "sg:tags":[
        "farm",
        "corn"
    ],
    "wof:name":"Greg Grommesh",
    "wof:placetype":"venue"
},
  "geometry": {"coordinates":[-96.43813,46.659796],"type":"Point"}
}