{
  "type": "Feature",
  "properties": {
    "iso:country":"US",
    "sg:address":"225 S 6th St Fl 46",
    "sg:city":"Minneapolis",
    "sg:classifiers":[
        {
            "category":"Banks & Credit Unions",
            "subcategory":"Bank",
            "type":"Services"
        },
        {
            "category":"Banks & Credit Unions",
            "subcategory":"Financial Services",
            "type":"Services"
        }
    ],
    "sg:phone":"+1 612 339 0500",
    "sg:postcode":"55402",
    "sg:province":"MN",
    "sg:tags":[
        "management",
        "broker",
        "bond",
        "investment",
        "stock"
    ],
    "sg:website":"http://www.agio.com",
    "wof:name":"Goldsmith, Agio, Helms & Lynner",
    "wof:placetype":"venue"
},
  "geometry": {"coordinates":[-93.26838600000001,44.976555],"type":"Point"}
}