{
  "type": "Feature",
  "properties": {
    "addr:full":"1068 Lake St S Forest Lake MN 55025",
    "addr:housenumber":"1068",
    "addr:postcode":"55025",
    "addr:street":"Lake St S",
    "iso:country":"US",
    "sg:address":"1068 Lake St S",
    "sg:city":"Forest Lake",
    "sg:classifiers":[
        {
            "category":"Health Services",
            "subcategory":"Doctor",
            "type":"Services"
        }
    ],
    "sg:phone":"+1 651 982 9212",
    "sg:postcode":"55025",
    "sg:province":"MN",
    "sg:tags":[
        "clinic"
    ],
    "wof:name":"Da Vita Inc",
    "wof:placetype":"venue"
},
  "geometry": {"coordinates":[-92.983628,45.269728],"type":"Point"}
}