{
  "type": "Feature",
  "properties": {
    "addr:full":"15535 45th Ave N Minneapolis MN 55446",
    "addr:housenumber":"15535",
    "addr:postcode":"55446",
    "addr:street":"45Th Ave N",
    "iso:country":"US",
    "sg:address":"15535 45th Ave N",
    "sg:city":"Minneapolis",
    "sg:classifiers":[
        {
            "category":"Professional",
            "subcategory":"Engineering",
            "type":"Services"
        }
    ],
    "sg:phone":"+1 763 550 1075",
    "sg:postcode":"55446",
    "sg:province":"MN",
    "wof:name":"Diversity Engineering",
    "wof:placetype":"venue"
},
  "geometry": {"coordinates":[-93.476789,45.036915],"type":"Point"}
}