{
  "type": "Feature",
  "properties": {
    "addr:full":"316 Sims Rd NW Cedar MN 55011",
    "addr:housenumber":"316",
    "addr:postcode":"55011",
    "addr:street":"Sims Rd Nw Cedar",
    "iso:country":"US",
    "sg:address":"316 Sims Rd NW",
    "sg:city":"Cedar",
    "sg:classifiers":[
        {
            "category":"Shopping",
            "subcategory":"Bicycles & Sporting Goods",
            "type":"Retail Goods"
        }
    ],
    "sg:phone":"+1 763 434 5736",
    "sg:postcode":"55011",
    "sg:province":"MN",
    "sg:tags":[
        "gun"
    ],
    "wof:name":"Thunder Arms",
    "wof:placetype":"venue"
},
  "geometry": {"coordinates":[-93.274638,45.356018],"type":"Point"}
}