{
  "type": "Feature",
  "properties": {
    "addr:full":"402 Mantorville Ave S Kasson MN 55944",
    "addr:housenumber":"402",
    "addr:postcode":"55944",
    "addr:street":"Mantorville Ave S Kasson",
    "iso:country":"US",
    "sg:address":"402 Mantorville Ave S",
    "sg:city":"Kasson",
    "sg:classifiers":[
        {
            "category":"Professional",
            "subcategory":"Lawyer & Legal Services",
            "type":"Services"
        }
    ],
    "sg:phone":"+1 507 634 3202",
    "sg:postcode":"55944",
    "sg:province":"MN",
    "wof:name":"Hanson Law Firm",
    "wof:placetype":"venue"
},
  "geometry": {"coordinates":[-92.748131,44.024985],"type":"Point"}
}