{
  "type": "Feature",
  "properties": {
    "addr:full":"7169 Commerce Cir W Minneapolis MN 55432",
    "addr:housenumber":"7169",
    "addr:postcode":"55432",
    "addr:street":"Commerce Cir W",
    "iso:country":"US",
    "sg:address":"7169 Commerce Cir W",
    "sg:city":"Minneapolis",
    "sg:classifiers":[
        {
            "category":"Manufacturing",
            "subcategory":"Tools & Machinery",
            "type":"Manufacturing & Wholesale Goods"
        }
    ],
    "sg:phone":"+1 763 780 5792",
    "sg:postcode":"55432",
    "sg:province":"MN",
    "sg:tags":[
        "machine",
        "shop"
    ],
    "wof:name":"Murphy's Machine Shop Inc",
    "wof:placetype":"venue"
},
  "geometry": {"coordinates":[-93.267737,45.09879],"type":"Point"}
}