{
  "type": "Feature",
  "properties": {
    "iso:country":"US",
    "sg:address":"110 W Wyoming St",
    "sg:city":"Redwood Falls",
    "sg:classifiers":[
        {
            "category":"Freight",
            "type":"Transportation"
        }
    ],
    "sg:phone":"+1 507 637 3342",
    "sg:postcode":"56283",
    "sg:province":"MN",
    "wof:name":"M & L Transport",
    "wof:placetype":"venue"
},
  "geometry": {"coordinates":[-95.12093900000001,44.535976],"type":"Point"}
}