{
  "type": "Feature",
  "properties": {
    "iso:country":"US",
    "sg:address":"713 S Mill St",
    "sg:city":"Redwood Falls",
    "sg:classifiers":[
        {
            "category":"Food & Beverages",
            "subcategory":"Groceries & Convenience Stores",
            "type":"Retail Goods"
        }
    ],
    "sg:phone":"+1 507 637 8479",
    "sg:postcode":"56283",
    "sg:province":"MN",
    "wof:name":"Handi Mart",
    "wof:placetype":"venue"
},
  "geometry": {"coordinates":[-95.119362,44.535932],"type":"Point"}
}