{
  "type": "Feature",
  "properties": {
    "iso:country":"US",
    "sg:address":"710 Medtronic Pkwy",
    "sg:city":"Minneapolis",
    "sg:classifiers":[
        {
            "category":"Wholesale",
            "subcategory":"Medical Equipment & Supplies",
            "type":"Manufacturing & Wholesale Goods"
        },
        {
            "category":"Health Services",
            "subcategory":"Hospital",
            "type":"Services"
        }
    ],
    "sg:phone":"+1 763 574 4000",
    "sg:postcode":"55432",
    "sg:province":"MN",
    "sg:website":"http://www.painroom.com",
    "wof:name":"Medtronic World Headquarters",
    "wof:placetype":"venue"
},
  "geometry": {"coordinates":[-93.24863000000001,45.071304],"type":"Point"}
}