{
  "type": "Feature",
  "properties": {
    "iso:country":"US",
    "sg:address":"322 Ramsey St",
    "sg:city":"Hastings",
    "sg:classifiers":[
        {
            "category":"Professional",
            "type":"Services"
        }
    ],
    "sg:phone":"+1 651 438 8748",
    "sg:postcode":"55033",
    "sg:province":"MN",
    "wof:name":"Chad A Beissel",
    "wof:placetype":"venue"
},
  "geometry": {"coordinates":[-92.85002299999999,44.742518],"type":"Point"}
}