{
  "type": "Feature",
  "properties": {
    "addr:full":"140 7th St S Winsted MN 55313",
    "addr:housenumber":"140",
    "addr:postcode":"55313",
    "addr:street":"7Th St S",
    "iso:country":"US",
    "sg:address":"140 7th St S",
    "sg:city":"Winsted",
    "sg:classifiers":[
        {
            "category":"Building & Trades",
            "subcategory":"Construction",
            "type":"Services"
        }
    ],
    "sg:phone":"+1 320 485 2270",
    "sg:postcode":"55313",
    "sg:province":"MN",
    "sg:tags":[
        "house"
    ],
    "wof:name":"Arvola Homes",
    "wof:placetype":"venue"
},
  "geometry": {"coordinates":[-93.87527,45.1635],"type":"Point"}
}