{
  "type": "Feature",
  "properties": {
    "addr:full":"1951 N Riverfront Dr Mankato MN 56001",
    "addr:housenumber":"1951",
    "addr:postcode":"56001",
    "addr:street":"N Riverfront Dr",
    "iso:country":"US",
    "sg:address":"1951 N Riverfront Dr",
    "sg:city":"Mankato",
    "sg:classifiers":[
        {
            "category":"Wholesale",
            "subcategory":"Farm Supplies",
            "type":"Manufacturing & Wholesale Goods"
        }
    ],
    "sg:phone":"+1 507 387 1171",
    "sg:postcode":"56001",
    "sg:province":"MN",
    "wof:name":"C & S Supply Co Inc",
    "wof:placetype":"venue"
},
  "geometry": {"coordinates":[-93.985263,44.185274],"type":"Point"}
}