{
  "type": "Feature",
  "properties": {
    "addr:full":"1801 W Country Hwy 42 Burnsville MN 55337",
    "addr:housenumber":"1801",
    "addr:postcode":"55337",
    "addr:street":"W Country Hwy 42",
    "iso:country":"US",
    "sg:address":"1801 W Country Hwy 42",
    "sg:city":"Burnsville",
    "sg:classifiers":[
        {
            "category":"Sports & Exercise",
            "subcategory":"Gym",
            "type":"Entertainment"
        }
    ],
    "sg:phone":"+1 952 656 7801",
    "sg:postcode":"55337",
    "sg:province":"MN",
    "wof:name":"La Fitness Burnsville",
    "wof:placetype":"venue"
},
  "geometry": {"coordinates":[-93.301169,44.746279],"type":"Point"}
}