{
  "type": "Feature",
  "properties": {
    "addr:full":"33565 County 6 Blvd Goodhue MN 55027",
    "addr:housenumber":"33565",
    "addr:postcode":"55027",
    "addr:street":"County 6 Blvd",
    "iso:country":"US",
    "sg:address":"33565 County 6 Blvd",
    "sg:city":"Goodhue",
    "sg:classifiers":[
        {
            "category":"Professional",
            "type":"Services"
        }
    ],
    "sg:phone":"+1 651 923 4916",
    "sg:postcode":"55027",
    "sg:province":"MN",
    "wof:name":"Welcome Services For You",
    "wof:placetype":"venue"
},
  "geometry": {"coordinates":[-92.64677,44.46312],"type":"Point"}
}