{
  "type": "Feature",
  "properties": {
    "addr:full":"9800 Shelard Pkwy Minneapolis MN 55441",
    "addr:postcode":"9800;55441",
    "addr:street":"Shelard Pkwy",
    "iso:country":"US",
    "sg:address":"9800 Shelard Pkwy",
    "sg:city":"Minneapolis",
    "sg:classifiers":[
        {
            "category":"Banks & Credit Unions",
            "subcategory":"Investment Brokerage",
            "type":"Services"
        }
    ],
    "sg:phone":"+1 763 542 1445",
    "sg:postcode":"55441",
    "sg:province":"MN",
    "sg:tags":[
        "mortgage"
    ],
    "wof:name":"Countrywide",
    "wof:placetype":"venue"
},
  "geometry": {"coordinates":[-93.40576900000001,44.978628],"type":"Point"}
}