{
  "type": "Feature",
  "properties": {
    "addr:full":"4416 35th Ave S Minneapolis MN 55406",
    "addr:housenumber":"4416",
    "addr:postcode":"55406",
    "addr:street":"35Th Ave S",
    "iso:country":"US",
    "sg:address":"4416 35th Ave S",
    "sg:city":"Minneapolis",
    "sg:classifiers":[
        {
            "category":"Shopping",
            "subcategory":"Music",
            "type":"Retail Goods"
        }
    ],
    "sg:phone":"+1 612 724 4515",
    "sg:postcode":"55406",
    "sg:province":"MN",
    "sg:tags":[
        "store"
    ],
    "wof:name":"Lakestate Records",
    "wof:placetype":"venue"
},
  "geometry": {"coordinates":[-93.22168600000001,44.92289],"type":"Point"}
}