{
  "type": "Feature",
  "properties": {
    "addr:full":"15601 Grove Cir N Maple Grove MN 55369",
    "addr:housenumber":"15601",
    "addr:postcode":"55369",
    "addr:street":"Grove Cir N",
    "iso:country":"US",
    "sg:address":"15601 Grove Cir N",
    "sg:city":"Maple Grove",
    "sg:classifiers":[
        {
            "category":"Banks & Credit Unions",
            "subcategory":"Bank",
            "type":"Services"
        }
    ],
    "sg:phone":"+1 763 255 2900",
    "sg:postcode":"55369",
    "sg:province":"MN",
    "wof:name":"North Memorial Federal Credit Union",
    "wof:placetype":"venue"
},
  "geometry": {"coordinates":[-93.47821500000001,45.134853],"type":"Point"}
}