{
  "type": "Feature",
  "properties": {
    "iso:country":"US",
    "sg:address":"444 8th St S",
    "sg:city":"Minneapolis",
    "sg:classifiers":[
        {
            "category":"Insurance",
            "subcategory":"Hazard Insurance",
            "type":"Services"
        }
    ],
    "sg:phone":"+1 612 333 3030",
    "sg:postcode":"55404",
    "sg:province":"MN",
    "sg:tags":[
        "bond"
    ],
    "sg:website":"www.absolutebailbonds.net",
    "wof:name":"Absolute Bail Bonds",
    "wof:placetype":"venue"
},
  "geometry": {"coordinates":[-93.266605,44.973357],"type":"Point"}
}