{
  "type": "Feature",
  "properties": {
    "iso:country":"US",
    "sg:address":"423 3rd Ave SE",
    "sg:city":"Perham",
    "sg:classifiers":[
        {
            "category":"Shopping",
            "type":"Retail Goods"
        }
    ],
    "sg:phone":"+1 218 346 2787",
    "sg:postcode":"56573",
    "sg:province":"MN",
    "sg:tags":[
        "art"
    ],
    "wof:name":"Artful Obsessions",
    "wof:placetype":"venue"
},
  "geometry": {"coordinates":[-95.573531,46.590289],"type":"Point"}
}