{
  "type": "Feature",
  "properties": {
    "addr:full":"4138 York Ave S Minneapolis MN 55410",
    "addr:housenumber":"4138",
    "addr:postcode":"55410",
    "addr:street":"York Ave S",
    "iso:country":"US",
    "sg:address":"4138 York Ave S",
    "sg:city":"Minneapolis",
    "sg:classifiers":[
        {
            "category":"Communications",
            "subcategory":"Film & Video Production",
            "type":"Services"
        }
    ],
    "sg:phone":"+1 612 926 0387",
    "sg:postcode":"55410",
    "sg:province":"MN",
    "sg:tags":[
        "motion"
    ],
    "wof:name":"Persevero Media Productions",
    "wof:placetype":"venue"
},
  "geometry": {"coordinates":[-93.320195,44.927587],"type":"Point"}
}