{
  "type": "Feature",
  "properties": {
    "addr:full":"908 Rum River Dr Isanti MN 55040",
    "addr:housenumber":"908",
    "addr:postcode":"55040",
    "addr:street":"Rum River Dr Isanti",
    "iso:country":"US",
    "sg:address":"908 Rum River Dr",
    "sg:city":"Isanti",
    "sg:classifiers":[
        {
            "category":"Government",
            "subcategory":"Office",
            "type":"Public Place"
        }
    ],
    "sg:phone":"+1 763 444 8283",
    "sg:postcode":"55040",
    "sg:province":"MN",
    "sg:tags":[
        "based",
        "community",
        "health",
        "rural",
        "nonprofit",
        "care"
    ],
    "wof:name":"Northern Minnesota Network",
    "wof:placetype":"venue"
},
  "geometry": {"coordinates":[-93.26480100000001,45.48131],"type":"Point"}
}