{
  "type": "Feature",
  "properties": {
    "addr:full":"641 Lake St E Wayzata MN 55391",
    "addr:housenumber":"641",
    "addr:postcode":"55391",
    "addr:street":"Lake St E",
    "iso:country":"US",
    "sg:address":"641 Lake St E",
    "sg:city":"Wayzata",
    "sg:classifiers":[
        {
            "category":"Real Estate",
            "subcategory":"Real Estate Agent",
            "type":"Services"
        }
    ],
    "sg:phone":"+1 952 475 4930",
    "sg:postcode":"55391",
    "sg:province":"MN",
    "wof:name":"Parks Real Estate",
    "wof:placetype":"venue"
},
  "geometry": {"coordinates":[-93.51227299999999,44.969412],"type":"Point"}
}