{
  "type": "Feature",
  "properties": {
    "addr:full":"1911 Pleasant Ave Minneapolis MN 55403",
    "addr:housenumber":"1911",
    "addr:postcode":"55403",
    "addr:street":"Pleasant Ave",
    "iso:country":"US",
    "sg:address":"1911 Pleasant Ave",
    "sg:city":"Minneapolis",
    "sg:classifiers":[
        {
            "category":"Manufacturing",
            "subcategory":"Printing",
            "type":"Manufacturing & Wholesale Goods"
        }
    ],
    "sg:phone":"+1 612 874 9811",
    "sg:postcode":"55403",
    "sg:province":"MN",
    "sg:tags":[
        "specialty",
        "periodical"
    ],
    "wof:name":"Create Inc",
    "wof:placetype":"venue"
},
  "geometry": {"coordinates":[-93.283334,44.962791],"type":"Point"}
}