{
  "type": "Feature",
  "properties": {
    "iso:country":"US",
    "sg:address":"13350 1st Ave S",
    "sg:city":"Zimmerman",
    "sg:classifiers":[
        {
            "category":"Banks & Credit Unions",
            "subcategory":"Bank",
            "type":"Services"
        }
    ],
    "sg:phone":"+1 763 856 5787",
    "sg:postcode":"55398",
    "sg:province":"MN",
    "sg:tags":[
        "mortgage"
    ],
    "wof:name":"C & J Mortgage Investments",
    "wof:placetype":"venue"
},
  "geometry": {"coordinates":[-93.607719,45.442325],"type":"Point"}
}