{
  "type": "Feature",
  "properties": {
    "addr:full":"420 Pheasant Ridge Rd Wayzata MN 55391",
    "addr:housenumber":"420",
    "addr:postcode":"55391",
    "addr:street":"Pheasant Ridge Rd",
    "iso:country":"US",
    "sg:address":"420 Pheasant Ridge Rd",
    "sg:city":"Wayzata",
    "sg:classifiers":[
        {
            "category":"Travel",
            "subcategory":"Travel Agent",
            "type":"Entertainment"
        }
    ],
    "sg:phone":"+1 763 476 8202",
    "sg:postcode":"55391",
    "sg:province":"MN",
    "sg:tags":[
        "agency"
    ],
    "wof:name":"Travel Source of Wayzata Inc",
    "wof:placetype":"venue"
},
  "geometry": {"coordinates":[-93.535595,45.003094],"type":"Point"}
}