{
  "type": "Feature",
  "properties": {
    "iso:country":"US",
    "sg:address":"43300 190th Ln",
    "sg:city":"Arlington",
    "sg:classifiers":[
        {
            "category":"Health Services",
            "subcategory":"Clinic",
            "type":"Services"
        }
    ],
    "sg:phone":"+1 320 864 4820",
    "sg:postcode":"55307",
    "sg:province":"MN",
    "wof:name":"United Healthcare Svc Inc",
    "wof:placetype":"venue"
},
  "geometry": {"coordinates":[-94.13731,44.675059],"type":"Point"}
}