{
  "type": "Feature",
  "properties": {
    "iso:country":"US",
    "sg:address":"8971 W Shipley Rd",
    "sg:city":"Alborn",
    "sg:classifiers":[
        {
            "category":"Building & Trades",
            "subcategory":"Electrical",
            "type":"Services"
        }
    ],
    "sg:phone":"+1 218 345 6901",
    "sg:postcode":"55702",
    "sg:province":"MN",
    "sg:tags":[
        "electrical",
        "contractor"
    ],
    "wof:name":"Lighting Maintenance Service",
    "wof:placetype":"venue"
},
  "geometry": {"coordinates":[-92.621773,46.998332],"type":"Point"}
}