{
  "type": "Feature",
  "properties": {
    "iso:country":"US",
    "sg:address":"26357 130th St",
    "sg:city":"Fulda",
    "sg:classifiers":[
        {
            "category":"Farming",
            "subcategory":"Livestock Farm",
            "type":"Manufacturing & Wholesale Goods"
        }
    ],
    "sg:phone":"+1 507 425 3282",
    "sg:postcode":"56131",
    "sg:province":"MN",
    "sg:tags":[
        "feedlot",
        "hog",
        "corn",
        "or",
        "soybean"
    ],
    "wof:name":"Paulzine Brothers",
    "wof:placetype":"venue"
},
  "geometry": {"coordinates":[-95.72682,43.805032],"type":"Point"}
}