{
  "type": "Feature",
  "properties": {
    "addr:full":"10526 Karston Ave NE Albertville MN 55301",
    "addr:housenumber":"10526",
    "addr:postcode":"55301",
    "addr:street":"Karston Ave Ne",
    "iso:country":"US",
    "sg:address":"10526 Karston Ave NE",
    "sg:city":"Albertville",
    "sg:classifiers":[
        {
            "category":"Manufacturing",
            "subcategory":"Printing",
            "type":"Manufacturing & Wholesale Goods"
        }
    ],
    "sg:phone":"+1 763 497 5436",
    "sg:postcode":"55301",
    "sg:province":"MN",
    "sg:tags":[
        "publishing"
    ],
    "wof:name":"Kartes Publishing",
    "wof:placetype":"venue"
},
  "geometry": {"coordinates":[-93.679306,45.240581],"type":"Point"}
}