{
  "type": "Feature",
  "properties": {
    "addr:full":"44468 320th St NW Argyle MN 56713",
    "addr:housenumber":"44468",
    "addr:postcode":"56713",
    "addr:street":"320Th St Nw",
    "iso:country":"US",
    "sg:address":"44468 320th St NW",
    "sg:city":"Argyle",
    "sg:phone":"+1 218 437 8215",
    "sg:postcode":"56713",
    "sg:province":"MN",
    "sg:tags":[
        "farm",
        "beet",
        "sugar"
    ],
    "wof:name":"Robert Chwialkowski",
    "wof:placetype":"venue"
},
  "geometry": {"coordinates":[-97.008894,48.340291],"type":"Point"}
}