{
  "type": "Feature",
  "properties": {
    "iso:country":"US",
    "sg:address":"320 Little Ranches Rd",
    "sg:city":"Mora",
    "sg:classifiers":[
        {
            "category":"Retail",
            "subcategory":"Repair Shop",
            "type":"Services"
        }
    ],
    "sg:phone":"+1 320 679 3267",
    "sg:postcode":"55051",
    "sg:province":"MN",
    "sg:tags":[
        "welding"
    ],
    "wof:name":"Westside Welding",
    "wof:placetype":"venue"
},
  "geometry": {"coordinates":[-93.298901,45.860893],"type":"Point"}
}