{
  "type": "Feature",
  "properties": {
    "addr:full":"14622 268th Ave Zimmerman MN 55398",
    "addr:housenumber":"14622",
    "addr:postcode":"55398",
    "addr:street":"268Th Ave",
    "iso:country":"US",
    "sg:address":"14622 268th Ave",
    "sg:city":"Zimmerman",
    "sg:classifiers":[
        {
            "category":"Professional",
            "type":"Services"
        },
        {
            "category":"Manufacturing",
            "subcategory":"Tools & Machinery",
            "type":"Manufacturing & Wholesale Goods"
        }
    ],
    "sg:phone":"+1 763 856 3800",
    "sg:postcode":"55398",
    "sg:province":"MN",
    "sg:tags":[
        "tank",
        "septic",
        "supply",
        "industry",
        "mfg",
        "con"
    ],
    "wof:name":"Septic Protectors",
    "wof:placetype":"venue"
},
  "geometry": {"coordinates":[-93.64033999999999,45.456554],"type":"Point"}
}