{
  "type": "Feature",
  "properties": {
    "addr:full":"2660 S Broadway Rochester MN 55904",
    "addr:housenumber":"2660",
    "addr:postcode":"55904",
    "addr:street":"S Broadway",
    "iso:country":"US",
    "sg:address":"2660 S Broadway",
    "sg:city":"Rochester",
    "sg:classifiers":[
        {
            "category":"Fast Food",
            "type":"Food & Drink"
        },
        {
            "category":"Restaurant",
            "type":"Food & Drink"
        },
        {
            "category":"Food & Beverages",
            "subcategory":"Groceries & Convenience Stores",
            "type":"Retail Goods"
        }
    ],
    "sg:phone":"+1 507 282 3582",
    "sg:postcode":"55904",
    "sg:province":"MN",
    "sg:tags":[
        "shop",
        "american",
        "sandwich",
        "take"
    ],
    "sg:website":"http://www.subway.com",
    "wof:name":"Subway",
    "wof:placetype":"venue"
},
  "geometry": {"coordinates":[-92.46216,43.983423],"type":"Point"}
}