{
  "type": "Feature",
  "properties": {
    "addr:full":"120 6th St S Minneapolis MN 55402",
    "addr:housenumber":"120",
    "addr:postcode":"55402",
    "addr:street":"6Th St S",
    "iso:country":"US",
    "sg:address":"120 6th St S",
    "sg:city":"Minneapolis",
    "sg:classifiers":[
        {
            "category":"Professional",
            "subcategory":"Lawyer & Legal Services",
            "type":"Services"
        }
    ],
    "sg:phone":"+1 612 573 3665",
    "sg:postcode":"55402",
    "sg:province":"MN",
    "sg:tags":[
        "attorney"
    ],
    "wof:name":"Brian N Larson",
    "wof:placetype":"venue"
},
  "geometry": {"coordinates":[-93.268857,44.976866],"type":"Point"}
}