{
  "type": "Feature",
  "properties": {
    "addr:full":"113 2nd St SW Young America MN 55397",
    "addr:housenumber":"113",
    "addr:postcode":"55397",
    "addr:street":"2Nd St Sw",
    "iso:country":"US",
    "sg:address":"113 2nd St SW",
    "sg:city":"Young America",
    "sg:classifiers":[
        {
            "category":"Social Services",
            "subcategory":"Child Care",
            "type":"Services"
        }
    ],
    "sg:phone":"+1 952 467 2123",
    "sg:postcode":"55397",
    "sg:province":"MN",
    "sg:tags":[
        "daycare",
        "provider"
    ],
    "wof:name":"Shawn Benkowski",
    "wof:placetype":"venue"
},
  "geometry": {"coordinates":[-93.91807900000001,44.780888],"type":"Point"}
}