{
  "type": "Feature",
  "properties": {
    "addr:full":"6212 222nd Ave Echo MN 56237",
    "addr:housenumber":"6212",
    "addr:postcode":"56237",
    "addr:street":"222Nd Ave",
    "iso:country":"US",
    "sg:address":"6212 222nd Ave",
    "sg:city":"Echo",
    "sg:classifiers":[
        {
            "category":"Building & Trades",
            "subcategory":"Construction",
            "type":"Services"
        }
    ],
    "sg:phone":"+1 507 925 4478",
    "sg:postcode":"56237",
    "sg:province":"MN",
    "sg:tags":[
        "house"
    ],
    "wof:name":"Rigges Construction",
    "wof:placetype":"venue"
},
  "geometry": {"coordinates":[-95.40111,44.713535],"type":"Point"}
}