{
  "type": "Feature",
  "properties": {
    "iso:country":"US",
    "sg:address":"185 Beaumount Ct",
    "sg:city":"Burnsville",
    "sg:classifiers":[
        {
            "category":"Autos & Motor Vehicles",
            "subcategory":"Automobile Sales",
            "type":"Retail Goods"
        },
        {
            "category":"Taxi",
            "type":"Transportation"
        },
        {
            "category":"Airline",
            "type":"Transportation"
        }
    ],
    "sg:phone":"+1 651 429 9876",
    "sg:postcode":"55337",
    "sg:province":"MN",
    "sg:tags":[
        "shuttle",
        "airport",
        "limo"
    ],
    "wof:name":"Aspen Travel Limousine Service",
    "wof:placetype":"venue"
},
  "geometry": {"coordinates":[-93.268799,44.771702],"type":"Point"}
}