{
  "type": "Feature",
  "properties": {
    "iso:country":"US",
    "sg:address":"3095 Autumn Woods Dr",
    "sg:city":"Chaska",
    "sg:classifiers":[
        {
            "category":"Building & Trades",
            "subcategory":"Construction",
            "type":"Services"
        }
    ],
    "sg:phone":"+1 952 448 5485",
    "sg:postcode":"55318",
    "sg:province":"MN",
    "sg:tags":[
        "home",
        "general",
        "commercial",
        "family",
        "contractor"
    ],
    "wof:name":"Doug Schoen Construction Inc",
    "wof:placetype":"venue"
},
  "geometry": {"coordinates":[-93.576142,44.834787],"type":"Point"}
}