{
  "type": "Feature",
  "properties": {
    "addr:full":"944 Birch Ln Brainerd MN 56401",
    "addr:housenumber":"944",
    "addr:postcode":"56401",
    "addr:street":"Birch Ln",
    "iso:country":"US",
    "sg:address":"944 Birch Ln",
    "sg:city":"Brainerd",
    "sg:classifiers":[
        {
            "category":"Professional",
            "subcategory":"Management & Consulting",
            "type":"Services"
        }
    ],
    "sg:phone":"+1 218 828 8134",
    "sg:postcode":"56401",
    "sg:province":"MN",
    "sg:tags":[
        "training",
        "safety"
    ],
    "wof:name":"T G S",
    "wof:placetype":"venue"
},
  "geometry": {"coordinates":[-94.336664,46.422117],"type":"Point"}
}