{
  "type": "Feature",
  "properties": {
    "iso:country":"US",
    "sg:address":"3646 370th Ave",
    "sg:city":"Elmore",
    "sg:classifiers":[
        {
            "category":"Farming",
            "subcategory":"Farm",
            "type":"Manufacturing & Wholesale Goods"
        }
    ],
    "sg:phone":"+1 507 943 3677",
    "sg:postcode":"56027",
    "sg:province":"MN",
    "sg:tags":[
        "crop",
        "general"
    ],
    "wof:name":"Tracey Zierke",
    "wof:placetype":"venue"
},
  "geometry": {"coordinates":[-94.127933,43.543399],"type":"Point"}
}