{
  "type": "Feature",
  "properties": {
    "addr:full":"976 Belanger Ave NW Buffalo MN 55313",
    "addr:housenumber":"976",
    "addr:postcode":"55313",
    "addr:street":"Belanger Ave Nw",
    "iso:country":"US",
    "sg:address":"976 Belanger Ave NW",
    "sg:city":"Buffalo",
    "sg:classifiers":[
        {
            "category":"Professional",
            "subcategory":"Business Services",
            "type":"Services"
        }
    ],
    "sg:phone":"+1 763 684 1054",
    "sg:postcode":"55313",
    "sg:province":"MN",
    "wof:name":"Fresh Configuration Inc",
    "wof:placetype":"venue"
},
  "geometry": {"coordinates":[-93.916883,45.162896],"type":"Point"}
}