{
  "type": "Feature",
  "properties": {
    "iso:country":"US",
    "sg:address":"845 Village Center Dr",
    "sg:city":"Saint Paul",
    "sg:classifiers":[
        {
            "category":"Restaurant",
            "type":"Food & Drink"
        }
    ],
    "sg:phone":"+1 651 292 4355",
    "sg:postcode":"55127",
    "sg:province":"MN",
    "sg:tags":[
        "eating"
    ],
    "wof:name":"Art Deco Restaurant",
    "wof:placetype":"venue"
},
  "geometry": {"coordinates":[-93.117108,45.081392],"type":"Point"}
}