{
  "type": "Feature",
  "properties": {
    "addr:full":"815 N 9th St St Peter MN 56082",
    "addr:housenumber":"815",
    "addr:postcode":"56082",
    "addr:street":"N 9Th St",
    "iso:country":"US",
    "sg:address":"815 N 9th St",
    "sg:city":"St Peter",
    "sg:classifiers":[
        {
            "category":"Education",
            "subcategory":"School",
            "type":"Public Place"
        }
    ],
    "sg:phone":"+1 507 934 3260",
    "sg:postcode":"56082",
    "sg:province":"MN",
    "wof:name":"St Peter Pub Schools N Inter",
    "wof:placetype":"venue"
},
  "geometry": {"coordinates":[-93.965164,44.336837],"type":"Point"}
}