{
  "type": "Feature",
  "properties": {
    "addr:full":"1900 Hennepin Ave Minneapolis MN 55403",
    "addr:housenumber":"1900",
    "addr:postcode":"55403",
    "addr:street":"Hennepin Ave",
    "iso:country":"US",
    "sg:address":"1900 Hennepin Ave",
    "sg:city":"Minneapolis",
    "sg:classifiers":[
        {
            "category":"Professional",
            "subcategory":"Lawyer & Legal Services",
            "type":"Services"
        }
    ],
    "sg:phone":"+1 612 872 0222",
    "sg:postcode":"55403",
    "sg:province":"MN",
    "wof:name":"Lowrey Hill Law Offices",
    "wof:placetype":"venue"
},
  "geometry": {"coordinates":[-93.29029800000001,44.964401],"type":"Point"}
}