{
  "type": "Feature",
  "properties": {
    "addr:full":"10515 49th Ave N Minneapolis MN 55442",
    "addr:housenumber":"10515",
    "addr:postcode":"55442",
    "addr:street":"49Th Ave N",
    "iso:country":"US",
    "sg:address":"10515 49th Ave N",
    "sg:city":"Minneapolis",
    "sg:classifiers":[
        {
            "category":"Professional",
            "type":"Services"
        }
    ],
    "sg:phone":"+1 763 559 7828",
    "sg:postcode":"55442",
    "sg:province":"MN",
    "wof:name":"Dale Novotny",
    "wof:placetype":"venue"
},
  "geometry": {"coordinates":[-93.414207,45.042908],"type":"Point"}
}