{
  "type": "Feature",
  "properties": {
    "iso:country":"US",
    "sg:address":"3325 75th St NE",
    "sg:city":"Rochester",
    "sg:classifiers":[
        {
            "category":"Building & Trades",
            "subcategory":"Construction",
            "type":"Services"
        }
    ],
    "sg:phone":"+1 507 280 7780",
    "sg:postcode":"55906",
    "sg:province":"MN",
    "sg:tags":[
        "nonresidential"
    ],
    "wof:name":"Sawyer Construction Services",
    "wof:placetype":"venue"
},
  "geometry": {"coordinates":[-92.411897,44.10715],"type":"Point"}
}