{
  "type": "Feature",
  "properties": {
    "iso:country":"US",
    "sg:address":"305 NW Jackson Ave",
    "sg:city":"Mcintosh",
    "sg:classifiers":[
        {
            "category":"Organizations",
            "subcategory":"Religious Organization",
            "type":"Services"
        }
    ],
    "sg:phone":"+1 218 563 2235",
    "sg:postcode":"56556",
    "sg:province":"MN",
    "sg:tags":[
        "church"
    ],
    "wof:name":"Immanuel Lutheran Church",
    "wof:placetype":"venue"
},
  "geometry": {"coordinates":[-95.888999,47.639879],"type":"Point"}
}