{
  "type": "Feature",
  "properties": {
    "addr:full":"13090 Westley Dr Orr MN 55771",
    "addr:housenumber":"13090",
    "addr:postcode":"55771",
    "addr:street":"Westley Dr",
    "iso:country":"US",
    "sg:address":"13090 Westley Dr",
    "sg:city":"Orr",
    "sg:classifiers":[
        {
            "category":"Social Services",
            "subcategory":"Child Care",
            "type":"Services"
        }
    ],
    "sg:phone":"+1 218 757 3265",
    "sg:postcode":"55771",
    "sg:province":"MN",
    "wof:name":"Bois Forte Head Start-Day Care",
    "wof:placetype":"venue"
},
  "geometry": {"coordinates":[-93.09405,48.111064],"type":"Point"}
}