{
  "type": "Feature",
  "properties": {
    "addr:full":"3324 Winpark Dr Minneapolis MN 55427",
    "addr:housenumber":"3324",
    "addr:postcode":"55427",
    "addr:street":"Winpark Dr",
    "iso:country":"US",
    "sg:address":"3324 Winpark Dr",
    "sg:city":"Minneapolis",
    "sg:classifiers":[
        {
            "category":"Travel",
            "subcategory":"Hotels & Motels",
            "type":"Entertainment"
        }
    ],
    "sg:phone":"+1 763 544 2721",
    "sg:postcode":"55427",
    "sg:province":"MN",
    "sg:tags":[
        "lodging"
    ],
    "sg:website":"http://www.phoenixsolutionsco.com",
    "wof:name":"Plasma Energy Corporation",
    "wof:placetype":"venue"
},
  "geometry": {"coordinates":[-93.37846999999999,45.017181],"type":"Point"}
}