{
  "type": "Feature",
  "properties": {
    "iso:country":"US",
    "sg:address":"413 Main St W",
    "sg:city":"Menahga",
    "sg:classifiers":[
        {
            "category":"Real Estate",
            "subcategory":"Real Estate Agent",
            "type":"Services"
        }
    ],
    "sg:phone":"+1 218 564 4503",
    "sg:postcode":"56464",
    "sg:province":"MN",
    "wof:name":"Evergreen Real Estate Co",
    "wof:placetype":"venue"
},
  "geometry": {"coordinates":[-95.10623099999999,46.752664],"type":"Point"}
}