{
  "type": "Feature",
  "properties": {
    "iso:country":"US",
    "sg:address":"3101 State Hwy 95",
    "sg:city":"Cambridge",
    "sg:classifiers":[
        {
            "category":"Recreation",
            "type":"Entertainment"
        },
        {
            "category":"Travel",
            "subcategory":"Campground",
            "type":"Entertainment"
        }
    ],
    "sg:phone":"+1 763 689 2555",
    "sg:postcode":"55008",
    "sg:province":"MN",
    "sg:tags":[
        "organization",
        "membership"
    ],
    "wof:name":"Isanti County Fairgrounds",
    "wof:placetype":"venue"
},
  "geometry": {"coordinates":[-93.193197,45.572768],"type":"Point"}
}