{
  "type": "Feature",
  "properties": {
    "iso:country":"US",
    "sg:address":"14449 Highway 13 S",
    "sg:city":"Prior Lake",
    "sg:classifiers":[
        {
            "category":"Retail",
            "subcategory":"Veterinary Services",
            "type":"Services"
        },
        {
            "category":"Retail",
            "subcategory":"Pet Boarding",
            "type":"Services"
        }
    ],
    "sg:phone":"+1 952 447 4171",
    "sg:postcode":"55372",
    "sg:province":"MN",
    "sg:tags":[
        "veterinarian",
        "boarding/pet",
        "sitting"
    ],
    "wof:name":"Avmc-Scott Lake Pet Clinic",
    "wof:placetype":"venue"
},
  "geometry": {"coordinates":[-93.38009599999999,44.742199],"type":"Point"}
}