{
  "type": "Feature",
  "properties": {
    "addr:full":"2545 Chicago Ave S Minneapolis MN 55404",
    "addr:housenumber":"2545",
    "addr:postcode":"55404",
    "addr:street":"Chicago Ave S",
    "iso:country":"US",
    "sg:address":"2545 Chicago Ave S",
    "sg:city":"Minneapolis",
    "sg:classifiers":[
        {
            "category":"Shopping",
            "type":"Retail Goods"
        }
    ],
    "sg:phone":"+1 612 872 4427",
    "sg:postcode":"55404",
    "sg:province":"MN",
    "sg:tags":[
        "hearing",
        "equipment",
        "supply",
        "impaired"
    ],
    "wof:name":"Northland Hearing Svc",
    "wof:placetype":"venue"
},
  "geometry": {"coordinates":[-93.262485,44.956329],"type":"Point"}
}