{
  "type": "Feature",
  "properties": {
    "iso:country":"US",
    "sg:address":"5344 Maywood Rd",
    "sg:city":"Mound",
    "sg:classifiers":[
        {
            "category":"Building & Trades",
            "subcategory":"Construction",
            "type":"Services"
        }
    ],
    "sg:phone":"+1 952 472 0635",
    "sg:postcode":"55364",
    "sg:province":"MN",
    "sg:tags":[
        "executive"
    ],
    "wof:name":"Mound Public Works Dept",
    "wof:placetype":"venue"
},
  "geometry": {"coordinates":[-93.658698,44.934651],"type":"Point"}
}