{
  "type": "Feature",
  "properties": {
    "addr:full":"2312 Louisiana Ave S Minneapolis MN 55426",
    "addr:housenumber":"2312",
    "addr:postcode":"55426",
    "addr:street":"Louisiana Ave S",
    "iso:country":"US",
    "sg:address":"2312 Louisiana Ave S",
    "sg:city":"Minneapolis",
    "sg:classifiers":[
        {
            "category":"Professional",
            "subcategory":"Accounting & Tax Preparation",
            "type":"Services"
        }
    ],
    "sg:phone":"+1 952 541 4858",
    "sg:postcode":"55426",
    "sg:province":"MN",
    "sg:tags":[
        "return",
        "preparation-business"
    ],
    "wof:name":"Tax Shop, The",
    "wof:placetype":"venue"
},
  "geometry": {"coordinates":[-93.371004,44.959228],"type":"Point"}
}