{
  "type": "Feature",
  "properties": {
    "iso:country":"US",
    "sg:address":"810 Hwy 10",
    "sg:city":"Dilworth",
    "sg:classifiers":[
        {
            "category":"Insurance",
            "subcategory":"Insurance Agent",
            "type":"Services"
        }
    ],
    "sg:phone":"+1 218 299 2617",
    "sg:postcode":"56529",
    "sg:province":"MN",
    "wof:name":"North Star Resource Group",
    "wof:placetype":"venue"
},
  "geometry": {"coordinates":[-96.68361299999999,46.876265],"type":"Point"}
}