{
  "type": "Feature",
  "properties": {
    "iso:country":"US",
    "sg:address":"1965 Roselawn Ave W",
    "sg:city":"Saint Paul",
    "sg:classifiers":[
        {
            "category":"Retail",
            "subcategory":"Portrait Studio",
            "type":"Services"
        }
    ],
    "sg:phone":"+1 651 646 5673",
    "sg:postcode":"55113",
    "sg:province":"MN",
    "sg:tags":[
        "photo"
    ],
    "wof:name":"Venkman Photography",
    "wof:placetype":"venue"
},
  "geometry": {"coordinates":[-93.182783,44.999018],"type":"Point"}
}