{
  "type": "Feature",
  "properties": {
    "iso:country":"US",
    "sg:address":"318 W Main St",
    "sg:city":"Adams",
    "sg:classifiers":[
        {
            "category":"Manufacturing",
            "subcategory":"Printing",
            "type":"Manufacturing & Wholesale Goods"
        }
    ],
    "sg:phone":"+1 507 582 3542",
    "sg:postcode":"55909",
    "sg:province":"MN",
    "sg:tags":[
        "newspaper"
    ],
    "wof:name":"Monitor Review",
    "wof:placetype":"venue"
},
  "geometry": {"coordinates":[-92.719049,43.565482],"type":"Point"}
}