{
  "type": "Feature",
  "properties": {
    "addr:full":"16291 84th Pl N Maple Grove MN 55311",
    "addr:housenumber":"16291",
    "addr:postcode":"55311",
    "addr:street":"84Th Pl N",
    "iso:country":"US",
    "sg:address":"16291 84th Pl N",
    "sg:city":"Maple Grove",
    "sg:classifiers":[
        {
            "category":"Wholesale",
            "subcategory":"Medical Equipment & Supplies",
            "type":"Manufacturing & Wholesale Goods"
        }
    ],
    "sg:phone":"+1 763 494 0921",
    "sg:postcode":"55311",
    "sg:province":"MN",
    "sg:tags":[
        "physician",
        "surgeon"
    ],
    "wof:name":"Murphy Medical Supply Inc",
    "wof:placetype":"venue"
},
  "geometry": {"coordinates":[-93.48713499999999,45.108432],"type":"Point"}
}