{
  "type": "Feature",
  "properties": {
    "iso:country":"US",
    "sg:address":"949 Wescott Sq",
    "sg:city":"Eagan",
    "sg:classifiers":[
        {
            "category":"Social Services",
            "type":"Services"
        }
    ],
    "sg:phone":"+1 651 256 3200",
    "sg:postcode":"55123",
    "sg:province":"MN",
    "sg:tags":[
        "organization",
        "welfare"
    ],
    "wof:name":"Somali Success",
    "wof:placetype":"venue"
},
  "geometry": {"coordinates":[-93.132802,44.832728],"type":"Point"}
}