{
  "type": "Feature",
  "properties": {
    "addr:full":"42745 200th Ave Zumbrota MN 55992",
    "addr:housenumber":"42745",
    "addr:postcode":"55992",
    "addr:street":"200Th Ave",
    "iso:country":"US",
    "sg:address":"42745 200th Ave",
    "sg:city":"Zumbrota",
    "sg:classifiers":[
        {
            "category":"Professional",
            "type":"Services"
        }
    ],
    "sg:phone":"+1 507 732 7222",
    "sg:postcode":"55992",
    "sg:province":"MN",
    "wof:name":"Rick Johnson",
    "wof:placetype":"venue"
},
  "geometry": {"coordinates":[-92.631697,44.328855],"type":"Point"}
}