{
  "type": "Feature",
  "properties": {
    "iso:country":"US",
    "sg:address":"4452 Centerville Rd",
    "sg:city":"Saint Paul",
    "sg:classifiers":[
        {
            "category":"Autos & Motor Vehicles",
            "subcategory":"Fuel & Gas Station",
            "type":"Retail Goods"
        }
    ],
    "sg:phone":"+1 651 429 4259",
    "sg:postcode":"55127",
    "sg:province":"MN",
    "sg:tags":[
        "station",
        "gasoline"
    ],
    "wof:name":"North Oaks Standard Inc",
    "wof:placetype":"venue"
},
  "geometry": {"coordinates":[-93.056065,45.072919],"type":"Point"}
}