{
  "type": "Feature",
  "properties": {
    "addr:full":"6112 Sheridan Ave S # 100 Minneapolis MN 55410",
    "addr:housenumber":"6112",
    "addr:postcode":"55410",
    "addr:street":"Sheridan Ave S # 100",
    "iso:country":"US",
    "sg:address":"6112 Sheridan Ave S # 100",
    "sg:city":"Minneapolis",
    "sg:classifiers":[
        {
            "category":"Shopping",
            "subcategory":"Clothing, Apparel, & Fashions",
            "type":"Retail Goods"
        }
    ],
    "sg:phone":"+1 612 926 8020",
    "sg:postcode":"55410",
    "sg:province":"MN",
    "sg:tags":[
        "handbag"
    ],
    "wof:name":"Ete Handbags",
    "wof:placetype":"venue"
},
  "geometry": {"coordinates":[-93.312448,44.892339],"type":"Point"}
}