{
  "type": "Feature",
  "properties": {
    "iso:country":"US",
    "sg:address":"333 East River Rd",
    "sg:city":"Minneapolis",
    "sg:classifiers":[
        {
            "category":"Museum",
            "type":"Entertainment"
        }
    ],
    "sg:phone":"+1 612 625 9494",
    "sg:postcode":"55455",
    "sg:province":"MN",
    "sg:website":"www.weisman.umn.edu",
    "wof:name":"Weisman Art Museum",
    "wof:placetype":"venue"
},
  "geometry": {"coordinates":[-93.237799,44.972236],"type":"Point"}
}