{
  "type": "Feature",
  "properties": {
    "iso:country":"US",
    "sg:address":"6451 Kurtz Ln",
    "sg:city":"Eden Prairie",
    "sg:classifiers":[
        {
            "category":"Professional",
            "subcategory":"Computer Services",
            "type":"Services"
        }
    ],
    "sg:phone":"+1 612 281 4509",
    "sg:postcode":"55346",
    "sg:province":"MN",
    "sg:tags":[
        "related"
    ],
    "wof:name":"Faridianslipcom",
    "wof:placetype":"venue"
},
  "geometry": {"coordinates":[-93.47259099999999,44.885984],"type":"Point"}
}