{
  "type": "Feature",
  "properties": {
    "addr:full":"117 7th St S St James MN 56081",
    "addr:housenumber":"117",
    "addr:postcode":"56081",
    "addr:street":"7Th St S St James",
    "iso:country":"US",
    "sg:address":"117 7th St S",
    "sg:city":"St James",
    "sg:classifiers":[
        {
            "category":"Real Estate",
            "subcategory":"Real Estate Services",
            "type":"Services"
        }
    ],
    "sg:phone":"+1 507 375 7115",
    "sg:postcode":"56081",
    "sg:province":"MN",
    "wof:name":"Hesse Abstract Co",
    "wof:placetype":"venue"
},
  "geometry": {"coordinates":[-94.626881,43.982333],"type":"Point"}
}