{
  "type": "Feature",
  "properties": {
    "iso:country":"US",
    "sg:address":"7924 Victoria Dr Ste 206",
    "sg:city":"Victoria",
    "sg:classifiers":[
        {
            "category":"Personal",
            "subcategory":"Massage",
            "type":"Services"
        },
        {
            "category":"Personal",
            "subcategory":"Beauty Salon",
            "type":"Services"
        }
    ],
    "sg:phone":"+1 952 679 4805",
    "sg:postcode":"55386",
    "sg:province":"MN",
    "sg:tags":[
        "hair"
    ],
    "wof:name":"The Parlour Salon & Spa",
    "wof:placetype":"venue"
},
  "geometry": {"coordinates":[-93.66238800000001,44.859709],"type":"Point"}
}