{
  "type": "Feature",
  "properties": {
    "addr:full":"32400 Oasis Rd Center City MN 55012",
    "addr:housenumber":"32400",
    "addr:postcode":"55012",
    "addr:street":"Oasis Rd",
    "iso:country":"US",
    "sg:address":"32400 Oasis Rd",
    "sg:city":"Center City",
    "sg:classifiers":[
        {
            "category":"Food & Beverages",
            "subcategory":"Groceries & Convenience Stores",
            "type":"Retail Goods"
        }
    ],
    "sg:phone":"+1 651 257 0664",
    "sg:postcode":"55012",
    "sg:province":"MN",
    "wof:name":"Global Food Partners LLC",
    "wof:placetype":"venue"
},
  "geometry": {"coordinates":[-92.823165,45.417132],"type":"Point"}
}