{
  "type": "Feature",
  "properties": {
    "iso:country":"US",
    "sg:address":"17221 State Hwy 30",
    "sg:city":"New Richland",
    "sg:classifiers":[
        {
            "category":"Building & Trades",
            "subcategory":"Construction",
            "type":"Services"
        }
    ],
    "sg:phone":"+1 507 465 9942",
    "sg:postcode":"56072",
    "sg:province":"MN",
    "sg:tags":[
        "general",
        "contractor"
    ],
    "wof:name":"K B Construction",
    "wof:placetype":"venue"
},
  "geometry": {"coordinates":[-93.41218000000001,43.87986],"type":"Point"}
}