{
  "type": "Feature",
  "properties": {
    "addr:full":"14275 Co Rd 33 Norwood MN 55368",
    "addr:housenumber":"14275;33",
    "addr:postcode":"55368",
    "addr:street":"Co Rd",
    "iso:country":"US",
    "sg:address":"14275 Co Rd 33",
    "sg:city":"Norwood",
    "sg:classifiers":[
        {
            "category":"Personal",
            "subcategory":"Beauty Salon",
            "type":"Services"
        }
    ],
    "sg:phone":"+1 952 467 3395",
    "sg:postcode":"55368",
    "sg:province":"MN",
    "sg:tags":[
        "shop"
    ],
    "wof:name":"Betsy's Beauty Haven",
    "wof:placetype":"venue"
},
  "geometry": {"coordinates":[-93.91423500000001,44.744308],"type":"Point"}
}