{
  "type": "Feature",
  "properties": {
    "iso:country":"US",
    "sg:address":"6101 University Ave NE",
    "sg:city":"Fridley",
    "sg:classifiers":[
        {
            "category":"Food & Beverages",
            "subcategory":"Groceries & Convenience Stores",
            "type":"Retail Goods"
        }
    ],
    "sg:phone":"+1 763 571 8411",
    "sg:postcode":"55432",
    "sg:province":"MN",
    "wof:name":"Total Petroleum Inc",
    "wof:placetype":"venue"
},
  "geometry": {"coordinates":[-93.26343,45.084353],"type":"Point"}
}