{
  "type": "Feature",
  "properties": {
    "iso:country":"US",
    "sg:address":"47 W Lyton Pl",
    "sg:city":"Saint Paul",
    "sg:classifiers":[
        {
            "category":"Building & Trades",
            "subcategory":"Cleaning & Sanitation",
            "type":"Services"
        }
    ],
    "sg:phone":"+1 651 488 5399",
    "sg:postcode":"55117",
    "sg:province":"MN",
    "sg:tags":[
        "maintenance"
    ],
    "wof:name":"Williamson Arthur Jantr Svc",
    "wof:placetype":"venue"
},
  "geometry": {"coordinates":[-93.10197700000001,44.965671],"type":"Point"}
}