{
  "type": "Feature",
  "properties": {
    "addr:full":"4305 Central Ave NE Minneapolis MN 55421",
    "addr:housenumber":"4305",
    "addr:postcode":"55421",
    "addr:street":"Central Ave Ne",
    "iso:country":"US",
    "sg:address":"4305 Central Ave NE",
    "sg:city":"Minneapolis",
    "sg:classifiers":[
        {
            "category":"Home & Garden",
            "subcategory":"Furniture",
            "type":"Retail Goods"
        }
    ],
    "sg:phone":"+1 763 781 9234",
    "sg:postcode":"55421",
    "sg:province":"MN",
    "wof:name":"Columbia Heights",
    "wof:placetype":"venue"
},
  "geometry": {"coordinates":[-93.24739700000001,45.047023],"type":"Point"}
}