{
  "type": "Feature",
  "properties": {
    "iso:country":"US",
    "sg:address":"4422 2nd Ave E",
    "sg:city":"Hibbing",
    "sg:classifiers":[
        {
            "category":"Utilities",
            "subcategory":"Refuse",
            "type":"Services"
        }
    ],
    "sg:phone":"+1 218 262 3308",
    "sg:postcode":"55746",
    "sg:province":"MN",
    "sg:tags":[
        "garbage",
        "collection"
    ],
    "wof:name":"Waste Management",
    "wof:placetype":"venue"
},
  "geometry": {"coordinates":[-92.939339,47.396348],"type":"Point"}
}