{
  "type": "Feature",
  "properties": {
    "addr:full":"1869 485th St W Stanchfield MN 55080",
    "addr:housenumber":"1869",
    "addr:postcode":"55080",
    "addr:street":"485Th St W Stanchfield",
    "iso:country":"US",
    "sg:address":"1869 485th St W",
    "sg:city":"Stanchfield",
    "sg:classifiers":[
        {
            "category":"Building & Trades",
            "subcategory":"Construction",
            "type":"Services"
        }
    ],
    "sg:phone":"+1 763 689 3177",
    "sg:postcode":"55080",
    "sg:province":"MN",
    "sg:tags":[
        "handyman"
    ],
    "wof:name":"East Central Handyman Svc",
    "wof:placetype":"venue"
},
  "geometry": {"coordinates":[-93.13492599999999,45.651394],"type":"Point"}
}