{
  "type": "Feature",
  "properties": {
    "iso:country":"US",
    "sg:address":"600 Highway 169 S Ste 1450",
    "sg:city":"Minneapolis",
    "sg:classifiers":[
        {
            "category":"Real Estate",
            "subcategory":"Real Estate Services",
            "type":"Services"
        },
        {
            "category":"Professional",
            "subcategory":"Research",
            "type":"Services"
        }
    ],
    "sg:phone":"+1 952 476 9430",
    "sg:postcode":"55426",
    "sg:province":"MN",
    "sg:tags":[
        "abstracter",
        "title"
    ],
    "wof:name":"Rels Title",
    "wof:placetype":"venue"
},
  "geometry": {"coordinates":[-93.402886,44.973972],"type":"Point"}
}