{
  "type": "Feature",
  "properties": {
    "iso:country":"US",
    "sg:address":"19292 172nd St",
    "sg:city":"Big Lake",
    "sg:classifiers":[
        {
            "category":"Manufacturing",
            "subcategory":"Food",
            "type":"Manufacturing & Wholesale Goods"
        }
    ],
    "sg:phone":"+1 763 263 2102",
    "sg:postcode":"55309",
    "sg:province":"MN",
    "sg:tags":[
        "product",
        "potato"
    ],
    "wof:name":"Del Hayes & Sons Potato Wrhs",
    "wof:placetype":"venue"
},
  "geometry": {"coordinates":[-93.706281,45.310142],"type":"Point"}
}