{
  "type": "Feature",
  "properties": {
    "iso:country":"US",
    "sg:address":"601 W 28th St Apt 3",
    "sg:city":"Minneapolis",
    "sg:classifiers":[
        {
            "category":"Ice Cream",
            "type":"Food & Drink"
        }
    ],
    "sg:phone":"+1 612 870 8899",
    "sg:postcode":"55408",
    "sg:province":"MN",
    "sg:tags":[
        "frozen",
        "dessert"
    ],
    "wof:name":"Aywa Inc",
    "wof:placetype":"venue"
},
  "geometry": {"coordinates":[-93.286812,44.95195],"type":"Point"}
}