{
  "type": "Feature",
  "properties": {
    "iso:country":"US",
    "sg:address":"305 Stillwater Rd",
    "sg:city":"Willernie",
    "sg:classifiers":[
        {
            "category":"Building & Trades",
            "subcategory":"Construction",
            "type":"Services"
        }
    ],
    "sg:phone":"+1 651 653 6807",
    "sg:postcode":"55090",
    "sg:province":"MN",
    "sg:tags":[
        "designer",
        "dealer",
        "pool",
        "swimming"
    ],
    "sg:website":"www.paragonpoolandspa.com",
    "wof:name":"Paragon Pool & Patio",
    "wof:placetype":"venue"
},
  "geometry": {"coordinates":[-92.95731600000001,45.056989],"type":"Point"}
}