{
  "type": "Feature",
  "properties": {
    "iso:country":"US",
    "sg:address":"4055 Johnny Cake Ridge Rd",
    "sg:city":"St Paul",
    "sg:classifiers":[
        {
            "category":"Professional",
            "subcategory":"Art Services",
            "type":"Services"
        }
    ],
    "sg:phone":"+1 651 405 3982",
    "sg:postcode":"55122",
    "sg:province":"MN",
    "sg:tags":[
        "photographer"
    ],
    "wof:name":"Oldenburg Studios",
    "wof:placetype":"venue"
},
  "geometry": {"coordinates":[-93.180252,44.809065],"type":"Point"}
}