{
  "type": "Feature",
  "properties": {
    "addr:full":"113 12th St Farmington MN 55024",
    "addr:housenumber":"113",
    "addr:postcode":"55024",
    "addr:street":"12Th St",
    "iso:country":"US",
    "sg:address":"113 12th St",
    "sg:city":"Farmington",
    "sg:classifiers":[
        {
            "category":"Building & Trades",
            "subcategory":"Construction",
            "type":"Services"
        }
    ],
    "sg:phone":"+1 651 463 4894",
    "sg:postcode":"55024",
    "sg:province":"MN",
    "sg:tags":[
        "house"
    ],
    "wof:name":"Allen Homes Corp",
    "wof:placetype":"venue"
},
  "geometry": {"coordinates":[-93.130281,44.641754],"type":"Point"}
}