{
  "type": "Feature",
  "properties": {
    "addr:full":"2647 Nicollet Ave Minneapolis MN 55408",
    "addr:housenumber":"2647",
    "addr:postcode":"55408",
    "addr:street":"Nicollet Ave",
    "iso:country":"US",
    "sg:address":"2647 Nicollet Ave",
    "sg:city":"Minneapolis",
    "sg:classifiers":[
        {
            "category":"Bars & Pubs",
            "type":"Food & Drink"
        }
    ],
    "sg:phone":"+1 612 872 0808",
    "sg:postcode":"55408",
    "sg:province":"MN",
    "sg:website":"www.porters.citysearch.com",
    "wof:name":"Porter's Bar & Grill",
    "wof:placetype":"venue"
},
  "geometry": {"coordinates":[-93.277812,44.954582],"type":"Point"}
}