{
  "type": "Feature",
  "properties": {
    "addr:full":"1209 S Lincoln St Redwood Falls MN 56283",
    "addr:housenumber":"1209",
    "addr:postcode":"56283",
    "addr:street":"S Lincoln St",
    "iso:country":"US",
    "sg:address":"1209 S Lincoln St",
    "sg:city":"Redwood Falls",
    "sg:classifiers":[
        {
            "category":"Real Estate",
            "subcategory":"Real Estate Operator",
            "type":"Services"
        }
    ],
    "sg:phone":"+1 507 637 5157",
    "sg:postcode":"56283",
    "sg:province":"MN",
    "sg:tags":[
        "property",
        "lessor"
    ],
    "wof:name":"Nelson Einar",
    "wof:placetype":"venue"
},
  "geometry": {"coordinates":[-95.114163,44.530963],"type":"Point"}
}