{
  "type": "Feature",
  "properties": {
    "addr:full":"303 22nd Ave W Alexandria MN 56308",
    "addr:housenumber":"303",
    "addr:postcode":"56308",
    "addr:street":"22Nd Ave W",
    "iso:country":"US",
    "sg:address":"303 22nd Ave W",
    "sg:city":"Alexandria",
    "sg:classifiers":[
        {
            "category":"Professional",
            "subcategory":"Employment Agencies",
            "type":"Services"
        }
    ],
    "sg:phone":"+1 320 763 3107",
    "sg:postcode":"56308",
    "sg:province":"MN",
    "wof:name":"Cep",
    "wof:placetype":"venue"
},
  "geometry": {"coordinates":[-95.386269,45.867541],"type":"Point"}
}