{
  "type": "Feature",
  "properties": {
    "iso:country":"US",
    "sg:address":"216 2nd Ave",
    "sg:city":"Lanesboro",
    "sg:classifiers":[
        {
            "category":"Professional",
            "subcategory":"Management & Consulting",
            "type":"Services"
        }
    ],
    "sg:phone":"+1 507 467 6580",
    "sg:postcode":"55949",
    "sg:province":"MN",
    "sg:tags":[
        "consultant",
        "business"
    ],
    "wof:name":"KMS Mfg",
    "wof:placetype":"venue"
},
  "geometry": {"coordinates":[-91.92692,43.73196],"type":"Point"}
}