{
  "type": "Feature",
  "properties": {
    "iso:country":"US",
    "sg:address":"561 Prairie Center Dr",
    "sg:city":"Eden Prairie",
    "sg:classifiers":[
        {
            "category":"Food & Beverages",
            "subcategory":"Specialty",
            "type":"Retail Goods"
        }
    ],
    "sg:phone":"+1 952 942 8331",
    "sg:postcode":"55344",
    "sg:province":"MN",
    "sg:tags":[
        "tea",
        "coffee"
    ],
    "sg:website":"www.dunnbros.com",
    "wof:name":"Dunn Brothers Coffee",
    "wof:placetype":"venue"
},
  "geometry": {"coordinates":[-93.42439299999999,44.851043],"type":"Point"}
}