{
  "type": "Feature",
  "properties": {
    "iso:country":"US",
    "sg:address":"733 18th St",
    "sg:city":"Windom",
    "sg:classifiers":[
        {
            "category":"Farming",
            "subcategory":"Farm",
            "type":"Manufacturing & Wholesale Goods"
        }
    ],
    "sg:phone":"+1 507 831 5486",
    "sg:postcode":"56101",
    "sg:province":"MN",
    "sg:tags":[
        "crop",
        "general"
    ],
    "wof:name":"John Salzwedel",
    "wof:placetype":"venue"
},
  "geometry": {"coordinates":[-95.123267,43.875599],"type":"Point"}
}