{
  "type": "Feature",
  "properties": {
    "addr:full":"326 70th Ave Hills MN 56122",
    "addr:housenumber":"326",
    "addr:postcode":"56122",
    "addr:street":"70Th Ave",
    "iso:country":"US",
    "sg:address":"326 70th Ave",
    "sg:city":"Hills",
    "sg:phone":"+1 507 962 3635",
    "sg:postcode":"56122",
    "sg:province":"MN",
    "sg:tags":[
        "hog",
        "beef",
        "f",
        "farm",
        "corn",
        "soybean",
        "cattle",
        "feedlot"
    ],
    "wof:name":"Dennis Erickson",
    "wof:placetype":"venue"
},
  "geometry": {"coordinates":[-95.92421899999999,43.895735],"type":"Point"}
}