{
  "type": "Feature",
  "properties": {
    "iso:country":"US",
    "sg:address":"1181 Homestead Ln",
    "sg:city":"Chanhassen",
    "sg:classifiers":[
        {
            "category":"Professional",
            "subcategory":"Management & Consulting",
            "type":"Services"
        }
    ],
    "sg:phone":"+1 952 402 9000",
    "sg:postcode":"55317",
    "sg:province":"MN",
    "sg:tags":[
        "computer",
        "design",
        "system"
    ],
    "wof:name":"Usmacnet",
    "wof:placetype":"venue"
},
  "geometry": {"coordinates":[-93.5497,44.828528],"type":"Point"}
}