{
  "type": "Feature",
  "properties": {
    "addr:full":"821 4th Ave Windom MN 56101",
    "addr:housenumber":"821",
    "addr:postcode":"56101",
    "addr:street":"4Th Ave",
    "iso:country":"US",
    "sg:address":"821 4th Ave",
    "sg:city":"Windom",
    "sg:classifiers":[
        {
            "category":"Organizations",
            "subcategory":"Community Association",
            "type":"Services"
        }
    ],
    "sg:phone":"+1 507 831 3891",
    "sg:postcode":"56101",
    "sg:province":"MN",
    "sg:tags":[
        "fraternal"
    ],
    "wof:name":"Fraternal Order Of Eagles",
    "wof:placetype":"venue"
},
  "geometry": {"coordinates":[-95.11764599999999,43.864575],"type":"Point"}
}