{
  "type": "Feature",
  "properties": {
    "addr:full":"18674 225th Ave Pierz MN 56364",
    "addr:housenumber":"18674",
    "addr:postcode":"56364",
    "addr:street":"225Th Ave",
    "iso:country":"US",
    "sg:address":"18674 225th Ave",
    "sg:city":"Pierz",
    "sg:classifiers":[
        {
            "category":"Farming",
            "subcategory":"Livestock Farm",
            "type":"Manufacturing & Wholesale Goods"
        }
    ],
    "sg:phone":"+1 320 745 2448",
    "sg:postcode":"56364",
    "sg:province":"MN",
    "sg:tags":[
        "feedlot",
        "cattle",
        "crop",
        "beef",
        "general"
    ],
    "wof:name":"Dickmann Reg Holstein Farms",
    "wof:placetype":"venue"
},
  "geometry": {"coordinates":[-94.187417,46.028807],"type":"Point"}
}