{
  "type": "Feature",
  "properties": {
    "iso:country":"US",
    "sg:address":"2422 Central Ave NE",
    "sg:city":"Minneapolis",
    "sg:classifiers":[
        {
            "category":"Restaurant",
            "type":"Food & Drink"
        }
    ],
    "sg:phone":"+1 612 781 3046",
    "sg:postcode":"55418",
    "sg:province":"MN",
    "sg:tags":[
        "thai"
    ],
    "sg:website":"www.senyai-senlek.com",
    "wof:name":"Sen Yai Sen Lek",
    "wof:placetype":"venue"
},
  "geometry": {"coordinates":[-93.24775,45.012896],"type":"Point"}
}