{
  "type": "Feature",
  "properties": {
    "iso:country":"US",
    "sg:address":"11835 Avocet Cir NW",
    "sg:city":"Minneapolis",
    "sg:classifiers":[
        {
            "category":"Health Services",
            "subcategory":"Health Practitioner",
            "type":"Services"
        }
    ],
    "sg:phone":"+1 763 228 2050",
    "sg:postcode":"55448",
    "sg:province":"MN",
    "sg:tags":[
        "hypnotherapy",
        "hypnotist"
    ],
    "wof:name":"Achieve With Hypnosis",
    "wof:placetype":"venue"
},
  "geometry": {"coordinates":[-93.30078899999999,45.185314],"type":"Point"}
}