{
  "type": "Feature",
  "properties": {
    "iso:country":"US",
    "sg:address":"901 9th St N",
    "sg:city":"Virginia",
    "sg:classifiers":[
        {
            "category":"Health Services",
            "subcategory":"Doctor",
            "type":"Services"
        }
    ],
    "sg:phone":"+1 218 741 3340",
    "sg:postcode":"55792",
    "sg:province":"MN",
    "sg:tags":[
        "medical",
        "executive",
        "general"
    ],
    "sg:website":"www.vrmc.org",
    "wof:name":"Virginia Regional Medical Ctr",
    "wof:placetype":"venue"
},
  "geometry": {"coordinates":[-92.54753700000001,47.530694],"type":"Point"}
}