{
  "type": "Feature",
  "properties": {
    "iso:country":"US",
    "sg:address":"4046 Lyndale Ave N",
    "sg:city":"Minneapolis",
    "sg:classifiers":[
        {
            "category":"Real Estate",
            "subcategory":"Real Estate Operator",
            "type":"Services"
        }
    ],
    "sg:phone":"+1 612 529 4822",
    "sg:postcode":"55412",
    "sg:province":"MN",
    "sg:tags":[
        "building",
        "apartment"
    ],
    "wof:name":"Prosperity Village",
    "wof:placetype":"venue"
},
  "geometry": {"coordinates":[-93.288101,45.0284],"type":"Point"}
}