{
  "type": "Feature",
  "properties": {
    "addr:full":"15720 Lincoln St NE Anoka MN 55304",
    "addr:housenumber":"15720",
    "addr:postcode":"55304",
    "addr:street":"Lincoln St Ne",
    "iso:country":"US",
    "sg:address":"15720 Lincoln St NE",
    "sg:city":"Anoka",
    "sg:classifiers":[
        {
            "category":"Manufacturing",
            "subcategory":"Tools & Machinery",
            "type":"Manufacturing & Wholesale Goods"
        }
    ],
    "sg:phone":"+1 763 434 4471",
    "sg:postcode":"55304",
    "sg:province":"MN",
    "sg:tags":[
        "pattern",
        "mold",
        "mfg"
    ],
    "wof:name":"Al-Cast Mold & Pattern Inc",
    "wof:placetype":"venue"
},
  "geometry": {"coordinates":[-93.238332,45.256515],"type":"Point"}
}