{
  "type": "Feature",
  "properties": {
    "addr:full":"900 Cannon Valley Dr Northfield MN 55057",
    "addr:housenumber":"900",
    "addr:postcode":"55057",
    "addr:street":"Cannon Valley Dr",
    "iso:country":"US",
    "sg:address":"900 Cannon Valley Dr",
    "sg:city":"Northfield",
    "sg:classifiers":[
        {
            "category":"Organizations",
            "subcategory":"Religious Organization",
            "type":"Services"
        },
        {
            "category":"Health Services",
            "subcategory":"Health Practitioner",
            "type":"Services"
        }
    ],
    "sg:phone":"+1 507 664 0134",
    "sg:postcode":"55057",
    "sg:province":"MN",
    "sg:tags":[
        "church"
    ],
    "wof:name":"Faith In Action Interfaith HLT",
    "wof:placetype":"venue"
},
  "geometry": {"coordinates":[-93.18087800000001,44.469463],"type":"Point"}
}