{
  "type": "Feature",
  "properties": {
    "iso:country":"US",
    "sg:address":"2645 Larch Ln N",
    "sg:city":"Minneapolis",
    "sg:classifiers":[
        {
            "category":"Social Services",
            "subcategory":"Child Care",
            "type":"Services"
        }
    ],
    "sg:phone":"+1 763 559 0922",
    "sg:postcode":"55441",
    "sg:province":"MN",
    "sg:tags":[
        "daycare",
        "provider"
    ],
    "wof:name":"Gayle Quinn",
    "wof:placetype":"venue"
},
  "geometry": {"coordinates":[-93.436069,45.009387],"type":"Point"}
}