{
  "type": "Feature",
  "properties": {
    "addr:full":"3305 Co Rd 101 Wayzata MN 55391",
    "addr:housenumber":"3305;101",
    "addr:postcode":"55391",
    "addr:street":"Co Rd",
    "iso:country":"US",
    "sg:address":"3305 Co Rd 101",
    "sg:city":"Wayzata",
    "sg:classifiers":[
        {
            "category":"Professional",
            "type":"Services"
        }
    ],
    "sg:phone":"+1 952 443 3947",
    "sg:postcode":"55391",
    "sg:province":"MN",
    "sg:tags":[
        "establishment"
    ],
    "wof:name":"C C & H Inc",
    "wof:placetype":"venue"
},
  "geometry": {"coordinates":[-93.502207,44.943005],"type":"Point"}
}