{
  "type": "Feature",
  "properties": {
    "iso:country":"US",
    "sg:address":"2211 Clinton Ave S",
    "sg:city":"Minneapolis",
    "sg:classifiers":[
        {
            "category":"Organizations",
            "subcategory":"Religious Organization",
            "type":"Services"
        }
    ],
    "sg:phone":"+1 612 874 0311",
    "sg:postcode":"55404",
    "sg:province":"MN",
    "wof:name":"Church of St Stephen",
    "wof:placetype":"venue"
},
  "geometry": {"coordinates":[-93.271424,44.95929],"type":"Point"}
}