{
  "type": "Feature",
  "properties": {
    "iso:country":"US",
    "sg:address":"16439 Gunflint Trl",
    "sg:city":"Lakeville",
    "sg:classifiers":[
        {
            "category":"Professional",
            "subcategory":"Art Services",
            "type":"Services"
        }
    ],
    "sg:phone":"+1 952 953 3406",
    "sg:postcode":"55044",
    "sg:province":"MN",
    "sg:tags":[
        "designer",
        "display",
        "producer"
    ],
    "wof:name":"Magical Image Design",
    "wof:placetype":"venue"
},
  "geometry": {"coordinates":[-93.235349,44.711067],"type":"Point"}
}