{
  "type": "Feature",
  "properties": {
    "iso:country":"US",
    "sg:address":"910 W Broadway Ave",
    "sg:city":"Minneapolis",
    "sg:classifiers":[
        {
            "category":"Shopping",
            "subcategory":"Shoes",
            "type":"Retail Goods"
        }
    ],
    "sg:phone":"+1 612 588 9054",
    "sg:postcode":"55411",
    "sg:province":"MN",
    "sg:tags":[
        "store"
    ],
    "sg:website":"www.footlocker.com",
    "wof:name":"Foot Locker #8696",
    "wof:placetype":"venue"
},
  "geometry": {"coordinates":[-93.291211,44.999277],"type":"Point"}
}