{
  "type": "Feature",
  "properties": {
    "iso:country":"US",
    "sg:address":"3744 4th Ave S",
    "sg:city":"Minneapolis",
    "sg:classifiers":[
        {
            "category":"Communications",
            "subcategory":"Newspaper",
            "type":"Services"
        }
    ],
    "sg:phone":"+1 612 827 4021",
    "sg:postcode":"55409",
    "sg:province":"MN",
    "sg:tags":[
        "print",
        "medium"
    ],
    "wof:name":"St Paul Recorder Newspr",
    "wof:placetype":"venue"
},
  "geometry": {"coordinates":[-93.270302,44.934399],"type":"Point"}
}