{
  "type": "Feature",
  "properties": {
    "iso:country":"US",
    "sg:address":"124 8th Ave NE",
    "sg:city":"Elbow Lake",
    "sg:classifiers":[
        {
            "category":"Retail",
            "subcategory":"Repair Shop",
            "type":"Services"
        }
    ],
    "sg:phone":"+1 218 685 4259",
    "sg:postcode":"56531",
    "sg:province":"MN",
    "wof:name":"Bills Cleaning Service",
    "wof:placetype":"venue"
},
  "geometry": {"coordinates":[-95.96625,45.993469],"type":"Point"}
}