{
  "type": "Feature",
  "properties": {
    "iso:country":"US",
    "sg:address":"1209 S Broadway St",
    "sg:city":"New Ulm",
    "sg:classifiers":[
        {
            "category":"Shopping",
            "subcategory":"Used Merchandise",
            "type":"Retail Goods"
        }
    ],
    "sg:phone":"+1 507 354 6108",
    "sg:postcode":"56073",
    "sg:province":"MN",
    "wof:name":"Treasure Haus Inc",
    "wof:placetype":"venue"
},
  "geometry": {"coordinates":[-94.449074,44.300804],"type":"Point"}
}