{
  "type": "Feature",
  "properties": {
    "addr:full":"7465 Eden Prairie Rd Eden Prairie MN 55346",
    "addr:housenumber":"7465",
    "addr:postcode":"55346",
    "addr:street":"Eden Prairie Rd",
    "iso:country":"US",
    "sg:address":"7465 Eden Prairie Rd",
    "sg:city":"Eden Prairie",
    "sg:classifiers":[
        {
            "category":"Social Services",
            "subcategory":"Child Care",
            "type":"Services"
        },
        {
            "category":"Social Services",
            "subcategory":"Job Training",
            "type":"Services"
        }
    ],
    "sg:phone":"+1 952 906 3822",
    "sg:postcode":"55346",
    "sg:province":"MN",
    "sg:tags":[
        "rehabilitation",
        "clinic",
        "outpatient",
        "day",
        "specialty"
    ],
    "wof:name":"Chrestomathy Center Inc",
    "wof:placetype":"venue"
},
  "geometry": {"coordinates":[-93.48544699999999,44.867153],"type":"Point"}
}