{
  "type": "Feature",
  "properties": {
    "addr:full":"5501 Lakeland Ave N Minneapolis MN 55429",
    "addr:housenumber":"5501",
    "addr:postcode":"55429",
    "addr:street":"Lakeland Ave N",
    "iso:country":"US",
    "sg:address":"5501 Lakeland Ave N",
    "sg:city":"Minneapolis",
    "sg:classifiers":[
        {
            "category":"Real Estate",
            "subcategory":"Real Estate Agent",
            "type":"Services"
        }
    ],
    "sg:phone":"+1 763 535 2170",
    "sg:postcode":"55429",
    "sg:province":"MN",
    "wof:name":"ALS Properties",
    "wof:placetype":"venue"
},
  "geometry": {"coordinates":[-93.358502,45.054641],"type":"Point"}
}