{
  "type": "Feature",
  "properties": {
    "iso:country":"US",
    "sg:address":"5411 142nd Ave NW",
    "sg:city":"Anoka",
    "sg:classifiers":[
        {
            "category":"Professional",
            "type":"Services"
        }
    ],
    "sg:phone":"+1 763 323 0477",
    "sg:postcode":"55303",
    "sg:province":"MN",
    "wof:name":"Troy Vertina",
    "wof:placetype":"venue"
},
  "geometry": {"coordinates":[-93.40650599999999,45.228561],"type":"Point"}
}