{
  "type": "Feature",
  "properties": {
    "addr:full":"104 1st St NW Dodge Center MN 55927",
    "addr:housenumber":"104",
    "addr:postcode":"55927",
    "addr:street":"1St St Nw",
    "iso:country":"US",
    "sg:address":"104 1st St NW",
    "sg:city":"Dodge Center",
    "sg:classifiers":[
        {
            "category":"Education",
            "subcategory":"School",
            "type":"Public Place"
        }
    ],
    "sg:phone":"+1 507 374 8046",
    "sg:postcode":"55927",
    "sg:province":"MN",
    "wof:name":"Zumbro Education District",
    "wof:placetype":"venue"
},
  "geometry": {"coordinates":[-92.855782,44.029063],"type":"Point"}
}