{
  "type": "Feature",
  "properties": {
    "addr:full":"6521 Nicollet Ave Minneapolis MN 55423",
    "addr:housenumber":"6521",
    "addr:postcode":"55423",
    "addr:street":"Nicollet Ave",
    "iso:country":"US",
    "sg:address":"6521 Nicollet Ave",
    "sg:city":"Minneapolis",
    "sg:classifiers":[
        {
            "category":"Personal",
            "subcategory":"Tanning Parlor",
            "type":"Services"
        }
    ],
    "sg:phone":"+1 612 866 3326",
    "sg:postcode":"55423",
    "sg:province":"MN",
    "sg:tags":[
        "salon"
    ],
    "wof:name":"Tan Line Of Richfield",
    "wof:placetype":"venue"
},
  "geometry": {"coordinates":[-93.278085,44.884916],"type":"Point"}
}