{
  "type": "Feature",
  "properties": {
    "addr:full":"2236 7th St W St Paul MN 55116",
    "addr:housenumber":"2236",
    "addr:postcode":"55116",
    "addr:street":"7Th St W",
    "iso:country":"US",
    "sg:address":"2236 7th St W",
    "sg:city":"St Paul",
    "sg:classifiers":[
        {
            "category":"Building & Trades",
            "subcategory":"Equipment Rental",
            "type":"Services"
        },
        {
            "category":"Cinema",
            "subcategory":"Movie Rental",
            "type":"Entertainment"
        }
    ],
    "sg:phone":"+1 651 699 6936",
    "sg:postcode":"55116",
    "sg:province":"MN",
    "sg:tags":[
        "tape",
        "video",
        "disc",
        "leasing"
    ],
    "wof:name":"Movie Station",
    "wof:placetype":"venue"
},
  "geometry": {"coordinates":[-93.161891,44.905701],"type":"Point"}
}