{
  "type": "Feature",
  "properties": {
    "iso:country":"US",
    "sg:address":"2400 W 102nd St",
    "sg:city":"Minneapolis",
    "sg:classifiers":[
        {
            "category":"Building & Trades",
            "subcategory":"Construction",
            "type":"Services"
        }
    ],
    "sg:phone":"+1 952 830 0505",
    "sg:postcode":"55431",
    "sg:province":"MN",
    "sg:tags":[
        "resurfacing",
        "laying",
        "refinishing",
        "floor"
    ],
    "wof:name":"Midwest Custom Hardwood Floors",
    "wof:placetype":"venue"
},
  "geometry": {"coordinates":[-93.310593,44.819099],"type":"Point"}
}