{
  "type": "Feature",
  "properties": {
    "addr:full":"440 US Hwy 212 Bird Island MN 55310",
    "addr:housenumber":"440",
    "addr:postcode":"55310",
    "addr:street":"Us Hwy 212;Island",
    "iso:country":"US",
    "sg:address":"440 US Hwy 212",
    "sg:city":"Bird Island",
    "sg:classifiers":[
        {
            "category":"Retail",
            "subcategory":"Auto Repair",
            "type":"Services"
        }
    ],
    "sg:phone":"+1 320 365 4041",
    "sg:postcode":"55310",
    "sg:province":"MN",
    "sg:tags":[
        "body",
        "automobile",
        "painting"
    ],
    "wof:name":"Bird Island Body Shop",
    "wof:placetype":"venue"
},
  "geometry": {"coordinates":[-94.890672,44.76764],"type":"Point"}
}