{
  "type": "Feature",
  "properties": {
    "addr:full":"13241 140th St NE Foley MN 56329",
    "addr:housenumber":"13241",
    "addr:postcode":"56329",
    "addr:street":"140Th St Ne",
    "iso:country":"US",
    "sg:address":"13241 140th St NE",
    "sg:city":"Foley",
    "sg:classifiers":[
        {
            "category":"Farming",
            "subcategory":"Dairy Farm",
            "type":"Manufacturing & Wholesale Goods"
        }
    ],
    "sg:phone":"+1 320 387 2258",
    "sg:postcode":"56329",
    "sg:province":"MN",
    "wof:name":"Don-Sha Dairy",
    "wof:placetype":"venue"
},
  "geometry": {"coordinates":[-93.88761599999999,45.77182],"type":"Point"}
}