{
  "type": "Feature",
  "properties": {
    "iso:country":"US",
    "sg:address":"15337 28th Ave S",
    "sg:city":"Glyndon",
    "sg:classifiers":[
        {
            "category":"Professional",
            "subcategory":"Management & Consulting",
            "type":"Services"
        },
        {
            "category":"Organizations",
            "subcategory":"Membership Organization",
            "type":"Services"
        }
    ],
    "sg:phone":"+1 218 498 2679",
    "sg:postcode":"56547",
    "sg:province":"MN",
    "sg:tags":[
        "consultant",
        "ecological",
        "conservation",
        "environmental"
    ],
    "sg:website":"http://www.nature.org",
    "wof:name":"The Nature Conservancy",
    "wof:placetype":"venue"
},
  "geometry": {"coordinates":[-96.479733,46.847774],"type":"Point"}
}