{
  "type": "Feature",
  "properties": {
    "iso:country":"US",
    "sg:address":"24537 Hwy 4",
    "sg:city":"Paynesville",
    "sg:classifiers":[
        {
            "category":"Freight",
            "type":"Transportation"
        }
    ],
    "sg:phone":"+1 320 243 3285",
    "sg:postcode":"56362",
    "sg:province":"MN",
    "sg:tags":[
        "operator",
        "trucking"
    ],
    "wof:name":"Jaeger Trucking",
    "wof:placetype":"venue"
},
  "geometry": {"coordinates":[-94.807863,45.485065],"type":"Point"}
}