{
  "type": "Feature",
  "properties": {
    "addr:full":"4049 Stockdale Dr Saint Paul MN 55127",
    "addr:housenumber":"4049",
    "addr:postcode":"55127",
    "addr:street":"Stockdale Dr",
    "iso:country":"US",
    "sg:address":"4049 Stockdale Dr",
    "sg:city":"Saint Paul",
    "sg:classifiers":[
        {
            "category":"Manufacturing",
            "subcategory":"Printing",
            "type":"Manufacturing & Wholesale Goods"
        }
    ],
    "sg:phone":"+1 651 426 8844",
    "sg:postcode":"55127",
    "sg:province":"MN",
    "sg:tags":[
        "commercial"
    ],
    "wof:name":"Buzzword",
    "wof:placetype":"venue"
},
  "geometry": {"coordinates":[-93.069791,45.062825],"type":"Point"}
}