{
  "type": "Feature",
  "properties": {
    "addr:full":"1420 2nd St N Sauk Rapids MN 56379",
    "addr:housenumber":"1420",
    "addr:postcode":"56379",
    "addr:street":"2Nd St N Sauk",
    "iso:country":"US",
    "sg:address":"1420 2nd St N",
    "sg:city":"Sauk Rapids",
    "sg:classifiers":[
        {
            "category":"Travel",
            "subcategory":"Hotels & Motels",
            "type":"Entertainment"
        }
    ],
    "sg:phone":"+1 320 251 9333",
    "sg:postcode":"56379",
    "sg:province":"MN",
    "wof:name":"Super 8",
    "wof:placetype":"venue"
},
  "geometry": {"coordinates":[-94.151774,45.598294],"type":"Point"}
}