{
  "type": "Feature",
  "properties": {
    "addr:full":"21919 330th St Rushmore MN 56168",
    "addr:housenumber":"21919",
    "addr:postcode":"56168",
    "addr:street":"330Th St",
    "iso:country":"US",
    "sg:address":"21919 330th St",
    "sg:city":"Rushmore",
    "sg:classifiers":[
        {
            "category":"Farming",
            "subcategory":"Livestock Farm",
            "type":"Manufacturing & Wholesale Goods"
        }
    ],
    "sg:phone":"+1 507 394 2334",
    "sg:postcode":"56168",
    "sg:province":"MN",
    "sg:tags":[
        "feedlot",
        "corn",
        "soybean",
        "beef",
        "cattle"
    ],
    "wof:name":"Houtsma Algene",
    "wof:placetype":"venue"
},
  "geometry": {"coordinates":[-95.816641,43.514263],"type":"Point"}
}