{
  "type": "Feature",
  "properties": {
    "addr:full":"6 Pine Tree Dr Arden Hills MN 55112",
    "addr:housenumber":"6",
    "addr:postcode":"55112",
    "addr:street":"Pine Tree Dr",
    "iso:country":"US",
    "sg:address":"6 Pine Tree Dr",
    "sg:city":"Arden Hills",
    "sg:classifiers":[
        {
            "category":"Wholesale",
            "subcategory":"Machinery & Supplies",
            "type":"Manufacturing & Wholesale Goods"
        },
        {
            "category":"Manufacturing",
            "subcategory":"Chemicals & Compounds",
            "type":"Manufacturing & Wholesale Goods"
        }
    ],
    "sg:phone":"+1 651 765 4585",
    "sg:postcode":"55112",
    "sg:province":"MN",
    "sg:tags":[
        "food",
        "equipment",
        "dairy"
    ],
    "wof:name":"North Star Processing LLC",
    "wof:placetype":"venue"
},
  "geometry": {"coordinates":[-93.152198,45.047023],"type":"Point"}
}