{
  "type": "Feature",
  "properties": {
    "iso:country":"US",
    "sg:address":"224 Water St",
    "sg:city":"Jordan",
    "sg:classifiers":[
        {
            "category":"Banks & Credit Unions",
            "subcategory":"Investment Brokerage",
            "type":"Services"
        },
        {
            "category":"Professional",
            "subcategory":"Management & Consulting",
            "type":"Services"
        }
    ],
    "sg:phone":"+1 952 492 3500",
    "sg:postcode":"55352",
    "sg:province":"MN",
    "sg:tags":[
        "advisory",
        "planning",
        "financial",
        "consultant"
    ],
    "wof:name":"High Financial Svc",
    "wof:placetype":"venue"
},
  "geometry": {"coordinates":[-93.626425,44.665244],"type":"Point"}
}