{
  "type": "Feature",
  "properties": {
    "addr:full":"13875 345th Ave Winnebago MN 56098",
    "addr:housenumber":"13875",
    "addr:postcode":"56098",
    "addr:street":"345Th Ave",
    "iso:country":"US",
    "sg:address":"13875 345th Ave",
    "sg:city":"Winnebago",
    "sg:classifiers":[
        {
            "category":"Manufacturing",
            "subcategory":"Apparel",
            "type":"Manufacturing & Wholesale Goods"
        }
    ],
    "sg:phone":"+1 507 526 5950",
    "sg:postcode":"56098",
    "sg:province":"MN",
    "sg:tags":[
        "farm",
        "underwear",
        "corn",
        "soybean",
        "mfg"
    ],
    "wof:name":"Tim Peterson",
    "wof:placetype":"venue"
},
  "geometry": {"coordinates":[-94.177724,43.680608],"type":"Point"}
}