{
  "type": "Feature",
  "properties": {
    "iso:country":"US",
    "sg:address":"1245 Washington Ave",
    "sg:city":"Detroit Lakes",
    "sg:classifiers":[
        {
            "category":"Health Services",
            "subcategory":"Doctor",
            "type":"Services"
        }
    ],
    "sg:phone":"+1 218 846 2258",
    "sg:postcode":"56501",
    "sg:province":"MN",
    "sg:tags":[
        "clinic"
    ],
    "wof:name":"Merit Care",
    "wof:placetype":"venue"
},
  "geometry": {"coordinates":[-95.845731,46.809003],"type":"Point"}
}