{
  "type": "Feature",
  "properties": {
    "iso:country":"US",
    "sg:address":"8660 W Beatrice Dr",
    "sg:city":"Clear Lake",
    "sg:classifiers":[
        {
            "category":"Retail",
            "subcategory":"Repair Shop",
            "type":"Services"
        }
    ],
    "sg:phone":"+1 763 261 2783",
    "sg:postcode":"55319",
    "sg:province":"MN",
    "sg:tags":[
        "refrigerating"
    ],
    "wof:name":"Northland Refrigeration",
    "wof:placetype":"venue"
},
  "geometry": {"coordinates":[-93.886386,45.444918],"type":"Point"}
}