{
  "type": "Feature",
  "properties": {
    "iso:country":"US",
    "sg:address":"7551 W 270th St",
    "sg:city":"Belle Plaine",
    "sg:phone":"+1 952 758 3728",
    "sg:postcode":"56011",
    "sg:province":"MN",
    "sg:tags":[
        "farm",
        "corn",
        "soybean"
    ],
    "wof:name":"Brian Entinger",
    "wof:placetype":"venue"
},
  "geometry": {"coordinates":[-93.676309,44.557307],"type":"Point"}
}