{
  "type": "Feature",
  "properties": {
    "addr:full":"1830 Hayes St NE Minneapolis MN 55418",
    "addr:housenumber":"1830",
    "addr:postcode":"55418",
    "addr:street":"Hayes St Ne",
    "iso:country":"US",
    "sg:address":"1830 Hayes St NE",
    "sg:city":"Minneapolis",
    "sg:classifiers":[
        {
            "category":"Taxi",
            "type":"Transportation"
        }
    ],
    "sg:phone":"+1 612 789 0231",
    "sg:postcode":"55418",
    "sg:province":"MN",
    "wof:name":"United Taxi",
    "wof:placetype":"venue"
},
  "geometry": {"coordinates":[-93.234602,45.006524],"type":"Point"}
}