{
  "type": "Feature",
  "properties": {
    "addr:full":"7066 Stillwater Blvd N Oakdale MN 55128",
    "addr:housenumber":"7066",
    "addr:postcode":"55128",
    "addr:street":"Stillwater Blvd N",
    "iso:country":"US",
    "sg:address":"7066 Stillwater Blvd N",
    "sg:city":"Oakdale",
    "sg:classifiers":[
        {
            "category":"Health Services",
            "subcategory":"Doctor",
            "type":"Services"
        }
    ],
    "sg:phone":"+1 651 681 1600",
    "sg:postcode":"55128",
    "sg:province":"MN",
    "sg:tags":[
        "physician",
        "surgeon"
    ],
    "wof:name":"Human Services Inc",
    "wof:placetype":"venue"
},
  "geometry": {"coordinates":[-92.962897,44.986395],"type":"Point"}
}