{
  "type": "Feature",
  "properties": {
    "iso:country":"US",
    "sg:address":"77770 380th St",
    "sg:city":"Bird Island",
    "sg:classifiers":[
        {
            "category":"Food & Beverages",
            "subcategory":"Candy",
            "type":"Retail Goods"
        }
    ],
    "sg:phone":"+1 320 365 3708",
    "sg:postcode":"55310",
    "sg:province":"MN",
    "wof:name":"Bakery Confectionery Toba",
    "wof:placetype":"venue"
},
  "geometry": {"coordinates":[-94.914907,44.716624],"type":"Point"}
}