{
  "type": "Feature",
  "properties": {
    "addr:full":"225 N State Ave Le Center MN 56057",
    "addr:housenumber":"225",
    "addr:postcode":"56057",
    "addr:street":"N State Ave",
    "iso:country":"US",
    "sg:address":"225 N State Ave",
    "sg:city":"Le Center",
    "sg:classifiers":[
        {
            "category":"Social Services",
            "subcategory":"Child Care",
            "type":"Services"
        }
    ],
    "sg:phone":"+1 507 357 6585",
    "sg:postcode":"56057",
    "sg:province":"MN",
    "sg:tags":[
        "day",
        "provider"
    ],
    "wof:name":"Susan M Shaughnessy",
    "wof:placetype":"venue"
},
  "geometry": {"coordinates":[-93.726355,44.392381],"type":"Point"}
}