{
  "type": "Feature",
  "properties": {
    "iso:country":"US",
    "sg:address":"501 19th St SE",
    "sg:city":"Willmar",
    "sg:phone":"+1 320 235 5281",
    "sg:postcode":"56201",
    "sg:province":"MN",
    "wof:name":"Farm Bureau Insurance",
    "wof:placetype":"venue"
},
  "geometry": {"coordinates":[-95.018328,45.11963],"type":"Point"}
}