{
  "type": "Feature",
  "properties": {
    "addr:full":"5820 Teakwood Ln N Apt G Minneapolis MN 55442",
    "addr:housenumber":"5820",
    "addr:postcode":"55442",
    "addr:street":"Teakwood Ln N Apt G",
    "iso:country":"US",
    "sg:address":"5820 Teakwood Ln N Apt G",
    "sg:city":"Minneapolis",
    "sg:classifiers":[
        {
            "category":"Social Services",
            "subcategory":"Job Training",
            "type":"Services"
        }
    ],
    "sg:phone":"+1 763 577 1084",
    "sg:postcode":"55442",
    "sg:province":"MN",
    "sg:tags":[
        "consultant"
    ],
    "wof:name":"Bacupp For Business",
    "wof:placetype":"venue"
},
  "geometry": {"coordinates":[-93.447165,45.058941],"type":"Point"}
}