{
  "type": "Feature",
  "properties": {
    "addr:full":"1426 Featherstone Rd Hastings MN 55033",
    "addr:housenumber":"1426",
    "addr:postcode":"55033",
    "addr:street":"Featherstone Rd",
    "iso:country":"US",
    "sg:address":"1426 Featherstone Rd",
    "sg:city":"Hastings",
    "sg:classifiers":[
        {
            "category":"Shopping",
            "subcategory":"Florist",
            "type":"Retail Goods"
        }
    ],
    "sg:phone":"+1 651 437 6220",
    "sg:postcode":"55033",
    "sg:province":"MN",
    "wof:name":"Wedding Flowers By Ginny",
    "wof:placetype":"venue"
},
  "geometry": {"coordinates":[-92.88126099999999,44.74581],"type":"Point"}
}