{
  "type": "Feature",
  "properties": {
    "addr:full":"3360 Chelsea Rd W Monticello MN 55362",
    "addr:housenumber":"3360",
    "addr:postcode":"55362",
    "addr:street":"Chelsea Rd W",
    "iso:country":"US",
    "sg:address":"3360 Chelsea Rd W",
    "sg:city":"Monticello",
    "sg:classifiers":[
        {
            "category":"Wholesale",
            "subcategory":"Beer",
            "type":"Manufacturing & Wholesale Goods"
        },
        {
            "category":"Food & Beverages",
            "subcategory":"Liquor & Beverages",
            "type":"Retail Goods"
        }
    ],
    "sg:phone":"+1 763 295 3347",
    "sg:postcode":"55362",
    "sg:province":"MN",
    "sg:tags":[
        "ale",
        "ale-wholesale",
        "manufacturer"
    ],
    "wof:name":"Dahlheimer Distributing Co Inc",
    "wof:placetype":"venue"
},
  "geometry": {"coordinates":[-93.80155600000001,45.294521],"type":"Point"}
}