{
  "type": "Feature",
  "properties": {
    "iso:country":"US",
    "sg:address":"21931 Flagstaff Ave",
    "sg:city":"Farmington",
    "sg:classifiers":[
        {
            "category":"Utilities",
            "subcategory":"Fuel Oil & Lpg",
            "type":"Services"
        }
    ],
    "sg:phone":"+1 651 463 8127",
    "sg:postcode":"55024",
    "sg:province":"MN",
    "sg:tags":[
        "dealer"
    ],
    "wof:name":"Farmington-Lakeville Oil Co",
    "wof:placetype":"venue"
},
  "geometry": {"coordinates":[-93.197385,44.641272],"type":"Point"}
}