{
  "type": "Feature",
  "properties": {
    "addr:full":"1835 W Co Rd C Saint Paul MN 55113",
    "addr:housenumber":"1835",
    "addr:postcode":"55113",
    "addr:street":"W Co Rd C",
    "iso:country":"US",
    "sg:address":"1835 W Co Rd C",
    "sg:city":"Saint Paul",
    "sg:classifiers":[
        {
            "category":"Health Services",
            "subcategory":"Clinic",
            "type":"Services"
        }
    ],
    "sg:phone":"+1 651 638 1680",
    "sg:postcode":"55113",
    "sg:province":"MN",
    "sg:tags":[
        "specialty",
        "outpatient"
    ],
    "wof:name":"Allina Mdcl Group Mntl Health",
    "wof:placetype":"venue"
},
  "geometry": {"coordinates":[-93.17938700000001,45.021314],"type":"Point"}
}