{
  "type": "Feature",
  "properties": {
    "addr:full":"4960 Lincoln Dr Edina MN 55436",
    "addr:housenumber":"4960",
    "addr:postcode":"55436",
    "addr:street":"Lincoln Dr",
    "iso:country":"US",
    "sg:address":"4960 Lincoln Dr",
    "sg:city":"Edina",
    "sg:classifiers":[
        {
            "category":"Building & Trades",
            "subcategory":"Construction",
            "type":"Services"
        }
    ],
    "sg:phone":"+1 952 912 9895",
    "sg:postcode":"55436",
    "sg:province":"MN",
    "sg:tags":[
        "home",
        "builder"
    ],
    "sg:website":"www.hansenconstruction.com",
    "wof:name":"Hansen Co",
    "wof:placetype":"venue"
},
  "geometry": {"coordinates":[-93.398819,44.913337],"type":"Point"}
}