{
  "type": "Feature",
  "properties": {
    "iso:country":"US",
    "sg:address":"7795 Upper 145th Ct W",
    "sg:city":"Saint Paul",
    "sg:classifiers":[
        {
            "category":"Social Services",
            "subcategory":"Child Care",
            "type":"Services"
        }
    ],
    "sg:phone":"+1 952 432 5652",
    "sg:postcode":"55124",
    "sg:province":"MN",
    "sg:tags":[
        "daycare",
        "provider"
    ],
    "wof:name":"Dianne J Scribner",
    "wof:placetype":"venue"
},
  "geometry": {"coordinates":[-93.223929,44.738568],"type":"Point"}
}