{
  "type": "Feature",
  "properties": {
    "addr:full":"13194 2nd St NE Spicer MN 56288",
    "addr:housenumber":"13194",
    "addr:postcode":"56288",
    "addr:street":"2Nd St Ne",
    "iso:country":"US",
    "sg:address":"13194 2nd St NE",
    "sg:city":"Spicer",
    "sg:classifiers":[
        {
            "category":"Travel",
            "subcategory":"Hotels & Motels",
            "type":"Entertainment"
        }
    ],
    "sg:phone":"+1 320 354 4272",
    "sg:postcode":"56288",
    "sg:province":"MN",
    "sg:tags":[
        "resort"
    ],
    "wof:name":"Dickersons Lake Florida Resort",
    "wof:placetype":"venue"
},
  "geometry": {"coordinates":[-95.04263400000001,45.255649],"type":"Point"}
}