{
  "type": "Feature",
  "properties": {
    "iso:country":"US",
    "sg:address":"400 Co Rd 37 NW",
    "sg:city":"Maple Lake",
    "sg:classifiers":[
        {
            "category":"Organizations",
            "subcategory":"Religious Organization",
            "type":"Services"
        }
    ],
    "sg:phone":"+1 320 963 3118",
    "sg:postcode":"55358",
    "sg:province":"MN",
    "sg:tags":[
        "church"
    ],
    "wof:name":"Bethlehem United Church-Christ",
    "wof:placetype":"venue"
},
  "geometry": {"coordinates":[-93.99848,45.236316],"type":"Point"}
}