{
  "type": "Feature",
  "properties": {
    "iso:country":"US",
    "sg:address":"820 Aspen Cir",
    "sg:city":"St Paul",
    "sg:classifiers":[
        {
            "category":"Health Services",
            "subcategory":"Clinic",
            "type":"Services"
        }
    ],
    "sg:phone":"+1 651 494 9058",
    "sg:postcode":"55109",
    "sg:province":"MN",
    "sg:tags":[
        "home"
    ],
    "wof:name":"Big Brother Home Health C",
    "wof:placetype":"venue"
},
  "geometry": {"coordinates":[-93.063063,45.034979],"type":"Point"}
}