{
  "type": "Feature",
  "properties": {
    "iso:country":"US",
    "sg:address":"4940 183rd Ln NW",
    "sg:city":"Anoka",
    "sg:classifiers":[
        {
            "category":"Retail",
            "subcategory":"Repair Shop",
            "type":"Services"
        }
    ],
    "sg:phone":"+1 763 753 4660",
    "sg:postcode":"55303",
    "sg:province":"MN",
    "wof:name":"Custom Gunsmithing",
    "wof:placetype":"venue"
},
  "geometry": {"coordinates":[-93.392363,45.303313],"type":"Point"}
}