{
  "type": "Feature",
  "properties": {
    "iso:country":"US",
    "sg:address":"251 Main St N",
    "sg:city":"Chatfield",
    "sg:classifiers":[
        {
            "category":"Food & Beverages",
            "subcategory":"Liquor & Beverages",
            "type":"Retail Goods"
        }
    ],
    "sg:phone":"+1 507 867 1640",
    "sg:postcode":"55923",
    "sg:province":"MN",
    "wof:name":"Countyline Wine & Liquor",
    "wof:placetype":"venue"
},
  "geometry": {"coordinates":[-92.192578,43.848629],"type":"Point"}
}