{
  "type": "Feature",
  "properties": {
    "addr:full":"25 University Ave SE Minneapolis MN 55414",
    "addr:housenumber":"25",
    "addr:postcode":"55414",
    "addr:street":"University Ave Se",
    "iso:country":"US",
    "sg:address":"25 University Ave SE",
    "sg:city":"Minneapolis",
    "sg:classifiers":[
        {
            "category":"Retail",
            "subcategory":"Laundry & Dry Cleaning",
            "type":"Services"
        },
        {
            "category":"Building & Trades",
            "subcategory":"Cleaning & Sanitation",
            "type":"Services"
        }
    ],
    "sg:phone":"+1 612 378 0922",
    "sg:postcode":"55414",
    "sg:province":"MN",
    "sg:tags":[
        "cleaner",
        "upholstery",
        "rug",
        "carpet"
    ],
    "wof:name":"Gregory's Carpet & Upholstery",
    "wof:placetype":"venue"
},
  "geometry": {"coordinates":[-93.25520299999999,44.987019],"type":"Point"}
}