{
  "type": "Feature",
  "properties": {
    "iso:country":"US",
    "sg:address":"1531 17th Ave E",
    "sg:city":"Shakopee",
    "sg:classifiers":[
        {
            "category":"Shopping",
            "subcategory":"Mobile Phones",
            "type":"Retail Goods"
        }
    ],
    "sg:phone":"+1 952 445 7711",
    "sg:postcode":"55379",
    "sg:province":"MN",
    "sg:website":"www.verizonwireless.com",
    "wof:name":"Verizon Wireless",
    "wof:placetype":"venue"
},
  "geometry": {"coordinates":[-93.504755,44.773927],"type":"Point"}
}