{
  "type": "Feature",
  "properties": {
    "addr:full":"1265 64th St NE Longville MN 56655",
    "addr:housenumber":"1265",
    "addr:postcode":"56655",
    "addr:street":"64Th St Ne",
    "iso:country":"US",
    "sg:address":"1265 64th St NE",
    "sg:city":"Longville",
    "sg:classifiers":[
        {
            "category":"Building & Trades",
            "subcategory":"Landscaping Services",
            "type":"Services"
        }
    ],
    "sg:phone":"+1 218 363 2260",
    "sg:postcode":"56655",
    "sg:province":"MN",
    "sg:tags":[
        "tree"
    ],
    "wof:name":"Beaver Tree Svc",
    "wof:placetype":"venue"
},
  "geometry": {"coordinates":[-94.22242900000001,47.037515],"type":"Point"}
}