{
  "type": "Feature",
  "properties": {
    "iso:country":"US",
    "sg:address":"5315 Knox Ave S",
    "sg:city":"Minneapolis",
    "sg:classifiers":[
        {
            "category":"Communications",
            "type":"Services"
        }
    ],
    "sg:phone":"+1 612 928 0202",
    "sg:postcode":"55419",
    "sg:province":"MN",
    "wof:name":"Mardi Larson Communications",
    "wof:placetype":"venue"
},
  "geometry": {"coordinates":[-93.30220199999999,44.905371],"type":"Point"}
}