{
  "type": "Feature",
  "properties": {
    "iso:country":"US",
    "sg:address":"5340 Lyndale Ave S",
    "sg:city":"Minneapolis",
    "sg:classifiers":[
        {
            "category":"Wholesale",
            "subcategory":"Hardware",
            "type":"Manufacturing & Wholesale Goods"
        },
        {
            "category":"Home & Garden",
            "subcategory":"Garden Supply",
            "type":"Retail Goods"
        },
        {
            "category":"Retail",
            "subcategory":"Repair Shop",
            "type":"Services"
        }
    ],
    "sg:phone":"+1 612 827 5525",
    "sg:postcode":"55419",
    "sg:province":"MN",
    "sg:tags":[
        "renting",
        "lawn",
        "outdoor",
        "power",
        "landscaping",
        "equipment-sales",
        "equipment",
        "saw"
    ],
    "sg:website":"http://www.stihlusa.com/",
    "wof:name":"DIAMOND LAKE EQUIPMENT",
    "wof:placetype":"venue"
},
  "geometry": {"coordinates":[-93.288358,44.906057],"type":"Point"}
}