{
  "type": "Feature",
  "properties": {
    "iso:country":"US",
    "sg:address":"2308 S Broadway St",
    "sg:city":"Alexandria",
    "sg:classifiers":[
        {
            "category":"Government",
            "subcategory":"Office",
            "type":"Public Place"
        }
    ],
    "sg:phone":"+1 320 763 6351",
    "sg:postcode":"56308",
    "sg:province":"MN",
    "sg:tags":[
        "armed",
        "force",
        "recruiting"
    ],
    "wof:name":"US Marine Corps Recruiting",
    "wof:placetype":"venue"
},
  "geometry": {"coordinates":[-95.377971,45.865669],"type":"Point"}
}