{
  "type": "Feature",
  "properties": {
    "iso:country":"US",
    "sg:address":"7424 Cardinal Rd",
    "sg:city":"Swanville",
    "sg:phone":"+1 320 573 2330",
    "sg:postcode":"56382",
    "sg:province":"MN",
    "sg:tags":[
        "farm",
        "corn",
        "soybean"
    ],
    "wof:name":"Robert Brezinka",
    "wof:placetype":"venue"
},
  "geometry": {"coordinates":[-94.53185499999999,45.883364],"type":"Point"}
}