{
  "type": "Feature",
  "properties": {
    "addr:full":"21598 478th Ave Lake Crystal MN 56055",
    "addr:housenumber":"21598",
    "addr:postcode":"56055",
    "addr:street":"478Th Ave",
    "iso:country":"US",
    "sg:address":"21598 478th Ave",
    "sg:city":"Lake Crystal",
    "sg:classifiers":[
        {
            "category":"Retail",
            "subcategory":"Repair Shop",
            "type":"Services"
        }
    ],
    "sg:phone":"+1 507 947 3753",
    "sg:postcode":"56055",
    "sg:province":"MN",
    "sg:tags":[
        "taxidermist"
    ],
    "wof:name":"Wallhangers Taxidermy",
    "wof:placetype":"venue"
},
  "geometry": {"coordinates":[-94.34951100000001,44.16319],"type":"Point"}
}