{
  "type": "Feature",
  "properties": {
    "addr:full":"199 3rd St Excelsior MN 55331",
    "addr:housenumber":"199",
    "addr:postcode":"55331",
    "addr:street":"3Rd St",
    "iso:country":"US",
    "sg:address":"199 3rd St",
    "sg:city":"Excelsior",
    "sg:classifiers":[
        {
            "category":"Professional",
            "type":"Services"
        }
    ],
    "sg:phone":"+1 952 474 8707",
    "sg:postcode":"55331",
    "sg:province":"MN",
    "wof:name":"Kathy Denman",
    "wof:placetype":"venue"
},
  "geometry": {"coordinates":[-93.572273,44.904517],"type":"Point"}
}