{
  "type": "Feature",
  "properties": {
    "iso:country":"US",
    "sg:address":"628 Roosevelt Rd",
    "sg:city":"St Cloud",
    "sg:classifiers":[
        {
            "category":"Education",
            "subcategory":"School",
            "type":"Public Place"
        }
    ],
    "sg:phone":"+1 320 253 9333",
    "sg:postcode":"56301",
    "sg:province":"MN",
    "sg:tags":[
        "district"
    ],
    "sg:website":"www.isd742.org",
    "wof:name":"St Cloud Area School Dist 742",
    "wof:placetype":"venue"
},
  "geometry": {"coordinates":[-94.18527899999999,45.54805],"type":"Point"}
}