{
  "type": "Feature",
  "properties": {
    "addr:full":"1881 E Chub Lake Rd Carlton MN 55718",
    "addr:housenumber":"1881",
    "addr:postcode":"55718",
    "addr:street":"E Chub Lake Rd",
    "iso:country":"US",
    "sg:address":"1881 E Chub Lake Rd",
    "sg:city":"Carlton",
    "sg:classifiers":[
        {
            "category":"Building & Trades",
            "subcategory":"Landscaping Services",
            "type":"Services"
        }
    ],
    "sg:phone":"+1 218 384 3121",
    "sg:postcode":"55718",
    "sg:province":"MN",
    "sg:tags":[
        "tree"
    ],
    "wof:name":"R H Grover Tree Svc",
    "wof:placetype":"venue"
},
  "geometry": {"coordinates":[-92.43348400000001,46.637695],"type":"Point"}
}