{
  "type": "Feature",
  "properties": {
    "addr:full":"5901 W 98th St Bloomington MN 55438",
    "addr:housenumber":"5901",
    "addr:postcode":"55438",
    "addr:street":"W 98Th St",
    "iso:country":"US",
    "sg:address":"5901 W 98th St",
    "sg:city":"Bloomington",
    "sg:classifiers":[
        {
            "category":"Recreation",
            "type":"Entertainment"
        }
    ],
    "sg:phone":"+1 952 941 8722",
    "sg:postcode":"55438",
    "sg:province":"MN",
    "sg:tags":[
        "martial",
        "arts",
        "instruction"
    ],
    "wof:name":"National Karate Schools",
    "wof:placetype":"venue"
},
  "geometry": {"coordinates":[-93.360474,44.827335],"type":"Point"}
}