{
  "type": "Feature",
  "properties": {
    "iso:country":"US",
    "sg:address":"1113 E Hennepin Ave",
    "sg:city":"Minneapolis",
    "sg:classifiers":[
        {
            "category":"Wholesale",
            "subcategory":"Apparel",
            "type":"Manufacturing & Wholesale Goods"
        }
    ],
    "sg:phone":"+1 612 331 8493",
    "sg:postcode":"55414",
    "sg:province":"MN",
    "sg:tags":[
        "shoe",
        "store"
    ],
    "wof:name":"Minnetonka Moccasin",
    "wof:placetype":"venue"
},
  "geometry": {"coordinates":[-93.23580200000001,44.991699],"type":"Point"}
}