{
  "type": "Feature",
  "properties": {
    "addr:full":"5801 Covington Ter Minnetonka MN 55345",
    "addr:housenumber":"5801",
    "addr:postcode":"55345",
    "addr:street":"Covington Ter",
    "iso:country":"US",
    "sg:address":"5801 Covington Ter",
    "sg:city":"Minnetonka",
    "sg:classifiers":[
        {
            "category":"Manufacturing",
            "subcategory":"Glass & Minerals",
            "type":"Manufacturing & Wholesale Goods"
        }
    ],
    "sg:phone":"+1 952 937 6125",
    "sg:postcode":"55345",
    "sg:province":"MN",
    "sg:tags":[
        "therapeutic",
        "mfg",
        "leak",
        "hand",
        "fuel",
        "kit",
        "cream"
    ],
    "wof:name":"Sowden Cos Inc",
    "wof:placetype":"venue"
},
  "geometry": {"coordinates":[-93.51009500000001,44.894338],"type":"Point"}
}