{
  "type": "Feature",
  "properties": {
    "addr:full":"51786 301st St Deer Creek MN 56527",
    "addr:housenumber":"51786",
    "addr:postcode":"56527",
    "addr:street":"301St St",
    "iso:country":"US",
    "sg:address":"51786 301st St",
    "sg:city":"Deer Creek",
    "sg:classifiers":[
        {
            "category":"Building & Trades",
            "subcategory":"Construction",
            "type":"Services"
        }
    ],
    "sg:phone":"+1 218 462 2330",
    "sg:postcode":"56527",
    "sg:province":"MN",
    "sg:tags":[
        "resurfacing",
        "laying",
        "refinishing",
        "floor"
    ],
    "wof:name":"Skoogs Hardwood Floors Inc",
    "wof:placetype":"venue"
},
  "geometry": {"coordinates":[-95.407546,46.400219],"type":"Point"}
}