{
  "type": "Feature",
  "properties": {
    "addr:full":"51808 90th St Bricelyn MN 56014",
    "addr:housenumber":"51808",
    "addr:postcode":"56014",
    "addr:street":"90Th St",
    "iso:country":"US",
    "sg:address":"51808 90th St",
    "sg:city":"Bricelyn",
    "sg:classifiers":[
        {
            "category":"Farming",
            "subcategory":"Livestock Farm",
            "type":"Manufacturing & Wholesale Goods"
        },
        {
            "category":"Farming",
            "subcategory":"Farm",
            "type":"Manufacturing & Wholesale Goods"
        }
    ],
    "sg:phone":"+1 507 653 4273",
    "sg:postcode":"56014",
    "sg:province":"MN",
    "sg:website":"http://www.dantimm.com",
    "wof:name":"Daniel Timm",
    "wof:placetype":"venue"
},
  "geometry": {"coordinates":[-93.832745,43.615871],"type":"Point"}
}