{
  "type": "Feature",
  "properties": {
    "addr:full":"21276 Monterey Ave Lakeville MN 55044",
    "addr:housenumber":"21276",
    "addr:postcode":"55044",
    "addr:street":"Monterey Ave",
    "iso:country":"US",
    "sg:address":"21276 Monterey Ave",
    "sg:city":"Lakeville",
    "sg:classifiers":[
        {
            "category":"Professional",
            "subcategory":"Computer Services",
            "type":"Services"
        },
        {
            "category":"Shopping",
            "subcategory":"Computers & Home Electronics",
            "type":"Retail Goods"
        }
    ],
    "sg:phone":"+1 952 461 3139",
    "sg:postcode":"55044",
    "sg:province":"MN",
    "sg:tags":[
        "prepackaged",
        "software"
    ],
    "wof:name":"Hunters Moon Software LTD",
    "wof:placetype":"venue"
},
  "geometry": {"coordinates":[-93.339465,44.64254],"type":"Point"}
}