{
  "type": "Feature",
  "properties": {
    "addr:full":"956 W 150th St Shakopee MN 55379",
    "addr:housenumber":"956",
    "addr:postcode":"55379",
    "addr:street":"W 150Th St",
    "iso:country":"US",
    "sg:address":"956 W 150th St",
    "sg:city":"Shakopee",
    "sg:classifiers":[
        {
            "category":"Government",
            "subcategory":"Office",
            "type":"Public Place"
        }
    ],
    "sg:phone":"+1 952 445 1718",
    "sg:postcode":"55379",
    "sg:province":"MN",
    "sg:tags":[
        "executive"
    ],
    "wof:name":"Township of Louisville",
    "wof:placetype":"venue"
},
  "geometry": {"coordinates":[-93.538443,44.732895],"type":"Point"}
}