{
  "type": "Feature",
  "properties": {
    "addr:full":"40345 Silent Acres Dr Dent MN 56528",
    "addr:housenumber":"40345",
    "addr:postcode":"56528",
    "addr:street":"Silent Acres Dr Dent",
    "iso:country":"US",
    "sg:address":"40345 Silent Acres Dr",
    "sg:city":"Dent",
    "sg:classifiers":[
        {
            "category":"Professional",
            "type":"Services"
        }
    ],
    "sg:phone":"+1 218 758 3346",
    "sg:postcode":"56528",
    "sg:province":"MN",
    "sg:tags":[
        "establishment"
    ],
    "wof:name":"Morris & Morris",
    "wof:placetype":"venue"
},
  "geometry": {"coordinates":[-95.89425199999999,46.54456],"type":"Point"}
}