{
  "type": "Feature",
  "properties": {
    "iso:country":"US",
    "sg:address":"508 State St NE",
    "sg:city":"Glyndon",
    "sg:classifiers":[
        {
            "category":"Government",
            "subcategory":"Fire Station",
            "type":"Public Place"
        }
    ],
    "sg:phone":"+1 218 498 2157",
    "sg:postcode":"56547",
    "sg:province":"MN",
    "sg:tags":[
        "dept",
        "v"
    ],
    "wof:name":"Glyndon Volunteer Fire Dept",
    "wof:placetype":"venue"
},
  "geometry": {"coordinates":[-96.571701,46.877273],"type":"Point"}
}