{
  "type": "Feature",
  "properties": {
    "addr:full":"1686 Cliff Rd E Burnsville MN 55337",
    "addr:housenumber":"1686",
    "addr:postcode":"55337",
    "addr:street":"Cliff Rd E",
    "iso:country":"US",
    "sg:address":"1686 Cliff Rd E",
    "sg:city":"Burnsville",
    "sg:classifiers":[
        {
            "category":"Professional",
            "type":"Services"
        }
    ],
    "sg:phone":"+1 952 746 7867",
    "sg:postcode":"55337",
    "sg:province":"MN",
    "sg:tags":[
        "publication",
        "editorial"
    ],
    "wof:name":"Red Line Editorial",
    "wof:placetype":"venue"
},
  "geometry": {"coordinates":[-93.24997999999999,44.79052],"type":"Point"}
}