{
  "type": "Feature",
  "properties": {
    "iso:country":"US",
    "sg:address":"13211 Ridgemount Ave W",
    "sg:city":"Hopkins",
    "sg:classifiers":[
        {
            "category":"Professional",
            "subcategory":"Management & Consulting",
            "type":"Services"
        }
    ],
    "sg:phone":"+1 612 703 7608",
    "sg:postcode":"55305",
    "sg:province":"MN",
    "sg:tags":[
        "business"
    ],
    "wof:name":"J L Banks Consulting Inc",
    "wof:placetype":"venue"
},
  "geometry": {"coordinates":[-93.446889,44.978635],"type":"Point"}
}