{
  "type": "Feature",
  "properties": {
    "addr:full":"936 64th St SW Pequot Lakes MN 56472",
    "addr:housenumber":"936",
    "addr:postcode":"56472",
    "addr:street":"64Th St Sw",
    "iso:country":"US",
    "sg:address":"936 64th St SW",
    "sg:city":"Pequot Lakes",
    "sg:classifiers":[
        {
            "category":"Retail",
            "subcategory":"Repair Shop",
            "type":"Services"
        }
    ],
    "sg:phone":"+1 218 568 5149",
    "sg:postcode":"56472",
    "sg:province":"MN",
    "sg:tags":[
        "engine"
    ],
    "wof:name":"Pete's Small Engine Repair",
    "wof:placetype":"venue"
},
  "geometry": {"coordinates":[-94.340076,46.573186],"type":"Point"}
}