{
  "type": "Feature",
  "properties": {
    "addr:full":"220 1st St NW Cass Lake MN 56633",
    "addr:housenumber":"220",
    "addr:postcode":"56633",
    "addr:street":"1St St Nw Cass",
    "iso:country":"US",
    "sg:address":"220 1st St NW",
    "sg:city":"Cass Lake",
    "sg:classifiers":[
        {
            "category":"Health Services",
            "subcategory":"Clinic",
            "type":"Services"
        }
    ],
    "sg:phone":"+1 218 335 2081",
    "sg:postcode":"56633",
    "sg:province":"MN",
    "sg:tags":[
        "organization",
        "maintenance"
    ],
    "wof:name":"Diabetes Fitness Ctr",
    "wof:placetype":"venue"
},
  "geometry": {"coordinates":[-94.60728899999999,47.378106],"type":"Point"}
}