{
  "type": "Feature",
  "properties": {
    "addr:full":"921 Hill Rd Willmar MN 56201",
    "addr:housenumber":"921",
    "addr:postcode":"56201",
    "addr:street":"Hill Rd",
    "iso:country":"US",
    "sg:address":"921 Hill Rd",
    "sg:city":"Willmar",
    "sg:classifiers":[
        {
            "category":"Building & Trades",
            "subcategory":"Construction",
            "type":"Services"
        },
        {
            "category":"Home & Garden",
            "subcategory":"Furniture",
            "type":"Retail Goods"
        }
    ],
    "sg:phone":"+1 320 212 7474",
    "sg:postcode":"56201",
    "sg:province":"MN",
    "sg:tags":[
        "maker",
        "cabinet"
    ],
    "wof:name":"Zeug Craft Cabinets",
    "wof:placetype":"venue"
},
  "geometry": {"coordinates":[-95.055386,45.113029],"type":"Point"}
}