{
  "type": "Feature",
  "properties": {
    "addr:full":"12521 290th Ave Waseca MN 56093",
    "addr:housenumber":"12521",
    "addr:postcode":"56093",
    "addr:street":"290Th Ave",
    "iso:country":"US",
    "sg:address":"12521 290th Ave",
    "sg:city":"Waseca",
    "sg:classifiers":[
        {
            "category":"Manufacturing",
            "subcategory":"Buildings",
            "type":"Manufacturing & Wholesale Goods"
        },
        {
            "category":"Building & Trades",
            "subcategory":"Construction",
            "type":"Services"
        }
    ],
    "sg:phone":"+1 507 835 7350",
    "sg:postcode":"56093",
    "sg:province":"MN",
    "sg:tags":[
        "home",
        "builder",
        "contractor"
    ],
    "wof:name":"Rob Ebnet Construction",
    "wof:placetype":"venue"
},
  "geometry": {"coordinates":[-93.515108,43.978655],"type":"Point"}
}