{
  "type": "Feature",
  "properties": {
    "addr:full":"3065 Norway Cir S Cambridge MN 55008",
    "addr:postcode":"3065;55008",
    "addr:street":"Cir S",
    "iso:country":"US",
    "sg:address":"3065 Norway Cir S",
    "sg:city":"Cambridge",
    "sg:classifiers":[
        {
            "category":"Real Estate",
            "subcategory":"Developer",
            "type":"Services"
        }
    ],
    "sg:phone":"+1 763 689 4194",
    "sg:postcode":"55008",
    "sg:province":"MN",
    "wof:name":"Al Torkelson Development",
    "wof:placetype":"venue"
},
  "geometry": {"coordinates":[-93.243398,45.54464],"type":"Point"}
}