{
  "type": "Feature",
  "properties": {
    "addr:full":"5023 Excelsior Blvd St Louis Park MN 55416",
    "addr:housenumber":"5023",
    "addr:postcode":"55416",
    "addr:street":"Excelsior Blvd",
    "iso:country":"US",
    "sg:address":"5023 Excelsior Blvd",
    "sg:city":"St Louis Park",
    "sg:classifiers":[
        {
            "category":"Health Services",
            "subcategory":"Doctor",
            "type":"Services"
        }
    ],
    "sg:phone":"+1 952 920 8860",
    "sg:postcode":"55416",
    "sg:province":"MN",
    "sg:tags":[
        "medical",
        "imaging"
    ],
    "wof:name":"Lifescan Stand Up Open Mri",
    "wof:placetype":"venue"
},
  "geometry": {"coordinates":[-93.345506,44.931654],"type":"Point"}
}