{
  "type": "Feature",
  "properties": {
    "addr:full":"3420 150th St W Rosemount MN 55068",
    "addr:housenumber":"3420",
    "addr:postcode":"55068",
    "addr:street":"150Th St W",
    "iso:country":"US",
    "sg:address":"3420 150th St W",
    "sg:city":"Rosemount",
    "sg:classifiers":[
        {
            "category":"Insurance",
            "subcategory":"Insurance Agent",
            "type":"Services"
        }
    ],
    "sg:phone":"+1 651 423 1300",
    "sg:postcode":"55068",
    "sg:province":"MN",
    "wof:name":"Help U Sell American Family",
    "wof:placetype":"venue"
},
  "geometry": {"coordinates":[-93.13490400000001,44.731688],"type":"Point"}
}