{
  "type": "Feature",
  "properties": {
    "addr:full":"420 N Munsterman St Appleton MN 56208",
    "addr:housenumber":"420",
    "addr:postcode":"56208",
    "addr:street":"N Munsterman St",
    "iso:country":"US",
    "sg:address":"420 N Munsterman St",
    "sg:city":"Appleton",
    "sg:classifiers":[
        {
            "category":"Home & Garden",
            "subcategory":"Garden Supply",
            "type":"Retail Goods"
        }
    ],
    "sg:phone":"+1 320 289 2663",
    "sg:postcode":"56208",
    "sg:province":"MN",
    "sg:tags":[
        "lawn",
        "mower"
    ],
    "wof:name":"Boettcher Service",
    "wof:placetype":"venue"
},
  "geometry": {"coordinates":[-96.020956,45.20372],"type":"Point"}
}