{
  "type": "Feature",
  "properties": {
    "iso:country":"US",
    "sg:address":"1530 London Rd",
    "sg:city":"Duluth",
    "sg:classifiers":[
        {
            "category":"Food & Beverages",
            "subcategory":"Groceries & Convenience Stores",
            "type":"Retail Goods"
        },
        {
            "category":"Retail",
            "subcategory":"Car Wash",
            "type":"Services"
        }
    ],
    "sg:phone":"+1 218 728 4201",
    "sg:postcode":"55812",
    "sg:province":"MN",
    "sg:tags":[
        "carwash",
        "station",
        "gasoline"
    ],
    "wof:name":"London Rd Car Wash & Lube Ctr",
    "wof:placetype":"venue"
},
  "geometry": {"coordinates":[-92.076746,46.800418],"type":"Point"}
}