{
  "type": "Feature",
  "properties": {
    "addr:full":"20096 Co Rd 4 Spring Grove MN 55974",
    "addr:housenumber":"20096",
    "addr:postcode":"55974",
    "addr:street":"Co Rd 4",
    "iso:country":"US",
    "sg:address":"20096 Co Rd 4",
    "sg:city":"Spring Grove",
    "sg:classifiers":[
        {
            "category":"Government",
            "subcategory":"Office",
            "type":"Public Place"
        }
    ],
    "sg:phone":"+1 507 498 3839",
    "sg:postcode":"55974",
    "sg:province":"MN",
    "sg:tags":[
        "city"
    ],
    "wof:name":"Spring Grove Town Hall",
    "wof:placetype":"venue"
},
  "geometry": {"coordinates":[-91.65092300000001,43.55702],"type":"Point"}
}