{
  "type": "Feature",
  "properties": {
    "iso:country":"US",
    "sg:address":"6600 France Ave S Ste 605",
    "sg:city":"Minneapolis",
    "sg:classifiers":[
        {
            "category":"Health Services",
            "subcategory":"Doctor",
            "type":"Services"
        },
        {
            "category":"Health Services",
            "subcategory":"Clinic",
            "type":"Services"
        },
        {
            "category":"Health Services",
            "subcategory":"Health Practitioner",
            "type":"Services"
        },
        {
            "category":"Community Center",
            "type":"Public Place"
        }
    ],
    "sg:phone":"+1 952 920 4333",
    "sg:postcode":"55435",
    "sg:province":"MN",
    "sg:tags":[
        "physician",
        "pediatrics-orthopedic",
        "medical",
        "surgeons",
        "therapist",
        "therapy",
        "orthopedics",
        "surgery",
        "surgeon",
        "physical"
    ],
    "sg:website":"http://www.orthorehabpt.com",
    "wof:name":"Orthopedic Specialists",
    "wof:placetype":"venue"
},
  "geometry": {"coordinates":[-93.329048,44.88282],"type":"Point"}
}