{
  "type": "Feature",
  "properties": {
    "addr:full":"3812 15th Ave S Minneapolis MN 55407",
    "addr:housenumber":"3812",
    "addr:postcode":"55407",
    "addr:street":"15Th Ave S",
    "iso:country":"US",
    "sg:address":"3812 15th Ave S",
    "sg:city":"Minneapolis",
    "sg:classifiers":[
        {
            "category":"Real Estate",
            "subcategory":"Architect",
            "type":"Services"
        }
    ],
    "sg:phone":"+1 612 827 8988",
    "sg:postcode":"55407",
    "sg:province":"MN",
    "wof:name":"Mooney Steven J Architecture",
    "wof:placetype":"venue"
},
  "geometry": {"coordinates":[-93.25382999999999,44.933899],"type":"Point"}
}