{
  "type": "Feature",
  "properties": {
    "iso:country":"US",
    "sg:address":"490 Cedar Ave S",
    "sg:city":"Minneapolis",
    "sg:classifiers":[
        {
            "category":"Health Services",
            "subcategory":"Clinic",
            "type":"Services"
        }
    ],
    "sg:phone":"+1 612 455 0299",
    "sg:postcode":"55454",
    "sg:province":"MN",
    "wof:name":"Dar Al Hijrah Health & Scrnng",
    "wof:placetype":"venue"
},
  "geometry": {"coordinates":[-93.247316,44.968701],"type":"Point"}
}