{
  "type": "Feature",
  "properties": {
    "iso:country":"US",
    "sg:address":"2025 W Superior St",
    "sg:city":"Duluth",
    "sg:classifiers":[
        {
            "category":"Home & Garden",
            "subcategory":"Furniture",
            "type":"Retail Goods"
        }
    ],
    "sg:phone":"+1 218 722 5755",
    "sg:postcode":"55806",
    "sg:province":"MN",
    "wof:name":"Arrowhead Furniture",
    "wof:placetype":"venue"
},
  "geometry": {"coordinates":[-92.12403500000001,46.767229],"type":"Point"}
}