{
  "type": "Feature",
  "properties": {
    "iso:country":"US",
    "sg:address":"144 Washington St",
    "sg:city":"Rollingstone",
    "sg:classifiers":[
        {
            "category":"Manufacturing",
            "subcategory":"Apparel",
            "type":"Manufacturing & Wholesale Goods"
        }
    ],
    "sg:phone":"+1 507 689 2113",
    "sg:postcode":"55969",
    "sg:province":"MN",
    "sg:tags":[
        "mfg",
        "house",
        "supply",
        "specialty",
        "dairy",
        "rental"
    ],
    "wof:name":"Stiehm Co",
    "wof:placetype":"venue"
},
  "geometry": {"coordinates":[-91.817412,44.098529],"type":"Point"}
}