{
  "type": "Feature",
  "properties": {
    "iso:country":"US",
    "sg:address":"860 S Hall Ave",
    "sg:city":"Saint Paul",
    "sg:classifiers":[
        {
            "category":"Social Services",
            "subcategory":"Child Care",
            "type":"Services"
        }
    ],
    "sg:phone":"+1 651 291 8793",
    "sg:postcode":"55107",
    "sg:province":"MN",
    "sg:tags":[
        "day",
        "provider"
    ],
    "wof:name":"Alices Daycare",
    "wof:placetype":"venue"
},
  "geometry": {"coordinates":[-93.086473,44.919872],"type":"Point"}
}