{
  "type": "Feature",
  "properties": {
    "iso:country":"US",
    "sg:address":"4514 Rice Lake Rd",
    "sg:city":"Duluth",
    "sg:classifiers":[
        {
            "category":"Manufacturing",
            "subcategory":"Signs",
            "type":"Manufacturing & Wholesale Goods"
        }
    ],
    "sg:phone":"+1 218 722 3995",
    "sg:postcode":"55803",
    "sg:province":"MN",
    "sg:tags":[
        "mfg"
    ],
    "wof:name":"Airport Signs & Graphics",
    "wof:placetype":"venue"
},
  "geometry": {"coordinates":[-92.15321400000001,46.836819],"type":"Point"}
}