{
  "type": "Feature",
  "properties": {
    "addr:full":"10616 Flora St NW Minneapolis MN 55433",
    "addr:housenumber":"10616",
    "addr:postcode":"55433",
    "addr:street":"Flora St Nw",
    "iso:country":"US",
    "sg:address":"10616 Flora St NW",
    "sg:city":"Minneapolis",
    "sg:classifiers":[
        {
            "category":"Social Services",
            "subcategory":"Child Care",
            "type":"Services"
        }
    ],
    "sg:phone":"+1 763 421 4139",
    "sg:postcode":"55433",
    "sg:province":"MN",
    "sg:tags":[
        "daycare",
        "provider"
    ],
    "wof:name":"Rebecca Studniski",
    "wof:placetype":"venue"
},
  "geometry": {"coordinates":[-93.341489,45.164271],"type":"Point"}
}