{
  "type": "Feature",
  "properties": {
    "addr:full":"14334 Sherwood Trl Zumbrota MN 55992",
    "addr:housenumber":"14334",
    "addr:postcode":"55992",
    "addr:street":"Sherwood Trl",
    "iso:country":"US",
    "sg:address":"14334 Sherwood Trl",
    "sg:city":"Zumbrota",
    "sg:classifiers":[
        {
            "category":"Travel",
            "subcategory":"Campground",
            "type":"Entertainment"
        }
    ],
    "sg:phone":"+1 507 732 5100",
    "sg:postcode":"55992",
    "sg:province":"MN",
    "sg:tags":[
        "camp"
    ],
    "wof:name":"Shades Of Sherwood",
    "wof:placetype":"venue"
},
  "geometry": {"coordinates":[-92.73545,44.318963],"type":"Point"}
}