{
  "type": "Feature",
  "properties": {
    "addr:full":"2514 5th Ave NW Rochester MN 55901",
    "addr:housenumber":"2514",
    "addr:postcode":"55901",
    "addr:street":"5Th Ave Nw",
    "iso:country":"US",
    "sg:address":"2514 5th Ave NW",
    "sg:city":"Rochester",
    "sg:phone":"+1 507 288 8839",
    "sg:postcode":"55901",
    "sg:province":"MN",
    "sg:tags":[
        "farm",
        "corn"
    ],
    "wof:name":"Harold De Witz",
    "wof:placetype":"venue"
},
  "geometry": {"coordinates":[-92.47067199999999,44.050453],"type":"Point"}
}