{
  "type": "Feature",
  "properties": {
    "addr:full":"1853 18th St NW Rochester MN 55901",
    "addr:housenumber":"1853",
    "addr:postcode":"55901",
    "addr:street":"18Th St Nw",
    "iso:country":"US",
    "sg:address":"1853 18th St NW",
    "sg:city":"Rochester",
    "sg:classifiers":[
        {
            "category":"Wholesale",
            "subcategory":"Machinery & Supplies",
            "type":"Manufacturing & Wholesale Goods"
        }
    ],
    "sg:phone":"+1 507 536 9270",
    "sg:postcode":"55901",
    "sg:province":"MN",
    "sg:tags":[
        "detergent",
        "soap"
    ],
    "wof:name":"Soap Bar",
    "wof:placetype":"venue"
},
  "geometry": {"coordinates":[-92.491147,44.041901],"type":"Point"}
}