{
  "type": "Feature",
  "properties": {
    "iso:country":"US",
    "sg:address":"700 State St",
    "sg:city":"St Paul",
    "sg:classifiers":[
        {
            "category":"Government",
            "subcategory":"Office",
            "type":"Public Place"
        }
    ],
    "sg:phone":"+1 651 296 2868",
    "sg:postcode":"55107",
    "sg:province":"MN",
    "wof:name":"Minnesota Revisor Of Statutes",
    "wof:placetype":"venue"
},
  "geometry": {"coordinates":[-93.080671,44.923977],"type":"Point"}
}