{
  "type": "Feature",
  "properties": {
    "addr:full":"1029 State Hwy 95 Cambridge MN 55008",
    "addr:housenumber":"1029",
    "addr:postcode":"55008",
    "addr:street":"State Hwy 95",
    "iso:country":"US",
    "sg:address":"1029 State Hwy 95",
    "sg:city":"Cambridge",
    "sg:classifiers":[
        {
            "category":"Recreation",
            "type":"Entertainment"
        }
    ],
    "sg:phone":"+1 763 552 5425",
    "sg:postcode":"55008",
    "sg:province":"MN",
    "sg:tags":[
        "martial",
        "arts",
        "instruction"
    ],
    "wof:name":"Professional Karate Studios",
    "wof:placetype":"venue"
},
  "geometry": {"coordinates":[-93.212891,45.572812],"type":"Point"}
}