{
  "type": "Feature",
  "properties": {
    "iso:country":"US",
    "sg:address":"142 8th St",
    "sg:city":"Albany",
    "sg:classifiers":[
        {
            "category":"Communications",
            "type":"Services"
        }
    ],
    "sg:phone":"+1 320 845 6450",
    "sg:postcode":"56307",
    "sg:province":"MN",
    "wof:name":"21st Century Consulting",
    "wof:placetype":"venue"
},
  "geometry": {"coordinates":[-94.57397899999999,45.631086],"type":"Point"}
}