{
  "type": "Feature",
  "properties": {
    "iso:country":"US",
    "sg:address":"3160 Wellner Dr NE",
    "sg:city":"Rochester",
    "sg:classifiers":[
        {
            "category":"Sports & Exercise",
            "subcategory":"Gym",
            "type":"Entertainment"
        }
    ],
    "sg:phone":"+1 507 280 8095",
    "sg:postcode":"55906",
    "sg:province":"MN",
    "sg:tags":[
        "club",
        "health",
        "studio",
        "gymnasium"
    ],
    "wof:name":"Curves For Women",
    "wof:placetype":"venue"
},
  "geometry": {"coordinates":[-92.452505,44.057018],"type":"Point"}
}