{
  "type": "Feature",
  "properties": {
    "addr:full":"218 Main St N Stillwater MN 55082",
    "addr:housenumber":"218",
    "addr:postcode":"55082",
    "addr:street":"Main St N",
    "iso:country":"US",
    "sg:address":"218 Main St N",
    "sg:city":"Stillwater",
    "sg:classifiers":[
        {
            "category":"Shopping",
            "subcategory":"Photographic Equipment",
            "type":"Retail Goods"
        }
    ],
    "sg:phone":"+1 651 439 1252",
    "sg:postcode":"55082",
    "sg:province":"MN",
    "sg:tags":[
        "repair",
        "supply"
    ],
    "wof:name":"Images of The Past of Stllwter",
    "wof:placetype":"venue"
},
  "geometry": {"coordinates":[-92.806589,45.057499],"type":"Point"}
}