{
  "type": "Feature",
  "properties": {
    "iso:country":"US",
    "sg:address":"603 Laurel St",
    "sg:city":"Brainerd",
    "sg:classifiers":[
        {
            "category":"Restaurant",
            "type":"Food & Drink"
        }
    ],
    "sg:phone":"+1 218 829 1551",
    "sg:postcode":"56401",
    "sg:province":"MN",
    "sg:tags":[
        "eating"
    ],
    "wof:name":"Northwind Grille",
    "wof:placetype":"venue"
},
  "geometry": {"coordinates":[-94.20057,46.355755],"type":"Point"}
}