{
  "type": "Feature",
  "properties": {
    "addr:full":"3659 Cedar Ave S Minneapolis MN 55407",
    "addr:housenumber":"3659",
    "addr:postcode":"55407",
    "addr:street":"Cedar Ave S",
    "iso:country":"US",
    "sg:address":"3659 Cedar Ave S",
    "sg:city":"Minneapolis",
    "sg:classifiers":[
        {
            "category":"Professional",
            "subcategory":"Accounting & Tax Preparation",
            "type":"Services"
        },
        {
            "category":"Banks & Credit Unions",
            "subcategory":"Financial Services",
            "type":"Services"
        }
    ],
    "sg:phone":"+1 612 721 0067",
    "sg:postcode":"55407",
    "sg:province":"MN",
    "sg:tags":[
        "return",
        "preparation-business",
        "taxes-consultants",
        "loan",
        "representative",
        "alternative",
        "bookkeeping"
    ],
    "sg:website":"http://www.hrblock.com",
    "wof:name":"H & R Block",
    "wof:placetype":"venue"
},
  "geometry": {"coordinates":[-93.247356,44.936652],"type":"Point"}
}