{
  "type": "Feature",
  "properties": {
    "addr:full":"117 N 2nd St Minneapolis MN 55401",
    "addr:housenumber":"117",
    "addr:postcode":"55401",
    "addr:street":"N 2Nd St",
    "iso:country":"US",
    "sg:address":"117 N 2nd St",
    "sg:city":"Minneapolis",
    "sg:classifiers":[
        {
            "category":"Manufacturing",
            "subcategory":"Printing",
            "type":"Manufacturing & Wholesale Goods"
        }
    ],
    "sg:phone":"+1 612 339 8193",
    "sg:postcode":"55401",
    "sg:province":"MN",
    "sg:tags":[
        "print",
        "computer",
        "lithographic",
        "printer",
        "supply"
    ],
    "sg:website":"http://www.merit72.com",
    "wof:name":"Merit Printing, Inc.",
    "wof:placetype":"venue"
},
  "geometry": {"coordinates":[-93.26918999999999,44.983906],"type":"Point"}
}