{
  "type": "Feature",
  "properties": {
    "addr:full":"119 24th Ave S Waite Park MN 56387",
    "addr:housenumber":"119",
    "addr:postcode":"56387",
    "addr:street":"24Th Ave S Waite Park",
    "iso:country":"US",
    "sg:address":"119 24th Ave S",
    "sg:city":"Waite Park",
    "sg:classifiers":[
        {
            "category":"Retail",
            "subcategory":"Laundry & Dry Cleaning",
            "type":"Services"
        },
        {
            "category":"Shopping",
            "subcategory":"Clothing, Apparel, & Fashions",
            "type":"Retail Goods"
        }
    ],
    "sg:phone":"+1 320 252 5474",
    "sg:postcode":"56387",
    "sg:province":"MN",
    "sg:tags":[
        "r",
        "alteration"
    ],
    "wof:name":"Saint Cloud Tailor Shop",
    "wof:placetype":"venue"
},
  "geometry": {"coordinates":[-94.250055,45.553226],"type":"Point"}
}