{
  "type": "Feature",
  "properties": {
    "addr:full":"13880 Co Rd 30 Mayer MN 55360",
    "addr:housenumber":"13880;30",
    "addr:postcode":"55360",
    "addr:street":"Co Rd",
    "iso:country":"US",
    "sg:address":"13880 Co Rd 30",
    "sg:city":"Mayer",
    "sg:classifiers":[
        {
            "category":"Farming",
            "subcategory":"Dairy Farm",
            "type":"Manufacturing & Wholesale Goods"
        }
    ],
    "sg:phone":"+1 952 657 2541",
    "sg:postcode":"55360",
    "sg:province":"MN",
    "wof:name":"Bernard Stoeckman",
    "wof:placetype":"venue"
},
  "geometry": {"coordinates":[-93.88030999999999,44.877414],"type":"Point"}
}