{
  "type": "Feature",
  "properties": {
    "addr:full":"321 Grove St Saint Paul MN 55101",
    "addr:housenumber":"321",
    "addr:postcode":"55101",
    "addr:street":"Grove St",
    "iso:country":"US",
    "sg:address":"321 Grove St",
    "sg:city":"Saint Paul",
    "sg:classifiers":[
        {
            "category":"Government",
            "subcategory":"Office",
            "type":"Public Place"
        }
    ],
    "sg:phone":"+1 651 296 2111",
    "sg:postcode":"55101",
    "sg:province":"MN",
    "sg:tags":[
        "department",
        "administration"
    ],
    "wof:name":"Administration Minnesota Dept",
    "wof:placetype":"venue"
},
  "geometry": {"coordinates":[-93.088809,44.955822],"type":"Point"}
}