{
  "type": "Feature",
  "properties": {
    "iso:country":"US",
    "sg:address":"11550 340th St",
    "sg:city":"Ellsworth",
    "sg:phone":"+1 507 967 2509",
    "sg:postcode":"56129",
    "sg:province":"MN",
    "sg:tags":[
        "farm",
        "corn",
        "soybean"
    ],
    "wof:name":"Douglas Klassan",
    "wof:placetype":"venue"
},
  "geometry": {"coordinates":[-96.027356,43.500182],"type":"Point"}
}