{
  "type": "Feature",
  "properties": {
    "iso:country":"US",
    "sg:address":"3313 Co Rd 8 NW",
    "sg:city":"Maple Lake",
    "sg:classifiers":[
        {
            "category":"Building & Trades",
            "subcategory":"Construction",
            "type":"Services"
        }
    ],
    "sg:phone":"+1 320 963 6269",
    "sg:postcode":"55358",
    "sg:province":"MN",
    "sg:tags":[
        "excavation",
        "excavating",
        "contractor"
    ],
    "wof:name":"Bauer Excavating Inc",
    "wof:placetype":"venue"
},
  "geometry": {"coordinates":[-93.991479,45.202419],"type":"Point"}
}