{
  "type": "Feature",
  "properties": {
    "iso:country":"US",
    "sg:address":"1771 410th St",
    "sg:city":"Twin Valley",
    "sg:classifiers":[
        {
            "category":"Building & Trades",
            "subcategory":"Construction",
            "type":"Services"
        }
    ],
    "sg:phone":"+1 218 584 5364",
    "sg:postcode":"56584",
    "sg:province":"MN",
    "wof:name":"Mike Bueng Construction",
    "wof:placetype":"venue"
},
  "geometry": {"coordinates":[-96.194594,47.26528],"type":"Point"}
}