{
  "type": "Feature",
  "properties": {
    "iso:country":"US",
    "sg:address":"12555 Central Ave NE",
    "sg:city":"Blaine",
    "sg:classifiers":[
        {
            "category":"Shopping",
            "type":"Retail Goods"
        }
    ],
    "sg:phone":"+1 763 767 7444",
    "sg:postcode":"55434",
    "sg:province":"MN",
    "sg:tags":[
        "pet",
        "food",
        "supply"
    ],
    "wof:name":"S & C Pet Inc",
    "wof:placetype":"venue"
},
  "geometry": {"coordinates":[-93.233925,45.200322],"type":"Point"}
}