{
  "type": "Feature",
  "properties": {
    "addr:full":"575 72nd St SE Montrose MN 55363",
    "addr:housenumber":"575",
    "addr:postcode":"55363",
    "addr:street":"72Nd St Se",
    "iso:country":"US",
    "sg:address":"575 72nd St SE",
    "sg:city":"Montrose",
    "sg:classifiers":[
        {
            "category":"Food & Beverages",
            "subcategory":"Groceries & Convenience Stores",
            "type":"Retail Goods"
        }
    ],
    "sg:phone":"+1 763 972 2774",
    "sg:postcode":"55363",
    "sg:province":"MN",
    "wof:name":"Great Alaskan Food Adventure",
    "wof:placetype":"venue"
},
  "geometry": {"coordinates":[-93.88415000000001,45.052102],"type":"Point"}
}