{
  "type": "Feature",
  "properties": {
    "addr:full":"34584 298th St Aitkin MN 56431",
    "addr:housenumber":"34584",
    "addr:postcode":"56431",
    "addr:street":"298Th St",
    "iso:country":"US",
    "sg:address":"34584 298th St",
    "sg:city":"Aitkin",
    "sg:classifiers":[
        {
            "category":"Building & Trades",
            "subcategory":"Construction",
            "type":"Services"
        }
    ],
    "sg:phone":"+1 218 927 5646",
    "sg:postcode":"56431",
    "sg:province":"MN",
    "sg:tags":[
        "concrete",
        "contractor"
    ],
    "wof:name":"Whipps Indus Blacktop & Seal",
    "wof:placetype":"venue"
},
  "geometry": {"coordinates":[-93.570204,46.446071],"type":"Point"}
}