{
  "type": "Feature",
  "properties": {
    "addr:full":"2830 Cedar Ave S Minneapolis MN 55407",
    "addr:housenumber":"2830",
    "addr:postcode":"55407",
    "addr:street":"Cedar Ave S",
    "iso:country":"US",
    "sg:address":"2830 Cedar Ave S",
    "sg:city":"Minneapolis",
    "sg:classifiers":[
        {
            "category":"Personal",
            "subcategory":"Beauty Salon",
            "type":"Services"
        }
    ],
    "sg:phone":"+1 612 724 5919",
    "sg:postcode":"55407",
    "sg:province":"MN",
    "sg:tags":[
        "shop"
    ],
    "wof:name":"Bodyology",
    "wof:placetype":"venue"
},
  "geometry": {"coordinates":[-93.24746399999999,44.951468],"type":"Point"}
}