{
  "type": "Feature",
  "properties": {
    "addr:full":"405 Central Ave E Saint Michael MN 55376",
    "addr:housenumber":"405",
    "addr:postcode":"55376",
    "addr:street":"Central Ave E Saint Michael",
    "iso:country":"US",
    "sg:address":"405 Central Ave E",
    "sg:city":"Saint Michael",
    "sg:classifiers":[
        {
            "category":"Cinema",
            "subcategory":"Movie Rental",
            "type":"Entertainment"
        }
    ],
    "sg:phone":"+1 763 497 3144",
    "sg:postcode":"55376",
    "sg:province":"MN",
    "sg:tags":[
        "video",
        "tape"
    ],
    "wof:name":"Mr Movies 16",
    "wof:placetype":"venue"
},
  "geometry": {"coordinates":[-93.65643300000001,45.209971],"type":"Point"}
}