{
  "type": "Feature",
  "properties": {
    "addr:full":"18015 Ute St NW Anoka MN 55303",
    "addr:housenumber":"18015",
    "addr:postcode":"55303",
    "addr:street":"Ute St Nw",
    "iso:country":"US",
    "sg:address":"18015 Ute St NW",
    "sg:city":"Anoka",
    "sg:classifiers":[
        {
            "category":"Building & Trades",
            "subcategory":"Construction",
            "type":"Services"
        }
    ],
    "sg:phone":"+1 763 753 1124",
    "sg:postcode":"55303",
    "sg:province":"MN",
    "sg:tags":[
        "siding",
        "contractor"
    ],
    "wof:name":"Rockow Exterior Remodelers",
    "wof:placetype":"venue"
},
  "geometry": {"coordinates":[-93.392533,45.298155],"type":"Point"}
}