{
  "type": "Feature",
  "properties": {
    "addr:full":"1325 4th St SE Minneapolis MN 55414",
    "addr:housenumber":"1325",
    "addr:postcode":"55414",
    "addr:street":"4Th St Se",
    "iso:country":"US",
    "sg:address":"1325 4th St SE",
    "sg:city":"Minneapolis",
    "sg:classifiers":[
        {
            "category":"Restaurant",
            "type":"Food & Drink"
        }
    ],
    "sg:phone":"+1 612 331 4194",
    "sg:postcode":"55414",
    "sg:province":"MN",
    "sg:tags":[
        "style",
        "chinese",
        "family",
        "asian",
        "pan"
    ],
    "wof:name":"Camdi Restaurant",
    "wof:placetype":"venue"
},
  "geometry": {"coordinates":[-93.236841,44.980912],"type":"Point"}
}