{
  "type": "Feature",
  "properties": {
    "addr:full":"359 20th Ave Edgerton MN 56128",
    "addr:housenumber":"359",
    "addr:postcode":"56128",
    "addr:street":"20Th Ave",
    "iso:country":"US",
    "sg:address":"359 20th Ave",
    "sg:city":"Edgerton",
    "sg:phone":"+1 507 443 5633",
    "sg:postcode":"56128",
    "sg:province":"MN",
    "sg:tags":[
        "farm",
        "corn"
    ],
    "wof:name":"Ronald Griffin",
    "wof:placetype":"venue"
},
  "geometry": {"coordinates":[-96.024264,43.892998],"type":"Point"}
}