{
  "type": "Feature",
  "properties": {
    "addr:full":"39839 E Madison Ave Mankato MN 56001",
    "addr:housenumber":"39839",
    "addr:postcode":"56001",
    "addr:street":"E Madison Ave",
    "iso:country":"US",
    "sg:address":"39839 E Madison Ave",
    "sg:city":"Mankato",
    "sg:classifiers":[
        {
            "category":"Manufacturing",
            "subcategory":"Tools & Machinery",
            "type":"Manufacturing & Wholesale Goods"
        },
        {
            "category":"Retail",
            "subcategory":"Repair Shop",
            "type":"Services"
        }
    ],
    "sg:phone":"+1 507 625 3567",
    "sg:postcode":"56001",
    "sg:province":"MN",
    "sg:tags":[
        "machine",
        "machinery-rebuild"
    ],
    "wof:name":"Done Right Machine",
    "wof:placetype":"venue"
},
  "geometry": {"coordinates":[-93.948761,44.166908],"type":"Point"}
}