{
  "type": "Feature",
  "properties": {
    "iso:country":"US",
    "sg:address":"12337 Bass Lake Rd",
    "sg:city":"Merrifield",
    "sg:classifiers":[
        {
            "category":"Building & Trades",
            "subcategory":"Construction",
            "type":"Services"
        }
    ],
    "sg:phone":"+1 218 765 4273",
    "sg:postcode":"56465",
    "sg:province":"MN",
    "sg:tags":[
        "home",
        "improvement"
    ],
    "wof:name":"John's Seamless Rain Gutters",
    "wof:placetype":"venue"
},
  "geometry": {"coordinates":[-94.143956,46.482375],"type":"Point"}
}