{
  "type": "Feature",
  "properties": {
    "iso:country":"US",
    "sg:address":"307 Ridgewood Ave",
    "sg:city":"Minneapolis",
    "sg:classifiers":[
        {
            "category":"Government",
            "subcategory":"Office",
            "type":"Public Place"
        }
    ],
    "sg:phone":"+1 612 870 1006",
    "sg:postcode":"55403",
    "sg:province":"MN",
    "sg:tags":[
        "federal",
        "affairs"
    ],
    "wof:name":"Netherlands Consulate",
    "wof:placetype":"venue"
},
  "geometry": {"coordinates":[-93.280784,44.963852],"type":"Point"}
}