{
  "type": "Feature",
  "properties": {
    "addr:full":"404 Snelling Ave S Saint Paul MN 55105",
    "addr:housenumber":"404",
    "addr:postcode":"55105",
    "addr:street":"Snelling Ave S",
    "iso:country":"US",
    "sg:address":"404 Snelling Ave S",
    "sg:city":"Saint Paul",
    "sg:classifiers":[
        {
            "category":"Shopping",
            "type":"Retail Goods"
        },
        {
            "category":"Shopping",
            "subcategory":"Used Merchandise",
            "type":"Retail Goods"
        }
    ],
    "sg:phone":"+1 651 695 1902",
    "sg:postcode":"55105",
    "sg:province":"MN",
    "sg:tags":[
        "antique"
    ],
    "wof:name":"Eastwood Gallery",
    "wof:placetype":"venue"
},
  "geometry": {"coordinates":[-93.167198,44.929401],"type":"Point"}
}