{
  "type": "Feature",
  "properties": {
    "addr:full":"15229 360th Ave Frazee MN 56544",
    "addr:housenumber":"15229",
    "addr:postcode":"56544",
    "addr:street":"360Th Ave",
    "iso:country":"US",
    "sg:address":"15229 360th Ave",
    "sg:city":"Frazee",
    "sg:classifiers":[
        {
            "category":"Manufacturing",
            "subcategory":"Buildings",
            "type":"Manufacturing & Wholesale Goods"
        },
        {
            "category":"Building & Trades",
            "subcategory":"Construction",
            "type":"Services"
        }
    ],
    "sg:phone":"+1 218 334 2264",
    "sg:postcode":"56544",
    "sg:province":"MN",
    "sg:tags":[
        "industrial",
        "system",
        "specialty",
        "builder",
        "heating",
        "contractor",
        "contractors-commercial",
        "home",
        "air conditioning"
    ],
    "wof:name":"Lomsdal, Howard Construction",
    "wof:placetype":"venue"
},
  "geometry": {"coordinates":[-95.647537,46.7857],"type":"Point"}
}