{
  "type": "Feature",
  "properties": {
    "addr:full":"2751 E Main St Albert Lea MN 56007",
    "addr:housenumber":"2751",
    "addr:postcode":"56007",
    "addr:street":"E Main St",
    "iso:country":"US",
    "sg:address":"2751 E Main St",
    "sg:city":"Albert Lea",
    "sg:classifiers":[
        {
            "category":"Restaurant",
            "type":"Food & Drink"
        }
    ],
    "sg:menulink":"http://www.allmenus.com/mn/albert-lea/182333-wendys/menu/",
    "sg:phone":"+1 502 377 2704",
    "sg:postcode":"56007",
    "sg:province":"MN",
    "sg:tags":[
        "burger",
        "american",
        "soup"
    ],
    "wof:name":"Wendy's",
    "wof:placetype":"venue"
},
  "geometry": {"coordinates":[-93.315675,43.658431],"type":"Point"}
}