{
  "type": "Feature",
  "properties": {
    "iso:country":"US",
    "sg:address":"15 5th Ave S",
    "sg:city":"Long Prairie",
    "sg:classifiers":[
        {
            "category":"Arts & Performance",
            "subcategory":"Theater",
            "type":"Entertainment"
        }
    ],
    "sg:phone":"+1 320 732 6806",
    "sg:postcode":"56347",
    "sg:province":"MN",
    "sg:tags":[
        "live",
        "music"
    ],
    "wof:name":"Multiple Choice",
    "wof:placetype":"venue"
},
  "geometry": {"coordinates":[-94.86527700000001,45.967418],"type":"Point"}
}