{
  "type": "Feature",
  "properties": {
    "addr:full":"540 N Broadway Ave Spring Valley MN 55975",
    "addr:housenumber":"540",
    "addr:postcode":"55975",
    "addr:street":"N Broadway Ave",
    "iso:country":"US",
    "sg:address":"540 N Broadway Ave",
    "sg:city":"Spring Valley",
    "sg:classifiers":[
        {
            "category":"Shopping",
            "subcategory":"Clothing, Apparel, & Fashions",
            "type":"Retail Goods"
        }
    ],
    "sg:phone":"+1 507 346 2074",
    "sg:postcode":"55975",
    "sg:province":"MN",
    "sg:tags":[
        "r"
    ],
    "wof:name":"Valley Clothiers",
    "wof:placetype":"venue"
},
  "geometry": {"coordinates":[-92.394268,43.693938],"type":"Point"}
}