{
  "type": "Feature",
  "properties": {
    "addr:full":"102 N Oak Ave Owatonna MN 55060",
    "addr:housenumber":"102",
    "addr:postcode":"55060",
    "addr:street":"N Oak Ave",
    "iso:country":"US",
    "sg:address":"102 N Oak Ave",
    "sg:city":"Owatonna",
    "sg:classifiers":[
        {
            "category":"Autos & Motor Vehicles",
            "subcategory":"Auto Supplies",
            "type":"Retail Goods"
        }
    ],
    "sg:phone":"+1 507 451 5230",
    "sg:postcode":"55060",
    "sg:province":"MN",
    "sg:tags":[
        "tire"
    ],
    "wof:name":"Expert Tire",
    "wof:placetype":"venue"
},
  "geometry": {"coordinates":[-93.228579,44.085769],"type":"Point"}
}