{
  "type": "Feature",
  "properties": {
    "addr:full":"5844 268th St Wyoming MN 55092",
    "addr:housenumber":"5844",
    "addr:postcode":"55092",
    "addr:street":"268Th St",
    "iso:country":"US",
    "sg:address":"5844 268th St",
    "sg:city":"Wyoming",
    "sg:classifiers":[
        {
            "category":"Professional",
            "subcategory":"Business Services",
            "type":"Services"
        }
    ],
    "sg:phone":"+1 651 462 2132",
    "sg:postcode":"55092",
    "sg:province":"MN",
    "wof:name":"Save Design",
    "wof:placetype":"venue"
},
  "geometry": {"coordinates":[-92.987081,45.337676],"type":"Point"}
}