{
  "type": "Feature",
  "properties": {
    "iso:country":"US",
    "sg:address":"1501 State Hwy 7",
    "sg:city":"Hopkins",
    "sg:classifiers":[
        {
            "category":"Real Estate",
            "subcategory":"Real Estate Operator",
            "type":"Services"
        }
    ],
    "sg:phone":"+1 952 933 0100",
    "sg:postcode":"55305",
    "sg:province":"MN",
    "sg:tags":[
        "condominium"
    ],
    "wof:name":"Summit Condos",
    "wof:placetype":"venue"
},
  "geometry": {"coordinates":[-93.405669,44.933686],"type":"Point"}
}