{
  "type": "Feature",
  "properties": {
    "addr:full":"80 8th St S Minneapolis MN 55404",
    "addr:housenumber":"80",
    "addr:postcode":"55404",
    "addr:street":"8Th St S",
    "iso:country":"US",
    "sg:address":"80 8th St S",
    "sg:city":"Minneapolis",
    "sg:classifiers":[
        {
            "category":"Banks & Credit Unions",
            "subcategory":"Investment Brokerage",
            "type":"Services"
        }
    ],
    "sg:phone":"+1 612 334 2000",
    "sg:postcode":"55404",
    "sg:province":"MN",
    "sg:tags":[
        "advisory",
        "financial"
    ],
    "wof:name":"Minneplis Portfolio Mgmt Group",
    "wof:placetype":"venue"
},
  "geometry": {"coordinates":[-93.27217899999999,44.975669],"type":"Point"}
}