{
  "type": "Feature",
  "properties": {
    "iso:country":"US",
    "sg:address":"9376 60th St W",
    "sg:city":"Lonsdale",
    "sg:classifiers":[
        {
            "category":"Real Estate",
            "subcategory":"Real Estate Operator",
            "type":"Services"
        }
    ],
    "sg:phone":"+1 507 744 2274",
    "sg:postcode":"55046",
    "sg:province":"MN",
    "sg:tags":[
        "farm",
        "management",
        "property",
        "lessor"
    ],
    "wof:name":"C Salaba",
    "wof:placetype":"venue"
},
  "geometry": {"coordinates":[-93.44978500000001,44.500775],"type":"Point"}
}