{
  "type": "Feature",
  "properties": {
    "iso:country":"US",
    "sg:address":"180 Co Rd 48",
    "sg:city":"Grand Marais",
    "sg:classifiers":[
        {
            "category":"Shopping",
            "subcategory":"Used Merchandise",
            "type":"Retail Goods"
        }
    ],
    "sg:phone":"+1 218 387 3391",
    "sg:postcode":"55604",
    "sg:province":"MN",
    "wof:name":"Time Passages Antiques",
    "wof:placetype":"venue"
},
  "geometry": {"coordinates":[-90.41666499999999,47.759582],"type":"Point"}
}