{
  "type": "Feature",
  "properties": {
    "iso:country":"US",
    "sg:address":"7237 Riverdale Rd",
    "sg:city":"Minneapolis",
    "sg:classifiers":[
        {
            "category":"Professional",
            "subcategory":"Management & Consulting",
            "type":"Services"
        }
    ],
    "sg:phone":"+1 763 566 2777",
    "sg:postcode":"55430",
    "sg:province":"MN",
    "wof:name":"Management Tech of Minn",
    "wof:placetype":"venue"
},
  "geometry": {"coordinates":[-93.284584,45.086361],"type":"Point"}
}