{
  "type": "Feature",
  "properties": {
    "iso:country":"US",
    "sg:address":"13750 Crosstown Dr NW Ste 100",
    "sg:city":"Andover",
    "sg:classifiers":[
        {
            "category":"Real Estate",
            "subcategory":"Real Estate Services",
            "type":"Services"
        }
    ],
    "sg:phone":"+1 763 587 7200",
    "sg:postcode":"55304",
    "sg:province":"MN",
    "sg:website":"www.freemovingtruck.com",
    "wof:name":"Team Firnstahl",
    "wof:placetype":"venue"
},
  "geometry": {"coordinates":[-93.33435299999999,45.220552],"type":"Point"}
}