{
  "type": "Feature",
  "properties": {
    "addr:full":"2305 Hwy 37 Hibbing MN 55746",
    "addr:housenumber":"2305",
    "addr:postcode":"55746",
    "addr:street":"Hwy 37",
    "iso:country":"US",
    "sg:address":"2305 Hwy 37",
    "sg:city":"Hibbing",
    "sg:classifiers":[
        {
            "category":"Professional",
            "type":"Services"
        }
    ],
    "sg:phone":"+1 218 262 3537",
    "sg:postcode":"55746",
    "sg:province":"MN",
    "wof:name":"R J Ikola Associates Inc",
    "wof:placetype":"venue"
},
  "geometry": {"coordinates":[-92.903423,47.399287],"type":"Point"}
}