{
  "type": "Feature",
  "properties": {
    "addr:full":"5408 Chicago Ave Minneapolis MN 55417",
    "addr:housenumber":"5408",
    "addr:postcode":"55417",
    "addr:street":"Chicago Ave",
    "iso:country":"US",
    "sg:address":"5408 Chicago Ave",
    "sg:city":"Minneapolis",
    "sg:classifiers":[
        {
            "category":"Social Services",
            "subcategory":"Child Care",
            "type":"Services"
        }
    ],
    "sg:phone":"+1 612 823 7921",
    "sg:postcode":"55417",
    "sg:province":"MN",
    "sg:tags":[
        "nursery",
        "day"
    ],
    "wof:name":"We Love Kids",
    "wof:placetype":"venue"
},
  "geometry": {"coordinates":[-93.262629,44.9051],"type":"Point"}
}