{
  "type": "Feature",
  "properties": {
    "iso:country":"US",
    "sg:address":"22513 Nolan Ave N",
    "sg:city":"Scandia",
    "sg:classifiers":[
        {
            "category":"Social Services",
            "subcategory":"Child Care",
            "type":"Services"
        }
    ],
    "sg:phone":"+1 651 433 5082",
    "sg:postcode":"55073",
    "sg:province":"MN",
    "sg:tags":[
        "daycare",
        "provider"
    ],
    "wof:name":"Sandra L Mckinnon",
    "wof:placetype":"venue"
},
  "geometry": {"coordinates":[-92.834695,45.272291],"type":"Point"}
}