{
  "type": "Feature",
  "properties": {
    "iso:country":"US",
    "sg:address":"2525 Nevada Ave N",
    "sg:city":"Golden Valley",
    "sg:classifiers":[
        {
            "category":"Wholesale",
            "subcategory":"Machinery & Supplies",
            "type":"Manufacturing & Wholesale Goods"
        },
        {
            "category":"Manufacturing",
            "subcategory":"Apparel",
            "type":"Manufacturing & Wholesale Goods"
        }
    ],
    "sg:phone":"+1 763 545 5550",
    "sg:postcode":"55427",
    "sg:province":"MN",
    "sg:tags":[
        "salon",
        "beauty",
        "mfg",
        "career",
        "uniform",
        "attire"
    ],
    "sg:website":"www.salonwear.com",
    "wof:name":"Salonwear",
    "wof:placetype":"venue"
},
  "geometry": {"coordinates":[-93.372466,45.006935],"type":"Point"}
}