{
  "type": "Feature",
  "properties": {
    "iso:country":"US",
    "sg:address":"401 4th Ave SW",
    "sg:city":"New Prague",
    "sg:classifiers":[
        {
            "category":"Professional",
            "subcategory":"Research",
            "type":"Services"
        }
    ],
    "sg:phone":"+1 952 758 4419",
    "sg:postcode":"56071",
    "sg:province":"MN",
    "sg:tags":[
        "development",
        "laboratory"
    ],
    "wof:name":"Wolff Labs",
    "wof:placetype":"venue"
},
  "geometry": {"coordinates":[-93.584007,44.540387],"type":"Point"}
}