{
  "type": "Feature",
  "properties": {
    "addr:full":"219 3rd Ave SE Pipestone MN 56164",
    "addr:housenumber":"219",
    "addr:postcode":"56164",
    "addr:street":"3Rd Ave Se",
    "iso:country":"US",
    "sg:address":"219 3rd Ave SE",
    "sg:city":"Pipestone",
    "sg:classifiers":[
        {
            "category":"Real Estate",
            "subcategory":"Real Estate Agent",
            "type":"Services"
        }
    ],
    "sg:phone":"+1 507 825 3649",
    "sg:postcode":"56164",
    "sg:province":"MN",
    "sg:tags":[
        "apartment"
    ],
    "wof:name":"Dekam Rentals",
    "wof:placetype":"venue"
},
  "geometry": {"coordinates":[-96.315111,43.99922],"type":"Point"}
}