{
  "type": "Feature",
  "properties": {
    "addr:full":"301 Huntsinger Ave Park Rapids MN 56470",
    "addr:housenumber":"301",
    "addr:postcode":"56470",
    "addr:street":"Huntsinger Ave",
    "iso:country":"US",
    "sg:address":"301 Huntsinger Ave",
    "sg:city":"Park Rapids",
    "sg:classifiers":[
        {
            "category":"Social Services",
            "type":"Services"
        }
    ],
    "sg:phone":"+1 218 732 0058",
    "sg:postcode":"56470",
    "sg:province":"MN",
    "sg:tags":[
        "organization",
        "welfare"
    ],
    "wof:name":"Kinship Of Park Rapids",
    "wof:placetype":"venue"
},
  "geometry": {"coordinates":[-95.06368999999999,46.92567],"type":"Point"}
}