{
  "type": "Feature",
  "properties": {
    "addr:full":"4525 Allendale Dr St Paul MN 55127",
    "addr:housenumber":"4525",
    "addr:postcode":"55127",
    "addr:street":"Allendale Dr",
    "iso:country":"US",
    "sg:address":"4525 Allendale Dr",
    "sg:city":"St Paul",
    "sg:classifiers":[
        {
            "category":"Banks & Credit Unions",
            "subcategory":"Bank",
            "type":"Services"
        }
    ],
    "sg:phone":"+1 651 429 5252",
    "sg:postcode":"55127",
    "sg:province":"MN",
    "sg:tags":[
        "loan",
        "real estate"
    ],
    "wof:name":"Northwoods Mortgage Co",
    "wof:placetype":"venue"
},
  "geometry": {"coordinates":[-93.061329,45.079827],"type":"Point"}
}