{
  "type": "Feature",
  "properties": {
    "addr:full":"8465 Plaza Blvd NE Minneapolis MN 55432",
    "addr:housenumber":"8465",
    "addr:postcode":"55432",
    "addr:street":"Plaza Blvd Ne",
    "iso:country":"US",
    "sg:address":"8465 Plaza Blvd NE",
    "sg:city":"Minneapolis",
    "sg:classifiers":[
        {
            "category":"Recreation",
            "type":"Entertainment"
        }
    ],
    "sg:phone":"+1 763 792 2102",
    "sg:postcode":"55432",
    "sg:province":"MN",
    "sg:tags":[
        "parlor",
        "billiard"
    ],
    "wof:name":"Corner Pocket",
    "wof:placetype":"venue"
},
  "geometry": {"coordinates":[-93.234661,45.124358],"type":"Point"}
}