{
  "type": "Feature",
  "properties": {
    "addr:full":"8300 City Centre Dr Woodbury MN 55125",
    "addr:housenumber":"8300",
    "addr:postcode":"55125",
    "addr:street":"City Centre Dr",
    "iso:country":"US",
    "sg:address":"8300 City Centre Dr",
    "sg:city":"Woodbury",
    "sg:classifiers":[
        {
            "category":"Manufacturing",
            "subcategory":"Printing",
            "type":"Manufacturing & Wholesale Goods"
        }
    ],
    "sg:phone":"+1 651 578 9000",
    "sg:postcode":"55125",
    "sg:province":"MN",
    "sg:tags":[
        "printer"
    ],
    "sg:website":"www.kinkos.com",
    "wof:name":"Fed Ex Kinko's Ofc & Print Ctr",
    "wof:placetype":"venue"
},
  "geometry": {"coordinates":[-92.93669199999999,44.920821],"type":"Point"}
}