{
  "type": "Feature",
  "properties": {
    "iso:country":"US",
    "sg:address":"8357 Sheridan Ave N",
    "sg:city":"Minneapolis",
    "sg:classifiers":[
        {
            "category":"Wholesale",
            "subcategory":"Medical Equipment & Supplies",
            "type":"Manufacturing & Wholesale Goods"
        }
    ],
    "sg:phone":"+1 763 424 9063",
    "sg:postcode":"55444",
    "sg:province":"MN",
    "wof:name":"Zanewood Medical Supply",
    "wof:placetype":"venue"
},
  "geometry": {"coordinates":[-93.312516,45.108343],"type":"Point"}
}