{
  "type": "Feature",
  "properties": {
    "iso:country":"US",
    "sg:address":"419 Beacon St",
    "sg:city":"Saint Paul",
    "sg:classifiers":[
        {
            "category":"Building & Trades",
            "subcategory":"Electrical",
            "type":"Services"
        }
    ],
    "sg:phone":"+1 651 645 5241",
    "sg:postcode":"55104",
    "sg:province":"MN",
    "sg:tags":[
        "electrical",
        "contractor"
    ],
    "wof:name":"Bc & As Electric Co",
    "wof:placetype":"venue"
},
  "geometry": {"coordinates":[-93.17599,44.952582],"type":"Point"}
}