{
  "type": "Feature",
  "properties": {
    "iso:country":"US",
    "sg:address":"4334 Metcalf Dr",
    "sg:city":"Saint Paul",
    "sg:classifiers":[
        {
            "category":"Banks & Credit Unions",
            "subcategory":"Investment Brokerage",
            "type":"Services"
        }
    ],
    "sg:phone":"+1 651 890 3428",
    "sg:postcode":"55122",
    "sg:province":"MN",
    "sg:tags":[
        "advisory"
    ],
    "wof:name":"Premium Financial Services",
    "wof:placetype":"venue"
},
  "geometry": {"coordinates":[-93.22571499999999,44.800744],"type":"Point"}
}