{
  "type": "Feature",
  "properties": {
    "addr:full":"2108 2nd Ave NW Faribault MN 55021",
    "addr:housenumber":"2108",
    "addr:postcode":"55021",
    "addr:street":"2Nd Ave Nw",
    "iso:country":"US",
    "sg:address":"2108 2nd Ave NW",
    "sg:city":"Faribault",
    "sg:classifiers":[
        {
            "category":"Social Services",
            "subcategory":"Child Care",
            "type":"Services"
        }
    ],
    "sg:phone":"+1 507 332 8422",
    "sg:postcode":"55021",
    "sg:province":"MN",
    "sg:tags":[
        "day"
    ],
    "wof:name":"Winters Sodding",
    "wof:placetype":"venue"
},
  "geometry": {"coordinates":[-93.272803,44.31403],"type":"Point"}
}