{
  "type": "Feature",
  "properties": {
    "addr:full":"8240 Golden Valley Rd Golden Valley MN 55427",
    "addr:housenumber":"8240",
    "addr:postcode":"55427",
    "addr:street":"Golden Valley Rd",
    "iso:country":"US",
    "sg:address":"8240 Golden Valley Rd",
    "sg:city":"Golden Valley",
    "sg:classifiers":[
        {
            "category":"Health Services",
            "subcategory":"Doctor",
            "type":"Services"
        }
    ],
    "sg:phone":"+1 952 993 8300",
    "sg:postcode":"55427",
    "sg:province":"MN",
    "sg:tags":[
        "clinic"
    ],
    "wof:name":"Park Nicollet Clinic",
    "wof:placetype":"venue"
},
  "geometry": {"coordinates":[-93.38385700000001,44.986725],"type":"Point"}
}