{
  "type": "Feature",
  "properties": {
    "iso:country":"US",
    "sg:address":"5 Jay Cooke Rd",
    "sg:city":"Esko",
    "sg:classifiers":[
        {
            "category":"Wholesale",
            "subcategory":"Groceries",
            "type":"Manufacturing & Wholesale Goods"
        }
    ],
    "sg:phone":"+1 218 879 5470",
    "sg:postcode":"55733",
    "sg:province":"MN",
    "sg:tags":[
        "frozen",
        "packaged"
    ],
    "wof:name":"Schwans Home Service Inc",
    "wof:placetype":"venue"
},
  "geometry": {"coordinates":[-92.344634,46.706397],"type":"Point"}
}