{
  "type": "Feature",
  "properties": {
    "iso:country":"US",
    "sg:address":"1337 139th Ave NW",
    "sg:city":"Anoka",
    "sg:classifiers":[
        {
            "category":"Professional",
            "subcategory":"Management & Consulting",
            "type":"Services"
        }
    ],
    "sg:phone":"+1 763 757 0845",
    "sg:postcode":"55304",
    "sg:province":"MN",
    "sg:tags":[
        "business"
    ],
    "wof:name":"Hoppenrath Professional Servic",
    "wof:placetype":"venue"
},
  "geometry": {"coordinates":[-93.299594,45.223045],"type":"Point"}
}