{
  "type": "Feature",
  "properties": {
    "iso:country":"US",
    "sg:address":"12011 Business Park Blvd N",
    "sg:city":"Champlin",
    "sg:classifiers":[
        {
            "category":"Banks & Credit Unions",
            "subcategory":"Bank",
            "type":"Services"
        }
    ],
    "sg:phone":"+1 763 230 6900",
    "sg:postcode":"55316",
    "sg:province":"MN",
    "wof:name":"Minnwest Bank",
    "wof:placetype":"venue"
},
  "geometry": {"coordinates":[-93.390822,45.173533],"type":"Point"}
}