{
  "type": "Feature",
  "properties": {
    "addr:full":"12011 Business Park Blvd N Champlin MN 55316",
    "addr:housenumber":"12011",
    "addr:postcode":"55316",
    "addr:street":"Business Park Blvd N",
    "iso:country":"US",
    "sg:address":"12011 Business Park Blvd N",
    "sg:city":"Champlin",
    "sg:classifiers":[
        {
            "category":"Banks & Credit Unions",
            "subcategory":"Bank",
            "type":"Services"
        }
    ],
    "sg:phone":"+1 763 230 6900",
    "sg:postcode":"55316",
    "sg:province":"MN",
    "wof:name":"Minnwest Bank",
    "wof:placetype":"venue"
},
  "geometry": {"coordinates":[-93.390822,45.173533],"type":"Point"}
}