{
  "type": "Feature",
  "properties": {
    "addr:full":"11660 Theatre Dr N Champlin MN 55316",
    "addr:housenumber":"11660",
    "addr:postcode":"55316",
    "addr:street":"Theatre Dr N",
    "iso:country":"US",
    "sg:address":"11660 Theatre Dr N",
    "sg:city":"Champlin",
    "sg:classifiers":[
        {
            "category":"Real Estate",
            "subcategory":"Real Estate Agent",
            "type":"Services"
        }
    ],
    "sg:phone":"+1 763 433 8040",
    "sg:postcode":"55316",
    "sg:province":"MN",
    "wof:name":"Stellar Realty Inc",
    "wof:placetype":"venue"
},
  "geometry": {"coordinates":[-93.39317,45.165575],"type":"Point"}
}