{
  "type": "Feature",
  "properties": {
    "addr:full":"11521 Spudville Rd Hibbing MN 55746",
    "addr:housenumber":"11521",
    "addr:postcode":"55746",
    "addr:street":"Spudville Rd",
    "iso:country":"US",
    "sg:address":"11521 Spudville Rd",
    "sg:city":"Hibbing",
    "sg:classifiers":[
        {
            "category":"Wholesale",
            "subcategory":"Metals & Minerals",
            "type":"Manufacturing & Wholesale Goods"
        }
    ],
    "sg:phone":"+1 218 262 1966",
    "sg:postcode":"55746",
    "sg:province":"MN",
    "sg:tags":[
        "steel",
        "warehouse"
    ],
    "wof:name":"Radko Iron & Supply Inc",
    "wof:placetype":"venue"
},
  "geometry": {"coordinates":[-92.89296899999999,47.440069],"type":"Point"}
}