{
  "type": "Feature",
  "properties": {
    "addr:full":"8823 Zealand Ave N Brooklyn Park MN 55445",
    "addr:housenumber":"8823",
    "addr:postcode":"55445",
    "addr:street":"Zealand Ave N",
    "iso:country":"US",
    "sg:address":"8823 Zealand Ave N",
    "sg:city":"Brooklyn Park",
    "sg:classifiers":[
        {
            "category":"Wholesale",
            "subcategory":"Machinery & Supplies",
            "type":"Manufacturing & Wholesale Goods"
        },
        {
            "category":"Building & Trades",
            "subcategory":"Plumbing",
            "type":"Services"
        }
    ],
    "sg:phone":"+1 763 424 5800",
    "sg:postcode":"55445",
    "sg:province":"MN",
    "sg:tags":[
        "fire",
        "protection",
        "system",
        "sprinkler"
    ],
    "wof:name":"AST Fire Protection Company",
    "wof:placetype":"venue"
},
  "geometry": {"coordinates":[-93.388858,45.114144],"type":"Point"}
}