{
  "type": "Feature",
  "properties": {
    "addr:full":"1213 Gilmore Ave Winona MN 55987",
    "addr:housenumber":"1213",
    "addr:postcode":"55987",
    "addr:street":"Gilmore Ave",
    "iso:country":"US",
    "sg:address":"1213 Gilmore Ave",
    "sg:city":"Winona",
    "sg:classifiers":[
        {
            "category":"Shopping",
            "subcategory":"Shoes",
            "type":"Retail Goods"
        }
    ],
    "sg:phone":"+1 507 452 9066",
    "sg:postcode":"55987",
    "sg:province":"MN",
    "wof:name":"Tradehome Shoes 11",
    "wof:placetype":"venue"
},
  "geometry": {"coordinates":[-91.670239,44.048547],"type":"Point"}
}