{
  "type": "Feature",
  "properties": {
    "addr:full":"44726 US Hwy 14 Springfield MN 56087",
    "addr:postcode":"44726;56087",
    "addr:street":"Us Hwy 14",
    "iso:country":"US",
    "sg:address":"44726 US Hwy 14",
    "sg:city":"Springfield",
    "sg:classifiers":[
        {
            "category":"Farming",
            "subcategory":"Dairy Farm",
            "type":"Manufacturing & Wholesale Goods"
        }
    ],
    "sg:phone":"+1 507 723 6731",
    "sg:postcode":"56087",
    "sg:province":"MN",
    "wof:name":"Runcks Dairy Farm",
    "wof:placetype":"venue"
},
  "geometry": {"coordinates":[-95.087355,44.238712],"type":"Point"}
}