{
  "type": "Feature",
  "properties": {
    "iso:country":"US",
    "sg:address":"12299 Champlin Dr",
    "sg:city":"Champlin",
    "sg:classifiers":[
        {
            "category":"Government",
            "subcategory":"Post Office",
            "type":"Public Place"
        }
    ],
    "sg:phone":"+1 763 427 2428",
    "sg:postcode":"55316",
    "sg:province":"MN",
    "sg:tags":[
        "postal",
        "us"
    ],
    "wof:name":"US Post Office",
    "wof:placetype":"venue"
},
  "geometry": {"coordinates":[-93.3927,45.17709],"type":"Point"}
}