{
  "type": "Feature",
  "properties": {
    "addr:full":"8501 Golden Valley Rd Minneapolis MN 55427",
    "addr:housenumber":"8501",
    "addr:postcode":"55427",
    "addr:street":"Golden Valley Rd",
    "iso:country":"US",
    "sg:address":"8501 Golden Valley Rd",
    "sg:city":"Minneapolis",
    "sg:classifiers":[
        {
            "category":"Banks & Credit Unions",
            "subcategory":"Investment Brokerage",
            "type":"Services"
        }
    ],
    "sg:phone":"+1 763 548 8208",
    "sg:postcode":"55427",
    "sg:province":"MN",
    "sg:tags":[
        "agency",
        "public",
        "relations"
    ],
    "wof:name":"Market Ready Public Relations",
    "wof:placetype":"venue"
},
  "geometry": {"coordinates":[-93.38827999999999,44.985993],"type":"Point"}
}