{
  "type": "Feature",
  "properties": {
    "iso:country":"US",
    "sg:address":"1005 W Morgan St",
    "sg:city":"Duluth",
    "sg:classifiers":[
        {
            "category":"Building & Trades",
            "subcategory":"Plumbing",
            "type":"Services"
        }
    ],
    "sg:phone":"+1 218 348 7473",
    "sg:postcode":"55811",
    "sg:province":"MN",
    "sg:tags":[
        "plumber",
        "industrial",
        "contractors-commercial"
    ],
    "wof:name":"Guthrie Plumbing & Heating",
    "wof:placetype":"venue"
},
  "geometry": {"coordinates":[-92.15025,46.816587],"type":"Point"}
}