{
  "type": "Feature",
  "properties": {
    "iso:country":"US",
    "sg:address":"8459 10th Ave N",
    "sg:city":"Minneapolis",
    "sg:classifiers":[
        {
            "category":"Professional",
            "subcategory":"Accounting & Tax Preparation",
            "type":"Services"
        }
    ],
    "sg:phone":"+1 763 546 2455",
    "sg:postcode":"55427",
    "sg:province":"MN",
    "sg:tags":[
        "billing"
    ],
    "wof:name":"Rapid Return Medical Billing",
    "wof:placetype":"venue"
},
  "geometry": {"coordinates":[-93.38932,44.989014],"type":"Point"}
}