{
  "type": "Feature",
  "properties": {
    "addr:full":"2531 Marshall St NE Minneapolis MN 55418",
    "addr:housenumber":"2531",
    "addr:postcode":"55418",
    "addr:street":"Marshall St Ne",
    "iso:country":"US",
    "sg:address":"2531 Marshall St NE",
    "sg:city":"Minneapolis",
    "sg:classifiers":[
        {
            "category":"Wholesale",
            "subcategory":"Machinery & Supplies",
            "type":"Manufacturing & Wholesale Goods"
        }
    ],
    "sg:phone":"+1 612 788 2217",
    "sg:postcode":"55418",
    "sg:province":"MN",
    "sg:tags":[
        "printer",
        "cartridge"
    ],
    "wof:name":"C H Edlund Co",
    "wof:placetype":"venue"
},
  "geometry": {"coordinates":[-93.27192599999999,45.014965],"type":"Point"}
}