{
  "type": "Feature",
  "properties": {
    "iso:country":"US",
    "sg:address":"10535 Roseanna Beach Rd NW",
    "sg:city":"Rice",
    "sg:classifiers":[
        {
            "category":"Insurance",
            "subcategory":"Insurance Agent",
            "type":"Services"
        }
    ],
    "sg:phone":"+1 320 393 2235",
    "sg:postcode":"56367",
    "sg:province":"MN",
    "wof:name":"Raveling Insurance",
    "wof:placetype":"venue"
},
  "geometry": {"coordinates":[-94.18550399999999,45.71739],"type":"Point"}
}