{
  "type": "Feature",
  "properties": {
    "iso:country":"US",
    "sg:address":"6631 Edgewood St",
    "sg:city":"Rockford",
    "sg:classifiers":[
        {
            "category":"Manufacturing",
            "subcategory":"Chemicals & Compounds",
            "type":"Manufacturing & Wholesale Goods"
        },
        {
            "category":"Building & Trades",
            "subcategory":"Cleaning & Sanitation",
            "type":"Services"
        },
        {
            "category":"Building & Trades",
            "subcategory":"Equipment Rental",
            "type":"Services"
        }
    ],
    "sg:phone":"+1 763 477 6658",
    "sg:postcode":"55373",
    "sg:province":"MN",
    "sg:tags":[
        "systems-pressure",
        "steam",
        "indust-wholesale",
        "manufacturer"
    ],
    "wof:name":"Kew Cleaning Systems",
    "wof:placetype":"venue"
},
  "geometry": {"coordinates":[-93.734917,45.095695],"type":"Point"}
}