{
  "type": "Feature",
  "properties": {
    "addr:full":"37451 Tiger St NW Princeton MN 55371",
    "addr:housenumber":"37451",
    "addr:postcode":"55371",
    "addr:street":"Tiger St Nw",
    "iso:country":"US",
    "sg:address":"37451 Tiger St NW",
    "sg:city":"Princeton",
    "sg:phone":"+1 763 389 9582",
    "sg:postcode":"55371",
    "sg:province":"MN",
    "sg:tags":[
        "farm",
        "corn",
        "soybean"
    ],
    "wof:name":"Russell Hoeft",
    "wof:placetype":"venue"
},
  "geometry": {"coordinates":[-93.49186899999999,45.64631],"type":"Point"}
}