{
  "type": "Feature",
  "properties": {
    "iso:country":"US",
    "sg:address":"42412 US Hwy 75 NW",
    "sg:city":"Stephen",
    "sg:classifiers":[
        {
            "category":"Farming",
            "subcategory":"Farm & Veterinary Services",
            "type":"Manufacturing & Wholesale Goods"
        }
    ],
    "sg:phone":"+1 218 478 3000",
    "sg:postcode":"56757",
    "sg:province":"MN",
    "sg:tags":[
        "crop"
    ],
    "wof:name":"Agri Spreading Inc",
    "wof:placetype":"venue"
},
  "geometry": {"coordinates":[-96.88089100000001,48.485351],"type":"Point"}
}