{
  "type": "Feature",
  "properties": {
    "iso:country":"US",
    "sg:address":"5196 Rice Lake Rd",
    "sg:city":"Duluth",
    "sg:classifiers":[
        {
            "category":"Building & Trades",
            "subcategory":"Equipment Rental",
            "type":"Services"
        }
    ],
    "sg:phone":"+1 218 727 5724",
    "sg:postcode":"55803",
    "sg:province":"MN",
    "wof:name":"Muellner Rental",
    "wof:placetype":"venue"
},
  "geometry": {"coordinates":[-92.153553,46.888899],"type":"Point"}
}