{
  "type": "Feature",
  "properties": {
    "addr:full":"10010 Bluff Rd Eden Prairie MN 55347",
    "addr:housenumber":"10010",
    "addr:postcode":"55347",
    "addr:street":"Bluff Rd",
    "iso:country":"US",
    "sg:address":"10010 Bluff Rd",
    "sg:city":"Eden Prairie",
    "sg:classifiers":[
        {
            "category":"Communications",
            "type":"Services"
        }
    ],
    "sg:phone":"+1 952 944 5532",
    "sg:postcode":"55347",
    "sg:province":"MN",
    "sg:tags":[
        "communication"
    ],
    "wof:name":"Aqua Media Networks",
    "wof:placetype":"venue"
},
  "geometry": {"coordinates":[-93.404747,44.814003],"type":"Point"}
}