{
  "type": "Feature",
  "properties": {
    "iso:country":"US",
    "sg:address":"14901 Co Hwy 29",
    "sg:city":"Frazee",
    "sg:classifiers":[
        {
            "category":"Health Services",
            "subcategory":"Nursing And Care Facility",
            "type":"Services"
        }
    ],
    "sg:phone":"+1 218 334 5651",
    "sg:postcode":"56544",
    "sg:province":"MN",
    "wof:name":"Smith Group Home",
    "wof:placetype":"venue"
},
  "geometry": {"coordinates":[-95.71123,46.784983],"type":"Point"}
}