{
  "type": "Feature",
  "properties": {
    "addr:full":"2001 2nd St SW Rochester MN 55902",
    "addr:housenumber":"2001",
    "addr:postcode":"55902",
    "addr:street":"2Nd St Sw",
    "iso:country":"US",
    "sg:address":"2001 2nd St SW",
    "sg:city":"Rochester",
    "sg:classifiers":[
        {
            "category":"Banks & Credit Unions",
            "subcategory":"Investment Brokerage",
            "type":"Services"
        }
    ],
    "sg:phone":"+1 507 285 3337",
    "sg:postcode":"55902",
    "sg:province":"MN",
    "wof:name":"Amundson Investment Management",
    "wof:placetype":"venue"
},
  "geometry": {"coordinates":[-92.49526899999999,44.021599],"type":"Point"}
}