{
  "type": "Feature",
  "properties": {
    "iso:country":"US",
    "sg:address":"395 S Main St",
    "sg:city":"Zumbrota",
    "sg:classifiers":[
        {
            "category":"Banks & Credit Unions",
            "subcategory":"Investment Brokerage",
            "type":"Services"
        },
        {
            "category":"Banks & Credit Unions",
            "subcategory":"Bank",
            "type":"Services"
        },
        {
            "category":"Banks & Credit Unions",
            "subcategory":"Financial Services",
            "type":"Services"
        }
    ],
    "sg:phone":"+1 507 732 5499",
    "sg:postcode":"55992",
    "sg:province":"MN",
    "sg:tags":[
        "mutual",
        "retirement",
        "broker",
        "fund",
        "planning",
        "security",
        "bond",
        "stock"
    ],
    "sg:website":"http://www.edwardjones.com/en_US/fa/index.html&CIRN=373535",
    "wof:name":"Edward Jones - Zumbrota Financial Advisor - Mark A Behrends",
    "wof:placetype":"venue"
},
  "geometry": {"coordinates":[-92.66915,44.290555],"type":"Point"}
}