{
  "type": "Feature",
  "properties": {
    "addr:full":"7300 France Ave S Edina MN 55435",
    "addr:housenumber":"7300",
    "addr:postcode":"55435",
    "addr:street":"France Ave S",
    "iso:country":"US",
    "sg:address":"7300 France Ave S",
    "sg:city":"Edina",
    "sg:classifiers":[
        {
            "category":"Building & Trades",
            "subcategory":"Construction",
            "type":"Services"
        }
    ],
    "sg:phone":"+1 952 897 1771",
    "sg:postcode":"55435",
    "sg:province":"MN",
    "sg:tags":[
        "roofing",
        "contractor"
    ],
    "wof:name":"Williams Family Roofing",
    "wof:placetype":"venue"
},
  "geometry": {"coordinates":[-93.32902,44.872228],"type":"Point"}
}