{
  "type": "Feature",
  "properties": {
    "iso:country":"US",
    "sg:address":"3347 Fillmore St. NE",
    "sg:city":"Minneapolis",
    "sg:classifiers":[
        {
            "category":"Shopping",
            "subcategory":"Pets & Pet Supplies",
            "type":"Retail Goods"
        }
    ],
    "sg:phone":"+1 612 788 1504",
    "sg:postcode":"55418",
    "sg:province":"MN",
    "sg:tags":[
        "store"
    ],
    "sg:website":"www.dogbedsforless.com/",
    "wof:name":"Dog Beds for Less",
    "wof:placetype":"venue"
},
  "geometry": {"coordinates":[-93.242255,45.028483],"type":"Point"}
}