{
  "type": "Feature",
  "properties": {
    "iso:country":"US",
    "sg:address":"14205 S 11th Ave",
    "sg:city":"Burnsville",
    "sg:classifiers":[
        {
            "category":"Shopping",
            "type":"Retail Goods"
        }
    ],
    "sg:phone":"+1 952 736 2900",
    "sg:postcode":"55337",
    "sg:province":"MN",
    "sg:tags":[
        "merchandise"
    ],
    "wof:name":"Copier Warehouse",
    "wof:placetype":"venue"
},
  "geometry": {"coordinates":[-93.259421,44.744525],"type":"Point"}
}