{
  "type": "Feature",
  "properties": {
    "iso:country":"US",
    "sg:address":"1733 Pine Cone Rd N",
    "sg:city":"Sartell",
    "sg:classifiers":[
        {
            "category":"Health Services",
            "subcategory":"Chiropractor",
            "type":"Services"
        }
    ],
    "sg:phone":"+1 320 255 0961",
    "sg:postcode":"56377",
    "sg:province":"MN",
    "wof:name":"Chiropractic Performance Ctr",
    "wof:placetype":"venue"
},
  "geometry": {"coordinates":[-94.222235,45.644847],"type":"Point"}
}