{
  "type": "Feature",
  "properties": {
    "addr:full":"253 2nd St SW Perham MN 56573",
    "addr:housenumber":"253",
    "addr:postcode":"56573",
    "addr:street":"2Nd St Sw",
    "iso:country":"US",
    "sg:address":"253 2nd St SW",
    "sg:city":"Perham",
    "sg:classifiers":[
        {
            "category":"Education",
            "subcategory":"School",
            "type":"Public Place"
        }
    ],
    "sg:phone":"+1 218 346 6190",
    "sg:postcode":"56573",
    "sg:province":"MN",
    "wof:name":"St Henry Area School",
    "wof:placetype":"venue"
},
  "geometry": {"coordinates":[-95.57572,46.59432],"type":"Point"}
}