{
  "type": "Feature",
  "properties": {
    "iso:country":"US",
    "sg:address":"11545 Lakeland Dr",
    "sg:city":"Osseo",
    "sg:classifiers":[
        {
            "category":"Wholesale",
            "subcategory":"Electrical",
            "type":"Manufacturing & Wholesale Goods"
        }
    ],
    "sg:phone":"+1 763 425 1032",
    "sg:postcode":"55369",
    "sg:province":"MN",
    "sg:tags":[
        "equipment"
    ],
    "wof:name":"Chris Meehl",
    "wof:placetype":"venue"
},
  "geometry": {"coordinates":[-93.426868,45.12528],"type":"Point"}
}