{
  "type": "Feature",
  "properties": {
    "addr:full":"3625 409th Ave NW Braham MN 55006",
    "addr:housenumber":"3625",
    "addr:postcode":"55006",
    "addr:street":"409Th Ave Nw",
    "iso:country":"US",
    "sg:address":"3625 409th Ave NW",
    "sg:city":"Braham",
    "sg:classifiers":[
        {
            "category":"Manufacturing",
            "subcategory":"Metals",
            "type":"Manufacturing & Wholesale Goods"
        }
    ],
    "sg:phone":"+1 320 396 3664",
    "sg:postcode":"55006",
    "sg:province":"MN",
    "sg:tags":[
        "abrasive",
        "product",
        "metalwork",
        "sheet",
        "mfg"
    ],
    "wof:name":"Eggert Ornamental Iron",
    "wof:placetype":"venue"
},
  "geometry": {"coordinates":[-93.36005299999999,45.709159],"type":"Point"}
}