{
  "type": "Feature",
  "properties": {
    "addr:full":"722 Sherburne Ave Saint Paul MN 55104",
    "addr:housenumber":"722",
    "addr:postcode":"55104",
    "addr:street":"Sherburne Ave",
    "iso:country":"US",
    "sg:address":"722 Sherburne Ave",
    "sg:city":"Saint Paul",
    "sg:classifiers":[
        {
            "category":"Recreation",
            "type":"Entertainment"
        }
    ],
    "sg:phone":"+1 651 222 2423",
    "sg:postcode":"55104",
    "sg:province":"MN",
    "wof:name":"Art Tysk Enterprises",
    "wof:placetype":"venue"
},
  "geometry": {"coordinates":[-93.130129,44.956551],"type":"Point"}
}