{
  "type": "Feature",
  "properties": {
    "addr:full":"11020 70th St NE Kerkhoven MN 56252",
    "addr:housenumber":"11020",
    "addr:postcode":"56252",
    "addr:street":"70Th St Ne",
    "iso:country":"US",
    "sg:address":"11020 70th St NE",
    "sg:city":"Kerkhoven",
    "sg:classifiers":[
        {
            "category":"Manufacturing",
            "subcategory":"Food",
            "type":"Manufacturing & Wholesale Goods"
        },
        {
            "category":"Farming",
            "subcategory":"Farm",
            "type":"Manufacturing & Wholesale Goods"
        }
    ],
    "sg:phone":"+1 320 264 1131",
    "sg:postcode":"56252",
    "sg:province":"MN",
    "sg:tags":[
        "corn",
        "product"
    ],
    "wof:name":"Randall Holmgren",
    "wof:placetype":"venue"
},
  "geometry": {"coordinates":[-95.369418,45.123639],"type":"Point"}
}