{
  "type": "Feature",
  "properties": {
    "iso:country":"US",
    "sg:address":"1400 Co Rd 101",
    "sg:city":"Minneapolis",
    "sg:classifiers":[
        {
            "category":"Personal",
            "subcategory":"Beauty Salon",
            "type":"Services"
        }
    ],
    "sg:phone":"+1 763 476 1158",
    "sg:postcode":"55447",
    "sg:province":"MN",
    "sg:tags":[
        "manicuring"
    ],
    "wof:name":"Salon Nails",
    "wof:placetype":"venue"
},
  "geometry": {"coordinates":[-93.50192199999999,44.995514],"type":"Point"}
}