{
  "type": "Feature",
  "properties": {
    "iso:country":"US",
    "sg:address":"9440 Clubhouse Rd",
    "sg:city":"Eden Prairie",
    "sg:classifiers":[
        {
            "category":"Wholesale",
            "subcategory":"Chemicals & Plastics",
            "type":"Manufacturing & Wholesale Goods"
        },
        {
            "category":"Manufacturing",
            "subcategory":"Chemicals & Compounds",
            "type":"Manufacturing & Wholesale Goods"
        }
    ],
    "sg:phone":"+1 952 943 1966",
    "sg:postcode":"55347",
    "sg:province":"MN",
    "sg:tags":[
        "material",
        "broker",
        "recycles"
    ],
    "wof:name":"T S Investment Company",
    "wof:placetype":"venue"
},
  "geometry": {"coordinates":[-93.41009699999999,44.832664],"type":"Point"}
}