{
  "type": "Feature",
  "properties": {
    "iso:country":"US",
    "sg:address":"32239 Teal Ave",
    "sg:city":"Shafer",
    "sg:classifiers":[
        {
            "category":"Home & Garden",
            "subcategory":"Building Materials",
            "type":"Retail Goods"
        },
        {
            "category":"Building & Trades",
            "subcategory":"Plumbing",
            "type":"Services"
        },
        {
            "category":"Home & Garden",
            "subcategory":"Home Furnishings",
            "type":"Retail Goods"
        },
        {
            "category":"Home & Garden",
            "subcategory":"Hardware",
            "type":"Retail Goods"
        },
        {
            "category":"Building & Trades",
            "subcategory":"Construction",
            "type":"Services"
        }
    ],
    "sg:phone":"+1 612 852 8918",
    "sg:postcode":"55074",
    "sg:province":"MN",
    "sg:tags":[
        "heater",
        "bathroom",
        "industrial",
        "refinish",
        "plumber",
        "contractor",
        "water",
        "piping",
        "contractors-commercial",
        "sinks-repair",
        "bathtub",
        "remodeling"
    ],
    "wof:name":"Hansen Plumbing",
    "wof:placetype":"venue"
},
  "geometry": {"coordinates":[-92.71305,45.411768],"type":"Point"}
}