{
  "type": "Feature",
  "properties": {
    "iso:country":"US",
    "sg:address":"9301 Science Center Dr",
    "sg:city":"Minneapolis",
    "sg:classifiers":[
        {
            "category":"Real Estate",
            "subcategory":"Real Estate Operator",
            "type":"Services"
        }
    ],
    "sg:phone":"+1 952 893 6751",
    "sg:postcode":"55428",
    "sg:province":"MN",
    "sg:tags":[
        "building",
        "nonresidential"
    ],
    "wof:name":"Industry Park Building",
    "wof:placetype":"venue"
},
  "geometry": {"coordinates":[-93.399643,45.050667],"type":"Point"}
}