{
  "type": "Feature",
  "properties": {
    "addr:full":"2934 Chicago Ave S Minneapolis MN 55407",
    "addr:housenumber":"2934",
    "addr:postcode":"55407",
    "addr:street":"Chicago Ave S",
    "iso:country":"US",
    "sg:address":"2934 Chicago Ave S",
    "sg:city":"Minneapolis",
    "sg:classifiers":[
        {
            "category":"Wholesale",
            "subcategory":"Home Furnishings",
            "type":"Manufacturing & Wholesale Goods"
        }
    ],
    "sg:phone":"+1 612 370 1921",
    "sg:postcode":"55407",
    "sg:province":"MN",
    "sg:tags":[
        "covering",
        "floor",
        "contractor"
    ],
    "wof:name":"Murray Floor Covering Co",
    "wof:placetype":"venue"
},
  "geometry": {"coordinates":[-93.262742,44.949016],"type":"Point"}
}