{
  "type": "Feature",
  "properties": {
    "addr:full":"912 E 24th St Minneapolis MN 55404",
    "addr:housenumber":"912",
    "addr:postcode":"55404",
    "addr:street":"E 24Th St",
    "iso:country":"US",
    "sg:address":"912 E 24th St",
    "sg:city":"Minneapolis",
    "sg:classifiers":[
        {
            "category":"Banks & Credit Unions",
            "subcategory":"Bank",
            "type":"Services"
        }
    ],
    "sg:phone":"+1 612 252 1412",
    "sg:postcode":"55404",
    "sg:province":"MN",
    "sg:tags":[
        "depository",
        "banking"
    ],
    "wof:name":"Salama Express",
    "wof:placetype":"venue"
},
  "geometry": {"coordinates":[-93.260166,44.959202],"type":"Point"}
}