{
  "type": "Feature",
  "properties": {
    "addr:full":"1930 E 86th St Minneapolis MN 55425",
    "addr:housenumber":"1930",
    "addr:postcode":"55425",
    "addr:street":"E 86Th St",
    "iso:country":"US",
    "sg:address":"1930 E 86th St",
    "sg:city":"Minneapolis",
    "sg:classifiers":[
        {
            "category":"Professional",
            "subcategory":"Computer Services",
            "type":"Services"
        }
    ],
    "sg:phone":"+1 952 851 9508",
    "sg:postcode":"55425",
    "sg:province":"MN",
    "sg:tags":[
        "information",
        "processing",
        "datum",
        "retrieval"
    ],
    "wof:name":"Mc Clelland Enterprises",
    "wof:placetype":"venue"
},
  "geometry": {"coordinates":[-93.243872,44.848031],"type":"Point"}
}