{
  "type": "Feature",
  "properties": {
    "iso:country":"US",
    "sg:address":"33505 109th Ave",
    "sg:city":"Menahga",
    "sg:classifiers":[
        {
            "category":"Professional",
            "type":"Services"
        }
    ],
    "sg:phone":"+1 218 564 5253",
    "sg:postcode":"56464",
    "sg:province":"MN",
    "wof:name":"Haverinen Brothers",
    "wof:placetype":"venue"
},
  "geometry": {"coordinates":[-95.142732,46.70878],"type":"Point"}
}