{
  "type": "Feature",
  "properties": {
    "addr:full":"2842 183rd Ave NE Wyoming MN 55092",
    "addr:housenumber":"2842",
    "addr:postcode":"55092",
    "addr:street":"183Rd Ave Ne",
    "iso:country":"US",
    "sg:address":"2842 183rd Ave NE",
    "sg:city":"Wyoming",
    "sg:classifiers":[
        {
            "category":"Building & Trades",
            "subcategory":"Electrical",
            "type":"Services"
        }
    ],
    "sg:phone":"+1 763 434 7465",
    "sg:postcode":"55092",
    "sg:province":"MN",
    "sg:tags":[
        "electric",
        "contractor"
    ],
    "wof:name":"North End Electrical Svc",
    "wof:placetype":"venue"
},
  "geometry": {"coordinates":[-93.198291,45.301232],"type":"Point"}
}