{
  "type": "Feature",
  "properties": {
    "addr:full":"4015 70th Ave SE Clara City MN 56222",
    "addr:housenumber":"4015",
    "addr:postcode":"56222",
    "addr:street":"70Th Ave Se",
    "iso:country":"US",
    "sg:address":"4015 70th Ave SE",
    "sg:city":"Clara City",
    "sg:classifiers":[
        {
            "category":"Personal",
            "subcategory":"Beauty Salon",
            "type":"Services"
        }
    ],
    "sg:phone":"+1 320 367 2153",
    "sg:postcode":"56222",
    "sg:province":"MN",
    "sg:tags":[
        "shop"
    ],
    "wof:name":"Jens Ultimate Styling & Tanni",
    "wof:placetype":"venue"
},
  "geometry": {"coordinates":[-95.452482,44.963061],"type":"Point"}
}