{
  "type": "Feature",
  "properties": {
    "iso:country":"US",
    "sg:address":"10521 Nassau St NE",
    "sg:city":"Minneapolis",
    "sg:classifiers":[
        {
            "category":"Professional",
            "subcategory":"Printing & Photocopies",
            "type":"Services"
        }
    ],
    "sg:phone":"+1 763 784 0358",
    "sg:postcode":"55449",
    "sg:province":"MN",
    "sg:tags":[
        "services-commercial",
        "duplicating",
        "copying"
    ],
    "wof:name":"Ink Spot Printing",
    "wof:placetype":"venue"
},
  "geometry": {"coordinates":[-93.217682,45.161006],"type":"Point"}
}