{
  "type": "Feature",
  "properties": {
    "iso:country":"US",
    "sg:address":"565 67th Ave NE",
    "sg:city":"Minneapolis",
    "sg:classifiers":[
        {
            "category":"Recreation",
            "type":"Entertainment"
        }
    ],
    "sg:phone":"+1 763 572 0779",
    "sg:postcode":"55432",
    "sg:province":"MN",
    "wof:name":"Super Skate",
    "wof:placetype":"venue"
},
  "geometry": {"coordinates":[-93.255477,45.088276],"type":"Point"}
}