{
  "type": "Feature",
  "properties": {
    "addr:full":"565 67th Ave NE Minneapolis MN 55432",
    "addr:housenumber":"565",
    "addr:postcode":"55432",
    "addr:street":"67Th Ave Ne",
    "iso:country":"US",
    "sg:address":"565 67th Ave NE",
    "sg:city":"Minneapolis",
    "sg:classifiers":[
        {
            "category":"Recreation",
            "type":"Entertainment"
        }
    ],
    "sg:phone":"+1 763 572 0779",
    "sg:postcode":"55432",
    "sg:province":"MN",
    "wof:name":"Super Skate",
    "wof:placetype":"venue"
},
  "geometry": {"coordinates":[-93.255477,45.088276],"type":"Point"}
}