{
  "type": "Feature",
  "properties": {
    "iso:country":"US",
    "sg:address":"18 Main St S",
    "sg:city":"Hutchinson",
    "sg:classifiers":[
        {
            "category":"Restaurant",
            "type":"Food & Drink"
        }
    ],
    "sg:phone":"+1 320 587 8450",
    "sg:postcode":"55350",
    "sg:province":"MN",
    "wof:name":"Coffee Co",
    "wof:placetype":"venue"
},
  "geometry": {"coordinates":[-94.369379,44.892066],"type":"Point"}
}