{
  "type": "Feature",
  "properties": {
    "addr:full":"1082 Grand Ave St Paul MN 55105",
    "addr:housenumber":"1082",
    "addr:postcode":"55105",
    "addr:street":"Grand Ave",
    "iso:country":"US",
    "sg:address":"1082 Grand Ave",
    "sg:city":"St Paul",
    "sg:classifiers":[
        {
            "category":"Shopping",
            "subcategory":"Gifts & Souvenirs",
            "type":"Retail Goods"
        }
    ],
    "sg:phone":"+1 651 222 0321",
    "sg:postcode":"55105",
    "sg:province":"MN",
    "sg:tags":[
        "shop"
    ],
    "sg:website":"www.bibelotshops.com",
    "wof:name":"Bibelot Shop",
    "wof:placetype":"venue"
},
  "geometry": {"coordinates":[-93.145296,44.939916],"type":"Point"}
}