{
  "type": "Feature",
  "properties": {
    "addr:full":"19450 Normandale Rd Prior Lake MN 55372",
    "addr:housenumber":"19450",
    "addr:postcode":"55372",
    "addr:street":"Normandale Rd",
    "iso:country":"US",
    "sg:address":"19450 Normandale Rd",
    "sg:city":"Prior Lake",
    "sg:classifiers":[
        {
            "category":"Building & Trades",
            "subcategory":"Construction",
            "type":"Services"
        }
    ],
    "sg:phone":"+1 952 447 5733",
    "sg:postcode":"55372",
    "sg:province":"MN",
    "sg:tags":[
        "paving",
        "asphalt",
        "contractor"
    ],
    "wof:name":"Radloff & Weber Blacktopping",
    "wof:placetype":"venue"
},
  "geometry": {"coordinates":[-93.348771,44.668864],"type":"Point"}
}