{
  "type": "Feature",
  "properties": {
    "addr:full":"1611 16th St NW Willmar MN 56201",
    "addr:housenumber":"1611",
    "addr:postcode":"56201",
    "addr:street":"16Th St Nw",
    "iso:country":"US",
    "sg:address":"1611 16th St NW",
    "sg:city":"Willmar",
    "sg:classifiers":[
        {
            "category":"Building & Trades",
            "subcategory":"Construction",
            "type":"Services"
        }
    ],
    "sg:phone":"+1 320 214 7529",
    "sg:postcode":"56201",
    "sg:province":"MN",
    "sg:tags":[
        "house"
    ],
    "wof:name":"Adam Knight Construction",
    "wof:placetype":"venue"
},
  "geometry": {"coordinates":[-95.064049,45.139943],"type":"Point"}
}