{
  "type": "Feature",
  "properties": {
    "addr:full":"16634 Imperial Ct Lakeville MN 55044",
    "addr:housenumber":"16634",
    "addr:postcode":"55044",
    "addr:street":"Imperial Ct",
    "iso:country":"US",
    "sg:address":"16634 Imperial Ct",
    "sg:city":"Lakeville",
    "sg:classifiers":[
        {
            "category":"Professional",
            "subcategory":"Computer Services",
            "type":"Services"
        }
    ],
    "sg:phone":"+1 952 953 9600",
    "sg:postcode":"55044",
    "sg:province":"MN",
    "sg:tags":[
        "programing",
        "custom"
    ],
    "wof:name":"Zaichik Consulting Inc",
    "wof:placetype":"venue"
},
  "geometry": {"coordinates":[-93.253456,44.708444],"type":"Point"}
}