{
  "type": "Feature",
  "properties": {
    "iso:country":"US",
    "sg:address":"2544 Hennepin Ave",
    "sg:city":"Minneapolis",
    "sg:classifiers":[
        {
            "category":"Personal",
            "subcategory":"Nail Salon",
            "type":"Services"
        }
    ],
    "sg:phone":"+1 612 977 9047",
    "sg:postcode":"55405",
    "sg:province":"MN",
    "wof:name":"Daisy Nail",
    "wof:placetype":"venue"
},
  "geometry": {"coordinates":[-93.29679899999999,44.9557],"type":"Point"}
}