{
  "type": "Feature",
  "properties": {
    "addr:full":"225 Triangle Ln N Jordan MN 55352",
    "addr:housenumber":"225",
    "addr:postcode":"55352",
    "addr:street":"Triangle Ln N",
    "iso:country":"US",
    "sg:address":"225 Triangle Ln N",
    "sg:city":"Jordan",
    "sg:classifiers":[
        {
            "category":"Restaurant",
            "type":"Food & Drink"
        }
    ],
    "sg:menulink":"http://www.allmenus.com/mn/jordan/58448-dominos-pizza/menu/",
    "sg:phone":"+1 952 492 5322",
    "sg:postcode":"55352",
    "sg:province":"MN",
    "sg:tags":[
        "american",
        "wing",
        "pizza"
    ],
    "wof:name":"Domino's Pizza",
    "wof:placetype":"venue"
},
  "geometry": {"coordinates":[-93.63719,44.670802],"type":"Point"}
}