{
  "type": "Feature",
  "properties": {
    "iso:country":"US",
    "sg:address":"13105 Main St",
    "sg:city":"Rogers",
    "sg:classifiers":[
        {
            "category":"Restaurant",
            "type":"Food & Drink"
        }
    ],
    "sg:phone":"+1 763 428 4176",
    "sg:postcode":"55374",
    "sg:province":"MN",
    "sg:tags":[
        "house",
        "steak",
        "barbecue"
    ],
    "wof:name":"Cottage Grill",
    "wof:placetype":"venue"
},
  "geometry": {"coordinates":[-93.55262,45.192436],"type":"Point"}
}