{
  "type": "Feature",
  "properties": {
    "addr:full":"1837 E 38th St Minneapolis MN 55407",
    "addr:housenumber":"1837",
    "addr:postcode":"55407",
    "addr:street":"E 38Th St",
    "iso:country":"US",
    "sg:address":"1837 E 38th St",
    "sg:city":"Minneapolis",
    "sg:classifiers":[
        {
            "category":"Restaurant",
            "type":"Food & Drink"
        }
    ],
    "sg:phone":"+1 612 728 9591",
    "sg:postcode":"55407",
    "sg:province":"MN",
    "sg:tags":[
        "eating"
    ],
    "wof:name":"La Loma",
    "wof:placetype":"venue"
},
  "geometry": {"coordinates":[-93.2466,44.934114],"type":"Point"}
}