{
  "type": "Feature",
  "properties": {
    "iso:country":"US",
    "sg:address":"5985 Marsh Lake Rd",
    "sg:city":"Victoria",
    "sg:classifiers":[
        {
            "category":"Building & Trades",
            "subcategory":"Plumbing",
            "type":"Services"
        }
    ],
    "sg:phone":"+1 952 443 0034",
    "sg:postcode":"55386",
    "sg:province":"MN",
    "sg:tags":[
        "plumbing",
        "contractor"
    ],
    "wof:name":"Victoria Plumbing Inc",
    "wof:placetype":"venue"
},
  "geometry": {"coordinates":[-93.68285,44.833995],"type":"Point"}
}