{
  "type": "Feature",
  "properties": {
    "addr:full":"207 Downtown Plz Fairmont MN 56031",
    "addr:postcode":"56031",
    "iso:country":"US",
    "sg:address":"207 Downtown Plz",
    "sg:city":"Fairmont",
    "sg:classifiers":[
        {
            "category":"Shopping",
            "subcategory":"Musical Instruments",
            "type":"Retail Goods"
        },
        {
            "category":"Shopping",
            "subcategory":"Computers & Home Electronics",
            "type":"Retail Goods"
        }
    ],
    "sg:phone":"+1 507 235 5190",
    "sg:postcode":"56031",
    "sg:province":"MN",
    "sg:tags":[
        "guitar",
        "stereo",
        "amplifier",
        "high",
        "stereophonic",
        "video",
        "equipment-dealers",
        "fidelity",
        "audio"
    ],
    "wof:name":"Gemini Musical Suppliers",
    "wof:placetype":"venue"
},
  "geometry": {"coordinates":[-94.462311,43.654005],"type":"Point"}
}