{
  "type": "Feature",
  "properties": {
    "iso:country":"US",
    "sg:address":"1500 Jackson St NE Dock 7",
    "sg:city":"Minneapolis",
    "sg:classifiers":[
        {
            "category":"Shopping",
            "subcategory":"Antiques",
            "type":"Retail Goods"
        },
        {
            "category":"Home & Garden",
            "subcategory":"Furniture",
            "type":"Retail Goods"
        }
    ],
    "sg:phone":"+1 612 706 3232",
    "sg:postcode":"55413",
    "sg:province":"MN",
    "sg:tags":[
        "store"
    ],
    "wof:name":"reSee House",
    "wof:placetype":"venue"
},
  "geometry": {"coordinates":[-93.24976599999999,45.003573],"type":"Point"}
}