{
  "type": "Feature",
  "properties": {
    "iso:country":"US",
    "sg:address":"6500 Labeaux Ave NE",
    "sg:city":"Albertville",
    "sg:classifiers":[
        {
            "category":"Shopping",
            "subcategory":"Clothing, Apparel, & Fashions",
            "type":"Retail Goods"
        }
    ],
    "sg:phone":"+1 763 425 4321",
    "sg:postcode":"55301",
    "sg:province":"MN",
    "sg:tags":[
        "infant",
        "wear"
    ],
    "wof:name":"Hartstrings LLC",
    "wof:placetype":"venue"
},
  "geometry": {"coordinates":[-93.663219,45.247229],"type":"Point"}
}