{
  "type": "Feature",
  "properties": {
    "iso:country":"US",
    "sg:address":"230 E Skyline Pkwy",
    "sg:city":"Duluth",
    "sg:classifiers":[
        {
            "category":"Place Of Worship",
            "subcategory":"Church",
            "type":"Public Place"
        },
        {
            "category":"Place Of Worship",
            "type":"Public Place"
        },
        {
            "category":"Organizations",
            "subcategory":"Religious Organization",
            "type":"Services"
        }
    ],
    "sg:phone":"+1 218 727 5021",
    "sg:postcode":"55811",
    "sg:province":"MN",
    "sg:tags":[
        "churches-methodist"
    ],
    "sg:website":"http://www.fumcduluth.com",
    "wof:name":"First United Methodist Church",
    "wof:placetype":"venue"
},
  "geometry": {"coordinates":[-92.106928,46.796833],"type":"Point"}
}