{
  "type": "Feature",
  "properties": {
    "addr:full":"12721 Central Ave NE Minneapolis MN 55434",
    "addr:housenumber":"12721",
    "addr:postcode":"55434",
    "addr:street":"Central Ave Ne",
    "iso:country":"US",
    "sg:address":"12721 Central Ave NE",
    "sg:city":"Minneapolis",
    "sg:classifiers":[
        {
            "category":"Ice Cream",
            "type":"Food & Drink"
        }
    ],
    "sg:menulink":"http://www.allmenus.com/mn/blaine/168216-dairy-queen/menu/",
    "sg:phone":"+1 763 755 8600",
    "sg:postcode":"55434",
    "sg:province":"MN",
    "sg:tags":[
        "burger",
        "american"
    ],
    "wof:name":"Dairy Queen",
    "wof:placetype":"venue"
},
  "geometry": {"coordinates":[-93.234086,45.202258],"type":"Point"}
}