{
  "type": "Feature",
  "properties": {
    "addr:full":"903 3rd Ave E Alexandria MN 56308",
    "addr:housenumber":"903",
    "addr:postcode":"56308",
    "addr:street":"3Rd Ave E",
    "iso:country":"US",
    "sg:address":"903 3rd Ave E",
    "sg:city":"Alexandria",
    "sg:classifiers":[
        {
            "category":"Restaurant",
            "type":"Food & Drink"
        }
    ],
    "sg:phone":"+1 320 762 5118",
    "sg:postcode":"56308",
    "sg:province":"MN",
    "sg:tags":[
        "cafe"
    ],
    "wof:name":"Lloyd's Cafe",
    "wof:placetype":"venue"
},
  "geometry": {"coordinates":[-95.364851,45.88944],"type":"Point"}
}