{
  "type": "Feature",
  "properties": {
    "iso:country":"US",
    "sg:address":"2100 Northdale Blvd NW",
    "sg:city":"Coon Rapids",
    "sg:classifiers":[
        {
            "category":"Food & Beverages",
            "subcategory":"Specialty",
            "type":"Retail Goods"
        }
    ],
    "sg:phone":"+1 763 754 2284",
    "sg:postcode":"55433",
    "sg:province":"MN",
    "sg:tags":[
        "vitamin"
    ],
    "wof:name":"Lifetime Health & Cafe",
    "wof:placetype":"venue"
},
  "geometry": {"coordinates":[-93.321077,45.182644],"type":"Point"}
}