{
  "type": "Feature",
  "properties": {
    "iso:country":"US",
    "sg:address":"6466 150th St SE",
    "sg:city":"Prior Lake",
    "sg:classifiers":[
        {
            "category":"Professional",
            "subcategory":"Management & Consulting",
            "type":"Services"
        }
    ],
    "sg:phone":"+1 952 447 6343",
    "sg:postcode":"55372",
    "sg:province":"MN",
    "sg:tags":[
        "business"
    ],
    "wof:name":"Benjamin Consulting LLC",
    "wof:placetype":"venue"
},
  "geometry": {"coordinates":[-93.391358,44.731855],"type":"Point"}
}