{
  "type": "Feature",
  "properties": {
    "addr:full":"335 Rolling Hills Dr Mound MN 55364",
    "addr:housenumber":"335",
    "addr:postcode":"55364",
    "addr:street":"Rolling Hills Dr Mound",
    "iso:country":"US",
    "sg:address":"335 Rolling Hills Dr",
    "sg:city":"Mound",
    "sg:classifiers":[
        {
            "category":"Social Services",
            "subcategory":"Child Care",
            "type":"Services"
        }
    ],
    "sg:phone":"+1 952 472 7140",
    "sg:postcode":"55364",
    "sg:province":"MN",
    "sg:tags":[
        "day"
    ],
    "wof:name":"Kristen R Palm",
    "wof:placetype":"venue"
},
  "geometry": {"coordinates":[-93.68103000000001,44.972614],"type":"Point"}
}