{
  "type": "Feature",
  "properties": {
    "addr:full":"805 Nokomis St Alexandria MN 56308",
    "addr:housenumber":"805",
    "addr:postcode":"56308",
    "addr:street":"Nokomis St",
    "iso:country":"US",
    "sg:address":"805 Nokomis St",
    "sg:city":"Alexandria",
    "sg:classifiers":[
        {
            "category":"Manufacturing",
            "subcategory":"Pet Food",
            "type":"Manufacturing & Wholesale Goods"
        }
    ],
    "sg:phone":"+1 320 763 5181",
    "sg:postcode":"56308",
    "sg:province":"MN",
    "sg:tags":[
        "feed"
    ],
    "wof:name":"Hubbard Feeds Inc",
    "wof:placetype":"venue"
},
  "geometry": {"coordinates":[-95.36663900000001,45.88352],"type":"Point"}
}