{
  "type": "Feature",
  "properties": {
    "addr:full":"1450 Gilmore Ave Winona MN 55987",
    "addr:housenumber":"1450",
    "addr:postcode":"55987",
    "addr:street":"Gilmore Ave",
    "iso:country":"US",
    "sg:address":"1450 Gilmore Ave",
    "sg:city":"Winona",
    "sg:classifiers":[
        {
            "category":"Travel",
            "subcategory":"Hotels & Motels",
            "type":"Entertainment"
        }
    ],
    "sg:phone":"+1 877 622 8420",
    "sg:postcode":"55987",
    "sg:province":"MN",
    "sg:tags":[
        "lodging"
    ],
    "sg:website":"http://www.webspawner.com/users/sterlingmotel",
    "wof:name":"Sterling Motel",
    "wof:placetype":"venue"
},
  "geometry": {"coordinates":[-91.67617799999999,44.048672],"type":"Point"}
}