{
  "type": "Feature",
  "properties": {
    "addr:full":"2616 E Swan Ave Saint Paul MN 55109",
    "addr:housenumber":"2616",
    "addr:postcode":"55109",
    "addr:street":"E Swan Ave",
    "iso:country":"US",
    "sg:address":"2616 E Swan Ave",
    "sg:city":"Saint Paul",
    "sg:classifiers":[
        {
            "category":"Professional",
            "subcategory":"Management & Consulting",
            "type":"Services"
        }
    ],
    "sg:phone":"+1 651 770 7319",
    "sg:postcode":"55109",
    "sg:province":"MN",
    "wof:name":"Northern Regional Sales",
    "wof:placetype":"venue"
},
  "geometry": {"coordinates":[-92.99111000000001,45.025282],"type":"Point"}
}