{
  "type": "Feature",
  "properties": {
    "addr:full":"490 E Lynnhurst Ave Saint Paul MN 55104",
    "addr:housenumber":"490",
    "addr:postcode":"55104",
    "addr:street":"E Lynnhurst Ave",
    "iso:country":"US",
    "sg:address":"490 E Lynnhurst Ave",
    "sg:city":"Saint Paul",
    "sg:classifiers":[
        {
            "category":"Social Services",
            "subcategory":"Adult Care",
            "type":"Services"
        }
    ],
    "sg:phone":"+1 651 646 1026",
    "sg:postcode":"55104",
    "sg:province":"MN",
    "sg:tags":[
        "residential"
    ],
    "wof:name":"Iris Park Commons",
    "wof:placetype":"venue"
},
  "geometry": {"coordinates":[-93.17970200000001,44.956251],"type":"Point"}
}