{
  "type": "Feature",
  "properties": {
    "addr:full":"6270 Westedge Blvd Mound MN 55364",
    "addr:housenumber":"6270",
    "addr:postcode":"55364",
    "addr:street":"Westedge Blvd",
    "iso:country":"US",
    "sg:address":"6270 Westedge Blvd",
    "sg:city":"Mound",
    "sg:classifiers":[
        {
            "category":"Utilities",
            "subcategory":"Water",
            "type":"Services"
        }
    ],
    "sg:phone":"+1 952 472 4288",
    "sg:postcode":"55364",
    "sg:province":"MN",
    "sg:tags":[
        "company",
        "sewage"
    ],
    "wof:name":"Metropolitan Council",
    "wof:placetype":"venue"
},
  "geometry": {"coordinates":[-93.681389,44.929545],"type":"Point"}
}