{
  "type": "Feature",
  "properties": {
    "iso:country":"US",
    "sg:address":"204 Central Ave",
    "sg:city":"Osseo",
    "sg:classifiers":[
        {
            "category":"Insurance",
            "subcategory":"Health Insurance",
            "type":"Services"
        },
        {
            "category":"Food & Beverages",
            "subcategory":"Groceries & Convenience Stores",
            "type":"Retail Goods"
        }
    ],
    "sg:phone":"+1 952 593 3000",
    "sg:postcode":"55569",
    "sg:province":"MN",
    "sg:tags":[
        "market"
    ],
    "sg:website":"www.indianfoodsco.com",
    "wof:name":"Indian Foods Company",
    "wof:placetype":"venue"
},
  "geometry": {"coordinates":[-93.40213199999999,45.118341],"type":"Point"}
}