{
  "type": "Feature",
  "properties": {
    "addr:full":"707 Southbend Ave Marshall MN 56258",
    "addr:housenumber":"707",
    "addr:postcode":"56258",
    "addr:street":"Southbend Ave",
    "iso:country":"US",
    "sg:address":"707 Southbend Ave",
    "sg:city":"Marshall",
    "sg:classifiers":[
        {
            "category":"Professional",
            "subcategory":"Accounting & Tax Preparation",
            "type":"Services"
        }
    ],
    "sg:phone":"+1 507 532 4393",
    "sg:postcode":"56258",
    "sg:province":"MN",
    "sg:tags":[
        "billing"
    ],
    "wof:name":"Med Services",
    "wof:placetype":"venue"
},
  "geometry": {"coordinates":[-95.799361,44.437728],"type":"Point"}
}