{
  "type": "Feature",
  "properties": {
    "iso:country":"US",
    "sg:address":"1161 Wayzata Blvd",
    "sg:city":"Wayzata",
    "sg:classifiers":[
        {
            "category":"Professional",
            "subcategory":"Advertising",
            "type":"Services"
        }
    ],
    "sg:phone":"+1 952 380 5080",
    "sg:postcode":"55391",
    "sg:province":"MN",
    "sg:website":"www.wayzata.com",
    "wof:name":"WAYZATA.COM",
    "wof:placetype":"venue"
},
  "geometry": {"coordinates":[-93.553589,44.984959],"type":"Point"}
}