{
  "type": "Feature",
  "properties": {
    "addr:full":"8525 Edinbrook Xing Minneapolis MN 55443",
    "addr:housenumber":"8525",
    "addr:postcode":"55443",
    "addr:street":"Edinbrook Xing",
    "iso:country":"US",
    "sg:address":"8525 Edinbrook Xing",
    "sg:city":"Minneapolis",
    "sg:classifiers":[
        {
            "category":"Organizations",
            "subcategory":"Community Association",
            "type":"Services"
        }
    ],
    "sg:phone":"+1 763 424 8525",
    "sg:postcode":"55443",
    "sg:province":"MN",
    "sg:tags":[
        "homeowner"
    ],
    "wof:name":"Pheasant Ridge 5th Association",
    "wof:placetype":"venue"
},
  "geometry": {"coordinates":[-93.32430100000001,45.108935],"type":"Point"}
}