{
  "type": "Feature",
  "properties": {
    "iso:country":"US",
    "sg:address":"24950 Wall Lake Point Cir",
    "sg:city":"Fergus Falls",
    "sg:classifiers":[
        {
            "category":"Building & Trades",
            "subcategory":"Construction",
            "type":"Services"
        }
    ],
    "sg:phone":"+1 218 736 4426",
    "sg:postcode":"56537",
    "sg:province":"MN",
    "sg:tags":[
        "house"
    ],
    "wof:name":"Komestakes Construction",
    "wof:placetype":"venue"
},
  "geometry": {"coordinates":[-95.97126,46.272202],"type":"Point"}
}