{
  "type": "Feature",
  "properties": {
    "addr:full":"8100 24th Ave S Minneapolis MN 55425",
    "addr:housenumber":"8100",
    "addr:postcode":"55425",
    "addr:street":"24Th Ave S",
    "iso:country":"US",
    "sg:address":"8100 24th Ave S",
    "sg:city":"Minneapolis",
    "sg:classifiers":[
        {
            "category":"Shopping",
            "subcategory":"Shoes",
            "type":"Retail Goods"
        }
    ],
    "sg:phone":"+1 952 883 0331",
    "sg:postcode":"55425",
    "sg:province":"MN",
    "sg:tags":[
        "store"
    ],
    "sg:website":"http://www.rockport.com",
    "wof:name":"Rockport",
    "wof:placetype":"venue"
},
  "geometry": {"coordinates":[-93.237717,44.856548],"type":"Point"}
}