{
  "type": "Feature",
  "properties": {
    "iso:country":"US",
    "sg:address":"101 E Rutherford St",
    "sg:city":"Ogilvie",
    "sg:classifiers":[
        {
            "category":"Autos & Motor Vehicles",
            "subcategory":"Fuel & Gas Station",
            "type":"Retail Goods"
        }
    ],
    "sg:phone":"+1 320 272 4423",
    "sg:postcode":"56358",
    "sg:province":"MN",
    "sg:tags":[
        "station"
    ],
    "wof:name":"Federated Co-Ops Inc",
    "wof:placetype":"venue"
},
  "geometry": {"coordinates":[-93.425917,45.831818],"type":"Point"}
}