{
  "type": "Feature",
  "properties": {
    "addr:full":"1803 Minnehuta Dr Fergus Falls MN 56537",
    "addr:housenumber":"1803",
    "addr:postcode":"56537",
    "addr:street":"Minnehuta Dr",
    "iso:country":"US",
    "sg:address":"1803 Minnehuta Dr",
    "sg:city":"Fergus Falls",
    "sg:classifiers":[
        {
            "category":"Real Estate",
            "subcategory":"Real Estate Operator",
            "type":"Services"
        }
    ],
    "sg:phone":"+1 218 739 9555",
    "sg:postcode":"56537",
    "sg:province":"MN",
    "sg:tags":[
        "building",
        "nonresidential"
    ],
    "wof:name":"Forty Four Inc",
    "wof:placetype":"venue"
},
  "geometry": {"coordinates":[-96.02646300000001,46.303173],"type":"Point"}
}