{
  "type": "Feature",
  "properties": {
    "addr:full":"2590 Ridgeway Ave NW Bemidji MN 56601",
    "addr:housenumber":"2590",
    "addr:postcode":"56601",
    "addr:street":"Ridgeway Ave Nw",
    "iso:country":"US",
    "sg:address":"2590 Ridgeway Ave NW",
    "sg:city":"Bemidji",
    "sg:classifiers":[
        {
            "category":"Social Services",
            "subcategory":"Adult Care",
            "type":"Services"
        }
    ],
    "sg:phone":"+1 218 444 3958",
    "sg:postcode":"56601",
    "sg:province":"MN",
    "sg:tags":[
        "home",
        "residential"
    ],
    "wof:name":"Lutheran Social Svc",
    "wof:placetype":"venue"
},
  "geometry": {"coordinates":[-94.895931,47.491823],"type":"Point"}
}