{
  "type": "Feature",
  "properties": {
    "addr:full":"3911 W 50th St Minneapolis MN 55424",
    "addr:housenumber":"3911",
    "addr:postcode":"55424",
    "addr:street":"W 50Th St",
    "iso:country":"US",
    "sg:address":"3911 W 50th St",
    "sg:city":"Minneapolis",
    "sg:classifiers":[
        {
            "category":"Cinema",
            "subcategory":"Movie Theater",
            "type":"Entertainment"
        }
    ],
    "sg:phone":"+1 651 649 4416",
    "sg:postcode":"55424",
    "sg:province":"MN",
    "sg:website":"www.landmarktheatres.com/market/...",
    "wof:name":"Edina Theatre",
    "wof:placetype":"venue"
},
  "geometry": {"coordinates":[-93.330101,44.912399],"type":"Point"}
}