{
  "type": "Feature",
  "properties": {
    "iso:country":"US",
    "sg:address":"177 3rd Ave NW",
    "sg:city":"Hutchinson",
    "sg:classifiers":[
        {
            "category":"Building & Trades",
            "subcategory":"Construction",
            "type":"Services"
        }
    ],
    "sg:phone":"+1 320 234 7970",
    "sg:postcode":"55350",
    "sg:province":"MN",
    "sg:tags":[
        "house"
    ],
    "wof:name":"Mast John",
    "wof:placetype":"venue"
},
  "geometry": {"coordinates":[-94.374601,44.896128],"type":"Point"}
}