{
  "type": "Feature",
  "properties": {
    "iso:country":"US",
    "sg:address":"511 Julii St SE",
    "sg:city":"Willmar",
    "sg:classifiers":[
        {
            "category":"Education",
            "subcategory":"School",
            "type":"Public Place"
        }
    ],
    "sg:phone":"+1 320 214 6690",
    "sg:postcode":"56201",
    "sg:province":"MN",
    "wof:name":"Lincoln Learning Ctr",
    "wof:placetype":"venue"
},
  "geometry": {"coordinates":[-95.033754,45.120314],"type":"Point"}
}