{
  "type": "Feature",
  "properties": {
    "iso:country":"US",
    "sg:address":"5435 109th Ave NE",
    "sg:city":"Spicer",
    "sg:classifiers":[
        {
            "category":"Building & Trades",
            "subcategory":"Construction",
            "type":"Services"
        }
    ],
    "sg:phone":"+1 320 796 6001",
    "sg:postcode":"56288",
    "sg:province":"MN",
    "sg:tags":[
        "house"
    ],
    "wof:name":"Cappelen Construction",
    "wof:placetype":"venue"
},
  "geometry": {"coordinates":[-94.968712,45.228608],"type":"Point"}
}