{
  "type": "Feature",
  "properties": {
    "addr:full":"30345 144th St Princeton MN 55371",
    "addr:housenumber":"30345",
    "addr:postcode":"55371",
    "addr:street":"144Th St",
    "iso:country":"US",
    "sg:address":"30345 144th St",
    "sg:city":"Princeton",
    "sg:phone":"+1 763 389 3881",
    "sg:postcode":"55371",
    "sg:province":"MN",
    "sg:tags":[
        "farm",
        "corn",
        "soybean"
    ],
    "wof:name":"Dale Hamner",
    "wof:placetype":"venue"
},
  "geometry": {"coordinates":[-93.63415999999999,45.518635],"type":"Point"}
}