{
  "type": "Feature",
  "properties": {
    "iso:country":"US",
    "sg:address":"2007 4th Ave E",
    "sg:city":"Hibbing",
    "sg:classifiers":[
        {
            "category":"Insurance",
            "subcategory":"Insurance Agent",
            "type":"Services"
        }
    ],
    "sg:phone":"+1 218 262 1075",
    "sg:postcode":"55746",
    "sg:province":"MN",
    "wof:name":"Mike Fay Insurance",
    "wof:placetype":"venue"
},
  "geometry": {"coordinates":[-92.93796399999999,47.427395],"type":"Point"}
}