{
  "type": "Feature",
  "properties": {
    "addr:full":"6461 Birch St North Branch MN 55056",
    "addr:housenumber":"6461",
    "addr:postcode":"55056",
    "addr:street":"Birch St",
    "iso:country":"US",
    "sg:address":"6461 Birch St",
    "sg:city":"North Branch",
    "sg:classifiers":[
        {
            "category":"Building & Trades",
            "subcategory":"Cleaning & Sanitation",
            "type":"Services"
        }
    ],
    "sg:phone":"+1 651 674 5972",
    "sg:postcode":"55056",
    "sg:province":"MN",
    "sg:tags":[
        "maintenance"
    ],
    "wof:name":"East Central Cleaning Services",
    "wof:placetype":"venue"
},
  "geometry": {"coordinates":[-92.978534,45.519186],"type":"Point"}
}