{
  "type": "Feature",
  "properties": {
    "addr:full":"111 York Dr Osseo MN 55369",
    "addr:housenumber":"111",
    "addr:postcode":"55369",
    "addr:street":"York Dr",
    "iso:country":"US",
    "sg:address":"111 York Dr",
    "sg:city":"Osseo",
    "sg:classifiers":[
        {
            "category":"Building & Trades",
            "subcategory":"Construction",
            "type":"Services"
        }
    ],
    "sg:phone":"+1 763 428 6323",
    "sg:postcode":"55369",
    "sg:province":"MN",
    "sg:tags":[
        "contractor"
    ],
    "wof:name":"Joseph M Stasik",
    "wof:placetype":"venue"
},
  "geometry": {"coordinates":[-93.517456,45.169613],"type":"Point"}
}