{
  "type": "Feature",
  "properties": {
    "iso:country":"US",
    "sg:address":"299 Coon Rapids Blvd NW",
    "sg:city":"Minneapolis",
    "sg:classifiers":[
        {
            "category":"Real Estate",
            "subcategory":"Real Estate Agent",
            "type":"Services"
        }
    ],
    "sg:phone":"+1 763 783 4427",
    "sg:postcode":"55433",
    "sg:province":"MN",
    "wof:name":"Metro Realty Team",
    "wof:placetype":"venue"
},
  "geometry": {"coordinates":[-93.274692,45.139095],"type":"Point"}
}