{
  "type": "Feature",
  "properties": {
    "iso:country":"US",
    "sg:address":"233 Ashland St N",
    "sg:city":"Cambridge",
    "sg:classifiers":[
        {
            "category":"Professional",
            "type":"Services"
        }
    ],
    "sg:phone":"+1 763 552 1407",
    "sg:postcode":"55008",
    "sg:province":"MN",
    "wof:name":"Robert L Nelson",
    "wof:placetype":"venue"
},
  "geometry": {"coordinates":[-93.225465,45.574335],"type":"Point"}
}