{
  "type": "Feature",
  "properties": {
    "addr:full":"16595 Crooked Lake Rd Deerwood MN 56444",
    "addr:housenumber":"16595",
    "addr:postcode":"56444",
    "addr:street":"Crooked Lake Rd",
    "iso:country":"US",
    "sg:address":"16595 Crooked Lake Rd",
    "sg:city":"Deerwood",
    "sg:classifiers":[
        {
            "category":"Organizations",
            "subcategory":"Religious Organization",
            "type":"Services"
        }
    ],
    "sg:phone":"+1 218 678 2325",
    "sg:postcode":"56444",
    "sg:province":"MN",
    "wof:name":"Presbyterian Clearwater Forest",
    "wof:placetype":"venue"
},
  "geometry": {"coordinates":[-93.888194,46.395407],"type":"Point"}
}