{
  "type": "Feature",
  "properties": {
    "iso:country":"US",
    "sg:address":"6930 Brooklyn Blvd Spc 9",
    "sg:city":"Minneapolis",
    "sg:classifiers":[
        {
            "category":"Shopping",
            "subcategory":"Beauty & Cosmetics",
            "type":"Retail Goods"
        },
        {
            "category":"Personal",
            "subcategory":"Barber",
            "type":"Services"
        }
    ],
    "sg:phone":"+1 763 561 1011",
    "sg:postcode":"55429",
    "sg:province":"MN",
    "sg:tags":[
        "equipment",
        "perfume",
        "salons-equipment",
        "supply"
    ],
    "wof:name":"F & G Beauty Supply",
    "wof:placetype":"venue"
},
  "geometry": {"coordinates":[-93.33727500000001,45.080625],"type":"Point"}
}