{
  "type": "Feature",
  "properties": {
    "iso:country":"US",
    "sg:address":"2946 N Chippewa Ave",
    "sg:city":"Saint Paul",
    "sg:classifiers":[
        {
            "category":"Building & Trades",
            "subcategory":"Landscaping Services",
            "type":"Services"
        }
    ],
    "sg:phone":"+1 651 770 2090",
    "sg:postcode":"55109",
    "sg:province":"MN",
    "sg:tags":[
        "planning"
    ],
    "wof:name":"Graystone Landscaping Inc",
    "wof:placetype":"venue"
},
  "geometry": {"coordinates":[-92.999456,45.030173],"type":"Point"}
}