{
  "type": "Feature",
  "properties": {
    "iso:country":"US",
    "sg:address":"71523 268th St",
    "sg:city":"Dassel",
    "sg:classifiers":[
        {
            "category":"Shopping",
            "subcategory":"Clothing, Apparel, & Fashions",
            "type":"Retail Goods"
        }
    ],
    "sg:phone":"+1 320 275 0178",
    "sg:postcode":"55325",
    "sg:province":"MN",
    "wof:name":"Ggs Sportswear Promotions",
    "wof:placetype":"venue"
},
  "geometry": {"coordinates":[-94.32716499999999,45.13663],"type":"Point"}
}