{
  "type": "Feature",
  "properties": {
    "addr:full":"27001 353rd Ave Belgrade MN 56312",
    "addr:housenumber":"27001",
    "addr:postcode":"56312",
    "addr:street":"353Rd Ave",
    "iso:country":"US",
    "sg:address":"27001 353rd Ave",
    "sg:city":"Belgrade",
    "sg:classifiers":[
        {
            "category":"Farming",
            "subcategory":"Dairy Farm",
            "type":"Manufacturing & Wholesale Goods"
        }
    ],
    "sg:phone":"+1 320 987 3201",
    "sg:postcode":"56312",
    "sg:province":"MN",
    "wof:name":"Norbert Waldorf",
    "wof:placetype":"venue"
},
  "geometry": {"coordinates":[-94.84511999999999,45.517309],"type":"Point"}
}