{
  "type": "Feature",
  "properties": {
    "addr:full":"651 Nicollet Mall Ste 501 Minneapolis MN 55402",
    "addr:housenumber":"651",
    "addr:postcode":"55402",
    "addr:street":"Nicollet Mall Ste 501",
    "iso:country":"US",
    "sg:address":"651 Nicollet Mall Ste 501",
    "sg:city":"Minneapolis",
    "sg:classifiers":[
        {
            "category":"Professional",
            "subcategory":"Lawyer & Legal Services",
            "type":"Services"
        }
    ],
    "sg:phone":"+1 612 341 0400",
    "sg:postcode":"55402",
    "sg:province":"MN",
    "wof:name":"Zimmerman Reed Pllp",
    "wof:placetype":"venue"
},
  "geometry": {"coordinates":[-93.271698,44.977402],"type":"Point"}
}