{
  "type": "Feature",
  "properties": {
    "iso:country":"US",
    "sg:address":"205 Red River Ave N",
    "sg:city":"Cold Spring",
    "sg:classifiers":[
        {
            "category":"Food & Beverages",
            "subcategory":"Specialty",
            "type":"Retail Goods"
        }
    ],
    "sg:phone":"+1 320 252 1358",
    "sg:postcode":"56320",
    "sg:province":"MN",
    "sg:tags":[
        "salt"
    ],
    "wof:name":"Erken's Water Softener Svc",
    "wof:placetype":"venue"
},
  "geometry": {"coordinates":[-94.42907,45.458406],"type":"Point"}
}