{
  "type": "Feature",
  "properties": {
    "addr:full":"105 2nd Ave NE Ste 109 Glenwood MN 56334",
    "addr:housenumber":"105",
    "addr:postcode":"56334",
    "addr:street":"2Nd Ave Ne Ste 109",
    "iso:country":"US",
    "sg:address":"105 2nd Ave NE Ste 109",
    "sg:city":"Glenwood",
    "sg:classifiers":[
        {
            "category":"Personal",
            "subcategory":"Massage",
            "type":"Services"
        },
        {
            "category":"Personal",
            "subcategory":"Beauty Salon",
            "type":"Services"
        },
        {
            "category":"Personal",
            "subcategory":"Tanning Parlor",
            "type":"Services"
        }
    ],
    "sg:phone":"+1 320 634 4476",
    "sg:postcode":"56334",
    "sg:province":"MN",
    "sg:tags":[
        "therapist"
    ],
    "wof:name":"Mi Lady & Mi Lad Hair Design",
    "wof:placetype":"venue"
},
  "geometry": {"coordinates":[-95.388409,45.652002],"type":"Point"}
}