{
  "type": "Feature",
  "properties": {
    "addr:full":"5055 85th St NW Montevideo MN 56265",
    "addr:housenumber":"5055",
    "addr:postcode":"56265",
    "addr:street":"85Th St Nw",
    "iso:country":"US",
    "sg:address":"5055 85th St NW",
    "sg:city":"Montevideo",
    "sg:phone":"+1 320 793 6623",
    "sg:postcode":"56265",
    "sg:province":"MN",
    "sg:tags":[
        "farm",
        "corn"
    ],
    "wof:name":"Greg Goulson Farm",
    "wof:placetype":"venue"
},
  "geometry": {"coordinates":[-95.715405,45.14486],"type":"Point"}
}