{
  "type": "Feature",
  "properties": {
    "addr:full":"12632 Old Hwy 169 Hibbing MN 55746",
    "addr:housenumber":"12632",
    "addr:postcode":"55746",
    "addr:street":"Old Hwy 169 Hibbing",
    "iso:country":"US",
    "sg:address":"12632 Old Hwy 169",
    "sg:city":"Hibbing",
    "sg:classifiers":[
        {
            "category":"Building & Trades",
            "subcategory":"Construction",
            "type":"Services"
        }
    ],
    "sg:phone":"+1 218 778 6703",
    "sg:postcode":"55746",
    "sg:province":"MN",
    "sg:tags":[
        "house",
        "contractor",
        "general"
    ],
    "wof:name":"Jones Construction Co",
    "wof:placetype":"venue"
},
  "geometry": {"coordinates":[-93.021136,47.393738],"type":"Point"}
}