{
  "type": "Feature",
  "properties": {
    "iso:country":"US",
    "sg:address":"14638 Cedar Ave Ste A",
    "sg:city":"Apple Valley",
    "sg:classifiers":[
        {
            "category":"Freight",
            "type":"Transportation"
        },
        {
            "category":"Professional",
            "subcategory":"Printing & Photocopies",
            "type":"Services"
        }
    ],
    "sg:phone":"+1 952 431 7724",
    "sg:postcode":"55124",
    "sg:province":"MN",
    "sg:tags":[
        "shipping"
    ],
    "sg:website":"www.fedex.com/us/office/",
    "wof:name":"FedEx Office Print & Ship Center",
    "wof:placetype":"venue"
},
  "geometry": {"coordinates":[-93.21753,44.736453],"type":"Point"}
}