{
  "type": "Feature",
  "properties": {
    "addr:full":"5622 Glen Ave Minnetonka MN 55345",
    "addr:housenumber":"5622",
    "addr:postcode":"55345",
    "addr:street":"Glen Ave",
    "iso:country":"US",
    "sg:address":"5622 Glen Ave",
    "sg:city":"Minnetonka",
    "sg:classifiers":[
        {
            "category":"Shopping",
            "subcategory":"Gifts & Souvenirs",
            "type":"Retail Goods"
        }
    ],
    "sg:phone":"+1 952 934 8422",
    "sg:postcode":"55345",
    "sg:province":"MN",
    "wof:name":"Northwoods Boutique",
    "wof:placetype":"venue"
},
  "geometry": {"coordinates":[-93.469505,44.901199],"type":"Point"}
}