{
  "type": "Feature",
  "properties": {
    "iso:country":"US",
    "sg:address":"501 7th St SW",
    "sg:city":"Dover",
    "sg:classifiers":[
        {
            "category":"Farming",
            "subcategory":"Nursery",
            "type":"Manufacturing & Wholesale Goods"
        },
        {
            "category":"Home & Garden",
            "subcategory":"Garden Supply",
            "type":"Retail Goods"
        }
    ],
    "sg:phone":"+1 507 932 5641",
    "sg:postcode":"55929",
    "sg:province":"MN",
    "sg:tags":[
        "ornamental",
        "center"
    ],
    "wof:name":"Gardens Galore & More Gift Sp",
    "wof:placetype":"venue"
},
  "geometry": {"coordinates":[-92.14447,43.96618],"type":"Point"}
}