{
  "type": "Feature",
  "properties": {
    "addr:full":"3266 12th Ave Anoka MN 55303",
    "addr:housenumber":"3266",
    "addr:postcode":"55303",
    "addr:street":"12Th Ave",
    "iso:country":"US",
    "sg:address":"3266 12th Ave",
    "sg:city":"Anoka",
    "sg:classifiers":[
        {
            "category":"Professional",
            "subcategory":"Business Services",
            "type":"Services"
        }
    ],
    "sg:phone":"+1 763 422 3759",
    "sg:postcode":"55303",
    "sg:province":"MN",
    "wof:name":"Jeanness Interior Works",
    "wof:placetype":"venue"
},
  "geometry": {"coordinates":[-93.365319,45.214346],"type":"Point"}
}