{
  "type": "Feature",
  "properties": {
    "iso:country":"US",
    "sg:address":"2101 W Broadway Ave",
    "sg:city":"Minneapolis",
    "sg:classifiers":[
        {
            "category":"Professional",
            "subcategory":"Computer Services",
            "type":"Services"
        }
    ],
    "sg:phone":"+1 612 522 7851",
    "sg:postcode":"55411",
    "sg:province":"MN",
    "wof:name":"ARS Computer Inc",
    "wof:placetype":"venue"
},
  "geometry": {"coordinates":[-93.30587,45.002232],"type":"Point"}
}