{
  "type": "Feature",
  "properties": {
    "addr:full":"1104 E College Dr Marshall MN 56258",
    "addr:housenumber":"1104",
    "addr:postcode":"56258",
    "addr:street":"E College Dr",
    "iso:country":"US",
    "sg:address":"1104 E College Dr",
    "sg:city":"Marshall",
    "sg:classifiers":[
        {
            "category":"Farming",
            "subcategory":"Farm & Veterinary Services",
            "type":"Manufacturing & Wholesale Goods"
        }
    ],
    "sg:phone":"+1 507 532 5120",
    "sg:postcode":"56258",
    "sg:province":"MN",
    "sg:tags":[
        "management"
    ],
    "sg:website":"www.nwfmco.com",
    "wof:name":"Northwestern Farm Management",
    "wof:placetype":"venue"
},
  "geometry": {"coordinates":[-95.776107,44.450286],"type":"Point"}
}