{
  "type": "Feature",
  "properties": {
    "addr:full":"607 Grand Ave St Paul MN 55102",
    "addr:housenumber":"607",
    "addr:postcode":"55102",
    "addr:street":"Grand Ave",
    "iso:country":"US",
    "sg:address":"607 Grand Ave",
    "sg:city":"St Paul",
    "sg:classifiers":[
        {
            "category":"Professional",
            "type":"Services"
        }
    ],
    "sg:phone":"+1 651 312 1131",
    "sg:postcode":"55102",
    "sg:province":"MN",
    "sg:tags":[
        "establishment"
    ],
    "wof:name":"Consumer Rights Advocate",
    "wof:placetype":"venue"
},
  "geometry": {"coordinates":[-93.12463,44.939996],"type":"Point"}
}