{
  "type": "Feature",
  "properties": {
    "addr:full":"1365 N Woodbridge St St Paul MN 55117",
    "addr:housenumber":"1365",
    "addr:postcode":"55117",
    "addr:street":"N Woodbridge St",
    "iso:country":"US",
    "sg:address":"1365 N Woodbridge St",
    "sg:city":"St Paul",
    "sg:classifiers":[
        {
            "category":"Real Estate",
            "subcategory":"Real Estate Agent",
            "type":"Services"
        }
    ],
    "sg:phone":"+1 651 489 6527",
    "sg:postcode":"55117",
    "sg:province":"MN",
    "sg:tags":[
        "appraiser"
    ],
    "wof:name":"Real Estate Resources",
    "wof:placetype":"venue"
},
  "geometry": {"coordinates":[-93.108508,44.982441],"type":"Point"}
}