{
  "type": "Feature",
  "properties": {
    "iso:country":"US",
    "sg:address":"831 E Superior St",
    "sg:city":"Duluth",
    "sg:classifiers":[
        {
            "category":"Organizations",
            "subcategory":"Community Association",
            "type":"Services"
        }
    ],
    "sg:phone":"+1 218 724 8589",
    "sg:postcode":"55802",
    "sg:province":"MN",
    "sg:tags":[
        "club",
        "a",
        "operates",
        "social"
    ],
    "wof:name":"Kitchi Gammi Club Inc",
    "wof:placetype":"venue"
},
  "geometry": {"coordinates":[-92.088217,46.794805],"type":"Point"}
}