{
  "type": "Feature",
  "properties": {
    "iso:country":"US",
    "sg:address":"15601 S Eden Dr",
    "sg:city":"Eden Prairie",
    "sg:classifiers":[
        {
            "category":"Professional",
            "subcategory":"Accounting & Tax Preparation",
            "type":"Services"
        }
    ],
    "sg:phone":"+1 952 936 9290",
    "sg:postcode":"55346",
    "sg:province":"MN",
    "wof:name":"Pd Enterprises",
    "wof:placetype":"venue"
},
  "geometry": {"coordinates":[-93.47871499999999,44.889513],"type":"Point"}
}