{
  "type": "Feature",
  "properties": {
    "addr:full":"46730 Co Hwy 54 Ottertail MN 56571",
    "addr:housenumber":"46730",
    "addr:postcode":"56571",
    "addr:street":"Co Hwy 54",
    "iso:country":"US",
    "sg:address":"46730 Co Hwy 54",
    "sg:city":"Ottertail",
    "sg:classifiers":[
        {
            "category":"Manufacturing",
            "subcategory":"Furniture",
            "type":"Manufacturing & Wholesale Goods"
        },
        {
            "category":"Home & Garden",
            "subcategory":"Furniture",
            "type":"Retail Goods"
        }
    ],
    "sg:phone":"+1 218 367 2885",
    "sg:postcode":"56571",
    "sg:province":"MN",
    "sg:tags":[
        "upholstered",
        "manufacture",
        "household",
        "wood"
    ],
    "wof:name":"Pine Mill Farm Furniture Co",
    "wof:placetype":"venue"
},
  "geometry": {"coordinates":[-95.516015,46.469962],"type":"Point"}
}