{
  "type": "Feature",
  "properties": {
    "addr:full":"1146 Brookdale Dr Minneapolis MN 55444",
    "addr:housenumber":"1146",
    "addr:postcode":"55444",
    "addr:street":"Brookdale Dr",
    "iso:country":"US",
    "sg:address":"1146 Brookdale Dr",
    "sg:city":"Minneapolis",
    "sg:classifiers":[
        {
            "category":"Building & Trades",
            "subcategory":"Construction",
            "type":"Services"
        }
    ],
    "sg:phone":"+1 763 561 4951",
    "sg:postcode":"55444",
    "sg:province":"MN",
    "sg:tags":[
        "carpentry",
        "contractor"
    ],
    "wof:name":"Mark Pulju",
    "wof:placetype":"venue"
},
  "geometry": {"coordinates":[-93.296363,45.094458],"type":"Point"}
}