{
  "type": "Feature",
  "properties": {
    "addr:full":"4545 Watertown Rd Maple Plain MN 55359",
    "addr:housenumber":"4545",
    "addr:postcode":"55359",
    "addr:street":"Watertown Rd;Plain",
    "iso:country":"US",
    "sg:address":"4545 Watertown Rd",
    "sg:city":"Maple Plain",
    "sg:classifiers":[
        {
            "category":"Building & Trades",
            "subcategory":"Landscaping Services",
            "type":"Services"
        }
    ],
    "sg:phone":"+1 952 473 2127",
    "sg:postcode":"55359",
    "sg:province":"MN",
    "sg:tags":[
        "lawn",
        "maintenance",
        "grounds"
    ],
    "wof:name":"Chem Free Lawn Inc",
    "wof:placetype":"venue"
},
  "geometry": {"coordinates":[-93.639521,44.989868],"type":"Point"}
}