{
  "type": "Feature",
  "properties": {
    "addr:full":"20101 Horseshoe Ln Mankato MN 56001",
    "addr:housenumber":"20101",
    "addr:postcode":"56001",
    "addr:street":"Horseshoe Ln",
    "iso:country":"US",
    "sg:address":"20101 Horseshoe Ln",
    "sg:city":"Mankato",
    "sg:classifiers":[
        {
            "category":"Professional",
            "subcategory":"Art Services",
            "type":"Services"
        }
    ],
    "sg:phone":"+1 507 388 1793",
    "sg:postcode":"56001",
    "sg:province":"MN",
    "sg:tags":[
        "commercial",
        "design",
        "gallery",
        "mi"
    ],
    "wof:name":"Anderson Marian Art",
    "wof:placetype":"venue"
},
  "geometry": {"coordinates":[-94.06370099999999,44.128488],"type":"Point"}
}