{
  "type": "Feature",
  "properties": {
    "addr:full":"6016 Co Rd 101 Minnetonka MN 55345",
    "addr:housenumber":"6016",
    "addr:postcode":"55345",
    "addr:street":"Co Rd 101",
    "iso:country":"US",
    "sg:address":"6016 Co Rd 101",
    "sg:city":"Minnetonka",
    "sg:classifiers":[
        {
            "category":"Retail",
            "subcategory":"Repair Shop",
            "type":"Services"
        }
    ],
    "sg:phone":"+1 952 401 0477",
    "sg:postcode":"55345",
    "sg:province":"MN",
    "wof:name":"Creekside Refinishing",
    "wof:placetype":"venue"
},
  "geometry": {"coordinates":[-93.515506,44.893603],"type":"Point"}
}