{
  "type": "Feature",
  "properties": {
    "iso:country":"US",
    "sg:address":"2100 7th St SW",
    "sg:city":"Willmar",
    "sg:classifiers":[
        {
            "category":"Recreation",
            "type":"Entertainment"
        }
    ],
    "sg:phone":"+1 320 235 1963",
    "sg:postcode":"56201",
    "sg:province":"MN",
    "sg:tags":[
        "skating",
        "rink"
    ],
    "wof:name":"Hilltop Skating Rink",
    "wof:placetype":"venue"
},
  "geometry": {"coordinates":[-95.04977100000001,45.102491],"type":"Point"}
}