{
  "type": "Feature",
  "properties": {
    "iso:country":"US",
    "sg:address":"1121 S Broadway",
    "sg:city":"Pelican Rapids",
    "sg:classifiers":[
        {
            "category":"Restaurant",
            "type":"Food & Drink"
        }
    ],
    "sg:phone":"+1 218 863 4151",
    "sg:postcode":"56572",
    "sg:province":"MN",
    "sg:tags":[
        "eating"
    ],
    "wof:name":"Dairy Queen",
    "wof:placetype":"venue"
},
  "geometry": {"coordinates":[-96.083411,46.558262],"type":"Point"}
}