{
  "type": "Feature",
  "properties": {
    "addr:full":"510 E 13th St Gibbon MN 55335",
    "addr:housenumber":"510",
    "addr:postcode":"55335",
    "addr:street":"E 13Th St",
    "iso:country":"US",
    "sg:address":"510 E 13th St",
    "sg:city":"Gibbon",
    "sg:classifiers":[
        {
            "category":"Sports & Exercise",
            "subcategory":"Bowling",
            "type":"Entertainment"
        }
    ],
    "sg:phone":"+1 507 834 6174",
    "sg:postcode":"55335",
    "sg:province":"MN",
    "sg:tags":[
        "center"
    ],
    "wof:name":"Tom's Bowling Ctr",
    "wof:placetype":"venue"
},
  "geometry": {"coordinates":[-94.517668,44.535799],"type":"Point"}
}