{
  "type": "Feature",
  "properties": {
    "addr:full":"17810 2nd Ave N Plymouth MN 55447",
    "addr:housenumber":"17810",
    "addr:postcode":"55447",
    "addr:street":"2Nd Ave N",
    "iso:country":"US",
    "sg:address":"17810 2nd Ave N",
    "sg:city":"Plymouth",
    "sg:classifiers":[
        {
            "category":"Building & Trades",
            "subcategory":"Landscaping Services",
            "type":"Services"
        }
    ],
    "sg:phone":"+1 952 476 9573",
    "sg:postcode":"55447",
    "sg:province":"MN",
    "sg:tags":[
        "designer",
        "landscape"
    ],
    "wof:name":"Insites Site Planning Arch",
    "wof:placetype":"venue"
},
  "geometry": {"coordinates":[-93.506333,44.980878],"type":"Point"}
}