{
  "type": "Feature",
  "properties": {
    "iso:country":"US",
    "sg:address":"254 Aurora Ave",
    "sg:city":"St Paul",
    "sg:classifiers":[
        {
            "category":"Real Estate",
            "subcategory":"Real Estate Agent",
            "type":"Services"
        }
    ],
    "sg:phone":"+1 651 222 8481",
    "sg:postcode":"55103",
    "sg:province":"MN",
    "wof:name":"Unity Realty",
    "wof:placetype":"venue"
},
  "geometry": {"coordinates":[-93.109994,44.954814],"type":"Point"}
}