{
  "type": "Feature",
  "properties": {
    "addr:full":"16190 Crystal Hills Dr Lakeville MN 55044",
    "addr:housenumber":"16190",
    "addr:postcode":"55044",
    "addr:street":"Crystal Hills Dr",
    "iso:country":"US",
    "sg:address":"16190 Crystal Hills Dr",
    "sg:city":"Lakeville",
    "sg:classifiers":[
        {
            "category":"Real Estate",
            "subcategory":"Real Estate Agent",
            "type":"Services"
        }
    ],
    "sg:phone":"+1 952 432 7702",
    "sg:postcode":"55044",
    "sg:province":"MN",
    "wof:name":"Greenleaf Properties Inc",
    "wof:placetype":"venue"
},
  "geometry": {"coordinates":[-93.253584,44.711647],"type":"Point"}
}