{
  "type": "Feature",
  "properties": {
    "iso:country":"US",
    "sg:address":"494 Portland Ave",
    "sg:city":"Minneapolis",
    "sg:classifiers":[
        {
            "category":"Personal",
            "type":"Services"
        },
        {
            "category":"Retail",
            "subcategory":"Auto Repair",
            "type":"Services"
        }
    ],
    "sg:phone":"+1 952 881 6300",
    "sg:postcode":"55415",
    "sg:province":"MN",
    "sg:tags":[
        "towing"
    ],
    "wof:name":"Amoco Oil Company",
    "wof:placetype":"venue"
},
  "geometry": {"coordinates":[-93.26159699999999,44.976299],"type":"Point"}
}