{
  "type": "Feature",
  "properties": {
    "iso:country":"US",
    "sg:address":"1204 Madison St",
    "sg:city":"Brainerd",
    "sg:classifiers":[
        {
            "category":"Building & Trades",
            "subcategory":"Construction",
            "type":"Services"
        }
    ],
    "sg:phone":"+1 218 828 6492",
    "sg:postcode":"56401",
    "sg:province":"MN",
    "sg:tags":[
        "insulation",
        "heat",
        "contractor"
    ],
    "wof:name":"Expert Insulation",
    "wof:placetype":"venue"
},
  "geometry": {"coordinates":[-94.190952,46.333705],"type":"Point"}
}