{
  "type": "Feature",
  "properties": {
    "iso:country":"US",
    "sg:address":"14070 23rd Ave N Ste A",
    "sg:city":"Minneapolis",
    "sg:classifiers":[
        {
            "category":"Building & Trades",
            "subcategory":"Landscaping Services",
            "type":"Services"
        },
        {
            "category":"Wholesale",
            "subcategory":"Machinery & Supplies",
            "type":"Manufacturing & Wholesale Goods"
        },
        {
            "category":"Professional",
            "subcategory":"Business Services",
            "type":"Services"
        }
    ],
    "sg:phone":"+1 763 559 1010",
    "sg:postcode":"55447",
    "sg:province":"MN",
    "sg:tags":[
        "lawn",
        "consultant",
        "irrigation",
        "system",
        "equipment",
        "maintenance"
    ],
    "sg:website":"http://www.ibdmn.com",
    "wof:name":"Irrigation Consultants & Control, Inc.",
    "wof:placetype":"venue"
},
  "geometry": {"coordinates":[-93.458882,45.003906],"type":"Point"}
}