{
  "type": "Feature",
  "properties": {
    "addr:full":"8409 Lyndale Ave S Minneapolis MN 55420",
    "addr:housenumber":"8409",
    "addr:postcode":"55420",
    "addr:street":"Lyndale Ave S",
    "iso:country":"US",
    "sg:address":"8409 Lyndale Ave S",
    "sg:city":"Minneapolis",
    "sg:classifiers":[
        {
            "category":"Utilities",
            "subcategory":"Mobile Phone",
            "type":"Services"
        },
        {
            "category":"Communications",
            "type":"Services"
        }
    ],
    "sg:phone":"+1 952 884 5330",
    "sg:postcode":"55420",
    "sg:province":"MN",
    "sg:tags":[
        "data",
        "telephone",
        "cellular"
    ],
    "sg:website":"http://www.cingular.com",
    "wof:name":"New Cingular Wireless Services, Inc.",
    "wof:placetype":"venue"
},
  "geometry": {"coordinates":[-93.28843000000001,44.851422],"type":"Point"}
}