{
  "type": "Feature",
  "properties": {
    "iso:country":"US",
    "sg:address":"2535 Central Ave NE",
    "sg:city":"Minneapolis",
    "sg:classifiers":[
        {
            "category":"Professional",
            "subcategory":"Business Services",
            "type":"Services"
        }
    ],
    "sg:phone":"+1 612 781 0656",
    "sg:postcode":"55418",
    "sg:province":"MN",
    "wof:name":"ITP Funding Solutions",
    "wof:placetype":"venue"
},
  "geometry": {"coordinates":[-93.247337,45.013161],"type":"Point"}
}