{
  "type": "Feature",
  "properties": {
    "iso:country":"US",
    "sg:address":"10644 Wellington Ln N",
    "sg:city":"Osseo",
    "sg:classifiers":[
        {
            "category":"Real Estate",
            "subcategory":"Real Estate Agent",
            "type":"Services"
        }
    ],
    "sg:phone":"+1 763 424 2297",
    "sg:postcode":"55369",
    "sg:province":"MN",
    "wof:name":"Lca Marketing Inc",
    "wof:placetype":"venue"
},
  "geometry": {"coordinates":[-93.418273,45.147106],"type":"Point"}
}