{
  "type": "Feature",
  "properties": {
    "addr:full":"571 Sand Creek Dr NW Minneapolis MN 55448",
    "addr:housenumber":"571",
    "addr:postcode":"55448",
    "addr:street":"Sand Creek Dr Nw",
    "iso:country":"US",
    "sg:address":"571 Sand Creek Dr NW",
    "sg:city":"Minneapolis",
    "sg:classifiers":[
        {
            "category":"Building & Trades",
            "subcategory":"Construction",
            "type":"Services"
        }
    ],
    "sg:phone":"+1 763 754 8039",
    "sg:postcode":"55448",
    "sg:province":"MN",
    "sg:tags":[
        "contractor"
    ],
    "wof:name":"Siding Plus MN",
    "wof:placetype":"venue"
},
  "geometry": {"coordinates":[-93.277399,45.184137],"type":"Point"}
}