{
  "type": "Feature",
  "properties": {
    "addr:full":"2815 162nd Ave NE Anoka MN 55304",
    "addr:housenumber":"2815",
    "addr:postcode":"55304",
    "addr:street":"162Nd Ave Ne",
    "iso:country":"US",
    "sg:address":"2815 162nd Ave NE",
    "sg:city":"Anoka",
    "sg:classifiers":[
        {
            "category":"Social Services",
            "subcategory":"Child Care",
            "type":"Services"
        }
    ],
    "sg:phone":"+1 763 434 1493",
    "sg:postcode":"55304",
    "sg:province":"MN",
    "sg:tags":[
        "day"
    ],
    "wof:name":"Dana J Kroone",
    "wof:placetype":"venue"
},
  "geometry": {"coordinates":[-93.198699,45.263606],"type":"Point"}
}