{
  "type": "Feature",
  "properties": {
    "iso:country":"US",
    "sg:address":"1659 Grand Ave",
    "sg:city":"Saint Paul",
    "sg:classifiers":[
        {
            "category":"Restaurant",
            "type":"Food & Drink"
        }
    ],
    "sg:phone":"+1 651 690 1393",
    "sg:postcode":"55105",
    "sg:province":"MN",
    "sg:tags":[
        "thai",
        "eating"
    ],
    "wof:name":"Pad Thai Grand Cafe",
    "wof:placetype":"venue"
},
  "geometry": {"coordinates":[-93.170097,44.939899],"type":"Point"}
}