{
  "type": "Feature",
  "properties": {
    "addr:full":"202 S Washington St Lake City MN 55041",
    "addr:housenumber":"202",
    "addr:postcode":"55041",
    "addr:street":"S Washington St",
    "iso:country":"US",
    "sg:address":"202 S Washington St",
    "sg:city":"Lake City",
    "sg:classifiers":[
        {
            "category":"Professional",
            "subcategory":"Computer Services",
            "type":"Services"
        }
    ],
    "sg:phone":"+1 651 345 6309",
    "sg:postcode":"55041",
    "sg:province":"MN",
    "wof:name":"Computer Connections",
    "wof:placetype":"venue"
},
  "geometry": {"coordinates":[-92.26507599999999,44.449152],"type":"Point"}
}