{
  "type": "Feature",
  "properties": {
    "iso:country":"US",
    "sg:address":"8408 27th Pl N",
    "sg:city":"Minneapolis",
    "sg:classifiers":[
        {
            "category":"Professional",
            "type":"Services"
        }
    ],
    "sg:phone":"+1 763 542 9363",
    "sg:postcode":"55427",
    "sg:province":"MN",
    "wof:name":"Hellen Onnen",
    "wof:placetype":"venue"
},
  "geometry": {"coordinates":[-93.38775,45.008332],"type":"Point"}
}