{
  "type": "Feature",
  "properties": {
    "addr:full":"9678 Colorado Ln N Minneapolis MN 55445",
    "addr:housenumber":"9678",
    "addr:postcode":"55445",
    "addr:street":"Colorado Ln N",
    "iso:country":"US",
    "sg:address":"9678 Colorado Ln N",
    "sg:city":"Minneapolis",
    "sg:classifiers":[
        {
            "category":"Health Services",
            "subcategory":"Chiropractor",
            "type":"Services"
        }
    ],
    "sg:phone":"+1 763 391 9484",
    "sg:postcode":"55445",
    "sg:province":"MN",
    "wof:name":"Brooklyn Park Chiropractic",
    "wof:placetype":"venue"
},
  "geometry": {"coordinates":[-93.360488,45.135083],"type":"Point"}
}