{
  "type": "Feature",
  "properties": {
    "iso:country":"US",
    "sg:address":"635 1st St SE",
    "sg:city":"Faribault",
    "sg:classifiers":[
        {
            "category":"Health Services",
            "subcategory":"Doctor",
            "type":"Services"
        }
    ],
    "sg:phone":"+1 507 333 3300",
    "sg:postcode":"55021",
    "sg:province":"MN",
    "sg:tags":[
        "medical",
        "clinic"
    ],
    "wof:name":"Cannon Valley Clinic",
    "wof:placetype":"venue"
},
  "geometry": {"coordinates":[-93.25797,44.289507],"type":"Point"}
}