{
  "type": "Feature",
  "properties": {
    "addr:full":"7971 Inland Ln N Osseo MN 55311",
    "addr:housenumber":"7971",
    "addr:postcode":"55311",
    "addr:street":"Inland Ln N",
    "iso:country":"US",
    "sg:address":"7971 Inland Ln N",
    "sg:city":"Osseo",
    "sg:classifiers":[
        {
            "category":"Professional",
            "subcategory":"Management & Consulting",
            "type":"Services"
        }
    ],
    "sg:phone":"+1 763 420 8836",
    "sg:postcode":"55311",
    "sg:province":"MN",
    "wof:name":"Lisa M Beckendorf",
    "wof:placetype":"venue"
},
  "geometry": {"coordinates":[-93.49825,45.100114],"type":"Point"}
}