{
  "type": "Feature",
  "properties": {
    "iso:country":"US",
    "sg:address":"10908 Decatur Ave S",
    "sg:city":"Minneapolis",
    "sg:classifiers":[
        {
            "category":"Cinema",
            "subcategory":"Movie Rental",
            "type":"Entertainment"
        }
    ],
    "sg:phone":"+1 952 829 4070",
    "sg:postcode":"55438",
    "sg:province":"MN",
    "sg:tags":[
        "video",
        "tape"
    ],
    "wof:name":"Lightstream Adio Video Systems",
    "wof:placetype":"venue"
},
  "geometry": {"coordinates":[-93.39604199999999,44.806301],"type":"Point"}
}