{
  "type": "Feature",
  "properties": {
    "addr:full":"3915 E Lake St Minneapolis MN 55406",
    "addr:housenumber":"3915",
    "addr:postcode":"55406",
    "addr:street":"E Lake St",
    "iso:country":"US",
    "sg:address":"3915 E Lake St",
    "sg:city":"Minneapolis",
    "sg:classifiers":[
        {
            "category":"Home & Garden",
            "subcategory":"Hardware",
            "type":"Retail Goods"
        }
    ],
    "sg:phone":"+1 612 238 1100",
    "sg:postcode":"55406",
    "sg:province":"MN",
    "sg:tags":[
        "store"
    ],
    "wof:name":"Ace Hardware Frattallone's",
    "wof:placetype":"venue"
},
  "geometry": {"coordinates":[-93.216334,44.948223],"type":"Point"}
}