{
  "type": "Feature",
  "properties": {
    "addr:full":"8800 66th Ave N Minneapolis MN 55428",
    "addr:housenumber":"8800",
    "addr:postcode":"55428",
    "addr:street":"66Th Ave N",
    "iso:country":"US",
    "sg:address":"8800 66th Ave N",
    "sg:city":"Minneapolis",
    "sg:classifiers":[
        {
            "category":"Shopping",
            "subcategory":"Clothing, Apparel, & Fashions",
            "type":"Retail Goods"
        }
    ],
    "sg:phone":"+1 763 535 4870",
    "sg:postcode":"55428",
    "sg:province":"MN",
    "wof:name":"Solution Men Inc",
    "wof:placetype":"venue"
},
  "geometry": {"coordinates":[-93.39559800000001,45.073876],"type":"Point"}
}