{
  "type": "Feature",
  "properties": {
    "iso:country":"US",
    "sg:address":"940 Curry Trl",
    "sg:city":"Saint Paul",
    "sg:classifiers":[
        {
            "category":"Retail",
            "subcategory":"Laundry & Dry Cleaning",
            "type":"Services"
        }
    ],
    "sg:phone":"+1 651 452 3954",
    "sg:postcode":"55123",
    "sg:province":"MN",
    "wof:name":"Candis Sewing",
    "wof:placetype":"venue"
},
  "geometry": {"coordinates":[-93.133972,44.802264],"type":"Point"}
}