{
  "type": "Feature",
  "properties": {
    "addr:full":"27185 Bayshore Cir Isanti MN 55040",
    "addr:housenumber":"27185",
    "addr:postcode":"55040",
    "addr:street":"Bayshore Cir",
    "iso:country":"US",
    "sg:address":"27185 Bayshore Cir",
    "sg:city":"Isanti",
    "sg:classifiers":[
        {
            "category":"Building & Trades",
            "subcategory":"Plumbing",
            "type":"Services"
        }
    ],
    "sg:phone":"+1 763 753 0092",
    "sg:postcode":"55040",
    "sg:province":"MN",
    "sg:tags":[
        "plumber",
        "industrial",
        "contractors-commercial"
    ],
    "wof:name":"Lakeland Plumbing",
    "wof:placetype":"venue"
},
  "geometry": {"coordinates":[-93.354153,45.462383],"type":"Point"}
}