{
  "type": "Feature",
  "properties": {
    "iso:country":"US",
    "sg:address":"2450 Riverside Ave",
    "sg:city":"Minneapolis",
    "sg:classifiers":[
        {
            "category":"Health Services",
            "subcategory":"Doctor",
            "type":"Services"
        }
    ],
    "sg:phone":"+1 612 672 7250",
    "sg:postcode":"55454",
    "sg:province":"MN",
    "sg:tags":[
        "physician",
        "medical",
        "thoracic",
        "surgeons",
        "surgery",
        "cardiovascular"
    ],
    "wof:name":"Andrew H Cragg Md",
    "wof:placetype":"venue"
},
  "geometry": {"coordinates":[-93.23708000000001,44.96589],"type":"Point"}
}