{
  "type": "Feature",
  "properties": {
    "iso:country":"US",
    "sg:address":"8607 N Zinnia Way",
    "sg:city":"Osseo",
    "sg:classifiers":[
        {
            "category":"Professional",
            "subcategory":"Computer Services",
            "type":"Services"
        }
    ],
    "sg:phone":"+1 763 420 3347",
    "sg:postcode":"55369",
    "sg:province":"MN",
    "sg:tags":[
        "internet"
    ],
    "wof:name":"Lavonne's Home Business Inc",
    "wof:placetype":"venue"
},
  "geometry": {"coordinates":[-93.454239,45.111149],"type":"Point"}
}