{
  "type": "Feature",
  "properties": {
    "addr:full":"2706 290th St Marshall MN 56258",
    "addr:housenumber":"2706",
    "addr:postcode":"56258",
    "addr:street":"290Th St",
    "iso:country":"US",
    "sg:address":"2706 290th St",
    "sg:city":"Marshall",
    "sg:classifiers":[
        {
            "category":"Manufacturing",
            "subcategory":"Signs",
            "type":"Manufacturing & Wholesale Goods"
        }
    ],
    "sg:phone":"+1 507 537 1148",
    "sg:postcode":"56258",
    "sg:province":"MN",
    "wof:name":"Sign Shop",
    "wof:placetype":"venue"
},
  "geometry": {"coordinates":[-95.75519199999999,44.472324],"type":"Point"}
}