{
  "type": "Feature",
  "properties": {
    "addr:full":"800 Century Ave SW Hutchinson MN 55350",
    "addr:housenumber":"800",
    "addr:postcode":"55350",
    "addr:street":"Century Ave Sw",
    "iso:country":"US",
    "sg:address":"800 Century Ave SW",
    "sg:city":"Hutchinson",
    "sg:classifiers":[
        {
            "category":"Recreation",
            "type":"Entertainment"
        }
    ],
    "sg:phone":"+1 320 587 2499",
    "sg:postcode":"55350",
    "sg:province":"MN",
    "wof:name":"McLoud County Agribition",
    "wof:placetype":"venue"
},
  "geometry": {"coordinates":[-94.38323699999999,44.874348],"type":"Point"}
}