{
  "type": "Feature",
  "properties": {
    "addr:full":"4638 381st Ave NW Dalbo MN 55017",
    "addr:housenumber":"4638",
    "addr:postcode":"55017",
    "addr:street":"381St Ave Nw Dalbo",
    "iso:country":"US",
    "sg:address":"4638 381st Ave NW",
    "sg:city":"Dalbo",
    "sg:classifiers":[
        {
            "category":"Social Services",
            "subcategory":"Child Care",
            "type":"Services"
        },
        {
            "category":"Organizations",
            "subcategory":"Religious Organization",
            "type":"Services"
        }
    ],
    "sg:phone":"+1 763 689 1687",
    "sg:postcode":"55017",
    "sg:province":"MN",
    "sg:tags":[
        "kindergarten",
        "academic",
        "school"
    ],
    "wof:name":"Salem Lutheran Church E L C A",
    "wof:placetype":"venue"
},
  "geometry": {"coordinates":[-93.383937,45.658658],"type":"Point"}
}