{
  "type": "Feature",
  "properties": {
    "addr:full":"5308 29th Ave S Minneapolis MN 55417",
    "addr:housenumber":"5308",
    "addr:postcode":"55417",
    "addr:street":"29Th Ave S",
    "iso:country":"US",
    "sg:address":"5308 29th Ave S",
    "sg:city":"Minneapolis",
    "sg:classifiers":[
        {
            "category":"Professional",
            "type":"Services"
        }
    ],
    "sg:phone":"+1 612 728 2109",
    "sg:postcode":"55417",
    "sg:province":"MN",
    "wof:name":"Ispaz Inc",
    "wof:placetype":"venue"
},
  "geometry": {"coordinates":[-93.23108999999999,44.905494],"type":"Point"}
}