{
  "type": "Feature",
  "properties": {
    "iso:country":"US",
    "sg:address":"1200 16th St SW",
    "sg:city":"Rochester",
    "sg:classifiers":[
        {
            "category":"Shopping",
            "subcategory":"Pharmacy",
            "type":"Retail Goods"
        }
    ],
    "sg:phone":"+1 507 282 6442",
    "sg:postcode":"55902",
    "sg:province":"MN",
    "wof:name":"Econo Family Pharmacy",
    "wof:placetype":"venue"
},
  "geometry": {"coordinates":[-92.48045999999999,44.00093],"type":"Point"}
}