{
  "type": "Feature",
  "properties": {
    "addr:full":"15111 Greenhaven Dr Burnsville MN 55306",
    "addr:housenumber":"15111",
    "addr:postcode":"55306",
    "addr:street":"Greenhaven Dr",
    "iso:country":"US",
    "sg:address":"15111 Greenhaven Dr",
    "sg:city":"Burnsville",
    "sg:classifiers":[
        {
            "category":"Shopping",
            "subcategory":"Computers & Home Electronics",
            "type":"Retail Goods"
        }
    ],
    "sg:phone":"+1 952 898 9526",
    "sg:postcode":"55306",
    "sg:province":"MN",
    "wof:name":"Vintage ERA Audio & Menagerie",
    "wof:placetype":"venue"
},
  "geometry": {"coordinates":[-93.290992,44.730261],"type":"Point"}
}