{
  "type": "Feature",
  "properties": {
    "iso:country":"US",
    "sg:address":"1155 Willow St",
    "sg:city":"Faribault",
    "sg:classifiers":[
        {
            "category":"Real Estate",
            "subcategory":"Developer",
            "type":"Services"
        },
        {
            "category":"Real Estate",
            "subcategory":"Real Estate Operator",
            "type":"Services"
        }
    ],
    "sg:phone":"+1 507 334 7786",
    "sg:postcode":"55021",
    "sg:province":"MN",
    "sg:tags":[
        "mobile",
        "home",
        "site"
    ],
    "wof:name":"Sunrise Mobile Home Park",
    "wof:placetype":"venue"
},
  "geometry": {"coordinates":[-93.272926,44.277075],"type":"Point"}
}