{
  "type": "Feature",
  "properties": {
    "iso:country":"US",
    "sg:address":"2525 Chicago Ave S",
    "sg:city":"Minneapolis",
    "sg:classifiers":[
        {
            "category":"Health Services",
            "subcategory":"Hospital",
            "type":"Services"
        }
    ],
    "sg:phone":"+1 612 813 6100",
    "sg:postcode":"55404",
    "sg:province":"MN",
    "sg:tags":[
        "specialty",
        "general"
    ],
    "sg:website":"www.childrenshc.org",
    "wof:name":"Children's Hospital & Clinics",
    "wof:placetype":"venue"
},
  "geometry": {"coordinates":[-93.26248699999999,44.955963],"type":"Point"}
}