{
  "type": "Feature",
  "properties": {
    "addr:full":"535 Coon Rapids Blvd NW # 100 Minneapolis MN 55433",
    "addr:housenumber":"535",
    "addr:postcode":"55433",
    "addr:street":"Coon Rapids Blvd Nw # 100",
    "iso:country":"US",
    "sg:address":"535 Coon Rapids Blvd NW # 100",
    "sg:city":"Minneapolis",
    "sg:classifiers":[
        {
            "category":"Professional",
            "subcategory":"Testing Lab",
            "type":"Services"
        }
    ],
    "sg:phone":"+1 952 854 7000",
    "sg:postcode":"55433",
    "sg:province":"MN",
    "sg:tags":[
        "analytical",
        "laboratory"
    ],
    "wof:name":"Technical Solutions, Inc.",
    "wof:placetype":"venue"
},
  "geometry": {"coordinates":[-93.280492,45.143818],"type":"Point"}
}