{
  "type": "Feature",
  "properties": {
    "addr:full":"6023 E Viking Blvd Wyoming MN 55092",
    "addr:housenumber":"6023",
    "addr:postcode":"55092",
    "addr:street":"E Viking Blvd",
    "iso:country":"US",
    "sg:address":"6023 E Viking Blvd",
    "sg:city":"Wyoming",
    "sg:classifiers":[
        {
            "category":"Real Estate",
            "subcategory":"Real Estate Operator",
            "type":"Services"
        }
    ],
    "sg:phone":"+1 651 462 4659",
    "sg:postcode":"55092",
    "sg:province":"MN",
    "sg:tags":[
        "building",
        "apartment"
    ],
    "wof:name":"Oak Ridge Apartments",
    "wof:placetype":"venue"
},
  "geometry": {"coordinates":[-92.98305499999999,45.336306],"type":"Point"}
}