{
  "type": "Feature",
  "properties": {
    "iso:country":"US",
    "sg:address":"105 3rd St SE",
    "sg:city":"Aitkin",
    "sg:classifiers":[
        {
            "category":"Building & Trades",
            "subcategory":"Electrical",
            "type":"Services"
        }
    ],
    "sg:phone":"+1 218 927 6075",
    "sg:postcode":"56431",
    "sg:province":"MN",
    "sg:tags":[
        "electric",
        "contractor"
    ],
    "wof:name":"Kenneth Curran Electric",
    "wof:placetype":"venue"
},
  "geometry": {"coordinates":[-93.705702,46.527072],"type":"Point"}
}