{
  "type": "Feature",
  "properties": {
    "iso:country":"US",
    "sg:address":"4900 Wisconsin Ave N",
    "sg:city":"Minneapolis",
    "sg:classifiers":[
        {
            "category":"Building & Trades",
            "subcategory":"Cleaning & Sanitation",
            "type":"Services"
        }
    ],
    "sg:phone":"+1 763 595 9457",
    "sg:postcode":"55428",
    "sg:province":"MN",
    "sg:tags":[
        "window"
    ],
    "wof:name":"A Picture Perfect Windows",
    "wof:placetype":"venue"
},
  "geometry": {"coordinates":[-93.38329899999999,45.044699],"type":"Point"}
}