{
  "type": "Feature",
  "properties": {
    "iso:country":"US",
    "sg:address":"920 E 1st St",
    "sg:city":"Duluth",
    "sg:classifiers":[
        {
            "category":"Health Services",
            "subcategory":"Doctor",
            "type":"Services"
        }
    ],
    "sg:phone":"+1 218 249 7950",
    "sg:postcode":"55805",
    "sg:province":"MN",
    "sg:tags":[
        "physician",
        "surgeon"
    ],
    "wof:name":"Northland Surgical Assoc",
    "wof:placetype":"venue"
},
  "geometry": {"coordinates":[-92.087042,46.796887],"type":"Point"}
}