{
  "type": "Feature",
  "properties": {
    "iso:country":"US",
    "sg:address":"7234 State Hwy 16",
    "sg:city":"Hokah",
    "sg:classifiers":[
        {
            "category":"Farming",
            "subcategory":"Farm",
            "type":"Manufacturing & Wholesale Goods"
        }
    ],
    "sg:phone":"+1 507 894 4441",
    "sg:postcode":"55941",
    "sg:province":"MN",
    "sg:tags":[
        "crop",
        "general"
    ],
    "wof:name":"Arnet Farm",
    "wof:placetype":"venue"
},
  "geometry": {"coordinates":[-91.398456,43.7585],"type":"Point"}
}