{
  "type": "Feature",
  "properties": {
    "iso:country":"US",
    "sg:address":"1949 Desoto St",
    "sg:city":"Saint Paul",
    "sg:classifiers":[
        {
            "category":"Real Estate",
            "subcategory":"Real Estate Operator",
            "type":"Services"
        }
    ],
    "sg:phone":"+1 651 774 1482",
    "sg:postcode":"55117",
    "sg:province":"MN",
    "sg:tags":[
        "building",
        "nonresidential"
    ],
    "wof:name":"Charai Properties LLC",
    "wof:placetype":"venue"
},
  "geometry": {"coordinates":[-93.081422,44.999942],"type":"Point"}
}