{
  "type": "Feature",
  "properties": {
    "addr:full":"2925 Dean Pkwy Minneapolis MN 55416",
    "addr:housenumber":"2925",
    "addr:postcode":"55416",
    "addr:street":"Dean Pkwy",
    "iso:country":"US",
    "sg:address":"2925 Dean Pkwy",
    "sg:city":"Minneapolis",
    "sg:classifiers":[
        {
            "category":"Banks & Credit Unions",
            "subcategory":"Bank",
            "type":"Services"
        }
    ],
    "sg:phone":"+1 612 925 8324",
    "sg:postcode":"55416",
    "sg:province":"MN",
    "sg:tags":[
        "loan"
    ],
    "wof:name":"Equity Captial",
    "wof:placetype":"venue"
},
  "geometry": {"coordinates":[-93.315685,44.950028],"type":"Point"}
}