{
  "type": "Feature",
  "properties": {
    "iso:country":"US",
    "sg:address":"495 W North St",
    "sg:city":"Owatonna",
    "sg:classifiers":[
        {
            "category":"Food & Beverages",
            "subcategory":"Supermarket",
            "type":"Retail Goods"
        },
        {
            "category":"Retail",
            "subcategory":"Photofinishing",
            "type":"Services"
        },
        {
            "category":"Professional",
            "subcategory":"Printing & Photocopies",
            "type":"Services"
        },
        {
            "category":"Shopping",
            "subcategory":"Pharmacy",
            "type":"Retail Goods"
        },
        {
            "category":"Shopping",
            "subcategory":"Florist",
            "type":"Retail Goods"
        }
    ],
    "sg:phone":"+1 507 451 7220",
    "sg:postcode":"55060",
    "sg:province":"MN",
    "sg:tags":[
        "photo",
        "finishing-custom",
        "laboratories-commercial",
        "laboratory",
        "super",
        "store"
    ],
    "wof:name":"Cashwise Photo Lab",
    "wof:placetype":"venue"
},
  "geometry": {"coordinates":[-93.236251,44.09346],"type":"Point"}
}