{
  "type": "Feature",
  "properties": {
    "iso:country":"US",
    "sg:address":"1427 Indian Oaks Ct",
    "sg:city":"Saint Paul",
    "sg:classifiers":[
        {
            "category":"Retail",
            "subcategory":"Laundry & Dry Cleaning",
            "type":"Services"
        }
    ],
    "sg:phone":"+1 612 724 9000",
    "sg:postcode":"55112",
    "sg:province":"MN",
    "wof:name":"Omega Carpet Cleaning",
    "wof:placetype":"venue"
},
  "geometry": {"coordinates":[-93.160766,45.070627],"type":"Point"}
}