{
  "type": "Feature",
  "properties": {
    "addr:full":"5510 W Broadway, Ste 113-C Minneapolis MN 55428",
    "addr:housenumber":"5510",
    "addr:postcode":"55428",
    "addr:street":"W Broadway Ste 113-C",
    "iso:country":"US",
    "sg:address":"5510 W Broadway, Ste 113-C",
    "sg:city":"Minneapolis",
    "sg:classifiers":[
        {
            "category":"Health Services",
            "subcategory":"Doctor",
            "type":"Services"
        },
        {
            "category":"Wholesale",
            "subcategory":"Medical Equipment & Supplies",
            "type":"Manufacturing & Wholesale Goods"
        },
        {
            "category":"Retail",
            "subcategory":"Repair Shop",
            "type":"Services"
        },
        {
            "category":"Health Services",
            "subcategory":"Health Practitioner",
            "type":"Services"
        },
        {
            "category":"Utilities",
            "subcategory":"Natural Gas",
            "type":"Services"
        }
    ],
    "sg:phone":"+1 763 533 5722",
    "sg:postcode":"55428",
    "sg:province":"MN",
    "sg:tags":[
        "sound",
        "aids-manufacturers",
        "level",
        "testing",
        "aids-parts",
        "hearing",
        "device",
        "assistive",
        "aid",
        "audiologists",
        "repairing"
    ],
    "sg:website":"http://local.sonus.com/Hearing-Aids-in-Crystal",
    "wof:name":"Sonus Hearing Care Professionals: Crystal",
    "wof:placetype":"venue"
},
  "geometry": {"coordinates":[-93.363539,45.052601],"type":"Point"}
}