{
  "type": "Feature",
  "properties": {
    "iso:country":"US",
    "sg:address":"8120 Penn Ave S",
    "sg:city":"Bloomington",
    "sg:classifiers":[
        {
            "category":"Wholesale",
            "subcategory":"Electrical",
            "type":"Manufacturing & Wholesale Goods"
        },
        {
            "category":"Wholesale",
            "subcategory":"Durable Goods & Equipment",
            "type":"Manufacturing & Wholesale Goods"
        }
    ],
    "sg:phone":"+1 952 884 6515",
    "sg:postcode":"55431",
    "sg:province":"MN",
    "sg:tags":[
        "electronic",
        "representative",
        "manufacturer"
    ],
    "wof:name":"Horizon Technologies Inc",
    "wof:placetype":"venue"
},
  "geometry": {"coordinates":[-93.308842,44.855943],"type":"Point"}
}