{
  "type": "Feature",
  "properties": {
    "addr:full":"2023 S Broadway St New Ulm MN 56073",
    "addr:housenumber":"2023",
    "addr:postcode":"56073",
    "addr:street":"S Broadway St",
    "iso:country":"US",
    "sg:address":"2023 S Broadway St",
    "sg:city":"New Ulm",
    "sg:classifiers":[
        {
            "category":"Health Services",
            "subcategory":"Doctor",
            "type":"Services"
        }
    ],
    "sg:phone":"+1 507 359 2995",
    "sg:postcode":"56073",
    "sg:province":"MN",
    "sg:tags":[
        "medical"
    ],
    "wof:name":"South Broadway Fmly Med Ctr PA",
    "wof:placetype":"venue"
},
  "geometry": {"coordinates":[-94.44111700000001,44.292967],"type":"Point"}
}