{
  "type": "Feature",
  "properties": {
    "addr:full":"5025 Cheshire Ln N Minneapolis MN 55446",
    "addr:housenumber":"5025",
    "addr:postcode":"55446",
    "addr:street":"Cheshire Ln N",
    "iso:country":"US",
    "sg:address":"5025 Cheshire Ln N",
    "sg:city":"Minneapolis",
    "sg:classifiers":[
        {
            "category":"Building & Trades",
            "subcategory":"Cleaning & Sanitation",
            "type":"Services"
        },
        {
            "category":"Retail",
            "subcategory":"Repair Shop",
            "type":"Services"
        }
    ],
    "sg:phone":"+1 763 551 0202",
    "sg:postcode":"55446",
    "sg:province":"MN",
    "sg:tags":[
        "property",
        "gen",
        "maintenance",
        "mechanical"
    ],
    "sg:website":"www.unitedoperations.com",
    "wof:name":"United Operations Inc",
    "wof:placetype":"venue"
},
  "geometry": {"coordinates":[-93.457694,45.045303],"type":"Point"}
}