{
  "type": "Feature",
  "properties": {
    "iso:country":"US",
    "sg:address":"2166 Silver Lake Rd NW",
    "sg:city":"St Paul",
    "sg:classifiers":[
        {
            "category":"Shopping",
            "subcategory":"Hobbies, Toys, & Games",
            "type":"Retail Goods"
        },
        {
            "category":"Manufacturing",
            "subcategory":"Toys & Sporting Goods",
            "type":"Manufacturing & Wholesale Goods"
        }
    ],
    "sg:phone":"+1 651 635 9480",
    "sg:postcode":"55112",
    "sg:province":"MN",
    "sg:tags":[
        "model",
        "mfg",
        "supply"
    ],
    "wof:name":"Beckers Model Railroad Supply",
    "wof:placetype":"venue"
},
  "geometry": {"coordinates":[-93.218987,45.083959],"type":"Point"}
}