{
  "type": "Feature",
  "properties": {
    "addr:full":"29868 410th St Le Sueur MN 56058",
    "addr:housenumber":"29868",
    "addr:postcode":"56058",
    "addr:street":"410Th St",
    "iso:country":"US",
    "sg:address":"29868 410th St",
    "sg:city":"Le Sueur",
    "sg:classifiers":[
        {
            "category":"Farming",
            "subcategory":"Farm",
            "type":"Manufacturing & Wholesale Goods"
        }
    ],
    "sg:phone":"+1 507 931 5622",
    "sg:postcode":"56058",
    "sg:province":"MN",
    "sg:tags":[
        "crop",
        "general"
    ],
    "wof:name":"Gerald Flowers",
    "wof:placetype":"venue"
},
  "geometry": {"coordinates":[-93.86539,44.355307],"type":"Point"}
}