{
  "type": "Feature",
  "properties": {
    "iso:country":"US",
    "sg:address":"85 Main St",
    "sg:city":"La Crescent",
    "sg:classifiers":[
        {
            "category":"Home & Garden",
            "subcategory":"Garden Supply",
            "type":"Retail Goods"
        }
    ],
    "sg:phone":"+1 507 895 8888",
    "sg:postcode":"55947",
    "sg:province":"MN",
    "sg:tags":[
        "landscaping",
        "equipment"
    ],
    "wof:name":"Classic Rock Products",
    "wof:placetype":"venue"
},
  "geometry": {"coordinates":[-91.34410699999999,43.760984],"type":"Point"}
}