{
  "type": "Feature",
  "properties": {
    "iso:country":"US",
    "sg:address":"4625 Decatur Ave N",
    "sg:city":"Minneapolis",
    "sg:classifiers":[
        {
            "category":"Professional",
            "subcategory":"Business Services",
            "type":"Services"
        }
    ],
    "sg:phone":"+1 612 715 0574",
    "sg:postcode":"55428",
    "sg:province":"MN",
    "sg:tags":[
        "embroidery"
    ],
    "wof:name":"Lgm Embroidery",
    "wof:placetype":"venue"
},
  "geometry": {"coordinates":[-93.392768,45.039201],"type":"Point"}
}