{
  "type": "Feature",
  "properties": {
    "iso:country":"US",
    "sg:address":"10007 Baltimore St NE",
    "sg:city":"Minneapolis",
    "sg:classifiers":[
        {
            "category":"Wholesale",
            "subcategory":"Machinery & Supplies",
            "type":"Manufacturing & Wholesale Goods"
        }
    ],
    "sg:phone":"+1 763 786 1803",
    "sg:postcode":"55449",
    "sg:province":"MN",
    "sg:tags":[
        "equipment",
        "laundry",
        "repair"
    ],
    "sg:website":"http://www.darlingsales.com",
    "wof:name":"Darlings Service Co",
    "wof:placetype":"venue"
},
  "geometry": {"coordinates":[-93.23334699999999,45.152232],"type":"Point"}
}