{
  "type": "Feature",
  "properties": {
    "iso:country":"US",
    "sg:address":"47308 180th Ave",
    "sg:city":"Zumbrota",
    "sg:phone":"+1 507 732 5692",
    "sg:postcode":"55992",
    "sg:province":"MN",
    "sg:tags":[
        "farm",
        "corn"
    ],
    "wof:name":"Fred Mark",
    "wof:placetype":"venue"
},
  "geometry": {"coordinates":[-92.670569,44.260359],"type":"Point"}
}