{
  "type": "Feature",
  "properties": {
    "iso:country":"US",
    "sg:address":"1002 3rd Ave NE",
    "sg:city":"Minneapolis",
    "sg:classifiers":[
        {
            "category":"Real Estate",
            "subcategory":"Real Estate Operator",
            "type":"Services"
        }
    ],
    "sg:phone":"+1 763 684 1907",
    "sg:postcode":"55413",
    "sg:province":"MN",
    "sg:tags":[
        "apartment"
    ],
    "wof:name":"Buffalo Court Apartments",
    "wof:placetype":"venue"
},
  "geometry": {"coordinates":[-93.247558,44.995162],"type":"Point"}
}