{
  "type": "Feature",
  "properties": {
    "addr:full":"300 Industrial Blvd NE Minneapolis MN 55413",
    "addr:housenumber":"300",
    "addr:postcode":"55413",
    "addr:street":"Industrial Blvd Ne",
    "iso:country":"US",
    "sg:address":"300 Industrial Blvd NE",
    "sg:city":"Minneapolis",
    "sg:classifiers":[
        {
            "category":"Education",
            "subcategory":"School",
            "type":"Public Place"
        }
    ],
    "sg:phone":"+1 612 722 5470",
    "sg:postcode":"55413",
    "sg:province":"MN",
    "wof:name":"Minnesota Internship Center",
    "wof:placetype":"venue"
},
  "geometry": {"coordinates":[-93.210353,44.991639],"type":"Point"}
}