{
  "type": "Feature",
  "properties": {
    "iso:country":"US",
    "sg:address":"4005 Central Ave NE",
    "sg:city":"Minneapolis",
    "sg:classifiers":[
        {
            "category":"Restaurant",
            "type":"Food & Drink"
        }
    ],
    "sg:phone":"+1 763 788 6673",
    "sg:postcode":"55421",
    "sg:province":"MN",
    "wof:name":"Starbar & Grill",
    "wof:placetype":"venue"
},
  "geometry": {"coordinates":[-93.247398,45.0411],"type":"Point"}
}