{
  "type": "Feature",
  "properties": {
    "addr:full":"18752 US Hwy 169 Milaca MN 56353",
    "addr:housenumber":"18752",
    "addr:postcode":"56353",
    "addr:street":"Us Hwy 169",
    "iso:country":"US",
    "sg:address":"18752 US Hwy 169",
    "sg:city":"Milaca",
    "sg:classifiers":[
        {
            "category":"Autos & Motor Vehicles",
            "subcategory":"Automobile Sales",
            "type":"Retail Goods"
        }
    ],
    "sg:phone":"+1 320 983 3224",
    "sg:postcode":"56353",
    "sg:province":"MN",
    "sg:tags":[
        "used"
    ],
    "wof:name":"Stony Hill Auto",
    "wof:placetype":"venue"
},
  "geometry": {"coordinates":[-93.655553,45.821435],"type":"Point"}
}