{
  "type": "Feature",
  "properties": {
    "addr:full":"7038 126th St SW Motley MN 56466",
    "addr:housenumber":"7038",
    "addr:postcode":"56466",
    "addr:street":"126Th St Sw",
    "iso:country":"US",
    "sg:address":"7038 126th St SW",
    "sg:city":"Motley",
    "sg:classifiers":[
        {
            "category":"Shopping",
            "subcategory":"Hobbies, Toys, & Games",
            "type":"Retail Goods"
        },
        {
            "category":"Shopping",
            "subcategory":"Crafts & Fabrics",
            "type":"Retail Goods"
        }
    ],
    "sg:phone":"+1 218 352 6495",
    "sg:postcode":"56466",
    "sg:province":"MN",
    "sg:tags":[
        "shop",
        "hobby",
        "model",
        "supply"
    ],
    "wof:name":"Crafts By Shari And Friends",
    "wof:placetype":"venue"
},
  "geometry": {"coordinates":[-94.64818699999999,46.347788],"type":"Point"}
}