{
  "type": "Feature",
  "properties": {
    "addr:full":"5642 Feltl Rd Hopkins MN 55343",
    "addr:housenumber":"5642",
    "addr:postcode":"55343",
    "addr:street":"Feltl Rd",
    "iso:country":"US",
    "sg:address":"5642 Feltl Rd",
    "sg:city":"Hopkins",
    "sg:classifiers":[
        {
            "category":"Building & Trades",
            "subcategory":"Construction",
            "type":"Services"
        }
    ],
    "sg:phone":"+1 952 884 0800",
    "sg:postcode":"55343",
    "sg:province":"MN",
    "sg:tags":[
        "contractor"
    ],
    "wof:name":"Twin City Roofing Inc",
    "wof:placetype":"venue"
},
  "geometry": {"coordinates":[-93.419686,44.903851],"type":"Point"}
}