{
  "type": "Feature",
  "properties": {
    "addr:full":"3925 Chicago Ave S Minneapolis MN 55407",
    "addr:housenumber":"3925",
    "addr:postcode":"55407",
    "addr:street":"Chicago Ave S",
    "iso:country":"US",
    "sg:address":"3925 Chicago Ave S",
    "sg:city":"Minneapolis",
    "sg:classifiers":[
        {
            "category":"Professional",
            "type":"Services"
        }
    ],
    "sg:phone":"+1 612 825 0531",
    "sg:postcode":"55407",
    "sg:province":"MN",
    "wof:name":"Michael Ackerman",
    "wof:placetype":"venue"
},
  "geometry": {"coordinates":[-93.262399,44.930987],"type":"Point"}
}