{
  "type": "Feature",
  "properties": {
    "iso:country":"US",
    "sg:address":"616 Atlantic Ave",
    "sg:city":"Morris",
    "sg:classifiers":[
        {
            "category":"Personal",
            "subcategory":"Beauty Salon",
            "type":"Services"
        }
    ],
    "sg:phone":"+1 320 589 1420",
    "sg:postcode":"56267",
    "sg:province":"MN",
    "sg:tags":[
        "shop",
        "tanning"
    ],
    "wof:name":"Sonia's Hair Clinic",
    "wof:placetype":"venue"
},
  "geometry": {"coordinates":[-95.914922,45.586914],"type":"Point"}
}