{
  "type": "Feature",
  "properties": {
    "iso:country":"US",
    "sg:address":"370 W 2nd St",
    "sg:city":"Winona",
    "sg:classifiers":[
        {
            "category":"Wholesale",
            "subcategory":"Computers",
            "type":"Manufacturing & Wholesale Goods"
        },
        {
            "category":"Professional",
            "subcategory":"Computer Services",
            "type":"Services"
        }
    ],
    "sg:phone":"+1 507 454 7786",
    "sg:postcode":"55987",
    "sg:province":"MN",
    "sg:tags":[
        "consultant",
        "provider",
        "network",
        "repair"
    ],
    "sg:website":"www.up-n-running.com",
    "wof:name":"Up-N-Running Consulting Inc",
    "wof:placetype":"venue"
},
  "geometry": {"coordinates":[-91.644722,44.05578],"type":"Point"}
}