{
  "type": "Feature",
  "properties": {
    "iso:country":"US",
    "sg:address":"1415 2nd St S",
    "sg:city":"Sauk Centre",
    "sg:classifiers":[
        {
            "category":"Farming",
            "subcategory":"Dairy Farm",
            "type":"Manufacturing & Wholesale Goods"
        }
    ],
    "sg:phone":"+1 320 352 2063",
    "sg:postcode":"56378",
    "sg:province":"MN",
    "wof:name":"Osakis Creamery Assn Coop",
    "wof:placetype":"venue"
},
  "geometry": {"coordinates":[-94.96438000000001,45.737953],"type":"Point"}
}