{
  "type": "Feature",
  "properties": {
    "addr:full":"66276 350th St Gibbon MN 55335",
    "addr:housenumber":"66276",
    "addr:postcode":"55335",
    "addr:street":"350Th St",
    "iso:country":"US",
    "sg:address":"66276 350th St",
    "sg:city":"Gibbon",
    "sg:classifiers":[
        {
            "category":"Farming",
            "subcategory":"Dairy Farm",
            "type":"Manufacturing & Wholesale Goods"
        }
    ],
    "sg:phone":"+1 507 359 9799",
    "sg:postcode":"55335",
    "sg:province":"MN",
    "wof:name":"Chad Farmer Tweit",
    "wof:placetype":"venue"
},
  "geometry": {"coordinates":[-94.603331,44.441998],"type":"Point"}
}