{
  "type": "Feature",
  "properties": {
    "iso:country":"US",
    "sg:address":"500 Vadnais Rd",
    "sg:city":"Vadnais Heights",
    "sg:classifiers":[
        {
            "category":"Professional",
            "subcategory":"Advertising",
            "type":"Services"
        }
    ],
    "sg:phone":"+1 651 605 3400",
    "sg:postcode":"55127",
    "sg:province":"MN",
    "sg:tags":[
        "designer",
        "display",
        "producer"
    ],
    "wof:name":"Immedia",
    "wof:placetype":"venue"
},
  "geometry": {"coordinates":[-93.079539,45.036948],"type":"Point"}
}