{
  "type": "Feature",
  "properties": {
    "addr:full":"11165 Zealand Ave N Champlin MN 55316",
    "addr:housenumber":"11165",
    "addr:postcode":"55316",
    "addr:street":"Zealand Ave N",
    "iso:country":"US",
    "sg:address":"11165 Zealand Ave N",
    "sg:city":"Champlin",
    "sg:classifiers":[
        {
            "category":"Building & Trades",
            "subcategory":"Construction",
            "type":"Services"
        }
    ],
    "sg:phone":"+1 763 422 6764",
    "sg:postcode":"55316",
    "sg:province":"MN",
    "sg:tags":[
        "contractor"
    ],
    "wof:name":"Aravia Group",
    "wof:placetype":"venue"
},
  "geometry": {"coordinates":[-93.39097,45.155689],"type":"Point"}
}