{
  "type": "Feature",
  "properties": {
    "iso:country":"US",
    "sg:address":"11165 Zealand Ave N",
    "sg:city":"Champlin",
    "sg:classifiers":[
        {
            "category":"Building & Trades",
            "subcategory":"Construction",
            "type":"Services"
        }
    ],
    "sg:phone":"+1 763 422 6764",
    "sg:postcode":"55316",
    "sg:province":"MN",
    "sg:tags":[
        "contractor"
    ],
    "wof:name":"Aravia Group",
    "wof:placetype":"venue"
},
  "geometry": {"coordinates":[-93.39097,45.155689],"type":"Point"}
}