{
  "type": "Feature",
  "properties": {
    "addr:full":"3952 Lyndale Ave S Minneapolis MN 55409",
    "addr:housenumber":"3952",
    "addr:postcode":"55409",
    "addr:street":"Lyndale Ave S",
    "iso:country":"US",
    "sg:address":"3952 Lyndale Ave S",
    "sg:city":"Minneapolis",
    "sg:classifiers":[
        {
            "category":"Shopping",
            "subcategory":"Clothing, Apparel, & Fashions",
            "type":"Retail Goods"
        }
    ],
    "sg:phone":"+1 612 822 7034",
    "sg:postcode":"55409",
    "sg:province":"MN",
    "wof:name":"Larues LLC",
    "wof:placetype":"venue"
},
  "geometry": {"coordinates":[-93.288337,44.931413],"type":"Point"}
}