{
  "type": "Feature",
  "properties": {
    "addr:full":"26967 Hidden Cove Rd Cold Spring MN 56320",
    "addr:housenumber":"26967",
    "addr:postcode":"56320",
    "addr:street":"Hidden Cove Rd",
    "iso:country":"US",
    "sg:address":"26967 Hidden Cove Rd",
    "sg:city":"Cold Spring",
    "sg:classifiers":[
        {
            "category":"Organizations",
            "subcategory":"Membership Organization",
            "type":"Services"
        }
    ],
    "sg:phone":"+1 320 685 3275",
    "sg:postcode":"56320",
    "sg:province":"MN",
    "wof:name":"Turnquist Family Partnership",
    "wof:placetype":"venue"
},
  "geometry": {"coordinates":[-94.45831099999999,45.515786],"type":"Point"}
}