{
  "type": "Feature",
  "properties": {
    "iso:country":"US",
    "sg:address":"1913 Keystone Dr",
    "sg:city":"Albert Lea",
    "sg:classifiers":[
        {
            "category":"Wholesale",
            "subcategory":"Non-durable Goods",
            "type":"Manufacturing & Wholesale Goods"
        }
    ],
    "sg:phone":"+1 507 377 8799",
    "sg:postcode":"56007",
    "sg:province":"MN",
    "wof:name":"Jt Ideas",
    "wof:placetype":"venue"
},
  "geometry": {"coordinates":[-93.361991,43.670583],"type":"Point"}
}