{
  "type": "Feature",
  "properties": {
    "iso:country":"US",
    "sg:address":"540 Old Crystal Bay Rd N",
    "sg:city":"Long Lake",
    "sg:classifiers":[
        {
            "category":"Shopping",
            "subcategory":"Clothing, Apparel, & Fashions",
            "type":"Retail Goods"
        }
    ],
    "sg:phone":"+1 952 475 3594",
    "sg:postcode":"55356",
    "sg:province":"MN",
    "sg:tags":[
        "leather",
        "shop"
    ],
    "wof:name":"Funks Leathercraft",
    "wof:placetype":"venue"
},
  "geometry": {"coordinates":[-93.594148,44.986658],"type":"Point"}
}