{
  "type": "Feature",
  "properties": {
    "iso:country":"US",
    "sg:address":"805 North Rd",
    "sg:city":"Cloquet",
    "sg:classifiers":[
        {
            "category":"Building & Trades",
            "subcategory":"Construction",
            "type":"Services"
        }
    ],
    "sg:phone":"+1 218 879 6631",
    "sg:postcode":"55720",
    "sg:province":"MN",
    "sg:tags":[
        "excavation",
        "excavating",
        "contractor"
    ],
    "wof:name":"Jerry Anderson Contracting",
    "wof:placetype":"venue"
},
  "geometry": {"coordinates":[-92.457144,46.735705],"type":"Point"}
}