{
  "type": "Feature",
  "properties": {
    "addr:full":"2785 Stark Rd Harris MN 55032",
    "addr:housenumber":"2785",
    "addr:postcode":"55032",
    "addr:street":"Stark Rd",
    "iso:country":"US",
    "sg:address":"2785 Stark Rd",
    "sg:city":"Harris",
    "sg:classifiers":[
        {
            "category":"Manufacturing",
            "subcategory":"Pottery",
            "type":"Manufacturing & Wholesale Goods"
        }
    ],
    "sg:phone":"+1 651 674 4656",
    "sg:postcode":"55032",
    "sg:province":"MN",
    "sg:tags":[
        "product",
        "mfg"
    ],
    "wof:name":"Robert Briscoe Stoneware",
    "wof:placetype":"venue"
},
  "geometry": {"coordinates":[-93.050389,45.583425],"type":"Point"}
}