{
  "type": "Feature",
  "properties": {
    "addr:full":"12156 Grandview Ter Saint Paul MN 55124",
    "addr:housenumber":"12156",
    "addr:postcode":"55124",
    "addr:street":"Grandview Ter",
    "iso:country":"US",
    "sg:address":"12156 Grandview Ter",
    "sg:city":"Saint Paul",
    "sg:classifiers":[
        {
            "category":"Professional",
            "subcategory":"Business Services",
            "type":"Services"
        }
    ],
    "sg:phone":"+1 651 686 9721",
    "sg:postcode":"55124",
    "sg:province":"MN",
    "wof:name":"Tadich Group LLC",
    "wof:placetype":"venue"
},
  "geometry": {"coordinates":[-93.22080099999999,44.773821],"type":"Point"}
}