{
  "type": "Feature",
  "properties": {
    "addr:full":"10745 Lawrence Ave NW Annandale MN 55302",
    "addr:housenumber":"10745",
    "addr:postcode":"55302",
    "addr:street":"Lawrence Ave Nw",
    "iso:country":"US",
    "sg:address":"10745 Lawrence Ave NW",
    "sg:city":"Annandale",
    "sg:classifiers":[
        {
            "category":"Real Estate",
            "subcategory":"Developer",
            "type":"Services"
        }
    ],
    "sg:phone":"+1 320 274 2082",
    "sg:postcode":"55302",
    "sg:province":"MN",
    "wof:name":"Jerry F Truman",
    "wof:placetype":"venue"
},
  "geometry": {"coordinates":[-94.123369,45.307975],"type":"Point"}
}