{
  "type": "Feature",
  "properties": {
    "addr:full":"1603 US Hwy 59 Garvin MN 56132",
    "addr:housenumber":"1603",
    "addr:postcode":"56132",
    "addr:street":"Us Hwy 59",
    "iso:country":"US",
    "sg:address":"1603 US Hwy 59",
    "sg:city":"Garvin",
    "sg:classifiers":[
        {
            "category":"Professional",
            "type":"Services"
        }
    ],
    "sg:phone":"+1 507 629 3271",
    "sg:postcode":"56132",
    "sg:province":"MN",
    "sg:tags":[
        "establishment"
    ],
    "wof:name":"Nature Nook",
    "wof:placetype":"venue"
},
  "geometry": {"coordinates":[-95.755278,44.297184],"type":"Point"}
}