{
  "type": "Feature",
  "properties": {
    "addr:full":"1200 State Hwy 36 E Saint Paul MN 55109",
    "addr:housenumber":"1200",
    "addr:postcode":"55109",
    "addr:street":"State Hwy 36 E",
    "iso:country":"US",
    "sg:address":"1200 State Hwy 36 E",
    "sg:city":"Saint Paul",
    "sg:classifiers":[
        {
            "category":"Restaurant",
            "type":"Food & Drink"
        }
    ],
    "sg:phone":"+1 651 484 8489",
    "sg:postcode":"55109",
    "sg:province":"MN",
    "sg:tags":[
        "eating"
    ],
    "wof:name":"Embers",
    "wof:placetype":"venue"
},
  "geometry": {"coordinates":[-93.04901099999999,45.011541],"type":"Point"}
}