{
  "type": "Feature",
  "properties": {
    "iso:country":"US",
    "sg:address":"1353 Clarence St",
    "sg:city":"Saint Paul",
    "sg:classifiers":[
        {
            "category":"Real Estate",
            "subcategory":"Real Estate Operator",
            "type":"Services"
        }
    ],
    "sg:phone":"+1 651 771 5861",
    "sg:postcode":"55106",
    "sg:province":"MN",
    "sg:tags":[
        "building",
        "nonresidential"
    ],
    "wof:name":"Osland Properties Inc",
    "wof:placetype":"venue"
},
  "geometry": {"coordinates":[-93.043198,44.981724],"type":"Point"}
}