{
  "type": "Feature",
  "properties": {
    "addr:full":"9237 Brandywine Rd Hamel MN 55340",
    "addr:housenumber":"9237",
    "addr:postcode":"55340",
    "addr:street":"Brandywine Rd",
    "iso:country":"US",
    "sg:address":"9237 Brandywine Rd",
    "sg:city":"Hamel",
    "sg:classifiers":[
        {
            "category":"Retail",
            "subcategory":"Auto Repair",
            "type":"Services"
        }
    ],
    "sg:phone":"+1 612 850 2226",
    "sg:postcode":"55340",
    "sg:province":"MN",
    "sg:tags":[
        "general"
    ],
    "wof:name":"Finishing Touch Automotive",
    "wof:placetype":"venue"
},
  "geometry": {"coordinates":[-93.530379,45.123645],"type":"Point"}
}