{
  "type": "Feature",
  "properties": {
    "iso:country":"US",
    "sg:address":"1055 Brentwood Ct SE",
    "sg:city":"Rochester",
    "sg:classifiers":[
        {
            "category":"Retail",
            "subcategory":"Auto Repair",
            "type":"Services"
        }
    ],
    "sg:phone":"+1 507 289 7309",
    "sg:postcode":"55904",
    "sg:province":"MN",
    "sg:tags":[
        "general"
    ],
    "wof:name":"Lanes Repair Service",
    "wof:placetype":"venue"
},
  "geometry": {"coordinates":[-92.370034,44.006134],"type":"Point"}
}