{
  "type": "Feature",
  "properties": {
    "iso:country":"US",
    "sg:address":"3415 Douglas Dr N",
    "sg:city":"Minneapolis",
    "sg:classifiers":[
        {
            "category":"Manufacturing",
            "subcategory":"Tools & Machinery",
            "type":"Manufacturing & Wholesale Goods"
        }
    ],
    "sg:phone":"+1 763 533 0034",
    "sg:postcode":"55422",
    "sg:province":"MN",
    "sg:tags":[
        "industry",
        "mfg"
    ],
    "wof:name":"Northland Water Cond Co",
    "wof:placetype":"venue"
},
  "geometry": {"coordinates":[-93.360128,45.0204],"type":"Point"}
}