{
  "type": "Feature",
  "properties": {
    "addr:full":"7537 Concord Blvd E Inver Grove Heights MN 55076",
    "addr:housenumber":"7537",
    "addr:postcode":"55076",
    "addr:street":"Concord Blvd E",
    "iso:country":"US",
    "sg:address":"7537 Concord Blvd E",
    "sg:city":"Inver Grove Heights",
    "sg:classifiers":[
        {
            "category":"Restaurant",
            "type":"Food & Drink"
        }
    ],
    "sg:phone":"+1 651 451 9151",
    "sg:postcode":"55076",
    "sg:province":"MN",
    "sg:tags":[
        "eating"
    ],
    "wof:name":"Mr Healthys Subs and Salads",
    "wof:placetype":"venue"
},
  "geometry": {"coordinates":[-93.022165,44.837654],"type":"Point"}
}