{
  "type": "Feature",
  "properties": {
    "addr:full":"150 Pioneer Trl Ste 111 Chaska MN 55318",
    "addr:housenumber":"150",
    "addr:postcode":"55318",
    "addr:street":"Pioneer Trl Ste 111",
    "iso:country":"US",
    "sg:address":"150 Pioneer Trl Ste 111",
    "sg:city":"Chaska",
    "sg:classifiers":[
        {
            "category":"Professional",
            "subcategory":"Computer Services",
            "type":"Services"
        }
    ],
    "sg:phone":"+1 952 448 3289",
    "sg:postcode":"55318",
    "sg:province":"MN",
    "sg:tags":[
        "repair"
    ],
    "sg:website":"techwizardservices.com",
    "wof:name":"TechWizard Services, LLC",
    "wof:placetype":"venue"
},
  "geometry": {"coordinates":[-93.525676,44.826292],"type":"Point"}
}