{
  "type": "Feature",
  "properties": {
    "addr:full":"2372 N Yoki Rd Forbes MN 55738",
    "addr:housenumber":"2372",
    "addr:postcode":"55738",
    "addr:street":"N Yoki Rd",
    "iso:country":"US",
    "sg:address":"2372 N Yoki Rd",
    "sg:city":"Forbes",
    "sg:classifiers":[
        {
            "category":"Building & Trades",
            "subcategory":"Construction",
            "type":"Services"
        }
    ],
    "sg:phone":"+1 218 744 2913",
    "sg:postcode":"55738",
    "sg:province":"MN",
    "sg:tags":[
        "product",
        "asphalt"
    ],
    "wof:name":"Hardrives Inc",
    "wof:placetype":"venue"
},
  "geometry": {"coordinates":[-92.73660599999999,47.288628],"type":"Point"}
}