{
  "type": "Feature",
  "properties": {
    "iso:country":"US",
    "sg:address":"15511 Armstrong Blvd NW",
    "sg:city":"Anoka",
    "sg:classifiers":[
        {
            "category":"Real Estate",
            "subcategory":"Real Estate Agent",
            "type":"Services"
        }
    ],
    "sg:phone":"+1 763 427 0015",
    "sg:postcode":"55303",
    "sg:province":"MN",
    "wof:name":"Animal Aspect By Carlyn Inc",
    "wof:placetype":"venue"
},
  "geometry": {"coordinates":[-93.470426,45.253783],"type":"Point"}
}