{
  "type": "Feature",
  "properties": {
    "iso:country":"US",
    "sg:address":"208 Main St S",
    "sg:city":"Stillwater",
    "sg:classifiers":[
        {
            "category":"Shopping",
            "subcategory":"Used Merchandise",
            "type":"Retail Goods"
        }
    ],
    "sg:phone":"+1 651 351 3167",
    "sg:postcode":"55082",
    "sg:province":"MN",
    "wof:name":"Chelsea Rose Antiques",
    "wof:placetype":"venue"
},
  "geometry": {"coordinates":[-92.80556199999999,45.05496],"type":"Point"}
}