{
  "type": "Feature",
  "properties": {
    "addr:full":"3601 W 145th St Burnsville MN 55306",
    "addr:housenumber":"3601",
    "addr:postcode":"55306",
    "addr:street":"W 145Th St",
    "iso:country":"US",
    "sg:address":"3601 W 145th St",
    "sg:city":"Burnsville",
    "sg:classifiers":[
        {
            "category":"Recreation",
            "subcategory":"Amusement Park",
            "type":"Entertainment"
        }
    ],
    "sg:phone":"+1 952 895 1962",
    "sg:postcode":"55306",
    "sg:province":"MN",
    "wof:name":"Soccer Blast Minnesota",
    "wof:placetype":"venue"
},
  "geometry": {"coordinates":[-93.32440200000001,44.7402],"type":"Point"}
}