{
  "type": "Feature",
  "properties": {
    "iso:country":"US",
    "sg:address":"10810 Toledo Cir",
    "sg:city":"Minneapolis",
    "sg:classifiers":[
        {
            "category":"Building & Trades",
            "subcategory":"Construction",
            "type":"Services"
        }
    ],
    "sg:phone":"+1 952 884 6528",
    "sg:postcode":"55437",
    "sg:province":"MN",
    "sg:tags":[
        "house"
    ],
    "wof:name":"Crystal Design & Service",
    "wof:placetype":"venue"
},
  "geometry": {"coordinates":[-93.349228,44.805939],"type":"Point"}
}