{
  "type": "Feature",
  "properties": {
    "addr:full":"1885 Howard Dr North Mankato MN 56003",
    "addr:housenumber":"1885",
    "addr:postcode":"56003",
    "addr:street":"Howard Dr North",
    "iso:country":"US",
    "sg:address":"1885 Howard Dr",
    "sg:city":"North Mankato",
    "sg:classifiers":[
        {
            "category":"Utilities",
            "subcategory":"Water",
            "type":"Services"
        }
    ],
    "sg:phone":"+1 507 625 7129",
    "sg:postcode":"56003",
    "sg:province":"MN",
    "sg:tags":[
        "company",
        "sewage"
    ],
    "wof:name":"North Mankato Water Dept",
    "wof:placetype":"venue"
},
  "geometry": {"coordinates":[-94.04278100000001,44.18415],"type":"Point"}
}