{
  "type": "Feature",
  "properties": {
    "addr:full":"1907 2nd St SW Rochester MN 55902",
    "addr:housenumber":"1907",
    "addr:postcode":"55902",
    "addr:street":"2Nd St Sw",
    "iso:country":"US",
    "sg:address":"1907 2nd St SW",
    "sg:city":"Rochester",
    "sg:classifiers":[
        {
            "category":"Building & Trades",
            "subcategory":"Construction",
            "type":"Services"
        },
        {
            "category":"Professional",
            "subcategory":"Management & Consulting",
            "type":"Services"
        }
    ],
    "sg:phone":"+1 507 280 9788",
    "sg:postcode":"55902",
    "sg:province":"MN",
    "sg:tags":[
        "nonresidential",
        "industrial",
        "general",
        "contractor"
    ],
    "sg:website":"www.knutsonconstruction.com",
    "wof:name":"Knutson Construction Co",
    "wof:placetype":"venue"
},
  "geometry": {"coordinates":[-92.493802,44.021674],"type":"Point"}
}