{
  "type": "Feature",
  "properties": {
    "iso:country":"US",
    "sg:address":"19969 Co Rd 9",
    "sg:city":"Lester Prairie",
    "sg:phone":"+1 320 395 2310",
    "sg:postcode":"55354",
    "sg:province":"MN",
    "sg:tags":[
        "farm",
        "field",
        "corn",
        "crop"
    ],
    "wof:name":"Otto Brothers Farm",
    "wof:placetype":"venue"
},
  "geometry": {"coordinates":[-94.032811,44.906194],"type":"Point"}
}