{
  "type": "Feature",
  "properties": {
    "addr:full":"2605 Cliff Rd E Burnsville MN 55337",
    "addr:housenumber":"2605",
    "addr:postcode":"55337",
    "addr:street":"Cliff Rd E",
    "iso:country":"US",
    "sg:address":"2605 Cliff Rd E",
    "sg:city":"Burnsville",
    "sg:classifiers":[
        {
            "category":"Professional",
            "subcategory":"Detective & Security Services",
            "type":"Services"
        }
    ],
    "sg:phone":"+1 952 890 2555",
    "sg:postcode":"55337",
    "sg:province":"MN",
    "sg:tags":[
        "car"
    ],
    "wof:name":"Probe Investigative Services",
    "wof:placetype":"venue"
},
  "geometry": {"coordinates":[-93.239723,44.790306],"type":"Point"}
}