{
  "type": "Feature",
  "properties": {
    "iso:country":"US",
    "sg:address":"3501 Aldrich Ave S",
    "sg:city":"Minneapolis",
    "sg:classifiers":[
        {
            "category":"Place Of Worship",
            "subcategory":"Church",
            "type":"Public Place"
        },
        {
            "category":"Place Of Worship",
            "type":"Public Place"
        }
    ],
    "sg:phone":"+1 612 825 2479",
    "sg:postcode":"55408",
    "sg:province":"MN",
    "sg:tags":[
        "churches-presbyterian-arp",
        "churches-presbyterian"
    ],
    "sg:website":"http://www.aldrichchurch.org",
    "wof:name":"Aldrich Avenue Presbyterian Ch",
    "wof:placetype":"venue"
},
  "geometry": {"coordinates":[-93.28948200000001,44.939499],"type":"Point"}
}