{
  "type": "Feature",
  "properties": {
    "addr:full":"122 3rd Ave NW Waseca MN 56093",
    "addr:housenumber":"122",
    "addr:postcode":"56093",
    "addr:street":"3Rd Ave Nw",
    "iso:country":"US",
    "sg:address":"122 3rd Ave NW",
    "sg:city":"Waseca",
    "sg:classifiers":[
        {
            "category":"Retail",
            "subcategory":"Repair Shop",
            "type":"Services"
        }
    ],
    "sg:phone":"+1 507 833 9098",
    "sg:postcode":"56093",
    "sg:province":"MN",
    "sg:tags":[
        "equipment",
        "telephone",
        "system"
    ],
    "wof:name":"Millennium Telecom",
    "wof:placetype":"venue"
},
  "geometry": {"coordinates":[-93.50767999999999,44.079524],"type":"Point"}
}