{
  "type": "Feature",
  "properties": {
    "iso:country":"US",
    "sg:address":"4917 33rd Ave S",
    "sg:city":"Minneapolis",
    "sg:classifiers":[
        {
            "category":"Shopping",
            "subcategory":"Beauty & Cosmetics",
            "type":"Retail Goods"
        }
    ],
    "sg:phone":"+1 612 722 2820",
    "sg:postcode":"55417",
    "sg:province":"MN",
    "sg:tags":[
        "perfume",
        "salons-equipment",
        "supply"
    ],
    "wof:name":"Mary Kay Tessman",
    "wof:placetype":"venue"
},
  "geometry": {"coordinates":[-93.22423000000001,44.91413],"type":"Point"}
}