{
  "type": "Feature",
  "properties": {
    "iso:country":"US",
    "sg:address":"930 Cory Ln",
    "sg:city":"St Cloud",
    "sg:classifiers":[
        {
            "category":"Social Services",
            "subcategory":"Adult Care",
            "type":"Services"
        }
    ],
    "sg:phone":"+1 320 240 8412",
    "sg:postcode":"56303",
    "sg:province":"MN",
    "sg:tags":[
        "foster"
    ],
    "wof:name":"Opportunity Manor Foster",
    "wof:placetype":"venue"
},
  "geometry": {"coordinates":[-94.237313,45.569775],"type":"Point"}
}