{
  "type": "Feature",
  "properties": {
    "addr:full":"419 Toronto St Saint Paul MN 55102",
    "addr:housenumber":"419",
    "addr:postcode":"55102",
    "addr:street":"Toronto St",
    "iso:country":"US",
    "sg:address":"419 Toronto St",
    "sg:city":"Saint Paul",
    "sg:classifiers":[
        {
            "category":"Personal",
            "subcategory":"Beauty Salon",
            "type":"Services"
        }
    ],
    "sg:phone":"+1 651 225 8058",
    "sg:postcode":"55102",
    "sg:province":"MN",
    "sg:tags":[
        "shop"
    ],
    "wof:name":"Hair By Lawrencius & Co",
    "wof:placetype":"venue"
},
  "geometry": {"coordinates":[-93.1258,44.92893],"type":"Point"}
}