{
  "type": "Feature",
  "properties": {
    "addr:full":"105 Governor St Oklee MN 56742",
    "addr:housenumber":"105",
    "addr:postcode":"56742",
    "addr:street":"Governor St",
    "iso:country":"US",
    "sg:address":"105 Governor St",
    "sg:city":"Oklee",
    "sg:classifiers":[
        {
            "category":"Shopping",
            "type":"Retail Goods"
        }
    ],
    "sg:phone":"+1 218 796 5177",
    "sg:postcode":"56742",
    "sg:province":"MN",
    "sg:tags":[
        "monument"
    ],
    "wof:name":"Johnson Funeral Svc Inc",
    "wof:placetype":"venue"
},
  "geometry": {"coordinates":[-95.85601200000001,47.841578],"type":"Point"}
}