{
  "type": "Feature",
  "properties": {
    "addr:full":"5380 Howards Point Rd Excelsior MN 55331",
    "addr:postcode":"5380;55331",
    "addr:street":"Howards Point Rd",
    "iso:country":"US",
    "sg:address":"5380 Howards Point Rd",
    "sg:city":"Excelsior",
    "sg:classifiers":[
        {
            "category":"Professional",
            "type":"Services"
        }
    ],
    "sg:phone":"+1 952 401 9457",
    "sg:postcode":"55331",
    "sg:province":"MN",
    "wof:name":"Coldwater Crossing I LLC",
    "wof:placetype":"venue"
},
  "geometry": {"coordinates":[-93.628592,44.904397],"type":"Point"}
}