{
  "type": "Feature",
  "properties": {
    "addr:full":"2218 W 53rd St Minneapolis MN 55419",
    "addr:housenumber":"2218",
    "addr:postcode":"55419",
    "addr:street":"W 53Rd St",
    "iso:country":"US",
    "sg:address":"2218 W 53rd St",
    "sg:city":"Minneapolis",
    "sg:classifiers":[
        {
            "category":"Personal",
            "type":"Services"
        }
    ],
    "sg:phone":"+1 612 926 8587",
    "sg:postcode":"55419",
    "sg:province":"MN",
    "sg:tags":[
        "therapist",
        "massage"
    ],
    "wof:name":"Nancy Hyvarinen Mssg Reikie",
    "wof:placetype":"venue"
},
  "geometry": {"coordinates":[-93.308481,44.907014],"type":"Point"}
}