{
  "type": "Feature",
  "properties": {
    "addr:full":"1741 200th Ave Currie MN 56123",
    "addr:housenumber":"1741",
    "addr:postcode":"56123",
    "addr:street":"200Th Ave",
    "iso:country":"US",
    "sg:address":"1741 200th Ave",
    "sg:city":"Currie",
    "sg:classifiers":[
        {
            "category":"Farming",
            "subcategory":"Livestock Farm",
            "type":"Manufacturing & Wholesale Goods"
        }
    ],
    "sg:phone":"+1 507 763 3153",
    "sg:postcode":"56123",
    "sg:province":"MN",
    "sg:tags":[
        "feedlot",
        "hog",
        "corn",
        "or",
        "soybean"
    ],
    "wof:name":"Bill Maher",
    "wof:placetype":"venue"
},
  "geometry": {"coordinates":[-95.663543,44.105795],"type":"Point"}
}