{
  "type": "Feature",
  "properties": {
    "addr:full":"211 N 5th St Henderson MN 56044",
    "addr:housenumber":"211",
    "addr:postcode":"56044",
    "addr:street":"N 5Th St",
    "iso:country":"US",
    "sg:address":"211 N 5th St",
    "sg:city":"Henderson",
    "sg:classifiers":[
        {
            "category":"Retail",
            "subcategory":"Funeral Services",
            "type":"Services"
        }
    ],
    "sg:phone":"+1 507 248 3505",
    "sg:postcode":"56044",
    "sg:province":"MN",
    "sg:tags":[
        "director"
    ],
    "wof:name":"Kolden Funeral Svc",
    "wof:placetype":"venue"
},
  "geometry": {"coordinates":[-93.907231,44.529703],"type":"Point"}
}