{
  "type": "Feature",
  "properties": {
    "addr:full":"130 N Ramsey Ave Litchfield MN 55355",
    "addr:housenumber":"130",
    "addr:postcode":"55355",
    "addr:street":"N Ramsey Ave",
    "iso:country":"US",
    "sg:address":"130 N Ramsey Ave",
    "sg:city":"Litchfield",
    "sg:classifiers":[
        {
            "category":"Retail",
            "subcategory":"Auto Repair",
            "type":"Services"
        }
    ],
    "sg:phone":"+1 320 693 0775",
    "sg:postcode":"55355",
    "sg:province":"MN",
    "sg:tags":[
        "body",
        "repairing",
        "automobile",
        "water",
        "carwash",
        "painting",
        "transport"
    ],
    "sg:website":"http://www.rainbowbody.net",
    "wof:name":"Rainbow Body & Paint",
    "wof:placetype":"venue"
},
  "geometry": {"coordinates":[-94.52954,45.12671],"type":"Point"}
}