{
  "type": "Feature",
  "properties": {
    "addr:full":"210 2nd Ave NE Perham MN 56573",
    "addr:housenumber":"210",
    "addr:postcode":"56573",
    "addr:street":"2Nd Ave Ne",
    "iso:country":"US",
    "sg:address":"210 2nd Ave NE",
    "sg:city":"Perham",
    "sg:classifiers":[
        {
            "category":"Professional",
            "subcategory":"Computer Services",
            "type":"Services"
        }
    ],
    "sg:phone":"+1 218 346 5665",
    "sg:postcode":"56573",
    "sg:province":"MN",
    "wof:name":"Anderson Computer Service",
    "wof:placetype":"venue"
},
  "geometry": {"coordinates":[-95.569565,46.595205],"type":"Point"}
}