{
  "type": "Feature",
  "properties": {
    "iso:country":"US",
    "sg:address":"24425 Dairy Ave",
    "sg:city":"Winsted",
    "sg:classifiers":[
        {
            "category":"Farming",
            "subcategory":"Dairy Farm",
            "type":"Manufacturing & Wholesale Goods"
        }
    ],
    "sg:phone":"+1 320 485 2577",
    "sg:postcode":"55395",
    "sg:province":"MN",
    "sg:tags":[
        "corn",
        "soybean"
    ],
    "wof:name":"Thomas Horstmann",
    "wof:placetype":"venue"
},
  "geometry": {"coordinates":[-94.093929,44.962036],"type":"Point"}
}