{
  "type": "Feature",
  "properties": {
    "iso:country":"US",
    "sg:address":"150 Eaton St",
    "sg:city":"Saint Paul",
    "sg:classifiers":[
        {
            "category":"Personal",
            "type":"Services"
        }
    ],
    "sg:phone":"+1 651 291 8878",
    "sg:postcode":"55107",
    "sg:province":"MN",
    "wof:name":"Fix It Now",
    "wof:placetype":"venue"
},
  "geometry": {"coordinates":[-93.07751500000001,44.935374],"type":"Point"}
}