{
  "type": "Feature",
  "properties": {
    "addr:full":"1731 State Hwy 76 Houston MN 55943",
    "addr:housenumber":"1731",
    "addr:postcode":"55943",
    "addr:street":"State Hwy 76",
    "iso:country":"US",
    "sg:address":"1731 State Hwy 76",
    "sg:city":"Houston",
    "sg:classifiers":[
        {
            "category":"Sports & Exercise",
            "subcategory":"Race Track",
            "type":"Entertainment"
        }
    ],
    "sg:phone":"+1 507 896 3223",
    "sg:postcode":"55943",
    "sg:province":"MN",
    "sg:tags":[
        "used",
        "auto",
        "driver",
        "new",
        "car",
        "professional"
    ],
    "wof:name":"Coreys Auto Sales",
    "wof:placetype":"venue"
},
  "geometry": {"coordinates":[-91.615555,43.821704],"type":"Point"}
}