{
  "type": "Feature",
  "properties": {
    "addr:full":"13030 Cannon City Blvd Northfield MN 55057",
    "addr:housenumber":"13030",
    "addr:postcode":"55057",
    "addr:street":"Cannon City Blvd",
    "iso:country":"US",
    "sg:address":"13030 Cannon City Blvd",
    "sg:city":"Northfield",
    "sg:classifiers":[
        {
            "category":"Shopping",
            "subcategory":"Books",
            "type":"Retail Goods"
        }
    ],
    "sg:phone":"+1 507 645 4242",
    "sg:postcode":"55057",
    "sg:province":"MN",
    "wof:name":"Trailblazer Books",
    "wof:placetype":"venue"
},
  "geometry": {"coordinates":[-93.191011,44.39887],"type":"Point"}
}