{
  "type": "Feature",
  "properties": {
    "iso:country":"US",
    "sg:address":"301 W 1st St Ste 713",
    "sg:city":"Duluth",
    "sg:classifiers":[
        {
            "category":"Professional",
            "subcategory":"Lawyer & Legal Services",
            "type":"Services"
        }
    ],
    "sg:phone":"+1 218 726 1175",
    "sg:postcode":"55802",
    "sg:province":"MN",
    "sg:tags":[
        "attorney",
        "practice"
    ],
    "wof:name":"Begeske Law Office",
    "wof:placetype":"venue"
},
  "geometry": {"coordinates":[-92.103027,46.784821],"type":"Point"}
}