{
  "type": "Feature",
  "properties": {
    "addr:full":"69471 190th St Albert Lea MN 56007",
    "addr:housenumber":"69471",
    "addr:postcode":"56007",
    "addr:street":"190Th St",
    "iso:country":"US",
    "sg:address":"69471 190th St",
    "sg:city":"Albert Lea",
    "sg:classifiers":[
        {
            "category":"Organizations",
            "subcategory":"Religious Organization",
            "type":"Services"
        }
    ],
    "sg:phone":"+1 507 265 3331",
    "sg:postcode":"56007",
    "sg:province":"MN",
    "wof:name":"Concordia Lutheran Church",
    "wof:placetype":"venue"
},
  "geometry": {"coordinates":[-93.479221,43.629647],"type":"Point"}
}