{
  "type": "Feature",
  "properties": {
    "addr:full":"2260 Jennifer Ln Saint Paul MN 55109",
    "addr:housenumber":"2260",
    "addr:postcode":"55109",
    "addr:street":"Jennifer Ln",
    "iso:country":"US",
    "sg:address":"2260 Jennifer Ln",
    "sg:city":"Saint Paul",
    "sg:classifiers":[
        {
            "category":"Building & Trades",
            "subcategory":"Construction",
            "type":"Services"
        }
    ],
    "sg:phone":"+1 651 779 8772",
    "sg:postcode":"55109",
    "sg:province":"MN",
    "sg:tags":[
        "carpentry",
        "contractor"
    ],
    "wof:name":"Marcon",
    "wof:placetype":"venue"
},
  "geometry": {"coordinates":[-93.013756,45.009594],"type":"Point"}
}