{
  "type": "Feature",
  "properties": {
    "addr:full":"7920 12th Ave S Bloomington MN 55425",
    "addr:housenumber":"7920",
    "addr:postcode":"55425",
    "addr:street":"12Th Ave S",
    "iso:country":"US",
    "sg:address":"7920 12th Ave S",
    "sg:city":"Bloomington",
    "sg:classifiers":[
        {
            "category":"Shopping",
            "type":"Retail Goods"
        },
        {
            "category":"Manufacturing",
            "subcategory":"Leather Goods",
            "type":"Manufacturing & Wholesale Goods"
        }
    ],
    "sg:phone":"+1 952 814 0225",
    "sg:postcode":"55425",
    "sg:province":"MN",
    "sg:tags":[
        "mfg",
        "product",
        "orthopedic",
        "appliance",
        "custom"
    ],
    "wof:name":"Promet Inc",
    "wof:placetype":"venue"
},
  "geometry": {"coordinates":[-93.2581,44.857862],"type":"Point"}
}