{
  "type": "Feature",
  "properties": {
    "iso:country":"US",
    "sg:address":"30525 119th St",
    "sg:city":"Princeton",
    "sg:classifiers":[
        {
            "category":"Building & Trades",
            "subcategory":"Electrical",
            "type":"Services"
        }
    ],
    "sg:phone":"+1 763 389 9978",
    "sg:postcode":"55371",
    "sg:province":"MN",
    "sg:tags":[
        "electrical",
        "contractor"
    ],
    "wof:name":"Princeton Electric Inc",
    "wof:placetype":"venue"
},
  "geometry": {"coordinates":[-93.571378,45.525214],"type":"Point"}
}