{
  "type": "Feature",
  "properties": {
    "addr:full":"405 Cottonwood Dr Winona MN 55987",
    "addr:housenumber":"405",
    "addr:postcode":"55987",
    "addr:street":"Cottonwood Dr",
    "iso:country":"US",
    "sg:address":"405 Cottonwood Dr",
    "sg:city":"Winona",
    "sg:classifiers":[
        {
            "category":"Shopping",
            "subcategory":"Shoes",
            "type":"Retail Goods"
        }
    ],
    "sg:phone":"+1 507 452 1534",
    "sg:postcode":"55987",
    "sg:province":"MN",
    "wof:name":"Payless Shoe Source",
    "wof:placetype":"venue"
},
  "geometry": {"coordinates":[-91.691569,44.053872],"type":"Point"}
}