{
  "type": "Feature",
  "properties": {
    "addr:full":"3905 92nd St SW Pequot Lakes MN 56472",
    "addr:housenumber":"3905",
    "addr:postcode":"56472",
    "addr:street":"92Nd St Sw",
    "iso:country":"US",
    "sg:address":"3905 92nd St SW",
    "sg:city":"Pequot Lakes",
    "sg:classifiers":[
        {
            "category":"Manufacturing",
            "subcategory":"Watercraft",
            "type":"Manufacturing & Wholesale Goods"
        }
    ],
    "sg:phone":"+1 218 746 3149",
    "sg:postcode":"56472",
    "sg:province":"MN",
    "wof:name":"Lake Shore Classic Boats",
    "wof:placetype":"venue"
},
  "geometry": {"coordinates":[-94.589991,46.470943],"type":"Point"}
}