{
  "type": "Feature",
  "properties": {
    "addr:full":"6672 148th St NW Cass Lake MN 56633",
    "addr:housenumber":"6672",
    "addr:postcode":"56633",
    "addr:street":"148Th St Nw Cass",
    "iso:country":"US",
    "sg:address":"6672 148th St NW",
    "sg:city":"Cass Lake",
    "sg:classifiers":[
        {
            "category":"Social Services",
            "subcategory":"Child Care",
            "type":"Services"
        }
    ],
    "sg:phone":"+1 218 335 6445",
    "sg:postcode":"56633",
    "sg:province":"MN",
    "sg:tags":[
        "home",
        "daycare",
        "provider"
    ],
    "wof:name":"Shellys Daycare",
    "wof:placetype":"venue"
},
  "geometry": {"coordinates":[-94.63664900000001,47.337801],"type":"Point"}
}