{
  "type": "Feature",
  "properties": {
    "iso:country":"US",
    "sg:address":"12575 10th St S",
    "sg:city":"Afton",
    "sg:classifiers":[
        {
            "category":"Professional",
            "subcategory":"Business Services",
            "type":"Services"
        }
    ],
    "sg:phone":"+1 651 436 4710",
    "sg:postcode":"55001",
    "sg:province":"MN",
    "wof:name":"Universal Marketing",
    "wof:placetype":"venue"
},
  "geometry": {"coordinates":[-92.850527,44.9345],"type":"Point"}
}