{
  "type": "Feature",
  "properties": {
    "addr:full":"5721 Grand Ave Duluth MN 55807",
    "addr:housenumber":"5721",
    "addr:postcode":"55807",
    "addr:street":"Grand Ave",
    "iso:country":"US",
    "sg:address":"5721 Grand Ave",
    "sg:city":"Duluth",
    "sg:classifiers":[
        {
            "category":"Real Estate",
            "subcategory":"Real Estate Agent",
            "type":"Services"
        }
    ],
    "sg:phone":"+1 218 624 4866",
    "sg:postcode":"55807",
    "sg:province":"MN",
    "sg:tags":[
        "appraiser"
    ],
    "wof:name":"Doyle Agency Inc",
    "wof:placetype":"venue"
},
  "geometry": {"coordinates":[-92.170457,46.738007],"type":"Point"}
}