{
  "type": "Feature",
  "properties": {
    "addr:full":"2155 Niagara Ln N Minneapolis MN 55447",
    "addr:housenumber":"2155",
    "addr:postcode":"55447",
    "addr:street":"Niagara Ln N",
    "iso:country":"US",
    "sg:address":"2155 Niagara Ln N",
    "sg:city":"Minneapolis",
    "sg:classifiers":[
        {
            "category":"Real Estate",
            "subcategory":"Real Estate Agent",
            "type":"Services"
        }
    ],
    "sg:phone":"+1 763 473 6104",
    "sg:postcode":"55447",
    "sg:province":"MN",
    "wof:name":"United Properties Northwest",
    "wof:placetype":"venue"
},
  "geometry": {"coordinates":[-93.471644,45.003043],"type":"Point"}
}