{
  "type": "Feature",
  "properties": {
    "iso:country":"US",
    "sg:address":"1905 Sioux Ct",
    "sg:city":"Burnsville",
    "sg:classifiers":[
        {
            "category":"Freight",
            "type":"Transportation"
        }
    ],
    "sg:phone":"+1 952 895 6075",
    "sg:postcode":"55337",
    "sg:province":"MN",
    "sg:tags":[
        "operator",
        "local",
        "trucking"
    ],
    "wof:name":"Salt Earth Delivery Service",
    "wof:placetype":"venue"
},
  "geometry": {"coordinates":[-93.24560200000001,44.803622],"type":"Point"}
}