{
  "type": "Feature",
  "properties": {
    "iso:country":"US",
    "sg:address":"5431 Welcome Ave N",
    "sg:city":"Minneapolis",
    "sg:classifiers":[
        {
            "category":"Social Services",
            "type":"Services"
        }
    ],
    "sg:phone":"+1 763 537 5873",
    "sg:postcode":"55429",
    "sg:province":"MN",
    "wof:name":"Welcome Place",
    "wof:placetype":"venue"
},
  "geometry": {"coordinates":[-93.35140800000001,45.051839],"type":"Point"}
}