{
  "type": "Feature",
  "properties": {
    "iso:country":"US",
    "sg:address":"525 1st St",
    "sg:city":"Madison",
    "sg:classifiers":[
        {
            "category":"Government",
            "subcategory":"Office",
            "type":"Public Place"
        }
    ],
    "sg:phone":"+1 612 598 3226",
    "sg:postcode":"56256",
    "sg:province":"MN",
    "wof:name":"Natural Rsrces Cnservation Svc",
    "wof:placetype":"venue"
},
  "geometry": {"coordinates":[-96.192125,45.009436],"type":"Point"}
}