{
  "type": "Feature",
  "properties": {
    "iso:country":"US",
    "sg:address":"338 13th St NE",
    "sg:city":"Owatonna",
    "sg:classifiers":[
        {
            "category":"Real Estate",
            "subcategory":"Real Estate Operator",
            "type":"Services"
        }
    ],
    "sg:phone":"+1 507 451 0766",
    "sg:postcode":"55060",
    "sg:province":"MN",
    "sg:tags":[
        "building",
        "nonresidential"
    ],
    "wof:name":"Bendorf Properties LLC",
    "wof:placetype":"venue"
},
  "geometry": {"coordinates":[-93.21695,44.097583],"type":"Point"}
}