{
  "type": "Feature",
  "properties": {
    "iso:country":"US",
    "sg:address":"14843 Colorado Ave",
    "sg:city":"Rosemount",
    "sg:classifiers":[
        {
            "category":"Sports & Exercise",
            "subcategory":"Ice Rink",
            "type":"Entertainment"
        }
    ],
    "sg:phone":"+1 651 423 2748",
    "sg:postcode":"55068",
    "sg:province":"MN",
    "sg:tags":[
        "skating"
    ],
    "wof:name":"Minn E Rink",
    "wof:placetype":"venue"
},
  "geometry": {"coordinates":[-93.142067,44.735613],"type":"Point"}
}