{
  "type": "Feature",
  "properties": {
    "addr:full":"20757 US Hwy 169 Grand Rapids MN 55744",
    "addr:postcode":"20757;55744",
    "addr:street":"Us Hwy 169",
    "iso:country":"US",
    "sg:address":"20757 US Hwy 169",
    "sg:city":"Grand Rapids",
    "sg:classifiers":[
        {
            "category":"Retail",
            "subcategory":"Repair Shop",
            "type":"Services"
        }
    ],
    "sg:phone":"+1 218 326 1524",
    "sg:postcode":"55744",
    "sg:province":"MN",
    "wof:name":"Cliff S Locksmith Service",
    "wof:placetype":"venue"
},
  "geometry": {"coordinates":[-93.541419,47.176679],"type":"Point"}
}