{
  "type": "Feature",
  "properties": {
    "addr:full":"3139 Co Rd 78 SE Osakis MN 56360",
    "addr:housenumber":"3139;78",
    "addr:postcode":"56360",
    "addr:street":"Co Rd;Se",
    "iso:country":"US",
    "sg:address":"3139 Co Rd 78 SE",
    "sg:city":"Osakis",
    "sg:classifiers":[
        {
            "category":"Travel",
            "subcategory":"Campground",
            "type":"Entertainment"
        }
    ],
    "sg:phone":"+1 320 763 7694",
    "sg:postcode":"56360",
    "sg:province":"MN",
    "sg:website":"www.shadyoakcamp.com",
    "wof:name":"Shady Oaks Campground",
    "wof:placetype":"venue"
},
  "geometry": {"coordinates":[-95.26422700000001,45.863563],"type":"Point"}
}