{
  "type": "Feature",
  "properties": {
    "iso:country":"US",
    "sg:address":"1 Snelling Ave S",
    "sg:city":"St Paul",
    "sg:classifiers":[
        {
            "category":"Shopping",
            "subcategory":"Musical Instruments",
            "type":"Retail Goods"
        }
    ],
    "sg:phone":"+1 651 690 2279",
    "sg:postcode":"55105",
    "sg:province":"MN",
    "wof:name":"Matts Professional Guitar Inst",
    "wof:placetype":"venue"
},
  "geometry": {"coordinates":[-93.16700299999999,44.940065],"type":"Point"}
}