{
  "type": "Feature",
  "properties": {
    "addr:full":"2579 Eastman Dr Saint Paul MN 55112",
    "addr:housenumber":"2579",
    "addr:postcode":"55112",
    "addr:street":"Eastman Dr",
    "iso:country":"US",
    "sg:address":"2579 Eastman Dr",
    "sg:city":"Saint Paul",
    "sg:classifiers":[
        {
            "category":"Professional",
            "type":"Services"
        }
    ],
    "sg:phone":"+1 651 784 1065",
    "sg:postcode":"55112",
    "sg:province":"MN",
    "wof:name":"Murphy Bros Designers & Remode",
    "wof:placetype":"venue"
},
  "geometry": {"coordinates":[-93.221233,45.092092],"type":"Point"}
}