{
  "type": "Feature",
  "properties": {
    "iso:country":"US",
    "sg:address":"515 1st St SW",
    "sg:city":"Clara City",
    "sg:classifiers":[
        {
            "category":"Government",
            "subcategory":"Office",
            "type":"Public Place"
        }
    ],
    "sg:phone":"+1 320 847 3413",
    "sg:postcode":"56222",
    "sg:province":"MN",
    "sg:tags":[
        "village"
    ],
    "wof:name":"Clara City Garage",
    "wof:placetype":"venue"
},
  "geometry": {"coordinates":[-95.36421799999999,44.951178],"type":"Point"}
}