{
  "type": "Feature",
  "properties": {
    "addr:full":"8671 Co Rd 8 SW Waverly MN 55390",
    "addr:housenumber":"8671",
    "addr:postcode":"55390",
    "addr:street":"Co Rd 8 Sw",
    "iso:country":"US",
    "sg:address":"8671 Co Rd 8 SW",
    "sg:city":"Waverly",
    "sg:classifiers":[
        {
            "category":"Building & Trades",
            "subcategory":"Construction",
            "type":"Services"
        }
    ],
    "sg:phone":"+1 763 658 4409",
    "sg:postcode":"55390",
    "sg:province":"MN",
    "sg:tags":[
        "equipment",
        "installation"
    ],
    "wof:name":"Kahlstorf Bros Inst Co Inc",
    "wof:placetype":"venue"
},
  "geometry": {"coordinates":[-93.97209700000001,45.026636],"type":"Point"}
}