{
  "type": "Feature",
  "properties": {
    "iso:country":"US",
    "sg:address":"610 Cottonwood Ln N",
    "sg:city":"Minneapolis",
    "sg:classifiers":[
        {
            "category":"Shopping",
            "type":"Retail Goods"
        }
    ],
    "sg:phone":"+1 612 870 7780",
    "sg:postcode":"55441",
    "sg:province":"MN",
    "sg:tags":[
        "fish",
        "aquarium",
        "supply"
    ],
    "wof:name":"Aquarium Ballet",
    "wof:placetype":"venue"
},
  "geometry": {"coordinates":[-93.425122,44.988196],"type":"Point"}
}