{
  "type": "Feature",
  "properties": {
    "iso:country":"US",
    "sg:address":"5150 SW 68th St",
    "sg:city":"Owatonna",
    "sg:phone":"+1 507 455 3194",
    "sg:postcode":"55060",
    "sg:province":"MN",
    "sg:tags":[
        "farm",
        "corn"
    ],
    "wof:name":"Mark Hafstad",
    "wof:placetype":"venue"
},
  "geometry": {"coordinates":[-93.30852299999999,43.993298],"type":"Point"}
}