{
  "type": "Feature",
  "properties": {
    "addr:full":"10540 Zion Ave S Bloomington MN 55437",
    "addr:housenumber":"10540",
    "addr:postcode":"55437",
    "addr:street":"Zion Ave S",
    "iso:country":"US",
    "sg:address":"10540 Zion Ave S",
    "sg:city":"Bloomington",
    "sg:classifiers":[
        {
            "category":"Professional",
            "subcategory":"Secretarial Services",
            "type":"Services"
        }
    ],
    "sg:phone":"+1 952 884 1458",
    "sg:postcode":"55437",
    "sg:province":"MN",
    "sg:tags":[
        "reporting",
        "court"
    ],
    "wof:name":"Zion Secretarial Svc",
    "wof:placetype":"venue"
},
  "geometry": {"coordinates":[-93.356932,44.812179],"type":"Point"}
}