{
  "type": "Feature",
  "properties": {
    "iso:country":"US",
    "sg:address":"63478 Fort Rd",
    "sg:city":"New Ulm",
    "sg:phone":"+1 507 354 1300",
    "sg:postcode":"56073",
    "sg:province":"MN",
    "sg:tags":[
        "farm",
        "corn",
        "soybean"
    ],
    "wof:name":"Alan Forst",
    "wof:placetype":"venue"
},
  "geometry": {"coordinates":[-94.53998900000001,44.39138],"type":"Point"}
}