{
  "type": "Feature",
  "properties": {
    "addr:full":"620 Randolph Rd Detroit Lakes MN 56501",
    "addr:housenumber":"620",
    "addr:postcode":"56501",
    "addr:street":"Randolph Rd",
    "iso:country":"US",
    "sg:address":"620 Randolph Rd",
    "sg:city":"Detroit Lakes",
    "sg:classifiers":[
        {
            "category":"Home & Garden",
            "subcategory":"Carpets & Floor Coverings",
            "type":"Retail Goods"
        }
    ],
    "sg:phone":"+1 218 847 5407",
    "sg:postcode":"56501",
    "sg:province":"MN",
    "sg:tags":[
        "dealer",
        "rug"
    ],
    "wof:name":"5407 Carpet & Furniture",
    "wof:placetype":"venue"
},
  "geometry": {"coordinates":[-95.837608,46.816753],"type":"Point"}
}