{
  "type": "Feature",
  "properties": {
    "iso:country":"US",
    "sg:address":"104 Lemieur St",
    "sg:city":"Little Falls",
    "sg:classifiers":[
        {
            "category":"Restaurant",
            "type":"Food & Drink"
        }
    ],
    "sg:menulink":"http://www.allmenus.com/mn/little-falls/193964-mcdonalds/menu/",
    "sg:postcode":"56345",
    "sg:province":"MN",
    "sg:tags":[
        "burger",
        "american"
    ],
    "wof:name":"McDonald's",
    "wof:placetype":"venue"
},
  "geometry": {"coordinates":[-94.33753900000001,45.975481],"type":"Point"}
}