{
  "type": "Feature",
  "properties": {
    "iso:country":"US",
    "sg:address":"127 Oak St",
    "sg:city":"Dawson",
    "sg:classifiers":[
        {
            "category":"Restaurant",
            "type":"Food & Drink"
        }
    ],
    "sg:phone":"+1 320 769 2004",
    "sg:postcode":"56232",
    "sg:province":"MN",
    "sg:tags":[
        "eating"
    ],
    "wof:name":"Sisters Candy",
    "wof:placetype":"venue"
},
  "geometry": {"coordinates":[-96.047922,44.935735],"type":"Point"}
}