{
  "type": "Feature",
  "properties": {
    "iso:country":"US",
    "sg:address":"107 Pleasant Ave E",
    "sg:city":"Atwater",
    "sg:classifiers":[
        {
            "category":"Food & Beverages",
            "subcategory":"Liquor & Beverages",
            "type":"Retail Goods"
        }
    ],
    "sg:phone":"+1 320 974 3110",
    "sg:postcode":"56209",
    "sg:province":"MN",
    "wof:name":"Atwater Liquor",
    "wof:placetype":"venue"
},
  "geometry": {"coordinates":[-94.77776299999999,45.138814],"type":"Point"}
}