{
  "type": "Feature",
  "properties": {
    "addr:full":"6885 Co Rd 6 SW Stewartville MN 55976",
    "addr:housenumber":"6885",
    "addr:postcode":"55976",
    "addr:street":"Co Rd 6 Sw",
    "iso:country":"US",
    "sg:address":"6885 Co Rd 6 SW",
    "sg:city":"Stewartville",
    "sg:classifiers":[
        {
            "category":"Building & Trades",
            "subcategory":"Construction",
            "type":"Services"
        }
    ],
    "sg:phone":"+1 507 533 8295",
    "sg:postcode":"55976",
    "sg:province":"MN",
    "sg:tags":[
        "house"
    ],
    "wof:name":"Radcliffe Homes Inc",
    "wof:placetype":"venue"
},
  "geometry": {"coordinates":[-92.57516,43.841307],"type":"Point"}
}