{
  "type": "Feature",
  "properties": {
    "iso:country":"US",
    "sg:address":"1423 Washington Ave S",
    "sg:city":"Minneapolis",
    "sg:classifiers":[
        {
            "category":"Professional",
            "type":"Services"
        }
    ],
    "sg:phone":"+1 612 321 9004",
    "sg:postcode":"55454",
    "sg:province":"MN",
    "sg:tags":[
        "establishment"
    ],
    "wof:name":"Travelot",
    "wof:placetype":"venue"
},
  "geometry": {"coordinates":[-93.2492,44.973869],"type":"Point"}
}