{
  "type": "Feature",
  "properties": {
    "addr:full":"1201 E Hwy 2 Grand Rapids MN 55744",
    "addr:housenumber":"1201",
    "addr:postcode":"55744",
    "addr:street":"E Hwy 2",
    "iso:country":"US",
    "sg:address":"1201 E Hwy 2",
    "sg:city":"Grand Rapids",
    "sg:classifiers":[
        {
            "category":"Government",
            "subcategory":"Office",
            "type":"Public Place"
        }
    ],
    "sg:phone":"+1 218 327 4455",
    "sg:postcode":"55744",
    "sg:province":"MN",
    "sg:tags":[
        "state"
    ],
    "wof:name":"Natural Resources Dept",
    "wof:placetype":"venue"
},
  "geometry": {"coordinates":[-93.507107,47.230178],"type":"Point"}
}