{
  "type": "Feature",
  "properties": {
    "addr:full":"624 13th St S Virginia MN 55792",
    "addr:housenumber":"624",
    "addr:postcode":"55792",
    "addr:street":"13Th St S",
    "iso:country":"US",
    "sg:address":"624 13th St S",
    "sg:city":"Virginia",
    "sg:classifiers":[
        {
            "category":"Health Services",
            "subcategory":"Hospital",
            "type":"Services"
        }
    ],
    "sg:phone":"+1 218 749 2881",
    "sg:postcode":"55792",
    "sg:province":"MN",
    "sg:tags":[
        "mental"
    ],
    "wof:name":"Range Mental Health Ctr Inc",
    "wof:placetype":"venue"
},
  "geometry": {"coordinates":[-92.54421600000001,47.511831],"type":"Point"}
}