{
  "type": "Feature",
  "properties": {
    "addr:full":"200 N Concord St Fergus Falls MN 56537",
    "addr:housenumber":"200",
    "addr:postcode":"56537",
    "addr:street":"N Concord St",
    "iso:country":"US",
    "sg:address":"200 N Concord St",
    "sg:city":"Fergus Falls",
    "sg:classifiers":[
        {
            "category":"Shopping",
            "subcategory":"Florist",
            "type":"Retail Goods"
        }
    ],
    "sg:phone":"+1 218 736 6933",
    "sg:postcode":"56537",
    "sg:province":"MN",
    "wof:name":"Posie Inn Floral & Green House",
    "wof:placetype":"venue"
},
  "geometry": {"coordinates":[-96.061753,46.285592],"type":"Point"}
}