{
  "type": "Feature",
  "properties": {
    "addr:full":"10285 Yellow Circle Dr Hopkins MN 55343",
    "addr:housenumber":"10285",
    "addr:postcode":"55343",
    "addr:street":"Yellow Circle Dr",
    "iso:country":"US",
    "sg:address":"10285 Yellow Circle Dr",
    "sg:city":"Hopkins",
    "sg:classifiers":[
        {
            "category":"Professional",
            "subcategory":"Computer Services",
            "type":"Services"
        },
        {
            "category":"Shopping",
            "subcategory":"Computers & Home Electronics",
            "type":"Retail Goods"
        }
    ],
    "sg:phone":"+1 952 933 8408",
    "sg:postcode":"55343",
    "sg:province":"MN",
    "sg:tags":[
        "prepackaged",
        "software"
    ],
    "wof:name":"Captiva Software Corp",
    "wof:placetype":"venue"
},
  "geometry": {"coordinates":[-93.411294,44.89211],"type":"Point"}
}