{
  "type": "Feature",
  "properties": {
    "iso:country":"US",
    "sg:address":"810 W Mill St",
    "sg:city":"Paynesville",
    "sg:classifiers":[
        {
            "category":"Shopping",
            "subcategory":"Department Store",
            "type":"Retail Goods"
        }
    ],
    "sg:phone":"+1 320 243 7174",
    "sg:postcode":"56362",
    "sg:province":"MN",
    "wof:name":"Alco Discount",
    "wof:placetype":"venue"
},
  "geometry": {"coordinates":[-94.726311,45.378923],"type":"Point"}
}