{
  "type": "Feature",
  "properties": {
    "iso:country":"US",
    "sg:address":"712 Mainstreet",
    "sg:city":"Hopkins",
    "sg:classifiers":[
        {
            "category":"Restaurant",
            "type":"Food & Drink"
        }
    ],
    "sg:phone":"+1 952 938 1366",
    "sg:postcode":"55343",
    "sg:province":"MN",
    "wof:name":"Camille's Cafe",
    "wof:placetype":"venue"
},
  "geometry": {"coordinates":[-93.410011,44.924323],"type":"Point"}
}