{
  "type": "Feature",
  "properties": {
    "addr:full":"4800 85th Ave N Minneapolis MN 55443",
    "addr:housenumber":"4800",
    "addr:postcode":"55443",
    "addr:street":"85Th Ave N",
    "iso:country":"US",
    "sg:address":"4800 85th Ave N",
    "sg:city":"Minneapolis",
    "sg:classifiers":[
        {
            "category":"Communications",
            "subcategory":"Television Station",
            "type":"Services"
        },
        {
            "category":"Utilities",
            "subcategory":"Telephone",
            "type":"Services"
        },
        {
            "category":"Professional",
            "subcategory":"Computer Services",
            "type":"Services"
        }
    ],
    "sg:phone":"+1 763 515 0033",
    "sg:postcode":"55443",
    "sg:province":"MN",
    "sg:tags":[
        "satellite",
        "cable",
        "isp",
        "provider",
        "internet"
    ],
    "wof:name":"Qwest Phone & Internet Authorized Dealer",
    "wof:placetype":"venue"
},
  "geometry": {"coordinates":[-93.34330300000001,45.108913],"type":"Point"}
}