{
  "type": "Feature",
  "properties": {
    "iso:country":"US",
    "sg:address":"56937 220th St",
    "sg:city":"Austin",
    "sg:classifiers":[
        {
            "category":"Organizations",
            "subcategory":"Religious Organization",
            "type":"Services"
        }
    ],
    "sg:phone":"+1 507 433 6709",
    "sg:postcode":"55912",
    "sg:province":"MN",
    "sg:tags":[
        "church"
    ],
    "wof:name":"St Peters Evangelical Lutheran",
    "wof:placetype":"venue"
},
  "geometry": {"coordinates":[-92.91031599999999,43.67414],"type":"Point"}
}