{
  "type": "Feature",
  "properties": {
    "iso:country":"US",
    "sg:address":"22300 Impala Ave",
    "sg:city":"Wabasso",
    "sg:phone":"+1 507 342 5466",
    "sg:postcode":"56293",
    "sg:province":"MN",
    "sg:tags":[
        "farm",
        "corn",
        "soybean"
    ],
    "wof:name":"Donald Pohlen",
    "wof:placetype":"venue"
},
  "geometry": {"coordinates":[-95.248581,44.384011],"type":"Point"}
}