{
  "type": "Feature",
  "properties": {
    "iso:country":"US",
    "sg:address":"738 Debbie Ln",
    "sg:city":"Carver",
    "sg:classifiers":[
        {
            "category":"Professional",
            "subcategory":"Employment Agencies",
            "type":"Services"
        }
    ],
    "sg:phone":"+1 952 361 0912",
    "sg:postcode":"55315",
    "sg:province":"MN",
    "wof:name":"Mano Services Inc",
    "wof:placetype":"venue"
},
  "geometry": {"coordinates":[-93.624262,44.770979],"type":"Point"}
}