{
  "type": "Feature",
  "properties": {
    "iso:country":"US",
    "sg:address":"117 1st Ave NW",
    "sg:city":"Austin",
    "sg:classifiers":[
        {
            "category":"Professional",
            "subcategory":"Advertising",
            "type":"Services"
        }
    ],
    "sg:phone":"+1 507 434 0751",
    "sg:postcode":"55912",
    "sg:province":"MN",
    "wof:name":"Advertising Attractions",
    "wof:placetype":"venue"
},
  "geometry": {"coordinates":[-92.97595200000001,43.667394],"type":"Point"}
}