{
  "type": "Feature",
  "properties": {
    "addr:full":"4315 Gladstone St Duluth MN 55804",
    "addr:housenumber":"4315",
    "addr:postcode":"55804",
    "addr:street":"Gladstone St",
    "iso:country":"US",
    "sg:address":"4315 Gladstone St",
    "sg:city":"Duluth",
    "sg:classifiers":[
        {
            "category":"Professional",
            "subcategory":"Management & Consulting",
            "type":"Services"
        }
    ],
    "sg:phone":"+1 218 525 1405",
    "sg:postcode":"55804",
    "sg:province":"MN",
    "sg:tags":[
        "business"
    ],
    "wof:name":"Browers Consulting LLC",
    "wof:placetype":"venue"
},
  "geometry": {"coordinates":[-92.035032,46.830437],"type":"Point"}
}