{
  "type": "Feature",
  "properties": {
    "addr:full":"4850 Valhalla Dr Saint Paul MN 55129",
    "addr:housenumber":"4850",
    "addr:postcode":"55129",
    "addr:street":"Valhalla Dr",
    "iso:country":"US",
    "sg:address":"4850 Valhalla Dr",
    "sg:city":"Saint Paul",
    "sg:classifiers":[
        {
            "category":"Building & Trades",
            "subcategory":"Construction",
            "type":"Services"
        }
    ],
    "sg:phone":"+1 651 210 9432",
    "sg:postcode":"55129",
    "sg:province":"MN",
    "sg:tags":[
        "house"
    ],
    "wof:name":"F W Gordon Construction Inc",
    "wof:placetype":"venue"
},
  "geometry": {"coordinates":[-92.976493,44.881788],"type":"Point"}
}