{
  "type": "Feature",
  "properties": {
    "addr:full":"5636 W 125th St Savage MN 55378",
    "addr:housenumber":"5636",
    "addr:postcode":"55378",
    "addr:street":"W 125Th St",
    "iso:country":"US",
    "sg:address":"5636 W 125th St",
    "sg:city":"Savage",
    "sg:classifiers":[
        {
            "category":"Retail",
            "subcategory":"Auto Rental",
            "type":"Services"
        },
        {
            "category":"Building & Trades",
            "subcategory":"Equipment Rental",
            "type":"Services"
        },
        {
            "category":"Sports & Exercise",
            "subcategory":"Ski Resort",
            "type":"Entertainment"
        }
    ],
    "sg:phone":"+1 952 736 1544",
    "sg:postcode":"55378",
    "sg:province":"MN",
    "sg:tags":[
        "supply",
        "system",
        "hydraulic",
        "automation",
        "pipe",
        "fitting"
    ],
    "sg:website":"http://www.universalpowerconversion.com",
    "wof:name":"Universal Power Conversion",
    "wof:placetype":"venue"
},
  "geometry": {"coordinates":[-93.350266,44.775716],"type":"Point"}
}