{
  "type": "Feature",
  "properties": {
    "addr:full":"8162 Bloomington Ave S Minneapolis MN 55425",
    "addr:housenumber":"8162",
    "addr:postcode":"55425",
    "addr:street":"Bloomington Ave S",
    "iso:country":"US",
    "sg:address":"8162 Bloomington Ave S",
    "sg:city":"Minneapolis",
    "sg:classifiers":[
        {
            "category":"Real Estate",
            "subcategory":"Real Estate Operator",
            "type":"Services"
        }
    ],
    "sg:phone":"+1 952 854 4141",
    "sg:postcode":"55425",
    "sg:province":"MN",
    "sg:tags":[
        "townhouses"
    ],
    "wof:name":"Georgetown Park Townhouses",
    "wof:placetype":"venue"
},
  "geometry": {"coordinates":[-93.252994,44.856537],"type":"Point"}
}