{
  "type": "Feature",
  "properties": {
    "iso:country":"US",
    "sg:address":"6401 Timber Ridge",
    "sg:city":"Minneapolis",
    "sg:classifiers":[
        {
            "category":"Wholesale",
            "subcategory":"Office Equipment",
            "type":"Manufacturing & Wholesale Goods"
        }
    ],
    "sg:phone":"+1 952 943 8827",
    "sg:postcode":"55439",
    "sg:province":"MN",
    "sg:tags":[
        "machine",
        "duplicating",
        "copying"
    ],
    "wof:name":"Sandgren Office Svc",
    "wof:placetype":"venue"
},
  "geometry": {"coordinates":[-93.388443,44.888335],"type":"Point"}
}