{
  "type": "Feature",
  "properties": {
    "iso:country":"US",
    "sg:address":"8970 Blueberry Trl",
    "sg:city":"Rush City",
    "sg:classifiers":[
        {
            "category":"Farming",
            "subcategory":"Livestock Farm",
            "type":"Manufacturing & Wholesale Goods"
        }
    ],
    "sg:phone":"+1 320 358 4952",
    "sg:postcode":"55069",
    "sg:province":"MN",
    "sg:tags":[
        "corn",
        "beef",
        "feedlot",
        "cattle"
    ],
    "wof:name":"Earl Schweigert Farm",
    "wof:placetype":"venue"
},
  "geometry": {"coordinates":[-92.927477,45.687395],"type":"Point"}
}