{
  "type": "Feature",
  "properties": {
    "iso:country":"US",
    "sg:address":"15608 Randall Ln",
    "sg:city":"Minnetonka",
    "sg:classifiers":[
        {
            "category":"Building & Trades",
            "subcategory":"Landscaping Services",
            "type":"Services"
        }
    ],
    "sg:phone":"+1 952 934 4816",
    "sg:postcode":"55345",
    "sg:province":"MN",
    "sg:tags":[
        "landscape"
    ],
    "wof:name":"Arborgate Horticultural",
    "wof:placetype":"venue"
},
  "geometry": {"coordinates":[-93.480405,44.901563],"type":"Point"}
}