{
  "type": "Feature",
  "properties": {
    "iso:country":"US",
    "sg:address":"1178 Benton Way",
    "sg:city":"St Paul",
    "sg:classifiers":[
        {
            "category":"Shopping",
            "subcategory":"Discount & Variety Stores",
            "type":"Retail Goods"
        }
    ],
    "sg:phone":"+1 651 483 9835",
    "sg:postcode":"55112",
    "sg:province":"MN",
    "sg:tags":[
        "merchandise",
        "general"
    ],
    "wof:name":"My Thai Store",
    "wof:placetype":"venue"
},
  "geometry": {"coordinates":[-93.15020699999999,45.046682],"type":"Point"}
}