{
  "type": "Feature",
  "properties": {
    "iso:country":"US",
    "sg:address":"2950 Niagara Ln N",
    "sg:city":"Minneapolis",
    "sg:classifiers":[
        {
            "category":"Wholesale",
            "subcategory":"Electrical",
            "type":"Manufacturing & Wholesale Goods"
        }
    ],
    "sg:phone":"+1 763 553 1090",
    "sg:postcode":"55447",
    "sg:province":"MN",
    "sg:tags":[
        "equipment"
    ],
    "wof:name":"Power Electric Dist Inc",
    "wof:placetype":"venue"
},
  "geometry": {"coordinates":[-93.471451,45.01375],"type":"Point"}
}