{
  "type": "Feature",
  "properties": {
    "addr:full":"1615 93rd Ln NE Minneapolis MN 55449",
    "addr:housenumber":"1615",
    "addr:postcode":"55449",
    "addr:street":"93Rd Ln Ne",
    "iso:country":"US",
    "sg:address":"1615 93rd Ln NE",
    "sg:city":"Minneapolis",
    "sg:classifiers":[
        {
            "category":"Professional",
            "subcategory":"Advertising",
            "type":"Services"
        }
    ],
    "sg:phone":"+1 763 792 4155",
    "sg:postcode":"55449",
    "sg:province":"MN",
    "sg:tags":[
        "marketing",
        "agency"
    ],
    "wof:name":"Leland & Associates",
    "wof:placetype":"venue"
},
  "geometry": {"coordinates":[-93.229755,45.140088],"type":"Point"}
}