{
  "type": "Feature",
  "properties": {
    "addr:full":"211 Main St New Munich MN 56356",
    "addr:housenumber":"211",
    "addr:postcode":"56356",
    "addr:street":"Main St",
    "iso:country":"US",
    "sg:address":"211 Main St",
    "sg:city":"New Munich",
    "sg:classifiers":[
        {
            "category":"Personal",
            "subcategory":"Beauty Salon",
            "type":"Services"
        }
    ],
    "sg:phone":"+1 320 837 5883",
    "sg:postcode":"56356",
    "sg:province":"MN",
    "wof:name":"Shear Image",
    "wof:placetype":"venue"
},
  "geometry": {"coordinates":[-94.754074,45.627294],"type":"Point"}
}