{
  "type": "Feature",
  "properties": {
    "addr:full":"5901 Omaha Ave N Stillwater MN 55082",
    "addr:housenumber":"5901",
    "addr:postcode":"55082",
    "addr:street":"Omaha Ave N",
    "iso:country":"US",
    "sg:address":"5901 Omaha Ave N",
    "sg:city":"Stillwater",
    "sg:classifiers":[
        {
            "category":"Retail",
            "subcategory":"Animal Services",
            "type":"Services"
        }
    ],
    "sg:phone":"+1 651 351 9591",
    "sg:postcode":"55082",
    "sg:province":"MN",
    "sg:tags":[
        "pet",
        "grooming",
        "washing"
    ],
    "wof:name":"Grooming Avenue Pet Salon",
    "wof:placetype":"venue"
},
  "geometry": {"coordinates":[-92.81262599999999,45.034555],"type":"Point"}
}