{
  "type": "Feature",
  "properties": {
    "addr:full":"8942 Southridge St SW Byron MN 55920",
    "addr:housenumber":"8942",
    "addr:postcode":"55920",
    "addr:street":"Southridge St Sw",
    "iso:country":"US",
    "sg:address":"8942 Southridge St SW",
    "sg:city":"Byron",
    "sg:classifiers":[
        {
            "category":"Professional",
            "type":"Services"
        }
    ],
    "sg:phone":"+1 507 775 2062",
    "sg:postcode":"55920",
    "sg:province":"MN",
    "wof:name":"Rj Timber S Traders",
    "wof:placetype":"venue"
},
  "geometry": {"coordinates":[-92.61659299999999,44.018929],"type":"Point"}
}