{
  "type": "Feature",
  "properties": {
    "addr:full":"2904 Stinson Blvd Minneapolis MN 55418",
    "addr:housenumber":"2904",
    "addr:postcode":"55418",
    "addr:street":"Stinson Blvd",
    "iso:country":"US",
    "sg:address":"2904 Stinson Blvd",
    "sg:city":"Minneapolis",
    "sg:classifiers":[
        {
            "category":"Banks & Credit Unions",
            "subcategory":"Financial Services",
            "type":"Services"
        }
    ],
    "sg:phone":"+1 612 781 7875",
    "sg:postcode":"55418",
    "sg:province":"MN",
    "sg:tags":[
        "investor"
    ],
    "wof:name":"Nye Investment Holdings LLC",
    "wof:placetype":"venue"
},
  "geometry": {"coordinates":[-93.226795,45.021543],"type":"Point"}
}