{
  "type": "Feature",
  "properties": {
    "addr:full":"7741 147th St W Apple Valley MN 55124",
    "addr:housenumber":"7741",
    "addr:postcode":"55124",
    "addr:street":"147Th St W",
    "iso:country":"US",
    "sg:address":"7741 147th St W",
    "sg:city":"Apple Valley",
    "sg:classifiers":[
        {
            "category":"Real Estate",
            "subcategory":"Real Estate Agent",
            "type":"Services"
        }
    ],
    "sg:phone":"+1 952 997 8899",
    "sg:postcode":"55124",
    "sg:province":"MN",
    "sg:website":"www.homesbytony.com",
    "wof:name":"Coldwell Banker, Tony & Lori Ashworth",
    "wof:placetype":"venue"
},
  "geometry": {"coordinates":[-93.22363900000001,44.735597],"type":"Point"}
}