{
  "type": "Feature",
  "properties": {
    "iso:country":"US",
    "sg:address":"6205 Grand Ave",
    "sg:city":"Duluth",
    "sg:classifiers":[
        {
            "category":"Professional",
            "type":"Services"
        }
    ],
    "sg:phone":"+1 218 628 3748",
    "sg:postcode":"55807",
    "sg:province":"MN",
    "wof:name":"Driven Visions Inc",
    "wof:placetype":"venue"
},
  "geometry": {"coordinates":[-92.17742800000001,46.733244],"type":"Point"}
}