{
  "type": "Feature",
  "properties": {
    "addr:full":"5015 Co Rd 151 Mound MN 55364",
    "addr:housenumber":"5015",
    "addr:postcode":"55364",
    "addr:street":"Co Rd 151 Mound",
    "iso:country":"US",
    "sg:address":"5015 Co Rd 151",
    "sg:city":"Mound",
    "sg:classifiers":[
        {
            "category":"Real Estate",
            "subcategory":"Developer",
            "type":"Services"
        }
    ],
    "sg:phone":"+1 952 472 3925",
    "sg:postcode":"55364",
    "sg:province":"MN",
    "sg:tags":[
        "cemetery"
    ],
    "wof:name":"Fairview Cemetery",
    "wof:placetype":"venue"
},
  "geometry": {"coordinates":[-93.64920100000001,44.963992],"type":"Point"}
}