{
  "type": "Feature",
  "properties": {
    "addr:full":"601 Carlson Pkwy S Hopkins MN 55305",
    "addr:housenumber":"601",
    "addr:postcode":"55305",
    "addr:street":"Carlson Pkwy S",
    "iso:country":"US",
    "sg:address":"601 Carlson Pkwy S",
    "sg:city":"Hopkins",
    "sg:classifiers":[
        {
            "category":"Banks & Credit Unions",
            "subcategory":"Investment Brokerage",
            "type":"Services"
        }
    ],
    "sg:phone":"+1 952 475 6872",
    "sg:postcode":"55305",
    "sg:province":"MN",
    "sg:tags":[
        "security"
    ],
    "wof:name":"Vector Securities LLC",
    "wof:placetype":"venue"
},
  "geometry": {"coordinates":[-93.469363,44.974638],"type":"Point"}
}