{
  "type": "Feature",
  "properties": {
    "iso:country":"US",
    "sg:address":"1410 Home Ln",
    "sg:city":"Internatl Falls",
    "sg:classifiers":[
        {
            "category":"Building & Trades",
            "subcategory":"Construction",
            "type":"Services"
        }
    ],
    "sg:phone":"+1 218 283 6212",
    "sg:postcode":"56649",
    "sg:province":"MN",
    "sg:tags":[
        "home",
        "builder"
    ],
    "wof:name":"REM Northstar Home Lane",
    "wof:placetype":"venue"
},
  "geometry": {"coordinates":[-93.42179899999999,48.59664],"type":"Point"}
}