{
  "type": "Feature",
  "properties": {
    "iso:country":"US",
    "sg:address":"11197 130th St",
    "sg:city":"Madelia",
    "sg:classifiers":[
        {
            "category":"Professional",
            "type":"Services"
        }
    ],
    "sg:phone":"+1 507 439 6478",
    "sg:postcode":"56062",
    "sg:province":"MN",
    "wof:name":"Darrell Hylen",
    "wof:placetype":"venue"
},
  "geometry": {"coordinates":[-94.399029,44.148726],"type":"Point"}
}