{
  "type": "Feature",
  "properties": {
    "addr:full":"9489 Co Rd 6 Princeton MN 55371",
    "addr:housenumber":"9489;6",
    "addr:postcode":"55371",
    "addr:street":"Co Rd",
    "iso:country":"US",
    "sg:address":"9489 Co Rd 6",
    "sg:city":"Princeton",
    "sg:phone":"+1 763 389 1486",
    "sg:postcode":"55371",
    "sg:province":"MN",
    "sg:tags":[
        "farm",
        "soybean"
    ],
    "wof:name":"Larry Lueck",
    "wof:placetype":"venue"
},
  "geometry": {"coordinates":[-93.511539,45.630576],"type":"Point"}
}