{
  "type": "Feature",
  "properties": {
    "addr:full":"128 Main St N Winnebago MN 56098",
    "addr:housenumber":"128",
    "addr:postcode":"56098",
    "addr:street":"Main St N",
    "iso:country":"US",
    "sg:address":"128 Main St N",
    "sg:city":"Winnebago",
    "sg:classifiers":[
        {
            "category":"Organizations",
            "subcategory":"Religious Organization",
            "type":"Services"
        }
    ],
    "sg:phone":"+1 507 893 3197",
    "sg:postcode":"56098",
    "sg:province":"MN",
    "sg:tags":[
        "church"
    ],
    "wof:name":"First Presbyterian Church",
    "wof:placetype":"venue"
},
  "geometry": {"coordinates":[-94.16568100000001,43.769588],"type":"Point"}
}