{
  "type": "Feature",
  "properties": {
    "addr:full":"6305 Cambridge St St Louis Park MN 55416",
    "addr:housenumber":"6305",
    "addr:postcode":"55416",
    "addr:street":"Cambridge St",
    "iso:country":"US",
    "sg:address":"6305 Cambridge St",
    "sg:city":"St Louis Park",
    "sg:classifiers":[
        {
            "category":"Retail",
            "subcategory":"Auto Repair",
            "type":"Services"
        }
    ],
    "sg:phone":"+1 952 926 1459",
    "sg:postcode":"55416",
    "sg:province":"MN",
    "sg:tags":[
        "repairing",
        "automobile"
    ],
    "wof:name":"U H Automotive Excellence",
    "wof:placetype":"venue"
},
  "geometry": {"coordinates":[-93.35836,44.933353],"type":"Point"}
}