{
  "type": "Feature",
  "properties": {
    "addr:full":"4350 Central Ave NE Minneapolis MN 55421",
    "addr:housenumber":"4350",
    "addr:postcode":"55421",
    "addr:street":"Central Ave Ne",
    "iso:country":"US",
    "sg:address":"4350 Central Ave NE",
    "sg:city":"Minneapolis",
    "sg:classifiers":[
        {
            "category":"Shopping",
            "subcategory":"Department Store",
            "type":"Retail Goods"
        },
        {
            "category":"Shopping",
            "type":"Retail Goods"
        },
        {
            "category":"Shopping",
            "subcategory":"Discount & Variety Stores",
            "type":"Retail Goods"
        }
    ],
    "sg:phone":"+1 763 788 0788",
    "sg:postcode":"55421",
    "sg:province":"MN",
    "sg:tags":[
        "merchandise"
    ],
    "sg:website":"http://www.dollartree.com/",
    "wof:name":"Dollar Tree",
    "wof:placetype":"venue"
},
  "geometry": {"coordinates":[-93.24749,45.047246],"type":"Point"}
}