{
  "type": "Feature",
  "properties": {
    "iso:country":"US",
    "sg:address":"1445 Lookout Dr",
    "sg:city":"North Mankato",
    "sg:classifiers":[
        {
            "category":"Insurance",
            "subcategory":"Insurance Agent",
            "type":"Services"
        }
    ],
    "sg:phone":"+1 507 625 2100",
    "sg:postcode":"56003",
    "sg:province":"MN",
    "wof:name":"American Family Insurance",
    "wof:placetype":"venue"
},
  "geometry": {"coordinates":[-94.047769,44.170596],"type":"Point"}
}