{
  "type": "Feature",
  "properties": {
    "addr:full":"1107 Hazeltine Blvd Chaska MN 55318",
    "addr:housenumber":"1107",
    "addr:postcode":"55318",
    "addr:street":"Hazeltine Blvd",
    "iso:country":"US",
    "sg:address":"1107 Hazeltine Blvd",
    "sg:city":"Chaska",
    "sg:classifiers":[
        {
            "category":"Travel",
            "subcategory":"Travel Agent",
            "type":"Entertainment"
        }
    ],
    "sg:phone":"+1 952 361 8800",
    "sg:postcode":"55318",
    "sg:province":"MN",
    "sg:tags":[
        "agency",
        "bureau"
    ],
    "wof:name":"Sage Travel",
    "wof:placetype":"venue"
},
  "geometry": {"coordinates":[-93.600819,44.835539],"type":"Point"}
}