{
  "type": "Feature",
  "properties": {
    "iso:country":"US",
    "sg:address":"1200 Bradford St SE Apt 4",
    "sg:city":"Hutchinson",
    "sg:classifiers":[
        {
            "category":"Building & Trades",
            "subcategory":"Construction",
            "type":"Services"
        }
    ],
    "sg:phone":"+1 320 234 6141",
    "sg:postcode":"55350",
    "sg:province":"MN",
    "sg:tags":[
        "system",
        "specialty",
        "heating",
        "contractor",
        "air conditioning"
    ],
    "wof:name":"Advantage Plumbing & Heating I",
    "wof:placetype":"venue"
},
  "geometry": {"coordinates":[-94.368889,44.874882],"type":"Point"}
}