{
  "type": "Feature",
  "properties": {
    "addr:full":"1700 3rd Ave S Wheaton MN 56296",
    "addr:housenumber":"1700",
    "addr:postcode":"56296",
    "addr:street":"3Rd Ave S",
    "iso:country":"US",
    "sg:address":"1700 3rd Ave S",
    "sg:city":"Wheaton",
    "sg:classifiers":[
        {
            "category":"Education",
            "subcategory":"School",
            "type":"Public Place"
        }
    ],
    "sg:phone":"+1 320 563 8282",
    "sg:postcode":"56296",
    "sg:province":"MN",
    "wof:name":"Wheaton High School",
    "wof:placetype":"venue"
},
  "geometry": {"coordinates":[-96.5107,45.802009],"type":"Point"}
}