{
  "type": "Feature",
  "properties": {
    "addr:full":"14590 300th St New Prague MN 56071",
    "addr:housenumber":"14590",
    "addr:postcode":"56071",
    "addr:street":"300Th St",
    "iso:country":"US",
    "sg:address":"14590 300th St",
    "sg:city":"New Prague",
    "sg:classifiers":[
        {
            "category":"Manufacturing",
            "subcategory":"Building Materials",
            "type":"Manufacturing & Wholesale Goods"
        }
    ],
    "sg:phone":"+1 952 758 2033",
    "sg:postcode":"56071",
    "sg:province":"MN",
    "sg:tags":[
        "mfg",
        "wood",
        "kitchen",
        "cabinet"
    ],
    "wof:name":"Washas Woodshop",
    "wof:placetype":"venue"
},
  "geometry": {"coordinates":[-93.553383,44.515289],"type":"Point"}
}