{
  "type": "Feature",
  "properties": {
    "addr:full":"125 1st St SE Fairfax MN 55332",
    "addr:housenumber":"125",
    "addr:postcode":"55332",
    "addr:street":"1St St Se",
    "iso:country":"US",
    "sg:address":"125 1st St SE",
    "sg:city":"Fairfax",
    "sg:classifiers":[
        {
            "category":"Retail",
            "subcategory":"Repair Shop",
            "type":"Services"
        }
    ],
    "sg:phone":"+1 507 426 7231",
    "sg:postcode":"55332",
    "sg:province":"MN",
    "sg:tags":[
        "farm",
        "equipment",
        "parts"
    ],
    "wof:name":"East Side Repair",
    "wof:placetype":"venue"
},
  "geometry": {"coordinates":[-94.71939,44.527606],"type":"Point"}
}