{
  "type": "Feature",
  "properties": {
    "iso:country":"US",
    "sg:address":"24861 Basswood Rd",
    "sg:city":"Cushing",
    "sg:classifiers":[
        {
            "category":"Wholesale",
            "subcategory":"Construction Materials",
            "type":"Manufacturing & Wholesale Goods"
        }
    ],
    "sg:phone":"+1 320 749 2222",
    "sg:postcode":"56443",
    "sg:province":"MN",
    "sg:tags":[
        "fence"
    ],
    "wof:name":"B & S Fencing",
    "wof:placetype":"venue"
},
  "geometry": {"coordinates":[-94.598697,46.122285],"type":"Point"}
}