{
  "type": "Feature",
  "properties": {
    "addr:full":"7331 Baker St NE Ste A Minneapolis MN 55432",
    "addr:housenumber":"7331",
    "addr:postcode":"55432",
    "addr:street":"Baker St Ne Ste A",
    "iso:country":"US",
    "sg:address":"7331 Baker St NE Ste A",
    "sg:city":"Minneapolis",
    "sg:classifiers":[
        {
            "category":"Building & Trades",
            "subcategory":"Electrical",
            "type":"Services"
        }
    ],
    "sg:phone":"+1 763 780 8658",
    "sg:postcode":"55432",
    "sg:province":"MN",
    "sg:tags":[
        "industrial",
        "electrician",
        "electric",
        "contractors-commercial"
    ],
    "wof:name":"Api Electric Company",
    "wof:placetype":"venue"
},
  "geometry": {"coordinates":[-93.247726,45.100977],"type":"Point"}
}