{
  "type": "Feature",
  "properties": {
    "addr:full":"38729 14th Ave North Branch MN 55056",
    "addr:housenumber":"38729",
    "addr:postcode":"55056",
    "addr:street":"14Th Ave",
    "iso:country":"US",
    "sg:address":"38729 14th Ave",
    "sg:city":"North Branch",
    "sg:classifiers":[
        {
            "category":"Ice Cream",
            "type":"Food & Drink"
        }
    ],
    "sg:menulink":"http://www.allmenus.com/mn/north-branch/168349-dairy-queen/menu/",
    "sg:phone":"+1 651 674 7680",
    "sg:postcode":"55056",
    "sg:province":"MN",
    "sg:tags":[
        "burger",
        "american"
    ],
    "wof:name":"Dairy Queen",
    "wof:placetype":"venue"
},
  "geometry": {"coordinates":[-92.99109900000001,45.509788],"type":"Point"}
}