{
  "type": "Feature",
  "properties": {
    "iso:country":"US",
    "sg:address":"1304 15th Ave N",
    "sg:city":"Moorhead",
    "sg:classifiers":[
        {
            "category":"Education",
            "subcategory":"School",
            "type":"Public Place"
        }
    ],
    "sg:phone":"+1 218 284 1440",
    "sg:postcode":"56560",
    "sg:province":"MN",
    "wof:name":"Moorhead Public School District 152 District Services",
    "wof:placetype":"venue"
},
  "geometry": {"coordinates":[-96.759247,46.890493],"type":"Point"}
}