{
  "type": "Feature",
  "properties": {
    "addr:full":"625 Silver Lake Rd NW Saint Paul MN 55112",
    "addr:housenumber":"625",
    "addr:postcode":"55112",
    "addr:street":"Silver Lake Rd Nw",
    "iso:country":"US",
    "sg:address":"625 Silver Lake Rd NW",
    "sg:city":"Saint Paul",
    "sg:classifiers":[
        {
            "category":"Professional",
            "subcategory":"Lawyer & Legal Services",
            "type":"Services"
        }
    ],
    "sg:phone":"+1 651 633 9408",
    "sg:postcode":"55112",
    "sg:province":"MN",
    "wof:name":"Freya O Hanson",
    "wof:placetype":"venue"
},
  "geometry": {"coordinates":[-93.218099,45.0586],"type":"Point"}
}