{
  "type": "Feature",
  "properties": {
    "addr:full":"7351 Kirkwood Ln N Maple Grove MN 55369",
    "addr:housenumber":"7351",
    "addr:postcode":"55369",
    "addr:street":"Kirkwood Ln N",
    "iso:country":"US",
    "sg:address":"7351 Kirkwood Ln N",
    "sg:city":"Maple Grove",
    "sg:classifiers":[
        {
            "category":"Professional",
            "subcategory":"Employment Agencies",
            "type":"Services"
        }
    ],
    "sg:phone":"+1 763 315 9000",
    "sg:postcode":"55369",
    "sg:province":"MN",
    "sg:tags":[
        "opportunity"
    ],
    "wof:name":"Aerotek",
    "wof:placetype":"venue"
},
  "geometry": {"coordinates":[-93.43454699999999,45.08757],"type":"Point"}
}