{
  "type": "Feature",
  "properties": {
    "addr:full":"100 Main St E Sleepy Eye MN 56085",
    "addr:housenumber":"100",
    "addr:postcode":"56085",
    "addr:street":"Main St E",
    "iso:country":"US",
    "sg:address":"100 Main St E",
    "sg:city":"Sleepy Eye",
    "sg:classifiers":[
        {
            "category":"Banks & Credit Unions",
            "subcategory":"Financial Services",
            "type":"Services"
        }
    ],
    "sg:phone":"+1 507 794 3911",
    "sg:postcode":"56085",
    "sg:province":"MN",
    "sg:tags":[
        "company",
        "holding"
    ],
    "wof:name":"First Sleepy Eye Bancorp",
    "wof:placetype":"venue"
},
  "geometry": {"coordinates":[-94.72284999999999,44.297257],"type":"Point"}
}