{
  "type": "Feature",
  "properties": {
    "iso:country":"US",
    "sg:address":"130 N Broadway Ave",
    "sg:city":"Albert Lea",
    "sg:classifiers":[
        {
            "category":"Real Estate",
            "subcategory":"Architect",
            "type":"Services"
        }
    ],
    "sg:phone":"+1 507 373 4205",
    "sg:postcode":"56007",
    "sg:province":"MN",
    "sg:tags":[
        "architectural"
    ],
    "wof:name":"Adrian C Hestness Architect",
    "wof:placetype":"venue"
},
  "geometry": {"coordinates":[-93.36864799999999,43.650383],"type":"Point"}
}