{
  "type": "Feature",
  "properties": {
    "iso:country":"US",
    "sg:address":"102 2nd St NW",
    "sg:city":"Ortonville",
    "sg:classifiers":[
        {
            "category":"Insurance",
            "subcategory":"Hazard Insurance",
            "type":"Services"
        }
    ],
    "sg:phone":"+1 320 487 0145",
    "sg:postcode":"56278",
    "sg:province":"MN",
    "sg:tags":[
        "commercial",
        "business"
    ],
    "wof:name":"Insurance Solutions Plus",
    "wof:placetype":"venue"
},
  "geometry": {"coordinates":[-96.44587300000001,45.305614],"type":"Point"}
}