{
  "type": "Feature",
  "properties": {
    "addr:full":"1001 E 7th St Blue Earth MN 56013",
    "addr:housenumber":"1001",
    "addr:postcode":"56013",
    "addr:street":"E 7Th St",
    "iso:country":"US",
    "sg:address":"1001 E 7th St",
    "sg:city":"Blue Earth",
    "sg:classifiers":[
        {
            "category":"Retail",
            "subcategory":"Veterinary Services",
            "type":"Services"
        }
    ],
    "sg:phone":"+1 507 526 5516",
    "sg:postcode":"56013",
    "sg:province":"MN",
    "sg:tags":[
        "pet",
        "clinic",
        "veterinarian"
    ],
    "wof:name":"Makotah Veterinary Center",
    "wof:placetype":"venue"
},
  "geometry": {"coordinates":[-94.089415,43.637701],"type":"Point"}
}