{
  "type": "Feature",
  "properties": {
    "addr:full":"9885 Hwy 10 NW Rice MN 56367",
    "addr:housenumber":"9885",
    "addr:postcode":"56367",
    "addr:street":"Hwy 10 Nw",
    "iso:country":"US",
    "sg:address":"9885 Hwy 10 NW",
    "sg:city":"Rice",
    "sg:classifiers":[
        {
            "category":"Wholesale",
            "subcategory":"Construction Materials",
            "type":"Manufacturing & Wholesale Goods"
        }
    ],
    "sg:phone":"+1 320 393 2160",
    "sg:postcode":"56367",
    "sg:province":"MN",
    "sg:tags":[
        "sand",
        "gravel"
    ],
    "wof:name":"Saldana Escavating-Aggregates",
    "wof:placetype":"venue"
},
  "geometry": {"coordinates":[-94.18975,45.719906],"type":"Point"}
}