{
  "type": "Feature",
  "properties": {
    "addr:full":"1400 4th Ave Worthington MN 56187",
    "addr:housenumber":"1400",
    "addr:postcode":"56187",
    "addr:street":"4Th Ave",
    "iso:country":"US",
    "sg:address":"1400 4th Ave",
    "sg:city":"Worthington",
    "sg:classifiers":[
        {
            "category":"Organizations",
            "subcategory":"Religious Organization",
            "type":"Services"
        }
    ],
    "sg:phone":"+1 507 376 5212",
    "sg:postcode":"56187",
    "sg:province":"MN",
    "sg:tags":[
        "place",
        "worship",
        "church"
    ],
    "wof:name":"Emmanuel United Methodist Church",
    "wof:placetype":"venue"
},
  "geometry": {"coordinates":[-95.59266700000001,43.62339],"type":"Point"}
}