{
  "type": "Feature",
  "properties": {
    "addr:full":"289 E 5th St Saint Paul MN 55101",
    "addr:housenumber":"289",
    "addr:postcode":"55101",
    "addr:street":"E 5Th St",
    "iso:country":"US",
    "sg:address":"289 E 5th St",
    "sg:city":"Saint Paul",
    "sg:classifiers":[
        {
            "category":"Professional",
            "subcategory":"Management & Consulting",
            "type":"Services"
        }
    ],
    "sg:phone":"+1 651 225 4554",
    "sg:postcode":"55101",
    "sg:province":"MN",
    "sg:tags":[
        "business"
    ],
    "wof:name":"Erm-NA Holdings Corp",
    "wof:placetype":"venue"
},
  "geometry": {"coordinates":[-93.08538,44.950085],"type":"Point"}
}