{
  "type": "Feature",
  "properties": {
    "iso:country":"US",
    "sg:address":"24005 112th St",
    "sg:city":"Zimmerman",
    "sg:classifiers":[
        {
            "category":"Retail",
            "subcategory":"Auto Repair",
            "type":"Services"
        }
    ],
    "sg:phone":"+1 612 860 8516",
    "sg:postcode":"55398",
    "sg:province":"MN",
    "sg:tags":[
        "automobile",
        "co",
        "drive",
        "transporter"
    ],
    "wof:name":"Mac's Transport Svc Inc",
    "wof:placetype":"venue"
},
  "geometry": {"coordinates":[-93.55018699999999,45.400323],"type":"Point"}
}