{
  "type": "Feature",
  "properties": {
    "addr:full":"3700 Annapolis Ln N # 115 Minneapolis MN 55447",
    "addr:housenumber":"3700",
    "addr:postcode":"55447",
    "addr:street":"Annapolis Ln N # 115",
    "iso:country":"US",
    "sg:address":"3700 Annapolis Ln N # 115",
    "sg:city":"Minneapolis",
    "sg:classifiers":[
        {
            "category":"Building & Trades",
            "subcategory":"Cleaning & Sanitation",
            "type":"Services"
        },
        {
            "category":"Manufacturing",
            "subcategory":"Textiles",
            "type":"Manufacturing & Wholesale Goods"
        },
        {
            "category":"Building & Trades",
            "subcategory":"Construction",
            "type":"Services"
        }
    ],
    "sg:phone":"+1 763 519 1444",
    "sg:postcode":"55447",
    "sg:province":"MN",
    "sg:tags":[
        "tile-wholesale",
        "tile-contractors",
        "terrazzo",
        "manufacturer",
        "marble"
    ],
    "sg:website":"http://www.walstadtile.com",
    "wof:name":"Walstad Tile & Stone Company",
    "wof:placetype":"venue"
},
  "geometry": {"coordinates":[-93.457351,45.025383],"type":"Point"}
}