{
  "type": "Feature",
  "properties": {
    "iso:country":"US",
    "sg:address":"1455 Skiles Ln",
    "sg:city":"Saint Paul",
    "sg:classifiers":[
        {
            "category":"Retail",
            "subcategory":"Repair Shop",
            "type":"Services"
        }
    ],
    "sg:phone":"+1 651 633 5476",
    "sg:postcode":"55112",
    "sg:province":"MN",
    "wof:name":"Clockmeister",
    "wof:placetype":"venue"
},
  "geometry": {"coordinates":[-93.162736,45.046673],"type":"Point"}
}