{
  "type": "Feature",
  "properties": {
    "iso:country":"US",
    "sg:address":"13813 State Highway 22",
    "sg:city":"Mapleton",
    "sg:classifiers":[
        {
            "category":"Manufacturing",
            "subcategory":"Food",
            "type":"Manufacturing & Wholesale Goods"
        },
        {
            "category":"Farming",
            "subcategory":"Farm",
            "type":"Manufacturing & Wholesale Goods"
        }
    ],
    "sg:phone":"+1 507 524 3047",
    "sg:postcode":"56065",
    "sg:province":"MN",
    "sg:tags":[
        "corn",
        "product"
    ],
    "wof:name":"John Trio",
    "wof:placetype":"venue"
},
  "geometry": {"coordinates":[-93.958445,43.949938],"type":"Point"}
}