{
  "type": "Feature",
  "properties": {
    "addr:full":"2460 Lambert Cir NE St Michael MN 55376",
    "addr:housenumber":"2460",
    "addr:postcode":"55376",
    "addr:street":"Lambert Cir Ne St",
    "iso:country":"US",
    "sg:address":"2460 Lambert Cir NE",
    "sg:city":"St Michael",
    "sg:classifiers":[
        {
            "category":"Professional",
            "subcategory":"Business Services",
            "type":"Services"
        },
        {
            "category":"Professional",
            "subcategory":"Management & Consulting",
            "type":"Services"
        }
    ],
    "sg:phone":"+1 763 497 4464",
    "sg:postcode":"55376",
    "sg:province":"MN",
    "sg:tags":[
        "control",
        "noise"
    ],
    "sg:website":"www.heartlandacoustics.com",
    "wof:name":"Heartland Acoustics LLC",
    "wof:placetype":"venue"
},
  "geometry": {"coordinates":[-93.66126300000001,45.187757],"type":"Point"}
}