{
  "type": "Feature",
  "properties": {
    "addr:full":"2454 Co Rd 143 Clearwater MN 55320",
    "addr:housenumber":"2454",
    "addr:postcode":"55320",
    "addr:street":"Co Rd 143",
    "iso:country":"US",
    "sg:address":"2454 Co Rd 143",
    "sg:city":"Clearwater",
    "sg:classifiers":[
        {
            "category":"Travel",
            "subcategory":"Campground",
            "type":"Entertainment"
        }
    ],
    "sg:phone":"+1 320 558 2876",
    "sg:postcode":"55320",
    "sg:province":"MN",
    "sg:tags":[
        "grocery",
        "drinking",
        "trailer"
    ],
    "wof:name":"St Cloud/Clearwater KOA",
    "wof:placetype":"venue"
},
  "geometry": {"coordinates":[-94.066401,45.423614],"type":"Point"}
}