{
  "type": "Feature",
  "properties": {
    "addr:full":"16014 US Hwy 10 SE Becker MN 55308",
    "addr:postcode":"16014;55308",
    "addr:street":"Us Hwy 10 Se",
    "iso:country":"US",
    "sg:address":"16014 US Hwy 10 SE",
    "sg:city":"Becker",
    "sg:classifiers":[
        {
            "category":"Retail",
            "subcategory":"Auto Repair",
            "type":"Services"
        }
    ],
    "sg:phone":"+1 763 262 8024",
    "sg:postcode":"55308",
    "sg:province":"MN",
    "sg:tags":[
        "general"
    ],
    "wof:name":"Rt Automotive",
    "wof:placetype":"venue"
},
  "geometry": {"coordinates":[-93.82428899999999,45.359645],"type":"Point"}
}