{
  "type": "Feature",
  "properties": {
    "iso:country":"US",
    "sg:address":"727 E Margaret St",
    "sg:city":"St Paul",
    "sg:classifiers":[
        {
            "category":"Organizations",
            "subcategory":"Religious Organization",
            "type":"Services"
        }
    ],
    "sg:phone":"+1 651 772 1740",
    "sg:postcode":"55106",
    "sg:province":"MN",
    "sg:tags":[
        "monastery",
        "convent"
    ],
    "wof:name":"Franciscan Sisters",
    "wof:placetype":"venue"
},
  "geometry": {"coordinates":[-93.068763,44.961283],"type":"Point"}
}