{
  "type": "Feature",
  "properties": {
    "addr:full":"22215 Jivaro St NW Anoka MN 55303",
    "addr:housenumber":"22215",
    "addr:postcode":"55303",
    "addr:street":"Jivaro St Nw",
    "iso:country":"US",
    "sg:address":"22215 Jivaro St NW",
    "sg:city":"Anoka",
    "sg:classifiers":[
        {
            "category":"Professional",
            "type":"Services"
        }
    ],
    "sg:phone":"+1 763 753 8836",
    "sg:postcode":"55303",
    "sg:province":"MN",
    "wof:name":"Montes Service",
    "wof:placetype":"venue"
},
  "geometry": {"coordinates":[-93.37841400000001,45.373976],"type":"Point"}
}