{
  "type": "Feature",
  "properties": {
    "iso:country":"US",
    "sg:address":"47196 820th St",
    "sg:city":"Lakefield",
    "sg:classifiers":[
        {
            "category":"Personal",
            "type":"Services"
        }
    ],
    "sg:phone":"+1 507 662 5443",
    "sg:postcode":"56150",
    "sg:province":"MN",
    "wof:name":"Health Connections",
    "wof:placetype":"venue"
},
  "geometry": {"coordinates":[-95.128287,43.674356],"type":"Point"}
}