{
  "type": "Feature",
  "properties": {
    "iso:country":"US",
    "sg:address":"116 E Pleasant St",
    "sg:city":"Mankato",
    "sg:classifiers":[
        {
            "category":"Building & Trades",
            "subcategory":"Construction",
            "type":"Services"
        }
    ],
    "sg:phone":"+1 507 625 7143",
    "sg:postcode":"56001",
    "sg:province":"MN",
    "sg:tags":[
        "roofing",
        "contractor"
    ],
    "wof:name":"R & R Renovation and Roofing",
    "wof:placetype":"venue"
},
  "geometry": {"coordinates":[-94.00849100000001,44.158087],"type":"Point"}
}