{
  "type": "Feature",
  "properties": {
    "iso:country":"US",
    "sg:address":"210 8th St SW",
    "sg:city":"Braham",
    "sg:classifiers":[
        {
            "category":"Freight",
            "type":"Transportation"
        }
    ],
    "sg:phone":"+1 320 396 0435",
    "sg:postcode":"55006",
    "sg:province":"MN",
    "wof:name":"Eagles Transportation",
    "wof:placetype":"venue"
},
  "geometry": {"coordinates":[-93.17756199999999,45.716663],"type":"Point"}
}