{
  "type": "Feature",
  "properties": {
    "iso:country":"US",
    "sg:address":"21500 Harlow Ave",
    "sg:city":"Jordan",
    "sg:classifiers":[
        {
            "category":"Farming",
            "subcategory":"Dairy Farm",
            "type":"Manufacturing & Wholesale Goods"
        }
    ],
    "sg:phone":"+1 952 492 6989",
    "sg:postcode":"55352",
    "sg:province":"MN",
    "wof:name":"David Steming",
    "wof:placetype":"venue"
},
  "geometry": {"coordinates":[-93.562522,44.653099],"type":"Point"}
}