{
  "type": "Feature",
  "properties": {
    "iso:country":"US",
    "sg:address":"15803 State Hwy 4",
    "sg:city":"Sleepy Eye",
    "sg:classifiers":[
        {
            "category":"Farming",
            "subcategory":"Dairy Farm",
            "type":"Manufacturing & Wholesale Goods"
        }
    ],
    "sg:phone":"+1 507 794 7777",
    "sg:postcode":"56085",
    "sg:province":"MN",
    "wof:name":"Dean Schumacher",
    "wof:placetype":"venue"
},
  "geometry": {"coordinates":[-94.721401,44.185106],"type":"Point"}
}