{
  "type": "Feature",
  "properties": {
    "addr:full":"950 Iris Cir Excelsior MN 55331",
    "addr:housenumber":"950",
    "addr:postcode":"55331",
    "addr:street":"Iris Cir",
    "iso:country":"US",
    "sg:address":"950 Iris Cir",
    "sg:city":"Excelsior",
    "sg:classifiers":[
        {
            "category":"Professional",
            "subcategory":"Business Services",
            "type":"Services"
        }
    ],
    "sg:phone":"+1 952 474 4154",
    "sg:postcode":"55331",
    "sg:province":"MN",
    "wof:name":"James B Frantz Inc",
    "wof:placetype":"venue"
},
  "geometry": {"coordinates":[-93.642297,44.88419],"type":"Point"}
}