{
  "type": "Feature",
  "properties": {
    "addr:full":"6558 University Ave NE Minneapolis MN 55432",
    "addr:housenumber":"6558",
    "addr:postcode":"ne;55432",
    "addr:street":"University Ave",
    "iso:country":"US",
    "sg:address":"6558 University Ave NE",
    "sg:city":"Minneapolis",
    "sg:classifiers":[
        {
            "category":"Personal",
            "subcategory":"Barber",
            "type":"Services"
        }
    ],
    "sg:phone":"+1 763 574 7270",
    "sg:postcode":"55432",
    "sg:province":"MN",
    "sg:tags":[
        "shop"
    ],
    "wof:name":"Rons Barber Shop & Stylist",
    "wof:placetype":"venue"
},
  "geometry": {"coordinates":[-93.263479,45.089403],"type":"Point"}
}