{
  "type": "Feature",
  "properties": {
    "addr:full":"107 Washington Ave N Minneapolis MN 55401",
    "addr:housenumber":"107",
    "addr:postcode":"55401",
    "addr:street":"Washington Ave N",
    "iso:country":"US",
    "sg:address":"107 Washington Ave N",
    "sg:city":"Minneapolis",
    "sg:classifiers":[
        {
            "category":"Fast Food",
            "type":"Food & Drink"
        },
        {
            "category":"Restaurant",
            "type":"Food & Drink"
        }
    ],
    "sg:phone":"+1 612 332 7158",
    "sg:postcode":"55401",
    "sg:province":"MN",
    "sg:tags":[
        "traditional",
        "american",
        "chicken",
        "wing"
    ],
    "wof:name":"Runyon's",
    "wof:placetype":"venue"
},
  "geometry": {"coordinates":[-93.27040100000001,44.982899],"type":"Point"}
}