{
  "type": "Feature",
  "properties": {
    "addr:full":"33512 Co Hwy 77 Wadena MN 56482",
    "addr:housenumber":"33512",
    "addr:postcode":"56482",
    "addr:street":"Co Hwy 77",
    "iso:country":"US",
    "sg:address":"33512 Co Hwy 77",
    "sg:city":"Wadena",
    "sg:classifiers":[
        {
            "category":"Airport",
            "type":"Transportation"
        }
    ],
    "sg:phone":"+1 218 631 1196",
    "sg:postcode":"56482",
    "sg:province":"MN",
    "sg:tags":[
        "aircraft",
        "maintenance"
    ],
    "wof:name":"Wadena Aviation",
    "wof:placetype":"venue"
},
  "geometry": {"coordinates":[-95.218338,46.448731],"type":"Point"}
}