{
  "type": "Feature",
  "properties": {
    "addr:full":"505 N Main St Mantorville MN 55955",
    "addr:housenumber":"505",
    "addr:postcode":"55955",
    "addr:street":"N Main St",
    "iso:country":"US",
    "sg:address":"505 N Main St",
    "sg:city":"Mantorville",
    "sg:classifiers":[
        {
            "category":"Building & Trades",
            "subcategory":"Plumbing",
            "type":"Services"
        }
    ],
    "sg:phone":"+1 507 635 5414",
    "sg:postcode":"55955",
    "sg:province":"MN",
    "sg:tags":[
        "plumbing",
        "heating",
        "air"
    ],
    "wof:name":"Donald L Huntington Plb",
    "wof:placetype":"venue"
},
  "geometry": {"coordinates":[-92.755387,44.067745],"type":"Point"}
}