{
  "type": "Feature",
  "properties": {
    "iso:country":"US",
    "sg:address":"20862 165th Ave",
    "sg:city":"Little Falls",
    "sg:phone":"+1 320 632 5883",
    "sg:postcode":"56345",
    "sg:province":"MN",
    "sg:tags":[
        "farm",
        "corn",
        "grain",
        "cash"
    ],
    "wof:name":"Lloyd Ledoux",
    "wof:placetype":"venue"
},
  "geometry": {"coordinates":[-94.313002,46.057388],"type":"Point"}
}