{
  "type": "Feature",
  "properties": {
    "addr:full":"110 2nd St NE Roseau MN 56751",
    "addr:housenumber":"110",
    "addr:postcode":"56751",
    "addr:street":"2Nd St Ne",
    "iso:country":"US",
    "sg:address":"110 2nd St NE",
    "sg:city":"Roseau",
    "sg:classifiers":[
        {
            "category":"Education",
            "subcategory":"Library",
            "type":"Public Place"
        },
        {
            "category":"Government",
            "subcategory":"Office",
            "type":"Public Place"
        }
    ],
    "sg:phone":"+1 218 463 2825",
    "sg:postcode":"56751",
    "sg:province":"MN",
    "sg:tags":[
        "township",
        "government-city",
        "village"
    ],
    "wof:name":"Roseau Public Library",
    "wof:placetype":"venue"
},
  "geometry": {"coordinates":[-95.762704,48.847159],"type":"Point"}
}