{
  "type": "Feature",
  "properties": {
    "addr:full":"17150 Jaybell Ct Lakeville MN 55044",
    "addr:housenumber":"17150",
    "addr:postcode":"55044",
    "addr:street":"Jaybell Ct",
    "iso:country":"US",
    "sg:address":"17150 Jaybell Ct",
    "sg:city":"Lakeville",
    "sg:classifiers":[
        {
            "category":"Professional",
            "subcategory":"Management & Consulting",
            "type":"Services"
        }
    ],
    "sg:phone":"+1 952 435 0955",
    "sg:postcode":"55044",
    "sg:province":"MN",
    "sg:tags":[
        "consultant",
        "educational"
    ],
    "wof:name":"Thomas Carr Consulting Inc",
    "wof:placetype":"venue"
},
  "geometry": {"coordinates":[-93.274084,44.701649],"type":"Point"}
}