{
  "type": "Feature",
  "properties": {
    "iso:country":"US",
    "sg:address":"1225 3rd St SW",
    "sg:city":"Faribault",
    "sg:classifiers":[
        {
            "category":"Education",
            "subcategory":"Junior College",
            "type":"Public Place"
        },
        {
            "category":"Education",
            "subcategory":"Vocational School",
            "type":"Public Place"
        }
    ],
    "sg:phone":"+1 507 334 3965",
    "sg:postcode":"55021",
    "sg:province":"MN",
    "sg:tags":[
        "technical"
    ],
    "sg:website":"www.southcentral.edu",
    "wof:name":"South Central Technical Colleg",
    "wof:placetype":"venue"
},
  "geometry": {"coordinates":[-93.286732,44.286653],"type":"Point"}
}