{
  "type": "Feature",
  "properties": {
    "addr:full":"66484 310th St Hartland MN 56042",
    "addr:housenumber":"66484",
    "addr:postcode":"56042",
    "addr:street":"310Th St",
    "iso:country":"US",
    "sg:address":"66484 310th St",
    "sg:city":"Hartland",
    "sg:phone":"+1 507 845 2866",
    "sg:postcode":"56042",
    "sg:province":"MN",
    "sg:tags":[
        "farm",
        "wheat"
    ],
    "wof:name":"Mark Christensen",
    "wof:placetype":"venue"
},
  "geometry": {"coordinates":[-93.53804599999999,43.800211],"type":"Point"}
}