{
  "type": "Feature",
  "properties": {
    "addr:full":"115 Railway St SW Lonsdale MN 55046",
    "addr:housenumber":"115",
    "addr:postcode":"55046",
    "addr:street":"Railway St Sw",
    "iso:country":"US",
    "sg:address":"115 Railway St SW",
    "sg:city":"Lonsdale",
    "sg:classifiers":[
        {
            "category":"Restaurant",
            "type":"Food & Drink"
        }
    ],
    "sg:phone":"+1 507 744 4945",
    "sg:postcode":"55046",
    "sg:province":"MN",
    "wof:name":"Treats Of Lonsdale",
    "wof:placetype":"venue"
},
  "geometry": {"coordinates":[-93.42974100000001,44.481143],"type":"Point"}
}