{
  "type": "Feature",
  "properties": {
    "addr:full":"204 Main St Evansville MN 56326",
    "addr:housenumber":"204",
    "addr:postcode":"56326",
    "addr:street":"Main St",
    "iso:country":"US",
    "sg:address":"204 Main St",
    "sg:city":"Evansville",
    "sg:classifiers":[
        {
            "category":"Home & Garden",
            "subcategory":"Building Materials",
            "type":"Retail Goods"
        }
    ],
    "sg:phone":"+1 320 834 4668",
    "sg:postcode":"56326",
    "sg:province":"MN",
    "wof:name":"Master Lumber & Craftwares",
    "wof:placetype":"venue"
},
  "geometry": {"coordinates":[-95.683947,46.006469],"type":"Point"}
}