{
  "type": "Feature",
  "properties": {
    "iso:country":"US",
    "sg:address":"15300 Crown Dr.",
    "sg:city":"Minnetonka",
    "sg:classifiers":[
        {
            "category":"Social Services",
            "type":"Services"
        }
    ],
    "sg:phone":"+1 612 986 3196",
    "sg:postcode":"55345",
    "sg:province":"MN",
    "sg:tags":[
        "consulting",
        "geriatric"
    ],
    "sg:website":"http://www.twincitieshelpingyoumove.com",
    "wof:name":"Twin Cities Senior Relocation Specialists",
    "wof:placetype":"venue"
},
  "geometry": {"coordinates":[-93.474816,44.916141],"type":"Point"}
}