{
  "type": "Feature",
  "properties": {
    "addr:full":"4317 Trenton Trl Eagan MN 55123",
    "addr:housenumber":"4317",
    "addr:postcode":"55123",
    "addr:street":"Trenton Trl",
    "iso:country":"US",
    "sg:address":"4317 Trenton Trl",
    "sg:city":"Eagan",
    "sg:classifiers":[
        {
            "category":"Building & Trades",
            "subcategory":"Construction",
            "type":"Services"
        }
    ],
    "sg:phone":"+1 651 452 7836",
    "sg:postcode":"55123",
    "sg:province":"MN",
    "sg:tags":[
        "hanging",
        "painter",
        "contractor"
    ],
    "wof:name":"Tulien Painting Company",
    "wof:placetype":"venue"
},
  "geometry": {"coordinates":[-93.129116,44.799955],"type":"Point"}
}