{
  "type": "Feature",
  "properties": {
    "iso:country":"US",
    "sg:address":"301 Cedar Ave W",
    "sg:city":"Hector",
    "sg:classifiers":[
        {
            "category":"Freight",
            "type":"Transportation"
        }
    ],
    "sg:phone":"+1 320 848 2675",
    "sg:postcode":"55342",
    "sg:province":"MN",
    "sg:tags":[
        "trucking"
    ],
    "wof:name":"Rosenau Trucking",
    "wof:placetype":"venue"
},
  "geometry": {"coordinates":[-94.722678,44.7431],"type":"Point"}
}