{
  "type": "Feature",
  "properties": {
    "iso:country":"US",
    "sg:address":"321 Center Ave N",
    "sg:city":"Madelia",
    "sg:classifiers":[
        {
            "category":"Wholesale",
            "subcategory":"Farm Supplies",
            "type":"Manufacturing & Wholesale Goods"
        }
    ],
    "sg:phone":"+1 507 642 8300",
    "sg:postcode":"56062",
    "sg:province":"MN",
    "sg:tags":[
        "feed"
    ],
    "wof:name":"Feed Mill-M & S Feeds Inc",
    "wof:placetype":"venue"
},
  "geometry": {"coordinates":[-94.41698700000001,44.054861],"type":"Point"}
}