{
  "type": "Feature",
  "properties": {
    "iso:country":"US",
    "sg:address":"2000 Plymouth Rd",
    "sg:city":"Hopkins",
    "sg:classifiers":[
        {
            "category":"Professional",
            "subcategory":"Computer Services",
            "type":"Services"
        }
    ],
    "sg:phone":"+1 952 544 1149",
    "sg:postcode":"55305",
    "sg:province":"MN",
    "sg:tags":[
        "internet"
    ],
    "wof:name":"Internet Offerings",
    "wof:placetype":"venue"
},
  "geometry": {"coordinates":[-93.442291,44.961963],"type":"Point"}
}