{
  "type": "Feature",
  "properties": {
    "addr:full":"2640 Minnehaha Ave Minneapolis MN 55406",
    "addr:housenumber":"2640",
    "addr:postcode":"55406",
    "addr:street":"Minnehaha Ave",
    "iso:country":"US",
    "sg:address":"2640 Minnehaha Ave",
    "sg:city":"Minneapolis",
    "sg:classifiers":[
        {
            "category":"Manufacturing",
            "subcategory":"Retail Goods",
            "type":"Manufacturing & Wholesale Goods"
        }
    ],
    "sg:phone":"+1 612 721 1285",
    "sg:postcode":"55406",
    "sg:province":"MN",
    "sg:tags":[
        "product",
        "mfg"
    ],
    "wof:name":"Aerotech Models Inc",
    "wof:placetype":"venue"
},
  "geometry": {"coordinates":[-93.239074,44.955063],"type":"Point"}
}