{
  "type": "Feature",
  "properties": {
    "addr:full":"5005 University Ave NE Minneapolis MN 55421",
    "addr:housenumber":"5005",
    "addr:postcode":"55421",
    "addr:street":"University Ave Ne",
    "iso:country":"US",
    "sg:address":"5005 University Ave NE",
    "sg:city":"Minneapolis",
    "sg:classifiers":[
        {
            "category":"Wholesale",
            "subcategory":"Machinery & Supplies",
            "type":"Manufacturing & Wholesale Goods"
        }
    ],
    "sg:phone":"+1 763 586 1066",
    "sg:postcode":"55421",
    "sg:province":"MN",
    "sg:tags":[
        "equipment",
        "industrial",
        "representative"
    ],
    "wof:name":"Arnold Associates Inc",
    "wof:placetype":"venue"
},
  "geometry": {"coordinates":[-93.262811,45.06078],"type":"Point"}
}