{
  "type": "Feature",
  "properties": {
    "iso:country":"US",
    "sg:address":"203 Little Canada Rd E",
    "sg:city":"Saint Paul",
    "sg:classifiers":[
        {
            "category":"Professional",
            "subcategory":"Engineering",
            "type":"Services"
        }
    ],
    "sg:phone":"+1 651 490 9266",
    "sg:postcode":"55117",
    "sg:province":"MN",
    "sg:tags":[
        "preparation",
        "soil"
    ],
    "wof:name":"PEC",
    "wof:placetype":"venue"
},
  "geometry": {"coordinates":[-93.091019,45.023329],"type":"Point"}
}