{
  "type": "Feature",
  "properties": {
    "addr:full":"130 Dakota St Woodstock MN 56186",
    "addr:housenumber":"130",
    "addr:postcode":"56186",
    "addr:street":"Dakota St",
    "iso:country":"US",
    "sg:address":"130 Dakota St",
    "sg:city":"Woodstock",
    "sg:classifiers":[
        {
            "category":"Organizations",
            "subcategory":"Non-profit Organization",
            "type":"Services"
        }
    ],
    "sg:phone":"+1 507 777 4325",
    "sg:postcode":"56186",
    "sg:province":"MN",
    "sg:tags":[
        "information",
        "alcoholism",
        "treatment"
    ],
    "wof:name":"Alcohol & Drug Counseling",
    "wof:placetype":"venue"
},
  "geometry": {"coordinates":[-96.102445,44.008116],"type":"Point"}
}