{
  "type": "Feature",
  "properties": {
    "addr:full":"8125 122nd St N Hugo MN 55038",
    "addr:housenumber":"8125",
    "addr:postcode":"55038",
    "addr:street":"122Nd St N Hugo",
    "iso:country":"US",
    "sg:address":"8125 122nd St N",
    "sg:city":"Hugo",
    "sg:classifiers":[
        {
            "category":"Building & Trades",
            "subcategory":"Landscaping Services",
            "type":"Services"
        }
    ],
    "sg:phone":"+1 651 222 0521",
    "sg:postcode":"55038",
    "sg:province":"MN",
    "sg:tags":[
        "landscape",
        "contractor"
    ],
    "sg:website":"www.holmandolsonlandscape.com",
    "wof:name":"Holm & Olson Landscape Design",
    "wof:placetype":"venue"
},
  "geometry": {"coordinates":[-92.93906,45.129022],"type":"Point"}
}