{
  "type": "Feature",
  "properties": {
    "addr:full":"720 W 66th St Minneapolis MN 55423",
    "addr:housenumber":"720",
    "addr:postcode":"55423",
    "addr:street":"W 66Th St",
    "iso:country":"US",
    "sg:address":"720 W 66th St",
    "sg:city":"Minneapolis",
    "sg:classifiers":[
        {
            "category":"Shopping",
            "type":"Retail Goods"
        }
    ],
    "sg:phone":"+1 612 861 2889",
    "sg:postcode":"55423",
    "sg:province":"MN",
    "sg:tags":[
        "religious"
    ],
    "sg:website":"www.stpatricksguild.com",
    "wof:name":"St Patrick's Guild",
    "wof:placetype":"venue"
},
  "geometry": {"coordinates":[-93.28818200000001,44.883417],"type":"Point"}
}