{
  "type": "Feature",
  "properties": {
    "addr:full":"9701 Girard Ave S Minneapolis MN 55431",
    "addr:housenumber":"9701",
    "addr:postcode":"55431",
    "addr:street":"Girard Ave S",
    "iso:country":"US",
    "sg:address":"9701 Girard Ave S",
    "sg:city":"Minneapolis",
    "sg:classifiers":[
        {
            "category":"Restaurant",
            "type":"Food & Drink"
        }
    ],
    "sg:phone":"+1 952 881 4003",
    "sg:postcode":"55431",
    "sg:province":"MN",
    "sg:tags":[
        "eating"
    ],
    "wof:name":"D C X LLC Tornado Slush",
    "wof:placetype":"venue"
},
  "geometry": {"coordinates":[-93.297467,44.826752],"type":"Point"}
}