{
  "type": "Feature",
  "properties": {
    "addr:full":"20555 Iceland Ave Lakeville MN 55044",
    "addr:housenumber":"20555",
    "addr:postcode":"55044",
    "addr:street":"Iceland Ave",
    "iso:country":"US",
    "sg:address":"20555 Iceland Ave",
    "sg:city":"Lakeville",
    "sg:classifiers":[
        {
            "category":"Social Services",
            "subcategory":"Child Care",
            "type":"Services"
        }
    ],
    "sg:phone":"+1 952 469 2251",
    "sg:postcode":"55044",
    "sg:province":"MN",
    "sg:tags":[
        "day"
    ],
    "wof:name":"Giant Step Theatre",
    "wof:placetype":"venue"
},
  "geometry": {"coordinates":[-93.25041899999999,44.651755],"type":"Point"}
}