{
  "type": "Feature",
  "properties": {
    "addr:full":"13536 State Hwy 65 Ham Lake MN 55304",
    "addr:housenumber":"13536",
    "addr:postcode":"55304",
    "addr:street":"State Hwy 65",
    "iso:country":"US",
    "sg:address":"13536 State Hwy 65",
    "sg:city":"Ham Lake",
    "sg:classifiers":[
        {
            "category":"Organizations",
            "subcategory":"Non-profit Organization",
            "type":"Services"
        }
    ],
    "sg:phone":"+1 763 757 9917",
    "sg:postcode":"55304",
    "sg:province":"MN",
    "sg:tags":[
        "information",
        "alcoholism",
        "treatment"
    ],
    "wof:name":"Alcoholics Anonymous",
    "wof:placetype":"venue"
},
  "geometry": {"coordinates":[-93.234841,45.218213],"type":"Point"}
}