{
  "type": "Feature",
  "properties": {
    "iso:country":"US",
    "sg:address":"404 5th St NE",
    "sg:city":"Staples",
    "sg:classifiers":[
        {
            "category":"Social Services",
            "subcategory":"Child Care",
            "type":"Services"
        }
    ],
    "sg:phone":"+1 218 894 1826",
    "sg:postcode":"56479",
    "sg:province":"MN",
    "sg:tags":[
        "day",
        "provides"
    ],
    "wof:name":"Dorothy A Nelson",
    "wof:placetype":"venue"
},
  "geometry": {"coordinates":[-94.793243,46.359064],"type":"Point"}
}