{
  "type": "Feature",
  "properties": {
    "addr:full":"221 1st Ave SE Long Prairie MN 56347",
    "addr:housenumber":"221",
    "addr:postcode":"56347",
    "addr:street":"1St Ave Se",
    "iso:country":"US",
    "sg:address":"221 1st Ave SE",
    "sg:city":"Long Prairie",
    "sg:classifiers":[
        {
            "category":"Social Services",
            "type":"Services"
        }
    ],
    "sg:phone":"+1 320 732 2319",
    "sg:postcode":"56347",
    "sg:province":"MN",
    "sg:tags":[
        "crisis",
        "intervention"
    ],
    "wof:name":"Hands Of Hope Resource Ctr",
    "wof:placetype":"venue"
},
  "geometry": {"coordinates":[-94.861851,45.972948],"type":"Point"}
}