{
  "type": "Feature",
  "properties": {
    "addr:full":"7455 France Ave S Minneapolis MN 55435",
    "addr:housenumber":"7455",
    "addr:postcode":"55435",
    "addr:street":"France Ave S",
    "iso:country":"US",
    "sg:address":"7455 France Ave S",
    "sg:city":"Minneapolis",
    "sg:phone":"+1 952 835 7662",
    "sg:postcode":"55435",
    "sg:province":"MN",
    "sg:website":"http://www.upsstore.com",
    "wof:name":"The UPS Store",
    "wof:placetype":"venue"
},
  "geometry": {"coordinates":[-93.328765,44.867558],"type":"Point"}
}