{
  "type": "Feature",
  "properties": {
    "iso:country":"US",
    "sg:address":"730 Tower Dr",
    "sg:city":"Hamel",
    "sg:phone":"+1 763 478 6162",
    "sg:postcode":"55340",
    "sg:province":"MN",
    "sg:tags":[
        "transmission",
        "facsimile"
    ],
    "sg:website":"www.jdsmarketing.net",
    "wof:name":"JDS Marketing & Sales Inc",
    "wof:placetype":"venue"
},
  "geometry": {"coordinates":[-93.539787,45.044405],"type":"Point"}
}