{
  "type": "Feature",
  "properties": {
    "iso:country":"US",
    "sg:address":"1660 Highway 100 S",
    "sg:city":"Minneapolis",
    "sg:classifiers":[
        {
            "category":"Professional",
            "type":"Services"
        }
    ],
    "sg:phone":"+1 612 331 1305",
    "sg:postcode":"55416",
    "sg:province":"MN",
    "sg:tags":[
        "caterer"
    ],
    "wof:name":"Joseph Catering",
    "wof:placetype":"venue"
},
  "geometry": {"coordinates":[-93.34320099999999,44.9678],"type":"Point"}
}