{
  "type": "Feature",
  "properties": {
    "iso:country":"US",
    "sg:address":"1215 N Riverfront Dr",
    "sg:city":"Mankato",
    "sg:classifiers":[
        {
            "category":"Retail",
            "subcategory":"Auto Repair",
            "type":"Services"
        }
    ],
    "sg:phone":"+1 507 387 3933",
    "sg:postcode":"56001",
    "sg:province":"MN",
    "sg:tags":[
        "automotive",
        "general"
    ],
    "wof:name":"North Front Repair",
    "wof:placetype":"venue"
},
  "geometry": {"coordinates":[-93.99267399999999,44.177714],"type":"Point"}
}