{
  "type": "Feature",
  "properties": {
    "addr:full":"6124 Apple Rd Excelsior MN 55331",
    "addr:housenumber":"6124",
    "addr:postcode":"55331",
    "addr:street":"Apple Rd",
    "iso:country":"US",
    "sg:address":"6124 Apple Rd",
    "sg:city":"Excelsior",
    "sg:classifiers":[
        {
            "category":"Professional",
            "type":"Services"
        }
    ],
    "sg:phone":"+1 952 474 8310",
    "sg:postcode":"55331",
    "sg:province":"MN",
    "sg:tags":[
        "establishment"
    ],
    "wof:name":"Woodhaven Well",
    "wof:placetype":"venue"
},
  "geometry": {"coordinates":[-93.558092,44.894125],"type":"Point"}
}