{
  "type": "Feature",
  "properties": {
    "addr:full":"7204 W 27th St Ste 101 Minneapolis MN 55426",
    "addr:housenumber":"7204",
    "addr:postcode":"55426",
    "addr:street":"W 27Th St Ste 101",
    "iso:country":"US",
    "sg:address":"7204 W 27th St Ste 101",
    "sg:city":"Minneapolis",
    "sg:classifiers":[
        {
            "category":"Social Services",
            "type":"Services"
        },
        {
            "category":"Health Services",
            "subcategory":"Clinic",
            "type":"Services"
        },
        {
            "category":"Organizations",
            "subcategory":"Membership Organization",
            "type":"Services"
        }
    ],
    "sg:phone":"+1 952 920 3961",
    "sg:postcode":"55426",
    "sg:province":"MN",
    "sg:tags":[
        "information",
        "support",
        "group",
        "treatment",
        "alcoholism"
    ],
    "sg:website":"http://www.al-anon.alateen.org",
    "wof:name":"Ais",
    "wof:placetype":"venue"
},
  "geometry": {"coordinates":[-93.370966,44.954891],"type":"Point"}
}