{
  "type": "Feature",
  "properties": {
    "addr:full":"220 Marie Ave E Saint Paul MN 55118",
    "addr:housenumber":"220",
    "addr:postcode":"55118",
    "addr:street":"Marie Ave E",
    "iso:country":"US",
    "sg:address":"220 Marie Ave E",
    "sg:city":"Saint Paul",
    "sg:classifiers":[
        {
            "category":"Professional",
            "subcategory":"Business Services",
            "type":"Services"
        }
    ],
    "sg:phone":"+1 651 450 5361",
    "sg:postcode":"55118",
    "sg:province":"MN",
    "wof:name":"Team Systems Inc",
    "wof:placetype":"venue"
},
  "geometry": {"coordinates":[-93.07469,44.891475],"type":"Point"}
}