{
  "type": "Feature",
  "properties": {
    "iso:country":"US",
    "sg:address":"15811 Boulder Creek Dr",
    "sg:city":"Minnetonka",
    "sg:classifiers":[
        {
            "category":"Shopping",
            "subcategory":"Used Merchandise",
            "type":"Retail Goods"
        }
    ],
    "sg:phone":"+1 952 934 7304",
    "sg:postcode":"55345",
    "sg:province":"MN",
    "wof:name":"Kaboodle",
    "wof:placetype":"venue"
},
  "geometry": {"coordinates":[-93.48187900000001,44.893474],"type":"Point"}
}