{
  "type": "Feature",
  "properties": {
    "addr:full":"9400 65th St NE Albertville MN 55301",
    "addr:housenumber":"9400",
    "addr:postcode":"55301",
    "addr:street":"65Th St Ne",
    "iso:country":"US",
    "sg:address":"9400 65th St NE",
    "sg:city":"Albertville",
    "sg:classifiers":[
        {
            "category":"Real Estate",
            "subcategory":"Real Estate Operator",
            "type":"Services"
        }
    ],
    "sg:phone":"+1 763 497 2159",
    "sg:postcode":"55301",
    "sg:province":"MN",
    "sg:tags":[
        "property",
        "lessor"
    ],
    "wof:name":"Dale Vetsch",
    "wof:placetype":"venue"
},
  "geometry": {"coordinates":[-93.696105,45.245135],"type":"Point"}
}