{
  "type": "Feature",
  "properties": {
    "addr:full":"366 Selby Ave Saint Paul MN 55102",
    "addr:housenumber":"366",
    "addr:postcode":"55102",
    "addr:street":"Selby Ave",
    "iso:country":"US",
    "sg:address":"366 Selby Ave",
    "sg:city":"Saint Paul",
    "sg:classifiers":[
        {
            "category":"Professional",
            "subcategory":"Management & Consulting",
            "type":"Services"
        }
    ],
    "sg:phone":"+1 651 292 8900",
    "sg:postcode":"55102",
    "sg:province":"MN",
    "sg:tags":[
        "public",
        "relations"
    ],
    "wof:name":"Garrity Group Inc",
    "wof:placetype":"venue"
},
  "geometry": {"coordinates":[-93.115971,44.946479],"type":"Point"}
}