{
  "type": "Feature",
  "properties": {
    "iso:country":"US",
    "sg:address":"919 5th Ave NW",
    "sg:city":"East Grand Forks",
    "sg:classifiers":[
        {
            "category":"Recreation",
            "type":"Entertainment"
        }
    ],
    "sg:phone":"+1 218 773 9231",
    "sg:postcode":"56721",
    "sg:province":"MN",
    "sg:tags":[
        "pool",
        "swimming"
    ],
    "wof:name":"East Grand Forks Swimming Pool",
    "wof:placetype":"venue"
},
  "geometry": {"coordinates":[-97.02560699999999,47.932727],"type":"Point"}
}