{
  "type": "Feature",
  "properties": {
    "addr:full":"8140 Arthur St NE Minneapolis MN 55432",
    "addr:housenumber":"8140",
    "addr:postcode":"55432",
    "addr:street":"Arthur St Ne",
    "iso:country":"US",
    "sg:address":"8140 Arthur St NE",
    "sg:city":"Minneapolis",
    "sg:classifiers":[
        {
            "category":"Building & Trades",
            "subcategory":"Plumbing",
            "type":"Services"
        }
    ],
    "sg:phone":"+1 763 780 0844",
    "sg:postcode":"55432",
    "sg:province":"MN",
    "sg:tags":[
        "conditioning",
        "air",
        "system",
        "contractor"
    ],
    "wof:name":"Action Heating & Air Condition",
    "wof:placetype":"venue"
},
  "geometry": {"coordinates":[-93.233017,45.115271],"type":"Point"}
}