{
  "type": "Feature",
  "properties": {
    "addr:full":"2110 Louis Ln Hastings MN 55033",
    "addr:housenumber":"2110",
    "addr:postcode":"55033",
    "addr:street":"Louis Ln",
    "iso:country":"US",
    "sg:address":"2110 Louis Ln",
    "sg:city":"Hastings",
    "sg:classifiers":[
        {
            "category":"Professional",
            "subcategory":"Business Services",
            "type":"Services"
        }
    ],
    "sg:phone":"+1 651 437 1267",
    "sg:postcode":"55033",
    "sg:province":"MN",
    "wof:name":"J&J Sales",
    "wof:placetype":"venue"
},
  "geometry": {"coordinates":[-92.867824,44.723908],"type":"Point"}
}