{
  "type": "Feature",
  "properties": {
    "addr:full":"4187 16th St NW Backus MN 56435",
    "addr:housenumber":"4187",
    "addr:postcode":"56435",
    "addr:street":"16Th St Nw Backus",
    "iso:country":"US",
    "sg:address":"4187 16th St NW",
    "sg:city":"Backus",
    "sg:classifiers":[
        {
            "category":"Retail",
            "subcategory":"Auto Repair",
            "type":"Services"
        }
    ],
    "sg:phone":"+1 218 947 3363",
    "sg:postcode":"56435",
    "sg:province":"MN",
    "sg:tags":[
        "transmission",
        "general"
    ],
    "wof:name":"F & S Transmission",
    "wof:placetype":"venue"
},
  "geometry": {"coordinates":[-94.49261199999999,46.863693],"type":"Point"}
}