{
  "type": "Feature",
  "properties": {
    "addr:full":"4000 Central Ave NE Minneapolis MN 55421",
    "addr:housenumber":"4000",
    "addr:postcode":"55421",
    "addr:street":"Central Ave Ne",
    "iso:country":"US",
    "sg:address":"4000 Central Ave NE",
    "sg:city":"Minneapolis",
    "sg:classifiers":[
        {
            "category":"Health Services",
            "subcategory":"Doctor",
            "type":"Services"
        }
    ],
    "sg:phone":"+1 612 926 8711",
    "sg:postcode":"55421",
    "sg:province":"MN",
    "sg:tags":[
        "medical"
    ],
    "wof:name":"Sandra Eliason MD",
    "wof:placetype":"venue"
},
  "geometry": {"coordinates":[-93.247434,45.04273],"type":"Point"}
}