{
  "type": "Feature",
  "properties": {
    "iso:country":"US",
    "sg:address":"423 White Oak Dr",
    "sg:city":"Saint Paul",
    "sg:classifiers":[
        {
            "category":"Building & Trades",
            "subcategory":"Construction",
            "type":"Services"
        }
    ],
    "sg:phone":"+1 612 865 1112",
    "sg:postcode":"55118",
    "sg:province":"MN",
    "sg:tags":[
        "residential"
    ],
    "wof:name":"Spargur Construction",
    "wof:placetype":"venue"
},
  "geometry": {"coordinates":[-93.10543,44.9039],"type":"Point"}
}