{
  "type": "Feature",
  "properties": {
    "addr:full":"1330 Missouri Ave Duluth MN 55811",
    "addr:housenumber":"1330",
    "addr:postcode":"55811",
    "addr:street":"Missouri Ave",
    "iso:country":"US",
    "sg:address":"1330 Missouri Ave",
    "sg:city":"Duluth",
    "sg:classifiers":[
        {
            "category":"Building & Trades",
            "subcategory":"Construction",
            "type":"Services"
        }
    ],
    "sg:phone":"+1 218 728 4007",
    "sg:postcode":"55811",
    "sg:province":"MN",
    "sg:tags":[
        "carpentry",
        "contractor"
    ],
    "wof:name":"Carpentry Works",
    "wof:placetype":"venue"
},
  "geometry": {"coordinates":[-92.094256,46.821209],"type":"Point"}
}