{
  "type": "Feature",
  "properties": {
    "addr:full":"861 11th St Chandler MN 56122",
    "addr:housenumber":"861",
    "addr:postcode":"56122",
    "addr:street":"11Th St",
    "iso:country":"US",
    "sg:address":"861 11th St",
    "sg:city":"Chandler",
    "sg:classifiers":[
        {
            "category":"Real Estate",
            "subcategory":"Real Estate Operator",
            "type":"Services"
        }
    ],
    "sg:phone":"+1 507 264 3707",
    "sg:postcode":"56122",
    "sg:province":"MN",
    "sg:tags":[
        "property",
        "lessor"
    ],
    "wof:name":"Doug Hart",
    "wof:placetype":"venue"
},
  "geometry": {"coordinates":[-95.892003,43.862922],"type":"Point"}
}