{
  "type": "Feature",
  "properties": {
    "iso:country":"US",
    "sg:address":"1539 Grand Ave",
    "sg:city":"Saint Paul",
    "sg:classifiers":[
        {
            "category":"Professional",
            "subcategory":"Lawyer & Legal Services",
            "type":"Services"
        }
    ],
    "sg:phone":"+1 651 698 5910",
    "sg:postcode":"55105",
    "sg:province":"MN",
    "sg:tags":[
        "divorce",
        "law",
        "family"
    ],
    "sg:website":"www.tdlattorneys.com",
    "wof:name":"Drummer Mary E",
    "wof:placetype":"venue"
},
  "geometry": {"coordinates":[-93.16526,44.940187],"type":"Point"}
}