{
  "type": "Feature",
  "properties": {
    "iso:country":"US",
    "sg:address":"2119 111th St",
    "sg:city":"Currie",
    "sg:phone":"+1 507 335 7715",
    "sg:postcode":"56172",
    "sg:province":"MN",
    "sg:tags":[
        "farm",
        "corn"
    ],
    "wof:name":"Dave Schreier",
    "wof:placetype":"venue"
},
  "geometry": {"coordinates":[-95.64279999999999,44.0076],"type":"Point"}
}