{
  "type": "Feature",
  "properties": {
    "addr:full":"4142 Co Rd 42 Savage MN 55378",
    "addr:housenumber":"4142;42",
    "addr:postcode":"55378",
    "addr:street":"Co Rd",
    "iso:country":"US",
    "sg:address":"4142 Co Rd 42",
    "sg:city":"Savage",
    "sg:classifiers":[
        {
            "category":"Personal",
            "subcategory":"Beauty Salon",
            "type":"Services"
        }
    ],
    "sg:phone":"+1 952 894 4459",
    "sg:postcode":"55378",
    "sg:province":"MN",
    "sg:tags":[
        "shop",
        "manicuring"
    ],
    "wof:name":"Primo Nails",
    "wof:placetype":"venue"
},
  "geometry": {"coordinates":[-93.330777,44.746528],"type":"Point"}
}