{
  "type": "Feature",
  "properties": {
    "addr:full":"15409 Co Hwy 116 Fergus Falls MN 56537",
    "addr:housenumber":"15409",
    "addr:postcode":"56537",
    "addr:street":"Co Hwy 116",
    "iso:country":"US",
    "sg:address":"15409 Co Hwy 116",
    "sg:city":"Fergus Falls",
    "sg:classifiers":[
        {
            "category":"Farming",
            "subcategory":"Dairy Farm",
            "type":"Manufacturing & Wholesale Goods"
        }
    ],
    "sg:phone":"+1 218 739 3920",
    "sg:postcode":"56537",
    "sg:province":"MN",
    "wof:name":"Paul Petersen",
    "wof:placetype":"venue"
},
  "geometry": {"coordinates":[-96.15498599999999,46.311494],"type":"Point"}
}