{
  "type": "Feature",
  "properties": {
    "addr:full":"1810 E Franklin Ave Minneapolis MN 55404",
    "addr:housenumber":"1810",
    "addr:postcode":"55404",
    "addr:street":"E Franklin Ave",
    "iso:country":"US",
    "sg:address":"1810 E Franklin Ave",
    "sg:city":"Minneapolis",
    "sg:classifiers":[
        {
            "category":"Bus Station",
            "type":"Transportation"
        }
    ],
    "sg:phone":"+1 612 341 5600",
    "sg:postcode":"55404",
    "sg:province":"MN",
    "sg:tags":[
        "maintenance",
        "facility"
    ],
    "wof:name":"Metro Transit Maintenance Shop",
    "wof:placetype":"venue"
},
  "geometry": {"coordinates":[-93.247523,44.962596],"type":"Point"}
}