{
  "type": "Feature",
  "properties": {
    "iso:country":"US",
    "sg:address":"404 E Broadway",
    "sg:city":"Minneapolis",
    "sg:classifiers":[
        {
            "category":"Home & Garden",
            "subcategory":"Household Appliances",
            "type":"Retail Goods"
        },
        {
            "category":"Retail",
            "subcategory":"Repair Shop",
            "type":"Services"
        },
        {
            "category":"Building & Trades",
            "subcategory":"Construction",
            "type":"Services"
        }
    ],
    "sg:phone":"+1 612 616 2297",
    "sg:postcode":"55425",
    "sg:province":"MN",
    "sg:tags":[
        "major",
        "specialty",
        "heating",
        "appliances-small",
        "system",
        "air conditioning",
        "mechanical",
        "contractor",
        "freezers-repair",
        "refrigerator"
    ],
    "sg:website":"http://www.altempmech.com",
    "wof:name":"Altemp Mechanical Inc",
    "wof:placetype":"venue"
},
  "geometry": {"coordinates":[-93.23948900000001,44.855447],"type":"Point"}
}