{
  "type": "Feature",
  "properties": {
    "iso:country":"US",
    "sg:address":"10300 Great Plains Blvd",
    "sg:city":"Chaska",
    "sg:classifiers":[
        {
            "category":"Autos & Motor Vehicles",
            "subcategory":"Auto Supplies",
            "type":"Retail Goods"
        }
    ],
    "sg:phone":"+1 952 445 4045",
    "sg:postcode":"55318",
    "sg:province":"MN",
    "sg:tags":[
        "tire"
    ],
    "wof:name":"Gopher State Tire",
    "wof:placetype":"venue"
},
  "geometry": {"coordinates":[-93.537689,44.816811],"type":"Point"}
}