{
  "type": "Feature",
  "properties": {
    "addr:full":"19670 Omega Ave Clements MN 56224",
    "addr:housenumber":"19670",
    "addr:postcode":"56224",
    "addr:street":"Omega Ave",
    "iso:country":"US",
    "sg:address":"19670 Omega Ave",
    "sg:city":"Clements",
    "sg:phone":"+1 507 723 6628",
    "sg:postcode":"56224",
    "sg:province":"MN",
    "sg:tags":[
        "farm",
        "corn"
    ],
    "wof:name":"Milo Veenstra",
    "wof:placetype":"venue"
},
  "geometry": {"coordinates":[-95.006592,44.330433],"type":"Point"}
}