{
  "type": "Feature",
  "properties": {
    "addr:full":"549 1st Ave NW Winnebago MN 56098",
    "addr:housenumber":"549",
    "addr:postcode":"56098",
    "addr:street":"1St Ave Nw",
    "iso:country":"US",
    "sg:address":"549 1st Ave NW",
    "sg:city":"Winnebago",
    "sg:classifiers":[
        {
            "category":"Freight",
            "type":"Transportation"
        }
    ],
    "sg:phone":"+1 507 893 3744",
    "sg:postcode":"56098",
    "sg:province":"MN",
    "sg:tags":[
        "operator",
        "trucking"
    ],
    "wof:name":"Dennis G Bartlett",
    "wof:placetype":"venue"
},
  "geometry": {"coordinates":[-94.17639800000001,43.768876],"type":"Point"}
}