{
  "type": "Feature",
  "properties": {
    "iso:country":"US",
    "sg:address":"2031 Victoria Rd S",
    "sg:city":"Saint Paul",
    "sg:classifiers":[
        {
            "category":"Health Services",
            "subcategory":"Nursing And Care Facility",
            "type":"Services"
        }
    ],
    "sg:phone":"+1 952 452 4295",
    "sg:postcode":"55118",
    "sg:province":"MN",
    "wof:name":"Dakota Communities Inc",
    "wof:placetype":"venue"
},
  "geometry": {"coordinates":[-93.144514,44.884067],"type":"Point"}
}