{
  "type": "Feature",
  "properties": {
    "iso:country":"US",
    "sg:address":"5555 Pioneer Creek Dr",
    "sg:city":"Maple Plain",
    "sg:classifiers":[
        {
            "category":"Recreation",
            "type":"Entertainment"
        }
    ],
    "sg:phone":"+1 763 479 3189",
    "sg:postcode":"55359",
    "sg:province":"MN",
    "wof:name":"Northshore Gymnastics",
    "wof:placetype":"venue"
},
  "geometry": {"coordinates":[-93.66427400000001,45.011903],"type":"Point"}
}