{
  "type": "Feature",
  "properties": {
    "iso:country":"US",
    "sg:address":"511 11th Ave S",
    "sg:city":"Minneapolis",
    "sg:classifiers":[
        {
            "category":"Professional",
            "subcategory":"Computer Services",
            "type":"Services"
        }
    ],
    "sg:phone":"+1 612 252 8300",
    "sg:postcode":"55415",
    "sg:province":"MN",
    "sg:tags":[
        "internet"
    ],
    "wof:name":"Isd Net",
    "wof:placetype":"venue"
},
  "geometry": {"coordinates":[-93.256283,44.971588],"type":"Point"}
}