{
  "type": "Feature",
  "properties": {
    "iso:country":"US",
    "sg:address":"907 8th Ave SE",
    "sg:city":"Forest Lake",
    "sg:classifiers":[
        {
            "category":"Wholesale",
            "subcategory":"Construction Materials",
            "type":"Manufacturing & Wholesale Goods"
        }
    ],
    "sg:phone":"+1 651 982 9298",
    "sg:postcode":"55025",
    "sg:province":"MN",
    "wof:name":"Northern Exteriors",
    "wof:placetype":"venue"
},
  "geometry": {"coordinates":[-92.970665,45.271132],"type":"Point"}
}