{
  "type": "Feature",
  "properties": {
    "addr:full":"211 S Newton Ave Albert Lea MN 56007",
    "addr:housenumber":"211",
    "addr:postcode":"56007",
    "addr:street":"S Newton Ave",
    "iso:country":"US",
    "sg:address":"211 S Newton Ave",
    "sg:city":"Albert Lea",
    "sg:classifiers":[
        {
            "category":"Professional",
            "subcategory":"Lawyer & Legal Services",
            "type":"Services"
        }
    ],
    "sg:phone":"+1 507 373 6491",
    "sg:postcode":"56007",
    "sg:province":"MN",
    "sg:tags":[
        "attorney"
    ],
    "sg:website":"www.pssdlaw.com",
    "wof:name":"Peterson Savelkoul & Davies",
    "wof:placetype":"venue"
},
  "geometry": {"coordinates":[-93.36729200000001,43.648733],"type":"Point"}
}