{
  "type": "Feature",
  "properties": {
    "addr:full":"306 Blaine Ave Cloquet MN 55720",
    "addr:housenumber":"306",
    "addr:postcode":"55720",
    "addr:street":"Blaine Ave",
    "iso:country":"US",
    "sg:address":"306 Blaine Ave",
    "sg:city":"Cloquet",
    "sg:classifiers":[
        {
            "category":"Social Services",
            "subcategory":"Child Care",
            "type":"Services"
        }
    ],
    "sg:phone":"+1 218 878 0128",
    "sg:postcode":"55720",
    "sg:province":"MN",
    "sg:tags":[
        "daycare",
        "provider"
    ],
    "wof:name":"Miss Debbies Day Care",
    "wof:placetype":"venue"
},
  "geometry": {"coordinates":[-92.45179899999999,46.733679],"type":"Point"}
}