{
  "type": "Feature",
  "properties": {
    "addr:full":"11479 Valley View Rd Eden Prairie MN 55344",
    "addr:housenumber":"11479",
    "addr:postcode":"55344",
    "addr:street":"Valley View Rd",
    "iso:country":"US",
    "sg:address":"11479 Valley View Rd",
    "sg:city":"Eden Prairie",
    "sg:classifiers":[
        {
            "category":"Home & Garden",
            "subcategory":"Furniture",
            "type":"Retail Goods"
        }
    ],
    "sg:phone":"+1 952 941 0475",
    "sg:postcode":"55344",
    "sg:province":"MN",
    "wof:name":"Otlari Designs",
    "wof:placetype":"venue"
},
  "geometry": {"coordinates":[-93.422331,44.867636],"type":"Point"}
}