{
  "type": "Feature",
  "properties": {
    "addr:full":"2795 Park Dr Owatonna MN 55060",
    "addr:housenumber":"2795",
    "addr:postcode":"55060",
    "addr:street":"Park Dr",
    "iso:country":"US",
    "sg:address":"2795 Park Dr",
    "sg:city":"Owatonna",
    "sg:classifiers":[
        {
            "category":"Food & Beverages",
            "subcategory":"Meat & Fish",
            "type":"Retail Goods"
        }
    ],
    "sg:phone":"+1 507 446 9075",
    "sg:postcode":"55060",
    "sg:province":"MN",
    "sg:tags":[
        "frozen"
    ],
    "wof:name":"Schwan's Ice Cream & Fine Food",
    "wof:placetype":"venue"
},
  "geometry": {"coordinates":[-93.260524,44.091779],"type":"Point"}
}