{
  "type": "Feature",
  "properties": {
    "iso:country":"US",
    "sg:address":"915 County Road 42 W",
    "sg:city":"Burnsville",
    "sg:classifiers":[
        {
            "category":"Sports & Exercise",
            "subcategory":"Bicycle Rental",
            "type":"Entertainment"
        }
    ],
    "sg:phone":"+1 952 435 5838",
    "sg:postcode":"55306",
    "sg:province":"MN",
    "sg:tags":[
        "wear"
    ],
    "wof:name":"Lids Corp",
    "wof:placetype":"venue"
},
  "geometry": {"coordinates":[-93.291,44.7463],"type":"Point"}
}