{
  "type": "Feature",
  "properties": {
    "iso:country":"US",
    "sg:address":"533 Hayward Ave N",
    "sg:city":"St Paul",
    "sg:classifiers":[
        {
            "category":"Real Estate",
            "subcategory":"Real Estate Agent",
            "type":"Services"
        },
        {
            "category":"Building & Trades",
            "subcategory":"Construction",
            "type":"Services"
        }
    ],
    "sg:phone":"+1 651 739 8033",
    "sg:postcode":"55128",
    "sg:province":"MN",
    "sg:tags":[
        "home",
        "builder"
    ],
    "sg:website":"www.cardinalremodeling.com",
    "wof:name":"Cardinal Realty Co",
    "wof:placetype":"venue"
},
  "geometry": {"coordinates":[-92.956782,44.954715],"type":"Point"}
}