{
  "type": "Feature",
  "properties": {
    "addr:full":"14140 Northdale Blvd Rogers MN 55374",
    "addr:housenumber":"14140",
    "addr:postcode":"55374",
    "addr:street":"Northdale Blvd",
    "iso:country":"US",
    "sg:address":"14140 Northdale Blvd",
    "sg:city":"Rogers",
    "sg:classifiers":[
        {
            "category":"Building & Trades",
            "subcategory":"Construction",
            "type":"Services"
        }
    ],
    "sg:phone":"+1 763 493 2230",
    "sg:postcode":"55374",
    "sg:province":"MN",
    "sg:tags":[
        "repairing",
        "remodeling",
        "contractor"
    ],
    "wof:name":"SCC Custom Remodeling",
    "wof:placetype":"venue"
},
  "geometry": {"coordinates":[-93.555736,45.211097],"type":"Point"}
}