{
  "type": "Feature",
  "properties": {
    "iso:country":"US",
    "sg:address":"2908 Hennepin Ave S",
    "sg:city":"Minneapolis",
    "sg:classifiers":[
        {
            "category":"Real Estate",
            "subcategory":"Real Estate Agent",
            "type":"Services"
        },
        {
            "category":"Professional",
            "subcategory":"Management & Consulting",
            "type":"Services"
        }
    ],
    "sg:phone":"+1 612 827 6555",
    "sg:postcode":"55408",
    "sg:province":"MN",
    "sg:tags":[
        "consultant",
        "construction"
    ],
    "sg:website":"www.ewatershed.com",
    "wof:name":"Watershed Partners Inc",
    "wof:placetype":"venue"
},
  "geometry": {"coordinates":[-93.298354,44.948437],"type":"Point"}
}