{
  "type": "Feature",
  "properties": {
    "addr:full":"4837 Bedford Rd Mound MN 55364",
    "addr:housenumber":"4837",
    "addr:postcode":"55364",
    "addr:street":"Bedford Rd",
    "iso:country":"US",
    "sg:address":"4837 Bedford Rd",
    "sg:city":"Mound",
    "sg:classifiers":[
        {
            "category":"Freight",
            "type":"Transportation"
        }
    ],
    "sg:phone":"+1 952 472 2692",
    "sg:postcode":"55364",
    "sg:province":"MN",
    "sg:tags":[
        "operator",
        "trucking"
    ],
    "wof:name":"Altenhofen Express Inc",
    "wof:placetype":"venue"
},
  "geometry": {"coordinates":[-93.648081,44.926608],"type":"Point"}
}