{
  "type": "Feature",
  "properties": {
    "addr:full":"2320 Periwinkle Ave N Stillwater MN 55082",
    "addr:housenumber":"2320",
    "addr:postcode":"55082",
    "addr:street":"Periwinkle Ave N",
    "iso:country":"US",
    "sg:address":"2320 Periwinkle Ave N",
    "sg:city":"Stillwater",
    "sg:classifiers":[
        {
            "category":"Organizations",
            "subcategory":"Community Association",
            "type":"Services"
        }
    ],
    "sg:phone":"+1 651 436 8376",
    "sg:postcode":"55082",
    "sg:province":"MN",
    "wof:name":"Thrivent Fincl For Lutherans",
    "wof:placetype":"venue"
},
  "geometry": {"coordinates":[-92.787553,44.983599],"type":"Point"}
}