{
  "type": "Feature",
  "properties": {
    "iso:country":"US",
    "sg:address":"907 Willow St",
    "sg:city":"Faribault",
    "sg:classifiers":[
        {
            "category":"Shopping",
            "subcategory":"Computers & Home Electronics",
            "type":"Retail Goods"
        }
    ],
    "sg:phone":"+1 507 838 5028",
    "sg:postcode":"55021",
    "sg:province":"MN",
    "sg:tags":[
        "equipment",
        "electronic",
        "supply"
    ],
    "wof:name":"Edison Custom Electronics",
    "wof:placetype":"venue"
},
  "geometry": {"coordinates":[-93.272819,44.281294],"type":"Point"}
}