{
  "type": "Feature",
  "properties": {
    "iso:country":"US",
    "sg:address":"406 3rd Ave E",
    "sg:city":"Alexandria",
    "sg:classifiers":[
        {
            "category":"Insurance",
            "subcategory":"Insurance Agent",
            "type":"Services"
        }
    ],
    "sg:phone":"+1 320 763 3155",
    "sg:postcode":"56308",
    "sg:province":"MN",
    "wof:name":"Long Term Care Advisors",
    "wof:placetype":"venue"
},
  "geometry": {"coordinates":[-95.372958,45.889342],"type":"Point"}
}