{
  "type": "Feature",
  "properties": {
    "iso:country":"US",
    "sg:address":"23777 Cedar Ave",
    "sg:city":"Farmington",
    "sg:classifiers":[
        {
            "category":"Building & Trades",
            "subcategory":"Construction",
            "type":"Services"
        }
    ],
    "sg:phone":"+1 952 469 5276",
    "sg:postcode":"55024",
    "sg:province":"MN",
    "sg:tags":[
        "house"
    ],
    "wof:name":"Mike Giles Homes",
    "wof:placetype":"venue"
},
  "geometry": {"coordinates":[-93.218104,44.591536],"type":"Point"}
}