{
  "type": "Feature",
  "properties": {
    "addr:full":"12026 Frontier Ave Revere MN 56166",
    "addr:housenumber":"12026",
    "addr:postcode":"56166",
    "addr:street":"Frontier Ave",
    "iso:country":"US",
    "sg:address":"12026 Frontier Ave",
    "sg:city":"Revere",
    "sg:classifiers":[
        {
            "category":"Farming",
            "subcategory":"Farm",
            "type":"Manufacturing & Wholesale Goods"
        }
    ],
    "sg:phone":"+1 507 752 7037",
    "sg:postcode":"56166",
    "sg:province":"MN",
    "sg:tags":[
        "crop"
    ],
    "wof:name":"Harnack Farms",
    "wof:placetype":"venue"
},
  "geometry": {"coordinates":[-95.37065800000001,44.225246],"type":"Point"}
}