{
  "type": "Feature",
  "properties": {
    "iso:country":"US",
    "sg:address":"726 S Benton Dr",
    "sg:city":"Sauk Rapids",
    "sg:classifiers":[
        {
            "category":"Personal",
            "subcategory":"Beauty Salon",
            "type":"Services"
        }
    ],
    "sg:phone":"+1 320 252 3282",
    "sg:postcode":"56379",
    "sg:province":"MN",
    "sg:tags":[
        "shop"
    ],
    "wof:name":"Village Plaza Salon",
    "wof:placetype":"venue"
},
  "geometry": {"coordinates":[-94.158359,45.582545],"type":"Point"}
}