{
  "type": "Feature",
  "properties": {
    "addr:full":"25916 E 9th St Winona MN 55987",
    "addr:housenumber":"25916",
    "addr:postcode":"55987",
    "addr:street":"E 9Th St",
    "iso:country":"US",
    "sg:address":"25916 E 9th St",
    "sg:city":"Winona",
    "sg:classifiers":[
        {
            "category":"Farming",
            "subcategory":"Livestock Farm",
            "type":"Manufacturing & Wholesale Goods"
        }
    ],
    "sg:phone":"+1 507 454 8170",
    "sg:postcode":"55987",
    "sg:province":"MN",
    "sg:tags":[
        "chicken",
        "beef",
        "feedlot",
        "cattle"
    ],
    "wof:name":"James Buege",
    "wof:placetype":"venue"
},
  "geometry": {"coordinates":[-91.75766,44.026009],"type":"Point"}
}