{
  "type": "Feature",
  "properties": {
    "addr:city":"Saint Paul",
    "addr:full":"1985 Buford Ave Saint Paul, Mn 55108",
    "addr:house_number":"1985",
    "addr:housenumber":"1985",
    "addr:phone":"+1 612-624-7434",
    "addr:postcode":"55108",
    "addr:road":"Buford Ave",
    "addr:state":"MN",
    "addr:street":"Buford Ave",
    "iso:country":"US",
    "sg:address":"University of Minnesota 1985 Buford Ave",
    "sg:city":"Saint Paul",
    "sg:classifiers":[
        {
            "category":"Museum",
            "type":"Entertainment"
        }
    ],
    "sg:phone":"+1 612 624 7434",
    "sg:postcode":"55108",
    "sg:province":"MN",
    "sg:website":"goldstein.che.umn.edu",
    "wof:airports":[
        102531131
    ],
    "wof:name":"Goldstein Museum Of Design",
    "wof:placetype":"venue"
},
  "geometry": {"coordinates":[-93.17746,44.98428],"type":"Point"}
}