{
  "type": "Feature",
  "properties": {
    "iso:country":"US",
    "sg:address":"University of Minnesota 1985 Buford Ave",
    "sg:city":"Saint Paul",
    "sg:classifiers":[
        {
            "category":"Museum",
            "type":"Entertainment"
        }
    ],
    "sg:phone":"+1 612 624 7434",
    "sg:postcode":"55108",
    "sg:province":"MN",
    "sg:website":"goldstein.che.umn.edu",
    "wof:name":"Goldstein Museum of Design",
    "wof:placetype":"venue"
},
  "geometry": {"coordinates":[-93.184009,44.986089],"type":"Point"}
}