{
  "type": "Feature",
  "properties": {
    "iso:country":"US",
    "sg:address":"605 21st Ave NW",
    "sg:city":"Austin",
    "sg:classifiers":[
        {
            "category":"Organizations",
            "subcategory":"Membership Organization",
            "type":"Services"
        },
        {
            "category":"Farming",
            "subcategory":"Fish & Marine Products",
            "type":"Manufacturing & Wholesale Goods"
        }
    ],
    "sg:phone":"+1 507 434 9092",
    "sg:postcode":"55912",
    "sg:province":"MN",
    "sg:tags":[
        "relocation",
        "rescue",
        "animal",
        "transporting"
    ],
    "wof:name":"Cats Off Broadway Pet Rescue",
    "wof:placetype":"venue"
},
  "geometry": {"coordinates":[-92.982635,43.688852],"type":"Point"}
}