{
  "type": "Feature",
  "properties": {
    "iso:country":"US",
    "sg:address":"25495 Co Rd 4",
    "sg:city":"Renville",
    "sg:phone":"+1 320 329 3274",
    "sg:postcode":"56284",
    "sg:province":"MN",
    "sg:tags":[
        "farm",
        "corn"
    ],
    "wof:name":"Roy Myers",
    "wof:placetype":"venue"
},
  "geometry": {"coordinates":[-95.16695300000001,44.672361],"type":"Point"}
}