{
  "type": "Feature",
  "properties": {
    "iso:country":"US",
    "sg:address":"901 Forest Ave E",
    "sg:city":"Mora",
    "sg:classifiers":[
        {
            "category":"Sports & Exercise",
            "subcategory":"Gym",
            "type":"Entertainment"
        }
    ],
    "sg:phone":"+1 320 679 6970",
    "sg:postcode":"55051",
    "sg:province":"MN",
    "sg:tags":[
        "fitness",
        "physical",
        "facility"
    ],
    "wof:name":"Mora Muscle & Fitness",
    "wof:placetype":"venue"
},
  "geometry": {"coordinates":[-93.284811,45.876312],"type":"Point"}
}