{
  "type": "Feature",
  "properties": {
    "iso:country":"US",
    "sg:address":"1500 Marshall Ave",
    "sg:city":"Saint Paul",
    "sg:classifiers":[
        {
            "category":"Retail",
            "subcategory":"Storage",
            "type":"Services"
        }
    ],
    "sg:phone":"+1 651 645 5072",
    "sg:postcode":"55104",
    "sg:province":"MN",
    "sg:tags":[
        "self"
    ],
    "sg:website":"www.allamericanself-storage.com",
    "wof:name":"All American Self Storage",
    "wof:placetype":"venue"
},
  "geometry": {"coordinates":[-93.1614,44.948502],"type":"Point"}
}