{
  "type": "Feature",
  "properties": {
    "addr:full":"420 8th St W Northfield MN 55057",
    "addr:housenumber":"420",
    "addr:postcode":"55057",
    "addr:street":"8Th St W",
    "iso:country":"US",
    "sg:address":"420 8th St W",
    "sg:city":"Northfield",
    "sg:classifiers":[
        {
            "category":"Organizations",
            "subcategory":"Religious Organization",
            "type":"Services"
        }
    ],
    "sg:phone":"+1 507 645 7660",
    "sg:postcode":"55057",
    "sg:province":"MN",
    "wof:name":"Unitarian Universalist Fellshp",
    "wof:placetype":"venue"
},
  "geometry": {"coordinates":[-93.165092,44.451788],"type":"Point"}
}