{
  "type": "Feature",
  "properties": {
    "iso:country":"US",
    "sg:address":"2805 Washington Ave SE",
    "sg:city":"Bemidji",
    "sg:classifiers":[
        {
            "category":"Building & Trades",
            "subcategory":"Construction",
            "type":"Services"
        }
    ],
    "sg:phone":"+1 218 751 4663",
    "sg:postcode":"56601",
    "sg:province":"MN",
    "sg:tags":[
        "general",
        "contractor"
    ],
    "wof:name":"Christiansen Industrial Dev",
    "wof:placetype":"venue"
},
  "geometry": {"coordinates":[-94.863675,47.432558],"type":"Point"}
}