{
  "type": "Feature",
  "properties": {
    "addr:full":"8738 210th St N Hawley MN 56549",
    "addr:housenumber":"8738",
    "addr:postcode":"56549",
    "addr:street":"210Th St N",
    "iso:country":"US",
    "sg:address":"8738 210th St N",
    "sg:city":"Hawley",
    "sg:phone":"+1 218 483 4167",
    "sg:postcode":"56549",
    "sg:province":"MN",
    "sg:tags":[
        "farm",
        "wheat"
    ],
    "wof:name":"Robert Bjerke",
    "wof:placetype":"venue"
},
  "geometry": {"coordinates":[-96.364172,46.964616],"type":"Point"}
}