{
  "type": "Feature",
  "properties": {
    "iso:country":"US",
    "sg:address":"5400 Vernon Ave S Apt 218",
    "sg:city":"Minneapolis",
    "sg:classifiers":[
        {
            "category":"Professional",
            "subcategory":"Computer Services",
            "type":"Services"
        }
    ],
    "sg:phone":"+1 952 848 7626",
    "sg:postcode":"55436",
    "sg:province":"MN",
    "sg:tags":[
        "graphic"
    ],
    "wof:name":"Slim Names",
    "wof:placetype":"venue"
},
  "geometry": {"coordinates":[-93.358887,44.90609],"type":"Point"}
}