{
  "type": "Feature",
  "properties": {
    "iso:country":"US",
    "sg:address":"5555 Matterhorn Dr NE",
    "sg:city":"Minneapolis",
    "sg:classifiers":[
        {
            "category":"Professional",
            "type":"Services"
        }
    ],
    "sg:phone":"+1 763 286 0018",
    "sg:postcode":"55432",
    "sg:province":"MN",
    "wof:name":"Aly Familytree Inc",
    "wof:placetype":"venue"
},
  "geometry": {"coordinates":[-93.236734,45.067655],"type":"Point"}
}