{
  "type": "Feature",
  "properties": {
    "addr:full":"7540 Edinborough Way Minneapolis MN 55435",
    "addr:housenumber":"7540",
    "addr:postcode":"55435",
    "addr:street":"Edinborough Way",
    "iso:country":"US",
    "sg:address":"7540 Edinborough Way",
    "sg:city":"Minneapolis",
    "sg:classifiers":[
        {
            "category":"Wholesale",
            "subcategory":"Machinery & Supplies",
            "type":"Manufacturing & Wholesale Goods"
        }
    ],
    "sg:phone":"+1 952 956 0262",
    "sg:postcode":"55435",
    "sg:province":"MN",
    "sg:tags":[
        "equipment",
        "printing"
    ],
    "wof:name":"Best Graphics Inc",
    "wof:placetype":"venue"
},
  "geometry": {"coordinates":[-93.32392299999999,44.866308],"type":"Point"}
}