{
  "type": "Feature",
  "properties": {
    "addr:full":"2131 Mississippi Cir Saint Paul MN 55112",
    "addr:housenumber":"2131",
    "addr:postcode":"55112",
    "addr:street":"Mississippi Cir",
    "iso:country":"US",
    "sg:address":"2131 Mississippi Cir",
    "sg:city":"Saint Paul",
    "sg:classifiers":[
        {
            "category":"Professional",
            "subcategory":"Management & Consulting",
            "type":"Services"
        }
    ],
    "sg:phone":"+1 651 633 2091",
    "sg:postcode":"55112",
    "sg:province":"MN",
    "wof:name":"Jerry Fruin",
    "wof:placetype":"venue"
},
  "geometry": {"coordinates":[-93.21473400000001,45.085373],"type":"Point"}
}