{
  "type": "Feature",
  "properties": {
    "addr:full":"3401 Canterbury Dr Minneapolis MN 55431",
    "addr:housenumber":"3401",
    "addr:postcode":"55431",
    "addr:street":"Canterbury Dr",
    "iso:country":"US",
    "sg:address":"3401 Canterbury Dr",
    "sg:city":"Minneapolis",
    "sg:classifiers":[
        {
            "category":"Travel",
            "subcategory":"Travel Agent",
            "type":"Entertainment"
        }
    ],
    "sg:phone":"+1 952 835 3700",
    "sg:postcode":"55431",
    "sg:province":"MN",
    "sg:tags":[
        "agency"
    ],
    "wof:name":"All Around Adventures",
    "wof:placetype":"venue"
},
  "geometry": {"coordinates":[-93.326061,44.815243],"type":"Point"}
}