{
  "type": "Feature",
  "properties": {
    "iso:country":"US",
    "sg:address":"8590 Excelsior Blvd",
    "sg:city":"Hopkins",
    "sg:classifiers":[
        {
            "category":"Shopping",
            "type":"Retail Goods"
        }
    ],
    "sg:phone":"+1 952 933 2244",
    "sg:postcode":"55343",
    "sg:province":"MN",
    "sg:tags":[
        "shop",
        "pet",
        "fish",
        "aquarium",
        "tropical"
    ],
    "wof:name":"Aqualand Aquarium Centers",
    "wof:placetype":"venue"
},
  "geometry": {"coordinates":[-93.387531,44.925353],"type":"Point"}
}