{
  "type": "Feature",
  "properties": {
    "addr:full":"10158 122nd St N Hugo MN 55038",
    "addr:housenumber":"10158",
    "addr:postcode":"55038",
    "addr:street":"122Nd St N Hugo",
    "iso:country":"US",
    "sg:address":"10158 122nd St N",
    "sg:city":"Hugo",
    "sg:classifiers":[
        {
            "category":"Education",
            "subcategory":"School",
            "type":"Public Place"
        }
    ],
    "sg:phone":"+1 651 351 8800",
    "sg:postcode":"55038",
    "sg:province":"MN",
    "wof:name":"Withrow Elementary School",
    "wof:placetype":"venue"
},
  "geometry": {"coordinates":[-92.899737,45.127301],"type":"Point"}
}