{
  "type": "Feature",
  "properties": {
    "iso:country":"US",
    "sg:address":"4100 Vinewood Ln N",
    "sg:city":"Minneapolis",
    "sg:classifiers":[
        {
            "category":"Restaurant",
            "type":"Food & Drink"
        }
    ],
    "sg:phone":"+1 763 519 8888",
    "sg:postcode":"55442",
    "sg:province":"MN",
    "sg:tags":[
        "asian",
        "chinese",
        "pan"
    ],
    "wof:name":"Peony's China Bistro",
    "wof:placetype":"venue"
},
  "geometry": {"coordinates":[-93.449063,45.029421],"type":"Point"}
}