{
  "type": "Feature",
  "properties": {
    "iso:country":"US",
    "sg:address":"8081 Garfield St NE",
    "sg:city":"Minneapolis",
    "sg:classifiers":[
        {
            "category":"Professional",
            "subcategory":"Detective & Security Services",
            "type":"Services"
        }
    ],
    "sg:phone":"+1 763 717 7272",
    "sg:postcode":"55432",
    "sg:province":"MN",
    "sg:tags":[
        "information",
        "bureau"
    ],
    "wof:name":"Pleasing Plates & Palates Personal Chef Service",
    "wof:placetype":"venue"
},
  "geometry": {"coordinates":[-93.23341499999999,45.113982],"type":"Point"}
}