{
  "type": "Feature",
  "properties": {
    "iso:country":"US",
    "sg:address":"4136 120th Ave NW",
    "sg:city":"Minneapolis",
    "sg:classifiers":[
        {
            "category":"Building & Trades",
            "subcategory":"Construction",
            "type":"Services"
        }
    ],
    "sg:phone":"+1 763 323 6525",
    "sg:postcode":"55433",
    "sg:province":"MN",
    "sg:tags":[
        "house"
    ],
    "wof:name":"Jbl Construction Services LLC",
    "wof:placetype":"venue"
},
  "geometry": {"coordinates":[-93.371494,45.189353],"type":"Point"}
}