{
  "type": "Feature",
  "properties": {
    "addr:full":"207 Parkway Ave N Lanesboro MN 55949",
    "addr:housenumber":"207",
    "addr:postcode":"55949",
    "addr:street":"Parkway Ave N Lanesboro",
    "iso:country":"US",
    "sg:address":"207 Parkway Ave N",
    "sg:city":"Lanesboro",
    "sg:classifiers":[
        {
            "category":"Shopping",
            "subcategory":"Jewelry",
            "type":"Retail Goods"
        }
    ],
    "sg:phone":"+1 507 467 3078",
    "sg:postcode":"55949",
    "sg:province":"MN",
    "sg:tags":[
        "designer"
    ],
    "sg:website":"www.crowntrout.net",
    "wof:name":"Crown Trout Jewelers",
    "wof:placetype":"venue"
},
  "geometry": {"coordinates":[-91.977086,43.722442],"type":"Point"}
}