{
  "type": "Feature",
  "properties": {
    "addr:full":"7400 Metro Blvd Ste 419 Minneapolis MN 55439",
    "addr:postcode":"7400;55439",
    "addr:street":"Metro Blvd Ste 419",
    "iso:country":"US",
    "sg:address":"7400 Metro Blvd Ste 419",
    "sg:city":"Minneapolis",
    "sg:classifiers":[
        {
            "category":"Professional",
            "subcategory":"Employment Agencies",
            "type":"Services"
        },
        {
            "category":"Professional",
            "subcategory":"Credit Reporting & Collection",
            "type":"Services"
        }
    ],
    "sg:phone":"+1 952 925 9592",
    "sg:postcode":"55439",
    "sg:province":"MN",
    "sg:tags":[
        "opportunity",
        "investigator"
    ],
    "wof:name":"Asp Racing",
    "wof:placetype":"venue"
},
  "geometry": {"coordinates":[-93.351539,44.868534],"type":"Point"}
}