{
  "type": "Feature",
  "properties": {
    "addr:full":"14100 23rd Ave N Minneapolis MN 55447",
    "addr:housenumber":"14100",
    "addr:postcode":"55447",
    "addr:street":"23Rd Ave N",
    "iso:country":"US",
    "sg:address":"14100 23rd Ave N",
    "sg:city":"Minneapolis",
    "sg:classifiers":[
        {
            "category":"Manufacturing",
            "subcategory":"Signs",
            "type":"Manufacturing & Wholesale Goods"
        }
    ],
    "sg:phone":"+1 763 392 4732",
    "sg:postcode":"55447",
    "sg:province":"MN",
    "sg:tags":[
        "specialty",
        "mfg"
    ],
    "wof:name":"Lake Way Signs Inc",
    "wof:placetype":"venue"
},
  "geometry": {"coordinates":[-93.459231,45.003909],"type":"Point"}
}