{
  "type": "Feature",
  "properties": {
    "addr:full":"7807 142nd Ave NW Anoka MN 55303",
    "addr:housenumber":"7807",
    "addr:postcode":"55303",
    "addr:street":"142Nd Ave Nw",
    "iso:country":"US",
    "sg:address":"7807 142nd Ave NW",
    "sg:city":"Anoka",
    "sg:classifiers":[
        {
            "category":"Real Estate",
            "subcategory":"Developer",
            "type":"Services"
        }
    ],
    "sg:phone":"+1 763 427 9366",
    "sg:postcode":"55303",
    "sg:province":"MN",
    "sg:tags":[
        "development",
        "land"
    ],
    "wof:name":"Alpaca Estates",
    "wof:placetype":"venue"
},
  "geometry": {"coordinates":[-93.46600100000001,45.228097],"type":"Point"}
}