{
  "type": "Feature",
  "properties": {
    "addr:full":"1101 McKnight Rd S St Paul MN 55119",
    "addr:housenumber":"1101",
    "addr:postcode":"55119",
    "addr:street":"Mcknight Rd S",
    "iso:country":"US",
    "sg:address":"1101 McKnight Rd S",
    "sg:city":"St Paul",
    "sg:classifiers":[
        {
            "category":"Shopping",
            "subcategory":"Stationery & Office Supplies",
            "type":"Retail Goods"
        }
    ],
    "sg:phone":"+1 651 738 0903",
    "sg:postcode":"55119",
    "sg:province":"MN",
    "sg:tags":[
        "school",
        "electronic"
    ],
    "wof:name":"Erickson Electronics",
    "wof:placetype":"venue"
},
  "geometry": {"coordinates":[-93.004617,44.908541],"type":"Point"}
}