{
  "type": "Feature",
  "properties": {
    "addr:full":"2177 Highland Dr Hastings MN 55033",
    "addr:housenumber":"2177",
    "addr:postcode":"55033",
    "addr:street":"Highland Dr",
    "iso:country":"US",
    "sg:address":"2177 Highland Dr",
    "sg:city":"Hastings",
    "sg:classifiers":[
        {
            "category":"Building & Trades",
            "subcategory":"Construction",
            "type":"Services"
        }
    ],
    "sg:phone":"+1 651 437 8760",
    "sg:postcode":"55033",
    "sg:province":"MN",
    "sg:tags":[
        "water",
        "contractor",
        "main",
        "sewer"
    ],
    "wof:name":"Gartzke Construction Inc",
    "wof:placetype":"venue"
},
  "geometry": {"coordinates":[-92.885482,44.726093],"type":"Point"}
}