{
  "type": "Feature",
  "properties": {
    "addr:full":"39774 560th Ave New York Mills MN 56567",
    "addr:housenumber":"39774",
    "addr:postcode":"56567",
    "addr:street":"560Th Ave",
    "iso:country":"US",
    "sg:address":"39774 560th Ave",
    "sg:city":"New York Mills",
    "sg:classifiers":[
        {
            "category":"Farming",
            "subcategory":"Livestock Farm",
            "type":"Manufacturing & Wholesale Goods"
        }
    ],
    "sg:phone":"+1 218 385 3297",
    "sg:postcode":"56567",
    "sg:province":"MN",
    "sg:tags":[
        "corn",
        "beef",
        "feedlot",
        "cattle"
    ],
    "wof:name":"Arnie Weller",
    "wof:placetype":"venue"
},
  "geometry": {"coordinates":[-95.322012,46.542781],"type":"Point"}
}