{
  "type": "Feature",
  "properties": {
    "iso:country":"US",
    "sg:address":"29268 Plotts Ave",
    "sg:city":"Worthington",
    "sg:phone":"+1 507 376 4683",
    "sg:postcode":"56187",
    "sg:province":"MN",
    "sg:tags":[
        "farm",
        "grain",
        "cash"
    ],
    "wof:name":"Tom Krohn",
    "wof:placetype":"venue"
},
  "geometry": {"coordinates":[-95.60405799999999,43.569382],"type":"Point"}
}