{
  "type": "Feature",
  "properties": {
    "addr:full":"89005 370th Ave Heron Lake MN 56137",
    "addr:housenumber":"89005",
    "addr:postcode":"56137",
    "addr:street":"370Th Ave",
    "iso:country":"US",
    "sg:address":"89005 370th Ave",
    "sg:city":"Heron Lake",
    "sg:phone":"+1 507 445 3341",
    "sg:postcode":"56137",
    "sg:province":"MN",
    "sg:tags":[
        "farm",
        "grain",
        "cash"
    ],
    "wof:name":"Leonard Grunig",
    "wof:placetype":"venue"
},
  "geometry": {"coordinates":[-95.335775,43.781027],"type":"Point"}
}