{
  "type": "Feature",
  "properties": {
    "addr:full":"8009 34th Ave S Minneapolis MN 55425",
    "addr:housenumber":"8009",
    "addr:postcode":"55425",
    "addr:street":"34Th Ave S",
    "iso:country":"US",
    "sg:address":"8009 34th Ave S",
    "sg:city":"Minneapolis",
    "sg:classifiers":[
        {
            "category":"Wholesale",
            "subcategory":"Electrical",
            "type":"Manufacturing & Wholesale Goods"
        }
    ],
    "sg:phone":"+1 952 854 3146",
    "sg:postcode":"55425",
    "sg:province":"MN",
    "sg:tags":[
        "electronic"
    ],
    "wof:name":"West 7th",
    "wof:placetype":"venue"
},
  "geometry": {"coordinates":[-93.223045,44.857384],"type":"Point"}
}