{
  "type": "Feature",
  "properties": {
    "iso:country":"US",
    "sg:address":"40993 551st Ave",
    "sg:city":"New Ulm",
    "sg:phone":"+1 507 359 4433",
    "sg:postcode":"56073",
    "sg:province":"MN",
    "sg:tags":[
        "farm",
        "corn",
        "soybean"
    ],
    "wof:name":"Duane Fluegge",
    "wof:placetype":"venue"
},
  "geometry": {"coordinates":[-94.371551,44.358809],"type":"Point"}
}