{
  "type": "Feature",
  "properties": {
    "iso:country":"US",
    "sg:address":"900 Rum River Dr S",
    "sg:city":"Princeton",
    "sg:classifiers":[
        {
            "category":"Professional",
            "type":"Services"
        }
    ],
    "sg:phone":"+1 763 631 2002",
    "sg:postcode":"55371",
    "sg:province":"MN",
    "wof:name":"Cricket Alley Too",
    "wof:placetype":"venue"
},
  "geometry": {"coordinates":[-93.581124,45.560075],"type":"Point"}
}