{
  "type": "Feature",
  "properties": {
    "addr:full":"100 W Franklin Ave Minneapolis MN 55467",
    "addr:housenumber":"100",
    "addr:postcode":"55467",
    "addr:street":"W Franklin Ave",
    "iso:country":"US",
    "sg:address":"100 W Franklin Ave",
    "sg:city":"Minneapolis",
    "sg:classifiers":[
        {
            "category":"Retail",
            "subcategory":"Event Space",
            "type":"Services"
        }
    ],
    "sg:phone":"+1 612 290 4448",
    "sg:postcode":"55467",
    "sg:province":"MN",
    "sg:tags":[
        "venue"
    ],
    "sg:website":"www.semplemansion.com",
    "wof:name":"Semple Mansion",
    "wof:placetype":"venue"
},
  "geometry": {"coordinates":[-93.279566,44.962697],"type":"Point"}
}