{
  "type": "Feature",
  "properties": {
    "iso:country":"US",
    "sg:address":"22735 Portage Ln",
    "sg:city":"Deerwood",
    "sg:classifiers":[
        {
            "category":"Building & Trades",
            "subcategory":"Landscaping Services",
            "type":"Services"
        }
    ],
    "sg:phone":"+1 218 838 4995",
    "sg:postcode":"56444",
    "sg:province":"MN",
    "sg:tags":[
        "lawn",
        "maintenance",
        "grounds"
    ],
    "wof:name":"Weekend Extensions",
    "wof:placetype":"venue"
},
  "geometry": {"coordinates":[-93.924674,46.348901],"type":"Point"}
}