{
  "type": "Feature",
  "properties": {
    "iso:country":"US",
    "sg:address":"330 River Dr W",
    "sg:city":"Milaca",
    "sg:classifiers":[
        {
            "category":"Autos & Motor Vehicles",
            "subcategory":"Auto Supplies",
            "type":"Retail Goods"
        },
        {
            "category":"Manufacturing",
            "subcategory":"Motor Vehicles & Parts",
            "type":"Manufacturing & Wholesale Goods"
        },
        {
            "category":"Retail",
            "subcategory":"Auto Repair",
            "type":"Services"
        }
    ],
    "sg:phone":"+1 320 983 5251",
    "sg:postcode":"56353",
    "sg:province":"MN",
    "sg:tags":[
        "body",
        "shop",
        "buses-distributors",
        "automobile",
        "buses-parts",
        "equipment",
        "parts",
        "accessories-wholesale",
        "painting",
        "repairing",
        "manufacturer"
    ],
    "wof:name":"Johnson Auto Body",
    "wof:placetype":"venue"
},
  "geometry": {"coordinates":[-93.661858,45.749767],"type":"Point"}
}