{
  "type": "Feature",
  "properties": {
    "iso:country":"US",
    "sg:address":"2510 Bridge Ave",
    "sg:city":"Albert Lea",
    "sg:classifiers":[
        {
            "category":"Real Estate",
            "subcategory":"Real Estate Operator",
            "type":"Services"
        }
    ],
    "sg:phone":"+1 507 377 3185",
    "sg:postcode":"56007",
    "sg:province":"MN",
    "sg:tags":[
        "shopping",
        "center"
    ],
    "wof:name":"Northbridge Shopping Center",
    "wof:placetype":"venue"
},
  "geometry": {"coordinates":[-93.358829,43.681892],"type":"Point"}
}