{
  "type": "Feature",
  "properties": {
    "addr:full":"408 N Central Ave Duluth MN 55807",
    "addr:housenumber":"408",
    "addr:postcode":"55807",
    "addr:street":"N Central Ave",
    "iso:country":"US",
    "sg:address":"408 N Central Ave",
    "sg:city":"Duluth",
    "sg:classifiers":[
        {
            "category":"Building & Trades",
            "subcategory":"Plumbing",
            "type":"Services"
        }
    ],
    "sg:phone":"+1 218 624 3693",
    "sg:postcode":"55807",
    "sg:province":"MN",
    "sg:tags":[
        "plumber",
        "contractor"
    ],
    "wof:name":"Ensign & Johnson Company",
    "wof:placetype":"venue"
},
  "geometry": {"coordinates":[-92.166512,46.739014],"type":"Point"}
}