{
  "type": "Feature",
  "properties": {
    "iso:country":"US",
    "sg:address":"258 Hennepin Ave",
    "sg:city":"Minneapolis",
    "sg:classifiers":[
        {
            "category":"Professional",
            "subcategory":"Employment Agencies",
            "type":"Services"
        }
    ],
    "sg:phone":"+1 612 371 6241",
    "sg:postcode":"55401",
    "sg:province":"MN",
    "sg:tags":[
        "opportunity"
    ],
    "wof:name":"Codeblu",
    "wof:placetype":"venue"
},
  "geometry": {"coordinates":[-93.26995700000001,44.98169],"type":"Point"}
}