{
  "type": "Feature",
  "properties": {
    "addr:full":"100 Banta Rd Long Prairie MN 56347",
    "addr:housenumber":"100",
    "addr:postcode":"56347",
    "addr:street":"Banta Rd",
    "iso:country":"US",
    "sg:address":"100 Banta Rd",
    "sg:city":"Long Prairie",
    "sg:classifiers":[
        {
            "category":"Manufacturing",
            "subcategory":"Printing",
            "type":"Manufacturing & Wholesale Goods"
        }
    ],
    "sg:phone":"+1 320 732 2121",
    "sg:postcode":"56347",
    "sg:province":"MN",
    "sg:tags":[
        "printer"
    ],
    "wof:name":"Banta Publications Group",
    "wof:placetype":"venue"
},
  "geometry": {"coordinates":[-94.867559,45.968178],"type":"Point"}
}