{
  "type": "Feature",
  "properties": {
    "addr:full":"11116 Welcome Ave N Champlin MN 55316",
    "addr:housenumber":"11116",
    "addr:postcode":"55316",
    "addr:street":"Welcome Ave N",
    "iso:country":"US",
    "sg:address":"11116 Welcome Ave N",
    "sg:city":"Champlin",
    "sg:classifiers":[
        {
            "category":"Travel",
            "subcategory":"Travel Agent",
            "type":"Entertainment"
        }
    ],
    "sg:phone":"+1 763 424 8549",
    "sg:postcode":"55316",
    "sg:province":"MN",
    "sg:tags":[
        "agency"
    ],
    "wof:name":"Time To Go Travel",
    "wof:placetype":"venue"
},
  "geometry": {"coordinates":[-93.352231,45.157324],"type":"Point"}
}