{
  "type": "Feature",
  "properties": {
    "addr:full":"260 W 4th St Rush City MN 55069",
    "addr:housenumber":"260",
    "addr:postcode":"55069",
    "addr:street":"W 4Th St",
    "iso:country":"US",
    "sg:address":"260 W 4th St",
    "sg:city":"Rush City",
    "sg:classifiers":[
        {
            "category":"Banks & Credit Unions",
            "subcategory":"Bank",
            "type":"Services"
        }
    ],
    "sg:phone":"+1 320 358 0800",
    "sg:postcode":"55069",
    "sg:province":"MN",
    "wof:name":"Northwoods Bank",
    "wof:placetype":"venue"
},
  "geometry": {"coordinates":[-92.96446400000001,45.684678],"type":"Point"}
}