{
  "type": "Feature",
  "properties": {
    "iso:country":"US",
    "sg:address":"102 Co Hwy 1",
    "sg:city":"Ottertail",
    "sg:classifiers":[
        {
            "category":"Restaurant",
            "type":"Food & Drink"
        }
    ],
    "sg:phone":"+1 218 367 2050",
    "sg:postcode":"56571",
    "sg:province":"MN",
    "wof:name":"Angler Inn",
    "wof:placetype":"venue"
},
  "geometry": {"coordinates":[-95.57379,46.43779],"type":"Point"}
}