{
  "type": "Feature",
  "properties": {
    "iso:country":"US",
    "sg:address":"224 S 1st St",
    "sg:city":"Montevideo",
    "sg:classifiers":[
        {
            "category":"Education",
            "subcategory":"Library",
            "type":"Public Place"
        }
    ],
    "sg:phone":"+1 320 269 6501",
    "sg:postcode":"56265",
    "sg:province":"MN",
    "sg:website":"www.montelibrary.org",
    "wof:name":"Montevideo Public Library",
    "wof:placetype":"venue"
},
  "geometry": {"coordinates":[-95.723877,44.944239],"type":"Point"}
}