{
  "type": "Feature",
  "properties": {
    "iso:country":"US",
    "sg:address":"18980 102nd St",
    "sg:city":"Young America",
    "sg:classifiers":[
        {
            "category":"Farming",
            "subcategory":"Dairy Farm",
            "type":"Manufacturing & Wholesale Goods"
        }
    ],
    "sg:phone":"+1 952 467 3157",
    "sg:postcode":"55397",
    "sg:province":"MN",
    "wof:name":"Elmbrink Holsteins D L Brink",
    "wof:placetype":"venue"
},
  "geometry": {"coordinates":[-94.000466,44.818635],"type":"Point"}
}