{
  "type": "Feature",
  "properties": {
    "addr:full":"702 Atlantic Ave S Hallock MN 56728",
    "addr:housenumber":"702",
    "addr:postcode":"56728",
    "addr:street":"Atlantic Ave S Hallock",
    "iso:country":"US",
    "sg:address":"702 Atlantic Ave S",
    "sg:city":"Hallock",
    "sg:classifiers":[
        {
            "category":"Travel",
            "subcategory":"Hotels & Motels",
            "type":"Entertainment"
        }
    ],
    "sg:phone":"+1 218 843 2032",
    "sg:postcode":"56728",
    "sg:province":"MN",
    "wof:name":"Gateway Motel",
    "wof:placetype":"venue"
},
  "geometry": {"coordinates":[-96.950715,48.781079],"type":"Point"}
}