{
  "type": "Feature",
  "properties": {
    "iso:country":"US",
    "sg:address":"7230 Emerson Ave N",
    "sg:city":"Minneapolis",
    "sg:classifiers":[
        {
            "category":"Real Estate",
            "subcategory":"Real Estate Operator",
            "type":"Services"
        }
    ],
    "sg:phone":"+1 763 561 7286",
    "sg:postcode":"55430",
    "sg:province":"MN",
    "sg:tags":[
        "property",
        "lessor"
    ],
    "wof:name":"Thomas Harbinson",
    "wof:placetype":"venue"
},
  "geometry": {"coordinates":[-93.29651800000001,45.085608],"type":"Point"}
}