{
  "type": "Feature",
  "properties": {
    "addr:full":"14407 Excelsior Blvd Minnetonka MN 55345",
    "addr:housenumber":"14407",
    "addr:postcode":"55345",
    "addr:street":"Excelsior Blvd",
    "iso:country":"US",
    "sg:address":"14407 Excelsior Blvd",
    "sg:city":"Minnetonka",
    "sg:classifiers":[
        {
            "category":"Personal",
            "subcategory":"Barber",
            "type":"Services"
        }
    ],
    "sg:phone":"+1 952 933 8111",
    "sg:postcode":"55345",
    "sg:province":"MN",
    "sg:tags":[
        "shop"
    ],
    "wof:name":"Glen Lake Barber Shop",
    "wof:placetype":"venue"
},
  "geometry": {"coordinates":[-93.465001,44.904556],"type":"Point"}
}