{
  "type": "Feature",
  "properties": {
    "addr:full":"3012 Asbury St Saint Paul MN 55113",
    "addr:housenumber":"3012",
    "addr:postcode":"55113",
    "addr:street":"Asbury St",
    "iso:country":"US",
    "sg:address":"3012 Asbury St",
    "sg:city":"Saint Paul",
    "sg:classifiers":[
        {
            "category":"Manufacturing",
            "subcategory":"Signs",
            "type":"Manufacturing & Wholesale Goods"
        }
    ],
    "sg:phone":"+1 651 639 0236",
    "sg:postcode":"55113",
    "sg:province":"MN",
    "sg:tags":[
        "specialty",
        "mfg"
    ],
    "wof:name":"Fire Within Banners",
    "wof:placetype":"venue"
},
  "geometry": {"coordinates":[-93.164328,45.032581],"type":"Point"}
}