{
  "type": "Feature",
  "properties": {
    "addr:full":"26634 Fallbrook Ave Wyoming MN 55092",
    "addr:housenumber":"26634",
    "addr:postcode":"55092",
    "addr:street":"Fallbrook Ave",
    "iso:country":"US",
    "sg:address":"26634 Fallbrook Ave",
    "sg:city":"Wyoming",
    "sg:classifiers":[
        {
            "category":"Autos & Motor Vehicles",
            "subcategory":"Boat Sales",
            "type":"Retail Goods"
        }
    ],
    "sg:phone":"+1 651 462 4088",
    "sg:postcode":"55092",
    "sg:province":"MN",
    "sg:tags":[
        "repair",
        "dealer",
        "sales"
    ],
    "sg:website":"www.linkrec.com",
    "wof:name":"Link Recreational Inc",
    "wof:placetype":"venue"
},
  "geometry": {"coordinates":[-93.00143,45.335501],"type":"Point"}
}