{
  "type": "Feature",
  "properties": {
    "iso:country":"US",
    "sg:address":"12710 Falcon Ct N",
    "sg:city":"Saint Paul",
    "sg:classifiers":[
        {
            "category":"Professional",
            "subcategory":"Secretarial Services",
            "type":"Services"
        }
    ],
    "sg:phone":"+1 651 429 4995",
    "sg:postcode":"55110",
    "sg:province":"MN",
    "sg:tags":[
        "reporting"
    ],
    "wof:name":"Quality Office Services",
    "wof:placetype":"venue"
},
  "geometry": {"coordinates":[-93.001823,45.133587],"type":"Point"}
}