{
  "type": "Feature",
  "properties": {
    "iso:country":"US",
    "sg:address":"1457 W Scheffer Ave",
    "sg:city":"Saint Paul",
    "sg:classifiers":[
        {
            "category":"Organizations",
            "subcategory":"Membership Organization",
            "type":"Services"
        }
    ],
    "sg:phone":"+1 651 698 5409",
    "sg:postcode":"55116",
    "sg:province":"MN",
    "wof:name":"Sharing Life Laura Neumann",
    "wof:placetype":"venue"
},
  "geometry": {"coordinates":[-93.160191,44.92161],"type":"Point"}
}