{
  "type": "Feature",
  "properties": {
    "iso:country":"US",
    "sg:address":"1200 Shakopee Town Sq",
    "sg:city":"Shakopee",
    "sg:classifiers":[
        {
            "category":"Education",
            "subcategory":"University",
            "type":"Public Place"
        }
    ],
    "sg:phone":"+1 952 345 1200",
    "sg:postcode":"55379",
    "sg:province":"MN",
    "sg:tags":[
        "college"
    ],
    "wof:name":"Minnesota School of Business",
    "wof:placetype":"venue"
},
  "geometry": {"coordinates":[-93.55229,44.78545],"type":"Point"}
}