{
  "type": "Feature",
  "properties": {
    "iso:country":"US",
    "sg:address":"436 Bruns Ct",
    "sg:city":"Saint Paul",
    "sg:classifiers":[
        {
            "category":"Professional",
            "subcategory":"Computer Services",
            "type":"Services"
        }
    ],
    "sg:phone":"+1 651 426 3457",
    "sg:postcode":"55127",
    "sg:province":"MN",
    "sg:tags":[
        "datum"
    ],
    "wof:name":"U Succeed Corp",
    "wof:placetype":"venue"
},
  "geometry": {"coordinates":[-93.082757,45.05707],"type":"Point"}
}