{
  "type": "Feature",
  "properties": {
    "addr:full":"7011 James Ave S Minneapolis MN 55423",
    "addr:housenumber":"7011",
    "addr:postcode":"55423",
    "addr:street":"James Ave S",
    "iso:country":"US",
    "sg:address":"7011 James Ave S",
    "sg:city":"Minneapolis",
    "sg:classifiers":[
        {
            "category":"Health Services",
            "subcategory":"Doctor",
            "type":"Services"
        }
    ],
    "sg:phone":"+1 612 798 4222",
    "sg:postcode":"55423",
    "sg:province":"MN",
    "sg:tags":[
        "physician",
        "surgery",
        "oral",
        "surgeons"
    ],
    "wof:name":"Jay P Wilson",
    "wof:placetype":"venue"
},
  "geometry": {"coordinates":[-93.300949,44.876105],"type":"Point"}
}