{
  "type": "Feature",
  "properties": {
    "addr:full":"1441 Silver Lake Rd NW New Brighton MN 55112",
    "addr:housenumber":"1441",
    "addr:postcode":"55112",
    "addr:street":"Silver Lake Rd Nw",
    "iso:country":"US",
    "sg:address":"1441 Silver Lake Rd NW",
    "sg:city":"New Brighton",
    "sg:classifiers":[
        {
            "category":"Personal",
            "subcategory":"Barber",
            "type":"Services"
        }
    ],
    "sg:phone":"+1 651 633 9838",
    "sg:postcode":"55112",
    "sg:province":"MN",
    "sg:tags":[
        "shop"
    ],
    "wof:name":"Razor's Edge",
    "wof:placetype":"venue"
},
  "geometry": {"coordinates":[-93.218677,45.072555],"type":"Point"}
}