{
  "type": "Feature",
  "properties": {
    "addr:full":"538 Westwood Ln Chaska MN 55318",
    "addr:housenumber":"538",
    "addr:postcode":"55318",
    "addr:street":"Westwood Ln",
    "iso:country":"US",
    "sg:address":"538 Westwood Ln",
    "sg:city":"Chaska",
    "sg:classifiers":[
        {
            "category":"Professional",
            "type":"Services"
        }
    ],
    "sg:phone":"+1 952 448 7780",
    "sg:postcode":"55318",
    "sg:province":"MN",
    "sg:tags":[
        "establishment"
    ],
    "wof:name":"Davies & Davies",
    "wof:placetype":"venue"
},
  "geometry": {"coordinates":[-93.61472000000001,44.811157],"type":"Point"}
}