{
  "type": "Feature",
  "properties": {
    "addr:full":"1210 Norell Ave N Stillwater MN 55082",
    "addr:housenumber":"1210",
    "addr:postcode":"55082",
    "addr:street":"Norell Ave N",
    "iso:country":"US",
    "sg:address":"1210 Norell Ave N",
    "sg:city":"Stillwater",
    "sg:classifiers":[
        {
            "category":"Building & Trades",
            "subcategory":"Construction",
            "type":"Services"
        },
        {
            "category":"Home & Garden",
            "subcategory":"Furniture",
            "type":"Retail Goods"
        }
    ],
    "sg:phone":"+1 651 436 5074",
    "sg:postcode":"55082",
    "sg:province":"MN",
    "sg:tags":[
        "equipment-household",
        "maker",
        "kitchen",
        "cabinet"
    ],
    "wof:name":"Creative Kitchen Bath Inc",
    "wof:placetype":"venue"
},
  "geometry": {"coordinates":[-92.829939,44.965165],"type":"Point"}
}