{
  "type": "Feature",
  "properties": {
    "addr:full":"1939 5th St S Minneapolis MN 55454",
    "addr:housenumber":"1939",
    "addr:postcode":"55454",
    "addr:street":"5Th St S",
    "iso:country":"US",
    "sg:address":"1939 5th St S",
    "sg:city":"Minneapolis",
    "sg:classifiers":[
        {
            "category":"Restaurant",
            "type":"Food & Drink"
        }
    ],
    "sg:phone":"+1 612 239 5790",
    "sg:postcode":"55454",
    "sg:province":"MN",
    "sg:tags":[
        "african"
    ],
    "wof:name":"Afro Deli & Coffee",
    "wof:placetype":"venue"
},
  "geometry": {"coordinates":[-93.24494900000001,44.968838],"type":"Point"}
}