{
  "type": "Feature",
  "properties": {
    "addr:full":"10561 170th St S Barnesville MN 56514",
    "addr:housenumber":"10561",
    "addr:postcode":"56514",
    "addr:street":"170Th St S",
    "iso:country":"US",
    "sg:address":"10561 170th St S",
    "sg:city":"Barnesville",
    "sg:classifiers":[
        {
            "category":"Building & Trades",
            "subcategory":"Construction",
            "type":"Services"
        }
    ],
    "sg:phone":"+1 218 937 5268",
    "sg:postcode":"56514",
    "sg:province":"MN",
    "sg:tags":[
        "house"
    ],
    "wof:name":"Healds Custom Homes Inc",
    "wof:placetype":"venue"
},
  "geometry": {"coordinates":[-96.44138599999999,46.738305],"type":"Point"}
}