{
  "type": "Feature",
  "properties": {
    "addr:full":"3010 4th Ave E Shakopee MN 55379",
    "addr:housenumber":"3010",
    "addr:postcode":"55379",
    "addr:street":"4Th Ave E",
    "iso:country":"US",
    "sg:address":"3010 4th Ave E",
    "sg:city":"Shakopee",
    "sg:classifiers":[
        {
            "category":"Building & Trades",
            "subcategory":"Construction",
            "type":"Services"
        }
    ],
    "sg:phone":"+1 952 403 9100",
    "sg:postcode":"55379",
    "sg:province":"MN",
    "sg:tags":[
        "home",
        "builder",
        "general"
    ],
    "sg:website":"www.sandauconstruction.com",
    "wof:name":"Sandau Construction Company",
    "wof:placetype":"venue"
},
  "geometry": {"coordinates":[-93.476789,44.797568],"type":"Point"}
}