{
  "type": "Feature",
  "properties": {
    "iso:country":"US",
    "sg:address":"778 Lower Colonial Dr",
    "sg:city":"Saint Paul",
    "sg:classifiers":[
        {
            "category":"Professional",
            "subcategory":"Advertising",
            "type":"Services"
        }
    ],
    "sg:phone":"+1 651 457 3618",
    "sg:postcode":"55118",
    "sg:province":"MN",
    "sg:tags":[
        "mail",
        "direct"
    ],
    "wof:name":"Kennedy Sports",
    "wof:placetype":"venue"
},
  "geometry": {"coordinates":[-93.124802,44.901093],"type":"Point"}
}