{
  "type": "Feature",
  "properties": {
    "iso:country":"US",
    "sg:address":"5300 Scenic Heights Dr",
    "sg:city":"Minnetonka",
    "sg:classifiers":[
        {
            "category":"Shopping",
            "type":"Retail Goods"
        },
        {
            "category":"Retail",
            "subcategory":"Repair Shop",
            "type":"Services"
        }
    ],
    "sg:phone":"+1 763 425 6200",
    "sg:postcode":"55345",
    "sg:province":"MN",
    "sg:tags":[
        "phone",
        "retailer",
        "system",
        "merchandise"
    ],
    "wof:name":"R & L Phone Outlet",
    "wof:placetype":"venue"
},
  "geometry": {"coordinates":[-93.49312500000001,44.90448],"type":"Point"}
}