{
  "type": "Feature",
  "properties": {
    "addr:full":"4865 Miller Trunk Hwy Hermantown MN 55811",
    "addr:housenumber":"4865",
    "addr:postcode":"55811",
    "addr:street":"Miller Trunk Hwy",
    "iso:country":"US",
    "sg:address":"4865 Miller Trunk Hwy",
    "sg:city":"Hermantown",
    "sg:classifiers":[
        {
            "category":"Sports & Exercise",
            "subcategory":"Gym",
            "type":"Entertainment"
        }
    ],
    "sg:phone":"+1 218 722 5930",
    "sg:postcode":"55811",
    "sg:province":"MN",
    "sg:tags":[
        "club",
        "health",
        "studio",
        "gymnasium"
    ],
    "wof:name":"Anytime Fitness",
    "wof:placetype":"venue"
},
  "geometry": {"coordinates":[-92.18913499999999,46.823743],"type":"Point"}
}