{
  "type": "Feature",
  "properties": {
    "addr:full":"780 Dorland Rd S Saint Paul MN 55119",
    "addr:housenumber":"780",
    "addr:postcode":"55119",
    "addr:street":"Dorland Rd S",
    "iso:country":"US",
    "sg:address":"780 Dorland Rd S",
    "sg:city":"Saint Paul",
    "sg:classifiers":[
        {
            "category":"Food & Beverages",
            "subcategory":"Specialty",
            "type":"Retail Goods"
        }
    ],
    "sg:phone":"+1 651 765 9759",
    "sg:postcode":"55119",
    "sg:province":"MN",
    "wof:name":"Blue Mountain LLC",
    "wof:placetype":"venue"
},
  "geometry": {"coordinates":[-93.001749,44.917571],"type":"Point"}
}