{
  "type": "Feature",
  "properties": {
    "addr:full":"1303 Juliet Ave St Paul MN 55105",
    "addr:housenumber":"1303",
    "addr:postcode":"55105",
    "addr:street":"Juliet Ave",
    "iso:country":"US",
    "sg:address":"1303 Juliet Ave",
    "sg:city":"St Paul",
    "sg:classifiers":[
        {
            "category":"Retail",
            "subcategory":"Auto Repair",
            "type":"Services"
        }
    ],
    "sg:phone":"+1 651 699 2843",
    "sg:postcode":"55105",
    "sg:province":"MN",
    "sg:tags":[
        "automotive",
        "wrecker"
    ],
    "wof:name":"Boeckman Towing",
    "wof:placetype":"venue"
},
  "geometry": {"coordinates":[-93.156148,44.929757],"type":"Point"}
}