{
  "type": "Feature",
  "properties": {
    "iso:country":"US",
    "sg:address":"1127 Adams St NE",
    "sg:city":"Minneapolis",
    "sg:classifiers":[
        {
            "category":"Retail",
            "subcategory":"Portrait Studio",
            "type":"Services"
        }
    ],
    "sg:phone":"+1 612 331 4216",
    "sg:postcode":"55413",
    "sg:province":"MN",
    "sg:tags":[
        "photo"
    ],
    "wof:name":"Picture Them Young",
    "wof:placetype":"venue"
},
  "geometry": {"coordinates":[-93.256198,45.000613],"type":"Point"}
}