{
  "type": "Feature",
  "properties": {
    "iso:country":"US",
    "sg:address":"3537 Lismore Rd",
    "sg:city":"Duluth",
    "sg:classifiers":[
        {
            "category":"Building & Trades",
            "subcategory":"Landscaping Services",
            "type":"Services"
        }
    ],
    "sg:phone":"+1 218 721 3630",
    "sg:postcode":"55803",
    "sg:province":"MN",
    "wof:name":"P M Donaldson",
    "wof:placetype":"venue"
},
  "geometry": {"coordinates":[-92.058893,46.938102],"type":"Point"}
}