{
  "type": "Feature",
  "properties": {
    "iso:country":"US",
    "sg:address":"2233 Hamline Ave N",
    "sg:city":"St Paul",
    "sg:classifiers":[
        {
            "category":"Shopping",
            "subcategory":"Computers & Home Electronics",
            "type":"Retail Goods"
        }
    ],
    "sg:phone":"+1 651 697 0500",
    "sg:postcode":"55113",
    "sg:province":"MN",
    "sg:tags":[
        "software"
    ],
    "sg:website":"www.starconsultants.com",
    "wof:name":"System Technologies",
    "wof:placetype":"venue"
},
  "geometry": {"coordinates":[-93.156696,45.007574],"type":"Point"}
}