{
  "type": "Feature",
  "properties": {
    "iso:country":"US",
    "sg:address":"5011 Penn Ave N",
    "sg:city":"Minneapolis",
    "sg:classifiers":[
        {
            "category":"Retail",
            "subcategory":"Auto Repair",
            "type":"Services"
        }
    ],
    "sg:phone":"+1 612 720 8116",
    "sg:postcode":"55430",
    "sg:province":"MN",
    "sg:tags":[
        "wrecker"
    ],
    "wof:name":"Nate's Towing Svc Inc",
    "wof:placetype":"venue"
},
  "geometry": {"coordinates":[-93.30936800000001,45.047402],"type":"Point"}
}