{
  "type": "Feature",
  "properties": {
    "iso:country":"US",
    "sg:address":"109 Main St S",
    "sg:city":"Austin",
    "sg:classifiers":[
        {
            "category":"Professional",
            "subcategory":"Business Services",
            "type":"Services"
        }
    ],
    "sg:phone":"+1 507 434 2299",
    "sg:postcode":"55912",
    "sg:province":"MN",
    "sg:tags":[
        "employee",
        "benefit",
        "financial"
    ],
    "wof:name":"Corporate Financial Svcs Inc",
    "wof:placetype":"venue"
},
  "geometry": {"coordinates":[-92.974779,43.666505],"type":"Point"}
}