{
  "type": "Feature",
  "properties": {
    "iso:country":"US",
    "sg:address":"5249 43rd Ave S",
    "sg:city":"Minneapolis",
    "sg:classifiers":[
        {
            "category":"Education",
            "subcategory":"Junior College",
            "type":"Public Place"
        }
    ],
    "sg:phone":"+1 612 721 0469",
    "sg:postcode":"55417",
    "sg:province":"MN",
    "sg:tags":[
        "doll"
    ],
    "wof:name":"Mourning Doll Playhouse",
    "wof:placetype":"venue"
},
  "geometry": {"coordinates":[-93.21138000000001,44.908103],"type":"Point"}
}