{
  "type": "Feature",
  "properties": {
    "iso:country":"US",
    "sg:address":"6501 Broadway St NW",
    "sg:city":"Moorhead",
    "sg:classifiers":[
        {
            "category":"Professional",
            "subcategory":"Computer Services",
            "type":"Services"
        }
    ],
    "sg:phone":"+1 218 236 7572",
    "sg:postcode":"56560",
    "sg:province":"MN",
    "sg:tags":[
        "consultant",
        "network",
        "integration"
    ],
    "wof:name":"New Century Info Systems",
    "wof:placetype":"venue"
},
  "geometry": {"coordinates":[-96.789019,46.943173],"type":"Point"}
}