{
  "type": "Feature",
  "properties": {
    "addr:full":"268 S Broadway Wells MN 56097",
    "addr:housenumber":"268",
    "addr:postcode":"56097",
    "addr:street":"S Broadway",
    "iso:country":"US",
    "sg:address":"268 S Broadway",
    "sg:city":"Wells",
    "sg:classifiers":[
        {
            "category":"Professional",
            "type":"Services"
        }
    ],
    "sg:phone":"+1 507 553 5440",
    "sg:postcode":"56097",
    "sg:province":"MN",
    "wof:name":"Barr Inc",
    "wof:placetype":"venue"
},
  "geometry": {"coordinates":[-93.725562,43.742376],"type":"Point"}
}