{
  "type": "Feature",
  "properties": {
    "iso:country":"US",
    "sg:address":"4355 Peavey Rd",
    "sg:city":"Chaska",
    "sg:classifiers":[
        {
            "category":"Retail",
            "subcategory":"Auto Rental",
            "type":"Services"
        }
    ],
    "sg:phone":"+1 952 448 2266",
    "sg:postcode":"55318",
    "sg:province":"MN",
    "sg:tags":[
        "recreational",
        "leasing",
        "vehicle"
    ],
    "wof:name":"Cruise America Motorhome",
    "wof:placetype":"venue"
},
  "geometry": {"coordinates":[-93.598845,44.84105],"type":"Point"}
}