{
  "type": "Feature",
  "properties": {
    "addr:full":"3149 Nicollet Ave Minneapolis MN 55408",
    "addr:housenumber":"3149",
    "addr:postcode":"55408",
    "addr:street":"Nicollet Ave",
    "iso:country":"US",
    "sg:address":"3149 Nicollet Ave",
    "sg:city":"Minneapolis",
    "sg:classifiers":[
        {
            "category":"Food & Beverages",
            "subcategory":"Meat & Fish",
            "type":"Retail Goods"
        }
    ],
    "sg:phone":"+1 612 823 4400",
    "sg:postcode":"55408",
    "sg:province":"MN",
    "sg:tags":[
        "market"
    ],
    "wof:name":"Valeries Carniceria",
    "wof:placetype":"venue"
},
  "geometry": {"coordinates":[-93.277912,44.945233],"type":"Point"}
}