{
  "type": "Feature",
  "properties": {
    "addr:full":"816 State Hwy 16 E Preston MN 55965",
    "addr:housenumber":"816",
    "addr:postcode":"55965",
    "addr:street":"State Hwy 16 E",
    "iso:country":"US",
    "sg:address":"816 State Hwy 16 E",
    "sg:city":"Preston",
    "sg:classifiers":[
        {
            "category":"Travel",
            "subcategory":"Hotels & Motels",
            "type":"Entertainment"
        }
    ],
    "sg:phone":"+1 507 765 5390",
    "sg:postcode":"55965",
    "sg:province":"MN",
    "wof:name":"Renee's Inn",
    "wof:placetype":"venue"
},
  "geometry": {"coordinates":[-92.071687,43.673446],"type":"Point"}
}