{
  "type": "Feature",
  "properties": {
    "iso:country":"US",
    "sg:address":"4520 19th Ave NW",
    "sg:city":"Rochester",
    "sg:classifiers":[
        {
            "category":"Education",
            "subcategory":"School",
            "type":"Public Place"
        }
    ],
    "sg:phone":"+1 507 282 8280",
    "sg:postcode":"55901",
    "sg:province":"MN",
    "sg:website":"www.resurrection-wels.org",
    "wof:name":"Resurrection Lutheran School",
    "wof:placetype":"venue"
},
  "geometry": {"coordinates":[-92.492341,44.070436],"type":"Point"}
}