{
  "type": "Feature",
  "properties": {
    "iso:country":"US",
    "sg:address":"2489 Rice St",
    "sg:city":"Saint Paul",
    "sg:classifiers":[
        {
            "category":"Building & Trades",
            "subcategory":"Electrical",
            "type":"Services"
        }
    ],
    "sg:phone":"+1 651 490 1499",
    "sg:postcode":"55113",
    "sg:province":"MN",
    "sg:tags":[
        "electrical",
        "contractor"
    ],
    "wof:name":"Haakenson Electric Company",
    "wof:placetype":"venue"
},
  "geometry": {"coordinates":[-93.106104,45.015895],"type":"Point"}
}