{
  "type": "Feature",
  "properties": {
    "iso:country":"US",
    "sg:address":"1135 Park Ave",
    "sg:city":"Saint Paul",
    "sg:classifiers":[
        {
            "category":"Professional",
            "subcategory":"Business Services",
            "type":"Services"
        }
    ],
    "sg:phone":"+1 651 429 7920",
    "sg:postcode":"55115",
    "sg:province":"MN",
    "wof:name":"Woodbury Business Plaza LLC",
    "wof:placetype":"venue"
},
  "geometry": {"coordinates":[-92.959771,45.070195],"type":"Point"}
}