{
  "type": "Feature",
  "properties": {
    "iso:country":"US",
    "sg:address":"5701 Shingle Creek Pkwy",
    "sg:city":"Brooklyn Center",
    "sg:classifiers":[
        {
            "category":"Professional",
            "subcategory":"Management & Consulting",
            "type":"Services"
        }
    ],
    "sg:phone":"+1 763 585 4545",
    "sg:postcode":"55430",
    "sg:province":"MN",
    "sg:tags":[
        "health",
        "care"
    ],
    "sg:website":"www.nationscarelink.com",
    "wof:name":"Nations Care Link",
    "wof:placetype":"venue"
},
  "geometry": {"coordinates":[-93.31008799999999,45.064575],"type":"Point"}
}