{
  "type": "Feature",
  "properties": {
    "addr:full":"1 Veterans Dr Rm 131 Minneapolis MN 55417",
    "addr:housenumber":"1;131",
    "addr:postcode":"55417",
    "addr:street":"Veterans Dr Rm",
    "iso:country":"US",
    "sg:address":"1 Veterans Dr Rm 131",
    "sg:city":"Minneapolis",
    "sg:classifiers":[
        {
            "category":"Organizations",
            "subcategory":"Membership Organization",
            "type":"Services"
        }
    ],
    "sg:phone":"+1 612 725 2263",
    "sg:postcode":"55417",
    "sg:province":"MN",
    "sg:tags":[
        "military",
        "veteran"
    ],
    "sg:website":"http://www.mscpva.org",
    "wof:name":"Minneplis Prlyzed Vterans Amer",
    "wof:placetype":"venue"
},
  "geometry": {"coordinates":[-93.20388800000001,44.901932],"type":"Point"}
}