{
  "type": "Feature",
  "properties": {
    "iso:country":"US",
    "sg:address":"10603 Hidden Dr SE",
    "sg:city":"Osakis",
    "sg:classifiers":[
        {
            "category":"Farming",
            "subcategory":"Livestock Farm",
            "type":"Manufacturing & Wholesale Goods"
        }
    ],
    "sg:phone":"+1 320 859 3900",
    "sg:postcode":"56360",
    "sg:province":"MN",
    "sg:tags":[
        "beef",
        "f",
        "corn",
        "crop",
        "field",
        "soybean",
        "cattle",
        "feedlot"
    ],
    "wof:name":"Gregg Thompson",
    "wof:placetype":"venue"
},
  "geometry": {"coordinates":[-95.23440600000001,45.86498],"type":"Point"}
}