{
  "type": "Feature",
  "properties": {
    "addr:full":"7545 Emerson Ave S Minneapolis MN 55423",
    "addr:housenumber":"7545",
    "addr:postcode":"55423",
    "addr:street":"Emerson Ave S",
    "iso:country":"US",
    "sg:address":"7545 Emerson Ave S",
    "sg:city":"Minneapolis",
    "sg:classifiers":[
        {
            "category":"Manufacturing",
            "subcategory":"Wood Products",
            "type":"Manufacturing & Wholesale Goods"
        }
    ],
    "sg:phone":"+1 612 861 4616",
    "sg:postcode":"55423",
    "sg:province":"MN",
    "sg:tags":[
        "mfg"
    ],
    "wof:name":"Marvs Woodworking",
    "wof:placetype":"venue"
},
  "geometry": {"coordinates":[-93.29464299999999,44.866371],"type":"Point"}
}