{
  "type": "Feature",
  "properties": {
    "iso:country":"US",
    "sg:address":"1300 Godward St NE",
    "sg:city":"Minneapolis",
    "sg:classifiers":[
        {
            "category":"Communications",
            "type":"Services"
        }
    ],
    "sg:phone":"+1 612 617 5700",
    "sg:postcode":"55413",
    "sg:province":"MN",
    "sg:tags":[
        "web",
        "design"
    ],
    "wof:name":"Avenet Web Solutions",
    "wof:placetype":"venue"
},
  "geometry": {"coordinates":[-93.21424399999999,45.000287],"type":"Point"}
}