{
  "type": "Feature",
  "properties": {
    "addr:full":"57890 280th St Brownsdale MN 55918",
    "addr:housenumber":"57890",
    "addr:postcode":"55918",
    "addr:street":"280Th St",
    "iso:country":"US",
    "sg:address":"57890 280th St",
    "sg:city":"Brownsdale",
    "sg:classifiers":[
        {
            "category":"Organizations",
            "subcategory":"Membership Organization",
            "type":"Services"
        }
    ],
    "sg:phone":"+1 507 567 2438",
    "sg:postcode":"55918",
    "sg:province":"MN",
    "wof:name":"Womens International Bowl",
    "wof:placetype":"venue"
},
  "geometry": {"coordinates":[-92.871151,43.761437],"type":"Point"}
}