{
  "type": "Feature",
  "properties": {
    "addr:full":"2525 Chicago Ave S Minneapolis MN 55404",
    "addr:housenumber":"2525",
    "addr:postcode":"55404",
    "addr:street":"Chicago Ave S",
    "iso:country":"US",
    "sg:address":"2525 Chicago Ave S",
    "sg:city":"Minneapolis",
    "sg:classifiers":[
        {
            "category":"Health Services",
            "subcategory":"Doctor",
            "type":"Services"
        }
    ],
    "sg:phone":"+1 612 813 5940",
    "sg:postcode":"55404",
    "sg:province":"MN",
    "sg:tags":[
        "clinic"
    ],
    "wof:name":"Park Nicollet Clinic",
    "wof:placetype":"venue"
},
  "geometry": {"coordinates":[-93.26248699999999,44.955963],"type":"Point"}
}