{
  "type": "Feature",
  "properties": {
    "iso:country":"US",
    "sg:address":"5810 Nicollet Ave",
    "sg:city":"Minneapolis",
    "sg:classifiers":[
        {
            "category":"Health Services",
            "subcategory":"Chiropractor",
            "type":"Services"
        }
    ],
    "sg:phone":"+1 612 861 2121",
    "sg:postcode":"55419",
    "sg:province":"MN",
    "sg:tags":[
        "chiropractic"
    ],
    "wof:name":"Roderick Ecklund",
    "wof:placetype":"venue"
},
  "geometry": {"coordinates":[-93.27813,44.897507],"type":"Point"}
}