{
  "type": "Feature",
  "properties": {
    "addr:full":"302 3rd Ave SE Fairfax MN 55332",
    "addr:housenumber":"302",
    "addr:postcode":"55332",
    "addr:street":"3Rd Ave Se",
    "iso:country":"US",
    "sg:address":"302 3rd Ave SE",
    "sg:city":"Fairfax",
    "sg:classifiers":[
        {
            "category":"Government",
            "subcategory":"Office",
            "type":"Public Place"
        }
    ],
    "sg:phone":"+1 507 426 7864",
    "sg:postcode":"55332",
    "sg:province":"MN",
    "sg:tags":[
        "village"
    ],
    "wof:name":"Fairfax City Office",
    "wof:placetype":"venue"
},
  "geometry": {"coordinates":[-94.71426599999999,44.525894],"type":"Point"}
}