{
  "type": "Feature",
  "properties": {
    "addr:full":"110 Division St Waite Park MN 56387",
    "addr:housenumber":"110",
    "addr:postcode":"56387",
    "addr:street":"Division St;Park",
    "iso:country":"US",
    "sg:address":"110 Division St",
    "sg:city":"Waite Park",
    "sg:classifiers":[
        {
            "category":"Real Estate",
            "subcategory":"Real Estate Agent",
            "type":"Services"
        }
    ],
    "sg:phone":"+1 320 420 6187",
    "sg:postcode":"56387",
    "sg:province":"MN",
    "wof:name":"Carrie Hunter",
    "wof:placetype":"venue"
},
  "geometry": {"coordinates":[-94.21873100000001,45.553413],"type":"Point"}
}