{
  "type": "Feature",
  "properties": {
    "addr:full":"1951 48th Ave NE Willmar MN 56201",
    "addr:housenumber":"1951",
    "addr:postcode":"56201",
    "addr:street":"48Th Ave Ne",
    "iso:country":"US",
    "sg:address":"1951 48th Ave NE",
    "sg:city":"Willmar",
    "sg:classifiers":[
        {
            "category":"Retail",
            "subcategory":"Auto Repair",
            "type":"Services"
        }
    ],
    "sg:phone":"+1 320 235 9661",
    "sg:postcode":"56201",
    "sg:province":"MN",
    "sg:tags":[
        "repairing",
        "automobile"
    ],
    "wof:name":"Jergenson Auto Repair & Tires",
    "wof:placetype":"venue"
},
  "geometry": {"coordinates":[-95.01563400000001,45.171315],"type":"Point"}
}