{
  "type": "Feature",
  "properties": {
    "iso:country":"US",
    "sg:address":"549 W Laurel Ave",
    "sg:city":"Saint Paul",
    "sg:classifiers":[
        {
            "category":"Professional",
            "type":"Services"
        }
    ],
    "sg:phone":"+1 651 222 5084",
    "sg:postcode":"55102",
    "sg:province":"MN",
    "wof:name":"Celeste R Raspanti PHD",
    "wof:placetype":"venue"
},
  "geometry": {"coordinates":[-93.122208,44.945517],"type":"Point"}
}