{
  "type": "Feature",
  "properties": {
    "addr:full":"2344 Nicollet Ave Minneapolis MN 55404",
    "addr:housenumber":"2344",
    "addr:postcode":"55404",
    "addr:street":"Nicollet Ave",
    "iso:country":"US",
    "sg:address":"2344 Nicollet Ave",
    "sg:city":"Minneapolis",
    "sg:classifiers":[
        {
            "category":"Professional",
            "subcategory":"Computer Services",
            "type":"Services"
        }
    ],
    "sg:phone":"+1 612 874 6823",
    "sg:postcode":"55404",
    "sg:province":"MN",
    "sg:tags":[
        "related"
    ],
    "wof:name":"Sound Choice-Sound Internet",
    "wof:placetype":"venue"
},
  "geometry": {"coordinates":[-93.277912,44.960439],"type":"Point"}
}