{
  "type": "Feature",
  "properties": {
    "addr:full":"255 W 5th St Rush City MN 55069",
    "addr:housenumber":"255",
    "addr:postcode":"55069",
    "addr:street":"W 5Th St",
    "iso:country":"US",
    "sg:address":"255 W 5th St",
    "sg:city":"Rush City",
    "sg:classifiers":[
        {
            "category":"Food & Beverages",
            "subcategory":"Specialty",
            "type":"Retail Goods"
        }
    ],
    "sg:phone":"+1 320 358 0920",
    "sg:postcode":"55069",
    "sg:province":"MN",
    "sg:tags":[
        "tea",
        "coffee"
    ],
    "wof:name":"Daily Grind Coffee House",
    "wof:placetype":"venue"
},
  "geometry": {"coordinates":[-92.964129,45.68411],"type":"Point"}
}