{
  "type": "Feature",
  "properties": {
    "iso:country":"US",
    "sg:address":"1091 State Hwy 15",
    "sg:city":"Hutchinson",
    "sg:classifiers":[
        {
            "category":"Health Services",
            "subcategory":"Health Practitioner",
            "type":"Services"
        }
    ],
    "sg:phone":"+1 320 864 3227",
    "sg:postcode":"55350",
    "sg:province":"MN",
    "sg:tags":[
        "farm",
        "field",
        "crop",
        "animal"
    ],
    "wof:name":"Mark R Smith PHD",
    "wof:placetype":"venue"
},
  "geometry": {"coordinates":[-94.37548,44.875325],"type":"Point"}
}