{
  "type": "Feature",
  "properties": {
    "iso:country":"US",
    "sg:address":"412 4th St NE",
    "sg:city":"Little Falls",
    "sg:phone":"+1 320 632 8147",
    "sg:postcode":"56345",
    "sg:province":"MN",
    "sg:tags":[
        "farm",
        "soybean"
    ],
    "wof:name":"Louis Filippi",
    "wof:placetype":"venue"
},
  "geometry": {"coordinates":[-94.356646,45.979866],"type":"Point"}
}