{
  "type": "Feature",
  "properties": {
    "iso:country":"US",
    "sg:address":"7671 Teal Rd",
    "sg:city":"Saint Paul",
    "sg:classifiers":[
        {
            "category":"Personal",
            "type":"Services"
        }
    ],
    "sg:phone":"+1 651 714 8954",
    "sg:postcode":"55125",
    "sg:province":"MN",
    "wof:name":"Jeannes Massage & Bodyworks",
    "wof:placetype":"venue"
},
  "geometry": {"coordinates":[-92.95120900000001,44.935719],"type":"Point"}
}