{
  "type": "Feature",
  "properties": {
    "iso:country":"US",
    "sg:address":"102 Broadway Ave",
    "sg:city":"Elizabeth",
    "sg:classifiers":[
        {
            "category":"Organizations",
            "subcategory":"Religious Organization",
            "type":"Services"
        }
    ],
    "sg:phone":"+1 218 739 2538",
    "sg:postcode":"56533",
    "sg:province":"MN",
    "sg:tags":[
        "church"
    ],
    "wof:name":"St John Lutheran Church",
    "wof:placetype":"venue"
},
  "geometry": {"coordinates":[-96.130321,46.379882],"type":"Point"}
}