{
  "type": "Feature",
  "properties": {
    "addr:full":"116 Co Hwy 34 Jackson MN 56143",
    "addr:housenumber":"116",
    "addr:postcode":"56143",
    "addr:street":"Co Hwy 34",
    "iso:country":"US",
    "sg:address":"116 Co Hwy 34",
    "sg:city":"Jackson",
    "sg:classifiers":[
        {
            "category":"Health Services",
            "subcategory":"Health Practitioner",
            "type":"Services"
        }
    ],
    "sg:phone":"+1 507 847 5952",
    "sg:postcode":"56143",
    "sg:province":"MN",
    "sg:tags":[
        "psychologist"
    ],
    "wof:name":"Jackson Center-Psychological",
    "wof:placetype":"venue"
},
  "geometry": {"coordinates":[-94.988519,43.619001],"type":"Point"}
}