{
  "type": "Feature",
  "properties": {
    "iso:country":"US",
    "sg:address":"18105 17th Ave N",
    "sg:city":"Minneapolis",
    "sg:classifiers":[
        {
            "category":"Building & Trades",
            "subcategory":"Construction",
            "type":"Services"
        }
    ],
    "sg:phone":"+1 763 205 1181",
    "sg:postcode":"55447",
    "sg:province":"MN",
    "sg:tags":[
        "hanging",
        "contractor"
    ],
    "wof:name":"Profesional Image Painting",
    "wof:placetype":"venue"
},
  "geometry": {"coordinates":[-93.508917,44.996734],"type":"Point"}
}