{
  "type": "Feature",
  "properties": {
    "addr:full":"201 1st Ave S Perham MN 56573",
    "addr:housenumber":"201",
    "addr:postcode":"56573",
    "addr:street":"1St Ave S Perham",
    "iso:country":"US",
    "sg:address":"201 1st Ave S",
    "sg:city":"Perham",
    "sg:classifiers":[
        {
            "category":"Place Of Worship",
            "subcategory":"Church",
            "type":"Public Place"
        },
        {
            "category":"Place Of Worship",
            "type":"Public Place"
        }
    ],
    "sg:phone":"+1 218 346 7203",
    "sg:postcode":"56573",
    "sg:province":"MN",
    "sg:tags":[
        "lutheran",
        "america",
        "churches-lutheran",
        "churches-lutheran-evangelical"
    ],
    "wof:name":"New Creations Lutheran Church",
    "wof:placetype":"venue"
},
  "geometry": {"coordinates":[-95.573853,46.593472],"type":"Point"}
}