{
  "type": "Feature",
  "properties": {
    "addr:full":"1505 9th St S Virginia MN 55792",
    "addr:housenumber":"1505",
    "addr:postcode":"55792",
    "addr:street":"9Th St S",
    "iso:country":"US",
    "sg:address":"1505 9th St S",
    "sg:city":"Virginia",
    "sg:classifiers":[
        {
            "category":"Building & Trades",
            "subcategory":"Construction",
            "type":"Services"
        }
    ],
    "sg:phone":"+1 218 749 6650",
    "sg:postcode":"55792",
    "sg:province":"MN",
    "sg:tags":[
        "landfill",
        "contractor"
    ],
    "wof:name":"R & M Mesabi Construction Inc",
    "wof:placetype":"venue"
},
  "geometry": {"coordinates":[-92.55945,47.51649],"type":"Point"}
}