{
  "type": "Feature",
  "properties": {
    "iso:country":"US",
    "sg:address":"2965 Kilmer Ln N",
    "sg:city":"Minneapolis",
    "sg:classifiers":[
        {
            "category":"Professional",
            "subcategory":"Management & Consulting",
            "type":"Services"
        }
    ],
    "sg:phone":"+1 763 545 2574",
    "sg:postcode":"55441",
    "sg:province":"MN",
    "wof:name":"Sava Financial Incorporated",
    "wof:placetype":"venue"
},
  "geometry": {"coordinates":[-93.40223400000001,45.012658],"type":"Point"}
}