{
  "type": "Feature",
  "properties": {
    "addr:full":"211 Division St S Northfield MN 55057",
    "addr:housenumber":"211",
    "addr:postcode":"55057",
    "addr:street":"Division St S",
    "iso:country":"US",
    "sg:address":"211 Division St S",
    "sg:city":"Northfield",
    "sg:classifiers":[
        {
            "category":"Real Estate",
            "subcategory":"Architect",
            "type":"Services"
        }
    ],
    "sg:phone":"+1 507 645 5027",
    "sg:postcode":"55057",
    "sg:province":"MN",
    "sg:tags":[
        "commercial",
        "design",
        "architectural"
    ],
    "sg:website":"www.nobledesignstudio.com",
    "wof:name":"Noble Design Studio",
    "wof:placetype":"venue"
},
  "geometry": {"coordinates":[-93.158891,44.458373],"type":"Point"}
}