{
  "type": "Feature",
  "properties": {
    "addr:full":"24000 State Hwy 7 Excelsior MN 55331",
    "addr:housenumber":"24000",
    "addr:postcode":"55331",
    "addr:street":"State Hwy 7",
    "iso:country":"US",
    "sg:address":"24000 State Hwy 7",
    "sg:city":"Excelsior",
    "sg:classifiers":[
        {
            "category":"Health Services",
            "subcategory":"Doctor",
            "type":"Services"
        }
    ],
    "sg:phone":"+1 952 474 4123",
    "sg:postcode":"55331",
    "sg:province":"MN",
    "sg:tags":[
        "dentist"
    ],
    "wof:name":"Kelly Bosworth DDS",
    "wof:placetype":"venue"
},
  "geometry": {"coordinates":[-93.581433,44.8918],"type":"Point"}
}