{
  "type": "Feature",
  "properties": {
    "iso:country":"US",
    "sg:address":"208 Rum River Dr N",
    "sg:city":"Princeton",
    "sg:classifiers":[
        {
            "category":"Manufacturing",
            "subcategory":"Printing",
            "type":"Manufacturing & Wholesale Goods"
        }
    ],
    "sg:phone":"+1 763 389 1222",
    "sg:postcode":"55371",
    "sg:province":"MN",
    "sg:tags":[
        "newspaper"
    ],
    "sg:website":"www.hometownsource.com",
    "wof:name":"Princeton Union Eagle",
    "wof:placetype":"venue"
},
  "geometry": {"coordinates":[-93.58004200000001,45.571669],"type":"Point"}
}