{
  "type": "Feature",
  "properties": {
    "iso:country":"US",
    "sg:address":"674 W 92nd St",
    "sg:city":"Minneapolis",
    "sg:classifiers":[
        {
            "category":"Building & Trades",
            "subcategory":"Construction",
            "type":"Services"
        }
    ],
    "sg:phone":"+1 952 345 6647",
    "sg:postcode":"55420",
    "sg:province":"MN",
    "sg:tags":[
        "carpentry",
        "contractor"
    ],
    "wof:name":"J P Woodworks",
    "wof:placetype":"venue"
},
  "geometry": {"coordinates":[-93.28764099999999,44.837187],"type":"Point"}
}