{
  "type": "Feature",
  "properties": {
    "iso:country":"US",
    "sg:address":"810 E Lake St",
    "sg:city":"Minneapolis",
    "sg:classifiers":[
        {
            "category":"Shopping",
            "subcategory":"Beauty & Cosmetics",
            "type":"Retail Goods"
        }
    ],
    "sg:phone":"+1 612 822 0096",
    "sg:postcode":"55407",
    "sg:province":"MN",
    "sg:tags":[
        "merchandise"
    ],
    "wof:name":"Variety Beauty Supply",
    "wof:placetype":"venue"
},
  "geometry": {"coordinates":[-93.261476,44.948433],"type":"Point"}
}