{
  "type": "Feature",
  "properties": {
    "iso:country":"US",
    "sg:address":"14021 Minnehaha Pl",
    "sg:city":"Wayzata",
    "sg:classifiers":[
        {
            "category":"Manufacturing",
            "subcategory":"Printing",
            "type":"Manufacturing & Wholesale Goods"
        }
    ],
    "sg:phone":"+1 952 939 0188",
    "sg:postcode":"55391",
    "sg:province":"MN",
    "sg:tags":[
        "direct",
        "mail",
        "advertising",
        "publishing"
    ],
    "wof:name":"Dolan Media Company",
    "wof:placetype":"venue"
},
  "geometry": {"coordinates":[-93.459103,44.94537],"type":"Point"}
}