{
  "type": "Feature",
  "properties": {
    "iso:country":"US",
    "sg:address":"2075 Daniels St",
    "sg:city":"Long Lake",
    "sg:classifiers":[
        {
            "category":"Recreation",
            "type":"Entertainment"
        }
    ],
    "sg:phone":"+1 952 473 4266",
    "sg:postcode":"55356",
    "sg:province":"MN",
    "sg:tags":[
        "diving",
        "instruction"
    ],
    "wof:name":"Underwater Schools Of America",
    "wof:placetype":"venue"
},
  "geometry": {"coordinates":[-93.57572,44.986631],"type":"Point"}
}