{
  "type": "Feature",
  "properties": {
    "addr:full":"2340 Co Rd 136 Saint Cloud MN 56301",
    "addr:housenumber":"2340;136",
    "addr:postcode":"56301",
    "addr:street":"Co Rd",
    "iso:country":"US",
    "sg:address":"2340 Co Rd 136",
    "sg:city":"Saint Cloud",
    "sg:classifiers":[
        {
            "category":"Travel",
            "subcategory":"Hotels & Motels",
            "type":"Entertainment"
        }
    ],
    "sg:phone":"+1 320 230 2404",
    "sg:postcode":"56301",
    "sg:province":"MN",
    "wof:name":"Morning Star Inn",
    "wof:placetype":"venue"
},
  "geometry": {"coordinates":[-94.193262,45.533131],"type":"Point"}
}