{
  "type": "Feature",
  "properties": {
    "iso:country":"US",
    "sg:address":"938 N Hering St",
    "sg:city":"Appleton",
    "sg:classifiers":[
        {
            "category":"Professional",
            "type":"Services"
        }
    ],
    "sg:phone":"+1 320 289 2327",
    "sg:postcode":"56208",
    "sg:province":"MN",
    "sg:tags":[
        "establishment"
    ],
    "wof:name":"Bader Construction",
    "wof:placetype":"venue"
},
  "geometry": {"coordinates":[-96.017346,45.209212],"type":"Point"}
}