{
  "type": "Feature",
  "properties": {
    "addr:full":"18582 Battle River Rd NE Kelliher MN 56650",
    "addr:housenumber":"18582",
    "addr:postcode":"56650",
    "addr:street":"Battle River Rd Ne",
    "iso:country":"US",
    "sg:address":"18582 Battle River Rd NE",
    "sg:city":"Kelliher",
    "sg:classifiers":[
        {
            "category":"Manufacturing",
            "subcategory":"Buildings",
            "type":"Manufacturing & Wholesale Goods"
        }
    ],
    "sg:phone":"+1 218 647 8373",
    "sg:postcode":"56650",
    "sg:province":"MN",
    "sg:tags":[
        "home",
        "log",
        "cabin"
    ],
    "wof:name":"Heim Hand-Crafted Log Homes",
    "wof:placetype":"venue"
},
  "geometry": {"coordinates":[-94.615865,47.96842],"type":"Point"}
}