{
  "type": "Feature",
  "properties": {
    "iso:country":"US",
    "sg:address":"12 N Oaks Rd",
    "sg:city":"North Oaks",
    "sg:classifiers":[
        {
            "category":"Travel",
            "subcategory":"Travel Agent",
            "type":"Entertainment"
        }
    ],
    "sg:phone":"+1 651 483 0221",
    "sg:postcode":"55127",
    "sg:province":"MN",
    "sg:tags":[
        "tours",
        "promoter"
    ],
    "wof:name":"Creative Tours",
    "wof:placetype":"venue"
},
  "geometry": {"coordinates":[-93.07661299999999,45.092447],"type":"Point"}
}