{
  "type": "Feature",
  "properties": {
    "addr:full":"124 Main St Sabin MN 56580",
    "addr:housenumber":"124",
    "addr:postcode":"56580",
    "addr:street":"Main St",
    "iso:country":"US",
    "sg:address":"124 Main St",
    "sg:city":"Sabin",
    "sg:classifiers":[
        {
            "category":"Building & Trades",
            "subcategory":"Construction",
            "type":"Services"
        }
    ],
    "sg:phone":"+1 218 789 7608",
    "sg:postcode":"56580",
    "sg:province":"MN",
    "sg:tags":[
        "concrete",
        "contractor"
    ],
    "wof:name":"Custom Concrete-Fargo",
    "wof:placetype":"venue"
},
  "geometry": {"coordinates":[-96.651703,46.777881],"type":"Point"}
}