{
  "type": "Feature",
  "properties": {
    "iso:country":"US",
    "sg:address":"642 11th Ave N",
    "sg:city":"South Saint Paul",
    "sg:classifiers":[
        {
            "category":"Building & Trades",
            "subcategory":"Construction",
            "type":"Services"
        }
    ],
    "sg:phone":"+1 651 455 1021",
    "sg:postcode":"55075",
    "sg:province":"MN",
    "sg:tags":[
        "floor",
        "laying",
        "contractor"
    ],
    "wof:name":"Woodchuck Flooring",
    "wof:placetype":"venue"
},
  "geometry": {"coordinates":[-93.047465,44.900765],"type":"Point"}
}