{
  "type": "Feature",
  "properties": {
    "addr:full":"14040 State Hwy 30 New Richland MN 56072",
    "addr:housenumber":"14040",
    "addr:postcode":"56072",
    "addr:street":"State Hwy 30 New",
    "iso:country":"US",
    "sg:address":"14040 State Hwy 30",
    "sg:city":"New Richland",
    "sg:classifiers":[
        {
            "category":"Autos & Motor Vehicles",
            "subcategory":"Automobile Sales",
            "type":"Retail Goods"
        }
    ],
    "sg:phone":"+1 507 465 9949",
    "sg:postcode":"56072",
    "sg:province":"MN",
    "sg:tags":[
        "car",
        "dealer"
    ],
    "wof:name":"Jim's Auto Sales",
    "wof:placetype":"venue"
},
  "geometry": {"coordinates":[-93.4781,43.891698],"type":"Point"}
}