{
  "type": "Feature",
  "properties": {
    "addr:full":"32733 Co Rd 13 Westbrook MN 56183",
    "addr:housenumber":"32733;13",
    "addr:postcode":"56183",
    "addr:street":"Co Rd",
    "iso:country":"US",
    "sg:address":"32733 Co Rd 13",
    "sg:city":"Westbrook",
    "sg:classifiers":[
        {
            "category":"Farming",
            "subcategory":"Livestock Farm",
            "type":"Manufacturing & Wholesale Goods"
        }
    ],
    "sg:phone":"+1 507 274 5936",
    "sg:postcode":"56183",
    "sg:province":"MN",
    "sg:tags":[
        "hog",
        "or",
        "feedlot"
    ],
    "wof:name":"Ronald Horkey",
    "wof:placetype":"venue"
},
  "geometry": {"coordinates":[-95.430075,43.948836],"type":"Point"}
}