{
  "type": "Feature",
  "properties": {
    "addr:full":"1749 Lexington Ave N St Paul MN 55113",
    "addr:housenumber":"1749",
    "addr:postcode":"55113",
    "addr:street":"Lexington Ave N",
    "iso:country":"US",
    "sg:address":"1749 Lexington Ave N",
    "sg:city":"St Paul",
    "sg:classifiers":[
        {
            "category":"Personal",
            "subcategory":"Beauty Salon",
            "type":"Services"
        }
    ],
    "sg:phone":"+1 651 487 7997",
    "sg:postcode":"55113",
    "sg:province":"MN",
    "sg:tags":[
        "shop",
        "manicuring"
    ],
    "wof:name":"Hollywood Nails",
    "wof:placetype":"venue"
},
  "geometry": {"coordinates":[-93.146507,44.994706],"type":"Point"}
}