{
  "type": "Feature",
  "properties": {
    "iso:country":"US",
    "sg:address":"3340 Gorham Ave",
    "sg:city":"Minneapolis",
    "sg:classifiers":[
        {
            "category":"Wholesale",
            "subcategory":"Hardware",
            "type":"Manufacturing & Wholesale Goods"
        }
    ],
    "sg:phone":"+1 952 920 0131",
    "sg:postcode":"55426",
    "sg:province":"MN",
    "sg:tags":[
        "control",
        "air",
        "refrigeration",
        "conditioning",
        "heating"
    ],
    "sg:website":"www.minvalco.com",
    "wof:name":"Minvalco Inc",
    "wof:placetype":"venue"
},
  "geometry": {"coordinates":[-93.368499,44.941548],"type":"Point"}
}