{
  "type": "Feature",
  "properties": {
    "iso:country":"US",
    "sg:address":"16020 Woodland Curv",
    "sg:city":"Minnetonka",
    "sg:classifiers":[
        {
            "category":"Communications",
            "subcategory":"Film & Video Production",
            "type":"Services"
        }
    ],
    "sg:phone":"+1 612 799 4000",
    "sg:postcode":"55345",
    "sg:province":"MN",
    "sg:tags":[
        "photographer",
        "aerial"
    ],
    "wof:name":"Peterson Aviation Inc",
    "wof:placetype":"venue"
},
  "geometry": {"coordinates":[-93.484173,44.917356],"type":"Point"}
}