{
  "type": "Feature",
  "properties": {
    "addr:full":"12940 Harriet Ave S Ste 120 Burnsville MN 55337",
    "addr:housenumber":"12940",
    "addr:postcode":"55337",
    "addr:street":"Harriet Ave S Ste 120",
    "iso:country":"US",
    "sg:address":"12940 Harriet Ave S Ste 120",
    "sg:city":"Burnsville",
    "sg:classifiers":[
        {
            "category":"Building & Trades",
            "subcategory":"Construction",
            "type":"Services"
        }
    ],
    "sg:phone":"+1 952 808 9300",
    "sg:postcode":"55337",
    "sg:province":"MN",
    "sg:tags":[
        "contractor"
    ],
    "wof:name":"Gen Con Construction",
    "wof:placetype":"venue"
},
  "geometry": {"coordinates":[-93.285715,44.769047],"type":"Point"}
}