{
  "type": "Feature",
  "properties": {
    "addr:full":"2365 Queens Dr Saint Paul MN 55125",
    "addr:housenumber":"2365",
    "addr:postcode":"55125",
    "addr:street":"Queens Dr",
    "iso:country":"US",
    "sg:address":"2365 Queens Dr",
    "sg:city":"Saint Paul",
    "sg:classifiers":[
        {
            "category":"Autos & Motor Vehicles",
            "subcategory":"Auto Supplies",
            "type":"Retail Goods"
        }
    ],
    "sg:phone":"+1 651 738 8513",
    "sg:postcode":"55125",
    "sg:province":"MN",
    "sg:tags":[
        "automobile",
        "parts"
    ],
    "wof:name":"Classic Auto Parts Of America",
    "wof:placetype":"venue"
},
  "geometry": {"coordinates":[-92.95869399999999,44.914887],"type":"Point"}
}