{
  "type": "Feature",
  "properties": {
    "addr:full":"50 S 5 St Minneapolis MN 55401",
    "addr:housenumber":"50;5",
    "addr:postcode":"55401",
    "addr:street":"S",
    "iso:country":"US",
    "sg:address":"50 S 5 St",
    "sg:city":"Minneapolis",
    "sg:classifiers":[
        {
            "category":"Real Estate",
            "subcategory":"Real Estate Services",
            "type":"Services"
        }
    ],
    "sg:phone":"+1 612 313 2500",
    "sg:postcode":"55401",
    "sg:province":"MN",
    "wof:name":"Capital Real Estate",
    "wof:placetype":"venue"
},
  "geometry": {"coordinates":[-93.270073,44.978596],"type":"Point"}
}