{
  "type": "Feature",
  "properties": {
    "addr:full":"1954 University Ave W Saint Paul MN 55104",
    "addr:housenumber":"1954",
    "addr:postcode":"55104",
    "addr:street":"University Ave W",
    "iso:country":"US",
    "sg:address":"1954 University Ave W",
    "sg:city":"Saint Paul",
    "sg:classifiers":[
        {
            "category":"Social Services",
            "type":"Services"
        }
    ],
    "sg:phone":"+1 651 917 0093",
    "sg:postcode":"55104",
    "sg:province":"MN",
    "sg:tags":[
        "association"
    ],
    "wof:name":"Admission Possible",
    "wof:placetype":"venue"
},
  "geometry": {"coordinates":[-93.18082200000001,44.956916],"type":"Point"}
}