{
  "type": "Feature",
  "properties": {
    "iso:country":"US",
    "sg:address":"108 West 98th Street",
    "sg:city":"Minneapolis",
    "sg:classifiers":[
        {
            "category":"Shopping",
            "subcategory":"Florist",
            "type":"Retail Goods"
        }
    ],
    "sg:phone":"+1 800 253 0638",
    "sg:postcode":"55420",
    "sg:province":"MN",
    "sg:website":"www.carrieresfloral.com",
    "wof:name":"Carriere's Floral & Gift",
    "wof:placetype":"venue"
},
  "geometry": {"coordinates":[-93.280694,44.826804],"type":"Point"}
}