{
  "type": "Feature",
  "properties": {
    "addr:full":"6978 10th Ave SW Rochester MN 55902",
    "addr:housenumber":"6978",
    "addr:postcode":"55902",
    "addr:street":"10Th Ave Sw",
    "iso:country":"US",
    "sg:address":"6978 10th Ave SW",
    "sg:city":"Rochester",
    "sg:classifiers":[
        {
            "category":"Wholesale",
            "subcategory":"Machinery & Supplies",
            "type":"Manufacturing & Wholesale Goods"
        }
    ],
    "sg:phone":"+1 507 292 1003",
    "sg:postcode":"55902",
    "sg:province":"MN",
    "sg:tags":[
        "trailer"
    ],
    "wof:name":"Valley Featherlight",
    "wof:placetype":"venue"
},
  "geometry": {"coordinates":[-92.475979,43.925234],"type":"Point"}
}