{
  "type": "Feature",
  "properties": {
    "iso:country":"US",
    "sg:address":"23136 Co Rd 24",
    "sg:city":"West Concord",
    "sg:classifiers":[
        {
            "category":"Organizations",
            "subcategory":"Religious Organization",
            "type":"Services"
        }
    ],
    "sg:phone":"+1 507 527 2622",
    "sg:postcode":"55985",
    "sg:province":"MN",
    "sg:tags":[
        "church"
    ],
    "wof:name":"Zwingli United Church-Christ",
    "wof:placetype":"venue"
},
  "geometry": {"coordinates":[-92.777006,44.163681],"type":"Point"}
}