{
  "type": "Feature",
  "properties": {
    "iso:country":"US",
    "sg:address":"1563 Como Ave",
    "sg:city":"Saint Paul",
    "sg:classifiers":[
        {
            "category":"Professional",
            "subcategory":"Employment Agencies",
            "type":"Services"
        }
    ],
    "sg:phone":"+1 651 641 1851",
    "sg:postcode":"55108",
    "sg:province":"MN",
    "wof:name":"Flexshifts Services Inc",
    "wof:placetype":"venue"
},
  "geometry": {"coordinates":[-93.16562,44.977507],"type":"Point"}
}