{
  "type": "Feature",
  "properties": {
    "addr:full":"1350 Wayzata Blvd E Wayzata MN 55391",
    "addr:housenumber":"1350",
    "addr:postcode":"55391",
    "addr:street":"Wayzata Blvd E",
    "iso:country":"US",
    "sg:address":"1350 Wayzata Blvd E",
    "sg:city":"Wayzata",
    "sg:classifiers":[
        {
            "category":"Restaurant",
            "type":"Food & Drink"
        }
    ],
    "sg:menulink":"http://www.allmenus.com/mn/wayzata/176575-kfc---kentucky-fried-chicken/menu/",
    "sg:phone":"+1 612 473 0207",
    "sg:postcode":"55391",
    "sg:province":"MN",
    "sg:tags":[
        "american",
        "chicken"
    ],
    "wof:name":"KFC - Kentucky Fried Chicken",
    "wof:placetype":"venue"
},
  "geometry": {"coordinates":[-93.49574699999999,44.9712],"type":"Point"}
}