{
  "type": "Feature",
  "properties": {
    "addr:full":"110 7th St W Northfield MN 55057",
    "addr:housenumber":"110",
    "addr:postcode":"55057",
    "addr:street":"7Th St W",
    "iso:country":"US",
    "sg:address":"110 7th St W",
    "sg:city":"Northfield",
    "sg:classifiers":[
        {
            "category":"Personal",
            "subcategory":"Beauty Salon",
            "type":"Services"
        }
    ],
    "sg:phone":"+1 507 645 7384",
    "sg:postcode":"55057",
    "sg:province":"MN",
    "sg:tags":[
        "shop"
    ],
    "wof:name":"Juanitas Hair Plus",
    "wof:placetype":"venue"
},
  "geometry": {"coordinates":[-93.16162,44.452925],"type":"Point"}
}