{
  "type": "Feature",
  "properties": {
    "iso:country":"US",
    "sg:address":"912 3rd St NE",
    "sg:city":"Kasson",
    "sg:classifiers":[
        {
            "category":"Building & Trades",
            "subcategory":"Construction",
            "type":"Services"
        }
    ],
    "sg:phone":"+1 507 634 2019",
    "sg:postcode":"55944",
    "sg:province":"MN",
    "sg:tags":[
        "concrete",
        "contractor"
    ],
    "wof:name":"Done Right Concrete",
    "wof:placetype":"venue"
},
  "geometry": {"coordinates":[-92.73591,44.032463],"type":"Point"}
}