{
  "type": "Feature",
  "properties": {
    "addr:full":"301 S West St Ceylon MN 56121",
    "addr:housenumber":"301",
    "addr:postcode":"56121",
    "addr:street":"S;St",
    "iso:country":"US",
    "sg:address":"301 S West St",
    "sg:city":"Ceylon",
    "sg:classifiers":[
        {
            "category":"Organizations",
            "subcategory":"Religious Organization",
            "type":"Services"
        }
    ],
    "sg:phone":"+1 507 632 4416",
    "sg:postcode":"56121",
    "sg:province":"MN",
    "sg:tags":[
        "church"
    ],
    "wof:name":"St Peter Lutheran Church",
    "wof:placetype":"venue"
},
  "geometry": {"coordinates":[-94.632988,43.531622],"type":"Point"}
}