{
  "type": "Feature",
  "properties": {
    "addr:full":"1800 E Ames Ave St Paul MN 55119",
    "addr:housenumber":"1800",
    "addr:postcode":"55119",
    "addr:street":"E Ames Ave",
    "iso:country":"US",
    "sg:address":"1800 E Ames Ave",
    "sg:city":"St Paul",
    "sg:classifiers":[
        {
            "category":"Education",
            "subcategory":"School",
            "type":"Public Place"
        }
    ],
    "sg:phone":"+1 651 735 3676",
    "sg:postcode":"55119",
    "sg:province":"MN",
    "wof:name":"Blessed Sacrament School",
    "wof:placetype":"venue"
},
  "geometry": {"coordinates":[-93.023422,44.97203],"type":"Point"}
}