{
  "type": "Feature",
  "properties": {
    "iso:country":"US",
    "sg:address":"8990 Springbrook Dr NW",
    "sg:city":"Coon Rapids",
    "sg:classifiers":[
        {
            "category":"Social Services",
            "type":"Services"
        }
    ],
    "sg:phone":"+1 763 780 4440",
    "sg:postcode":"55433",
    "sg:province":"MN",
    "sg:tags":[
        "health",
        "counselor",
        "marriage",
        "family"
    ],
    "wof:name":"Alternative Counseling Clinic",
    "wof:placetype":"venue"
},
  "geometry": {"coordinates":[-93.272881,45.133506],"type":"Point"}
}