{
  "type": "Feature",
  "properties": {
    "iso:country":"US",
    "sg:address":"409 Boulder St SW",
    "sg:city":"Hutchinson",
    "sg:classifiers":[
        {
            "category":"Professional",
            "subcategory":"Business Services",
            "type":"Services"
        }
    ],
    "sg:phone":"+1 320 587 7618",
    "sg:postcode":"55350",
    "sg:province":"MN",
    "wof:name":"McKasy & Assoc Sales Inc",
    "wof:placetype":"venue"
},
  "geometry": {"coordinates":[-94.393451,44.886416],"type":"Point"}
}