{
  "type": "Feature",
  "properties": {
    "addr:full":"944 24th Ave SW Backus MN 56435",
    "addr:housenumber":"944",
    "addr:postcode":"56435",
    "addr:street":"24Th Ave Sw",
    "iso:country":"US",
    "sg:address":"944 24th Ave SW",
    "sg:city":"Backus",
    "sg:classifiers":[
        {
            "category":"Building & Trades",
            "subcategory":"Construction",
            "type":"Services"
        }
    ],
    "sg:phone":"+1 218 587 4899",
    "sg:postcode":"56435",
    "sg:province":"MN",
    "sg:tags":[
        "woodworker"
    ],
    "wof:name":"Henry's Woodworking",
    "wof:placetype":"venue"
},
  "geometry": {"coordinates":[-94.408102,46.77148],"type":"Point"}
}