{
  "type": "Feature",
  "properties": {
    "iso:country":"US",
    "sg:address":"5330 Beacon Hill Rd",
    "sg:city":"Minnetonka",
    "sg:classifiers":[
        {
            "category":"Shopping",
            "subcategory":"Jewelry",
            "type":"Retail Goods"
        }
    ],
    "sg:phone":"+1 952 988 7869",
    "sg:postcode":"55345",
    "sg:province":"MN",
    "sg:tags":[
        "pearl"
    ],
    "wof:name":"Stender Pearl",
    "wof:placetype":"venue"
},
  "geometry": {"coordinates":[-93.46508799999999,44.907314],"type":"Point"}
}