{
  "type": "Feature",
  "properties": {
    "iso:country":"US",
    "sg:address":"1 Oriole Ln",
    "sg:city":"Saint Paul",
    "sg:classifiers":[
        {
            "category":"Real Estate",
            "subcategory":"Real Estate Operator",
            "type":"Services"
        }
    ],
    "sg:phone":"+1 651 486 3905",
    "sg:postcode":"55127",
    "sg:province":"MN",
    "sg:tags":[
        "property",
        "lessor"
    ],
    "wof:name":"Madison Equities Inc",
    "wof:placetype":"venue"
},
  "geometry": {"coordinates":[-93.08260300000001,45.105545],"type":"Point"}
}