{
  "type": "Feature",
  "properties": {
    "iso:country":"US",
    "sg:address":"20497 Co Rd 154",
    "sg:city":"Albany",
    "sg:classifiers":[
        {
            "category":"Farming",
            "subcategory":"Dairy Farm",
            "type":"Manufacturing & Wholesale Goods"
        }
    ],
    "sg:phone":"+1 320 845 2633",
    "sg:postcode":"56307",
    "sg:province":"MN",
    "wof:name":"Thomas Auer",
    "wof:placetype":"venue"
},
  "geometry": {"coordinates":[-94.530608,45.651692],"type":"Point"}
}