{
  "type": "Feature",
  "properties": {
    "addr:full":"3411 156th St W Rosemount MN 55068",
    "addr:housenumber":"3411",
    "addr:postcode":"55068",
    "addr:street":"156Th St W",
    "iso:country":"US",
    "sg:address":"3411 156th St W",
    "sg:city":"Rosemount",
    "sg:classifiers":[
        {
            "category":"Shopping",
            "type":"Retail Goods"
        }
    ],
    "sg:phone":"+1 651 322 7585",
    "sg:postcode":"55068",
    "sg:province":"MN",
    "sg:tags":[
        "merchandise"
    ],
    "wof:name":"Amerigifts Store",
    "wof:placetype":"venue"
},
  "geometry": {"coordinates":[-93.133499,44.72282],"type":"Point"}
}