{
  "type": "Feature",
  "properties": {
    "addr:full":"222 N River Ridge Cir Burnsville MN 55337",
    "addr:housenumber":"222",
    "addr:postcode":"55337",
    "addr:street":"N River Ridge Cir",
    "iso:country":"US",
    "sg:address":"222 N River Ridge Cir",
    "sg:city":"Burnsville",
    "sg:classifiers":[
        {
            "category":"Retail",
            "subcategory":"Auto Repair",
            "type":"Services"
        }
    ],
    "sg:phone":"+1 952 746 1440",
    "sg:postcode":"55337",
    "sg:province":"MN",
    "wof:name":"Fleetwheel Llc",
    "wof:placetype":"venue"
},
  "geometry": {"coordinates":[-93.283984,44.778596],"type":"Point"}
}