{
  "type": "Feature",
  "properties": {
    "addr:full":"17396 Mushtown Rd Prior Lake MN 55372",
    "addr:housenumber":"17396",
    "addr:postcode":"55372",
    "addr:street":"Mushtown Rd",
    "iso:country":"US",
    "sg:address":"17396 Mushtown Rd",
    "sg:city":"Prior Lake",
    "sg:classifiers":[
        {
            "category":"Professional",
            "subcategory":"Art Services",
            "type":"Services"
        }
    ],
    "sg:phone":"+1 952 447 0833",
    "sg:postcode":"55372",
    "sg:province":"MN",
    "sg:tags":[
        "commercial",
        "design"
    ],
    "wof:name":"Mushtown Graphics",
    "wof:placetype":"venue"
},
  "geometry": {"coordinates":[-93.429322,44.698589],"type":"Point"}
}