{
  "type": "Feature",
  "properties": {
    "addr:full":"7823 State Hwy 135 Virginia MN 55792",
    "addr:housenumber":"7823",
    "addr:postcode":"55792",
    "addr:street":"State Hwy 135",
    "iso:country":"US",
    "sg:address":"7823 State Hwy 135",
    "sg:city":"Virginia",
    "sg:classifiers":[
        {
            "category":"Government",
            "subcategory":"Office",
            "type":"Public Place"
        }
    ],
    "sg:phone":"+1 218 742 9800",
    "sg:postcode":"55792",
    "sg:province":"MN",
    "wof:name":"St Louis County Highway Mntnc",
    "wof:placetype":"venue"
},
  "geometry": {"coordinates":[-92.50769099999999,47.499126],"type":"Point"}
}