{
  "type": "Feature",
  "properties": {
    "addr:full":"245 Ruth St N St Paul MN 55119",
    "addr:housenumber":"245",
    "addr:postcode":"55119",
    "addr:street":"Ruth St N",
    "iso:country":"US",
    "sg:address":"245 Ruth St N",
    "sg:city":"St Paul",
    "sg:classifiers":[
        {
            "category":"Professional",
            "subcategory":"Accounting & Tax Preparation",
            "type":"Services"
        }
    ],
    "sg:phone":"+1 651 731 6202",
    "sg:postcode":"55119",
    "sg:province":"MN",
    "sg:tags":[
        "return",
        "filing"
    ],
    "wof:name":"June M Larsen CPA",
    "wof:placetype":"venue"
},
  "geometry": {"coordinates":[-93.01518900000001,44.949436],"type":"Point"}
}