{
  "type": "Feature",
  "properties": {
    "iso:country":"US",
    "sg:address":"2100 Snelling Ave N",
    "sg:city":"St Paul",
    "sg:classifiers":[
        {
            "category":"Shopping",
            "subcategory":"Used Merchandise",
            "type":"Retail Goods"
        },
        {
            "category":"Shopping",
            "subcategory":"Books",
            "type":"Retail Goods"
        }
    ],
    "sg:phone":"+1 651 636 3176",
    "sg:postcode":"55113",
    "sg:province":"MN",
    "sg:tags":[
        "rare",
        "dealer"
    ],
    "wof:name":"Bookshop",
    "wof:placetype":"venue"
},
  "geometry": {"coordinates":[-93.166516,45.005893],"type":"Point"}
}