{
  "type": "Feature",
  "properties": {
    "iso:country":"US",
    "sg:address":"2892 Rice Creek Ter",
    "sg:city":"Saint Paul",
    "sg:classifiers":[
        {
            "category":"Building & Trades",
            "subcategory":"Cleaning & Sanitation",
            "type":"Services"
        }
    ],
    "sg:phone":"+1 651 628 0648",
    "sg:postcode":"55112",
    "sg:province":"MN",
    "sg:tags":[
        "maintenance"
    ],
    "wof:name":"Deer Ridge Properties",
    "wof:placetype":"venue"
},
  "geometry": {"coordinates":[-93.22378399999999,45.088829],"type":"Point"}
}