{
  "type": "Feature",
  "properties": {
    "iso:country":"US",
    "sg:address":"20266 Kensington Way",
    "sg:city":"Lakeville",
    "sg:classifiers":[
        {
            "category":"Wholesale",
            "subcategory":"Electrical",
            "type":"Manufacturing & Wholesale Goods"
        }
    ],
    "sg:phone":"+1 952 469 5975",
    "sg:postcode":"55044",
    "sg:province":"MN",
    "sg:tags":[
        "electronic"
    ],
    "wof:name":"PDQ Production",
    "wof:placetype":"venue"
},
  "geometry": {"coordinates":[-93.286978,44.653819],"type":"Point"}
}