{
  "type": "Feature",
  "properties": {
    "iso:country":"US",
    "sg:address":"289 89th Ln NE",
    "sg:city":"Minneapolis",
    "sg:classifiers":[
        {
            "category":"Building & Trades",
            "subcategory":"Landscaping Services",
            "type":"Services"
        }
    ],
    "sg:phone":"+1 763 786 0652",
    "sg:postcode":"55434",
    "sg:province":"MN",
    "wof:name":"On Time Lawn & Snow Services",
    "wof:placetype":"venue"
},
  "geometry": {"coordinates":[-93.257183,45.132785],"type":"Point"}
}