{
  "type": "Feature",
  "properties": {
    "addr:full":"27902 180th St Reading MN 56165",
    "addr:housenumber":"27902",
    "addr:postcode":"56165",
    "addr:street":"180Th St",
    "iso:country":"US",
    "sg:address":"27902 180th St",
    "sg:city":"Reading",
    "sg:phone":"+1 507 926 5340",
    "sg:postcode":"56165",
    "sg:province":"MN",
    "sg:tags":[
        "farm",
        "corn",
        "soybean"
    ],
    "wof:name":"Wally Cooper",
    "wof:placetype":"venue"
},
  "geometry": {"coordinates":[-95.699485,43.732716],"type":"Point"}
}