{
  "type": "Feature",
  "properties": {
    "iso:country":"US",
    "sg:address":"6340 Kobmagergade",
    "sg:city":"Askov",
    "sg:classifiers":[
        {
            "category":"Banks & Credit Unions",
            "subcategory":"Bank",
            "type":"Services"
        }
    ],
    "sg:phone":"+1 320 838 3131",
    "sg:postcode":"55704",
    "sg:province":"MN",
    "wof:name":"First National Bank",
    "wof:placetype":"venue"
},
  "geometry": {"coordinates":[-92.781119,46.189997],"type":"Point"}
}