{
  "type": "Feature",
  "properties": {
    "iso:country":"US",
    "sg:address":"246 W Broadway Ave",
    "sg:city":"Bloomington",
    "sg:classifiers":[
        {
            "category":"Shopping",
            "subcategory":"Clothing, Apparel, & Fashions",
            "type":"Retail Goods"
        }
    ],
    "sg:phone":"+1 952 854 8110",
    "sg:postcode":"55411",
    "sg:province":"MN",
    "sg:tags":[
        "t"
    ],
    "wof:name":"City Shirts",
    "wof:placetype":"venue"
},
  "geometry": {"coordinates":[-93.28232199999999,44.999203],"type":"Point"}
}