{
  "type": "Feature",
  "properties": {
    "addr:full":"22382 Co Rd 6 Revere MN 56166",
    "addr:housenumber":"22382;6",
    "addr:postcode":"56166",
    "addr:street":"Co Rd",
    "iso:country":"US",
    "sg:address":"22382 Co Rd 6",
    "sg:city":"Revere",
    "sg:phone":"+1 507 752 7226",
    "sg:postcode":"56166",
    "sg:province":"MN",
    "sg:tags":[
        "farm",
        "corn",
        "soybean"
    ],
    "wof:name":"Jay Warner",
    "wof:placetype":"venue"
},
  "geometry": {"coordinates":[-95.38226,44.162433],"type":"Point"}
}