{
  "type": "Feature",
  "properties": {
    "iso:country":"US",
    "sg:address":"3150 Co Rd 90",
    "sg:city":"Maple Plain",
    "sg:classifiers":[
        {
            "category":"Building & Trades",
            "subcategory":"Construction",
            "type":"Services"
        }
    ],
    "sg:phone":"+1 763 479 2678",
    "sg:postcode":"55359",
    "sg:province":"MN",
    "sg:tags":[
        "excavating",
        "contractor"
    ],
    "wof:name":"Metro Contracting Co Inc",
    "wof:placetype":"venue"
},
  "geometry": {"coordinates":[-93.686797,45.034828],"type":"Point"}
}