{
  "type": "Feature",
  "properties": {
    "addr:full":"136 S Broadway Wells MN 56097",
    "addr:housenumber":"136",
    "addr:postcode":"56097",
    "addr:street":"S Broadway",
    "iso:country":"US",
    "sg:address":"136 S Broadway",
    "sg:city":"Wells",
    "sg:classifiers":[
        {
            "category":"Shopping",
            "subcategory":"Computers & Home Electronics",
            "type":"Retail Goods"
        }
    ],
    "sg:phone":"+1 507 553 5956",
    "sg:postcode":"56097",
    "sg:province":"MN",
    "sg:tags":[
        "equipment",
        "dealer"
    ],
    "sg:website":"www.mscwells.com",
    "wof:name":"Management Systems",
    "wof:placetype":"venue"
},
  "geometry": {"coordinates":[-93.72555699999999,43.743759],"type":"Point"}
}