{
  "type": "Feature",
  "properties": {
    "addr:full":"3015 Highway 29 S # 4126 Alexandria MN 56308",
    "addr:housenumber":"3015",
    "addr:postcode":"56308",
    "addr:street":"Highway 29 S # 4126",
    "iso:country":"US",
    "sg:address":"3015 Highway 29 S # 4126",
    "sg:city":"Alexandria",
    "sg:classifiers":[
        {
            "category":"Shopping",
            "subcategory":"Beauty & Cosmetics",
            "type":"Retail Goods"
        },
        {
            "category":"Personal",
            "subcategory":"Beauty Salon",
            "type":"Services"
        }
    ],
    "sg:phone":"+1 320 763 8031",
    "sg:postcode":"56308",
    "sg:province":"MN",
    "sg:tags":[
        "perfume",
        "salons-equipment",
        "supply"
    ],
    "sg:website":"http://www.bathbodyworks.net",
    "wof:name":"Bath Body Works 1718",
    "wof:placetype":"venue"
},
  "geometry": {"coordinates":[-95.383014,45.862543],"type":"Point"}
}