{
  "type": "Feature",
  "properties": {
    "addr:full":"215 N Maple St Mabel MN 55954",
    "addr:housenumber":"215",
    "addr:postcode":"55954",
    "addr:street":"N Maple St",
    "iso:country":"US",
    "sg:address":"215 N Maple St",
    "sg:city":"Mabel",
    "sg:phone":"+1 507 493 5710",
    "sg:postcode":"55954",
    "sg:province":"MN",
    "sg:tags":[
        "farm",
        "corn",
        "grain",
        "cash"
    ],
    "wof:name":"Roger Bacon",
    "wof:placetype":"venue"
},
  "geometry": {"coordinates":[-91.771142,43.52241],"type":"Point"}
}