{
  "type": "Feature",
  "properties": {
    "iso:country":"US",
    "sg:address":"349 Willow Bend",
    "sg:city":"Minneapolis",
    "sg:classifiers":[
        {
            "category":"Shopping",
            "subcategory":"Hobbies, Toys, & Games",
            "type":"Retail Goods"
        }
    ],
    "sg:phone":"+1 763 533 0403",
    "sg:postcode":"55428",
    "sg:province":"MN",
    "sg:tags":[
        "supply"
    ],
    "wof:name":"EB Games",
    "wof:placetype":"venue"
},
  "geometry": {"coordinates":[-93.368452,45.054261],"type":"Point"}
}