{
  "type": "Feature",
  "properties": {
    "iso:country":"US",
    "sg:address":"570 2nd Ave",
    "sg:city":"Zumbrota",
    "sg:classifiers":[
        {
            "category":"Real Estate",
            "subcategory":"Developer",
            "type":"Services"
        }
    ],
    "sg:phone":"+1 507 732 5111",
    "sg:postcode":"55992",
    "sg:province":"MN",
    "sg:tags":[
        "cemetery"
    ],
    "wof:name":"Zumbrota Cemetery Assoc",
    "wof:placetype":"venue"
},
  "geometry": {"coordinates":[-92.664615,44.291826],"type":"Point"}
}