{
  "type": "Feature",
  "properties": {
    "iso:country":"US",
    "sg:address":"14309 Lennell Dr",
    "sg:city":"Minnetonka",
    "sg:classifiers":[
        {
            "category":"Professional",
            "subcategory":"Management & Consulting",
            "type":"Services"
        }
    ],
    "sg:phone":"+1 952 938 3751",
    "sg:postcode":"55345",
    "sg:province":"MN",
    "wof:name":"Diet By Design",
    "wof:placetype":"venue"
},
  "geometry": {"coordinates":[-93.460735,44.928149],"type":"Point"}
}