{
  "type": "Feature",
  "properties": {
    "addr:full":"3359 W Broadway Ave Minneapolis MN 55422",
    "addr:housenumber":"3359",
    "addr:postcode":"55422",
    "addr:street":"W Broadway Ave",
    "iso:country":"US",
    "sg:address":"3359 W Broadway Ave",
    "sg:city":"Minneapolis",
    "sg:classifiers":[
        {
            "category":"Health Services",
            "subcategory":"Dentist",
            "type":"Services"
        }
    ],
    "sg:phone":"+1 763 392 6593",
    "sg:postcode":"55422",
    "sg:province":"MN",
    "sg:tags":[
        "dentists-cosmetic",
        "dentistry"
    ],
    "sg:website":"http://www.thomasdewerddds.com",
    "wof:name":"Thomas M DeWerd, DDS, PA",
    "wof:placetype":"venue"
},
  "geometry": {"coordinates":[-93.322344,45.015822],"type":"Point"}
}