{
  "type": "Feature",
  "properties": {
    "iso:country":"US",
    "sg:address":"312 E Howard St",
    "sg:city":"Hibbing",
    "sg:classifiers":[
        {
            "category":"Personal",
            "subcategory":"Beauty Salon",
            "type":"Services"
        },
        {
            "category":"Personal",
            "subcategory":"Barber",
            "type":"Services"
        }
    ],
    "sg:phone":"+1 218 262 2646",
    "sg:postcode":"55746",
    "sg:province":"MN",
    "sg:tags":[
        "hair",
        "stylist"
    ],
    "wof:name":"The Ultimate",
    "wof:placetype":"venue"
},
  "geometry": {"coordinates":[-92.939055,47.427471],"type":"Point"}
}