{
  "type": "Feature",
  "properties": {
    "iso:country":"US",
    "sg:address":"303 S Lakeshore Dr",
    "sg:city":"Lake City",
    "sg:classifiers":[
        {
            "category":"Food & Beverages",
            "subcategory":"Groceries & Convenience Stores",
            "type":"Retail Goods"
        }
    ],
    "sg:phone":"+1 651 345 3200",
    "sg:postcode":"55041",
    "sg:province":"MN",
    "wof:name":"Severson Food Mart",
    "wof:placetype":"venue"
},
  "geometry": {"coordinates":[-92.264538,44.448117],"type":"Point"}
}