{
  "type": "Feature",
  "properties": {
    "iso:country":"US",
    "sg:address":"2014 8th St N",
    "sg:city":"St Cloud",
    "sg:classifiers":[
        {
            "category":"Personal",
            "subcategory":"Beauty Salon",
            "type":"Services"
        }
    ],
    "sg:phone":"+1 320 251 4854",
    "sg:postcode":"56303",
    "sg:province":"MN",
    "wof:name":"Hair Cut Co",
    "wof:placetype":"venue"
},
  "geometry": {"coordinates":[-94.182317,45.565263],"type":"Point"}
}