{
  "type": "Feature",
  "properties": {
    "addr:full":"701 Humboldt Ave N Minneapolis MN 55411",
    "addr:housenumber":"701",
    "addr:postcode":"55411",
    "addr:street":"Humboldt Ave N",
    "iso:country":"US",
    "sg:address":"701 Humboldt Ave N",
    "sg:city":"Minneapolis",
    "sg:classifiers":[
        {
            "category":"Organizations",
            "subcategory":"Religious Organization",
            "type":"Services"
        }
    ],
    "sg:phone":"+1 763 374 2793",
    "sg:postcode":"55411",
    "sg:province":"MN",
    "sg:tags":[
        "church"
    ],
    "wof:name":"Glenwood Congregatn Jehovahs",
    "wof:placetype":"venue"
},
  "geometry": {"coordinates":[-93.298203,44.986362],"type":"Point"}
}