{
  "type": "Feature",
  "properties": {
    "addr:full":"4528 Casco Ave Minneapolis MN 55424",
    "addr:housenumber":"4528",
    "addr:postcode":"55424",
    "addr:street":"Casco Ave",
    "iso:country":"US",
    "sg:address":"4528 Casco Ave",
    "sg:city":"Minneapolis",
    "sg:classifiers":[
        {
            "category":"Health Services",
            "subcategory":"Health Practitioner",
            "type":"Services"
        }
    ],
    "sg:phone":"+1 952 929 0019",
    "sg:postcode":"55424",
    "sg:province":"MN",
    "wof:name":"Expanded Awareness Institute",
    "wof:placetype":"venue"
},
  "geometry": {"coordinates":[-93.337501,44.917478],"type":"Point"}
}