{
  "type": "Feature",
  "properties": {
    "addr:full":"202 S Johnson Ave Fosston MN 56542",
    "addr:housenumber":"202",
    "addr:postcode":"56542",
    "addr:street":"S Johnson Ave",
    "iso:country":"US",
    "sg:address":"202 S Johnson Ave",
    "sg:city":"Fosston",
    "sg:classifiers":[
        {
            "category":"Manufacturing",
            "subcategory":"Motor Vehicles & Parts",
            "type":"Manufacturing & Wholesale Goods"
        }
    ],
    "sg:phone":"+1 218 435 1188",
    "sg:postcode":"56542",
    "sg:province":"MN",
    "sg:tags":[
        "suppl",
        "mfg"
    ],
    "wof:name":"Carquest Auto Parts",
    "wof:placetype":"venue"
},
  "geometry": {"coordinates":[-95.752753,47.575227],"type":"Point"}
}