{
  "type": "Feature",
  "properties": {
    "iso:country":"US",
    "sg:address":"3320 Terminal Dr",
    "sg:city":"Eagan",
    "sg:classifiers":[
        {
            "category":"Home & Garden",
            "subcategory":"Building Materials",
            "type":"Retail Goods"
        },
        {
            "category":"Manufacturing",
            "subcategory":"Building Materials",
            "type":"Manufacturing & Wholesale Goods"
        }
    ],
    "sg:phone":"+1 651 454 2993",
    "sg:postcode":"55121",
    "sg:province":"MN",
    "sg:tags":[
        "steel",
        "door",
        "mfg",
        "devices",
        "wood",
        "operating",
        "gate"
    ],
    "sg:website":"www.prehungdoorsinc.com",
    "wof:name":"Pre-Hung Doors Inc",
    "wof:placetype":"venue"
},
  "geometry": {"coordinates":[-93.19490399999999,44.836303],"type":"Point"}
}