{
  "type": "Feature",
  "properties": {
    "iso:country":"US",
    "sg:address":"301 2nd St S",
    "sg:city":"Stillwater",
    "sg:classifiers":[
        {
            "category":"Restaurant",
            "type":"Food & Drink"
        }
    ],
    "sg:phone":"+1 651 351 1262",
    "sg:postcode":"55082",
    "sg:province":"MN",
    "sg:tags":[
        "personal",
        "eating",
        "pizza"
    ],
    "wof:name":"Grand Pizza",
    "wof:placetype":"venue"
},
  "geometry": {"coordinates":[-92.806786,45.054634],"type":"Point"}
}