{
  "type": "Feature",
  "properties": {
    "iso:country":"US",
    "sg:address":"26820 US Hwy 169",
    "sg:city":"Zimmerman",
    "sg:classifiers":[
        {
            "category":"Farming",
            "subcategory":"Nursery",
            "type":"Manufacturing & Wholesale Goods"
        }
    ],
    "sg:phone":"+1 763 856 3693",
    "sg:postcode":"55398",
    "sg:province":"MN",
    "sg:tags":[
        "ornamental",
        "greenhouse",
        "supply"
    ],
    "sg:website":"www.globalgardens.com",
    "wof:name":"Global Gardens Inc",
    "wof:placetype":"venue"
},
  "geometry": {"coordinates":[-93.58395899999999,45.463451],"type":"Point"}
}