{
  "type": "Feature",
  "properties": {
    "iso:country":"US",
    "sg:address":"2524 Maple Grove Rd",
    "sg:city":"Duluth",
    "sg:classifiers":[
        {
            "category":"Social Services",
            "type":"Services"
        },
        {
            "category":"Education",
            "subcategory":"Special Training",
            "type":"Public Place"
        },
        {
            "category":"Professional",
            "subcategory":"Detective & Security Services",
            "type":"Services"
        },
        {
            "category":"Government",
            "subcategory":"Fire Station",
            "type":"Public Place"
        },
        {
            "category":"Health Services",
            "subcategory":"Medical Lab",
            "type":"Services"
        },
        {
            "category":"Organizations",
            "subcategory":"Community Association",
            "type":"Services"
        },
        {
            "category":"Organizations",
            "subcategory":"Non-profit Organization",
            "type":"Services"
        }
    ],
    "sg:phone":"+1 218 722 0071",
    "sg:postcode":"55811",
    "sg:province":"MN",
    "sg:tags":[
        "disaster",
        "recovery",
        "emergency",
        "notification",
        "instruction",
        "safety",
        "relief",
        "human",
        "aid",
        "first",
        "charity"
    ],
    "sg:website":"http://www.americanredcross.com",
    "wof:name":"American Red Cross",
    "wof:placetype":"venue"
},
  "geometry": {"coordinates":[-92.170331,46.80756],"type":"Point"}
}