{
  "type": "Feature",
  "properties": {
    "iso:country":"US",
    "sg:address":"1045 Hudson Rd",
    "sg:city":"St Paul",
    "sg:classifiers":[
        {
            "category":"Bars & Pubs",
            "type":"Food & Drink"
        }
    ],
    "sg:phone":"+1 651 774 1099",
    "sg:postcode":"55106",
    "sg:province":"MN",
    "sg:tags":[
        "lounge",
        "drinking",
        "cocktail"
    ],
    "wof:name":"Pauls Lounge",
    "wof:placetype":"venue"
},
  "geometry": {"coordinates":[-93.057119,44.952304],"type":"Point"}
}