{
  "type": "Feature",
  "properties": {
    "iso:country":"US",
    "sg:address":"6001 Oakland Ave S",
    "sg:city":"Minneapolis",
    "sg:classifiers":[
        {
            "category":"Manufacturing",
            "subcategory":"Printing",
            "type":"Manufacturing & Wholesale Goods"
        }
    ],
    "sg:phone":"+1 612 869 3767",
    "sg:postcode":"55417",
    "sg:province":"MN",
    "sg:tags":[
        "publishing"
    ],
    "wof:name":"BGS Enterprises",
    "wof:placetype":"venue"
},
  "geometry": {"coordinates":[-93.26656199999999,44.892517],"type":"Point"}
}