{
  "type": "Feature",
  "properties": {
    "addr:full":"30 Division St N Rice MN 56373",
    "addr:housenumber":"30",
    "addr:postcode":"56373",
    "addr:street":"Division St N",
    "iso:country":"US",
    "sg:address":"30 Division St N",
    "sg:city":"Rice",
    "sg:classifiers":[
        {
            "category":"Bars & Pubs",
            "type":"Food & Drink"
        }
    ],
    "sg:phone":"+1 320 393 2691",
    "sg:postcode":"56373",
    "sg:province":"MN",
    "wof:name":"Alamo Liquors",
    "wof:placetype":"venue"
},
  "geometry": {"coordinates":[-94.22022800000001,45.753138],"type":"Point"}
}