{
  "type": "Feature",
  "properties": {
    "addr:full":"219 N 2nd St Minneapolis MN 55401",
    "addr:housenumber":"219",
    "addr:postcode":"55401",
    "addr:street":"N 2Nd St",
    "iso:country":"US",
    "sg:address":"219 N 2nd St",
    "sg:city":"Minneapolis",
    "sg:classifiers":[
        {
            "category":"Communications",
            "subcategory":"Film & Video Production",
            "type":"Services"
        }
    ],
    "sg:phone":"+1 612 332 8864",
    "sg:postcode":"55401",
    "sg:province":"MN",
    "sg:tags":[
        "motion",
        "picture",
        "studio",
        "producer"
    ],
    "sg:website":"www.dublinproductions.com",
    "wof:name":"Dublin Productions",
    "wof:placetype":"venue"
},
  "geometry": {"coordinates":[-93.271145,44.985261],"type":"Point"}
}