{
  "type": "Feature",
  "properties": {
    "iso:country":"US",
    "sg:address":"154 Main St",
    "sg:city":"Vining",
    "sg:classifiers":[
        {
            "category":"Government",
            "subcategory":"Office",
            "type":"Public Place"
        }
    ],
    "sg:phone":"+1 320 815 1015",
    "sg:postcode":"56588",
    "sg:province":"MN",
    "wof:name":"City of Urbank",
    "wof:placetype":"venue"
},
  "geometry": {"coordinates":[-95.510023,46.122577],"type":"Point"}
}