{
  "type": "Feature",
  "properties": {
    "iso:country":"US",
    "sg:address":"1162 129th Ave NE",
    "sg:city":"Minneapolis",
    "sg:classifiers":[
        {
            "category":"Wholesale",
            "subcategory":"Hardware",
            "type":"Manufacturing & Wholesale Goods"
        }
    ],
    "sg:phone":"+1 763 754 3059",
    "sg:postcode":"55434",
    "sg:province":"MN",
    "wof:name":"Dbh Distribution",
    "wof:placetype":"venue"
},
  "geometry": {"coordinates":[-93.241124,45.204714],"type":"Point"}
}