{
  "type": "Feature",
  "properties": {
    "iso:country":"US",
    "sg:address":"16765 Willow Ln SW",
    "sg:city":"Prior Lake",
    "sg:classifiers":[
        {
            "category":"Arts & Performance",
            "subcategory":"Theater",
            "type":"Entertainment"
        }
    ],
    "sg:phone":"+1 952 440 5834",
    "sg:postcode":"55372",
    "sg:province":"MN",
    "sg:tags":[
        "group"
    ],
    "wof:name":"Drivetime",
    "wof:placetype":"venue"
},
  "geometry": {"coordinates":[-93.444644,44.706701],"type":"Point"}
}