{
  "type": "Feature",
  "properties": {
    "addr:full":"16584 Pebblebrook Ct Prior Lake MN 55372",
    "addr:housenumber":"16584",
    "addr:postcode":"55372",
    "addr:street":"Pebblebrook Ct",
    "iso:country":"US",
    "sg:address":"16584 Pebblebrook Ct",
    "sg:city":"Prior Lake",
    "sg:classifiers":[
        {
            "category":"Building & Trades",
            "subcategory":"Plumbing",
            "type":"Services"
        }
    ],
    "sg:phone":"+1 952 447 8110",
    "sg:postcode":"55372",
    "sg:province":"MN",
    "sg:tags":[
        "contractor"
    ],
    "wof:name":"Prior Lake Heating & AC",
    "wof:placetype":"venue"
},
  "geometry": {"coordinates":[-93.387232,44.708412],"type":"Point"}
}