{
  "type": "Feature",
  "properties": {
    "iso:country":"US",
    "sg:address":"3015 18th Ave SW",
    "sg:city":"Rochester",
    "sg:phone":"+1 507 282 5985",
    "sg:postcode":"55902",
    "sg:province":"MN",
    "sg:tags":[
        "farm",
        "corn",
        "soybean"
    ],
    "wof:name":"Eugene Peters",
    "wof:placetype":"venue"
},
  "geometry": {"coordinates":[-92.488361,43.981967],"type":"Point"}
}