{
  "type": "Feature",
  "properties": {
    "addr:full":"4946 Arrowood Ln N Minneapolis MN 55442",
    "addr:housenumber":"4946",
    "addr:postcode":"55442",
    "addr:street":"Arrowood Ln N",
    "iso:country":"US",
    "sg:address":"4946 Arrowood Ln N",
    "sg:city":"Minneapolis",
    "sg:classifiers":[
        {
            "category":"Professional",
            "type":"Services"
        }
    ],
    "sg:phone":"+1 763 559 5581",
    "sg:postcode":"55442",
    "sg:province":"MN",
    "wof:name":"B Squared Designs Inc",
    "wof:placetype":"venue"
},
  "geometry": {"coordinates":[-93.423007,45.045413],"type":"Point"}
}