{
  "type": "Feature",
  "properties": {
    "addr:full":"26470 Fallbrook Ave Wyoming MN 55092",
    "addr:housenumber":"26470",
    "addr:postcode":"55092",
    "addr:street":"Fallbrook Ave",
    "iso:country":"US",
    "sg:address":"26470 Fallbrook Ave",
    "sg:city":"Wyoming",
    "sg:classifiers":[
        {
            "category":"Autos & Motor Vehicles",
            "subcategory":"Boat Sales",
            "type":"Retail Goods"
        }
    ],
    "sg:phone":"+1 651 462 4516",
    "sg:postcode":"55092",
    "sg:province":"MN",
    "sg:tags":[
        "dealer",
        "sales"
    ],
    "sg:website":"www.hallbergmarine.com",
    "wof:name":"Hallberg Marine Inc",
    "wof:placetype":"venue"
},
  "geometry": {"coordinates":[-93.001366,45.332412],"type":"Point"}
}