{
  "type": "Feature",
  "properties": {
    "addr:full":"4100 Lakeview Ave Minneapolis MN 55422",
    "addr:housenumber":"4100",
    "addr:postcode":"55422",
    "addr:street":"Lakeview Ave",
    "iso:country":"US",
    "sg:address":"4100 Lakeview Ave",
    "sg:city":"Minneapolis",
    "sg:classifiers":[
        {
            "category":"Professional",
            "subcategory":"Business Services",
            "type":"Services"
        },
        {
            "category":"Government",
            "subcategory":"Department Of Motor Vehicles",
            "type":"Public Place"
        }
    ],
    "sg:phone":"+1 763 535 8133",
    "sg:postcode":"55422",
    "sg:province":"MN",
    "sg:tags":[
        "license",
        "registration"
    ],
    "wof:name":"Robbinsdale Motor Vehicle License Bureau",
    "wof:placetype":"venue"
},
  "geometry": {"coordinates":[-93.335579,45.03104],"type":"Point"}
}