{
  "type": "Feature",
  "properties": {
    "addr:full":"15785 95th Ave N Osseo MN 55369",
    "addr:housenumber":"15785",
    "addr:postcode":"55369",
    "addr:street":"95Th Ave N",
    "iso:country":"US",
    "sg:address":"15785 95th Ave N",
    "sg:city":"Osseo",
    "sg:classifiers":[
        {
            "category":"Health Services",
            "subcategory":"Dentist",
            "type":"Services"
        }
    ],
    "sg:phone":"+1 763 494 6612",
    "sg:postcode":"55369",
    "sg:province":"MN",
    "sg:tags":[
        "orthodontist"
    ],
    "wof:name":"Kelly Chad H Orthodontist",
    "wof:placetype":"venue"
},
  "geometry": {"coordinates":[-93.480103,45.126598],"type":"Point"}
}