{
  "type": "Feature",
  "properties": {
    "iso:country":"US",
    "sg:address":"3112 N 2nd St",
    "sg:city":"Minneapolis",
    "sg:classifiers":[
        {
            "category":"Wholesale",
            "subcategory":"Stationery",
            "type":"Manufacturing & Wholesale Goods"
        }
    ],
    "sg:phone":"+1 612 522 3822",
    "sg:postcode":"55411",
    "sg:province":"MN",
    "sg:tags":[
        "product",
        "paper"
    ],
    "wof:name":"Trio Supply Co",
    "wof:placetype":"venue"
},
  "geometry": {"coordinates":[-93.28075,45.012971],"type":"Point"}
}