{
  "type": "Feature",
  "properties": {
    "iso:country":"US",
    "sg:address":"8301 Golden Valley Rd",
    "sg:city":"Minneapolis",
    "sg:classifiers":[
        {
            "category":"Professional",
            "type":"Services"
        }
    ],
    "sg:phone":"+1 763 544 0197",
    "sg:postcode":"55427",
    "sg:province":"MN",
    "sg:tags":[
        "establishment"
    ],
    "wof:name":"Dealer's Process",
    "wof:placetype":"venue"
},
  "geometry": {"coordinates":[-93.384624,44.986734],"type":"Point"}
}