{
  "type": "Feature",
  "properties": {
    "iso:country":"US",
    "sg:address":"9151 Breezy Point Dr",
    "sg:city":"Pequot Lakes",
    "sg:classifiers":[
        {
            "category":"Professional",
            "type":"Services"
        }
    ],
    "sg:phone":"+1 218 562 4235",
    "sg:postcode":"56472",
    "sg:province":"MN",
    "sg:tags":[
        "establishment"
    ],
    "wof:name":"John Roberts Co",
    "wof:placetype":"venue"
},
  "geometry": {"coordinates":[-94.206036,46.588437],"type":"Point"}
}