{
  "type": "Feature",
  "properties": {
    "iso:country":"US",
    "sg:address":"9676 275th St",
    "sg:city":"Chisago City",
    "sg:classifiers":[
        {
            "category":"Manufacturing",
            "subcategory":"Printing",
            "type":"Manufacturing & Wholesale Goods"
        }
    ],
    "sg:phone":"+1 651 257 3348",
    "sg:postcode":"55013",
    "sg:province":"MN",
    "sg:tags":[
        "commercial"
    ],
    "wof:name":"Northwest Quality Print",
    "wof:placetype":"venue"
},
  "geometry": {"coordinates":[-92.907219,45.347258],"type":"Point"}
}