{
  "type": "Feature",
  "properties": {
    "iso:country":"US",
    "sg:address":"32679 380th St",
    "sg:city":"Le Sueur",
    "sg:phone":"+1 507 665 3894",
    "sg:postcode":"56058",
    "sg:province":"MN",
    "sg:tags":[
        "farm",
        "corn"
    ],
    "wof:name":"Tim Tellijohn",
    "wof:placetype":"venue"
},
  "geometry": {"coordinates":[-93.91927099999999,44.398902],"type":"Point"}
}