{
  "type": "Feature",
  "properties": {
    "addr:full":"107 Bowery St Wykoff MN 55990",
    "addr:housenumber":"107",
    "addr:postcode":"55990",
    "addr:street":"Bowery St",
    "iso:country":"US",
    "sg:address":"107 Bowery St",
    "sg:city":"Wykoff",
    "sg:classifiers":[
        {
            "category":"Home & Garden",
            "subcategory":"Building Materials",
            "type":"Retail Goods"
        }
    ],
    "sg:phone":"+1 507 352 6546",
    "sg:postcode":"55990",
    "sg:province":"MN",
    "sg:tags":[
        "lumber"
    ],
    "wof:name":"Fillmore Sawmill & Saw Shop",
    "wof:placetype":"venue"
},
  "geometry": {"coordinates":[-92.265097,43.749317],"type":"Point"}
}