{
  "type": "Feature",
  "properties": {
    "iso:country":"US",
    "sg:address":"1305 W Birch Ave",
    "sg:city":"Olivia",
    "sg:classifiers":[
        {
            "category":"Food & Beverages",
            "subcategory":"Specialty",
            "type":"Retail Goods"
        }
    ],
    "sg:phone":"+1 320 523 2400",
    "sg:postcode":"56277",
    "sg:province":"MN",
    "sg:tags":[
        "water",
        "bulk",
        "company"
    ],
    "wof:name":"Olivia Bottled Water",
    "wof:placetype":"venue"
},
  "geometry": {"coordinates":[-94.995769,44.76853],"type":"Point"}
}