{
  "type": "Feature",
  "properties": {
    "addr:full":"3903 Chip Shot Ln SE Rochester MN 55904",
    "addr:housenumber":"3903",
    "addr:postcode":"55904",
    "addr:street":"Chip Shot Ln Se",
    "iso:country":"US",
    "sg:address":"3903 Chip Shot Ln SE",
    "sg:city":"Rochester",
    "sg:classifiers":[
        {
            "category":"Health Services",
            "subcategory":"Doctor",
            "type":"Services"
        }
    ],
    "sg:phone":"+1 507 289 1247",
    "sg:postcode":"55904",
    "sg:province":"MN",
    "sg:tags":[
        "physician",
        "surgeon"
    ],
    "wof:name":"Victoria J. Hagstrom, M.D., P.A.",
    "wof:placetype":"venue"
},
  "geometry": {"coordinates":[-92.4004,44.008766],"type":"Point"}
}