{
  "type": "Feature",
  "properties": {
    "addr:full":"240 Harrison St Red Wing MN 55066",
    "addr:housenumber":"240",
    "addr:postcode":"55066",
    "addr:street":"Harrison St",
    "iso:country":"US",
    "sg:address":"240 Harrison St",
    "sg:city":"Red Wing",
    "sg:classifiers":[
        {
            "category":"Professional",
            "type":"Services"
        }
    ],
    "sg:phone":"+1 651 385 8794",
    "sg:postcode":"55066",
    "sg:province":"MN",
    "wof:name":"Personalized Childrens Music",
    "wof:placetype":"venue"
},
  "geometry": {"coordinates":[-92.558053,44.563663],"type":"Point"}
}