{
  "type": "Feature",
  "properties": {
    "iso:country":"US",
    "sg:address":"1566 W Thomas Ave",
    "sg:city":"St Paul",
    "sg:classifiers":[
        {
            "category":"Organizations",
            "subcategory":"Religious Organization",
            "type":"Services"
        }
    ],
    "sg:phone":"+1 651 644 7100",
    "sg:postcode":"55104",
    "sg:province":"MN",
    "sg:tags":[
        "church"
    ],
    "wof:name":"Hmong Lutheran Church",
    "wof:placetype":"venue"
},
  "geometry": {"coordinates":[-93.166128,44.959182],"type":"Point"}
}