{
  "type": "Feature",
  "properties": {
    "iso:country":"US",
    "sg:address":"356 12th St SW",
    "sg:city":"Forest Lake",
    "sg:classifiers":[
        {
            "category":"Shopping",
            "subcategory":"Department Store",
            "type":"Retail Goods"
        }
    ],
    "sg:phone":"+1 651 464 4700",
    "sg:postcode":"55025",
    "sg:province":"MN",
    "sg:website":"www.target.com",
    "wof:name":"Target",
    "wof:placetype":"venue"
},
  "geometry": {"coordinates":[-92.99891700000001,45.273892],"type":"Point"}
}