{
  "type": "Feature",
  "properties": {
    "iso:country":"US",
    "sg:address":"204 E Vine St",
    "sg:city":"Mankato",
    "sg:classifiers":[
        {
            "category":"Communications",
            "subcategory":"Television Station",
            "type":"Services"
        }
    ],
    "sg:phone":"+1 507 625 6771",
    "sg:postcode":"56001",
    "sg:province":"MN",
    "wof:name":"Cctv-Public Access",
    "wof:placetype":"venue"
},
  "geometry": {"coordinates":[-93.99510100000001,44.173358],"type":"Point"}
}