{
  "type": "Feature",
  "properties": {
    "iso:country":"US",
    "sg:address":"3515 Minnehaha Ave",
    "sg:city":"Minneapolis",
    "sg:classifiers":[
        {
            "category":"Retail",
            "subcategory":"Auto Repair",
            "type":"Services"
        }
    ],
    "sg:phone":"+1 612 729 4119",
    "sg:postcode":"55406",
    "sg:province":"MN",
    "wof:name":"Sandberg Imports",
    "wof:placetype":"venue"
},
  "geometry": {"coordinates":[-93.227203,44.938999],"type":"Point"}
}