{
  "type": "Feature",
  "properties": {
    "iso:country":"US",
    "sg:address":"407 4th St",
    "sg:city":"International Falls",
    "sg:classifiers":[
        {
            "category":"Social Services",
            "type":"Services"
        }
    ],
    "sg:phone":"+1 218 283 3460",
    "sg:postcode":"56649",
    "sg:province":"MN",
    "wof:name":"Arrowhead Ecnomic Oprtnty Agcy",
    "wof:placetype":"venue"
},
  "geometry": {"coordinates":[-93.40521099999999,48.601596],"type":"Point"}
}