{
  "type": "Feature",
  "properties": {
    "addr:full":"1076 230th Ave Ogilvie MN 56358",
    "addr:housenumber":"1076",
    "addr:postcode":"56358",
    "addr:street":"230Th Ave",
    "iso:country":"US",
    "sg:address":"1076 230th Ave",
    "sg:city":"Ogilvie",
    "sg:classifiers":[
        {
            "category":"Utilities",
            "subcategory":"Refuse",
            "type":"Services"
        }
    ],
    "sg:phone":"+1 320 272 4366",
    "sg:postcode":"56358",
    "sg:province":"MN",
    "sg:tags":[
        "system"
    ],
    "wof:name":"Monsons Roll Off Service",
    "wof:placetype":"venue"
},
  "geometry": {"coordinates":[-93.502127,45.922172],"type":"Point"}
}