{
  "type": "Feature",
  "properties": {
    "iso:country":"US",
    "sg:address":"1789 Woodlane Dr",
    "sg:city":"Woodbury",
    "sg:classifiers":[
        {
            "category":"Personal",
            "type":"Services"
        }
    ],
    "sg:phone":"+1 952 835 5181",
    "sg:postcode":"55125",
    "sg:province":"MN",
    "sg:tags":[
        "control",
        "weight"
    ],
    "wof:name":"Hi-Energy Weight Control Ctr",
    "wof:placetype":"venue"
},
  "geometry": {"coordinates":[-92.96634400000001,44.922846],"type":"Point"}
}