{
  "type": "Feature",
  "properties": {
    "iso:country":"US",
    "sg:address":"1505 Queens Dr",
    "sg:city":"Woodbury",
    "sg:classifiers":[
        {
            "category":"Personal",
            "type":"Services"
        }
    ],
    "sg:phone":"+1 651 730 4970",
    "sg:postcode":"55125",
    "sg:province":"MN",
    "sg:tags":[
        "control",
        "weight"
    ],
    "wof:name":"Jenny Craig Weight Loss Ctr",
    "wof:placetype":"venue"
},
  "geometry": {"coordinates":[-92.957157,44.927218],"type":"Point"}
}