{
  "type": "Feature",
  "properties": {
    "addr:full":"24078 Greenway Rd Forest Lake MN 55025",
    "addr:housenumber":"24078",
    "addr:postcode":"55025",
    "addr:street":"Greenway Rd",
    "iso:country":"US",
    "sg:address":"24078 Greenway Rd",
    "sg:city":"Forest Lake",
    "sg:classifiers":[
        {
            "category":"Autos & Motor Vehicles",
            "subcategory":"Automobile Sales",
            "type":"Retail Goods"
        }
    ],
    "sg:phone":"+1 651 466 0212",
    "sg:postcode":"55025",
    "sg:province":"MN",
    "sg:tags":[
        "repair"
    ],
    "wof:name":"Straightline Performance",
    "wof:placetype":"venue"
},
  "geometry": {"coordinates":[-92.97436500000001,45.297871],"type":"Point"}
}