{
  "type": "Feature",
  "properties": {
    "addr:full":"427 Snelling Ave St Paul MN 55104",
    "addr:housenumber":"427",
    "addr:postcode":"55104",
    "addr:street":"Snelling Ave",
    "iso:country":"US",
    "sg:address":"427 Snelling Ave",
    "sg:city":"St Paul",
    "sg:classifiers":[
        {
            "category":"Banks & Credit Unions",
            "subcategory":"Bank",
            "type":"Services"
        }
    ],
    "sg:phone":"+1 651 659 0465",
    "sg:postcode":"55104",
    "sg:province":"MN",
    "wof:name":"Bremer Investments",
    "wof:placetype":"venue"
},
  "geometry": {"coordinates":[-93.16706600000001,44.952706],"type":"Point"}
}