{
  "type": "Feature",
  "properties": {
    "iso:country":"US",
    "sg:address":"9939 Lyndale Ave S",
    "sg:city":"Minneapolis",
    "sg:classifiers":[
        {
            "category":"Home & Garden",
            "subcategory":"Carpets & Floor Coverings",
            "type":"Retail Goods"
        }
    ],
    "sg:phone":"+1 952 881 5825",
    "sg:postcode":"55420",
    "sg:province":"MN",
    "sg:tags":[
        "carpeting"
    ],
    "wof:name":"Bloomington Linoleum & Carpet Inc",
    "wof:placetype":"venue"
},
  "geometry": {"coordinates":[-93.288498,44.822899],"type":"Point"}
}