{
  "type": "Feature",
  "properties": {
    "addr:full":"2570 7th Ave E Saint Paul MN 55109",
    "addr:housenumber":"2570",
    "addr:postcode":"55109",
    "addr:street":"7Th Ave E",
    "iso:country":"US",
    "sg:address":"2570 7th Ave E",
    "sg:city":"Saint Paul",
    "sg:classifiers":[
        {
            "category":"Health Services",
            "subcategory":"Clinic",
            "type":"Services"
        }
    ],
    "sg:phone":"+1 651 777 0350",
    "sg:postcode":"55109",
    "sg:province":"MN",
    "sg:tags":[
        "specialty",
        "outpatient"
    ],
    "wof:name":"Womens Life Care Center",
    "wof:placetype":"venue"
},
  "geometry": {"coordinates":[-92.990606,45.012976],"type":"Point"}
}