{
  "type": "Feature",
  "properties": {
    "addr:full":"3850 Linden Dr W Hamel MN 55340",
    "addr:housenumber":"3850",
    "addr:postcode":"55340",
    "addr:street":"Linden Dr W Hamel",
    "iso:country":"US",
    "sg:address":"3850 Linden Dr W",
    "sg:city":"Hamel",
    "sg:classifiers":[
        {
            "category":"Professional",
            "subcategory":"Management & Consulting",
            "type":"Services"
        }
    ],
    "sg:phone":"+1 763 478 6809",
    "sg:postcode":"55340",
    "sg:province":"MN",
    "sg:tags":[
        "marketing",
        "consultant"
    ],
    "wof:name":"SLB Consulting",
    "wof:placetype":"venue"
},
  "geometry": {"coordinates":[-93.52522999999999,45.046822],"type":"Point"}
}