{
  "type": "Feature",
  "properties": {
    "addr:full":"14198 Commerce Ave NE Prior Lake MN 55372",
    "addr:housenumber":"14198",
    "addr:postcode":"55372",
    "addr:street":"Commerce Ave Ne",
    "iso:country":"US",
    "sg:address":"14198 Commerce Ave NE",
    "sg:city":"Prior Lake",
    "sg:classifiers":[
        {
            "category":"Banks & Credit Unions",
            "subcategory":"Investment Brokerage",
            "type":"Services"
        }
    ],
    "sg:phone":"+1 952 226 1470",
    "sg:postcode":"55372",
    "sg:province":"MN",
    "sg:tags":[
        "consultant",
        "planning",
        "financial"
    ],
    "wof:name":"American Express Financial Adv",
    "wof:placetype":"venue"
},
  "geometry": {"coordinates":[-93.38028199999999,44.743584],"type":"Point"}
}