{
  "type": "Feature",
  "properties": {
    "addr:full":"933 140th Ave Luverne MN 56172",
    "addr:housenumber":"933",
    "addr:postcode":"56172",
    "addr:street":"140Th Ave",
    "iso:country":"US",
    "sg:address":"933 140th Ave",
    "sg:city":"Luverne",
    "sg:phone":"+1 507 283 8991",
    "sg:postcode":"56172",
    "sg:province":"MN",
    "sg:tags":[
        "hog",
        "beef",
        "f",
        "farm",
        "corn",
        "soybean",
        "cattle",
        "feedlot"
    ],
    "wof:name":"Warren Sandbulte",
    "wof:placetype":"venue"
},
  "geometry": {"coordinates":[-95.783599,43.985199],"type":"Point"}
}