{
  "type": "Feature",
  "properties": {
    "addr:full":"13413 York Ave Burnsville MN 55337",
    "addr:housenumber":"13413",
    "addr:postcode":"55337",
    "addr:street":"York Ave",
    "iso:country":"US",
    "sg:address":"13413 York Ave",
    "sg:city":"Burnsville",
    "sg:classifiers":[
        {
            "category":"Shopping",
            "subcategory":"Bicycles & Sporting Goods",
            "type":"Retail Goods"
        }
    ],
    "sg:phone":"+1 952 890 4997",
    "sg:postcode":"55337",
    "sg:province":"MN",
    "wof:name":"Aj Guns Inc",
    "wof:placetype":"venue"
},
  "geometry": {"coordinates":[-93.318945,44.761749],"type":"Point"}
}