{
  "type": "Feature",
  "properties": {
    "iso:country":"US",
    "sg:address":"3740 123rd Ln NW",
    "sg:city":"Minneapolis",
    "sg:classifiers":[
        {
            "category":"Banks & Credit Unions",
            "subcategory":"Bank",
            "type":"Services"
        }
    ],
    "sg:phone":"+1 763 464 4177",
    "sg:postcode":"55433",
    "sg:province":"MN",
    "sg:tags":[
        "loan",
        "real estate"
    ],
    "wof:name":"Mc Kenna Financial Group",
    "wof:placetype":"venue"
},
  "geometry": {"coordinates":[-93.362371,45.194739],"type":"Point"}
}