{
  "type": "Feature",
  "properties": {
    "addr:full":"42423 160th St Waseca MN 55052",
    "addr:housenumber":"42423",
    "addr:postcode":"55052",
    "addr:street":"160Th St",
    "iso:country":"US",
    "sg:address":"42423 160th St",
    "sg:city":"Waseca",
    "sg:phone":"+1 507 685 4217",
    "sg:postcode":"55052",
    "sg:province":"MN",
    "sg:tags":[
        "farm",
        "corn"
    ],
    "wof:name":"Delbert Velzke",
    "wof:placetype":"venue"
},
  "geometry": {"coordinates":[-93.44700400000001,44.167303],"type":"Point"}
}