{
  "type": "Feature",
  "properties": {
    "addr:full":"335 Canal Park Dr Duluth MN 55802",
    "addr:housenumber":"335",
    "addr:postcode":"55802",
    "addr:street":"Canal Park Dr",
    "iso:country":"US",
    "sg:address":"335 Canal Park Dr",
    "sg:city":"Duluth",
    "sg:classifiers":[
        {
            "category":"Shopping",
            "subcategory":"Used Merchandise",
            "type":"Retail Goods"
        }
    ],
    "sg:phone":"+1 218 726 1994",
    "sg:postcode":"55802",
    "sg:province":"MN",
    "sg:tags":[
        "antique"
    ],
    "wof:name":"Antique Centre Duluth",
    "wof:placetype":"venue"
},
  "geometry": {"coordinates":[-92.094303,46.782911],"type":"Point"}
}