{
  "type": "Feature",
  "properties": {
    "addr:full":"905 Hopkins Xrd Hopkins MN 55305",
    "addr:housenumber":"905",
    "addr:postcode":"55305",
    "addr:street":"Hopkins Xrd",
    "iso:country":"US",
    "sg:address":"905 Hopkins Xrd",
    "sg:city":"Hopkins",
    "sg:classifiers":[
        {
            "category":"Insurance",
            "subcategory":"Insurance Agent",
            "type":"Services"
        }
    ],
    "sg:phone":"+1 952 906 1943",
    "sg:postcode":"55305",
    "sg:province":"MN",
    "wof:name":"ABC Insurance",
    "wof:placetype":"venue"
},
  "geometry": {"coordinates":[-93.42057800000001,44.974125],"type":"Point"}
}