{
  "type": "Feature",
  "properties": {
    "addr:full":"530 Industrial Rd Moose Lake MN 55767",
    "addr:housenumber":"530",
    "addr:postcode":"55767",
    "addr:street":"Industrial Rd",
    "iso:country":"US",
    "sg:address":"530 Industrial Rd",
    "sg:city":"Moose Lake",
    "sg:classifiers":[
        {
            "category":"Professional",
            "subcategory":"Management & Consulting",
            "type":"Services"
        }
    ],
    "sg:phone":"+1 218 485 5722",
    "sg:postcode":"55767",
    "sg:province":"MN",
    "sg:tags":[
        "consultant",
        "educational"
    ],
    "wof:name":"Creativity Services",
    "wof:placetype":"venue"
},
  "geometry": {"coordinates":[-92.761555,46.455303],"type":"Point"}
}