{
  "type": "Feature",
  "properties": {
    "iso:country":"US",
    "sg:address":"6307 Burnham Cir",
    "sg:city":"Inver Grove Hts",
    "sg:classifiers":[
        {
            "category":"Social Services",
            "subcategory":"Adult Care",
            "type":"Services"
        }
    ],
    "sg:phone":"+1 651 451 5959",
    "sg:postcode":"55076",
    "sg:province":"MN",
    "sg:tags":[
        "home",
        "facility",
        "intermediate",
        "residential"
    ],
    "wof:name":"Presbyterian Homes of Inver Gr",
    "wof:placetype":"venue"
},
  "geometry": {"coordinates":[-93.04613999999999,44.855275],"type":"Point"}
}