{
  "type": "Feature",
  "properties": {
    "iso:country":"US",
    "sg:address":"2415 W Broadway Ave",
    "sg:city":"Minneapolis",
    "sg:classifiers":[
        {
            "category":"Personal",
            "subcategory":"Barber",
            "type":"Services"
        }
    ],
    "sg:phone":"+1 612 529 1776",
    "sg:postcode":"55411",
    "sg:province":"MN",
    "sg:tags":[
        "shop"
    ],
    "wof:name":"Mr Afro's Barber Shop",
    "wof:placetype":"venue"
},
  "geometry": {"coordinates":[-93.311302,45.005699],"type":"Point"}
}