{
  "type": "Feature",
  "properties": {
    "iso:country":"US",
    "sg:address":"110 N Park St",
    "sg:city":"Fairmont",
    "sg:classifiers":[
        {
            "category":"Education",
            "subcategory":"Library",
            "type":"Public Place"
        }
    ],
    "sg:phone":"+1 507 238 4207",
    "sg:postcode":"56031",
    "sg:province":"MN",
    "wof:name":"Martin County Library",
    "wof:placetype":"venue"
},
  "geometry": {"coordinates":[-94.460808,43.653854],"type":"Point"}
}