{
  "type": "Feature",
  "properties": {
    "addr:full":"14715 Krypton St NW Anoka MN 55303",
    "addr:postcode":"14715;55303",
    "addr:street":"Krypton St Nw",
    "iso:country":"US",
    "sg:address":"14715 Krypton St NW",
    "sg:city":"Anoka",
    "sg:classifiers":[
        {
            "category":"Professional",
            "subcategory":"Management & Consulting",
            "type":"Services"
        }
    ],
    "sg:phone":"+1 763 421 3790",
    "sg:postcode":"55303",
    "sg:province":"MN",
    "sg:tags":[
        "business"
    ],
    "wof:name":"Spirit of Hospitality",
    "wof:placetype":"venue"
},
  "geometry": {"coordinates":[-93.411693,45.238383],"type":"Point"}
}