{
  "type": "Feature",
  "properties": {
    "addr:full":"13105 W 6th St Duluth MN 55808",
    "addr:housenumber":"13105",
    "addr:postcode":"55808",
    "addr:street":"W 6Th St",
    "iso:country":"US",
    "sg:address":"13105 W 6th St",
    "sg:city":"Duluth",
    "sg:classifiers":[
        {
            "category":"Shopping",
            "subcategory":"Books",
            "type":"Retail Goods"
        }
    ],
    "sg:phone":"+1 218 626 0038",
    "sg:postcode":"55808",
    "sg:province":"MN",
    "wof:name":"Bible House",
    "wof:placetype":"venue"
},
  "geometry": {"coordinates":[-92.27477500000001,46.662728],"type":"Point"}
}