{
  "type": "Feature",
  "properties": {
    "addr:full":"1 Main St N Aurora MN 55705",
    "addr:housenumber":"1",
    "addr:postcode":"55705",
    "addr:street":"Main St N",
    "iso:country":"US",
    "sg:address":"1 Main St N",
    "sg:city":"Aurora",
    "sg:classifiers":[
        {
            "category":"Shopping",
            "subcategory":"Musical Instruments",
            "type":"Retail Goods"
        }
    ],
    "sg:phone":"+1 218 229 2107",
    "sg:postcode":"55705",
    "sg:province":"MN",
    "sg:website":"www.scottsundergroundsound.com",
    "wof:name":"Scott's Underground Sound",
    "wof:placetype":"venue"
},
  "geometry": {"coordinates":[-92.236767,47.528209],"type":"Point"}
}