{
  "type": "Feature",
  "properties": {
    "addr:full":"5880 73rd Ave N Minneapolis MN 55429",
    "addr:housenumber":"5880",
    "addr:postcode":"55429",
    "addr:street":"73Rd Ave N",
    "iso:country":"US",
    "sg:address":"5880 73rd Ave N",
    "sg:city":"Minneapolis",
    "sg:classifiers":[
        {
            "category":"Building & Trades",
            "subcategory":"Construction",
            "type":"Services"
        }
    ],
    "sg:phone":"+1 763 424 3342",
    "sg:postcode":"55429",
    "sg:province":"MN",
    "sg:tags":[
        "contractor"
    ],
    "wof:name":"Williams Exteriors Inc",
    "wof:placetype":"venue"
},
  "geometry": {"coordinates":[-93.356229,45.087329],"type":"Point"}
}