{
  "type": "Feature",
  "properties": {
    "addr:full":"15477 Co Hwy 35 Dalton MN 56324",
    "addr:housenumber":"15477",
    "addr:postcode":"56324",
    "addr:street":"Co Hwy 35",
    "iso:country":"US",
    "sg:address":"15477 Co Hwy 35",
    "sg:city":"Dalton",
    "sg:classifiers":[
        {
            "category":"Wholesale",
            "subcategory":"Machinery & Supplies",
            "type":"Manufacturing & Wholesale Goods"
        }
    ],
    "sg:phone":"+1 218 589 7502",
    "sg:postcode":"56324",
    "sg:province":"MN",
    "sg:tags":[
        "equipment",
        "establishment"
    ],
    "wof:name":"Natural Images Taxidermy",
    "wof:placetype":"venue"
},
  "geometry": {"coordinates":[-95.905557,46.193259],"type":"Point"}
}