{
  "type": "Feature",
  "properties": {
    "addr:full":"707 W Arrowhead Rd Duluth MN 55811",
    "addr:housenumber":"707",
    "addr:postcode":"55811",
    "addr:street":"W Arrowhead Rd",
    "iso:country":"US",
    "sg:address":"707 W Arrowhead Rd",
    "sg:city":"Duluth",
    "sg:classifiers":[
        {
            "category":"Social Services",
            "type":"Services"
        }
    ],
    "sg:phone":"+1 218 727 2696",
    "sg:postcode":"55811",
    "sg:province":"MN",
    "sg:tags":[
        "organization",
        "welfare"
    ],
    "wof:name":"Residential Services Inc II",
    "wof:placetype":"venue"
},
  "geometry": {"coordinates":[-92.083618,46.825929],"type":"Point"}
}