{
  "type": "Feature",
  "properties": {
    "addr:full":"1016 Smith Ave S West St Paul MN 55118",
    "addr:housenumber":"1016",
    "addr:postcode":"55118",
    "addr:street":"Smith Ave S",
    "iso:country":"US",
    "sg:address":"1016 Smith Ave S",
    "sg:city":"West St Paul",
    "sg:classifiers":[
        {
            "category":"Cinema",
            "subcategory":"Movie Rental",
            "type":"Entertainment"
        }
    ],
    "sg:phone":"+1 651 451 7170",
    "sg:postcode":"55118",
    "sg:province":"MN",
    "sg:tags":[
        "leasing",
        "video",
        "disc",
        "tape"
    ],
    "wof:name":"Home Video",
    "wof:placetype":"venue"
},
  "geometry": {"coordinates":[-93.10171699999999,44.913006],"type":"Point"}
}