{
  "type": "Feature",
  "properties": {
    "iso:country":"US",
    "sg:address":"314 N Main St",
    "sg:city":"Fairmont",
    "sg:classifiers":[
        {
            "category":"Building & Trades",
            "subcategory":"Electrical",
            "type":"Services"
        }
    ],
    "sg:phone":"+1 507 235 9034",
    "sg:postcode":"56031",
    "sg:province":"MN",
    "sg:tags":[
        "electric",
        "contractor"
    ],
    "wof:name":"Boesch Electrical Construction",
    "wof:placetype":"venue"
},
  "geometry": {"coordinates":[-94.46365400000001,43.655614],"type":"Point"}
}