{
  "type": "Feature",
  "properties": {
    "addr:full":"4988 Vermilion Trl Gilbert MN 55741",
    "addr:housenumber":"4988",
    "addr:postcode":"55741",
    "addr:street":"Vermilion Trl",
    "iso:country":"US",
    "sg:address":"4988 Vermilion Trl",
    "sg:city":"Gilbert",
    "sg:classifiers":[
        {
            "category":"Professional",
            "subcategory":"Business Services",
            "type":"Services"
        }
    ],
    "sg:phone":"+1 218 865 4383",
    "sg:postcode":"55741",
    "sg:province":"MN",
    "sg:tags":[
        "inspection"
    ],
    "wof:name":"JBN Inc",
    "wof:placetype":"venue"
},
  "geometry": {"coordinates":[-92.34129299999999,47.479334],"type":"Point"}
}