{
  "type": "Feature",
  "properties": {
    "iso:country":"US",
    "sg:address":"5829 Jeff Pl",
    "sg:city":"Minneapolis",
    "sg:classifiers":[
        {
            "category":"Health Services",
            "subcategory":"Clinic",
            "type":"Services"
        }
    ],
    "sg:phone":"+1 952 926 9190",
    "sg:postcode":"55436",
    "sg:province":"MN",
    "sg:tags":[
        "welfare"
    ],
    "wof:name":"Solutions For Wellness Inc",
    "wof:placetype":"venue"
},
  "geometry": {"coordinates":[-93.371039,44.892812],"type":"Point"}
}