{
  "type": "Feature",
  "properties": {
    "iso:country":"US",
    "sg:address":"5101 W 98th St",
    "sg:city":"Minneapolis",
    "sg:classifiers":[
        {
            "category":"Personal",
            "subcategory":"Nail Salon",
            "type":"Services"
        }
    ],
    "sg:phone":"+1 952 835 5337",
    "sg:postcode":"55437",
    "sg:province":"MN",
    "wof:name":"N K Spa Nails",
    "wof:placetype":"venue"
},
  "geometry": {"coordinates":[-93.345933,44.82462],"type":"Point"}
}