{
  "type": "Feature",
  "properties": {
    "addr:full":"1364 Cedarwood Cir Saint Paul MN 55125",
    "addr:housenumber":"1364",
    "addr:postcode":"55125",
    "addr:street":"Cedarwood Cir",
    "iso:country":"US",
    "sg:address":"1364 Cedarwood Cir",
    "sg:city":"Saint Paul",
    "sg:classifiers":[
        {
            "category":"Health Services",
            "subcategory":"Chiropractor",
            "type":"Services"
        }
    ],
    "sg:phone":"+1 651 739 7246",
    "sg:postcode":"55125",
    "sg:province":"MN",
    "wof:name":"Earl R Josephson DC",
    "wof:placetype":"venue"
},
  "geometry": {"coordinates":[-92.982618,44.928362],"type":"Point"}
}