{
  "type": "Feature",
  "properties": {
    "iso:country":"US",
    "sg:address":"701 Decatur Ave N",
    "sg:city":"Minneapolis",
    "sg:classifiers":[
        {
            "category":"Communications",
            "type":"Services"
        },
        {
            "category":"Professional",
            "subcategory":"Computer Services",
            "type":"Services"
        }
    ],
    "sg:phone":"+1 763 544 6807",
    "sg:postcode":"55427",
    "sg:province":"MN",
    "sg:tags":[
        "equipment",
        "telecommunication",
        "systems-repair",
        "telephone"
    ],
    "wof:name":"IDEACOM MID-AMERICA",
    "wof:placetype":"venue"
},
  "geometry": {"coordinates":[-93.392853,44.985722],"type":"Point"}
}