{
  "type": "Feature",
  "properties": {
    "addr:full":"32 Hamel Rd Hamel MN 55340",
    "addr:housenumber":"32",
    "addr:postcode":"55340",
    "addr:street":"Hamel Rd",
    "iso:country":"US",
    "sg:address":"32 Hamel Rd",
    "sg:city":"Hamel",
    "sg:classifiers":[
        {
            "category":"Banks & Credit Unions",
            "subcategory":"Financial Services",
            "type":"Services"
        }
    ],
    "sg:phone":"+1 763 478 9064",
    "sg:postcode":"55340",
    "sg:province":"MN",
    "sg:tags":[
        "company",
        "holding"
    ],
    "wof:name":"Provenance Holding LLC",
    "wof:placetype":"venue"
},
  "geometry": {"coordinates":[-93.531927,45.041994],"type":"Point"}
}