{
  "type": "Feature",
  "properties": {
    "iso:country":"US",
    "sg:address":"424 Harding St NE",
    "sg:city":"Minneapolis",
    "sg:classifiers":[
        {
            "category":"Transit Center",
            "subcategory":"Freight",
            "type":"Transportation"
        },
        {
            "category":"Freight",
            "type":"Transportation"
        }
    ],
    "sg:phone":"+1 763 302 5763",
    "sg:postcode":"55413",
    "sg:province":"MN",
    "sg:tags":[
        "local",
        "trucking-motor",
        "trucking"
    ],
    "wof:name":"Stan Koch Sons Trucking I",
    "wof:placetype":"venue"
},
  "geometry": {"coordinates":[-93.221524,44.993948],"type":"Point"}
}