{
  "type": "Feature",
  "properties": {
    "addr:full":"4000 Quincy St NE Minneapolis MN 55421",
    "addr:housenumber":"4000",
    "addr:postcode":"55421",
    "addr:street":"Quincy St Ne",
    "iso:country":"US",
    "sg:address":"4000 Quincy St NE",
    "sg:city":"Minneapolis",
    "sg:phone":"+1 763 789 8710",
    "sg:postcode":"55421",
    "sg:province":"MN",
    "wof:name":"Greater Life Tabernacle",
    "wof:placetype":"venue"
},
  "geometry": {"coordinates":[-93.251198,45.040958],"type":"Point"}
}