{
  "type": "Feature",
  "properties": {
    "addr:full":"3334 White Oaks Ln Saint Paul MN 55125",
    "addr:housenumber":"3334",
    "addr:postcode":"55125",
    "addr:street":"White Oaks Ln",
    "iso:country":"US",
    "sg:address":"3334 White Oaks Ln",
    "sg:city":"Saint Paul",
    "sg:classifiers":[
        {
            "category":"Professional",
            "subcategory":"Employment Agencies",
            "type":"Services"
        }
    ],
    "sg:phone":"+1 651 501 6036",
    "sg:postcode":"55125",
    "sg:province":"MN",
    "wof:name":"Rencor",
    "wof:placetype":"venue"
},
  "geometry": {"coordinates":[-92.95331,44.900091],"type":"Point"}
}