{
  "type": "Feature",
  "properties": {
    "iso:country":"US",
    "sg:address":"970 Raymond Ave",
    "sg:city":"St Paul",
    "sg:classifiers":[
        {
            "category":"Health Services",
            "subcategory":"Chiropractor",
            "type":"Services"
        }
    ],
    "sg:phone":"+1 651 644 0455",
    "sg:postcode":"55114",
    "sg:province":"MN",
    "wof:name":"Midtown Chiropractic",
    "wof:placetype":"venue"
},
  "geometry": {"coordinates":[-93.19750000000001,44.970069],"type":"Point"}
}