{
  "type": "Feature",
  "properties": {
    "addr:full":"Rosedale Marketplace 2401 Fairview Avenue North Roseville MN 55113",
    "addr:housenumber":"2401",
    "addr:postcode":"55113",
    "addr:street":"Fairview Avenue North",
    "iso:country":"US",
    "sg:address":"Rosedale Marketplace 2401 Fairview Avenue North",
    "sg:city":"Roseville",
    "sg:classifiers":[
        {
            "category":"Shopping",
            "subcategory":"Stationery & Office Supplies",
            "type":"Retail Goods"
        }
    ],
    "sg:phone":"+1 651 636 9566",
    "sg:postcode":"55113",
    "sg:province":"MN",
    "sg:tags":[
        "equipment"
    ],
    "sg:website":"www.officemax.com",
    "wof:name":"Office Max",
    "wof:placetype":"venue"
},
  "geometry": {"coordinates":[-93.178433,45.013396],"type":"Point"}
}