{
  "type": "Feature",
  "properties": {
    "addr:full":"202 Galewski Dr Winona MN 55987",
    "addr:housenumber":"202",
    "addr:postcode":"55987",
    "addr:street":"Galewski Dr",
    "iso:country":"US",
    "sg:address":"202 Galewski Dr",
    "sg:city":"Winona",
    "sg:classifiers":[
        {
            "category":"Manufacturing",
            "subcategory":"Paper Products",
            "type":"Manufacturing & Wholesale Goods"
        }
    ],
    "sg:phone":"+1 507 452 2315",
    "sg:postcode":"55987",
    "sg:province":"MN",
    "sg:tags":[
        "box"
    ],
    "sg:website":"www.boelterindustries.com",
    "wof:name":"Boelter Industries Inc",
    "wof:placetype":"venue"
},
  "geometry": {"coordinates":[-91.707353,44.073228],"type":"Point"}
}