{
  "type": "Feature",
  "properties": {
    "iso:country":"US",
    "sg:address":"120 Norman Ave S",
    "sg:city":"Foley",
    "sg:classifiers":[
        {
            "category":"Social Services",
            "type":"Services"
        }
    ],
    "sg:phone":"+1 320 968 6425",
    "sg:postcode":"56329",
    "sg:province":"MN",
    "wof:name":"Heritage Pl Senior Apartments",
    "wof:placetype":"venue"
},
  "geometry": {"coordinates":[-93.91511199999999,45.661114],"type":"Point"}
}