{
  "type": "Feature",
  "properties": {
    "addr:full":"11201 Hampshire Ave S Bloomington MN 55438",
    "addr:housenumber":"11201",
    "addr:postcode":"55438",
    "addr:street":"Hampshire Ave S",
    "iso:country":"US",
    "sg:address":"11201 Hampshire Ave S",
    "sg:city":"Bloomington",
    "sg:classifiers":[
        {
            "category":"Manufacturing",
            "subcategory":"Tools & Machinery",
            "type":"Manufacturing & Wholesale Goods"
        }
    ],
    "sg:phone":"+1 952 829 5444",
    "sg:postcode":"55438",
    "sg:province":"MN",
    "sg:tags":[
        "photographic",
        "supply"
    ],
    "wof:name":"Gretag Imaging Lab Systems",
    "wof:placetype":"venue"
},
  "geometry": {"coordinates":[-93.368799,44.799432],"type":"Point"}
}