{
  "type": "Feature",
  "properties": {
    "addr:full":"14531 Forest Blvd N Hugo MN 55038",
    "addr:housenumber":"14531",
    "addr:postcode":"55038",
    "addr:street":"Forest Blvd N Hugo",
    "iso:country":"US",
    "sg:address":"14531 Forest Blvd N",
    "sg:city":"Hugo",
    "sg:classifiers":[
        {
            "category":"Restaurant",
            "type":"Food & Drink"
        }
    ],
    "sg:menulink":"http://www.allmenus.com/mn/hugo/58440-dominos-pizza/menu/",
    "sg:phone":"+1 651 426 3030",
    "sg:postcode":"55038",
    "sg:province":"MN",
    "sg:tags":[
        "american",
        "wing",
        "pizza"
    ],
    "wof:name":"Domino's Pizza",
    "wof:placetype":"venue"
},
  "geometry": {"coordinates":[-92.993139,45.160225],"type":"Point"}
}