{
  "type": "Feature",
  "properties": {
    "iso:country":"US",
    "sg:address":"1280 Lyman Ave",
    "sg:city":"Wayzata",
    "sg:classifiers":[
        {
            "category":"Travel",
            "subcategory":"Travel Agent",
            "type":"Entertainment"
        }
    ],
    "sg:phone":"+1 763 258 1280",
    "sg:postcode":"55391",
    "sg:province":"MN",
    "sg:tags":[
        "agency"
    ],
    "wof:name":"Northern Traveler",
    "wof:placetype":"venue"
},
  "geometry": {"coordinates":[-93.555311,44.977552],"type":"Point"}
}