{
  "type": "Feature",
  "properties": {
    "addr:full":"3344 Big North Rd NW Bemidji MN 56601",
    "addr:housenumber":"3344",
    "addr:postcode":"56601",
    "addr:street":"Big North Rd Nw",
    "iso:country":"US",
    "sg:address":"3344 Big North Rd NW",
    "sg:city":"Bemidji",
    "sg:classifiers":[
        {
            "category":"Health Services",
            "subcategory":"Medical Lab",
            "type":"Services"
        }
    ],
    "sg:phone":"+1 218 444 6625",
    "sg:postcode":"56601",
    "sg:province":"MN",
    "wof:name":"Michael M Mock",
    "wof:placetype":"venue"
},
  "geometry": {"coordinates":[-94.931231,47.479487],"type":"Point"}
}