{
  "type": "Feature",
  "properties": {
    "addr:full":"8653 Hwy 27 E Osakis MN 56360",
    "addr:housenumber":"8653",
    "addr:postcode":"56360",
    "addr:street":"Hwy 27 E",
    "iso:country":"US",
    "sg:address":"8653 Hwy 27 E",
    "sg:city":"Osakis",
    "sg:classifiers":[
        {
            "category":"Farming",
            "subcategory":"Livestock Farm",
            "type":"Manufacturing & Wholesale Goods"
        }
    ],
    "sg:phone":"+1 320 763 3415",
    "sg:postcode":"56360",
    "sg:province":"MN",
    "sg:tags":[
        "feedlot",
        "hog",
        "or",
        "beef",
        "cattle"
    ],
    "wof:name":"Tony Rassat",
    "wof:placetype":"venue"
},
  "geometry": {"coordinates":[-95.258353,45.878563],"type":"Point"}
}