{
  "type": "Feature",
  "properties": {
    "iso:country":"US",
    "sg:address":"44956 Birch Hill Rd",
    "sg:city":"Melrose",
    "sg:classifiers":[
        {
            "category":"Farming",
            "subcategory":"Farm",
            "type":"Manufacturing & Wholesale Goods"
        }
    ],
    "sg:phone":"+1 320 256 7511",
    "sg:postcode":"56352",
    "sg:province":"MN",
    "wof:name":"ACE Farm",
    "wof:placetype":"venue"
},
  "geometry": {"coordinates":[-94.764534,45.771791],"type":"Point"}
}