{
  "type": "Feature",
  "properties": {
    "iso:country":"US",
    "sg:address":"7635 S Bay Dr",
    "sg:city":"Minneapolis",
    "sg:classifiers":[
        {
            "category":"Real Estate",
            "subcategory":"Real Estate Agent",
            "type":"Services"
        }
    ],
    "sg:phone":"+1 952 844 6109",
    "sg:postcode":"55438",
    "sg:province":"MN",
    "wof:name":"Pam Mogen Realtor",
    "wof:placetype":"venue"
},
  "geometry": {"coordinates":[-93.38373900000001,44.826861],"type":"Point"}
}