{
  "type": "Feature",
  "properties": {
    "addr:full":"7300 147th St W Saint Paul MN 55124",
    "addr:housenumber":"7300",
    "addr:postcode":"55124",
    "addr:street":"147Th St W",
    "iso:country":"US",
    "sg:address":"7300 147th St W",
    "sg:city":"Saint Paul",
    "sg:classifiers":[
        {
            "category":"Professional",
            "subcategory":"Lawyer & Legal Services",
            "type":"Services"
        }
    ],
    "sg:phone":"+1 952 432 3136",
    "sg:postcode":"55124",
    "sg:province":"MN",
    "wof:name":"Michael E Molenda",
    "wof:placetype":"venue"
},
  "geometry": {"coordinates":[-93.213626,44.734716],"type":"Point"}
}