{
  "type": "Feature",
  "properties": {
    "addr:full":"2604 Aga Dr Alexandria MN 56308",
    "addr:housenumber":"2604",
    "addr:postcode":"56308",
    "addr:street":"Aga Dr",
    "iso:country":"US",
    "sg:address":"2604 Aga Dr",
    "sg:city":"Alexandria",
    "sg:classifiers":[
        {
            "category":"Airport",
            "type":"Transportation"
        }
    ],
    "sg:phone":"+1 320 762 2111",
    "sg:postcode":"56308",
    "sg:province":"MN",
    "wof:name":"Alexandria Aviation Inc",
    "wof:placetype":"venue"
},
  "geometry": {"coordinates":[-95.387439,45.865834],"type":"Point"}
}