{
  "type": "Feature",
  "properties": {
    "iso:country":"US",
    "sg:address":"2900 Lone Oak Pkwy",
    "sg:city":"Saint Paul",
    "sg:classifiers":[
        {
            "category":"Professional",
            "subcategory":"Management & Consulting",
            "type":"Services"
        }
    ],
    "sg:phone":"+1 651 452 4396",
    "sg:postcode":"55121",
    "sg:province":"MN",
    "sg:tags":[
        "business"
    ],
    "wof:name":"Foth & Van Dyke and Associates",
    "wof:placetype":"venue"
},
  "geometry": {"coordinates":[-93.125838,44.853513],"type":"Point"}
}