{
  "type": "Feature",
  "properties": {
    "iso:country":"US",
    "sg:address":"2248 Bunker Lake Blvd NW",
    "sg:city":"Andover",
    "sg:classifiers":[
        {
            "category":"Shopping",
            "subcategory":"Tobacco",
            "type":"Retail Goods"
        }
    ],
    "sg:phone":"+1 763 767 3397",
    "sg:postcode":"55304",
    "sg:province":"MN",
    "sg:tags":[
        "cigarette",
        "product",
        "cigar",
        "dealer"
    ],
    "wof:name":"Tobacco Shop",
    "wof:placetype":"venue"
},
  "geometry": {"coordinates":[-93.322292,45.219609],"type":"Point"}
}