{
  "type": "Feature",
  "properties": {
    "addr:full":"702 Clearbrook Ln Saint Paul MN 55127",
    "addr:housenumber":"702",
    "addr:postcode":"55127",
    "addr:street":"Clearbrook Ln",
    "iso:country":"US",
    "sg:address":"702 Clearbrook Ln",
    "sg:city":"Saint Paul",
    "sg:classifiers":[
        {
            "category":"Professional",
            "type":"Services"
        }
    ],
    "sg:phone":"+1 651 426 1130",
    "sg:postcode":"55127",
    "sg:province":"MN",
    "wof:name":"Spiritfire Coaching & Facilita",
    "wof:placetype":"venue"
},
  "geometry": {"coordinates":[-93.070533,45.074849],"type":"Point"}
}