{
  "type": "Feature",
  "properties": {
    "addr:full":"41285 Chasewood Rd Deer River MN 56636",
    "addr:housenumber":"41285",
    "addr:postcode":"56636",
    "addr:street":"Chasewood Rd",
    "iso:country":"US",
    "sg:address":"41285 Chasewood Rd",
    "sg:city":"Deer River",
    "sg:classifiers":[
        {
            "category":"Building & Trades",
            "subcategory":"Construction",
            "type":"Services"
        }
    ],
    "sg:phone":"+1 218 246 8970",
    "sg:postcode":"56636",
    "sg:province":"MN",
    "sg:tags":[
        "hanging",
        "contractor"
    ],
    "wof:name":"J Rick Interiors",
    "wof:placetype":"venue"
},
  "geometry": {"coordinates":[-93.729308,47.367448],"type":"Point"}
}