{
  "type": "Feature",
  "properties": {
    "addr:full":"115 S Newton Ave Albert Lea MN 56007",
    "addr:housenumber":"115",
    "addr:postcode":"56007",
    "addr:street":"S Newton Ave",
    "iso:country":"US",
    "sg:address":"115 S Newton Ave",
    "sg:city":"Albert Lea",
    "sg:classifiers":[
        {
            "category":"Insurance",
            "subcategory":"Insurance Agent",
            "type":"Services"
        }
    ],
    "sg:phone":"+1 507 373 2181",
    "sg:postcode":"56007",
    "sg:province":"MN",
    "wof:name":"Fred Nelson Agency",
    "wof:placetype":"venue"
},
  "geometry": {"coordinates":[-93.367294,43.649618],"type":"Point"}
}