{
  "type": "Feature",
  "properties": {
    "addr:full":"14312 Burnhaven Dr Burnsville MN 55306",
    "addr:housenumber":"14312",
    "addr:postcode":"55306",
    "addr:street":"Burnhaven Dr",
    "iso:country":"US",
    "sg:address":"14312 Burnhaven Dr",
    "sg:city":"Burnsville",
    "sg:classifiers":[
        {
            "category":"Professional",
            "type":"Services"
        }
    ],
    "sg:phone":"+1 952 435 2124",
    "sg:postcode":"55306",
    "sg:province":"MN",
    "wof:name":"Picture Perfect Scrapbooking I",
    "wof:placetype":"venue"
},
  "geometry": {"coordinates":[-93.293605,44.742996],"type":"Point"}
}