{
  "type": "Feature",
  "properties": {
    "addr:full":"401 20th St S New Ulm MN 56073",
    "addr:housenumber":"401",
    "addr:postcode":"56073",
    "addr:street":"20Th St S",
    "iso:country":"US",
    "sg:address":"401 20th St S",
    "sg:city":"New Ulm",
    "sg:classifiers":[
        {
            "category":"Retail",
            "subcategory":"Veterinary Services",
            "type":"Services"
        }
    ],
    "sg:phone":"+1 507 233 2500",
    "sg:postcode":"56073",
    "sg:province":"MN",
    "wof:name":"New Ulm Rgional Veterinary Ctr",
    "wof:placetype":"venue"
},
  "geometry": {"coordinates":[-94.439257,44.294198],"type":"Point"}
}