{
  "type": "Feature",
  "properties": {
    "addr:full":"48291 440th St Sauk Centre MN 56378",
    "addr:housenumber":"48291",
    "addr:postcode":"56378",
    "addr:street":"440Th St",
    "iso:country":"US",
    "sg:address":"48291 440th St",
    "sg:city":"Sauk Centre",
    "sg:phone":"+1 320 352 3123",
    "sg:postcode":"56378",
    "sg:province":"MN",
    "sg:tags":[
        "farm",
        "soybean"
    ],
    "wof:name":"James Mathaler",
    "wof:placetype":"venue"
},
  "geometry": {"coordinates":[-95.111194,45.758987],"type":"Point"}
}