{
  "type": "Feature",
  "properties": {
    "iso:country":"US",
    "sg:address":"26794 Hoffman Rd",
    "sg:city":"Hillman",
    "sg:classifiers":[
        {
            "category":"Building & Trades",
            "subcategory":"Construction",
            "type":"Services"
        }
    ],
    "sg:phone":"+1 320 277 3737",
    "sg:postcode":"56338",
    "sg:province":"MN",
    "sg:tags":[
        "excavation",
        "contractor"
    ],
    "wof:name":"Hoffman Gravel & Excvtg Inc",
    "wof:placetype":"venue"
},
  "geometry": {"coordinates":[-93.919713,46.149268],"type":"Point"}
}