{
  "type": "Feature",
  "properties": {
    "addr:full":"1605 1st St S Willmar MN 56201",
    "addr:housenumber":"1605",
    "addr:postcode":"56201",
    "addr:street":"1St St S",
    "iso:country":"US",
    "sg:address":"1605 1st St S",
    "sg:city":"Willmar",
    "sg:classifiers":[
        {
            "category":"Personal",
            "subcategory":"Beauty Salon",
            "type":"Services"
        }
    ],
    "sg:phone":"+1 320 231 2303",
    "sg:postcode":"56201",
    "sg:province":"MN",
    "sg:tags":[
        "manicuring"
    ],
    "wof:name":"Angel Nails",
    "wof:placetype":"venue"
},
  "geometry": {"coordinates":[-95.04261,45.106862],"type":"Point"}
}