{
  "type": "Feature",
  "properties": {
    "iso:country":"US",
    "sg:address":"29427 Goldenrod St NW",
    "sg:city":"Isanti",
    "sg:classifiers":[
        {
            "category":"Transit Center",
            "subcategory":"Freight",
            "type":"Transportation"
        },
        {
            "category":"Freight",
            "type":"Transportation"
        }
    ],
    "sg:phone":"+1 763 360 2987",
    "sg:postcode":"55040",
    "sg:province":"MN",
    "sg:tags":[
        "local",
        "trucking-motor",
        "trucking"
    ],
    "wof:name":"Jeff Knoll Trucking",
    "wof:placetype":"venue"
},
  "geometry": {"coordinates":[-93.27309700000001,45.502365],"type":"Point"}
}