{
  "type": "Feature",
  "properties": {
    "addr:full":"845 Meadow Ln N Golden Valley MN 55422",
    "addr:housenumber":"845",
    "addr:postcode":"55422",
    "addr:street":"Meadow Ln N",
    "iso:country":"US",
    "sg:address":"845 Meadow Ln N",
    "sg:city":"Golden Valley",
    "sg:classifiers":[
        {
            "category":"Animal Shelter",
            "type":"Public Place"
        }
    ],
    "sg:phone":"+1 763 489 2201",
    "sg:postcode":"55422",
    "sg:province":"MN",
    "sg:website":"www.animalhumanesociety.org",
    "wof:name":"Animal Humane Society",
    "wof:placetype":"venue"
},
  "geometry": {"coordinates":[-93.329345,44.987267],"type":"Point"}
}