{
  "type": "Feature",
  "properties": {
    "addr:full":"10045 Hwy 27 W Alexandria MN 56308",
    "addr:housenumber":"10045",
    "addr:postcode":"56308",
    "addr:street":"Hwy 27 W",
    "iso:country":"US",
    "sg:address":"10045 Hwy 27 W",
    "sg:city":"Alexandria",
    "sg:classifiers":[
        {
            "category":"Travel",
            "subcategory":"Hotels & Motels",
            "type":"Entertainment"
        }
    ],
    "sg:phone":"+1 320 886 5688",
    "sg:postcode":"56308",
    "sg:province":"MN",
    "sg:tags":[
        "operation"
    ],
    "wof:name":"Sun Valley Resort",
    "wof:placetype":"venue"
},
  "geometry": {"coordinates":[-95.524815,45.845978],"type":"Point"}
}