{
  "type": "Feature",
  "properties": {
    "addr:full":"731 8th Ave Two Harbors MN 55616",
    "addr:housenumber":"731",
    "addr:postcode":"55616",
    "addr:street":"8Th Ave",
    "iso:country":"US",
    "sg:address":"731 8th Ave",
    "sg:city":"Two Harbors",
    "sg:classifiers":[
        {
            "category":"Building & Trades",
            "subcategory":"Construction",
            "type":"Services"
        }
    ],
    "sg:phone":"+1 218 830 1606",
    "sg:postcode":"55616",
    "sg:province":"MN",
    "sg:tags":[
        "residential"
    ],
    "wof:name":"Brenna Construction & Rmdlg",
    "wof:placetype":"venue"
},
  "geometry": {"coordinates":[-91.674207,47.026744],"type":"Point"}
}