{
  "type": "Feature",
  "properties": {
    "addr:full":"370 Summit Ave Saint Paul MN 55102",
    "addr:housenumber":"370",
    "addr:postcode":"55102",
    "addr:street":"Summit Ave",
    "iso:country":"US",
    "sg:address":"370 Summit Ave",
    "sg:city":"Saint Paul",
    "sg:classifiers":[
        {
            "category":"Professional",
            "type":"Services"
        }
    ],
    "sg:phone":"+1 651 227 2153",
    "sg:postcode":"55102",
    "sg:province":"MN",
    "wof:name":"Johnston House Condo Associati",
    "wof:placetype":"venue"
},
  "geometry": {"coordinates":[-93.11511,44.943075],"type":"Point"}
}