{
  "type": "Feature",
  "properties": {
    "addr:full":"1020 Stearns St Crookston MN 56716",
    "addr:housenumber":"1020",
    "addr:postcode":"56716",
    "addr:street":"Stearns St",
    "iso:country":"US",
    "sg:address":"1020 Stearns St",
    "sg:city":"Crookston",
    "sg:classifiers":[
        {
            "category":"Professional",
            "subcategory":"Business Services",
            "type":"Services"
        }
    ],
    "sg:phone":"+1 218 281 7938",
    "sg:postcode":"56716",
    "sg:province":"MN",
    "wof:name":"J & J Halland Ltd Partnership",
    "wof:placetype":"venue"
},
  "geometry": {"coordinates":[-96.599884,47.782333],"type":"Point"}
}