{
  "type": "Feature",
  "properties": {
    "addr:full":"58742 85th St Wells MN 56097",
    "addr:housenumber":"58742",
    "addr:postcode":"56097",
    "addr:street":"85Th St",
    "iso:country":"US",
    "sg:address":"58742 85th St",
    "sg:city":"Wells",
    "sg:phone":"+1 507 294 3194",
    "sg:postcode":"56097",
    "sg:province":"MN",
    "sg:tags":[
        "farm",
        "corn",
        "soybean"
    ],
    "wof:name":"Marvin Courrier",
    "wof:placetype":"venue"
},
  "geometry": {"coordinates":[-93.69338399999999,43.6083],"type":"Point"}
}