{
  "type": "Feature",
  "properties": {
    "addr:full":"5461 N Shore Dr Duluth MN 55804",
    "addr:housenumber":"5461",
    "addr:postcode":"55804",
    "addr:street":"N Shore Dr",
    "iso:country":"US",
    "sg:address":"5461 N Shore Dr",
    "sg:city":"Duluth",
    "sg:classifiers":[
        {
            "category":"Restaurant",
            "type":"Food & Drink"
        }
    ],
    "sg:phone":"+1 218 525 6274",
    "sg:postcode":"55804",
    "sg:province":"MN",
    "sg:tags":[
        "eating"
    ],
    "sg:website":"www.sceniccafe.com",
    "wof:name":"New Scenic Cafe Inc",
    "wof:placetype":"venue"
},
  "geometry": {"coordinates":[-91.87140100000001,46.908792],"type":"Point"}
}