{
  "type": "Feature",
  "properties": {
    "addr:full":"1204 W Lake St Minneapolis MN 55408",
    "addr:housenumber":"1204",
    "addr:postcode":"55408",
    "addr:street":"W Lake St",
    "iso:country":"US",
    "sg:address":"1204 W Lake St",
    "sg:city":"Minneapolis",
    "sg:classifiers":[
        {
            "category":"Wholesale",
            "subcategory":"Apparel",
            "type":"Manufacturing & Wholesale Goods"
        }
    ],
    "sg:phone":"+1 763 449 5292",
    "sg:postcode":"55408",
    "sg:province":"MN",
    "sg:tags":[
        "clothing"
    ],
    "wof:name":"Creative Design Group Inc",
    "wof:placetype":"venue"
},
  "geometry": {"coordinates":[-93.295693,44.948439],"type":"Point"}
}