{
  "type": "Feature",
  "properties": {
    "addr:full":"332 Laurel St W Stillwater MN 55082",
    "addr:housenumber":"332",
    "addr:postcode":"55082",
    "addr:street":"Laurel St W",
    "iso:country":"US",
    "sg:address":"332 Laurel St W",
    "sg:city":"Stillwater",
    "sg:classifiers":[
        {
            "category":"Social Services",
            "subcategory":"Child Care",
            "type":"Services"
        }
    ],
    "sg:phone":"+1 651 439 5732",
    "sg:postcode":"55082",
    "sg:province":"MN",
    "sg:tags":[
        "daycare",
        "provider"
    ],
    "wof:name":"Pattys Daycare",
    "wof:placetype":"venue"
},
  "geometry": {"coordinates":[-92.8139,45.060146],"type":"Point"}
}