{
  "type": "Feature",
  "properties": {
    "addr:full":"53018 158th St Garden City MN 56034",
    "addr:housenumber":"53018",
    "addr:postcode":"56034",
    "addr:street":"158Th St",
    "iso:country":"US",
    "sg:address":"53018 158th St",
    "sg:city":"Garden City",
    "sg:classifiers":[
        {
            "category":"Wholesale",
            "subcategory":"Machinery & Supplies",
            "type":"Manufacturing & Wholesale Goods"
        },
        {
            "category":"Manufacturing",
            "subcategory":"Tools & Machinery",
            "type":"Manufacturing & Wholesale Goods"
        }
    ],
    "sg:phone":"+1 507 549 3779",
    "sg:postcode":"56034",
    "sg:province":"MN",
    "sg:tags":[
        "feed",
        "equipment",
        "mill",
        "industrial"
    ],
    "wof:name":"Sprout-Matador Inc",
    "wof:placetype":"venue"
},
  "geometry": {"coordinates":[-94.160301,44.007386],"type":"Point"}
}