{
  "type": "Feature",
  "properties": {
    "addr:full":"8916 Kirkwood Cir Osseo MN 55369",
    "addr:housenumber":"8916",
    "addr:postcode":"55369",
    "addr:street":"Kirkwood Cir",
    "iso:country":"US",
    "sg:address":"8916 Kirkwood Cir",
    "sg:city":"Osseo",
    "sg:classifiers":[
        {
            "category":"Building & Trades",
            "subcategory":"Construction",
            "type":"Services"
        }
    ],
    "sg:phone":"+1 763 424 3293",
    "sg:postcode":"55369",
    "sg:province":"MN",
    "sg:tags":[
        "excavation",
        "contractor"
    ],
    "wof:name":"Wood Dale Atmtive/ Ryder Rentl",
    "wof:placetype":"venue"
},
  "geometry": {"coordinates":[-93.435041,45.117295],"type":"Point"}
}