{
  "type": "Feature",
  "properties": {
    "addr:full":"12490 55th St NE Foley MN 56329",
    "addr:housenumber":"12490",
    "addr:postcode":"56329",
    "addr:street":"55Th St Ne",
    "iso:country":"US",
    "sg:address":"12490 55th St NE",
    "sg:city":"Foley",
    "sg:classifiers":[
        {
            "category":"Social Services",
            "subcategory":"Child Care",
            "type":"Services"
        }
    ],
    "sg:phone":"+1 320 968 7910",
    "sg:postcode":"56329",
    "sg:province":"MN",
    "sg:tags":[
        "daycare",
        "provider"
    ],
    "wof:name":"Jennifer Fogel",
    "wof:placetype":"venue"
},
  "geometry": {"coordinates":[-93.905755,45.647874],"type":"Point"}
}