{
  "type": "Feature",
  "properties": {
    "addr:full":"50901 360th St Paynesville MN 56362",
    "addr:housenumber":"50901",
    "addr:postcode":"56362",
    "addr:street":"360Th St",
    "iso:country":"US",
    "sg:address":"50901 360th St",
    "sg:city":"Paynesville",
    "sg:classifiers":[
        {
            "category":"Building & Trades",
            "subcategory":"Construction",
            "type":"Services"
        }
    ],
    "sg:phone":"+1 320 276 8607",
    "sg:postcode":"56362",
    "sg:province":"MN",
    "sg:tags":[
        "contractor"
    ],
    "wof:name":"J & J Builders Inc",
    "wof:placetype":"venue"
},
  "geometry": {"coordinates":[-94.749549,45.268522],"type":"Point"}
}