{
  "type": "Feature",
  "properties": {
    "iso:country":"US",
    "sg:address":"3960 Coon Rapids Blvd NW # 200",
    "sg:city":"Minneapolis",
    "sg:classifiers":[
        {
            "category":"Health Services",
            "subcategory":"Doctor",
            "type":"Services"
        }
    ],
    "sg:phone":"+1 763 427 7300",
    "sg:postcode":"55433",
    "sg:province":"MN",
    "sg:tags":[
        "physician",
        "pediatrics-orthopedic",
        "surgeons",
        "orthopedics",
        "surgery",
        "surgeon"
    ],
    "wof:name":"Orthopedic Partners Pa",
    "wof:placetype":"venue"
},
  "geometry": {"coordinates":[-93.367243,45.183461],"type":"Point"}
}