{
  "type": "Feature",
  "properties": {
    "iso:country":"US",
    "sg:address":"7520 Market Place Dr",
    "sg:city":"Eden Prairie",
    "sg:classifiers":[
        {
            "category":"Banks & Credit Unions",
            "subcategory":"Investment Brokerage",
            "type":"Services"
        }
    ],
    "sg:phone":"+1 952 944 8250",
    "sg:postcode":"55344",
    "sg:province":"MN",
    "sg:tags":[
        "advisory",
        "consulting",
        "management"
    ],
    "wof:name":"Fure Financial Inc",
    "wof:placetype":"venue"
},
  "geometry": {"coordinates":[-93.424986,44.868584],"type":"Point"}
}