{
  "type": "Feature",
  "properties": {
    "addr:full":"5100 Eden Ave Minneapolis MN 55436",
    "addr:housenumber":"5100",
    "addr:postcode":"55436",
    "addr:street":"Eden Ave",
    "iso:country":"US",
    "sg:address":"5100 Eden Ave",
    "sg:city":"Minneapolis",
    "sg:classifiers":[
        {
            "category":"Shopping",
            "type":"Retail Goods"
        }
    ],
    "sg:phone":"+1 952 922 1111",
    "sg:postcode":"55436",
    "sg:province":"MN",
    "sg:tags":[
        "enforcement",
        "law",
        "equipment"
    ],
    "wof:name":"Pse Enterprises",
    "wof:placetype":"venue"
},
  "geometry": {"coordinates":[-93.353661,44.909197],"type":"Point"}
}