{
  "type": "Feature",
  "properties": {
    "iso:country":"US",
    "sg:address":"4003 Pennsylvania Ave",
    "sg:city":"Saint Paul",
    "sg:classifiers":[
        {
            "category":"Communications",
            "subcategory":"Film & Video Production",
            "type":"Services"
        }
    ],
    "sg:phone":"+1 651 686 9631",
    "sg:postcode":"55123",
    "sg:province":"MN",
    "sg:tags":[
        "motion"
    ],
    "wof:name":"Thomas Productions",
    "wof:placetype":"venue"
},
  "geometry": {"coordinates":[-93.12752999999999,44.809892],"type":"Point"}
}