{
  "type": "Feature",
  "properties": {
    "addr:full":"13950 Holyoke Path Saint Paul MN 55124",
    "addr:housenumber":"13950",
    "addr:postcode":"55124",
    "addr:street":"Holyoke Path",
    "iso:country":"US",
    "sg:address":"13950 Holyoke Path",
    "sg:city":"Saint Paul",
    "sg:classifiers":[
        {
            "category":"Building & Trades",
            "subcategory":"Construction",
            "type":"Services"
        }
    ],
    "sg:phone":"+1 612 669 9893",
    "sg:postcode":"55124",
    "sg:province":"MN",
    "sg:tags":[
        "floor",
        "laying",
        "contractor"
    ],
    "wof:name":"Martins Wood Flooring LLC",
    "wof:placetype":"venue"
},
  "geometry": {"coordinates":[-93.239394,44.746778],"type":"Point"}
}