{
  "type": "Feature",
  "properties": {
    "addr:full":"320 Sunrise Dr St Peter MN 56082",
    "addr:housenumber":"320",
    "addr:postcode":"56082",
    "addr:street":"Sunrise Dr",
    "iso:country":"US",
    "sg:address":"320 Sunrise Dr",
    "sg:city":"St Peter",
    "sg:classifiers":[
        {
            "category":"Social Services",
            "type":"Services"
        }
    ],
    "sg:phone":"+1 507 934 2222",
    "sg:postcode":"56082",
    "sg:province":"MN",
    "sg:tags":[
        "crisis",
        "intervention"
    ],
    "wof:name":"Nicollet/Sibley Sexual Assault",
    "wof:placetype":"venue"
},
  "geometry": {"coordinates":[-93.960076,44.293286],"type":"Point"}
}