{
  "type": "Feature",
  "properties": {
    "iso:country":"US",
    "sg:address":"851 30th Ave SE",
    "sg:city":"Rochester",
    "sg:classifiers":[
        {
            "category":"Shopping",
            "subcategory":"Books",
            "type":"Retail Goods"
        }
    ],
    "sg:phone":"+1 507 285 7202",
    "sg:postcode":"55904",
    "sg:province":"MN",
    "wof:name":"Rctc Bookstore",
    "wof:placetype":"venue"
},
  "geometry": {"coordinates":[-92.41947500000001,44.01414],"type":"Point"}
}