{
  "type": "Feature",
  "properties": {
    "addr:full":"4633 McDonald Dr N Stillwater MN 55082",
    "addr:housenumber":"4633",
    "addr:postcode":"55082",
    "addr:street":"Mcdonald Dr N",
    "iso:country":"US",
    "sg:address":"4633 McDonald Dr N",
    "sg:city":"Stillwater",
    "sg:classifiers":[
        {
            "category":"Autos & Motor Vehicles",
            "subcategory":"Boat Sales",
            "type":"Retail Goods"
        }
    ],
    "sg:phone":"+1 651 275 0911",
    "sg:postcode":"55082",
    "sg:province":"MN",
    "sg:tags":[
        "repair"
    ],
    "wof:name":"Rilar Marine",
    "wof:placetype":"venue"
},
  "geometry": {"coordinates":[-92.852327,45.015858],"type":"Point"}
}