{
  "type": "Feature",
  "properties": {
    "addr:full":"12315 48th Ave N Plymouth MN 55442",
    "addr:housenumber":"12315",
    "addr:postcode":"55442",
    "addr:street":"48Th Ave N",
    "iso:country":"US",
    "sg:address":"12315 48th Ave N",
    "sg:city":"Plymouth",
    "sg:classifiers":[
        {
            "category":"Health Services",
            "subcategory":"Clinic",
            "type":"Services"
        }
    ],
    "sg:phone":"+1 763 553 1820",
    "sg:postcode":"55442",
    "sg:province":"MN",
    "sg:tags":[
        "home"
    ],
    "wof:name":"Mueller Home Health Care Inc",
    "wof:placetype":"venue"
},
  "geometry": {"coordinates":[-93.436217,45.040839],"type":"Point"}
}