{
  "type": "Feature",
  "properties": {
    "addr:full":"2871 Humboldt Ave S Minneapolis MN 55408",
    "addr:housenumber":"2871",
    "addr:postcode":"55408",
    "addr:street":"Humboldt Ave S",
    "iso:country":"US",
    "sg:address":"2871 Humboldt Ave S",
    "sg:city":"Minneapolis",
    "sg:classifiers":[
        {
            "category":"Utilities",
            "subcategory":"Telephone",
            "type":"Services"
        }
    ],
    "sg:phone":"+1 612 823 2054",
    "sg:postcode":"55408",
    "sg:province":"MN",
    "sg:tags":[
        "communications"
    ],
    "wof:name":"Glenn Shope",
    "wof:placetype":"venue"
},
  "geometry": {"coordinates":[-93.300754,44.949301],"type":"Point"}
}