{
  "type": "Feature",
  "properties": {
    "iso:country":"US",
    "sg:address":"51506 210th Ave",
    "sg:city":"Pine Island",
    "sg:classifiers":[
        {
            "category":"Professional",
            "subcategory":"Business Services",
            "type":"Services"
        }
    ],
    "sg:phone":"+1 507 356 8889",
    "sg:postcode":"55963",
    "sg:province":"MN",
    "wof:name":"Rj Interiors",
    "wof:placetype":"venue"
},
  "geometry": {"coordinates":[-92.611419,44.199573],"type":"Point"}
}