{
  "type": "Feature",
  "properties": {
    "iso:country":"US",
    "sg:address":"29849 Landmark Rd",
    "sg:city":"Brooten",
    "sg:classifiers":[
        {
            "category":"Farming",
            "subcategory":"Dairy Farm",
            "type":"Manufacturing & Wholesale Goods"
        }
    ],
    "sg:phone":"+1 320 346 2807",
    "sg:postcode":"56316",
    "sg:province":"MN",
    "wof:name":"Hinnenkamp Farms",
    "wof:placetype":"venue"
},
  "geometry": {"coordinates":[-95.069963,45.559032],"type":"Point"}
}