{
  "type": "Feature",
  "properties": {
    "iso:country":"US",
    "sg:address":"10720 Dunkirk Ln N",
    "sg:city":"Osseo",
    "sg:classifiers":[
        {
            "category":"Building & Trades",
            "subcategory":"Plumbing",
            "type":"Services"
        }
    ],
    "sg:phone":"+1 763 424 5514",
    "sg:postcode":"55369",
    "sg:province":"MN",
    "wof:name":"Robillard Plumbing",
    "wof:placetype":"venue"
},
  "geometry": {"coordinates":[-93.49189800000001,45.150101],"type":"Point"}
}