{
  "type": "Feature",
  "properties": {
    "addr:full":"4134 40th Ave S Moorhead MN 56560",
    "addr:housenumber":"4134",
    "addr:postcode":"56560",
    "addr:street":"40Th Ave S Moorhead",
    "iso:country":"US",
    "sg:address":"4134 40th Ave S",
    "sg:city":"Moorhead",
    "sg:classifiers":[
        {
            "category":"Building & Trades",
            "subcategory":"Electrical",
            "type":"Services"
        }
    ],
    "sg:phone":"+1 218 287 7925",
    "sg:postcode":"56560",
    "sg:province":"MN",
    "sg:tags":[
        "electrical",
        "contractor"
    ],
    "wof:name":"Wades Electrical Service",
    "wof:placetype":"venue"
},
  "geometry": {"coordinates":[-96.711806,46.833304],"type":"Point"}
}