{
  "type": "Feature",
  "properties": {
    "addr:full":"305 E College Dr Marshall MN 56258",
    "addr:housenumber":"305",
    "addr:postcode":"56258",
    "addr:street":"E College Dr",
    "iso:country":"US",
    "sg:address":"305 E College Dr",
    "sg:city":"Marshall",
    "sg:classifiers":[
        {
            "category":"Insurance",
            "subcategory":"Insurance Agent",
            "type":"Services"
        }
    ],
    "sg:phone":"+1 507 537 1448",
    "sg:postcode":"56258",
    "sg:province":"MN",
    "wof:name":"Southwest Assurance Corp",
    "wof:placetype":"venue"
},
  "geometry": {"coordinates":[-95.786343,44.448731],"type":"Point"}
}