{
  "type": "Feature",
  "properties": {
    "iso:country":"US",
    "sg:address":"2611 Hwy 13 E",
    "sg:city":"Burnsville",
    "sg:classifiers":[
        {
            "category":"Autos & Motor Vehicles",
            "subcategory":"Auto Supplies",
            "type":"Retail Goods"
        }
    ],
    "sg:phone":"+1 952 707 0100",
    "sg:postcode":"55337",
    "sg:province":"MN",
    "sg:tags":[
        "equipment",
        "racing",
        "car",
        "automobile"
    ],
    "wof:name":"R S Motors",
    "wof:placetype":"venue"
},
  "geometry": {"coordinates":[-93.231477,44.801685],"type":"Point"}
}