{
  "type": "Feature",
  "properties": {
    "addr:full":"305 Lake St Barrett MN 56311",
    "addr:housenumber":"305",
    "addr:postcode":"56311",
    "addr:street":"Lake St",
    "iso:country":"US",
    "sg:address":"305 Lake St",
    "sg:city":"Barrett",
    "sg:classifiers":[
        {
            "category":"Professional",
            "type":"Services"
        }
    ],
    "sg:phone":"+1 320 528 2463",
    "sg:postcode":"56311",
    "sg:province":"MN",
    "sg:tags":[
        "establishment"
    ],
    "wof:name":"Vipond Cabin",
    "wof:placetype":"venue"
},
  "geometry": {"coordinates":[-95.887578,45.912136],"type":"Point"}
}