{
  "type": "Feature",
  "properties": {
    "iso:country":"US",
    "sg:address":"285 N Brown Rd",
    "sg:city":"Long Lake",
    "sg:classifiers":[
        {
            "category":"Retail",
            "subcategory":"Repair Shop",
            "type":"Services"
        }
    ],
    "sg:phone":"+1 952 473 6716",
    "sg:postcode":"55356",
    "sg:province":"MN",
    "sg:tags":[
        "refinishing",
        "furniture"
    ],
    "wof:name":"Back To The Future Furniture",
    "wof:placetype":"venue"
},
  "geometry": {"coordinates":[-93.57387300000001,44.983403],"type":"Point"}
}