{
  "type": "Feature",
  "properties": {
    "addr:full":"8517 244th St N Forest Lake MN 55025",
    "addr:housenumber":"8517",
    "addr:postcode":"55025",
    "addr:street":"244Th St N",
    "iso:country":"US",
    "sg:address":"8517 244th St N",
    "sg:city":"Forest Lake",
    "sg:classifiers":[
        {
            "category":"Wholesale",
            "subcategory":"Machinery & Supplies",
            "type":"Manufacturing & Wholesale Goods"
        }
    ],
    "sg:phone":"+1 651 462 9962",
    "sg:postcode":"55025",
    "sg:province":"MN",
    "sg:tags":[
        "packaging",
        "equipment",
        "processing",
        "dist"
    ],
    "wof:name":"Taylor Packaging Inc",
    "wof:placetype":"venue"
},
  "geometry": {"coordinates":[-92.935874,45.301641],"type":"Point"}
}