{
  "type": "Feature",
  "properties": {
    "addr:full":"91 Ridder Cir St Paul MN 55107",
    "addr:housenumber":"91",
    "addr:postcode":"55107",
    "addr:street":"Ridder Cir",
    "iso:country":"US",
    "sg:address":"91 Ridder Cir",
    "sg:city":"St Paul",
    "sg:classifiers":[
        {
            "category":"Building & Trades",
            "subcategory":"Construction",
            "type":"Services"
        }
    ],
    "sg:phone":"+1 651 772 1449",
    "sg:postcode":"55107",
    "sg:province":"MN",
    "sg:tags":[
        "demolition",
        "contractor"
    ],
    "wof:name":"Semple Excavating & Trucking",
    "wof:placetype":"venue"
},
  "geometry": {"coordinates":[-93.068726,44.944461],"type":"Point"}
}