{
  "type": "Feature",
  "properties": {
    "iso:country":"US",
    "sg:address":"10400 Baltimore St NE",
    "sg:city":"Minneapolis",
    "sg:classifiers":[
        {
            "category":"Ice Cream",
            "type":"Food & Drink"
        }
    ],
    "sg:menulink":"http://www.allmenus.com/mn/blaine/184896-cold-stone-creamery/menu/",
    "sg:phone":"+1 763 784 3630",
    "sg:postcode":"55449",
    "sg:province":"MN",
    "sg:tags":[
        "smoothy",
        "juice",
        "american"
    ],
    "wof:name":"Cold Stone Creamery",
    "wof:placetype":"venue"
},
  "geometry": {"coordinates":[-93.23267800000001,45.159948],"type":"Point"}
}