{
  "type": "Feature",
  "properties": {
    "addr:full":"3005 Carriage Dr Hamel MN 55340",
    "addr:housenumber":"3005",
    "addr:postcode":"55340",
    "addr:street":"Carriage Dr",
    "iso:country":"US",
    "sg:address":"3005 Carriage Dr",
    "sg:city":"Hamel",
    "sg:classifiers":[
        {
            "category":"Wholesale",
            "subcategory":"Office Equipment",
            "type":"Manufacturing & Wholesale Goods"
        }
    ],
    "sg:phone":"+1 763 478 2474",
    "sg:postcode":"55340",
    "sg:province":"MN",
    "wof:name":"Casio Inc",
    "wof:placetype":"venue"
},
  "geometry": {"coordinates":[-93.538037,45.033863],"type":"Point"}
}