{
  "type": "Feature",
  "properties": {
    "addr:full":"1406 W Lake St Ste 205 Minneapolis MN 55408",
    "addr:housenumber":"1406",
    "addr:postcode":"55408",
    "addr:street":"W Lake St Ste 205",
    "iso:country":"US",
    "sg:address":"1406 W Lake St Ste 205",
    "sg:city":"Minneapolis",
    "sg:classifiers":[
        {
            "category":"Real Estate",
            "subcategory":"Real Estate Services",
            "type":"Services"
        },
        {
            "category":"Real Estate",
            "subcategory":"Real Estate Operator",
            "type":"Services"
        }
    ],
    "sg:phone":"+1 612 822 2277",
    "sg:postcode":"55408",
    "sg:province":"MN",
    "sg:tags":[
        "apartment",
        "vacancy",
        "management",
        "listing",
        "property",
        "rental",
        "finder"
    ],
    "wof:name":"B & J Property Management",
    "wof:placetype":"venue"
},
  "geometry": {"coordinates":[-93.29740099999999,44.948399],"type":"Point"}
}