{
  "type": "Feature",
  "properties": {
    "addr:full":"13241 Maple Island Dr SE Glenwood MN 56334",
    "addr:housenumber":"13241",
    "addr:postcode":"56334",
    "addr:street":"Maple Island Dr Se",
    "iso:country":"US",
    "sg:address":"13241 Maple Island Dr SE",
    "sg:city":"Glenwood",
    "sg:classifiers":[
        {
            "category":"Travel",
            "subcategory":"Hotels & Motels",
            "type":"Entertainment"
        }
    ],
    "sg:phone":"+1 320 763 7292",
    "sg:postcode":"56334",
    "sg:province":"MN",
    "sg:tags":[
        "operation"
    ],
    "wof:name":"Maple Island Resort",
    "wof:placetype":"venue"
},
  "geometry": {"coordinates":[-95.376048,45.770548],"type":"Point"}
}