{
  "type": "Feature",
  "properties": {
    "iso:country":"US",
    "sg:address":"16372 Wagner Way",
    "sg:city":"Eden Prairie",
    "sg:classifiers":[
        {
            "category":"Restaurant",
            "type":"Food & Drink"
        }
    ],
    "sg:phone":"+1 952 937 1118",
    "sg:postcode":"55344",
    "sg:province":"MN",
    "sg:tags":[
        "chinese"
    ],
    "sg:website":"www.chinawok.com",
    "wof:name":"China Wok",
    "wof:placetype":"venue"
},
  "geometry": {"coordinates":[-93.484258,44.863632],"type":"Point"}
}