{
  "type": "Feature",
  "properties": {
    "addr:full":"114 N Holcombe Ave Litchfield MN 55355",
    "addr:housenumber":"114",
    "addr:postcode":"55355",
    "addr:street":"N Holcombe Ave",
    "iso:country":"US",
    "sg:address":"114 N Holcombe Ave",
    "sg:city":"Litchfield",
    "sg:classifiers":[
        {
            "category":"Government",
            "subcategory":"Office",
            "type":"Public Place"
        }
    ],
    "sg:phone":"+1 320 693 5205",
    "sg:postcode":"55355",
    "sg:province":"MN",
    "sg:tags":[
        "county",
        "taxation"
    ],
    "wof:name":"Meeker County Assessor",
    "wof:placetype":"venue"
},
  "geometry": {"coordinates":[-94.52512,45.127233],"type":"Point"}
}