{
  "type": "Feature",
  "properties": {
    "addr:full":"22085 586th Ave Austin MN 55912",
    "addr:housenumber":"22085",
    "addr:postcode":"55912",
    "addr:street":"586Th Ave",
    "iso:country":"US",
    "sg:address":"22085 586th Ave",
    "sg:city":"Austin",
    "sg:classifiers":[
        {
            "category":"Transit Center",
            "subcategory":"Freight",
            "type":"Transportation"
        },
        {
            "category":"Freight",
            "type":"Transportation"
        }
    ],
    "sg:phone":"+1 507 433 2503",
    "sg:postcode":"55912",
    "sg:province":"MN",
    "sg:tags":[
        "local",
        "trucking-motor",
        "trucking"
    ],
    "wof:name":"Collett Trucking",
    "wof:placetype":"venue"
},
  "geometry": {"coordinates":[-92.877735,43.674967],"type":"Point"}
}