{
  "type": "Feature",
  "properties": {
    "iso:country":"US",
    "sg:address":"28650 Foliage Ave",
    "sg:city":"Northfield",
    "sg:classifiers":[
        {
            "category":"Home & Garden",
            "subcategory":"Building Materials",
            "type":"Retail Goods"
        }
    ],
    "sg:phone":"+1 507 645 0097",
    "sg:postcode":"55057",
    "sg:province":"MN",
    "wof:name":"Valleyview Glass & Screen",
    "wof:placetype":"venue"
},
  "geometry": {"coordinates":[-93.20096100000001,44.543791],"type":"Point"}
}