{
  "type": "Feature",
  "properties": {
    "addr:full":"541 N Wheeler St Saint Paul MN 55104",
    "addr:housenumber":"541",
    "addr:postcode":"55104",
    "addr:street":"N Wheeler St",
    "iso:country":"US",
    "sg:address":"541 N Wheeler St",
    "sg:city":"Saint Paul",
    "sg:classifiers":[
        {
            "category":"Building & Trades",
            "subcategory":"Plumbing",
            "type":"Services"
        }
    ],
    "sg:phone":"+1 651 646 3837",
    "sg:postcode":"55104",
    "sg:province":"MN",
    "sg:tags":[
        "plumbing",
        "repair"
    ],
    "wof:name":"MSI",
    "wof:placetype":"venue"
},
  "geometry": {"coordinates":[-93.174649,44.958456],"type":"Point"}
}