{
  "type": "Feature",
  "properties": {
    "addr:full":"19500 Goodwin Ave Hastings MN 55033",
    "addr:housenumber":"19500",
    "addr:postcode":"55033",
    "addr:street":"Goodwin Ave",
    "iso:country":"US",
    "sg:address":"19500 Goodwin Ave",
    "sg:city":"Hastings",
    "sg:classifiers":[
        {
            "category":"Freight",
            "type":"Transportation"
        }
    ],
    "sg:phone":"+1 651 437 3669",
    "sg:postcode":"55033",
    "sg:province":"MN",
    "sg:tags":[
        "delivery"
    ],
    "wof:name":"Beskau's Home Delivery",
    "wof:placetype":"venue"
},
  "geometry": {"coordinates":[-92.954167,44.672174],"type":"Point"}
}