{
  "type": "Feature",
  "properties": {
    "addr:full":"50819 141st Ave Verndale MN 56481",
    "addr:housenumber":"50819",
    "addr:postcode":"56481",
    "addr:street":"141St Ave",
    "iso:country":"US",
    "sg:address":"50819 141st Ave",
    "sg:city":"Verndale",
    "sg:classifiers":[
        {
            "category":"Building & Trades",
            "subcategory":"Construction",
            "type":"Services"
        }
    ],
    "sg:phone":"+1 218 924 2533",
    "sg:postcode":"56481",
    "sg:province":"MN",
    "sg:tags":[
        "contractor"
    ],
    "wof:name":"Lovelace Construction",
    "wof:placetype":"venue"
},
  "geometry": {"coordinates":[-95.07214,46.355471],"type":"Point"}
}