{
  "type": "Feature",
  "properties": {
    "addr:full":"11080 189th St N Marine On Saint Croix MN 55047",
    "addr:housenumber":"11080",
    "addr:postcode":"55047",
    "addr:street":"189Th St N;Saint",
    "iso:country":"US",
    "sg:address":"11080 189th St N",
    "sg:city":"Marine On Saint Croix",
    "sg:classifiers":[
        {
            "category":"Retail",
            "subcategory":"Auto Repair",
            "type":"Services"
        }
    ],
    "sg:phone":"+1 651 433 2979",
    "sg:postcode":"55047",
    "sg:province":"MN",
    "sg:tags":[
        "body"
    ],
    "wof:name":"Kaj Enterprises",
    "wof:placetype":"venue"
},
  "geometry": {"coordinates":[-92.87945000000001,45.223718],"type":"Point"}
}