{
  "type": "Feature",
  "properties": {
    "addr:full":"7393 Bush Lake Rd Minneapolis MN 55439",
    "addr:housenumber":"7393",
    "addr:postcode":"55439",
    "addr:street":"Bush Lake Rd",
    "iso:country":"US",
    "sg:address":"7393 Bush Lake Rd",
    "sg:city":"Minneapolis",
    "sg:classifiers":[
        {
            "category":"Shopping",
            "subcategory":"Crafts & Fabrics",
            "type":"Retail Goods"
        }
    ],
    "sg:phone":"+1 952 831 3511",
    "sg:postcode":"55439",
    "sg:province":"MN",
    "sg:tags":[
        "shop"
    ],
    "sg:website":"http://www.chenillemagic.com",
    "wof:name":"Chenille Magic",
    "wof:placetype":"venue"
},
  "geometry": {"coordinates":[-93.35971600000001,44.868483],"type":"Point"}
}