{
  "type": "Feature",
  "properties": {
    "addr:full":"56721 State Hwy 11 Warroad MN 56763",
    "addr:housenumber":"56721",
    "addr:postcode":"56763",
    "addr:street":"State Hwy 11",
    "iso:country":"US",
    "sg:address":"56721 State Hwy 11",
    "sg:city":"Warroad",
    "sg:classifiers":[
        {
            "category":"Building & Trades",
            "subcategory":"Electrical",
            "type":"Services"
        }
    ],
    "sg:phone":"+1 218 386 1846",
    "sg:postcode":"56763",
    "sg:province":"MN",
    "sg:tags":[
        "electric",
        "contractor"
    ],
    "wof:name":"Fish Electric Sales & Svc",
    "wof:placetype":"venue"
},
  "geometry": {"coordinates":[-95.384018,48.905339],"type":"Point"}
}