{
  "type": "Feature",
  "properties": {
    "iso:country":"US",
    "sg:address":"16801 Industrial Cir SE",
    "sg:city":"Prior Lake",
    "sg:classifiers":[
        {
            "category":"Building & Trades",
            "subcategory":"Construction",
            "type":"Services"
        }
    ],
    "sg:phone":"+1 952 707 9663",
    "sg:postcode":"55372",
    "sg:province":"MN",
    "sg:tags":[
        "resurfacing",
        "laying",
        "refinishing",
        "floor"
    ],
    "wof:name":"Above All Hardwood Floors",
    "wof:placetype":"venue"
},
  "geometry": {"coordinates":[-93.40430499999999,44.70466],"type":"Point"}
}