{
  "type": "Feature",
  "properties": {
    "addr:full":"1159 Oxford St Worthington MN 56187",
    "addr:housenumber":"1159",
    "addr:postcode":"56187",
    "addr:street":"Oxford St",
    "iso:country":"US",
    "sg:address":"1159 Oxford St",
    "sg:city":"Worthington",
    "sg:classifiers":[
        {
            "category":"Autos & Motor Vehicles",
            "subcategory":"Auto Supplies",
            "type":"Retail Goods"
        },
        {
            "category":"Wholesale",
            "subcategory":"Auto Parts",
            "type":"Manufacturing & Wholesale Goods"
        }
    ],
    "sg:phone":"+1 507 376 3191",
    "sg:postcode":"56187",
    "sg:province":"MN",
    "sg:tags":[
        "automobile"
    ],
    "wof:name":"Karl's Carquest Auto Parts",
    "wof:placetype":"venue"
},
  "geometry": {"coordinates":[-95.60050099999999,43.631159],"type":"Point"}
}