{
  "type": "Feature",
  "properties": {
    "addr:full":"1323 Southview Blvd South Saint Paul MN 55075",
    "addr:housenumber":"1323",
    "addr:postcode":"55075",
    "addr:street":"Southview Blvd South",
    "iso:country":"US",
    "sg:address":"1323 Southview Blvd",
    "sg:city":"South Saint Paul",
    "sg:classifiers":[
        {
            "category":"Professional",
            "subcategory":"Business Services",
            "type":"Services"
        }
    ],
    "sg:phone":"+1 651 451 0287",
    "sg:postcode":"55075",
    "sg:province":"MN",
    "sg:tags":[
        "gasoline"
    ],
    "wof:name":"Gands LLC",
    "wof:placetype":"venue"
},
  "geometry": {"coordinates":[-93.051108,44.888891],"type":"Point"}
}