{
  "type": "Feature",
  "properties": {
    "iso:country":"US",
    "sg:address":"6418 Bass Lake Rd",
    "sg:city":"Minneapolis",
    "sg:classifiers":[
        {
            "category":"Wholesale",
            "subcategory":"Electrical",
            "type":"Manufacturing & Wholesale Goods"
        }
    ],
    "sg:phone":"+1 763 533 7112",
    "sg:postcode":"55428",
    "sg:province":"MN",
    "sg:tags":[
        "alarm",
        "burglar",
        "system"
    ],
    "wof:name":"Pro Alarm & Comm",
    "wof:placetype":"venue"
},
  "geometry": {"coordinates":[-93.36138,45.054723],"type":"Point"}
}