{
  "type": "Feature",
  "properties": {
    "addr:full":"4141 Dupont Ave S Minneapolis MN 55409",
    "addr:housenumber":"4141",
    "addr:postcode":"55409",
    "addr:street":"Dupont Ave S",
    "iso:country":"US",
    "sg:address":"4141 Dupont Ave S",
    "sg:city":"Minneapolis",
    "sg:classifiers":[
        {
            "category":"Professional",
            "subcategory":"Research",
            "type":"Services"
        }
    ],
    "sg:phone":"+1 612 825 9537",
    "sg:postcode":"55409",
    "sg:province":"MN",
    "sg:tags":[
        "development",
        "laboratories-research",
        "noncommercial"
    ],
    "sg:website":"http://www.internationalpianoinstitute.com",
    "wof:name":"International Piano Institute",
    "wof:placetype":"venue"
},
  "geometry": {"coordinates":[-93.293358,44.927883],"type":"Point"}
}