{
  "type": "Feature",
  "properties": {
    "iso:country":"US",
    "sg:address":"2344 Cork Hollow Dr",
    "sg:city":"Brownsville",
    "sg:classifiers":[
        {
            "category":"Wholesale",
            "subcategory":"Auto Parts",
            "type":"Manufacturing & Wholesale Goods"
        }
    ],
    "sg:phone":"+1 507 482 6618",
    "sg:postcode":"55919",
    "sg:province":"MN",
    "sg:tags":[
        "tr",
        "supply"
    ],
    "wof:name":"Tri State Transmission Exch",
    "wof:placetype":"venue"
},
  "geometry": {"coordinates":[-91.29898799999999,43.694214],"type":"Point"}
}