{
  "type": "Feature",
  "properties": {
    "addr:full":"7711 Berkshire Way Maple Grove MN 55311",
    "addr:housenumber":"7711",
    "addr:postcode":"55311",
    "addr:street":"Berkshire Way",
    "iso:country":"US",
    "sg:address":"7711 Berkshire Way",
    "sg:city":"Maple Grove",
    "sg:classifiers":[
        {
            "category":"Wholesale",
            "subcategory":"Medical Equipment & Supplies",
            "type":"Manufacturing & Wholesale Goods"
        }
    ],
    "sg:phone":"+1 763 420 7828",
    "sg:postcode":"55311",
    "sg:province":"MN",
    "sg:tags":[
        "dental"
    ],
    "wof:name":"Disposable Medical Resources",
    "wof:placetype":"venue"
},
  "geometry": {"coordinates":[-93.455394,45.095193],"type":"Point"}
}