{
  "type": "Feature",
  "properties": {
    "iso:country":"US",
    "sg:address":"123 21st St N",
    "sg:city":"Moorhead",
    "sg:classifiers":[
        {
            "category":"Organizations",
            "subcategory":"Religious Organization",
            "type":"Services"
        }
    ],
    "sg:phone":"+1 218 291 1992",
    "sg:postcode":"56560",
    "sg:province":"MN",
    "sg:tags":[
        "church"
    ],
    "wof:name":"Moorhead Church Of Christ",
    "wof:placetype":"venue"
},
  "geometry": {"coordinates":[-96.746807,46.87697],"type":"Point"}
}