{
  "type": "Feature",
  "properties": {
    "addr:full":"4836 Ohlgren Rd Moose Lake MN 55783",
    "addr:housenumber":"4836",
    "addr:postcode":"55783",
    "addr:street":"Ohlgren Rd",
    "iso:country":"US",
    "sg:address":"4836 Ohlgren Rd",
    "sg:city":"Moose Lake",
    "sg:classifiers":[
        {
            "category":"Building & Trades",
            "subcategory":"Construction",
            "type":"Services"
        }
    ],
    "sg:phone":"+1 218 485 8604",
    "sg:postcode":"55783",
    "sg:province":"MN",
    "sg:tags":[
        "roofing",
        "contractor"
    ],
    "wof:name":"Beaver Roofing Inc",
    "wof:placetype":"venue"
},
  "geometry": {"coordinates":[-92.733148,46.418389],"type":"Point"}
}