{
  "type": "Feature",
  "properties": {
    "addr:full":"106 E Lake St Minneapolis MN 55408",
    "addr:housenumber":"106",
    "addr:postcode":"55408",
    "addr:street":"E Lake St",
    "iso:country":"US",
    "sg:address":"106 E Lake St",
    "sg:city":"Minneapolis",
    "sg:classifiers":[
        {
            "category":"Professional",
            "subcategory":"Accounting & Tax Preparation",
            "type":"Services"
        }
    ],
    "sg:phone":"+1 612 827 3917",
    "sg:postcode":"55408",
    "sg:province":"MN",
    "sg:tags":[
        "return",
        "filing"
    ],
    "wof:name":"Jackson Hewitt Tax Svc",
    "wof:placetype":"venue"
},
  "geometry": {"coordinates":[-93.275627,44.948428],"type":"Point"}
}