{
  "type": "Feature",
  "properties": {
    "addr:full":"14863 595th St Claremont MN 55924",
    "addr:housenumber":"14863",
    "addr:postcode":"55924",
    "addr:street":"595Th St",
    "iso:country":"US",
    "sg:address":"14863 595th St",
    "sg:city":"Claremont",
    "sg:classifiers":[
        {
            "category":"Building & Trades",
            "subcategory":"Construction",
            "type":"Services"
        }
    ],
    "sg:phone":"+1 507 528 2570",
    "sg:postcode":"55924",
    "sg:province":"MN",
    "sg:tags":[
        "contractor"
    ],
    "wof:name":"Keller Masonry",
    "wof:placetype":"venue"
},
  "geometry": {"coordinates":[-92.948638,44.087972],"type":"Point"}
}