{
  "type": "Feature",
  "properties": {
    "addr:full":"101 W Main St Perham MN 56573",
    "addr:housenumber":"101",
    "addr:postcode":"56573",
    "addr:street":"W Main St",
    "iso:country":"US",
    "sg:address":"101 W Main St",
    "sg:city":"Perham",
    "sg:classifiers":[
        {
            "category":"Shopping",
            "subcategory":"Gifts & Souvenirs",
            "type":"Retail Goods"
        }
    ],
    "sg:phone":"+1 218 346 5435",
    "sg:postcode":"56573",
    "sg:province":"MN",
    "wof:name":"Pines The",
    "wof:placetype":"venue"
},
  "geometry": {"coordinates":[-95.573948,46.594882],"type":"Point"}
}