{
  "type": "Feature",
  "properties": {
    "iso:country":"US",
    "sg:address":"304 W 50th St",
    "sg:city":"Minneapolis",
    "sg:classifiers":[
        {
            "category":"Communications",
            "subcategory":"Film & Video Production",
            "type":"Services"
        }
    ],
    "sg:phone":"+1 612 822 6227",
    "sg:postcode":"55419",
    "sg:province":"MN",
    "sg:tags":[
        "motion"
    ],
    "wof:name":"Dream Out Loud Productions",
    "wof:placetype":"venue"
},
  "geometry": {"coordinates":[-93.28563699999999,44.912337],"type":"Point"}
}