{
  "type": "Feature",
  "properties": {
    "iso:country":"US",
    "sg:address":"104 Marty Dr",
    "sg:city":"Buffalo",
    "sg:classifiers":[
        {
            "category":"Real Estate",
            "subcategory":"Surveying",
            "type":"Services"
        }
    ],
    "sg:phone":"+1 763 682 2587",
    "sg:postcode":"55313",
    "sg:province":"MN",
    "sg:tags":[
        "surveyor"
    ],
    "wof:name":"Westwood Professional Svc Inc",
    "wof:placetype":"venue"
},
  "geometry": {"coordinates":[-93.87336500000001,45.192935],"type":"Point"}
}