{
  "type": "Feature",
  "properties": {
    "iso:country":"US",
    "sg:address":"400 Broadway E",
    "sg:city":"Little Falls",
    "sg:classifiers":[
        {
            "category":"Shopping",
            "type":"Retail Goods"
        }
    ],
    "sg:phone":"+1 320 632 6557",
    "sg:postcode":"56345",
    "sg:province":"MN",
    "sg:tags":[
        "hearing",
        "equipment",
        "supply",
        "impaired"
    ],
    "wof:name":"American Hearing Care Clinic",
    "wof:placetype":"venue"
},
  "geometry": {"coordinates":[-94.356685,45.975799],"type":"Point"}
}