{
  "type": "Feature",
  "properties": {
    "addr:full":"9360 Ensign Ave S Minneapolis MN 55438",
    "addr:housenumber":"9360",
    "addr:postcode":"55438",
    "addr:street":"Ensign Ave S",
    "iso:country":"US",
    "sg:address":"9360 Ensign Ave S",
    "sg:city":"Minneapolis",
    "sg:classifiers":[
        {
            "category":"Professional",
            "subcategory":"Computer Services",
            "type":"Services"
        }
    ],
    "sg:phone":"+1 952 851 0818",
    "sg:postcode":"55438",
    "sg:province":"MN",
    "sg:tags":[
        "consulting",
        "programming"
    ],
    "wof:name":"Uniscope Data Services Inc",
    "wof:placetype":"venue"
},
  "geometry": {"coordinates":[-93.395916,44.834281],"type":"Point"}
}