{
  "type": "Feature",
  "properties": {
    "addr:full":"2778 180th St Granada MN 56039",
    "addr:housenumber":"2778",
    "addr:postcode":"56039",
    "addr:street":"180Th St",
    "iso:country":"US",
    "sg:address":"2778 180th St",
    "sg:city":"Granada",
    "sg:phone":"+1 507 447 2299",
    "sg:postcode":"56039",
    "sg:province":"MN",
    "sg:tags":[
        "farm",
        "corn",
        "soybean"
    ],
    "wof:name":"Loren Mapson",
    "wof:placetype":"venue"
},
  "geometry": {"coordinates":[-94.312101,43.745912],"type":"Point"}
}