{
  "type": "Feature",
  "properties": {
    "addr:full":"10995 Hwy 37 Hibbing MN 55746",
    "addr:housenumber":"10995",
    "addr:postcode":"55746",
    "addr:street":"Hwy 37",
    "iso:country":"US",
    "sg:address":"10995 Hwy 37",
    "sg:city":"Hibbing",
    "sg:classifiers":[
        {
            "category":"Recreation",
            "type":"Entertainment"
        }
    ],
    "sg:phone":"+1 218 262 2300",
    "sg:postcode":"55746",
    "sg:province":"MN",
    "sg:tags":[
        "sporting"
    ],
    "wof:name":"Mulligans Drving Rnge Golf Ctr",
    "wof:placetype":"venue"
},
  "geometry": {"coordinates":[-92.832257,47.394379],"type":"Point"}
}