{
  "type": "Feature",
  "properties": {
    "iso:country":"US",
    "sg:address":"8832 Aldrich Ave S",
    "sg:city":"Minneapolis",
    "sg:classifiers":[
        {
            "category":"Taxi",
            "type":"Transportation"
        },
        {
            "category":"Airport",
            "type":"Transportation"
        }
    ],
    "sg:phone":"+1 952 888 6800",
    "sg:postcode":"55420",
    "sg:province":"MN",
    "sg:website":"http://twincities.citysearch.com/profile/external/43258875/bloomington_mn/gopher_state_airport_taxi.html?publisher=yellowpages&reference_id=1&placement=ypwebsitemip",
    "wof:name":"Gopher State Airport Taxi",
    "wof:placetype":"venue"
},
  "geometry": {"coordinates":[-93.28984800000001,44.843336],"type":"Point"}
}