{
  "type": "Feature",
  "properties": {
    "iso:country":"US",
    "sg:address":"643 121st Ln NW",
    "sg:city":"Minneapolis",
    "sg:classifiers":[
        {
            "category":"Wholesale",
            "subcategory":"Non-durable Goods",
            "type":"Manufacturing & Wholesale Goods"
        }
    ],
    "sg:phone":"+1 763 757 5878",
    "sg:postcode":"55448",
    "sg:province":"MN",
    "sg:tags":[
        "shop",
        "product",
        "gift",
        "mfg"
    ],
    "wof:name":"Morningstar Marketing Inc",
    "wof:placetype":"venue"
},
  "geometry": {"coordinates":[-93.283252,45.190966],"type":"Point"}
}