{
  "type": "Feature",
  "properties": {
    "addr:full":"2120 Park Ave S Minneapolis MN 55404",
    "addr:housenumber":"2120",
    "addr:postcode":"55404",
    "addr:street":"Park Ave S",
    "iso:country":"US",
    "sg:address":"2120 Park Ave S",
    "sg:city":"Minneapolis",
    "sg:classifiers":[
        {
            "category":"Health Services",
            "subcategory":"Doctor",
            "type":"Services"
        }
    ],
    "sg:phone":"+1 612 871 1264",
    "sg:postcode":"55404",
    "sg:province":"MN",
    "sg:tags":[
        "medical"
    ],
    "wof:name":"Park House",
    "wof:placetype":"venue"
},
  "geometry": {"coordinates":[-93.26518900000001,44.961995],"type":"Point"}
}