{
  "type": "Feature",
  "properties": {
    "addr:full":"3182 Village Trl Hastings MN 55033",
    "addr:housenumber":"3182",
    "addr:postcode":"55033",
    "addr:street":"Village Trl",
    "iso:country":"US",
    "sg:address":"3182 Village Trl",
    "sg:city":"Hastings",
    "sg:classifiers":[
        {
            "category":"Banks & Credit Unions",
            "subcategory":"Investment Brokerage",
            "type":"Services"
        },
        {
            "category":"Banks & Credit Unions",
            "subcategory":"Financial Services",
            "type":"Services"
        }
    ],
    "sg:phone":"+1 651 480 1100",
    "sg:postcode":"55033",
    "sg:province":"MN",
    "sg:tags":[
        "advisory",
        "planner"
    ],
    "wof:name":"Diversified Financial Group",
    "wof:placetype":"venue"
},
  "geometry": {"coordinates":[-92.871314,44.715983],"type":"Point"}
}