{
  "type": "Feature",
  "properties": {
    "iso:country":"US",
    "sg:address":"17117 Riverwood Dr",
    "sg:city":"Little Falls",
    "sg:classifiers":[
        {
            "category":"Organizations",
            "subcategory":"Religious Organization",
            "type":"Services"
        }
    ],
    "sg:phone":"+1 320 632 3629",
    "sg:postcode":"56345",
    "sg:province":"MN",
    "wof:name":"Grace Covenant Church",
    "wof:placetype":"venue"
},
  "geometry": {"coordinates":[-94.355113,46.011504],"type":"Point"}
}