{
  "type": "Feature",
  "properties": {
    "addr:full":"4057 28th St NW Ste 200 Rochester MN 55901",
    "addr:housenumber":"4057",
    "addr:postcode":"55901",
    "addr:street":"28Th St Nw Ste 200",
    "iso:country":"US",
    "sg:address":"4057 28th St NW Ste 200",
    "sg:city":"Rochester",
    "sg:classifiers":[
        {
            "category":"Real Estate",
            "subcategory":"Real Estate Services",
            "type":"Services"
        },
        {
            "category":"Real Estate",
            "subcategory":"Real Estate Agent",
            "type":"Services"
        }
    ],
    "sg:phone":"+1 507 281 1002",
    "sg:postcode":"55901",
    "sg:province":"MN",
    "sg:tags":[
        "buyer",
        "broker"
    ],
    "sg:website":"http://www.hamiltonmn.com",
    "wof:name":"Hamilton Real Estate Inc",
    "wof:placetype":"venue"
},
  "geometry": {"coordinates":[-92.52409900000001,44.053253],"type":"Point"}
}