{
  "type": "Feature",
  "properties": {
    "addr:full":"321 19th Ave S Minneapolis MN 55455",
    "addr:housenumber":"321",
    "addr:postcode":"55455",
    "addr:street":"19Th Ave S",
    "iso:country":"US",
    "sg:address":"321 19th Ave S",
    "sg:city":"Minneapolis",
    "sg:classifiers":[
        {
            "category":"Education",
            "subcategory":"College",
            "type":"Public Place"
        }
    ],
    "sg:phone":"+1 612 624 1385",
    "sg:postcode":"55455",
    "sg:province":"MN",
    "sg:tags":[
        "academic",
        "school"
    ],
    "sg:website":"www.csom.umn.edu",
    "wof:name":"Carlson Executive Mba Program",
    "wof:placetype":"venue"
},
  "geometry": {"coordinates":[-93.24573100000001,44.971362],"type":"Point"}
}