{
  "type": "Feature",
  "properties": {
    "iso:country":"US",
    "sg:address":"10519 Humboldt Ave S",
    "sg:city":"Minneapolis",
    "sg:classifiers":[
        {
            "category":"Professional",
            "subcategory":"Advertising",
            "type":"Services"
        }
    ],
    "sg:phone":"+1 952 884 9061",
    "sg:postcode":"55431",
    "sg:province":"MN",
    "sg:tags":[
        "marketing",
        "internet"
    ],
    "wof:name":"Pro Muskie Guide.Com",
    "wof:placetype":"venue"
},
  "geometry": {"coordinates":[-93.298796,44.813277],"type":"Point"}
}