{
  "type": "Feature",
  "properties": {
    "iso:country":"US",
    "sg:address":"1130 Hiawatha Dr W",
    "sg:city":"Wabasha",
    "sg:classifiers":[
        {
            "category":"Restaurant",
            "type":"Food & Drink"
        }
    ],
    "sg:phone":"+1 651 565 2040",
    "sg:postcode":"55981",
    "sg:province":"MN",
    "sg:tags":[
        "eating"
    ],
    "wof:name":"Eagle Valley Cafe",
    "wof:placetype":"venue"
},
  "geometry": {"coordinates":[-92.050994,44.380852],"type":"Point"}
}