{
  "type": "Feature",
  "properties": {
    "iso:country":"US",
    "sg:address":"10009 Yukon Ave S",
    "sg:city":"Minneapolis",
    "sg:classifiers":[
        {
            "category":"Personal",
            "type":"Services"
        }
    ],
    "sg:phone":"+1 952 941 1423",
    "sg:postcode":"55438",
    "sg:province":"MN",
    "wof:name":"Pland Properties",
    "wof:placetype":"venue"
},
  "geometry": {"coordinates":[-93.387512,44.82188],"type":"Point"}
}