{
  "type": "Feature",
  "properties": {
    "addr:full":"1122 Spring St NE Minneapolis MN 55413",
    "addr:housenumber":"1122",
    "addr:postcode":"55413",
    "addr:street":"Spring St Ne",
    "iso:country":"US",
    "sg:address":"1122 Spring St NE",
    "sg:city":"Minneapolis",
    "sg:classifiers":[
        {
            "category":"Food & Beverages",
            "subcategory":"Groceries & Convenience Stores",
            "type":"Retail Goods"
        }
    ],
    "sg:phone":"+1 612 331 9048",
    "sg:postcode":"55413",
    "sg:province":"MN",
    "wof:name":"Schullo Grocery",
    "wof:placetype":"venue"
},
  "geometry": {"coordinates":[-93.24244400000001,44.995026],"type":"Point"}
}