{
  "type": "Feature",
  "properties": {
    "addr:full":"1501 Glenwood Ave Minneapolis MN 55405",
    "addr:housenumber":"1501",
    "addr:postcode":"55405",
    "addr:street":"Glenwood Ave",
    "iso:country":"US",
    "sg:address":"1501 Glenwood Ave",
    "sg:city":"Minneapolis",
    "sg:classifiers":[
        {
            "category":"Professional",
            "subcategory":"Business Services",
            "type":"Services"
        }
    ],
    "sg:phone":"+1 612 377 0277",
    "sg:postcode":"55405",
    "sg:province":"MN",
    "wof:name":"Twin City Business Inc",
    "wof:placetype":"venue"
},
  "geometry": {"coordinates":[-93.300758,44.980903],"type":"Point"}
}