{
  "type": "Feature",
  "properties": {
    "iso:country":"US",
    "sg:address":"209 Grant Ave",
    "sg:city":"Eveleth",
    "sg:classifiers":[
        {
            "category":"Insurance",
            "subcategory":"Insurance Agent",
            "type":"Services"
        }
    ],
    "sg:phone":"+1 218 744 2075",
    "sg:postcode":"55734",
    "sg:province":"MN",
    "wof:name":"American Family Insurance",
    "wof:placetype":"venue"
},
  "geometry": {"coordinates":[-92.53994899999999,47.462318],"type":"Point"}
}