{
  "type": "Feature",
  "properties": {
    "addr:full":"9454 Kimbro Ave S Cottage Grove MN 55016",
    "addr:postcode":"9454;55016",
    "addr:street":"Kimbro Ave S Cottage Grove",
    "iso:country":"US",
    "sg:address":"9454 Kimbro Ave S",
    "sg:city":"Cottage Grove",
    "sg:classifiers":[
        {
            "category":"Wholesale",
            "subcategory":"Motor Vehicles",
            "type":"Manufacturing & Wholesale Goods"
        }
    ],
    "sg:phone":"+1 651 459 2344",
    "sg:postcode":"55016",
    "sg:province":"MN",
    "wof:name":"Dean Lurken",
    "wof:placetype":"venue"
},
  "geometry": {"coordinates":[-92.892994,44.812347],"type":"Point"}
}