{
  "type": "Feature",
  "properties": {
    "addr:full":"204 N 3rd Ave Proctor MN 55810",
    "addr:housenumber":"204",
    "addr:postcode":"55810",
    "addr:street":"N 3Rd Ave",
    "iso:country":"US",
    "sg:address":"204 N 3rd Ave",
    "sg:city":"Proctor",
    "sg:classifiers":[
        {
            "category":"Personal",
            "type":"Services"
        }
    ],
    "sg:phone":"+1 218 590 7981",
    "sg:postcode":"55810",
    "sg:province":"MN",
    "sg:tags":[
        "therapist",
        "massage"
    ],
    "wof:name":"Proctor Massage",
    "wof:placetype":"venue"
},
  "geometry": {"coordinates":[-92.224158,46.744894],"type":"Point"}
}