{
  "type": "Feature",
  "properties": {
    "addr:full":"13950 Jarvis Ave NW South Haven MN 55382",
    "addr:housenumber":"13950",
    "addr:postcode":"55382",
    "addr:street":"Jarvis Ave Nw;Haven",
    "iso:country":"US",
    "sg:address":"13950 Jarvis Ave NW",
    "sg:city":"South Haven",
    "sg:classifiers":[
        {
            "category":"Shopping",
            "type":"Retail Goods"
        }
    ],
    "sg:phone":"+1 320 558 2822",
    "sg:postcode":"55382",
    "sg:province":"MN",
    "sg:tags":[
        "merchandise"
    ],
    "wof:name":"Forner Auction Service",
    "wof:placetype":"venue"
},
  "geometry": {"coordinates":[-94.07611799999999,45.352708],"type":"Point"}
}