{
  "type": "Feature",
  "properties": {
    "iso:country":"US",
    "sg:address":"1340 Town Centre Dr",
    "sg:city":"Saint Paul",
    "sg:classifiers":[
        {
            "category":"Restaurant",
            "type":"Food & Drink"
        }
    ],
    "sg:menulink":"http://www.allmenus.com/mn/eagan/104681-noodles--company/menu/",
    "sg:phone":"+1 651 994 1111",
    "sg:postcode":"55123",
    "sg:province":"MN",
    "sg:tags":[
        "noodle",
        "bar",
        "salad",
        "chinese",
        "japanese",
        "soup",
        "american",
        "asian",
        "thai",
        "italian"
    ],
    "wof:name":"Noodles & Company",
    "wof:placetype":"venue"
},
  "geometry": {"coordinates":[-93.163314,44.830907],"type":"Point"}
}