{
  "type": "Feature",
  "properties": {
    "addr:full":"14505 21st Ave N Plymouth MN 55447",
    "addr:housenumber":"14505",
    "addr:postcode":"55447",
    "addr:street":"21St Ave N",
    "iso:country":"US",
    "sg:address":"14505 21st Ave N",
    "sg:city":"Plymouth",
    "sg:classifiers":[
        {
            "category":"Wholesale",
            "subcategory":"Chemicals & Plastics",
            "type":"Manufacturing & Wholesale Goods"
        }
    ],
    "sg:phone":"+1 763 473 1200",
    "sg:postcode":"55447",
    "sg:province":"MN",
    "wof:name":"Signature USA",
    "wof:placetype":"venue"
},
  "geometry": {"coordinates":[-93.467806,45.000935],"type":"Point"}
}