{
  "type": "Feature",
  "properties": {
    "iso:country":"US",
    "sg:address":"27669 390th St NE",
    "sg:city":"Middle River",
    "sg:phone":"+1 218 222 3686",
    "sg:postcode":"56737",
    "sg:province":"MN",
    "sg:tags":[
        "farm",
        "grain",
        "cash"
    ],
    "wof:name":"Clarence Dahl",
    "wof:placetype":"venue"
},
  "geometry": {"coordinates":[-95.867349,48.439831],"type":"Point"}
}