{
  "type": "Feature",
  "properties": {
    "iso:country":"US",
    "sg:address":"12685 53rd St N",
    "sg:city":"Stillwater",
    "sg:classifiers":[
        {
            "category":"Professional",
            "subcategory":"Detective & Security Services",
            "type":"Services"
        }
    ],
    "sg:phone":"+1 651 430 0421",
    "sg:postcode":"55082",
    "sg:province":"MN",
    "sg:tags":[
        "private",
        "investigator"
    ],
    "wof:name":"James N Mcgann",
    "wof:placetype":"venue"
},
  "geometry": {"coordinates":[-92.85041,45.023747],"type":"Point"}
}