{
  "type": "Feature",
  "properties": {
    "addr:full":"20417 213th Ave Big Lake MN 55309",
    "addr:housenumber":"20417",
    "addr:postcode":"55309",
    "addr:street":"213Th Ave",
    "iso:country":"US",
    "sg:address":"20417 213th Ave",
    "sg:city":"Big Lake",
    "sg:classifiers":[
        {
            "category":"Manufacturing",
            "subcategory":"Rubber & Plastics",
            "type":"Manufacturing & Wholesale Goods"
        }
    ],
    "sg:phone":"+1 763 263 0361",
    "sg:postcode":"55309",
    "sg:province":"MN",
    "sg:tags":[
        "product",
        "fabricated",
        "mfg"
    ],
    "wof:name":"Qual Med Co",
    "wof:placetype":"venue"
},
  "geometry": {"coordinates":[-93.78939099999999,45.357422],"type":"Point"}
}