{
  "type": "Feature",
  "properties": {
    "addr:full":"15850 Azurite Ct NW Anoka MN 55303",
    "addr:housenumber":"15850",
    "addr:postcode":"55303",
    "addr:street":"Azurite Ct Nw",
    "iso:country":"US",
    "sg:address":"15850 Azurite Ct NW",
    "sg:city":"Anoka",
    "sg:classifiers":[
        {
            "category":"Building & Trades",
            "subcategory":"Construction",
            "type":"Services"
        }
    ],
    "sg:phone":"+1 763 422 8285",
    "sg:postcode":"55303",
    "sg:province":"MN",
    "sg:tags":[
        "pipeline",
        "sewer",
        "excavating",
        "contractor"
    ],
    "wof:name":"Ron-Son Contracting Inc",
    "wof:placetype":"venue"
},
  "geometry": {"coordinates":[-93.433089,45.257412],"type":"Point"}
}