{
  "type": "Feature",
  "properties": {
    "addr:full":"12371 County 6 Park Rapids MN 56470",
    "addr:housenumber":"12371",
    "addr:postcode":"56470",
    "addr:street":"County 6",
    "iso:country":"US",
    "sg:address":"12371 County 6",
    "sg:city":"Park Rapids",
    "sg:classifiers":[
        {
            "category":"Restaurant",
            "type":"Food & Drink"
        }
    ],
    "sg:phone":"+1 218 732 5644",
    "sg:postcode":"56470",
    "sg:province":"MN",
    "wof:name":"Hilltop",
    "wof:placetype":"venue"
},
  "geometry": {"coordinates":[-95.010575,46.840936],"type":"Point"}
}