{
  "type": "Feature",
  "properties": {
    "addr:full":"13200 20th St SE Eyota MN 55934",
    "addr:housenumber":"13200",
    "addr:postcode":"55934",
    "addr:street":"20Th St Se",
    "iso:country":"US",
    "sg:address":"13200 20th St SE",
    "sg:city":"Eyota",
    "sg:classifiers":[
        {
            "category":"Local Transit",
            "type":"Transportation"
        }
    ],
    "sg:phone":"+1 507 545 2777",
    "sg:postcode":"55934",
    "sg:province":"MN",
    "sg:tags":[
        "limousine"
    ],
    "wof:name":"Classic Limousine",
    "wof:placetype":"venue"
},
  "geometry": {"coordinates":[-92.208416,43.991694],"type":"Point"}
}