{
  "type": "Feature",
  "properties": {
    "addr:full":"10 Higbie Ave W Minnesota Lake MN 56068",
    "addr:housenumber":"10",
    "addr:postcode":"56068",
    "addr:street":"Higbie Ave W;Lake",
    "iso:country":"US",
    "sg:address":"10 Higbie Ave W",
    "sg:city":"Minnesota Lake",
    "sg:classifiers":[
        {
            "category":"Farming",
            "subcategory":"Livestock Farm",
            "type":"Manufacturing & Wholesale Goods"
        }
    ],
    "sg:phone":"+1 507 462 3757",
    "sg:postcode":"56068",
    "sg:province":"MN",
    "sg:tags":[
        "corn",
        "beef",
        "feedlot",
        "cattle"
    ],
    "wof:name":"Richard Walser",
    "wof:placetype":"venue"
},
  "geometry": {"coordinates":[-93.83531600000001,43.838364],"type":"Point"}
}