{
  "type": "Feature",
  "properties": {
    "addr:full":"226 W Broadway Ave Minneapolis MN 55411",
    "addr:housenumber":"226",
    "addr:postcode":"55411",
    "addr:street":"W Broadway Ave",
    "iso:country":"US",
    "sg:address":"226 W Broadway Ave",
    "sg:city":"Minneapolis",
    "sg:classifiers":[
        {
            "category":"Food & Beverages",
            "subcategory":"Liquor & Beverages",
            "type":"Retail Goods"
        }
    ],
    "sg:phone":"+1 612 521 9994",
    "sg:postcode":"55411",
    "sg:province":"MN",
    "wof:name":"Jug Liquor Store",
    "wof:placetype":"venue"
},
  "geometry": {"coordinates":[-93.28074599999999,44.999195],"type":"Point"}
}