{
  "type": "Feature",
  "properties": {
    "addr:full":"350 N Sibley St St Paul MN 55101",
    "addr:housenumber":"350",
    "addr:postcode":"55101",
    "addr:street":"N Sibley St",
    "iso:country":"US",
    "sg:address":"350 N Sibley St",
    "sg:city":"St Paul",
    "sg:classifiers":[
        {
            "category":"Real Estate",
            "subcategory":"Real Estate Operator",
            "type":"Services"
        }
    ],
    "sg:phone":"+1 651 228 7212",
    "sg:postcode":"55101",
    "sg:province":"MN",
    "sg:tags":[
        "apartment"
    ],
    "wof:name":"Strauss Loft",
    "wof:placetype":"venue"
},
  "geometry": {"coordinates":[-93.08774,44.948289],"type":"Point"}
}