{
  "type": "Feature",
  "properties": {
    "iso:country":"US",
    "sg:address":"1506 Buerkle Rd",
    "sg:city":"St Paul",
    "sg:classifiers":[
        {
            "category":"Building & Trades",
            "subcategory":"Electrical",
            "type":"Services"
        }
    ],
    "sg:phone":"+1 651 294 2287",
    "sg:postcode":"55110",
    "sg:province":"MN",
    "sg:tags":[
        "installation"
    ],
    "wof:name":"All Install",
    "wof:placetype":"venue"
},
  "geometry": {"coordinates":[-93.037012,45.041052],"type":"Point"}
}