{
  "type": "Feature",
  "properties": {
    "iso:country":"US",
    "sg:address":"1 Central Ave",
    "sg:city":"Buffalo",
    "sg:classifiers":[
        {
            "category":"Shopping",
            "type":"Retail Goods"
        }
    ],
    "sg:phone":"+1 763 684 0058",
    "sg:postcode":"55313",
    "sg:province":"MN",
    "sg:tags":[
        "merchandise"
    ],
    "wof:name":"Buffalo Saddle Shop",
    "wof:placetype":"venue"
},
  "geometry": {"coordinates":[-93.87621300000001,45.173051],"type":"Point"}
}