{
  "type": "Feature",
  "properties": {
    "addr:full":"1983 Field Ave Saint Paul MN 55116",
    "addr:housenumber":"1983",
    "addr:postcode":"55116",
    "addr:street":"Field Ave",
    "iso:country":"US",
    "sg:address":"1983 Field Ave",
    "sg:city":"Saint Paul",
    "sg:classifiers":[
        {
            "category":"Wholesale",
            "subcategory":"Vending Machines",
            "type":"Manufacturing & Wholesale Goods"
        }
    ],
    "sg:phone":"+1 651 690 1717",
    "sg:postcode":"55116",
    "sg:province":"MN",
    "sg:tags":[
        "operator",
        "merchandising"
    ],
    "wof:name":"Harmony Vending Services",
    "wof:placetype":"venue"
},
  "geometry": {"coordinates":[-93.18541500000001,44.90251],"type":"Point"}
}