{
  "type": "Feature",
  "properties": {
    "iso:country":"US",
    "sg:address":"101 Brown St W",
    "sg:city":"Comfrey",
    "sg:classifiers":[
        {
            "category":"Insurance",
            "subcategory":"Insurance Agent",
            "type":"Services"
        }
    ],
    "sg:phone":"+1 507 877 4111",
    "sg:postcode":"56019",
    "sg:province":"MN",
    "wof:name":"Peoples State Agency Inc",
    "wof:placetype":"venue"
},
  "geometry": {"coordinates":[-94.90596499999999,44.109897],"type":"Point"}
}