{
  "type": "Feature",
  "properties": {
    "addr:full":"1015 Tonkawa Rd Long Lake MN 55356",
    "addr:housenumber":"1015",
    "addr:postcode":"55356",
    "addr:street":"Tonkawa Rd",
    "iso:country":"US",
    "sg:address":"1015 Tonkawa Rd",
    "sg:city":"Long Lake",
    "sg:classifiers":[
        {
            "category":"Real Estate",
            "subcategory":"Real Estate Operator",
            "type":"Services"
        }
    ],
    "sg:phone":"+1 952 471 7315",
    "sg:postcode":"55356",
    "sg:province":"MN",
    "sg:tags":[
        "property",
        "lessor"
    ],
    "wof:name":"Daniel C Parten",
    "wof:placetype":"venue"
},
  "geometry": {"coordinates":[-93.614908,44.960747],"type":"Point"}
}