{
  "type": "Feature",
  "properties": {
    "iso:country":"US",
    "sg:address":"1425 Colorado Ave S",
    "sg:city":"Minneapolis",
    "sg:classifiers":[
        {
            "category":"Real Estate",
            "subcategory":"Real Estate Operator",
            "type":"Services"
        }
    ],
    "sg:phone":"+1 952 546 3170",
    "sg:postcode":"55416",
    "sg:province":"MN",
    "sg:tags":[
        "apartment"
    ],
    "wof:name":"St Anthony Inc",
    "wof:placetype":"venue"
},
  "geometry": {"coordinates":[-93.359191,44.968814],"type":"Point"}
}