{
  "type": "Feature",
  "properties": {
    "addr:full":"12819 25th Ave SW Pillager MN 56473",
    "addr:housenumber":"12819",
    "addr:postcode":"56473",
    "addr:street":"25Th Ave Sw",
    "iso:country":"US",
    "sg:address":"12819 25th Ave SW",
    "sg:city":"Pillager",
    "sg:classifiers":[
        {
            "category":"Social Services",
            "subcategory":"Adult Care",
            "type":"Services"
        }
    ],
    "sg:phone":"+1 218 764 4298",
    "sg:postcode":"56473",
    "sg:province":"MN",
    "sg:tags":[
        "foster"
    ],
    "wof:name":"Pillager Foster Home",
    "wof:placetype":"venue"
},
  "geometry": {"coordinates":[-94.411462,46.3396],"type":"Point"}
}