{
  "type": "Feature",
  "properties": {
    "addr:full":"15246 140th St Foreston MN 56330",
    "addr:housenumber":"15246",
    "addr:postcode":"56330",
    "addr:street":"140Th St",
    "iso:country":"US",
    "sg:address":"15246 140th St",
    "sg:city":"Foreston",
    "sg:classifiers":[
        {
            "category":"Professional",
            "subcategory":"Business Services",
            "type":"Services"
        }
    ],
    "sg:phone":"+1 320 294 5430",
    "sg:postcode":"56330",
    "sg:province":"MN",
    "wof:name":"Mickelson Cleaning",
    "wof:placetype":"venue"
},
  "geometry": {"coordinates":[-93.729175,45.749818],"type":"Point"}
}