{
  "type": "Feature",
  "properties": {
    "iso:country":"US",
    "sg:address":"507 Division St N",
    "sg:city":"Clara City",
    "sg:classifiers":[
        {
            "category":"Restaurant",
            "type":"Food & Drink"
        }
    ],
    "sg:phone":"+1 320 847 3210",
    "sg:postcode":"56222",
    "sg:province":"MN",
    "sg:tags":[
        "eating"
    ],
    "wof:name":"Rjs Drive Inn",
    "wof:placetype":"venue"
},
  "geometry": {"coordinates":[-95.370915,44.957427],"type":"Point"}
}