{
  "type": "Feature",
  "properties": {
    "addr:full":"43297 840th Ave Hector MN 55342",
    "addr:housenumber":"43297",
    "addr:postcode":"55342",
    "addr:street":"840Th Ave Hector",
    "iso:country":"US",
    "sg:address":"43297 840th Ave",
    "sg:city":"Hector",
    "sg:classifiers":[
        {
            "category":"Farming",
            "subcategory":"Farm",
            "type":"Manufacturing & Wholesale Goods"
        }
    ],
    "sg:phone":"+1 320 848 2863",
    "sg:postcode":"55342",
    "sg:province":"MN",
    "sg:tags":[
        "crop",
        "general"
    ],
    "wof:name":"Dan Gass",
    "wof:placetype":"venue"
},
  "geometry": {"coordinates":[-94.806777,44.804404],"type":"Point"}
}