{
  "type": "Feature",
  "properties": {
    "iso:country":"US",
    "sg:address":"24692 133rd St",
    "sg:city":"Pierz",
    "sg:classifiers":[
        {
            "category":"Professional",
            "subcategory":"Accounting & Tax Preparation",
            "type":"Services"
        }
    ],
    "sg:phone":"+1 320 468 6034",
    "sg:postcode":"56364",
    "sg:province":"MN",
    "sg:tags":[
        "return"
    ],
    "wof:name":"Wehlage Tax Service",
    "wof:placetype":"venue"
},
  "geometry": {"coordinates":[-94.14075800000001,45.955785],"type":"Point"}
}