{
  "type": "Feature",
  "properties": {
    "iso:country":"US",
    "sg:address":"1530 Greenview Dr SW",
    "sg:city":"Rochester",
    "sg:classifiers":[
        {
            "category":"Manufacturing",
            "subcategory":"Signs",
            "type":"Manufacturing & Wholesale Goods"
        }
    ],
    "sg:phone":"+1 507 282 8787",
    "sg:postcode":"55902",
    "sg:province":"MN",
    "sg:website":"www.precisionsigns.net",
    "wof:name":"Precision Signs",
    "wof:placetype":"venue"
},
  "geometry": {"coordinates":[-92.487016,44.003473],"type":"Point"}
}