{
  "type": "Feature",
  "properties": {
    "iso:country":"US",
    "sg:address":"1361 200th Ave",
    "sg:city":"Currie",
    "sg:phone":"+1 507 763 3590",
    "sg:postcode":"56123",
    "sg:province":"MN",
    "sg:tags":[
        "farm",
        "corn"
    ],
    "wof:name":"D Schmitz",
    "wof:placetype":"venue"
},
  "geometry": {"coordinates":[-95.66316999999999,44.044769],"type":"Point"}
}