{
  "type": "Feature",
  "properties": {
    "iso:country":"US",
    "sg:address":"4919 Hwy 52 N",
    "sg:city":"Rochester",
    "sg:classifiers":[
        {
            "category":"Social Services",
            "subcategory":"Child Care",
            "type":"Services"
        }
    ],
    "sg:phone":"+1 507 285 5439",
    "sg:postcode":"55901",
    "sg:province":"MN",
    "wof:name":"City Kidz Academy Inc",
    "wof:placetype":"venue"
},
  "geometry": {"coordinates":[-92.505669,44.075111],"type":"Point"}
}