{
  "type": "Feature",
  "properties": {
    "addr:full":"11670 Forada Beach Rd SE Alexandria MN 56308",
    "addr:housenumber":"11670",
    "addr:postcode":"56308",
    "addr:street":"Forada Beach Rd Se",
    "iso:country":"US",
    "sg:address":"11670 Forada Beach Rd SE",
    "sg:city":"Alexandria",
    "sg:classifiers":[
        {
            "category":"Wholesale",
            "subcategory":"Machinery & Supplies",
            "type":"Manufacturing & Wholesale Goods"
        }
    ],
    "sg:phone":"+1 320 763 7803",
    "sg:postcode":"56308",
    "sg:province":"MN",
    "sg:tags":[
        "equipment",
        "safety"
    ],
    "wof:name":"Alex Air Apparatus Inc",
    "wof:placetype":"venue"
},
  "geometry": {"coordinates":[-95.353818,45.784199],"type":"Point"}
}