{
  "type": "Feature",
  "properties": {
    "iso:country":"US",
    "sg:address":"4124 Quebec Ave N",
    "sg:city":"Minneapolis",
    "sg:classifiers":[
        {
            "category":"Professional",
            "subcategory":"Advertising",
            "type":"Services"
        }
    ],
    "sg:phone":"+1 763 537 7540",
    "sg:postcode":"55427",
    "sg:province":"MN",
    "sg:tags":[
        "agency"
    ],
    "wof:name":"Mark Baker Company Inc",
    "wof:placetype":"venue"
},
  "geometry": {"coordinates":[-93.37642200000001,45.029308],"type":"Point"}
}