{
  "type": "Feature",
  "properties": {
    "addr:full":"7371 Devin Ln Shakopee MN 55379",
    "addr:housenumber":"7371",
    "addr:postcode":"55379",
    "addr:street":"Devin Ln",
    "iso:country":"US",
    "sg:address":"7371 Devin Ln",
    "sg:city":"Shakopee",
    "sg:classifiers":[
        {
            "category":"Professional",
            "subcategory":"Management & Consulting",
            "type":"Services"
        }
    ],
    "sg:phone":"+1 952 402 9511",
    "sg:postcode":"55379",
    "sg:province":"MN",
    "sg:tags":[
        "retail",
        "direct",
        "sales"
    ],
    "wof:name":"Higher Ground Ventures LLC",
    "wof:placetype":"venue"
},
  "geometry": {"coordinates":[-93.420632,44.780114],"type":"Point"}
}