{
  "type": "Feature",
  "properties": {
    "addr:full":"18329 Exodus Ct Farmington MN 55024",
    "addr:postcode":"18329;55024",
    "addr:street":"Exodus Ct",
    "iso:country":"US",
    "sg:address":"18329 Exodus Ct",
    "sg:city":"Farmington",
    "sg:classifiers":[
        {
            "category":"Organizations",
            "subcategory":"Community Association",
            "type":"Services"
        }
    ],
    "sg:phone":"+1 651 460 3799",
    "sg:postcode":"55024",
    "sg:province":"MN",
    "wof:name":"On Eagles Wings Charters Inc",
    "wof:placetype":"venue"
},
  "geometry": {"coordinates":[-93.185243,44.683951],"type":"Point"}
}