{
  "type": "Feature",
  "properties": {
    "iso:country":"US",
    "sg:address":"2325 Rosewood Ln N",
    "sg:city":"Minneapolis",
    "sg:classifiers":[
        {
            "category":"Professional",
            "subcategory":"Computer Services",
            "type":"Services"
        }
    ],
    "sg:phone":"+1 763 557 6603",
    "sg:postcode":"55441",
    "sg:province":"MN",
    "wof:name":"NTS Computer Services Inc",
    "wof:placetype":"venue"
},
  "geometry": {"coordinates":[-93.44367699999999,45.006164],"type":"Point"}
}