{
  "type": "Feature",
  "properties": {
    "iso:country":"US",
    "sg:address":"3290 Ronneby Rd NE",
    "sg:city":"Foley",
    "sg:phone":"+1 320 968 7784",
    "sg:postcode":"56329",
    "sg:province":"MN",
    "sg:tags":[
        "farm",
        "corn"
    ],
    "wof:name":"Duane Hodel",
    "wof:placetype":"venue"
},
  "geometry": {"coordinates":[-93.852391,45.610599],"type":"Point"}
}