{
  "type": "Feature",
  "properties": {
    "addr:full":"1261 120th St Welcome MN 56181",
    "addr:housenumber":"1261",
    "addr:postcode":"56181",
    "addr:street":"120Th St",
    "iso:country":"US",
    "sg:address":"1261 120th St",
    "sg:city":"Welcome",
    "sg:phone":"+1 507 728 8280",
    "sg:postcode":"56181",
    "sg:province":"MN",
    "sg:tags":[
        "farm",
        "corn"
    ],
    "wof:name":"Harry Petrowiak",
    "wof:placetype":"venue"
},
  "geometry": {"coordinates":[-94.62586400000001,43.659887],"type":"Point"}
}