{
  "type": "Feature",
  "properties": {
    "addr:full":"112 Central Ave Nashwauk MN 55769",
    "addr:housenumber":"112",
    "addr:postcode":"55769",
    "addr:street":"Central Ave",
    "iso:country":"US",
    "sg:address":"112 Central Ave",
    "sg:city":"Nashwauk",
    "sg:classifiers":[
        {
            "category":"Insurance",
            "subcategory":"Insurance Agent",
            "type":"Services"
        }
    ],
    "sg:phone":"+1 218 885 2714",
    "sg:postcode":"55769",
    "sg:province":"MN",
    "wof:name":"Mike Olson Insurance",
    "wof:placetype":"venue"
},
  "geometry": {"coordinates":[-93.16732,47.380393],"type":"Point"}
}