{
  "type": "Feature",
  "properties": {
    "addr:full":"16052 Cardinal Rd Osakis MN 56360",
    "addr:housenumber":"16052",
    "addr:postcode":"56360",
    "addr:street":"Cardinal Rd",
    "iso:country":"US",
    "sg:address":"16052 Cardinal Rd",
    "sg:city":"Osakis",
    "sg:classifiers":[
        {
            "category":"Farming",
            "subcategory":"Dairy Farm",
            "type":"Manufacturing & Wholesale Goods"
        }
    ],
    "sg:phone":"+1 320 352 2056",
    "sg:postcode":"56360",
    "sg:province":"MN",
    "wof:name":"Fritz Didier Farm",
    "wof:placetype":"venue"
},
  "geometry": {"coordinates":[-95.022896,45.845029],"type":"Point"}
}