{
  "type": "Feature",
  "properties": {
    "iso:country":"US",
    "sg:address":"45184 State Hwy 65",
    "sg:city":"Mcgregor",
    "sg:classifiers":[
        {
            "category":"Banks & Credit Unions",
            "subcategory":"Bank",
            "type":"Services"
        }
    ],
    "sg:phone":"+1 218 426 0089",
    "sg:postcode":"55760",
    "sg:province":"MN",
    "sg:tags":[
        "loan",
        "real estate"
    ],
    "wof:name":"Wells Fargo Home Mortgage",
    "wof:placetype":"venue"
},
  "geometry": {"coordinates":[-93.317167,46.668093],"type":"Point"}
}