{
  "type": "Feature",
  "properties": {
    "iso:country":"US",
    "sg:address":"227 Colfax Avenue North Suite 260",
    "sg:city":"Minneapolis",
    "sg:classifiers":[
        {
            "category":"Professional",
            "subcategory":"Computer Services",
            "type":"Services"
        }
    ],
    "sg:phone":"+1 612 353 2161",
    "sg:postcode":"55405",
    "sg:province":"MN",
    "sg:website":"http://exosite.com/",
    "wof:name":"Exosite",
    "wof:placetype":"venue"
},
  "geometry": {"coordinates":[-93.291428,44.979965],"type":"Point"}
}