{
  "type": "Feature",
  "properties": {
    "iso:country":"US",
    "sg:address":"7150 163rd St W",
    "sg:city":"Rosemount",
    "sg:classifiers":[
        {
            "category":"Building & Trades",
            "subcategory":"Landscaping Services",
            "type":"Services"
        }
    ],
    "sg:phone":"+1 952 432 7526",
    "sg:postcode":"55068",
    "sg:province":"MN",
    "wof:name":"Ricks Snowplowing & Lawn Care",
    "wof:placetype":"venue"
},
  "geometry": {"coordinates":[-93.21083,44.713848],"type":"Point"}
}