{
  "type": "Feature",
  "properties": {
    "iso:country":"US",
    "sg:address":"2616 27th Ave S",
    "sg:city":"Minneapolis",
    "sg:classifiers":[
        {
            "category":"Shopping",
            "subcategory":"Discount & Variety Stores",
            "type":"Retail Goods"
        }
    ],
    "sg:phone":"+1 612 724 1000",
    "sg:postcode":"55406",
    "sg:province":"MN",
    "sg:tags":[
        "liquidator"
    ],
    "wof:name":"Quick Sales Corp",
    "wof:placetype":"venue"
},
  "geometry": {"coordinates":[-93.23309500000001,44.955284],"type":"Point"}
}