{
  "type": "Feature",
  "properties": {
    "addr:full":"319 Main St Cold Spring MN 56320",
    "addr:housenumber":"319",
    "addr:postcode":"56320",
    "addr:street":"Main St",
    "iso:country":"US",
    "sg:address":"319 Main St",
    "sg:city":"Cold Spring",
    "sg:classifiers":[
        {
            "category":"Home & Garden",
            "subcategory":"Hardware",
            "type":"Retail Goods"
        }
    ],
    "sg:phone":"+1 320 685 8673",
    "sg:postcode":"56320",
    "sg:province":"MN",
    "sg:website":"www.wennerco.doitbest.com",
    "wof:name":"Wenner Do It Best Hardware",
    "wof:placetype":"venue"
},
  "geometry": {"coordinates":[-94.427558,45.455899],"type":"Point"}
}