{
  "type": "Feature",
  "properties": {
    "iso:country":"US",
    "sg:address":"10301 Bren Rd W",
    "sg:city":"Hopkins",
    "sg:classifiers":[
        {
            "category":"Shopping",
            "type":"Retail Goods"
        }
    ],
    "sg:phone":"+1 952 933 4615",
    "sg:postcode":"55343",
    "sg:province":"MN",
    "sg:tags":[
        "outdoor",
        "lighting",
        "specialty"
    ],
    "wof:name":"Kurt Adler Inc",
    "wof:placetype":"venue"
},
  "geometry": {"coordinates":[-93.40849300000001,44.899529],"type":"Point"}
}