{
  "type": "Feature",
  "properties": {
    "iso:country":"US",
    "sg:address":"49 Stenman Rd",
    "sg:city":"Esko",
    "sg:classifiers":[
        {
            "category":"Wholesale",
            "subcategory":"Machinery & Supplies",
            "type":"Manufacturing & Wholesale Goods"
        }
    ],
    "sg:phone":"+1 218 879 3554",
    "sg:postcode":"55733",
    "sg:province":"MN",
    "sg:tags":[
        "equipment",
        "establishment"
    ],
    "wof:name":"Hemmila Amway Home Pdts Distrs",
    "wof:placetype":"venue"
},
  "geometry": {"coordinates":[-92.31201,46.694399],"type":"Point"}
}