{
  "type": "Feature",
  "properties": {
    "iso:country":"US",
    "sg:address":"34901 Co Rd 14",
    "sg:city":"Melrose",
    "sg:phone":"+1 320 987 3128",
    "sg:postcode":"56352",
    "sg:province":"MN",
    "sg:tags":[
        "farm",
        "corn",
        "cash",
        "general",
        "grain",
        "animal"
    ],
    "wof:name":"Norma Hemmesch",
    "wof:placetype":"venue"
},
  "geometry": {"coordinates":[-94.842136,45.528249],"type":"Point"}
}