{
  "type": "Feature",
  "properties": {
    "iso:country":"US",
    "sg:address":"42144 190th Ave",
    "sg:city":"Zumbrota",
    "sg:classifiers":[
        {
            "category":"Farming",
            "subcategory":"Dairy Farm",
            "type":"Manufacturing & Wholesale Goods"
        }
    ],
    "sg:phone":"+1 507 732 7001",
    "sg:postcode":"55992",
    "sg:province":"MN",
    "wof:name":"Jerry Clemenson",
    "wof:placetype":"venue"
},
  "geometry": {"coordinates":[-92.651892,44.337919],"type":"Point"}
}