{
  "type": "Feature",
  "properties": {
    "addr:full":"530 W Main St Anoka MN 55303",
    "addr:housenumber":"530",
    "addr:postcode":"55303",
    "addr:street":"W Main St",
    "iso:country":"US",
    "sg:address":"530 W Main St",
    "sg:city":"Anoka",
    "sg:classifiers":[
        {
            "category":"Banks & Credit Unions",
            "subcategory":"Bank",
            "type":"Services"
        }
    ],
    "sg:phone":"+1 763 746 2900",
    "sg:postcode":"55303",
    "sg:province":"MN",
    "sg:tags":[
        "lending",
        "broker"
    ],
    "wof:name":"Diversified Lending Mrtg Svcs",
    "wof:placetype":"venue"
},
  "geometry": {"coordinates":[-93.399315,45.203618],"type":"Point"}
}