{
  "type": "Feature",
  "properties": {
    "addr:full":"3711 3rd St N Saint Cloud MN 56303",
    "addr:housenumber":"3711",
    "addr:postcode":"56303",
    "addr:street":"3Rd St N",
    "iso:country":"US",
    "sg:address":"3711 3rd St N",
    "sg:city":"Saint Cloud",
    "sg:classifiers":[
        {
            "category":"Insurance",
            "subcategory":"Insurance Agent",
            "type":"Services"
        }
    ],
    "sg:phone":"+1 320 259 0420",
    "sg:postcode":"56303",
    "sg:province":"MN",
    "sg:tags":[
        "broker"
    ],
    "wof:name":"MSI Claims Department",
    "wof:placetype":"venue"
},
  "geometry": {"coordinates":[-94.204589,45.558684],"type":"Point"}
}