{
  "type": "Feature",
  "properties": {
    "addr:full":"13784 Bass Lake Rd Osseo MN 55311",
    "addr:housenumber":"13784",
    "addr:postcode":"55311",
    "addr:street":"Bass Lake Rd",
    "iso:country":"US",
    "sg:address":"13784 Bass Lake Rd",
    "sg:city":"Osseo",
    "sg:classifiers":[
        {
            "category":"Professional",
            "type":"Services"
        }
    ],
    "sg:phone":"+1 763 509 9783",
    "sg:postcode":"55311",
    "sg:province":"MN",
    "wof:name":"Anne B Cronquist",
    "wof:placetype":"venue"
},
  "geometry": {"coordinates":[-93.45514900000001,45.07244],"type":"Point"}
}