{
  "type": "Feature",
  "properties": {
    "addr:full":"603 E Spring St Redwood Falls MN 56283",
    "addr:housenumber":"603",
    "addr:postcode":"56283",
    "addr:street":"E Spring St",
    "iso:country":"US",
    "sg:address":"603 E Spring St",
    "sg:city":"Redwood Falls",
    "sg:classifiers":[
        {
            "category":"Building & Trades",
            "subcategory":"Equipment Rental",
            "type":"Services"
        }
    ],
    "sg:phone":"+1 507 641 8425",
    "sg:postcode":"56283",
    "sg:province":"MN",
    "sg:tags":[
        "camping"
    ],
    "wof:name":"Good Time Tent Rental",
    "wof:placetype":"venue"
},
  "geometry": {"coordinates":[-95.111375,44.542336],"type":"Point"}
}