{
  "type": "Feature",
  "properties": {
    "iso:country":"US",
    "sg:address":"547 131st St",
    "sg:city":"Pipestone",
    "sg:phone":"+1 507 368 9280",
    "sg:postcode":"56164",
    "sg:province":"MN",
    "sg:tags":[
        "farm",
        "corn",
        "soybean"
    ],
    "wof:name":"Ralph E Grenz",
    "wof:placetype":"venue"
},
  "geometry": {"coordinates":[-96.35870300000001,44.037786],"type":"Point"}
}