{
  "type": "Feature",
  "properties": {
    "addr:full":"414 Eastern Ave N Winthrop MN 55396",
    "addr:housenumber":"414",
    "addr:postcode":"55396",
    "addr:street":"Eastern Ave N",
    "iso:country":"US",
    "sg:address":"414 Eastern Ave N",
    "sg:city":"Winthrop",
    "sg:classifiers":[
        {
            "category":"Organizations",
            "subcategory":"Religious Organization",
            "type":"Services"
        }
    ],
    "sg:phone":"+1 507 647 5544",
    "sg:postcode":"55396",
    "sg:province":"MN",
    "sg:tags":[
        "church"
    ],
    "wof:name":"Zion Lutheran Parsonage",
    "wof:placetype":"venue"
},
  "geometry": {"coordinates":[-94.37246500000001,44.544361],"type":"Point"}
}