{
  "type": "Feature",
  "properties": {
    "addr:full":"7710 Computer Ave Edina MN 55435",
    "addr:postcode":"55435",
    "addr:street":"Ave",
    "iso:country":"US",
    "sg:address":"7710 Computer Ave",
    "sg:city":"Edina",
    "sg:classifiers":[
        {
            "category":"Banks & Credit Unions",
            "subcategory":"Bank",
            "type":"Services"
        }
    ],
    "sg:phone":"+1 952 830 1700",
    "sg:postcode":"55435",
    "sg:province":"MN",
    "sg:tags":[
        "loan",
        "real estate"
    ],
    "sg:website":"www.1stpremieremortgage.com",
    "wof:name":"First Premiere Mortgage",
    "wof:placetype":"venue"
},
  "geometry": {"coordinates":[-93.34576,44.862043],"type":"Point"}
}