{
  "type": "Feature",
  "properties": {
    "addr:full":"7130 177th St N Hugo MN 55038",
    "addr:housenumber":"7130",
    "addr:postcode":"55038",
    "addr:street":"177Th St N Hugo",
    "iso:country":"US",
    "sg:address":"7130 177th St N",
    "sg:city":"Hugo",
    "sg:classifiers":[
        {
            "category":"Building & Trades",
            "subcategory":"Construction",
            "type":"Services"
        }
    ],
    "sg:phone":"+1 651 353 7858",
    "sg:postcode":"55038",
    "sg:province":"MN",
    "sg:tags":[
        "concrete",
        "contractor"
    ],
    "wof:name":"LAlllier Concrete Inc",
    "wof:placetype":"venue"
},
  "geometry": {"coordinates":[-92.97032,45.20579],"type":"Point"}
}