{
  "type": "Feature",
  "properties": {
    "iso:country":"US",
    "sg:address":"1789 Iglehart Ave",
    "sg:city":"Saint Paul",
    "sg:classifiers":[
        {
            "category":"Organizations",
            "subcategory":"Religious Organization",
            "type":"Services"
        }
    ],
    "sg:phone":"+1 651 644 8694",
    "sg:postcode":"55104",
    "sg:province":"MN",
    "wof:name":"Disciplship Trining Ministries",
    "wof:placetype":"venue"
},
  "geometry": {"coordinates":[-93.175287,44.949515],"type":"Point"}
}