{
  "type": "Feature",
  "properties": {
    "addr:full":"107 14th Ave E Alexandria MN 56308",
    "addr:housenumber":"107",
    "addr:postcode":"56308",
    "addr:street":"14Th Ave E",
    "iso:country":"US",
    "sg:address":"107 14th Ave E",
    "sg:city":"Alexandria",
    "sg:classifiers":[
        {
            "category":"Health Services",
            "subcategory":"Doctor",
            "type":"Services"
        }
    ],
    "sg:phone":"+1 320 762 1551",
    "sg:postcode":"56308",
    "sg:province":"MN",
    "sg:tags":[
        "dental",
        "clinic",
        "dentist"
    ],
    "wof:name":"Arthur J Hermes Dds",
    "wof:placetype":"venue"
},
  "geometry": {"coordinates":[-95.377627,45.876621],"type":"Point"}
}