{
  "type": "Feature",
  "properties": {
    "iso:country":"US",
    "sg:address":"1200 W 280th St",
    "sg:city":"New Prague",
    "sg:classifiers":[
        {
            "category":"Social Services",
            "subcategory":"Child Care",
            "type":"Services"
        }
    ],
    "sg:phone":"+1 952 758 3515",
    "sg:postcode":"56071",
    "sg:province":"MN",
    "sg:tags":[
        "daycare",
        "provider"
    ],
    "wof:name":"Albert Simon",
    "wof:placetype":"venue"
},
  "geometry": {"coordinates":[-93.54530699999999,44.543555],"type":"Point"}
}