{
  "type": "Feature",
  "properties": {
    "addr:full":"121 Main Ave W Winsted MN 55395",
    "addr:housenumber":"121",
    "addr:postcode":"55395",
    "addr:street":"Main Ave W",
    "iso:country":"US",
    "sg:address":"121 Main Ave W",
    "sg:city":"Winsted",
    "sg:classifiers":[
        {
            "category":"Real Estate",
            "subcategory":"Real Estate Agent",
            "type":"Services"
        }
    ],
    "sg:phone":"+1 320 485 2216",
    "sg:postcode":"55395",
    "sg:province":"MN",
    "wof:name":"Today's Realty",
    "wof:placetype":"venue"
},
  "geometry": {"coordinates":[-94.047246,44.964052],"type":"Point"}
}