{
  "type": "Feature",
  "properties": {
    "addr:full":"521 10th Ave NW Lonsdale MN 55046",
    "addr:housenumber":"521",
    "addr:postcode":"55046",
    "addr:street":"10Th Ave Nw",
    "iso:country":"US",
    "sg:address":"521 10th Ave NW",
    "sg:city":"Lonsdale",
    "sg:classifiers":[
        {
            "category":"Building & Trades",
            "subcategory":"Construction",
            "type":"Services"
        }
    ],
    "sg:phone":"+1 507 744 5855",
    "sg:postcode":"55046",
    "sg:province":"MN",
    "sg:tags":[
        "home",
        "builder"
    ],
    "wof:name":"Keyland Homes Tiffany Realty",
    "wof:placetype":"venue"
},
  "geometry": {"coordinates":[-93.44298999999999,44.482425],"type":"Point"}
}