{
  "type": "Feature",
  "properties": {
    "iso:country":"US",
    "sg:address":"24811 State Hwy 15",
    "sg:city":"Dassel",
    "sg:phone":"+1 320 275 2842",
    "sg:postcode":"55325",
    "sg:province":"MN",
    "sg:tags":[
        "farm",
        "corn",
        "soybean"
    ],
    "wof:name":"Clifford Johnson",
    "wof:placetype":"venue"
},
  "geometry": {"coordinates":[-94.32255499999999,45.104123],"type":"Point"}
}