{
  "type": "Feature",
  "properties": {
    "addr:full":"8393 510th Ave Bricelyn MN 56014",
    "addr:housenumber":"8393",
    "addr:postcode":"56014",
    "addr:street":"510Th Ave",
    "iso:country":"US",
    "sg:address":"8393 510th Ave",
    "sg:city":"Bricelyn",
    "sg:classifiers":[
        {
            "category":"Farming",
            "subcategory":"Farm",
            "type":"Manufacturing & Wholesale Goods"
        }
    ],
    "sg:phone":"+1 507 653 4193",
    "sg:postcode":"56014",
    "sg:province":"MN",
    "wof:name":"Choice Connection",
    "wof:placetype":"venue"
},
  "geometry": {"coordinates":[-93.848055,43.614324],"type":"Point"}
}