{
  "type": "Feature",
  "properties": {
    "addr:full":"2634 Russell Ave N Minneapolis MN 55411",
    "addr:housenumber":"2634",
    "addr:postcode":"55411",
    "addr:street":"Russell Ave N",
    "iso:country":"US",
    "sg:address":"2634 Russell Ave N",
    "sg:city":"Minneapolis",
    "sg:classifiers":[
        {
            "category":"Social Services",
            "type":"Services"
        }
    ],
    "sg:phone":"+1 612 521 2128",
    "sg:postcode":"55411",
    "sg:province":"MN",
    "sg:tags":[
        "shelter",
        "homeless"
    ],
    "sg:website":"www.stannesplace.org",
    "wof:name":"St Anne's Place",
    "wof:placetype":"venue"
},
  "geometry": {"coordinates":[-93.31068999999999,45.007515],"type":"Point"}
}