{
  "type": "Feature",
  "properties": {
    "iso:country":"US",
    "sg:address":"1720 48th Ave NE",
    "sg:city":"Willmar",
    "sg:classifiers":[
        {
            "category":"Freight",
            "type":"Transportation"
        }
    ],
    "sg:phone":"+1 320 235 6714",
    "sg:postcode":"56201",
    "sg:province":"MN",
    "sg:tags":[
        "operator",
        "trucking"
    ],
    "wof:name":"Sun Ray Transport",
    "wof:placetype":"venue"
},
  "geometry": {"coordinates":[-95.017678,45.171526],"type":"Point"}
}