{
  "type": "Feature",
  "properties": {
    "addr:full":"805 Spring Hill Dr St Paul MN 55125",
    "addr:housenumber":"805",
    "addr:postcode":"55125",
    "addr:street":"Spring Hill Dr",
    "iso:country":"US",
    "sg:address":"805 Spring Hill Dr",
    "sg:city":"St Paul",
    "sg:classifiers":[
        {
            "category":"Banks & Credit Unions",
            "subcategory":"Bank",
            "type":"Services"
        }
    ],
    "sg:phone":"+1 651 578 9230",
    "sg:postcode":"55125",
    "sg:province":"MN",
    "wof:name":"B B & J Sales",
    "wof:placetype":"venue"
},
  "geometry": {"coordinates":[-92.924638,44.935598],"type":"Point"}
}