{
  "type": "Feature",
  "properties": {
    "iso:country":"US",
    "sg:address":"13604 Co Rd 11",
    "sg:city":"Burnsville",
    "sg:classifiers":[
        {
            "category":"Insurance",
            "subcategory":"Insurance Agent",
            "type":"Services"
        }
    ],
    "sg:phone":"+1 952 891 2774",
    "sg:postcode":"55337",
    "sg:province":"MN",
    "wof:name":"State Farm Insurance",
    "wof:placetype":"venue"
},
  "geometry": {"coordinates":[-93.24812799999999,44.757344],"type":"Point"}
}