{
  "type": "Feature",
  "properties": {
    "iso:country":"US",
    "sg:address":"13405 15th Ave N",
    "sg:city":"Minneapolis",
    "sg:classifiers":[
        {
            "category":"Home & Garden",
            "subcategory":"Household Appliances",
            "type":"Retail Goods"
        }
    ],
    "sg:phone":"+1 763 553 1445",
    "sg:postcode":"55441",
    "sg:province":"MN",
    "wof:name":"Builders Wholesale",
    "wof:placetype":"venue"
},
  "geometry": {"coordinates":[-93.446878,44.994342],"type":"Point"}
}