{
  "type": "Feature",
  "properties": {
    "iso:country":"US",
    "sg:address":"765 Windemere Dr",
    "sg:city":"Minneapolis",
    "sg:classifiers":[
        {
            "category":"Shopping",
            "subcategory":"Catalog Store",
            "type":"Retail Goods"
        },
        {
            "category":"Shopping",
            "type":"Retail Goods"
        }
    ],
    "sg:phone":"+1 763 545 6655",
    "sg:postcode":"55441",
    "sg:province":"MN",
    "sg:tags":[
        "collectible",
        "order",
        "mail",
        "online"
    ],
    "wof:name":"Rfw Stamps & Supplies",
    "wof:placetype":"venue"
},
  "geometry": {"coordinates":[-93.44422900000001,44.987148],"type":"Point"}
}