{
  "type": "Feature",
  "properties": {
    "addr:full":"40320 Co Rd 11 Clarissa MN 56440",
    "addr:housenumber":"40320;11",
    "addr:postcode":"56440",
    "addr:street":"Co Rd",
    "iso:country":"US",
    "sg:address":"40320 Co Rd 11",
    "sg:city":"Clarissa",
    "sg:classifiers":[
        {
            "category":"Farming",
            "subcategory":"Dairy Farm",
            "type":"Manufacturing & Wholesale Goods"
        }
    ],
    "sg:phone":"+1 218 756 2285",
    "sg:postcode":"56440",
    "sg:province":"MN",
    "wof:name":"Jerome C Gjerstad",
    "wof:placetype":"venue"
},
  "geometry": {"coordinates":[-94.968468,46.21013],"type":"Point"}
}