{
  "type": "Feature",
  "properties": {
    "iso:country":"US",
    "sg:address":"1187 Benton St",
    "sg:city":"Anoka",
    "sg:classifiers":[
        {
            "category":"Manufacturing",
            "subcategory":"Building Materials",
            "type":"Manufacturing & Wholesale Goods"
        }
    ],
    "sg:phone":"+1 763 421 2892",
    "sg:postcode":"55303",
    "sg:province":"MN",
    "sg:tags":[
        "mfg"
    ],
    "wof:name":"Soll Mill Fine Woodworking LLC",
    "wof:placetype":"venue"
},
  "geometry": {"coordinates":[-93.412852,45.201363],"type":"Point"}
}