{
  "type": "Feature",
  "properties": {
    "iso:country":"US",
    "sg:address":"93759 Viking Way",
    "sg:city":"Sturgeon Lake",
    "sg:classifiers":[
        {
            "category":"Building & Trades",
            "subcategory":"Electrical",
            "type":"Services"
        }
    ],
    "sg:phone":"+1 218 485 8469",
    "sg:postcode":"55783",
    "sg:province":"MN",
    "sg:tags":[
        "electric",
        "contractor"
    ],
    "wof:name":"Ketchum Electrical Contracting",
    "wof:placetype":"venue"
},
  "geometry": {"coordinates":[-92.787137,46.409954],"type":"Point"}
}