{
  "type": "Feature",
  "properties": {
    "iso:country":"US",
    "sg:address":"211 Demers Ave",
    "sg:city":"East Grand Forks",
    "sg:classifiers":[
        {
            "category":"Shopping",
            "subcategory":"Hobbies, Toys, & Games",
            "type":"Retail Goods"
        }
    ],
    "sg:phone":"+1 218 773 3492",
    "sg:postcode":"56721",
    "sg:province":"MN",
    "sg:tags":[
        "craft",
        "store"
    ],
    "wof:name":"Ben Franklin Crafts 274",
    "wof:placetype":"venue"
},
  "geometry": {"coordinates":[-97.025835,47.929092],"type":"Point"}
}