{
  "type": "Feature",
  "properties": {
    "iso:country":"US",
    "sg:address":"2355 Polaris Ln N Ste 114",
    "sg:city":"Minneapolis",
    "sg:classifiers":[
        {
            "category":"Retail",
            "subcategory":"Storage",
            "type":"Services"
        }
    ],
    "sg:phone":"+1 763 258 5438",
    "sg:postcode":"55447",
    "sg:province":"MN",
    "sg:tags":[
        "warehouse",
        "cold"
    ],
    "sg:website":"http://www.steinecoldstorage.com",
    "wof:name":"Designer Giftpaks Inc",
    "wof:placetype":"venue"
},
  "geometry": {"coordinates":[-93.47508999999999,45.005341],"type":"Point"}
}