{
  "type": "Feature",
  "properties": {
    "addr:full":"118 Staley Ln Mankato MN 56003",
    "addr:housenumber":"118",
    "addr:postcode":"56003",
    "addr:street":"Staley Ln",
    "iso:country":"US",
    "sg:address":"118 Staley Ln",
    "sg:city":"Mankato",
    "sg:classifiers":[
        {
            "category":"Retail",
            "subcategory":"Auto Repair",
            "type":"Services"
        }
    ],
    "sg:phone":"+1 507 388 8546",
    "sg:postcode":"56003",
    "sg:province":"MN",
    "sg:tags":[
        "body"
    ],
    "wof:name":"Garys Custom Auto",
    "wof:placetype":"venue"
},
  "geometry": {"coordinates":[-94.05486000000001,44.172157],"type":"Point"}
}