{
  "type": "Feature",
  "properties": {
    "addr:full":"923 Brian Ct Saint Cloud MN 56303",
    "addr:housenumber":"923",
    "addr:postcode":"56303",
    "addr:street":"Brian Ct",
    "iso:country":"US",
    "sg:address":"923 Brian Ct",
    "sg:city":"Saint Cloud",
    "sg:classifiers":[
        {
            "category":"Autos & Motor Vehicles",
            "subcategory":"Automobile Sales",
            "type":"Retail Goods"
        }
    ],
    "sg:phone":"+1 320 253 8099",
    "sg:postcode":"56303",
    "sg:province":"MN",
    "sg:tags":[
        "used"
    ],
    "wof:name":"Courtesy Motors",
    "wof:placetype":"venue"
},
  "geometry": {"coordinates":[-94.232017,45.571575],"type":"Point"}
}