{
  "type": "Feature",
  "properties": {
    "iso:country":"US",
    "sg:address":"5860 Kirkwood Ln N",
    "sg:city":"Minneapolis",
    "sg:classifiers":[
        {
            "category":"Farming",
            "subcategory":"Farm & Veterinary Services",
            "type":"Manufacturing & Wholesale Goods"
        }
    ],
    "sg:phone":"+1 763 559 5294",
    "sg:postcode":"55442",
    "sg:province":"MN",
    "sg:tags":[
        "tree",
        "vine",
        "orchard"
    ],
    "wof:name":"Monticello Orchards",
    "wof:placetype":"venue"
},
  "geometry": {"coordinates":[-93.435982,45.059894],"type":"Point"}
}