{
  "type": "Feature",
  "properties": {
    "iso:country":"US",
    "sg:address":"2700 W Michigan St",
    "sg:city":"Duluth",
    "sg:classifiers":[
        {
            "category":"Building & Trades",
            "subcategory":"Construction",
            "type":"Services"
        }
    ],
    "sg:phone":"+1 218 733 1495",
    "sg:postcode":"55806",
    "sg:province":"MN",
    "sg:tags":[
        "house"
    ],
    "wof:name":"Ci Construction",
    "wof:placetype":"venue"
},
  "geometry": {"coordinates":[-92.13235899999999,46.759896],"type":"Point"}
}