{
  "type": "Feature",
  "properties": {
    "iso:country":"US",
    "sg:address":"17499 Driftwood Ln",
    "sg:city":"Park Rapids",
    "sg:classifiers":[
        {
            "category":"Travel",
            "subcategory":"Hotels & Motels",
            "type":"Entertainment"
        }
    ],
    "sg:phone":"+1 218 732 4663",
    "sg:postcode":"56470",
    "sg:province":"MN",
    "sg:tags":[
        "resort"
    ],
    "sg:website":"www.edgewood-resort.com",
    "wof:name":"Edgewood Lodge Resort",
    "wof:placetype":"venue"
},
  "geometry": {"coordinates":[-95.00440999999999,46.90998],"type":"Point"}
}