{
  "type": "Feature",
  "properties": {
    "iso:country":"US",
    "sg:address":"12 Indian Hills Dr",
    "sg:city":"Circle Pines",
    "sg:classifiers":[
        {
            "category":"Social Services",
            "subcategory":"Child Care",
            "type":"Services"
        }
    ],
    "sg:phone":"+1 763 786 6988",
    "sg:postcode":"55014",
    "sg:province":"MN",
    "sg:tags":[
        "day",
        "provider"
    ],
    "wof:name":"Dorothys Daycare",
    "wof:placetype":"venue"
},
  "geometry": {"coordinates":[-93.14918299999999,45.126421],"type":"Point"}
}