{
  "type": "Feature",
  "properties": {
    "addr:full":"313 W 46th St Minneapolis MN 55419",
    "addr:housenumber":"313",
    "addr:postcode":"55419",
    "addr:street":"W 46Th St",
    "iso:country":"US",
    "sg:address":"313 W 46th St",
    "sg:city":"Minneapolis",
    "sg:classifiers":[
        {
            "category":"Professional",
            "type":"Services"
        }
    ],
    "sg:phone":"+1 612 821 1611",
    "sg:postcode":"55419",
    "sg:province":"MN",
    "wof:name":"VIP Svc",
    "wof:placetype":"venue"
},
  "geometry": {"coordinates":[-93.284319,44.919519],"type":"Point"}
}