{
  "type": "Feature",
  "properties": {
    "addr:full":"14386 300th St Adrian MN 56110",
    "addr:housenumber":"14386",
    "addr:postcode":"56110",
    "addr:street":"300Th St",
    "iso:country":"US",
    "sg:address":"14386 300th St",
    "sg:city":"Adrian",
    "sg:phone":"+1 507 967 2103",
    "sg:postcode":"56110",
    "sg:province":"MN",
    "sg:tags":[
        "farm",
        "corn",
        "soybean"
    ],
    "wof:name":"William Debeer",
    "wof:placetype":"venue"
},
  "geometry": {"coordinates":[-95.96613499999999,43.558149],"type":"Point"}
}