{
  "type": "Feature",
  "properties": {
    "addr:full":"604 Saint Olaf Ave Northfield MN 55057",
    "addr:housenumber":"604",
    "addr:postcode":"55057",
    "addr:street":"Saint Olaf Ave",
    "iso:country":"US",
    "sg:address":"604 Saint Olaf Ave",
    "sg:city":"Northfield",
    "sg:classifiers":[
        {
            "category":"Shopping",
            "subcategory":"Jewelry",
            "type":"Retail Goods"
        }
    ],
    "sg:phone":"+1 507 663 8629",
    "sg:postcode":"55057",
    "sg:province":"MN",
    "sg:tags":[
        "jeweler"
    ],
    "wof:name":"Ceecee Designs",
    "wof:placetype":"venue"
},
  "geometry": {"coordinates":[-93.169146,44.460632],"type":"Point"}
}