{
  "type": "Feature",
  "properties": {
    "addr:full":"1672 Lakeland Cir Hugo MN 55038",
    "addr:housenumber":"1672",
    "addr:postcode":"55038",
    "addr:street":"Lakeland Cir Hugo",
    "iso:country":"US",
    "sg:address":"1672 Lakeland Cir",
    "sg:city":"Hugo",
    "sg:classifiers":[
        {
            "category":"Building & Trades",
            "subcategory":"Cleaning & Sanitation",
            "type":"Services"
        }
    ],
    "sg:phone":"+1 651 230 5638",
    "sg:postcode":"55038",
    "sg:province":"MN",
    "sg:tags":[
        "maintenance"
    ],
    "wof:name":"Mikes Clean Sweep Services",
    "wof:placetype":"venue"
},
  "geometry": {"coordinates":[-93.059061,45.168578],"type":"Point"}
}