{
  "type": "Feature",
  "properties": {
    "addr:full":"301 Boulevard Ave NW Montgomery MN 56069",
    "addr:housenumber":"301",
    "addr:postcode":"56069",
    "addr:street":"Boulevard Ave Nw",
    "iso:country":"US",
    "sg:address":"301 Boulevard Ave NW",
    "sg:city":"Montgomery",
    "sg:classifiers":[
        {
            "category":"Education",
            "subcategory":"School",
            "type":"Public Place"
        }
    ],
    "sg:phone":"+1 507 364 8676",
    "sg:postcode":"56069",
    "sg:province":"MN",
    "wof:name":"New Le-Mont Area Learning Ctr",
    "wof:placetype":"venue"
},
  "geometry": {"coordinates":[-93.58515800000001,44.441634],"type":"Point"}
}