{
  "type": "Feature",
  "properties": {
    "addr:full":"929 Goodrich Ave Saint Paul MN 55105",
    "addr:housenumber":"929",
    "addr:postcode":"55105",
    "addr:street":"Goodrich Ave",
    "iso:country":"US",
    "sg:address":"929 Goodrich Ave",
    "sg:city":"Saint Paul",
    "sg:classifiers":[
        {
            "category":"Banks & Credit Unions",
            "subcategory":"Financial Services",
            "type":"Services"
        }
    ],
    "sg:phone":"+1 651 291 8528",
    "sg:postcode":"55105",
    "sg:province":"MN",
    "sg:tags":[
        "investor"
    ],
    "wof:name":"Lifetime Achievement Investors",
    "wof:placetype":"venue"
},
  "geometry": {"coordinates":[-93.141251,44.937912],"type":"Point"}
}