{
  "type": "Feature",
  "properties": {
    "addr:full":"7180 Jubert Ln Hamel MN 55340",
    "addr:housenumber":"7180",
    "addr:postcode":"55340",
    "addr:street":"Jubert Ln",
    "iso:country":"US",
    "sg:address":"7180 Jubert Ln",
    "sg:city":"Hamel",
    "sg:classifiers":[
        {
            "category":"Building & Trades",
            "subcategory":"Construction",
            "type":"Services"
        }
    ],
    "sg:phone":"+1 763 498 6617",
    "sg:postcode":"55340",
    "sg:province":"MN",
    "sg:tags":[
        "home",
        "builder"
    ],
    "wof:name":"Swanson Homes",
    "wof:placetype":"venue"
},
  "geometry": {"coordinates":[-93.607615,45.085847],"type":"Point"}
}