{
  "type": "Feature",
  "properties": {
    "addr:full":"7872 Penn Ave N Minneapolis MN 55444",
    "addr:housenumber":"7872",
    "addr:postcode":"55444",
    "addr:street":"Penn Ave N",
    "iso:country":"US",
    "sg:address":"7872 Penn Ave N",
    "sg:city":"Minneapolis",
    "sg:classifiers":[
        {
            "category":"Building & Trades",
            "subcategory":"Construction",
            "type":"Services"
        }
    ],
    "sg:phone":"+1 763 561 4624",
    "sg:postcode":"55444",
    "sg:province":"MN",
    "sg:tags":[
        "cabinet",
        "contractor",
        "maker",
        "carpentry"
    ],
    "wof:name":"Wood & Things",
    "wof:placetype":"venue"
},
  "geometry": {"coordinates":[-93.311525,45.098021],"type":"Point"}
}