{
  "type": "Feature",
  "properties": {
    "addr:full":"23238 Co Rd 27 Sleepy Eye MN 56085",
    "addr:housenumber":"23238;27",
    "addr:postcode":"56085",
    "addr:street":"Co Rd;Eye",
    "iso:country":"US",
    "sg:address":"23238 Co Rd 27",
    "sg:city":"Sleepy Eye",
    "sg:phone":"+1 507 794 3652",
    "sg:postcode":"56085",
    "sg:province":"MN",
    "sg:tags":[
        "farm",
        "soybean"
    ],
    "wof:name":"Steve Konz",
    "wof:placetype":"venue"
},
  "geometry": {"coordinates":[-94.64447699999999,44.304502],"type":"Point"}
}