{
  "type": "Feature",
  "properties": {
    "addr:full":"10511 Co Rd 23 SE Becker MN 55308",
    "addr:housenumber":"10511;23",
    "addr:postcode":"55308",
    "addr:street":"Co Rd;Se Becker",
    "iso:country":"US",
    "sg:address":"10511 Co Rd 23 SE",
    "sg:city":"Becker",
    "sg:classifiers":[
        {
            "category":"Social Services",
            "subcategory":"Child Care",
            "type":"Services"
        }
    ],
    "sg:phone":"+1 763 261 5165",
    "sg:postcode":"55308",
    "sg:province":"MN",
    "sg:tags":[
        "day"
    ],
    "wof:name":"Quality Child Care",
    "wof:placetype":"venue"
},
  "geometry": {"coordinates":[-93.87082100000001,45.417896],"type":"Point"}
}