{
  "type": "Feature",
  "properties": {
    "iso:country":"US",
    "sg:address":"118 Bush Ct NW",
    "sg:city":"Bemidji",
    "sg:classifiers":[
        {
            "category":"Personal",
            "subcategory":"Beauty Salon",
            "type":"Services"
        }
    ],
    "sg:phone":"+1 218 444 4133",
    "sg:postcode":"56601",
    "sg:province":"MN",
    "wof:name":"Xtreme Lengths Hair Extensions",
    "wof:placetype":"venue"
},
  "geometry": {"coordinates":[-94.917754,47.468678],"type":"Point"}
}