{
  "type": "Feature",
  "properties": {
    "addr:full":"1210 Irving Ave N Minneapolis MN 55411",
    "addr:housenumber":"1210",
    "addr:postcode":"55411",
    "addr:street":"Irving Ave N",
    "iso:country":"US",
    "sg:address":"1210 Irving Ave N",
    "sg:city":"Minneapolis",
    "sg:classifiers":[
        {
            "category":"Building & Trades",
            "subcategory":"Construction",
            "type":"Services"
        }
    ],
    "sg:phone":"+1 763 242 9475",
    "sg:postcode":"55411",
    "sg:province":"MN",
    "sg:tags":[
        "porch",
        "enclosure",
        "patio",
        "deck"
    ],
    "wof:name":"Pro-Tec Deck Care",
    "wof:placetype":"venue"
},
  "geometry": {"coordinates":[-93.29946099999999,44.990026],"type":"Point"}
}