{
  "type": "Feature",
  "properties": {
    "addr:full":"11 Bridge Run Ln Tofte MN 55612",
    "addr:housenumber":"11",
    "addr:postcode":"55612",
    "addr:street":"Bridge Run Ln",
    "iso:country":"US",
    "sg:address":"11 Bridge Run Ln",
    "sg:city":"Tofte",
    "sg:classifiers":[
        {
            "category":"Restaurant",
            "type":"Food & Drink"
        }
    ],
    "sg:phone":"+1 218 663 7316",
    "sg:postcode":"55612",
    "sg:province":"MN",
    "wof:name":"Tracks Restaurant & Bar",
    "wof:placetype":"venue"
},
  "geometry": {"coordinates":[-90.712673,47.658621],"type":"Point"}
}