{
  "type": "Feature",
  "properties": {
    "addr:full":"1816 Field Ave Saint Paul MN 55116",
    "addr:housenumber":"1816",
    "addr:postcode":"55116",
    "addr:street":"Field Ave",
    "iso:country":"US",
    "sg:address":"1816 Field Ave",
    "sg:city":"Saint Paul",
    "sg:classifiers":[
        {
            "category":"Professional",
            "type":"Services"
        }
    ],
    "sg:phone":"+1 651 698 7755",
    "sg:postcode":"55116",
    "sg:province":"MN",
    "wof:name":"Auxilium Funding Services",
    "wof:placetype":"venue"
},
  "geometry": {"coordinates":[-93.177201,44.902578],"type":"Point"}
}