{
  "type": "Feature",
  "properties": {
    "addr:full":"10675 Arkola Rd Meadowlands MN 55765",
    "addr:housenumber":"10675",
    "addr:postcode":"55765",
    "addr:street":"Arkola Rd",
    "iso:country":"US",
    "sg:address":"10675 Arkola Rd",
    "sg:city":"Meadowlands",
    "sg:classifiers":[
        {
            "category":"Shopping",
            "subcategory":"Hobbies, Toys, & Games",
            "type":"Retail Goods"
        }
    ],
    "sg:phone":"+1 218 427 2799",
    "sg:postcode":"55765",
    "sg:province":"MN",
    "sg:tags":[
        "craft"
    ],
    "wof:name":"Windflower Creations",
    "wof:placetype":"venue"
},
  "geometry": {"coordinates":[-92.80804000000001,47.167128],"type":"Point"}
}