{
  "type": "Feature",
  "properties": {
    "iso:country":"US",
    "sg:address":"5249 US Hwy 12",
    "sg:city":"Maple Plain",
    "sg:classifiers":[
        {
            "category":"Food & Beverages",
            "subcategory":"Groceries & Convenience Stores",
            "type":"Retail Goods"
        }
    ],
    "sg:phone":"+1 763 479 6222",
    "sg:postcode":"55359",
    "sg:province":"MN",
    "wof:name":"Olsons's Market",
    "wof:placetype":"venue"
},
  "geometry": {"coordinates":[-93.656868,45.008232],"type":"Point"}
}