{
  "type": "Feature",
  "properties": {
    "iso:country":"US",
    "sg:address":"720 W 3rd St",
    "sg:city":"Red Wing",
    "sg:classifiers":[
        {
            "category":"Building & Trades",
            "subcategory":"Construction",
            "type":"Services"
        }
    ],
    "sg:phone":"+1 651 388 1204",
    "sg:postcode":"55066",
    "sg:province":"MN",
    "sg:tags":[
        "painter"
    ],
    "wof:name":"Gustner Painting",
    "wof:placetype":"venue"
},
  "geometry": {"coordinates":[-92.53752799999999,44.563499],"type":"Point"}
}