{
  "type": "Feature",
  "properties": {
    "addr:full":"912 Mainstreet Hopkins MN 55343",
    "addr:housenumber":"912",
    "addr:postcode":"55343",
    "addr:street":"Mainstreet",
    "iso:country":"US",
    "sg:address":"912 Mainstreet",
    "sg:city":"Hopkins",
    "sg:classifiers":[
        {
            "category":"Shopping",
            "subcategory":"Hobbies, Toys, & Games",
            "type":"Retail Goods"
        }
    ],
    "sg:phone":"+1 952 933 0200",
    "sg:postcode":"55343",
    "sg:province":"MN",
    "sg:tags":[
        "model",
        "supply"
    ],
    "wof:name":"Steve's Train City",
    "wof:placetype":"venue"
},
  "geometry": {"coordinates":[-93.41258000000001,44.924303],"type":"Point"}
}