{
  "type": "Feature",
  "properties": {
    "iso:country":"US",
    "sg:address":"5600 US Hwy 169",
    "sg:city":"Minneapolis",
    "sg:classifiers":[
        {
            "category":"Real Estate",
            "subcategory":"Real Estate Operator",
            "type":"Services"
        }
    ],
    "sg:phone":"+1 763 536 6636",
    "sg:postcode":"55428",
    "sg:province":"MN",
    "sg:tags":[
        "operation"
    ],
    "wof:name":"F L S Properties",
    "wof:placetype":"venue"
},
  "geometry": {"coordinates":[-93.40064099999999,45.054065],"type":"Point"}
}