{
  "type": "Feature",
  "properties": {
    "iso:country":"US",
    "sg:address":"10557 Karston Ave NE",
    "sg:city":"Albertville",
    "sg:classifiers":[
        {
            "category":"Banks & Credit Unions",
            "subcategory":"Bank",
            "type":"Services"
        }
    ],
    "sg:phone":"+1 763 428 8580",
    "sg:postcode":"55301",
    "sg:province":"MN",
    "sg:tags":[
        "broker",
        "mortgage"
    ],
    "wof:name":"Metro Mortgage Group Inc",
    "wof:placetype":"venue"
},
  "geometry": {"coordinates":[-93.67944300000001,45.238332],"type":"Point"}
}