{
  "type": "Feature",
  "properties": {
    "addr:full":"3028 37th Ave SE St Cloud MN 56304",
    "addr:housenumber":"3028",
    "addr:postcode":"56304",
    "addr:street":"37Th Ave Se",
    "iso:country":"US",
    "sg:address":"3028 37th Ave SE",
    "sg:city":"St Cloud",
    "sg:classifiers":[
        {
            "category":"Organizations",
            "subcategory":"Professional Association",
            "type":"Services"
        }
    ],
    "sg:phone":"+1 320 654 6775",
    "sg:postcode":"56304",
    "sg:province":"MN",
    "wof:name":"Minnesota Jewelers Assn",
    "wof:placetype":"venue"
},
  "geometry": {"coordinates":[-94.084599,45.52504],"type":"Point"}
}