{
  "type": "Feature",
  "properties": {
    "iso:country":"US",
    "sg:address":"8301 160th St",
    "sg:city":"Kimball",
    "sg:classifiers":[
        {
            "category":"Farming",
            "subcategory":"Livestock Farm",
            "type":"Manufacturing & Wholesale Goods"
        }
    ],
    "sg:phone":"+1 320 398 3085",
    "sg:postcode":"55353",
    "sg:province":"MN",
    "sg:tags":[
        "feedlot",
        "corn",
        "soybean",
        "beef",
        "cattle"
    ],
    "wof:name":"Daniel Dahnke",
    "wof:placetype":"venue"
},
  "geometry": {"coordinates":[-94.28140999999999,45.353989],"type":"Point"}
}