{
  "type": "Feature",
  "properties": {
    "addr:full":"331 State St N Waseca MN 56093",
    "addr:housenumber":"331",
    "addr:postcode":"56093",
    "addr:street":"State St N",
    "iso:country":"US",
    "sg:address":"331 State St N",
    "sg:city":"Waseca",
    "sg:classifiers":[
        {
            "category":"Personal",
            "subcategory":"Massage",
            "type":"Services"
        },
        {
            "category":"Health Services",
            "subcategory":"Clinic",
            "type":"Services"
        },
        {
            "category":"Health Services",
            "subcategory":"Health Practitioner",
            "type":"Services"
        }
    ],
    "sg:phone":"+1 507 835 1392",
    "sg:postcode":"56093",
    "sg:province":"MN",
    "sg:tags":[
        "medicine",
        "therapist",
        "therapy",
        "acupuncture",
        "alternative",
        "physical"
    ],
    "wof:name":"Healing Hands Wellness Group",
    "wof:placetype":"venue"
},
  "geometry": {"coordinates":[-93.507435,44.091049],"type":"Point"}
}