{
  "type": "Feature",
  "properties": {
    "addr:full":"27340 Co Hwy 4 Pelican Rapids MN 56572",
    "addr:housenumber":"27340",
    "addr:postcode":"56572",
    "addr:street":"Co Hwy 4",
    "iso:country":"US",
    "sg:address":"27340 Co Hwy 4",
    "sg:city":"Pelican Rapids",
    "sg:phone":"+1 218 342 2606",
    "sg:postcode":"56572",
    "sg:province":"MN",
    "sg:tags":[
        "farm",
        "field",
        "corn",
        "crop"
    ],
    "wof:name":"David Colosky",
    "wof:placetype":"venue"
},
  "geometry": {"coordinates":[-95.928608,46.601865],"type":"Point"}
}