{
  "type": "Feature",
  "properties": {
    "addr:full":"2801 18th Ave S Minneapolis MN 55467",
    "addr:housenumber":"2801",
    "addr:postcode":"55467",
    "addr:street":"18Th Ave S",
    "iso:country":"US",
    "sg:address":"2801 18th Ave S",
    "sg:city":"Minneapolis",
    "sg:classifiers":[
        {
            "category":"Arts & Performance",
            "subcategory":"Arts Center",
            "type":"Entertainment"
        }
    ],
    "sg:phone":"+1 612 729 1965",
    "sg:postcode":"55467",
    "sg:province":"MN",
    "sg:website":"www.myspace.com/indigenousinmusic",
    "wof:name":"Indigenous in Music",
    "wof:placetype":"venue"
},
  "geometry": {"coordinates":[-93.24864700000001,44.951942],"type":"Point"}
}