{
  "type": "Feature",
  "properties": {
    "addr:full":"802 Birch St Floodwood MN 55736",
    "addr:housenumber":"802",
    "addr:postcode":"55736",
    "addr:street":"Birch St",
    "iso:country":"US",
    "sg:address":"802 Birch St",
    "sg:city":"Floodwood",
    "sg:classifiers":[
        {
            "category":"Building & Trades",
            "subcategory":"Landscaping Services",
            "type":"Services"
        }
    ],
    "sg:phone":"+1 218 476 2862",
    "sg:postcode":"55736",
    "sg:province":"MN",
    "wof:name":"Hendrickson Lawn Care",
    "wof:placetype":"venue"
},
  "geometry": {"coordinates":[-92.920283,46.926024],"type":"Point"}
}