{
  "type": "Feature",
  "properties": {
    "addr:full":"21401 Hemlock Ave Lakeville MN 55044",
    "addr:housenumber":"21401",
    "addr:postcode":"55044",
    "addr:street":"Hemlock Ave",
    "iso:country":"US",
    "sg:address":"21401 Hemlock Ave",
    "sg:city":"Lakeville",
    "sg:classifiers":[
        {
            "category":"Manufacturing",
            "subcategory":"Tools & Machinery",
            "type":"Manufacturing & Wholesale Goods"
        }
    ],
    "sg:phone":"+1 952 469 2445",
    "sg:postcode":"55044",
    "sg:province":"MN",
    "sg:tags":[
        "dental",
        "mfg",
        "supply"
    ],
    "wof:name":"Pinnacle Products Inc",
    "wof:placetype":"venue"
},
  "geometry": {"coordinates":[-93.234056,44.638849],"type":"Point"}
}