{
  "type": "Feature",
  "properties": {
    "addr:full":"2089 Nightengale St Mora MN 55051",
    "addr:housenumber":"2089",
    "addr:postcode":"55051",
    "addr:street":"Nightengale St",
    "iso:country":"US",
    "sg:address":"2089 Nightengale St",
    "sg:city":"Mora",
    "sg:classifiers":[
        {
            "category":"Manufacturing",
            "subcategory":"Lumber",
            "type":"Manufacturing & Wholesale Goods"
        }
    ],
    "sg:phone":"+1 320 679 4645",
    "sg:postcode":"55051",
    "sg:province":"MN",
    "sg:tags":[
        "operation",
        "timber",
        "tract"
    ],
    "wof:name":"Bob Smiths Christmas Trees",
    "wof:placetype":"venue"
},
  "geometry": {"coordinates":[-93.235727,45.87846],"type":"Point"}
}