{
  "type": "Feature",
  "properties": {
    "addr:full":"5008 Hillsboro Ave N Minneapolis MN 55428",
    "addr:housenumber":"5008",
    "addr:postcode":"55428",
    "addr:street":"Hillsboro Ave N",
    "iso:country":"US",
    "sg:address":"5008 Hillsboro Ave N",
    "sg:city":"Minneapolis",
    "sg:classifiers":[
        {
            "category":"Wholesale",
            "subcategory":"Office Equipment",
            "type":"Manufacturing & Wholesale Goods"
        },
        {
            "category":"Manufacturing",
            "subcategory":"Electronics",
            "type":"Manufacturing & Wholesale Goods"
        },
        {
            "category":"Shopping",
            "subcategory":"Computers & Home Electronics",
            "type":"Retail Goods"
        }
    ],
    "sg:phone":"+1 763 531 8222",
    "sg:postcode":"55428",
    "sg:province":"MN",
    "sg:tags":[
        "scanning",
        "printers-equipment",
        "printer",
        "plotting",
        "supply"
    ],
    "sg:website":"http://www.northlightcolor.com",
    "wof:name":"North Light Color, Inc.",
    "wof:placetype":"venue"
},
  "geometry": {"coordinates":[-93.398724,45.046364],"type":"Point"}
}