{
  "type": "Feature",
  "properties": {
    "iso:country":"US",
    "sg:address":"9564 Baptist Church Rd",
    "sg:city":"Princeton",
    "sg:classifiers":[
        {
            "category":"Organizations",
            "subcategory":"Religious Organization",
            "type":"Services"
        }
    ],
    "sg:phone":"+1 763 389 2777",
    "sg:postcode":"55371",
    "sg:province":"MN",
    "sg:tags":[
        "churches-baptist"
    ],
    "sg:website":"http://www.abc-usa.org",
    "wof:name":"First Baptist Church",
    "wof:placetype":"venue"
},
  "geometry": {"coordinates":[-93.60433399999999,45.58807],"type":"Point"}
}