{
  "type": "Feature",
  "properties": {
    "addr:full":"25970 US Hwy 14 Sleepy Eye MN 56085",
    "addr:postcode":"25970;56085",
    "addr:street":"Us Hwy 14 Sleepy",
    "iso:country":"US",
    "sg:address":"25970 US Hwy 14",
    "sg:city":"Sleepy Eye",
    "sg:classifiers":[
        {
            "category":"Building & Trades",
            "subcategory":"Construction",
            "type":"Services"
        },
        {
            "category":"Home & Garden",
            "subcategory":"Furniture",
            "type":"Retail Goods"
        }
    ],
    "sg:phone":"+1 507 794 5123",
    "sg:postcode":"56085",
    "sg:province":"MN",
    "sg:tags":[
        "cabinet",
        "carpentry",
        "contractor"
    ],
    "wof:name":"Sleepy Eye Cabinets & More",
    "wof:placetype":"venue"
},
  "geometry": {"coordinates":[-94.709018,44.297184],"type":"Point"}
}