{
  "type": "Feature",
  "properties": {
    "addr:full":"493 37th St NE Rochester MN 55906",
    "addr:housenumber":"493",
    "addr:postcode":"55906",
    "addr:street":"37Th St Ne",
    "iso:country":"US",
    "sg:address":"493 37th St NE",
    "sg:city":"Rochester",
    "sg:classifiers":[
        {
            "category":"Insurance",
            "subcategory":"Insurance Agent",
            "type":"Services"
        }
    ],
    "sg:phone":"+1 507 281 1210",
    "sg:postcode":"55906",
    "sg:province":"MN",
    "wof:name":"Mike Busch Insurance",
    "wof:placetype":"venue"
},
  "geometry": {"coordinates":[-92.455493,44.05942],"type":"Point"}
}