{
  "type": "Feature",
  "properties": {
    "addr:full":"331 2nd Ave. S Minneapolis MN 55401",
    "addr:housenumber":"331",
    "addr:postcode":"55401",
    "addr:street":"2Nd Ave. S",
    "iso:country":"US",
    "sg:address":"331 2nd Ave. S",
    "sg:city":"Minneapolis",
    "sg:classifiers":[
        {
            "category":"Restaurant",
            "type":"Food & Drink"
        }
    ],
    "sg:phone":"+1 612 340 0890",
    "sg:postcode":"55401",
    "sg:province":"MN",
    "sg:tags":[
        "chinese"
    ],
    "wof:name":"The Bamboo Shoot",
    "wof:placetype":"venue"
},
  "geometry": {"coordinates":[-93.266543,44.978677],"type":"Point"}
}