{
  "type": "Feature",
  "properties": {
    "addr:full":"851 W Pierce Butler Rte Saint Paul MN 55104",
    "addr:housenumber":"851",
    "addr:postcode":"55104",
    "addr:street":"W Pierce",
    "iso:country":"US",
    "sg:address":"851 W Pierce Butler Rte",
    "sg:city":"Saint Paul",
    "sg:classifiers":[
        {
            "category":"Organizations",
            "subcategory":"Labor Organization",
            "type":"Services"
        }
    ],
    "sg:phone":"+1 651 489 1488",
    "sg:postcode":"55104",
    "sg:province":"MN",
    "sg:tags":[
        "trade",
        "contractor"
    ],
    "wof:name":"Iron Workers Local 512",
    "wof:placetype":"venue"
},
  "geometry": {"coordinates":[-93.134957,44.964796],"type":"Point"}
}