{
  "type": "Feature",
  "properties": {
    "iso:country":"US",
    "sg:address":"1935 Century Ave S",
    "sg:city":"Saint Paul",
    "sg:classifiers":[
        {
            "category":"Health Services",
            "subcategory":"Health Practitioner",
            "type":"Services"
        }
    ],
    "sg:phone":"+1 651 636 2666",
    "sg:postcode":"55125",
    "sg:province":"MN",
    "sg:tags":[
        "therapy",
        "treatment",
        "physical"
    ],
    "wof:name":"HealthSouth",
    "wof:placetype":"venue"
},
  "geometry": {"coordinates":[-92.984358,44.922064],"type":"Point"}
}