{
  "type": "Feature",
  "properties": {
    "addr:full":"11359 Creekridge Dr Eden Prairie MN 55347",
    "addr:housenumber":"11359",
    "addr:postcode":"55347",
    "addr:street":"Creekridge Dr",
    "iso:country":"US",
    "sg:address":"11359 Creekridge Dr",
    "sg:city":"Eden Prairie",
    "sg:classifiers":[
        {
            "category":"Professional",
            "subcategory":"Employment Agencies",
            "type":"Services"
        }
    ],
    "sg:phone":"+1 952 941 3465",
    "sg:postcode":"55347",
    "sg:province":"MN",
    "sg:tags":[
        "help",
        "supply"
    ],
    "wof:name":"Temporary Heroes",
    "wof:placetype":"venue"
},
  "geometry": {"coordinates":[-93.420652,44.825142],"type":"Point"}
}