{
  "type": "Feature",
  "properties": {
    "iso:country":"US",
    "sg:address":"3517 Orchard Ln",
    "sg:city":"Minnetonka",
    "sg:classifiers":[
        {
            "category":"Professional",
            "subcategory":"Employment Agencies",
            "type":"Services"
        }
    ],
    "sg:phone":"+1 952 932 9662",
    "sg:postcode":"55305",
    "sg:province":"MN",
    "sg:tags":[
        "consultant",
        "search",
        "executive"
    ],
    "wof:name":"Leadership Tactics",
    "wof:placetype":"venue"
},
  "geometry": {"coordinates":[-93.440049,44.93928],"type":"Point"}
}