{
  "type": "Feature",
  "properties": {
    "addr:full":"4328 W 6th St Duluth MN 55807",
    "addr:housenumber":"4328",
    "addr:postcode":"55807",
    "addr:street":"W 6Th St",
    "iso:country":"US",
    "sg:address":"4328 W 6th St",
    "sg:city":"Duluth",
    "sg:classifiers":[
        {
            "category":"Education",
            "subcategory":"Vocational School",
            "type":"Public Place"
        }
    ],
    "sg:phone":"+1 218 624 7711",
    "sg:postcode":"55807",
    "sg:province":"MN",
    "wof:name":"Northland Per Training Svcs",
    "wof:placetype":"venue"
},
  "geometry": {"coordinates":[-92.159312,46.750116],"type":"Point"}
}