{
  "type": "Feature",
  "properties": {
    "addr:full":"624 S Minnesota Ave St Peter MN 56082",
    "addr:housenumber":"624",
    "addr:postcode":"56082",
    "addr:street":"S Minnesota Ave",
    "iso:country":"US",
    "sg:address":"624 S Minnesota Ave",
    "sg:city":"St Peter",
    "sg:classifiers":[
        {
            "category":"Food & Beverages",
            "subcategory":"Groceries & Convenience Stores",
            "type":"Retail Goods"
        }
    ],
    "sg:phone":"+1 507 931 6841",
    "sg:postcode":"56082",
    "sg:province":"MN",
    "wof:name":"Freedom Valu Ctr",
    "wof:placetype":"venue"
},
  "geometry": {"coordinates":[-93.95958,44.321406],"type":"Point"}
}