{
  "type": "Feature",
  "properties": {
    "addr:full":"3794 Elynwood Rd Hibbing MN 55746",
    "addr:housenumber":"3794",
    "addr:postcode":"55746",
    "addr:street":"Elynwood Rd",
    "iso:country":"US",
    "sg:address":"3794 Elynwood Rd",
    "sg:city":"Hibbing",
    "sg:classifiers":[
        {
            "category":"Retail",
            "subcategory":"Auto Repair",
            "type":"Services"
        }
    ],
    "sg:phone":"+1 218 778 0018",
    "sg:postcode":"55746",
    "sg:province":"MN",
    "sg:tags":[
        "body",
        "automobile",
        "painting",
        "repairing"
    ],
    "wof:name":"Joby Wolff Autobody",
    "wof:placetype":"venue"
},
  "geometry": {"coordinates":[-93.024473,47.391608],"type":"Point"}
}