{
  "type": "Feature",
  "properties": {
    "iso:country":"US",
    "sg:address":"1100 Aspen Dr",
    "sg:city":"Burnsville",
    "sg:classifiers":[
        {
            "category":"Professional",
            "subcategory":"Business Services",
            "type":"Services"
        }
    ],
    "sg:phone":"+1 952 895 0002",
    "sg:postcode":"55337",
    "sg:province":"MN",
    "sg:tags":[
        "trade",
        "contractor"
    ],
    "wof:name":"Waters Plus",
    "wof:placetype":"venue"
},
  "geometry": {"coordinates":[-93.25957200000001,44.76661],"type":"Point"}
}