{
  "type": "Feature",
  "properties": {
    "addr:full":"165 James Ave N Minneapolis MN 55405",
    "addr:housenumber":"165",
    "addr:postcode":"55405",
    "addr:street":"James Ave N",
    "iso:country":"US",
    "sg:address":"165 James Ave N",
    "sg:city":"Minneapolis",
    "sg:classifiers":[
        {
            "category":"Building & Trades",
            "subcategory":"Landscaping Services",
            "type":"Services"
        }
    ],
    "sg:phone":"+1 612 374 4228",
    "sg:postcode":"55405",
    "sg:province":"MN",
    "sg:tags":[
        "lawn",
        "maintenance",
        "grounds"
    ],
    "wof:name":"Hawes Lawn Svc",
    "wof:placetype":"venue"
},
  "geometry": {"coordinates":[-93.30079499999999,44.977447],"type":"Point"}
}