{
  "type": "Feature",
  "properties": {
    "iso:country":"US",
    "sg:address":"1512 E Lake St",
    "sg:city":"Minneapolis",
    "sg:classifiers":[
        {
            "category":"Shopping",
            "type":"Retail Goods"
        }
    ],
    "sg:phone":"+1 612 721 6688",
    "sg:postcode":"55407",
    "sg:province":"MN",
    "sg:tags":[
        "cosmetic",
        "perfume"
    ],
    "wof:name":"Perfumeria Sanchez",
    "wof:placetype":"venue"
},
  "geometry": {"coordinates":[-93.252956,44.948439],"type":"Point"}
}