{
  "type": "Feature",
  "properties": {
    "iso:country":"US",
    "sg:address":"5709 Newport Dr",
    "sg:city":"Minneapolis",
    "sg:classifiers":[
        {
            "category":"Organizations",
            "subcategory":"Religious Organization",
            "type":"Services"
        }
    ],
    "sg:phone":"+1 612 729 1935",
    "sg:postcode":"55436",
    "sg:province":"MN",
    "sg:tags":[
        "church"
    ],
    "wof:name":"Hugh Thomas Presbyterian Ch",
    "wof:placetype":"venue"
},
  "geometry": {"coordinates":[-93.3905,44.900356],"type":"Point"}
}