{
  "type": "Feature",
  "properties": {
    "addr:full":"1692 440th St Harris MN 55032",
    "addr:housenumber":"1692",
    "addr:postcode":"55032",
    "addr:street":"440Th St",
    "iso:country":"US",
    "sg:address":"1692 440th St",
    "sg:city":"Harris",
    "sg:classifiers":[
        {
            "category":"Home & Garden",
            "subcategory":"Furniture",
            "type":"Retail Goods"
        }
    ],
    "sg:phone":"+1 651 674 8660",
    "sg:postcode":"55032",
    "sg:province":"MN",
    "sg:tags":[
        "shop",
        "custom",
        "cabinet"
    ],
    "wof:name":"D & K Kustom Kabinets Inc",
    "wof:placetype":"venue"
},
  "geometry": {"coordinates":[-93.072762,45.587186],"type":"Point"}
}