{
  "type": "Feature",
  "properties": {
    "addr:full":"15521 Edgewood Dr Brainerd MN 56401",
    "addr:housenumber":"15521",
    "addr:postcode":"56401",
    "addr:street":"Edgewood Dr",
    "iso:country":"US",
    "sg:address":"15521 Edgewood Dr",
    "sg:city":"Brainerd",
    "sg:classifiers":[
        {
            "category":"Building & Trades",
            "subcategory":"Landscaping Services",
            "type":"Services"
        }
    ],
    "sg:phone":"+1 218 829 0880",
    "sg:postcode":"56401",
    "sg:province":"MN",
    "sg:tags":[
        "landscape",
        "contractor"
    ],
    "wof:name":"Dans Sod Service",
    "wof:placetype":"venue"
},
  "geometry": {"coordinates":[-94.249107,46.376107],"type":"Point"}
}