{
  "type": "Feature",
  "properties": {
    "addr:full":"1760 Cottonwood Cir Saint Cloud MN 56303",
    "addr:housenumber":"1760",
    "addr:postcode":"56303",
    "addr:street":"Cottonwood Cir",
    "iso:country":"US",
    "sg:address":"1760 Cottonwood Cir",
    "sg:city":"Saint Cloud",
    "sg:classifiers":[
        {
            "category":"Social Services",
            "subcategory":"Child Care",
            "type":"Services"
        }
    ],
    "sg:phone":"+1 320 251 8542",
    "sg:postcode":"56303",
    "sg:province":"MN",
    "sg:tags":[
        "daycare",
        "provider"
    ],
    "wof:name":"Marilyn J Liverca",
    "wof:placetype":"venue"
},
  "geometry": {"coordinates":[-94.245175,45.57986],"type":"Point"}
}