{
  "type": "Feature",
  "properties": {
    "addr:full":"920 Tyler St Hastings MN 55033",
    "addr:housenumber":"920",
    "addr:postcode":"55033",
    "addr:street":"Tyler St",
    "iso:country":"US",
    "sg:address":"920 Tyler St",
    "sg:city":"Hastings",
    "sg:classifiers":[
        {
            "category":"Personal",
            "subcategory":"Beauty Salon",
            "type":"Services"
        }
    ],
    "sg:phone":"+1 651 437 4197",
    "sg:postcode":"55033",
    "sg:province":"MN",
    "sg:tags":[
        "shop"
    ],
    "wof:name":"Hastings Beauty Salon",
    "wof:placetype":"venue"
},
  "geometry": {"coordinates":[-92.848748,44.737496],"type":"Point"}
}