{
  "type": "Feature",
  "properties": {
    "iso:country":"US",
    "sg:address":"17252 Lyons St NE",
    "sg:city":"Forest Lake",
    "sg:classifiers":[
        {
            "category":"Professional",
            "subcategory":"Business Services",
            "type":"Services"
        }
    ],
    "sg:phone":"+1 651 982 9674",
    "sg:postcode":"55025",
    "sg:province":"MN",
    "wof:name":"1st Choice Home Inspections",
    "wof:placetype":"venue"
},
  "geometry": {"coordinates":[-93.019611,45.283536],"type":"Point"}
}