{
  "type": "Feature",
  "properties": {
    "addr:full":"1011 1st St E Park Rapids MN 56470",
    "addr:housenumber":"1011",
    "addr:postcode":"56470",
    "addr:street":"1St St E",
    "iso:country":"US",
    "sg:address":"1011 1st St E",
    "sg:city":"Park Rapids",
    "sg:classifiers":[
        {
            "category":"Insurance",
            "subcategory":"Insurance Agent",
            "type":"Services"
        }
    ],
    "sg:phone":"+1 218 237 3276",
    "sg:postcode":"56470",
    "sg:province":"MN",
    "wof:name":"Farm Bureau Insurance",
    "wof:placetype":"venue"
},
  "geometry": {"coordinates":[-95.04189,46.92192],"type":"Point"}
}