{
  "type": "Feature",
  "properties": {
    "iso:country":"US",
    "sg:address":"11300 Minnetonka Mills Rd Ste A",
    "sg:city":"Hopkins",
    "sg:classifiers":[
        {
            "category":"Place Of Worship",
            "type":"Public Place"
        }
    ],
    "sg:phone":"+1 952 935 6593",
    "sg:postcode":"55305",
    "sg:province":"MN",
    "sg:tags":[
        "church"
    ],
    "wof:name":"Living Faith Spiritual Center",
    "wof:placetype":"venue"
},
  "geometry": {"coordinates":[-93.42235599999999,44.934039],"type":"Point"}
}