{
  "type": "Feature",
  "properties": {
    "iso:country":"US",
    "sg:address":"7308 Aspen Ln N",
    "sg:city":"Minneapolis",
    "sg:classifiers":[
        {
            "category":"Manufacturing",
            "subcategory":"Apparel",
            "type":"Manufacturing & Wholesale Goods"
        }
    ],
    "sg:phone":"+1 763 425 4996",
    "sg:postcode":"55428",
    "sg:province":"MN",
    "sg:tags":[
        "flag",
        "banner"
    ],
    "wof:name":"Creative Changeables",
    "wof:placetype":"venue"
},
  "geometry": {"coordinates":[-93.388784,45.090684],"type":"Point"}
}