{
  "type": "Feature",
  "properties": {
    "addr:full":"4518 Wentworth Ave S Minneapolis MN 55419",
    "addr:housenumber":"4518",
    "addr:postcode":"55419",
    "addr:street":"Wentworth Ave S",
    "iso:country":"US",
    "sg:address":"4518 Wentworth Ave S",
    "sg:city":"Minneapolis",
    "sg:classifiers":[
        {
            "category":"Wholesale",
            "subcategory":"Computers",
            "type":"Manufacturing & Wholesale Goods"
        }
    ],
    "sg:phone":"+1 612 825 6416",
    "sg:postcode":"55419",
    "sg:province":"MN",
    "sg:tags":[
        "farm",
        "crop",
        "general"
    ],
    "wof:name":"Manage Farm",
    "wof:placetype":"venue"
},
  "geometry": {"coordinates":[-93.280614,44.919954],"type":"Point"}
}