{
  "type": "Feature",
  "properties": {
    "addr:full":"6301 Timber Trl Minneapolis MN 55439",
    "addr:housenumber":"6301",
    "addr:postcode":"55439",
    "addr:street":"Timber Trl",
    "iso:country":"US",
    "sg:address":"6301 Timber Trl",
    "sg:city":"Minneapolis",
    "sg:classifiers":[
        {
            "category":"Building & Trades",
            "subcategory":"Construction",
            "type":"Services"
        }
    ],
    "sg:phone":"+1 952 942 6129",
    "sg:postcode":"55439",
    "sg:province":"MN",
    "sg:tags":[
        "concrete",
        "pumping",
        "contractor"
    ],
    "wof:name":"Burbidge Minerals",
    "wof:placetype":"venue"
},
  "geometry": {"coordinates":[-93.391724,44.88958],"type":"Point"}
}