{
  "type": "Feature",
  "properties": {
    "iso:country":"US",
    "sg:address":"47420 Co Hwy 16",
    "sg:city":"Henning",
    "sg:classifiers":[
        {
            "category":"Sports & Exercise",
            "subcategory":"Golf",
            "type":"Entertainment"
        },
        {
            "category":"Wholesale",
            "subcategory":"Painting Supplies",
            "type":"Manufacturing & Wholesale Goods"
        }
    ],
    "sg:phone":"+1 218 583 2127",
    "sg:postcode":"56551",
    "sg:province":"MN",
    "sg:tags":[
        "course"
    ],
    "wof:name":"Oakwood Golf Course",
    "wof:placetype":"venue"
},
  "geometry": {"coordinates":[-95.50334599999999,46.325484],"type":"Point"}
}