{
  "type": "Feature",
  "properties": {
    "addr:full":"7201 Portland Ave S Minneapolis MN 55423",
    "addr:housenumber":"7201",
    "addr:postcode":"55423",
    "addr:street":"Portland Ave S",
    "iso:country":"US",
    "sg:address":"7201 Portland Ave S",
    "sg:city":"Minneapolis",
    "sg:classifiers":[
        {
            "category":"Professional",
            "type":"Services"
        }
    ],
    "sg:phone":"+1 952 886 9886",
    "sg:postcode":"55423",
    "sg:province":"MN",
    "wof:name":"Stocker Diversified",
    "wof:placetype":"venue"
},
  "geometry": {"coordinates":[-93.26805899999999,44.870895],"type":"Point"}
}