{
  "type": "Feature",
  "properties": {
    "addr:full":"650 Quaker Ave Jordan MN 55352",
    "addr:housenumber":"650",
    "addr:postcode":"55352",
    "addr:street":"Quaker Ave",
    "iso:country":"US",
    "sg:address":"650 Quaker Ave",
    "sg:city":"Jordan",
    "sg:classifiers":[
        {
            "category":"Building & Trades",
            "subcategory":"Construction",
            "type":"Services"
        }
    ],
    "sg:phone":"+1 952 492 5700",
    "sg:postcode":"55352",
    "sg:province":"MN",
    "sg:tags":[
        "excavating",
        "contractor"
    ],
    "wof:name":"S M Hentges & Sons Inc",
    "wof:placetype":"venue"
},
  "geometry": {"coordinates":[-93.641575,44.673697],"type":"Point"}
}