{
  "type": "Feature",
  "properties": {
    "addr:full":"2585 Hamline Ave N Roseville MN 55113",
    "addr:housenumber":"2585",
    "addr:postcode":"55113",
    "addr:street":"Hamline Ave N",
    "iso:country":"US",
    "sg:address":"2585 Hamline Ave N",
    "sg:city":"Roseville",
    "sg:classifiers":[
        {
            "category":"Professional",
            "subcategory":"Business Services",
            "type":"Services"
        },
        {
            "category":"Professional",
            "subcategory":"Advertising",
            "type":"Services"
        }
    ],
    "sg:phone":"+1 651 636 0343",
    "sg:postcode":"55113",
    "sg:province":"MN",
    "sg:tags":[
        "counselor"
    ],
    "sg:website":"www.mirageadvertising.com",
    "wof:name":"Wise Buy Media",
    "wof:placetype":"venue"
},
  "geometry": {"coordinates":[-93.156863,45.017962],"type":"Point"}
}