{
  "type": "Feature",
  "properties": {
    "iso:country":"US",
    "sg:address":"220 4th St SE",
    "sg:city":"Hallock",
    "sg:classifiers":[
        {
            "category":"Social Services",
            "subcategory":"Child Care",
            "type":"Services"
        }
    ],
    "sg:phone":"+1 218 843 2087",
    "sg:postcode":"56728",
    "sg:province":"MN",
    "sg:tags":[
        "nursery",
        "day"
    ],
    "wof:name":"Anita Anderson",
    "wof:placetype":"venue"
},
  "geometry": {"coordinates":[-96.94799,48.771679],"type":"Point"}
}