{
  "type": "Feature",
  "properties": {
    "addr:full":"20020 Co Hwy 25 Detroit Lakes MN 56501",
    "addr:housenumber":"20020",
    "addr:postcode":"56501",
    "addr:street":"Co Hwy 25",
    "iso:country":"US",
    "sg:address":"20020 Co Hwy 25",
    "sg:city":"Detroit Lakes",
    "sg:classifiers":[
        {
            "category":"Building & Trades",
            "subcategory":"Construction",
            "type":"Services"
        }
    ],
    "sg:phone":"+1 218 847 6374",
    "sg:postcode":"56501",
    "sg:province":"MN",
    "sg:tags":[
        "excavating",
        "contractor"
    ],
    "wof:name":"Keith Drews Excavating",
    "wof:placetype":"venue"
},
  "geometry": {"coordinates":[-95.77419399999999,46.862638],"type":"Point"}
}