{
  "type": "Feature",
  "properties": {
    "iso:country":"US",
    "sg:address":"2 E Franklin Ave",
    "sg:city":"Minneapolis",
    "sg:classifiers":[
        {
            "category":"Professional",
            "subcategory":"Computer Services",
            "type":"Services"
        }
    ],
    "sg:phone":"+1 612 872 0535",
    "sg:postcode":"55404",
    "sg:province":"MN",
    "sg:tags":[
        "processing",
        "datum",
        "reporting"
    ],
    "wof:name":"Manipudata LLC",
    "wof:placetype":"venue"
},
  "geometry": {"coordinates":[-93.276573,44.962692],"type":"Point"}
}