{
  "type": "Feature",
  "properties": {
    "addr:full":"3805 Dakota St Alexandria MN 56308",
    "addr:housenumber":"3805",
    "addr:postcode":"56308",
    "addr:street":"Dakota St",
    "iso:country":"US",
    "sg:address":"3805 Dakota St",
    "sg:city":"Alexandria",
    "sg:classifiers":[
        {
            "category":"Utilities",
            "subcategory":"Mobile Phone",
            "type":"Services"
        }
    ],
    "sg:phone":"+1 320 762 2000",
    "sg:postcode":"56308",
    "sg:province":"MN",
    "sg:tags":[
        "telephone",
        "cellular"
    ],
    "sg:website":"www.rccwireless.com",
    "wof:name":"Unicel",
    "wof:placetype":"venue"
},
  "geometry": {"coordinates":[-95.392781,45.853913],"type":"Point"}
}