{
  "type": "Feature",
  "properties": {
    "addr:full":"2220 Central Ave NE Minneapolis MN 55418",
    "addr:housenumber":"2220",
    "addr:postcode":"55418",
    "addr:street":"Central Ave Ne",
    "iso:country":"US",
    "sg:address":"2220 Central Ave NE",
    "sg:city":"Minneapolis",
    "sg:classifiers":[
        {
            "category":"Organizations",
            "subcategory":"Non-profit Organization",
            "type":"Services"
        }
    ],
    "sg:phone":"+1 612 789 8030",
    "sg:postcode":"55418",
    "sg:province":"MN",
    "sg:tags":[
        "information",
        "alcoholism",
        "treatment"
    ],
    "wof:name":"3 R's-Nuway Counseling Ctr",
    "wof:placetype":"venue"
},
  "geometry": {"coordinates":[-93.24740300000001,45.010663],"type":"Point"}
}