{
  "type": "Feature",
  "properties": {
    "addr:full":"15920 29th Ave N Minneapolis MN 55447",
    "addr:housenumber":"15920",
    "addr:postcode":"55447",
    "addr:street":"29Th Ave N",
    "iso:country":"US",
    "sg:address":"15920 29th Ave N",
    "sg:city":"Minneapolis",
    "sg:classifiers":[
        {
            "category":"Restaurant",
            "type":"Food & Drink"
        }
    ],
    "sg:phone":"+1 763 559 5756",
    "sg:postcode":"55447",
    "sg:province":"MN",
    "sg:tags":[
        "eating"
    ],
    "wof:name":"Side Walk Cafe",
    "wof:placetype":"venue"
},
  "geometry": {"coordinates":[-93.48310499999999,45.01411],"type":"Point"}
}