{
  "type": "Feature",
  "properties": {
    "addr:full":"212 3rd Ave N Minneapolis MN 55401",
    "addr:housenumber":"212",
    "addr:postcode":"55401",
    "addr:street":"3Rd Ave N",
    "iso:country":"US",
    "sg:address":"212 3rd Ave N",
    "sg:city":"Minneapolis",
    "sg:classifiers":[
        {
            "category":"Professional",
            "subcategory":"Management & Consulting",
            "type":"Services"
        }
    ],
    "sg:phone":"+1 612 677 0640",
    "sg:postcode":"55401",
    "sg:province":"MN",
    "sg:tags":[
        "consultant",
        "business"
    ],
    "wof:name":"Evantage Consulting",
    "wof:placetype":"venue"
},
  "geometry": {"coordinates":[-93.27223600000001,44.984904],"type":"Point"}
}