{
  "type": "Feature",
  "properties": {
    "iso:country":"US",
    "sg:address":"10032 Pleasant Ave S",
    "sg:city":"Minneapolis",
    "sg:classifiers":[
        {
            "category":"Professional",
            "type":"Services"
        }
    ],
    "sg:phone":"+1 952 881 6805",
    "sg:postcode":"55420",
    "sg:province":"MN",
    "wof:name":"Jon A Wacker",
    "wof:placetype":"venue"
},
  "geometry": {"coordinates":[-93.283649,44.819662],"type":"Point"}
}