{
  "type": "Feature",
  "properties": {
    "iso:country":"US",
    "sg:address":"301 N 3rd St",
    "sg:city":"Marshall",
    "sg:classifiers":[
        {
            "category":"Health Services",
            "subcategory":"Doctor",
            "type":"Services"
        }
    ],
    "sg:phone":"+1 507 537 4176",
    "sg:postcode":"56258",
    "sg:province":"MN",
    "sg:tags":[
        "dentist"
    ],
    "sg:website":"www.oralfacialsurgerypa.com",
    "wof:name":"Oral-Facial Surgery",
    "wof:placetype":"venue"
},
  "geometry": {"coordinates":[-95.78734900000001,44.449519],"type":"Point"}
}