{
  "type": "Feature",
  "properties": {
    "addr:full":"702 School St Ellendale MN 56026",
    "addr:housenumber":"702",
    "addr:postcode":"56026",
    "addr:street":"School St",
    "iso:country":"US",
    "sg:address":"702 School St",
    "sg:city":"Ellendale",
    "sg:classifiers":[
        {
            "category":"Retail",
            "subcategory":"Auto Repair",
            "type":"Services"
        }
    ],
    "sg:phone":"+1 507 684 9617",
    "sg:postcode":"56026",
    "sg:province":"MN",
    "sg:tags":[
        "body",
        "automobile",
        "painting"
    ],
    "wof:name":"Al's Body Shop",
    "wof:placetype":"venue"
},
  "geometry": {"coordinates":[-93.297025,43.871335],"type":"Point"}
}