{
  "type": "Feature",
  "properties": {
    "addr:full":"1901 4th Ave Newport MN 55055",
    "addr:housenumber":"1901",
    "addr:postcode":"55055",
    "addr:street":"4Th Ave",
    "iso:country":"US",
    "sg:address":"1901 4th Ave",
    "sg:city":"Newport",
    "sg:classifiers":[
        {
            "category":"Retail",
            "subcategory":"Auto Repair",
            "type":"Services"
        }
    ],
    "sg:phone":"+1 651 459 0581",
    "sg:postcode":"55055",
    "sg:province":"MN",
    "sg:tags":[
        "body",
        "automobile",
        "painting"
    ],
    "wof:name":"Newport Collision Ctr",
    "wof:placetype":"venue"
},
  "geometry": {"coordinates":[-93.004497,44.879963],"type":"Point"}
}