{
  "type": "Feature",
  "properties": {
    "iso:country":"US",
    "sg:address":"424 James St",
    "sg:city":"Brainerd",
    "sg:classifiers":[
        {
            "category":"Personal",
            "subcategory":"Tanning Parlor",
            "type":"Services"
        }
    ],
    "sg:phone":"+1 218 828 9996",
    "sg:postcode":"56401",
    "sg:province":"MN",
    "sg:tags":[
        "salon"
    ],
    "wof:name":"Endless Summer",
    "wof:placetype":"venue"
},
  "geometry": {"coordinates":[-94.21717599999999,46.358467],"type":"Point"}
}