{
  "type": "Feature",
  "properties": {
    "addr:full":"11356 215th St W Lakeville MN 55044",
    "addr:housenumber":"11356",
    "addr:postcode":"55044",
    "addr:street":"215Th St W",
    "iso:country":"US",
    "sg:address":"11356 215th St W",
    "sg:city":"Lakeville",
    "sg:classifiers":[
        {
            "category":"Wholesale",
            "subcategory":"Construction Materials",
            "type":"Manufacturing & Wholesale Goods"
        }
    ],
    "sg:phone":"+1 952 469 3466",
    "sg:postcode":"55044",
    "sg:province":"MN",
    "sg:tags":[
        "hardware",
        "builder"
    ],
    "wof:name":"Bernco Inc",
    "wof:placetype":"venue"
},
  "geometry": {"coordinates":[-93.29445699999999,44.637856],"type":"Point"}
}