{
  "type": "Feature",
  "properties": {
    "addr:full":"213 1st Ave SE Little Falls MN 56345",
    "addr:housenumber":"213",
    "addr:postcode":"56345",
    "addr:street":"1St Ave Se",
    "iso:country":"US",
    "sg:address":"213 1st Ave SE",
    "sg:city":"Little Falls",
    "sg:classifiers":[
        {
            "category":"Government",
            "subcategory":"Jail",
            "type":"Public Place"
        }
    ],
    "sg:phone":"+1 320 632 0304",
    "sg:postcode":"56345",
    "sg:province":"MN",
    "sg:tags":[
        "county",
        "govt",
        "correctional",
        "institution"
    ],
    "wof:name":"Community Corrections",
    "wof:placetype":"venue"
},
  "geometry": {"coordinates":[-94.36112199999999,45.975172],"type":"Point"}
}