{
  "type": "Feature",
  "properties": {
    "addr:full":"307 Dakota St Red Wing MN 55066",
    "addr:housenumber":"307",
    "addr:postcode":"55066",
    "addr:street":"Dakota St",
    "iso:country":"US",
    "sg:address":"307 Dakota St",
    "sg:city":"Red Wing",
    "sg:classifiers":[
        {
            "category":"Insurance",
            "subcategory":"Insurance Agent",
            "type":"Services"
        }
    ],
    "sg:phone":"+1 651 388 9594",
    "sg:postcode":"55066",
    "sg:province":"MN",
    "sg:website":"www.discoveryfinancial.com",
    "wof:name":"Discovery Financial Ctr",
    "wof:placetype":"venue"
},
  "geometry": {"coordinates":[-92.53720300000001,44.563499],"type":"Point"}
}