{
  "type": "Feature",
  "properties": {
    "iso:country":"US",
    "sg:address":"501 11th St NE",
    "sg:city":"Austin",
    "sg:classifiers":[
        {
            "category":"Autos & Motor Vehicles",
            "subcategory":"Automobile Sales",
            "type":"Retail Goods"
        },
        {
            "category":"Autos & Motor Vehicles",
            "subcategory":"Auto Supplies",
            "type":"Retail Goods"
        }
    ],
    "sg:phone":"+1 507 236 7092",
    "sg:postcode":"55912",
    "sg:province":"MN",
    "sg:tags":[
        "trucks-industrial",
        "washing",
        "truck",
        "cleaning"
    ],
    "sg:website":"http://www.grtruckwash.com",
    "wof:name":"G & R Truck Wash",
    "wof:placetype":"venue"
},
  "geometry": {"coordinates":[-92.958687,43.669868],"type":"Point"}
}