{
  "type": "Feature",
  "properties": {
    "addr:full":"7516 Bayside Dr Crane Lake MN 55725",
    "addr:housenumber":"7516",
    "addr:postcode":"55725",
    "addr:street":"Bayside Dr Crane",
    "iso:country":"US",
    "sg:address":"7516 Bayside Dr",
    "sg:city":"Crane Lake",
    "sg:classifiers":[
        {
            "category":"Travel",
            "subcategory":"Campground",
            "type":"Entertainment"
        }
    ],
    "sg:phone":"+1 218 993 2389",
    "sg:postcode":"55725",
    "sg:province":"MN",
    "sg:tags":[
        "trailer"
    ],
    "wof:name":"Beddow's Campground",
    "wof:placetype":"venue"
},
  "geometry": {"coordinates":[-92.485142,48.264821],"type":"Point"}
}