{
  "type": "Feature",
  "properties": {
    "addr:full":"823 Spruce Pl Saint Peter MN 56082",
    "addr:housenumber":"823",
    "addr:postcode":"56082",
    "addr:street":"Spruce Pl",
    "iso:country":"US",
    "sg:address":"823 Spruce Pl",
    "sg:city":"Saint Peter",
    "sg:classifiers":[
        {
            "category":"Real Estate",
            "subcategory":"Real Estate Agent",
            "type":"Services"
        }
    ],
    "sg:phone":"+1 507 934 2700",
    "sg:postcode":"56082",
    "sg:province":"MN",
    "wof:name":"Gerald Juell",
    "wof:placetype":"venue"
},
  "geometry": {"coordinates":[-93.976102,44.313137],"type":"Point"}
}