{
  "type": "Feature",
  "properties": {
    "addr:full":"4410 Shoreline Dr Spring Park MN 55384",
    "addr:housenumber":"4410",
    "addr:postcode":"55384",
    "addr:street":"Shoreline Dr Spring Park",
    "iso:country":"US",
    "sg:address":"4410 Shoreline Dr",
    "sg:city":"Spring Park",
    "sg:classifiers":[
        {
            "category":"Building & Trades",
            "subcategory":"Construction",
            "type":"Services"
        }
    ],
    "sg:phone":"+1 952 471 0532",
    "sg:postcode":"55384",
    "sg:province":"MN",
    "sg:tags":[
        "home",
        "builder"
    ],
    "wof:name":"Danberry Co",
    "wof:placetype":"venue"
},
  "geometry": {"coordinates":[-93.635239,44.935364],"type":"Point"}
}