{
  "type": "Feature",
  "properties": {
    "iso:country":"US",
    "sg:address":"1911 25th St",
    "sg:city":"Slayton",
    "sg:classifiers":[
        {
            "category":"Building & Trades",
            "subcategory":"Construction",
            "type":"Services"
        }
    ],
    "sg:phone":"+1 507 836 8079",
    "sg:postcode":"56172",
    "sg:province":"MN",
    "sg:tags":[
        "house"
    ],
    "wof:name":"Dan Conway Construction",
    "wof:placetype":"venue"
},
  "geometry": {"coordinates":[-95.76430999999999,43.989194],"type":"Point"}
}