{
  "type": "Feature",
  "properties": {
    "iso:country":"US",
    "sg:address":"71273 225th St",
    "sg:city":"Dexter",
    "sg:phone":"+1 507 754 5412",
    "sg:postcode":"55926",
    "sg:province":"MN",
    "sg:tags":[
        "farm",
        "corn",
        "soybean"
    ],
    "wof:name":"Baldus Farms of Dexter",
    "wof:placetype":"venue"
},
  "geometry": {"coordinates":[-92.628621,43.681102],"type":"Point"}
}