{
  "type": "Feature",
  "properties": {
    "iso:country":"US",
    "sg:address":"13835 Johnson St NE",
    "sg:city":"Anoka",
    "sg:classifiers":[
        {
            "category":"Freight",
            "type":"Transportation"
        }
    ],
    "sg:phone":"+1 763 413 2521",
    "sg:postcode":"55304",
    "sg:province":"MN",
    "sg:tags":[
        "mobile",
        "home",
        "transporting"
    ],
    "wof:name":"Reggies Mobile Home Transport",
    "wof:placetype":"venue"
},
  "geometry": {"coordinates":[-93.236802,45.22218],"type":"Point"}
}