{
  "type": "Feature",
  "properties": {
    "addr:full":"15025 Glazier Ave St Paul MN 55124",
    "addr:postcode":"15025;55124",
    "addr:street":"Glazier Ave",
    "iso:country":"US",
    "sg:address":"15025 Glazier Ave",
    "sg:city":"St Paul",
    "sg:classifiers":[
        {
            "category":"Insurance",
            "subcategory":"Insurance Agent",
            "type":"Services"
        }
    ],
    "sg:phone":"+1 952 432 5900",
    "sg:postcode":"55124",
    "sg:province":"MN",
    "wof:name":"Mayer Insurance",
    "wof:placetype":"venue"
},
  "geometry": {"coordinates":[-93.216425,44.734115],"type":"Point"}
}