{
  "type": "Feature",
  "properties": {
    "iso:country":"US",
    "sg:address":"415 6th Ave NE",
    "sg:city":"Pine City",
    "sg:classifiers":[
        {
            "category":"Personal",
            "subcategory":"Beauty Salon",
            "type":"Services"
        }
    ],
    "sg:phone":"+1 320 629 6364",
    "sg:postcode":"55063",
    "sg:province":"MN",
    "sg:tags":[
        "shop"
    ],
    "wof:name":"Kathys Beauty Salon",
    "wof:placetype":"venue"
},
  "geometry": {"coordinates":[-92.96048399999999,45.836655],"type":"Point"}
}