{
  "type": "Feature",
  "properties": {
    "iso:country":"US",
    "sg:address":"123 Industrial Loop",
    "sg:city":"Paynesville",
    "sg:classifiers":[
        {
            "category":"Wholesale",
            "subcategory":"Machinery & Supplies",
            "type":"Manufacturing & Wholesale Goods"
        }
    ],
    "sg:phone":"+1 320 243 5200",
    "sg:postcode":"56362",
    "sg:province":"MN",
    "sg:tags":[
        "valve"
    ],
    "wof:name":"OPD Valves",
    "wof:placetype":"venue"
},
  "geometry": {"coordinates":[-94.70342599999999,45.387155],"type":"Point"}
}