{
  "type": "Feature",
  "properties": {
    "iso:country":"US",
    "sg:address":"15 E Main St",
    "sg:city":"Crosby",
    "sg:classifiers":[
        {
            "category":"Real Estate",
            "subcategory":"Real Estate Agent",
            "type":"Services"
        }
    ],
    "sg:phone":"+1 218 545 2112",
    "sg:postcode":"56441",
    "sg:province":"MN",
    "wof:name":"Cornerstone Pro Realty Svc",
    "wof:placetype":"venue"
},
  "geometry": {"coordinates":[-93.952116,46.482495],"type":"Point"}
}