{
  "type": "Feature",
  "properties": {
    "addr:full":"3298 Donald Ave Saint Paul MN 55121",
    "addr:housenumber":"3298",
    "addr:postcode":"55121",
    "addr:street":"Donald Ave",
    "iso:country":"US",
    "sg:address":"3298 Donald Ave",
    "sg:city":"Saint Paul",
    "sg:classifiers":[
        {
            "category":"Museum",
            "subcategory":"Botanical Garden",
            "type":"Entertainment"
        }
    ],
    "sg:phone":"+1 651 208 1466",
    "sg:postcode":"55121",
    "sg:province":"MN",
    "wof:name":"Aqualux",
    "wof:placetype":"venue"
},
  "geometry": {"coordinates":[-93.18493700000001,44.838443],"type":"Point"}
}