{
  "type": "Feature",
  "properties": {
    "iso:country":"US",
    "sg:address":"155 Gleason Lake Dr",
    "sg:city":"Wayzata",
    "sg:classifiers":[
        {
            "category":"Real Estate",
            "subcategory":"Real Estate Agent",
            "type":"Services"
        },
        {
            "category":"Real Estate",
            "subcategory":"Real Estate Operator",
            "type":"Services"
        }
    ],
    "sg:phone":"+1 952 473 6646",
    "sg:postcode":"55391",
    "sg:province":"MN",
    "sg:tags":[
        "apartment"
    ],
    "wof:name":"Gleason Lake Apartments",
    "wof:placetype":"venue"
},
  "geometry": {"coordinates":[-93.489137,44.973381],"type":"Point"}
}