{
  "type": "Feature",
  "properties": {
    "iso:country":"US",
    "sg:address":"9795 Greenfield Rd",
    "sg:city":"Loretto",
    "sg:classifiers":[
        {
            "category":"Farming",
            "subcategory":"Dairy Farm",
            "type":"Manufacturing & Wholesale Goods"
        }
    ],
    "sg:phone":"+1 763 498 8528",
    "sg:postcode":"55357",
    "sg:province":"MN",
    "wof:name":"Duane Beise",
    "wof:placetype":"venue"
},
  "geometry": {"coordinates":[-93.686836,45.123225],"type":"Point"}
}