{
  "type": "Feature",
  "properties": {
    "iso:country":"US",
    "sg:address":"4916 W 96th St",
    "sg:city":"Bloomington",
    "sg:classifiers":[
        {
            "category":"Professional",
            "type":"Services"
        }
    ],
    "sg:phone":"+1 952 832 9550",
    "sg:postcode":"55437",
    "sg:province":"MN",
    "sg:tags":[
        "establishment"
    ],
    "wof:name":"NVP Co",
    "wof:placetype":"venue"
},
  "geometry": {"coordinates":[-93.343063,44.829042],"type":"Point"}
}