{
  "type": "Feature",
  "properties": {
    "addr:full":"4940 US Hwy 61 Saint Paul MN 55110",
    "addr:housenumber":"4940",
    "addr:postcode":"55110",
    "addr:street":"Us Hwy 61",
    "iso:country":"US",
    "sg:address":"4940 US Hwy 61",
    "sg:city":"Saint Paul",
    "sg:classifiers":[
        {
            "category":"Restaurant",
            "type":"Food & Drink"
        },
        {
            "category":"Travel",
            "subcategory":"Hotels & Motels",
            "type":"Entertainment"
        }
    ],
    "sg:phone":"+1 651 429 5393",
    "sg:postcode":"55110",
    "sg:province":"MN",
    "sg:tags":[
        "drinking",
        "eating",
        "operation"
    ],
    "wof:name":"Best Western Inn",
    "wof:placetype":"venue"
},
  "geometry": {"coordinates":[-93.00725799999999,45.089857],"type":"Point"}
}