{
  "type": "Feature",
  "properties": {
    "iso:country":"US",
    "sg:address":"13999 Alabama Ave S",
    "sg:city":"Savage",
    "sg:classifiers":[
        {
            "category":"Building & Trades",
            "subcategory":"Locksmith",
            "type":"Services"
        }
    ],
    "sg:phone":"+1 612 216 0120",
    "sg:postcode":"55378",
    "sg:province":"MN",
    "sg:tags":[
        "key"
    ],
    "wof:name":"A & 1 Locksmith 24 Hour",
    "wof:placetype":"venue"
},
  "geometry": {"coordinates":[-93.355457,44.750668],"type":"Point"}
}