{
  "type": "Feature",
  "properties": {
    "addr:full":"36 17th Ave NW Rochester MN 55901",
    "addr:housenumber":"36",
    "addr:postcode":"55901",
    "addr:street":"17Th Ave Nw",
    "iso:country":"US",
    "sg:address":"36 17th Ave NW",
    "sg:city":"Rochester",
    "sg:classifiers":[
        {
            "category":"Wholesale",
            "subcategory":"Medical Equipment & Supplies",
            "type":"Manufacturing & Wholesale Goods"
        },
        {
            "category":"Shopping",
            "subcategory":"Pharmacy",
            "type":"Retail Goods"
        }
    ],
    "sg:phone":"+1 507 218 0246",
    "sg:postcode":"55901",
    "sg:province":"MN",
    "sg:tags":[
        "home",
        "wheelchair",
        "health",
        "care"
    ],
    "sg:website":"http://www.cornermedical.com",
    "wof:name":"Corner Medical",
    "wof:placetype":"venue"
},
  "geometry": {"coordinates":[-92.487567,44.02377],"type":"Point"}
}