{
  "type": "Feature",
  "properties": {
    "addr:full":"845 38th St NW Rochester MN 55901",
    "addr:housenumber":"845",
    "addr:postcode":"55901",
    "addr:street":"38Th St Nw",
    "iso:country":"US",
    "sg:address":"845 38th St NW",
    "sg:city":"Rochester",
    "sg:classifiers":[
        {
            "category":"Home & Garden",
            "subcategory":"Building Materials",
            "type":"Retail Goods"
        }
    ],
    "sg:phone":"+1 507 252 1000",
    "sg:postcode":"55901",
    "sg:province":"MN",
    "wof:name":"Novus Auto Glass Repair",
    "wof:placetype":"venue"
},
  "geometry": {"coordinates":[-92.47469,44.062362],"type":"Point"}
}