{
  "type": "Feature",
  "properties": {
    "iso:country":"US",
    "sg:address":"1139 5th Ave N",
    "sg:city":"Sauk Rapids",
    "sg:classifiers":[
        {
            "category":"Health Services",
            "subcategory":"Doctor",
            "type":"Services"
        }
    ],
    "sg:phone":"+1 320 253 4242",
    "sg:postcode":"56379",
    "sg:province":"MN",
    "sg:tags":[
        "dentist"
    ],
    "wof:name":"Scott R Wilcox DDS",
    "wof:placetype":"venue"
},
  "geometry": {"coordinates":[-94.171888,45.603478],"type":"Point"}
}