{
  "type": "Feature",
  "properties": {
    "addr:full":"12270 Nicollet Ave Burnsville MN 55337",
    "addr:housenumber":"12270",
    "addr:postcode":"55337",
    "addr:street":"Nicollet Ave",
    "iso:country":"US",
    "sg:address":"12270 Nicollet Ave",
    "sg:city":"Burnsville",
    "sg:classifiers":[
        {
            "category":"Banks & Credit Unions",
            "subcategory":"Investment Brokerage",
            "type":"Services"
        }
    ],
    "sg:phone":"+1 952 736 9805",
    "sg:postcode":"55337",
    "sg:province":"MN",
    "sg:tags":[
        "advisory",
        "financial"
    ],
    "wof:name":"Tran Central In",
    "wof:placetype":"venue"
},
  "geometry": {"coordinates":[-93.27880999999999,44.780635],"type":"Point"}
}