{
  "type": "Feature",
  "properties": {
    "addr:full":"8000 Portland Ave S Minneapolis MN 55420",
    "addr:housenumber":"8000",
    "addr:postcode":"55420",
    "addr:street":"Portland Ave S",
    "iso:country":"US",
    "sg:address":"8000 Portland Ave S",
    "sg:city":"Minneapolis",
    "sg:classifiers":[
        {
            "category":"Social Services",
            "subcategory":"Child Care",
            "type":"Services"
        },
        {
            "category":"Education",
            "subcategory":"Preschool",
            "type":"Public Place"
        }
    ],
    "sg:phone":"+1 888 867 0212",
    "sg:postcode":"55420",
    "sg:province":"MN",
    "sg:tags":[
        "kindergarten"
    ],
    "sg:website":"http://www.babycarekids.com/",
    "wof:name":"Baby Care",
    "wof:placetype":"venue"
},
  "geometry": {"coordinates":[-93.26820600000001,44.857813],"type":"Point"}
}