{
  "type": "Feature",
  "properties": {
    "addr:full":"420 N Pokegama Ave Grand Rapids MN 55744",
    "addr:housenumber":"420",
    "addr:postcode":"55744",
    "addr:street":"N Pokegama Ave",
    "iso:country":"US",
    "sg:address":"420 N Pokegama Ave",
    "sg:city":"Grand Rapids",
    "sg:classifiers":[
        {
            "category":"Utilities",
            "subcategory":"Electric",
            "type":"Services"
        }
    ],
    "sg:phone":"+1 218 326 7604",
    "sg:postcode":"55744",
    "sg:province":"MN",
    "sg:tags":[
        "works",
        "public"
    ],
    "wof:name":"Public Utilities",
    "wof:placetype":"venue"
},
  "geometry": {"coordinates":[-93.528215,47.236746],"type":"Point"}
}