{
  "type": "Feature",
  "properties": {
    "iso:country":"US",
    "sg:address":"2327 Hennepin Ave S",
    "sg:city":"Minneapolis",
    "sg:classifiers":[
        {
            "category":"Recreation",
            "type":"Entertainment"
        }
    ],
    "sg:phone":"+1 612 377 6988",
    "sg:postcode":"55405",
    "sg:province":"MN",
    "sg:tags":[
        "instruction",
        "yoga"
    ],
    "wof:name":"Yoga 360",
    "wof:placetype":"venue"
},
  "geometry": {"coordinates":[-93.293823,44.959427],"type":"Point"}
}