{
  "type": "Feature",
  "properties": {
    "addr:full":"221 Drew Ave NE Madelia MN 56062",
    "addr:housenumber":"221",
    "addr:postcode":"56062",
    "addr:street":"Drew Ave Ne Madelia",
    "iso:country":"US",
    "sg:address":"221 Drew Ave NE",
    "sg:city":"Madelia",
    "sg:classifiers":[
        {
            "category":"Education",
            "subcategory":"Special Training",
            "type":"Public Place"
        }
    ],
    "sg:phone":"+1 507 642 8320",
    "sg:postcode":"56062",
    "sg:province":"MN",
    "wof:name":"Jody R Hruby",
    "wof:placetype":"venue"
},
  "geometry": {"coordinates":[-94.409398,44.054061],"type":"Point"}
}