{
  "type": "Feature",
  "properties": {
    "iso:country":"US",
    "sg:address":"36004 276 St",
    "sg:city":"Henderson",
    "sg:classifiers":[
        {
            "category":"Building & Trades",
            "subcategory":"Landscaping Services",
            "type":"Services"
        }
    ],
    "sg:phone":"+1 507 248 3614",
    "sg:postcode":"56044",
    "sg:province":"MN",
    "sg:tags":[
        "landscape",
        "contractor"
    ],
    "wof:name":"Boehne Construction",
    "wof:placetype":"venue"
},
  "geometry": {"coordinates":[-93.9717,44.54692],"type":"Point"}
}