{
  "type": "Feature",
  "properties": {
    "addr:full":"612 2nd Ave N Windom MN 56101",
    "addr:housenumber":"612",
    "addr:postcode":"56101",
    "addr:street":"2Nd Ave N",
    "iso:country":"US",
    "sg:address":"612 2nd Ave N",
    "sg:city":"Windom",
    "sg:classifiers":[
        {
            "category":"Food & Beverages",
            "subcategory":"Groceries & Convenience Stores",
            "type":"Retail Goods"
        }
    ],
    "sg:phone":"+1 507 831 9918",
    "sg:postcode":"56101",
    "sg:province":"MN",
    "wof:name":"Caseys General Store",
    "wof:placetype":"venue"
},
  "geometry": {"coordinates":[-95.11500599999999,43.863021],"type":"Point"}
}