{
  "type": "Feature",
  "properties": {
    "iso:country":"US",
    "sg:address":"920 Toledo Ave N",
    "sg:city":"Minneapolis",
    "sg:classifiers":[
        {
            "category":"Wholesale",
            "subcategory":"Machinery & Supplies",
            "type":"Manufacturing & Wholesale Goods"
        }
    ],
    "sg:phone":"+1 763 588 0223",
    "sg:postcode":"55422",
    "sg:province":"MN",
    "sg:tags":[
        "equipment",
        "industrial"
    ],
    "wof:name":"Affordable Tools",
    "wof:placetype":"venue"
},
  "geometry": {"coordinates":[-93.346271,44.989459],"type":"Point"}
}