{
  "type": "Feature",
  "properties": {
    "addr:full":"1558 Saari Rd Ely MN 55731",
    "addr:housenumber":"1558",
    "addr:postcode":"55731",
    "addr:street":"Saari Rd",
    "iso:country":"US",
    "sg:address":"1558 Saari Rd",
    "sg:city":"Ely",
    "sg:classifiers":[
        {
            "category":"Banks & Credit Unions",
            "subcategory":"Financial Services",
            "type":"Services"
        }
    ],
    "sg:phone":"+1 218 365 5396",
    "sg:postcode":"55731",
    "sg:province":"MN",
    "sg:tags":[
        "trust",
        "management"
    ],
    "wof:name":"White Iron Trust",
    "wof:placetype":"venue"
},
  "geometry": {"coordinates":[-91.81752,47.835255],"type":"Point"}
}