{
  "type": "Feature",
  "properties": {
    "iso:country":"US",
    "sg:address":"4155 Cedar Ave S",
    "sg:city":"Minneapolis",
    "sg:classifiers":[
        {
            "category":"Bars & Pubs",
            "subcategory":"Nightclub",
            "type":"Food & Drink"
        }
    ],
    "sg:phone":"+1 612 729 9785",
    "sg:postcode":"55407",
    "sg:province":"MN",
    "sg:tags":[
        "nightlife"
    ],
    "wof:name":"Cedar Inn",
    "wof:placetype":"venue"
},
  "geometry": {"coordinates":[-93.247101,44.9272],"type":"Point"}
}