{
  "type": "Feature",
  "properties": {
    "addr:full":"5220 Hwy 63 N Rochester MN 55906",
    "addr:housenumber":"5220",
    "addr:postcode":"55906",
    "addr:street":"Hwy 63 N",
    "iso:country":"US",
    "sg:address":"5220 Hwy 63 N",
    "sg:city":"Rochester",
    "sg:classifiers":[
        {
            "category":"Home & Garden",
            "subcategory":"Mobile Homes",
            "type":"Retail Goods"
        }
    ],
    "sg:phone":"+1 507 282 9833",
    "sg:postcode":"55906",
    "sg:province":"MN",
    "wof:name":"Homes Of Harmony",
    "wof:placetype":"venue"
},
  "geometry": {"coordinates":[-92.450124,44.076414],"type":"Point"}
}