{
  "type": "Feature",
  "properties": {
    "addr:full":"9000 10th Ave N Minneapolis MN 55427",
    "addr:housenumber":"9000",
    "addr:postcode":"55427",
    "addr:street":"10Th Ave N",
    "iso:country":"US",
    "sg:address":"9000 10th Ave N",
    "sg:city":"Minneapolis",
    "sg:classifiers":[
        {
            "category":"Airline",
            "type":"Transportation"
        }
    ],
    "sg:phone":"+1 763 546 5300",
    "sg:postcode":"55427",
    "sg:province":"MN",
    "sg:tags":[
        "rental",
        "leasing",
        "aircraft-charter"
    ],
    "wof:name":"Pioneer Private Aviation Inc",
    "wof:placetype":"venue"
},
  "geometry": {"coordinates":[-93.39286800000001,44.989101],"type":"Point"}
}