{
  "type": "Feature",
  "properties": {
    "iso:country":"US",
    "sg:address":"105 N Main St",
    "sg:city":"Mabel",
    "sg:classifiers":[
        {
            "category":"Real Estate",
            "subcategory":"Real Estate Agent",
            "type":"Services"
        }
    ],
    "sg:phone":"+1 507 493 5506",
    "sg:postcode":"55954",
    "sg:province":"MN",
    "wof:name":"Amdahl Realty",
    "wof:placetype":"venue"
},
  "geometry": {"coordinates":[-91.769884,43.521517],"type":"Point"}
}