{
  "type": "Feature",
  "properties": {
    "iso:country":"US",
    "sg:address":"19246 140th St",
    "sg:city":"Park Rapids",
    "sg:classifiers":[
        {
            "category":"Farming",
            "subcategory":"Farm",
            "type":"Manufacturing & Wholesale Goods"
        }
    ],
    "sg:phone":"+1 218 732 7170",
    "sg:postcode":"56470",
    "sg:province":"MN",
    "sg:tags":[
        "crop",
        "general"
    ],
    "wof:name":"Kyle Woodrum Farm",
    "wof:placetype":"venue"
},
  "geometry": {"coordinates":[-94.954142,46.864095],"type":"Point"}
}