{
  "type": "Feature",
  "properties": {
    "iso:country":"US",
    "sg:address":"11878 Lake Ln",
    "sg:city":"Lindstrom",
    "sg:classifiers":[
        {
            "category":"Real Estate",
            "subcategory":"Real Estate Services",
            "type":"Services"
        },
        {
            "category":"Real Estate",
            "subcategory":"Real Estate Agent",
            "type":"Services"
        }
    ],
    "sg:phone":"+1 651 257 4455",
    "sg:postcode":"55045",
    "sg:province":"MN",
    "sg:tags":[
        "buyer",
        "management",
        "broker"
    ],
    "wof:name":"Smothers Group Realty",
    "wof:placetype":"venue"
},
  "geometry": {"coordinates":[-92.86578299999999,45.38998],"type":"Point"}
}