{
  "type": "Feature",
  "properties": {
    "addr:full":"507 S Shore Dr Worthington MN 56187",
    "addr:housenumber":"507",
    "addr:postcode":"56187",
    "addr:street":"S Shore Dr",
    "iso:country":"US",
    "sg:address":"507 S Shore Dr",
    "sg:city":"Worthington",
    "sg:classifiers":[
        {
            "category":"Health Services",
            "subcategory":"Doctor",
            "type":"Services"
        }
    ],
    "sg:phone":"+1 507 372 2072",
    "sg:postcode":"56187",
    "sg:province":"MN",
    "sg:tags":[
        "dentist"
    ],
    "wof:name":"Lakeshore Dental DDS",
    "wof:placetype":"venue"
},
  "geometry": {"coordinates":[-95.59966900000001,43.615621],"type":"Point"}
}