{
  "type": "Feature",
  "properties": {
    "addr:full":"1532 University Ave W Saint Paul MN 55104",
    "addr:housenumber":"1532",
    "addr:postcode":"55104",
    "addr:street":"University Ave W",
    "iso:country":"US",
    "sg:address":"1532 University Ave W",
    "sg:city":"Saint Paul",
    "sg:classifiers":[
        {
            "category":"Professional",
            "subcategory":"Lawyer & Legal Services",
            "type":"Services"
        },
        {
            "category":"Building & Trades",
            "subcategory":"Locksmith",
            "type":"Services"
        }
    ],
    "sg:phone":"+1 651 644 2176",
    "sg:postcode":"55104",
    "sg:province":"MN",
    "sg:tags":[
        "notary",
        "key"
    ],
    "wof:name":"Apollo Locksmith Inc",
    "wof:placetype":"venue"
},
  "geometry": {"coordinates":[-93.165199,44.955601],"type":"Point"}
}