{
  "type": "Feature",
  "properties": {
    "addr:full":"2059 120th Ave Russell MN 56169",
    "addr:housenumber":"2059",
    "addr:postcode":"56169",
    "addr:street":"120Th Ave",
    "iso:country":"US",
    "sg:address":"2059 120th Ave",
    "sg:city":"Russell",
    "sg:phone":"+1 507 823 4233",
    "sg:postcode":"56169",
    "sg:province":"MN",
    "sg:tags":[
        "farm",
        "corn",
        "soybean"
    ],
    "wof:name":"Steven Williams",
    "wof:placetype":"venue"
},
  "geometry": {"coordinates":[-96.05922099999999,44.353214],"type":"Point"}
}