{
  "type": "Feature",
  "properties": {
    "addr:full":"12885 Leroy Ave Waterville MN 56096",
    "addr:housenumber":"12885",
    "addr:postcode":"56096",
    "addr:street":"Leroy Ave",
    "iso:country":"US",
    "sg:address":"12885 Leroy Ave",
    "sg:city":"Waterville",
    "sg:classifiers":[
        {
            "category":"Travel",
            "subcategory":"Hotels & Motels",
            "type":"Entertainment"
        }
    ],
    "sg:phone":"+1 507 362 4602",
    "sg:postcode":"56096",
    "sg:province":"MN",
    "sg:tags":[
        "resort"
    ],
    "wof:name":"Knotty Pine Resort",
    "wof:placetype":"venue"
},
  "geometry": {"coordinates":[-93.51859399999999,44.233468],"type":"Point"}
}