{
  "type": "Feature",
  "properties": {
    "iso:country":"US",
    "sg:address":"3205 W 76th St",
    "sg:city":"Minneapolis",
    "sg:classifiers":[
        {
            "category":"Shopping",
            "type":"Retail Goods"
        }
    ],
    "sg:phone":"+1 612 802 0033",
    "sg:postcode":"55435",
    "sg:province":"MN",
    "sg:tags":[
        "merchandise"
    ],
    "wof:name":"Avirat Inc",
    "wof:placetype":"venue"
},
  "geometry": {"coordinates":[-93.321209,44.865442],"type":"Point"}
}