{
  "type": "Feature",
  "properties": {
    "addr:full":"1101 E 78th St Bloomington MN 55420",
    "addr:housenumber":"1101",
    "addr:postcode":"55420",
    "addr:street":"E 78Th St",
    "iso:country":"US",
    "sg:address":"1101 E 78th St",
    "sg:city":"Bloomington",
    "sg:classifiers":[
        {
            "category":"Education",
            "subcategory":"Junior College",
            "type":"Public Place"
        }
    ],
    "sg:phone":"+1 952 851 0066",
    "sg:postcode":"55420",
    "sg:province":"MN",
    "sg:tags":[
        "technical",
        "institute"
    ],
    "sg:website":"www.academycollege.edu",
    "wof:name":"Academy College",
    "wof:placetype":"venue"
},
  "geometry": {"coordinates":[-93.260705,44.861731],"type":"Point"}
}