{
  "type": "Feature",
  "properties": {
    "iso:country":"US",
    "sg:address":"357 13th Ave NE",
    "sg:city":"Minneapolis",
    "sg:classifiers":[
        {
            "category":"Professional",
            "type":"Services"
        }
    ],
    "sg:phone":"+1 612 379 4403",
    "sg:postcode":"55413",
    "sg:province":"MN",
    "wof:name":"Langworks",
    "wof:placetype":"venue"
},
  "geometry": {"coordinates":[-93.261976,45.000823],"type":"Point"}
}