{
  "type": "Feature",
  "properties": {
    "iso:country":"US",
    "sg:address":"201 Lake Ave",
    "sg:city":"Fairmont",
    "sg:classifiers":[
        {
            "category":"Social Services",
            "type":"Services"
        }
    ],
    "sg:phone":"+1 507 238 3209",
    "sg:postcode":"56031",
    "sg:province":"MN",
    "wof:name":"Victim/Witness Coordinator",
    "wof:placetype":"venue"
},
  "geometry": {"coordinates":[-94.46587599999999,43.654576],"type":"Point"}
}