{
  "type": "Feature",
  "properties": {
    "addr:full":"22811 Rum River Blvd NW Saint Francis MN 55070",
    "addr:postcode":"22811;55070",
    "addr:street":"River Blvd Nw Saint Francis",
    "iso:country":"US",
    "sg:address":"22811 Rum River Blvd NW",
    "sg:city":"Saint Francis",
    "sg:classifiers":[
        {
            "category":"Banks & Credit Unions",
            "subcategory":"Bank",
            "type":"Services"
        }
    ],
    "sg:phone":"+1 763 753 3640",
    "sg:postcode":"55070",
    "sg:province":"MN",
    "sg:tags":[
        "mortgage"
    ],
    "wof:name":"Sisters Cntract Mrtg Solutions",
    "wof:placetype":"venue"
},
  "geometry": {"coordinates":[-93.360747,45.384378],"type":"Point"}
}