{
  "type": "Feature",
  "properties": {
    "addr:full":"2004 8th Ave N Moorhead MN 56560",
    "addr:housenumber":"2004",
    "addr:postcode":"56560",
    "addr:street":"8Th Ave N",
    "iso:country":"US",
    "sg:address":"2004 8th Ave N",
    "sg:city":"Moorhead",
    "sg:classifiers":[
        {
            "category":"Social Services",
            "subcategory":"Adult Care",
            "type":"Services"
        }
    ],
    "sg:phone":"+1 218 233 1583",
    "sg:postcode":"56560",
    "sg:province":"MN",
    "sg:tags":[
        "residential"
    ],
    "wof:name":"Northside Retirement Home",
    "wof:placetype":"venue"
},
  "geometry": {"coordinates":[-96.74938,46.883506],"type":"Point"}
}