{
  "type": "Feature",
  "properties": {
    "addr:full":"11599 Hillside Rd Brownsville MN 55919",
    "addr:housenumber":"11599",
    "addr:postcode":"55919",
    "addr:street":"Hillside Rd",
    "iso:country":"US",
    "sg:address":"11599 Hillside Rd",
    "sg:city":"Brownsville",
    "sg:phone":"+1 507 482 6873",
    "sg:postcode":"55919",
    "sg:province":"MN",
    "sg:tags":[
        "farm",
        "field",
        "crop"
    ],
    "wof:name":"Dan Hurley",
    "wof:placetype":"venue"
},
  "geometry": {"coordinates":[-91.29392199999999,43.680671],"type":"Point"}
}