{
  "type": "Feature",
  "properties": {
    "iso:country":"US",
    "sg:address":"27596 325th Ave",
    "sg:city":"Paynesville",
    "sg:phone":"+1 320 987 3419",
    "sg:postcode":"56362",
    "sg:province":"MN",
    "sg:tags":[
        "farm",
        "real",
        "corn",
        "property",
        "lessor"
    ],
    "wof:name":"Ervin Winter",
    "wof:placetype":"venue"
},
  "geometry": {"coordinates":[-94.788026,45.528143],"type":"Point"}
}