{
  "type": "Feature",
  "properties": {
    "addr:full":"467 Maryland Ave W St Paul MN 55117",
    "addr:housenumber":"467",
    "addr:postcode":"55117",
    "addr:street":"Maryland Ave W",
    "iso:country":"US",
    "sg:address":"467 Maryland Ave W",
    "sg:city":"St Paul",
    "sg:classifiers":[
        {
            "category":"Professional",
            "type":"Services"
        }
    ],
    "sg:phone":"+1 651 489 2509",
    "sg:postcode":"55117",
    "sg:province":"MN",
    "sg:tags":[
        "establishment"
    ],
    "wof:name":"Emmanulle Oguneka",
    "wof:placetype":"venue"
},
  "geometry": {"coordinates":[-93.119388,44.977446],"type":"Point"}
}