{
  "type": "Feature",
  "properties": {
    "addr:full":"106 Washington Ave NE Fertile MN 56540",
    "addr:housenumber":"106",
    "addr:postcode":"56540",
    "addr:street":"Washington Ave Ne",
    "iso:country":"US",
    "sg:address":"106 Washington Ave NE",
    "sg:city":"Fertile",
    "sg:classifiers":[
        {
            "category":"Food & Beverages",
            "subcategory":"Meat & Fish",
            "type":"Retail Goods"
        }
    ],
    "sg:phone":"+1 218 945 6132",
    "sg:postcode":"56540",
    "sg:province":"MN",
    "wof:name":"Al-Lauras Meats",
    "wof:placetype":"venue"
},
  "geometry": {"coordinates":[-96.280423,47.536074],"type":"Point"}
}