{
  "type": "Feature",
  "properties": {
    "iso:country":"US",
    "sg:address":"17592 100th Ave",
    "sg:city":"Little Falls",
    "sg:phone":"+1 320 632 3407",
    "sg:postcode":"56345",
    "sg:province":"MN",
    "sg:tags":[
        "farm",
        "field",
        "corn",
        "crop"
    ],
    "wof:name":"Marlin Knopik",
    "wof:placetype":"venue"
},
  "geometry": {"coordinates":[-94.451452,46.006163],"type":"Point"}
}