{
  "type": "Feature",
  "properties": {
    "iso:country":"US",
    "sg:address":"3621 Lancaster Ln N",
    "sg:city":"Minneapolis",
    "sg:classifiers":[
        {
            "category":"Professional",
            "subcategory":"Computer Services",
            "type":"Services"
        }
    ],
    "sg:phone":"+1 763 540 0410",
    "sg:postcode":"55441",
    "sg:province":"MN",
    "sg:tags":[
        "hardware",
        "support",
        "software"
    ],
    "wof:name":"Thomas Knutson Computer Engrg",
    "wof:placetype":"venue"
},
  "geometry": {"coordinates":[-93.402418,45.024757],"type":"Point"}
}