{
  "type": "Feature",
  "properties": {
    "addr:full":"5842 Blackshire Path Inver Grove Hts MN 55076",
    "addr:housenumber":"5842",
    "addr:postcode":"55076",
    "addr:street":"Blackshire Path",
    "iso:country":"US",
    "sg:address":"5842 Blackshire Path",
    "sg:city":"Inver Grove Hts",
    "sg:classifiers":[
        {
            "category":"Education",
            "subcategory":"School",
            "type":"Public Place"
        },
        {
            "category":"Education",
            "subcategory":"Special Training",
            "type":"Public Place"
        }
    ],
    "sg:phone":"+1 651 552 8145",
    "sg:postcode":"55076",
    "sg:province":"MN",
    "sg:tags":[
        "instruction",
        "driving"
    ],
    "wof:name":"One-Way Driving School",
    "wof:placetype":"venue"
},
  "geometry": {"coordinates":[-93.054073,44.864112],"type":"Point"}
}