{
  "type": "Feature",
  "properties": {
    "addr:full":"1581 Selby Ave Saint Paul MN 55104",
    "addr:housenumber":"1581",
    "addr:postcode":"55104",
    "addr:street":"Selby Ave",
    "iso:country":"US",
    "sg:address":"1581 Selby Ave",
    "sg:city":"Saint Paul",
    "sg:classifiers":[
        {
            "category":"Shopping",
            "type":"Retail Goods"
        }
    ],
    "sg:phone":"+1 651 644 5444",
    "sg:postcode":"55104",
    "sg:province":"MN",
    "wof:name":"Patina",
    "wof:placetype":"venue"
},
  "geometry": {"coordinates":[-93.167406,44.946789],"type":"Point"}
}