{
  "type": "Feature",
  "properties": {
    "iso:country":"US",
    "sg:address":"103 4th St NE",
    "sg:city":"Grand Meadow",
    "sg:classifiers":[
        {
            "category":"Real Estate",
            "subcategory":"Real Estate Operator",
            "type":"Services"
        }
    ],
    "sg:phone":"+1 507 754 6116",
    "sg:postcode":"55936",
    "sg:province":"MN",
    "sg:tags":[
        "building",
        "nonresidential"
    ],
    "wof:name":"Lake 14 Properties Inc",
    "wof:placetype":"venue"
},
  "geometry": {"coordinates":[-92.56659399999999,43.709535],"type":"Point"}
}