{
  "type": "Feature",
  "properties": {
    "iso:country":"US",
    "sg:address":"132 8th Ave",
    "sg:city":"Granite Falls",
    "sg:classifiers":[
        {
            "category":"Professional",
            "subcategory":"Lawyer & Legal Services",
            "type":"Services"
        }
    ],
    "sg:phone":"+1 320 564 2340",
    "sg:postcode":"56241",
    "sg:province":"MN",
    "sg:tags":[
        "attorney"
    ],
    "wof:name":"Kramer Law Office",
    "wof:placetype":"venue"
},
  "geometry": {"coordinates":[-95.539676,44.810447],"type":"Point"}
}