{
  "type": "Feature",
  "properties": {
    "addr:full":"215 N 40th Ave W Duluth MN 55807",
    "addr:housenumber":"215",
    "addr:postcode":"55807",
    "addr:street":"N 40Th Ave W",
    "iso:country":"US",
    "sg:address":"215 N 40th Ave W",
    "sg:city":"Duluth",
    "sg:classifiers":[
        {
            "category":"Real Estate",
            "subcategory":"Real Estate Agent",
            "type":"Services"
        }
    ],
    "sg:phone":"+1 218 624 4895",
    "sg:postcode":"55807",
    "sg:province":"MN",
    "sg:tags":[
        "cooperative"
    ],
    "sg:website":"www.membersccu.org",
    "wof:name":"Members Co Op Credit Union",
    "wof:placetype":"venue"
},
  "geometry": {"coordinates":[-92.15120899999999,46.751449],"type":"Point"}
}