{
  "type": "Feature",
  "properties": {
    "addr:full":"5219 14th Ave S Minneapolis MN 55417",
    "addr:housenumber":"5219",
    "addr:postcode":"55417",
    "addr:street":"14Th Ave S",
    "iso:country":"US",
    "sg:address":"5219 14th Ave S",
    "sg:city":"Minneapolis",
    "sg:classifiers":[
        {
            "category":"Arts & Performance",
            "subcategory":"Art Gallery",
            "type":"Entertainment"
        },
        {
            "category":"Museum",
            "type":"Entertainment"
        }
    ],
    "sg:phone":"+1 612 387 7736",
    "sg:postcode":"55417",
    "sg:province":"MN",
    "sg:tags":[
        "consultant",
        "galleries"
    ],
    "wof:name":"Rummel Design",
    "wof:placetype":"venue"
},
  "geometry": {"coordinates":[-93.254991,44.90854],"type":"Point"}
}