{
  "type": "Feature",
  "properties": {
    "iso:country":"US",
    "sg:address":"150 3rd St NW",
    "sg:city":"Wells",
    "sg:classifiers":[
        {
            "category":"Health Services",
            "subcategory":"Health Practitioner",
            "type":"Services"
        }
    ],
    "sg:phone":"+1 507 553 6645",
    "sg:postcode":"56097",
    "sg:province":"MN",
    "sg:tags":[
        "therapist",
        "physical"
    ],
    "wof:name":"Independent Therapy Svc",
    "wof:placetype":"venue"
},
  "geometry": {"coordinates":[-93.727383,43.748331],"type":"Point"}
}