{
  "type": "Feature",
  "properties": {
    "addr:full":"3505 Northdale Blvd NW Coon Rapids MN 55448",
    "addr:housenumber":"3505",
    "addr:postcode":"55448",
    "addr:street":"Northdale Blvd Nw",
    "iso:country":"US",
    "sg:address":"3505 Northdale Blvd NW",
    "sg:city":"Coon Rapids",
    "sg:classifiers":[
        {
            "category":"Banks & Credit Unions",
            "subcategory":"Bank",
            "type":"Services"
        }
    ],
    "sg:phone":"+1 763 422 0290",
    "sg:postcode":"55448",
    "sg:province":"MN",
    "sg:tags":[
        "federal",
        "state"
    ],
    "sg:website":"www.ahcu.com",
    "wof:name":"Anoka Hennepin Credit Union",
    "wof:placetype":"venue"
},
  "geometry": {"coordinates":[-93.346706,45.196111],"type":"Point"}
}