{
  "type": "Feature",
  "properties": {
    "addr:full":"9145 Eden Prairie Rd Eden Prairie MN 55347",
    "addr:housenumber":"9145",
    "addr:postcode":"55347",
    "addr:street":"Eden Prairie Rd",
    "iso:country":"US",
    "sg:address":"9145 Eden Prairie Rd",
    "sg:city":"Eden Prairie",
    "sg:classifiers":[
        {
            "category":"Organizations",
            "subcategory":"Religious Organization",
            "type":"Services"
        }
    ],
    "sg:phone":"+1 952 975 1900",
    "sg:postcode":"55347",
    "sg:province":"MN",
    "sg:tags":[
        "church"
    ],
    "sg:website":"www.eppc.com",
    "wof:name":"Eden Prairie Presbyterian Chr",
    "wof:placetype":"venue"
},
  "geometry": {"coordinates":[-93.48039900000001,44.83695],"type":"Point"}
}