{
  "type": "Feature",
  "properties": {
    "addr:full":"32489 155th St Springfield MN 56087",
    "addr:housenumber":"32489",
    "addr:postcode":"56087",
    "addr:street":"155Th St",
    "iso:country":"US",
    "sg:address":"32489 155th St",
    "sg:city":"Springfield",
    "sg:classifiers":[
        {
            "category":"Shopping",
            "subcategory":"Bicycles & Sporting Goods",
            "type":"Retail Goods"
        }
    ],
    "sg:phone":"+1 507 877 3077",
    "sg:postcode":"56087",
    "sg:province":"MN",
    "sg:tags":[
        "gun",
        "gunsmith"
    ],
    "wof:name":"Hunters Den",
    "wof:placetype":"venue"
},
  "geometry": {"coordinates":[-94.828926,44.18803],"type":"Point"}
}