{
  "type": "Feature",
  "properties": {
    "addr:full":"2319 Boxwood Ave St Paul MN 55119",
    "addr:housenumber":"2319",
    "addr:postcode":"55119",
    "addr:street":"Boxwood Ave",
    "iso:country":"US",
    "sg:address":"2319 Boxwood Ave",
    "sg:city":"St Paul",
    "sg:classifiers":[
        {
            "category":"Professional",
            "subcategory":"Computer Services",
            "type":"Services"
        }
    ],
    "sg:phone":"+1 612 801 8201",
    "sg:postcode":"55119",
    "sg:province":"MN",
    "sg:tags":[
        "consultant",
        "designer"
    ],
    "sg:website":"www.techcited.com",
    "wof:name":"Techcicted",
    "wof:placetype":"venue"
},
  "geometry": {"coordinates":[-93.001929,44.905165],"type":"Point"}
}