{
  "type": "Feature",
  "properties": {
    "addr:full":"2788 Marion St Saint Paul MN 55113",
    "addr:housenumber":"2788",
    "addr:postcode":"55113",
    "addr:street":"Marion St",
    "iso:country":"US",
    "sg:address":"2788 Marion St",
    "sg:city":"Saint Paul",
    "sg:classifiers":[
        {
            "category":"Real Estate",
            "subcategory":"Real Estate Agent",
            "type":"Services"
        }
    ],
    "sg:phone":"+1 651 766 8028",
    "sg:postcode":"55113",
    "sg:province":"MN",
    "wof:name":"For Ever Green Investment Club",
    "wof:placetype":"venue"
},
  "geometry": {"coordinates":[-93.10987,45.027324],"type":"Point"}
}