{
  "type": "Feature",
  "properties": {
    "addr:full":"445 Lakota Ln Chaska MN 55318",
    "addr:housenumber":"445",
    "addr:postcode":"55318",
    "addr:street":"Lakota Ln",
    "iso:country":"US",
    "sg:address":"445 Lakota Ln",
    "sg:city":"Chaska",
    "sg:classifiers":[
        {
            "category":"Travel",
            "subcategory":"Travel Agent",
            "type":"Entertainment"
        }
    ],
    "sg:phone":"+1 952 496 1759",
    "sg:postcode":"55318",
    "sg:province":"MN",
    "sg:tags":[
        "agency"
    ],
    "wof:name":"Babette Wheeler Custom Travel",
    "wof:placetype":"venue"
},
  "geometry": {"coordinates":[-93.531694,44.818149],"type":"Point"}
}