{
  "type": "Feature",
  "properties": {
    "addr:full":"2115 White Oak Cir NE Alexandria MN 56308",
    "addr:housenumber":"2115",
    "addr:postcode":"56308",
    "addr:street":"White Oak Cir Ne",
    "iso:country":"US",
    "sg:address":"2115 White Oak Cir NE",
    "sg:city":"Alexandria",
    "sg:classifiers":[
        {
            "category":"Real Estate",
            "subcategory":"Real Estate Services",
            "type":"Services"
        },
        {
            "category":"Real Estate",
            "subcategory":"Real Estate Agent",
            "type":"Services"
        }
    ],
    "sg:phone":"+1 320 763 7035",
    "sg:postcode":"56308",
    "sg:province":"MN",
    "sg:tags":[
        "management"
    ],
    "wof:name":"Kim Runck",
    "wof:placetype":"venue"
},
  "geometry": {"coordinates":[-95.35503799999999,45.913862],"type":"Point"}
}