{
  "type": "Feature",
  "properties": {
    "addr:full":"681 17th Ave NE Minneapolis MN 55413",
    "addr:housenumber":"681",
    "addr:postcode":"55413",
    "addr:street":"17Th Ave Ne",
    "iso:country":"US",
    "sg:address":"681 17th Ave NE",
    "sg:city":"Minneapolis",
    "sg:classifiers":[
        {
            "category":"Arts & Performance",
            "subcategory":"Art Gallery",
            "type":"Entertainment"
        }
    ],
    "sg:phone":"+1 612 788 5551",
    "sg:postcode":"55413",
    "sg:province":"MN",
    "sg:website":"www.casketarts.com",
    "wof:name":"Casket Art Building",
    "wof:placetype":"venue"
},
  "geometry": {"coordinates":[-93.253653,45.005093],"type":"Point"}
}