{
  "type": "Feature",
  "properties": {
    "addr:full":"731 Reichel Cir NE Stewartville MN 55976",
    "addr:housenumber":"731",
    "addr:postcode":"55976",
    "addr:street":"Reichel Cir Ne",
    "iso:country":"US",
    "sg:address":"731 Reichel Cir NE",
    "sg:city":"Stewartville",
    "sg:classifiers":[
        {
            "category":"Shopping",
            "subcategory":"Gifts & Souvenirs",
            "type":"Retail Goods"
        }
    ],
    "sg:phone":"+1 507 533 4070",
    "sg:postcode":"55976",
    "sg:province":"MN",
    "wof:name":"Lilys Gift & Gourmet",
    "wof:placetype":"venue"
},
  "geometry": {"coordinates":[-92.47917,43.86013],"type":"Point"}
}