{
  "type": "Feature",
  "properties": {
    "addr:full":"1519 13th Ave Clarkfield MN 56223",
    "addr:housenumber":"1519",
    "addr:postcode":"56223",
    "addr:street":"13Th Ave",
    "iso:country":"US",
    "sg:address":"1519 13th Ave",
    "sg:city":"Clarkfield",
    "sg:classifiers":[
        {
            "category":"Manufacturing",
            "subcategory":"Tools & Machinery",
            "type":"Manufacturing & Wholesale Goods"
        }
    ],
    "sg:phone":"+1 320 669 4628",
    "sg:postcode":"56223",
    "sg:province":"MN",
    "wof:name":"Miller Equipment & Mfg Inc",
    "wof:placetype":"venue"
},
  "geometry": {"coordinates":[-95.813309,44.793463],"type":"Point"}
}