{
  "type": "Feature",
  "properties": {
    "addr:full":"271 Silver Lake Rd SW New Brighton MN 55112",
    "addr:housenumber":"271",
    "addr:postcode":"55112",
    "addr:street":"Silver Lake Rd Sw",
    "iso:country":"US",
    "sg:address":"271 Silver Lake Rd SW",
    "sg:city":"New Brighton",
    "sg:classifiers":[
        {
            "category":"Wholesale",
            "subcategory":"Medical Equipment & Supplies",
            "type":"Manufacturing & Wholesale Goods"
        }
    ],
    "sg:phone":"+1 651 631 3380",
    "sg:postcode":"55112",
    "sg:province":"MN",
    "sg:tags":[
        "hospital"
    ],
    "wof:name":"Bio Instruments Inc",
    "wof:placetype":"venue"
},
  "geometry": {"coordinates":[-93.21824599999999,45.04603],"type":"Point"}
}