{
  "type": "Feature",
  "properties": {
    "iso:country":"US",
    "sg:address":"301 19th Ave S",
    "sg:city":"Minneapolis",
    "sg:classifiers":[
        {
            "category":"Organizations",
            "subcategory":"Professional Association",
            "type":"Services"
        }
    ],
    "sg:phone":"+1 612 625 5093",
    "sg:postcode":"55455",
    "sg:province":"MN",
    "sg:tags":[
        "business"
    ],
    "wof:name":"Intl Womens Rghts Actn Watch",
    "wof:placetype":"venue"
},
  "geometry": {"coordinates":[-93.24565800000001,44.971157],"type":"Point"}
}