{
  "type": "Feature",
  "properties": {
    "addr:full":"1101 Stinson Blvd Ste 17 Minneapolis MN 55413",
    "addr:housenumber":"1101",
    "addr:postcode":"55413",
    "addr:street":"Stinson Blvd Ste 17",
    "iso:country":"US",
    "sg:address":"1101 Stinson Blvd Ste 17",
    "sg:city":"Minneapolis",
    "sg:classifiers":[
        {
            "category":"Shopping",
            "subcategory":"Books",
            "type":"Retail Goods"
        }
    ],
    "sg:phone":"+1 612 623 7736",
    "sg:postcode":"55413",
    "sg:province":"MN",
    "sg:tags":[
        "bookstore"
    ],
    "wof:name":"You Work For Them",
    "wof:placetype":"venue"
},
  "geometry": {"coordinates":[-93.226546,44.998698],"type":"Point"}
}