{
  "type": "Feature",
  "properties": {
    "addr:full":"6305 Cambridge St Minneapolis MN 55416",
    "addr:housenumber":"6305",
    "addr:postcode":"55416",
    "addr:street":"Cambridge St",
    "iso:country":"US",
    "sg:address":"6305 Cambridge St",
    "sg:city":"Minneapolis",
    "sg:classifiers":[
        {
            "category":"Science Facility",
            "type":"Public Place"
        }
    ],
    "sg:phone":"+1 952 929 4711",
    "sg:postcode":"55416",
    "sg:province":"MN",
    "sg:tags":[
        "development",
        "laboratories-research"
    ],
    "wof:name":"Nordlich Manufacturing Inc",
    "wof:placetype":"venue"
},
  "geometry": {"coordinates":[-93.359272,44.933442],"type":"Point"}
}