{
  "type": "Feature",
  "properties": {
    "iso:country":"US",
    "sg:address":"116 E 26th St",
    "sg:city":"Minneapolis",
    "sg:classifiers":[
        {
            "category":"Building & Trades",
            "subcategory":"Construction",
            "type":"Services"
        }
    ],
    "sg:phone":"+1 612 872 0440",
    "sg:postcode":"55404",
    "sg:province":"MN",
    "sg:tags":[
        "house"
    ],
    "wof:name":"City Coin Laundry",
    "wof:placetype":"venue"
},
  "geometry": {"coordinates":[-93.275948,44.95546],"type":"Point"}
}