{
  "type": "Feature",
  "properties": {
    "addr:full":"15692 Highview Dr Saint Paul MN 55124",
    "addr:postcode":"15692;55124",
    "addr:street":"Highview Dr",
    "iso:country":"US",
    "sg:address":"15692 Highview Dr",
    "sg:city":"Saint Paul",
    "sg:classifiers":[
        {
            "category":"Real Estate",
            "subcategory":"Real Estate Agent",
            "type":"Services"
        }
    ],
    "sg:phone":"+1 952 431 5751",
    "sg:postcode":"55124",
    "sg:province":"MN",
    "wof:name":"Gold Key Realty",
    "wof:placetype":"venue"
},
  "geometry": {"coordinates":[-93.24034,44.723989],"type":"Point"}
}