{
  "type": "Feature",
  "properties": {
    "addr:full":"463 105th Ave NW Spicer MN 56288",
    "addr:housenumber":"463",
    "addr:postcode":"56288",
    "addr:street":"105Th Ave Nw",
    "iso:country":"US",
    "sg:address":"463 105th Ave NW",
    "sg:city":"Spicer",
    "sg:phone":"+1 320 796 2359",
    "sg:postcode":"56288",
    "sg:province":"MN",
    "sg:tags":[
        "farm",
        "corn",
        "soybean"
    ],
    "wof:name":"Heveron Cookie",
    "wof:placetype":"venue"
},
  "geometry": {"coordinates":[-95.048497,45.226285],"type":"Point"}
}