{
  "type": "Feature",
  "properties": {
    "addr:full":"4200 Lake Road Ave Robbinsdale MN 55422",
    "addr:housenumber":"4200",
    "addr:postcode":"55422",
    "addr:street":"Lake Road Ave",
    "iso:country":"US",
    "sg:address":"4200 Lake Road Ave",
    "sg:city":"Robbinsdale",
    "sg:classifiers":[
        {
            "category":"Social Services",
            "subcategory":"Child Care",
            "type":"Services"
        }
    ],
    "sg:phone":"+1 763 537 1213",
    "sg:postcode":"55422",
    "sg:province":"MN",
    "sg:tags":[
        "day"
    ],
    "wof:name":"Fun & Friends Before & After School Care",
    "wof:placetype":"venue"
},
  "geometry": {"coordinates":[-93.33380099999999,45.030998],"type":"Point"}
}