{
  "type": "Feature",
  "properties": {
    "iso:country":"US",
    "sg:address":"2721 Roosevelt Rd SE",
    "sg:city":"Bemidji",
    "sg:classifiers":[
        {
            "category":"Building & Trades",
            "subcategory":"Construction",
            "type":"Services"
        }
    ],
    "sg:phone":"+1 218 444 9993",
    "sg:postcode":"56601",
    "sg:province":"MN",
    "sg:tags":[
        "contractor",
        "laying",
        "floor",
        "covering"
    ],
    "wof:name":"Shepards World of Flooring",
    "wof:placetype":"venue"
},
  "geometry": {"coordinates":[-94.82788600000001,47.45337],"type":"Point"}
}