{
  "type": "Feature",
  "properties": {
    "iso:country":"US",
    "sg:address":"24795 Co Rd 75",
    "sg:city":"Saint Cloud",
    "sg:classifiers":[
        {
            "category":"Manufacturing",
            "subcategory":"Signs",
            "type":"Manufacturing & Wholesale Goods"
        }
    ],
    "sg:phone":"+1 320 654 6979",
    "sg:postcode":"56301",
    "sg:province":"MN",
    "sg:tags":[
        "m",
        "specialty",
        "mfg"
    ],
    "wof:name":"Coasters By Design",
    "wof:placetype":"venue"
},
  "geometry": {"coordinates":[-94.148888,45.48209],"type":"Point"}
}