{
  "type": "Feature",
  "properties": {
    "addr:full":"2830 NE Arthur St Minneapolis MN 55418",
    "addr:housenumber":"2830",
    "addr:postcode":"55418",
    "addr:street":"Ne Arthur St",
    "iso:country":"US",
    "sg:address":"2830 NE Arthur St",
    "sg:city":"Minneapolis",
    "sg:classifiers":[
        {
            "category":"Shopping",
            "subcategory":"Gifts & Souvenirs",
            "type":"Retail Goods"
        }
    ],
    "sg:phone":"+1 612 789 1595",
    "sg:postcode":"55418",
    "sg:province":"MN",
    "wof:name":"Green Couch Cards",
    "wof:placetype":"venue"
},
  "geometry": {"coordinates":[-93.23191300000001,45.0199],"type":"Point"}
}