{
  "type": "Feature",
  "properties": {
    "iso:country":"US",
    "sg:address":"23031 E Martin Lake Dr NE",
    "sg:city":"Stacy",
    "sg:classifiers":[
        {
            "category":"Manufacturing",
            "subcategory":"Jewelry",
            "type":"Manufacturing & Wholesale Goods"
        }
    ],
    "sg:phone":"+1 651 462 0017",
    "sg:postcode":"55079",
    "sg:province":"MN",
    "sg:tags":[
        "ware",
        "mfg"
    ],
    "wof:name":"Awards USA",
    "wof:placetype":"venue"
},
  "geometry": {"coordinates":[-93.077844,45.388246],"type":"Point"}
}