{
  "type": "Feature",
  "properties": {
    "addr:full":"14081 Glazier Ave Saint Paul MN 55124",
    "addr:housenumber":"14081",
    "addr:postcode":"55124",
    "addr:street":"Glazier Ave",
    "iso:country":"US",
    "sg:address":"14081 Glazier Ave",
    "sg:city":"Saint Paul",
    "sg:classifiers":[
        {
            "category":"Social Services",
            "subcategory":"Child Care",
            "type":"Services"
        }
    ],
    "sg:phone":"+1 952 432 7318",
    "sg:postcode":"55124",
    "sg:province":"MN",
    "sg:tags":[
        "daycare",
        "provider"
    ],
    "wof:name":"Marie R Lay",
    "wof:placetype":"venue"
},
  "geometry": {"coordinates":[-93.215771,44.744956],"type":"Point"}
}