{
  "type": "Feature",
  "properties": {
    "iso:country":"US",
    "sg:address":"19232 594th Ave",
    "sg:city":"Mankato",
    "sg:phone":"+1 507 245 3021",
    "sg:postcode":"56001",
    "sg:province":"MN",
    "sg:tags":[
        "farm",
        "corn"
    ],
    "wof:name":"Paul Bowe",
    "wof:placetype":"venue"
},
  "geometry": {"coordinates":[-93.908795,44.103866],"type":"Point"}
}