{
  "type": "Feature",
  "properties": {
    "iso:country":"US",
    "sg:address":"314 Garfield Ave",
    "sg:city":"Duluth",
    "sg:classifiers":[
        {
            "category":"Wholesale",
            "subcategory":"Machinery & Supplies",
            "type":"Manufacturing & Wholesale Goods"
        }
    ],
    "sg:phone":"+1 218 727 8611",
    "sg:postcode":"55802",
    "sg:province":"MN",
    "sg:tags":[
        "contractor"
    ],
    "wof:name":"Road Machinery & Supplies Co",
    "wof:placetype":"venue"
},
  "geometry": {"coordinates":[-92.113259,46.765198],"type":"Point"}
}