{
  "type": "Feature",
  "properties": {
    "iso:country":"US",
    "sg:address":"11307 Sibley Dr",
    "sg:city":"Burnsville",
    "sg:classifiers":[
        {
            "category":"Wholesale",
            "subcategory":"Electrical",
            "type":"Manufacturing & Wholesale Goods"
        }
    ],
    "sg:phone":"+1 952 808 0200",
    "sg:postcode":"55337",
    "sg:province":"MN",
    "sg:tags":[
        "semiconductor",
        "representative",
        "devices",
        "for"
    ],
    "sg:website":"www.tea-mn.com",
    "wof:name":"Technical Engineering Assoc",
    "wof:placetype":"venue"
},
  "geometry": {"coordinates":[-93.244379,44.799965],"type":"Point"}
}