{
  "type": "Feature",
  "properties": {
    "addr:full":"15559 Cherry Path Rosemount MN 55068",
    "addr:housenumber":"15559",
    "addr:postcode":"55068",
    "addr:street":"Cherry Path",
    "iso:country":"US",
    "sg:address":"15559 Cherry Path",
    "sg:city":"Rosemount",
    "sg:classifiers":[
        {
            "category":"Shopping",
            "subcategory":"Pharmacy",
            "type":"Retail Goods"
        }
    ],
    "sg:phone":"+1 651 322 1291",
    "sg:postcode":"55068",
    "sg:province":"MN",
    "wof:name":"Novo Nordisk Pharm Inc",
    "wof:placetype":"venue"
},
  "geometry": {"coordinates":[-93.135284,44.723575],"type":"Point"}
}