{
  "type": "Feature",
  "properties": {
    "iso:country":"US",
    "sg:address":"15559 Cherry Path",
    "sg:city":"Rosemount",
    "sg:classifiers":[
        {
            "category":"Shopping",
            "subcategory":"Pharmacy",
            "type":"Retail Goods"
        }
    ],
    "sg:phone":"+1 651 322 1291",
    "sg:postcode":"55068",
    "sg:province":"MN",
    "wof:name":"Novo Nordisk Pharm Inc",
    "wof:placetype":"venue"
},
  "geometry": {"coordinates":[-93.135284,44.723575],"type":"Point"}
}