{
  "type": "Feature",
  "properties": {
    "addr:full":"6138 76th Ln Loretto MN 55357",
    "addr:housenumber":"6138",
    "addr:postcode":"55357",
    "addr:street":"76Th Ln",
    "iso:country":"US",
    "sg:address":"6138 76th Ln",
    "sg:city":"Loretto",
    "sg:classifiers":[
        {
            "category":"Professional",
            "subcategory":"Business Services",
            "type":"Services"
        }
    ],
    "sg:phone":"+1 763 477 6470",
    "sg:postcode":"55357",
    "sg:province":"MN",
    "wof:name":"Alcon Associates",
    "wof:placetype":"venue"
},
  "geometry": {"coordinates":[-93.681752,45.091959],"type":"Point"}
}