{
  "type": "Feature",
  "properties": {
    "addr:full":"231 6th Ave NW Chisholm MN 55719",
    "addr:housenumber":"231",
    "addr:postcode":"55719",
    "addr:street":"6Th Ave Nw",
    "iso:country":"US",
    "sg:address":"231 6th Ave NW",
    "sg:city":"Chisholm",
    "sg:classifiers":[
        {
            "category":"Food & Beverages",
            "subcategory":"Groceries & Convenience Stores",
            "type":"Retail Goods"
        }
    ],
    "sg:phone":"+1 218 254 3306",
    "sg:postcode":"55719",
    "sg:province":"MN",
    "wof:name":"Chisholm EZ Stop",
    "wof:placetype":"venue"
},
  "geometry": {"coordinates":[-92.88909700000001,47.492167],"type":"Point"}
}