{
  "type": "Feature",
  "properties": {
    "iso:country":"US",
    "sg:address":"717 Stinson Blvd",
    "sg:city":"Minneapolis",
    "sg:phone":"+1 612 670 9484",
    "sg:postcode":"55413",
    "sg:province":"MN",
    "sg:website":"http://www.GreatLakesHauling.com",
    "wof:name":"Great Lakes Hauling",
    "wof:placetype":"venue"
},
  "geometry": {"coordinates":[-93.226759,44.9972],"type":"Point"}
}