{
  "type": "Feature",
  "properties": {
    "addr:full":"6015 Lyndale Ave S Minneapolis MN 55419",
    "addr:housenumber":"6015",
    "addr:postcode":"55419",
    "addr:street":"Lyndale Ave S",
    "iso:country":"US",
    "sg:address":"6015 Lyndale Ave S",
    "sg:city":"Minneapolis",
    "sg:classifiers":[
        {
            "category":"Sports & Exercise",
            "subcategory":"Gym",
            "type":"Entertainment"
        }
    ],
    "sg:phone":"+1 612 866 0832",
    "sg:postcode":"55419",
    "sg:province":"MN",
    "sg:tags":[
        "club",
        "health",
        "studio",
        "gymnasium"
    ],
    "wof:name":"Time Out For Fitness",
    "wof:placetype":"venue"
},
  "geometry": {"coordinates":[-93.288262,44.892652],"type":"Point"}
}