{
  "type": "Feature",
  "properties": {
    "iso:country":"US",
    "sg:address":"6931 Lake Dr",
    "sg:city":"Circle Pines",
    "sg:classifiers":[
        {
            "category":"Building & Trades",
            "subcategory":"Equipment Rental",
            "type":"Services"
        }
    ],
    "sg:phone":"+1 651 783 1332",
    "sg:postcode":"55014",
    "sg:province":"MN",
    "sg:tags":[
        "yard"
    ],
    "wof:name":"Volvo Rents Construction Equip",
    "wof:placetype":"venue"
},
  "geometry": {"coordinates":[-93.130624,45.156071],"type":"Point"}
}