{
  "type": "Feature",
  "properties": {
    "addr:full":"2208 4th St Saint Paul MN 55110",
    "addr:housenumber":"2208",
    "addr:postcode":"55110",
    "addr:street":"4Th St",
    "iso:country":"US",
    "sg:address":"2208 4th St",
    "sg:city":"Saint Paul",
    "sg:classifiers":[
        {
            "category":"Cafe",
            "type":"Food & Drink"
        }
    ],
    "sg:menulink":"http://www.allmenus.com/mn/white-bear-lake/244030-keys-cafe/menu/",
    "sg:phone":"+1 651 426 2885",
    "sg:postcode":"55110",
    "sg:province":"MN",
    "sg:tags":[
        "american"
    ],
    "wof:name":"Keys Cafe",
    "wof:placetype":"venue"
},
  "geometry": {"coordinates":[-93.007645,45.085401],"type":"Point"}
}