{
  "type": "Feature",
  "properties": {
    "addr:full":"5241 Lannon Ave NE Albertville MN 55301",
    "addr:postcode":"5241;55301",
    "addr:street":"Lannon Ave Ne",
    "iso:country":"US",
    "sg:address":"5241 Lannon Ave NE",
    "sg:city":"Albertville",
    "sg:classifiers":[
        {
            "category":"Manufacturing",
            "subcategory":"Tools & Machinery",
            "type":"Manufacturing & Wholesale Goods"
        }
    ],
    "sg:phone":"+1 763 497 2289",
    "sg:postcode":"55301",
    "sg:province":"MN",
    "sg:tags":[
        "semiconductor",
        "production",
        "rebuilds"
    ],
    "wof:name":"Rite Track",
    "wof:placetype":"venue"
},
  "geometry": {"coordinates":[-93.648748,45.228743],"type":"Point"}
}