{
  "type": "Feature",
  "properties": {
    "iso:country":"US",
    "sg:address":"117 2nd St NE",
    "sg:city":"Waseca",
    "sg:classifiers":[
        {
            "category":"Real Estate",
            "subcategory":"Real Estate Agent",
            "type":"Services"
        }
    ],
    "sg:phone":"+1 507 835 8116",
    "sg:postcode":"56093",
    "sg:province":"MN",
    "sg:tags":[
        "investment"
    ],
    "sg:website":"www.realestatemarketinginc.com",
    "wof:name":"Real Estate Marketing Service",
    "wof:placetype":"venue"
},
  "geometry": {"coordinates":[-93.506068,44.07831],"type":"Point"}
}