{
  "type": "Feature",
  "properties": {
    "iso:country":"US",
    "sg:address":"16101 15th St SE",
    "sg:city":"Blomkest",
    "sg:classifiers":[
        {
            "category":"Farming",
            "subcategory":"Poultry Farm",
            "type":"Manufacturing & Wholesale Goods"
        }
    ],
    "sg:phone":"+1 320 995 6443",
    "sg:postcode":"56216",
    "sg:province":"MN",
    "sg:tags":[
        "turkey"
    ],
    "wof:name":"Norling Farms Inc",
    "wof:placetype":"venue"
},
  "geometry": {"coordinates":[-95.02316399999999,44.96943],"type":"Point"}
}