{
  "type": "Feature",
  "properties": {
    "addr:full":"464 2nd St Excelsior MN 55331",
    "addr:housenumber":"464",
    "addr:postcode":"55331",
    "addr:street":"2Nd St",
    "iso:country":"US",
    "sg:address":"464 2nd St",
    "sg:city":"Excelsior",
    "sg:classifiers":[
        {
            "category":"Professional",
            "subcategory":"Employment Agencies",
            "type":"Services"
        }
    ],
    "sg:phone":"+1 952 380 4919",
    "sg:postcode":"55331",
    "sg:province":"MN",
    "wof:name":"Computer Personnel of Minnesota",
    "wof:placetype":"venue"
},
  "geometry": {"coordinates":[-93.576401,44.899101],"type":"Point"}
}