{
  "type": "Feature",
  "properties": {
    "addr:full":"2245 Roosevelt Rd St Cloud MN 56301",
    "addr:housenumber":"2245",
    "addr:postcode":"56301",
    "addr:street":"Roosevelt Rd",
    "iso:country":"US",
    "sg:address":"2245 Roosevelt Rd",
    "sg:city":"St Cloud",
    "sg:classifiers":[
        {
            "category":"Shopping",
            "type":"Retail Goods"
        }
    ],
    "sg:phone":"+1 320 252 0130",
    "sg:postcode":"56301",
    "sg:province":"MN",
    "sg:tags":[
        "spa",
        "hot",
        "tub"
    ],
    "wof:name":"Ament Spas & Pools",
    "wof:placetype":"venue"
},
  "geometry": {"coordinates":[-94.164518,45.534004],"type":"Point"}
}