{
  "type": "Feature",
  "properties": {
    "addr:full":"16820 Duluth Ave SE Prior Lake MN 55372",
    "addr:housenumber":"16820",
    "addr:postcode":"55372",
    "addr:street":"Duluth Ave Se",
    "iso:country":"US",
    "sg:address":"16820 Duluth Ave SE",
    "sg:city":"Prior Lake",
    "sg:classifiers":[
        {
            "category":"Home & Garden",
            "subcategory":"Hardware",
            "type":"Retail Goods"
        }
    ],
    "sg:phone":"+1 952 447 5580",
    "sg:postcode":"55372",
    "sg:province":"MN",
    "sg:tags":[
        "supply"
    ],
    "wof:name":"Als True Value Hardware",
    "wof:placetype":"venue"
},
  "geometry": {"coordinates":[-93.430241,44.706506],"type":"Point"}
}