{
  "type": "Feature",
  "properties": {
    "addr:full":"20232 Norgard Dr Spring Grove MN 55974",
    "addr:housenumber":"20232",
    "addr:postcode":"55974",
    "addr:street":"Norgard Dr",
    "iso:country":"US",
    "sg:address":"20232 Norgard Dr",
    "sg:city":"Spring Grove",
    "sg:classifiers":[
        {
            "category":"Personal",
            "type":"Services"
        }
    ],
    "sg:phone":"+1 507 498 5226",
    "sg:postcode":"55974",
    "sg:province":"MN",
    "wof:name":"Healing Hands Massage",
    "wof:placetype":"venue"
},
  "geometry": {"coordinates":[-91.65606,43.654084],"type":"Point"}
}