{
  "type": "Feature",
  "properties": {
    "iso:country":"US",
    "sg:address":"956 Albion Ave",
    "sg:city":"Fairmont",
    "sg:classifiers":[
        {
            "category":"Banks & Credit Unions",
            "subcategory":"Bank",
            "type":"Services"
        }
    ],
    "sg:phone":"+1 507 238 2351",
    "sg:postcode":"56031",
    "sg:province":"MN",
    "sg:tags":[
        "depository",
        "central",
        "reserve"
    ],
    "wof:name":"Heritage Est Buyers",
    "wof:placetype":"venue"
},
  "geometry": {"coordinates":[-94.460275,43.642604],"type":"Point"}
}