{
  "type": "Feature",
  "properties": {
    "iso:country":"US",
    "sg:address":"1800 Cloquet Ave",
    "sg:city":"Cloquet",
    "sg:classifiers":[
        {
            "category":"Manufacturing",
            "subcategory":"Wood Products",
            "type":"Manufacturing & Wholesale Goods"
        }
    ],
    "sg:phone":"+1 218 879 6700",
    "sg:postcode":"55720",
    "sg:province":"MN",
    "sg:website":"www.alltrista.com",
    "wof:name":"Jarden Consumer Solutions",
    "wof:placetype":"venue"
},
  "geometry": {"coordinates":[-92.44387999999999,46.72137],"type":"Point"}
}