{
  "type": "Feature",
  "properties": {
    "addr:full":"19146 Co Rd 28 Glenwood MN 56334",
    "addr:housenumber":"19146;28",
    "addr:postcode":"56334",
    "addr:street":"Co Rd",
    "iso:country":"US",
    "sg:address":"19146 Co Rd 28",
    "sg:city":"Glenwood",
    "sg:classifiers":[
        {
            "category":"Farming",
            "subcategory":"Dairy Farm",
            "type":"Manufacturing & Wholesale Goods"
        }
    ],
    "sg:phone":"+1 320 283 5480",
    "sg:postcode":"56334",
    "sg:province":"MN",
    "wof:name":"John Lanigan",
    "wof:placetype":"venue"
},
  "geometry": {"coordinates":[-95.330117,45.722825],"type":"Point"}
}