{
  "type": "Feature",
  "properties": {
    "addr:full":"7200 80th St S Cottage Grove MN 55016",
    "addr:housenumber":"7200",
    "addr:postcode":"55016",
    "addr:street":"80Th St S",
    "iso:country":"US",
    "sg:address":"7200 80th St S",
    "sg:city":"Cottage Grove",
    "sg:classifiers":[
        {
            "category":"Professional",
            "subcategory":"Advertising",
            "type":"Services"
        }
    ],
    "sg:phone":"+1 651 459 0919",
    "sg:postcode":"55016",
    "sg:province":"MN",
    "wof:name":"Metro Dining Club",
    "wof:placetype":"venue"
},
  "geometry": {"coordinates":[-92.959694,44.833541],"type":"Point"}
}