{
  "type": "Feature",
  "properties": {
    "addr:full":"1382 Camelback Dr Saint Paul MN 55123",
    "addr:housenumber":"1382",
    "addr:postcode":"55123",
    "addr:street":"Camelback Dr",
    "iso:country":"US",
    "sg:address":"1382 Camelback Dr",
    "sg:city":"Saint Paul",
    "sg:classifiers":[
        {
            "category":"Professional",
            "subcategory":"Computer Services",
            "type":"Services"
        }
    ],
    "sg:phone":"+1 651 208 0058",
    "sg:postcode":"55123",
    "sg:province":"MN",
    "sg:tags":[
        "programing",
        "custom"
    ],
    "wof:name":"Net Data Inc",
    "wof:placetype":"venue"
},
  "geometry": {"coordinates":[-93.16422900000001,44.788305],"type":"Point"}
}