{
  "type": "Feature",
  "properties": {
    "addr:full":"11555 Van Buren Ct NE Minneapolis MN 55434",
    "addr:housenumber":"11555",
    "addr:postcode":"55434",
    "addr:street":"Van Buren Ct Ne",
    "iso:country":"US",
    "sg:address":"11555 Van Buren Ct NE",
    "sg:city":"Minneapolis",
    "sg:classifiers":[
        {
            "category":"Retail",
            "subcategory":"Laundry & Dry Cleaning",
            "type":"Services"
        }
    ],
    "sg:phone":"+1 651 426 9726",
    "sg:postcode":"55434",
    "sg:province":"MN",
    "sg:tags":[
        "cleaner",
        "rug",
        "carpet"
    ],
    "wof:name":"Carpet Cleaning Solutions, Inc",
    "wof:placetype":"venue"
},
  "geometry": {"coordinates":[-93.249763,45.179675],"type":"Point"}
}