{
  "type": "Feature",
  "properties": {
    "addr:full":"8188 Brooklyn Blvd Minneapolis MN 55445",
    "addr:housenumber":"8188",
    "addr:postcode":"55445",
    "addr:street":"Brooklyn Blvd",
    "iso:country":"US",
    "sg:address":"8188 Brooklyn Blvd",
    "sg:city":"Minneapolis",
    "sg:classifiers":[
        {
            "category":"Autos & Motor Vehicles",
            "subcategory":"Automobile Sales",
            "type":"Retail Goods"
        }
    ],
    "sg:phone":"+1 763 535 5200",
    "sg:postcode":"55445",
    "sg:province":"MN",
    "sg:tags":[
        "new",
        "car"
    ],
    "sg:website":"http://www.dodge.com/hostc/fad/findDealers.do",
    "wof:name":"Luther Brookdale Chrysler Jeep Dodge",
    "wof:placetype":"venue"
},
  "geometry": {"coordinates":[-93.383431,45.094608],"type":"Point"}
}