{
  "type": "Feature",
  "properties": {
    "addr:full":"591 2nd Ave N Bayport MN 55003",
    "addr:housenumber":"591",
    "addr:postcode":"55003",
    "addr:street":"2Nd Ave N",
    "iso:country":"US",
    "sg:address":"591 2nd Ave N",
    "sg:city":"Bayport",
    "sg:classifiers":[
        {
            "category":"Home & Garden",
            "subcategory":"Building Materials",
            "type":"Retail Goods"
        }
    ],
    "sg:phone":"+1 651 439 3147",
    "sg:postcode":"55003",
    "sg:province":"MN",
    "wof:name":"Valley Window Service",
    "wof:placetype":"venue"
},
  "geometry": {"coordinates":[-92.783528,45.018317],"type":"Point"}
}