{
  "type": "Feature",
  "properties": {
    "addr:full":"4428 Josephine Ln Minneapolis MN 55422",
    "addr:housenumber":"4428",
    "addr:postcode":"55422",
    "addr:street":"Josephine Ln",
    "iso:country":"US",
    "sg:address":"4428 Josephine Ln",
    "sg:city":"Minneapolis",
    "sg:classifiers":[
        {
            "category":"Professional",
            "subcategory":"Business Services",
            "type":"Services"
        }
    ],
    "sg:phone":"+1 763 533 7432",
    "sg:postcode":"55422",
    "sg:province":"MN",
    "wof:name":"D&V Assoc Inc",
    "wof:placetype":"venue"
},
  "geometry": {"coordinates":[-93.33604099999999,45.034478],"type":"Point"}
}