{
  "type": "Feature",
  "properties": {
    "addr:full":"2002 Black Oak Ave Montevideo MN 56265",
    "addr:housenumber":"2002",
    "addr:postcode":"56265",
    "addr:street":"Black Oak Ave",
    "iso:country":"US",
    "sg:address":"2002 Black Oak Ave",
    "sg:city":"Montevideo",
    "sg:classifiers":[
        {
            "category":"Manufacturing",
            "subcategory":"Tools & Machinery",
            "type":"Manufacturing & Wholesale Goods"
        }
    ],
    "sg:phone":"+1 320 269 6562",
    "sg:postcode":"56265",
    "sg:province":"MN",
    "sg:tags":[
        "m",
        "mfg"
    ],
    "sg:website":"www.slmti.com",
    "wof:name":"SL Montevideo Technology Inc",
    "wof:placetype":"venue"
},
  "geometry": {"coordinates":[-95.70201900000001,44.948961],"type":"Point"}
}