{
  "type": "Feature",
  "properties": {
    "addr:full":"23006 280th St Red Wing MN 55066",
    "addr:housenumber":"23006",
    "addr:postcode":"55066",
    "addr:street":"280Th St",
    "iso:country":"US",
    "sg:address":"23006 280th St",
    "sg:city":"Red Wing",
    "sg:classifiers":[
        {
            "category":"Building & Trades",
            "subcategory":"Construction",
            "type":"Services"
        }
    ],
    "sg:phone":"+1 651 388 9306",
    "sg:postcode":"55066",
    "sg:province":"MN",
    "sg:tags":[
        "house"
    ],
    "wof:name":"Cornerstone Construction",
    "wof:placetype":"venue"
},
  "geometry": {"coordinates":[-92.57114199999999,44.542071],"type":"Point"}
}