{
  "type": "Feature",
  "properties": {
    "addr:full":"12785 James Ave Hastings MN 55033",
    "addr:housenumber":"12785",
    "addr:postcode":"55033",
    "addr:street":"James Ave",
    "iso:country":"US",
    "sg:address":"12785 James Ave",
    "sg:city":"Hastings",
    "sg:classifiers":[
        {
            "category":"Personal",
            "subcategory":"Beauty Salon",
            "type":"Services"
        }
    ],
    "sg:phone":"+1 651 437 4474",
    "sg:postcode":"55033",
    "sg:province":"MN",
    "wof:name":"Hillside Beauty Salon",
    "wof:placetype":"venue"
},
  "geometry": {"coordinates":[-92.90282000000001,44.763452],"type":"Point"}
}