{
  "type": "Feature",
  "properties": {
    "iso:country":"US",
    "sg:address":"750 4th St NW",
    "sg:city":"Saint Paul",
    "sg:classifiers":[
        {
            "category":"Retail",
            "subcategory":"Auto Repair",
            "type":"Services"
        }
    ],
    "sg:phone":"+1 651 633 2576",
    "sg:postcode":"55112",
    "sg:province":"MN",
    "sg:tags":[
        "general"
    ],
    "wof:name":"New Brighton Services",
    "wof:placetype":"venue"
},
  "geometry": {"coordinates":[-93.199096,45.056087],"type":"Point"}
}