{
  "type": "Feature",
  "properties": {
    "iso:country":"US",
    "sg:address":"109 N Main St",
    "sg:city":"Mahnomen",
    "sg:classifiers":[
        {
            "category":"Shopping",
            "subcategory":"Florist",
            "type":"Retail Goods"
        }
    ],
    "sg:phone":"+1 218 935 2585",
    "sg:postcode":"56557",
    "sg:province":"MN",
    "wof:name":"Country Rose Floral",
    "wof:placetype":"venue"
},
  "geometry": {"coordinates":[-95.968698,47.316203],"type":"Point"}
}