{
  "type": "Feature",
  "properties": {
    "iso:country":"US",
    "sg:address":"1100 E 80th St",
    "sg:city":"Minneapolis",
    "sg:classifiers":[
        {
            "category":"Professional",
            "subcategory":"Business Services",
            "type":"Services"
        },
        {
            "category":"Professional",
            "subcategory":"Printing & Photocopies",
            "type":"Services"
        }
    ],
    "sg:phone":"+1 952 888 2712",
    "sg:postcode":"55420",
    "sg:province":"MN",
    "sg:tags":[
        "services-commercial",
        "system",
        "form",
        "printers-business"
    ],
    "wof:name":"Tenenz, Inc.",
    "wof:placetype":"venue"
},
  "geometry": {"coordinates":[-93.259168,44.857636],"type":"Point"}
}