{
  "type": "Feature",
  "properties": {
    "addr:full":"9136 13th St NE Saint Michael MN 55376",
    "addr:housenumber":"9136",
    "addr:postcode":"55376",
    "addr:street":"13Th St Ne Saint Michael",
    "iso:country":"US",
    "sg:address":"9136 13th St NE",
    "sg:city":"Saint Michael",
    "sg:classifiers":[
        {
            "category":"Professional",
            "subcategory":"Computer Services",
            "type":"Services"
        }
    ],
    "sg:phone":"+1 763 497 8556",
    "sg:postcode":"55376",
    "sg:province":"MN",
    "sg:tags":[
        "related"
    ],
    "wof:name":"Diamond Consulting Inc",
    "wof:placetype":"venue"
},
  "geometry": {"coordinates":[-93.70578500000001,45.172103],"type":"Point"}
}