{
  "type": "Feature",
  "properties": {
    "iso:country":"US",
    "sg:address":"4280 Irvin Ct N",
    "sg:city":"Lake Elmo",
    "sg:classifiers":[
        {
            "category":"Professional",
            "subcategory":"Business Services",
            "type":"Services"
        }
    ],
    "sg:phone":"+1 651 779 7659",
    "sg:postcode":"55042",
    "sg:province":"MN",
    "sg:tags":[
        "recording",
        "studio"
    ],
    "wof:name":"Gregg Sound Studios",
    "wof:placetype":"venue"
},
  "geometry": {"coordinates":[-92.92942600000001,45.010878],"type":"Point"}
}