{
  "type": "Feature",
  "properties": {
    "addr:full":"20122 480th Ave Easton MN 56025",
    "addr:housenumber":"20122",
    "addr:postcode":"56025",
    "addr:street":"480Th Ave",
    "iso:country":"US",
    "sg:address":"20122 480th Ave",
    "sg:city":"Easton",
    "sg:classifiers":[
        {
            "category":"Manufacturing",
            "subcategory":"Food",
            "type":"Manufacturing & Wholesale Goods"
        },
        {
            "category":"Farming",
            "subcategory":"Farm",
            "type":"Manufacturing & Wholesale Goods"
        }
    ],
    "sg:phone":"+1 507 787 2395",
    "sg:postcode":"56025",
    "sg:province":"MN",
    "sg:tags":[
        "corn",
        "product"
    ],
    "wof:name":"Jeff Schrader",
    "wof:placetype":"venue"
},
  "geometry": {"coordinates":[-93.907471,43.77617],"type":"Point"}
}