{
  "type": "Feature",
  "properties": {
    "addr:full":"857 Grand Ave St Paul MN 55105",
    "addr:housenumber":"857",
    "addr:postcode":"55105",
    "addr:street":"Grand Ave",
    "iso:country":"US",
    "sg:address":"857 Grand Ave",
    "sg:city":"St Paul",
    "sg:classifiers":[
        {
            "category":"Shopping",
            "subcategory":"Hobbies, Toys, & Games",
            "type":"Retail Goods"
        },
        {
            "category":"Shopping",
            "type":"Retail Goods"
        }
    ],
    "sg:phone":"+1 651 228 0414",
    "sg:postcode":"55105",
    "sg:province":"MN",
    "sg:tags":[
        "art",
        "gallery",
        "dealer"
    ],
    "wof:name":"Sorrayah Studios",
    "wof:placetype":"venue"
},
  "geometry": {"coordinates":[-93.134659,44.940002],"type":"Point"}
}