{
  "type": "Feature",
  "properties": {
    "addr:full":"61077 Duxbury Rd Sandstone MN 55072",
    "addr:housenumber":"61077",
    "addr:postcode":"55072",
    "addr:street":"Duxbury Rd",
    "iso:country":"US",
    "sg:address":"61077 Duxbury Rd",
    "sg:city":"Sandstone",
    "sg:classifiers":[
        {
            "category":"Restaurant",
            "type":"Food & Drink"
        }
    ],
    "sg:phone":"+1 320 245 2517",
    "sg:postcode":"55072",
    "sg:province":"MN",
    "wof:name":"Duxbury Store",
    "wof:placetype":"venue"
},
  "geometry": {"coordinates":[-92.505324,46.127894],"type":"Point"}
}