{
  "type": "Feature",
  "properties": {
    "addr:full":"1517 Pennsylvania Ave N Minneapolis MN 55427",
    "addr:housenumber":"1517",
    "addr:postcode":"55427",
    "addr:street":"Pennsylvania Ave N",
    "iso:country":"US",
    "sg:address":"1517 Pennsylvania Ave N",
    "sg:city":"Minneapolis",
    "sg:classifiers":[
        {
            "category":"Real Estate",
            "subcategory":"Real Estate Agent",
            "type":"Services"
        }
    ],
    "sg:phone":"+1 763 591 5996",
    "sg:postcode":"55427",
    "sg:province":"MN",
    "sg:tags":[
        "counseling",
        "appraisal"
    ],
    "wof:name":"Russell Smith Associates Inc",
    "wof:placetype":"venue"
},
  "geometry": {"coordinates":[-93.375373,44.995862],"type":"Point"}
}