{
  "type": "Feature",
  "properties": {
    "iso:country":"US",
    "sg:address":"6420 Oxford St",
    "sg:city":"Minneapolis",
    "sg:classifiers":[
        {
            "category":"Restaurant",
            "type":"Food & Drink"
        }
    ],
    "sg:phone":"+1 952 927 5057",
    "sg:postcode":"55426",
    "sg:province":"MN",
    "sg:tags":[
        "eating"
    ],
    "wof:name":"Special Events America Inc",
    "wof:placetype":"venue"
},
  "geometry": {"coordinates":[-93.360411,44.935809],"type":"Point"}
}