{
  "type": "Feature",
  "properties": {
    "iso:country":"US",
    "sg:address":"7322 Imperial Ave S",
    "sg:city":"Cottage Grove",
    "sg:classifiers":[
        {
            "category":"Shopping",
            "subcategory":"Florist",
            "type":"Retail Goods"
        }
    ],
    "sg:phone":"+1 651 459 6661",
    "sg:postcode":"55016",
    "sg:province":"MN",
    "wof:name":"Pjs Flowers",
    "wof:placetype":"venue"
},
  "geometry": {"coordinates":[-92.940893,44.843506],"type":"Point"}
}