{
  "type": "Feature",
  "properties": {
    "addr:full":"1234 State Hwy 13 Waseca MN 56093",
    "addr:housenumber":"1234",
    "addr:postcode":"56093",
    "addr:street":"State Hwy 13",
    "iso:country":"US",
    "sg:address":"1234 State Hwy 13",
    "sg:city":"Waseca",
    "sg:classifiers":[
        {
            "category":"Shopping",
            "subcategory":"Gifts & Souvenirs",
            "type":"Retail Goods"
        }
    ],
    "sg:phone":"+1 507 835 5800",
    "sg:postcode":"56093",
    "sg:province":"MN",
    "sg:tags":[
        "shop"
    ],
    "wof:name":"Myron's Hallmark Cards & Gifts",
    "wof:placetype":"venue"
},
  "geometry": {"coordinates":[-93.506241,44.065809],"type":"Point"}
}