{
  "type": "Feature",
  "properties": {
    "iso:country":"US",
    "sg:address":"1171 Pleasant Ct SW",
    "sg:city":"Bemidji",
    "sg:classifiers":[
        {
            "category":"Freight",
            "type":"Transportation"
        }
    ],
    "sg:phone":"+1 218 751 3408",
    "sg:postcode":"56601",
    "sg:province":"MN",
    "sg:tags":[
        "hauling",
        "trucking"
    ],
    "wof:name":"Senske & Son Transfer",
    "wof:placetype":"venue"
},
  "geometry": {"coordinates":[-94.892743,47.449728],"type":"Point"}
}