{
  "type": "Feature",
  "properties": {
    "iso:country":"US",
    "sg:address":"444 Lafayette Rd",
    "sg:city":"St Paul",
    "sg:classifiers":[
        {
            "category":"Social Services",
            "type":"Services"
        }
    ],
    "sg:phone":"+1 651 296 5690",
    "sg:postcode":"55155",
    "sg:province":"MN",
    "sg:tags":[
        "government"
    ],
    "wof:name":"Children & Family Program",
    "wof:placetype":"venue"
},
  "geometry": {"coordinates":[-93.084447,44.954651],"type":"Point"}
}