{
  "type": "Feature",
  "properties": {
    "iso:country":"US",
    "sg:address":"15187 90th Ave S",
    "sg:city":"Barnesville",
    "sg:classifiers":[
        {
            "category":"Wholesale",
            "subcategory":"Scrap",
            "type":"Manufacturing & Wholesale Goods"
        }
    ],
    "sg:phone":"+1 218 789 7848",
    "sg:postcode":"56514",
    "sg:province":"MN",
    "sg:tags":[
        "metal"
    ],
    "wof:name":"Valley Iron & Metal",
    "wof:placetype":"venue"
},
  "geometry": {"coordinates":[-96.479426,46.753939],"type":"Point"}
}