{
  "type": "Feature",
  "properties": {
    "addr:full":"809 1st Ave NE East Grand Forks MN 56721",
    "addr:housenumber":"809",
    "addr:postcode":"56721",
    "addr:street":"1St Ave Ne",
    "iso:country":"US",
    "sg:address":"809 1st Ave NE",
    "sg:city":"East Grand Forks",
    "sg:classifiers":[
        {
            "category":"Building & Trades",
            "subcategory":"Construction",
            "type":"Services"
        }
    ],
    "sg:phone":"+1 218 773 0797",
    "sg:postcode":"56721",
    "sg:province":"MN",
    "sg:tags":[
        "contractor"
    ],
    "wof:name":"Bren Steel Siding",
    "wof:placetype":"venue"
},
  "geometry": {"coordinates":[-97.018575,47.933054],"type":"Point"}
}