{
  "type": "Feature",
  "properties": {
    "iso:country":"US",
    "sg:address":"4402 1/2 France Ave S",
    "sg:city":"Minneapolis",
    "sg:classifiers":[
        {
            "category":"Education",
            "subcategory":"Special Training",
            "type":"Public Place"
        },
        {
            "category":"Shopping",
            "subcategory":"Pets & Pet Supplies",
            "type":"Retail Goods"
        }
    ],
    "sg:phone":"+1 612 816 2675",
    "sg:postcode":"55416",
    "sg:province":"MN",
    "sg:tags":[
        "tutor",
        "private"
    ],
    "sg:website":"www.dogsmn.com",
    "wof:name":"Your Dog's Best Friend",
    "wof:placetype":"venue"
},
  "geometry": {"coordinates":[-93.32865,44.977147],"type":"Point"}
}