{
  "type": "Feature",
  "properties": {
    "addr:full":"420 Summit Ave Saint Paul MN 55102",
    "addr:housenumber":"420",
    "addr:postcode":"55102",
    "addr:street":"Summit Ave",
    "iso:country":"US",
    "sg:address":"420 Summit Ave",
    "sg:city":"Saint Paul",
    "sg:classifiers":[
        {
            "category":"Professional",
            "subcategory":"Management & Consulting",
            "type":"Services"
        }
    ],
    "sg:phone":"+1 651 222 8716",
    "sg:postcode":"55102",
    "sg:province":"MN",
    "sg:tags":[
        "marketing",
        "public",
        "relations"
    ],
    "wof:name":"Rowland Cmmnications Worldwide",
    "wof:placetype":"venue"
},
  "geometry": {"coordinates":[-93.118213,44.941281],"type":"Point"}
}