{
  "type": "Feature",
  "properties": {
    "addr:full":"10181 101st Pl N Osseo MN 55369",
    "addr:housenumber":"10181",
    "addr:postcode":"55369",
    "addr:street":"101St Pl N",
    "iso:country":"US",
    "sg:address":"10181 101st Pl N",
    "sg:city":"Osseo",
    "sg:classifiers":[
        {
            "category":"Freight",
            "type":"Transportation"
        }
    ],
    "sg:phone":"+1 763 391 6160",
    "sg:postcode":"55369",
    "sg:province":"MN",
    "sg:tags":[
        "trucking"
    ],
    "wof:name":"Two River's Transport Inc",
    "wof:placetype":"venue"
},
  "geometry": {"coordinates":[-93.40993400000001,45.138634],"type":"Point"}
}