{
  "type": "Feature",
  "properties": {
    "iso:country":"US",
    "sg:address":"815 Cherie Ln",
    "sg:city":"Duluth",
    "sg:classifiers":[
        {
            "category":"Professional",
            "type":"Services"
        }
    ],
    "sg:phone":"+1 218 525 9038",
    "sg:postcode":"55803",
    "sg:province":"MN",
    "wof:name":"D & C Letourneau",
    "wof:placetype":"venue"
},
  "geometry": {"coordinates":[-92.053808,46.839232],"type":"Point"}
}