{
  "type": "Feature",
  "properties": {
    "iso:country":"US",
    "sg:address":"701 Village Green Pl",
    "sg:city":"Mora",
    "sg:classifiers":[
        {
            "category":"Professional",
            "type":"Services"
        }
    ],
    "sg:phone":"+1 320 679 3079",
    "sg:postcode":"55051",
    "sg:province":"MN",
    "wof:name":"Townhouses of Village Green",
    "wof:placetype":"venue"
},
  "geometry": {"coordinates":[-93.296454,45.884668],"type":"Point"}
}