{
  "type": "Feature",
  "properties": {
    "iso:country":"US",
    "sg:address":"205 W Elm Ave",
    "sg:city":"Waseca",
    "sg:classifiers":[
        {
            "category":"Autos & Motor Vehicles",
            "subcategory":"Fuel & Gas Station",
            "type":"Retail Goods"
        }
    ],
    "sg:phone":"+1 507 835 5407",
    "sg:postcode":"56093",
    "sg:province":"MN",
    "sg:tags":[
        "bulk",
        "station",
        "dealer"
    ],
    "wof:name":"Bock Service Inc",
    "wof:placetype":"venue"
},
  "geometry": {"coordinates":[-93.508814,44.077536],"type":"Point"}
}