{
  "type": "Feature",
  "properties": {
    "addr:full":"1501 Northway Dr St Cloud MN 56303",
    "addr:housenumber":"1501",
    "addr:postcode":"56303",
    "addr:street":"Northway Dr",
    "iso:country":"US",
    "sg:address":"1501 Northway Dr",
    "sg:city":"St Cloud",
    "sg:classifiers":[
        {
            "category":"Personal",
            "subcategory":"Beauty Salon",
            "type":"Services"
        }
    ],
    "sg:phone":"+1 320 253 8158",
    "sg:postcode":"56303",
    "sg:province":"MN",
    "wof:name":"Total Hair Design",
    "wof:placetype":"venue"
},
  "geometry": {"coordinates":[-94.18218899999999,45.57892],"type":"Point"}
}