{
  "type": "Feature",
  "properties": {
    "addr:full":"506 4th St SW Montgomery MN 56069",
    "addr:housenumber":"506",
    "addr:postcode":"56069",
    "addr:street":"4Th St Sw",
    "iso:country":"US",
    "sg:address":"506 4th St SW",
    "sg:city":"Montgomery",
    "sg:classifiers":[
        {
            "category":"Social Services",
            "subcategory":"Child Care",
            "type":"Services"
        }
    ],
    "sg:phone":"+1 507 364 8016",
    "sg:postcode":"56069",
    "sg:province":"MN",
    "sg:tags":[
        "day",
        "provider"
    ],
    "wof:name":"Cjs Check Imports",
    "wof:placetype":"venue"
},
  "geometry": {"coordinates":[-93.58520900000001,44.434175],"type":"Point"}
}