{
  "type": "Feature",
  "properties": {
    "addr:full":"61106 265th Ave Mantorville MN 55955",
    "addr:housenumber":"61106",
    "addr:postcode":"55955",
    "addr:street":"265Th Ave",
    "iso:country":"US",
    "sg:address":"61106 265th Ave",
    "sg:city":"Mantorville",
    "sg:classifiers":[
        {
            "category":"Manufacturing",
            "subcategory":"Apparel",
            "type":"Manufacturing & Wholesale Goods"
        }
    ],
    "sg:phone":"+1 507 635 5537",
    "sg:postcode":"55955",
    "sg:province":"MN",
    "wof:name":"Embroidery Hutch",
    "wof:placetype":"venue"
},
  "geometry": {"coordinates":[-92.708005,44.061894],"type":"Point"}
}