{
  "type": "Feature",
  "properties": {
    "addr:full":"8401 73rd Ave N Brooklyn Park MN 55428",
    "addr:housenumber":"8401",
    "addr:postcode":"55428",
    "addr:street":"73Rd Ave N",
    "iso:country":"US",
    "sg:address":"8401 73rd Ave N",
    "sg:city":"Brooklyn Park",
    "sg:classifiers":[
        {
            "category":"Building & Trades",
            "subcategory":"Landscaping Services",
            "type":"Services"
        }
    ],
    "sg:phone":"+1 763 478 5390",
    "sg:postcode":"55428",
    "sg:province":"MN",
    "sg:tags":[
        "lawn",
        "maintenance",
        "grounds"
    ],
    "wof:name":"Natural Lawn of America",
    "wof:placetype":"venue"
},
  "geometry": {"coordinates":[-93.389664,45.087371],"type":"Point"}
}