{
  "type": "Feature",
  "properties": {
    "addr:full":"216 Wilkins St W Stillwater MN 55082",
    "addr:housenumber":"216",
    "addr:postcode":"55082",
    "addr:street":"Wilkins St W",
    "iso:country":"US",
    "sg:address":"216 Wilkins St W",
    "sg:city":"Stillwater",
    "sg:classifiers":[
        {
            "category":"Professional",
            "subcategory":"Business Services",
            "type":"Services"
        }
    ],
    "sg:phone":"+1 651 430 8183",
    "sg:postcode":"55082",
    "sg:province":"MN",
    "wof:name":"Aerostar Enterprises",
    "wof:placetype":"venue"
},
  "geometry": {"coordinates":[-92.812828,45.064823],"type":"Point"}
}