{
  "type": "Feature",
  "properties": {
    "iso:country":"US",
    "sg:address":"7993 Labeaux Ave NE",
    "sg:city":"Albertville",
    "sg:classifiers":[
        {
            "category":"Farming",
            "subcategory":"Livestock Farm",
            "type":"Manufacturing & Wholesale Goods"
        }
    ],
    "sg:phone":"+1 763 497 3759",
    "sg:postcode":"55301",
    "sg:province":"MN",
    "sg:tags":[
        "beef",
        "corn",
        "crop",
        "field",
        "cattle",
        "feedlot"
    ],
    "wof:name":"Michael Bistodeau",
    "wof:placetype":"venue"
},
  "geometry": {"coordinates":[-93.663456,45.262403],"type":"Point"}
}