{
  "type": "Feature",
  "properties": {
    "addr:full":"12044 W River Rd Champlin MN 55316",
    "addr:housenumber":"12044",
    "addr:postcode":"55316",
    "addr:street":"W River Rd",
    "iso:country":"US",
    "sg:address":"12044 W River Rd",
    "sg:city":"Champlin",
    "sg:classifiers":[
        {
            "category":"Building & Trades",
            "subcategory":"Construction",
            "type":"Services"
        }
    ],
    "sg:phone":"+1 763 427 7348",
    "sg:postcode":"55316",
    "sg:province":"MN",
    "sg:tags":[
        "house"
    ],
    "wof:name":"Williams Painting & Cnstr",
    "wof:placetype":"venue"
},
  "geometry": {"coordinates":[-93.370209,45.173519],"type":"Point"}
}