{
  "type": "Feature",
  "properties": {
    "addr:full":"715 Florida Ave S Minneapolis MN 55426",
    "addr:housenumber":"715",
    "addr:postcode":"55426",
    "addr:street":"Florida Ave S",
    "iso:country":"US",
    "sg:address":"715 Florida Ave S",
    "sg:city":"Minneapolis",
    "sg:classifiers":[
        {
            "category":"Manufacturing",
            "subcategory":"Retail Goods",
            "type":"Manufacturing & Wholesale Goods"
        }
    ],
    "sg:phone":"+1 763 544 2356",
    "sg:postcode":"55426",
    "sg:province":"MN",
    "sg:tags":[
        "product",
        "mfg"
    ],
    "wof:name":"Project Group Inc",
    "wof:placetype":"venue"
},
  "geometry": {"coordinates":[-93.362796,44.974384],"type":"Point"}
}