{
  "type": "Feature",
  "properties": {
    "iso:country":"US",
    "sg:address":"941 Curry Trl",
    "sg:city":"Saint Paul",
    "sg:classifiers":[
        {
            "category":"Social Services",
            "subcategory":"Child Care",
            "type":"Services"
        }
    ],
    "sg:phone":"+1 651 688 7990",
    "sg:postcode":"55123",
    "sg:province":"MN",
    "sg:tags":[
        "daycare",
        "provider"
    ],
    "wof:name":"Lisa M Fry",
    "wof:placetype":"venue"
},
  "geometry": {"coordinates":[-93.134114,44.802312],"type":"Point"}
}