{
  "type": "Feature",
  "properties": {
    "iso:country":"US",
    "sg:address":"3585 124th Ave NW",
    "sg:city":"Minneapolis",
    "sg:classifiers":[
        {
            "category":"Banks & Credit Unions",
            "subcategory":"Bank",
            "type":"Services"
        }
    ],
    "sg:phone":"+1 763 422 4500",
    "sg:postcode":"55433",
    "sg:province":"MN",
    "wof:name":"Central Bank",
    "wof:placetype":"venue"
},
  "geometry": {"coordinates":[-93.35430100000001,45.196701],"type":"Point"}
}