{
  "type": "Feature",
  "properties": {
    "iso:country":"US",
    "sg:address":"1209 Wellington Cres",
    "sg:city":"Faribault",
    "sg:classifiers":[
        {
            "category":"Social Services",
            "subcategory":"Child Care",
            "type":"Services"
        }
    ],
    "sg:phone":"+1 507 332 2606",
    "sg:postcode":"55021",
    "sg:province":"MN",
    "sg:tags":[
        "day"
    ],
    "wof:name":"Tiny Stars Child Care",
    "wof:placetype":"venue"
},
  "geometry": {"coordinates":[-93.286272,44.276576],"type":"Point"}
}