{
  "type": "Feature",
  "properties": {
    "iso:country":"US",
    "sg:address":"800 E Main St",
    "sg:city":"Marshall",
    "sg:classifiers":[
        {
            "category":"Retail",
            "subcategory":"Auto Repair",
            "type":"Services"
        }
    ],
    "sg:phone":"+1 507 532 5761",
    "sg:postcode":"56258",
    "sg:province":"MN",
    "sg:tags":[
        "shop",
        "glass",
        "glazing",
        "replacement",
        "contractor"
    ],
    "wof:name":"Quality Glass and Mirror",
    "wof:placetype":"venue"
},
  "geometry": {"coordinates":[-95.777552,44.439028],"type":"Point"}
}