{
  "type": "Feature",
  "properties": {
    "iso:country":"US",
    "sg:address":"23 Fir St N",
    "sg:city":"Lester Prairie",
    "sg:classifiers":[
        {
            "category":"Retail",
            "subcategory":"Funeral Services",
            "type":"Services"
        }
    ],
    "sg:phone":"+1 320 395 2513",
    "sg:postcode":"55354",
    "sg:province":"MN",
    "sg:tags":[
        "director"
    ],
    "wof:name":"Paul-Mc Bride Funeral Home",
    "wof:placetype":"venue"
},
  "geometry": {"coordinates":[-94.044504,44.884837],"type":"Point"}
}