{
  "type": "Feature",
  "properties": {
    "iso:country":"US",
    "sg:address":"608 6th St S",
    "sg:city":"Breckenridge",
    "sg:classifiers":[
        {
            "category":"Social Services",
            "subcategory":"Child Care",
            "type":"Services"
        }
    ],
    "sg:phone":"+1 218 643 3132",
    "sg:postcode":"56520",
    "sg:province":"MN",
    "sg:tags":[
        "daycare",
        "provider"
    ],
    "wof:name":"Trupka Karie",
    "wof:placetype":"venue"
},
  "geometry": {"coordinates":[-96.586865,46.257416],"type":"Point"}
}