{
  "type": "Feature",
  "properties": {
    "addr:full":"2700 Manning Ave S St Paul MN 55129",
    "addr:housenumber":"2700",
    "addr:postcode":"55129",
    "addr:street":"Manning Ave S",
    "iso:country":"US",
    "sg:address":"2700 Manning Ave S",
    "sg:city":"St Paul",
    "sg:classifiers":[
        {
            "category":"Farming",
            "subcategory":"Livestock Farm",
            "type":"Manufacturing & Wholesale Goods"
        },
        {
            "category":"Retail",
            "subcategory":"Animal Services",
            "type":"Services"
        }
    ],
    "sg:phone":"+1 651 436 6557",
    "sg:postcode":"55129",
    "sg:province":"MN",
    "sg:tags":[
        "ranch"
    ],
    "wof:name":"Windy Ridge Ranch",
    "wof:placetype":"venue"
},
  "geometry": {"coordinates":[-92.862661,44.909703],"type":"Point"}
}