{
  "type": "Feature",
  "properties": {
    "addr:full":"1000 E 146th St Burnsville MN 55337",
    "addr:housenumber":"1000",
    "addr:postcode":"55337",
    "addr:street":"E 146Th St",
    "iso:country":"US",
    "sg:address":"1000 E 146th St",
    "sg:city":"Burnsville",
    "sg:classifiers":[
        {
            "category":"Shopping",
            "type":"Retail Goods"
        }
    ],
    "sg:phone":"+1 952 891 8533",
    "sg:postcode":"55337",
    "sg:province":"MN",
    "sg:tags":[
        "merchandise"
    ],
    "wof:name":"Kes Equipment",
    "wof:placetype":"venue"
},
  "geometry": {"coordinates":[-93.262097,44.74014],"type":"Point"}
}