{
  "type": "Feature",
  "properties": {
    "addr:full":"1101 9th St S Virginia MN 55792",
    "addr:housenumber":"1101",
    "addr:postcode":"55792",
    "addr:street":"9Th St S",
    "iso:country":"US",
    "sg:address":"1101 9th St S",
    "sg:city":"Virginia",
    "sg:classifiers":[
        {
            "category":"Shopping",
            "type":"Retail Goods"
        }
    ],
    "sg:phone":"+1 218 741 7833",
    "sg:postcode":"55792",
    "sg:province":"MN",
    "sg:tags":[
        "commercial",
        "design",
        "merchandise"
    ],
    "wof:name":"House of Mats Picture Framing",
    "wof:placetype":"venue"
},
  "geometry": {"coordinates":[-92.55171,47.515836],"type":"Point"}
}