{
  "type": "Feature",
  "properties": {
    "iso:country":"US",
    "sg:address":"907 W 50th St",
    "sg:city":"Minneapolis",
    "sg:classifiers":[
        {
            "category":"Retail",
            "subcategory":"Laundry & Dry Cleaning",
            "type":"Services"
        }
    ],
    "sg:phone":"+1 612 822 5121",
    "sg:postcode":"55419",
    "sg:province":"MN",
    "wof:name":"Anderson Cleaners",
    "wof:placetype":"venue"
},
  "geometry": {"coordinates":[-93.29090100000001,44.912399],"type":"Point"}
}