{
  "type": "Feature",
  "properties": {
    "iso:country":"US",
    "sg:address":"3406 Bemidji Ave N",
    "sg:city":"Bemidji",
    "sg:classifiers":[
        {
            "category":"Home & Garden",
            "subcategory":"Building Materials",
            "type":"Retail Goods"
        },
        {
            "category":"Home & Garden",
            "subcategory":"Furniture",
            "type":"Retail Goods"
        }
    ],
    "sg:phone":"+1 218 444 6224",
    "sg:postcode":"56601",
    "sg:province":"MN",
    "sg:tags":[
        "decorating",
        "cabinet",
        "supply"
    ],
    "wof:name":"Birchwood Color Center",
    "wof:placetype":"venue"
},
  "geometry": {"coordinates":[-94.878467,47.499494],"type":"Point"}
}