{
  "type": "Feature",
  "properties": {
    "addr:full":"5289 Lannon Ave NE Albertville MN 55301",
    "addr:housenumber":"5289",
    "addr:postcode":"55301",
    "addr:street":"Lannon Ave Ne",
    "iso:country":"US",
    "sg:address":"5289 Lannon Ave NE",
    "sg:city":"Albertville",
    "sg:classifiers":[
        {
            "category":"Personal",
            "subcategory":"Beauty Salon",
            "type":"Services"
        }
    ],
    "sg:phone":"+1 763 497 2844",
    "sg:postcode":"55301",
    "sg:province":"MN",
    "sg:tags":[
        "shop"
    ],
    "wof:name":"Sue's On Lannon",
    "wof:placetype":"venue"
},
  "geometry": {"coordinates":[-93.648195,45.229121],"type":"Point"}
}