{
  "type": "Feature",
  "properties": {
    "iso:country":"US",
    "sg:address":"5995 149th St W",
    "sg:city":"Saint Paul",
    "sg:classifiers":[
        {
            "category":"Manufacturing",
            "subcategory":"Printing",
            "type":"Manufacturing & Wholesale Goods"
        }
    ],
    "sg:phone":"+1 952 431 0883",
    "sg:postcode":"55124",
    "sg:province":"MN",
    "sg:tags":[
        "lithographic",
        "commercial"
    ],
    "wof:name":"Ross Printing Inc",
    "wof:placetype":"venue"
},
  "geometry": {"coordinates":[-93.18686700000001,44.733579],"type":"Point"}
}