{
  "type": "Feature",
  "properties": {
    "addr:full":"229 Chestnut St E Stillwater MN 55082",
    "addr:housenumber":"229",
    "addr:postcode":"55082",
    "addr:street":"Chestnut St E",
    "iso:country":"US",
    "sg:address":"229 Chestnut St E",
    "sg:city":"Stillwater",
    "sg:classifiers":[
        {
            "category":"Home & Garden",
            "subcategory":"Furniture",
            "type":"Retail Goods"
        }
    ],
    "sg:phone":"+1 651 351 2062",
    "sg:postcode":"55082",
    "sg:province":"MN",
    "wof:name":"Simply Uniques",
    "wof:placetype":"venue"
},
  "geometry": {"coordinates":[-92.80663800000001,45.055553],"type":"Point"}
}