{
  "type": "Feature",
  "properties": {
    "addr:full":"12091 Co Rd 100 Wadena MN 56482",
    "addr:housenumber":"12091",
    "addr:postcode":"56482",
    "addr:street":"Co Rd 100",
    "iso:country":"US",
    "sg:address":"12091 Co Rd 100",
    "sg:city":"Wadena",
    "sg:classifiers":[
        {
            "category":"Freight",
            "type":"Transportation"
        }
    ],
    "sg:phone":"+1 218 631 2105",
    "sg:postcode":"56482",
    "sg:province":"MN",
    "sg:tags":[
        "operator",
        "local",
        "trucking"
    ],
    "wof:name":"Myron Waln",
    "wof:placetype":"venue"
},
  "geometry": {"coordinates":[-95.1147,46.398419],"type":"Point"}
}