{
  "type": "Feature",
  "properties": {
    "iso:country":"US",
    "sg:address":"2740 Sycamore Ln N",
    "sg:city":"Minneapolis",
    "sg:classifiers":[
        {
            "category":"Professional",
            "subcategory":"Engineering",
            "type":"Services"
        }
    ],
    "sg:phone":"+1 763 553 0444",
    "sg:postcode":"55441",
    "sg:province":"MN",
    "wof:name":"Industrial Insite",
    "wof:placetype":"venue"
},
  "geometry": {"coordinates":[-93.444512,45.010366],"type":"Point"}
}