{
  "type": "Feature",
  "properties": {
    "addr:full":"1505 Yuma Ln N Minneapolis MN 55447",
    "addr:housenumber":"1505",
    "addr:postcode":"55447",
    "addr:street":"Yuma Ln N",
    "iso:country":"US",
    "sg:address":"1505 Yuma Ln N",
    "sg:city":"Minneapolis",
    "sg:classifiers":[
        {
            "category":"Organizations",
            "subcategory":"Community Association",
            "type":"Services"
        }
    ],
    "sg:phone":"+1 763 475 2725",
    "sg:postcode":"55447",
    "sg:province":"MN",
    "wof:name":"Home Owners Association",
    "wof:placetype":"venue"
},
  "geometry": {"coordinates":[-93.485349,44.996975],"type":"Point"}
}