{
  "type": "Feature",
  "properties": {
    "addr:full":"1100 13th St S Moorhead MN 56560",
    "addr:housenumber":"1100",
    "addr:postcode":"56560",
    "addr:street":"13Th St S",
    "iso:country":"US",
    "sg:address":"1100 13th St S",
    "sg:city":"Moorhead",
    "sg:classifiers":[
        {
            "category":"Social Services",
            "subcategory":"Child Care",
            "type":"Services"
        }
    ],
    "sg:phone":"+1 218 236 8470",
    "sg:postcode":"56560",
    "sg:province":"MN",
    "sg:tags":[
        "day"
    ],
    "wof:name":"Char M Andersen",
    "wof:placetype":"venue"
},
  "geometry": {"coordinates":[-96.75979100000001,46.862187],"type":"Point"}
}