{
  "type": "Feature",
  "properties": {
    "addr:full":"652 1st Ave Westbrook MN 56183",
    "addr:housenumber":"652",
    "addr:postcode":"56183",
    "addr:street":"1St Ave",
    "iso:country":"US",
    "sg:address":"652 1st Ave",
    "sg:city":"Westbrook",
    "sg:classifiers":[
        {
            "category":"Organizations",
            "subcategory":"Community Association",
            "type":"Services"
        }
    ],
    "sg:phone":"+1 507 274 5661",
    "sg:postcode":"56183",
    "sg:province":"MN",
    "sg:tags":[
        "military"
    ],
    "wof:name":"Veterans Of Foreign Wars",
    "wof:placetype":"venue"
},
  "geometry": {"coordinates":[-95.436097,44.042555],"type":"Point"}
}