{
  "type": "Feature",
  "properties": {
    "addr:full":"8349 90th St S Sabin MN 56580",
    "addr:housenumber":"8349",
    "addr:postcode":"56580",
    "addr:street":"90Th St S Sabin",
    "iso:country":"US",
    "sg:address":"8349 90th St S",
    "sg:city":"Sabin",
    "sg:classifiers":[
        {
            "category":"Home & Garden",
            "subcategory":"Furniture",
            "type":"Retail Goods"
        }
    ],
    "sg:phone":"+1 218 789 7700",
    "sg:postcode":"56580",
    "sg:province":"MN",
    "sg:tags":[
        "cabinet"
    ],
    "wof:name":"Rosenfeldt Fabrication",
    "wof:placetype":"venue"
},
  "geometry": {"coordinates":[-96.61058,46.770432],"type":"Point"}
}