{
  "type": "Feature",
  "properties": {
    "addr:full":"2731 Mackubin St Saint Paul MN 55113",
    "addr:housenumber":"2731",
    "addr:postcode":"55113",
    "addr:street":"Mackubin St",
    "iso:country":"US",
    "sg:address":"2731 Mackubin St",
    "sg:city":"Saint Paul",
    "sg:classifiers":[
        {
            "category":"Retail",
            "subcategory":"Laundry & Dry Cleaning",
            "type":"Services"
        }
    ],
    "sg:phone":"+1 651 487 0397",
    "sg:postcode":"55113",
    "sg:province":"MN",
    "wof:name":"Finson Carpet Cleaning",
    "wof:placetype":"venue"
},
  "geometry": {"coordinates":[-93.122394,45.022365],"type":"Point"}
}