{
  "type": "Feature",
  "properties": {
    "addr:full":"18167 Co Hwy 47 Battle Lake MN 56515",
    "addr:housenumber":"18167",
    "addr:postcode":"56515",
    "addr:street":"Co Hwy 47",
    "iso:country":"US",
    "sg:address":"18167 Co Hwy 47",
    "sg:city":"Battle Lake",
    "sg:classifiers":[
        {
            "category":"Farming",
            "subcategory":"Dairy Farm",
            "type":"Manufacturing & Wholesale Goods"
        }
    ],
    "sg:phone":"+1 218 864 8654",
    "sg:postcode":"56515",
    "sg:province":"MN",
    "wof:name":"Franze Dairy",
    "wof:placetype":"venue"
},
  "geometry": {"coordinates":[-95.7701,46.230959],"type":"Point"}
}