{
  "type": "Feature",
  "properties": {
    "addr:full":"1025 E King St Winona MN 55987",
    "addr:housenumber":"1025",
    "addr:postcode":"55987",
    "addr:street":"E King St",
    "iso:country":"US",
    "sg:address":"1025 E King St",
    "sg:city":"Winona",
    "sg:classifiers":[
        {
            "category":"Retail",
            "subcategory":"Repair Shop",
            "type":"Services"
        },
        {
            "category":"Professional",
            "subcategory":"Detective & Security Services",
            "type":"Services"
        }
    ],
    "sg:phone":"+1 507 453 0000",
    "sg:postcode":"55987",
    "sg:province":"MN",
    "sg:tags":[
        "skip",
        "tracing",
        "bail",
        "bond"
    ],
    "wof:name":"Liberty Bail Bonds",
    "wof:placetype":"venue"
},
  "geometry": {"coordinates":[-91.61393,44.039389],"type":"Point"}
}