{
  "type": "Feature",
  "properties": {
    "iso:country":"US",
    "sg:address":"440 Washington Ave",
    "sg:city":"Villard",
    "sg:classifiers":[
        {
            "category":"Banks & Credit Unions",
            "subcategory":"Bank",
            "type":"Services"
        }
    ],
    "sg:phone":"+1 320 554 3021",
    "sg:postcode":"56385",
    "sg:province":"MN",
    "sg:tags":[
        "state",
        "commercial",
        "mortgage"
    ],
    "wof:name":"Glenwood State Bank Inc",
    "wof:placetype":"venue"
},
  "geometry": {"coordinates":[-95.268998,45.712718],"type":"Point"}
}