{
  "type": "Feature",
  "properties": {
    "iso:country":"US",
    "sg:address":"403 N 1st St",
    "sg:city":"Montevideo",
    "sg:classifiers":[
        {
            "category":"Personal",
            "subcategory":"Beauty Salon",
            "type":"Services"
        }
    ],
    "sg:phone":"+1 320 269 2239",
    "sg:postcode":"56265",
    "sg:province":"MN",
    "wof:name":"It's About You",
    "wof:placetype":"venue"
},
  "geometry": {"coordinates":[-95.725279,44.94852],"type":"Point"}
}