{
  "type": "Feature",
  "properties": {
    "iso:country":"US",
    "sg:address":"1836 S Cedar Ave",
    "sg:city":"Owatonna",
    "sg:classifiers":[
        {
            "category":"Government",
            "subcategory":"Office",
            "type":"Public Place"
        }
    ],
    "sg:phone":"+1 507 444 2400",
    "sg:postcode":"55060",
    "sg:province":"MN",
    "sg:tags":[
        "state",
        "taxation"
    ],
    "wof:name":"Lottery Regional Office",
    "wof:placetype":"venue"
},
  "geometry": {"coordinates":[-93.226156,44.065745],"type":"Point"}
}