{
  "type": "Feature",
  "properties": {
    "iso:country":"US",
    "sg:address":"329 N Broad St",
    "sg:city":"Mankato",
    "sg:classifiers":[
        {
            "category":"Professional",
            "subcategory":"Computer Services",
            "type":"Services"
        },
        {
            "category":"Shopping",
            "subcategory":"Computers & Home Electronics",
            "type":"Retail Goods"
        }
    ],
    "sg:phone":"+1 507 625 5129",
    "sg:postcode":"56001",
    "sg:province":"MN",
    "sg:tags":[
        "prepackaged",
        "software"
    ],
    "wof:name":"Systems Design & Installation",
    "wof:placetype":"venue"
},
  "geometry": {"coordinates":[-93.99752599999999,44.168672],"type":"Point"}
}