{
  "type": "Feature",
  "properties": {
    "iso:country":"US",
    "sg:address":"301 Industrial Blvd",
    "sg:city":"Young America",
    "sg:classifiers":[
        {
            "category":"Wholesale",
            "subcategory":"Groceries",
            "type":"Manufacturing & Wholesale Goods"
        }
    ],
    "sg:phone":"+1 952 467 2668",
    "sg:postcode":"55387",
    "sg:province":"MN",
    "sg:tags":[
        "food",
        "product"
    ],
    "wof:name":"Tino's Division Of SSE Mfg",
    "wof:placetype":"venue"
},
  "geometry": {"coordinates":[-93.791417,44.837983],"type":"Point"}
}