{
  "type": "Feature",
  "properties": {
    "addr:full":"2600 Cobble Hill Dr Saint Paul MN 55125",
    "addr:housenumber":"2600",
    "addr:postcode":"55125",
    "addr:street":"Cobble Hill Dr",
    "iso:country":"US",
    "sg:address":"2600 Cobble Hill Dr",
    "sg:city":"Saint Paul",
    "sg:classifiers":[
        {
            "category":"Real Estate",
            "subcategory":"Real Estate Operator",
            "type":"Services"
        }
    ],
    "sg:phone":"+1 651 735 2230",
    "sg:postcode":"55125",
    "sg:province":"MN",
    "sg:tags":[
        "building",
        "apartment"
    ],
    "wof:name":"Cobble Hill Apartments",
    "wof:placetype":"venue"
},
  "geometry": {"coordinates":[-92.97235000000001,44.910989],"type":"Point"}
}