{
  "type": "Feature",
  "properties": {
    "addr:full":"12954 Zero Ave Plato MN 55370",
    "addr:postcode":"55370",
    "addr:street":"Ave",
    "iso:country":"US",
    "sg:address":"12954 Zero Ave",
    "sg:city":"Plato",
    "sg:classifiers":[
        {
            "category":"Building & Trades",
            "subcategory":"Electrical",
            "type":"Services"
        },
        {
            "category":"Manufacturing",
            "subcategory":"Tools & Machinery",
            "type":"Manufacturing & Wholesale Goods"
        }
    ],
    "sg:phone":"+1 320 238 2552",
    "sg:postcode":"55370",
    "sg:province":"MN",
    "sg:tags":[
        "industry",
        "mfg",
        "electric",
        "contractor"
    ],
    "wof:name":"Water Control Installations",
    "wof:placetype":"venue"
},
  "geometry": {"coordinates":[-94.020117,44.802879],"type":"Point"}
}