{
  "type": "Feature",
  "properties": {
    "addr:full":"21963 169th St Big Lake MN 55309",
    "addr:housenumber":"21963",
    "addr:postcode":"55309",
    "addr:street":"169Th St",
    "iso:country":"US",
    "sg:address":"21963 169th St",
    "sg:city":"Big Lake",
    "sg:classifiers":[
        {
            "category":"Shopping",
            "type":"Retail Goods"
        }
    ],
    "sg:phone":"+1 763 263 8052",
    "sg:postcode":"55309",
    "sg:province":"MN",
    "sg:tags":[
        "merchandise"
    ],
    "wof:name":"Precious Pets Personal Pet Svc",
    "wof:placetype":"venue"
},
  "geometry": {"coordinates":[-93.69811199999999,45.36881],"type":"Point"}
}