{
  "type": "Feature",
  "properties": {
    "iso:country":"US",
    "sg:address":"2939 Long Lake Rd",
    "sg:city":"Saint Paul",
    "sg:classifiers":[
        {
            "category":"Freight",
            "type":"Transportation"
        }
    ],
    "sg:phone":"+1 651 636 0918",
    "sg:postcode":"55113",
    "sg:province":"MN",
    "sg:tags":[
        "general"
    ],
    "wof:name":"Murphy Warehouse",
    "wof:placetype":"venue"
},
  "geometry": {"coordinates":[-93.19524699999999,45.034659],"type":"Point"}
}