{
  "type": "Feature",
  "properties": {
    "iso:country":"US",
    "sg:address":"6176 Olson Memorial Hwy",
    "sg:city":"Minneapolis",
    "sg:classifiers":[
        {
            "category":"Shopping",
            "subcategory":"Stationery & Office Supplies",
            "type":"Retail Goods"
        },
        {
            "category":"Professional",
            "subcategory":"Printing & Photocopies",
            "type":"Services"
        }
    ],
    "sg:phone":"+1 763 546 1844",
    "sg:postcode":"55422",
    "sg:province":"MN",
    "sg:tags":[
        "envelope",
        "services-commercial",
        "store",
        "lithographer"
    ],
    "wof:name":"Holographic Security Concepts, Inc.",
    "wof:placetype":"venue"
},
  "geometry": {"coordinates":[-93.36060500000001,44.98421],"type":"Point"}
}