{
  "type": "Feature",
  "properties": {
    "iso:country":"US",
    "sg:address":"11250 150th St",
    "sg:city":"Cologne",
    "sg:phone":"+1 952 466 2619",
    "sg:postcode":"55322",
    "sg:province":"MN",
    "sg:tags":[
        "farm",
        "corn"
    ],
    "wof:name":"Dale Karnitz",
    "wof:placetype":"venue"
},
  "geometry": {"coordinates":[-93.810439,44.731522],"type":"Point"}
}