{
  "type": "Feature",
  "properties": {
    "addr:full":"8 2nd St NE Aitkin MN 56431",
    "addr:housenumber":"8",
    "addr:postcode":"56431",
    "addr:street":"2Nd St Ne",
    "iso:country":"US",
    "sg:address":"8 2nd St NE",
    "sg:city":"Aitkin",
    "sg:classifiers":[
        {
            "category":"Insurance",
            "subcategory":"Hazard Insurance",
            "type":"Services"
        }
    ],
    "sg:phone":"+1 218 927 4868",
    "sg:postcode":"56431",
    "sg:province":"MN",
    "sg:tags":[
        "commercial",
        "business"
    ],
    "wof:name":"Collins Doug Gene Pagels",
    "wof:placetype":"venue"
},
  "geometry": {"coordinates":[-93.706519,46.533401],"type":"Point"}
}