{
  "type": "Feature",
  "properties": {
    "addr:full":"811 Mainstreet Hopkins MN 55343",
    "addr:housenumber":"811",
    "addr:postcode":"55343",
    "addr:street":"Mainstreet",
    "iso:country":"US",
    "sg:address":"811 Mainstreet",
    "sg:city":"Hopkins",
    "sg:classifiers":[
        {
            "category":"Restaurant",
            "type":"Food & Drink"
        }
    ],
    "sg:phone":"+1 952 935 9944",
    "sg:postcode":"55343",
    "sg:province":"MN",
    "wof:name":"Main Street Cafe",
    "wof:placetype":"venue"
},
  "geometry": {"coordinates":[-93.411345,44.924461],"type":"Point"}
}