{
  "type": "Feature",
  "properties": {
    "iso:country":"US",
    "sg:address":"1320 Winnebago Ave",
    "sg:city":"Fairmont",
    "sg:classifiers":[
        {
            "category":"Building & Trades",
            "subcategory":"Construction",
            "type":"Services"
        }
    ],
    "sg:phone":"+1 507 238 9927",
    "sg:postcode":"56031",
    "sg:province":"MN",
    "sg:tags":[
        "insulation",
        "heat",
        "contractor"
    ],
    "wof:name":"Indoor Technologies Inc",
    "wof:placetype":"venue"
},
  "geometry": {"coordinates":[-94.444166,43.666557],"type":"Point"}
}