{
  "type": "Feature",
  "properties": {
    "addr:full":"1201 Harmon Pl Minneapolis MN 55403",
    "addr:housenumber":"1201",
    "addr:postcode":"55403",
    "addr:street":"Harmon Pl",
    "iso:country":"US",
    "sg:address":"1201 Harmon Pl",
    "sg:city":"Minneapolis",
    "sg:classifiers":[
        {
            "category":"Professional",
            "subcategory":"Computer Services",
            "type":"Services"
        }
    ],
    "sg:phone":"+1 612 630 9100",
    "sg:postcode":"55403",
    "sg:province":"MN",
    "sg:tags":[
        "processing",
        "datum",
        "software"
    ],
    "wof:name":"Active Software",
    "wof:placetype":"venue"
},
  "geometry": {"coordinates":[-93.28093800000001,44.973265],"type":"Point"}
}