{
  "type": "Feature",
  "properties": {
    "iso:country":"US",
    "sg:address":"32336 40th Ave",
    "sg:city":"Cannon Falls",
    "sg:classifiers":[
        {
            "category":"Home & Garden",
            "subcategory":"Home Furnishings",
            "type":"Retail Goods"
        }
    ],
    "sg:phone":"+1 507 263 7410",
    "sg:postcode":"55009",
    "sg:province":"MN",
    "sg:tags":[
        "merchandise",
        "drug"
    ],
    "wof:name":"Frog Creek Pottery",
    "wof:placetype":"venue"
},
  "geometry": {"coordinates":[-92.959166,44.484222],"type":"Point"}
}