{
  "type": "Feature",
  "properties": {
    "iso:country":"US",
    "sg:address":"2077 Ellis Ave",
    "sg:city":"St Paul",
    "sg:classifiers":[
        {
            "category":"Freight",
            "type":"Transportation"
        }
    ],
    "sg:phone":"+1 651 644 5888",
    "sg:postcode":"55114",
    "sg:province":"MN",
    "sg:tags":[
        "distance",
        "storage",
        "long",
        "trucking",
        "mover",
        "local"
    ],
    "wof:name":"Hirte Transfer & Storage Inc",
    "wof:placetype":"venue"
},
  "geometry": {"coordinates":[-93.188379,44.966188],"type":"Point"}
}