{
  "type": "Feature",
  "properties": {
    "iso:country":"US",
    "sg:address":"40091 Co Rd 1",
    "sg:city":"Rice",
    "sg:classifiers":[
        {
            "category":"Manufacturing",
            "subcategory":"Tools & Machinery",
            "type":"Manufacturing & Wholesale Goods"
        }
    ],
    "sg:phone":"+1 320 654 8352",
    "sg:postcode":"56367",
    "sg:province":"MN",
    "sg:tags":[
        "machine",
        "shop"
    ],
    "wof:name":"Nett Work Mfg",
    "wof:placetype":"venue"
},
  "geometry": {"coordinates":[-94.22335,45.70574],"type":"Point"}
}