{
  "type": "Feature",
  "properties": {
    "iso:country":"US",
    "sg:address":"320 S 6th St",
    "sg:city":"Brainerd",
    "sg:classifiers":[
        {
            "category":"Banks & Credit Unions",
            "subcategory":"Bank",
            "type":"Services"
        },
        {
            "category":"Banks & Credit Unions",
            "subcategory":"Financial Services",
            "type":"Services"
        }
    ],
    "sg:phone":"+1 800 872 2657",
    "sg:postcode":"56401",
    "sg:province":"MN",
    "sg:tags":[
        "saving",
        "commercial"
    ],
    "sg:website":"http://usbank.com",
    "wof:name":"U.S. Bank ATM",
    "wof:placetype":"venue"
},
  "geometry": {"coordinates":[-94.20069100000001,46.355099],"type":"Point"}
}