{
  "type": "Feature",
  "properties": {
    "iso:country":"US",
    "sg:address":"619 Beltrami Ave NW",
    "sg:city":"Bemidji",
    "sg:classifiers":[
        {
            "category":"Government",
            "subcategory":"Office",
            "type":"Public Place"
        }
    ],
    "sg:phone":"+1 218 333 4109",
    "sg:postcode":"56601",
    "sg:province":"MN",
    "wof:name":"Beltrami County Adm",
    "wof:placetype":"venue"
},
  "geometry": {"coordinates":[-94.881288,47.474508],"type":"Point"}
}