{
  "type": "Feature",
  "properties": {
    "addr:full":"4410 Lincoln Ln NW Rochester MN 55901",
    "addr:housenumber":"4410",
    "addr:postcode":"55901",
    "addr:street":"Lincoln Ln Nw",
    "iso:country":"US",
    "sg:address":"4410 Lincoln Ln NW",
    "sg:city":"Rochester",
    "sg:phone":"+1 507 280 9742",
    "sg:postcode":"55901",
    "sg:province":"MN",
    "sg:tags":[
        "farm",
        "corn",
        "soybean"
    ],
    "wof:name":"Christy Olsen",
    "wof:placetype":"venue"
},
  "geometry": {"coordinates":[-92.51161500000001,44.069492],"type":"Point"}
}