{
  "type": "Feature",
  "properties": {
    "addr:full":"8040 Old Cedar Ave S Bloomington MN 55425",
    "addr:housenumber":"8040",
    "addr:postcode":"55425",
    "addr:street":"Old Cedar Ave S",
    "iso:country":"US",
    "sg:address":"8040 Old Cedar Ave S",
    "sg:city":"Bloomington",
    "sg:classifiers":[
        {
            "category":"Organizations",
            "subcategory":"Religious Organization",
            "type":"Services"
        }
    ],
    "sg:phone":"+1 952 250 0085",
    "sg:postcode":"55425",
    "sg:province":"MN",
    "sg:tags":[
        "christian",
        "ministry"
    ],
    "wof:name":"Emmanuel Inc",
    "wof:placetype":"venue"
},
  "geometry": {"coordinates":[-93.247992,44.857323],"type":"Point"}
}