{
  "type": "Feature",
  "properties": {
    "iso:country":"US",
    "sg:address":"8902 Wentworth Ave S",
    "sg:city":"Minneapolis",
    "sg:classifiers":[
        {
            "category":"Professional",
            "subcategory":"Accounting & Tax Preparation",
            "type":"Services"
        }
    ],
    "sg:phone":"+1 952 884 4545",
    "sg:postcode":"55420",
    "sg:province":"MN",
    "wof:name":"Krueger Bookkeeping Services",
    "wof:placetype":"venue"
},
  "geometry": {"coordinates":[-93.281035,44.843362],"type":"Point"}
}