{
  "type": "Feature",
  "properties": {
    "addr:full":"122 Rose St Saint Paul MN 55115",
    "addr:housenumber":"122",
    "addr:postcode":"55115",
    "addr:street":"Rose St",
    "iso:country":"US",
    "sg:address":"122 Rose St",
    "sg:city":"Saint Paul",
    "sg:classifiers":[
        {
            "category":"Shopping",
            "subcategory":"Crafts & Fabrics",
            "type":"Retail Goods"
        }
    ],
    "sg:phone":"+1 651 426 7865",
    "sg:postcode":"55115",
    "sg:province":"MN",
    "sg:tags":[
        "sewing"
    ],
    "wof:name":"W B Woolies",
    "wof:placetype":"venue"
},
  "geometry": {"coordinates":[-92.95942700000001,45.076273],"type":"Point"}
}