{
  "type": "Feature",
  "properties": {
    "addr:full":"14901 State Hwy 27 E Osakis MN 56360",
    "addr:housenumber":"14901",
    "addr:postcode":"56360",
    "addr:street":"State Hwy 27 E",
    "iso:country":"US",
    "sg:address":"14901 State Hwy 27 E",
    "sg:city":"Osakis",
    "sg:classifiers":[
        {
            "category":"Farming",
            "subcategory":"Dairy Farm",
            "type":"Manufacturing & Wholesale Goods"
        }
    ],
    "sg:phone":"+1 320 859 4804",
    "sg:postcode":"56360",
    "sg:province":"MN",
    "wof:name":"Lake View Farms",
    "wof:placetype":"venue"
},
  "geometry": {"coordinates":[-95.17486,45.867505],"type":"Point"}
}