{
  "type": "Feature",
  "properties": {
    "addr:full":"517 4th St Internatl Falls MN 56649",
    "addr:housenumber":"517",
    "addr:postcode":"56649",
    "addr:street":"4Th St Internatl",
    "iso:country":"US",
    "sg:address":"517 4th St",
    "sg:city":"Internatl Falls",
    "sg:classifiers":[
        {
            "category":"Retail",
            "subcategory":"Funeral Services",
            "type":"Services"
        }
    ],
    "sg:phone":"+1 218 283 2588",
    "sg:postcode":"56649",
    "sg:province":"MN",
    "sg:tags":[
        "director"
    ],
    "wof:name":"Green-Larsen Mortuary Inc",
    "wof:placetype":"venue"
},
  "geometry": {"coordinates":[-93.406826,48.601604],"type":"Point"}
}