{
  "type": "Feature",
  "properties": {
    "addr:full":"105 W Blue Earth Ave Fairmont MN 56031",
    "addr:housenumber":"105",
    "addr:postcode":"56031",
    "addr:street":"W Blue Earth Ave",
    "iso:country":"US",
    "sg:address":"105 W Blue Earth Ave",
    "sg:city":"Fairmont",
    "sg:classifiers":[
        {
            "category":"Shopping",
            "type":"Retail Goods"
        }
    ],
    "sg:phone":"+1 507 238 2390",
    "sg:postcode":"56031",
    "sg:province":"MN",
    "sg:tags":[
        "hearing",
        "equipment",
        "supply",
        "impaired"
    ],
    "wof:name":"Miracle-Ear",
    "wof:placetype":"venue"
},
  "geometry": {"coordinates":[-94.46364800000001,43.65222],"type":"Point"}
}