{
  "type": "Feature",
  "properties": {
    "addr:full":"857 US Hwy 12 Ortonville MN 56278",
    "addr:housenumber":"857",
    "addr:postcode":"56278",
    "addr:street":"Us Hwy 12",
    "iso:country":"US",
    "sg:address":"857 US Hwy 12",
    "sg:city":"Ortonville",
    "sg:classifiers":[
        {
            "category":"Cinema",
            "subcategory":"Movie Rental",
            "type":"Entertainment"
        }
    ],
    "sg:phone":"+1 320 839 2957",
    "sg:postcode":"56278",
    "sg:province":"MN",
    "sg:tags":[
        "leasing",
        "video",
        "disc",
        "tape"
    ],
    "wof:name":"Hilltop Video",
    "wof:placetype":"venue"
},
  "geometry": {"coordinates":[-96.440151,45.299028],"type":"Point"}
}