{
  "type": "Feature",
  "properties": {
    "addr:full":"1209 Greeley Ave N Glencoe MN 55336",
    "addr:housenumber":"1209",
    "addr:postcode":"55336",
    "addr:street":"Greeley Ave N",
    "iso:country":"US",
    "sg:address":"1209 Greeley Ave N",
    "sg:city":"Glencoe",
    "sg:classifiers":[
        {
            "category":"Shopping",
            "type":"Retail Goods"
        }
    ],
    "sg:phone":"+1 320 864 6630",
    "sg:postcode":"55336",
    "sg:province":"MN",
    "sg:tags":[
        "equipment",
        "care",
        "health",
        "home"
    ],
    "wof:name":"LMI Home Medical Equipment",
    "wof:placetype":"venue"
},
  "geometry": {"coordinates":[-94.153211,44.771955],"type":"Point"}
}