{
  "type": "Feature",
  "properties": {
    "addr:full":"3582 Clementa Ave SW Waverly MN 55390",
    "addr:postcode":"3582;55390",
    "addr:street":"Clementa Ave Sw",
    "iso:country":"US",
    "sg:address":"3582 Clementa Ave SW",
    "sg:city":"Waverly",
    "sg:classifiers":[
        {
            "category":"Building & Trades",
            "subcategory":"Construction",
            "type":"Services"
        }
    ],
    "sg:phone":"+1 763 658 4469",
    "sg:postcode":"55390",
    "sg:province":"MN",
    "sg:tags":[
        "contractor"
    ],
    "wof:name":"Bowman & Sons Construction",
    "wof:placetype":"venue"
},
  "geometry": {"coordinates":[-93.931181,45.100326],"type":"Point"}
}