{
  "type": "Feature",
  "properties": {
    "addr:full":"3508 E Lake St Minneapolis MN 55406",
    "addr:housenumber":"3508",
    "addr:postcode":"55406",
    "addr:street":"E Lake St",
    "iso:country":"US",
    "sg:address":"3508 E Lake St",
    "sg:city":"Minneapolis",
    "sg:classifiers":[
        {
            "category":"Restaurant",
            "type":"Food & Drink"
        }
    ],
    "sg:phone":"+1 612 729 8820",
    "sg:postcode":"55406",
    "sg:province":"MN",
    "sg:tags":[
        "new",
        "american"
    ],
    "wof:name":"Italianni's",
    "wof:placetype":"venue"
},
  "geometry": {"coordinates":[-93.221536,44.948498],"type":"Point"}
}