{
  "type": "Feature",
  "properties": {
    "addr:full":"510 Broadway St E New Germany MN 55367",
    "addr:housenumber":"510",
    "addr:postcode":"55367",
    "addr:street":"Broadway St E",
    "iso:country":"US",
    "sg:address":"510 Broadway St E",
    "sg:city":"New Germany",
    "sg:classifiers":[
        {
            "category":"Organizations",
            "subcategory":"Religious Organization",
            "type":"Services"
        }
    ],
    "sg:phone":"+1 952 353 2578",
    "sg:postcode":"55367",
    "sg:province":"MN",
    "sg:tags":[
        "church"
    ],
    "wof:name":"St Marks Lutheran Church",
    "wof:placetype":"venue"
},
  "geometry": {"coordinates":[-93.96146299999999,44.884436],"type":"Point"}
}