{
  "type": "Feature",
  "properties": {
    "iso:country":"US",
    "sg:address":"325 Oak St",
    "sg:city":"Farmington",
    "sg:classifiers":[
        {
            "category":"Recreation",
            "type":"Entertainment"
        }
    ],
    "sg:phone":"+1 651 463 1853",
    "sg:postcode":"55024",
    "sg:province":"MN",
    "sg:tags":[
        "parks"
    ],
    "wof:name":"Farmington Park Maintenance",
    "wof:placetype":"venue"
},
  "geometry": {"coordinates":[-93.144263,44.639253],"type":"Point"}
}