{
  "type": "Feature",
  "properties": {
    "iso:country":"US",
    "sg:address":"175 Co Rd 26",
    "sg:city":"Windom",
    "sg:classifiers":[
        {
            "category":"Government",
            "subcategory":"Office",
            "type":"Public Place"
        }
    ],
    "sg:phone":"+1 507 831 2900",
    "sg:postcode":"56101",
    "sg:province":"MN",
    "sg:tags":[
        "state"
    ],
    "wof:name":"Minnesota Natural Resources",
    "wof:placetype":"venue"
},
  "geometry": {"coordinates":[-95.101855,43.859029],"type":"Point"}
}