{
  "type": "Feature",
  "properties": {
    "addr:full":"521 Main St Onamia MN 56359",
    "addr:housenumber":"521",
    "addr:postcode":"56359",
    "addr:street":"Main St",
    "iso:country":"US",
    "sg:address":"521 Main St",
    "sg:city":"Onamia",
    "sg:classifiers":[
        {
            "category":"Restaurant",
            "type":"Food & Drink"
        }
    ],
    "sg:phone":"+1 320 532 3168",
    "sg:postcode":"56359",
    "sg:province":"MN",
    "wof:name":"Pizza Plus",
    "wof:placetype":"venue"
},
  "geometry": {"coordinates":[-93.66745899999999,46.070697],"type":"Point"}
}