{
  "type": "Feature",
  "properties": {
    "addr:full":"4281 State 210 SW Pillager MN 56473",
    "addr:housenumber":"4281;210",
    "addr:postcode":"56473",
    "addr:street":"State;Sw",
    "iso:country":"US",
    "sg:address":"4281 State 210 SW",
    "sg:city":"Pillager",
    "sg:classifiers":[
        {
            "category":"Autos & Motor Vehicles",
            "subcategory":"Automobile Sales",
            "type":"Retail Goods"
        }
    ],
    "sg:phone":"+1 218 746 4299",
    "sg:postcode":"56473",
    "sg:province":"MN",
    "sg:tags":[
        "car",
        "dealer"
    ],
    "wof:name":"S D Auto Sales",
    "wof:placetype":"venue"
},
  "geometry": {"coordinates":[-94.504862,46.340135],"type":"Point"}
}