{
  "type": "Feature",
  "properties": {
    "addr:full":"28316 141st Ave New Prague MN 56071",
    "addr:housenumber":"28316",
    "addr:postcode":"56071",
    "addr:street":"141St Ave",
    "iso:country":"US",
    "sg:address":"28316 141st Ave",
    "sg:city":"New Prague",
    "sg:classifiers":[
        {
            "category":"Farming",
            "subcategory":"Livestock Farm",
            "type":"Manufacturing & Wholesale Goods"
        }
    ],
    "sg:phone":"+1 952 758 2944",
    "sg:postcode":"56071",
    "sg:province":"MN",
    "sg:tags":[
        "animal",
        "general"
    ],
    "wof:name":"Dave Simon",
    "wof:placetype":"venue"
},
  "geometry": {"coordinates":[-93.54463199999999,44.539338],"type":"Point"}
}