{
  "type": "Feature",
  "properties": {
    "addr:full":"38688 296 Ave Waubun MN 56589",
    "addr:housenumber":"38688",
    "addr:postcode":"56589",
    "addr:street":"296 Ave",
    "iso:country":"US",
    "sg:address":"38688 296 Ave",
    "sg:city":"Waubun",
    "sg:classifiers":[
        {
            "category":"Professional",
            "type":"Services"
        }
    ],
    "sg:phone":"+1 218 473 3211",
    "sg:postcode":"56589",
    "sg:province":"MN",
    "sg:tags":[
        "establishment"
    ],
    "wof:name":"Worner & Worner",
    "wof:placetype":"venue"
},
  "geometry": {"coordinates":[-95.77303999999999,47.128841],"type":"Point"}
}