{
  "type": "Feature",
  "properties": {
    "addr:full":"15040 Garnet St NW Anoka MN 55303",
    "addr:housenumber":"15040",
    "addr:postcode":"55303",
    "addr:street":"Garnet St Nw",
    "iso:country":"US",
    "sg:address":"15040 Garnet St NW",
    "sg:city":"Anoka",
    "sg:classifiers":[
        {
            "category":"Building & Trades",
            "subcategory":"Construction",
            "type":"Services"
        }
    ],
    "sg:phone":"+1 763 427 1559",
    "sg:postcode":"55303",
    "sg:province":"MN",
    "sg:tags":[
        "concrete",
        "masonry",
        "contractor"
    ],
    "wof:name":"Craftsman Concrete & Masonry",
    "wof:placetype":"venue"
},
  "geometry": {"coordinates":[-93.44060500000001,45.243854],"type":"Point"}
}