{
  "type": "Feature",
  "properties": {
    "iso:country":"US",
    "sg:address":"901 Central Ave",
    "sg:city":"Buffalo",
    "sg:classifiers":[
        {
            "category":"Building & Trades",
            "subcategory":"Construction",
            "type":"Services"
        }
    ],
    "sg:phone":"+1 763 682 4441",
    "sg:postcode":"55313",
    "sg:province":"MN",
    "sg:tags":[
        "contracting",
        "material"
    ],
    "sg:website":"www.wrightlumber.com",
    "wof:name":"Wright Lumber & Millwork Inc",
    "wof:placetype":"venue"
},
  "geometry": {"coordinates":[-93.876265,45.180133],"type":"Point"}
}