{
  "type": "Feature",
  "properties": {
    "addr:full":"2550 N Broadway Rochester MN 55906",
    "addr:housenumber":"2550",
    "addr:postcode":"55906",
    "addr:street":"N Broadway",
    "iso:country":"US",
    "sg:address":"2550 N Broadway",
    "sg:city":"Rochester",
    "sg:classifiers":[
        {
            "category":"Autos & Motor Vehicles",
            "subcategory":"Automobile Sales",
            "type":"Retail Goods"
        }
    ],
    "sg:phone":"+1 507 529 3633",
    "sg:postcode":"55906",
    "sg:province":"MN",
    "sg:tags":[
        "classic"
    ],
    "wof:name":"Braatens Auto Ctr",
    "wof:placetype":"venue"
},
  "geometry": {"coordinates":[-92.455414,44.051081],"type":"Point"}
}