{
  "type": "Feature",
  "properties": {
    "addr:full":"11922 302nd Ave NW Princeton MN 55371",
    "addr:housenumber":"11922",
    "addr:postcode":"55371",
    "addr:street":"302Nd Ave Nw",
    "iso:country":"US",
    "sg:address":"11922 302nd Ave NW",
    "sg:city":"Princeton",
    "sg:classifiers":[
        {
            "category":"Home & Garden",
            "subcategory":"Building Materials",
            "type":"Retail Goods"
        }
    ],
    "sg:phone":"+1 763 633 8677",
    "sg:postcode":"55371",
    "sg:province":"MN",
    "wof:name":"Countertop Solutions",
    "wof:placetype":"venue"
},
  "geometry": {"coordinates":[-93.575478,45.517909],"type":"Point"}
}