{
  "type": "Feature",
  "properties": {
    "addr:full":"22 Wilson Ave SE Saint Cloud MN 56304",
    "addr:housenumber":"22",
    "addr:postcode":"56304",
    "addr:street":"Wilson Ave Se",
    "iso:country":"US",
    "sg:address":"22 Wilson Ave SE",
    "sg:city":"Saint Cloud",
    "sg:classifiers":[
        {
            "category":"Shopping",
            "subcategory":"Florist",
            "type":"Retail Goods"
        }
    ],
    "sg:phone":"+1 320 253 2298",
    "sg:postcode":"56304",
    "sg:province":"MN",
    "wof:name":"All Occssion Floral Basket Btq",
    "wof:placetype":"venue"
},
  "geometry": {"coordinates":[-94.150576,45.564647],"type":"Point"}
}