{
  "type": "Feature",
  "properties": {
    "iso:country":"US",
    "sg:address":"17159 Highway 65 NE Suite A",
    "sg:city":"Andover",
    "sg:classifiers":[
        {
            "category":"Autos & Motor Vehicles",
            "subcategory":"Auto Supplies",
            "type":"Retail Goods"
        },
        {
            "category":"Retail",
            "subcategory":"Auto Repair",
            "type":"Services"
        }
    ],
    "sg:phone":"+1 763 355 5120",
    "sg:postcode":"55304",
    "sg:province":"MN",
    "sg:tags":[
        "engine",
        "exhaust",
        "installation",
        "exchange",
        "transmission",
        "automobile",
        "body",
        "system",
        "truck",
        "muffler",
        "brake",
        "rebuilding",
        "painting",
        "repairing"
    ],
    "sg:website":"http://www.midtownservicecentermn.com",
    "wof:name":"Midtown Service Center",
    "wof:placetype":"venue"
},
  "geometry": {"coordinates":[-93.235516,45.26978],"type":"Point"}
}