{
  "type": "Feature",
  "properties": {
    "addr:full":"212 Park St W South Saint Paul MN 55075",
    "addr:housenumber":"212",
    "addr:postcode":"55075",
    "addr:street":"Park St W South Saint Paul",
    "iso:country":"US",
    "sg:address":"212 Park St W",
    "sg:city":"South Saint Paul",
    "sg:classifiers":[
        {
            "category":"Social Services",
            "subcategory":"Child Care",
            "type":"Services"
        }
    ],
    "sg:phone":"+1 651 451 1281",
    "sg:postcode":"55075",
    "sg:province":"MN",
    "sg:tags":[
        "day"
    ],
    "wof:name":"Cheryl L McKay",
    "wof:placetype":"venue"
},
  "geometry": {"coordinates":[-93.039666,44.875503],"type":"Point"}
}