{
  "type": "Feature",
  "properties": {
    "addr:full":"12800 Industrial Park Blvd Minneapolis MN 55441",
    "addr:housenumber":"12800",
    "addr:postcode":"55441",
    "addr:street":"Industrial Park Blvd",
    "iso:country":"US",
    "sg:address":"12800 Industrial Park Blvd",
    "sg:city":"Minneapolis",
    "sg:classifiers":[
        {
            "category":"Health Services",
            "subcategory":"Clinic",
            "type":"Services"
        }
    ],
    "sg:phone":"+1 763 557 1126",
    "sg:postcode":"55441",
    "sg:province":"MN",
    "sg:tags":[
        "home",
        "care"
    ],
    "wof:name":"Petersen Home Health Care",
    "wof:placetype":"venue"
},
  "geometry": {"coordinates":[-93.44817399999999,45.002513],"type":"Point"}
}