{
  "type": "Feature",
  "properties": {
    "addr:full":"1869 Mahogany St Mora MN 55051",
    "addr:housenumber":"1869",
    "addr:postcode":"55051",
    "addr:street":"Mahogany St",
    "iso:country":"US",
    "sg:address":"1869 Mahogany St",
    "sg:city":"Mora",
    "sg:phone":"+1 320 679 3750",
    "sg:postcode":"55051",
    "sg:province":"MN",
    "sg:tags":[
        "farm",
        "corn",
        "grain",
        "cash"
    ],
    "wof:name":"Steven Strelow",
    "wof:placetype":"venue"
},
  "geometry": {"coordinates":[-93.26624,45.844612],"type":"Point"}
}