{
  "type": "Feature",
  "properties": {
    "addr:full":"800 S Cleveland Ave Saint Paul MN 55116",
    "addr:housenumber":"800",
    "addr:postcode":"55116",
    "addr:street":"S Cleveland Ave",
    "iso:country":"US",
    "sg:address":"800 S Cleveland Ave",
    "sg:city":"Saint Paul",
    "sg:classifiers":[
        {
            "category":"Bars & Pubs",
            "type":"Food & Drink"
        },
        {
            "category":"Restaurant",
            "type":"Food & Drink"
        },
        {
            "category":"Bars & Pubs",
            "subcategory":"Lounge",
            "type":"Food & Drink"
        }
    ],
    "sg:phone":"+1 651 699 1154",
    "sg:postcode":"55116",
    "sg:province":"MN",
    "sg:tags":[
        "traditional",
        "american",
        "karaoke"
    ],
    "sg:website":"www.chatterboxpub.net",
    "wof:name":"Chatterbox Pub",
    "wof:placetype":"venue"
},
  "geometry": {"coordinates":[-93.18732,44.917698],"type":"Point"}
}