{
  "type": "Feature",
  "properties": {
    "addr:full":"901 Washington Ave SE Minneapolis MN 55414",
    "addr:housenumber":"901",
    "addr:postcode":"55414",
    "addr:street":"Washington Ave Se",
    "iso:country":"US",
    "sg:address":"901 Washington Ave SE",
    "sg:city":"Minneapolis",
    "sg:classifiers":[
        {
            "category":"Structure",
            "subcategory":"Office Building",
            "type":"Public Place"
        }
    ],
    "sg:phone":"+1 612 331 3898",
    "sg:postcode":"55414",
    "sg:province":"MN",
    "sg:tags":[
        "park"
    ],
    "wof:name":"Bennett Medich Properties",
    "wof:placetype":"venue"
},
  "geometry": {"coordinates":[-93.225647,44.97361],"type":"Point"}
}