{
  "type": "Feature",
  "properties": {
    "iso:country":"US",
    "sg:address":"10155 Greenbrier Rd",
    "sg:city":"Minnetonka",
    "sg:classifiers":[
        {
            "category":"Building & Trades",
            "subcategory":"Landscaping Services",
            "type":"Services"
        }
    ],
    "sg:phone":"+1 952 938 6060",
    "sg:postcode":"55305",
    "sg:province":"MN",
    "sg:tags":[
        "landscape",
        "contractor"
    ],
    "wof:name":"Quatrozona Landscape Group",
    "wof:placetype":"venue"
},
  "geometry": {"coordinates":[-93.410993,44.953256],"type":"Point"}
}