{
  "type": "Feature",
  "properties": {
    "iso:country":"US",
    "sg:address":"16630 Jaguar Ave",
    "sg:city":"Lakeville",
    "sg:classifiers":[
        {
            "category":"Building & Trades",
            "subcategory":"Construction",
            "type":"Services"
        }
    ],
    "sg:phone":"+1 952 435 5424",
    "sg:postcode":"55044",
    "sg:province":"MN",
    "sg:tags":[
        "general"
    ],
    "wof:name":"Steve Dahl Construction Inc",
    "wof:placetype":"venue"
},
  "geometry": {"coordinates":[-93.271154,44.709081],"type":"Point"}
}