{
  "type": "Feature",
  "properties": {
    "addr:full":"8500 127th St E Hastings MN 55033",
    "addr:housenumber":"8500",
    "addr:postcode":"55033",
    "addr:street":"127Th St E",
    "iso:country":"US",
    "sg:address":"8500 127th St E",
    "sg:city":"Hastings",
    "sg:classifiers":[
        {
            "category":"Government",
            "subcategory":"Office",
            "type":"Public Place"
        }
    ],
    "sg:phone":"+1 651 438 4660",
    "sg:postcode":"55033",
    "sg:province":"MN",
    "sg:tags":[
        "combined"
    ],
    "wof:name":"Dakota County Park Department",
    "wof:placetype":"venue"
},
  "geometry": {"coordinates":[-92.924318,44.763656],"type":"Point"}
}