{
  "type": "Feature",
  "properties": {
    "iso:country":"US",
    "sg:address":"18 1st Ave S",
    "sg:city":"Buffalo",
    "sg:classifiers":[
        {
            "category":"Shopping",
            "subcategory":"Gifts & Souvenirs",
            "type":"Retail Goods"
        }
    ],
    "sg:phone":"+1 763 682 5798",
    "sg:postcode":"55313",
    "sg:province":"MN",
    "wof:name":"Renaissance West",
    "wof:placetype":"venue"
},
  "geometry": {"coordinates":[-93.874735,45.171862],"type":"Point"}
}