{
  "type": "Feature",
  "properties": {
    "addr:full":"1380 Energy Ln Saint Paul MN 55108",
    "addr:housenumber":"1380",
    "addr:postcode":"55108",
    "addr:street":"Energy Ln",
    "iso:country":"US",
    "sg:address":"1380 Energy Ln",
    "sg:city":"Saint Paul",
    "sg:classifiers":[
        {
            "category":"Government",
            "subcategory":"Office",
            "type":"Public Place"
        }
    ],
    "sg:phone":"+1 651 603 8108",
    "sg:postcode":"55108",
    "sg:province":"MN",
    "sg:tags":[
        "agricultural",
        "regulation",
        "marketing"
    ],
    "wof:name":"Auri AG Innovations",
    "wof:placetype":"venue"
},
  "geometry": {"coordinates":[-93.15860000000001,44.970426],"type":"Point"}
}