{
  "type": "Feature",
  "properties": {
    "iso:country":"US",
    "sg:address":"22545 York Rd",
    "sg:city":"Hutchinson",
    "sg:classifiers":[
        {
            "category":"Farming",
            "subcategory":"Dairy Farm",
            "type":"Manufacturing & Wholesale Goods"
        }
    ],
    "sg:phone":"+1 320 587 9154",
    "sg:postcode":"55350",
    "sg:province":"MN",
    "wof:name":"Mark Theuringer",
    "wof:placetype":"venue"
},
  "geometry": {"coordinates":[-94.44896199999999,44.856195],"type":"Point"}
}