{
  "type": "Feature",
  "properties": {
    "iso:country":"US",
    "sg:address":"6150 Hemlock Ln N",
    "sg:city":"Minneapolis",
    "sg:classifiers":[
        {
            "category":"Building & Trades",
            "subcategory":"Construction",
            "type":"Services"
        }
    ],
    "sg:phone":"+1 763 559 0085",
    "sg:postcode":"55442",
    "sg:province":"MN",
    "sg:tags":[
        "land",
        "family",
        "subdivide",
        "general",
        "home",
        "contractor"
    ],
    "wof:name":"Lowry Hill Construction Co",
    "wof:placetype":"venue"
},
  "geometry": {"coordinates":[-93.430932,45.065559],"type":"Point"}
}