{
  "type": "Feature",
  "properties": {
    "addr:full":"11151 Douglas Dr N Champlin MN 55316",
    "addr:housenumber":"11151",
    "addr:postcode":"55316",
    "addr:street":"Douglas Dr N",
    "iso:country":"US",
    "sg:address":"11151 Douglas Dr N",
    "sg:city":"Champlin",
    "sg:classifiers":[
        {
            "category":"Food & Beverages",
            "subcategory":"Groceries & Convenience Stores",
            "type":"Retail Goods"
        }
    ],
    "sg:phone":"+1 763 425 4898",
    "sg:postcode":"55316",
    "sg:province":"MN",
    "wof:name":"Douglas Food & Gas",
    "wof:placetype":"venue"
},
  "geometry": {"coordinates":[-93.360716,45.15847],"type":"Point"}
}