{
  "type": "Feature",
  "properties": {
    "addr:full":"105 Hensonshire Ct Mankato MN 56001",
    "addr:housenumber":"105",
    "addr:postcode":"56001",
    "addr:street":"Hensonshire Ct",
    "iso:country":"US",
    "sg:address":"105 Hensonshire Ct",
    "sg:city":"Mankato",
    "sg:classifiers":[
        {
            "category":"Building & Trades",
            "subcategory":"Construction",
            "type":"Services"
        }
    ],
    "sg:phone":"+1 507 388 8604",
    "sg:postcode":"56001",
    "sg:province":"MN",
    "sg:tags":[
        "residential"
    ],
    "wof:name":"Ken Ackerman Construction",
    "wof:placetype":"venue"
},
  "geometry": {"coordinates":[-93.95459200000001,44.196895],"type":"Point"}
}