{
  "type": "Feature",
  "properties": {
    "addr:full":"2051 44th St NW Rochester MN 55901",
    "addr:housenumber":"2051",
    "addr:postcode":"55901",
    "addr:street":"44Th St Nw",
    "iso:country":"US",
    "sg:address":"2051 44th St NW",
    "sg:city":"Rochester",
    "sg:classifiers":[
        {
            "category":"Freight",
            "type":"Transportation"
        }
    ],
    "sg:phone":"+1 507 281 0415",
    "sg:postcode":"55901",
    "sg:province":"MN",
    "sg:tags":[
        "operator",
        "local",
        "trucking"
    ],
    "wof:name":"Ladean Otterness",
    "wof:placetype":"venue"
},
  "geometry": {"coordinates":[-92.49723,44.069359],"type":"Point"}
}