{
  "type": "Feature",
  "properties": {
    "iso:country":"US",
    "sg:address":"5532 Hanrehan Lake Blvd",
    "sg:city":"Savage",
    "sg:classifiers":[
        {
            "category":"Organizations",
            "subcategory":"Religious Organization",
            "type":"Services"
        }
    ],
    "sg:phone":"+1 952 440 7200",
    "sg:postcode":"55378",
    "sg:province":"MN",
    "wof:name":"Three Rivers Church",
    "wof:placetype":"venue"
},
  "geometry": {"coordinates":[-93.34941000000001,44.725597],"type":"Point"}
}