{
  "type": "Feature",
  "properties": {
    "addr:full":"4446 Central Ave NE Minneapolis MN 55421",
    "addr:housenumber":"4446",
    "addr:postcode":"55421",
    "addr:street":"Central Ave Ne",
    "iso:country":"US",
    "sg:address":"4446 Central Ave NE",
    "sg:city":"Minneapolis",
    "sg:classifiers":[
        {
            "category":"Organizations",
            "subcategory":"Membership Organization",
            "type":"Services"
        }
    ],
    "sg:phone":"+1 763 788 8187",
    "sg:postcode":"55421",
    "sg:province":"MN",
    "sg:tags":[
        "military",
        "veteran"
    ],
    "sg:website":"http://www.vfw.org",
    "wof:name":"Veterans of Foreign Wars",
    "wof:placetype":"venue"
},
  "geometry": {"coordinates":[-93.24749799999999,45.048857],"type":"Point"}
}