{
  "type": "Feature",
  "properties": {
    "iso:country":"US",
    "sg:address":"510 Deborah Ave",
    "sg:city":"Lewiston",
    "sg:classifiers":[
        {
            "category":"Retail",
            "subcategory":"Auto Repair",
            "type":"Services"
        }
    ],
    "sg:phone":"+1 507 523 2129",
    "sg:postcode":"55987",
    "sg:province":"MN",
    "sg:tags":[
        "repairing",
        "automobile"
    ],
    "wof:name":"Rislow Service Ctr",
    "wof:placetype":"venue"
},
  "geometry": {"coordinates":[-91.688928,44.050305],"type":"Point"}
}