{
  "type": "Feature",
  "properties": {
    "addr:full":"18951 290th St New Prague MN 56071",
    "addr:housenumber":"18951",
    "addr:postcode":"56071",
    "addr:street":"290Th St",
    "iso:country":"US",
    "sg:address":"18951 290th St",
    "sg:city":"New Prague",
    "sg:phone":"+1 952 758 5319",
    "sg:postcode":"56071",
    "sg:province":"MN",
    "sg:tags":[
        "farm",
        "corn",
        "soybean"
    ],
    "wof:name":"Paul Jahn",
    "wof:placetype":"venue"
},
  "geometry": {"coordinates":[-93.64303099999999,44.529575],"type":"Point"}
}