{
  "type": "Feature",
  "properties": {
    "iso:country":"US",
    "sg:address":"10187 Nightingale St NW",
    "sg:city":"Minneapolis",
    "sg:classifiers":[
        {
            "category":"Real Estate",
            "subcategory":"Real Estate Operator",
            "type":"Services"
        }
    ],
    "sg:phone":"+1 763 754 0054",
    "sg:postcode":"55433",
    "sg:province":"MN",
    "sg:tags":[
        "property",
        "lessor"
    ],
    "wof:name":"Urban Enterprises",
    "wof:placetype":"venue"
},
  "geometry": {"coordinates":[-93.32286999999999,45.154863],"type":"Point"}
}