{
  "type": "Feature",
  "properties": {
    "addr:full":"2868 Woodridge Ct SW Bemidji MN 56601",
    "addr:housenumber":"2868",
    "addr:postcode":"56601",
    "addr:street":"Woodridge Ct Sw",
    "iso:country":"US",
    "sg:address":"2868 Woodridge Ct SW",
    "sg:city":"Bemidji",
    "sg:classifiers":[
        {
            "category":"Professional",
            "subcategory":"Computer Services",
            "type":"Services"
        }
    ],
    "sg:phone":"+1 218 751 2376",
    "sg:postcode":"56601",
    "sg:province":"MN",
    "sg:tags":[
        "related"
    ],
    "wof:name":"Trust Tech Svc",
    "wof:placetype":"venue"
},
  "geometry": {"coordinates":[-94.890051,47.433042],"type":"Point"}
}