{
  "type": "Feature",
  "properties": {
    "addr:full":"150 W Wenberg St Dunnell MN 56127",
    "addr:housenumber":"150",
    "addr:postcode":"56127",
    "addr:street":"W Wenberg St",
    "iso:country":"US",
    "sg:address":"150 W Wenberg St",
    "sg:city":"Dunnell",
    "sg:classifiers":[
        {
            "category":"Government",
            "subcategory":"Post Office",
            "type":"Public Place"
        }
    ],
    "sg:phone":"+1 507 695 2959",
    "sg:postcode":"56127",
    "sg:province":"MN",
    "wof:name":"US Post Office",
    "wof:placetype":"venue"
},
  "geometry": {"coordinates":[-94.78022300000001,43.559131],"type":"Point"}
}