{
  "type": "Feature",
  "properties": {
    "addr:full":"1062 Harrison St W Annandale MN 55302",
    "addr:housenumber":"1062",
    "addr:postcode":"55302",
    "addr:street":"Harrison St W",
    "iso:country":"US",
    "sg:address":"1062 Harrison St W",
    "sg:city":"Annandale",
    "sg:classifiers":[
        {
            "category":"Social Services",
            "subcategory":"Child Care",
            "type":"Services"
        }
    ],
    "sg:phone":"+1 320 274 8599",
    "sg:postcode":"55302",
    "sg:province":"MN",
    "sg:tags":[
        "day"
    ],
    "wof:name":"Glendas Daycare",
    "wof:placetype":"venue"
},
  "geometry": {"coordinates":[-94.13731300000001,45.261111],"type":"Point"}
}