{
  "type": "Feature",
  "properties": {
    "iso:country":"US",
    "sg:address":"802 Carlton Ave",
    "sg:city":"Cloquet",
    "sg:classifiers":[
        {
            "category":"Shopping",
            "subcategory":"Computers & Home Electronics",
            "type":"Retail Goods"
        }
    ],
    "sg:phone":"+1 218 879 0911",
    "sg:postcode":"55720",
    "sg:province":"MN",
    "sg:tags":[
        "equipment",
        "satellite",
        "system"
    ],
    "wof:name":"S & S Cable Alternative Inc",
    "wof:placetype":"venue"
},
  "geometry": {"coordinates":[-92.45462999999999,46.717749],"type":"Point"}
}