{
  "type": "Feature",
  "properties": {
    "iso:country":"US",
    "sg:address":"7401 Metro Blvd Ste 560",
    "sg:city":"Minneapolis",
    "sg:classifiers":[
        {
            "category":"Wholesale",
            "subcategory":"Computers",
            "type":"Manufacturing & Wholesale Goods"
        }
    ],
    "sg:phone":"+1 952 831 5604",
    "sg:postcode":"55439",
    "sg:province":"MN",
    "sg:tags":[
        "equipment"
    ],
    "sg:website":"http://www.watersnet.com",
    "wof:name":"Waters Network Systems",
    "wof:placetype":"venue"
},
  "geometry": {"coordinates":[-93.352829,44.867939],"type":"Point"}
}