{
  "type": "Feature",
  "properties": {
    "addr:full":"4831 Winterset Dr Minnetonka MN 55343",
    "addr:housenumber":"4831",
    "addr:postcode":"55343",
    "addr:street":"Winterset Dr",
    "iso:country":"US",
    "sg:address":"4831 Winterset Dr",
    "sg:city":"Minnetonka",
    "sg:classifiers":[
        {
            "category":"Professional",
            "subcategory":"Research",
            "type":"Services"
        }
    ],
    "sg:phone":"+1 952 934 5026",
    "sg:postcode":"55343",
    "sg:province":"MN",
    "sg:tags":[
        "development",
        "laboratory"
    ],
    "wof:name":"Enterprise Technology",
    "wof:placetype":"venue"
},
  "geometry": {"coordinates":[-93.434844,44.913946],"type":"Point"}
}