{
  "type": "Feature",
  "properties": {
    "addr:full":"606 S 7th St Olivia MN 56277",
    "addr:housenumber":"606",
    "addr:postcode":"56277",
    "addr:street":"S 7Th St",
    "iso:country":"US",
    "sg:address":"606 S 7th St",
    "sg:city":"Olivia",
    "sg:classifiers":[
        {
            "category":"Building & Trades",
            "subcategory":"Electrical",
            "type":"Services"
        }
    ],
    "sg:phone":"+1 320 523 1979",
    "sg:postcode":"56277",
    "sg:province":"MN",
    "sg:tags":[
        "electric",
        "contractor"
    ],
    "wof:name":"J & R Electric",
    "wof:placetype":"venue"
},
  "geometry": {"coordinates":[-94.98644299999999,44.771213],"type":"Point"}
}