{
  "type": "Feature",
  "properties": {
    "addr:full":"3601 Park Center Blvd Minneapolis MN 55416",
    "addr:housenumber":"3601",
    "addr:postcode":"55416",
    "addr:street":"Park Center Blvd",
    "iso:country":"US",
    "sg:address":"3601 Park Center Blvd",
    "sg:city":"Minneapolis",
    "sg:classifiers":[
        {
            "category":"Insurance",
            "subcategory":"Insurance Agent",
            "type":"Services"
        }
    ],
    "sg:phone":"+1 952 927 8082",
    "sg:postcode":"55416",
    "sg:province":"MN",
    "wof:name":"Farmers Insurance",
    "wof:placetype":"venue"
},
  "geometry": {"coordinates":[-93.34955600000001,44.933071],"type":"Point"}
}