{
  "type": "Feature",
  "properties": {
    "addr:full":"7900 International Dr Minneapolis MN 55425",
    "addr:housenumber":"7900",
    "addr:postcode":"55425",
    "addr:street":"International Dr",
    "iso:country":"US",
    "sg:address":"7900 International Dr",
    "sg:city":"Minneapolis",
    "sg:classifiers":[
        {
            "category":"Professional",
            "type":"Services"
        },
        {
            "category":"Professional",
            "subcategory":"Lawyer & Legal Services",
            "type":"Services"
        }
    ],
    "sg:phone":"+1 952 876 4010",
    "sg:postcode":"55425",
    "sg:province":"MN",
    "sg:tags":[
        "arbitration",
        "mediation"
    ],
    "sg:website":"http://www.mediatedsolutions.org",
    "wof:name":"Rebecca Picard JD LLM",
    "wof:placetype":"venue"
},
  "geometry": {"coordinates":[-93.226067,44.860458],"type":"Point"}
}