{
  "type": "Feature",
  "properties": {
    "addr:full":"102 1st St E Fosston MN 56542",
    "addr:housenumber":"102",
    "addr:postcode":"56542",
    "addr:street":"1St St E",
    "iso:country":"US",
    "sg:address":"102 1st St E",
    "sg:city":"Fosston",
    "sg:classifiers":[
        {
            "category":"Shopping",
            "subcategory":"Clothing, Apparel, & Fashions",
            "type":"Retail Goods"
        }
    ],
    "sg:phone":"+1 218 435 6644",
    "sg:postcode":"56542",
    "sg:province":"MN",
    "wof:name":"Korner Store",
    "wof:placetype":"venue"
},
  "geometry": {"coordinates":[-95.751733,47.576078],"type":"Point"}
}