{
  "type": "Feature",
  "properties": {
    "addr:full":"4769 Hauge Cir Eagan MN 55122",
    "addr:postcode":"4769;55122",
    "addr:street":"Hauge Cir",
    "iso:country":"US",
    "sg:address":"4769 Hauge Cir",
    "sg:city":"Eagan",
    "sg:classifiers":[
        {
            "category":"Professional",
            "type":"Services"
        }
    ],
    "sg:phone":"+1 651 686 0041",
    "sg:postcode":"55122",
    "sg:province":"MN",
    "sg:tags":[
        "establishment"
    ],
    "sg:website":"www.giz.com",
    "wof:name":"Strinz Creative",
    "wof:placetype":"venue"
},
  "geometry": {"coordinates":[-93.18859999999999,44.785012],"type":"Point"}
}