{
  "type": "Feature",
  "properties": {
    "iso:country":"US",
    "sg:address":"4076 Hampshire Ave N",
    "sg:city":"Minneapolis",
    "sg:classifiers":[
        {
            "category":"Social Services",
            "type":"Services"
        },
        {
            "category":"Professional",
            "subcategory":"Employment Agencies",
            "type":"Services"
        }
    ],
    "sg:phone":"+1 763 531 9267",
    "sg:postcode":"55427",
    "sg:province":"MN",
    "sg:tags":[
        "workers'",
        "placement",
        "volunteer"
    ],
    "wof:name":"Adventures In Fathering Inc",
    "wof:placetype":"venue"
},
  "geometry": {"coordinates":[-93.365145,45.03033],"type":"Point"}
}