{
  "type": "Feature",
  "properties": {
    "iso:country":"US",
    "sg:address":"301 4th Ave S",
    "sg:city":"Minneapolis",
    "sg:classifiers":[
        {
            "category":"Travel",
            "subcategory":"Hotels & Motels",
            "type":"Entertainment"
        }
    ],
    "sg:phone":"+1 612 253 2020",
    "sg:postcode":"55415",
    "sg:province":"MN",
    "sg:website":"www.fourseasons.com",
    "wof:name":"Four Seasons Inc",
    "wof:placetype":"venue"
},
  "geometry": {"coordinates":[-93.263383,44.97833],"type":"Point"}
}