{
  "type": "Feature",
  "properties": {
    "addr:full":"7406 Mitchell Rd Eden Prairie MN 55344",
    "addr:housenumber":"7406",
    "addr:postcode":"55344",
    "addr:street":"Mitchell Rd",
    "iso:country":"US",
    "sg:address":"7406 Mitchell Rd",
    "sg:city":"Eden Prairie",
    "sg:classifiers":[
        {
            "category":"Restaurant",
            "type":"Food & Drink"
        }
    ],
    "sg:phone":"+1 952 934 5736",
    "sg:postcode":"55344",
    "sg:province":"MN",
    "sg:tags":[
        "chinese"
    ],
    "sg:website":"www.houseofkai.com/",
    "wof:name":"House of Kai",
    "wof:placetype":"venue"
},
  "geometry": {"coordinates":[-93.45610000000001,44.8689],"type":"Point"}
}