{
  "type": "Feature",
  "properties": {
    "iso:country":"US",
    "sg:address":"38427 370th St SE",
    "sg:city":"Fosston",
    "sg:classifiers":[
        {
            "category":"Utilities",
            "subcategory":"Natural Gas",
            "type":"Services"
        }
    ],
    "sg:phone":"+1 218 435 6697",
    "sg:postcode":"56542",
    "sg:province":"MN",
    "sg:tags":[
        "carburetor"
    ],
    "wof:name":"Valley Carburetor & Automotive",
    "wof:placetype":"venue"
},
  "geometry": {"coordinates":[-95.652885,47.629871],"type":"Point"}
}