{
  "type": "Feature",
  "properties": {
    "addr:full":"233 Main St La Crescent MN 55947",
    "addr:housenumber":"233",
    "addr:postcode":"55947",
    "addr:street":"Main St",
    "iso:country":"US",
    "sg:address":"233 Main St",
    "sg:city":"La Crescent",
    "sg:classifiers":[
        {
            "category":"Shopping",
            "subcategory":"Gifts & Souvenirs",
            "type":"Retail Goods"
        }
    ],
    "sg:phone":"+1 507 895 4806",
    "sg:postcode":"55947",
    "sg:province":"MN",
    "wof:name":"LA Crescent Gift Shop",
    "wof:placetype":"venue"
},
  "geometry": {"coordinates":[-91.303574,43.829141],"type":"Point"}
}