{
  "type": "Feature",
  "properties": {
    "addr:full":"22493 181st Ave Sebeka MN 56477",
    "addr:housenumber":"22493",
    "addr:postcode":"56477",
    "addr:street":"181St Ave",
    "iso:country":"US",
    "sg:address":"22493 181st Ave",
    "sg:city":"Sebeka",
    "sg:classifiers":[
        {
            "category":"Retail",
            "subcategory":"Animal Services",
            "type":"Services"
        }
    ],
    "sg:phone":"+1 218 631 2289",
    "sg:postcode":"56477",
    "sg:province":"MN",
    "wof:name":"Bluegrass Kennel",
    "wof:placetype":"venue"
},
  "geometry": {"coordinates":[-94.98908,46.546978],"type":"Point"}
}