{
  "type": "Feature",
  "properties": {
    "addr:full":"28572 172 Ave Callaway MN 56521",
    "addr:housenumber":"28572",
    "addr:postcode":"56521",
    "addr:street":"172 Ave",
    "iso:country":"US",
    "sg:address":"28572 172 Ave",
    "sg:city":"Callaway",
    "sg:phone":"+1 218 375 3285",
    "sg:postcode":"56521",
    "sg:province":"MN",
    "sg:tags":[
        "farm",
        "wheat",
        "beef",
        "feedlot",
        "cattle"
    ],
    "wof:name":"Lyle Osten",
    "wof:placetype":"venue"
},
  "geometry": {"coordinates":[-96.03501799999999,46.992021],"type":"Point"}
}