{
  "type": "Feature",
  "properties": {
    "addr:full":"9142 Neill Lake Rd Eden Prairie MN 55347",
    "addr:housenumber":"9142",
    "addr:postcode":"55347",
    "addr:street":"Neill Lake Rd",
    "iso:country":"US",
    "sg:address":"9142 Neill Lake Rd",
    "sg:city":"Eden Prairie",
    "sg:classifiers":[
        {
            "category":"Insurance",
            "subcategory":"Hazard Insurance",
            "type":"Services"
        }
    ],
    "sg:phone":"+1 952 944 6120",
    "sg:postcode":"55347",
    "sg:province":"MN",
    "sg:tags":[
        "surety",
        "agency",
        "employment",
        "carrier"
    ],
    "wof:name":"Nexstar Financial Corp",
    "wof:placetype":"venue"
},
  "geometry": {"coordinates":[-93.41154,44.838541],"type":"Point"}
}