{
  "type": "Feature",
  "properties": {
    "iso:country":"US",
    "sg:address":"10209 W Tark Rd",
    "sg:city":"Forbes",
    "sg:classifiers":[
        {
            "category":"Building & Trades",
            "subcategory":"Landscaping Services",
            "type":"Services"
        }
    ],
    "sg:phone":"+1 218 427 2585",
    "sg:postcode":"55738",
    "sg:province":"MN",
    "sg:tags":[
        "forester"
    ],
    "wof:name":"Duwayne A Morrow",
    "wof:placetype":"venue"
},
  "geometry": {"coordinates":[-92.752866,47.247134],"type":"Point"}
}