{
  "type": "Feature",
  "properties": {
    "addr:full":"8039 Dakota Ln Chanhassen MN 55317",
    "addr:housenumber":"8039",
    "addr:postcode":"55317",
    "addr:street":"Dakota Ln",
    "iso:country":"US",
    "sg:address":"8039 Dakota Ln",
    "sg:city":"Chanhassen",
    "sg:classifiers":[
        {
            "category":"Professional",
            "subcategory":"Management & Consulting",
            "type":"Services"
        }
    ],
    "sg:phone":"+1 952 975 1953",
    "sg:postcode":"55317",
    "sg:province":"MN",
    "wof:name":"Sica Management LLC",
    "wof:placetype":"venue"
},
  "geometry": {"coordinates":[-93.52407700000001,44.856526],"type":"Point"}
}