{
  "type": "Feature",
  "properties": {
    "addr:full":"49659 State Line Rd Sandstone MN 55072",
    "addr:housenumber":"49659",
    "addr:postcode":"55072",
    "addr:street":"State Line Rd",
    "iso:country":"US",
    "sg:address":"49659 State Line Rd",
    "sg:city":"Sandstone",
    "sg:classifiers":[
        {
            "category":"Building & Trades",
            "subcategory":"Construction",
            "type":"Services"
        }
    ],
    "sg:phone":"+1 320 242 3165",
    "sg:postcode":"55072",
    "sg:province":"MN",
    "sg:tags":[
        "concrete",
        "contractor"
    ],
    "wof:name":"Coveau Concrete",
    "wof:placetype":"venue"
},
  "geometry": {"coordinates":[-92.294023,46.088758],"type":"Point"}
}