{
  "type": "Feature",
  "properties": {
    "addr:full":"3784 150th St W Rosemount MN 55068",
    "addr:housenumber":"3784",
    "addr:postcode":"55068",
    "addr:street":"150Th St W",
    "iso:country":"US",
    "sg:address":"3784 150th St W",
    "sg:city":"Rosemount",
    "sg:classifiers":[
        {
            "category":"Banks & Credit Unions",
            "subcategory":"Bank",
            "type":"Services"
        }
    ],
    "sg:phone":"+1 651 423 0277",
    "sg:postcode":"55068",
    "sg:province":"MN",
    "sg:tags":[
        "federal",
        "savings",
        "institution"
    ],
    "wof:name":"TCF Bank",
    "wof:placetype":"venue"
},
  "geometry": {"coordinates":[-93.142,44.73166],"type":"Point"}
}