{
  "type": "Feature",
  "properties": {
    "addr:full":"13033 Deborah Ln SW Motley MN 56466",
    "addr:housenumber":"13033",
    "addr:postcode":"56466",
    "addr:street":"Deborah Ln Sw",
    "iso:country":"US",
    "sg:address":"13033 Deborah Ln SW",
    "sg:city":"Motley",
    "sg:classifiers":[
        {
            "category":"Autos & Motor Vehicles",
            "subcategory":"Auto Supplies",
            "type":"Retail Goods"
        }
    ],
    "sg:phone":"+1 218 352 6127",
    "sg:postcode":"56466",
    "sg:province":"MN",
    "wof:name":"Lukes Diesel Repair",
    "wof:placetype":"venue"
},
  "geometry": {"coordinates":[-94.60103599999999,46.330992],"type":"Point"}
}