{
  "type": "Feature",
  "properties": {
    "addr:full":"1002 Bailey Rd Newport MN 55055",
    "addr:housenumber":"1002",
    "addr:postcode":"55055",
    "addr:street":"Bailey Rd",
    "iso:country":"US",
    "sg:address":"1002 Bailey Rd",
    "sg:city":"Newport",
    "sg:classifiers":[
        {
            "category":"Building & Trades",
            "subcategory":"Construction",
            "type":"Services"
        }
    ],
    "sg:phone":"+1 651 459 0406",
    "sg:postcode":"55055",
    "sg:province":"MN",
    "sg:tags":[
        "contractor"
    ],
    "wof:name":"St. Paul Cycle Restoration, Inc.",
    "wof:placetype":"venue"
},
  "geometry": {"coordinates":[-92.999775,44.888259],"type":"Point"}
}