{
  "type": "Feature",
  "properties": {
    "iso:country":"US",
    "sg:address":"9476 92nd St S",
    "sg:city":"Cottage Grove",
    "sg:classifiers":[
        {
            "category":"Retail",
            "subcategory":"Portrait Studio",
            "type":"Services"
        }
    ],
    "sg:phone":"+1 651 768 8616",
    "sg:postcode":"55016",
    "sg:province":"MN",
    "sg:tags":[
        "photo"
    ],
    "wof:name":"Custom Photography",
    "wof:placetype":"venue"
},
  "geometry": {"coordinates":[-92.91477,44.815675],"type":"Point"}
}