{
  "type": "Feature",
  "properties": {
    "addr:full":"120 Tile St Mankato MN 56001",
    "addr:housenumber":"120",
    "addr:postcode":"56001",
    "addr:street":"Tile St",
    "iso:country":"US",
    "sg:address":"120 Tile St",
    "sg:city":"Mankato",
    "sg:classifiers":[
        {
            "category":"Professional",
            "subcategory":"Accounting & Tax Preparation",
            "type":"Services"
        }
    ],
    "sg:phone":"+1 507 388 3740",
    "sg:postcode":"56001",
    "sg:province":"MN",
    "sg:tags":[
        "accountant"
    ],
    "wof:name":"Richard J Breiter CPA",
    "wof:placetype":"venue"
},
  "geometry": {"coordinates":[-94.023605,44.153934],"type":"Point"}
}