{
  "type": "Feature",
  "properties": {
    "iso:country":"US",
    "sg:address":"6800 France Ave S",
    "sg:city":"Minneapolis",
    "sg:classifiers":[
        {
            "category":"Professional",
            "subcategory":"Management & Consulting",
            "type":"Services"
        }
    ],
    "sg:phone":"+1 952 925 5882",
    "sg:postcode":"55435",
    "sg:province":"MN",
    "sg:tags":[
        "independent",
        "medical",
        "examination"
    ],
    "wof:name":"Evalumed",
    "wof:placetype":"venue"
},
  "geometry": {"coordinates":[-93.328957,44.878161],"type":"Point"}
}