{
  "type": "Feature",
  "properties": {
    "addr:full":"23520 Sunrise Rd NE Stacy MN 55079",
    "addr:housenumber":"23520",
    "addr:postcode":"55079",
    "addr:street":"Sunrise Rd Ne",
    "iso:country":"US",
    "sg:address":"23520 Sunrise Rd NE",
    "sg:city":"Stacy",
    "sg:classifiers":[
        {
            "category":"Building & Trades",
            "subcategory":"Construction",
            "type":"Services"
        }
    ],
    "sg:phone":"+1 651 462 1244",
    "sg:postcode":"55079",
    "sg:province":"MN",
    "sg:tags":[
        "contractor"
    ],
    "wof:name":"S D K Masonry",
    "wof:placetype":"venue"
},
  "geometry": {"coordinates":[-93.043098,45.393904],"type":"Point"}
}