{
  "type": "Feature",
  "properties": {
    "iso:country":"US",
    "sg:address":"1155 Centre Pointe Dr",
    "sg:city":"Saint Paul",
    "sg:classifiers":[
        {
            "category":"Professional",
            "subcategory":"Lawyer & Legal Services",
            "type":"Services"
        }
    ],
    "sg:phone":"+1 651 225 0618",
    "sg:postcode":"55120",
    "sg:province":"MN",
    "wof:name":"Susan E Torgerson",
    "wof:placetype":"venue"
},
  "geometry": {"coordinates":[-93.14937399999999,44.880875],"type":"Point"}
}