{
  "type": "Feature",
  "properties": {
    "addr:full":"7575 Golden Valley Rd Minneapolis MN 55427",
    "addr:housenumber":"7575",
    "addr:postcode":"55427",
    "addr:street":"Golden Valley Rd",
    "iso:country":"US",
    "sg:address":"7575 Golden Valley Rd",
    "sg:city":"Minneapolis",
    "sg:classifiers":[
        {
            "category":"Professional",
            "subcategory":"Engineering",
            "type":"Services"
        }
    ],
    "sg:phone":"+1 763 544 8456",
    "sg:postcode":"55427",
    "sg:province":"MN",
    "sg:tags":[
        "engineer",
        "structural"
    ],
    "sg:website":"www.dbm-inc.com",
    "wof:name":"Darg Bolgrean Menk Inc",
    "wof:placetype":"venue"
},
  "geometry": {"coordinates":[-93.376379,44.986306],"type":"Point"}
}