{
  "type": "Feature",
  "properties": {
    "iso:country":"US",
    "sg:address":"125 1st Ave NE",
    "sg:city":"Faribault",
    "sg:classifiers":[
        {
            "category":"Restaurant",
            "type":"Food & Drink"
        }
    ],
    "sg:menulink":"http://www.allmenus.com/mn/faribault/88328-bostons-gourmet-pizza/menu/",
    "sg:phone":"+1 507 331 3255",
    "sg:postcode":"55021",
    "sg:province":"MN",
    "sg:tags":[
        "american",
        "pizza"
    ],
    "wof:name":"Boston's Gourmet Pizza",
    "wof:placetype":"venue"
},
  "geometry": {"coordinates":[-93.266595,44.29173],"type":"Point"}
}