{
  "type": "Feature",
  "properties": {
    "addr:full":"20376 Holyoke Ave Lakeville MN 55044",
    "addr:housenumber":"20376",
    "addr:postcode":"55044",
    "addr:street":"Holyoke Ave",
    "iso:country":"US",
    "sg:address":"20376 Holyoke Ave",
    "sg:city":"Lakeville",
    "sg:classifiers":[
        {
            "category":"Building & Trades",
            "subcategory":"Construction",
            "type":"Services"
        }
    ],
    "sg:phone":"+1 952 469 4749",
    "sg:postcode":"55044",
    "sg:province":"MN",
    "sg:tags":[
        "hanging",
        "contractor"
    ],
    "wof:name":"Faux Creations",
    "wof:placetype":"venue"
},
  "geometry": {"coordinates":[-93.242667,44.653889],"type":"Point"}
}