{
  "type": "Feature",
  "properties": {
    "addr:full":"601 W Broadway Ave Minneapolis MN 55411",
    "addr:housenumber":"601",
    "addr:postcode":"55411",
    "addr:street":"W Broadway Ave",
    "iso:country":"US",
    "sg:address":"601 W Broadway Ave",
    "sg:city":"Minneapolis",
    "sg:classifiers":[
        {
            "category":"Personal",
            "subcategory":"Beauty Salon",
            "type":"Services"
        }
    ],
    "sg:phone":"+1 612 522 8147",
    "sg:postcode":"55411",
    "sg:province":"MN",
    "sg:tags":[
        "shop"
    ],
    "wof:name":"Oriental Nails",
    "wof:placetype":"venue"
},
  "geometry": {"coordinates":[-93.28685400000001,44.999142],"type":"Point"}
}