{
  "type": "Feature",
  "properties": {
    "addr:full":"1449 Coon Rapids Blvd NW Minneapolis MN 55433",
    "addr:housenumber":"1449",
    "addr:postcode":"55433",
    "addr:street":"Coon Rapids Blvd Nw",
    "iso:country":"US",
    "sg:address":"1449 Coon Rapids Blvd NW",
    "sg:city":"Minneapolis",
    "sg:classifiers":[
        {
            "category":"Autos & Motor Vehicles",
            "subcategory":"Auto Supplies",
            "type":"Retail Goods"
        }
    ],
    "sg:phone":"+1 763 757 3130",
    "sg:postcode":"55433",
    "sg:province":"MN",
    "sg:tags":[
        "automotive",
        "tire",
        "repair"
    ],
    "wof:name":"North Country Tire Service",
    "wof:placetype":"venue"
},
  "geometry": {"coordinates":[-93.304423,45.153641],"type":"Point"}
}