{
  "type": "Feature",
  "properties": {
    "addr:full":"2377 Margaret St N Saint Paul MN 55109",
    "addr:housenumber":"2377",
    "addr:postcode":"55109",
    "addr:street":"Margaret St N",
    "iso:country":"US",
    "sg:address":"2377 Margaret St N",
    "sg:city":"Saint Paul",
    "sg:classifiers":[
        {
            "category":"Health Services",
            "subcategory":"Doctor",
            "type":"Services"
        }
    ],
    "sg:phone":"+1 651 777 3009",
    "sg:postcode":"55109",
    "sg:province":"MN",
    "wof:name":"Paul E Nelson DDS",
    "wof:placetype":"venue"
},
  "geometry": {"coordinates":[-92.992357,45.014663],"type":"Point"}
}