{
  "type": "Feature",
  "properties": {
    "iso:country":"US",
    "sg:address":"122 W Demont Ave",
    "sg:city":"Little Canada",
    "sg:classifiers":[
        {
            "category":"Retail",
            "subcategory":"Auto Repair",
            "type":"Services"
        }
    ],
    "sg:phone":"+1 651 484 5722",
    "sg:postcode":"55117",
    "sg:province":"MN",
    "sg:tags":[
        "glass",
        "coating",
        "tinting"
    ],
    "wof:name":"Suntech Energy Control Film",
    "wof:placetype":"venue"
},
  "geometry": {"coordinates":[-93.105456,45.017049],"type":"Point"}
}