{
  "type": "Feature",
  "properties": {
    "addr:full":"5879 Wyoming Trl Wyoming MN 55092",
    "addr:housenumber":"5879",
    "addr:postcode":"55092",
    "addr:street":"Wyoming Trl",
    "iso:country":"US",
    "sg:address":"5879 Wyoming Trl",
    "sg:city":"Wyoming",
    "sg:classifiers":[
        {
            "category":"Organizations",
            "subcategory":"Religious Organization",
            "type":"Services"
        }
    ],
    "sg:phone":"+1 651 462 5212",
    "sg:postcode":"55092",
    "sg:province":"MN",
    "sg:tags":[
        "churches-lutheran",
        "church"
    ],
    "sg:website":"http://www.sharingchristslove.org",
    "wof:name":"Saint Paul Lutheran Church",
    "wof:placetype":"venue"
},
  "geometry": {"coordinates":[-92.986791,45.332905],"type":"Point"}
}