{
  "type": "Feature",
  "properties": {
    "iso:country":"US",
    "sg:address":"125 S 1st St",
    "sg:city":"Montevideo",
    "sg:classifiers":[
        {
            "category":"Insurance",
            "subcategory":"Insurance Agent",
            "type":"Services"
        }
    ],
    "sg:phone":"+1 320 269 6588",
    "sg:postcode":"56265",
    "sg:province":"MN",
    "wof:name":"Hein Theobald & Assoc Inc",
    "wof:placetype":"venue"
},
  "geometry": {"coordinates":[-95.724332,44.945248],"type":"Point"}
}