{
  "type": "Feature",
  "properties": {
    "iso:country":"US",
    "sg:address":"107 12th St S",
    "sg:city":"Virginia",
    "sg:classifiers":[
        {
            "category":"Professional",
            "subcategory":"Accounting & Tax Preparation",
            "type":"Services"
        }
    ],
    "sg:phone":"+1 218 741 8285",
    "sg:postcode":"55792",
    "sg:province":"MN",
    "sg:tags":[
        "return",
        "preparation-business"
    ],
    "wof:name":"Perslin Tax Preparer",
    "wof:placetype":"venue"
},
  "geometry": {"coordinates":[-92.53095999999999,47.511824],"type":"Point"}
}