{
  "type": "Feature",
  "properties": {
    "addr:full":"10210 Dogwood St NW Minneapolis MN 55448",
    "addr:housenumber":"10210",
    "addr:postcode":"55448",
    "addr:street":"Dogwood St Nw",
    "iso:country":"US",
    "sg:address":"10210 Dogwood St NW",
    "sg:city":"Minneapolis",
    "sg:classifiers":[
        {
            "category":"Professional",
            "type":"Services"
        }
    ],
    "sg:phone":"+1 763 862 2813",
    "sg:postcode":"55448",
    "sg:province":"MN",
    "wof:name":"Display Concepts",
    "wof:placetype":"venue"
},
  "geometry": {"coordinates":[-93.27174599999999,45.155062],"type":"Point"}
}