{
  "type": "Feature",
  "properties": {
    "addr:full":"715 Debbie Cir Carver MN 55315",
    "addr:housenumber":"715",
    "addr:postcode":"55315",
    "addr:street":"Debbie Cir",
    "iso:country":"US",
    "sg:address":"715 Debbie Cir",
    "sg:city":"Carver",
    "sg:classifiers":[
        {
            "category":"Building & Trades",
            "subcategory":"Construction",
            "type":"Services"
        }
    ],
    "sg:phone":"+1 952 380 9916",
    "sg:postcode":"55315",
    "sg:province":"MN",
    "sg:tags":[
        "contractor"
    ],
    "wof:name":"First Choice Seamless Inc",
    "wof:placetype":"venue"
},
  "geometry": {"coordinates":[-93.627134,44.77081],"type":"Point"}
}