{
  "type": "Feature",
  "properties": {
    "addr:full":"8201 Isaak Ave NW Annandale MN 55302",
    "addr:housenumber":"8201",
    "addr:postcode":"55302",
    "addr:street":"Isaak Ave Nw",
    "iso:country":"US",
    "sg:address":"8201 Isaak Ave NW",
    "sg:city":"Annandale",
    "sg:classifiers":[
        {
            "category":"Education",
            "subcategory":"Dance Studio",
            "type":"Public Place"
        }
    ],
    "sg:phone":"+1 320 274 5276",
    "sg:postcode":"55302",
    "sg:province":"MN",
    "sg:tags":[
        "instruction",
        "dancing"
    ],
    "wof:name":"Barbara Lee's Studio Of Dance",
    "wof:placetype":"venue"
},
  "geometry": {"coordinates":[-94.076357,45.272257],"type":"Point"}
}