{
  "type": "Feature",
  "properties": {
    "addr:full":"30614 State Hwy 28 Grey Eagle MN 56336",
    "addr:housenumber":"30614",
    "addr:postcode":"56336",
    "addr:street":"State Hwy 28",
    "iso:country":"US",
    "sg:address":"30614 State Hwy 28",
    "sg:city":"Grey Eagle",
    "sg:classifiers":[
        {
            "category":"Retail",
            "subcategory":"Repair Shop",
            "type":"Services"
        }
    ],
    "sg:phone":"+1 320 285 2578",
    "sg:postcode":"56336",
    "sg:province":"MN",
    "sg:tags":[
        "sharpening"
    ],
    "wof:name":"Viking Sharpening",
    "wof:placetype":"venue"
},
  "geometry": {"coordinates":[-94.735359,45.826362],"type":"Point"}
}