{
  "type": "Feature",
  "properties": {
    "addr:full":"6090 Shingle Creek Pkwy Minneapolis MN 55430",
    "addr:housenumber":"6090",
    "addr:postcode":"55430",
    "addr:street":"Shingle Creek Pkwy",
    "iso:country":"US",
    "sg:address":"6090 Shingle Creek Pkwy",
    "sg:city":"Minneapolis",
    "sg:classifiers":[
        {
            "category":"Restaurant",
            "type":"Food & Drink"
        }
    ],
    "sg:menulink":"http://www.allmenus.com/mn/brooklyn-center/54025-g1-buffet/menu/",
    "sg:phone":"+1 763 566 5588",
    "sg:postcode":"55430",
    "sg:province":"MN",
    "sg:tags":[
        "asian",
        "chinese"
    ],
    "wof:name":"G1 Buffet",
    "wof:placetype":"venue"
},
  "geometry": {"coordinates":[-93.309123,45.0657],"type":"Point"}
}