{
  "type": "Feature",
  "properties": {
    "iso:country":"US",
    "sg:address":"14050 Saint Francis Blvd",
    "sg:city":"Ramsey",
    "sg:classifiers":[
        {
            "category":"Retail",
            "subcategory":"Laundry & Dry Cleaning",
            "type":"Services"
        }
    ],
    "sg:phone":"+1 763 323 0106",
    "sg:postcode":"55303",
    "sg:province":"MN",
    "wof:name":"Cleaners One",
    "wof:placetype":"venue"
},
  "geometry": {"coordinates":[-93.3974,45.225399],"type":"Point"}
}