{
  "type": "Feature",
  "properties": {
    "iso:country":"US",
    "sg:address":"13436 Hwy 25",
    "sg:city":"Pierz",
    "sg:classifiers":[
        {
            "category":"Travel",
            "subcategory":"Campground",
            "type":"Entertainment"
        }
    ],
    "sg:phone":"+1 320 468 2555",
    "sg:postcode":"56364",
    "sg:province":"MN",
    "wof:name":"Genola Campground",
    "wof:placetype":"venue"
},
  "geometry": {"coordinates":[-94.115059,45.956342],"type":"Point"}
}