{
  "type": "Feature",
  "properties": {
    "iso:country":"US",
    "sg:address":"80 7th St W",
    "sg:city":"Saint Paul",
    "sg:classifiers":[
        {
            "category":"Social Services",
            "type":"Services"
        }
    ],
    "sg:phone":"+1 651 646 7771",
    "sg:postcode":"55102",
    "sg:province":"MN",
    "sg:tags":[
        "agency",
        "center",
        "day"
    ],
    "wof:name":"Childrens Home Soc & Fmly Svcs",
    "wof:placetype":"venue"
},
  "geometry": {"coordinates":[-93.098794,44.947404],"type":"Point"}
}