{
  "type": "Feature",
  "properties": {
    "iso:country":"US",
    "sg:address":"6530 Grand Ave",
    "sg:city":"Duluth",
    "sg:classifiers":[
        {
            "category":"Home & Garden",
            "subcategory":"Building Materials",
            "type":"Retail Goods"
        },
        {
            "category":"Building & Trades",
            "subcategory":"Construction",
            "type":"Services"
        }
    ],
    "sg:phone":"+1 218 628 0715",
    "sg:postcode":"55807",
    "sg:province":"MN",
    "sg:tags":[
        "roofing",
        "contractor"
    ],
    "sg:website":"www.unitedproducts.com",
    "wof:name":"United Products Corp of Amer",
    "wof:placetype":"venue"
},
  "geometry": {"coordinates":[-92.180959,46.73058],"type":"Point"}
}