{
  "type": "Feature",
  "properties": {
    "iso:country":"US",
    "sg:address":"2949 120th Ave NW",
    "sg:city":"Minneapolis",
    "sg:classifiers":[
        {
            "category":"Building & Trades",
            "subcategory":"Cleaning & Sanitation",
            "type":"Services"
        }
    ],
    "sg:phone":"+1 651 293 8070",
    "sg:postcode":"55433",
    "sg:province":"MN",
    "sg:tags":[
        "maintenance"
    ],
    "wof:name":"Ben Building Maintenance",
    "wof:placetype":"venue"
},
  "geometry": {"coordinates":[-93.341932,45.188857],"type":"Point"}
}