{
  "type": "Feature",
  "properties": {
    "addr:full":"1885 University Ave W Saint Paul MN 55104",
    "addr:housenumber":"1885",
    "addr:postcode":"55104",
    "addr:street":"University Ave W",
    "iso:country":"US",
    "sg:address":"1885 University Ave W",
    "sg:city":"Saint Paul",
    "sg:classifiers":[
        {
            "category":"Organizations",
            "subcategory":"Community Association",
            "type":"Services"
        }
    ],
    "sg:phone":"+1 651 645 0261",
    "sg:postcode":"55104",
    "sg:province":"MN",
    "sg:tags":[
        "senior",
        "citizen"
    ],
    "wof:name":"Minnesota Snior Fdration Metro",
    "wof:placetype":"venue"
},
  "geometry": {"coordinates":[-93.17829999999999,44.956232],"type":"Point"}
}