{
  "type": "Feature",
  "properties": {
    "iso:country":"US",
    "sg:address":"1050 Hyacinth Ave E",
    "sg:city":"St Paul",
    "sg:classifiers":[
        {
            "category":"Building & Trades",
            "subcategory":"Construction",
            "type":"Services"
        }
    ],
    "sg:phone":"+1 651 771 2032",
    "sg:postcode":"55106",
    "sg:province":"MN",
    "sg:tags":[
        "roofing",
        "contractor"
    ],
    "wof:name":"A S Hable Construction Co",
    "wof:placetype":"venue"
},
  "geometry": {"coordinates":[-93.059168,44.980162],"type":"Point"}
}