{
  "type": "Feature",
  "properties": {
    "addr:full":"350 4th St NE Crosby MN 56441",
    "addr:housenumber":"350",
    "addr:postcode":"56441",
    "addr:street":"4Th St Ne",
    "iso:country":"US",
    "sg:address":"350 4th St NE",
    "sg:city":"Crosby",
    "sg:classifiers":[
        {
            "category":"Health Services",
            "subcategory":"Nursing And Care Facility",
            "type":"Services"
        }
    ],
    "sg:phone":"+1 218 546 6265",
    "sg:postcode":"56441",
    "sg:province":"MN",
    "sg:tags":[
        "intermediate"
    ],
    "wof:name":"Hallett Cottages",
    "wof:placetype":"venue"
},
  "geometry": {"coordinates":[-93.94567499999999,46.486049],"type":"Point"}
}