{
  "type": "Feature",
  "properties": {
    "addr:full":"112 Kensington Dr Hoyt Lakes MN 55750",
    "addr:housenumber":"112",
    "addr:postcode":"55750",
    "addr:street":"Kensington Dr",
    "iso:country":"US",
    "sg:address":"112 Kensington Dr",
    "sg:city":"Hoyt Lakes",
    "sg:classifiers":[
        {
            "category":"Organizations",
            "subcategory":"Community Association",
            "type":"Services"
        }
    ],
    "sg:phone":"+1 218 225 2455",
    "sg:postcode":"55750",
    "sg:province":"MN",
    "sg:tags":[
        "club"
    ],
    "wof:name":"Veterans Of Foreign Wars",
    "wof:placetype":"venue"
},
  "geometry": {"coordinates":[-92.143711,47.522259],"type":"Point"}
}