{
  "type": "Feature",
  "properties": {
    "addr:full":"13791 Fleetwood Ave Saint Paul MN 55124",
    "addr:housenumber":"13791",
    "addr:postcode":"55124",
    "addr:street":"Fleetwood Ave",
    "iso:country":"US",
    "sg:address":"13791 Fleetwood Ave",
    "sg:city":"Saint Paul",
    "sg:classifiers":[
        {
            "category":"Restaurant",
            "type":"Food & Drink"
        }
    ],
    "sg:phone":"+1 952 895 0011",
    "sg:postcode":"55124",
    "sg:province":"MN",
    "wof:name":"Lantern Garden Restaurant",
    "wof:placetype":"venue"
},
  "geometry": {"coordinates":[-93.1996,44.750301],"type":"Point"}
}