{
  "type": "Feature",
  "properties": {
    "iso:country":"US",
    "sg:address":"211 Fifth Ave NE",
    "sg:city":"Melrose",
    "sg:classifiers":[
        {
            "category":"Organizations",
            "subcategory":"Religious Organization",
            "type":"Services"
        }
    ],
    "sg:phone":"+1 320 256 4207",
    "sg:postcode":"56352",
    "sg:province":"MN",
    "wof:name":"Saint Marys Church",
    "wof:placetype":"venue"
},
  "geometry": {"coordinates":[-94.807816,45.677909],"type":"Point"}
}