{
  "type": "Feature",
  "properties": {
    "iso:country":"US",
    "sg:address":"2928 5th Ave S",
    "sg:city":"Minneapolis",
    "sg:classifiers":[
        {
            "category":"Real Estate",
            "subcategory":"Architect",
            "type":"Services"
        }
    ],
    "sg:phone":"+1 612 824 6567",
    "sg:postcode":"55408",
    "sg:province":"MN",
    "wof:name":"Heinen Mary Jane Archt",
    "wof:placetype":"venue"
},
  "geometry": {"coordinates":[-93.269203,44.949501],"type":"Point"}
}