{
  "type": "Feature",
  "properties": {
    "addr:full":"74851 124th Ave Blooming Prairie MN 55917",
    "addr:housenumber":"74851",
    "addr:postcode":"55917",
    "addr:street":"124Th Ave",
    "iso:country":"US",
    "sg:address":"74851 124th Ave",
    "sg:city":"Blooming Prairie",
    "sg:phone":"+1 507 583 2209",
    "sg:postcode":"55917",
    "sg:province":"MN",
    "sg:tags":[
        "farm",
        "corn",
        "grain",
        "cash",
        "soybean"
    ],
    "wof:name":"Burton Knutson",
    "wof:placetype":"venue"
},
  "geometry": {"coordinates":[-92.99767900000001,43.864355],"type":"Point"}
}