{
  "type": "Feature",
  "properties": {
    "iso:country":"US",
    "sg:address":"2715 Evergreen Cir",
    "sg:city":"Saint Paul",
    "sg:classifiers":[
        {
            "category":"Shopping",
            "subcategory":"Music",
            "type":"Retail Goods"
        }
    ],
    "sg:phone":"+1 651 762 4680",
    "sg:postcode":"55110",
    "sg:province":"MN",
    "wof:name":"Klik Records",
    "wof:placetype":"venue"
},
  "geometry": {"coordinates":[-92.98536199999999,45.102155],"type":"Point"}
}