{
  "type": "Feature",
  "properties": {
    "addr:full":"2832 1st Ave Hibbing MN 55746",
    "addr:housenumber":"2832",
    "addr:postcode":"55746",
    "addr:street":"1St Ave",
    "iso:country":"US",
    "sg:address":"2832 1st Ave",
    "sg:city":"Hibbing",
    "sg:classifiers":[
        {
            "category":"Professional",
            "subcategory":"Management & Consulting",
            "type":"Services"
        }
    ],
    "sg:phone":"+1 218 263 7540",
    "sg:postcode":"55746",
    "sg:province":"MN",
    "wof:name":"Advantage Billing Concepts",
    "wof:placetype":"venue"
},
  "geometry": {"coordinates":[-92.94164600000001,47.417612],"type":"Point"}
}