{
  "type": "Feature",
  "properties": {
    "iso:country":"US",
    "sg:address":"14601 Ramsey Blvd NW",
    "sg:city":"Ramsey",
    "sg:classifiers":[
        {
            "category":"Retail",
            "subcategory":"Auto Repair",
            "type":"Services"
        }
    ],
    "sg:phone":"+1 763 323 4253",
    "sg:postcode":"55303",
    "sg:province":"MN",
    "sg:tags":[
        "truck"
    ],
    "wof:name":"Utility Truck Svc",
    "wof:placetype":"venue"
},
  "geometry": {"coordinates":[-93.44970000000001,45.234975],"type":"Point"}
}