{
  "type": "Feature",
  "properties": {
    "iso:country":"US",
    "sg:address":"1265 Grey Fox Rd",
    "sg:city":"Arden Hills",
    "sg:classifiers":[
        {
            "category":"Professional",
            "type":"Services"
        },
        {
            "category":"Manufacturing",
            "subcategory":"Tools & Machinery",
            "type":"Manufacturing & Wholesale Goods"
        }
    ],
    "sg:phone":"+1 651 636 0458",
    "sg:postcode":"55112",
    "sg:province":"MN",
    "sg:tags":[
        "mfg",
        "medical",
        "doctor",
        "establishment",
        "instr"
    ],
    "wof:name":"Deltec Inc",
    "wof:placetype":"venue"
},
  "geometry": {"coordinates":[-93.156228,45.053897],"type":"Point"}
}