{
  "type": "Feature",
  "properties": {
    "iso:country":"US",
    "sg:address":"3908 Victoria St",
    "sg:city":"Minnetonka",
    "sg:classifiers":[
        {
            "category":"Professional",
            "subcategory":"Management & Consulting",
            "type":"Services"
        }
    ],
    "sg:phone":"+1 952 931 1152",
    "sg:postcode":"55345",
    "sg:province":"MN",
    "sg:tags":[
        "public",
        "relations"
    ],
    "wof:name":"1st Impression Critiques",
    "wof:placetype":"venue"
},
  "geometry": {"coordinates":[-93.47748799999999,44.932031],"type":"Point"}
}