{
  "type": "Feature",
  "properties": {
    "addr:full":"38245 30th Ave Isle MN 56342",
    "addr:housenumber":"38245",
    "addr:postcode":"56342",
    "addr:street":"30Th Ave Isle",
    "iso:country":"US",
    "sg:address":"38245 30th Ave",
    "sg:city":"Isle",
    "sg:classifiers":[
        {
            "category":"Shopping",
            "subcategory":"Used Merchandise",
            "type":"Retail Goods"
        }
    ],
    "sg:phone":"+1 320 676 1234",
    "sg:postcode":"56342",
    "sg:province":"MN",
    "sg:tags":[
        "book",
        "rare",
        "dealer"
    ],
    "wof:name":"These Old Books",
    "wof:placetype":"venue"
},
  "geometry": {"coordinates":[-93.473623,46.103356],"type":"Point"}
}