{
  "type": "Feature",
  "properties": {
    "iso:country":"US",
    "sg:address":"20260 Oxboro Ln N",
    "sg:city":"Marine On Saint Croix",
    "sg:classifiers":[
        {
            "category":"Retail",
            "subcategory":"Repair Shop",
            "type":"Services"
        }
    ],
    "sg:phone":"+1 651 773 5422",
    "sg:postcode":"55047",
    "sg:province":"MN",
    "sg:tags":[
        "control",
        "pr",
        "industrial",
        "for",
        "mfg",
        "instrument"
    ],
    "wof:name":"Cie",
    "wof:placetype":"venue"
},
  "geometry": {"coordinates":[-92.79986599999999,45.243407],"type":"Point"}
}