{
  "type": "Feature",
  "properties": {
    "iso:country":"US",
    "sg:address":"235 N Main St",
    "sg:city":"Wahkon",
    "sg:classifiers":[
        {
            "category":"Travel",
            "subcategory":"Bed & Breakfast",
            "type":"Entertainment"
        }
    ],
    "sg:phone":"+1 320 495 3304",
    "sg:postcode":"56386",
    "sg:province":"MN",
    "sg:tags":[
        "inn"
    ],
    "wof:name":"Wahkon Inn",
    "wof:placetype":"venue"
},
  "geometry": {"coordinates":[-93.521049,46.119576],"type":"Point"}
}