{
  "type": "Feature",
  "properties": {
    "addr:full":"9762 102nd Ave N Osseo MN 55369",
    "addr:housenumber":"9762",
    "addr:postcode":"55369",
    "addr:street":"102Nd Ave N",
    "iso:country":"US",
    "sg:address":"9762 102nd Ave N",
    "sg:city":"Osseo",
    "sg:classifiers":[
        {
            "category":"Building & Trades",
            "subcategory":"Landscaping Services",
            "type":"Services"
        }
    ],
    "sg:phone":"+1 763 425 6461",
    "sg:postcode":"55369",
    "sg:province":"MN",
    "wof:name":"Done Right Landscaping",
    "wof:placetype":"venue"
},
  "geometry": {"coordinates":[-93.40446,45.139698],"type":"Point"}
}