{
  "type": "Feature",
  "properties": {
    "addr:full":"600 9th St Howard Lake MN 55349",
    "addr:housenumber":"600",
    "addr:postcode":"55349",
    "addr:street":"9Th St",
    "iso:country":"US",
    "sg:address":"600 9th St",
    "sg:city":"Howard Lake",
    "sg:classifiers":[
        {
            "category":"Organizations",
            "subcategory":"Religious Organization",
            "type":"Services"
        }
    ],
    "sg:phone":"+1 320 543 2196",
    "sg:postcode":"55349",
    "sg:province":"MN",
    "sg:tags":[
        "church"
    ],
    "wof:name":"Blessed Hope Church",
    "wof:placetype":"venue"
},
  "geometry": {"coordinates":[-94.068833,45.057613],"type":"Point"}
}