{
  "type": "Feature",
  "properties": {
    "iso:country":"US",
    "sg:address":"5805 Krueger Ln",
    "sg:city":"Stillwater",
    "sg:classifiers":[
        {
            "category":"Shopping",
            "subcategory":"Department Store",
            "type":"Retail Goods"
        }
    ],
    "sg:phone":"+1 651 439 2256",
    "sg:postcode":"55082",
    "sg:province":"MN",
    "sg:website":"http://www.kohls.com",
    "wof:name":"Kohl's",
    "wof:placetype":"venue"
},
  "geometry": {"coordinates":[-92.837968,45.032371],"type":"Point"}
}