{
  "type": "Feature",
  "properties": {
    "iso:country":"US",
    "sg:address":"3240 Owasso Heights Rd",
    "sg:city":"Shoreview",
    "sg:classifiers":[
        {
            "category":"Professional",
            "type":"Services"
        },
        {
            "category":"Personal",
            "subcategory":"Beauty Salon",
            "type":"Services"
        }
    ],
    "sg:phone":"+1 651 486 2922",
    "sg:postcode":"55126",
    "sg:province":"MN",
    "sg:tags":[
        "shop",
        "writer"
    ],
    "sg:website":"www.2hc.com",
    "wof:name":"2 Heads Communications Inc",
    "wof:placetype":"venue"
},
  "geometry": {"coordinates":[-93.126462,45.039744],"type":"Point"}
}