{
  "type": "Feature",
  "properties": {
    "iso:country":"US",
    "sg:address":"11 E Riverside Ave",
    "sg:city":"Melrose",
    "sg:classifiers":[
        {
            "category":"Social Services",
            "subcategory":"Adult Care",
            "type":"Services"
        }
    ],
    "sg:phone":"+1 320 256 4333",
    "sg:postcode":"56352",
    "sg:province":"MN",
    "sg:tags":[
        "home",
        "group"
    ],
    "wof:name":"Quality Care Homes Inc",
    "wof:placetype":"venue"
},
  "geometry": {"coordinates":[-94.814091,45.67608],"type":"Point"}
}