{
  "type": "Feature",
  "properties": {
    "addr:full":"33711 340th St NW Argyle MN 56713",
    "addr:housenumber":"33711",
    "addr:postcode":"56713",
    "addr:street":"340Th St Nw",
    "iso:country":"US",
    "sg:address":"33711 340th St NW",
    "sg:city":"Argyle",
    "sg:classifiers":[
        {
            "category":"Farming",
            "subcategory":"Farm",
            "type":"Manufacturing & Wholesale Goods"
        }
    ],
    "sg:phone":"+1 218 437 8583",
    "sg:postcode":"56713",
    "sg:province":"MN",
    "sg:tags":[
        "crop",
        "general"
    ],
    "wof:name":"DLS Farms Inc",
    "wof:placetype":"venue"
},
  "geometry": {"coordinates":[-96.776425,48.369725],"type":"Point"}
}