{
  "type": "Feature",
  "properties": {
    "addr:full":"3605 Hwy 52 N Rochester MN 55901",
    "addr:housenumber":"3605",
    "addr:postcode":"55901",
    "addr:street":"Hwy 52 N",
    "iso:country":"US",
    "sg:address":"3605 Hwy 52 N",
    "sg:city":"Rochester",
    "sg:classifiers":[
        {
            "category":"Professional",
            "subcategory":"Computer Services",
            "type":"Services"
        }
    ],
    "sg:phone":"+1 507 529 9372",
    "sg:postcode":"55901",
    "sg:province":"MN",
    "sg:tags":[
        "consultant",
        "designer"
    ],
    "wof:name":"MC2",
    "wof:placetype":"venue"
},
  "geometry": {"coordinates":[-92.496684,44.059033],"type":"Point"}
}