{
  "type": "Feature",
  "properties": {
    "iso:country":"US",
    "sg:address":"420 N Main St",
    "sg:city":"Le Sueur",
    "sg:classifiers":[
        {
            "category":"Autos & Motor Vehicles",
            "subcategory":"Fuel & Gas Station",
            "type":"Retail Goods"
        }
    ],
    "sg:phone":"+1 507 665 6061",
    "sg:postcode":"56058",
    "sg:province":"MN",
    "sg:tags":[
        "grocery"
    ],
    "wof:name":"Holiday Stationstores 233",
    "wof:placetype":"venue"
},
  "geometry": {"coordinates":[-93.91258999999999,44.465011],"type":"Point"}
}