{
  "type": "Feature",
  "properties": {
    "iso:country":"US",
    "sg:address":"1 Oakridge Dr",
    "sg:city":"Chaska",
    "sg:classifiers":[
        {
            "category":"Travel",
            "subcategory":"Hotels & Motels",
            "type":"Entertainment"
        },
        {
            "category":"Banks & Credit Unions",
            "subcategory":"Investment Brokerage",
            "type":"Services"
        }
    ],
    "sg:phone":"+1 612 338 9245",
    "sg:postcode":"55318",
    "sg:province":"MN",
    "sg:tags":[
        "investing"
    ],
    "wof:name":"American Express Financial Advisors",
    "wof:placetype":"venue"
},
  "geometry": {"coordinates":[-93.601501,44.838799],"type":"Point"}
}