{
  "type": "Feature",
  "properties": {
    "addr:full":"141 S 8th St Bird Island MN 55310",
    "addr:housenumber":"141",
    "addr:postcode":"55310",
    "addr:street":"S 8Th St",
    "iso:country":"US",
    "sg:address":"141 S 8th St",
    "sg:city":"Bird Island",
    "sg:classifiers":[
        {
            "category":"Building & Trades",
            "subcategory":"Electrical",
            "type":"Services"
        }
    ],
    "sg:phone":"+1 320 365 4198",
    "sg:postcode":"55310",
    "sg:province":"MN",
    "sg:tags":[
        "electric",
        "contractor"
    ],
    "wof:name":"Ewers Electric",
    "wof:placetype":"venue"
},
  "geometry": {"coordinates":[-94.89635199999999,44.767097],"type":"Point"}
}