{
  "type": "Feature",
  "properties": {
    "iso:country":"US",
    "sg:address":"2002 2nd St SW",
    "sg:city":"Rochester",
    "sg:classifiers":[
        {
            "category":"Organizations",
            "subcategory":"Community Association",
            "type":"Services"
        }
    ],
    "sg:phone":"+1 507 289 8263",
    "sg:postcode":"55902",
    "sg:province":"MN",
    "sg:tags":[
        "fraternal"
    ],
    "wof:name":"Rochester Scottish Rite Bodies",
    "wof:placetype":"venue"
},
  "geometry": {"coordinates":[-92.495249,44.021524],"type":"Point"}
}