{
  "type": "Feature",
  "properties": {
    "iso:country":"US",
    "sg:address":"210 7th Ave N",
    "sg:city":"Hopkins",
    "sg:classifiers":[
        {
            "category":"Banks & Credit Unions",
            "subcategory":"Bank",
            "type":"Services"
        }
    ],
    "sg:phone":"+1 952 938 5997",
    "sg:postcode":"55343",
    "sg:province":"MN",
    "sg:tags":[
        "short",
        "institution",
        "business"
    ],
    "wof:name":"Accountable Funding",
    "wof:placetype":"venue"
},
  "geometry": {"coordinates":[-93.408551,44.929532],"type":"Point"}
}