{
  "type": "Feature",
  "properties": {
    "iso:country":"US",
    "sg:address":"9205 Lexington Ave N",
    "sg:city":"Circle Pines",
    "sg:classifiers":[
        {
            "category":"Professional",
            "subcategory":"Accounting & Tax Preparation",
            "type":"Services"
        }
    ],
    "sg:phone":"+1 763 784 4842",
    "sg:postcode":"55014",
    "sg:province":"MN",
    "sg:tags":[
        "accountant"
    ],
    "wof:name":"Accounting Associates Inc",
    "wof:placetype":"venue"
},
  "geometry": {"coordinates":[-93.163674,45.139675],"type":"Point"}
}