{
  "type": "Feature",
  "properties": {
    "iso:country":"US",
    "sg:address":"654 Roundhouse St",
    "sg:city":"Shakopee",
    "sg:classifiers":[
        {
            "category":"Taxi",
            "type":"Transportation"
        }
    ],
    "sg:phone":"+1 952 403 9750",
    "sg:postcode":"55379",
    "sg:province":"MN",
    "wof:name":"Shakopee Taxi",
    "wof:placetype":"venue"
},
  "geometry": {"coordinates":[-93.504576,44.794272],"type":"Point"}
}