{
  "type": "Feature",
  "properties": {
    "iso:country":"US",
    "sg:address":"10827 53rd Ave N",
    "sg:city":"Minneapolis",
    "sg:classifiers":[
        {
            "category":"Manufacturing",
            "subcategory":"Textiles",
            "type":"Manufacturing & Wholesale Goods"
        },
        {
            "category":"Building & Trades",
            "subcategory":"Construction",
            "type":"Services"
        }
    ],
    "sg:phone":"+1 763 557 6539",
    "sg:postcode":"55442",
    "sg:province":"MN",
    "sg:tags":[
        "tile-wholesale",
        "manufacturer",
        "tile-contractors"
    ],
    "wof:name":"Charles Lemieux",
    "wof:placetype":"venue"
},
  "geometry": {"coordinates":[-93.41811,45.050896],"type":"Point"}
}