{
  "type": "Feature",
  "properties": {
    "addr:full":"250 2nd Ave NE Cambridge MN 55008",
    "addr:housenumber":"250",
    "addr:postcode":"55008",
    "addr:street":"2Nd Ave Ne",
    "iso:country":"US",
    "sg:address":"250 2nd Ave NE",
    "sg:city":"Cambridge",
    "sg:classifiers":[
        {
            "category":"Banks & Credit Unions",
            "subcategory":"Bank",
            "type":"Services"
        }
    ],
    "sg:phone":"+1 763 689 4440",
    "sg:postcode":"55008",
    "sg:province":"MN",
    "sg:tags":[
        "national",
        "commercial"
    ],
    "wof:name":"Wells Fargo",
    "wof:placetype":"venue"
},
  "geometry": {"coordinates":[-93.222183,45.57373],"type":"Point"}
}