{
  "type": "Feature",
  "properties": {
    "iso:country":"US",
    "sg:address":"1001 Marquette Ave",
    "sg:city":"Minneapolis",
    "sg:classifiers":[
        {
            "category":"Travel",
            "subcategory":"Travel Agent",
            "type":"Entertainment"
        }
    ],
    "sg:phone":"+1 612 204 8928",
    "sg:postcode":"55403",
    "sg:province":"MN",
    "sg:tags":[
        "agency",
        "services-commercial"
    ],
    "wof:name":"Travel Traders",
    "wof:placetype":"venue"
},
  "geometry": {"coordinates":[-93.27330000000001,44.973412],"type":"Point"}
}