{
  "type": "Feature",
  "properties": {
    "addr:full":"1298 60th Ave SW Rochester MN 55902",
    "addr:housenumber":"1298",
    "addr:postcode":"55902",
    "addr:street":"60Th Ave Sw",
    "iso:country":"US",
    "sg:address":"1298 60th Ave SW",
    "sg:city":"Rochester",
    "sg:classifiers":[
        {
            "category":"Real Estate",
            "subcategory":"Real Estate Operator",
            "type":"Services"
        }
    ],
    "sg:phone":"+1 507 529 0657",
    "sg:postcode":"55902",
    "sg:province":"MN",
    "sg:tags":[
        "building",
        "nonresidential"
    ],
    "wof:name":"Eg Properties LLC",
    "wof:placetype":"venue"
},
  "geometry": {"coordinates":[-92.558055,44.00339],"type":"Point"}
}