{
  "type": "Feature",
  "properties": {
    "iso:country":"US",
    "sg:address":"600 Weir Dr",
    "sg:city":"Saint Paul",
    "sg:classifiers":[
        {
            "category":"Education",
            "subcategory":"School",
            "type":"Public Place"
        }
    ],
    "sg:phone":"+1 651 264 3500",
    "sg:postcode":"55125",
    "sg:province":"MN",
    "wof:name":"Crosswinds Middle School",
    "wof:placetype":"venue"
},
  "geometry": {"coordinates":[-92.964686,44.93781],"type":"Point"}
}