{
  "type": "Feature",
  "properties": {
    "addr:full":"5501 Opportunity Ct Hopkins MN 55343",
    "addr:housenumber":"5501",
    "addr:postcode":"55343",
    "addr:street":"Opportunity Ct",
    "iso:country":"US",
    "sg:address":"5501 Opportunity Ct",
    "sg:city":"Hopkins",
    "sg:classifiers":[
        {
            "category":"Wholesale",
            "subcategory":"Seafood",
            "type":"Manufacturing & Wholesale Goods"
        }
    ],
    "sg:phone":"+1 952 935 3474",
    "sg:postcode":"55343",
    "sg:province":"MN",
    "sg:tags":[
        "packaged",
        "restaurant"
    ],
    "wof:name":"American Fish & Seafood, Inc.",
    "wof:placetype":"venue"
},
  "geometry": {"coordinates":[-93.404006,44.903172],"type":"Point"}
}