{
  "type": "Feature",
  "properties": {
    "addr:full":"11574 State Hwy 70 Pine City MN 55063",
    "addr:housenumber":"11574",
    "addr:postcode":"55063",
    "addr:street":"State Hwy 70 Pine",
    "iso:country":"US",
    "sg:address":"11574 State Hwy 70",
    "sg:city":"Pine City",
    "sg:classifiers":[
        {
            "category":"Building & Trades",
            "subcategory":"Construction",
            "type":"Services"
        }
    ],
    "sg:phone":"+1 320 629 1318",
    "sg:postcode":"55063",
    "sg:province":"MN",
    "sg:tags":[
        "contractor"
    ],
    "wof:name":"Rolling Rock Landscaping Inc",
    "wof:placetype":"venue"
},
  "geometry": {"coordinates":[-92.868853,45.773345],"type":"Point"}
}