{
  "type": "Feature",
  "properties": {
    "addr:full":"810 4th Ave S Suite 141 Moorhead MN 56560",
    "addr:housenumber":"810",
    "addr:postcode":"56560",
    "addr:street":"4Th Ave S Suite 141",
    "iso:country":"US",
    "sg:address":"810 4th Ave S Suite 141",
    "sg:city":"Moorhead",
    "sg:classifiers":[
        {
            "category":"Professional",
            "subcategory":"Management & Consulting",
            "type":"Services"
        }
    ],
    "sg:phone":"+1 218 731 2320",
    "sg:postcode":"56560",
    "sg:province":"MN",
    "sg:tags":[
        "consultant"
    ],
    "sg:website":"http://www.drcccounseling.com",
    "wof:name":"Conventional Corporate Coaching",
    "wof:placetype":"venue"
},
  "geometry": {"coordinates":[-96.767679,46.870684],"type":"Point"}
}