{
  "type": "Feature",
  "properties": {
    "addr:full":"320 5th St Moose Lake MN 55767",
    "addr:housenumber":"320",
    "addr:postcode":"55767",
    "addr:street":"5Th St",
    "iso:country":"US",
    "sg:address":"320 5th St",
    "sg:city":"Moose Lake",
    "sg:classifiers":[
        {
            "category":"Shopping",
            "subcategory":"Gifts & Souvenirs",
            "type":"Retail Goods"
        }
    ],
    "sg:phone":"+1 218 485 4832",
    "sg:postcode":"55767",
    "sg:province":"MN",
    "sg:tags":[
        "cards",
        "greeting"
    ],
    "wof:name":"Gramma's Attic",
    "wof:placetype":"venue"
},
  "geometry": {"coordinates":[-92.76006700000001,46.454801],"type":"Point"}
}