{
  "type": "Feature",
  "properties": {
    "addr:full":"205 Broadway Ave N Cokato MN 55321",
    "addr:housenumber":"205",
    "addr:postcode":"55321",
    "addr:street":"Broadway Ave N",
    "iso:country":"US",
    "sg:address":"205 Broadway Ave N",
    "sg:city":"Cokato",
    "sg:classifiers":[
        {
            "category":"Shopping",
            "subcategory":"Pharmacy",
            "type":"Retail Goods"
        }
    ],
    "sg:phone":"+1 320 286 5618",
    "sg:postcode":"55321",
    "sg:province":"MN",
    "wof:name":"Keaveny Thrifty White Drug",
    "wof:placetype":"venue"
},
  "geometry": {"coordinates":[-94.19,45.083655],"type":"Point"}
}