{
  "type": "Feature",
  "properties": {
    "addr:full":"715 5th St N Stillwater MN 55082",
    "addr:housenumber":"715",
    "addr:postcode":"55082",
    "addr:street":"5Th St N",
    "iso:country":"US",
    "sg:address":"715 5th St N",
    "sg:city":"Stillwater",
    "sg:classifiers":[
        {
            "category":"Professional",
            "subcategory":"Business Services",
            "type":"Services"
        }
    ],
    "sg:phone":"+1 651 430 9639",
    "sg:postcode":"55082",
    "sg:province":"MN",
    "sg:tags":[
        "interior",
        "consultant",
        "design",
        "decorator"
    ],
    "wof:name":"Mary's Finishing Touch",
    "wof:placetype":"venue"
},
  "geometry": {"coordinates":[-92.813716,45.061309],"type":"Point"}
}