{
  "type": "Feature",
  "properties": {
    "addr:full":"34232 Co Rd 155 Avon MN 56310",
    "addr:housenumber":"34232",
    "addr:postcode":"56310",
    "addr:street":"Co Rd 155",
    "iso:country":"US",
    "sg:address":"34232 Co Rd 155",
    "sg:city":"Avon",
    "sg:classifiers":[
        {
            "category":"Social Services",
            "subcategory":"Child Care",
            "type":"Services"
        }
    ],
    "sg:phone":"+1 320 356 7687",
    "sg:postcode":"56310",
    "sg:province":"MN",
    "sg:tags":[
        "daycare",
        "provider"
    ],
    "wof:name":"Deloris Nelson",
    "wof:placetype":"venue"
},
  "geometry": {"coordinates":[-94.444227,45.616202],"type":"Point"}
}