{
  "type": "Feature",
  "properties": {
    "addr:full":"156 E Maine St Amboy MN 56010",
    "addr:housenumber":"156",
    "addr:postcode":"56010",
    "addr:street":"E Maine St",
    "iso:country":"US",
    "sg:address":"156 E Maine St",
    "sg:city":"Amboy",
    "sg:classifiers":[
        {
            "category":"Banks & Credit Unions",
            "subcategory":"Bank",
            "type":"Services"
        }
    ],
    "sg:phone":"+1 507 674 3030",
    "sg:postcode":"56010",
    "sg:province":"MN",
    "sg:tags":[
        "institution",
        "business"
    ],
    "wof:name":"First Insurance",
    "wof:placetype":"venue"
},
  "geometry": {"coordinates":[-94.157786,43.888016],"type":"Point"}
}