{
  "type": "Feature",
  "properties": {
    "iso:country":"US",
    "sg:address":"5389 Maple Ridge Ct",
    "sg:city":"Hopkins",
    "sg:classifiers":[
        {
            "category":"Manufacturing",
            "subcategory":"Furniture",
            "type":"Manufacturing & Wholesale Goods"
        }
    ],
    "sg:phone":"+1 952 931 9393",
    "sg:postcode":"55343",
    "sg:province":"MN",
    "sg:tags":[
        "mfg"
    ],
    "wof:name":"Rileys Restful Sleep Products",
    "wof:placetype":"venue"
},
  "geometry": {"coordinates":[-93.43893,44.905517],"type":"Point"}
}