{
  "type": "Feature",
  "properties": {
    "iso:country":"US",
    "sg:address":"5835 Lyndale Ave S",
    "sg:city":"Minneapolis",
    "sg:classifiers":[
        {
            "category":"Organizations",
            "subcategory":"Religious Organization",
            "type":"Services"
        }
    ],
    "sg:phone":"+1 612 869 2616",
    "sg:postcode":"55419",
    "sg:province":"MN",
    "sg:tags":[
        "church"
    ],
    "wof:name":"Great Love Mission Church",
    "wof:placetype":"venue"
},
  "geometry": {"coordinates":[-93.28823800000001,44.896679],"type":"Point"}
}