{
  "type": "Feature",
  "properties": {
    "addr:full":"13 7th St S Minneapolis MN 55402",
    "addr:housenumber":"13",
    "addr:postcode":"55402",
    "addr:street":"7Th St S",
    "iso:country":"US",
    "sg:address":"13 7th St S",
    "sg:city":"Minneapolis",
    "sg:classifiers":[
        {
            "category":"Shopping",
            "subcategory":"Clothing, Apparel, & Fashions",
            "type":"Retail Goods"
        }
    ],
    "sg:phone":"+1 612 371 4775",
    "sg:postcode":"55402",
    "sg:province":"MN",
    "sg:tags":[
        "specialty"
    ],
    "wof:name":"J J Flash",
    "wof:placetype":"venue"
},
  "geometry": {"coordinates":[-93.27224,44.976867],"type":"Point"}
}