{
  "type": "Feature",
  "properties": {
    "iso:country":"US",
    "sg:address":"5422 Hwy 71 NE",
    "sg:city":"Bemidji",
    "sg:classifiers":[
        {
            "category":"Retail",
            "subcategory":"Auto Repair",
            "type":"Services"
        }
    ],
    "sg:phone":"+1 218 759 8554",
    "sg:postcode":"56601",
    "sg:province":"MN",
    "sg:tags":[
        "body",
        "automobile",
        "painting"
    ],
    "wof:name":"Stretch Auto Body & Repair",
    "wof:placetype":"venue"
},
  "geometry": {"coordinates":[-94.906012,47.513198],"type":"Point"}
}