{
  "type": "Feature",
  "properties": {
    "iso:country":"US",
    "sg:address":"9325 4th Ave S",
    "sg:city":"Minneapolis",
    "sg:classifiers":[
        {
            "category":"Real Estate",
            "subcategory":"Real Estate Operator",
            "type":"Services"
        }
    ],
    "sg:phone":"+1 952 881 1854",
    "sg:postcode":"55420",
    "sg:province":"MN",
    "sg:tags":[
        "property",
        "lessor"
    ],
    "wof:name":"Jon Sostarich",
    "wof:placetype":"venue"
},
  "geometry": {"coordinates":[-93.27074399999999,44.835762],"type":"Point"}
}