{
  "type": "Feature",
  "properties": {
    "iso:country":"US",
    "sg:address":"1024 7th Ave",
    "sg:city":"Worthington",
    "sg:classifiers":[
        {
            "category":"Health Services",
            "subcategory":"Hospital",
            "type":"Services"
        }
    ],
    "sg:phone":"+1 507 376 4141",
    "sg:postcode":"56187",
    "sg:province":"MN",
    "sg:tags":[
        "mental"
    ],
    "wof:name":"Southwestern Mental Health Inc",
    "wof:placetype":"venue"
},
  "geometry": {"coordinates":[-95.59959600000001,43.62282],"type":"Point"}
}