{
  "type": "Feature",
  "properties": {
    "addr:full":"21540 141st Ave N Rogers MN 55374",
    "addr:housenumber":"21540",
    "addr:postcode":"55374",
    "addr:street":"141St Ave N",
    "iso:country":"US",
    "sg:address":"21540 141st Ave N",
    "sg:city":"Rogers",
    "sg:classifiers":[
        {
            "category":"Wholesale",
            "subcategory":"Machinery & Supplies",
            "type":"Manufacturing & Wholesale Goods"
        }
    ],
    "sg:phone":"+1 763 428 4870",
    "sg:postcode":"55374",
    "sg:province":"MN",
    "sg:tags":[
        "equipment"
    ],
    "wof:name":"Rogers & Hanover Self Storage",
    "wof:placetype":"venue"
},
  "geometry": {"coordinates":[-93.55372300000001,45.210428],"type":"Point"}
}