{
  "type": "Feature",
  "properties": {
    "addr:full":"2088 Co Rd 88 SW Alexandria MN 56308",
    "addr:housenumber":"2088",
    "addr:postcode":"56308",
    "addr:street":"Co Rd 88 Sw",
    "iso:country":"US",
    "sg:address":"2088 Co Rd 88 SW",
    "sg:city":"Alexandria",
    "sg:classifiers":[
        {
            "category":"Building & Trades",
            "subcategory":"Construction",
            "type":"Services"
        }
    ],
    "sg:phone":"+1 320 283 6102",
    "sg:postcode":"56308",
    "sg:province":"MN",
    "sg:tags":[
        "downspouts",
        "gutter",
        "contractor"
    ],
    "wof:name":"All Seamless Rain Gutters",
    "wof:placetype":"venue"
},
  "geometry": {"coordinates":[-95.409198,45.759907],"type":"Point"}
}