{
  "type": "Feature",
  "properties": {
    "addr:full":"2420 4th Ave Anoka MN 55303",
    "addr:housenumber":"2420",
    "addr:postcode":"55303",
    "addr:street":"4Th Ave",
    "iso:country":"US",
    "sg:address":"2420 4th Ave",
    "sg:city":"Anoka",
    "sg:classifiers":[
        {
            "category":"Professional",
            "subcategory":"Business Services",
            "type":"Services"
        }
    ],
    "sg:phone":"+1 763 421 1313",
    "sg:postcode":"55303",
    "sg:province":"MN",
    "wof:name":"Tom McFarland",
    "wof:placetype":"venue"
},
  "geometry": {"coordinates":[-93.385293,45.203709],"type":"Point"}
}