{
  "type": "Feature",
  "properties": {
    "addr:full":"6738 20th Ave S Hugo MN 55038",
    "addr:housenumber":"6738",
    "addr:postcode":"55038",
    "addr:street":"20Th Ave S Hugo",
    "iso:country":"US",
    "sg:address":"6738 20th Ave S",
    "sg:city":"Hugo",
    "sg:classifiers":[
        {
            "category":"Building & Trades",
            "subcategory":"Cleaning & Sanitation",
            "type":"Services"
        }
    ],
    "sg:phone":"+1 651 426 0786",
    "sg:postcode":"55038",
    "sg:province":"MN",
    "sg:tags":[
        "maintenance"
    ],
    "wof:name":"Dirt Busters Power Washing",
    "wof:placetype":"venue"
},
  "geometry": {"coordinates":[-93.04076499999999,45.150929],"type":"Point"}
}