{
  "type": "Feature",
  "properties": {
    "addr:full":"1650 Park Place Blvd Minneapolis MN 55416",
    "addr:housenumber":"1650",
    "addr:postcode":"55416",
    "addr:street":"Park Place Blvd",
    "iso:country":"US",
    "sg:address":"1650 Park Place Blvd",
    "sg:city":"Minneapolis",
    "sg:classifiers":[
        {
            "category":"Food & Beverages",
            "subcategory":"Specialty",
            "type":"Retail Goods"
        }
    ],
    "sg:phone":"+1 763 417 0550",
    "sg:postcode":"55416",
    "sg:province":"MN",
    "wof:name":"G N C General Nutrition Center",
    "wof:placetype":"venue"
},
  "geometry": {"coordinates":[-93.349225,44.963191],"type":"Point"}
}