{
  "type": "Feature",
  "properties": {
    "iso:country":"US",
    "sg:address":"4345 Vivian Ave",
    "sg:city":"Saint Paul",
    "sg:classifiers":[
        {
            "category":"Professional",
            "subcategory":"Computer Services",
            "type":"Services"
        }
    ],
    "sg:phone":"+1 651 484 7982",
    "sg:postcode":"55126",
    "sg:province":"MN",
    "sg:tags":[
        "related"
    ],
    "wof:name":"Objective Resources Inc",
    "wof:placetype":"venue"
},
  "geometry": {"coordinates":[-93.137681,45.072974],"type":"Point"}
}