{
  "type": "Feature",
  "properties": {
    "iso:country":"US",
    "sg:address":"24033 N Isaac Lake Ln",
    "sg:city":"Bovey",
    "sg:classifiers":[
        {
            "category":"Travel",
            "subcategory":"Hotels & Motels",
            "type":"Entertainment"
        }
    ],
    "sg:phone":"+1 218 245 3675",
    "sg:postcode":"55709",
    "sg:province":"MN",
    "sg:tags":[
        "operation",
        "carpentry",
        "contractor"
    ],
    "wof:name":"Creative Cabins Inc",
    "wof:placetype":"venue"
},
  "geometry": {"coordinates":[-93.366241,47.489826],"type":"Point"}
}