{
  "type": "Feature",
  "properties": {
    "iso:country":"US",
    "sg:address":"3333 Co Rd 101",
    "sg:city":"Wayzata",
    "sg:classifiers":[
        {
            "category":"Retail",
            "subcategory":"Auto Repair",
            "type":"Services"
        }
    ],
    "sg:phone":"+1 952 473 3001",
    "sg:postcode":"55391",
    "sg:province":"MN",
    "sg:tags":[
        "repairing",
        "automobile"
    ],
    "wof:name":"Leighton's Garage",
    "wof:placetype":"venue"
},
  "geometry": {"coordinates":[-93.502205,44.943174],"type":"Point"}
}