{
  "type": "Feature",
  "properties": {
    "addr:full":"114 5th Ave E Ellendale MN 56026",
    "addr:housenumber":"114",
    "addr:postcode":"56026",
    "addr:street":"5Th Ave E",
    "iso:country":"US",
    "sg:address":"114 5th Ave E",
    "sg:city":"Ellendale",
    "sg:classifiers":[
        {
            "category":"Professional",
            "subcategory":"Accounting & Tax Preparation",
            "type":"Services"
        }
    ],
    "sg:phone":"+1 507 684 3840",
    "sg:postcode":"56026",
    "sg:province":"MN",
    "sg:tags":[
        "return",
        "preparation-business"
    ],
    "wof:name":"Ellendale Tax Center Inc",
    "wof:placetype":"venue"
},
  "geometry": {"coordinates":[-93.30446600000001,43.874889],"type":"Point"}
}