{
  "type": "Feature",
  "properties": {
    "addr:full":"102 5th St NW Dilworth MN 56529",
    "addr:housenumber":"102",
    "addr:postcode":"56529",
    "addr:street":"5Th St Nw",
    "iso:country":"US",
    "sg:address":"102 5th St NW",
    "sg:city":"Dilworth",
    "sg:classifiers":[
        {
            "category":"Professional",
            "type":"Services"
        }
    ],
    "sg:phone":"+1 218 236 8944",
    "sg:postcode":"56529",
    "sg:province":"MN",
    "wof:name":"Kellie Jenkins",
    "wof:placetype":"venue"
},
  "geometry": {"coordinates":[-96.710565,46.878489],"type":"Point"}
}