{
  "type": "Feature",
  "properties": {
    "iso:country":"US",
    "sg:address":"6100 Industry Ave",
    "sg:city":"Anoka",
    "sg:classifiers":[
        {
            "category":"Manufacturing",
            "subcategory":"Glass & Minerals",
            "type":"Manufacturing & Wholesale Goods"
        }
    ],
    "sg:phone":"+1 763 427 7630",
    "sg:postcode":"55303",
    "sg:province":"MN",
    "sg:tags":[
        "ready",
        "concrete",
        "mfg"
    ],
    "wof:name":"Aggregate Industries Inc",
    "wof:placetype":"venue"
},
  "geometry": {"coordinates":[-93.42070099999999,45.226533],"type":"Point"}
}