{
  "type": "Feature",
  "properties": {
    "iso:country":"US",
    "sg:address":"1710 Spring Lake Cir",
    "sg:city":"Jordan",
    "sg:classifiers":[
        {
            "category":"Shopping",
            "subcategory":"Computers & Home Electronics",
            "type":"Retail Goods"
        }
    ],
    "sg:phone":"+1 952 440 8271",
    "sg:postcode":"55352",
    "sg:province":"MN",
    "wof:name":"G & M Computer Services",
    "wof:placetype":"venue"
},
  "geometry": {"coordinates":[-93.48653899999999,44.69075],"type":"Point"}
}