{
  "type": "Feature",
  "properties": {
    "addr:full":"2510 Mayfair St SE Rochester MN 55904",
    "addr:housenumber":"2510",
    "addr:postcode":"55904",
    "addr:street":"Mayfair St Se",
    "iso:country":"US",
    "sg:address":"2510 Mayfair St SE",
    "sg:city":"Rochester",
    "sg:classifiers":[
        {
            "category":"Professional",
            "subcategory":"Credit Reporting & Collection",
            "type":"Services"
        }
    ],
    "sg:phone":"+1 507 285 5691",
    "sg:postcode":"55904",
    "sg:province":"MN",
    "wof:name":"Broadcast Credit Reporting",
    "wof:placetype":"venue"
},
  "geometry": {"coordinates":[-92.42652200000001,43.998515],"type":"Point"}
}