{
  "type": "Feature",
  "properties": {
    "addr:full":"14750 Lac Lavon Dr Burnsville MN 55306",
    "addr:housenumber":"14750",
    "addr:postcode":"55306",
    "addr:street":"Lac Lavon Dr",
    "iso:country":"US",
    "sg:address":"14750 Lac Lavon Dr",
    "sg:city":"Burnsville",
    "sg:classifiers":[
        {
            "category":"Banks & Credit Unions",
            "subcategory":"Bank",
            "type":"Services"
        }
    ],
    "sg:phone":"+1 952 224 2510",
    "sg:postcode":"55306",
    "sg:province":"MN",
    "sg:tags":[
        "company",
        "mortgage"
    ],
    "wof:name":"Lakeland Mortgage Corporation",
    "wof:placetype":"venue"
},
  "geometry": {"coordinates":[-93.25830499999999,44.733983],"type":"Point"}
}