{
  "type": "Feature",
  "properties": {
    "addr:full":"7800 Metro Pkwy Bloomington MN 55425",
    "addr:postcode":"7800;55425",
    "addr:street":"Metro Pkwy",
    "iso:country":"US",
    "sg:address":"7800 Metro Pkwy",
    "sg:city":"Bloomington",
    "sg:classifiers":[
        {
            "category":"Organizations",
            "subcategory":"Non-profit Organization",
            "type":"Services"
        }
    ],
    "sg:phone":"+1 952 854 8300",
    "sg:postcode":"55425",
    "sg:province":"MN",
    "sg:website":"www.psai.org",
    "wof:name":"Portable Sanitation Assn Intl",
    "wof:placetype":"venue"
},
  "geometry": {"coordinates":[-93.229148,44.860199],"type":"Point"}
}