{
  "type": "Feature",
  "properties": {
    "addr:full":"161 10th St Albany MN 56307",
    "addr:housenumber":"161",
    "addr:postcode":"56307",
    "addr:street":"10Th St",
    "iso:country":"US",
    "sg:address":"161 10th St",
    "sg:city":"Albany",
    "sg:classifiers":[
        {
            "category":"Manufacturing",
            "subcategory":"Printing",
            "type":"Manufacturing & Wholesale Goods"
        }
    ],
    "sg:phone":"+1 320 845 7255",
    "sg:postcode":"56307",
    "sg:province":"MN",
    "sg:tags":[
        "lithographic",
        "commercial"
    ],
    "wof:name":"Mh Custom Printing",
    "wof:placetype":"venue"
},
  "geometry": {"coordinates":[-94.57669,45.631212],"type":"Point"}
}