{
  "type": "Feature",
  "properties": {
    "addr:full":"219 Broadway Ave S Braham MN 55006",
    "addr:housenumber":"219",
    "addr:postcode":"55006",
    "addr:street":"Broadway Ave S Braham",
    "iso:country":"US",
    "sg:address":"219 Broadway Ave S",
    "sg:city":"Braham",
    "sg:classifiers":[
        {
            "category":"Building & Trades",
            "subcategory":"Plumbing",
            "type":"Services"
        }
    ],
    "sg:phone":"+1 320 396 3045",
    "sg:postcode":"55006",
    "sg:province":"MN",
    "sg:tags":[
        "sheet",
        "work",
        "metal",
        "contractor"
    ],
    "wof:name":"Regent Fab",
    "wof:placetype":"venue"
},
  "geometry": {"coordinates":[-93.172363,45.72373],"type":"Point"}
}