{
  "type": "Feature",
  "properties": {
    "addr:full":"29 9th St N Cloquet MN 55720",
    "addr:housenumber":"29",
    "addr:postcode":"55720",
    "addr:street":"9Th St N",
    "iso:country":"US",
    "sg:address":"29 9th St N",
    "sg:city":"Cloquet",
    "sg:classifiers":[
        {
            "category":"Home & Garden",
            "subcategory":"Furniture",
            "type":"Retail Goods"
        }
    ],
    "sg:phone":"+1 218 878 1515",
    "sg:postcode":"55720",
    "sg:province":"MN",
    "sg:tags":[
        "cabinet"
    ],
    "wof:name":"Miles Custom Cabinetry",
    "wof:placetype":"venue"
},
  "geometry": {"coordinates":[-92.45473,46.722575],"type":"Point"}
}