{
  "type": "Feature",
  "properties": {
    "addr:full":"5025 Cheshire Ln N Minneapolis MN 55446",
    "addr:housenumber":"5025",
    "addr:postcode":"55446",
    "addr:street":"Cheshire Ln N",
    "iso:country":"US",
    "sg:address":"5025 Cheshire Ln N",
    "sg:city":"Minneapolis",
    "sg:classifiers":[
        {
            "category":"Professional",
            "subcategory":"Business Services",
            "type":"Services"
        }
    ],
    "sg:phone":"+1 763 551 9600",
    "sg:postcode":"55446",
    "sg:province":"MN",
    "sg:tags":[
        "design"
    ],
    "wof:name":"Sharp Design",
    "wof:placetype":"venue"
},
  "geometry": {"coordinates":[-93.457694,45.045303],"type":"Point"}
}