{
  "type": "Feature",
  "properties": {
    "addr:full":"11020 Wisconsin Ave N Champlin MN 55316",
    "addr:housenumber":"11020",
    "addr:postcode":"55316",
    "addr:street":"Wisconsin Ave N",
    "iso:country":"US",
    "sg:address":"11020 Wisconsin Ave N",
    "sg:city":"Champlin",
    "sg:classifiers":[
        {
            "category":"Building & Trades",
            "subcategory":"Cleaning & Sanitation",
            "type":"Services"
        }
    ],
    "sg:phone":"+1 763 424 0521",
    "sg:postcode":"55316",
    "sg:province":"MN",
    "sg:tags":[
        "maintenance"
    ],
    "wof:name":"D & S Cleaning",
    "wof:placetype":"venue"
},
  "geometry": {"coordinates":[-93.383281,45.153586],"type":"Point"}
}