{
  "type": "Feature",
  "properties": {
    "addr:full":"187 Cheshire Ln N Minneapolis MN 55441",
    "addr:housenumber":"187",
    "addr:postcode":"55441",
    "addr:street":"Cheshire Ln N",
    "iso:country":"US",
    "sg:address":"187 Cheshire Ln N",
    "sg:city":"Minneapolis",
    "sg:phone":"+1 763 404 1770",
    "sg:postcode":"55441",
    "sg:province":"MN",
    "wof:name":"Red Pepper Chinese Restaurant",
    "wof:placetype":"venue"
},
  "geometry": {"coordinates":[-93.456232,44.980106],"type":"Point"}
}