{
  "type": "Feature",
  "properties": {
    "iso:country":"US",
    "sg:address":"21075 Eaton Ave",
    "sg:city":"Farmington",
    "sg:classifiers":[
        {
            "category":"Home & Garden",
            "subcategory":"Furniture",
            "type":"Retail Goods"
        }
    ],
    "sg:phone":"+1 651 463 3442",
    "sg:postcode":"55024",
    "sg:province":"MN",
    "sg:tags":[
        "cabinet"
    ],
    "wof:name":"Thelen Cabinet Co",
    "wof:placetype":"venue"
},
  "geometry": {"coordinates":[-93.16812899999999,44.643231],"type":"Point"}
}