{
  "type": "Feature",
  "properties": {
    "iso:country":"US",
    "sg:address":"43 Main St SE",
    "sg:city":"Minneapolis",
    "sg:classifiers":[
        {
            "category":"Banks & Credit Unions",
            "subcategory":"Investment Brokerage",
            "type":"Services"
        }
    ],
    "sg:phone":"+1 612 604 1806",
    "sg:postcode":"55414",
    "sg:province":"MN",
    "sg:tags":[
        "advisory"
    ],
    "wof:name":"Masterypoint Financial",
    "wof:placetype":"venue"
},
  "geometry": {"coordinates":[-93.257549,44.985567],"type":"Point"}
}