{
  "type": "Feature",
  "properties": {
    "iso:country":"US",
    "sg:address":"550 W 79th St",
    "sg:city":"Chanhassen",
    "sg:classifiers":[
        {
            "category":"Restaurant",
            "type":"Food & Drink"
        }
    ],
    "sg:phone":"+1 952 934 9453",
    "sg:postcode":"55317",
    "sg:province":"MN",
    "sg:website":"www.buffalowildwings.com",
    "wof:name":"Buffalo Wild Wings Grill & Bar",
    "wof:placetype":"venue"
},
  "geometry": {"coordinates":[-93.533897,44.859299],"type":"Point"}
}