{
  "type": "Feature",
  "properties": {
    "iso:country":"US",
    "sg:address":"10550 Karston Ave NE",
    "sg:city":"Albertville",
    "sg:classifiers":[
        {
            "category":"Wholesale",
            "subcategory":"Hardware",
            "type":"Manufacturing & Wholesale Goods"
        }
    ],
    "sg:phone":"+1 763 497 7900",
    "sg:postcode":"55301",
    "sg:province":"MN",
    "sg:tags":[
        "tool"
    ],
    "wof:name":"Techni Tool Inc",
    "wof:placetype":"venue"
},
  "geometry": {"coordinates":[-93.679367,45.238345],"type":"Point"}
}