{
  "type": "Feature",
  "properties": {
    "addr:full":"5905 Golden Valley Rd Golden Valley MN 55422",
    "addr:housenumber":"5905",
    "addr:postcode":"55422",
    "addr:street":"Golden Valley Rd",
    "iso:country":"US",
    "sg:address":"5905 Golden Valley Rd",
    "sg:city":"Golden Valley",
    "sg:classifiers":[
        {
            "category":"Social Services",
            "type":"Services"
        }
    ],
    "sg:phone":"+1 763 546 3243",
    "sg:postcode":"55422",
    "sg:province":"MN",
    "sg:tags":[
        "organization",
        "welfare"
    ],
    "wof:name":"Family Treatment Program",
    "wof:placetype":"venue"
},
  "geometry": {"coordinates":[-93.356292,44.992472],"type":"Point"}
}