{
  "type": "Feature",
  "properties": {
    "addr:full":"11 Main St N Winnebago MN 56098",
    "addr:housenumber":"11",
    "addr:postcode":"56098",
    "addr:street":"Main St N",
    "iso:country":"US",
    "sg:address":"11 Main St N",
    "sg:city":"Winnebago",
    "sg:classifiers":[
        {
            "category":"Food & Beverages",
            "subcategory":"Bakery",
            "type":"Retail Goods"
        }
    ],
    "sg:phone":"+1 507 893 3851",
    "sg:postcode":"56098",
    "sg:province":"MN",
    "wof:name":"Cravings On Main",
    "wof:placetype":"venue"
},
  "geometry": {"coordinates":[-94.165845,43.768728],"type":"Point"}
}