{
  "type": "Feature",
  "properties": {
    "addr:full":"130 Orchard Ave SE Hutchinson MN 55350",
    "addr:housenumber":"130",
    "addr:postcode":"55350",
    "addr:street":"Orchard Ave Se",
    "iso:country":"US",
    "sg:address":"130 Orchard Ave SE",
    "sg:city":"Hutchinson",
    "sg:classifiers":[
        {
            "category":"Social Services",
            "subcategory":"Child Care",
            "type":"Services"
        }
    ],
    "sg:phone":"+1 320 587 4801",
    "sg:postcode":"55350",
    "sg:province":"MN",
    "sg:tags":[
        "daycare",
        "provider"
    ],
    "wof:name":"Sherry S Knudsen",
    "wof:placetype":"venue"
},
  "geometry": {"coordinates":[-94.365331,44.8728],"type":"Point"}
}