{
  "type": "Feature",
  "properties": {
    "addr:full":"1117 Linda Ln Worthington MN 56187",
    "addr:housenumber":"1117",
    "addr:postcode":"56187",
    "addr:street":"Linda Ln",
    "iso:country":"US",
    "sg:address":"1117 Linda Ln",
    "sg:city":"Worthington",
    "sg:classifiers":[
        {
            "category":"Social Services",
            "subcategory":"Child Care",
            "type":"Services"
        }
    ],
    "sg:phone":"+1 507 376 5588",
    "sg:postcode":"56187",
    "sg:province":"MN",
    "sg:tags":[
        "daycare",
        "provider"
    ],
    "wof:name":"Paulette Bass",
    "wof:placetype":"venue"
},
  "geometry": {"coordinates":[-95.613319,43.607098],"type":"Point"}
}