{
  "type": "Feature",
  "properties": {
    "iso:country":"US",
    "sg:address":"4929 Sycamore Dr",
    "sg:city":"Saint Paul",
    "sg:classifiers":[
        {
            "category":"Manufacturing",
            "subcategory":"Food",
            "type":"Manufacturing & Wholesale Goods"
        }
    ],
    "sg:phone":"+1 651 322 4165",
    "sg:postcode":"55123",
    "sg:province":"MN",
    "sg:tags":[
        "preparation",
        "mfg"
    ],
    "wof:name":"Maple Grove Bg Foods Inc",
    "wof:placetype":"venue"
},
  "geometry": {"coordinates":[-93.106697,44.777192],"type":"Point"}
}