{
  "type": "Feature",
  "properties": {
    "addr:full":"79250 380th Ave Lakefield MN 56150",
    "addr:housenumber":"79250",
    "addr:postcode":"56150",
    "addr:street":"380Th Ave",
    "iso:country":"US",
    "sg:address":"79250 380th Ave",
    "sg:city":"Lakefield",
    "sg:classifiers":[
        {
            "category":"Farming",
            "subcategory":"Livestock Farm",
            "type":"Manufacturing & Wholesale Goods"
        },
        {
            "category":"Farming",
            "subcategory":"Farm",
            "type":"Manufacturing & Wholesale Goods"
        }
    ],
    "sg:phone":"+1 507 853 4451",
    "sg:postcode":"56150",
    "sg:province":"MN",
    "sg:tags":[
        "feeding"
    ],
    "wof:name":"Dale Heseman",
    "wof:placetype":"venue"
},
  "geometry": {"coordinates":[-95.31466899999999,43.631807],"type":"Point"}
}