{
  "type": "Feature",
  "properties": {
    "iso:country":"US",
    "sg:address":"1145 13th Ave SE",
    "sg:city":"Detroit Lakes",
    "sg:classifiers":[
        {
            "category":"Home & Garden",
            "subcategory":"Garden Supply",
            "type":"Retail Goods"
        }
    ],
    "sg:phone":"+1 218 847 2157",
    "sg:postcode":"56501",
    "sg:province":"MN",
    "sg:tags":[
        "engine"
    ],
    "wof:name":"Swansons' Repair Inc",
    "wof:placetype":"venue"
},
  "geometry": {"coordinates":[-95.82705199999999,46.81374],"type":"Point"}
}