{
  "type": "Feature",
  "properties": {
    "addr:full":"2021 W 245th St New Prague MN 56071",
    "addr:housenumber":"2021",
    "addr:postcode":"56071",
    "addr:street":"W 245Th St",
    "iso:country":"US",
    "sg:address":"2021 W 245th St",
    "sg:city":"New Prague",
    "sg:classifiers":[
        {
            "category":"Farming",
            "subcategory":"Dairy Farm",
            "type":"Manufacturing & Wholesale Goods"
        }
    ],
    "sg:phone":"+1 952 758 3446",
    "sg:postcode":"56071",
    "sg:province":"MN",
    "wof:name":"Lawrence Schoenbauer",
    "wof:placetype":"venue"
},
  "geometry": {"coordinates":[-93.57703100000001,44.594243],"type":"Point"}
}