{
  "type": "Feature",
  "properties": {
    "iso:country":"US",
    "sg:address":"250 2nd Ave S Ste 225",
    "sg:city":"Minneapolis",
    "sg:classifiers":[
        {
            "category":"Professional",
            "subcategory":"Lawyer & Legal Services",
            "type":"Services"
        }
    ],
    "sg:phone":"+1 612 332 3100",
    "sg:postcode":"55401",
    "sg:province":"MN",
    "wof:name":"Oleisky and Oleisky PA",
    "wof:placetype":"venue"
},
  "geometry": {"coordinates":[-93.265503,44.980499],"type":"Point"}
}