{
  "type": "Feature",
  "properties": {
    "iso:country":"US",
    "sg:address":"35017 139th Ave",
    "sg:city":"Menahga",
    "sg:classifiers":[
        {
            "category":"Real Estate",
            "subcategory":"Developer",
            "type":"Services"
        }
    ],
    "sg:phone":"+1 218 564 4026",
    "sg:postcode":"56464",
    "sg:province":"MN",
    "sg:tags":[
        "mobile",
        "home"
    ],
    "wof:name":"Country Side Mobile Home Court",
    "wof:placetype":"venue"
},
  "geometry": {"coordinates":[-95.080563,46.733994],"type":"Point"}
}