{
  "type": "Feature",
  "properties": {
    "iso:country":"US",
    "sg:address":"3537 Lake Elmo Ave N",
    "sg:city":"Lake Elmo",
    "sg:classifiers":[
        {
            "category":"Professional",
            "subcategory":"Lawyer & Legal Services",
            "type":"Services"
        }
    ],
    "sg:phone":"+1 651 291 1717",
    "sg:postcode":"55042",
    "sg:province":"MN",
    "sg:tags":[
        "attorney"
    ],
    "sg:website":"www.dudleyandsmith.com",
    "wof:name":"Dudley & Smith",
    "wof:placetype":"venue"
},
  "geometry": {"coordinates":[-92.880067,44.999803],"type":"Point"}
}