{
  "type": "Feature",
  "properties": {
    "addr:full":"15102 Mary Ln Little Falls MN 56345",
    "addr:housenumber":"15102",
    "addr:postcode":"56345",
    "addr:street":"Mary Ln",
    "iso:country":"US",
    "sg:address":"15102 Mary Ln",
    "sg:city":"Little Falls",
    "sg:classifiers":[
        {
            "category":"Shopping",
            "subcategory":"Shoes",
            "type":"Retail Goods"
        }
    ],
    "sg:phone":"+1 320 632 4225",
    "sg:postcode":"56345",
    "sg:province":"MN",
    "wof:name":"Family Shoe Store",
    "wof:placetype":"venue"
},
  "geometry": {"coordinates":[-94.327319,45.98114],"type":"Point"}
}