{
  "type": "Feature",
  "properties": {
    "addr:full":"3519 W 70th St Minneapolis MN 55435",
    "addr:housenumber":"3519",
    "addr:postcode":"55435",
    "addr:street":"W 70Th St",
    "iso:country":"US",
    "sg:address":"3519 W 70th St",
    "sg:city":"Minneapolis",
    "sg:classifiers":[
        {
            "category":"Personal",
            "subcategory":"Beauty Salon",
            "type":"Services"
        },
        {
            "category":"Personal",
            "subcategory":"Hair Removal",
            "type":"Services"
        }
    ],
    "sg:phone":"+1 612 284 7178",
    "sg:postcode":"55435",
    "sg:province":"MN",
    "sg:tags":[
        "stylist"
    ],
    "sg:website":"http://www.dexknows.com/rd?dku=http://AppelStudios.net%3Fmkt=65901",
    "wof:name":"Appel Studios",
    "wof:placetype":"venue"
},
  "geometry": {"coordinates":[-93.32296599999999,44.876362],"type":"Point"}
}