{
  "type": "Feature",
  "properties": {
    "iso:country":"US",
    "sg:address":"505 E 4th St",
    "sg:city":"Hills",
    "sg:classifiers":[
        {
            "category":"Personal",
            "subcategory":"Beauty Salon",
            "type":"Services"
        }
    ],
    "sg:phone":"+1 507 962 3288",
    "sg:postcode":"56138",
    "sg:province":"MN",
    "wof:name":"Tuff Beauty Shop",
    "wof:placetype":"venue"
},
  "geometry": {"coordinates":[-96.353441,43.525976],"type":"Point"}
}