{
  "type": "Feature",
  "properties": {
    "iso:country":"US",
    "sg:address":"305 3rd Ave NW",
    "sg:city":"Stewartville",
    "sg:classifiers":[
        {
            "category":"Shopping",
            "subcategory":"Florist",
            "type":"Retail Goods"
        }
    ],
    "sg:phone":"+1 507 533 6871",
    "sg:postcode":"55976",
    "sg:province":"MN",
    "wof:name":"Flower Cellar",
    "wof:placetype":"venue"
},
  "geometry": {"coordinates":[-92.490334,43.857581],"type":"Point"}
}