{
  "type": "Feature",
  "properties": {
    "iso:country":"US",
    "sg:address":"14365 293rd Ave NE",
    "sg:city":"Belgrade",
    "sg:classifiers":[
        {
            "category":"Wholesale",
            "subcategory":"Farm Supplies",
            "type":"Manufacturing & Wholesale Goods"
        }
    ],
    "sg:phone":"+1 320 243 4220",
    "sg:postcode":"56312",
    "sg:province":"MN",
    "sg:tags":[
        "feed",
        "grain"
    ],
    "wof:name":"Regal Elevator Inc",
    "wof:placetype":"venue"
},
  "geometry": {"coordinates":[-94.84823900000001,45.405729],"type":"Point"}
}