{
  "type": "Feature",
  "properties": {
    "iso:country":"US",
    "sg:address":"3665 Sibley Memorial Hwy",
    "sg:city":"Saint Paul",
    "sg:classifiers":[
        {
            "category":"Restaurant",
            "type":"Food & Drink"
        }
    ],
    "sg:phone":"+1 651 452 0190",
    "sg:postcode":"55122",
    "sg:province":"MN",
    "sg:tags":[
        "mexican"
    ],
    "wof:name":"La Fonda De Los Lobos",
    "wof:placetype":"venue"
},
  "geometry": {"coordinates":[-93.2015,44.824402],"type":"Point"}
}