{
  "type": "Feature",
  "properties": {
    "iso:country":"US",
    "sg:address":"3211 Allandale Ave",
    "sg:city":"Duluth",
    "sg:classifiers":[
        {
            "category":"Arena",
            "subcategory":"Sports Club",
            "type":"Entertainment"
        }
    ],
    "sg:phone":"+1 218 724 0094",
    "sg:postcode":"55803",
    "sg:province":"MN",
    "sg:tags":[
        "executive"
    ],
    "wof:name":"Duluth Amateur Association",
    "wof:placetype":"venue"
},
  "geometry": {"coordinates":[-92.079572,46.842774],"type":"Point"}
}