{
  "type": "Feature",
  "properties": {
    "addr:full":"6795 Gerdine Path W Rosemount MN 55068",
    "addr:housenumber":"6795",
    "addr:postcode":"55068",
    "addr:street":"Gerdine Path W",
    "iso:country":"US",
    "sg:address":"6795 Gerdine Path W",
    "sg:city":"Rosemount",
    "sg:classifiers":[
        {
            "category":"Education",
            "subcategory":"School",
            "type":"Public Place"
        }
    ],
    "sg:phone":"+1 952 431 8350",
    "sg:postcode":"55068",
    "sg:province":"MN",
    "sg:tags":[
        "elementary"
    ],
    "wof:name":"Parkview Elementary School",
    "wof:placetype":"venue"
},
  "geometry": {"coordinates":[-93.20176600000001,44.711784],"type":"Point"}
}