{
  "type": "Feature",
  "properties": {
    "iso:country":"US",
    "sg:address":"1003 8th St N",
    "sg:city":"Northwood",
    "sg:classifiers":[
        {
            "category":"Sports & Exercise",
            "subcategory":"Bowling",
            "type":"Entertainment"
        }
    ],
    "sg:phone":"+1 641 324 2749",
    "sg:postcode":"50459",
    "sg:province":"MN",
    "sg:tags":[
        "center"
    ],
    "wof:name":"Nordic Lanes",
    "wof:placetype":"venue"
},
  "geometry": {"coordinates":[-93.22084599999999,43.454353],"type":"Point"}
}