{
  "type": "Feature",
  "properties": {
    "iso:country":"US",
    "sg:address":"15600 Wayzata Blvd",
    "sg:city":"Wayzata",
    "sg:classifiers":[
        {
            "category":"Professional",
            "subcategory":"Employment Agencies",
            "type":"Services"
        }
    ],
    "sg:phone":"+1 952 404 2600",
    "sg:postcode":"55391",
    "sg:province":"MN",
    "wof:name":"Professonal Alternatives L L C",
    "wof:placetype":"venue"
},
  "geometry": {"coordinates":[-93.48177200000001,44.971394],"type":"Point"}
}