{
  "type": "Feature",
  "properties": {
    "iso:country":"US",
    "sg:address":"5652 Brookdale Dr N",
    "sg:city":"Minneapolis",
    "sg:classifiers":[
        {
            "category":"Retail",
            "subcategory":"Laundry & Dry Cleaning",
            "type":"Services"
        }
    ],
    "sg:phone":"+1 763 566 0648",
    "sg:postcode":"55443",
    "sg:province":"MN",
    "wof:name":"Chands Pro Alterations",
    "wof:placetype":"venue"
},
  "geometry": {"coordinates":[-93.354168,45.095457],"type":"Point"}
}