{
  "type": "Feature",
  "properties": {
    "addr:full":"11739 306th Ave NW Princeton MN 55371",
    "addr:housenumber":"11739",
    "addr:postcode":"55371",
    "addr:street":"306Th Ave Nw",
    "iso:country":"US",
    "sg:address":"11739 306th Ave NW",
    "sg:city":"Princeton",
    "sg:classifiers":[
        {
            "category":"Autos & Motor Vehicles",
            "subcategory":"Automobile Sales",
            "type":"Retail Goods"
        }
    ],
    "sg:phone":"+1 612 802 4259",
    "sg:postcode":"55371",
    "sg:province":"MN",
    "sg:tags":[
        "performance",
        "race",
        "dealer"
    ],
    "wof:name":"Speedfab",
    "wof:placetype":"venue"
},
  "geometry": {"coordinates":[-93.57026,45.525372],"type":"Point"}
}