{
  "type": "Feature",
  "properties": {
    "iso:country":"US",
    "sg:address":"635 39th Ave NE",
    "sg:city":"Columbia Heights",
    "sg:classifiers":[
        {
            "category":"Manufacturing",
            "subcategory":"Metals",
            "type":"Manufacturing & Wholesale Goods"
        },
        {
            "category":"Retail",
            "subcategory":"Repair Shop",
            "type":"Services"
        }
    ],
    "sg:phone":"+1 763 788 1197",
    "sg:postcode":"55421",
    "sg:province":"MN",
    "sg:tags":[
        "steel",
        "welding"
    ],
    "wof:name":"Heights-Northeast Welding Inc",
    "wof:placetype":"venue"
},
  "geometry": {"coordinates":[-93.25268,45.038325],"type":"Point"}
}