{
  "type": "Feature",
  "properties": {
    "addr:full":"10045 70th Ave NE Elgin MN 55932",
    "addr:housenumber":"10045",
    "addr:postcode":"55932",
    "addr:street":"70Th Ave Ne",
    "iso:country":"US",
    "sg:address":"10045 70th Ave NE",
    "sg:city":"Elgin",
    "sg:phone":"+1 507 876 2992",
    "sg:postcode":"55932",
    "sg:province":"MN",
    "sg:tags":[
        "farm",
        "corn"
    ],
    "wof:name":"Raymond Hampel",
    "wof:placetype":"venue"
},
  "geometry": {"coordinates":[-92.339043,44.137186],"type":"Point"}
}