{
  "type": "Feature",
  "properties": {
    "addr:full":"18625 Verna Ln Prior Lake MN 55372",
    "addr:housenumber":"18625",
    "addr:postcode":"55372",
    "addr:street":"Verna Ln",
    "iso:country":"US",
    "sg:address":"18625 Verna Ln",
    "sg:city":"Prior Lake",
    "sg:classifiers":[
        {
            "category":"Professional",
            "subcategory":"Management & Consulting",
            "type":"Services"
        }
    ],
    "sg:phone":"+1 952 440 8669",
    "sg:postcode":"55372",
    "sg:province":"MN",
    "sg:tags":[
        "consultant",
        "business"
    ],
    "wof:name":"American Software Consulting",
    "wof:placetype":"venue"
},
  "geometry": {"coordinates":[-93.349491,44.679506],"type":"Point"}
}