{
  "type": "Feature",
  "properties": {
    "addr:full":"9401 Riverview Ave S Minneapolis MN 55425",
    "addr:housenumber":"9401",
    "addr:postcode":"55425",
    "addr:street":"Riverview Ave S",
    "iso:country":"US",
    "sg:address":"9401 Riverview Ave S",
    "sg:city":"Minneapolis",
    "sg:classifiers":[
        {
            "category":"Retail",
            "subcategory":"Repair Shop",
            "type":"Services"
        }
    ],
    "sg:phone":"+1 952 884 5121",
    "sg:postcode":"55425",
    "sg:province":"MN",
    "wof:name":"Metro Drain Master",
    "wof:placetype":"venue"
},
  "geometry": {"coordinates":[-93.253906,44.832615],"type":"Point"}
}