{
  "type": "Feature",
  "properties": {
    "addr:full":"1219 Mourning Dove Ct Saint Paul MN 55123",
    "addr:housenumber":"1219",
    "addr:postcode":"55123",
    "addr:street":"Mourning Dove Ct",
    "iso:country":"US",
    "sg:address":"1219 Mourning Dove Ct",
    "sg:city":"Saint Paul",
    "sg:classifiers":[
        {
            "category":"Manufacturing",
            "subcategory":"Wood Products",
            "type":"Manufacturing & Wholesale Goods"
        }
    ],
    "sg:phone":"+1 651 905 9999",
    "sg:postcode":"55123",
    "sg:province":"MN",
    "sg:tags":[
        "mfg"
    ],
    "wof:name":"Luoma Enterprises",
    "wof:placetype":"venue"
},
  "geometry": {"coordinates":[-93.156139,44.82365],"type":"Point"}
}