{
  "type": "Feature",
  "properties": {
    "iso:country":"US",
    "sg:address":"26 E Exchange St",
    "sg:city":"St Paul",
    "sg:classifiers":[
        {
            "category":"Professional",
            "subcategory":"Management & Consulting",
            "type":"Services"
        },
        {
            "category":"Organizations",
            "subcategory":"Professional Association",
            "type":"Services"
        }
    ],
    "sg:phone":"+1 651 293 9295",
    "sg:postcode":"55101",
    "sg:province":"MN",
    "sg:tags":[
        "lobbyist",
        "trade"
    ],
    "sg:website":"www.capitolconnections.com",
    "wof:name":"Capitol Connections",
    "wof:placetype":"venue"
},
  "geometry": {"coordinates":[-93.096667,44.949429],"type":"Point"}
}