{
  "type": "Feature",
  "properties": {
    "iso:country":"US",
    "sg:address":"1399 Town Centre Dr",
    "sg:city":"Eagan",
    "sg:classifiers":[
        {
            "category":"Retail",
            "subcategory":"Auto Repair",
            "type":"Services"
        }
    ],
    "sg:phone":"+1 651 688 6991",
    "sg:postcode":"55123",
    "sg:province":"MN",
    "sg:tags":[
        "repairing",
        "automobile"
    ],
    "wof:name":"Car-X Muffler & Brake",
    "wof:placetype":"venue"
},
  "geometry": {"coordinates":[-93.16515099999999,44.827663],"type":"Point"}
}