{
  "type": "Feature",
  "properties": {
    "iso:country":"US",
    "sg:address":"61 Park Ave",
    "sg:city":"Lake Lillian",
    "sg:classifiers":[
        {
            "category":"Organizations",
            "subcategory":"Religious Organization",
            "type":"Services"
        }
    ],
    "sg:phone":"+1 320 664 4545",
    "sg:postcode":"56253",
    "sg:province":"MN",
    "sg:tags":[
        "church"
    ],
    "wof:name":"Grace Lutheran Church",
    "wof:placetype":"venue"
},
  "geometry": {"coordinates":[-94.88140799999999,44.945204],"type":"Point"}
}