{
  "type": "Feature",
  "properties": {
    "iso:country":"US",
    "sg:address":"12515 40th St S",
    "sg:city":"Afton",
    "sg:classifiers":[
        {
            "category":"Building & Trades",
            "subcategory":"Landscaping Services",
            "type":"Services"
        }
    ],
    "sg:phone":"+1 651 769 0010",
    "sg:postcode":"55001",
    "sg:province":"MN",
    "sg:tags":[
        "designer",
        "landscape"
    ],
    "sg:website":"www.landscaperenovations.com",
    "wof:name":"Landscape Renovations Inc",
    "wof:placetype":"venue"
},
  "geometry": {"coordinates":[-92.855707,44.890785],"type":"Point"}
}