{
  "type": "Feature",
  "properties": {
    "addr:full":"16824 221st Ave Big Lake MN 55309",
    "addr:housenumber":"16824",
    "addr:postcode":"55309",
    "addr:street":"221St Ave",
    "iso:country":"US",
    "sg:address":"16824 221st Ave",
    "sg:city":"Big Lake",
    "sg:classifiers":[
        {
            "category":"Building & Trades",
            "subcategory":"Construction",
            "type":"Services"
        }
    ],
    "sg:phone":"+1 763 263 7492",
    "sg:postcode":"55309",
    "sg:province":"MN",
    "sg:tags":[
        "house"
    ],
    "wof:name":"Theisen Construction",
    "wof:placetype":"venue"
},
  "geometry": {"coordinates":[-93.697861,45.373042],"type":"Point"}
}