{
  "type": "Feature",
  "properties": {
    "addr:full":"310 2nd St NE Austin MN 55912",
    "addr:housenumber":"310",
    "addr:postcode":"55912",
    "addr:street":"2Nd St Ne",
    "iso:country":"US",
    "sg:address":"310 2nd St NE",
    "sg:city":"Austin",
    "sg:classifiers":[
        {
            "category":"Manufacturing",
            "subcategory":"Printing",
            "type":"Manufacturing & Wholesale Goods"
        }
    ],
    "sg:phone":"+1 507 433 8851",
    "sg:postcode":"55912",
    "sg:province":"MN",
    "sg:tags":[
        "newspaper"
    ],
    "sg:website":"www.austindailyherald.com",
    "wof:name":"Austin Daily Herald",
    "wof:placetype":"venue"
},
  "geometry": {"coordinates":[-92.97222499999999,43.669104],"type":"Point"}
}