{
  "type": "Feature",
  "properties": {
    "addr:full":"14223 68th St NW Annandale MN 55302",
    "addr:housenumber":"14223",
    "addr:postcode":"55302",
    "addr:street":"68Th St Nw",
    "iso:country":"US",
    "sg:address":"14223 68th St NW",
    "sg:city":"Annandale",
    "sg:classifiers":[
        {
            "category":"Professional",
            "subcategory":"Engineering",
            "type":"Services"
        }
    ],
    "sg:phone":"+1 320 274 3466",
    "sg:postcode":"55302",
    "sg:province":"MN",
    "sg:tags":[
        "furnishes",
        "installs",
        "ceiling",
        "acoustical"
    ],
    "wof:name":"Acoustical Innovations",
    "wof:placetype":"venue"
},
  "geometry": {"coordinates":[-94.18376499999999,45.253251],"type":"Point"}
}