{
  "type": "Feature",
  "properties": {
    "addr:full":"3105 Industrial Dr Faribault MN 55021",
    "addr:housenumber":"3105",
    "addr:postcode":"55021",
    "addr:street":"Industrial Dr",
    "iso:country":"US",
    "sg:address":"3105 Industrial Dr",
    "sg:city":"Faribault",
    "sg:classifiers":[
        {
            "category":"Building & Trades",
            "subcategory":"Plumbing",
            "type":"Services"
        }
    ],
    "sg:phone":"+1 507 334 7951",
    "sg:postcode":"55021",
    "sg:province":"MN",
    "sg:tags":[
        "conditioning",
        "air",
        "system",
        "contractor"
    ],
    "sg:website":"www.bgcompanies.com",
    "wof:name":"Bauernfeind & Goedtel",
    "wof:placetype":"venue"
},
  "geometry": {"coordinates":[-93.286326,44.324161],"type":"Point"}
}