{
  "type": "Feature",
  "properties": {
    "addr:full":"18 N Minnesota St New Ulm MN 56073",
    "addr:housenumber":"18",
    "addr:postcode":"56073",
    "addr:street":"N Minnesota St",
    "iso:country":"US",
    "sg:address":"18 N Minnesota St",
    "sg:city":"New Ulm",
    "sg:classifiers":[
        {
            "category":"Personal",
            "subcategory":"Beauty Salon",
            "type":"Services"
        }
    ],
    "sg:phone":"+1 507 354 4227",
    "sg:postcode":"56073",
    "sg:province":"MN",
    "sg:tags":[
        "shop"
    ],
    "wof:name":"Haar Friseure",
    "wof:placetype":"venue"
},
  "geometry": {"coordinates":[-94.45975300000001,44.314168],"type":"Point"}
}