{
  "type": "Feature",
  "properties": {
    "addr:full":"2100 W Old Shakopee Rd Minneapolis MN 55431",
    "addr:housenumber":"2100",
    "addr:postcode":"55431",
    "addr:street":"W Old Shakopee Rd",
    "iso:country":"US",
    "sg:address":"2100 W Old Shakopee Rd",
    "sg:city":"Minneapolis",
    "sg:classifiers":[
        {
            "category":"Food & Beverages",
            "subcategory":"Groceries & Convenience Stores",
            "type":"Retail Goods"
        }
    ],
    "sg:phone":"+1 952 884 7889",
    "sg:postcode":"55431",
    "sg:province":"MN",
    "sg:tags":[
        "fruit",
        "veggie"
    ],
    "wof:name":"Cal's Market & Garden Center",
    "wof:placetype":"venue"
},
  "geometry": {"coordinates":[-93.306,44.820599],"type":"Point"}
}