{
  "type": "Feature",
  "properties": {
    "addr:full":"303 Central Ave N Dodge Center MN 55927",
    "addr:housenumber":"303",
    "addr:postcode":"55927",
    "addr:street":"Central Ave N",
    "iso:country":"US",
    "sg:address":"303 Central Ave N",
    "sg:city":"Dodge Center",
    "sg:classifiers":[
        {
            "category":"Social Services",
            "subcategory":"Child Care",
            "type":"Services"
        }
    ],
    "sg:phone":"+1 507 374 2794",
    "sg:postcode":"55927",
    "sg:province":"MN",
    "wof:name":"Cheryl's Child Care",
    "wof:placetype":"venue"
},
  "geometry": {"coordinates":[-92.854879,44.03108],"type":"Point"}
}