{
  "type": "Feature",
  "properties": {
    "addr:full":"400 American Blvd E Bloomington MN 55420",
    "addr:housenumber":"400",
    "addr:postcode":"55420",
    "addr:street":"American Blvd E",
    "iso:country":"US",
    "sg:address":"400 American Blvd E",
    "sg:city":"Bloomington",
    "sg:classifiers":[
        {
            "category":"Wholesale",
            "subcategory":"Furniture",
            "type":"Manufacturing & Wholesale Goods"
        },
        {
            "category":"Professional",
            "subcategory":"Advertising",
            "type":"Services"
        }
    ],
    "sg:phone":"+1 952 888 4550",
    "sg:postcode":"55420",
    "sg:province":"MN",
    "wof:name":"Epitome Marketing",
    "wof:placetype":"venue"
},
  "geometry": {"coordinates":[-93.26990499999999,44.859772],"type":"Point"}
}