{
  "type": "Feature",
  "properties": {
    "addr:full":"210 2nd St Shelly MN 56581",
    "addr:housenumber":"210",
    "addr:postcode":"56581",
    "addr:street":"2Nd St",
    "iso:country":"US",
    "sg:address":"210 2nd St",
    "sg:city":"Shelly",
    "sg:classifiers":[
        {
            "category":"Organizations",
            "subcategory":"Religious Organization",
            "type":"Services"
        }
    ],
    "sg:phone":"+1 218 886 6915",
    "sg:postcode":"56581",
    "sg:province":"MN",
    "sg:tags":[
        "church"
    ],
    "wof:name":"Shelly Lutheran Church",
    "wof:placetype":"venue"
},
  "geometry": {"coordinates":[-96.81844599999999,47.458279],"type":"Point"}
}