{
  "type": "Feature",
  "properties": {
    "iso:country":"US",
    "sg:address":"319 S Payne St",
    "sg:city":"New Ulm",
    "sg:classifiers":[
        {
            "category":"Farming",
            "subcategory":"Farm & Veterinary Services",
            "type":"Manufacturing & Wholesale Goods"
        }
    ],
    "sg:phone":"+1 507 354 4834",
    "sg:postcode":"56073",
    "sg:province":"MN",
    "sg:tags":[
        "preparation",
        "soil"
    ],
    "wof:name":"Richard Goff",
    "wof:placetype":"venue"
},
  "geometry": {"coordinates":[-94.46424399999999,44.306115],"type":"Point"}
}