{
  "type": "Feature",
  "properties": {
    "addr:full":"26949 140th St Staples MN 56479",
    "addr:housenumber":"26949",
    "addr:postcode":"56479",
    "addr:street":"140Th St",
    "iso:country":"US",
    "sg:address":"26949 140th St",
    "sg:city":"Staples",
    "sg:classifiers":[
        {
            "category":"Shopping",
            "subcategory":"Used Merchandise",
            "type":"Retail Goods"
        }
    ],
    "sg:phone":"+1 218 894 3815",
    "sg:postcode":"56479",
    "sg:province":"MN",
    "sg:tags":[
        "resale",
        "shop"
    ],
    "wof:name":"J And P Consignment",
    "wof:placetype":"venue"
},
  "geometry": {"coordinates":[-94.804243,46.426624],"type":"Point"}
}