{
  "type": "Feature",
  "properties": {
    "iso:country":"US",
    "sg:address":"1404 W 149th St",
    "sg:city":"Burnsville",
    "sg:classifiers":[
        {
            "category":"Building & Trades",
            "subcategory":"Construction",
            "type":"Services"
        }
    ],
    "sg:phone":"+1 952 435 5806",
    "sg:postcode":"55306",
    "sg:province":"MN",
    "sg:tags":[
        "repair",
        "handyman",
        "maintenance",
        "home"
    ],
    "wof:name":"Dels Handyman Svcs",
    "wof:placetype":"venue"
},
  "geometry": {"coordinates":[-93.296527,44.733631],"type":"Point"}
}