{
  "type": "Feature",
  "properties": {
    "addr:full":"109 W Robert St Crookston MN 56716",
    "addr:housenumber":"109",
    "addr:postcode":"56716",
    "addr:street":"W Robert St",
    "iso:country":"US",
    "sg:address":"109 W Robert St",
    "sg:city":"Crookston",
    "sg:classifiers":[
        {
            "category":"Home & Garden",
            "subcategory":"Building Materials",
            "type":"Retail Goods"
        }
    ],
    "sg:phone":"+1 218 281 4215",
    "sg:postcode":"56716",
    "sg:province":"MN",
    "sg:tags":[
        "glass",
        "window",
        "plate"
    ],
    "wof:name":"Crookston Paint Glass Co",
    "wof:placetype":"venue"
},
  "geometry": {"coordinates":[-96.60816199999999,47.774164],"type":"Point"}
}