{
  "type": "Feature",
  "properties": {
    "iso:country":"US",
    "sg:address":"3024 Major Ave N",
    "sg:city":"Minneapolis",
    "sg:classifiers":[
        {
            "category":"Real Estate",
            "subcategory":"Real Estate Services",
            "type":"Services"
        }
    ],
    "sg:phone":"+1 763 588 5236",
    "sg:postcode":"55422",
    "sg:province":"MN",
    "sg:tags":[
        "commercial"
    ],
    "wof:name":"Admore Realty",
    "wof:placetype":"venue"
},
  "geometry": {"coordinates":[-93.33733700000001,45.011612],"type":"Point"}
}