{
  "type": "Feature",
  "properties": {
    "iso:country":"US",
    "sg:address":"7671 Central Ave NE # 104",
    "sg:city":"Minneapolis",
    "sg:classifiers":[
        {
            "category":"Manufacturing",
            "subcategory":"Tools & Machinery",
            "type":"Manufacturing & Wholesale Goods"
        }
    ],
    "sg:phone":"+1 763 780 0964",
    "sg:postcode":"55432",
    "sg:province":"MN",
    "sg:tags":[
        "abrasives-wholesale",
        "manufacturer"
    ],
    "wof:name":"H & H Supply, Inc.",
    "wof:placetype":"venue"
},
  "geometry": {"coordinates":[-93.23813,45.106761],"type":"Point"}
}