{
  "type": "Feature",
  "properties": {
    "iso:country":"US",
    "sg:address":"1754 Birch Lake Ave",
    "sg:city":"Saint Paul",
    "sg:classifiers":[
        {
            "category":"Personal",
            "type":"Services"
        }
    ],
    "sg:phone":"+1 651 308 7954",
    "sg:postcode":"55110",
    "sg:province":"MN",
    "wof:name":"Young Wolf Inc",
    "wof:placetype":"venue"
},
  "geometry": {"coordinates":[-93.030996,45.082771],"type":"Point"}
}