{
  "type": "Feature",
  "properties": {
    "iso:country":"US",
    "sg:address":"117 N 1st St",
    "sg:city":"Montevideo",
    "sg:classifiers":[
        {
            "category":"Shopping",
            "subcategory":"Optical Goods",
            "type":"Retail Goods"
        }
    ],
    "sg:phone":"+1 320 269 5771",
    "sg:postcode":"56265",
    "sg:province":"MN",
    "wof:name":"Midwest Vision Ctr",
    "wof:placetype":"venue"
},
  "geometry": {"coordinates":[-95.72460599999999,44.946216],"type":"Point"}
}