{
  "type": "Feature",
  "properties": {
    "iso:country":"US",
    "sg:address":"30070 251st Ave",
    "sg:city":"Le Sueur",
    "sg:classifiers":[
        {
            "category":"Building & Trades",
            "subcategory":"Construction",
            "type":"Services"
        }
    ],
    "sg:phone":"+1 507 665 6635",
    "sg:postcode":"56058",
    "sg:province":"MN",
    "sg:tags":[
        "repairing",
        "remodeling",
        "contractor"
    ],
    "wof:name":"Bouska & Bouska",
    "wof:placetype":"venue"
},
  "geometry": {"coordinates":[-93.768278,44.518873],"type":"Point"}
}