{
  "type": "Feature",
  "properties": {
    "iso:country":"US",
    "sg:address":"4720 32nd Ave S",
    "sg:city":"Minneapolis",
    "sg:classifiers":[
        {
            "category":"Communications",
            "subcategory":"Television Station",
            "type":"Services"
        }
    ],
    "sg:phone":"+1 612 721 8055",
    "sg:postcode":"55406",
    "sg:province":"MN",
    "sg:tags":[
        "print",
        "broadcasting",
        "co",
        "advertising"
    ],
    "wof:name":"Allies Media Art",
    "wof:placetype":"venue"
},
  "geometry": {"coordinates":[-93.225635,44.917061],"type":"Point"}
}