{
  "type": "Feature",
  "properties": {
    "iso:country":"US",
    "sg:address":"1400 4th Ave SE",
    "sg:city":"Austin",
    "sg:classifiers":[
        {
            "category":"Social Services",
            "subcategory":"Child Care",
            "type":"Services"
        }
    ],
    "sg:phone":"+1 507 437 3040",
    "sg:postcode":"55912",
    "sg:province":"MN",
    "sg:tags":[
        "day",
        "provider"
    ],
    "wof:name":"Nancy K Allore",
    "wof:placetype":"venue"
},
  "geometry": {"coordinates":[-92.956422,43.663067],"type":"Point"}
}