{
  "type": "Feature",
  "properties": {
    "addr:full":"99 Cherry Ave S Annandale MN 55302",
    "addr:housenumber":"99",
    "addr:postcode":"55302",
    "addr:street":"Cherry Ave S Annandale",
    "iso:country":"US",
    "sg:address":"99 Cherry Ave S",
    "sg:city":"Annandale",
    "sg:classifiers":[
        {
            "category":"Shopping",
            "subcategory":"Computers & Home Electronics",
            "type":"Retail Goods"
        }
    ],
    "sg:phone":"+1 320 274 5535",
    "sg:postcode":"55302",
    "sg:province":"MN",
    "sg:tags":[
        "equipment",
        "dealer"
    ],
    "wof:name":"Computer Doctor",
    "wof:placetype":"venue"
},
  "geometry": {"coordinates":[-94.12307800000001,45.261155],"type":"Point"}
}