{
  "type": "Feature",
  "properties": {
    "iso:country":"US",
    "sg:address":"1160 Highway 3 S",
    "sg:city":"Northfield",
    "sg:classifiers":[
        {
            "category":"Restaurant",
            "type":"Food & Drink"
        }
    ],
    "sg:menulink":"http://www.allmenus.com/mn/northfield/244498-georges-vineyard/menu/",
    "sg:phone":"+1 507 645 0100",
    "sg:postcode":"55057",
    "sg:province":"MN",
    "sg:tags":[
        "american",
        "pizza"
    ],
    "wof:name":"George's Vineyard",
    "wof:placetype":"venue"
},
  "geometry": {"coordinates":[-93.171429,44.448795],"type":"Point"}
}