{
  "type": "Feature",
  "properties": {
    "addr:full":"174 W 3rd St Winona MN 55987",
    "addr:housenumber":"174",
    "addr:postcode":"55987",
    "addr:street":"W 3Rd St",
    "iso:country":"US",
    "sg:address":"174 W 3rd St",
    "sg:city":"Winona",
    "sg:classifiers":[
        {
            "category":"Shopping",
            "type":"Retail Goods"
        }
    ],
    "sg:phone":"+1 507 452 4672",
    "sg:postcode":"55987",
    "sg:province":"MN",
    "sg:tags":[
        "monument"
    ],
    "wof:name":"Winona Monument By Sunset",
    "wof:placetype":"venue"
},
  "geometry": {"coordinates":[-91.64052,44.05349],"type":"Point"}
}