{
  "type": "Feature",
  "properties": {
    "addr:full":"3320 46th Ave N Minneapolis MN 55422",
    "addr:housenumber":"3320",
    "addr:postcode":"55422",
    "addr:street":"46Th Ave N",
    "iso:country":"US",
    "sg:address":"3320 46th Ave N",
    "sg:city":"Minneapolis",
    "sg:classifiers":[
        {
            "category":"Professional",
            "type":"Services"
        }
    ],
    "sg:phone":"+1 763 531 0369",
    "sg:postcode":"55422",
    "sg:province":"MN",
    "wof:name":"Timeless Hip Designs",
    "wof:placetype":"venue"
},
  "geometry": {"coordinates":[-93.32083799999999,45.0385],"type":"Point"}
}