{
  "type": "Feature",
  "properties": {
    "addr:full":"120 W Saint Julien St Saint Peter MN 56082",
    "addr:housenumber":"120",
    "addr:postcode":"56082",
    "addr:street":"W Saint Julien St",
    "iso:country":"US",
    "sg:address":"120 W Saint Julien St",
    "sg:city":"Saint Peter",
    "sg:classifiers":[
        {
            "category":"Restaurant",
            "type":"Food & Drink"
        }
    ],
    "sg:phone":"+1 507 931 3011",
    "sg:postcode":"56082",
    "sg:province":"MN",
    "sg:tags":[
        "eating"
    ],
    "wof:name":"McDonalds",
    "wof:placetype":"venue"
},
  "geometry": {"coordinates":[-93.948885,44.339775],"type":"Point"}
}