{
  "type": "Feature",
  "properties": {
    "addr:full":"5891 Co Rd 1 SW Pequot Lakes MN 56472",
    "addr:housenumber":"5891",
    "addr:postcode":"56472",
    "addr:street":"Co Rd 1 Sw",
    "iso:country":"US",
    "sg:address":"5891 Co Rd 1 SW",
    "sg:city":"Pequot Lakes",
    "sg:classifiers":[
        {
            "category":"Building & Trades",
            "subcategory":"Construction",
            "type":"Services"
        }
    ],
    "sg:phone":"+1 218 568 4265",
    "sg:postcode":"56472",
    "sg:province":"MN",
    "sg:tags":[
        "general",
        "contractor"
    ],
    "wof:name":"Northern Excavating Inc",
    "wof:placetype":"venue"
},
  "geometry": {"coordinates":[-94.43537600000001,46.587537],"type":"Point"}
}