{
  "type": "Feature",
  "properties": {
    "iso:country":"US",
    "sg:address":"301 Carlson Pkwy S",
    "sg:city":"Minnetonka",
    "sg:classifiers":[
        {
            "category":"Banks & Credit Unions",
            "subcategory":"Investment Brokerage",
            "type":"Services"
        }
    ],
    "sg:phone":"+1 952 475 1200",
    "sg:postcode":"55305",
    "sg:province":"MN",
    "sg:tags":[
        "advisory",
        "financial"
    ],
    "wof:name":"O'Donnell & Assoc",
    "wof:placetype":"venue"
},
  "geometry": {"coordinates":[-93.467127,44.976839],"type":"Point"}
}