{
  "type": "Feature",
  "properties": {
    "addr:full":"21440 State Hwy 78 Battle Lake MN 56515",
    "addr:housenumber":"21440",
    "addr:postcode":"56515",
    "addr:street":"State Hwy 78",
    "iso:country":"US",
    "sg:address":"21440 State Hwy 78",
    "sg:city":"Battle Lake",
    "sg:classifiers":[
        {
            "category":"Autos & Motor Vehicles",
            "subcategory":"Boat Sales",
            "type":"Retail Goods"
        }
    ],
    "sg:phone":"+1 218 864 5567",
    "sg:postcode":"56515",
    "sg:province":"MN",
    "sg:tags":[
        "dealer",
        "sales"
    ],
    "wof:name":"Battle Lake Boat Works",
    "wof:placetype":"venue"
},
  "geometry": {"coordinates":[-95.713606,46.273114],"type":"Point"}
}