{
  "type": "Feature",
  "properties": {
    "iso:country":"US",
    "sg:address":"25532 200th Ave N",
    "sg:city":"Ulen",
    "sg:classifiers":[
        {
            "category":"Building & Trades",
            "subcategory":"Construction",
            "type":"Services"
        }
    ],
    "sg:phone":"+1 218 596 8630",
    "sg:postcode":"56585",
    "sg:province":"MN",
    "sg:tags":[
        "general",
        "nonresidential",
        "crop",
        "mach"
    ],
    "wof:name":"Braseth Sales & Construction",
    "wof:placetype":"venue"
},
  "geometry": {"coordinates":[-96.26826699999999,47.136775],"type":"Point"}
}