{
  "type": "Feature",
  "properties": {
    "iso:country":"US",
    "sg:address":"202 Central Ave N",
    "sg:city":"Faribault",
    "sg:classifiers":[
        {
            "category":"Shopping",
            "subcategory":"Florist",
            "type":"Retail Goods"
        }
    ],
    "sg:phone":"+1 507 334 6442",
    "sg:postcode":"55021",
    "sg:province":"MN",
    "wof:name":"Mike Young's Flowers Evrlstng",
    "wof:placetype":"venue"
},
  "geometry": {"coordinates":[-93.268438,44.293609],"type":"Point"}
}