{
  "type": "Feature",
  "properties": {
    "iso:country":"US",
    "sg:address":"4367 Soldier Rd",
    "sg:city":"Moose Lake",
    "sg:classifiers":[
        {
            "category":"Retail",
            "subcategory":"Animal Services",
            "type":"Services"
        }
    ],
    "sg:phone":"+1 218 485 8233",
    "sg:postcode":"55767",
    "sg:province":"MN",
    "sg:tags":[
        "pet",
        "boarding",
        "sitting"
    ],
    "wof:name":"Kennelz & Bitz",
    "wof:placetype":"venue"
},
  "geometry": {"coordinates":[-92.75757400000001,46.472374],"type":"Point"}
}