{
  "type": "Feature",
  "properties": {
    "addr:full":"271 Norman Ridge Dr Bloomington MN 55437",
    "addr:housenumber":"271",
    "addr:postcode":"55437",
    "addr:street":"Norman Ridge Dr",
    "iso:country":"US",
    "sg:address":"271 Norman Ridge Dr",
    "sg:city":"Bloomington",
    "sg:classifiers":[
        {
            "category":"Shopping",
            "type":"Retail Goods"
        }
    ],
    "sg:phone":"+1 952 831 2912",
    "sg:postcode":"55437",
    "sg:province":"MN",
    "sg:tags":[
        "cosmetic",
        "perfume"
    ],
    "wof:name":"Mary Kay Cosmetics",
    "wof:placetype":"venue"
},
  "geometry": {"coordinates":[-93.35579199999999,44.837509],"type":"Point"}
}