{
  "type": "Feature",
  "properties": {
    "iso:country":"US",
    "sg:address":"1700 N Broadway St",
    "sg:city":"New Ulm",
    "sg:classifiers":[
        {
            "category":"Ice Cream",
            "type":"Food & Drink"
        }
    ],
    "sg:menulink":"http://www.allmenus.com/mn/new-ulm/74359-happy-joes/menu/",
    "sg:phone":"+1 507 359 9811",
    "sg:postcode":"56073",
    "sg:province":"MN",
    "sg:tags":[
        "american",
        "pizza"
    ],
    "wof:name":"Happy Joe's",
    "wof:placetype":"venue"
},
  "geometry": {"coordinates":[-94.476097,44.329285],"type":"Point"}
}