{
  "type": "Feature",
  "properties": {
    "iso:country":"US",
    "sg:address":"421 1st Ave SW",
    "sg:city":"Rochester",
    "sg:classifiers":[
        {
            "category":"Manufacturing",
            "subcategory":"Wood Products",
            "type":"Manufacturing & Wholesale Goods"
        }
    ],
    "sg:phone":"+1 507 206 6969",
    "sg:postcode":"55902",
    "sg:province":"MN",
    "sg:tags":[
        "millwork-wholesale",
        "millwork",
        "manufacturer"
    ],
    "wof:name":"1760 Millwork Manufacturing Company",
    "wof:placetype":"venue"
},
  "geometry": {"coordinates":[-92.46442,44.019016],"type":"Point"}
}