{
  "type": "Feature",
  "properties": {
    "addr:full":"421 1st Ave SW Rochester MN 55902",
    "addr:housenumber":"421",
    "addr:postcode":"55902",
    "addr:street":"1St Ave Sw",
    "iso:country":"US",
    "sg:address":"421 1st Ave SW",
    "sg:city":"Rochester",
    "sg:classifiers":[
        {
            "category":"Manufacturing",
            "subcategory":"Wood Products",
            "type":"Manufacturing & Wholesale Goods"
        }
    ],
    "sg:phone":"+1 507 206 6969",
    "sg:postcode":"55902",
    "sg:province":"MN",
    "sg:tags":[
        "millwork-wholesale",
        "millwork",
        "manufacturer"
    ],
    "wof:name":"1760 Millwork Manufacturing Company",
    "wof:placetype":"venue"
},
  "geometry": {"coordinates":[-92.46442,44.019016],"type":"Point"}
}