{
  "type": "Feature",
  "properties": {
    "addr:full":"18470 Territorial Rd Osseo MN 55369",
    "addr:housenumber":"18470",
    "addr:postcode":"55369",
    "addr:street":"Territorial Rd",
    "iso:country":"US",
    "sg:address":"18470 Territorial Rd",
    "sg:city":"Osseo",
    "sg:classifiers":[
        {
            "category":"Professional",
            "type":"Services"
        }
    ],
    "sg:phone":"+1 763 425 5530",
    "sg:postcode":"55369",
    "sg:province":"MN",
    "sg:tags":[
        "establishment"
    ],
    "wof:name":"Midwest Car Search",
    "wof:placetype":"venue"
},
  "geometry": {"coordinates":[-93.505734,45.159171],"type":"Point"}
}