{
  "type": "Feature",
  "properties": {
    "addr:full":"800 N Boundary Ave Duluth MN 55810",
    "addr:housenumber":"800",
    "addr:postcode":"55810",
    "addr:street":"N Boundary Ave",
    "iso:country":"US",
    "sg:address":"800 N Boundary Ave",
    "sg:city":"Duluth",
    "sg:classifiers":[
        {
            "category":"Community Center",
            "type":"Public Place"
        }
    ],
    "sg:phone":"+1 218 624 7988",
    "sg:postcode":"55810",
    "sg:province":"MN",
    "sg:tags":[
        "recreation"
    ],
    "wof:name":"Proctor Arena",
    "wof:placetype":"venue"
},
  "geometry": {"coordinates":[-92.217072,46.750648],"type":"Point"}
}