{
  "type": "Feature",
  "properties": {
    "addr:full":"226 S Washington St Redwood Falls MN 56283",
    "addr:housenumber":"226",
    "addr:postcode":"56283",
    "addr:street":"S Washington St",
    "iso:country":"US",
    "sg:address":"226 S Washington St",
    "sg:city":"Redwood Falls",
    "sg:classifiers":[
        {
            "category":"Shopping",
            "subcategory":"Clothing, Apparel, & Fashions",
            "type":"Retail Goods"
        }
    ],
    "sg:phone":"+1 507 637 5597",
    "sg:postcode":"56283",
    "sg:province":"MN",
    "sg:tags":[
        "ready"
    ],
    "wof:name":"Treonne's",
    "wof:placetype":"venue"
},
  "geometry": {"coordinates":[-95.117931,44.540229],"type":"Point"}
}