{
  "type": "Feature",
  "properties": {
    "addr:full":"35249 248th Ave Albany MN 56307",
    "addr:housenumber":"35249",
    "addr:postcode":"56307",
    "addr:street":"248Th Ave",
    "iso:country":"US",
    "sg:address":"35249 248th Ave",
    "sg:city":"Albany",
    "sg:classifiers":[
        {
            "category":"Farming",
            "subcategory":"Dairy Farm",
            "type":"Manufacturing & Wholesale Goods"
        }
    ],
    "sg:phone":"+1 320 845 7427",
    "sg:postcode":"56307",
    "sg:province":"MN",
    "wof:name":"Ronald Robert Budde",
    "wof:placetype":"venue"
},
  "geometry": {"coordinates":[-94.624692,45.630336],"type":"Point"}
}