{
  "type": "Feature",
  "properties": {
    "addr:full":"28915 Bello Cir Grand Rapids MN 55744",
    "addr:postcode":"28915;55744",
    "addr:street":"Bello Cir",
    "iso:country":"US",
    "sg:address":"28915 Bello Cir",
    "sg:city":"Grand Rapids",
    "sg:classifiers":[
        {
            "category":"Retail",
            "subcategory":"Repair Shop",
            "type":"Services"
        }
    ],
    "sg:phone":"+1 218 327 0222",
    "sg:postcode":"55744",
    "sg:province":"MN",
    "sg:tags":[
        "lock",
        "locksmith"
    ],
    "wof:name":"Johnson's Lock & Safe",
    "wof:placetype":"venue"
},
  "geometry": {"coordinates":[-93.52319199999999,47.295556],"type":"Point"}
}