{
  "type": "Feature",
  "properties": {
    "addr:full":"402 W Vernon Ave Fergus Falls MN 56537",
    "addr:housenumber":"402",
    "addr:postcode":"56537",
    "addr:street":"W Vernon Ave",
    "iso:country":"US",
    "sg:address":"402 W Vernon Ave",
    "sg:city":"Fergus Falls",
    "sg:classifiers":[
        {
            "category":"Professional",
            "subcategory":"Management & Consulting",
            "type":"Services"
        },
        {
            "category":"Professional",
            "subcategory":"Advertising",
            "type":"Services"
        }
    ],
    "sg:phone":"+1 218 736 7300",
    "sg:postcode":"56537",
    "sg:province":"MN",
    "sg:tags":[
        "counselor",
        "business"
    ],
    "wof:name":"Creative Prtnerships Unlimited",
    "wof:placetype":"venue"
},
  "geometry": {"coordinates":[-96.080206,46.278392],"type":"Point"}
}