{
  "type": "Feature",
  "properties": {
    "addr:full":"13875 Crosstown Dr NW Andover MN 55304",
    "addr:postcode":"13875;55304",
    "addr:street":"Crosstown Dr Nw",
    "iso:country":"US",
    "sg:address":"13875 Crosstown Dr NW",
    "sg:city":"Andover",
    "sg:classifiers":[
        {
            "category":"Government",
            "subcategory":"Fire Station",
            "type":"Public Place"
        }
    ],
    "sg:phone":"+1 763 755 9825",
    "sg:postcode":"55304",
    "sg:province":"MN",
    "sg:tags":[
        "department"
    ],
    "wof:name":"Andover City Fire Dept",
    "wof:placetype":"venue"
},
  "geometry": {"coordinates":[-93.329857,45.223723],"type":"Point"}
}