{
  "type": "Feature",
  "properties": {
    "addr:full":"322 W Rock St Springfield MN 56087",
    "addr:housenumber":"322",
    "addr:postcode":"56087",
    "addr:street":"W Rock St",
    "iso:country":"US",
    "sg:address":"322 W Rock St",
    "sg:city":"Springfield",
    "sg:classifiers":[
        {
            "category":"Building & Trades",
            "subcategory":"Construction",
            "type":"Services"
        }
    ],
    "sg:phone":"+1 507 723 5051",
    "sg:postcode":"56087",
    "sg:province":"MN",
    "sg:tags":[
        "contractor",
        "recreational",
        "campers-wholesale",
        "manufacturer",
        "vehicle"
    ],
    "wof:name":"Springfield Wldg & Trlr Repr",
    "wof:placetype":"venue"
},
  "geometry": {"coordinates":[-94.981155,44.243445],"type":"Point"}
}