{
  "type": "Feature",
  "properties": {
    "addr:full":"22887 350th Ave SE Trail MN 56684",
    "addr:housenumber":"22887",
    "addr:postcode":"56684",
    "addr:street":"350Th Ave Se Trail",
    "iso:country":"US",
    "sg:address":"22887 350th Ave SE",
    "sg:city":"Trail",
    "sg:classifiers":[
        {
            "category":"Social Services",
            "subcategory":"Child Care",
            "type":"Services"
        }
    ],
    "sg:phone":"+1 218 796 4565",
    "sg:postcode":"56684",
    "sg:province":"MN",
    "sg:tags":[
        "nursery",
        "day"
    ],
    "wof:name":"Pams Child Care",
    "wof:placetype":"venue"
},
  "geometry": {"coordinates":[-95.730745,47.834321],"type":"Point"}
}