{
  "type": "Feature",
  "properties": {
    "addr:full":"11949 9th St NE Hanover MN 55341",
    "addr:housenumber":"11949",
    "addr:postcode":"55341",
    "addr:street":"9Th St Ne",
    "iso:country":"US",
    "sg:address":"11949 9th St NE",
    "sg:city":"Hanover",
    "sg:classifiers":[
        {
            "category":"Organizations",
            "subcategory":"Membership Organization",
            "type":"Services"
        }
    ],
    "sg:phone":"+1 763 497 5489",
    "sg:postcode":"55341",
    "sg:province":"MN",
    "wof:name":"American Federation of St",
    "wof:placetype":"venue"
},
  "geometry": {"coordinates":[-93.646641,45.164528],"type":"Point"}
}