{
  "type": "Feature",
  "properties": {
    "iso:country":"US",
    "sg:address":"31181 State Hwy 15",
    "sg:city":"Kimball",
    "sg:classifiers":[
        {
            "category":"Building & Trades",
            "subcategory":"Construction",
            "type":"Services"
        }
    ],
    "sg:phone":"+1 320 398 8533",
    "sg:postcode":"55353",
    "sg:province":"MN",
    "sg:tags":[
        "contractor"
    ],
    "wof:name":"W K F Enterprises",
    "wof:placetype":"venue"
},
  "geometry": {"coordinates":[-94.316804,45.196672],"type":"Point"}
}