{
  "type": "Feature",
  "properties": {
    "addr:full":"1900 Stevens Ave S Minneapolis MN 55403",
    "addr:housenumber":"1900",
    "addr:postcode":"55403",
    "addr:street":"Stevens Ave S",
    "iso:country":"US",
    "sg:address":"1900 Stevens Ave S",
    "sg:city":"Minneapolis",
    "sg:classifiers":[
        {
            "category":"Professional",
            "subcategory":"Employment Agencies",
            "type":"Services"
        }
    ],
    "sg:phone":"+1 612 872 4624",
    "sg:postcode":"55403",
    "sg:province":"MN",
    "wof:name":"101 Nannies Placement Age",
    "wof:placetype":"venue"
},
  "geometry": {"coordinates":[-93.275284,44.962696],"type":"Point"}
}