{
  "type": "Feature",
  "properties": {
    "iso:country":"US",
    "sg:address":"709 21st St NE",
    "sg:city":"Austin",
    "sg:classifiers":[
        {
            "category":"Autos & Motor Vehicles",
            "subcategory":"Fuel & Gas Station",
            "type":"Retail Goods"
        }
    ],
    "sg:phone":"+1 507 433 7071",
    "sg:postcode":"55912",
    "sg:province":"MN",
    "sg:tags":[
        "oil"
    ],
    "wof:name":"Shell Food Mart Of Austin",
    "wof:placetype":"venue"
},
  "geometry": {"coordinates":[-92.93957899999999,43.671972],"type":"Point"}
}