{
  "type": "Feature",
  "properties": {
    "iso:country":"US",
    "sg:address":"718 Mound Ave",
    "sg:city":"Mankato",
    "sg:classifiers":[
        {
            "category":"Restaurant",
            "type":"Food & Drink"
        }
    ],
    "sg:phone":"+1 507 385 4379",
    "sg:postcode":"56001",
    "sg:province":"MN",
    "sg:tags":[
        "caterer"
    ],
    "wof:name":"Gourmet Apron Catering",
    "wof:placetype":"venue"
},
  "geometry": {"coordinates":[-94.029087,44.162734],"type":"Point"}
}