{
  "type": "Feature",
  "properties": {
    "addr:full":"728 8th Ave S Sauk Rapids MN 56379",
    "addr:housenumber":"728",
    "addr:postcode":"56379",
    "addr:street":"8Th Ave S Sauk",
    "iso:country":"US",
    "sg:address":"728 8th Ave S",
    "sg:city":"Sauk Rapids",
    "sg:classifiers":[
        {
            "category":"Professional",
            "subcategory":"Management & Consulting",
            "type":"Services"
        }
    ],
    "sg:phone":"+1 320 251 9100",
    "sg:postcode":"56379",
    "sg:province":"MN",
    "sg:tags":[
        "public",
        "relations"
    ],
    "wof:name":"Warner Promotions Group",
    "wof:placetype":"venue"
},
  "geometry": {"coordinates":[-94.15530200000001,45.582661],"type":"Point"}
}