{
  "type": "Feature",
  "properties": {
    "addr:full":"2512 Conifer Ave Alexandria MN 56308",
    "addr:housenumber":"2512",
    "addr:postcode":"56308",
    "addr:street":"Conifer Ave",
    "iso:country":"US",
    "sg:address":"2512 Conifer Ave",
    "sg:city":"Alexandria",
    "sg:classifiers":[
        {
            "category":"Wholesale",
            "subcategory":"Non-durable Goods",
            "type":"Manufacturing & Wholesale Goods"
        }
    ],
    "sg:phone":"+1 320 759 3965",
    "sg:postcode":"56308",
    "sg:province":"MN",
    "wof:name":"Express It With A Basket",
    "wof:placetype":"venue"
},
  "geometry": {"coordinates":[-95.33627,45.90029],"type":"Point"}
}