{
  "type": "Feature",
  "properties": {
    "iso:country":"US",
    "sg:address":"11657 N Heights Dr NW",
    "sg:city":"Minneapolis",
    "sg:classifiers":[
        {
            "category":"Professional",
            "subcategory":"Advertising",
            "type":"Services"
        },
        {
            "category":"Professional",
            "subcategory":"Art Services",
            "type":"Services"
        }
    ],
    "sg:phone":"+1 763 755 6769",
    "sg:postcode":"55433",
    "sg:province":"MN",
    "sg:tags":[
        "design",
        "graphic",
        "commercial",
        "designer"
    ],
    "wof:name":"Crown Graphics",
    "wof:placetype":"venue"
},
  "geometry": {"coordinates":[-93.336257,45.180997],"type":"Point"}
}