{
  "type": "Feature",
  "properties": {
    "addr:full":"2845 Harriet Ave Ste 107 Minneapolis MN 55408",
    "addr:housenumber":"2845",
    "addr:postcode":"55408",
    "addr:street":"Harriet Ave Ste 107",
    "iso:country":"US",
    "sg:address":"2845 Harriet Ave Ste 107",
    "sg:city":"Minneapolis",
    "sg:classifiers":[
        {
            "category":"Wholesale",
            "subcategory":"Office Equipment",
            "type":"Manufacturing & Wholesale Goods"
        }
    ],
    "sg:phone":"+1 612 381 9333",
    "sg:postcode":"55408",
    "sg:province":"MN",
    "sg:tags":[
        "equipment-installation",
        "furniture"
    ],
    "wof:name":"Instant Install",
    "wof:placetype":"venue"
},
  "geometry": {"coordinates":[-93.285534,44.951163],"type":"Point"}
}