{
  "type": "Feature",
  "properties": {
    "addr:full":"4904 US Hwy 12 Maple Plain MN 55359",
    "addr:housenumber":"4904",
    "addr:postcode":"55359",
    "addr:street":"Us Hwy 12;Plain",
    "iso:country":"US",
    "sg:address":"4904 US Hwy 12",
    "sg:city":"Maple Plain",
    "sg:classifiers":[
        {
            "category":"Sports & Exercise",
            "subcategory":"Gym",
            "type":"Entertainment"
        }
    ],
    "sg:phone":"+1 763 479 0159",
    "sg:postcode":"55359",
    "sg:province":"MN",
    "sg:tags":[
        "center",
        "fitness"
    ],
    "wof:name":"Curves For Women",
    "wof:placetype":"venue"
},
  "geometry": {"coordinates":[-93.646496,45.003469],"type":"Point"}
}