{
  "type": "Feature",
  "properties": {
    "iso:country":"US",
    "sg:address":"650 Bunker Lake Blvd NW",
    "sg:city":"Anoka",
    "sg:classifiers":[
        {
            "category":"Building & Trades",
            "subcategory":"Construction",
            "type":"Services"
        }
    ],
    "sg:phone":"+1 763 323 7550",
    "sg:postcode":"55304",
    "sg:province":"MN",
    "sg:tags":[
        "house",
        "nonresidential"
    ],
    "wof:name":"Hedberg Homes Inc",
    "wof:placetype":"venue"
},
  "geometry": {"coordinates":[-93.28067,45.220771],"type":"Point"}
}