{
  "type": "Feature",
  "properties": {
    "addr:full":"1515 Cloquet Ave Cloquet MN 55720",
    "addr:housenumber":"1515",
    "addr:postcode":"55720",
    "addr:street":"Cloquet Ave",
    "iso:country":"US",
    "sg:address":"1515 Cloquet Ave",
    "sg:city":"Cloquet",
    "sg:classifiers":[
        {
            "category":"Autos & Motor Vehicles",
            "subcategory":"Automobile Sales",
            "type":"Retail Goods"
        }
    ],
    "sg:phone":"+1 218 879 1164",
    "sg:postcode":"55720",
    "sg:province":"MN",
    "sg:tags":[
        "car",
        "dealer"
    ],
    "wof:name":"Midwest Auto Exchange",
    "wof:placetype":"venue"
},
  "geometry": {"coordinates":[-92.44749,46.721485],"type":"Point"}
}