{
  "type": "Feature",
  "properties": {
    "addr:full":"14725 Cimarron Ave W Rosemount MN 55068",
    "addr:housenumber":"14725",
    "addr:postcode":"55068",
    "addr:street":"Cimarron Ave W",
    "iso:country":"US",
    "sg:address":"14725 Cimarron Ave W",
    "sg:city":"Rosemount",
    "sg:classifiers":[
        {
            "category":"Building & Trades",
            "subcategory":"Construction",
            "type":"Services"
        }
    ],
    "sg:phone":"+1 651 423 6666",
    "sg:postcode":"55068",
    "sg:province":"MN",
    "sg:tags":[
        "house"
    ],
    "wof:name":"All Done Contracting Inc",
    "wof:placetype":"venue"
},
  "geometry": {"coordinates":[-93.140817,44.734228],"type":"Point"}
}