{
  "type": "Feature",
  "properties": {
    "addr:full":"14321 Nicollet Ct Burnsville MN 55306",
    "addr:housenumber":"14321",
    "addr:postcode":"55306",
    "addr:street":"Nicollet Ct",
    "iso:country":"US",
    "sg:address":"14321 Nicollet Ct",
    "sg:city":"Burnsville",
    "sg:classifiers":[
        {
            "category":"Professional",
            "subcategory":"Employment Agencies",
            "type":"Services"
        }
    ],
    "sg:phone":"+1 952 848 1831",
    "sg:postcode":"55306",
    "sg:province":"MN",
    "sg:tags":[
        "opportunity"
    ],
    "wof:name":"Hrprincipals",
    "wof:placetype":"venue"
},
  "geometry": {"coordinates":[-93.280907,44.743467],"type":"Point"}
}