{
  "type": "Feature",
  "properties": {
    "addr:full":"105 Mantorville Ave S Kasson MN 55944",
    "addr:housenumber":"105",
    "addr:postcode":"55944",
    "addr:street":"Mantorville Ave S Kasson",
    "iso:country":"US",
    "sg:address":"105 Mantorville Ave S",
    "sg:city":"Kasson",
    "sg:classifiers":[
        {
            "category":"Manufacturing",
            "subcategory":"Printing",
            "type":"Manufacturing & Wholesale Goods"
        }
    ],
    "sg:phone":"+1 507 634 7776",
    "sg:postcode":"55944",
    "sg:province":"MN",
    "sg:tags":[
        "commercial",
        "merchandise",
        "mfg"
    ],
    "sg:website":"www.imagesonmetal.com",
    "wof:name":"Images On Metal Inc",
    "wof:placetype":"venue"
},
  "geometry": {"coordinates":[-92.748261,44.028446],"type":"Point"}
}