{
  "type": "Feature",
  "properties": {
    "iso:country":"US",
    "sg:address":"670 50th Ave NE",
    "sg:city":"Benson",
    "sg:classifiers":[
        {
            "category":"Home & Garden",
            "subcategory":"Garden Supply",
            "type":"Retail Goods"
        }
    ],
    "sg:phone":"+1 320 843 2857",
    "sg:postcode":"56215",
    "sg:province":"MN",
    "wof:name":"Lees Seed Farm",
    "wof:placetype":"venue"
},
  "geometry": {"coordinates":[-95.520991,45.384787],"type":"Point"}
}