{
  "type": "Feature",
  "properties": {
    "iso:country":"US",
    "sg:address":"7600 France Ave S",
    "sg:city":"Edina",
    "sg:classifiers":[
        {
            "category":"Education",
            "subcategory":"Special Training",
            "type":"Public Place"
        }
    ],
    "sg:phone":"+1 952 820 5000",
    "sg:postcode":"55435",
    "sg:province":"MN",
    "sg:tags":[
        "tutoring"
    ],
    "wof:name":"Sylvan Learning Ctr",
    "wof:placetype":"venue"
},
  "geometry": {"coordinates":[-93.328812,44.861897],"type":"Point"}
}