{
  "type": "Feature",
  "properties": {
    "addr:full":"524 Circle Dr Tracy MN 56175",
    "addr:housenumber":"524",
    "addr:postcode":"56175",
    "addr:street":"Circle Dr",
    "iso:country":"US",
    "sg:address":"524 Circle Dr",
    "sg:city":"Tracy",
    "sg:classifiers":[
        {
            "category":"Utilities",
            "subcategory":"Electric",
            "type":"Services"
        }
    ],
    "sg:phone":"+1 507 629 4288",
    "sg:postcode":"56175",
    "sg:province":"MN",
    "wof:name":"J T Gary Inc",
    "wof:placetype":"venue"
},
  "geometry": {"coordinates":[-95.606956,44.23842],"type":"Point"}
}