{
  "type": "Feature",
  "properties": {
    "iso:country":"US",
    "sg:address":"14655 Chicago Ave",
    "sg:city":"Burnsville",
    "sg:classifiers":[
        {
            "category":"Building & Trades",
            "subcategory":"Construction",
            "type":"Services"
        }
    ],
    "sg:phone":"+1 952 997 7504",
    "sg:postcode":"55306",
    "sg:province":"MN",
    "sg:tags":[
        "contractor"
    ],
    "wof:name":"Elizondo Drywall",
    "wof:placetype":"venue"
},
  "geometry": {"coordinates":[-93.263166,44.737531],"type":"Point"}
}