{
  "type": "Feature",
  "properties": {
    "iso:country":"US",
    "sg:address":"903 Crofoot Ave SW",
    "sg:city":"Buffalo",
    "sg:classifiers":[
        {
            "category":"Retail",
            "subcategory":"Laundry & Dry Cleaning",
            "type":"Services"
        }
    ],
    "sg:phone":"+1 612 388 3734",
    "sg:postcode":"55313",
    "sg:province":"MN",
    "sg:tags":[
        "cleaner",
        "rug",
        "carpet"
    ],
    "sg:website":"http://ezlocal.com/MN/Buffalo/Carpet-Cleaning-Service/36974",
    "wof:name":"Minnetonka Carpet Care",
    "wof:placetype":"venue"
},
  "geometry": {"coordinates":[-93.941166,45.140108],"type":"Point"}
}