{
  "type": "Feature",
  "properties": {
    "iso:country":"US",
    "sg:address":"2751 Market St",
    "sg:city":"Mahtowa",
    "sg:classifiers":[
        {
            "category":"Food & Beverages",
            "subcategory":"Groceries & Convenience Stores",
            "type":"Retail Goods"
        }
    ],
    "sg:phone":"+1 218 389 6257",
    "sg:postcode":"55707",
    "sg:province":"MN",
    "sg:tags":[
        "grocer"
    ],
    "wof:name":"T J's Country Corner",
    "wof:placetype":"venue"
},
  "geometry": {"coordinates":[-92.634028,46.57326],"type":"Point"}
}