{
  "type": "Feature",
  "properties": {
    "addr:full":"46588 Hagen Rd NW Grygla MN 56727",
    "addr:housenumber":"46588",
    "addr:postcode":"56727",
    "addr:street":"Hagen Rd Nw",
    "iso:country":"US",
    "sg:address":"46588 Hagen Rd NW",
    "sg:city":"Grygla",
    "sg:phone":"+1 218 294 6382",
    "sg:postcode":"56727",
    "sg:province":"MN",
    "sg:tags":[
        "farm",
        "wheat",
        "grain",
        "cash"
    ],
    "wof:name":"Norris Hagen",
    "wof:placetype":"venue"
},
  "geometry": {"coordinates":[-95.577224,48.395141],"type":"Point"}
}