{
  "type": "Feature",
  "properties": {
    "addr:full":"315 N 6th St Brainerd MN 56401",
    "addr:housenumber":"315",
    "addr:postcode":"56401",
    "addr:street":"N 6Th St",
    "iso:country":"US",
    "sg:address":"315 N 6th St",
    "sg:city":"Brainerd",
    "sg:classifiers":[
        {
            "category":"Education",
            "subcategory":"Preschool",
            "type":"Public Place"
        },
        {
            "category":"Education",
            "subcategory":"School",
            "type":"Public Place"
        }
    ],
    "sg:phone":"+1 218 829 5222",
    "sg:postcode":"56401",
    "sg:province":"MN",
    "sg:tags":[
        "kindergarten"
    ],
    "wof:name":"Life Lessons Inc",
    "wof:placetype":"venue"
},
  "geometry": {"coordinates":[-94.20062900000001,46.359229],"type":"Point"}
}