{
  "type": "Feature",
  "properties": {
    "iso:country":"US",
    "sg:address":"81 9th St S",
    "sg:city":"Minneapolis",
    "sg:classifiers":[
        {
            "category":"Food & Beverages",
            "subcategory":"Liquor & Beverages",
            "type":"Retail Goods"
        }
    ],
    "sg:phone":"+1 612 333 2434",
    "sg:postcode":"55402",
    "sg:province":"MN",
    "sg:tags":[
        "spirits",
        "wine"
    ],
    "wof:name":"Haskells Wine & Spirits",
    "wof:placetype":"venue"
},
  "geometry": {"coordinates":[-93.273027,44.974538],"type":"Point"}
}