{
  "type": "Feature",
  "properties": {
    "addr:full":"312 N Main St Center City MN 55012",
    "addr:housenumber":"312",
    "addr:postcode":"55012",
    "addr:street":"N Main St",
    "iso:country":"US",
    "sg:address":"312 N Main St",
    "sg:city":"Center City",
    "sg:classifiers":[
        {
            "category":"Government",
            "subcategory":"Office",
            "type":"Public Place"
        }
    ],
    "sg:phone":"+1 651 257 0384",
    "sg:postcode":"55012",
    "sg:province":"MN",
    "sg:tags":[
        "county",
        "safety",
        "order"
    ],
    "wof:name":"Emergency Management",
    "wof:placetype":"venue"
},
  "geometry": {"coordinates":[-92.821696,45.401591],"type":"Point"}
}