{
  "type": "Feature",
  "properties": {
    "addr:full":"3094 25th St NW Rochester MN 55901",
    "addr:housenumber":"3094",
    "addr:postcode":"55901",
    "addr:street":"25Th St Nw",
    "iso:country":"US",
    "sg:address":"3094 25th St NW",
    "sg:city":"Rochester",
    "sg:classifiers":[
        {
            "category":"Real Estate",
            "subcategory":"Real Estate Operator",
            "type":"Services"
        }
    ],
    "sg:phone":"+1 877 271 7870",
    "sg:postcode":"55901",
    "sg:province":"MN",
    "sg:tags":[
        "apartment"
    ],
    "sg:website":"http://local.ingenio.com/Listings/Details.aspx?NUM=a%3a10313603%3a13%3a4859924%3a14%3a0%3a7",
    "wof:name":"Royal Oaks Apartments",
    "wof:placetype":"venue"
},
  "geometry": {"coordinates":[-92.508324,44.049278],"type":"Point"}
}