{
  "type": "Feature",
  "properties": {
    "addr:full":"7201 Walker St Minneapolis MN 55426",
    "addr:housenumber":"7201",
    "addr:postcode":"55426",
    "addr:street":"Walker St",
    "iso:country":"US",
    "sg:address":"7201 Walker St",
    "sg:city":"Minneapolis",
    "sg:classifiers":[
        {
            "category":"Building & Trades",
            "subcategory":"Construction",
            "type":"Services"
        }
    ],
    "sg:phone":"+1 952 351 4540",
    "sg:postcode":"55426",
    "sg:province":"MN",
    "sg:tags":[
        "commercial",
        "contractor"
    ],
    "wof:name":"M S P Real Estate and Cnstr",
    "wof:placetype":"venue"
},
  "geometry": {"coordinates":[-93.368037,44.938784],"type":"Point"}
}