{
  "type": "Feature",
  "properties": {
    "addr:full":"50 Circuit Dr New Ulm MN 56073",
    "addr:housenumber":"50",
    "addr:postcode":"56073",
    "addr:street":"Circuit Dr",
    "iso:country":"US",
    "sg:address":"50 Circuit Dr",
    "sg:city":"New Ulm",
    "sg:classifiers":[
        {
            "category":"Professional",
            "subcategory":"Management & Consulting",
            "type":"Services"
        }
    ],
    "sg:phone":"+1 507 359 9790",
    "sg:postcode":"56073",
    "sg:province":"MN",
    "wof:name":"Commercial Choice Inc",
    "wof:placetype":"venue"
},
  "geometry": {"coordinates":[-94.462406,44.297971],"type":"Point"}
}