{
  "type": "Feature",
  "properties": {
    "iso:country":"US",
    "sg:address":"221 Briarwood Ln",
    "sg:city":"La Crescent",
    "sg:classifiers":[
        {
            "category":"Home & Garden",
            "subcategory":"Building Materials",
            "type":"Retail Goods"
        }
    ],
    "sg:phone":"+1 507 895 7777",
    "sg:postcode":"55947",
    "sg:province":"MN",
    "sg:tags":[
        "door"
    ],
    "wof:name":"Olson's Tri State Overhead",
    "wof:placetype":"venue"
},
  "geometry": {"coordinates":[-91.337791,43.812993],"type":"Point"}
}