{
  "type": "Feature",
  "properties": {
    "addr:full":"180 Birch St N Cambridge MN 55008",
    "addr:housenumber":"180",
    "addr:postcode":"55008",
    "addr:street":"Birch St N",
    "iso:country":"US",
    "sg:address":"180 Birch St N",
    "sg:city":"Cambridge",
    "sg:classifiers":[
        {
            "category":"Insurance",
            "subcategory":"Insurance Agent",
            "type":"Services"
        }
    ],
    "sg:phone":"+1 763 689 2028",
    "sg:postcode":"55008",
    "sg:province":"MN",
    "wof:name":"American Family Insurance",
    "wof:placetype":"venue"
},
  "geometry": {"coordinates":[-93.226782,45.57281],"type":"Point"}
}