{
  "type": "Feature",
  "properties": {
    "addr:full":"2548 Broadway Ave Slayton MN 56172",
    "addr:housenumber":"2548",
    "addr:postcode":"56172",
    "addr:street":"Broadway Ave",
    "iso:country":"US",
    "sg:address":"2548 Broadway Ave",
    "sg:city":"Slayton",
    "sg:classifiers":[
        {
            "category":"Professional",
            "subcategory":"Lawyer & Legal Services",
            "type":"Services"
        }
    ],
    "sg:phone":"+1 507 836 6757",
    "sg:postcode":"56172",
    "sg:province":"MN",
    "sg:tags":[
        "law"
    ],
    "wof:name":"Johnson Lynn A Attorney At Law",
    "wof:placetype":"venue"
},
  "geometry": {"coordinates":[-95.75640799999999,43.988499],"type":"Point"}
}