{
  "type": "Feature",
  "properties": {
    "iso:country":"US",
    "sg:address":"61858 Co Rd 527",
    "sg:city":"Cook",
    "sg:classifiers":[
        {
            "category":"Retail",
            "subcategory":"Auto Repair",
            "type":"Services"
        }
    ],
    "sg:phone":"+1 218 376 4583",
    "sg:postcode":"55723",
    "sg:province":"MN",
    "sg:tags":[
        "general"
    ],
    "wof:name":"Up North Auto Inc",
    "wof:placetype":"venue"
},
  "geometry": {"coordinates":[-93.08053099999999,47.822213],"type":"Point"}
}