{
  "type": "Feature",
  "properties": {
    "addr:full":"10201 Wayzata Blvd. Suite 250 Minneapolis MN 55305",
    "addr:housenumber":"10201",
    "addr:postcode":"55305",
    "addr:street":"Wayzata Blvd. Suite 250",
    "iso:country":"US",
    "sg:address":"10201 Wayzata Blvd. Suite 250",
    "sg:city":"Minneapolis",
    "sg:classifiers":[
        {
            "category":"Professional",
            "subcategory":"Research",
            "type":"Services"
        }
    ],
    "sg:phone":"+1 763 226 2701",
    "sg:postcode":"55305",
    "sg:province":"MN",
    "sg:website":"http://www.advancedbioenergy.com/",
    "wof:name":"Advanced BioEnergy",
    "wof:placetype":"venue"
},
  "geometry": {"coordinates":[-93.51223,44.972752],"type":"Point"}
}