{
  "type": "Feature",
  "properties": {
    "addr:full":"7964 245th St Saint Cloud MN 56301",
    "addr:housenumber":"7964",
    "addr:postcode":"56301",
    "addr:street":"245Th St",
    "iso:country":"US",
    "sg:address":"7964 245th St",
    "sg:city":"Saint Cloud",
    "sg:classifiers":[
        {
            "category":"Organizations",
            "subcategory":"Membership Organization",
            "type":"Services"
        }
    ],
    "sg:phone":"+1 320 251 7410",
    "sg:postcode":"56301",
    "sg:province":"MN",
    "wof:name":"Percherons of Minnesota",
    "wof:placetype":"venue"
},
  "geometry": {"coordinates":[-94.275283,45.479374],"type":"Point"}
}