{
  "type": "Feature",
  "properties": {
    "addr:full":"1621 7th St W St Paul MN 55102",
    "addr:housenumber":"1621",
    "addr:postcode":"55102",
    "addr:street":"7Th St W",
    "iso:country":"US",
    "sg:address":"1621 7th St W",
    "sg:city":"St Paul",
    "sg:classifiers":[
        {
            "category":"Banks & Credit Unions",
            "subcategory":"Financial Services",
            "type":"Services"
        },
        {
            "category":"Wholesale",
            "subcategory":"Durable Goods & Equipment",
            "type":"Manufacturing & Wholesale Goods"
        }
    ],
    "sg:phone":"+1 651 329 2938",
    "sg:postcode":"55102",
    "sg:province":"MN",
    "sg:tags":[
        "importer",
        "investor"
    ],
    "wof:name":"Semakula Investments",
    "wof:placetype":"venue"
},
  "geometry": {"coordinates":[-93.14346500000001,44.916365],"type":"Point"}
}