{
  "type": "Feature",
  "properties": {
    "iso:country":"US",
    "sg:address":"18 University Ave NE",
    "sg:city":"Minneapolis",
    "sg:classifiers":[
        {
            "category":"Shopping",
            "subcategory":"Jewelry",
            "type":"Retail Goods"
        }
    ],
    "sg:phone":"+1 612 789 2656",
    "sg:postcode":"55413",
    "sg:province":"MN",
    "sg:tags":[
        "jeweler"
    ],
    "sg:website":"www.tleegold.com",
    "wof:name":"T Lee Fine Designer Jewelry",
    "wof:placetype":"venue"
},
  "geometry": {"coordinates":[-93.256401,44.988201],"type":"Point"}
}