{
  "type": "Feature",
  "properties": {
    "addr:full":"16144 700th Ave Taopi MN 55977",
    "addr:housenumber":"16144",
    "addr:postcode":"55977",
    "addr:street":"700Th Ave",
    "iso:country":"US",
    "sg:address":"16144 700th Ave",
    "sg:city":"Taopi",
    "sg:phone":"+1 507 582 7772",
    "sg:postcode":"55977",
    "sg:province":"MN",
    "sg:tags":[
        "farm",
        "corn"
    ],
    "wof:name":"David Voigt",
    "wof:placetype":"venue"
},
  "geometry": {"coordinates":[-92.648966,43.586887],"type":"Point"}
}