{
  "type": "Feature",
  "properties": {
    "addr:full":"7583 Irish Ave S Cottage Grove MN 55016",
    "addr:housenumber":"7583",
    "addr:postcode":"55016",
    "addr:street":"Irish Ave S Cottage Grove",
    "iso:country":"US",
    "sg:address":"7583 Irish Ave S",
    "sg:city":"Cottage Grove",
    "sg:classifiers":[
        {
            "category":"Personal",
            "subcategory":"Beauty Salon",
            "type":"Services"
        }
    ],
    "sg:phone":"+1 651 458 0242",
    "sg:postcode":"55016",
    "sg:province":"MN",
    "sg:tags":[
        "shop"
    ],
    "wof:name":"Joans Little Hair House",
    "wof:placetype":"venue"
},
  "geometry": {"coordinates":[-92.932901,44.839751],"type":"Point"}
}