{
  "type": "Feature",
  "properties": {
    "iso:country":"US",
    "sg:address":"5881 Pagenkopf Rd",
    "sg:city":"Maple Plain",
    "sg:classifiers":[
        {
            "category":"Building & Trades",
            "subcategory":"Cleaning & Sanitation",
            "type":"Services"
        }
    ],
    "sg:phone":"+1 763 479 2946",
    "sg:postcode":"55359",
    "sg:province":"MN",
    "sg:tags":[
        "maintenance"
    ],
    "wof:name":"Minnetonka Maintenance",
    "wof:placetype":"venue"
},
  "geometry": {"coordinates":[-93.66937299999999,45.019008],"type":"Point"}
}