{
  "type": "Feature",
  "properties": {
    "addr:full":"108 W 2nd St Winona MN 55987",
    "addr:housenumber":"108",
    "addr:postcode":"55987",
    "addr:street":"W 2Nd St",
    "iso:country":"US",
    "sg:address":"108 W 2nd St",
    "sg:city":"Winona",
    "sg:classifiers":[
        {
            "category":"Wholesale",
            "subcategory":"Electrical",
            "type":"Manufacturing & Wholesale Goods"
        }
    ],
    "sg:phone":"+1 507 452 3103",
    "sg:postcode":"55987",
    "sg:province":"MN",
    "sg:tags":[
        "electric",
        "motor"
    ],
    "wof:name":"Lackore Electric Motor Repair",
    "wof:placetype":"venue"
},
  "geometry": {"coordinates":[-91.63854600000001,44.054059],"type":"Point"}
}