{
  "type": "Feature",
  "properties": {
    "iso:country":"US",
    "sg:address":"80 S 8th St Ste 900",
    "sg:city":"Minneapolis",
    "sg:classifiers":[
        {
            "category":"Insurance",
            "subcategory":"Hazard Insurance",
            "type":"Services"
        },
        {
            "category":"Banks & Credit Unions",
            "subcategory":"Financial Services",
            "type":"Services"
        }
    ],
    "sg:phone":"+1 612 349 5271",
    "sg:postcode":"55402",
    "sg:province":"MN",
    "sg:tags":[
        "retirement",
        "business",
        "profit",
        "annuity",
        "sharing",
        "commercial",
        "planning",
        "plan",
        "pension"
    ],
    "wof:name":"Northern Pension Corp",
    "wof:placetype":"venue"
},
  "geometry": {"coordinates":[-93.272398,44.975636],"type":"Point"}
}