{
  "type": "Feature",
  "properties": {
    "addr:full":"290 W Market Minneapolis MN 55425",
    "addr:housenumber":"290",
    "addr:postcode":"55425",
    "addr:street":"W Market",
    "iso:country":"US",
    "sg:address":"290 W Market",
    "sg:city":"Minneapolis",
    "sg:classifiers":[
        {
            "category":"Sports & Exercise",
            "subcategory":"Swimming Pool",
            "type":"Entertainment"
        }
    ],
    "sg:phone":"+1 952 858 9563",
    "sg:postcode":"55425",
    "sg:province":"MN",
    "sg:tags":[
        "swimwear",
        "accessory"
    ],
    "sg:website":"http://www.everythingbutwater.com",
    "wof:name":"Everything But Water",
    "wof:placetype":"venue"
},
  "geometry": {"coordinates":[-93.245313,44.853442],"type":"Point"}
}