{
  "type": "Feature",
  "properties": {
    "addr:full":"17470 90th Ave SE Atwater MN 56209",
    "addr:housenumber":"17470",
    "addr:postcode":"56209",
    "addr:street":"90Th Ave Se",
    "iso:country":"US",
    "sg:address":"17470 90th Ave SE",
    "sg:city":"Atwater",
    "sg:classifiers":[
        {
            "category":"Farming",
            "subcategory":"Farm",
            "type":"Manufacturing & Wholesale Goods"
        }
    ],
    "sg:phone":"+1 320 974 8085",
    "sg:postcode":"56209",
    "sg:province":"MN",
    "sg:tags":[
        "crop",
        "general"
    ],
    "wof:name":"Lamor",
    "wof:placetype":"venue"
},
  "geometry": {"coordinates":[-94.80621499999999,45.037983],"type":"Point"}
}