{
  "type": "Feature",
  "properties": {
    "iso:country":"US",
    "sg:address":"2841 Coon Rapids Blvd NW",
    "sg:city":"Coon Rapids",
    "sg:classifiers":[
        {
            "category":"Retail",
            "subcategory":"Auto Repair",
            "type":"Services"
        }
    ],
    "sg:phone":"+1 763 421 7270",
    "sg:postcode":"55433",
    "sg:province":"MN",
    "sg:tags":[
        "repairing",
        "automobile"
    ],
    "wof:name":"Auto Max Brake & Muffler Spec",
    "wof:placetype":"venue"
},
  "geometry": {"coordinates":[-93.339691,45.171614],"type":"Point"}
}