{
  "type": "Feature",
  "properties": {
    "addr:full":"2405 Meadow Ct St Cloud MN 56301",
    "addr:housenumber":"2405",
    "addr:postcode":"56301",
    "addr:street":"Meadow Ct",
    "iso:country":"US",
    "sg:address":"2405 Meadow Ct",
    "sg:city":"St Cloud",
    "sg:classifiers":[
        {
            "category":"Building & Trades",
            "subcategory":"Landscaping Services",
            "type":"Services"
        }
    ],
    "sg:phone":"+1 320 259 0991",
    "sg:postcode":"56301",
    "sg:province":"MN",
    "sg:tags":[
        "tree"
    ],
    "wof:name":"Kolstad Tree & Shrub Care",
    "wof:placetype":"venue"
},
  "geometry": {"coordinates":[-94.185136,45.542721],"type":"Point"}
}