{
  "type": "Feature",
  "properties": {
    "iso:country":"US",
    "sg:address":"9340 US Hwy 10",
    "sg:city":"Anoka",
    "sg:classifiers":[
        {
            "category":"Farming",
            "subcategory":"Livestock Farm",
            "type":"Manufacturing & Wholesale Goods"
        }
    ],
    "sg:phone":"+1 763 427 3390",
    "sg:postcode":"55303",
    "sg:province":"MN",
    "sg:tags":[
        "specialty",
        "animal"
    ],
    "wof:name":"Kitty Acres",
    "wof:placetype":"venue"
},
  "geometry": {"coordinates":[-93.505342,45.247568],"type":"Point"}
}