{
  "type": "Feature",
  "properties": {
    "addr:full":"3571 144th Ave NW Andover MN 55304",
    "addr:housenumber":"3571",
    "addr:postcode":"55304",
    "addr:street":"144Th Ave Nw",
    "iso:country":"US",
    "sg:address":"3571 144th Ave NW",
    "sg:city":"Andover",
    "sg:classifiers":[
        {
            "category":"Freight",
            "type":"Transportation"
        }
    ],
    "sg:phone":"+1 763 422 8918",
    "sg:postcode":"55304",
    "sg:province":"MN",
    "sg:tags":[
        "local",
        "trucking"
    ],
    "wof:name":"E & E Trucking",
    "wof:placetype":"venue"
},
  "geometry": {"coordinates":[-93.356443,45.232729],"type":"Point"}
}