{
  "type": "Feature",
  "properties": {
    "iso:country":"US",
    "sg:address":"3768 Auger Ave",
    "sg:city":"Saint Paul",
    "sg:classifiers":[
        {
            "category":"Professional",
            "subcategory":"Management & Consulting",
            "type":"Services"
        }
    ],
    "sg:phone":"+1 651 407 0656",
    "sg:postcode":"55110",
    "sg:province":"MN",
    "wof:name":"Monroe Smith Inc",
    "wof:placetype":"venue"
},
  "geometry": {"coordinates":[-93.022682,45.052595],"type":"Point"}
}