{
  "type": "Feature",
  "properties": {
    "addr:full":"5575 W 78th St Minneapolis MN 55439",
    "addr:housenumber":"5575",
    "addr:postcode":"55439",
    "addr:street":"W 78Th St",
    "iso:country":"US",
    "sg:address":"5575 W 78th St",
    "sg:city":"Minneapolis",
    "sg:classifiers":[
        {
            "category":"Shopping",
            "subcategory":"Catalog Store",
            "type":"Retail Goods"
        }
    ],
    "sg:phone":"+1 952 942 8010",
    "sg:postcode":"55439",
    "sg:province":"MN",
    "sg:tags":[
        "house",
        "mail"
    ],
    "wof:name":"Haverhills",
    "wof:placetype":"venue"
},
  "geometry": {"coordinates":[-93.361942,44.862167],"type":"Point"}
}