{
  "type": "Feature",
  "properties": {
    "iso:country":"US",
    "sg:address":"6501 Girard Ave S",
    "sg:city":"Minneapolis",
    "sg:classifiers":[
        {
            "category":"Professional",
            "subcategory":"Management & Consulting",
            "type":"Services"
        }
    ],
    "sg:phone":"+1 612 869 2947",
    "sg:postcode":"55423",
    "sg:province":"MN",
    "sg:tags":[
        "business"
    ],
    "wof:name":"Tool Qit",
    "wof:placetype":"venue"
},
  "geometry": {"coordinates":[-93.29721000000001,44.883446],"type":"Point"}
}