{
  "type": "Feature",
  "properties": {
    "iso:country":"US",
    "sg:address":"15790 78th St",
    "sg:city":"Mayer",
    "sg:classifiers":[
        {
            "category":"Building & Trades",
            "subcategory":"Electrical",
            "type":"Services"
        }
    ],
    "sg:phone":"+1 952 657 1060",
    "sg:postcode":"55360",
    "sg:province":"MN",
    "sg:tags":[
        "electrical",
        "contractor"
    ],
    "wof:name":"Martin Seltz Electric",
    "wof:placetype":"venue"
},
  "geometry": {"coordinates":[-93.92273400000001,44.862579],"type":"Point"}
}