{
  "type": "Feature",
  "properties": {
    "addr:full":"309 Pinecrest Ct SW Pine Island MN 55963",
    "addr:housenumber":"309",
    "addr:postcode":"55963",
    "addr:street":"Pinecrest Ct Sw Pine Island",
    "iso:country":"US",
    "sg:address":"309 Pinecrest Ct SW",
    "sg:city":"Pine Island",
    "sg:classifiers":[
        {
            "category":"Real Estate",
            "subcategory":"Real Estate Operator",
            "type":"Services"
        }
    ],
    "sg:phone":"+1 507 356 8979",
    "sg:postcode":"55963",
    "sg:province":"MN",
    "sg:tags":[
        "building",
        "apartment"
    ],
    "wof:name":"Weis Management",
    "wof:placetype":"venue"
},
  "geometry": {"coordinates":[-92.65114699999999,44.19902],"type":"Point"}
}