{
  "type": "Feature",
  "properties": {
    "addr:full":"2917 26th Ave S Minneapolis MN 55406",
    "addr:housenumber":"2917",
    "addr:postcode":"55406",
    "addr:street":"26Th Ave S",
    "iso:country":"US",
    "sg:address":"2917 26th Ave S",
    "sg:city":"Minneapolis",
    "sg:classifiers":[
        {
            "category":"Retail",
            "subcategory":"Photofinishing",
            "type":"Services"
        }
    ],
    "sg:phone":"+1 612 724 0726",
    "sg:postcode":"55406",
    "sg:province":"MN",
    "sg:tags":[
        "photo",
        "finishing"
    ],
    "sg:website":"www.proex.com",
    "wof:name":"Proex Photo",
    "wof:placetype":"venue"
},
  "geometry": {"coordinates":[-93.234695,44.949244],"type":"Point"}
}