{
  "type": "Feature",
  "properties": {
    "iso:country":"US",
    "sg:address":"711 Kragness Ave",
    "sg:city":"Worthington",
    "sg:classifiers":[
        {
            "category":"Home & Garden",
            "subcategory":"Building Materials",
            "type":"Retail Goods"
        }
    ],
    "sg:phone":"+1 507 376 6191",
    "sg:postcode":"56187",
    "sg:province":"MN",
    "sg:tags":[
        "lumber"
    ],
    "wof:name":"United Building Center",
    "wof:placetype":"venue"
},
  "geometry": {"coordinates":[-95.580659,43.624346],"type":"Point"}
}