{
  "type": "Feature",
  "properties": {
    "iso:country":"US",
    "sg:address":"9637 Hampshire Ln",
    "sg:city":"Eden Prairie",
    "sg:classifiers":[
        {
            "category":"Manufacturing",
            "subcategory":"Electronics",
            "type":"Manufacturing & Wholesale Goods"
        }
    ],
    "sg:phone":"+1 952 829 0374",
    "sg:postcode":"55347",
    "sg:province":"MN",
    "sg:tags":[
        "electronic",
        "component",
        "mfg"
    ],
    "wof:name":"Rainbow Bridge Enterprise",
    "wof:placetype":"venue"
},
  "geometry": {"coordinates":[-93.400379,44.827385],"type":"Point"}
}