{
  "type": "Feature",
  "properties": {
    "iso:country":"US",
    "sg:address":"1928 Co Rd 3",
    "sg:city":"Carlton",
    "sg:classifiers":[
        {
            "category":"Freight",
            "type":"Transportation"
        }
    ],
    "sg:phone":"+1 218 384 9358",
    "sg:postcode":"55718",
    "sg:province":"MN",
    "sg:tags":[
        "operator",
        "local",
        "trucking"
    ],
    "wof:name":"Thompson Koop Trucking",
    "wof:placetype":"venue"
},
  "geometry": {"coordinates":[-92.42791,46.63324],"type":"Point"}
}