{
  "type": "Feature",
  "properties": {
    "iso:country":"US",
    "sg:address":"205 S 1st St",
    "sg:city":"Montevideo",
    "sg:classifiers":[
        {
            "category":"Utilities",
            "subcategory":"Natural Gas",
            "type":"Services"
        }
    ],
    "sg:phone":"+1 320 269 5529",
    "sg:postcode":"56265",
    "sg:province":"MN",
    "sg:tags":[
        "company"
    ],
    "sg:website":"www.gpng.com",
    "wof:name":"Great Plains Natural Gas Co",
    "wof:placetype":"venue"
},
  "geometry": {"coordinates":[-95.72406599999999,44.944406],"type":"Point"}
}