{
  "type": "Feature",
  "properties": {
    "addr:full":"9909 S Shore Dr # 1G Minneapolis MN 55441",
    "addr:housenumber":"9909",
    "addr:postcode":"55441",
    "addr:street":"S Shore Dr # 1G",
    "iso:country":"US",
    "sg:address":"9909 S Shore Dr # 1G",
    "sg:city":"Minneapolis",
    "sg:classifiers":[
        {
            "category":"Home & Garden",
            "subcategory":"Carpets & Floor Coverings",
            "type":"Retail Goods"
        }
    ],
    "sg:phone":"+1 763 231 3127",
    "sg:postcode":"55441",
    "sg:province":"MN",
    "sg:tags":[
        "material",
        "installation",
        "rug"
    ],
    "wof:name":"Carpet The World",
    "wof:placetype":"venue"
},
  "geometry": {"coordinates":[-93.406183,44.995935],"type":"Point"}
}