{
  "type": "Feature",
  "properties": {
    "addr:full":"415 Main Ave N Harmony MN 55939",
    "addr:housenumber":"415",
    "addr:postcode":"55939",
    "addr:street":"Main Ave N",
    "iso:country":"US",
    "sg:address":"415 Main Ave N",
    "sg:city":"Harmony",
    "sg:classifiers":[
        {
            "category":"Food & Beverages",
            "subcategory":"Groceries & Convenience Stores",
            "type":"Retail Goods"
        }
    ],
    "sg:phone":"+1 507 886 2424",
    "sg:postcode":"55939",
    "sg:province":"MN",
    "wof:name":"KWIK Trip",
    "wof:placetype":"venue"
},
  "geometry": {"coordinates":[-92.01002200000001,43.558881],"type":"Point"}
}