{
  "type": "Feature",
  "properties": {
    "iso:country":"US",
    "sg:address":"906 10th Ave S",
    "sg:city":"St James",
    "sg:classifiers":[
        {
            "category":"Retail",
            "subcategory":"Funeral Services",
            "type":"Services"
        }
    ],
    "sg:phone":"+1 507 375 7342",
    "sg:postcode":"56081",
    "sg:province":"MN",
    "sg:tags":[
        "plan"
    ],
    "wof:name":"Sturm Funeral Home",
    "wof:placetype":"venue"
},
  "geometry": {"coordinates":[-94.62200900000001,43.975157],"type":"Point"}
}