{
  "type": "Feature",
  "properties": {
    "addr:full":"2480 Periwinkle Ave N Stillwater MN 55082",
    "addr:housenumber":"2480",
    "addr:postcode":"55082",
    "addr:street":"Periwinkle Ave N",
    "iso:country":"US",
    "sg:address":"2480 Periwinkle Ave N",
    "sg:city":"Stillwater",
    "sg:classifiers":[
        {
            "category":"Building & Trades",
            "subcategory":"Construction",
            "type":"Services"
        }
    ],
    "sg:phone":"+1 651 436 7265",
    "sg:postcode":"55082",
    "sg:province":"MN",
    "sg:tags":[
        "contractor"
    ],
    "wof:name":"CNA Glass Inc",
    "wof:placetype":"venue"
},
  "geometry": {"coordinates":[-92.788741,44.98057],"type":"Point"}
}