{
  "type": "Feature",
  "properties": {
    "addr:full":"1014 9th Ave Mountain Lake MN 56159",
    "addr:housenumber":"1014",
    "addr:postcode":"56159",
    "addr:street":"9Th Ave",
    "iso:country":"US",
    "sg:address":"1014 9th Ave",
    "sg:city":"Mountain Lake",
    "sg:classifiers":[
        {
            "category":"Social Services",
            "subcategory":"Child Care",
            "type":"Services"
        }
    ],
    "sg:phone":"+1 507 427 2063",
    "sg:postcode":"56159",
    "sg:province":"MN",
    "sg:tags":[
        "daycare",
        "provider"
    ],
    "wof:name":"Rodney Fast",
    "wof:placetype":"venue"
},
  "geometry": {"coordinates":[-94.929408,43.946256],"type":"Point"}
}