{
  "type": "Feature",
  "properties": {
    "addr:full":"8718 18th Ave NW Rochester MN 55901",
    "addr:housenumber":"8718",
    "addr:postcode":"55901",
    "addr:street":"18Th Ave Nw",
    "iso:country":"US",
    "sg:address":"8718 18th Ave NW",
    "sg:city":"Rochester",
    "sg:phone":"+1 507 288 1715",
    "sg:postcode":"55901",
    "sg:province":"MN",
    "sg:tags":[
        "farm",
        "field",
        "crop"
    ],
    "wof:name":"Koenigs John",
    "wof:placetype":"venue"
},
  "geometry": {"coordinates":[-92.488488,44.126652],"type":"Point"}
}