{
  "type": "Feature",
  "properties": {
    "iso:country":"US",
    "sg:address":"5841 Cedar Lake Rd S",
    "sg:city":"Minneapolis",
    "sg:classifiers":[
        {
            "category":"Professional",
            "subcategory":"Secretarial Services",
            "type":"Services"
        }
    ],
    "sg:phone":"+1 952 935 8099",
    "sg:postcode":"55416",
    "sg:province":"MN",
    "sg:tags":[
        "reporting"
    ],
    "wof:name":"Kee Secretarial Solutions Inc",
    "wof:placetype":"venue"
},
  "geometry": {"coordinates":[-93.35534699999999,44.965602],"type":"Point"}
}