{
  "type": "Feature",
  "properties": {
    "addr:full":"104 Center St Mankato MN 56001",
    "addr:housenumber":"104",
    "addr:postcode":"56001",
    "addr:street":"Center St",
    "iso:country":"US",
    "sg:address":"104 Center St",
    "sg:city":"Mankato",
    "sg:classifiers":[
        {
            "category":"Farming",
            "subcategory":"Farm & Veterinary Services",
            "type":"Manufacturing & Wholesale Goods"
        }
    ],
    "sg:phone":"+1 507 625 1363",
    "sg:postcode":"56001",
    "sg:province":"MN",
    "sg:tags":[
        "management"
    ],
    "wof:name":"Agricultural Resource Mgmt Co",
    "wof:placetype":"venue"
},
  "geometry": {"coordinates":[-94.00684,44.159112],"type":"Point"}
}