{
  "type": "Feature",
  "properties": {
    "addr:full":"223 Main St N Austin MN 55912",
    "addr:housenumber":"223",
    "addr:postcode":"55912",
    "addr:street":"Main St",
    "iso:country":"US",
    "sg:address":"223 Main St N",
    "sg:city":"Austin",
    "sg:classifiers":[
        {
            "category":"Banks & Credit Unions",
            "subcategory":"Bank",
            "type":"Services"
        }
    ],
    "sg:phone":"+1 507 437 6360",
    "sg:postcode":"55912",
    "sg:province":"MN",
    "wof:name":"Mower County Employees Credit",
    "wof:placetype":"venue"
},
  "geometry": {"coordinates":[-92.974912,43.668136],"type":"Point"}
}