{
  "type": "Feature",
  "properties": {
    "addr:full":"1660 11th Ave Granite Falls MN 56241",
    "addr:housenumber":"1660",
    "addr:postcode":"56241",
    "addr:street":"11Th Ave",
    "iso:country":"US",
    "sg:address":"1660 11th Ave",
    "sg:city":"Granite Falls",
    "sg:phone":"+1 320 564 4822",
    "sg:postcode":"56241",
    "sg:province":"MN",
    "sg:tags":[
        "farm",
        "corn"
    ],
    "wof:name":"Donald Hendrickson",
    "wof:placetype":"venue"
},
  "geometry": {"coordinates":[-95.562303,44.808151],"type":"Point"}
}