{
  "type": "Feature",
  "properties": {
    "iso:country":"US",
    "sg:address":"8089 Lost Lake Rd",
    "sg:city":"Nisswa",
    "sg:classifiers":[
        {
            "category":"Autos & Motor Vehicles",
            "subcategory":"Boat Sales",
            "type":"Retail Goods"
        }
    ],
    "sg:phone":"+1 218 963 1010",
    "sg:postcode":"56468",
    "sg:province":"MN",
    "wof:name":"Port of Gull Rentals",
    "wof:placetype":"venue"
},
  "geometry": {"coordinates":[-94.340582,46.512747],"type":"Point"}
}