{
  "type": "Feature",
  "properties": {
    "addr:full":"15 1st Ave SE Dodge Center MN 55927",
    "addr:housenumber":"15",
    "addr:postcode":"55927",
    "addr:street":"1St Ave Se",
    "iso:country":"US",
    "sg:address":"15 1st Ave SE",
    "sg:city":"Dodge Center",
    "sg:classifiers":[
        {
            "category":"Professional",
            "type":"Services"
        }
    ],
    "sg:phone":"+1 507 374 9383",
    "sg:postcode":"55927",
    "sg:province":"MN",
    "sg:tags":[
        "establishment"
    ],
    "wof:name":"Hickory Tech Corp",
    "wof:placetype":"venue"
},
  "geometry": {"coordinates":[-92.85317000000001,44.027144],"type":"Point"}
}