{
  "type": "Feature",
  "properties": {
    "iso:country":"US",
    "sg:address":"431 Lark Ave",
    "sg:city":"Maplewood",
    "sg:classifiers":[
        {
            "category":"Wholesale",
            "subcategory":"Hardware",
            "type":"Manufacturing & Wholesale Goods"
        }
    ],
    "sg:phone":"+1 651 772 8585",
    "sg:postcode":"55117",
    "sg:province":"MN",
    "wof:name":"Railock Inc",
    "wof:placetype":"venue"
},
  "geometry": {"coordinates":[-93.083923,45.009139],"type":"Point"}
}