{
  "type": "Feature",
  "properties": {
    "addr:full":"2897 14th Ter NW Saint Paul MN 55112",
    "addr:housenumber":"2897",
    "addr:postcode":"55112",
    "addr:street":"14Th Ter Nw",
    "iso:country":"US",
    "sg:address":"2897 14th Ter NW",
    "sg:city":"Saint Paul",
    "sg:classifiers":[
        {
            "category":"Social Services",
            "subcategory":"Child Care",
            "type":"Services"
        }
    ],
    "sg:phone":"+1 651 631 1725",
    "sg:postcode":"55112",
    "sg:province":"MN",
    "sg:tags":[
        "day"
    ],
    "wof:name":"Little People Plus Daycare",
    "wof:placetype":"venue"
},
  "geometry": {"coordinates":[-93.223043,45.072369],"type":"Point"}
}