{
  "type": "Feature",
  "properties": {
    "addr:full":"1178 Delaware Ave Saint Paul MN 55118",
    "addr:housenumber":"1178",
    "addr:postcode":"55118",
    "addr:street":"Delaware Ave",
    "iso:country":"US",
    "sg:address":"1178 Delaware Ave",
    "sg:city":"Saint Paul",
    "sg:classifiers":[
        {
            "category":"Shopping",
            "subcategory":"Used Merchandise",
            "type":"Retail Goods"
        }
    ],
    "sg:phone":"+1 651 455 5206",
    "sg:postcode":"55118",
    "sg:province":"MN",
    "wof:name":"Delaware Antiques",
    "wof:placetype":"venue"
},
  "geometry": {"coordinates":[-93.10581500000001,44.911746],"type":"Point"}
}