{
  "type": "Feature",
  "properties": {
    "addr:full":"29846 Co Rd 157 Freeport MN 56331",
    "addr:housenumber":"29846",
    "addr:postcode":"56331",
    "addr:street":"Co Rd 157",
    "iso:country":"US",
    "sg:address":"29846 Co Rd 157",
    "sg:city":"Freeport",
    "sg:classifiers":[
        {
            "category":"Farming",
            "subcategory":"Dairy Farm",
            "type":"Manufacturing & Wholesale Goods"
        }
    ],
    "sg:phone":"+1 320 836 2742",
    "sg:postcode":"56331",
    "sg:province":"MN",
    "wof:name":"Steve Herdering",
    "wof:placetype":"venue"
},
  "geometry": {"coordinates":[-94.734768,45.669972],"type":"Point"}
}