{
  "type": "Feature",
  "properties": {
    "addr:full":"16045 Nightingale St NW Anoka MN 55304",
    "addr:housenumber":"16045",
    "addr:postcode":"55304",
    "addr:street":"Nightingale St Nw",
    "iso:country":"US",
    "sg:address":"16045 Nightingale St NW",
    "sg:city":"Anoka",
    "sg:classifiers":[
        {
            "category":"Organizations",
            "subcategory":"Religious Organization",
            "type":"Services"
        }
    ],
    "sg:phone":"+1 763 755 2537",
    "sg:postcode":"55304",
    "sg:province":"MN",
    "wof:name":"Coon Rapids Christian Church",
    "wof:placetype":"venue"
},
  "geometry": {"coordinates":[-93.315962,45.262508],"type":"Point"}
}