{
  "type": "Feature",
  "properties": {
    "iso:country":"US",
    "sg:address":"1800 Coon Rapids Blvd NW",
    "sg:city":"Minneapolis",
    "sg:classifiers":[
        {
            "category":"Social Services",
            "subcategory":"Child Care",
            "type":"Services"
        },
        {
            "category":"Education",
            "subcategory":"Preschool",
            "type":"Public Place"
        },
        {
            "category":"Education",
            "subcategory":"School",
            "type":"Public Place"
        }
    ],
    "sg:phone":"+1 763 755 0010",
    "sg:postcode":"55433",
    "sg:province":"MN",
    "sg:tags":[
        "elementary",
        "day"
    ],
    "wof:name":"Kindercare Learning Centers",
    "wof:placetype":"venue"
},
  "geometry": {"coordinates":[-93.313599,45.158699],"type":"Point"}
}