{
  "type": "Feature",
  "properties": {
    "iso:country":"US",
    "sg:address":"2001 Flag Ave S",
    "sg:city":"Minneapolis",
    "sg:classifiers":[
        {
            "category":"Restaurant",
            "type":"Food & Drink"
        },
        {
            "category":"Sports & Exercise",
            "subcategory":"Golf",
            "type":"Entertainment"
        }
    ],
    "sg:phone":"+1 952 544 4471",
    "sg:postcode":"55426",
    "sg:province":"MN",
    "sg:tags":[
        "course",
        "courses-private",
        "instruction"
    ],
    "sg:website":"http://www.minneapolisgolfclub.com",
    "wof:name":"Minneapolis Golf Club",
    "wof:placetype":"venue"
},
  "geometry": {"coordinates":[-93.39624000000001,44.964218],"type":"Point"}
}