{
  "type": "Feature",
  "properties": {
    "addr:full":"5701 Kentucky Ave N Minneapolis MN 55428",
    "addr:housenumber":"5701",
    "addr:postcode":"55428",
    "addr:street":"Kentucky Ave N",
    "iso:country":"US",
    "sg:address":"5701 Kentucky Ave N",
    "sg:city":"Minneapolis",
    "sg:classifiers":[
        {
            "category":"Professional",
            "type":"Services"
        }
    ],
    "sg:phone":"+1 763 504 9166",
    "sg:postcode":"55428",
    "sg:province":"MN",
    "wof:name":"Dynamic Ldrshp Serv Inc",
    "wof:placetype":"venue"
},
  "geometry": {"coordinates":[-93.369072,45.058215],"type":"Point"}
}