{
  "type": "Feature",
  "properties": {
    "iso:country":"US",
    "sg:address":"24926 Groningen Rd",
    "sg:city":"Sandstone",
    "sg:classifiers":[
        {
            "category":"Wholesale",
            "subcategory":"Groceries",
            "type":"Manufacturing & Wholesale Goods"
        },
        {
            "category":"Wholesale",
            "subcategory":"Beer",
            "type":"Manufacturing & Wholesale Goods"
        }
    ],
    "sg:phone":"+1 320 245 5364",
    "sg:postcode":"55072",
    "sg:province":"MN",
    "sg:tags":[
        "carbonated",
        "beverage"
    ],
    "wof:name":"Sandstone Distributing Co",
    "wof:placetype":"venue"
},
  "geometry": {"coordinates":[-92.89716,46.14404],"type":"Point"}
}