{
  "type": "Feature",
  "properties": {
    "iso:country":"US",
    "sg:address":"1624 Quail Ridge Cir",
    "sg:city":"Saint Paul",
    "sg:classifiers":[
        {
            "category":"Real Estate",
            "subcategory":"Developer",
            "type":"Services"
        }
    ],
    "sg:phone":"+1 651 261 2488",
    "sg:postcode":"55125",
    "sg:province":"MN",
    "wof:name":"CIT Partnership",
    "wof:placetype":"venue"
},
  "geometry": {"coordinates":[-92.925999,44.925222],"type":"Point"}
}