{
  "type": "Feature",
  "properties": {
    "iso:country":"US",
    "sg:address":"4215 Bloomington Ave",
    "sg:city":"Minneapolis",
    "sg:classifiers":[
        {
            "category":"Restaurant",
            "type":"Food & Drink"
        }
    ],
    "sg:phone":"+1 612 722 6274",
    "sg:postcode":"55407",
    "sg:province":"MN",
    "sg:tags":[
        "chinese"
    ],
    "wof:name":"Mei Inn Chinese Foods",
    "wof:placetype":"venue"
},
  "geometry": {"coordinates":[-93.252197,44.926201],"type":"Point"}
}