{
  "type": "Feature",
  "properties": {
    "iso:country":"US",
    "sg:address":"609 Oak St",
    "sg:city":"Brainerd",
    "sg:classifiers":[
        {
            "category":"Health Services",
            "subcategory":"Nursing And Care Facility",
            "type":"Services"
        },
        {
            "category":"Health Services",
            "subcategory":"Health Practitioner",
            "type":"Services"
        },
        {
            "category":"Social Services",
            "subcategory":"Adult Care",
            "type":"Services"
        },
        {
            "category":"Health Services",
            "subcategory":"Hospice",
            "type":"Services"
        }
    ],
    "sg:phone":"+1 218 829 1252",
    "sg:postcode":"56401",
    "sg:province":"MN",
    "sg:tags":[
        "nurses-home",
        "nurse",
        "therapist",
        "physical",
        "home"
    ],
    "sg:website":"http://www.heartlandhospice.com/StCloud",
    "wof:name":"Heartland Hospice Services",
    "wof:placetype":"venue"
},
  "geometry": {"coordinates":[-94.200569,46.352669],"type":"Point"}
}