{
  "type": "Feature",
  "properties": {
    "addr:full":"1610 Cliff Rd E Bldg 5 Burnsville MN 55337",
    "addr:housenumber":"1610",
    "addr:postcode":"55337",
    "addr:street":"Cliff Rd E Bldg 5",
    "iso:country":"US",
    "sg:address":"1610 Cliff Rd E Bldg 5",
    "sg:city":"Burnsville",
    "sg:classifiers":[
        {
            "category":"Professional",
            "subcategory":"Advertising",
            "type":"Services"
        },
        {
            "category":"Retail",
            "subcategory":"Repair Shop",
            "type":"Services"
        },
        {
            "category":"Manufacturing",
            "subcategory":"Signs",
            "type":"Manufacturing & Wholesale Goods"
        }
    ],
    "sg:phone":"+1 952 894 2421",
    "sg:postcode":"55337",
    "sg:province":"MN",
    "sg:tags":[
        "signs-erectors",
        "hanger",
        "specialty",
        "signs-maintenance"
    ],
    "sg:website":"http://www.schadtracy.com",
    "wof:name":"Schad-Tracy Signs Inc",
    "wof:placetype":"venue"
},
  "geometry": {"coordinates":[-93.25012599999999,44.790471],"type":"Point"}
}