{
  "type": "Feature",
  "properties": {
    "iso:country":"US",
    "sg:address":"2855 Campus Dr",
    "sg:city":"Minneapolis",
    "sg:classifiers":[
        {
            "category":"Health Services",
            "subcategory":"Doctor",
            "type":"Services"
        }
    ],
    "sg:phone":"+1 763 383 8870",
    "sg:postcode":"55441",
    "sg:province":"MN",
    "sg:tags":[
        "physician",
        "surgeon"
    ],
    "wof:name":"Wong Hoo Yin MD FACS Frcsc",
    "wof:placetype":"venue"
},
  "geometry": {"coordinates":[-93.451995,45.011017],"type":"Point"}
}