{
  "type": "Feature",
  "properties": {
    "iso:country":"US",
    "sg:address":"312 Central Ave SE",
    "sg:city":"Minneapolis",
    "sg:classifiers":[
        {
            "category":"Organizations",
            "subcategory":"Labor Organization",
            "type":"Services"
        }
    ],
    "sg:phone":"+1 612 379 1292",
    "sg:postcode":"55414",
    "sg:province":"MN",
    "sg:website":"www.ibew292.org",
    "wof:name":"IBEW",
    "wof:placetype":"venue"
},
  "geometry": {"coordinates":[-93.25413,44.987705],"type":"Point"}
}