{
  "type": "Feature",
  "properties": {
    "iso:country":"US",
    "sg:address":"24139 Greenway Rd",
    "sg:city":"Forest Lake",
    "sg:classifiers":[
        {
            "category":"Professional",
            "subcategory":"Business Services",
            "type":"Services"
        },
        {
            "category":"Home & Garden",
            "subcategory":"Furniture",
            "type":"Retail Goods"
        }
    ],
    "sg:phone":"+1 651 982 0944",
    "sg:postcode":"55025",
    "sg:province":"MN",
    "wof:name":"Interiors For Your HOMe&",
    "wof:placetype":"venue"
},
  "geometry": {"coordinates":[-92.973879,45.298766],"type":"Point"}
}