{
  "type": "Feature",
  "properties": {
    "iso:country":"US",
    "sg:address":"6055 80th St NE",
    "sg:city":"Murdock",
    "sg:classifiers":[
        {
            "category":"Farming",
            "subcategory":"Livestock Farm",
            "type":"Manufacturing & Wholesale Goods"
        }
    ],
    "sg:phone":"+1 320 875 2036",
    "sg:postcode":"56271",
    "sg:province":"MN",
    "sg:tags":[
        "feedlot",
        "corn",
        "soybean",
        "beef",
        "cattle"
    ],
    "wof:name":"Dan Benson",
    "wof:placetype":"venue"
},
  "geometry": {"coordinates":[-95.461215,45.137634],"type":"Point"}
}