{
  "type": "Feature",
  "properties": {
    "addr:full":"101 Forest Oaks Ct Winona MN 55987",
    "addr:housenumber":"101",
    "addr:postcode":"55987",
    "addr:street":"Forest Oaks Ct",
    "iso:country":"US",
    "sg:address":"101 Forest Oaks Ct",
    "sg:city":"Winona",
    "sg:classifiers":[
        {
            "category":"Professional",
            "subcategory":"Business Services",
            "type":"Services"
        }
    ],
    "sg:phone":"+1 507 453 9231",
    "sg:postcode":"55987",
    "sg:province":"MN",
    "sg:tags":[
        "interior",
        "consultant",
        "design",
        "decorator"
    ],
    "wof:name":"Other Arrangements",
    "wof:placetype":"venue"
},
  "geometry": {"coordinates":[-91.631894,44.012402],"type":"Point"}
}