{
  "type": "Feature",
  "properties": {
    "iso:country":"US",
    "sg:address":"22820 170th Ave NW",
    "sg:city":"Crookston",
    "sg:phone":"+1 218 281 5898",
    "sg:postcode":"56760",
    "sg:province":"MN",
    "sg:tags":[
        "farm",
        "grain",
        "cash"
    ],
    "wof:name":"Paul M Hanson",
    "wof:placetype":"venue"
},
  "geometry": {"coordinates":[-96.41282200000001,48.203868],"type":"Point"}
}