{
  "type": "Feature",
  "properties": {
    "iso:country":"US",
    "sg:address":"16750 Baywood Ter",
    "sg:city":"Eden Prairie",
    "sg:classifiers":[
        {
            "category":"Professional",
            "subcategory":"Computer Services",
            "type":"Services"
        }
    ],
    "sg:phone":"+1 952 934 1016",
    "sg:postcode":"55346",
    "sg:province":"MN",
    "sg:tags":[
        "prepackaged",
        "software",
        "custom"
    ],
    "sg:website":"www.lindquistsystems.com",
    "wof:name":"Lindquist Systems Inc",
    "wof:placetype":"venue"
},
  "geometry": {"coordinates":[-93.48850299999999,44.879473],"type":"Point"}
}