{
  "type": "Feature",
  "properties": {
    "addr:full":"2700 E Lake St Minneapolis MN 55406",
    "addr:housenumber":"2700",
    "addr:postcode":"55406",
    "addr:street":"E Lake St",
    "iso:country":"US",
    "sg:address":"2700 E Lake St",
    "sg:city":"Minneapolis",
    "sg:classifiers":[
        {
            "category":"Restaurant",
            "type":"Food & Drink"
        }
    ],
    "sg:phone":"+1 612 728 0975",
    "sg:postcode":"55406",
    "sg:province":"MN",
    "sg:tags":[
        "breakfast",
        "brunch",
        "diner"
    ],
    "sg:website":"www.dennys.com",
    "wof:name":"Denny's",
    "wof:placetype":"venue"
},
  "geometry": {"coordinates":[-93.2332,44.948399],"type":"Point"}
}