{
  "type": "Feature",
  "properties": {
    "addr:full":"4861 Irving Ave S Minneapolis MN 55419",
    "addr:housenumber":"4861",
    "addr:postcode":"55419",
    "addr:street":"Irving Ave S",
    "iso:country":"US",
    "sg:address":"4861 Irving Ave S",
    "sg:city":"Minneapolis",
    "sg:classifiers":[
        {
            "category":"Professional",
            "subcategory":"Lawyer & Legal Services",
            "type":"Services"
        }
    ],
    "sg:phone":"+1 612 342 0035",
    "sg:postcode":"55419",
    "sg:province":"MN",
    "wof:name":"General Council Ltd",
    "wof:placetype":"venue"
},
  "geometry": {"coordinates":[-93.299678,44.915377],"type":"Point"}
}