{
  "type": "Feature",
  "properties": {
    "iso:country":"US",
    "sg:address":"4479 Foothill Trl",
    "sg:city":"Saint Paul",
    "sg:classifiers":[
        {
            "category":"Communications",
            "subcategory":"Film & Video Production",
            "type":"Services"
        }
    ],
    "sg:phone":"+1 651 484 3016",
    "sg:postcode":"55127",
    "sg:province":"MN",
    "sg:tags":[
        "motion",
        "picture"
    ],
    "wof:name":"Visual Reality Inc",
    "wof:placetype":"venue"
},
  "geometry": {"coordinates":[-93.090052,45.076111],"type":"Point"}
}