{
  "type": "Feature",
  "properties": {
    "addr:full":"1635 Oxford St Worthington MN 56187",
    "addr:housenumber":"1635",
    "addr:postcode":"56187",
    "addr:street":"Oxford St",
    "iso:country":"US",
    "sg:address":"1635 Oxford St",
    "sg:city":"Worthington",
    "sg:classifiers":[
        {
            "category":"Shopping",
            "subcategory":"Shoes",
            "type":"Retail Goods"
        }
    ],
    "sg:phone":"+1 507 376 4575",
    "sg:postcode":"56187",
    "sg:province":"MN",
    "wof:name":"Payless Shoesource 3528",
    "wof:placetype":"venue"
},
  "geometry": {"coordinates":[-95.587722,43.631191],"type":"Point"}
}