{
  "type": "Feature",
  "properties": {
    "addr:full":"509 7th St E Thief River Falls MN 56701",
    "addr:housenumber":"509",
    "addr:postcode":"56701",
    "addr:street":"7Th St",
    "iso:country":"US",
    "sg:address":"509 7th St E",
    "sg:city":"Thief River Falls",
    "sg:classifiers":[
        {
            "category":"Restaurant",
            "type":"Food & Drink"
        }
    ],
    "sg:phone":"+1 218 681 4680",
    "sg:postcode":"56701",
    "sg:province":"MN",
    "sg:tags":[
        "eating"
    ],
    "wof:name":"Rose Catering",
    "wof:placetype":"venue"
},
  "geometry": {"coordinates":[-96.175281,48.123325],"type":"Point"}
}