{
  "type": "Feature",
  "properties": {
    "addr:full":"329 W Broadway Plainview MN 55964",
    "addr:housenumber":"329",
    "addr:postcode":"55964",
    "addr:street":"W Broadway",
    "iso:country":"US",
    "sg:address":"329 W Broadway",
    "sg:city":"Plainview",
    "sg:classifiers":[
        {
            "category":"Retail",
            "subcategory":"Laundry & Dry Cleaning",
            "type":"Services"
        }
    ],
    "sg:phone":"+1 507 534 4328",
    "sg:postcode":"55964",
    "sg:province":"MN",
    "sg:tags":[
        "power"
    ],
    "wof:name":"Wash Tub",
    "wof:placetype":"venue"
},
  "geometry": {"coordinates":[-92.171025,44.164863],"type":"Point"}
}