{
  "type": "Feature",
  "properties": {
    "addr:full":"1907 14th St NE Austin MN 55912",
    "addr:housenumber":"1907",
    "addr:postcode":"55912",
    "addr:street":"14Th St Ne",
    "iso:country":"US",
    "sg:address":"1907 14th St NE",
    "sg:city":"Austin",
    "sg:classifiers":[
        {
            "category":"Structure",
            "subcategory":"Warehouse",
            "type":"Public Place"
        },
        {
            "category":"Retail",
            "subcategory":"Storage",
            "type":"Services"
        }
    ],
    "sg:phone":"+1 507 437 1982",
    "sg:postcode":"55912",
    "sg:province":"MN",
    "sg:tags":[
        "cold",
        "warehouses-merchandise",
        "self"
    ],
    "sg:website":"http://www.mfwc-cold.com",
    "wof:name":"Austin Freezer",
    "wof:placetype":"venue"
},
  "geometry": {"coordinates":[-92.954932,43.684746],"type":"Point"}
}