{
  "type": "Feature",
  "properties": {
    "iso:country":"US",
    "sg:address":"4760 W Branch Rd",
    "sg:city":"Mound",
    "sg:classifiers":[
        {
            "category":"Professional",
            "type":"Services"
        }
    ],
    "sg:phone":"+1 952 472 8338",
    "sg:postcode":"55364",
    "sg:province":"MN",
    "sg:tags":[
        "establishment"
    ],
    "sg:website":"www.lambtonquay.com",
    "wof:name":"Lambton Quay Inc",
    "wof:placetype":"venue"
},
  "geometry": {"coordinates":[-93.645158,44.964145],"type":"Point"}
}