{
  "type": "Feature",
  "properties": {
    "addr:full":"17129 235th Ct Hutchinson MN 55350",
    "addr:housenumber":"17129",
    "addr:postcode":"55350",
    "addr:street":"235Th Ct",
    "iso:country":"US",
    "sg:address":"17129 235th Ct",
    "sg:city":"Hutchinson",
    "sg:classifiers":[
        {
            "category":"Professional",
            "subcategory":"Business Services",
            "type":"Services"
        }
    ],
    "sg:phone":"+1 320 587 9283",
    "sg:postcode":"55350",
    "sg:province":"MN",
    "sg:tags":[
        "hanging",
        "contractor"
    ],
    "wof:name":"Rahn Painting & Decorating",
    "wof:placetype":"venue"
},
  "geometry": {"coordinates":[-94.33684599999999,44.957331],"type":"Point"}
}