{
  "type": "Feature",
  "properties": {
    "iso:country":"US",
    "sg:address":"1583 Highway 1",
    "sg:city":"Ely",
    "sg:classifiers":[
        {
            "category":"Airline",
            "type":"Transportation"
        }
    ],
    "sg:phone":"+1 800 433 7300",
    "sg:postcode":"55731",
    "sg:province":"MN",
    "sg:website":"http://duluth.citysearch.com/profile/external/603441632/ely_mn/american_airlines.html?publisher=yellowpages&reference_id=1&placement=ypwebsitemip",
    "wof:name":"American Airlines",
    "wof:placetype":"venue"
},
  "geometry": {"coordinates":[-91.81854,47.83232],"type":"Point"}
}