{
  "type": "Feature",
  "properties": {
    "addr:full":"4908 40th St SW Rochester MN 55902",
    "addr:housenumber":"4908",
    "addr:postcode":"55902",
    "addr:street":"40Th St Sw",
    "iso:country":"US",
    "sg:address":"4908 40th St SW",
    "sg:city":"Rochester",
    "sg:classifiers":[
        {
            "category":"Retail",
            "subcategory":"Repair Shop",
            "type":"Services"
        }
    ],
    "sg:phone":"+1 507 282 2879",
    "sg:postcode":"55902",
    "sg:province":"MN",
    "sg:tags":[
        "welding"
    ],
    "wof:name":"Greening Welding",
    "wof:placetype":"venue"
},
  "geometry": {"coordinates":[-92.536524,43.963945],"type":"Point"}
}