{
  "type": "Feature",
  "properties": {
    "addr:full":"501 Broadway Ave Detroit Lakes MN 56501",
    "addr:housenumber":"501",
    "addr:postcode":"56501",
    "addr:street":"Broadway Ave",
    "iso:country":"US",
    "sg:address":"501 Broadway Ave",
    "sg:city":"Detroit Lakes",
    "sg:classifiers":[
        {
            "category":"Retail",
            "subcategory":"Repair Shop",
            "type":"Services"
        }
    ],
    "sg:phone":"+1 218 847 1840",
    "sg:postcode":"56501",
    "sg:province":"MN",
    "sg:tags":[
        "welding"
    ],
    "wof:name":"Johnson Welding & Repair Inc",
    "wof:placetype":"venue"
},
  "geometry": {"coordinates":[-95.834825,46.83237],"type":"Point"}
}