{
  "type": "Feature",
  "properties": {
    "iso:country":"US",
    "sg:address":"262 Sundance Rd",
    "sg:city":"Sartell",
    "sg:classifiers":[
        {
            "category":"Shopping",
            "subcategory":"Computers & Home Electronics",
            "type":"Retail Goods"
        }
    ],
    "sg:phone":"+1 320 203 7215",
    "sg:postcode":"56377",
    "sg:province":"MN",
    "sg:tags":[
        "system"
    ],
    "wof:name":"Audio Video Innovations",
    "wof:placetype":"venue"
},
  "geometry": {"coordinates":[-94.22416,45.61399],"type":"Point"}
}