{
  "type": "Feature",
  "properties": {
    "iso:country":"US",
    "sg:address":"300 SE 4th St",
    "sg:city":"Grand Rapids",
    "sg:classifiers":[
        {
            "category":"Education",
            "subcategory":"School",
            "type":"Public Place"
        }
    ],
    "sg:phone":"+1 218 327 5850",
    "sg:postcode":"55744",
    "sg:province":"MN",
    "wof:name":"Riverview Elementary",
    "wof:placetype":"venue"
},
  "geometry": {"coordinates":[-93.52331,47.227859],"type":"Point"}
}