{
  "type": "Feature",
  "properties": {
    "addr:full":"807 1st St E Park Rapids MN 56470",
    "addr:housenumber":"807",
    "addr:postcode":"56470",
    "addr:street":"1St St E",
    "iso:country":"US",
    "sg:address":"807 1st St E",
    "sg:city":"Park Rapids",
    "sg:classifiers":[
        {
            "category":"Retail",
            "subcategory":"Auto Repair",
            "type":"Services"
        }
    ],
    "sg:phone":"+1 218 732 4274",
    "sg:postcode":"56470",
    "sg:province":"MN",
    "sg:tags":[
        "repairing",
        "automobile"
    ],
    "wof:name":"Warren's Tire & Auto Repair",
    "wof:placetype":"venue"
},
  "geometry": {"coordinates":[-95.04765399999999,46.922278],"type":"Point"}
}