{
  "type": "Feature",
  "properties": {
    "addr:full":"203 E Main St Dodge Center MN 55927",
    "addr:housenumber":"203",
    "addr:postcode":"55927",
    "addr:street":"E Main St",
    "iso:country":"US",
    "sg:address":"203 E Main St",
    "sg:city":"Dodge Center",
    "sg:classifiers":[
        {
            "category":"Organizations",
            "subcategory":"Religious Organization",
            "type":"Services"
        }
    ],
    "sg:phone":"+1 507 374 6755",
    "sg:postcode":"55927",
    "sg:province":"MN",
    "sg:tags":[
        "church"
    ],
    "wof:name":"Seventh Day Baptist Church",
    "wof:placetype":"venue"
},
  "geometry": {"coordinates":[-92.852778,44.02799],"type":"Point"}
}