{
  "type": "Feature",
  "properties": {
    "addr:full":"922 53rd Ave N Minneapolis MN 55430",
    "addr:housenumber":"922",
    "addr:postcode":"55430",
    "addr:street":"53Rd Ave N",
    "iso:country":"US",
    "sg:address":"922 53rd Ave N",
    "sg:city":"Minneapolis",
    "sg:classifiers":[
        {
            "category":"Social Services",
            "subcategory":"Child Care",
            "type":"Services"
        }
    ],
    "sg:phone":"+1 763 560 3937",
    "sg:postcode":"55430",
    "sg:province":"MN",
    "sg:tags":[
        "daycare",
        "provider"
    ],
    "wof:name":"Debra Engles",
    "wof:placetype":"venue"
},
  "geometry": {"coordinates":[-93.29260499999999,45.051203],"type":"Point"}
}