{
  "type": "Feature",
  "properties": {
    "addr:full":"4217 Boone Ave N Minneapolis MN 55428",
    "addr:housenumber":"4217",
    "addr:postcode":"55428",
    "addr:street":"Boone Ave N",
    "iso:country":"US",
    "sg:address":"4217 Boone Ave N",
    "sg:city":"Minneapolis",
    "sg:classifiers":[
        {
            "category":"Organizations",
            "subcategory":"Religious Organization",
            "type":"Services"
        }
    ],
    "sg:phone":"+1 763 533 2994",
    "sg:postcode":"55428",
    "sg:province":"MN",
    "wof:name":"Mennonite Brethren Church",
    "wof:placetype":"venue"
},
  "geometry": {"coordinates":[-93.390494,45.036329],"type":"Point"}
}