{
  "type": "Feature",
  "properties": {
    "iso:country":"US",
    "sg:address":"2080 Opal Dr",
    "sg:city":"Saint Paul",
    "sg:classifiers":[
        {
            "category":"Professional",
            "subcategory":"Computer Services",
            "type":"Services"
        }
    ],
    "sg:phone":"+1 651 905 0796",
    "sg:postcode":"55122",
    "sg:province":"MN",
    "sg:tags":[
        "automation",
        "integration",
        "system"
    ],
    "wof:name":"Strategic Automation Solutions",
    "wof:placetype":"venue"
},
  "geometry": {"coordinates":[-93.21383400000001,44.807764],"type":"Point"}
}