{
  "type": "Feature",
  "properties": {
    "iso:country":"US",
    "sg:address":"2800 Aquila Ave N",
    "sg:city":"Minneapolis",
    "sg:classifiers":[
        {
            "category":"Communications",
            "subcategory":"Film & Video Production",
            "type":"Services"
        }
    ],
    "sg:phone":"+1 763 546 5766",
    "sg:postcode":"55427",
    "sg:province":"MN",
    "sg:tags":[
        "motion",
        "picture"
    ],
    "wof:name":"E & A Enterprise",
    "wof:placetype":"venue"
},
  "geometry": {"coordinates":[-93.38951900000001,45.010548],"type":"Point"}
}