{
  "type": "Feature",
  "properties": {
    "addr:full":"15936 35th Ave South Haven MN 55382",
    "addr:housenumber":"15936",
    "addr:postcode":"55382",
    "addr:street":"35Th Ave",
    "iso:country":"US",
    "sg:address":"15936 35th Ave",
    "sg:city":"South Haven",
    "sg:classifiers":[
        {
            "category":"Building & Trades",
            "subcategory":"Landscaping Services",
            "type":"Services"
        }
    ],
    "sg:phone":"+1 320 236 2480",
    "sg:postcode":"55382",
    "sg:province":"MN",
    "sg:tags":[
        "tree"
    ],
    "wof:name":"Tri-County Tree Svc",
    "wof:placetype":"venue"
},
  "geometry": {"coordinates":[-94.183896,45.353553],"type":"Point"}
}