{
  "type": "Feature",
  "properties": {
    "addr:full":"821 Marquette Ave S Minneapolis MN 55402",
    "addr:housenumber":"821",
    "addr:postcode":"55402",
    "addr:street":"Marquette Ave S",
    "iso:country":"US",
    "sg:address":"821 Marquette Ave S",
    "sg:city":"Minneapolis",
    "sg:classifiers":[
        {
            "category":"Professional",
            "subcategory":"Accounting & Tax Preparation",
            "type":"Services"
        }
    ],
    "sg:phone":"+1 612 337 8114",
    "sg:postcode":"55402",
    "sg:province":"MN",
    "wof:name":"David R Orenstein",
    "wof:placetype":"venue"
},
  "geometry": {"coordinates":[-93.272125,44.974869],"type":"Point"}
}