{
  "type": "Feature",
  "properties": {
    "addr:full":"2105 Cliff Rd Saint Paul MN 55122",
    "addr:housenumber":"2105",
    "addr:postcode":"55122",
    "addr:street":"Cliff Rd",
    "iso:country":"US",
    "sg:address":"2105 Cliff Rd",
    "sg:city":"Saint Paul",
    "sg:classifiers":[
        {
            "category":"Personal",
            "subcategory":"Nail Salon",
            "type":"Services"
        }
    ],
    "sg:phone":"+1 651 452 1981",
    "sg:postcode":"55122",
    "sg:province":"MN",
    "wof:name":"Nail Design",
    "wof:placetype":"venue"
},
  "geometry": {"coordinates":[-93.21260100000001,44.790199],"type":"Point"}
}