{
  "type": "Feature",
  "properties": {
    "addr:full":"2526 Arcola Ln Wayzata MN 55391",
    "addr:housenumber":"2526",
    "addr:postcode":"55391",
    "addr:street":"Arcola Ln",
    "iso:country":"US",
    "sg:address":"2526 Arcola Ln",
    "sg:city":"Wayzata",
    "sg:classifiers":[
        {
            "category":"Manufacturing",
            "subcategory":"Chemicals & Compounds",
            "type":"Manufacturing & Wholesale Goods"
        }
    ],
    "sg:phone":"+1 952 471 7672",
    "sg:postcode":"55391",
    "sg:province":"MN",
    "sg:tags":[
        "mfg",
        "cyclic"
    ],
    "wof:name":"Roliso Corporation",
    "wof:placetype":"venue"
},
  "geometry": {"coordinates":[-93.58367,44.940294],"type":"Point"}
}