{
  "type": "Feature",
  "properties": {
    "iso:country":"US",
    "sg:address":"22356 Sunrise Rd NE",
    "sg:city":"Stacy",
    "sg:classifiers":[
        {
            "category":"Building & Trades",
            "subcategory":"Landscaping Services",
            "type":"Services"
        }
    ],
    "sg:phone":"+1 612 221 2438",
    "sg:postcode":"55079",
    "sg:province":"MN",
    "sg:tags":[
        "landscape"
    ],
    "wof:name":"Gods Country Nursery",
    "wof:placetype":"venue"
},
  "geometry": {"coordinates":[-93.049232,45.374359],"type":"Point"}
}