{
  "type": "Feature",
  "properties": {
    "addr:full":"213 Sibley St Hastings MN 55033",
    "addr:housenumber":"213",
    "addr:postcode":"55033",
    "addr:street":"Sibley St",
    "iso:country":"US",
    "sg:address":"213 Sibley St",
    "sg:city":"Hastings",
    "sg:classifiers":[
        {
            "category":"Professional",
            "type":"Services"
        },
        {
            "category":"Sports & Exercise",
            "subcategory":"Gym",
            "type":"Entertainment"
        }
    ],
    "sg:phone":"+1 651 438 3536",
    "sg:postcode":"55033",
    "sg:province":"MN",
    "sg:tags":[
        "spa",
        "health"
    ],
    "wof:name":"Royal Treatment Mini Spas",
    "wof:placetype":"venue"
},
  "geometry": {"coordinates":[-92.851147,44.743423],"type":"Point"}
}