{
  "type": "Feature",
  "properties": {
    "addr:full":"630 W 37th St Hibbing MN 55746",
    "addr:housenumber":"630",
    "addr:postcode":"55746",
    "addr:street":"W 37Th St",
    "iso:country":"US",
    "sg:address":"630 W 37th St",
    "sg:city":"Hibbing",
    "sg:classifiers":[
        {
            "category":"Food & Beverages",
            "subcategory":"Specialty",
            "type":"Retail Goods"
        },
        {
            "category":"Food & Beverages",
            "subcategory":"Groceries & Convenience Stores",
            "type":"Retail Goods"
        }
    ],
    "sg:phone":"+1 218 262 4667",
    "sg:postcode":"55746",
    "sg:province":"MN",
    "sg:tags":[
        "grocers-specialty"
    ],
    "wof:name":"Geary's Grocery Inc",
    "wof:placetype":"venue"
},
  "geometry": {"coordinates":[-92.948609,47.407545],"type":"Point"}
}