{
  "type": "Feature",
  "properties": {
    "iso:country":"US",
    "sg:address":"4760 Merrimac Ct N",
    "sg:city":"Minneapolis",
    "sg:classifiers":[
        {
            "category":"Freight",
            "type":"Transportation"
        }
    ],
    "sg:phone":"+1 763 383 5151",
    "sg:postcode":"55446",
    "sg:province":"MN",
    "sg:tags":[
        "arrangement"
    ],
    "wof:name":"Sie World Trading Inc",
    "wof:placetype":"venue"
},
  "geometry": {"coordinates":[-93.503547,45.040525],"type":"Point"}
}