{
  "type": "Feature",
  "properties": {
    "addr:full":"10 Minneapolis Ave Duluth MN 55803",
    "addr:housenumber":"10",
    "addr:postcode":"55803",
    "addr:street":"Minneapolis Ave",
    "iso:country":"US",
    "sg:address":"10 Minneapolis Ave",
    "sg:city":"Duluth",
    "sg:classifiers":[
        {
            "category":"Professional",
            "subcategory":"Accounting & Tax Preparation",
            "type":"Services"
        }
    ],
    "sg:phone":"+1 218 724 2660",
    "sg:postcode":"55803",
    "sg:province":"MN",
    "wof:name":"ADP",
    "wof:placetype":"venue"
},
  "geometry": {"coordinates":[-92.076148,46.841031],"type":"Point"}
}