{
  "type": "Feature",
  "properties": {
    "addr:full":"1509 Coon Rapids Blvd NW Minneapolis MN 55433",
    "addr:housenumber":"1509",
    "addr:postcode":"55433",
    "addr:street":"Coon Rapids Blvd Nw",
    "iso:country":"US",
    "sg:address":"1509 Coon Rapids Blvd NW",
    "sg:city":"Minneapolis",
    "sg:classifiers":[
        {
            "category":"Manufacturing",
            "subcategory":"Printing",
            "type":"Manufacturing & Wholesale Goods"
        }
    ],
    "sg:phone":"+1 763 755 2973",
    "sg:postcode":"55433",
    "sg:province":"MN",
    "sg:tags":[
        "photocopying",
        "printer",
        "supply",
        "lithographic",
        "commercial",
        "computer"
    ],
    "sg:website":"www.pressroomprinting.com",
    "wof:name":"Pressroom Inc the",
    "wof:placetype":"venue"
},
  "geometry": {"coordinates":[-93.305702,45.1544],"type":"Point"}
}