{
  "type": "Feature",
  "properties": {
    "addr:full":"7845 Turner Rd Maple Plain MN 55359",
    "addr:housenumber":"7845",
    "addr:postcode":"55359",
    "addr:street":"Turner Rd;Plain",
    "iso:country":"US",
    "sg:address":"7845 Turner Rd",
    "sg:city":"Maple Plain",
    "sg:classifiers":[
        {
            "category":"Insurance",
            "subcategory":"Insurance Agent",
            "type":"Services"
        }
    ],
    "sg:phone":"+1 763 479 2448",
    "sg:postcode":"55359",
    "sg:province":"MN",
    "wof:name":"Harvey Medica/Fred Agent",
    "wof:placetype":"venue"
},
  "geometry": {"coordinates":[-93.722984,44.999673],"type":"Point"}
}