{
  "type": "Feature",
  "properties": {
    "addr:full":"900 N 7th St Marshall MN 56258",
    "addr:housenumber":"900",
    "addr:postcode":"56258",
    "addr:street":"N 7Th St",
    "iso:country":"US",
    "sg:address":"900 N 7th St",
    "sg:city":"Marshall",
    "sg:classifiers":[
        {
            "category":"Building & Trades",
            "subcategory":"Construction",
            "type":"Services"
        }
    ],
    "sg:phone":"+1 507 532 4511",
    "sg:postcode":"56258",
    "sg:province":"MN",
    "sg:tags":[
        "contractor"
    ],
    "wof:name":"Hisken Construction Co",
    "wof:placetype":"venue"
},
  "geometry": {"coordinates":[-95.78908,44.45992],"type":"Point"}
}