{
  "type": "Feature",
  "properties": {
    "iso:country":"US",
    "sg:address":"6005 Lamar Ave S",
    "sg:city":"Cottage Grove",
    "sg:phone":"+1 651 459 6780",
    "sg:postcode":"55016",
    "sg:province":"MN",
    "sg:tags":[
        "farm",
        "corn",
        "soybean"
    ],
    "wof:name":"Erickson Farm",
    "wof:placetype":"venue"
},
  "geometry": {"coordinates":[-92.88317000000001,44.860566],"type":"Point"}
}