{
  "type": "Feature",
  "properties": {
    "addr:full":"33 S 6th St Minneapolis MN 55402",
    "addr:housenumber":"33",
    "addr:postcode":"55402",
    "addr:street":"S 6Th St",
    "iso:country":"US",
    "sg:address":"33 S 6th St",
    "sg:city":"Minneapolis",
    "sg:classifiers":[
        {
            "category":"Utilities",
            "subcategory":"Mobile Phone",
            "type":"Services"
        },
        {
            "category":"Coffee & Tea",
            "type":"Food & Drink"
        }
    ],
    "sg:phone":"+1 612 339 7084",
    "sg:postcode":"55402",
    "sg:province":"MN",
    "sg:tags":[
        "shop",
        "wi-fi",
        "espresso",
        "hotspot",
        "restaurant"
    ],
    "sg:website":"http://www.starbuckscoffee.com",
    "wof:name":"Starbucks Coffee",
    "wof:placetype":"venue"
},
  "geometry": {"coordinates":[-93.272746,44.978384],"type":"Point"}
}