{
  "type": "Feature",
  "properties": {
    "addr:full":"3460 Washington Dr Eagan MN 55122",
    "addr:housenumber":"3460",
    "addr:postcode":"55122",
    "addr:street":"Washington Dr",
    "iso:country":"US",
    "sg:address":"3460 Washington Dr",
    "sg:city":"Eagan",
    "sg:classifiers":[
        {
            "category":"Utilities",
            "subcategory":"Mobile Phone",
            "type":"Services"
        }
    ],
    "sg:phone":"+1 651 687 9285",
    "sg:postcode":"55122",
    "sg:province":"MN",
    "sg:tags":[
        "telephone",
        "cellular"
    ],
    "sg:website":"www.uslink.com",
    "wof:name":"US Link",
    "wof:placetype":"venue"
},
  "geometry": {"coordinates":[-93.17027400000001,44.831233],"type":"Point"}
}