{
  "type": "Feature",
  "properties": {
    "addr:full":"1802 2nd Ave N Moorhead MN 56560",
    "addr:housenumber":"1802",
    "addr:postcode":"56560",
    "addr:street":"2Nd Ave N",
    "iso:country":"US",
    "sg:address":"1802 2nd Ave N",
    "sg:city":"Moorhead",
    "sg:classifiers":[
        {
            "category":"Manufacturing",
            "subcategory":"Lumber",
            "type":"Manufacturing & Wholesale Goods"
        }
    ],
    "sg:phone":"+1 218 233 5145",
    "sg:postcode":"56560",
    "sg:province":"MN",
    "sg:tags":[
        "compounds-manufacturers",
        "cleaning"
    ],
    "sg:website":"http://www.roffecontainer.com",
    "wof:name":"Roffe Container, Inc",
    "wof:placetype":"venue"
},
  "geometry": {"coordinates":[-96.751024,46.87714],"type":"Point"}
}