{
  "type": "Feature",
  "properties": {
    "iso:country":"US",
    "sg:address":"2375 Orkla Dr",
    "sg:city":"Minneapolis",
    "sg:classifiers":[
        {
            "category":"Building & Trades",
            "subcategory":"Construction",
            "type":"Services"
        }
    ],
    "sg:phone":"+1 763 542 9058",
    "sg:postcode":"55427",
    "sg:province":"MN",
    "sg:tags":[
        "repairing",
        "remodeling",
        "contractor"
    ],
    "wof:name":"Van Heel Brothers Construction",
    "wof:placetype":"venue"
},
  "geometry": {"coordinates":[-93.38394,45.00492],"type":"Point"}
}