{
  "type": "Feature",
  "properties": {
    "addr:full":"351 2nd St Excelsior MN 55331",
    "addr:housenumber":"351",
    "addr:postcode":"55331",
    "addr:street":"2Nd St",
    "iso:country":"US",
    "sg:address":"351 2nd St",
    "sg:city":"Excelsior",
    "sg:classifiers":[
        {
            "category":"Shopping",
            "subcategory":"Musical Instruments",
            "type":"Retail Goods"
        }
    ],
    "sg:phone":"+1 952 474 7002",
    "sg:postcode":"55331",
    "sg:province":"MN",
    "wof:name":"My Favorite Martin Guitars",
    "wof:placetype":"venue"
},
  "geometry": {"coordinates":[-93.566242,44.903632],"type":"Point"}
}