{
  "type": "Feature",
  "properties": {
    "iso:country":"US",
    "sg:address":"6817 Dakota Trl",
    "sg:city":"Minneapolis",
    "sg:classifiers":[
        {
            "category":"Real Estate",
            "subcategory":"Real Estate Operator",
            "type":"Services"
        }
    ],
    "sg:phone":"+1 952 941 4003",
    "sg:postcode":"55439",
    "sg:province":"MN",
    "sg:tags":[
        "building",
        "residential",
        "operates"
    ],
    "wof:name":"Erlmar Properties",
    "wof:placetype":"venue"
},
  "geometry": {"coordinates":[-93.389608,44.881535],"type":"Point"}
}