{
  "type": "Feature",
  "properties": {
    "addr:full":"9403 Wellington Ln N Osseo MN 55369",
    "addr:housenumber":"9403",
    "addr:postcode":"55369",
    "addr:street":"Wellington Ln N",
    "iso:country":"US",
    "sg:address":"9403 Wellington Ln N",
    "sg:city":"Osseo",
    "sg:classifiers":[
        {
            "category":"Professional",
            "type":"Services"
        }
    ],
    "sg:phone":"+1 763 493 0024",
    "sg:postcode":"55369",
    "sg:province":"MN",
    "wof:name":"Wisdom For Life LLC",
    "wof:placetype":"venue"
},
  "geometry": {"coordinates":[-93.418378,45.126537],"type":"Point"}
}