{
  "type": "Feature",
  "properties": {
    "iso:country":"US",
    "sg:address":"11315 Florida Ave N",
    "sg:city":"Champlin",
    "sg:classifiers":[
        {
            "category":"Building & Trades",
            "subcategory":"Construction",
            "type":"Services"
        }
    ],
    "sg:phone":"+1 763 424 4226",
    "sg:postcode":"55316",
    "sg:province":"MN",
    "sg:tags":[
        "contractor",
        "mechanical"
    ],
    "wof:name":"Cornerstone Mechanical",
    "wof:placetype":"venue"
},
  "geometry": {"coordinates":[-93.363156,45.159033],"type":"Point"}
}