{
  "type": "Feature",
  "properties": {
    "addr:full":"21883 Hwy 371 Little Falls MN 56345",
    "addr:housenumber":"21883",
    "addr:postcode":"56345",
    "addr:street":"Hwy 371",
    "iso:country":"US",
    "sg:address":"21883 Hwy 371",
    "sg:city":"Little Falls",
    "sg:classifiers":[
        {
            "category":"Wholesale",
            "subcategory":"Durable Goods & Equipment",
            "type":"Manufacturing & Wholesale Goods"
        }
    ],
    "sg:phone":"+1 320 632 3599",
    "sg:postcode":"56345",
    "sg:province":"MN",
    "wof:name":"Aqua Driving Range and Bar",
    "wof:placetype":"venue"
},
  "geometry": {"coordinates":[-94.32850000000001,46.078515],"type":"Point"}
}