{
  "type": "Feature",
  "properties": {
    "addr:full":"6161 Pine Beach Rd Brainerd MN 56401",
    "addr:housenumber":"6161",
    "addr:postcode":"56401",
    "addr:street":"Pine Beach Rd",
    "iso:country":"US",
    "sg:address":"6161 Pine Beach Rd",
    "sg:city":"Brainerd",
    "sg:classifiers":[
        {
            "category":"Building & Trades",
            "subcategory":"Landscaping Services",
            "type":"Services"
        },
        {
            "category":"Home & Garden",
            "subcategory":"Garden Supply",
            "type":"Retail Goods"
        }
    ],
    "sg:phone":"+1 218 828 7011",
    "sg:postcode":"56401",
    "sg:province":"MN",
    "sg:tags":[
        "sod",
        "sodding",
        "topsoil",
        "contractor",
        "landscape"
    ],
    "wof:name":"Dan's Sod Service",
    "wof:placetype":"venue"
},
  "geometry": {"coordinates":[-94.279055,46.383819],"type":"Point"}
}