{
  "type": "Feature",
  "properties": {
    "iso:country":"US",
    "sg:address":"1201 Charlton St",
    "sg:city":"Saint Paul",
    "sg:classifiers":[
        {
            "category":"Freight",
            "type":"Transportation"
        }
    ],
    "sg:phone":"+1 612 850 8500",
    "sg:postcode":"55118",
    "sg:province":"MN",
    "sg:tags":[
        "arrangement"
    ],
    "wof:name":"Air Express Cab",
    "wof:placetype":"venue"
},
  "geometry": {"coordinates":[-93.09607200000001,44.909625],"type":"Point"}
}