{
  "type": "Feature",
  "properties": {
    "iso:country":"US",
    "sg:address":"621 Olson Memorial Hwy",
    "sg:city":"Minneapolis",
    "sg:classifiers":[
        {
            "category":"Retail",
            "subcategory":"Laundry & Dry Cleaning",
            "type":"Services"
        },
        {
            "category":"Personal",
            "subcategory":"Skin Care",
            "type":"Services"
        }
    ],
    "sg:phone":"+1 612 333 2225",
    "sg:postcode":"55405",
    "sg:province":"MN",
    "sg:tags":[
        "linen",
        "uniform",
        "commercial",
        "supply"
    ],
    "sg:website":"http://www.gandkservices.com",
    "wof:name":"G&K Services, Inc.",
    "wof:placetype":"venue"
},
  "geometry": {"coordinates":[-93.286649,44.984255],"type":"Point"}
}