{
  "type": "Feature",
  "properties": {
    "iso:country":"US",
    "sg:address":"1535 Sextant Ave W",
    "sg:city":"Saint Paul",
    "sg:classifiers":[
        {
            "category":"Professional",
            "subcategory":"Management & Consulting",
            "type":"Services"
        }
    ],
    "sg:phone":"+1 612 790 3987",
    "sg:postcode":"55113",
    "sg:province":"MN",
    "sg:tags":[
        "business"
    ],
    "wof:name":"Bella Scoperta Consulting Inc",
    "wof:placetype":"venue"
},
  "geometry": {"coordinates":[-93.16537099999999,45.014745],"type":"Point"}
}