{
  "type": "Feature",
  "properties": {
    "iso:country":"US",
    "sg:address":"1707 Cope Ave E",
    "sg:city":"St Paul",
    "sg:classifiers":[
        {
            "category":"Manufacturing",
            "subcategory":"Tools & Machinery",
            "type":"Manufacturing & Wholesale Goods"
        }
    ],
    "sg:phone":"+1 651 777 1518",
    "sg:postcode":"55109",
    "sg:province":"MN",
    "sg:tags":[
        "water",
        "cutting",
        "jet"
    ],
    "wof:name":"Cd Systems",
    "wof:placetype":"venue"
},
  "geometry": {"coordinates":[-93.029252,45.010099],"type":"Point"}
}