{
  "type": "Feature",
  "properties": {
    "iso:country":"US",
    "sg:address":"808 Washington Ave",
    "sg:city":"Detroit Lakes",
    "sg:classifiers":[
        {
            "category":"Organizations",
            "subcategory":"Non-profit Organization",
            "type":"Services"
        },
        {
            "category":"Professional",
            "subcategory":"Management & Consulting",
            "type":"Services"
        }
    ],
    "sg:phone":"+1 218 844 4332",
    "sg:postcode":"56501",
    "sg:province":"MN",
    "sg:tags":[
        "fund",
        "counselor",
        "raising",
        "business"
    ],
    "wof:name":"Solutions of Dl LLC",
    "wof:placetype":"venue"
},
  "geometry": {"coordinates":[-95.845366,46.818327],"type":"Point"}
}