{
  "type": "Feature",
  "properties": {
    "addr:full":"6600 France Ave S Minneapolis MN 55435",
    "addr:housenumber":"6600",
    "addr:postcode":"55435",
    "addr:street":"France Ave S",
    "iso:country":"US",
    "sg:address":"6600 France Ave S",
    "sg:city":"Minneapolis",
    "sg:classifiers":[
        {
            "category":"Real Estate",
            "subcategory":"Real Estate Services",
            "type":"Services"
        }
    ],
    "sg:phone":"+1 952 484 8623",
    "sg:postcode":"55435",
    "sg:province":"MN",
    "sg:tags":[
        "closing",
        "title"
    ],
    "wof:name":"Twin Cities Title Associates",
    "wof:placetype":"venue"
},
  "geometry": {"coordinates":[-93.32894899999999,44.879861],"type":"Point"}
}