{
  "type": "Feature",
  "properties": {
    "iso:country":"US",
    "sg:address":"614 Pine St",
    "sg:city":"Circle Pines",
    "sg:classifiers":[
        {
            "category":"Food & Beverages",
            "subcategory":"Specialty",
            "type":"Retail Goods"
        }
    ],
    "sg:phone":"+1 651 785 0468",
    "sg:postcode":"55014",
    "sg:province":"MN",
    "wof:name":"Naturelink Health Systems",
    "wof:placetype":"venue"
},
  "geometry": {"coordinates":[-93.109882,45.21088],"type":"Point"}
}