{
  "type": "Feature",
  "properties": {
    "iso:country":"US",
    "sg:address":"3058 Ranchview Ln N",
    "sg:city":"Minneapolis",
    "sg:classifiers":[
        {
            "category":"Manufacturing",
            "subcategory":"Wood Products",
            "type":"Manufacturing & Wholesale Goods"
        }
    ],
    "sg:phone":"+1 763 476 8113",
    "sg:postcode":"55447",
    "sg:province":"MN",
    "sg:tags":[
        "picture",
        "frames-wholesale",
        "manufacturer"
    ],
    "sg:website":"http://www.globalminiatures.com",
    "wof:name":"Global Miniatures, Ltd.",
    "wof:placetype":"venue"
},
  "geometry": {"coordinates":[-93.476613,45.01455],"type":"Point"}
}