{
  "type": "Feature",
  "properties": {
    "addr:full":"2224 W 3rd St Duluth MN 55806",
    "addr:housenumber":"2224",
    "addr:postcode":"55806",
    "addr:street":"W 3Rd St",
    "iso:country":"US",
    "sg:address":"2224 W 3rd St",
    "sg:city":"Duluth",
    "sg:classifiers":[
        {
            "category":"Shopping",
            "type":"Retail Goods"
        }
    ],
    "sg:phone":"+1 218 722 2860",
    "sg:postcode":"55806",
    "sg:province":"MN",
    "sg:tags":[
        "church",
        "supply"
    ],
    "wof:name":"Sacred Heart Church Supplies",
    "wof:placetype":"venue"
},
  "geometry": {"coordinates":[-92.129729,46.767236],"type":"Point"}
}