{
  "type": "Feature",
  "properties": {
    "addr:full":"2900 Bryant Ave S Apt 206 Minneapolis MN 55408",
    "addr:housenumber":"2900;206",
    "addr:postcode":"55408",
    "addr:street":"Bryant Ave S Apt",
    "iso:country":"US",
    "sg:address":"2900 Bryant Ave S Apt 206",
    "sg:city":"Minneapolis",
    "sg:classifiers":[
        {
            "category":"Food & Beverages",
            "subcategory":"Farmers Market",
            "type":"Retail Goods"
        }
    ],
    "sg:phone":"+1 612 242 5154",
    "sg:postcode":"55408",
    "sg:province":"MN",
    "sg:tags":[
        "vegetable",
        "fruit"
    ],
    "wof:name":"Kelly Produces",
    "wof:placetype":"venue"
},
  "geometry": {"coordinates":[-93.290627,44.950031],"type":"Point"}
}