{
  "type": "Feature",
  "properties": {
    "addr:full":"175 E Co Rd C Saint Paul MN 55117",
    "addr:housenumber":"175",
    "addr:postcode":"55117",
    "addr:street":"E Co Rd C",
    "iso:country":"US",
    "sg:address":"175 E Co Rd C",
    "sg:city":"Saint Paul",
    "sg:classifiers":[
        {
            "category":"Real Estate",
            "subcategory":"Real Estate Agent",
            "type":"Services"
        }
    ],
    "sg:phone":"+1 651 483 5855",
    "sg:postcode":"55117",
    "sg:province":"MN",
    "wof:name":"Canterbury Pond",
    "wof:placetype":"venue"
},
  "geometry": {"coordinates":[-93.096273,45.023402],"type":"Point"}
}