{
  "type": "Feature",
  "properties": {
    "addr:full":"4150 Dupont Ave N Minneapolis MN 55412",
    "addr:housenumber":"4150",
    "addr:postcode":"55412",
    "addr:street":"Dupont Ave N",
    "iso:country":"US",
    "sg:address":"4150 Dupont Ave N",
    "sg:city":"Minneapolis",
    "sg:classifiers":[
        {
            "category":"Education",
            "subcategory":"Preschool",
            "type":"Public Place"
        },
        {
            "category":"Education",
            "subcategory":"School",
            "type":"Public Place"
        }
    ],
    "sg:phone":"+1 612 521 3185",
    "sg:postcode":"55412",
    "sg:province":"MN",
    "sg:tags":[
        "elementary"
    ],
    "wof:name":"Camden Community Pre School",
    "wof:placetype":"venue"
},
  "geometry": {"coordinates":[-93.29299899999999,45.0312],"type":"Point"}
}