{
  "type": "Feature",
  "properties": {
    "addr:full":"2548 Co Rd 10 Minneapolis MN 55430",
    "addr:housenumber":"2548;10",
    "addr:postcode":"55430",
    "addr:street":"Co Rd",
    "iso:country":"US",
    "sg:address":"2548 Co Rd 10",
    "sg:city":"Minneapolis",
    "sg:classifiers":[
        {
            "category":"Restaurant",
            "type":"Food & Drink"
        }
    ],
    "sg:phone":"+1 763 786 2383",
    "sg:postcode":"55430",
    "sg:province":"MN",
    "wof:name":"Domino's Pizza",
    "wof:placetype":"venue"
},
  "geometry": {"coordinates":[-93.31248100000001,45.059194],"type":"Point"}
}