{
  "type": "Feature",
  "properties": {
    "addr:full":"35756 State Hwy 15 Kimball MN 55353",
    "addr:housenumber":"35756",
    "addr:postcode":"55353",
    "addr:street":"State Hwy 15",
    "iso:country":"US",
    "sg:address":"35756 State Hwy 15",
    "sg:city":"Kimball",
    "sg:classifiers":[
        {
            "category":"Farming",
            "subcategory":"Farm",
            "type":"Manufacturing & Wholesale Goods"
        }
    ],
    "sg:phone":"+1 320 398 6252",
    "sg:postcode":"55353",
    "sg:province":"MN",
    "sg:tags":[
        "gen",
        "crop"
    ],
    "wof:name":"Earthberry Farm",
    "wof:placetype":"venue"
},
  "geometry": {"coordinates":[-94.31226599999999,45.26355],"type":"Point"}
}