{
  "type": "Feature",
  "properties": {
    "addr:full":"106 6th Ave N Princeton MN 55371",
    "addr:housenumber":"106",
    "addr:postcode":"55371",
    "addr:street":"6Th Ave N",
    "iso:country":"US",
    "sg:address":"106 6th Ave N",
    "sg:city":"Princeton",
    "sg:classifiers":[
        {
            "category":"Retail",
            "subcategory":"Laundry & Dry Cleaning",
            "type":"Services"
        }
    ],
    "sg:phone":"+1 763 389 0013",
    "sg:postcode":"55371",
    "sg:province":"MN",
    "sg:tags":[
        "garment",
        "agent"
    ],
    "wof:name":"Neighborhood Cleaners",
    "wof:placetype":"venue"
},
  "geometry": {"coordinates":[-93.581613,45.570154],"type":"Point"}
}