{
  "type": "Feature",
  "properties": {
    "addr:full":"10929 323rd Ave Princeton MN 55371",
    "addr:housenumber":"10929",
    "addr:postcode":"55371",
    "addr:street":"323Rd Ave",
    "iso:country":"US",
    "sg:address":"10929 323rd Ave",
    "sg:city":"Princeton",
    "sg:classifiers":[
        {
            "category":"Banks & Credit Unions",
            "subcategory":"Investment Brokerage",
            "type":"Services"
        }
    ],
    "sg:phone":"+1 763 389 9477",
    "sg:postcode":"55371",
    "sg:province":"MN",
    "sg:tags":[
        "advisory"
    ],
    "wof:name":"DAS Financial",
    "wof:placetype":"venue"
},
  "geometry": {"coordinates":[-93.548016,45.555538],"type":"Point"}
}