{
  "type": "Feature",
  "properties": {
    "iso:country":"US",
    "sg:address":"15250 Wayzata Blvd",
    "sg:city":"Wayzata",
    "sg:classifiers":[
        {
            "category":"Professional",
            "subcategory":"Management & Consulting",
            "type":"Services"
        }
    ],
    "sg:phone":"+1 952 473 1212",
    "sg:postcode":"55391",
    "sg:province":"MN",
    "sg:tags":[
        "residential",
        "construction"
    ],
    "wof:name":"Hotel Development & Mgt Inc",
    "wof:placetype":"venue"
},
  "geometry": {"coordinates":[-93.47475300000001,44.971396],"type":"Point"}
}