{
  "type": "Feature",
  "properties": {
    "iso:country":"US",
    "sg:address":"179 Hultberg Rd",
    "sg:city":"Esko",
    "sg:phone":"+1 218 879 9406",
    "sg:postcode":"55733",
    "sg:province":"MN",
    "sg:tags":[
        "farm",
        "field",
        "crop"
    ],
    "wof:name":"Jankowski Farms",
    "wof:placetype":"venue"
},
  "geometry": {"coordinates":[-92.41928299999999,46.734652],"type":"Point"}
}