{
  "type": "Feature",
  "properties": {
    "addr:full":"117 S Broadway Pelican Rapids MN 56572",
    "addr:housenumber":"117",
    "addr:postcode":"56572",
    "addr:street":"S Broadway",
    "iso:country":"US",
    "sg:address":"117 S Broadway",
    "sg:city":"Pelican Rapids",
    "sg:classifiers":[
        {
            "category":"Banks & Credit Unions",
            "subcategory":"Investment Brokerage",
            "type":"Services"
        }
    ],
    "sg:phone":"+1 218 863 1699",
    "sg:postcode":"56572",
    "sg:province":"MN",
    "sg:tags":[
        "advisory",
        "financial"
    ],
    "wof:name":"Raymond James Financial Svc",
    "wof:placetype":"venue"
},
  "geometry": {"coordinates":[-96.08349800000001,46.568603],"type":"Point"}
}