{
  "type": "Feature",
  "properties": {
    "iso:country":"US",
    "sg:address":"7200 Hemlock Ln N",
    "sg:city":"Osseo",
    "sg:classifiers":[
        {
            "category":"Manufacturing",
            "subcategory":"Electronics",
            "type":"Manufacturing & Wholesale Goods"
        }
    ],
    "sg:phone":"+1 763 425 5181",
    "sg:postcode":"55369",
    "sg:province":"MN",
    "sg:tags":[
        "apparatus",
        "mfg"
    ],
    "wof:name":"Fujitsu Network Communications",
    "wof:placetype":"venue"
},
  "geometry": {"coordinates":[-93.431288,45.085789],"type":"Point"}
}