{
  "type": "Feature",
  "properties": {
    "iso:country":"US",
    "sg:address":"610 Ottawa Ave N",
    "sg:city":"Minneapolis",
    "sg:classifiers":[
        {
            "category":"Professional",
            "subcategory":"Lawyer & Legal Services",
            "type":"Services"
        }
    ],
    "sg:phone":"+1 763 521 4499",
    "sg:postcode":"55422",
    "sg:province":"MN",
    "wof:name":"Peterson Byron M",
    "wof:placetype":"venue"
},
  "geometry": {"coordinates":[-93.339798,44.9851],"type":"Point"}
}