{
  "type": "Feature",
  "properties": {
    "addr:full":"224 E Highway 61 Esko MN 55733",
    "addr:housenumber":"224",
    "addr:postcode":"55733",
    "addr:street":"E Highway 61",
    "iso:country":"US",
    "sg:address":"224 E Highway 61",
    "sg:city":"Esko",
    "sg:classifiers":[
        {
            "category":"Manufacturing",
            "subcategory":"Buildings",
            "type":"Manufacturing & Wholesale Goods"
        },
        {
            "category":"Building & Trades",
            "subcategory":"Construction",
            "type":"Services"
        }
    ],
    "sg:phone":"+1 218 879 8644",
    "sg:postcode":"55733",
    "sg:province":"MN",
    "sg:tags":[
        "home",
        "builder",
        "contractor"
    ],
    "wof:name":"Bob Grover Construction",
    "wof:placetype":"venue"
},
  "geometry": {"coordinates":[-92.32126100000001,46.706051],"type":"Point"}
}