{
  "type": "Feature",
  "properties": {
    "addr:full":"227 14 St NW Bemidji MN 56601",
    "addr:housenumber":"14",
    "addr:postcode":"56601",
    "addr:street":"227;St Nw",
    "iso:country":"US",
    "sg:address":"227 14 St NW",
    "sg:city":"Bemidji",
    "sg:classifiers":[
        {
            "category":"Professional",
            "subcategory":"Accounting & Tax Preparation",
            "type":"Services"
        }
    ],
    "sg:phone":"+1 218 751 2709",
    "sg:postcode":"56601",
    "sg:province":"MN",
    "wof:name":"Donald O Anderson Accountant",
    "wof:placetype":"venue"
},
  "geometry": {"coordinates":[-94.83642999999999,48.741513],"type":"Point"}
}