{
  "type": "Feature",
  "properties": {
    "iso:country":"US",
    "sg:address":"7010 Willow Creek Rd",
    "sg:city":"Eden Prairie",
    "sg:classifiers":[
        {
            "category":"Professional",
            "subcategory":"Business Services",
            "type":"Services"
        }
    ],
    "sg:phone":"+1 952 941 4583",
    "sg:postcode":"55344",
    "sg:province":"MN",
    "wof:name":"Raynelle Designs",
    "wof:placetype":"venue"
},
  "geometry": {"coordinates":[-93.419802,44.872844],"type":"Point"}
}