{
  "type": "Feature",
  "properties": {
    "addr:full":"111 Waterfront Dr Two Harbors MN 55616",
    "addr:housenumber":"111",
    "addr:postcode":"55616",
    "addr:street":"Waterfront Dr",
    "iso:country":"US",
    "sg:address":"111 Waterfront Dr",
    "sg:city":"Two Harbors",
    "sg:classifiers":[
        {
            "category":"Retail",
            "subcategory":"Portrait Studio",
            "type":"Services"
        }
    ],
    "sg:phone":"+1 218 834 6304",
    "sg:postcode":"55616",
    "sg:province":"MN",
    "sg:tags":[
        "photo"
    ],
    "wof:name":"H Brian Rauvola Photographic",
    "wof:placetype":"venue"
},
  "geometry": {"coordinates":[-91.671047,47.019842],"type":"Point"}
}