{
  "type": "Feature",
  "properties": {
    "iso:country":"US",
    "sg:address":"816 W 98th St",
    "sg:city":"Minneapolis",
    "sg:phone":"+1 952 884 4103",
    "sg:postcode":"55420",
    "sg:province":"MN",
    "sg:website":"http://www.wildbirdstore.net",
    "wof:name":"All Seasons Wild Bird Store",
    "wof:placetype":"venue"
},
  "geometry": {"coordinates":[-93.29003899999999,44.826368],"type":"Point"}
}