{
  "type": "Feature",
  "properties": {
    "iso:country":"US",
    "sg:address":"6087 46th St N",
    "sg:city":"Saint Paul",
    "sg:classifiers":[
        {
            "category":"Wholesale",
            "subcategory":"Hardware",
            "type":"Manufacturing & Wholesale Goods"
        }
    ],
    "sg:phone":"+1 651 777 6901",
    "sg:postcode":"55128",
    "sg:province":"MN",
    "sg:tags":[
        "plumbing",
        "industry",
        "m",
        "mfg"
    ],
    "wof:name":"Suburban",
    "wof:placetype":"venue"
},
  "geometry": {"coordinates":[-92.984172,45.01482],"type":"Point"}
}