{
  "type": "Feature",
  "properties": {
    "addr:full":"425 West St Sleepy Eye MN 56085",
    "addr:housenumber":"425",
    "addr:postcode":"56085",
    "addr:street":"West St",
    "iso:country":"US",
    "sg:address":"425 West St",
    "sg:city":"Sleepy Eye",
    "sg:classifiers":[
        {
            "category":"Farming",
            "subcategory":"Farm & Veterinary Services",
            "type":"Manufacturing & Wholesale Goods"
        }
    ],
    "sg:phone":"+1 507 794 7368",
    "sg:postcode":"56085",
    "sg:province":"MN",
    "sg:tags":[
        "livestock"
    ],
    "wof:name":"Tessmer Live Stock",
    "wof:placetype":"venue"
},
  "geometry": {"coordinates":[-94.850567,44.285609],"type":"Point"}
}