{
  "type": "Feature",
  "properties": {
    "iso:country":"US",
    "sg:address":"3525 Haug Ave SE",
    "sg:city":"Rockford",
    "sg:classifiers":[
        {
            "category":"Animal Shelter",
            "type":"Public Place"
        },
        {
            "category":"Retail",
            "subcategory":"Pet Boarding",
            "type":"Services"
        }
    ],
    "sg:phone":"+1 763 477 9999",
    "sg:postcode":"55373",
    "sg:province":"MN",
    "sg:tags":[
        "kennel"
    ],
    "sg:website":"http://www.happydaysdoggiecamp.com",
    "wof:name":"Happy Days Doggie Camp Inc",
    "wof:placetype":"venue"
},
  "geometry": {"coordinates":[-93.748441,45.101398],"type":"Point"}
}