{
  "type": "Feature",
  "properties": {
    "iso:country":"US",
    "sg:address":"4101 Normanna Rd",
    "sg:city":"Duluth",
    "sg:classifiers":[
        {
            "category":"Restaurant",
            "type":"Food & Drink"
        }
    ],
    "sg:phone":"+1 218 721 3568",
    "sg:postcode":"55803",
    "sg:province":"MN",
    "sg:tags":[
        "eating"
    ],
    "wof:name":"Sportsmens Inn",
    "wof:placetype":"venue"
},
  "geometry": {"coordinates":[-92.111632,46.98166],"type":"Point"}
}