{
  "type": "Feature",
  "properties": {
    "addr:full":"161 Main Ave W Winsted MN 55395",
    "addr:housenumber":"161",
    "addr:postcode":"55395",
    "addr:street":"Main Ave W",
    "iso:country":"US",
    "sg:address":"161 Main Ave W",
    "sg:city":"Winsted",
    "sg:classifiers":[
        {
            "category":"Home & Garden",
            "subcategory":"Hardware",
            "type":"Retail Goods"
        }
    ],
    "sg:phone":"+1 320 485 2443",
    "sg:postcode":"55395",
    "sg:province":"MN",
    "wof:name":"True Value",
    "wof:placetype":"venue"
},
  "geometry": {"coordinates":[-94.047209,44.964203],"type":"Point"}
}