{
  "type": "Feature",
  "properties": {
    "iso:country":"US",
    "sg:address":"4047 25th Ave S",
    "sg:city":"Minneapolis",
    "sg:classifiers":[
        {
            "category":"Communications",
            "subcategory":"Film & Video Production",
            "type":"Services"
        },
        {
            "category":"Communications",
            "subcategory":"Television Station",
            "type":"Services"
        }
    ],
    "sg:phone":"+1 718 852 9703",
    "sg:postcode":"55406",
    "sg:province":"MN",
    "sg:tags":[
        "companies-film",
        "producer",
        "tv",
        "program",
        "radio",
        "distributor"
    ],
    "wof:name":"Hissy Fit",
    "wof:placetype":"venue"
},
  "geometry": {"coordinates":[-93.23593099999999,44.929666],"type":"Point"}
}