{
  "type": "Feature",
  "properties": {
    "iso:country":"US",
    "sg:address":"718 Front St",
    "sg:city":"Brainerd",
    "sg:classifiers":[
        {
            "category":"Professional",
            "subcategory":"Lawyer & Legal Services",
            "type":"Services"
        }
    ],
    "sg:phone":"+1 218 829 7365",
    "sg:postcode":"56401",
    "sg:province":"MN",
    "sg:tags":[
        "attorney"
    ],
    "wof:name":"Charpentier & Lange",
    "wof:placetype":"venue"
},
  "geometry": {"coordinates":[-94.198936,46.356734],"type":"Point"}
}