{
  "type": "Feature",
  "properties": {
    "addr:full":"1642 Harbor St Ogilvie MN 56358",
    "addr:housenumber":"1642",
    "addr:postcode":"56358",
    "addr:street":"Harbor St",
    "iso:country":"US",
    "sg:address":"1642 Harbor St",
    "sg:city":"Ogilvie",
    "sg:classifiers":[
        {
            "category":"Personal",
            "type":"Services"
        }
    ],
    "sg:phone":"+1 320 272 0011",
    "sg:postcode":"56358",
    "sg:province":"MN",
    "sg:tags":[
        "therapist",
        "massage"
    ],
    "wof:name":"Massage Therapeutic By Barb",
    "wof:placetype":"venue"
},
  "geometry": {"coordinates":[-93.36864300000001,45.825238],"type":"Point"}
}