{
  "type": "Feature",
  "properties": {
    "addr:full":"17808 State Hwy 65 Ham Lake MN 55304",
    "addr:housenumber":"17808",
    "addr:postcode":"55304",
    "addr:street":"State Hwy 65",
    "iso:country":"US",
    "sg:address":"17808 State Hwy 65",
    "sg:city":"Ham Lake",
    "sg:classifiers":[
        {
            "category":"Home & Garden",
            "subcategory":"Building Materials",
            "type":"Retail Goods"
        }
    ],
    "sg:phone":"+1 763 413 9960",
    "sg:postcode":"55304",
    "sg:province":"MN",
    "sg:tags":[
        "siding"
    ],
    "wof:name":"Kaycan LTD",
    "wof:placetype":"venue"
},
  "geometry": {"coordinates":[-93.234272,45.296795],"type":"Point"}
}