{
  "type": "Feature",
  "properties": {
    "addr:full":"1175 Nininger Rd Hastings MN 55033",
    "addr:housenumber":"1175",
    "addr:postcode":"55033",
    "addr:street":"Nininger Rd",
    "iso:country":"US",
    "sg:address":"1175 Nininger Rd",
    "sg:city":"Hastings",
    "sg:classifiers":[
        {
            "category":"Government",
            "subcategory":"Office",
            "type":"Public Place"
        }
    ],
    "sg:phone":"+1 651 437 4282",
    "sg:postcode":"55033",
    "sg:province":"MN",
    "sg:tags":[
        "city"
    ],
    "wof:name":"Nininger Town Hall",
    "wof:placetype":"venue"
},
  "geometry": {"coordinates":[-92.872282,44.748263],"type":"Point"}
}