{
  "type": "Feature",
  "properties": {
    "iso:country":"US",
    "sg:address":"885 Katydid Ln NE",
    "sg:city":"St Michael",
    "sg:classifiers":[
        {
            "category":"Building & Trades",
            "subcategory":"Plumbing",
            "type":"Services"
        }
    ],
    "sg:phone":"+1 763 497 4577",
    "sg:postcode":"55376",
    "sg:province":"MN",
    "sg:tags":[
        "plumbing",
        "contractor"
    ],
    "wof:name":"Voss Utility & Plumbing",
    "wof:placetype":"venue"
},
  "geometry": {"coordinates":[-93.667379,45.165685],"type":"Point"}
}