{
  "type": "Feature",
  "properties": {
    "iso:country":"US",
    "sg:address":"1220 79th St",
    "sg:city":"Victoria",
    "sg:classifiers":[
        {
            "category":"Building & Trades",
            "subcategory":"Landscaping Services",
            "type":"Services"
        }
    ],
    "sg:phone":"+1 952 443 9941",
    "sg:postcode":"55386",
    "sg:province":"MN",
    "wof:name":"By The Woods LLC",
    "wof:placetype":"venue"
},
  "geometry": {"coordinates":[-93.650966,44.862137],"type":"Point"}
}