{
  "type": "Feature",
  "properties": {
    "iso:country":"US",
    "sg:address":"1122 N State St",
    "sg:city":"Fairmont",
    "sg:classifiers":[
        {
            "category":"Travel",
            "subcategory":"Hotels & Motels",
            "type":"Entertainment"
        }
    ],
    "sg:phone":"+1 507 235 3373",
    "sg:postcode":"56031",
    "sg:province":"MN",
    "wof:name":"Budget Inn",
    "wof:placetype":"venue"
},
  "geometry": {"coordinates":[-94.447453,43.665178],"type":"Point"}
}