{
  "type": "Feature",
  "properties": {
    "iso:country":"US",
    "sg:address":"2616 Cleveland Ave N",
    "sg:city":"Roseville",
    "sg:classifiers":[
        {
            "category":"Manufacturing",
            "subcategory":"Building Materials",
            "type":"Manufacturing & Wholesale Goods"
        }
    ],
    "sg:phone":"+1 651 294 2020",
    "sg:postcode":"55113",
    "sg:province":"MN",
    "wof:name":"Shopworks Inc",
    "wof:placetype":"venue"
},
  "geometry": {"coordinates":[-93.187223,45.020383],"type":"Point"}
}