{
  "type": "Feature",
  "properties": {
    "addr:full":"2980 Cleveland Ave N Saint Paul MN 55113",
    "addr:housenumber":"2980",
    "addr:postcode":"55113",
    "addr:street":"Cleveland Ave N",
    "iso:country":"US",
    "sg:address":"2980 Cleveland Ave N",
    "sg:city":"Saint Paul",
    "sg:classifiers":[
        {
            "category":"Wholesale",
            "subcategory":"Vending Machines",
            "type":"Manufacturing & Wholesale Goods"
        }
    ],
    "sg:phone":"+1 651 227 7622",
    "sg:postcode":"55113",
    "sg:province":"MN",
    "sg:tags":[
        "operator"
    ],
    "wof:name":"Vendstar Inc",
    "wof:placetype":"venue"
},
  "geometry": {"coordinates":[-93.187545,45.032464],"type":"Point"}
}