{
  "type": "Feature",
  "properties": {
    "addr:full":"6501 Humboldt Ave N Minneapolis MN 55430",
    "addr:housenumber":"6501",
    "addr:postcode":"55430",
    "addr:street":"Humboldt Ave N",
    "iso:country":"US",
    "sg:address":"6501 Humboldt Ave N",
    "sg:city":"Minneapolis",
    "sg:classifiers":[
        {
            "category":"Wholesale",
            "subcategory":"Machinery & Supplies",
            "type":"Manufacturing & Wholesale Goods"
        }
    ],
    "sg:phone":"+1 763 503 5004",
    "sg:postcode":"55430",
    "sg:province":"MN",
    "sg:tags":[
        "medical-cylinder",
        "bulk",
        "gas-industrial"
    ],
    "wof:name":"Winner Gas Brooklyn Cente",
    "wof:placetype":"venue"
},
  "geometry": {"coordinates":[-93.299583,45.07452],"type":"Point"}
}