{
  "type": "Feature",
  "properties": {
    "addr:full":"4701 Beard Ave S Minneapolis MN 55410",
    "addr:housenumber":"4701",
    "addr:postcode":"55410",
    "addr:street":"Beard Ave S",
    "iso:country":"US",
    "sg:address":"4701 Beard Ave S",
    "sg:city":"Minneapolis",
    "sg:classifiers":[
        {
            "category":"Building & Trades",
            "subcategory":"Construction",
            "type":"Services"
        }
    ],
    "sg:phone":"+1 612 922 9723",
    "sg:postcode":"55410",
    "sg:province":"MN",
    "wof:name":"Viking Drain Cleaning & Sewer",
    "wof:placetype":"venue"
},
  "geometry": {"coordinates":[-93.323967,44.916104],"type":"Point"}
}