{
  "type": "Feature",
  "properties": {
    "iso:country":"US",
    "sg:address":"4824 W 40th Ln",
    "sg:city":"Minneapolis",
    "sg:classifiers":[
        {
            "category":"Professional",
            "subcategory":"Business Services",
            "type":"Services"
        }
    ],
    "sg:phone":"+1 952 929 4637",
    "sg:postcode":"55416",
    "sg:province":"MN",
    "sg:tags":[
        "consultant",
        "coach"
    ],
    "wof:name":"United Auto Consultants",
    "wof:placetype":"venue"
},
  "geometry": {"coordinates":[-93.342652,44.929538],"type":"Point"}
}