{
  "type": "Feature",
  "properties": {
    "iso:country":"US",
    "sg:address":"500 Carlton St",
    "sg:city":"Maplewood",
    "sg:classifiers":[
        {
            "category":"Professional",
            "type":"Services"
        }
    ],
    "sg:phone":"+1 651 501 0367",
    "sg:postcode":"55119",
    "sg:province":"MN",
    "sg:tags":[
        "establishment"
    ],
    "wof:name":"Brooks Fiber Comm-Minnesota",
    "wof:placetype":"venue"
},
  "geometry": {"coordinates":[-92.992637,44.957066],"type":"Point"}
}