{
  "type": "Feature",
  "properties": {
    "iso:country":"US",
    "sg:address":"51949 Co Hwy 52",
    "sg:city":"New York Mills",
    "sg:phone":"+1 218 385 3712",
    "sg:postcode":"56571",
    "sg:province":"MN",
    "sg:tags":[
        "farm",
        "grain",
        "cash"
    ],
    "wof:name":"Jaaska Brothers",
    "wof:placetype":"venue"
},
  "geometry": {"coordinates":[-95.415099,46.427101],"type":"Point"}
}