{
  "type": "Feature",
  "properties": {
    "iso:country":"US",
    "sg:address":"6120 Logan Ave S",
    "sg:city":"Minneapolis",
    "sg:classifiers":[
        {
            "category":"Professional",
            "subcategory":"Computer Services",
            "type":"Services"
        }
    ],
    "sg:phone":"+1 612 869 2557",
    "sg:postcode":"55419",
    "sg:province":"MN",
    "sg:tags":[
        "programing",
        "custom"
    ],
    "wof:name":"Frey Software Solutions I",
    "wof:placetype":"venue"
},
  "geometry": {"coordinates":[-93.304778,44.891223],"type":"Point"}
}