{
  "type": "Feature",
  "properties": {
    "iso:country":"US",
    "sg:address":"14715 11th Ave N",
    "sg:city":"Minneapolis",
    "sg:classifiers":[
        {
            "category":"Professional",
            "subcategory":"Engineering",
            "type":"Services"
        }
    ],
    "sg:phone":"+1 612 559 2722",
    "sg:postcode":"55447",
    "sg:province":"MN",
    "wof:name":"RB Engineering Services",
    "wof:placetype":"venue"
},
  "geometry": {"coordinates":[-93.464912,44.990214],"type":"Point"}
}