{
  "type": "Feature",
  "properties": {
    "addr:full":"1932 Viking Dr NW Rochester MN 55901",
    "addr:housenumber":"1932",
    "addr:postcode":"55901",
    "addr:street":"Viking Dr Nw",
    "iso:country":"US",
    "sg:address":"1932 Viking Dr NW",
    "sg:city":"Rochester",
    "sg:classifiers":[
        {
            "category":"Health Services",
            "subcategory":"Hospital",
            "type":"Services"
        },
        {
            "category":"Health Services",
            "subcategory":"Clinic",
            "type":"Services"
        }
    ],
    "sg:phone":"+1 507 281 6240",
    "sg:postcode":"55901",
    "sg:province":"MN",
    "sg:tags":[
        "center",
        "mental"
    ],
    "wof:name":"Zumbro Valley Mental Hlth Ctr",
    "wof:placetype":"venue"
},
  "geometry": {"coordinates":[-92.468473,44.044966],"type":"Point"}
}