{
  "type": "Feature",
  "properties": {
    "addr:full":"1609 Pleasant St Saint Paul MN 55108",
    "addr:housenumber":"1609",
    "addr:postcode":"55108",
    "addr:street":"Pleasant St",
    "iso:country":"US",
    "sg:address":"1609 Pleasant St",
    "sg:city":"Saint Paul",
    "sg:classifiers":[
        {
            "category":"Building & Trades",
            "subcategory":"Construction",
            "type":"Services"
        }
    ],
    "sg:phone":"+1 651 739 3500",
    "sg:postcode":"55108",
    "sg:province":"MN",
    "sg:tags":[
        "house"
    ],
    "wof:name":"Kim Thomas Construction Compan",
    "wof:placetype":"venue"
},
  "geometry": {"coordinates":[-93.199833,44.991043],"type":"Point"}
}