{
  "type": "Feature",
  "properties": {
    "iso:country":"US",
    "sg:address":"6150 Aspen Ln",
    "sg:city":"Gilbert",
    "sg:classifiers":[
        {
            "category":"Building & Trades",
            "subcategory":"Construction",
            "type":"Services"
        }
    ],
    "sg:phone":"+1 218 865 6330",
    "sg:postcode":"55741",
    "sg:province":"MN",
    "sg:tags":[
        "home",
        "builder"
    ],
    "wof:name":"Rod & Sons Carpentry",
    "wof:placetype":"venue"
},
  "geometry": {"coordinates":[-92.330772,47.504939],"type":"Point"}
}