{
  "type": "Feature",
  "properties": {
    "iso:country":"US",
    "sg:address":"7084 E Fish Lake Rd",
    "sg:city":"Maple Grove",
    "sg:classifiers":[
        {
            "category":"Banks & Credit Unions",
            "subcategory":"Investment Brokerage",
            "type":"Services"
        }
    ],
    "sg:phone":"+1 763 494 0095",
    "sg:postcode":"55311",
    "sg:province":"MN",
    "sg:tags":[
        "consultant",
        "planning",
        "financial"
    ],
    "sg:website":"www.sessionsfinancial.com",
    "wof:name":"Sessions Financial Group Inc",
    "wof:placetype":"venue"
},
  "geometry": {"coordinates":[-93.449332,45.083564],"type":"Point"}
}