{
  "type": "Feature",
  "properties": {
    "iso:country":"US",
    "sg:address":"5009 Excelsior Blvd # 102",
    "sg:city":"Minneapolis",
    "sg:classifiers":[
        {
            "category":"Health Services",
            "subcategory":"Doctor",
            "type":"Services"
        },
        {
            "category":"Social Services",
            "type":"Services"
        },
        {
            "category":"Personal",
            "type":"Services"
        }
    ],
    "sg:phone":"+1 952 836 1689",
    "sg:postcode":"55416",
    "sg:province":"MN",
    "sg:tags":[
        "physician",
        "family",
        "surgeons",
        "counselors-licensed",
        "individual",
        "marriage",
        "child",
        "psychiatry",
        "professional",
        "counseling",
        "counselor"
    ],
    "wof:name":"Dahnke Jan Licsw",
    "wof:placetype":"venue"
},
  "geometry": {"coordinates":[-93.344341,44.931918],"type":"Point"}
}