{
  "type": "Feature",
  "properties": {
    "addr:full":"711 S 17th St Montevideo MN 56265",
    "addr:housenumber":"711",
    "addr:postcode":"56265",
    "addr:street":"S 17Th St",
    "iso:country":"US",
    "sg:address":"711 S 17th St",
    "sg:city":"Montevideo",
    "sg:classifiers":[
        {
            "category":"Government",
            "subcategory":"Office",
            "type":"Public Place"
        }
    ],
    "sg:phone":"+1 320 269 0959",
    "sg:postcode":"56265",
    "sg:province":"MN",
    "sg:tags":[
        "federal",
        "security",
        "national"
    ],
    "wof:name":"National Guard Army",
    "wof:placetype":"venue"
},
  "geometry": {"coordinates":[-95.706788,44.941267],"type":"Point"}
}