{
  "type": "Feature",
  "properties": {
    "addr:full":"2330 Cloud Dr NE Minneapolis MN 55449",
    "addr:housenumber":"2330",
    "addr:postcode":"55449",
    "addr:street":"Cloud Dr Ne",
    "iso:country":"US",
    "sg:address":"2330 Cloud Dr NE",
    "sg:city":"Minneapolis",
    "sg:classifiers":[
        {
            "category":"Shopping",
            "subcategory":"Department Store",
            "type":"Retail Goods"
        },
        {
            "category":"Home & Garden",
            "subcategory":"Hardware",
            "type":"Retail Goods"
        }
    ],
    "sg:phone":"+1 763 767 3353",
    "sg:postcode":"55449",
    "sg:province":"MN",
    "sg:tags":[
        "cleaner",
        "janitor",
        "equipment",
        "supply"
    ],
    "wof:name":"Martinizing Dry Cleaners",
    "wof:placetype":"venue"
},
  "geometry": {"coordinates":[-93.21357,45.191143],"type":"Point"}
}