{
  "type": "Feature",
  "properties": {
    "addr:full":"111 Market St Winona MN 55987",
    "addr:housenumber":"111",
    "addr:postcode":"55987",
    "addr:street":"Market St",
    "iso:country":"US",
    "sg:address":"111 Market St",
    "sg:city":"Winona",
    "sg:classifiers":[
        {
            "category":"Insurance",
            "subcategory":"Insurance Agent",
            "type":"Services"
        }
    ],
    "sg:phone":"+1 507 453 7985",
    "sg:postcode":"55987",
    "sg:province":"MN",
    "sg:tags":[
        "buyer",
        "broker",
        "real estate"
    ],
    "wof:name":"City Country Property",
    "wof:placetype":"venue"
},
  "geometry": {"coordinates":[-91.63209999999999,44.051985],"type":"Point"}
}