{
  "type": "Feature",
  "properties": {
    "iso:country":"US",
    "sg:address":"2933 33rd Ave S",
    "sg:city":"Minneapolis",
    "sg:classifiers":[
        {
            "category":"Wholesale",
            "subcategory":"Vending Machines",
            "type":"Manufacturing & Wholesale Goods"
        }
    ],
    "sg:phone":"+1 612 721 1802",
    "sg:postcode":"55406",
    "sg:province":"MN",
    "sg:tags":[
        "operator"
    ],
    "wof:name":"Seifert Vending",
    "wof:placetype":"venue"
},
  "geometry": {"coordinates":[-93.22424599999999,44.948955],"type":"Point"}
}