{
  "type": "Feature",
  "properties": {
    "iso:country":"US",
    "sg:address":"14001 Ridgedale Dr # 200",
    "sg:city":"Hopkins",
    "sg:classifiers":[
        {
            "category":"Health Services",
            "subcategory":"Doctor",
            "type":"Services"
        }
    ],
    "sg:phone":"+1 952 249 2000",
    "sg:postcode":"55305",
    "sg:province":"MN",
    "sg:tags":[
        "physician",
        "surgeon"
    ],
    "wof:name":"Teigen, Greg A, Md - Obstetrics & Gynecology West",
    "wof:placetype":"venue"
},
  "geometry": {"coordinates":[-93.457988,44.970068],"type":"Point"}
}