{
  "type": "Feature",
  "properties": {
    "addr:full":"222 S 9th St Ste 2100 Minneapolis MN 55402",
    "addr:housenumber":"222",
    "addr:postcode":"55402",
    "addr:street":"S 9Th St Ste 2100",
    "iso:country":"US",
    "sg:address":"222 S 9th St Ste 2100",
    "sg:city":"Minneapolis",
    "sg:classifiers":[
        {
            "category":"Banks & Credit Unions",
            "subcategory":"Financial Services",
            "type":"Services"
        }
    ],
    "sg:phone":"+1 612 347 6900",
    "sg:postcode":"55402",
    "sg:province":"MN",
    "sg:tags":[
        "cashing",
        "check"
    ],
    "sg:website":"http://www.cashplusinc.com",
    "wof:name":"Cash Plus",
    "wof:placetype":"venue"
},
  "geometry": {"coordinates":[-93.27082299999999,44.973679],"type":"Point"}
}