{
  "type": "Feature",
  "properties": {
    "addr:full":"689 S Cherokee Ave Saint Paul MN 55107",
    "addr:housenumber":"689",
    "addr:postcode":"55107",
    "addr:street":"S Cherokee Ave",
    "iso:country":"US",
    "sg:address":"689 S Cherokee Ave",
    "sg:city":"Saint Paul",
    "sg:classifiers":[
        {
            "category":"Professional",
            "subcategory":"Business Services",
            "type":"Services"
        }
    ],
    "sg:phone":"+1 651 227 4810",
    "sg:postcode":"55107",
    "sg:province":"MN",
    "sg:tags":[
        "consulting",
        "management"
    ],
    "wof:name":"Championchip Minnesota Inc",
    "wof:placetype":"venue"
},
  "geometry": {"coordinates":[-93.10472900000001,44.924946],"type":"Point"}
}