{
  "type": "Feature",
  "properties": {
    "iso:country":"US",
    "sg:address":"4722 42nd Ave N",
    "sg:city":"Minneapolis",
    "sg:classifiers":[
        {
            "category":"Real Estate",
            "subcategory":"Real Estate Services",
            "type":"Services"
        },
        {
            "category":"Real Estate",
            "subcategory":"Real Estate Agent",
            "type":"Services"
        }
    ],
    "sg:phone":"+1 763 533 2444",
    "sg:postcode":"55422",
    "sg:province":"MN",
    "sg:tags":[
        "buyer",
        "management",
        "broker"
    ],
    "wof:name":"Mr Real Estate Properties Inc",
    "wof:placetype":"venue"
},
  "geometry": {"coordinates":[-93.340304,45.031349],"type":"Point"}
}