{
  "type": "Feature",
  "properties": {
    "addr:full":"306 W Michigan St Ste 300 Duluth MN 55802",
    "addr:housenumber":"306",
    "addr:postcode":"55802",
    "addr:street":"W Michigan St Ste 300",
    "iso:country":"US",
    "sg:address":"306 W Michigan St Ste 300",
    "sg:city":"Duluth",
    "sg:classifiers":[
        {
            "category":"Real Estate",
            "subcategory":"Real Estate Services",
            "type":"Services"
        }
    ],
    "sg:phone":"+1 218 720 3712",
    "sg:postcode":"55802",
    "sg:province":"MN",
    "sg:tags":[
        "management",
        "vacancy",
        "apartment",
        "listing",
        "rental",
        "finder"
    ],
    "sg:website":"http://www.melhus.org",
    "wof:name":"Melhus Management Company",
    "wof:placetype":"venue"
},
  "geometry": {"coordinates":[-92.101426,46.783699],"type":"Point"}
}