{
  "type": "Feature",
  "properties": {
    "iso:country":"US",
    "sg:address":"34226 Sybil Lake Rd",
    "sg:city":"Vergas",
    "sg:classifiers":[
        {
            "category":"Building & Trades",
            "subcategory":"Plumbing",
            "type":"Services"
        }
    ],
    "sg:phone":"+1 218 342 2632",
    "sg:postcode":"56587",
    "sg:province":"MN",
    "sg:tags":[
        "contractor"
    ],
    "wof:name":"Anytime Drain Cleaning",
    "wof:placetype":"venue"
},
  "geometry": {"coordinates":[-95.76612,46.614367],"type":"Point"}
}