{
  "type": "Feature",
  "properties": {
    "addr:full":"17115 Nassau St NE Andover MN 55304",
    "addr:housenumber":"17115",
    "addr:postcode":"55304",
    "addr:street":"Nassau St Ne",
    "iso:country":"US",
    "sg:address":"17115 Nassau St NE",
    "sg:city":"Andover",
    "sg:classifiers":[
        {
            "category":"Real Estate",
            "subcategory":"Developer",
            "type":"Services"
        }
    ],
    "sg:phone":"+1 763 413 9132",
    "sg:postcode":"55304",
    "sg:province":"MN",
    "wof:name":"Krawiecki Development Co",
    "wof:placetype":"venue"
},
  "geometry": {"coordinates":[-93.216917,45.281108],"type":"Point"}
}