{
  "type": "Feature",
  "properties": {
    "addr:full":"511 Kenwood Pkwy Minneapolis MN 55403",
    "addr:housenumber":"511",
    "addr:postcode":"55403",
    "addr:street":"Kenwood Pkwy",
    "iso:country":"US",
    "sg:address":"511 Kenwood Pkwy",
    "sg:city":"Minneapolis",
    "sg:classifiers":[
        {
            "category":"Education",
            "subcategory":"School",
            "type":"Public Place"
        }
    ],
    "sg:phone":"+1 952 988 3700",
    "sg:postcode":"55403",
    "sg:province":"MN",
    "wof:name":"Blake School the",
    "wof:placetype":"venue"
},
  "geometry": {"coordinates":[-93.293297,44.969799],"type":"Point"}
}