{
  "type": "Feature",
  "properties": {
    "addr:full":"4801 Woodridge Rd Minnetonka MN 55345",
    "addr:housenumber":"4801",
    "addr:postcode":"55345",
    "addr:street":"Woodridge Rd",
    "iso:country":"US",
    "sg:address":"4801 Woodridge Rd",
    "sg:city":"Minnetonka",
    "sg:classifiers":[
        {
            "category":"Education",
            "subcategory":"School",
            "type":"Public Place"
        }
    ],
    "sg:phone":"+1 952 988 5200",
    "sg:postcode":"55345",
    "sg:province":"MN",
    "wof:name":"Hopkins Public Schools",
    "wof:placetype":"venue"
},
  "geometry": {"coordinates":[-93.45790100000001,44.916199],"type":"Point"}
}