{
  "type": "Feature",
  "properties": {
    "iso:country":"US",
    "sg:address":"12955 State Hwy 55",
    "sg:city":"Minneapolis",
    "sg:classifiers":[
        {
            "category":"Building & Trades",
            "subcategory":"Construction",
            "type":"Services"
        }
    ],
    "sg:phone":"+1 763 478 3232",
    "sg:postcode":"55441",
    "sg:province":"MN",
    "sg:tags":[
        "residential",
        "drywall",
        "painting",
        "painter",
        "contractor"
    ],
    "sg:website":"www.brushmasters.com",
    "wof:name":"Brush Masters Inc",
    "wof:placetype":"venue"
},
  "geometry": {"coordinates":[-93.442483,44.999937],"type":"Point"}
}