{
  "type": "Feature",
  "properties": {
    "addr:full":"1836 W Pinehurst Ave Saint Paul MN 55116",
    "addr:housenumber":"1836",
    "addr:postcode":"55116",
    "addr:street":"W Pinehurst Ave",
    "iso:country":"US",
    "sg:address":"1836 W Pinehurst Ave",
    "sg:city":"Saint Paul",
    "sg:classifiers":[
        {
            "category":"Building & Trades",
            "subcategory":"Construction",
            "type":"Services"
        }
    ],
    "sg:phone":"+1 651 690 0810",
    "sg:postcode":"55116",
    "sg:province":"MN",
    "sg:tags":[
        "house",
        "residential"
    ],
    "wof:name":"Remodeling Designs Inc",
    "wof:placetype":"venue"
},
  "geometry": {"coordinates":[-93.180362,44.91879],"type":"Point"}
}