{
  "type": "Feature",
  "properties": {
    "addr:full":"247 3rd Ave S Minneapolis MN 55415",
    "addr:housenumber":"247",
    "addr:postcode":"55415",
    "addr:street":"3Rd Ave S",
    "iso:country":"US",
    "sg:address":"247 3rd Ave S",
    "sg:city":"Minneapolis",
    "sg:classifiers":[
        {
            "category":"Professional",
            "subcategory":"Lawyer & Legal Services",
            "type":"Services"
        }
    ],
    "sg:phone":"+1 612 341 2525",
    "sg:postcode":"55415",
    "sg:province":"MN",
    "sg:tags":[
        "personal",
        "attorney",
        "injury",
        "law"
    ],
    "sg:website":"http://www.lawyers.com/keithjohnson/",
    "wof:name":"Law Office of Keith D. Johnson",
    "wof:placetype":"venue"
},
  "geometry": {"coordinates":[-93.26400599999999,44.980098],"type":"Point"}
}