{
  "type": "Feature",
  "properties": {
    "addr:full":"1509 Sattre Rd NW Oronoco MN 55960",
    "addr:housenumber":"1509",
    "addr:postcode":"55960",
    "addr:street":"Sattre Rd Nw",
    "iso:country":"US",
    "sg:address":"1509 Sattre Rd NW",
    "sg:city":"Oronoco",
    "sg:classifiers":[
        {
            "category":"Professional",
            "subcategory":"Business Services",
            "type":"Services"
        }
    ],
    "sg:phone":"+1 507 289 0275",
    "sg:postcode":"55960",
    "sg:province":"MN",
    "wof:name":"K B Interiors",
    "wof:placetype":"venue"
},
  "geometry": {"coordinates":[-92.476455,44.139966],"type":"Point"}
}