{
  "type": "Feature",
  "properties": {
    "addr:full":"254 2nd Ave S Waite Park MN 56387",
    "addr:housenumber":"254",
    "addr:postcode":"56387",
    "addr:street":"2Nd Ave S Waite Park",
    "iso:country":"US",
    "sg:address":"254 2nd Ave S",
    "sg:city":"Waite Park",
    "sg:classifiers":[
        {
            "category":"Government",
            "subcategory":"Post Office",
            "type":"Public Place"
        }
    ],
    "sg:phone":"+1 320 251 8415",
    "sg:postcode":"56387",
    "sg:province":"MN",
    "wof:name":"US Post Office",
    "wof:placetype":"venue"
},
  "geometry": {"coordinates":[-94.21892200000001,45.549243],"type":"Point"}
}