{
  "type": "Feature",
  "properties": {
    "iso:country":"US",
    "sg:address":"8200 Northern Dr",
    "sg:city":"Minneapolis",
    "sg:classifiers":[
        {
            "category":"Wholesale",
            "subcategory":"Computers",
            "type":"Manufacturing & Wholesale Goods"
        }
    ],
    "sg:phone":"+1 612 251 6251",
    "sg:postcode":"55427",
    "sg:province":"MN",
    "sg:tags":[
        "sales"
    ],
    "wof:name":"Mid Metro Computing",
    "wof:placetype":"venue"
},
  "geometry": {"coordinates":[-93.38155999999999,45.013946],"type":"Point"}
}