{
  "type": "Feature",
  "properties": {
    "iso:country":"US",
    "sg:address":"56993 Fort Rd",
    "sg:city":"New Ulm",
    "sg:phone":"+1 507 359 4457",
    "sg:postcode":"56073",
    "sg:province":"MN",
    "sg:tags":[
        "farm",
        "grain",
        "cash"
    ],
    "wof:name":"P Muehlbauer",
    "wof:placetype":"venue"
},
  "geometry": {"coordinates":[-94.40965,44.36607],"type":"Point"}
}