{
  "type": "Feature",
  "properties": {
    "iso:country":"US",
    "sg:address":"430 Oak Grove St",
    "sg:city":"Minneapolis",
    "sg:classifiers":[
        {
            "category":"Professional",
            "subcategory":"Credit Reporting & Collection",
            "type":"Services"
        }
    ],
    "sg:phone":"+1 952 448 3665",
    "sg:postcode":"55403",
    "sg:province":"MN",
    "sg:tags":[
        "agency"
    ],
    "sg:website":"www.hfscollects.com",
    "wof:name":"Heartland Financial Svc",
    "wof:placetype":"venue"
},
  "geometry": {"coordinates":[-93.285967,44.968115],"type":"Point"}
}