{
  "type": "Feature",
  "properties": {
    "addr:full":"19758 Blaine Ave Farmington MN 55024",
    "addr:housenumber":"19758",
    "addr:postcode":"55024",
    "addr:street":"Blaine Ave",
    "iso:country":"US",
    "sg:address":"19758 Blaine Ave",
    "sg:city":"Farmington",
    "sg:classifiers":[
        {
            "category":"Manufacturing",
            "subcategory":"Food",
            "type":"Manufacturing & Wholesale Goods"
        },
        {
            "category":"Farming",
            "subcategory":"Farm",
            "type":"Manufacturing & Wholesale Goods"
        }
    ],
    "sg:phone":"+1 651 463 3158",
    "sg:postcode":"55024",
    "sg:province":"MN",
    "sg:tags":[
        "corn",
        "product"
    ],
    "wof:name":"Schuhweck, John",
    "wof:placetype":"venue"
},
  "geometry": {"coordinates":[-93.055206,44.661595],"type":"Point"}
}