{
  "type": "Feature",
  "properties": {
    "addr:full":"8534 Keats Ave SW Howard Lake MN 55349",
    "addr:housenumber":"8534",
    "addr:postcode":"55349",
    "addr:street":"Keats Ave Sw Howard Lake",
    "iso:country":"US",
    "sg:address":"8534 Keats Ave SW",
    "sg:city":"Howard Lake",
    "sg:classifiers":[
        {
            "category":"Manufacturing",
            "subcategory":"Tools & Machinery",
            "type":"Manufacturing & Wholesale Goods"
        }
    ],
    "sg:phone":"+1 320 543 3877",
    "sg:postcode":"55349",
    "sg:province":"MN",
    "sg:tags":[
        "machine",
        "shop",
        "industrial",
        "mfg"
    ],
    "wof:name":"Schuelke Machine Co",
    "wof:placetype":"venue"
},
  "geometry": {"coordinates":[-94.093745,45.026542],"type":"Point"}
}