{
  "type": "Feature",
  "properties": {
    "iso:country":"US",
    "sg:address":"2340 26th St",
    "sg:city":"Slayton",
    "sg:classifiers":[
        {
            "category":"Shopping",
            "subcategory":"Computers & Home Electronics",
            "type":"Retail Goods"
        }
    ],
    "sg:phone":"+1 507 836 6161",
    "sg:postcode":"56172",
    "sg:province":"MN",
    "sg:tags":[
        "equipment",
        "dealer"
    ],
    "wof:name":"CAD Consulting Svc",
    "wof:placetype":"venue"
},
  "geometry": {"coordinates":[-95.75872099999999,43.987765],"type":"Point"}
}