{
  "type": "Feature",
  "properties": {
    "addr:full":"11400 42nd St Clear Lake MN 55319",
    "addr:housenumber":"11400",
    "addr:postcode":"55319",
    "addr:street":"42Nd St",
    "iso:country":"US",
    "sg:address":"11400 42nd St",
    "sg:city":"Clear Lake",
    "sg:classifiers":[
        {
            "category":"Professional",
            "type":"Services"
        }
    ],
    "sg:phone":"+1 320 743 3512",
    "sg:postcode":"55319",
    "sg:province":"MN",
    "wof:name":"Iray",
    "wof:placetype":"venue"
},
  "geometry": {"coordinates":[-93.927633,45.504989],"type":"Point"}
}