{
  "type": "Feature",
  "properties": {
    "addr:full":"200 6th St SW Willmar MN 56201",
    "addr:housenumber":"200",
    "addr:postcode":"56201",
    "addr:street":"6Th St Sw",
    "iso:country":"US",
    "sg:address":"200 6th St SW",
    "sg:city":"Willmar",
    "sg:classifiers":[
        {
            "category":"Shopping",
            "subcategory":"Used Merchandise",
            "type":"Retail Goods"
        }
    ],
    "sg:phone":"+1 320 235 1565",
    "sg:postcode":"56201",
    "sg:province":"MN",
    "wof:name":"Use It Again",
    "wof:placetype":"venue"
},
  "geometry": {"coordinates":[-95.051028,45.121662],"type":"Point"}
}