{
  "type": "Feature",
  "properties": {
    "iso:country":"US",
    "sg:address":"8565 Edinburgh Centre Dr N",
    "sg:city":"Minneapolis",
    "sg:classifiers":[
        {
            "category":"Restaurant",
            "type":"Food & Drink"
        }
    ],
    "sg:phone":"+1 763 315 1110",
    "sg:postcode":"55443",
    "sg:province":"MN",
    "wof:name":"Pizza Man",
    "wof:placetype":"venue"
},
  "geometry": {"coordinates":[-93.302907,45.110677],"type":"Point"}
}