{
  "type": "Feature",
  "properties": {
    "addr:full":"3007 Utah Ave S Minneapolis MN 55426",
    "addr:housenumber":"3007",
    "addr:postcode":"55426",
    "addr:street":"Utah Ave S",
    "iso:country":"US",
    "sg:address":"3007 Utah Ave S",
    "sg:city":"Minneapolis",
    "sg:classifiers":[
        {
            "category":"Personal",
            "subcategory":"Beauty Salon",
            "type":"Services"
        }
    ],
    "sg:phone":"+1 952 938 2407",
    "sg:postcode":"55426",
    "sg:province":"MN",
    "sg:tags":[
        "manicuring"
    ],
    "wof:name":"Paris Nail",
    "wof:placetype":"venue"
},
  "geometry": {"coordinates":[-93.382058,44.948521],"type":"Point"}
}