{
  "type": "Feature",
  "properties": {
    "iso:country":"US",
    "sg:address":"7024 Kenmare Dr",
    "sg:city":"Minneapolis",
    "sg:classifiers":[
        {
            "category":"Insurance",
            "subcategory":"Insurance Agent",
            "type":"Services"
        }
    ],
    "sg:phone":"+1 952 946 9985",
    "sg:postcode":"55438",
    "sg:province":"MN",
    "wof:name":"Lb &J Risk Management Insur",
    "wof:placetype":"venue"
},
  "geometry": {"coordinates":[-93.376786,44.796563],"type":"Point"}
}