{
  "type": "Feature",
  "properties": {
    "iso:country":"US",
    "sg:address":"601 Carlson Pkwy S",
    "sg:city":"Hopkins",
    "sg:classifiers":[
        {
            "category":"Professional",
            "subcategory":"Management & Consulting",
            "type":"Services"
        }
    ],
    "sg:phone":"+1 952 449 5271",
    "sg:postcode":"55305",
    "sg:province":"MN",
    "sg:tags":[
        "business"
    ],
    "wof:name":"Returnritecom Inc",
    "wof:placetype":"venue"
},
  "geometry": {"coordinates":[-93.469363,44.974638],"type":"Point"}
}