{
  "type": "Feature",
  "properties": {
    "addr:full":"14016 Quinn St NW Anoka MN 55304",
    "addr:housenumber":"14016",
    "addr:postcode":"55304",
    "addr:street":"Quinn St Nw",
    "iso:country":"US",
    "sg:address":"14016 Quinn St NW",
    "sg:city":"Anoka",
    "sg:classifiers":[
        {
            "category":"Wholesale",
            "subcategory":"Apparel",
            "type":"Manufacturing & Wholesale Goods"
        }
    ],
    "sg:phone":"+1 763 754 6624",
    "sg:postcode":"55304",
    "sg:province":"MN",
    "sg:tags":[
        "clothing"
    ],
    "wof:name":"Tailored For Tots",
    "wof:placetype":"venue"
},
  "geometry": {"coordinates":[-93.32095200000001,45.224917],"type":"Point"}
}