{
  "type": "Feature",
  "properties": {
    "iso:country":"US",
    "sg:address":"103 20th St SW",
    "sg:city":"Austin",
    "sg:classifiers":[
        {
            "category":"Building & Trades",
            "subcategory":"Construction",
            "type":"Services"
        }
    ],
    "sg:phone":"+1 507 437 2557",
    "sg:postcode":"55912",
    "sg:province":"MN",
    "sg:tags":[
        "system",
        "contractor",
        "air conditioning"
    ],
    "wof:name":"Tom's Heating Ac & Rfrgn",
    "wof:placetype":"venue"
},
  "geometry": {"coordinates":[-93.00286699999999,43.666196],"type":"Point"}
}