{
  "type": "Feature",
  "properties": {
    "iso:country":"US",
    "sg:address":"4801 W 81st St",
    "sg:city":"Minneapolis",
    "sg:classifiers":[
        {
            "category":"Health Services",
            "subcategory":"Doctor",
            "type":"Services"
        }
    ],
    "sg:phone":"+1 952 837 9700",
    "sg:postcode":"55437",
    "sg:province":"MN",
    "sg:tags":[
        "medical",
        "management"
    ],
    "wof:name":"Suburban Radiologic Cons",
    "wof:placetype":"venue"
},
  "geometry": {"coordinates":[-93.33985,44.856414],"type":"Point"}
}