{
  "type": "Feature",
  "properties": {
    "addr:full":"5824 Long Brake Trl Minneapolis MN 55439",
    "addr:housenumber":"5824",
    "addr:postcode":"55439",
    "addr:street":"Long Brake Trl",
    "iso:country":"US",
    "sg:address":"5824 Long Brake Trl",
    "sg:city":"Minneapolis",
    "sg:classifiers":[
        {
            "category":"Manufacturing",
            "subcategory":"Printing",
            "type":"Manufacturing & Wholesale Goods"
        }
    ],
    "sg:phone":"+1 612 339 8888",
    "sg:postcode":"55439",
    "sg:province":"MN",
    "sg:tags":[
        "commercial"
    ],
    "wof:name":"Shirt Shack International",
    "wof:placetype":"venue"
},
  "geometry": {"coordinates":[-93.370318,44.865533],"type":"Point"}
}