{
  "type": "Feature",
  "properties": {
    "iso:country":"US",
    "sg:address":"4110 Marion Rd SE",
    "sg:city":"Rochester",
    "sg:classifiers":[
        {
            "category":"Retail",
            "subcategory":"Auto Rental",
            "type":"Services"
        }
    ],
    "sg:phone":"+1 507 289 2284",
    "sg:postcode":"55904",
    "sg:province":"MN",
    "sg:tags":[
        "recreational",
        "leasing",
        "vehicle"
    ],
    "wof:name":"L & S Rv Rental",
    "wof:placetype":"venue"
},
  "geometry": {"coordinates":[-92.35286000000001,43.95367],"type":"Point"}
}