{
  "type": "Feature",
  "properties": {
    "iso:country":"US",
    "sg:address":"3610 US Hwy 61",
    "sg:city":"White Bear Lake",
    "sg:classifiers":[
        {
            "category":"Retail",
            "subcategory":"Auto Repair",
            "type":"Services"
        }
    ],
    "sg:phone":"+1 651 429 3391",
    "sg:postcode":"55110",
    "sg:province":"MN",
    "sg:tags":[
        "body",
        "automobile",
        "painting"
    ],
    "sg:website":"www.barnettchrysler.com",
    "wof:name":"Barnett Chrysler Jeep-KIA",
    "wof:placetype":"venue"
},
  "geometry": {"coordinates":[-93.035804,45.05063],"type":"Point"}
}