{
  "type": "Feature",
  "properties": {
    "iso:country":"US",
    "sg:address":"1059 Hudson Rd",
    "sg:city":"St Paul",
    "sg:classifiers":[
        {
            "category":"Restaurant",
            "type":"Food & Drink"
        }
    ],
    "sg:phone":"+1 651 771 0305",
    "sg:postcode":"55106",
    "sg:province":"MN",
    "sg:tags":[
        "eating",
        "out"
    ],
    "wof:name":"Leo's Chow Mein",
    "wof:placetype":"venue"
},
  "geometry": {"coordinates":[-93.058273,44.952228],"type":"Point"}
}