{
  "type": "Feature",
  "properties": {
    "iso:country":"US",
    "sg:address":"9101 Science Center Dr",
    "sg:city":"Minneapolis",
    "sg:classifiers":[
        {
            "category":"Manufacturing",
            "subcategory":"Metals",
            "type":"Manufacturing & Wholesale Goods"
        },
        {
            "category":"Building & Trades",
            "subcategory":"Construction",
            "type":"Services"
        }
    ],
    "sg:phone":"+1 763 533 4822",
    "sg:postcode":"55428",
    "sg:province":"MN",
    "sg:tags":[
        "forming",
        "finisher",
        "rolling"
    ],
    "wof:name":"Avtech Finishing",
    "wof:placetype":"venue"
},
  "geometry": {"coordinates":[-93.394764,45.050669],"type":"Point"}
}