{
  "type": "Feature",
  "properties": {
    "iso:country":"US",
    "sg:address":"195 Washington Ave",
    "sg:city":"Foreston",
    "sg:classifiers":[
        {
            "category":"Retail",
            "subcategory":"Auto Repair",
            "type":"Services"
        }
    ],
    "sg:phone":"+1 320 294 5320",
    "sg:postcode":"56330",
    "sg:province":"MN",
    "sg:tags":[
        "repairing",
        "automobile"
    ],
    "wof:name":"Foreston Auto Svc",
    "wof:placetype":"venue"
},
  "geometry": {"coordinates":[-93.710933,45.733764],"type":"Point"}
}