{
  "type": "Feature",
  "properties": {
    "iso:country":"US",
    "sg:address":"104 E Chapman St",
    "sg:city":"Ely",
    "sg:classifiers":[
        {
            "category":"Banks & Credit Unions",
            "subcategory":"Bank",
            "type":"Services"
        }
    ],
    "sg:phone":"+1 218 365 3121",
    "sg:postcode":"55731",
    "sg:province":"MN",
    "sg:website":"www.wellsfargo.com",
    "wof:name":"Wells Fargo Bank",
    "wof:placetype":"venue"
},
  "geometry": {"coordinates":[-91.865377,47.902235],"type":"Point"}
}