{
  "type": "Feature",
  "properties": {
    "addr:full":"2728 9th Ave Ln NE Rochester MN 55906",
    "addr:housenumber":"2728",
    "addr:postcode":"55906",
    "addr:street":"9Th Ave Ln Ne",
    "iso:country":"US",
    "sg:address":"2728 9th Ave Ln NE",
    "sg:city":"Rochester",
    "sg:classifiers":[
        {
            "category":"Professional",
            "type":"Services"
        }
    ],
    "sg:phone":"+1 507 282 5752",
    "sg:postcode":"55906",
    "sg:province":"MN",
    "sg:tags":[
        "establishment"
    ],
    "wof:name":"Aerodrome Group Inc",
    "wof:placetype":"venue"
},
  "geometry": {"coordinates":[-92.446467,44.053164],"type":"Point"}
}