{
  "type": "Feature",
  "properties": {
    "addr:full":"10249 Yellow Circle Dr Hopkins MN 55343",
    "addr:housenumber":"10249",
    "addr:postcode":"55343",
    "addr:street":"Yellow Circle Dr",
    "iso:country":"US",
    "sg:address":"10249 Yellow Circle Dr",
    "sg:city":"Hopkins",
    "sg:classifiers":[
        {
            "category":"Health Services",
            "subcategory":"Clinic",
            "type":"Services"
        }
    ],
    "sg:phone":"+1 952 253 6600",
    "sg:postcode":"55343",
    "sg:province":"MN",
    "sg:tags":[
        "examination",
        "insurance"
    ],
    "sg:website":"www.woodlakemedical.com",
    "wof:name":"Woodlake Medical Management",
    "wof:placetype":"venue"
},
  "geometry": {"coordinates":[-93.41153199999999,44.89213],"type":"Point"}
}