{
  "type": "Feature",
  "properties": {
    "iso:country":"US",
    "sg:address":"5125 Hanover Rd",
    "sg:city":"Mound",
    "sg:classifiers":[
        {
            "category":"Professional",
            "type":"Services"
        }
    ],
    "sg:phone":"+1 952 472 1197",
    "sg:postcode":"55364",
    "sg:province":"MN",
    "wof:name":"ADS Imaging Incorporated",
    "wof:placetype":"venue"
},
  "geometry": {"coordinates":[-93.655377,44.920209],"type":"Point"}
}