{
  "type": "Feature",
  "properties": {
    "addr:full":"31528 Farm Ln Rochert MN 56578",
    "addr:housenumber":"31528",
    "addr:postcode":"56578",
    "addr:street":"Farm Ln",
    "iso:country":"US",
    "sg:address":"31528 Farm Ln",
    "sg:city":"Rochert",
    "sg:classifiers":[
        {
            "category":"Farming",
            "subcategory":"Dairy Farm",
            "type":"Manufacturing & Wholesale Goods"
        }
    ],
    "sg:phone":"+1 218 847 5195",
    "sg:postcode":"56578",
    "sg:province":"MN",
    "wof:name":"Erickson Dairy Farm",
    "wof:placetype":"venue"
},
  "geometry": {"coordinates":[-95.734915,46.977564],"type":"Point"}
}