{
  "type": "Feature",
  "properties": {
    "addr:full":"2309 28th Ave S Minneapolis MN 55406",
    "addr:housenumber":"2309",
    "addr:postcode":"55406",
    "addr:street":"28Th Ave S",
    "iso:country":"US",
    "sg:address":"2309 28th Ave S",
    "sg:city":"Minneapolis",
    "sg:classifiers":[
        {
            "category":"Education",
            "subcategory":"School",
            "type":"Public Place"
        }
    ],
    "sg:phone":"+1 612 668 4950",
    "sg:postcode":"55406",
    "sg:province":"MN",
    "sg:tags":[
        "high",
        "middle",
        "elementary"
    ],
    "wof:name":"Seward Montessori Elementary School",
    "wof:placetype":"venue"
},
  "geometry": {"coordinates":[-93.23139999999999,44.9604],"type":"Point"}
}