{
  "type": "Feature",
  "properties": {
    "iso:country":"US",
    "sg:address":"201 E Elizabeth Ave",
    "sg:city":"Keewatin",
    "sg:classifiers":[
        {
            "category":"Education",
            "subcategory":"Special Training",
            "type":"Public Place"
        }
    ],
    "sg:phone":"+1 218 778 6739",
    "sg:postcode":"55753",
    "sg:province":"MN",
    "sg:tags":[
        "instruction",
        "driving"
    ],
    "wof:name":"Arrowhead Driver Training",
    "wof:placetype":"venue"
},
  "geometry": {"coordinates":[-93.07133899999999,47.39621],"type":"Point"}
}