{
  "type": "Feature",
  "properties": {
    "iso:country":"US",
    "sg:address":"17480 Butternut St NW",
    "sg:city":"Andover",
    "sg:classifiers":[
        {
            "category":"Building & Trades",
            "subcategory":"Construction",
            "type":"Services"
        }
    ],
    "sg:phone":"+1 763 434 9768",
    "sg:postcode":"55304",
    "sg:province":"MN",
    "sg:tags":[
        "layer",
        "contractor",
        "laying",
        "floor",
        "carpet"
    ],
    "wof:name":"Ultimate Carpet Inc",
    "wof:placetype":"venue"
},
  "geometry": {"coordinates":[-93.267787,45.287093],"type":"Point"}
}