{
  "type": "Feature",
  "properties": {
    "addr:full":"6448 Oakwood Rd Saint Paul MN 55125",
    "addr:housenumber":"6448",
    "addr:postcode":"55125",
    "addr:street":"Oakwood Rd",
    "iso:country":"US",
    "sg:address":"6448 Oakwood Rd",
    "sg:city":"Saint Paul",
    "sg:classifiers":[
        {
            "category":"Education",
            "subcategory":"Special Training",
            "type":"Public Place"
        }
    ],
    "sg:phone":"+1 651 738 6737",
    "sg:postcode":"55125",
    "sg:province":"MN",
    "wof:name":"Brad Manor",
    "wof:placetype":"venue"
},
  "geometry": {"coordinates":[-92.97477499999999,44.93424],"type":"Point"}
}