{
  "type": "Feature",
  "properties": {
    "iso:country":"US",
    "sg:address":"12420 Aberdeen St NE",
    "sg:city":"Blaine",
    "sg:classifiers":[
        {
            "category":"Personal",
            "type":"Services"
        }
    ],
    "sg:phone":"+1 763 784 4747",
    "sg:postcode":"55449",
    "sg:province":"MN",
    "sg:tags":[
        "program",
        "physical",
        "exercise",
        "fitness"
    ],
    "wof:name":"Gold's Gym",
    "wof:placetype":"venue"
},
  "geometry": {"coordinates":[-93.231709,45.195527],"type":"Point"}
}