{
  "type": "Feature",
  "properties": {
    "addr:full":"23355 State Hwy 60 Mazeppa MN 55956",
    "addr:housenumber":"23355",
    "addr:postcode":"55956",
    "addr:street":"State Hwy 60 Mazeppa",
    "iso:country":"US",
    "sg:address":"23355 State Hwy 60",
    "sg:city":"Mazeppa",
    "sg:classifiers":[
        {
            "category":"Farming",
            "subcategory":"Livestock Farm",
            "type":"Manufacturing & Wholesale Goods"
        }
    ],
    "sg:phone":"+1 507 843 4120",
    "sg:postcode":"55956",
    "sg:province":"MN",
    "sg:tags":[
        "beef",
        "feedlot",
        "cattle"
    ],
    "wof:name":"Terry Poncelet",
    "wof:placetype":"venue"
},
  "geometry": {"coordinates":[-92.567077,44.26956],"type":"Point"}
}