{
  "type": "Feature",
  "properties": {
    "iso:country":"US",
    "sg:address":"501 Cliff Rd E",
    "sg:city":"Burnsville",
    "sg:classifiers":[
        {
            "category":"Manufacturing",
            "subcategory":"Tobacco Products",
            "type":"Manufacturing & Wholesale Goods"
        }
    ],
    "sg:phone":"+1 952 890 9273",
    "sg:postcode":"55337",
    "sg:province":"MN",
    "sg:tags":[
        "cigarette",
        "cigar",
        "mfg"
    ],
    "wof:name":"R J Reynolds Tobacco Company",
    "wof:placetype":"venue"
},
  "geometry": {"coordinates":[-93.270903,44.78794],"type":"Point"}
}