{
  "type": "Feature",
  "properties": {
    "iso:country":"US",
    "sg:address":"28547 Co Hwy 21",
    "sg:city":"Clinton",
    "sg:phone":"+1 320 325 5357",
    "sg:postcode":"56284",
    "sg:province":"MN",
    "sg:tags":[
        "farm",
        "corn",
        "soybean"
    ],
    "wof:name":"Gordon Strobel",
    "wof:placetype":"venue"
},
  "geometry": {"coordinates":[-95.17107300000001,44.789151],"type":"Point"}
}