{
  "type": "Feature",
  "properties": {
    "addr:full":"1287 2nd St N Sauk Rapids MN 56379",
    "addr:housenumber":"1287",
    "addr:postcode":"56379",
    "addr:street":"2Nd St N Sauk",
    "iso:country":"US",
    "sg:address":"1287 2nd St N",
    "sg:city":"Sauk Rapids",
    "sg:classifiers":[
        {
            "category":"Professional",
            "subcategory":"Lawyer & Legal Services",
            "type":"Services"
        }
    ],
    "sg:phone":"+1 320 251 1423",
    "sg:postcode":"56379",
    "sg:province":"MN",
    "wof:name":"Timothy Reuter",
    "wof:placetype":"venue"
},
  "geometry": {"coordinates":[-94.153673,45.598229],"type":"Point"}
}