{
  "type": "Feature",
  "properties": {
    "iso:country":"US",
    "sg:address":"13 13th Ave SW",
    "sg:city":"Saint Paul",
    "sg:classifiers":[
        {
            "category":"Food & Beverages",
            "subcategory":"Liquor & Beverages",
            "type":"Retail Goods"
        }
    ],
    "sg:phone":"+1 651 552 5955",
    "sg:postcode":"55112",
    "sg:province":"MN",
    "sg:tags":[
        "alcoholic"
    ],
    "wof:name":"S Jim Diamond Liquor",
    "wof:placetype":"venue"
},
  "geometry": {"coordinates":[-93.204853,45.047133],"type":"Point"}
}