{
  "type": "Feature",
  "properties": {
    "iso:country":"US",
    "sg:address":"1527 N Westminster St",
    "sg:city":"St Paul",
    "sg:classifiers":[
        {
            "category":"Building & Trades",
            "subcategory":"Construction",
            "type":"Services"
        }
    ],
    "sg:phone":"+1 651 336 1544",
    "sg:postcode":"55101",
    "sg:province":"MN",
    "sg:tags":[
        "maintenance",
        "contractor"
    ],
    "wof:name":"Meric Maintenance",
    "wof:placetype":"venue"
},
  "geometry": {"coordinates":[-93.086336,44.987322],"type":"Point"}
}