{
  "type": "Feature",
  "properties": {
    "iso:country":"US",
    "sg:address":"9184 Ranchview Ln N",
    "sg:city":"Osseo",
    "sg:classifiers":[
        {
            "category":"Building & Trades",
            "subcategory":"Construction",
            "type":"Services"
        }
    ],
    "sg:phone":"+1 612 703 9733",
    "sg:postcode":"55369",
    "sg:province":"MN",
    "sg:tags":[
        "tile",
        "dealer"
    ],
    "wof:name":"Exell Ceramic Co",
    "wof:placetype":"venue"
},
  "geometry": {"coordinates":[-93.47640800000001,45.1212],"type":"Point"}
}