{
  "type": "Feature",
  "properties": {
    "addr:full":"30153 Huntersville Rd Sebeka MN 56477",
    "addr:postcode":"30153;56477",
    "addr:street":"Huntersville Rd",
    "iso:country":"US",
    "sg:address":"30153 Huntersville Rd",
    "sg:city":"Sebeka",
    "sg:classifiers":[
        {
            "category":"Autos & Motor Vehicles",
            "subcategory":"Boat Sales",
            "type":"Retail Goods"
        }
    ],
    "sg:phone":"+1 218 472 3250",
    "sg:postcode":"56477",
    "sg:province":"MN",
    "sg:tags":[
        "canoe"
    ],
    "wof:name":"Gloege's Canoe Outfitters",
    "wof:placetype":"venue"
},
  "geometry": {"coordinates":[-94.858458,46.661157],"type":"Point"}
}