{
  "type": "Feature",
  "properties": {
    "iso:country":"US",
    "sg:address":"148 25th St SE",
    "sg:city":"Willmar",
    "sg:classifiers":[
        {
            "category":"Shopping",
            "subcategory":"Bicycles & Sporting Goods",
            "type":"Retail Goods"
        },
        {
            "category":"Recreation",
            "subcategory":"Fishing",
            "type":"Entertainment"
        }
    ],
    "sg:phone":"+1 320 222 2248",
    "sg:postcode":"56201",
    "sg:province":"MN",
    "sg:tags":[
        "tackle"
    ],
    "wof:name":"Js Bait & Sport",
    "wof:placetype":"venue"
},
  "geometry": {"coordinates":[-95.009383,45.123687],"type":"Point"}
}