{
  "type": "Feature",
  "properties": {
    "addr:full":"15942 Granada Ave Saint Paul MN 55124",
    "addr:postcode":"15942;55124",
    "addr:street":"Granada Ave",
    "iso:country":"US",
    "sg:address":"15942 Granada Ave",
    "sg:city":"Saint Paul",
    "sg:classifiers":[
        {
            "category":"Professional",
            "type":"Services"
        }
    ],
    "sg:phone":"+1 952 432 4680",
    "sg:postcode":"55124",
    "sg:province":"MN",
    "wof:name":"Northstar Adventure Racing",
    "wof:placetype":"venue"
},
  "geometry": {"coordinates":[-93.22235499999999,44.718193],"type":"Point"}
}