{
  "type": "Feature",
  "properties": {
    "addr:full":"221 Minnesota Ave N Aitkin MN 56431",
    "addr:housenumber":"221",
    "addr:postcode":"56431",
    "addr:street":"Minnesota Ave N",
    "iso:country":"US",
    "sg:address":"221 Minnesota Ave N",
    "sg:city":"Aitkin",
    "sg:classifiers":[
        {
            "category":"Shopping",
            "subcategory":"Books",
            "type":"Retail Goods"
        }
    ],
    "sg:phone":"+1 218 927 6771",
    "sg:postcode":"56431",
    "sg:province":"MN",
    "wof:name":"Booktowne",
    "wof:placetype":"venue"
},
  "geometry": {"coordinates":[-93.706693,46.534212],"type":"Point"}
}