{
  "type": "Feature",
  "properties": {
    "addr:full":"7470 Chanhassen Rd Chanhassen MN 55317",
    "addr:postcode":"7470;55317",
    "addr:street":"Chanhassen Rd",
    "iso:country":"US",
    "sg:address":"7470 Chanhassen Rd",
    "sg:city":"Chanhassen",
    "sg:classifiers":[
        {
            "category":"Banks & Credit Unions",
            "subcategory":"Investment Brokerage",
            "type":"Services"
        }
    ],
    "sg:phone":"+1 952 250 7515",
    "sg:postcode":"55317",
    "sg:province":"MN",
    "sg:tags":[
        "security"
    ],
    "wof:name":"K L C Investments",
    "wof:placetype":"venue"
},
  "geometry": {"coordinates":[-93.52085700000001,44.869565],"type":"Point"}
}