{
  "type": "Feature",
  "properties": {
    "addr:full":"3299 Co Rd 45 Owatonna MN 55060",
    "addr:housenumber":"3299;45",
    "addr:postcode":"55060",
    "addr:street":"Co Rd",
    "iso:country":"US",
    "sg:address":"3299 Co Rd 45",
    "sg:city":"Owatonna",
    "sg:classifiers":[
        {
            "category":"Wholesale",
            "subcategory":"Machinery & Supplies",
            "type":"Manufacturing & Wholesale Goods"
        },
        {
            "category":"Wholesale",
            "subcategory":"Chemicals & Plastics",
            "type":"Manufacturing & Wholesale Goods"
        }
    ],
    "sg:phone":"+1 507 455 0682",
    "sg:postcode":"55060",
    "sg:province":"MN",
    "sg:tags":[
        "building",
        "industrial",
        "janitor",
        "maintenance"
    ],
    "wof:name":"Hillyard Floor Care Supply Co",
    "wof:placetype":"venue"
},
  "geometry": {"coordinates":[-93.22610400000001,44.046651],"type":"Point"}
}