{
  "type": "Feature",
  "properties": {
    "addr:full":"590 University Ave W St Paul MN 55103",
    "addr:housenumber":"590",
    "addr:postcode":"55103",
    "addr:street":"University Ave W",
    "iso:country":"US",
    "sg:address":"590 University Ave W",
    "sg:city":"St Paul",
    "sg:classifiers":[
        {
            "category":"Education",
            "subcategory":"School",
            "type":"Public Place"
        }
    ],
    "sg:phone":"+1 651 293 5900",
    "sg:postcode":"55103",
    "sg:province":"MN",
    "wof:name":"St Paul Area Learning Center",
    "wof:placetype":"venue"
},
  "geometry": {"coordinates":[-93.125412,44.955649],"type":"Point"}
}