{
  "type": "Feature",
  "properties": {
    "iso:country":"US",
    "sg:address":"8485 Rose St",
    "sg:city":"Owatonna",
    "sg:classifiers":[
        {
            "category":"Government",
            "subcategory":"Office",
            "type":"Public Place"
        }
    ],
    "sg:phone":"+1 507 455 5841",
    "sg:postcode":"55060",
    "sg:province":"MN",
    "wof:name":"Wildlife Management",
    "wof:placetype":"venue"
},
  "geometry": {"coordinates":[-93.05711100000001,44.097751],"type":"Point"}
}