{
  "type": "Feature",
  "properties": {
    "iso:country":"US",
    "sg:address":"173 Lothenbach Ave",
    "sg:city":"Saint Paul",
    "sg:classifiers":[
        {
            "category":"Restaurant",
            "type":"Food & Drink"
        }
    ],
    "sg:phone":"+1 651 451 7431",
    "sg:postcode":"55118",
    "sg:province":"MN",
    "sg:tags":[
        "bar"
    ],
    "wof:name":"Dunhams Food & Drink Inc",
    "wof:placetype":"venue"
},
  "geometry": {"coordinates":[-93.077304,44.894495],"type":"Point"}
}