{
  "type": "Feature",
  "properties": {
    "addr:full":"608 W Main St Perham MN 56573",
    "addr:housenumber":"608",
    "addr:postcode":"56573",
    "addr:street":"W Main St",
    "iso:country":"US",
    "sg:address":"608 W Main St",
    "sg:city":"Perham",
    "sg:classifiers":[
        {
            "category":"Retail",
            "subcategory":"Animal Services",
            "type":"Services"
        }
    ],
    "sg:phone":"+1 218 346 4269",
    "sg:postcode":"56573",
    "sg:province":"MN",
    "sg:tags":[
        "pet",
        "grooming",
        "washing"
    ],
    "wof:name":"Main Street Grooming",
    "wof:placetype":"venue"
},
  "geometry": {"coordinates":[-95.579716,46.598199],"type":"Point"}
}