{
  "type": "Feature",
  "properties": {
    "addr:full":"2530 Xenium Ln N Ste 100 Minneapolis MN 55441",
    "addr:housenumber":"2530",
    "addr:postcode":"55441",
    "addr:street":"Xenium Ln N Ste 100",
    "iso:country":"US",
    "sg:address":"2530 Xenium Ln N Ste 100",
    "sg:city":"Minneapolis",
    "sg:classifiers":[
        {
            "category":"Recreation",
            "subcategory":"Amusement Park",
            "type":"Entertainment"
        },
        {
            "category":"Recreation",
            "subcategory":"Picnic Area",
            "type":"Entertainment"
        }
    ],
    "sg:phone":"+1 763 577 9990",
    "sg:postcode":"55441",
    "sg:province":"MN",
    "sg:tags":[
        "equipment",
        "ride",
        "place",
        "arcade"
    ],
    "wof:name":"Acceleration Northwest",
    "wof:placetype":"venue"
},
  "geometry": {"coordinates":[-93.45129799999999,45.007491],"type":"Point"}
}