{
  "type": "Feature",
  "properties": {
    "iso:country":"US",
    "sg:address":"911 18th St N",
    "sg:city":"Saint Cloud",
    "sg:classifiers":[
        {
            "category":"Professional",
            "subcategory":"Accounting & Tax Preparation",
            "type":"Services"
        }
    ],
    "sg:phone":"+1 320 203 5522",
    "sg:postcode":"56303",
    "sg:province":"MN",
    "wof:name":"Deborah A Ramsdell",
    "wof:placetype":"venue"
},
  "geometry": {"coordinates":[-94.172197,45.582085],"type":"Point"}
}