{
  "type": "Feature",
  "properties": {
    "iso:country":"US",
    "sg:address":"4801 W 50th St",
    "sg:city":"Edina",
    "sg:classifiers":[
        {
            "category":"Government",
            "subcategory":"Police Station",
            "type":"Public Place"
        }
    ],
    "sg:phone":"+1 952 826 1600",
    "sg:postcode":"55424",
    "sg:province":"MN",
    "sg:tags":[
        "department"
    ],
    "sg:website":"www.ci.edina.mn.us",
    "wof:name":"Edina Police Dept",
    "wof:placetype":"venue"
},
  "geometry": {"coordinates":[-93.34760799999999,44.911558],"type":"Point"}
}