{
  "type": "Feature",
  "properties": {
    "iso:country":"US",
    "sg:address":"8537 Braxton Dr",
    "sg:city":"Eden Prairie",
    "sg:classifiers":[
        {
            "category":"Banks & Credit Unions",
            "subcategory":"Financial Services",
            "type":"Services"
        }
    ],
    "sg:phone":"+1 952 949 3545",
    "sg:postcode":"55347",
    "sg:province":"MN",
    "sg:tags":[
        "investor"
    ],
    "wof:name":"Babes In Bucks Investment",
    "wof:placetype":"venue"
},
  "geometry": {"coordinates":[-93.49035499999999,44.848577],"type":"Point"}
}