{
  "type": "Feature",
  "properties": {
    "iso:country":"US",
    "sg:address":"1130 N River Dr",
    "sg:city":"Mankato",
    "sg:classifiers":[
        {
            "category":"Autos & Motor Vehicles",
            "subcategory":"Automobile Sales",
            "type":"Retail Goods"
        }
    ],
    "sg:phone":"+1 507 345 1267",
    "sg:postcode":"56003",
    "sg:province":"MN",
    "sg:tags":[
        "car",
        "used",
        "dealer"
    ],
    "wof:name":"Blackman Motors",
    "wof:placetype":"venue"
},
  "geometry": {"coordinates":[-94.007671,44.182075],"type":"Point"}
}