{
  "type": "Feature",
  "properties": {
    "iso:country":"US",
    "sg:address":"100 Co Rd 63 NE",
    "sg:city":"Parkers Prairie",
    "sg:classifiers":[
        {
            "category":"Farming",
            "subcategory":"Dairy Farm",
            "type":"Manufacturing & Wholesale Goods"
        }
    ],
    "sg:phone":"+1 218 943 1211",
    "sg:postcode":"56361",
    "sg:province":"MN",
    "wof:name":"Grothen Brothers",
    "wof:placetype":"venue"
},
  "geometry": {"coordinates":[-95.37353,46.093227],"type":"Point"}
}