{
  "type": "Feature",
  "properties": {
    "addr:full":"6200 Excelsior Blvd Ste 104 Minneapolis MN 55416",
    "addr:housenumber":"6200",
    "addr:postcode":"55416",
    "addr:street":"Excelsior Blvd Ste 104",
    "iso:country":"US",
    "sg:address":"6200 Excelsior Blvd Ste 104",
    "sg:city":"Minneapolis",
    "sg:classifiers":[
        {
            "category":"Banks & Credit Unions",
            "subcategory":"Financial Services",
            "type":"Services"
        }
    ],
    "sg:phone":"+1 952 920 9201",
    "sg:postcode":"55416",
    "sg:province":"MN",
    "sg:tags":[
        "broker",
        "mortgage"
    ],
    "wof:name":"Meridian Residential Mortgage Inc",
    "wof:placetype":"venue"
},
  "geometry": {"coordinates":[-93.35790299999999,44.9277],"type":"Point"}
}