{
  "type": "Feature",
  "properties": {
    "iso:country":"US",
    "sg:address":"1935 Beam Ave",
    "sg:city":"Saint Paul",
    "sg:classifiers":[
        {
            "category":"Cinema",
            "subcategory":"Movie Rental",
            "type":"Entertainment"
        }
    ],
    "sg:phone":"+1 651 773 8363",
    "sg:postcode":"55109",
    "sg:province":"MN",
    "sg:tags":[
        "video",
        "store"
    ],
    "wof:name":"Blockbuster",
    "wof:placetype":"venue"
},
  "geometry": {"coordinates":[-93.023909,45.028084],"type":"Point"}
}