{
  "type": "Feature",
  "properties": {
    "iso:country":"US",
    "sg:address":"4110 W Superior St",
    "sg:city":"Duluth",
    "sg:classifiers":[
        {
            "category":"Manufacturing",
            "subcategory":"Tools & Machinery",
            "type":"Manufacturing & Wholesale Goods"
        }
    ],
    "sg:phone":"+1 218 624 3611",
    "sg:postcode":"55807",
    "sg:province":"MN",
    "sg:tags":[
        "machine",
        "shop",
        "job"
    ],
    "wof:name":"Kramer and Moen Machine Co",
    "wof:placetype":"venue"
},
  "geometry": {"coordinates":[-92.151627,46.748253],"type":"Point"}
}