{
  "type": "Feature",
  "properties": {
    "iso:country":"US",
    "sg:address":"1141 Chestnut St",
    "sg:city":"Fairmont",
    "sg:classifiers":[
        {
            "category":"Social Services",
            "type":"Services"
        }
    ],
    "sg:phone":"+1 507 238 1822",
    "sg:postcode":"56031",
    "sg:province":"MN",
    "sg:tags":[
        "organization",
        "welfare"
    ],
    "wof:name":"Rem Heartland Inc",
    "wof:placetype":"venue"
},
  "geometry": {"coordinates":[-94.448424,43.641382],"type":"Point"}
}