{
  "type": "Feature",
  "properties": {
    "addr:full":"1056 Sylvandale Rd Saint Paul MN 55118",
    "addr:housenumber":"1056",
    "addr:postcode":"55118",
    "addr:street":"Sylvandale Rd",
    "iso:country":"US",
    "sg:address":"1056 Sylvandale Rd",
    "sg:city":"Saint Paul",
    "sg:classifiers":[
        {
            "category":"Home & Garden",
            "subcategory":"Furniture",
            "type":"Retail Goods"
        }
    ],
    "sg:phone":"+1 651 457 8410",
    "sg:postcode":"55118",
    "sg:province":"MN",
    "sg:tags":[
        "household",
        "appliance",
        "carpet"
    ],
    "wof:name":"Northern Furniture Co",
    "wof:placetype":"venue"
},
  "geometry": {"coordinates":[-93.116777,44.913239],"type":"Point"}
}