{
  "type": "Feature",
  "properties": {
    "addr:full":"2001 29th Ave SE Austin MN 55912",
    "addr:housenumber":"2001",
    "addr:postcode":"55912",
    "addr:street":"29Th Ave Se",
    "iso:country":"US",
    "sg:address":"2001 29th Ave SE",
    "sg:city":"Austin",
    "sg:classifiers":[
        {
            "category":"Building & Trades",
            "subcategory":"Electrical",
            "type":"Services"
        },
        {
            "category":"Wholesale",
            "subcategory":"Electrical",
            "type":"Manufacturing & Wholesale Goods"
        }
    ],
    "sg:phone":"+1 507 433 9650",
    "sg:postcode":"55912",
    "sg:province":"MN",
    "sg:tags":[
        "sound",
        "burglar",
        "installs",
        "alarm",
        "system",
        "equipment"
    ],
    "wof:name":"Austin Communications Center",
    "wof:placetype":"venue"
},
  "geometry": {"coordinates":[-92.94151599999999,43.637827],"type":"Point"}
}