{
  "type": "Feature",
  "properties": {
    "iso:country":"US",
    "sg:address":"1557 Coon Rapids Blvd NW",
    "sg:city":"Coon Rapids",
    "sg:classifiers":[
        {
            "category":"Organizations",
            "subcategory":"Non-profit Organization",
            "type":"Services"
        }
    ],
    "sg:phone":"+1 763 754 8606",
    "sg:postcode":"55433",
    "sg:province":"MN",
    "sg:tags":[
        "information",
        "alcoholism",
        "treatment"
    ],
    "wof:name":"Alcoholics Anonymous",
    "wof:placetype":"venue"
},
  "geometry": {"coordinates":[-93.307326,45.155274],"type":"Point"}
}