{
  "type": "Feature",
  "properties": {
    "iso:country":"US",
    "sg:address":"12380 Ivanhoe Way",
    "sg:city":"Hastings",
    "sg:classifiers":[
        {
            "category":"Professional",
            "subcategory":"Employment Agencies",
            "type":"Services"
        }
    ],
    "sg:phone":"+1 651 437 5270",
    "sg:postcode":"55033",
    "sg:province":"MN",
    "wof:name":"Whiteford & Associates",
    "wof:placetype":"venue"
},
  "geometry": {"coordinates":[-92.904931,44.771568],"type":"Point"}
}