{
  "type": "Feature",
  "properties": {
    "addr:full":"37371 State Hwy 111 Nicollet MN 56074",
    "addr:housenumber":"37371",
    "addr:postcode":"56074",
    "addr:street":"State Hwy 111",
    "iso:country":"US",
    "sg:address":"37371 State Hwy 111",
    "sg:city":"Nicollet",
    "sg:phone":"+1 507 246 5240",
    "sg:postcode":"56074",
    "sg:province":"MN",
    "sg:tags":[
        "farm",
        "corn",
        "soybean"
    ],
    "wof:name":"Rachel Schott",
    "wof:placetype":"venue"
},
  "geometry": {"coordinates":[-94.19025999999999,44.405474],"type":"Point"}
}