{
  "type": "Feature",
  "properties": {
    "iso:country":"US",
    "sg:address":"628 Cortland Ln SW",
    "sg:city":"Rochester",
    "sg:classifiers":[
        {
            "category":"Building & Trades",
            "subcategory":"Pest Control",
            "type":"Services"
        }
    ],
    "sg:phone":"+1 507 289 2869",
    "sg:postcode":"55902",
    "sg:province":"MN",
    "wof:name":"All-Pest Exterminating Co",
    "wof:placetype":"venue"
},
  "geometry": {"coordinates":[-92.472595,43.99167],"type":"Point"}
}