{
  "type": "Feature",
  "properties": {
    "iso:country":"US",
    "sg:address":"2515 8th St S",
    "sg:city":"Moorhead",
    "sg:classifiers":[
        {
            "category":"Shopping",
            "subcategory":"Discount & Variety Stores",
            "type":"Retail Goods"
        }
    ],
    "sg:phone":"+1 218 287 9052",
    "sg:postcode":"56560",
    "sg:province":"MN",
    "sg:tags":[
        "merchandise",
        "general"
    ],
    "wof:name":"Dollar Etc",
    "wof:placetype":"venue"
},
  "geometry": {"coordinates":[-96.76831199999999,46.849212],"type":"Point"}
}