{
  "type": "Feature",
  "properties": {
    "iso:country":"US",
    "sg:address":"805 Kaywood Dr",
    "sg:city":"Park Rapids",
    "sg:classifiers":[
        {
            "category":"Building & Trades",
            "subcategory":"Construction",
            "type":"Services"
        }
    ],
    "sg:phone":"+1 218 732 4151",
    "sg:postcode":"56470",
    "sg:province":"MN",
    "sg:tags":[
        "ready",
        "concrete",
        "contractor",
        "mfg"
    ],
    "wof:name":"Douglas Dickinson Contractor",
    "wof:placetype":"venue"
},
  "geometry": {"coordinates":[-95.047471,46.932714],"type":"Point"}
}