{
  "type": "Feature",
  "properties": {
    "addr:full":"6101 Kaymar Dr Minneapolis MN 55436",
    "addr:housenumber":"6101",
    "addr:postcode":"55436",
    "addr:street":"Kaymar Dr",
    "iso:country":"US",
    "sg:address":"6101 Kaymar Dr",
    "sg:city":"Minneapolis",
    "sg:classifiers":[
        {
            "category":"Animal Shelter",
            "type":"Public Place"
        }
    ],
    "sg:phone":"+1 952 820 8174",
    "sg:postcode":"55436",
    "sg:province":"MN",
    "sg:tags":[
        "wildlife",
        "refuge"
    ],
    "sg:website":"http://www.ducks.org",
    "wof:name":"Ducks Unlimited, Inc.",
    "wof:placetype":"venue"
},
  "geometry": {"coordinates":[-93.379288,44.90139],"type":"Point"}
}