{
  "type": "Feature",
  "properties": {
    "addr:full":"8055 State Hwy 55 Rockford MN 55373",
    "addr:housenumber":"8055",
    "addr:postcode":"55373",
    "addr:street":"State Hwy 55",
    "iso:country":"US",
    "sg:address":"8055 State Hwy 55",
    "sg:city":"Rockford",
    "sg:classifiers":[
        {
            "category":"Building & Trades",
            "subcategory":"Electrical",
            "type":"Services"
        }
    ],
    "sg:phone":"+1 763 477 0010",
    "sg:postcode":"55373",
    "sg:province":"MN",
    "sg:tags":[
        "electrical",
        "electric",
        "contractor"
    ],
    "wof:name":"Vista Electric  Inc",
    "wof:placetype":"venue"
},
  "geometry": {"coordinates":[-93.718649,45.079538],"type":"Point"}
}