{
  "type": "Feature",
  "properties": {
    "addr:full":"511 2nd Ave Erskine MN 56535",
    "addr:housenumber":"511",
    "addr:postcode":"56535",
    "addr:street":"2Nd Ave",
    "iso:country":"US",
    "sg:address":"511 2nd Ave",
    "sg:city":"Erskine",
    "sg:classifiers":[
        {
            "category":"Building & Trades",
            "subcategory":"Landscaping Services",
            "type":"Services"
        }
    ],
    "sg:phone":"+1 218 687 2500",
    "sg:postcode":"56535",
    "sg:province":"MN",
    "wof:name":"Oses Construction & Lawn Serv",
    "wof:placetype":"venue"
},
  "geometry": {"coordinates":[-96.015367,47.660663],"type":"Point"}
}