{
  "type": "Feature",
  "properties": {
    "iso:country":"US",
    "sg:address":"4729 Martin Rd",
    "sg:city":"Duluth",
    "sg:classifiers":[
        {
            "category":"Freight",
            "type":"Transportation"
        }
    ],
    "sg:phone":"+1 218 390 4662",
    "sg:postcode":"55803",
    "sg:province":"MN",
    "sg:tags":[
        "commercial",
        "storage"
    ],
    "wof:name":"Sorlie Acoustics Storage",
    "wof:placetype":"venue"
},
  "geometry": {"coordinates":[-92.17661699999999,46.865581],"type":"Point"}
}