{
  "type": "Feature",
  "properties": {
    "addr:full":"1910 W Co Rd C Roseville MN 55113",
    "addr:housenumber":"1910",
    "addr:postcode":"55113",
    "addr:street":"W Co Rd",
    "iso:country":"US",
    "sg:address":"1910 W Co Rd C",
    "sg:city":"Roseville",
    "sg:phone":"+1 651 433 2663",
    "sg:postcode":"55113",
    "sg:province":"MN",
    "sg:tags":[
        "oil"
    ],
    "wof:name":"Diesel Dogs Fuel Svc",
    "wof:placetype":"venue"
},
  "geometry": {"coordinates":[-93.181076,45.021022],"type":"Point"}
}