{
  "type": "Feature",
  "properties": {
    "addr:full":"2650 Hwy 12 E Willmar MN 56201",
    "addr:housenumber":"2650",
    "addr:postcode":"56201",
    "addr:street":"Hwy 12 E",
    "iso:country":"US",
    "sg:address":"2650 Hwy 12 E",
    "sg:city":"Willmar",
    "sg:classifiers":[
        {
            "category":"Building & Trades",
            "subcategory":"Construction",
            "type":"Services"
        }
    ],
    "sg:phone":"+1 320 231 2018",
    "sg:postcode":"56201",
    "sg:province":"MN",
    "sg:tags":[
        "excavating",
        "contractor"
    ],
    "wof:name":"Vreeman Construction Inc",
    "wof:placetype":"venue"
},
  "geometry": {"coordinates":[-95.00751700000001,45.124924],"type":"Point"}
}