{
  "type": "Feature",
  "properties": {
    "iso:country":"US",
    "sg:address":"1650 W 82nd St",
    "sg:city":"Bloomington",
    "sg:classifiers":[
        {
            "category":"Restaurant",
            "type":"Food & Drink"
        }
    ],
    "sg:phone":"+1 952 885 5826",
    "sg:postcode":"55431",
    "sg:province":"MN",
    "wof:name":"Southpoint Express",
    "wof:placetype":"venue"
},
  "geometry": {"coordinates":[-93.30101500000001,44.855277],"type":"Point"}
}