{
  "type": "Feature",
  "properties": {
    "iso:country":"US",
    "sg:address":"4041 Linden Hills Blvd",
    "sg:city":"Minneapolis",
    "sg:classifiers":[
        {
            "category":"Health Services",
            "subcategory":"Chiropractor",
            "type":"Services"
        }
    ],
    "sg:phone":"+1 612 925 4537",
    "sg:postcode":"55410",
    "sg:province":"MN",
    "wof:name":"Steven R Pierson DC",
    "wof:placetype":"venue"
},
  "geometry": {"coordinates":[-93.31127600000001,44.928128],"type":"Point"}
}