{
  "type": "Feature",
  "properties": {
    "iso:country":"US",
    "sg:address":"5414 Xenia Ave N",
    "sg:city":"Minneapolis",
    "sg:classifiers":[
        {
            "category":"Building & Trades",
            "subcategory":"Construction",
            "type":"Services"
        }
    ],
    "sg:phone":"+1 612 220 8418",
    "sg:postcode":"55429",
    "sg:province":"MN",
    "sg:tags":[
        "house"
    ],
    "wof:name":"New Century Construction",
    "wof:placetype":"venue"
},
  "geometry": {"coordinates":[-93.35252199999999,45.052064],"type":"Point"}
}