{
  "type": "Feature",
  "properties": {
    "iso:country":"US",
    "sg:address":"13531 Balsam Ln N",
    "sg:city":"Dayton",
    "sg:classifiers":[
        {
            "category":"Retail",
            "subcategory":"Auto Repair",
            "type":"Services"
        }
    ],
    "sg:phone":"+1 763 427 9821",
    "sg:postcode":"55327",
    "sg:province":"MN",
    "sg:tags":[
        "repairing",
        "automobile"
    ],
    "wof:name":"Huttner Enterprises Inc",
    "wof:placetype":"venue"
},
  "geometry": {"coordinates":[-93.42595799999999,45.199474],"type":"Point"}
}