{
  "type": "Feature",
  "properties": {
    "addr:full":"406 Belgrade Ave Mankato MN 56003",
    "addr:housenumber":"406",
    "addr:postcode":"56003",
    "addr:street":"Belgrade Ave",
    "iso:country":"US",
    "sg:address":"406 Belgrade Ave",
    "sg:city":"Mankato",
    "sg:classifiers":[
        {
            "category":"Shopping",
            "subcategory":"Pharmacy",
            "type":"Retail Goods"
        }
    ],
    "sg:phone":"+1 507 387 6521",
    "sg:postcode":"56003",
    "sg:province":"MN",
    "wof:name":"Medicine Shoppe",
    "wof:placetype":"venue"
},
  "geometry": {"coordinates":[-94.01130999999999,44.170183],"type":"Point"}
}