{
  "type": "Feature",
  "properties": {
    "iso:country":"US",
    "sg:address":"3300 Richmond Alcove",
    "sg:city":"Saint Paul",
    "sg:classifiers":[
        {
            "category":"Real Estate",
            "subcategory":"Real Estate Agent",
            "type":"Services"
        }
    ],
    "sg:phone":"+1 651 730 4570",
    "sg:postcode":"55129",
    "sg:province":"MN",
    "wof:name":"Minnesota Real Solut",
    "wof:placetype":"venue"
},
  "geometry": {"coordinates":[-92.898719,44.901222],"type":"Point"}
}