{
  "type": "Feature",
  "properties": {
    "addr:full":"83 10th St S Minneapolis MN 55403",
    "addr:housenumber":"83",
    "addr:postcode":"55403",
    "addr:street":"10Th St S",
    "iso:country":"US",
    "sg:address":"83 10th St S",
    "sg:city":"Minneapolis",
    "sg:classifiers":[
        {
            "category":"Professional",
            "subcategory":"Lawyer & Legal Services",
            "type":"Services"
        },
        {
            "category":"Real Estate",
            "subcategory":"Real Estate Operator",
            "type":"Services"
        }
    ],
    "sg:phone":"+1 612 338 4759",
    "sg:postcode":"55403",
    "sg:province":"MN",
    "sg:tags":[
        "building",
        "attorney",
        "nonresidential"
    ],
    "wof:name":"Siegel Properties",
    "wof:placetype":"venue"
},
  "geometry": {"coordinates":[-93.27332199999999,44.973411],"type":"Point"}
}