{
  "type": "Feature",
  "properties": {
    "iso:country":"US",
    "sg:address":"2294 240th Ave",
    "sg:city":"Mora",
    "sg:classifiers":[
        {
            "category":"Manufacturing",
            "subcategory":"Printing",
            "type":"Manufacturing & Wholesale Goods"
        }
    ],
    "sg:phone":"+1 320 679 1095",
    "sg:postcode":"55051",
    "sg:province":"MN",
    "sg:tags":[
        "commercial"
    ],
    "wof:name":"Larrys Printing",
    "wof:placetype":"venue"
},
  "geometry": {"coordinates":[-93.24737399999999,45.933557],"type":"Point"}
}