{
  "type": "Feature",
  "properties": {
    "addr:full":"10631 James Cir Minneapolis MN 55431",
    "addr:housenumber":"10631",
    "addr:postcode":"55431",
    "addr:street":"James Cir",
    "iso:country":"US",
    "sg:address":"10631 James Cir",
    "sg:city":"Minneapolis",
    "sg:classifiers":[
        {
            "category":"Real Estate",
            "subcategory":"Architect",
            "type":"Services"
        }
    ],
    "sg:phone":"+1 952 881 8060",
    "sg:postcode":"55431",
    "sg:province":"MN",
    "sg:tags":[
        "design",
        "golf",
        "architectural",
        "course"
    ],
    "wof:name":"Don Herfort Inc",
    "wof:placetype":"venue"
},
  "geometry": {"coordinates":[-93.30057499999999,44.810263],"type":"Point"}
}