{
  "type": "Feature",
  "properties": {
    "iso:country":"US",
    "sg:address":"1081 395th St",
    "sg:city":"Isle",
    "sg:classifiers":[
        {
            "category":"Building & Trades",
            "subcategory":"Construction",
            "type":"Services"
        }
    ],
    "sg:phone":"+1 320 676 3386",
    "sg:postcode":"56342",
    "sg:province":"MN",
    "sg:tags":[
        "water",
        "well",
        "drilling"
    ],
    "wof:name":"A & M Drilling",
    "wof:placetype":"venue"
},
  "geometry": {"coordinates":[-93.436155,46.118099],"type":"Point"}
}