{
  "type": "Feature",
  "properties": {
    "addr:full":"34 17th Ave NW Rochester MN 55901",
    "addr:housenumber":"34",
    "addr:postcode":"55901",
    "addr:street":"17Th Ave Nw",
    "iso:country":"US",
    "sg:address":"34 17th Ave NW",
    "sg:city":"Rochester",
    "sg:classifiers":[
        {
            "category":"Restaurant",
            "type":"Food & Drink"
        }
    ],
    "sg:phone":"+1 507 281 1813",
    "sg:postcode":"55901",
    "sg:province":"MN",
    "sg:tags":[
        "eating"
    ],
    "wof:name":"Sky Dragon Buffet",
    "wof:placetype":"venue"
},
  "geometry": {"coordinates":[-92.487567,44.02375],"type":"Point"}
}