{
  "type": "Feature",
  "properties": {
    "iso:country":"US",
    "sg:address":"10161 Pleasure Creek Pkwy E",
    "sg:city":"Minneapolis",
    "sg:classifiers":[
        {
            "category":"Manufacturing",
            "subcategory":"Electronics",
            "type":"Manufacturing & Wholesale Goods"
        }
    ],
    "sg:phone":"+1 763 717 9972",
    "sg:postcode":"55434",
    "sg:province":"MN",
    "sg:tags":[
        "equipment",
        "mfg",
        "communication"
    ],
    "wof:name":"White Glove Communication Inc",
    "wof:placetype":"venue"
},
  "geometry": {"coordinates":[-93.25407199999999,45.153434],"type":"Point"}
}