{
  "type": "Feature",
  "properties": {
    "addr:full":"1260 Lincoln Ter Minneapolis MN 55421",
    "addr:housenumber":"1260",
    "addr:postcode":"55421",
    "addr:street":"Lincoln Ter",
    "iso:country":"US",
    "sg:address":"1260 Lincoln Ter",
    "sg:city":"Minneapolis",
    "sg:classifiers":[
        {
            "category":"Wholesale",
            "subcategory":"Computers",
            "type":"Manufacturing & Wholesale Goods"
        }
    ],
    "sg:phone":"+1 763 574 0378",
    "sg:postcode":"55421",
    "sg:province":"MN",
    "sg:tags":[
        "co",
        "related"
    ],
    "wof:name":"Applications Research Tech",
    "wof:placetype":"venue"
},
  "geometry": {"coordinates":[-93.24404,45.057573],"type":"Point"}
}