{
  "type": "Feature",
  "properties": {
    "addr:full":"10872 143rd Ave Becker MN 55308",
    "addr:housenumber":"10872",
    "addr:postcode":"55308",
    "addr:street":"143Rd Ave",
    "iso:country":"US",
    "sg:address":"10872 143rd Ave",
    "sg:city":"Becker",
    "sg:classifiers":[
        {
            "category":"Education",
            "subcategory":"Dance Studio",
            "type":"Public Place"
        }
    ],
    "sg:phone":"+1 763 261 2919",
    "sg:postcode":"55308",
    "sg:province":"MN",
    "wof:name":"Starz Dance Studio",
    "wof:placetype":"venue"
},
  "geometry": {"coordinates":[-93.86438699999999,45.41417],"type":"Point"}
}