{
  "type": "Feature",
  "properties": {
    "addr:full":"744 Fuller Ave Saint Paul MN 55104",
    "addr:housenumber":"744",
    "addr:postcode":"55104",
    "addr:street":"Fuller Ave",
    "iso:country":"US",
    "sg:address":"744 Fuller Ave",
    "sg:city":"Saint Paul",
    "sg:classifiers":[
        {
            "category":"Banks & Credit Unions",
            "subcategory":"Bank",
            "type":"Services"
        }
    ],
    "sg:phone":"+1 651 292 1384",
    "sg:postcode":"55104",
    "sg:province":"MN",
    "sg:tags":[
        "state"
    ],
    "wof:name":"Kemba Company",
    "wof:placetype":"venue"
},
  "geometry": {"coordinates":[-93.133089,44.953847],"type":"Point"}
}