{
  "type": "Feature",
  "properties": {
    "addr:full":"580 Cokato St W Cokato MN 55321",
    "addr:housenumber":"580",
    "addr:postcode":"55321",
    "addr:street":"Cokato St W",
    "iso:country":"US",
    "sg:address":"580 Cokato St W",
    "sg:city":"Cokato",
    "sg:classifiers":[
        {
            "category":"Personal",
            "type":"Services"
        }
    ],
    "sg:phone":"+1 320 286 2145",
    "sg:postcode":"55321",
    "sg:province":"MN",
    "wof:name":"Asplin Kirk Oil Co Inc",
    "wof:placetype":"venue"
},
  "geometry": {"coordinates":[-94.199212,45.079945],"type":"Point"}
}