{
  "type": "Feature",
  "properties": {
    "iso:country":"US",
    "sg:address":"516 S Pokegama Ave",
    "sg:city":"Grand Rapids",
    "sg:classifiers":[
        {
            "category":"Government",
            "subcategory":"Office",
            "type":"Public Place"
        }
    ],
    "sg:phone":"+1 218 326 8584",
    "sg:postcode":"55744",
    "sg:province":"MN",
    "sg:tags":[
        "federal",
        "planning",
        "dev"
    ],
    "wof:name":"USDA Rural Development",
    "wof:placetype":"venue"
},
  "geometry": {"coordinates":[-93.52847199999999,47.2263],"type":"Point"}
}