{
  "type": "Feature",
  "properties": {
    "iso:country":"US",
    "sg:address":"328 5th Ave SE",
    "sg:city":"East Grand Forks",
    "sg:classifiers":[
        {
            "category":"Building & Trades",
            "subcategory":"Construction",
            "type":"Services"
        }
    ],
    "sg:phone":"+1 701 780 8450",
    "sg:postcode":"56721",
    "sg:province":"MN",
    "sg:tags":[
        "contractor"
    ],
    "wof:name":"D R Hilde Drywall",
    "wof:placetype":"venue"
},
  "geometry": {"coordinates":[-97.013856,47.916881],"type":"Point"}
}