{
  "type": "Feature",
  "properties": {
    "addr:full":"990 State Hwy 7 Excelsior MN 55331",
    "addr:housenumber":"990",
    "addr:postcode":"55331",
    "addr:street":"State Hwy 7",
    "iso:country":"US",
    "sg:address":"990 State Hwy 7",
    "sg:city":"Excelsior",
    "sg:classifiers":[
        {
            "category":"Social Services",
            "subcategory":"Child Care",
            "type":"Services"
        }
    ],
    "sg:phone":"+1 952 474 7489",
    "sg:postcode":"55331",
    "sg:province":"MN",
    "sg:tags":[
        "provider"
    ],
    "wof:name":"Robyn Lukes",
    "wof:placetype":"venue"
},
  "geometry": {"coordinates":[-93.643204,44.882473],"type":"Point"}
}