{
  "type": "Feature",
  "properties": {
    "iso:country":"US",
    "sg:address":"8854 13th Ave E",
    "sg:city":"Shakopee",
    "sg:classifiers":[
        {
            "category":"Building & Trades",
            "subcategory":"Construction",
            "type":"Services"
        }
    ],
    "sg:phone":"+1 952 233 1326",
    "sg:postcode":"55379",
    "sg:province":"MN",
    "sg:tags":[
        "blacktopping"
    ],
    "wof:name":"Richfield Quailty Blacktop",
    "wof:placetype":"venue"
},
  "geometry": {"coordinates":[-93.398932,44.782589],"type":"Point"}
}