{
  "type": "Feature",
  "properties": {
    "addr:full":"345 Main St S Renville MN 56284",
    "addr:housenumber":"345",
    "addr:postcode":"56284",
    "addr:street":"Main St S Renville",
    "iso:country":"US",
    "sg:address":"345 Main St S",
    "sg:city":"Renville",
    "sg:classifiers":[
        {
            "category":"Food & Beverages",
            "subcategory":"Liquor & Beverages",
            "type":"Retail Goods"
        }
    ],
    "sg:phone":"+1 320 329 3907",
    "sg:postcode":"56284",
    "sg:province":"MN",
    "wof:name":"Renville Municipal Liquor",
    "wof:placetype":"venue"
},
  "geometry": {"coordinates":[-95.211922,44.786911],"type":"Point"}
}