{
  "type": "Feature",
  "properties": {
    "iso:country":"US",
    "sg:address":"1132 81st St",
    "sg:city":"Pipestone",
    "sg:classifiers":[
        {
            "category":"Farming",
            "subcategory":"Livestock Farm",
            "type":"Manufacturing & Wholesale Goods"
        }
    ],
    "sg:phone":"+1 507 825 2040",
    "sg:postcode":"56164",
    "sg:province":"MN",
    "sg:tags":[
        "hog",
        "beef",
        "cash",
        "cattle",
        "or",
        "feedlot"
    ],
    "wof:name":"Shaffer Farms Inc",
    "wof:placetype":"venue"
},
  "geometry": {"coordinates":[-96.238274,43.96494],"type":"Point"}
}