{
  "type": "Feature",
  "properties": {
    "addr:full":"1727 170th Ave Luverne MN 56139",
    "addr:housenumber":"1727",
    "addr:postcode":"56139",
    "addr:street":"170Th Ave",
    "iso:country":"US",
    "sg:address":"1727 170th Ave",
    "sg:city":"Luverne",
    "sg:phone":"+1 507 283 8411",
    "sg:postcode":"56139",
    "sg:province":"MN",
    "sg:tags":[
        "farm",
        "corn"
    ],
    "wof:name":"Dave Remme",
    "wof:placetype":"venue"
},
  "geometry": {"coordinates":[-96.124548,44.105948],"type":"Point"}
}