{
  "type": "Feature",
  "properties": {
    "addr:full":"825 S 8th St Minneapolis MN 55404",
    "addr:housenumber":"825",
    "addr:postcode":"55404",
    "addr:street":"S 8Th St",
    "iso:country":"US",
    "sg:address":"825 S 8th St",
    "sg:city":"Minneapolis",
    "sg:classifiers":[
        {
            "category":"Shopping",
            "subcategory":"Pharmacy",
            "type":"Retail Goods"
        }
    ],
    "sg:phone":"+1 612 332 8500",
    "sg:postcode":"55404",
    "sg:province":"MN",
    "sg:tags":[
        "drugstore"
    ],
    "sg:website":"www.walgreens.com",
    "wof:name":"Walgreen Drug Stores",
    "wof:placetype":"venue"
},
  "geometry": {"coordinates":[-93.261893,44.971028],"type":"Point"}
}