{
  "type": "Feature",
  "properties": {
    "iso:country":"US",
    "sg:address":"307 E Lincoln Ave",
    "sg:city":"Olivia",
    "sg:classifiers":[
        {
            "category":"Retail",
            "subcategory":"Auto Repair",
            "type":"Services"
        }
    ],
    "sg:phone":"+1 320 523 2402",
    "sg:postcode":"56277",
    "sg:province":"MN",
    "sg:tags":[
        "automotive",
        "general"
    ],
    "wof:name":"Schultz Machine Shop",
    "wof:placetype":"venue"
},
  "geometry": {"coordinates":[-94.98070800000001,44.776465],"type":"Point"}
}