{
  "type": "Feature",
  "properties": {
    "addr:full":"8133 Wyoming Ave N Minneapolis MN 55445",
    "addr:housenumber":"8133",
    "addr:postcode":"55445",
    "addr:street":"Wyoming Ave N",
    "iso:country":"US",
    "sg:address":"8133 Wyoming Ave N",
    "sg:city":"Minneapolis",
    "sg:classifiers":[
        {
            "category":"Shopping",
            "subcategory":"Hobbies, Toys, & Games",
            "type":"Retail Goods"
        }
    ],
    "sg:phone":"+1 763 424 8998",
    "sg:postcode":"55445",
    "sg:province":"MN",
    "sg:tags":[
        "toy",
        "store"
    ],
    "wof:name":"Fj Toys",
    "wof:placetype":"venue"
},
  "geometry": {"coordinates":[-93.38636099999999,45.102256],"type":"Point"}
}