{
  "type": "Feature",
  "properties": {
    "addr:full":"4800 Diamond Ln Atwater MN 56209",
    "addr:housenumber":"4800",
    "addr:postcode":"56209",
    "addr:street":"Diamond Ln",
    "iso:country":"US",
    "sg:address":"4800 Diamond Ln",
    "sg:city":"Atwater",
    "sg:classifiers":[
        {
            "category":"Manufacturing",
            "subcategory":"Buildings",
            "type":"Manufacturing & Wholesale Goods"
        },
        {
            "category":"Building & Trades",
            "subcategory":"Construction",
            "type":"Services"
        }
    ],
    "sg:phone":"+1 320 974 8789",
    "sg:postcode":"56209",
    "sg:province":"MN",
    "sg:tags":[
        "home",
        "builder",
        "contractor"
    ],
    "wof:name":"Doug Losing Construction",
    "wof:placetype":"venue"
},
  "geometry": {"coordinates":[-94.836039,45.173463],"type":"Point"}
}