{
  "type": "Feature",
  "properties": {
    "addr:full":"1800 Louisiana Ave N Minneapolis MN 55427",
    "addr:housenumber":"1800",
    "addr:postcode":"55427",
    "addr:street":"Louisiana Ave N",
    "iso:country":"US",
    "sg:address":"1800 Louisiana Ave N",
    "sg:city":"Minneapolis",
    "sg:classifiers":[
        {
            "category":"Government",
            "subcategory":"Court House",
            "type":"Public Place"
        },
        {
            "category":"Professional",
            "subcategory":"Lawyer & Legal Services",
            "type":"Services"
        },
        {
            "category":"Government",
            "subcategory":"Office",
            "type":"Public Place"
        }
    ],
    "sg:phone":"+1 612 987 7821",
    "sg:postcode":"55427",
    "sg:province":"MN",
    "sg:tags":[
        "justice",
        "parish",
        "attorney",
        "government-county"
    ],
    "sg:website":"http://hstrial-DHedlund.homestead.com",
    "wof:name":"Elect Judge Hedlund to Minnesota Supreme Court",
    "wof:placetype":"venue"
},
  "geometry": {"coordinates":[-93.369659,44.998521],"type":"Point"}
}