{
  "type": "Feature",
  "properties": {
    "iso:country":"US",
    "sg:address":"750 Boone Ave N",
    "sg:city":"Minneapolis",
    "sg:classifiers":[
        {
            "category":"Professional",
            "subcategory":"Accounting & Tax Preparation",
            "type":"Services"
        }
    ],
    "sg:phone":"+1 763 746 4556",
    "sg:postcode":"55427",
    "sg:province":"MN",
    "sg:tags":[
        "return",
        "filing"
    ],
    "wof:name":"Global Tax Network",
    "wof:placetype":"venue"
},
  "geometry": {"coordinates":[-93.39024499999999,44.98823],"type":"Point"}
}