{
  "type": "Feature",
  "properties": {
    "addr:full":"11365 State Hwy 60 Wanamingo MN 55983",
    "addr:housenumber":"11365",
    "addr:postcode":"55983",
    "addr:street":"State Hwy 60 Wanamingo",
    "iso:country":"US",
    "sg:address":"11365 State Hwy 60",
    "sg:city":"Wanamingo",
    "sg:classifiers":[
        {
            "category":"Autos & Motor Vehicles",
            "subcategory":"Auto Supplies",
            "type":"Retail Goods"
        }
    ],
    "sg:phone":"+1 507 824 2479",
    "sg:postcode":"55983",
    "sg:province":"MN",
    "wof:name":"Bakers Tire Warehouse",
    "wof:placetype":"venue"
},
  "geometry": {"coordinates":[-92.805426,44.298064],"type":"Point"}
}