{
  "type": "Feature",
  "properties": {
    "iso:country":"US",
    "sg:address":"1437 119th Ln NW",
    "sg:city":"Minneapolis",
    "sg:classifiers":[
        {
            "category":"Building & Trades",
            "subcategory":"Electrical",
            "type":"Services"
        }
    ],
    "sg:phone":"+1 763 755 1740",
    "sg:postcode":"55448",
    "sg:province":"MN",
    "sg:tags":[
        "electrical",
        "merchandise",
        "contractor"
    ],
    "wof:name":"B & R Telephone Services Inc",
    "wof:placetype":"venue"
},
  "geometry": {"coordinates":[-93.303318,45.186766],"type":"Point"}
}