{
  "type": "Feature",
  "properties": {
    "addr:full":"7500 Pleasant Ave S Minneapolis MN 55423",
    "addr:housenumber":"7500",
    "addr:postcode":"55423",
    "addr:street":"Pleasant Ave S",
    "iso:country":"US",
    "sg:address":"7500 Pleasant Ave S",
    "sg:city":"Minneapolis",
    "sg:classifiers":[
        {
            "category":"Recreation",
            "type":"Entertainment"
        },
        {
            "category":"Social Services",
            "type":"Services"
        }
    ],
    "sg:phone":"+1 612 866 7848",
    "sg:postcode":"55423",
    "sg:province":"MN",
    "sg:tags":[
        "youth",
        "organization",
        "membership",
        "club",
        "center"
    ],
    "wof:name":"West Richfield Little League",
    "wof:placetype":"venue"
},
  "geometry": {"coordinates":[-93.28348699999999,44.865505],"type":"Point"}
}