{
  "type": "Feature",
  "properties": {
    "iso:country":"US",
    "sg:address":"1665 Pattison Rd",
    "sg:city":"St Cloud",
    "sg:classifiers":[
        {
            "category":"Organizations",
            "subcategory":"Labor Organization",
            "type":"Services"
        }
    ],
    "sg:phone":"+1 320 259 4949",
    "sg:postcode":"56303",
    "sg:province":"MN",
    "wof:name":"Letter Carriers Union NALC",
    "wof:placetype":"venue"
},
  "geometry": {"coordinates":[-94.239504,45.580749],"type":"Point"}
}