{
  "type": "Feature",
  "properties": {
    "addr:full":"1709 27th St S Moorhead MN 56560",
    "addr:housenumber":"1709",
    "addr:postcode":"56560",
    "addr:street":"27Th St S",
    "iso:country":"US",
    "sg:address":"1709 27th St S",
    "sg:city":"Moorhead",
    "sg:classifiers":[
        {
            "category":"Freight",
            "type":"Transportation"
        }
    ],
    "sg:phone":"+1 218 233 5237",
    "sg:postcode":"56560",
    "sg:province":"MN",
    "sg:tags":[
        "special"
    ],
    "wof:name":"U-Haul",
    "wof:placetype":"venue"
},
  "geometry": {"coordinates":[-96.73555500000001,46.8563],"type":"Point"}
}