{
  "type": "Feature",
  "properties": {
    "addr:full":"854 N Woodbridge St St Paul MN 55117",
    "addr:housenumber":"854",
    "addr:postcode":"55117",
    "addr:street":"N Woodbridge St",
    "iso:country":"US",
    "sg:address":"854 N Woodbridge St",
    "sg:city":"St Paul",
    "sg:classifiers":[
        {
            "category":"Organizations",
            "subcategory":"Religious Organization",
            "type":"Services"
        }
    ],
    "sg:phone":"+1 651 489 5618",
    "sg:postcode":"55117",
    "sg:province":"MN",
    "sg:tags":[
        "church"
    ],
    "wof:name":"St Marys Romanian Orthodox Chr",
    "wof:placetype":"venue"
},
  "geometry": {"coordinates":[-93.108411,44.967049],"type":"Point"}
}