{
  "type": "Feature",
  "properties": {
    "addr:full":"3025 Brooks Ln Wayzata MN 55391",
    "addr:housenumber":"3025",
    "addr:postcode":"55391",
    "addr:street":"Brooks Ln",
    "iso:country":"US",
    "sg:address":"3025 Brooks Ln",
    "sg:city":"Wayzata",
    "sg:classifiers":[
        {
            "category":"Real Estate",
            "subcategory":"Real Estate Agent",
            "type":"Services"
        }
    ],
    "sg:phone":"+1 952 471 1028",
    "sg:postcode":"55391",
    "sg:province":"MN",
    "wof:name":"Dolan Realty",
    "wof:placetype":"venue"
},
  "geometry": {"coordinates":[-93.60113,44.939387],"type":"Point"}
}