{
  "type": "Feature",
  "properties": {
    "iso:country":"US",
    "sg:address":"800 Lasalle Ave",
    "sg:city":"Minneapolis",
    "sg:classifiers":[
        {
            "category":"Professional",
            "subcategory":"Lawyer & Legal Services",
            "type":"Services"
        }
    ],
    "sg:phone":"+1 612 349 8400",
    "sg:postcode":"55403",
    "sg:province":"MN",
    "wof:name":"R K M C L L P",
    "wof:placetype":"venue"
},
  "geometry": {"coordinates":[-93.27530299999999,44.975546],"type":"Point"}
}