{
  "type": "Feature",
  "properties": {
    "addr:full":"1812 W Saint Germain St Saint Cloud MN 56301",
    "addr:housenumber":"1812",
    "addr:postcode":"56301",
    "addr:street":"W Saint Germain St",
    "iso:country":"US",
    "sg:address":"1812 W Saint Germain St",
    "sg:city":"Saint Cloud",
    "sg:classifiers":[
        {
            "category":"Shopping",
            "subcategory":"Gifts & Souvenirs",
            "type":"Retail Goods"
        }
    ],
    "sg:phone":"+1 320 253 5622",
    "sg:postcode":"56301",
    "sg:province":"MN",
    "sg:tags":[
        "equipment",
        "business"
    ],
    "wof:name":"Geyer Wedding & Party Store",
    "wof:placetype":"venue"
},
  "geometry": {"coordinates":[-94.17581,45.553599],"type":"Point"}
}