{
  "type": "Feature",
  "properties": {
    "iso:country":"US",
    "sg:address":"33236 Oakland Rd",
    "sg:city":"Freeport",
    "sg:classifiers":[
        {
            "category":"Farming",
            "subcategory":"Poultry Farm",
            "type":"Manufacturing & Wholesale Goods"
        }
    ],
    "sg:phone":"+1 320 837 5347",
    "sg:postcode":"56331",
    "sg:province":"MN",
    "sg:tags":[
        "chicken",
        "egg"
    ],
    "wof:name":"Schlangen Produce Inc",
    "wof:placetype":"venue"
},
  "geometry": {"coordinates":[-94.732508,45.610712],"type":"Point"}
}