{
  "type": "Feature",
  "properties": {
    "addr:full":"300 Prairie Center Dr Eden Prairie MN 55344",
    "addr:housenumber":"300",
    "addr:postcode":"55344",
    "addr:street":"Prairie Center Dr",
    "iso:country":"US",
    "sg:address":"300 Prairie Center Dr",
    "sg:city":"Eden Prairie",
    "sg:classifiers":[
        {
            "category":"Wholesale",
            "subcategory":"Computers",
            "type":"Manufacturing & Wholesale Goods"
        },
        {
            "category":"Professional",
            "subcategory":"Management & Consulting",
            "type":"Services"
        }
    ],
    "sg:phone":"+1 952 941 3422",
    "sg:postcode":"55344",
    "sg:province":"MN",
    "sg:tags":[
        "equipment",
        "program",
        "marketing"
    ],
    "wof:name":"Comtech Marketing Inc",
    "wof:placetype":"venue"
},
  "geometry": {"coordinates":[-93.435126,44.855992],"type":"Point"}
}