{
  "type": "Feature",
  "properties": {
    "iso:country":"US",
    "sg:address":"30 25th St SE",
    "sg:city":"Rochester",
    "sg:classifiers":[
        {
            "category":"Shopping",
            "subcategory":"Shoes",
            "type":"Retail Goods"
        }
    ],
    "sg:phone":"+1 507 286 1286",
    "sg:postcode":"55904",
    "sg:province":"MN",
    "sg:website":"www.famousfootwear.com",
    "wof:name":"Famous Footwear 29",
    "wof:placetype":"venue"
},
  "geometry": {"coordinates":[-92.461226,43.985422],"type":"Point"}
}