{
  "type": "Feature",
  "properties": {
    "addr:full":"1708 N 4th St Mankato MN 56001",
    "addr:housenumber":"1708",
    "addr:postcode":"56001",
    "addr:street":"N 4Th St",
    "iso:country":"US",
    "sg:address":"1708 N 4th St",
    "sg:city":"Mankato",
    "sg:classifiers":[
        {
            "category":"Professional",
            "type":"Services"
        }
    ],
    "sg:phone":"+1 507 625 2306",
    "sg:postcode":"56001",
    "sg:province":"MN",
    "wof:name":"Accents & More",
    "wof:placetype":"venue"
},
  "geometry": {"coordinates":[-93.982787,44.182362],"type":"Point"}
}