{
  "type": "Feature",
  "properties": {
    "addr:full":"301 W Hill St Comfrey MN 56019",
    "addr:housenumber":"301",
    "addr:postcode":"56019",
    "addr:street":"W Hill St",
    "iso:country":"US",
    "sg:address":"301 W Hill St",
    "sg:city":"Comfrey",
    "sg:phone":"+1 507 877 5500",
    "sg:postcode":"56019",
    "sg:province":"MN",
    "sg:tags":[
        "farm",
        "corn",
        "soybean"
    ],
    "wof:name":"Troy Toll",
    "wof:placetype":"venue"
},
  "geometry": {"coordinates":[-94.90877999999999,44.113975],"type":"Point"}
}