{
  "type": "Feature",
  "properties": {
    "addr:full":"2500 Cleveland Ave N Saint Paul MN 55113",
    "addr:housenumber":"2500",
    "addr:postcode":"55113",
    "addr:street":"Cleveland Ave N",
    "iso:country":"US",
    "sg:address":"2500 Cleveland Ave N",
    "sg:city":"Saint Paul",
    "sg:classifiers":[
        {
            "category":"Shopping",
            "subcategory":"Party Supplies",
            "type":"Retail Goods"
        }
    ],
    "sg:phone":"+1 651 631 4921",
    "sg:postcode":"55113",
    "sg:province":"MN",
    "wof:name":"Party America",
    "wof:placetype":"venue"
},
  "geometry": {"coordinates":[-93.18710299999999,45.016399],"type":"Point"}
}