{
  "type": "Feature",
  "properties": {
    "addr:full":"16575 Co Rd 48 Kimball MN 55353",
    "addr:housenumber":"16575;48",
    "addr:postcode":"55353",
    "addr:street":"Co Rd",
    "iso:country":"US",
    "sg:address":"16575 Co Rd 48",
    "sg:city":"Kimball",
    "sg:classifiers":[
        {
            "category":"Farming",
            "subcategory":"Farm",
            "type":"Manufacturing & Wholesale Goods"
        }
    ],
    "sg:phone":"+1 320 398 7308",
    "sg:postcode":"55353",
    "sg:province":"MN",
    "sg:tags":[
        "crop",
        "general"
    ],
    "wof:name":"Jerome Garding",
    "wof:placetype":"venue"
},
  "geometry": {"coordinates":[-94.353623,45.363156],"type":"Point"}
}