{
  "type": "Feature",
  "properties": {
    "addr:full":"7635 Edinborough Way Edina MN 55435",
    "addr:housenumber":"7635",
    "addr:postcode":"55435",
    "addr:street":"Edinborough Way",
    "iso:country":"US",
    "sg:address":"7635 Edinborough Way",
    "sg:city":"Edina",
    "sg:classifiers":[
        {
            "category":"Real Estate",
            "subcategory":"Real Estate Agent",
            "type":"Services"
        },
        {
            "category":"Real Estate",
            "subcategory":"Real Estate Operator",
            "type":"Services"
        }
    ],
    "sg:phone":"+1 952 838 3818",
    "sg:postcode":"55435",
    "sg:province":"MN",
    "sg:tags":[
        "condominium"
    ],
    "wof:name":"Edinborough Condominiums",
    "wof:placetype":"venue"
},
  "geometry": {"coordinates":[-93.323756,44.864315],"type":"Point"}
}