{
  "type": "Feature",
  "properties": {
    "addr:full":"9000 Hwy 10 NW Rice MN 56367",
    "addr:housenumber":"9000",
    "addr:postcode":"56367",
    "addr:street":"Hwy 10 Nw",
    "iso:country":"US",
    "sg:address":"9000 Hwy 10 NW",
    "sg:city":"Rice",
    "sg:classifiers":[
        {
            "category":"Shopping",
            "subcategory":"Bicycles & Sporting Goods",
            "type":"Retail Goods"
        }
    ],
    "sg:phone":"+1 320 259 8969",
    "sg:postcode":"56367",
    "sg:province":"MN",
    "sg:tags":[
        "equipment",
        "golf",
        "supply"
    ],
    "sg:website":"www.oakhillgolfclub.com",
    "wof:name":"Oak Hill Golf Club",
    "wof:placetype":"venue"
},
  "geometry": {"coordinates":[-94.171677,45.701039],"type":"Point"}
}