{
  "type": "Feature",
  "properties": {
    "iso:country":"US",
    "sg:address":"107 N 3rd St",
    "sg:city":"Waterville",
    "sg:classifiers":[
        {
            "category":"Wholesale",
            "subcategory":"Metals & Minerals",
            "type":"Manufacturing & Wholesale Goods"
        }
    ],
    "sg:phone":"+1 507 362 8088",
    "sg:postcode":"56096",
    "sg:province":"MN",
    "sg:tags":[
        "building",
        "prefabricated",
        "center",
        "mfg"
    ],
    "wof:name":"Bush Garden Works",
    "wof:placetype":"venue"
},
  "geometry": {"coordinates":[-93.566361,44.219841],"type":"Point"}
}