{
  "type": "Feature",
  "properties": {
    "iso:country":"US",
    "sg:address":"1570 Tower Blvd",
    "sg:city":"North Mankato",
    "sg:classifiers":[
        {
            "category":"Real Estate",
            "subcategory":"Developer",
            "type":"Services"
        }
    ],
    "sg:phone":"+1 507 625 9200",
    "sg:postcode":"56003",
    "sg:province":"MN",
    "wof:name":"Montag Development",
    "wof:placetype":"venue"
},
  "geometry": {"coordinates":[-94.043657,44.172257],"type":"Point"}
}