{
  "type": "Feature",
  "properties": {
    "addr:full":"7565 Mariner Dr Osseo MN 55311",
    "addr:housenumber":"7565",
    "addr:postcode":"55311",
    "addr:street":"Mariner Dr",
    "iso:country":"US",
    "sg:address":"7565 Mariner Dr",
    "sg:city":"Osseo",
    "sg:classifiers":[
        {
            "category":"Insurance",
            "subcategory":"Insurance Agent",
            "type":"Services"
        },
        {
            "category":"Insurance",
            "subcategory":"Hazard Insurance",
            "type":"Services"
        }
    ],
    "sg:phone":"+1 763 420 9107",
    "sg:postcode":"55311",
    "sg:province":"MN",
    "sg:tags":[
        "fire",
        "property",
        "casualty"
    ],
    "wof:name":"Indiana Insurance Company",
    "wof:placetype":"venue"
},
  "geometry": {"coordinates":[-93.46788599999999,45.092318],"type":"Point"}
}