{
  "type": "Feature",
  "properties": {
    "iso:country":"US",
    "sg:address":"3549 46th Ave S",
    "sg:city":"Minneapolis",
    "sg:classifiers":[
        {
            "category":"Professional",
            "subcategory":"Art Services",
            "type":"Services"
        }
    ],
    "sg:phone":"+1 612 724 4440",
    "sg:postcode":"55406",
    "sg:province":"MN",
    "sg:tags":[
        "commercial",
        "design"
    ],
    "wof:name":"Reed Susan Design",
    "wof:placetype":"venue"
},
  "geometry": {"coordinates":[-93.20756299999999,44.938797],"type":"Point"}
}