{
  "type": "Feature",
  "properties": {
    "iso:country":"US",
    "sg:address":"3137 122nd Ln NW",
    "sg:city":"Minneapolis",
    "sg:classifiers":[
        {
            "category":"Building & Trades",
            "subcategory":"Construction",
            "type":"Services"
        }
    ],
    "sg:phone":"+1 763 421 5334",
    "sg:postcode":"55433",
    "sg:province":"MN",
    "sg:tags":[
        "specialty",
        "contractor"
    ],
    "wof:name":"Magnum Earthworks, Inc.",
    "wof:placetype":"venue"
},
  "geometry": {"coordinates":[-93.347264,45.192634],"type":"Point"}
}