{
  "type": "Feature",
  "properties": {
    "iso:country":"US",
    "sg:address":"17 E Stark Rd",
    "sg:city":"Esko",
    "sg:classifiers":[
        {
            "category":"Building & Trades",
            "subcategory":"Construction",
            "type":"Services"
        }
    ],
    "sg:phone":"+1 218 879 7327",
    "sg:postcode":"55733",
    "sg:province":"MN",
    "sg:tags":[
        "house",
        "c",
        "hanging",
        "contractor"
    ],
    "wof:name":"Jobin Painting & Construction",
    "wof:placetype":"venue"
},
  "geometry": {"coordinates":[-92.363924,46.750065],"type":"Point"}
}