{
  "type": "Feature",
  "properties": {
    "iso:country":"US",
    "sg:address":"4638 Co Rd 11",
    "sg:city":"Pequot Lakes",
    "sg:classifiers":[
        {
            "category":"Sports & Exercise",
            "subcategory":"Gym",
            "type":"Entertainment"
        }
    ],
    "sg:phone":"+1 218 568 6060",
    "sg:postcode":"56472",
    "sg:province":"MN",
    "sg:tags":[
        "club",
        "health",
        "studio",
        "gymnasium"
    ],
    "wof:name":"It Figures Fitness Ctr",
    "wof:placetype":"venue"
},
  "geometry": {"coordinates":[-94.30459500000001,46.602983],"type":"Point"}
}