{
  "type": "Feature",
  "properties": {
    "addr:full":"751 Highland Rd Windom MN 56101",
    "addr:housenumber":"751",
    "addr:postcode":"56101",
    "addr:street":"Highland Rd",
    "iso:country":"US",
    "sg:address":"751 Highland Rd",
    "sg:city":"Windom",
    "sg:classifiers":[
        {
            "category":"Home & Garden",
            "subcategory":"Furniture",
            "type":"Retail Goods"
        }
    ],
    "sg:phone":"+1 507 831 4701",
    "sg:postcode":"56101",
    "sg:province":"MN",
    "sg:tags":[
        "product",
        "mfg"
    ],
    "wof:name":"Jims Custom Cabinets",
    "wof:placetype":"venue"
},
  "geometry": {"coordinates":[-95.12512099999999,43.864089],"type":"Point"}
}