{
  "type": "Feature",
  "properties": {
    "iso:country":"US",
    "sg:address":"7100 Wayzata Blvd",
    "sg:city":"Minneapolis",
    "sg:phone":"+1 763 545 7171",
    "sg:postcode":"55426",
    "sg:province":"MN",
    "wof:name":"Jim Lupient Auto Mall",
    "wof:placetype":"venue"
},
  "geometry": {"coordinates":[-93.376282,44.971588],"type":"Point"}
}