{
  "type": "Feature",
  "properties": {
    "addr:full":"17789 State 34 Park Rapids MN 56470",
    "addr:housenumber":"17789;34",
    "addr:postcode":"56470",
    "addr:street":"State",
    "iso:country":"US",
    "sg:address":"17789 State 34",
    "sg:city":"Park Rapids",
    "sg:classifiers":[
        {
            "category":"Restaurant",
            "type":"Food & Drink"
        }
    ],
    "sg:menulink":"http://www.allmenus.com/mn/henrietta/236756-goose-crossing/menu/",
    "sg:phone":"+1 218 732 2700",
    "sg:postcode":"56470",
    "sg:province":"MN",
    "sg:tags":[
        "american"
    ],
    "wof:name":"Goose Crossing",
    "wof:placetype":"venue"
},
  "geometry": {"coordinates":[-94.99622100000001,46.92951],"type":"Point"}
}