{
  "type": "Feature",
  "properties": {
    "addr:full":"109 W 2nd Ave Ellsworth MN 56129",
    "addr:housenumber":"109",
    "addr:postcode":"56129",
    "addr:street":"W 2Nd Ave",
    "iso:country":"US",
    "sg:address":"109 W 2nd Ave",
    "sg:city":"Ellsworth",
    "sg:classifiers":[
        {
            "category":"Building & Trades",
            "subcategory":"Construction",
            "type":"Services"
        }
    ],
    "sg:phone":"+1 507 967 2255",
    "sg:postcode":"56129",
    "sg:province":"MN",
    "sg:tags":[
        "maker",
        "cabinet"
    ],
    "wof:name":"Cabinets & More",
    "wof:placetype":"venue"
},
  "geometry": {"coordinates":[-96.018314,43.518937],"type":"Point"}
}