{
  "type": "Feature",
  "properties": {
    "addr:full":"17542 Janssen Dr Cold Spring MN 56320",
    "addr:housenumber":"17542",
    "addr:postcode":"56320",
    "addr:street":"Janssen Dr",
    "iso:country":"US",
    "sg:address":"17542 Janssen Dr",
    "sg:city":"Cold Spring",
    "sg:classifiers":[
        {
            "category":"Insurance",
            "subcategory":"Insurance Agent",
            "type":"Services"
        }
    ],
    "sg:phone":"+1 320 685 8225",
    "sg:postcode":"56320",
    "sg:province":"MN",
    "wof:name":"Dj Thomes & Associates",
    "wof:placetype":"venue"
},
  "geometry": {"coordinates":[-94.472802,45.448471],"type":"Point"}
}