{
  "type": "Feature",
  "properties": {
    "addr:full":"200 Chancery Ln Mankato MN 56001",
    "addr:housenumber":"200",
    "addr:postcode":"56001",
    "addr:street":"Chancery Ln",
    "iso:country":"US",
    "sg:address":"200 Chancery Ln",
    "sg:city":"Mankato",
    "sg:classifiers":[
        {
            "category":"Professional",
            "subcategory":"Employment Agencies",
            "type":"Services"
        }
    ],
    "sg:phone":"+1 507 345 7461",
    "sg:postcode":"56001",
    "sg:province":"MN",
    "wof:name":"Bkb Assoc",
    "wof:placetype":"venue"
},
  "geometry": {"coordinates":[-93.999799,44.132213],"type":"Point"}
}