{
  "type": "Feature",
  "properties": {
    "iso:country":"US",
    "sg:address":"502 Lake St NE",
    "sg:city":"Warroad",
    "sg:classifiers":[
        {
            "category":"Banks & Credit Unions",
            "subcategory":"Bank",
            "type":"Services"
        }
    ],
    "sg:phone":"+1 218 386 1818",
    "sg:postcode":"56763",
    "sg:province":"MN",
    "wof:name":"Security State Insurance",
    "wof:placetype":"venue"
},
  "geometry": {"coordinates":[-95.315078,48.9051],"type":"Point"}
}