{
  "type": "Feature",
  "properties": {
    "iso:country":"US",
    "sg:address":"130 W Superior St",
    "sg:city":"Duluth",
    "sg:classifiers":[
        {
            "category":"Utilities",
            "subcategory":"Natural Gas",
            "type":"Services"
        }
    ],
    "sg:phone":"+1 218 727 8709",
    "sg:postcode":"55802",
    "sg:province":"MN",
    "sg:tags":[
        "transmission"
    ],
    "wof:name":"Great Lkes Gas Trnsm Ltd Prtnr",
    "wof:placetype":"venue"
},
  "geometry": {"coordinates":[-92.100257,46.785288],"type":"Point"}
}