{
  "type": "Feature",
  "properties": {
    "addr:full":"15561 Cherry Path Rosemount MN 55068",
    "addr:housenumber":"15561",
    "addr:postcode":"55068",
    "addr:street":"Cherry Path",
    "iso:country":"US",
    "sg:address":"15561 Cherry Path",
    "sg:city":"Rosemount",
    "sg:classifiers":[
        {
            "category":"Social Services",
            "type":"Services"
        }
    ],
    "sg:phone":"+1 952 942 9463",
    "sg:postcode":"55068",
    "sg:province":"MN",
    "wof:name":"New Directions Counseling",
    "wof:placetype":"venue"
},
  "geometry": {"coordinates":[-93.135248,44.723586],"type":"Point"}
}