{
  "type": "Feature",
  "properties": {
    "iso:country":"US",
    "sg:address":"312 Plum St",
    "sg:city":"Red Wing",
    "sg:classifiers":[
        {
            "category":"Bars & Pubs",
            "type":"Food & Drink"
        }
    ],
    "sg:phone":"+1 651 385 0715",
    "sg:postcode":"55066",
    "sg:province":"MN",
    "wof:name":"Black Dog Tavern",
    "wof:placetype":"venue"
},
  "geometry": {"coordinates":[-92.533034,44.565848],"type":"Point"}
}