{
  "type": "Feature",
  "properties": {
    "addr:full":"7681 70th Ave Clear Lake MN 55319",
    "addr:housenumber":"7681",
    "addr:postcode":"55319",
    "addr:street":"70Th Ave",
    "iso:country":"US",
    "sg:address":"7681 70th Ave",
    "sg:city":"Clear Lake",
    "sg:classifiers":[
        {
            "category":"Home & Garden",
            "subcategory":"Furniture",
            "type":"Retail Goods"
        }
    ],
    "sg:phone":"+1 763 300 3345",
    "sg:postcode":"55319",
    "sg:province":"MN",
    "wof:name":"Judy Lindemann",
    "wof:placetype":"venue"
},
  "geometry": {"coordinates":[-94.01667,45.459789],"type":"Point"}
}