{
  "type": "Feature",
  "properties": {
    "addr:full":"23442 Rebel Rd Merrifield MN 56465",
    "addr:housenumber":"23442",
    "addr:postcode":"56465",
    "addr:street":"Rebel Rd",
    "iso:country":"US",
    "sg:address":"23442 Rebel Rd",
    "sg:city":"Merrifield",
    "sg:classifiers":[
        {
            "category":"Social Services",
            "type":"Services"
        }
    ],
    "sg:phone":"+1 218 765 3993",
    "sg:postcode":"56465",
    "sg:province":"MN",
    "sg:tags":[
        "human"
    ],
    "wof:name":"Lampp",
    "wof:placetype":"venue"
},
  "geometry": {"coordinates":[-94.125823,46.493142],"type":"Point"}
}