{
  "type": "Feature",
  "properties": {
    "addr:full":"207 N 1st St Montevideo MN 56265",
    "addr:housenumber":"207",
    "addr:postcode":"56265",
    "addr:street":"N 1St St",
    "iso:country":"US",
    "sg:address":"207 N 1st St",
    "sg:city":"Montevideo",
    "sg:classifiers":[
        {
            "category":"Sports & Exercise",
            "subcategory":"Gym",
            "type":"Entertainment"
        }
    ],
    "sg:phone":"+1 320 269 8993",
    "sg:postcode":"56265",
    "sg:province":"MN",
    "sg:tags":[
        "club",
        "health",
        "studio",
        "gymnasium"
    ],
    "wof:name":"Curves For Women",
    "wof:placetype":"venue"
},
  "geometry": {"coordinates":[-95.724908,44.947167],"type":"Point"}
}