{
  "type": "Feature",
  "properties": {
    "addr:full":"5897 Portland Ave S Minneapolis MN 55417",
    "addr:housenumber":"5897",
    "addr:postcode":"55417",
    "addr:street":"Portland Ave S",
    "iso:country":"US",
    "sg:address":"5897 Portland Ave S",
    "sg:city":"Minneapolis",
    "sg:classifiers":[
        {
            "category":"Building & Trades",
            "subcategory":"Construction",
            "type":"Services"
        }
    ],
    "sg:phone":"+1 612 333 7757",
    "sg:postcode":"55417",
    "sg:province":"MN",
    "sg:tags":[
        "house"
    ],
    "wof:name":"Decks Etc",
    "wof:placetype":"venue"
},
  "geometry": {"coordinates":[-93.266779,44.899261],"type":"Point"}
}