{
  "type": "Feature",
  "properties": {
    "iso:country":"US",
    "sg:address":"18598 Haven Heights Ln",
    "sg:city":"Houston",
    "sg:classifiers":[
        {
            "category":"Shopping",
            "type":"Retail Goods"
        }
    ],
    "sg:phone":"+1 507 896 3619",
    "sg:postcode":"55943",
    "sg:province":"MN",
    "sg:tags":[
        "cosmetic",
        "perfume"
    ],
    "wof:name":"Avon Representative",
    "wof:placetype":"venue"
},
  "geometry": {"coordinates":[-91.62307199999999,43.818124],"type":"Point"}
}