{
  "type": "Feature",
  "properties": {
    "iso:country":"US",
    "sg:address":"1421 1st St S",
    "sg:city":"Willmar",
    "sg:classifiers":[
        {
            "category":"Home & Garden",
            "subcategory":"Household Appliances",
            "type":"Retail Goods"
        }
    ],
    "sg:phone":"+1 320 235 6880",
    "sg:postcode":"56201",
    "sg:province":"MN",
    "wof:name":"Quality Appliance & Television",
    "wof:placetype":"venue"
},
  "geometry": {"coordinates":[-95.042633,45.109187],"type":"Point"}
}