{
  "type": "Feature",
  "properties": {
    "addr:full":"29526 State Hwy 220 NW Oslo MN 56744",
    "addr:housenumber":"29526",
    "addr:postcode":"56744",
    "addr:street":"State Hwy 220 Nw",
    "iso:country":"US",
    "sg:address":"29526 State Hwy 220 NW",
    "sg:city":"Oslo",
    "sg:classifiers":[
        {
            "category":"Real Estate",
            "subcategory":"Real Estate Operator",
            "type":"Services"
        }
    ],
    "sg:phone":"+1 218 695 2590",
    "sg:postcode":"56744",
    "sg:province":"MN",
    "sg:tags":[
        "property",
        "lessor"
    ],
    "wof:name":"Clara Swanson",
    "wof:placetype":"venue"
},
  "geometry": {"coordinates":[-97.10845999999999,48.303537],"type":"Point"}
}