{
  "type": "Feature",
  "properties": {
    "iso:country":"US",
    "sg:address":"20034 Erickson Path",
    "sg:city":"Farmington",
    "sg:classifiers":[
        {
            "category":"Retail",
            "subcategory":"Repair Shop",
            "type":"Services"
        }
    ],
    "sg:phone":"+1 651 463 2103",
    "sg:postcode":"55024",
    "sg:province":"MN",
    "wof:name":"Dave Huber Companies Inc",
    "wof:placetype":"venue"
},
  "geometry": {"coordinates":[-93.17498500000001,44.658669],"type":"Point"}
}