{
  "type": "Feature",
  "properties": {
    "addr:full":"614 W Portland Ave Saint Paul MN 55102",
    "addr:housenumber":"614",
    "addr:postcode":"55102",
    "addr:street":"W Portland Ave",
    "iso:country":"US",
    "sg:address":"614 W Portland Ave",
    "sg:city":"Saint Paul",
    "sg:classifiers":[
        {
            "category":"Professional",
            "subcategory":"Business Services",
            "type":"Services"
        }
    ],
    "sg:phone":"+1 651 222 6866",
    "sg:postcode":"55102",
    "sg:province":"MN",
    "wof:name":"Chance Music LLC",
    "wof:placetype":"venue"
},
  "geometry": {"coordinates":[-93.124509,44.94233],"type":"Point"}
}