{
  "type": "Feature",
  "properties": {
    "addr:full":"2500 University Avenue W. #F5 St Paul MN 55114",
    "addr:housenumber":"2500",
    "addr:postcode":"55114",
    "addr:street":"University Avenue W. # F5",
    "iso:country":"US",
    "sg:address":"2500 University Avenue W. #F5",
    "sg:city":"St Paul",
    "sg:classifiers":[
        {
            "category":"Personal",
            "subcategory":"Massage",
            "type":"Services"
        },
        {
            "category":"Sports & Exercise",
            "subcategory":"Gym",
            "type":"Entertainment"
        }
    ],
    "sg:phone":"+1 651 235 8254",
    "sg:postcode":"55114",
    "sg:province":"MN",
    "sg:tags":[
        "yoga"
    ],
    "sg:website":"www.embodied-health.com",
    "wof:name":"Seva Yoga Studio",
    "wof:placetype":"venue"
},
  "geometry": {"coordinates":[-93.20019600000001,44.964906],"type":"Point"}
}