{
  "type": "Feature",
  "properties": {
    "iso:country":"US",
    "sg:address":"3642 20th Ave S",
    "sg:city":"Minneapolis",
    "sg:classifiers":[
        {
            "category":"Wholesale",
            "subcategory":"Scrap",
            "type":"Manufacturing & Wholesale Goods"
        }
    ],
    "sg:phone":"+1 612 216 0057",
    "sg:postcode":"55407",
    "sg:province":"MN",
    "sg:tags":[
        "junk",
        "hauling",
        "removal"
    ],
    "sg:website":"www.budgetdumpster.com",
    "wof:name":"Budget Dumpster Rental",
    "wof:placetype":"venue"
},
  "geometry": {"coordinates":[-93.243922,44.936325],"type":"Point"}
}