{
  "type": "Feature",
  "properties": {
    "iso:country":"US",
    "sg:address":"8559 Edinburgh Center Dr",
    "sg:city":"Minneapolis",
    "sg:classifiers":[
        {
            "category":"Coffee & Tea",
            "type":"Food & Drink"
        }
    ],
    "sg:menulink":"http://www.allmenus.com/mn/brooklyn-park/58490-caribou-coffee/menu/",
    "sg:phone":"+1 763 315 1943",
    "sg:postcode":"55443",
    "sg:province":"MN",
    "sg:tags":[
        "american"
    ],
    "wof:name":"Caribou Coffee",
    "wof:placetype":"venue"
},
  "geometry": {"coordinates":[-93.30559100000001,45.110992],"type":"Point"}
}