{
  "type": "Feature",
  "properties": {
    "addr:full":"1575 Cliff Rd Saint Paul MN 55122",
    "addr:housenumber":"1575",
    "addr:postcode":"55122",
    "addr:street":"Cliff Rd",
    "iso:country":"US",
    "sg:address":"1575 Cliff Rd",
    "sg:city":"Saint Paul",
    "sg:classifiers":[
        {
            "category":"Autos & Motor Vehicles",
            "subcategory":"Auto Supplies",
            "type":"Retail Goods"
        }
    ],
    "sg:phone":"+1 651 688 0931",
    "sg:postcode":"55122",
    "sg:province":"MN",
    "sg:tags":[
        "tire"
    ],
    "wof:name":"Car Care Advanced Service Center",
    "wof:placetype":"venue"
},
  "geometry": {"coordinates":[-93.184477,44.790238],"type":"Point"}
}