{
  "type": "Feature",
  "properties": {
    "addr:full":"4737 Bouleau Rd St Paul MN 55110",
    "addr:postcode":"4737;55110",
    "addr:street":"Bouleau Rd",
    "iso:country":"US",
    "sg:address":"4737 Bouleau Rd",
    "sg:city":"St Paul",
    "sg:classifiers":[
        {
            "category":"Freight",
            "type":"Transportation"
        }
    ],
    "sg:phone":"+1 651 426 4995",
    "sg:postcode":"55110",
    "sg:province":"MN",
    "sg:tags":[
        "trucking"
    ],
    "wof:name":"Pam Trucking",
    "wof:placetype":"venue"
},
  "geometry": {"coordinates":[-93.045845,45.083826],"type":"Point"}
}