{
  "type": "Feature",
  "properties": {
    "iso:country":"US",
    "sg:address":"2301 Indiana Ave N",
    "sg:city":"Minneapolis",
    "sg:classifiers":[
        {
            "category":"Parking",
            "type":"Transportation"
        }
    ],
    "sg:phone":"+1 612 370 0567",
    "sg:postcode":"55422",
    "sg:province":"MN",
    "sg:tags":[
        "lots",
        "mail",
        "book",
        "order",
        "operates"
    ],
    "wof:name":"Book Express The",
    "wof:placetype":"venue"
},
  "geometry": {"coordinates":[-93.332137,45.000796],"type":"Point"}
}