{
  "type": "Feature",
  "properties": {
    "addr:full":"415 S 4th St Milan MN 56262",
    "addr:housenumber":"415",
    "addr:postcode":"56262",
    "addr:street":"S 4Th St",
    "iso:country":"US",
    "sg:address":"415 S 4th St",
    "sg:city":"Milan",
    "sg:classifiers":[
        {
            "category":"Shopping",
            "subcategory":"Gifts & Souvenirs",
            "type":"Retail Goods"
        }
    ],
    "sg:phone":"+1 320 734 4838",
    "sg:postcode":"56262",
    "sg:province":"MN",
    "sg:tags":[
        "shop"
    ],
    "wof:name":"Shear Country-Uniquely Santa",
    "wof:placetype":"venue"
},
  "geometry": {"coordinates":[-95.91399699999999,45.107],"type":"Point"}
}