{
  "type": "Feature",
  "properties": {
    "addr:full":"12521 Main St Rogers MN 55374",
    "addr:housenumber":"12521",
    "addr:postcode":"55374",
    "addr:street":"Main St",
    "iso:country":"US",
    "sg:address":"12521 Main St",
    "sg:city":"Rogers",
    "sg:classifiers":[
        {
            "category":"Social Services",
            "subcategory":"Child Care",
            "type":"Services"
        }
    ],
    "sg:phone":"+1 763 428 4138",
    "sg:postcode":"55374",
    "sg:province":"MN",
    "wof:name":"Appletime At School",
    "wof:placetype":"venue"
},
  "geometry": {"coordinates":[-93.55261,45.180658],"type":"Point"}
}