{
  "type": "Feature",
  "properties": {
    "iso:country":"US",
    "sg:address":"110 E Lincoln Ave",
    "sg:city":"Fergus Falls",
    "sg:classifiers":[
        {
            "category":"Organizations",
            "subcategory":"Community Association",
            "type":"Services"
        }
    ],
    "sg:phone":"+1 218 998 5473",
    "sg:postcode":"56537",
    "sg:province":"MN",
    "wof:name":"Veterans Resource Network Assn",
    "wof:placetype":"venue"
},
  "geometry": {"coordinates":[-96.072535,46.283434],"type":"Point"}
}