{
  "type": "Feature",
  "properties": {
    "iso:country":"US",
    "sg:address":"1830 Woodale Dr",
    "sg:city":"Saint Paul",
    "sg:classifiers":[
        {
            "category":"Professional",
            "subcategory":"Business Services",
            "type":"Services"
        }
    ],
    "sg:phone":"+1 651 735 1608",
    "sg:postcode":"55125",
    "sg:province":"MN",
    "sg:tags":[
        "interior",
        "consultant",
        "design",
        "decorator"
    ],
    "wof:name":"Interior Inspirations Inc",
    "wof:placetype":"venue"
},
  "geometry": {"coordinates":[-92.969387,44.922374],"type":"Point"}
}