{
  "type": "Feature",
  "properties": {
    "iso:country":"US",
    "sg:address":"1204 Hillsboro Ave",
    "sg:city":"Champlin",
    "sg:classifiers":[
        {
            "category":"Home & Garden",
            "subcategory":"Home Furnishings",
            "type":"Retail Goods"
        },
        {
            "category":"Manufacturing",
            "subcategory":"Textiles",
            "type":"Manufacturing & Wholesale Goods"
        }
    ],
    "sg:phone":"+1 763 427 8429",
    "sg:postcode":"55316",
    "sg:province":"MN",
    "sg:tags":[
        "linen",
        "towels-cloth-wholesale",
        "manufacturer"
    ],
    "wof:name":"Sunkissed Towels",
    "wof:placetype":"venue"
},
  "geometry": {"coordinates":[-93.398831,45.180279],"type":"Point"}
}