{
  "type": "Feature",
  "properties": {
    "addr:full":"10333 Yukon Ave S Minneapolis MN 55438",
    "addr:housenumber":"10333",
    "addr:postcode":"55438",
    "addr:street":"Yukon Ave S",
    "iso:country":"US",
    "sg:address":"10333 Yukon Ave S",
    "sg:city":"Minneapolis",
    "sg:classifiers":[
        {
            "category":"Wholesale",
            "subcategory":"Construction Materials",
            "type":"Manufacturing & Wholesale Goods"
        },
        {
            "category":"Building & Trades",
            "subcategory":"Construction",
            "type":"Services"
        }
    ],
    "sg:phone":"+1 952 944 7474",
    "sg:postcode":"55438",
    "sg:province":"MN",
    "sg:tags":[
        "waterproofing",
        "asphalt",
        "supply",
        "contractor",
        "equipment",
        "paving",
        "fireproofing",
        "masonry",
        "sealcoating"
    ],
    "sg:website":"http://www.jet-black.com",
    "wof:name":"Jetblack",
    "wof:placetype":"venue"
},
  "geometry": {"coordinates":[-93.38921999999999,44.816042],"type":"Point"}
}