{
  "type": "Feature",
  "properties": {
    "addr:full":"1526 E 6th St St Paul MN 55106",
    "addr:housenumber":"1526",
    "addr:postcode":"55106",
    "addr:street":"E 6Th St",
    "iso:country":"US",
    "sg:address":"1526 E 6th St",
    "sg:city":"St Paul",
    "sg:classifiers":[
        {
            "category":"Professional",
            "subcategory":"Lawyer & Legal Services",
            "type":"Services"
        }
    ],
    "sg:phone":"+1 651 738 4800",
    "sg:postcode":"55106",
    "sg:province":"MN",
    "sg:tags":[
        "attorney"
    ],
    "wof:name":"Jeff Besikof Robinson Law Ofc",
    "wof:placetype":"venue"
},
  "geometry": {"coordinates":[-93.03651499999999,44.960328],"type":"Point"}
}