{
  "type": "Feature",
  "properties": {
    "iso:country":"US",
    "sg:address":"138 S Olive St",
    "sg:city":"Waconia",
    "sg:classifiers":[
        {
            "category":"Shopping",
            "subcategory":"Bicycles & Sporting Goods",
            "type":"Retail Goods"
        }
    ],
    "sg:phone":"+1 952 442 9891",
    "sg:postcode":"55387",
    "sg:province":"MN",
    "wof:name":"Sports Locker",
    "wof:placetype":"venue"
},
  "geometry": {"coordinates":[-93.78752299999999,44.849197],"type":"Point"}
}