{
  "type": "Feature",
  "properties": {
    "addr:full":"2011 Chicago Ave S Minneapolis MN 55404",
    "addr:housenumber":"2011",
    "addr:postcode":"55404",
    "addr:street":"Chicago Ave S",
    "iso:country":"US",
    "sg:address":"2011 Chicago Ave S",
    "sg:city":"Minneapolis",
    "sg:classifiers":[
        {
            "category":"Organizations",
            "subcategory":"Religious Organization",
            "type":"Services"
        }
    ],
    "sg:phone":"+1 612 871 6330",
    "sg:postcode":"55404",
    "sg:province":"MN",
    "wof:name":"Gospel Light Baptist Church",
    "wof:placetype":"venue"
},
  "geometry": {"coordinates":[-93.262474,44.96191],"type":"Point"}
}