{
  "type": "Feature",
  "properties": {
    "iso:country":"US",
    "sg:address":"5931 Carlson St",
    "sg:city":"Saint Paul",
    "sg:classifiers":[
        {
            "category":"Manufacturing",
            "subcategory":"Electronics",
            "type":"Manufacturing & Wholesale Goods"
        }
    ],
    "sg:phone":"+1 651 482 0805",
    "sg:postcode":"55126",
    "sg:province":"MN",
    "sg:tags":[
        "electronic",
        "component",
        "mfg"
    ],
    "wof:name":"Atronic Inc",
    "wof:placetype":"venue"
},
  "geometry": {"coordinates":[-93.130741,45.121126],"type":"Point"}
}