{
  "type": "Feature",
  "properties": {
    "addr:full":"1259 White Bear Ave N Saint Paul MN 55106",
    "addr:housenumber":"1259",
    "addr:postcode":"55106",
    "addr:street":"White Bear Ave N",
    "iso:country":"US",
    "sg:address":"1259 White Bear Ave N",
    "sg:city":"Saint Paul",
    "sg:classifiers":[
        {
            "category":"Real Estate",
            "subcategory":"Real Estate Operator",
            "type":"Services"
        }
    ],
    "sg:phone":"+1 651 774 3584",
    "sg:postcode":"55106",
    "sg:province":"MN",
    "sg:tags":[
        "building",
        "apartment"
    ],
    "wof:name":"Apartment Prep & Maintenace",
    "wof:placetype":"venue"
},
  "geometry": {"coordinates":[-93.025294,44.978407],"type":"Point"}
}