{
  "type": "Feature",
  "properties": {
    "addr:full":"5604 International Pkwy Minneapolis MN 55428",
    "addr:housenumber":"5604",
    "addr:postcode":"55428",
    "addr:street":"International Pkwy",
    "iso:country":"US",
    "sg:address":"5604 International Pkwy",
    "sg:city":"Minneapolis",
    "sg:classifiers":[
        {
            "category":"Wholesale",
            "subcategory":"Machinery & Supplies",
            "type":"Manufacturing & Wholesale Goods"
        },
        {
            "category":"Manufacturing",
            "subcategory":"Rubber & Plastics",
            "type":"Manufacturing & Wholesale Goods"
        }
    ],
    "sg:phone":"+1 763 533 4532",
    "sg:postcode":"55428",
    "sg:province":"MN",
    "sg:tags":[
        "box",
        "equipment",
        "material",
        "handling",
        "transparent"
    ],
    "wof:name":"Midwest Container Systems",
    "wof:placetype":"venue"
},
  "geometry": {"coordinates":[-93.396811,45.055159],"type":"Point"}
}