{
  "type": "Feature",
  "properties": {
    "addr:full":"1575 L'Orient St St Paul MN 55117",
    "addr:housenumber":"1575",
    "addr:postcode":"55117",
    "addr:street":"L'Orient St",
    "iso:country":"US",
    "sg:address":"1575 L'Orient St",
    "sg:city":"St Paul",
    "sg:classifiers":[
        {
            "category":"Education",
            "subcategory":"School",
            "type":"Public Place"
        }
    ],
    "sg:phone":"+1 651 293 8840",
    "sg:postcode":"55117",
    "sg:province":"MN",
    "wof:name":"Mississippi Magnet Elementary",
    "wof:placetype":"venue"
},
  "geometry": {"coordinates":[-93.089365,44.986562],"type":"Point"}
}