{
  "type": "Feature",
  "properties": {
    "iso:country":"US",
    "sg:address":"8120 Penn Ave S",
    "sg:city":"Bloomington",
    "sg:classifiers":[
        {
            "category":"Building & Trades",
            "subcategory":"Construction",
            "type":"Services"
        }
    ],
    "sg:phone":"+1 952 888 3503",
    "sg:postcode":"55431",
    "sg:province":"MN",
    "sg:tags":[
        "layer",
        "carpet"
    ],
    "wof:name":"Metro City Carpet",
    "wof:placetype":"venue"
},
  "geometry": {"coordinates":[-93.308842,44.855943],"type":"Point"}
}