{
  "type": "Feature",
  "properties": {
    "addr:full":"1940 Commerce Ln North Mankato MN 56003",
    "addr:housenumber":"1940",
    "addr:postcode":"56003",
    "addr:street":"Commerce Ln North",
    "iso:country":"US",
    "sg:address":"1940 Commerce Ln",
    "sg:city":"North Mankato",
    "sg:classifiers":[
        {
            "category":"Manufacturing",
            "subcategory":"Tools & Machinery",
            "type":"Manufacturing & Wholesale Goods"
        }
    ],
    "sg:phone":"+1 507 345 6200",
    "sg:postcode":"56003",
    "sg:province":"MN",
    "sg:tags":[
        "physician",
        "surgeon"
    ],
    "wof:name":"Coloplast Corp Skin Care Div",
    "wof:placetype":"venue"
},
  "geometry": {"coordinates":[-94.05029,44.178593],"type":"Point"}
}