{
  "type": "Feature",
  "properties": {
    "iso:country":"US",
    "sg:address":"210 N Broadway",
    "sg:city":"Rochester",
    "sg:classifiers":[
        {
            "category":"Food & Beverages",
            "subcategory":"Dairy",
            "type":"Retail Goods"
        }
    ],
    "sg:phone":"+1 507 288 1888",
    "sg:postcode":"55906",
    "sg:province":"MN",
    "sg:tags":[
        "cheese"
    ],
    "wof:name":"Nelson Cheese Factory",
    "wof:placetype":"venue"
},
  "geometry": {"coordinates":[-92.462954,44.025656],"type":"Point"}
}