{
  "type": "Feature",
  "properties": {
    "addr:full":"1306 10th St N Sauk Rapids MN 56379",
    "addr:housenumber":"1306",
    "addr:postcode":"56379",
    "addr:street":"10Th St N Sauk",
    "iso:country":"US",
    "sg:address":"1306 10th St N",
    "sg:city":"Sauk Rapids",
    "sg:classifiers":[
        {
            "category":"Bus Charters",
            "type":"Transportation"
        }
    ],
    "sg:phone":"+1 320 252 2828",
    "sg:postcode":"56379",
    "sg:province":"MN",
    "sg:tags":[
        "rental"
    ],
    "wof:name":"Larson Bus Svc",
    "wof:placetype":"venue"
},
  "geometry": {"coordinates":[-94.154926,45.599848],"type":"Point"}
}