{
  "type": "Feature",
  "properties": {
    "iso:country":"US",
    "sg:address":"4050 Brookside Ave",
    "sg:city":"Minneapolis",
    "sg:classifiers":[
        {
            "category":"Personal",
            "subcategory":"Beauty Salon",
            "type":"Services"
        }
    ],
    "sg:phone":"+1 952 224 8080",
    "sg:postcode":"55416",
    "sg:province":"MN",
    "wof:name":"Art Of Hair",
    "wof:placetype":"venue"
},
  "geometry": {"coordinates":[-93.355771,44.927878],"type":"Point"}
}