{
  "type": "Feature",
  "properties": {
    "addr:full":"67623 270th Ave Kasson MN 55944",
    "addr:housenumber":"67623",
    "addr:postcode":"55944",
    "addr:street":"270Th Ave",
    "iso:country":"US",
    "sg:address":"67623 270th Ave",
    "sg:city":"Kasson",
    "sg:classifiers":[
        {
            "category":"Professional",
            "subcategory":"Computer Services",
            "type":"Services"
        }
    ],
    "sg:phone":"+1 507 365 8939",
    "sg:postcode":"55944",
    "sg:province":"MN",
    "sg:tags":[
        "prepackaged",
        "software"
    ],
    "wof:name":"Carlson Software Consulti",
    "wof:placetype":"venue"
},
  "geometry": {"coordinates":[-92.69822499999999,43.966788],"type":"Point"}
}