{
  "type": "Feature",
  "properties": {
    "addr:full":"1124 W 5th St Winona MN 55987",
    "addr:housenumber":"1124",
    "addr:postcode":"55987",
    "addr:street":"W 5Th St",
    "iso:country":"US",
    "sg:address":"1124 W 5th St",
    "sg:city":"Winona",
    "sg:classifiers":[
        {
            "category":"Manufacturing",
            "subcategory":"Signs",
            "type":"Manufacturing & Wholesale Goods"
        }
    ],
    "sg:phone":"+1 507 454 5510",
    "sg:postcode":"55987",
    "sg:province":"MN",
    "sg:tags":[
        "badges-wholesale",
        "specialty",
        "manufacturer",
        "mfg"
    ],
    "sg:website":"http://www.wincraft.com",
    "wof:name":"Lar Lu",
    "wof:placetype":"venue"
},
  "geometry": {"coordinates":[-91.66661499999999,44.053936],"type":"Point"}
}