{
  "type": "Feature",
  "properties": {
    "iso:country":"US",
    "sg:address":"1414 Marshall St NE",
    "sg:city":"Minneapolis",
    "sg:phone":"+1 612 225 9612",
    "sg:postcode":"55413",
    "sg:province":"MN",
    "sg:website":"http://www.worrell.com",
    "wof:name":"Worrell Prototyping",
    "wof:placetype":"venue"
},
  "geometry": {"coordinates":[-93.270793,45.001234],"type":"Point"}
}