{
  "type": "Feature",
  "properties": {
    "addr:full":"100 S Main St Mcgregor MN 55760",
    "addr:housenumber":"100",
    "addr:postcode":"55760",
    "addr:street":"S Main St",
    "iso:country":"US",
    "sg:address":"100 S Main St",
    "sg:city":"Mcgregor",
    "sg:classifiers":[
        {
            "category":"Insurance",
            "subcategory":"Insurance Agent",
            "type":"Services"
        }
    ],
    "sg:phone":"+1 218 768 2444",
    "sg:postcode":"55760",
    "sg:province":"MN",
    "wof:name":"Mc Gregor Insurance",
    "wof:placetype":"venue"
},
  "geometry": {"coordinates":[-93.309613,46.606818],"type":"Point"}
}