{
  "type": "Feature",
  "properties": {
    "iso:country":"US",
    "sg:address":"1613 W 98th St",
    "sg:city":"Bloomington",
    "sg:classifiers":[
        {
            "category":"Professional",
            "subcategory":"Accounting & Tax Preparation",
            "type":"Services"
        }
    ],
    "sg:phone":"+1 952 746 0774",
    "sg:postcode":"55431",
    "sg:province":"MN",
    "sg:tags":[
        "return",
        "filing"
    ],
    "wof:name":"H & R Block Tax Svc",
    "wof:placetype":"venue"
},
  "geometry": {"coordinates":[-93.301175,44.826237],"type":"Point"}
}