{
  "type": "Feature",
  "properties": {
    "addr:full":"16526 W 78th St Eden Prairie MN 55346",
    "addr:housenumber":"16526",
    "addr:postcode":"55346",
    "addr:street":"W 78Th St",
    "iso:country":"US",
    "sg:address":"16526 W 78th St",
    "sg:city":"Eden Prairie",
    "sg:classifiers":[
        {
            "category":"Manufacturing",
            "subcategory":"Printing",
            "type":"Manufacturing & Wholesale Goods"
        }
    ],
    "sg:phone":"+1 952 975 9000",
    "sg:postcode":"55346",
    "sg:province":"MN",
    "sg:tags":[
        "publisher"
    ],
    "wof:name":"Finkstrom Licensing Intl",
    "wof:placetype":"venue"
},
  "geometry": {"coordinates":[-93.489514,44.862824],"type":"Point"}
}