{
  "type": "Feature",
  "properties": {
    "addr:full":"15034 Shannon Pkwy Rosemount MN 55068",
    "addr:housenumber":"15034",
    "addr:postcode":"55068",
    "addr:street":"Shannon Pkwy",
    "iso:country":"US",
    "sg:address":"15034 Shannon Pkwy",
    "sg:city":"Rosemount",
    "sg:classifiers":[
        {
            "category":"Wholesale",
            "subcategory":"Medical Equipment & Supplies",
            "type":"Manufacturing & Wholesale Goods"
        },
        {
            "category":"Shopping",
            "subcategory":"Pharmacy",
            "type":"Retail Goods"
        }
    ],
    "sg:phone":"+1 651 322 6603",
    "sg:postcode":"55068",
    "sg:province":"MN",
    "sg:tags":[
        "health",
        "aid",
        "home",
        "first",
        "care"
    ],
    "sg:website":"http://www.walgreens.com",
    "wof:name":"Walgreen Drug Stores",
    "wof:placetype":"venue"
},
  "geometry": {"coordinates":[-93.146529,44.729957],"type":"Point"}
}