{
  "type": "Feature",
  "properties": {
    "iso:country":"US",
    "sg:address":"131 5th Ave S",
    "sg:city":"Brownton",
    "sg:classifiers":[
        {
            "category":"Freight",
            "type":"Transportation"
        }
    ],
    "sg:phone":"+1 320 583 5897",
    "sg:postcode":"55312",
    "sg:province":"MN",
    "sg:tags":[
        "trucking"
    ],
    "wof:name":"Nussbaum Brothers Trucking",
    "wof:placetype":"venue"
},
  "geometry": {"coordinates":[-94.350708,44.732036],"type":"Point"}
}