{
  "type": "Feature",
  "properties": {
    "iso:country":"US",
    "sg:address":"10738 350th St NE",
    "sg:city":"Newfolden",
    "sg:classifiers":[
        {
            "category":"Personal",
            "subcategory":"Beauty Salon",
            "type":"Services"
        }
    ],
    "sg:phone":"+1 218 874 6445",
    "sg:postcode":"56738",
    "sg:province":"MN",
    "sg:tags":[
        "shop"
    ],
    "wof:name":"Country Cutters",
    "wof:placetype":"venue"
},
  "geometry": {"coordinates":[-96.23470500000001,48.383744],"type":"Point"}
}