{
  "type": "Feature",
  "properties": {
    "iso:country":"US",
    "sg:address":"1653 W Wellesley Ave",
    "sg:city":"Saint Paul",
    "sg:classifiers":[
        {
            "category":"Farming",
            "subcategory":"Farm",
            "type":"Manufacturing & Wholesale Goods"
        }
    ],
    "sg:phone":"+1 651 698 6159",
    "sg:postcode":"55105",
    "sg:province":"MN",
    "sg:tags":[
        "crop",
        "general"
    ],
    "wof:name":"James Gibbons Midwest Farms",
    "wof:placetype":"venue"
},
  "geometry": {"coordinates":[-93.171739,44.931624],"type":"Point"}
}