{
  "type": "Feature",
  "properties": {
    "addr:full":"1680 Industrial Park Rd S Baxter MN 56425",
    "addr:housenumber":"1680",
    "addr:postcode":"56425",
    "addr:street":"Industrial Park Rd S",
    "iso:country":"US",
    "sg:address":"1680 Industrial Park Rd S",
    "sg:city":"Baxter",
    "sg:classifiers":[
        {
            "category":"Food & Beverages",
            "subcategory":"Groceries & Convenience Stores",
            "type":"Retail Goods"
        }
    ],
    "sg:phone":"+1 218 828 9316",
    "sg:postcode":"56425",
    "sg:province":"MN",
    "sg:tags":[
        "product"
    ],
    "wof:name":"Schwan's Consumer Brands",
    "wof:placetype":"venue"
},
  "geometry": {"coordinates":[-94.234095,46.349402],"type":"Point"}
}