{
  "type": "Feature",
  "properties": {
    "addr:full":"305 Division St S Northfield MN 55057",
    "addr:housenumber":"305",
    "addr:postcode":"55057",
    "addr:street":"Division St S",
    "iso:country":"US",
    "sg:address":"305 Division St S",
    "sg:city":"Northfield",
    "sg:classifiers":[
        {
            "category":"Personal",
            "subcategory":"Beauty Salon",
            "type":"Services"
        }
    ],
    "sg:phone":"+1 507 645 7451",
    "sg:postcode":"55057",
    "sg:province":"MN",
    "sg:tags":[
        "shop"
    ],
    "wof:name":"Mane Effects Hair Design",
    "wof:placetype":"venue"
},
  "geometry": {"coordinates":[-93.159496,44.457305],"type":"Point"}
}