{
  "type": "Feature",
  "properties": {
    "iso:country":"US",
    "sg:address":"793 14th St",
    "sg:city":"Granite Falls",
    "sg:classifiers":[
        {
            "category":"Wholesale",
            "subcategory":"Farm Supplies",
            "type":"Manufacturing & Wholesale Goods"
        }
    ],
    "sg:phone":"+1 320 564 3833",
    "sg:postcode":"56241",
    "sg:province":"MN",
    "sg:tags":[
        "fertilizer"
    ],
    "wof:name":"Cenex Ag Ctr",
    "wof:placetype":"venue"
},
  "geometry": {"coordinates":[-95.558207,44.811187],"type":"Point"}
}