{
  "type": "Feature",
  "properties": {
    "addr:full":"421 E Travelers Trl Burnsville MN 55337",
    "addr:housenumber":"421",
    "addr:postcode":"55337",
    "addr:street":"E Travelers Trl",
    "iso:country":"US",
    "sg:address":"421 E Travelers Trl",
    "sg:city":"Burnsville",
    "sg:classifiers":[
        {
            "category":"Manufacturing",
            "subcategory":"Retail Goods",
            "type":"Manufacturing & Wholesale Goods"
        }
    ],
    "sg:phone":"+1 952 707 0150",
    "sg:postcode":"55337",
    "sg:province":"MN",
    "sg:tags":[
        "manufacturer"
    ],
    "wof:name":"Clarke Industries",
    "wof:placetype":"venue"
},
  "geometry": {"coordinates":[-93.271128,44.778063],"type":"Point"}
}