{
  "type": "Feature",
  "properties": {
    "addr:full":"410 N Main St Stewartville MN 55976",
    "addr:housenumber":"410",
    "addr:postcode":"55976",
    "addr:street":"N Main St",
    "iso:country":"US",
    "sg:address":"410 N Main St",
    "sg:city":"Stewartville",
    "sg:classifiers":[
        {
            "category":"Food & Beverages",
            "subcategory":"Groceries & Convenience Stores",
            "type":"Retail Goods"
        }
    ],
    "sg:phone":"+1 507 533 9307",
    "sg:postcode":"55976",
    "sg:province":"MN",
    "sg:website":"www.kwiktrip.com",
    "wof:name":"KWIK Trip",
    "wof:placetype":"venue"
},
  "geometry": {"coordinates":[-92.488415,43.858509],"type":"Point"}
}