{
  "type": "Feature",
  "properties": {
    "iso:country":"US",
    "sg:address":"13722 Nicollet Ave",
    "sg:city":"Burnsville",
    "sg:classifiers":[
        {
            "category":"Shopping",
            "subcategory":"Jewelry",
            "type":"Retail Goods"
        }
    ],
    "sg:phone":"+1 952 882 9712",
    "sg:postcode":"55337",
    "sg:province":"MN",
    "sg:tags":[
        "platinum",
        "silver",
        "gold"
    ],
    "wof:name":"Max Gamman",
    "wof:placetype":"venue"
},
  "geometry": {"coordinates":[-93.27785900000001,44.754995],"type":"Point"}
}