{
  "type": "Feature",
  "properties": {
    "iso:country":"US",
    "sg:address":"615 16th St SW",
    "sg:city":"Rochester",
    "sg:classifiers":[
        {
            "category":"Health Services",
            "subcategory":"Doctor",
            "type":"Services"
        }
    ],
    "sg:phone":"+1 507 288 2539",
    "sg:postcode":"55902",
    "sg:province":"MN",
    "sg:tags":[
        "dentist"
    ],
    "wof:name":"Stone Barn Dentistry",
    "wof:placetype":"venue"
},
  "geometry": {"coordinates":[-92.47219800000001,44.000122],"type":"Point"}
}