{
  "type": "Feature",
  "properties": {
    "addr:full":"625 Nicolette Blvd Minneapolis MN 55401",
    "addr:housenumber":"625",
    "addr:postcode":"55401",
    "addr:street":"Nicolette Blvd",
    "iso:country":"US",
    "sg:address":"625 Nicolette Blvd",
    "sg:city":"Minneapolis",
    "sg:classifiers":[
        {
            "category":"Health Services",
            "subcategory":"Doctor",
            "type":"Services"
        },
        {
            "category":"Recreation",
            "type":"Entertainment"
        }
    ],
    "sg:phone":"+1 952 920 4595",
    "sg:postcode":"55401",
    "sg:province":"MN",
    "sg:tags":[
        "throat",
        "active",
        "life",
        "ear",
        "nose"
    ],
    "wof:name":"Minneapolis Otolaryngology-Head & Neck Surgery PA",
    "wof:placetype":"venue"
},
  "geometry": {"coordinates":[-93.269997,44.984501],"type":"Point"}
}