{
  "type": "Feature",
  "properties": {
    "addr:full":"69995 Co Rd 260 Effie MN 56639",
    "addr:housenumber":"69995;260",
    "addr:postcode":"56639",
    "addr:street":"Co Rd",
    "iso:country":"US",
    "sg:address":"69995 Co Rd 260",
    "sg:city":"Effie",
    "sg:classifiers":[
        {
            "category":"Manufacturing",
            "subcategory":"Lumber",
            "type":"Manufacturing & Wholesale Goods"
        }
    ],
    "sg:phone":"+1 218 743 3812",
    "sg:postcode":"56639",
    "sg:province":"MN",
    "sg:tags":[
        "logging"
    ],
    "wof:name":"Lovdahl & Sons LLC",
    "wof:placetype":"venue"
},
  "geometry": {"coordinates":[-93.574873,47.894306],"type":"Point"}
}