{
  "type": "Feature",
  "properties": {
    "addr:full":"455 W Atwater St St Paul MN 55117",
    "addr:housenumber":"455",
    "addr:postcode":"55117",
    "addr:street":"W Atwater St",
    "iso:country":"US",
    "sg:address":"455 W Atwater St",
    "sg:city":"St Paul",
    "sg:classifiers":[
        {
            "category":"Retail",
            "subcategory":"Auto Repair",
            "type":"Services"
        }
    ],
    "sg:phone":"+1 651 770 2929",
    "sg:postcode":"55117",
    "sg:province":"MN",
    "sg:tags":[
        "repairing",
        "automobile"
    ],
    "wof:name":"Mr Clutch",
    "wof:placetype":"venue"
},
  "geometry": {"coordinates":[-93.121118,44.96664],"type":"Point"}
}