{
  "type": "Feature",
  "properties": {
    "addr:full":"1612 White Bear Ave N St Paul MN 55106",
    "addr:housenumber":"1612",
    "addr:postcode":"55106",
    "addr:street":"White Bear Ave N",
    "iso:country":"US",
    "sg:address":"1612 White Bear Ave N",
    "sg:city":"St Paul",
    "sg:classifiers":[
        {
            "category":"Banks & Credit Unions",
            "subcategory":"Bank",
            "type":"Services"
        }
    ],
    "sg:phone":"+1 651 641 8695",
    "sg:postcode":"55106",
    "sg:province":"MN",
    "sg:tags":[
        "cashing",
        "check"
    ],
    "wof:name":"Un Loan",
    "wof:placetype":"venue"
},
  "geometry": {"coordinates":[-93.025149,44.989498],"type":"Point"}
}