{
  "type": "Feature",
  "properties": {
    "iso:country":"US",
    "sg:address":"312 2nd Ave SE",
    "sg:city":"Pine Island",
    "sg:classifiers":[
        {
            "category":"Building & Trades",
            "subcategory":"Plumbing",
            "type":"Services"
        }
    ],
    "sg:phone":"+1 507 356 6080",
    "sg:postcode":"55963",
    "sg:province":"MN",
    "sg:tags":[
        "contractor"
    ],
    "wof:name":"Bushman Mechanical Inc",
    "wof:placetype":"venue"
},
  "geometry": {"coordinates":[-92.64381899999999,44.199408],"type":"Point"}
}