{
  "type": "Feature",
  "properties": {
    "iso:country":"US",
    "sg:address":"2895 250th St",
    "sg:city":"Ada",
    "sg:phone":"+1 218 784 4418",
    "sg:postcode":"56510",
    "sg:province":"MN",
    "sg:tags":[
        "farm",
        "grain",
        "cash"
    ],
    "wof:name":"Peterson Farm",
    "wof:placetype":"venue"
},
  "geometry": {"coordinates":[-96.537592,47.426262],"type":"Point"}
}