{
  "type": "Feature",
  "properties": {
    "iso:country":"US",
    "sg:address":"1710 10th St E",
    "sg:city":"Glencoe",
    "sg:classifiers":[
        {
            "category":"Professional",
            "subcategory":"Accounting & Tax Preparation",
            "type":"Services"
        }
    ],
    "sg:phone":"+1 320 864 5595",
    "sg:postcode":"55336",
    "sg:province":"MN",
    "sg:tags":[
        "return",
        "filing"
    ],
    "sg:website":"www.agstar.com",
    "wof:name":"Agstar Financial Svc",
    "wof:placetype":"venue"
},
  "geometry": {"coordinates":[-94.13841499999999,44.76912],"type":"Point"}
}