{
  "type": "Feature",
  "properties": {
    "addr:full":"210 Co Rd 101 Wayzata MN 55391",
    "addr:housenumber":"210;101",
    "addr:postcode":"55391",
    "addr:street":"Co Rd",
    "iso:country":"US",
    "sg:address":"210 Co Rd 101",
    "sg:city":"Wayzata",
    "sg:classifiers":[
        {
            "category":"Education",
            "subcategory":"School",
            "type":"Public Place"
        }
    ],
    "sg:phone":"+1 952 745 5000",
    "sg:postcode":"55391",
    "sg:province":"MN",
    "wof:name":"Wayzata Schools",
    "wof:placetype":"venue"
},
  "geometry": {"coordinates":[-93.49577600000001,44.96831],"type":"Point"}
}