{
  "type": "Feature",
  "properties": {
    "iso:country":"US",
    "sg:address":"1230 N State St",
    "sg:city":"Waseca",
    "sg:classifiers":[
        {
            "category":"Food & Beverages",
            "subcategory":"Groceries & Convenience Stores",
            "type":"Retail Goods"
        }
    ],
    "sg:phone":"+1 507 835 8030",
    "sg:postcode":"56093",
    "sg:province":"MN",
    "wof:name":"Hy-Vee 1848",
    "wof:placetype":"venue"
},
  "geometry": {"coordinates":[-93.506918,44.090261],"type":"Point"}
}