{
  "type": "Feature",
  "properties": {
    "iso:country":"US",
    "sg:address":"116 Maple Ridge Cir",
    "sg:city":"Delano",
    "sg:classifiers":[
        {
            "category":"Manufacturing",
            "subcategory":"Chemicals & Compounds",
            "type":"Manufacturing & Wholesale Goods"
        }
    ],
    "sg:phone":"+1 763 972 3244",
    "sg:postcode":"55328",
    "sg:province":"MN",
    "sg:tags":[
        "preparation",
        "mfg"
    ],
    "wof:name":"Releasagen Manufacturing Inc",
    "wof:placetype":"venue"
},
  "geometry": {"coordinates":[-93.775424,45.040611],"type":"Point"}
}