{
  "type": "Feature",
  "properties": {
    "addr:full":"38574 E Pike Lake Rd Waubun MN 56589",
    "addr:housenumber":"38574",
    "addr:postcode":"56589",
    "addr:street":"E Pike Lake Rd",
    "iso:country":"US",
    "sg:address":"38574 E Pike Lake Rd",
    "sg:city":"Waubun",
    "sg:classifiers":[
        {
            "category":"Building & Trades",
            "subcategory":"Plumbing",
            "type":"Services"
        }
    ],
    "sg:phone":"+1 218 734 2460",
    "sg:postcode":"56589",
    "sg:province":"MN",
    "sg:tags":[
        "contractor"
    ],
    "wof:name":"R C Plumbing",
    "wof:placetype":"venue"
},
  "geometry": {"coordinates":[-95.529954,47.131492],"type":"Point"}
}