{
  "type": "Feature",
  "properties": {
    "addr:full":"1008 Maplehill Dr Albert Lea MN 56007",
    "addr:housenumber":"1008",
    "addr:postcode":"56007",
    "addr:street":"Maplehill Dr",
    "iso:country":"US",
    "sg:address":"1008 Maplehill Dr",
    "sg:city":"Albert Lea",
    "sg:classifiers":[
        {
            "category":"Social Services",
            "subcategory":"Child Care",
            "type":"Services"
        }
    ],
    "sg:phone":"+1 507 377 1841",
    "sg:postcode":"56007",
    "sg:province":"MN",
    "sg:tags":[
        "daycare",
        "provider"
    ],
    "wof:name":"Maple Hill Day Care",
    "wof:placetype":"venue"
},
  "geometry": {"coordinates":[-93.386349,43.639098],"type":"Point"}
}