{
  "type": "Feature",
  "properties": {
    "addr:full":"10751 Dodd Rd Kilkenny MN 56052",
    "addr:housenumber":"10751",
    "addr:postcode":"56052",
    "addr:street":"Dodd Rd",
    "iso:country":"US",
    "sg:address":"10751 Dodd Rd",
    "sg:city":"Kilkenny",
    "sg:classifiers":[
        {
            "category":"Retail",
            "subcategory":"Repair Shop",
            "type":"Services"
        }
    ],
    "sg:phone":"+1 507 332 7823",
    "sg:postcode":"56052",
    "sg:province":"MN",
    "sg:tags":[
        "welding"
    ],
    "wof:name":"Rice Lake Fab Inc",
    "wof:placetype":"venue"
},
  "geometry": {"coordinates":[-93.48066900000001,44.316601],"type":"Point"}
}