{
  "type": "Feature",
  "properties": {
    "addr:full":"9571 140th St NW South Haven MN 55382",
    "addr:housenumber":"9571",
    "addr:postcode":"55382",
    "addr:street":"140Th St Nw;Haven",
    "iso:country":"US",
    "sg:address":"9571 140th St NW",
    "sg:city":"South Haven",
    "sg:classifiers":[
        {
            "category":"Professional",
            "type":"Services"
        }
    ],
    "sg:phone":"+1 320 558 6342",
    "sg:postcode":"55382",
    "sg:province":"MN",
    "wof:name":"Primitive Origins",
    "wof:placetype":"venue"
},
  "geometry": {"coordinates":[-94.08037,45.354813],"type":"Point"}
}