{
  "type": "Feature",
  "properties": {
    "iso:country":"US",
    "sg:address":"21800 290th St",
    "sg:city":"Rushmore",
    "sg:phone":"+1 507 478 4364",
    "sg:postcode":"56168",
    "sg:province":"MN",
    "sg:tags":[
        "farm",
        "corn",
        "grain",
        "cash"
    ],
    "wof:name":"H Groenewold",
    "wof:placetype":"venue"
},
  "geometry": {"coordinates":[-95.818079,43.572534],"type":"Point"}
}