{
  "type": "Feature",
  "properties": {
    "addr:full":"1717 English St Maplewood MN 55109",
    "addr:housenumber":"1717",
    "addr:postcode":"55109",
    "addr:street":"English St",
    "iso:country":"US",
    "sg:address":"1717 English St",
    "sg:city":"Maplewood",
    "sg:classifiers":[
        {
            "category":"Organizations",
            "subcategory":"Religious Organization",
            "type":"Services"
        }
    ],
    "sg:phone":"+1 651 776 1536",
    "sg:postcode":"55109",
    "sg:province":"MN",
    "sg:tags":[
        "church"
    ],
    "sg:website":"www.lakephalencommunitychurch.org",
    "wof:name":"Lake Phalen Community Church",
    "wof:placetype":"venue"
},
  "geometry": {"coordinates":[-93.045771,44.994531],"type":"Point"}
}