{
  "type": "Feature",
  "properties": {
    "iso:country":"US",
    "sg:address":"2408 4th St NW",
    "sg:city":"Austin",
    "sg:classifiers":[
        {
            "category":"Retail",
            "subcategory":"Auto Repair",
            "type":"Services"
        }
    ],
    "sg:phone":"+1 507 437 3708",
    "sg:postcode":"55912",
    "sg:province":"MN",
    "sg:tags":[
        "repairing",
        "transmission",
        "general",
        "automobile"
    ],
    "wof:name":"Keith's Repair",
    "wof:placetype":"venue"
},
  "geometry": {"coordinates":[-92.979491,43.691696],"type":"Point"}
}