{
  "type": "Feature",
  "properties": {
    "addr:full":"5600 SE 14th Ave Owatonna MN 55060",
    "addr:housenumber":"5600",
    "addr:postcode":"55060",
    "addr:street":"Se 14Th Ave",
    "iso:country":"US",
    "sg:address":"5600 SE 14th Ave",
    "sg:city":"Owatonna",
    "sg:classifiers":[
        {
            "category":"Professional",
            "type":"Services"
        }
    ],
    "sg:phone":"+1 507 451 0705",
    "sg:postcode":"55060",
    "sg:province":"MN",
    "wof:name":"Timothy J Nelson",
    "wof:placetype":"venue"
},
  "geometry": {"coordinates":[-93.20585,44.013832],"type":"Point"}
}