{
  "type": "Feature",
  "properties": {
    "addr:full":"212 Jones St Eveleth MN 55734",
    "addr:housenumber":"212",
    "addr:postcode":"55734",
    "addr:street":"Jones St",
    "iso:country":"US",
    "sg:address":"212 Jones St",
    "sg:city":"Eveleth",
    "sg:classifiers":[
        {
            "category":"Wholesale",
            "subcategory":"Beer",
            "type":"Manufacturing & Wholesale Goods"
        }
    ],
    "sg:phone":"+1 218 744 5381",
    "sg:postcode":"55734",
    "sg:province":"MN",
    "sg:tags":[
        "ale"
    ],
    "wof:name":"Mahnich Distributing Co",
    "wof:placetype":"venue"
},
  "geometry": {"coordinates":[-92.541353,47.463248],"type":"Point"}
}