{
  "type": "Feature",
  "properties": {
    "addr:full":"9455 215th St W Lakeville MN 55044",
    "addr:housenumber":"9455",
    "addr:postcode":"55044",
    "addr:street":"215Th St W",
    "iso:country":"US",
    "sg:address":"9455 215th St W",
    "sg:city":"Lakeville",
    "sg:classifiers":[
        {
            "category":"Freight",
            "type":"Transportation"
        }
    ],
    "sg:phone":"+1 952 469 4900",
    "sg:postcode":"55044",
    "sg:province":"MN",
    "sg:tags":[
        "special"
    ],
    "wof:name":"Lakeville Storage",
    "wof:placetype":"venue"
},
  "geometry": {"coordinates":[-93.255911,44.638001],"type":"Point"}
}