{
  "type": "Feature",
  "properties": {
    "iso:country":"US",
    "sg:address":"2014 Prairie Ln SW",
    "sg:city":"Willmar",
    "sg:classifiers":[
        {
            "category":"Real Estate",
            "subcategory":"Real Estate Services",
            "type":"Services"
        },
        {
            "category":"Building & Trades",
            "subcategory":"Cleaning & Sanitation",
            "type":"Services"
        }
    ],
    "sg:phone":"+1 320 231 3264",
    "sg:postcode":"56201",
    "sg:province":"MN",
    "sg:tags":[
        "maintenance",
        "cleaners-interior"
    ],
    "wof:name":"Anderson Cleaning Service",
    "wof:placetype":"venue"
},
  "geometry": {"coordinates":[-95.054962,45.10122],"type":"Point"}
}