{
  "type": "Feature",
  "properties": {
    "addr:full":"64 Ridge Rd Burnsville MN 55337",
    "addr:housenumber":"64",
    "addr:postcode":"55337",
    "addr:street":"Ridge Rd",
    "iso:country":"US",
    "sg:address":"64 Ridge Rd",
    "sg:city":"Burnsville",
    "sg:classifiers":[
        {
            "category":"Retail",
            "subcategory":"Repair Shop",
            "type":"Services"
        }
    ],
    "sg:phone":"+1 952 894 4465",
    "sg:postcode":"55337",
    "sg:province":"MN",
    "sg:tags":[
        "refrigeration"
    ],
    "wof:name":"Lance Lloyd Hanson",
    "wof:placetype":"venue"
},
  "geometry": {"coordinates":[-93.280069,44.759975],"type":"Point"}
}