{
  "type": "Feature",
  "properties": {
    "addr:full":"100 Dublin Rd Apt 3322 Mankato MN 56001",
    "addr:housenumber":"100",
    "addr:postcode":"3322;56001",
    "addr:street":"Dublin Rd Apt",
    "iso:country":"US",
    "sg:address":"100 Dublin Rd Apt 3322",
    "sg:city":"Mankato",
    "sg:classifiers":[
        {
            "category":"Personal",
            "subcategory":"Beauty Salon",
            "type":"Services"
        }
    ],
    "sg:phone":"+1 507 381 9870",
    "sg:postcode":"56001",
    "sg:province":"MN",
    "wof:name":"Generations Spa",
    "wof:placetype":"venue"
},
  "geometry": {"coordinates":[-93.96571400000001,44.16996],"type":"Point"}
}