{
  "type": "Feature",
  "properties": {
    "addr:full":"31010 651st Ave Gibbon MN 55335",
    "addr:housenumber":"31010",
    "addr:postcode":"55335",
    "addr:street":"651St Ave",
    "iso:country":"US",
    "sg:address":"31010 651st Ave",
    "sg:city":"Gibbon",
    "sg:phone":"+1 507 834 6740",
    "sg:postcode":"55335",
    "sg:province":"MN",
    "sg:tags":[
        "farm",
        "grain",
        "cash"
    ],
    "wof:name":"Carolyn Rathman",
    "wof:placetype":"venue"
},
  "geometry": {"coordinates":[-94.573424,44.500151],"type":"Point"}
}