{
  "type": "Feature",
  "properties": {
    "addr:full":"2223 6th St NE Minneapolis MN 55418",
    "addr:housenumber":"2223",
    "addr:postcode":"55418",
    "addr:street":"6Th St Ne",
    "iso:country":"US",
    "sg:address":"2223 6th St NE",
    "sg:city":"Minneapolis",
    "sg:classifiers":[
        {
            "category":"Shopping",
            "subcategory":"Books",
            "type":"Retail Goods"
        }
    ],
    "sg:phone":"+1 612 789 5074",
    "sg:postcode":"55418",
    "sg:province":"MN",
    "sg:tags":[
        "store"
    ],
    "wof:name":"Glued To Tube Books",
    "wof:placetype":"venue"
},
  "geometry": {"coordinates":[-93.259146,45.010239],"type":"Point"}
}