{
  "type": "Feature",
  "properties": {
    "iso:country":"US",
    "sg:address":"33438 535 Ave",
    "sg:city":"Park Rapids",
    "sg:classifiers":[
        {
            "category":"Building & Trades",
            "subcategory":"Construction",
            "type":"Services"
        }
    ],
    "sg:phone":"+1 218 732 5345",
    "sg:postcode":"56470",
    "sg:province":"MN",
    "sg:tags":[
        "excavating",
        "work"
    ],
    "wof:name":"Thelens Excavating",
    "wof:placetype":"venue"
},
  "geometry": {"coordinates":[-95.265282,47.055748],"type":"Point"}
}