{
  "type": "Feature",
  "properties": {
    "iso:country":"US",
    "sg:address":"103 3rd St W",
    "sg:city":"Northfield",
    "sg:classifiers":[
        {
            "category":"Professional",
            "subcategory":"Accounting & Tax Preparation",
            "type":"Services"
        }
    ],
    "sg:phone":"+1 507 645 8735",
    "sg:postcode":"55057",
    "sg:province":"MN",
    "sg:tags":[
        "payroll"
    ],
    "wof:name":"Tim O'Connell",
    "wof:placetype":"venue"
},
  "geometry": {"coordinates":[-93.16247,44.457196],"type":"Point"}
}