{
  "type": "Feature",
  "properties": {
    "iso:country":"US",
    "sg:address":"819 S Swift Ave",
    "sg:city":"Litchfield",
    "sg:classifiers":[
        {
            "category":"Restaurant",
            "type":"Food & Drink"
        }
    ],
    "sg:phone":"+1 320 693 3711",
    "sg:postcode":"55355",
    "sg:province":"MN",
    "wof:name":"J & J Meyer Inc",
    "wof:placetype":"venue"
},
  "geometry": {"coordinates":[-94.53228799999999,45.117576],"type":"Point"}
}