{
  "type": "Feature",
  "properties": {
    "iso:country":"US",
    "sg:address":"1481 Co Rd 5",
    "sg:city":"Longville",
    "sg:classifiers":[
        {
            "category":"Real Estate",
            "subcategory":"Real Estate Services",
            "type":"Services"
        }
    ],
    "sg:phone":"+1 218 363 2656",
    "sg:postcode":"56655",
    "sg:province":"MN",
    "sg:tags":[
        "company",
        "title"
    ],
    "wof:name":"Northland Title & Abstract",
    "wof:placetype":"venue"
},
  "geometry": {"coordinates":[-94.211482,46.986295],"type":"Point"}
}