{
  "type": "Feature",
  "properties": {
    "addr:full":"1250 W Broadway Ave Minneapolis MN 55411",
    "addr:housenumber":"1250",
    "addr:postcode":"55411",
    "addr:street":"W Broadway Ave",
    "iso:country":"US",
    "sg:address":"1250 W Broadway Ave",
    "sg:city":"Minneapolis",
    "sg:classifiers":[
        {
            "category":"Social Services",
            "type":"Services"
        }
    ],
    "sg:phone":"+1 612 287 1290",
    "sg:postcode":"55411",
    "sg:province":"MN",
    "sg:website":"www.mul.org",
    "wof:name":"Fresh Start Academy",
    "wof:placetype":"venue"
},
  "geometry": {"coordinates":[-93.29661,44.999219],"type":"Point"}
}