{
  "type": "Feature",
  "properties": {
    "iso:country":"US",
    "sg:address":"3445 Girard Ave S",
    "sg:city":"Minneapolis",
    "sg:classifiers":[
        {
            "category":"Social Services",
            "subcategory":"Child Care",
            "type":"Services"
        }
    ],
    "sg:phone":"+1 612 822 0626",
    "sg:postcode":"55408",
    "sg:province":"MN",
    "sg:tags":[
        "adoption"
    ],
    "sg:website":"http://www.afamilyjourney.org",
    "wof:name":"A Family Journey Adoption Agen",
    "wof:placetype":"venue"
},
  "geometry": {"coordinates":[-93.297088,44.940497],"type":"Point"}
}