{
  "type": "Feature",
  "properties": {
    "addr:full":"1417 Barnes Place Minneapolis MN 55411",
    "addr:housenumber":"1417",
    "addr:postcode":"55411",
    "addr:street":"Barnes Place",
    "iso:country":"US",
    "sg:address":"1417 Barnes Place",
    "sg:city":"Minneapolis",
    "sg:classifiers":[
        {
            "category":"Personal",
            "type":"Services"
        }
    ],
    "sg:phone":"+1 612 369 8961",
    "sg:postcode":"55411",
    "sg:province":"MN",
    "sg:tags":[
        "mover",
        "full",
        "storage"
    ],
    "wof:name":"PAS Moving and Storage",
    "wof:placetype":"venue"
},
  "geometry": {"coordinates":[-93.29849,44.988124],"type":"Point"}
}