{
  "type": "Feature",
  "properties": {
    "addr:full":"540 S 2nd St La Crescent MN 55947",
    "addr:housenumber":"540",
    "addr:postcode":"55947",
    "addr:street":"S 2Nd St;Crescent",
    "iso:country":"US",
    "sg:address":"540 S 2nd St",
    "sg:city":"La Crescent",
    "sg:classifiers":[
        {
            "category":"Social Services",
            "subcategory":"Child Care",
            "type":"Services"
        }
    ],
    "sg:phone":"+1 507 895 6773",
    "sg:postcode":"55947",
    "sg:province":"MN",
    "sg:tags":[
        "day",
        "provides"
    ],
    "wof:name":"Leslie A Kreibich",
    "wof:placetype":"venue"
},
  "geometry": {"coordinates":[-91.309753,43.827232],"type":"Point"}
}