{
  "type": "Feature",
  "properties": {
    "addr:full":"3645 Hermann Ct NE Rochester MN 55906",
    "addr:housenumber":"3645",
    "addr:postcode":"55906",
    "addr:street":"Hermann Ct Ne",
    "iso:country":"US",
    "sg:address":"3645 Hermann Ct NE",
    "sg:city":"Rochester",
    "sg:classifiers":[
        {
            "category":"Professional",
            "subcategory":"Business Services",
            "type":"Services"
        }
    ],
    "sg:phone":"+1 507 288 8160",
    "sg:postcode":"55906",
    "sg:province":"MN",
    "sg:tags":[
        "auctioneer"
    ],
    "wof:name":"Hermann Auction Svc",
    "wof:placetype":"venue"
},
  "geometry": {"coordinates":[-92.411655,44.058706],"type":"Point"}
}