{
  "type": "Feature",
  "properties": {
    "addr:full":"39719 149th Ave Menahga MN 56464",
    "addr:housenumber":"39719",
    "addr:postcode":"56464",
    "addr:street":"149Th Ave",
    "iso:country":"US",
    "sg:address":"39719 149th Ave",
    "sg:city":"Menahga",
    "sg:classifiers":[
        {
            "category":"Professional",
            "subcategory":"Business Services",
            "type":"Services"
        }
    ],
    "sg:phone":"+1 218 583 2193",
    "sg:postcode":"56464",
    "sg:province":"MN",
    "sg:tags":[
        "water",
        "treatment"
    ],
    "wof:name":"Farmgard Water Treatment",
    "wof:placetype":"venue"
},
  "geometry": {"coordinates":[-95.058869,46.79774],"type":"Point"}
}