{
  "type": "Feature",
  "properties": {
    "addr:full":"1308 Hwy 13 E Burnsville MN 55337",
    "addr:housenumber":"1308",
    "addr:postcode":"55337",
    "addr:street":"Hwy 13 E",
    "iso:country":"US",
    "sg:address":"1308 Hwy 13 E",
    "sg:city":"Burnsville",
    "sg:classifiers":[
        {
            "category":"Retail",
            "subcategory":"Auto Repair",
            "type":"Services"
        }
    ],
    "sg:phone":"+1 952 890 1907",
    "sg:postcode":"55337",
    "sg:province":"MN",
    "sg:tags":[
        "automobile",
        "lubrication"
    ],
    "wof:name":"Valvoline Instant Oil Change",
    "wof:placetype":"venue"
},
  "geometry": {"coordinates":[-93.255937,44.784224],"type":"Point"}
}