{
  "type": "Feature",
  "properties": {
    "addr:full":"13705 26th Ave N Minneapolis MN 55441",
    "addr:housenumber":"13705",
    "addr:postcode":"55441",
    "addr:street":"26Th Ave N",
    "iso:country":"US",
    "sg:address":"13705 26th Ave N",
    "sg:city":"Minneapolis",
    "sg:classifiers":[
        {
            "category":"Manufacturing",
            "subcategory":"Tools & Machinery",
            "type":"Manufacturing & Wholesale Goods"
        }
    ],
    "sg:phone":"+1 763 551 1125",
    "sg:postcode":"55441",
    "sg:province":"MN",
    "sg:tags":[
        "electrical",
        "electric",
        "fence",
        "mfg"
    ],
    "sg:website":"www.watersinst.com",
    "wof:name":"Waters Instruments Inc",
    "wof:placetype":"venue"
},
  "geometry": {"coordinates":[-93.453833,45.007437],"type":"Point"}
}