{
  "type": "Feature",
  "properties": {
    "addr:full":"9515 Nathan Ln N Osseo MN 55369",
    "addr:housenumber":"9515",
    "addr:postcode":"55369",
    "addr:street":"Nathan Ln N",
    "iso:country":"US",
    "sg:address":"9515 Nathan Ln N",
    "sg:city":"Osseo",
    "sg:classifiers":[
        {
            "category":"Farming",
            "subcategory":"Farm",
            "type":"Manufacturing & Wholesale Goods"
        }
    ],
    "sg:phone":"+1 763 425 1461",
    "sg:postcode":"55369",
    "sg:province":"MN",
    "sg:tags":[
        "crop",
        "general"
    ],
    "wof:name":"Roger Kiekow",
    "wof:placetype":"venue"
},
  "geometry": {"coordinates":[-93.40698500000001,45.128443],"type":"Point"}
}