{
  "type": "Feature",
  "properties": {
    "iso:country":"US",
    "sg:address":"31362 230th St",
    "sg:city":"Winnebago",
    "sg:classifiers":[
        {
            "category":"Freight",
            "type":"Transportation"
        }
    ],
    "sg:phone":"+1 507 526 4729",
    "sg:postcode":"56098",
    "sg:province":"MN",
    "sg:tags":[
        "operator",
        "local",
        "trucking"
    ],
    "wof:name":"T&L Trucking",
    "wof:placetype":"venue"
},
  "geometry": {"coordinates":[-94.247288,43.818427],"type":"Point"}
}