{
  "type": "Feature",
  "properties": {
    "addr:full":"314 2nd St E Hastings MN 55033",
    "addr:housenumber":"314",
    "addr:postcode":"55033",
    "addr:street":"2Nd St E",
    "iso:country":"US",
    "sg:address":"314 2nd St E",
    "sg:city":"Hastings",
    "sg:classifiers":[
        {
            "category":"Health Services",
            "subcategory":"Chiropractor",
            "type":"Services"
        }
    ],
    "sg:phone":"+1 651 437 9411",
    "sg:postcode":"55033",
    "sg:province":"MN",
    "wof:name":"Rupp Chiropractic",
    "wof:placetype":"venue"
},
  "geometry": {"coordinates":[-92.848809,44.744272],"type":"Point"}
}