{
  "type": "Feature",
  "properties": {
    "iso:country":"US",
    "sg:address":"803 N Nokomis St",
    "sg:city":"Alexandria",
    "sg:classifiers":[
        {
            "category":"Banks & Credit Unions",
            "subcategory":"Investment Brokerage",
            "type":"Services"
        }
    ],
    "sg:phone":"+1 320 763 2160",
    "sg:postcode":"56308",
    "sg:province":"MN",
    "sg:tags":[
        "security"
    ],
    "wof:name":"Vipond Financial Svc Co",
    "wof:placetype":"venue"
},
  "geometry": {"coordinates":[-95.36708900000001,45.899168],"type":"Point"}
}