{
  "type": "Feature",
  "properties": {
    "addr:full":"112 4th St S Gaylord MN 55307",
    "addr:housenumber":"112",
    "addr:postcode":"55307",
    "addr:street":"4Th St S",
    "iso:country":"US",
    "sg:address":"112 4th St S",
    "sg:city":"Gaylord",
    "sg:classifiers":[
        {
            "category":"Home & Garden",
            "subcategory":"Hardware",
            "type":"Retail Goods"
        }
    ],
    "sg:phone":"+1 507 237 5241",
    "sg:postcode":"55307",
    "sg:province":"MN",
    "wof:name":"Brandt's Ok Hardware",
    "wof:placetype":"venue"
},
  "geometry": {"coordinates":[-94.220596,44.549445],"type":"Point"}
}