{
  "type": "Feature",
  "properties": {
    "addr:full":"1110 Trailwood N Hopkins MN 55343",
    "addr:housenumber":"1110",
    "addr:postcode":"55343",
    "addr:street":"Trailwood N",
    "iso:country":"US",
    "sg:address":"1110 Trailwood N",
    "sg:city":"Hopkins",
    "sg:classifiers":[
        {
            "category":"Building & Trades",
            "subcategory":"Landscaping Services",
            "type":"Services"
        },
        {
            "category":"Home & Garden",
            "subcategory":"Garden Supply",
            "type":"Retail Goods"
        }
    ],
    "sg:phone":"+1 952 938 3829",
    "sg:postcode":"55343",
    "sg:province":"MN",
    "sg:tags":[
        "lawn",
        "installation",
        "sprinkler",
        "sprinklers-garden",
        "system",
        "supervisory"
    ],
    "wof:name":"Sprinkler Services On Demand",
    "wof:placetype":"venue"
},
  "geometry": {"coordinates":[-93.415093,44.90955],"type":"Point"}
}