{
  "type": "Feature",
  "properties": {
    "addr:full":"5380 7th St NE Minneapolis MN 55421",
    "addr:housenumber":"5380",
    "addr:postcode":"55421",
    "addr:street":"7Th St Ne",
    "iso:country":"US",
    "sg:address":"5380 7th St NE",
    "sg:city":"Minneapolis",
    "sg:classifiers":[
        {
            "category":"Social Services",
            "subcategory":"Child Care",
            "type":"Services"
        }
    ],
    "sg:phone":"+1 763 572 9169",
    "sg:postcode":"55421",
    "sg:province":"MN",
    "sg:tags":[
        "daycare",
        "provider"
    ],
    "wof:name":"Carols Day Care",
    "wof:placetype":"venue"
},
  "geometry": {"coordinates":[-93.25784,45.065644],"type":"Point"}
}