{
  "type": "Feature",
  "properties": {
    "iso:country":"US",
    "sg:address":"12537 Danbury Way",
    "sg:city":"Rosemount",
    "sg:classifiers":[
        {
            "category":"Building & Trades",
            "subcategory":"Plumbing",
            "type":"Services"
        }
    ],
    "sg:phone":"+1 651 423 3391",
    "sg:postcode":"55068",
    "sg:province":"MN",
    "sg:tags":[
        "heating",
        "contractor"
    ],
    "wof:name":"South River Heating & Cooling",
    "wof:placetype":"venue"
},
  "geometry": {"coordinates":[-93.143736,44.763552],"type":"Point"}
}