{
  "type": "Feature",
  "properties": {
    "iso:country":"US",
    "sg:address":"6433 Walleye Ln NW",
    "sg:city":"Williams",
    "sg:classifiers":[
        {
            "category":"Travel",
            "subcategory":"Hotels & Motels",
            "type":"Entertainment"
        },
        {
            "category":"Travel",
            "subcategory":"Resort",
            "type":"Entertainment"
        }
    ],
    "sg:phone":"+1 218 783 6345",
    "sg:postcode":"56686",
    "sg:province":"MN",
    "wof:name":"Winter-Sett Resort",
    "wof:placetype":"venue"
},
  "geometry": {"coordinates":[-94.912818,48.867183],"type":"Point"}
}