{
  "type": "Feature",
  "properties": {
    "iso:country":"US",
    "sg:address":"1730 New Brighton Blvd",
    "sg:city":"Minneapolis",
    "sg:classifiers":[
        {
            "category":"Shopping",
            "subcategory":"Tobacco",
            "type":"Retail Goods"
        }
    ],
    "sg:phone":"+1 612 706 0863",
    "sg:postcode":"55413",
    "sg:province":"MN",
    "sg:tags":[
        "shop"
    ],
    "wof:name":"Smokers Haven",
    "wof:placetype":"venue"
},
  "geometry": {"coordinates":[-93.22730300000001,45.0051],"type":"Point"}
}