{
  "type": "Feature",
  "properties": {
    "iso:country":"US",
    "sg:address":"11325 Co Rd 20",
    "sg:city":"Watertown",
    "sg:classifiers":[
        {
            "category":"Farming",
            "subcategory":"Livestock Farm",
            "type":"Manufacturing & Wholesale Goods"
        }
    ],
    "sg:phone":"+1 952 955 3348",
    "sg:postcode":"55388",
    "sg:province":"MN",
    "sg:tags":[
        "specialty",
        "animal"
    ],
    "wof:name":"Ames Farm",
    "wof:placetype":"venue"
},
  "geometry": {"coordinates":[-93.81025699999999,44.96318],"type":"Point"}
}