{
  "type": "Feature",
  "properties": {
    "addr:full":"2720 Winnetka Ave Minneapolis MN 55427",
    "addr:housenumber":"2720",
    "addr:postcode":"55427",
    "addr:street":"Winnetka Ave",
    "iso:country":"US",
    "sg:address":"2720 Winnetka Ave",
    "sg:city":"Minneapolis",
    "sg:classifiers":[
        {
            "category":"Food & Beverages",
            "subcategory":"Groceries & Convenience Stores",
            "type":"Retail Goods"
        }
    ],
    "sg:phone":"+1 763 746 2377",
    "sg:postcode":"55427",
    "sg:province":"MN",
    "sg:tags":[
        "grocer"
    ],
    "wof:name":"New Hope Grocery",
    "wof:placetype":"venue"
},
  "geometry": {"coordinates":[-93.380219,45.008803],"type":"Point"}
}