{
  "type": "Feature",
  "properties": {
    "addr:full":"2209 Childs Rd St Paul MN 55106",
    "addr:housenumber":"2209",
    "addr:postcode":"55106",
    "addr:street":"Childs Rd",
    "iso:country":"US",
    "sg:address":"2209 Childs Rd",
    "sg:city":"St Paul",
    "sg:classifiers":[
        {
            "category":"Manufacturing",
            "subcategory":"Petroleum Products",
            "type":"Manufacturing & Wholesale Goods"
        }
    ],
    "sg:phone":"+1 651 774 9763",
    "sg:postcode":"55106",
    "sg:province":"MN",
    "sg:tags":[
        "asphalt",
        "mfg"
    ],
    "wof:name":"Koch Materials Company",
    "wof:placetype":"venue"
},
  "geometry": {"coordinates":[-93.049296,44.939251],"type":"Point"}
}