{
  "type": "Feature",
  "properties": {
    "addr:full":"5930 Shingle Creek Pkwy Minneapolis MN 55430",
    "addr:housenumber":"5930",
    "addr:postcode":"55430",
    "addr:street":"Shingle Creek Pkwy",
    "iso:country":"US",
    "sg:address":"5930 Shingle Creek Pkwy",
    "sg:city":"Minneapolis",
    "sg:classifiers":[
        {
            "category":"Shopping",
            "subcategory":"Department Store",
            "type":"Retail Goods"
        },
        {
            "category":"Building & Trades",
            "subcategory":"Cleaning & Sanitation",
            "type":"Services"
        }
    ],
    "sg:phone":"+1 763 746 7333",
    "sg:postcode":"55430",
    "sg:province":"MN",
    "sg:tags":[
        "cleaner",
        "supply",
        "house",
        "contractor",
        "equipment",
        "cleaning-industrial"
    ],
    "sg:website":"http://www.janiking.com",
    "wof:name":"Jani-King",
    "wof:placetype":"venue"
},
  "geometry": {"coordinates":[-93.31237,45.063012],"type":"Point"}
}