{
  "type": "Feature",
  "properties": {
    "addr:full":"12676 River Rd North Branch MN 55056",
    "addr:housenumber":"12676",
    "addr:postcode":"55056",
    "addr:street":"River Rd",
    "iso:country":"US",
    "sg:address":"12676 River Rd",
    "sg:city":"North Branch",
    "sg:classifiers":[
        {
            "category":"Professional",
            "type":"Services"
        }
    ],
    "sg:phone":"+1 651 674 0767",
    "sg:postcode":"55056",
    "sg:province":"MN",
    "wof:name":"Kurt Wyandt",
    "wof:placetype":"venue"
},
  "geometry": {"coordinates":[-92.849538,45.550505],"type":"Point"}
}