{
  "type": "Feature",
  "properties": {
    "iso:country":"US",
    "sg:address":"5220 Hwy 63 N",
    "sg:city":"Rochester",
    "sg:classifiers":[
        {
            "category":"Retail",
            "subcategory":"Repair Shop",
            "type":"Services"
        }
    ],
    "sg:phone":"+1 507 282 9867",
    "sg:postcode":"55906",
    "sg:province":"MN",
    "sg:tags":[
        "marina",
        "special"
    ],
    "wof:name":"Lock Away Storage",
    "wof:placetype":"venue"
},
  "geometry": {"coordinates":[-92.450124,44.076414],"type":"Point"}
}