{
  "type": "Feature",
  "properties": {
    "addr:full":"16401 255th St Fergus Falls MN 56537",
    "addr:housenumber":"16401",
    "addr:postcode":"56537",
    "addr:street":"255Th St",
    "iso:country":"US",
    "sg:address":"16401 255th St",
    "sg:city":"Fergus Falls",
    "sg:classifiers":[
        {
            "category":"Farming",
            "subcategory":"Livestock Farm",
            "type":"Manufacturing & Wholesale Goods"
        }
    ],
    "sg:phone":"+1 218 739 2543",
    "sg:postcode":"56537",
    "sg:province":"MN",
    "sg:tags":[
        "beef",
        "feedlot",
        "cattle"
    ],
    "wof:name":"L Steve Roeh",
    "wof:placetype":"venue"
},
  "geometry": {"coordinates":[-96.145917,46.333113],"type":"Point"}
}