{
  "type": "Feature",
  "properties": {
    "addr:full":"1010 Idaho Ave N Minneapolis MN 55427",
    "addr:housenumber":"1010",
    "addr:postcode":"55427",
    "addr:street":"Idaho Ave N",
    "iso:country":"US",
    "sg:address":"1010 Idaho Ave N",
    "sg:city":"Minneapolis",
    "sg:classifiers":[
        {
            "category":"Home & Garden",
            "subcategory":"Carpets & Floor Coverings",
            "type":"Retail Goods"
        }
    ],
    "sg:phone":"+1 651 226 9663",
    "sg:postcode":"55427",
    "sg:province":"MN",
    "sg:tags":[
        "hardwood",
        "flooring",
        "contractor"
    ],
    "sg:website":"http://www.woodchuckflooringmn.com",
    "wof:name":"Woodchuck Flooring",
    "wof:placetype":"venue"
},
  "geometry": {"coordinates":[-93.365731,44.989659],"type":"Point"}
}