{
  "type": "Feature",
  "properties": {
    "addr:full":"1929 Northern Viola Ln NE Rochester MN 55906",
    "addr:housenumber":"1929",
    "addr:postcode":"55906",
    "addr:street":"Northern Viola Ln Ne",
    "iso:country":"US",
    "sg:address":"1929 Northern Viola Ln NE",
    "sg:city":"Rochester",
    "sg:classifiers":[
        {
            "category":"Personal",
            "subcategory":"Beauty Salon",
            "type":"Services"
        }
    ],
    "sg:phone":"+1 507 292 1900",
    "sg:postcode":"55906",
    "sg:province":"MN",
    "sg:tags":[
        "shop"
    ],
    "wof:name":"Sherry Johnsons Salon",
    "wof:placetype":"venue"
},
  "geometry": {"coordinates":[-92.433716,44.048365],"type":"Point"}
}