{
  "type": "Feature",
  "properties": {
    "addr:full":"17965 535th St West Concord MN 55985",
    "addr:housenumber":"17965",
    "addr:postcode":"55985",
    "addr:street":"535Th St",
    "iso:country":"US",
    "sg:address":"17965 535th St",
    "sg:city":"West Concord",
    "sg:phone":"+1 507 527 2496",
    "sg:postcode":"55985",
    "sg:province":"MN",
    "sg:tags":[
        "real",
        "lessor",
        "farm",
        "crop",
        "field",
        "property"
    ],
    "wof:name":"Don Vrieze Fram",
    "wof:placetype":"venue"
},
  "geometry": {"coordinates":[-92.874296,44.174653],"type":"Point"}
}