{
  "type": "Feature",
  "properties": {
    "addr:full":"5710 W 36th St Minneapolis MN 55416",
    "addr:housenumber":"5710",
    "addr:postcode":"55416",
    "addr:street":"W 36Th St",
    "iso:country":"US",
    "sg:address":"5710 W 36th St",
    "sg:city":"Minneapolis",
    "sg:classifiers":[
        {
            "category":"Professional",
            "type":"Services"
        }
    ],
    "sg:phone":"+1 952 920 8071",
    "sg:postcode":"55416",
    "sg:province":"MN",
    "sg:tags":[
        "establishment"
    ],
    "wof:name":"Design Group MB",
    "wof:placetype":"venue"
},
  "geometry": {"coordinates":[-93.352941,44.937858],"type":"Point"}
}