{
  "type": "Feature",
  "properties": {
    "iso:country":"US",
    "sg:address":"1635 Greenview Dr SW",
    "sg:city":"Rochester",
    "sg:classifiers":[
        {
            "category":"Utilities",
            "subcategory":"Fuel Oil & Lpg",
            "type":"Services"
        }
    ],
    "sg:phone":"+1 507 252 1200",
    "sg:postcode":"55902",
    "sg:province":"MN",
    "sg:tags":[
        "liquefied",
        "gas",
        "petroleum"
    ],
    "wof:name":"Country Propane",
    "wof:placetype":"venue"
},
  "geometry": {"coordinates":[-92.487168,44.001625],"type":"Point"}
}