{
  "type": "Feature",
  "properties": {
    "iso:country":"US",
    "sg:address":"3201 County Road 42 W # 104",
    "sg:city":"Burnsville",
    "sg:classifiers":[
        {
            "category":"Airline",
            "type":"Transportation"
        }
    ],
    "sg:phone":"+1 952 223 0317",
    "sg:postcode":"55306",
    "sg:province":"MN",
    "sg:tags":[
        "pilot"
    ],
    "wof:name":"Newcastle Aviation Partners",
    "wof:placetype":"venue"
},
  "geometry": {"coordinates":[-93.270691,44.740219],"type":"Point"}
}