{
  "type": "Feature",
  "properties": {
    "iso:country":"US",
    "sg:address":"47946 Co Hwy 53",
    "sg:city":"Perham",
    "sg:classifiers":[
        {
            "category":"Farming",
            "subcategory":"Dairy Farm",
            "type":"Manufacturing & Wholesale Goods"
        }
    ],
    "sg:phone":"+1 218 346 4646",
    "sg:postcode":"56573",
    "sg:province":"MN",
    "wof:name":"David Fiedler",
    "wof:placetype":"venue"
},
  "geometry": {"coordinates":[-95.456198,46.646278],"type":"Point"}
}