{
  "type": "Feature",
  "properties": {
    "addr:full":"2106 110th Ave NW Minneapolis MN 55433",
    "addr:housenumber":"2106",
    "addr:postcode":"55433",
    "addr:street":"110Th Ave Nw",
    "iso:country":"US",
    "sg:address":"2106 110th Ave NW",
    "sg:city":"Minneapolis",
    "sg:classifiers":[
        {
            "category":"Retail",
            "subcategory":"Funeral Services",
            "type":"Services"
        }
    ],
    "sg:phone":"+1 763 205 6442",
    "sg:postcode":"55433",
    "sg:province":"MN",
    "sg:tags":[
        "burial",
        "vault"
    ],
    "wof:name":"Minneapolis Closet Vaults Inc",
    "wof:placetype":"venue"
},
  "geometry": {"coordinates":[-93.320313,45.170712],"type":"Point"}
}