{
  "type": "Feature",
  "properties": {
    "addr:full":"603 E 3rd Ave Hewitt MN 56453",
    "addr:housenumber":"603",
    "addr:postcode":"56453",
    "addr:street":"E 3Rd Ave",
    "iso:country":"US",
    "sg:address":"603 E 3rd Ave",
    "sg:city":"Hewitt",
    "sg:classifiers":[
        {
            "category":"Restaurant",
            "type":"Food & Drink"
        }
    ],
    "sg:phone":"+1 218 924 2032",
    "sg:postcode":"56453",
    "sg:province":"MN",
    "wof:name":"Grandma's Place",
    "wof:placetype":"venue"
},
  "geometry": {"coordinates":[-95.085392,46.325753],"type":"Point"}
}