{
  "type": "Feature",
  "properties": {
    "addr:full":"2381 Wilshire Blvd Mound MN 55364",
    "addr:housenumber":"2381",
    "addr:postcode":"55364",
    "addr:street":"Wilshire Blvd",
    "iso:country":"US",
    "sg:address":"2381 Wilshire Blvd",
    "sg:city":"Mound",
    "sg:classifiers":[
        {
            "category":"Utilities",
            "subcategory":"Cable",
            "type":"Services"
        }
    ],
    "sg:phone":"+1 952 472 6416",
    "sg:postcode":"55364",
    "sg:province":"MN",
    "sg:tags":[
        "technician"
    ],
    "wof:name":"Triax Cable Vision",
    "wof:placetype":"venue"
},
  "geometry": {"coordinates":[-93.658013,44.93536],"type":"Point"}
}