{
  "type": "Feature",
  "properties": {
    "iso:country":"US",
    "sg:address":"9235 Morgan Ln",
    "sg:city":"Cologne",
    "sg:classifiers":[
        {
            "category":"Building & Trades",
            "subcategory":"Construction",
            "type":"Services"
        }
    ],
    "sg:phone":"+1 612 385 4094",
    "sg:postcode":"55322",
    "sg:province":"MN",
    "sg:tags":[
        "general",
        "contractor"
    ],
    "wof:name":"J & R Trim Specialist's",
    "wof:placetype":"venue"
},
  "geometry": {"coordinates":[-93.84883000000001,44.838166],"type":"Point"}
}