{
  "type": "Feature",
  "properties": {
    "addr:full":"5353 Wayzata Blvd Minneapolis MN 55416",
    "addr:housenumber":"5353",
    "addr:postcode":"55416",
    "addr:street":"Wayzata Blvd",
    "iso:country":"US",
    "sg:address":"5353 Wayzata Blvd",
    "sg:city":"Minneapolis",
    "sg:classifiers":[
        {
            "category":"Professional",
            "subcategory":"Employment Agencies",
            "type":"Services"
        }
    ],
    "sg:phone":"+1 763 519 0000",
    "sg:postcode":"55416",
    "sg:province":"MN",
    "sg:tags":[
        "opportunity",
        "contractor"
    ],
    "wof:name":"Tmc Management Corporation",
    "wof:placetype":"venue"
},
  "geometry": {"coordinates":[-93.34857599999999,44.970032],"type":"Point"}
}