{
  "type": "Feature",
  "properties": {
    "iso:country":"US",
    "sg:address":"104 S Broadway Ave",
    "sg:city":"Albert Lea",
    "sg:classifiers":[
        {
            "category":"Restaurant",
            "type":"Food & Drink"
        }
    ],
    "sg:phone":"+1 507 373 2428",
    "sg:postcode":"56007",
    "sg:province":"MN",
    "sg:tags":[
        "eating"
    ],
    "wof:name":"Grammas Kitchen",
    "wof:placetype":"venue"
},
  "geometry": {"coordinates":[-93.368793,43.649715],"type":"Point"}
}