{
  "type": "Feature",
  "properties": {
    "iso:country":"US",
    "sg:address":"3024 10th Ave S",
    "sg:city":"Minneapolis",
    "sg:classifiers":[
        {
            "category":"Restaurant",
            "type":"Food & Drink"
        }
    ],
    "sg:phone":"+1 612 823 1371",
    "sg:postcode":"55407",
    "sg:province":"MN",
    "sg:tags":[
        "eating"
    ],
    "wof:name":"Aunties Frydbread",
    "wof:placetype":"venue"
},
  "geometry": {"coordinates":[-93.260178,44.946992],"type":"Point"}
}