{
  "type": "Feature",
  "properties": {
    "iso:country":"US",
    "sg:address":"1849 Danforth Cir",
    "sg:city":"Clearwater",
    "sg:classifiers":[
        {
            "category":"Social Services",
            "subcategory":"Child Care",
            "type":"Services"
        }
    ],
    "sg:phone":"+1 320 558 6077",
    "sg:postcode":"55320",
    "sg:province":"MN",
    "sg:tags":[
        "day"
    ],
    "wof:name":"Nita's Day Care",
    "wof:placetype":"venue"
},
  "geometry": {"coordinates":[-94.07915300000001,45.395671],"type":"Point"}
}