{
  "type": "Feature",
  "properties": {
    "iso:country":"US",
    "sg:address":"16994 Co Rd 6",
    "sg:city":"Madelia",
    "sg:phone":"+1 507 439 6456",
    "sg:postcode":"56062",
    "sg:province":"MN",
    "sg:tags":[
        "farm",
        "corn"
    ],
    "wof:name":"Wellmann Wellmann",
    "wof:placetype":"venue"
},
  "geometry": {"coordinates":[-94.506996,44.108941],"type":"Point"}
}