{
  "type": "Feature",
  "properties": {
    "addr:full":"13448 125th Ave Milaca MN 56353",
    "addr:housenumber":"13448",
    "addr:postcode":"56353",
    "addr:street":"125Th Ave",
    "iso:country":"US",
    "sg:address":"13448 125th Ave",
    "sg:city":"Milaca",
    "sg:classifiers":[
        {
            "category":"Freight",
            "type":"Transportation"
        }
    ],
    "sg:phone":"+1 320 983 2393",
    "sg:postcode":"56353",
    "sg:province":"MN",
    "sg:tags":[
        "operator",
        "local",
        "trucking"
    ],
    "wof:name":"Vansickel Trucking",
    "wof:placetype":"venue"
},
  "geometry": {"coordinates":[-93.667653,45.741803],"type":"Point"}
}