{
  "type": "Feature",
  "properties": {
    "addr:full":"33595 205th St Clements MN 56087",
    "addr:housenumber":"33595",
    "addr:postcode":"56087",
    "addr:street":"205Th St Clements",
    "iso:country":"US",
    "sg:address":"33595 205th St",
    "sg:city":"Clements",
    "sg:classifiers":[
        {
            "category":"Farming",
            "subcategory":"Livestock Farm",
            "type":"Manufacturing & Wholesale Goods"
        }
    ],
    "sg:phone":"+1 507 723 4354",
    "sg:postcode":"56087",
    "sg:province":"MN",
    "sg:tags":[
        "feedlot",
        "hog",
        "or",
        "beef",
        "cattle"
    ],
    "wof:name":"Berg Brothers",
    "wof:placetype":"venue"
},
  "geometry": {"coordinates":[-95.11493400000001,44.347305],"type":"Point"}
}