{
  "type": "Feature",
  "properties": {
    "addr:full":"5204 Marble Lk Rd Two Harbors MN 55616",
    "addr:housenumber":"5204",
    "addr:postcode":"55616",
    "addr:street":"Marble Lk Rd",
    "iso:country":"US",
    "sg:address":"5204 Marble Lk Rd",
    "sg:city":"Two Harbors",
    "sg:classifiers":[
        {
            "category":"Retail",
            "subcategory":"Repair Shop",
            "type":"Services"
        }
    ],
    "sg:phone":"+1 218 834 4392",
    "sg:postcode":"55616",
    "sg:province":"MN",
    "wof:name":"Anderson Piano Service",
    "wof:placetype":"venue"
},
  "geometry": {"coordinates":[-91.644125,47.309316],"type":"Point"}
}