{
  "type": "Feature",
  "properties": {
    "iso:country":"US",
    "sg:address":"5402 Parkdale Dr",
    "sg:city":"Minneapolis",
    "sg:classifiers":[
        {
            "category":"Professional",
            "subcategory":"Research",
            "type":"Services"
        }
    ],
    "sg:phone":"+1 952 544 9724",
    "sg:postcode":"55416",
    "sg:province":"MN",
    "sg:tags":[
        "marketing"
    ],
    "wof:name":"Four Seasons Research Inc",
    "wof:placetype":"venue"
},
  "geometry": {"coordinates":[-93.349468,44.963148],"type":"Point"}
}