{
  "type": "Feature",
  "properties": {
    "iso:country":"US",
    "sg:address":"410 37th Ave N",
    "sg:city":"Saint Cloud",
    "sg:classifiers":[
        {
            "category":"Manufacturing",
            "subcategory":"Printing",
            "type":"Manufacturing & Wholesale Goods"
        }
    ],
    "sg:phone":"+1 320 252 2400",
    "sg:postcode":"56303",
    "sg:province":"MN",
    "sg:tags":[
        "newspaper"
    ],
    "wof:name":"Star Tribune",
    "wof:placetype":"venue"
},
  "geometry": {"coordinates":[-94.203305,45.56146],"type":"Point"}
}