{
  "type": "Feature",
  "properties": {
    "iso:country":"US",
    "sg:address":"6414 Penn Ave S",
    "sg:city":"Minneapolis",
    "sg:classifiers":[
        {
            "category":"Home & Garden",
            "subcategory":"Building Materials",
            "type":"Retail Goods"
        },
        {
            "category":"Wholesale",
            "subcategory":"Painting Supplies",
            "type":"Manufacturing & Wholesale Goods"
        }
    ],
    "sg:phone":"+1 612 861 3316",
    "sg:postcode":"55423",
    "sg:province":"MN",
    "sg:tags":[
        "paint"
    ],
    "wof:name":"Hirshfields Contractor Svc Ctr",
    "wof:placetype":"venue"
},
  "geometry": {"coordinates":[-93.308716,44.885584],"type":"Point"}
}