{
  "type": "Feature",
  "properties": {
    "addr:full":"701 Xenia Ave S Minneapolis MN 55416",
    "addr:housenumber":"701",
    "addr:postcode":"55416",
    "addr:street":"Xenia Ave S",
    "iso:country":"US",
    "sg:address":"701 Xenia Ave S",
    "sg:city":"Minneapolis",
    "sg:classifiers":[
        {
            "category":"Banks & Credit Unions",
            "subcategory":"Investment Brokerage",
            "type":"Services"
        }
    ],
    "sg:phone":"+1 763 923 2200",
    "sg:postcode":"55416",
    "sg:province":"MN",
    "sg:tags":[
        "advisory"
    ],
    "wof:name":"Oak Ridge Financial Services G",
    "wof:placetype":"venue"
},
  "geometry": {"coordinates":[-93.352126,44.973489],"type":"Point"}
}