{
  "type": "Feature",
  "properties": {
    "addr:full":"136 South St Foreston MN 56330",
    "addr:housenumber":"136",
    "addr:postcode":"56330",
    "addr:street":"South St",
    "iso:country":"US",
    "sg:address":"136 South St",
    "sg:city":"Foreston",
    "sg:classifiers":[
        {
            "category":"Freight",
            "type":"Transportation"
        }
    ],
    "sg:phone":"+1 320 294 5243",
    "sg:postcode":"56330",
    "sg:province":"MN",
    "sg:tags":[
        "commercial",
        "storage"
    ],
    "wof:name":"Foreston Mini Storage",
    "wof:placetype":"venue"
},
  "geometry": {"coordinates":[-93.706237,45.732129],"type":"Point"}
}