{
  "type": "Feature",
  "properties": {
    "addr:full":"2057 190th St Marshall MN 56169",
    "addr:housenumber":"2057",
    "addr:postcode":"56169",
    "addr:street":"190Th St",
    "iso:country":"US",
    "sg:address":"2057 190th St",
    "sg:city":"Marshall",
    "sg:classifiers":[
        {
            "category":"Real Estate",
            "subcategory":"Real Estate Operator",
            "type":"Services"
        }
    ],
    "sg:phone":"+1 507 823 4671",
    "sg:postcode":"56169",
    "sg:province":"MN",
    "sg:tags":[
        "property",
        "lessor"
    ],
    "wof:name":"J&J Welding",
    "wof:placetype":"venue"
},
  "geometry": {"coordinates":[-95.88594500000001,44.326455],"type":"Point"}
}