{
  "type": "Feature",
  "properties": {
    "addr:full":"8130 E 6th St Winona MN 55987",
    "addr:housenumber":"8130",
    "addr:postcode":"55987",
    "addr:street":"E 6Th St",
    "iso:country":"US",
    "sg:address":"8130 E 6th St",
    "sg:city":"Winona",
    "sg:classifiers":[
        {
            "category":"Building & Trades",
            "subcategory":"Plumbing",
            "type":"Services"
        }
    ],
    "sg:phone":"+1 507 689 2889",
    "sg:postcode":"55987",
    "sg:province":"MN",
    "sg:tags":[
        "plumber",
        "industrial",
        "contractors-commercial"
    ],
    "wof:name":"Jj's Plumbing & Heating",
    "wof:placetype":"venue"
},
  "geometry": {"coordinates":[-91.76493000000001,44.028444],"type":"Point"}
}