{
  "type": "Feature",
  "properties": {
    "addr:full":"1302 1st Ave Mankato MN 56001",
    "addr:housenumber":"1302",
    "addr:postcode":"56001",
    "addr:street":"1St Ave",
    "iso:country":"US",
    "sg:address":"1302 1st Ave",
    "sg:city":"Mankato",
    "sg:classifiers":[
        {
            "category":"Wholesale",
            "subcategory":"Auto Parts",
            "type":"Manufacturing & Wholesale Goods"
        }
    ],
    "sg:phone":"+1 507 345 3820",
    "sg:postcode":"56001",
    "sg:province":"MN",
    "sg:tags":[
        "automotive",
        "accessory"
    ],
    "wof:name":"Aim Auto & Body Parts Inc",
    "wof:placetype":"venue"
},
  "geometry": {"coordinates":[-93.992654,44.179132],"type":"Point"}
}