{
  "type": "Feature",
  "properties": {
    "addr:full":"1747 Valley Ridge Pl Chanhassen MN 55317",
    "addr:housenumber":"1747",
    "addr:postcode":"55317",
    "addr:street":"Valley Ridge Pl",
    "iso:country":"US",
    "sg:address":"1747 Valley Ridge Pl",
    "sg:city":"Chanhassen",
    "sg:classifiers":[
        {
            "category":"Building & Trades",
            "subcategory":"Construction",
            "type":"Services"
        }
    ],
    "sg:phone":"+1 952 368 9399",
    "sg:postcode":"55317",
    "sg:province":"MN",
    "sg:tags":[
        "painter"
    ],
    "wof:name":"Thomas Painting & LA Rae Dsgn",
    "wof:placetype":"venue"
},
  "geometry": {"coordinates":[-93.566039,44.846055],"type":"Point"}
}