{
  "type": "Feature",
  "properties": {
    "addr:full":"488 Tamarack Ave Long Lake MN 55356",
    "addr:housenumber":"488",
    "addr:postcode":"55356",
    "addr:street":"Tamarack Ave",
    "iso:country":"US",
    "sg:address":"488 Tamarack Ave",
    "sg:city":"Long Lake",
    "sg:classifiers":[
        {
            "category":"Professional",
            "subcategory":"Accounting & Tax Preparation",
            "type":"Services"
        }
    ],
    "sg:phone":"+1 952 473 5563",
    "sg:postcode":"55356",
    "sg:province":"MN",
    "sg:tags":[
        "return",
        "filing"
    ],
    "wof:name":"Computerized Bookkeeping Svc",
    "wof:placetype":"venue"
},
  "geometry": {"coordinates":[-93.581391,44.988202],"type":"Point"}
}