{
  "type": "Feature",
  "properties": {
    "iso:country":"US",
    "sg:address":"1802 7th St NW",
    "sg:city":"Rochester",
    "sg:classifiers":[
        {
            "category":"Home & Garden",
            "subcategory":"Garden Supply",
            "type":"Retail Goods"
        },
        {
            "category":"Shopping",
            "subcategory":"Party Supplies",
            "type":"Retail Goods"
        },
        {
            "category":"Wholesale",
            "subcategory":"Machinery & Supplies",
            "type":"Manufacturing & Wholesale Goods"
        },
        {
            "category":"Building & Trades",
            "subcategory":"Equipment Rental",
            "type":"Services"
        },
        {
            "category":"Home & Garden",
            "subcategory":"Furniture",
            "type":"Retail Goods"
        }
    ],
    "sg:phone":"+1 507 288 2741",
    "sg:postcode":"55901",
    "sg:province":"MN",
    "sg:tags":[
        "renting",
        "lawn",
        "industrial",
        "leasing",
        "favors",
        "mower",
        "decoration",
        "landscaping",
        "yard",
        "store",
        "contractors'"
    ],
    "sg:website":"http://www.rentaldepot.com",
    "wof:name":"Rental Depot",
    "wof:placetype":"venue"
},
  "geometry": {"coordinates":[-92.489329,44.033076],"type":"Point"}
}