{
  "type": "Feature",
  "properties": {
    "addr:full":"965 S Lake Shore Dr Glenwood MN 56334",
    "addr:housenumber":"965",
    "addr:postcode":"56334",
    "addr:street":"S Lake Shore Dr",
    "iso:country":"US",
    "sg:address":"965 S Lake Shore Dr",
    "sg:city":"Glenwood",
    "sg:classifiers":[
        {
            "category":"Recreation",
            "type":"Entertainment"
        }
    ],
    "sg:phone":"+1 320 634 9984",
    "sg:postcode":"56334",
    "sg:province":"MN",
    "sg:tags":[
        "pool",
        "swimming"
    ],
    "wof:name":"Glenwood City Beach",
    "wof:placetype":"venue"
},
  "geometry": {"coordinates":[-95.38686199999999,45.641554],"type":"Point"}
}