{
  "type": "Feature",
  "properties": {
    "iso:country":"US",
    "sg:address":"2410 14th St S",
    "sg:city":"Moorhead",
    "sg:classifiers":[
        {
            "category":"Education",
            "subcategory":"Special Training",
            "type":"Public Place"
        }
    ],
    "sg:phone":"+1 218 287 1663",
    "sg:postcode":"56560",
    "sg:province":"MN",
    "wof:name":"Partners In Learning",
    "wof:placetype":"venue"
},
  "geometry": {"coordinates":[-96.757442,46.849638],"type":"Point"}
}