{
  "type": "Feature",
  "properties": {
    "addr:full":"515 E 1st St Fairmont MN 56031",
    "addr:housenumber":"515",
    "addr:postcode":"56031",
    "addr:street":"E 1St St",
    "iso:country":"US",
    "sg:address":"515 E 1st St",
    "sg:city":"Fairmont",
    "sg:classifiers":[
        {
            "category":"Professional",
            "subcategory":"Management & Consulting",
            "type":"Services"
        }
    ],
    "sg:phone":"+1 507 238 9394",
    "sg:postcode":"56031",
    "sg:province":"MN",
    "sg:tags":[
        "business"
    ],
    "wof:name":"Wollam Intl Grdn Dsn",
    "wof:placetype":"venue"
},
  "geometry": {"coordinates":[-94.45493,43.653144],"type":"Point"}
}