{
  "type": "Feature",
  "properties": {
    "addr:full":"7499 360th Street Way Cannon Falls MN 55009",
    "addr:housenumber":"7499",
    "addr:postcode":"55009",
    "addr:street":"360Th Street Way",
    "iso:country":"US",
    "sg:address":"7499 360th Street Way",
    "sg:city":"Cannon Falls",
    "sg:classifiers":[
        {
            "category":"Manufacturing",
            "subcategory":"Lumber",
            "type":"Manufacturing & Wholesale Goods"
        }
    ],
    "sg:phone":"+1 507 263 5711",
    "sg:postcode":"55009",
    "sg:province":"MN",
    "sg:tags":[
        "company",
        "logging"
    ],
    "wof:name":"Johnson Logging Inc",
    "wof:placetype":"venue"
},
  "geometry": {"coordinates":[-92.879829,44.427498],"type":"Point"}
}