{
  "type": "Feature",
  "properties": {
    "addr:full":"309 Linden St SE Sleepy Eye MN 56085",
    "addr:housenumber":"309",
    "addr:postcode":"56085",
    "addr:street":"Linden St Se;Eye",
    "iso:country":"US",
    "sg:address":"309 Linden St SE",
    "sg:city":"Sleepy Eye",
    "sg:classifiers":[
        {
            "category":"Social Services",
            "subcategory":"Child Care",
            "type":"Services"
        }
    ],
    "sg:phone":"+1 507 794 5630",
    "sg:postcode":"56085",
    "sg:province":"MN",
    "sg:tags":[
        "day"
    ],
    "wof:name":"B & J Tree House Daycare",
    "wof:placetype":"venue"
},
  "geometry": {"coordinates":[-94.719826,44.293025],"type":"Point"}
}