{
  "type": "Feature",
  "properties": {
    "addr:full":"1281 330th Ave Tracy MN 56175",
    "addr:housenumber":"1281",
    "addr:postcode":"56175",
    "addr:street":"330Th Ave",
    "iso:country":"US",
    "sg:address":"1281 330th Ave",
    "sg:city":"Tracy",
    "sg:classifiers":[
        {
            "category":"Manufacturing",
            "subcategory":"Toys & Sporting Goods",
            "type":"Manufacturing & Wholesale Goods"
        }
    ],
    "sg:phone":"+1 507 629 3969",
    "sg:postcode":"56175",
    "sg:province":"MN",
    "sg:tags":[
        "equipment",
        "fishing",
        "mfg"
    ],
    "wof:name":"Jnb Originals Inc",
    "wof:placetype":"venue"
},
  "geometry": {"coordinates":[-95.63393499999999,44.237256],"type":"Point"}
}