{
  "type": "Feature",
  "properties": {
    "addr:full":"7057 Whitehall Rd Shakopee MN 55379",
    "addr:housenumber":"7057",
    "addr:postcode":"55379",
    "addr:street":"Whitehall Rd",
    "iso:country":"US",
    "sg:address":"7057 Whitehall Rd",
    "sg:city":"Shakopee",
    "sg:classifiers":[
        {
            "category":"Shopping",
            "subcategory":"Clothing, Apparel, & Fashions",
            "type":"Retail Goods"
        }
    ],
    "sg:phone":"+1 952 854 3091",
    "sg:postcode":"55379",
    "sg:province":"MN",
    "wof:name":"ABC Bridal",
    "wof:placetype":"venue"
},
  "geometry": {"coordinates":[-93.425118,44.774494],"type":"Point"}
}