{
  "type": "Feature",
  "properties": {
    "addr:full":"34965 63rd St Pierz MN 56364",
    "addr:housenumber":"34965",
    "addr:postcode":"56364",
    "addr:street":"63Rd St",
    "iso:country":"US",
    "sg:address":"34965 63rd St",
    "sg:city":"Pierz",
    "sg:classifiers":[
        {
            "category":"Government",
            "subcategory":"Office",
            "type":"Public Place"
        }
    ],
    "sg:phone":"+1 320 355 2481",
    "sg:postcode":"56364",
    "sg:province":"MN",
    "wof:name":"Lee Michael Johnson",
    "wof:placetype":"venue"
},
  "geometry": {"coordinates":[-93.932688,45.853201],"type":"Point"}
}