{
  "type": "Feature",
  "properties": {
    "iso:country":"US",
    "sg:address":"3024 Snelling Ave",
    "sg:city":"Minneapolis",
    "sg:classifiers":[
        {
            "category":"Health Services",
            "subcategory":"Nursing And Care Facility",
            "type":"Services"
        }
    ],
    "sg:phone":"+1 612 728 1800",
    "sg:postcode":"55406",
    "sg:province":"MN",
    "sg:tags":[
        "nurse",
        "practice-arnp",
        "nurses-advanced"
    ],
    "wof:name":"Lemm Susan",
    "wof:placetype":"venue"
},
  "geometry": {"coordinates":[-93.235617,44.94787],"type":"Point"}
}