{
  "type": "Feature",
  "properties": {
    "iso:country":"US",
    "sg:address":"6840 78th Ave N",
    "sg:city":"Brooklyn Park",
    "sg:classifiers":[
        {
            "category":"Organizations",
            "subcategory":"Non-profit Organization",
            "type":"Services"
        }
    ],
    "sg:phone":"+1 763 566 9600",
    "sg:postcode":"55445",
    "sg:province":"MN",
    "sg:website":"www.ceap.com",
    "wof:name":"Community Emergency Assistance",
    "wof:placetype":"venue"
},
  "geometry": {"coordinates":[-93.371566,45.095379],"type":"Point"}
}