{
  "type": "Feature",
  "properties": {
    "iso:country":"US",
    "sg:address":"16120 Creekwood Dr",
    "sg:city":"Prior Lake",
    "sg:classifiers":[
        {
            "category":"Professional",
            "subcategory":"Research",
            "type":"Services"
        }
    ],
    "sg:phone":"+1 952 447 7425",
    "sg:postcode":"55372",
    "sg:province":"MN",
    "sg:tags":[
        "environmental"
    ],
    "wof:name":"Suzanne Trapp",
    "wof:placetype":"venue"
},
  "geometry": {"coordinates":[-93.37044299999999,44.714997],"type":"Point"}
}