{
  "type": "Feature",
  "properties": {
    "addr:full":"26205 German Rd Belle Plaine MN 56011",
    "addr:housenumber":"26205",
    "addr:postcode":"56011",
    "addr:street":"German Rd;Plaine",
    "iso:country":"US",
    "sg:address":"26205 German Rd",
    "sg:city":"Belle Plaine",
    "sg:classifiers":[
        {
            "category":"Farming",
            "subcategory":"Dairy Farm",
            "type":"Manufacturing & Wholesale Goods"
        }
    ],
    "sg:phone":"+1 952 873 5521",
    "sg:postcode":"56011",
    "sg:province":"MN",
    "wof:name":"Armin Dahn",
    "wof:placetype":"venue"
},
  "geometry": {"coordinates":[-93.79836,44.589548],"type":"Point"}
}