{
  "type": "Feature",
  "properties": {
    "iso:country":"US",
    "sg:address":"9696 Pine Pt Rd NW",
    "sg:city":"Walker",
    "sg:classifiers":[
        {
            "category":"Professional",
            "type":"Services"
        }
    ],
    "sg:phone":"+1 218 547 2525",
    "sg:postcode":"56484",
    "sg:province":"MN",
    "sg:tags":[
        "establishment"
    ],
    "wof:name":"Moor & Moor",
    "wof:placetype":"venue"
},
  "geometry": {"coordinates":[-94.524637,47.15978],"type":"Point"}
}