{
  "type": "Feature",
  "properties": {
    "iso:country":"US",
    "sg:address":"3760 Dunlap St N",
    "sg:city":"Arden Hills",
    "sg:classifiers":[
        {
            "category":"Local Transit",
            "type":"Transportation"
        }
    ],
    "sg:phone":"+1 651 482 9829",
    "sg:postcode":"55112",
    "sg:province":"MN",
    "sg:tags":[
        "ambulance"
    ],
    "wof:name":"Medical Transport-Allina",
    "wof:placetype":"venue"
},
  "geometry": {"coordinates":[-93.150862,45.055479],"type":"Point"}
}