{
  "type": "Feature",
  "properties": {
    "iso:country":"US",
    "sg:address":"4 2nd St NE",
    "sg:city":"Aitkin",
    "sg:classifiers":[
        {
            "category":"Real Estate",
            "subcategory":"Real Estate Agent",
            "type":"Services"
        }
    ],
    "sg:phone":"+1 218 927 6542",
    "sg:postcode":"56431",
    "sg:province":"MN",
    "wof:name":"Century 21",
    "wof:placetype":"venue"
},
  "geometry": {"coordinates":[-93.70655499999999,46.533446],"type":"Point"}
}