{
  "type": "Feature",
  "properties": {
    "addr:full":"702 2nd Ave N Wheaton MN 56296",
    "addr:housenumber":"702",
    "addr:postcode":"56296",
    "addr:street":"2Nd Ave N",
    "iso:country":"US",
    "sg:address":"702 2nd Ave N",
    "sg:city":"Wheaton",
    "sg:classifiers":[
        {
            "category":"Government",
            "subcategory":"Office",
            "type":"Public Place"
        }
    ],
    "sg:phone":"+1 320 563 4411",
    "sg:postcode":"56296",
    "sg:province":"MN",
    "wof:name":"Traverse County Veterans Svc",
    "wof:placetype":"venue"
},
  "geometry": {"coordinates":[-96.49403,45.806204],"type":"Point"}
}