{
  "type": "Feature",
  "properties": {
    "iso:country":"US",
    "sg:address":"15410 Kangaroo St NW",
    "sg:city":"Anoka",
    "sg:classifiers":[
        {
            "category":"Building & Trades",
            "subcategory":"Construction",
            "type":"Services"
        }
    ],
    "sg:phone":"+1 763 427 5184",
    "sg:postcode":"55303",
    "sg:province":"MN",
    "sg:tags":[
        "house"
    ],
    "wof:name":"Cja Construction Inc",
    "wof:placetype":"venue"
},
  "geometry": {"coordinates":[-93.478955,45.250249],"type":"Point"}
}