{
  "type": "Feature",
  "properties": {
    "iso:country":"US",
    "sg:address":"4182 Knob Cir",
    "sg:city":"St Paul",
    "sg:classifiers":[
        {
            "category":"Professional",
            "subcategory":"Art Services",
            "type":"Services"
        }
    ],
    "sg:phone":"+1 612 801 6415",
    "sg:postcode":"55122",
    "sg:province":"MN",
    "sg:tags":[
        "photographer"
    ],
    "wof:name":"Peter Caley Photography",
    "wof:placetype":"venue"
},
  "geometry": {"coordinates":[-93.171528,44.806393],"type":"Point"}
}