{
  "type": "Feature",
  "properties": {
    "iso:country":"US",
    "sg:address":"7700 Wentworth Ave S",
    "sg:city":"Minneapolis",
    "sg:classifiers":[
        {
            "category":"Building & Trades",
            "subcategory":"Construction",
            "type":"Services"
        }
    ],
    "sg:phone":"+1 612 822 0435",
    "sg:postcode":"55423",
    "sg:province":"MN",
    "sg:tags":[
        "home",
        "remodeling",
        "family"
    ],
    "wof:name":"Polland Brothers Construction",
    "wof:placetype":"venue"
},
  "geometry": {"coordinates":[-93.280807,44.862305],"type":"Point"}
}