{
  "type": "Feature",
  "properties": {
    "iso:country":"US",
    "sg:address":"7815 Hill Rd",
    "sg:city":"Saint Paul",
    "sg:classifiers":[
        {
            "category":"Professional",
            "subcategory":"Business Services",
            "type":"Services"
        }
    ],
    "sg:phone":"+1 651 714 8387",
    "sg:postcode":"55125",
    "sg:province":"MN",
    "wof:name":"Dl Skaja Enterprises",
    "wof:placetype":"venue"
},
  "geometry": {"coordinates":[-92.948171,44.89387],"type":"Point"}
}