{
  "type": "Feature",
  "properties": {
    "addr:full":"21270 480th St Zumbrota MN 55992",
    "addr:housenumber":"21270",
    "addr:postcode":"55992",
    "addr:street":"480Th St",
    "iso:country":"US",
    "sg:address":"21270 480th St",
    "sg:city":"Zumbrota",
    "sg:phone":"+1 507 732 5563",
    "sg:postcode":"55992",
    "sg:province":"MN",
    "sg:tags":[
        "farm",
        "corn",
        "grain",
        "cash"
    ],
    "wof:name":"Keith Olson",
    "wof:placetype":"venue"
},
  "geometry": {"coordinates":[-92.600876,44.252735],"type":"Point"}
}