{
  "type": "Feature",
  "properties": {
    "addr:full":"22381 Johnson Memorial Dr Belle Plaine MN 56011",
    "addr:housenumber":"22381",
    "addr:postcode":"56011",
    "addr:street":"Johnson Memorial Dr Belle Plaine",
    "iso:country":"US",
    "sg:address":"22381 Johnson Memorial Dr",
    "sg:city":"Belle Plaine",
    "sg:classifiers":[
        {
            "category":"Building & Trades",
            "subcategory":"Construction",
            "type":"Services"
        }
    ],
    "sg:phone":"+1 952 873 2820",
    "sg:postcode":"56011",
    "sg:province":"MN",
    "wof:name":"J & W Asphalt",
    "wof:placetype":"venue"
},
  "geometry": {"coordinates":[-93.748169,44.623269],"type":"Point"}
}