{
  "type": "Feature",
  "properties": {
    "iso:country":"US",
    "sg:address":"3933 Harriet Ave S",
    "sg:city":"Minneapolis",
    "sg:classifiers":[
        {
            "category":"Building & Trades",
            "subcategory":"Construction",
            "type":"Services"
        }
    ],
    "sg:phone":"+1 612 823 8637",
    "sg:postcode":"55409",
    "sg:province":"MN",
    "sg:tags":[
        "house"
    ],
    "wof:name":"D&R Wilson Construction",
    "wof:placetype":"venue"
},
  "geometry": {"coordinates":[-93.285588,44.931054],"type":"Point"}
}