{
  "type": "Feature",
  "properties": {
    "iso:country":"US",
    "sg:address":"8910 Hudson Blvd N",
    "sg:city":"Lake Elmo",
    "sg:classifiers":[
        {
            "category":"Retail",
            "subcategory":"Auto Repair",
            "type":"Services"
        }
    ],
    "sg:phone":"+1 651 738 1244",
    "sg:postcode":"55042",
    "sg:province":"MN",
    "sg:tags":[
        "body",
        "shop",
        "painting",
        "automobile"
    ],
    "sg:website":"www.crossroadscollision.com",
    "wof:name":"Crossroads Collision Center",
    "wof:placetype":"venue"
},
  "geometry": {"coordinates":[-92.926654,44.949735],"type":"Point"}
}