{
  "type": "Feature",
  "properties": {
    "iso:country":"US",
    "sg:address":"1625 Old Audubon Rd",
    "sg:city":"Chaska",
    "sg:classifiers":[
        {
            "category":"Building & Trades",
            "subcategory":"Construction",
            "type":"Services"
        }
    ],
    "sg:phone":"+1 952 556 0217",
    "sg:postcode":"55318",
    "sg:province":"MN",
    "sg:tags":[
        "contractor"
    ],
    "wof:name":"Nelson Masonry & Concrete Inc",
    "wof:placetype":"venue"
},
  "geometry": {"coordinates":[-93.580868,44.804287],"type":"Point"}
}