{
  "type": "Feature",
  "properties": {
    "iso:country":"US",
    "sg:address":"1144 16th Ave SE",
    "sg:city":"Minneapolis",
    "sg:classifiers":[
        {
            "category":"Professional",
            "subcategory":"Business Services",
            "type":"Services"
        }
    ],
    "sg:phone":"+1 612 331 4702",
    "sg:postcode":"55414",
    "sg:province":"MN",
    "sg:tags":[
        "recording",
        "studio"
    ],
    "wof:name":"Sidecar Studios",
    "wof:placetype":"venue"
},
  "geometry": {"coordinates":[-93.22943100000001,44.992345],"type":"Point"}
}