{
  "type": "Feature",
  "properties": {
    "iso:country":"US",
    "sg:address":"509 State Hwy 25",
    "sg:city":"Monticello",
    "sg:classifiers":[
        {
            "category":"Utilities",
            "subcategory":"Mobile Phone",
            "type":"Services"
        }
    ],
    "sg:phone":"+1 763 295 0164",
    "sg:postcode":"55362",
    "sg:province":"MN",
    "sg:tags":[
        "telephone",
        "cellular"
    ],
    "wof:name":"Centcom",
    "wof:placetype":"venue"
},
  "geometry": {"coordinates":[-93.796831,45.302057],"type":"Point"}
}