{
  "type": "Feature",
  "properties": {
    "iso:country":"US",
    "sg:address":"685 Cedar Cir",
    "sg:city":"Annandale",
    "sg:classifiers":[
        {
            "category":"Insurance",
            "subcategory":"Insurance Agent",
            "type":"Services"
        }
    ],
    "sg:phone":"+1 320 274 6035",
    "sg:postcode":"55302",
    "sg:province":"MN",
    "wof:name":"Royal Alliance Associates",
    "wof:placetype":"venue"
},
  "geometry": {"coordinates":[-94.11460099999999,45.263819],"type":"Point"}
}