{
  "type": "Feature",
  "properties": {
    "addr:full":"16869 Simpkins Ave SW Prior Lake MN 55372",
    "addr:postcode":"16869;55372",
    "addr:street":"Simpkins Ave Sw Prior",
    "iso:country":"US",
    "sg:address":"16869 Simpkins Ave SW",
    "sg:city":"Prior Lake",
    "sg:classifiers":[
        {
            "category":"Professional",
            "subcategory":"Management & Consulting",
            "type":"Services"
        }
    ],
    "sg:phone":"+1 952 440 4866",
    "sg:postcode":"55372",
    "sg:province":"MN",
    "sg:tags":[
        "business"
    ],
    "wof:name":"Wsi Intrnet Consulting Educatn",
    "wof:placetype":"venue"
},
  "geometry": {"coordinates":[-93.44126199999999,44.705656],"type":"Point"}
}