{
  "type": "Feature",
  "properties": {
    "iso:country":"US",
    "sg:address":"355 S Kenneth St",
    "sg:city":"St Paul",
    "sg:classifiers":[
        {
            "category":"Communications",
            "subcategory":"Film & Video Production",
            "type":"Services"
        }
    ],
    "sg:phone":"+1 651 690 1029",
    "sg:postcode":"55105",
    "sg:province":"MN",
    "sg:tags":[
        "motion",
        "picture",
        "studio",
        "producer"
    ],
    "wof:name":"John D Goodell",
    "wof:placetype":"venue"
},
  "geometry": {"coordinates":[-93.18491899999999,44.931468],"type":"Point"}
}