{
  "type": "Feature",
  "properties": {
    "addr:full":"20494 223rd St Little Falls MN 56345",
    "addr:housenumber":"20494",
    "addr:postcode":"56345",
    "addr:street":"223Rd St",
    "iso:country":"US",
    "sg:address":"20494 223rd St",
    "sg:city":"Little Falls",
    "sg:classifiers":[
        {
            "category":"Retail",
            "subcategory":"Auto Repair",
            "type":"Services"
        }
    ],
    "sg:phone":"+1 320 745 2424",
    "sg:postcode":"56345",
    "sg:province":"MN",
    "sg:tags":[
        "body"
    ],
    "wof:name":"B & J Auto Body",
    "wof:placetype":"venue"
},
  "geometry": {"coordinates":[-94.221019,46.085182],"type":"Point"}
}