{
  "type": "Feature",
  "properties": {
    "addr:full":"1320 Foothill Ct Fergus Falls MN 56537",
    "addr:housenumber":"1320",
    "addr:postcode":"56537",
    "addr:street":"Foothill Ct",
    "iso:country":"US",
    "sg:address":"1320 Foothill Ct",
    "sg:city":"Fergus Falls",
    "sg:classifiers":[
        {
            "category":"Social Services",
            "subcategory":"Child Care",
            "type":"Services"
        }
    ],
    "sg:phone":"+1 218 739 9018",
    "sg:postcode":"56537",
    "sg:province":"MN",
    "sg:tags":[
        "day",
        "provider"
    ],
    "wof:name":"Sheri Jones",
    "wof:placetype":"venue"
},
  "geometry": {"coordinates":[-96.052859,46.295508],"type":"Point"}
}