{
  "type": "Feature",
  "properties": {
    "addr:full":"9816 Kalenda Ave NE Monticello MN 55362",
    "addr:housenumber":"9816",
    "addr:postcode":"55362",
    "addr:street":"Kalenda Ave Ne",
    "iso:country":"US",
    "sg:address":"9816 Kalenda Ave NE",
    "sg:city":"Monticello",
    "sg:classifiers":[
        {
            "category":"Banks & Credit Unions",
            "subcategory":"Investment Brokerage",
            "type":"Services"
        },
        {
            "category":"Professional",
            "subcategory":"Business Services",
            "type":"Services"
        }
    ],
    "sg:phone":"+1 763 295 4474",
    "sg:postcode":"55362",
    "sg:province":"MN",
    "sg:tags":[
        "advisory",
        "financial"
    ],
    "wof:name":"Boleen & Associates Inc",
    "wof:placetype":"venue"
},
  "geometry": {"coordinates":[-93.669572,45.289744],"type":"Point"}
}