{
  "type": "Feature",
  "properties": {
    "iso:country":"US",
    "sg:address":"800 E Depue Ave",
    "sg:city":"Olivia",
    "sg:classifiers":[
        {
            "category":"Professional",
            "subcategory":"Accounting & Tax Preparation",
            "type":"Services"
        }
    ],
    "sg:phone":"+1 320 523 2448",
    "sg:postcode":"56277",
    "sg:province":"MN",
    "wof:name":"Curtis D Sather",
    "wof:placetype":"venue"
},
  "geometry": {"coordinates":[-94.98945999999999,44.775451],"type":"Point"}
}