{
  "type": "Feature",
  "properties": {
    "iso:country":"US",
    "sg:address":"208 W Marshall St",
    "sg:city":"Marshall",
    "sg:classifiers":[
        {
            "category":"Organizations",
            "subcategory":"Religious Organization",
            "type":"Services"
        }
    ],
    "sg:phone":"+1 507 532 9359",
    "sg:postcode":"56258",
    "sg:province":"MN",
    "sg:tags":[
        "church"
    ],
    "wof:name":"Christ Lutheran Church",
    "wof:placetype":"venue"
},
  "geometry": {"coordinates":[-95.786564,44.449718],"type":"Point"}
}