{
  "type": "Feature",
  "properties": {
    "iso:country":"US",
    "sg:address":"13046 6th Ave Cir",
    "sg:city":"Zimmerman",
    "sg:classifiers":[
        {
            "category":"Shopping",
            "subcategory":"Gifts & Souvenirs",
            "type":"Retail Goods"
        }
    ],
    "sg:phone":"+1 763 856 0280",
    "sg:postcode":"55398",
    "sg:province":"MN",
    "wof:name":"Lilys On Main",
    "wof:placetype":"venue"
},
  "geometry": {"coordinates":[-93.59567199999999,45.447948],"type":"Point"}
}