{
  "type": "Feature",
  "properties": {
    "addr:full":"308 S Minnesota Ave St Peter MN 56082",
    "addr:housenumber":"308",
    "addr:postcode":"56082",
    "addr:street":"S Minnesota Ave",
    "iso:country":"US",
    "sg:address":"308 S Minnesota Ave",
    "sg:city":"St Peter",
    "sg:classifiers":[
        {
            "category":"Banks & Credit Unions",
            "subcategory":"Investment Brokerage",
            "type":"Services"
        }
    ],
    "sg:phone":"+1 507 931 9110",
    "sg:postcode":"56082",
    "sg:province":"MN",
    "sg:tags":[
        "stock",
        "bond"
    ],
    "sg:website":"www.edwardjones.com",
    "wof:name":"Edward Jones Co",
    "wof:placetype":"venue"
},
  "geometry": {"coordinates":[-93.957376,44.324128],"type":"Point"}
}