{
  "type": "Feature",
  "properties": {
    "addr:full":"2116 40th Ave NE Minneapolis MN 55421",
    "addr:housenumber":"2116",
    "addr:postcode":"55421",
    "addr:street":"40Th Ave Ne",
    "iso:country":"US",
    "sg:address":"2116 40th Ave NE",
    "sg:city":"Minneapolis",
    "sg:classifiers":[
        {
            "category":"Retail",
            "subcategory":"Car Wash",
            "type":"Services"
        }
    ],
    "sg:phone":"+1 651 639 1552",
    "sg:postcode":"55421",
    "sg:province":"MN",
    "wof:name":"New Brighton Car Wash",
    "wof:placetype":"venue"
},
  "geometry": {"coordinates":[-93.230301,45.040901],"type":"Point"}
}