{
  "type": "Feature",
  "properties": {
    "addr:full":"21170 Eaton Ave Ste A Farmington MN 55024",
    "addr:housenumber":"21170",
    "addr:postcode":"55024",
    "addr:street":"Eaton Ave Ste A",
    "iso:country":"US",
    "sg:address":"21170 Eaton Ave Ste A",
    "sg:city":"Farmington",
    "sg:classifiers":[
        {
            "category":"Wholesale",
            "subcategory":"Home Furnishings",
            "type":"Manufacturing & Wholesale Goods"
        }
    ],
    "sg:phone":"+1 651 460 6955",
    "sg:postcode":"55024",
    "sg:province":"MN",
    "sg:tags":[
        "plumbing",
        "supplies-wholesale",
        "part",
        "fixture",
        "manufacturer"
    ],
    "sg:website":"http://www.steinair.com",
    "wof:name":"Steinair, Inc",
    "wof:placetype":"venue"
},
  "geometry": {"coordinates":[-93.168087,44.642489],"type":"Point"}
}