{
  "type": "Feature",
  "properties": {
    "iso:country":"US",
    "sg:address":"9028 Tee Rd",
    "sg:city":"Angora",
    "sg:classifiers":[
        {
            "category":"Building & Trades",
            "subcategory":"Construction",
            "type":"Services"
        }
    ],
    "sg:phone":"+1 218 666 5710",
    "sg:postcode":"55703",
    "sg:province":"MN",
    "sg:tags":[
        "masonry",
        "contractor"
    ],
    "wof:name":"JH Masonry",
    "wof:placetype":"venue"
},
  "geometry": {"coordinates":[-92.647991,47.774296],"type":"Point"}
}