{
  "type": "Feature",
  "properties": {
    "addr:full":"9240 Grand Ave S Minneapolis MN 55420",
    "addr:housenumber":"9240",
    "addr:postcode":"55420",
    "addr:street":"Grand Ave S",
    "iso:country":"US",
    "sg:address":"9240 Grand Ave S",
    "sg:city":"Minneapolis",
    "sg:classifiers":[
        {
            "category":"Wholesale",
            "subcategory":"Machinery & Supplies",
            "type":"Manufacturing & Wholesale Goods"
        }
    ],
    "sg:phone":"+1 952 888 9507",
    "sg:postcode":"55420",
    "sg:province":"MN",
    "sg:tags":[
        "engraving",
        "spec",
        "industrial",
        "suppl",
        "sign"
    ],
    "sg:website":"www.johnsonplastics.com",
    "wof:name":"Johnson Plastics",
    "wof:placetype":"venue"
},
  "geometry": {"coordinates":[-93.285357,44.835893],"type":"Point"}
}