{
  "type": "Feature",
  "properties": {
    "addr:full":"1423 Gardena Ave NE Minneapolis MN 55432",
    "addr:housenumber":"1423",
    "addr:postcode":"55432",
    "addr:street":"Gardena Ave Ne",
    "iso:country":"US",
    "sg:address":"1423 Gardena Ave NE",
    "sg:city":"Minneapolis",
    "sg:classifiers":[
        {
            "category":"Professional",
            "type":"Services"
        }
    ],
    "sg:phone":"+1 763 574 9540",
    "sg:postcode":"55432",
    "sg:province":"MN",
    "wof:name":"Wr Dougherty Inc",
    "wof:placetype":"venue"
},
  "geometry": {"coordinates":[-93.233226,45.074897],"type":"Point"}
}