{
  "type": "Feature",
  "properties": {
    "iso:country":"US",
    "sg:address":"7 6th Ave",
    "sg:city":"Forest Lake",
    "sg:classifiers":[
        {
            "category":"Travel",
            "subcategory":"Hotels & Motels",
            "type":"Entertainment"
        }
    ],
    "sg:phone":"+1 651 464 4077",
    "sg:postcode":"55025",
    "sg:province":"MN",
    "wof:name":"Forest Lake Motel",
    "wof:placetype":"venue"
},
  "geometry": {"coordinates":[-92.983766,45.272735],"type":"Point"}
}