{
  "type": "Feature",
  "properties": {
    "addr:full":"5009 92nd Cres Minneapolis MN 55443",
    "addr:housenumber":"5009",
    "addr:postcode":"55443",
    "addr:street":"92Nd Cres",
    "iso:country":"US",
    "sg:address":"5009 92nd Cres",
    "sg:city":"Minneapolis",
    "sg:phone":"+1 763 425 0216",
    "sg:postcode":"55443",
    "sg:province":"MN",
    "wof:name":"Ksc Sales",
    "wof:placetype":"venue"
},
  "geometry": {"coordinates":[-93.345662,45.121429],"type":"Point"}
}