{
  "type": "Feature",
  "properties": {
    "iso:country":"US",
    "sg:address":"4787 Midway Rd",
    "sg:city":"Duluth",
    "sg:classifiers":[
        {
            "category":"Professional",
            "subcategory":"Business Services",
            "type":"Services"
        }
    ],
    "sg:phone":"+1 218 729 4811",
    "sg:postcode":"55811",
    "sg:province":"MN",
    "wof:name":"Saint Louis County Pub Works",
    "wof:placetype":"venue"
},
  "geometry": {"coordinates":[-92.280491,46.856365],"type":"Point"}
}