{
  "type": "Feature",
  "properties": {
    "iso:country":"US",
    "sg:address":"12 177th Ave NW",
    "sg:city":"Andover",
    "sg:classifiers":[
        {
            "category":"Real Estate",
            "subcategory":"Real Estate Services",
            "type":"Services"
        },
        {
            "category":"Real Estate",
            "subcategory":"Real Estate Agent",
            "type":"Services"
        }
    ],
    "sg:phone":"+1 612 845 0452",
    "sg:postcode":"55304",
    "sg:province":"MN",
    "sg:tags":[
        "management"
    ],
    "wof:name":"Birchwood Realty, Inc.",
    "wof:placetype":"venue"
},
  "geometry": {"coordinates":[-93.265327,45.290901],"type":"Point"}
}