{
  "type": "Feature",
  "properties": {
    "iso:country":"US",
    "sg:address":"7600 W. 150th St",
    "sg:city":"Apple Valley",
    "sg:classifiers":[
        {
            "category":"Shopping",
            "subcategory":"Music",
            "type":"Retail Goods"
        },
        {
            "category":"Shopping",
            "subcategory":"Books",
            "type":"Retail Goods"
        },
        {
            "category":"Shopping",
            "subcategory":"Comic Books",
            "type":"Retail Goods"
        }
    ],
    "sg:phone":"+1 952 431 0749",
    "sg:postcode":"55124",
    "sg:province":"MN",
    "sg:tags":[
        "bookstore",
        "dvd's"
    ],
    "sg:website":"halfpricebooks.com",
    "wof:name":"Half Price Books",
    "wof:placetype":"venue"
},
  "geometry": {"coordinates":[-93.220018,44.731804],"type":"Point"}
}