{
  "type": "Feature",
  "properties": {
    "addr:full":"21343 John Milless Dr Rogers MN 55374",
    "addr:housenumber":"21343",
    "addr:postcode":"55374",
    "addr:street":"John Milless Dr",
    "iso:country":"US",
    "sg:address":"21343 John Milless Dr",
    "sg:city":"Rogers",
    "sg:classifiers":[
        {
            "category":"Personal",
            "type":"Services"
        },
        {
            "category":"Sports & Exercise",
            "subcategory":"Gym",
            "type":"Entertainment"
        },
        {
            "category":"Health Services",
            "subcategory":"Health Practitioner",
            "type":"Services"
        },
        {
            "category":"Arena",
            "subcategory":"Sports Club",
            "type":"Entertainment"
        }
    ],
    "sg:phone":"+1 800 615 7352",
    "sg:postcode":"55374",
    "sg:province":"MN",
    "sg:tags":[
        "control",
        "weight",
        "consultant",
        "trainer",
        "program",
        "fitness",
        "physical"
    ],
    "sg:website":"http://twincities.citysearch.com/profile/external/37685995/rogers_mn/curves.html?publisher=yellowpages&reference_id=1&placement=ypwebsitemip",
    "wof:name":"Curves",
    "wof:placetype":"venue"
},
  "geometry": {"coordinates":[-93.550282,45.192249],"type":"Point"}
}