{
  "type": "Feature",
  "properties": {
    "addr:full":"36047 Naples St NE Cambridge MN 55008",
    "addr:postcode":"36047;55008",
    "addr:street":"Naples St Ne",
    "iso:country":"US",
    "sg:address":"36047 Naples St NE",
    "sg:city":"Cambridge",
    "sg:phone":"+1 763 689 3919",
    "sg:postcode":"55008",
    "sg:province":"MN",
    "sg:tags":[
        "farm",
        "corn"
    ],
    "wof:name":"Fred Sanquist",
    "wof:placetype":"venue"
},
  "geometry": {"coordinates":[-93.183379,45.623381],"type":"Point"}
}