{
  "type": "Feature",
  "properties": {
    "addr:full":"225 W Anoka St Duluth MN 55803",
    "addr:housenumber":"225",
    "addr:postcode":"55803",
    "addr:street":"W Anoka St",
    "iso:country":"US",
    "sg:address":"225 W Anoka St",
    "sg:city":"Duluth",
    "sg:classifiers":[
        {
            "category":"Manufacturing",
            "subcategory":"Toys & Sporting Goods",
            "type":"Manufacturing & Wholesale Goods"
        }
    ],
    "sg:phone":"+1 218 724 6157",
    "sg:postcode":"55803",
    "sg:province":"MN",
    "sg:tags":[
        "go",
        "cutlery",
        "mfg"
    ],
    "wof:name":"Band Man The",
    "wof:placetype":"venue"
},
  "geometry": {"coordinates":[-92.08931699999999,46.843985],"type":"Point"}
}