{
  "type": "Feature",
  "properties": {
    "iso:country":"US",
    "sg:address":"48895 180th St",
    "sg:city":"Vining",
    "sg:classifiers":[
        {
            "category":"Farming",
            "subcategory":"Dairy Farm",
            "type":"Manufacturing & Wholesale Goods"
        }
    ],
    "sg:phone":"+1 218 769 4425",
    "sg:postcode":"56588",
    "sg:province":"MN",
    "wof:name":"Donald Hansen",
    "wof:placetype":"venue"
},
  "geometry": {"coordinates":[-95.460686,46.223906],"type":"Point"}
}