{
  "type": "Feature",
  "properties": {
    "addr:full":"24925 Glen Rd Excelsior MN 55331",
    "addr:housenumber":"24925",
    "addr:postcode":"55331",
    "addr:street":"Glen Rd",
    "iso:country":"US",
    "sg:address":"24925 Glen Rd",
    "sg:city":"Excelsior",
    "sg:classifiers":[
        {
            "category":"Building & Trades",
            "subcategory":"Construction",
            "type":"Services"
        }
    ],
    "sg:phone":"+1 952 474 4165",
    "sg:postcode":"55331",
    "sg:province":"MN",
    "sg:tags":[
        "house",
        "contractor"
    ],
    "sg:website":"www.waldenwood.com",
    "wof:name":"Waldenwood LTD",
    "wof:placetype":"venue"
},
  "geometry": {"coordinates":[-93.592462,44.903361],"type":"Point"}
}