{
  "type": "Feature",
  "properties": {
    "iso:country":"US",
    "sg:address":"1200 12th St SW",
    "sg:city":"Rochester",
    "sg:classifiers":[
        {
            "category":"Restaurant",
            "type":"Food & Drink"
        }
    ],
    "sg:phone":"+1 507 288 5117",
    "sg:postcode":"55902",
    "sg:province":"MN",
    "sg:tags":[
        "shop",
        "coffee"
    ],
    "sg:website":"www.caribou.com",
    "wof:name":"Caribou Coffee House",
    "wof:placetype":"venue"
},
  "geometry": {"coordinates":[-92.48204,44.00703],"type":"Point"}
}