{
  "type": "Feature",
  "properties": {
    "iso:country":"US",
    "sg:address":"106 S Sheridan St",
    "sg:city":"Houston",
    "sg:classifiers":[
        {
            "category":"Retail",
            "subcategory":"Repair Shop",
            "type":"Services"
        }
    ],
    "sg:phone":"+1 507 896 3731",
    "sg:postcode":"55943",
    "sg:province":"MN",
    "sg:tags":[
        "tractor"
    ],
    "wof:name":"Ken's Repair & Supply",
    "wof:placetype":"venue"
},
  "geometry": {"coordinates":[-91.56591,43.763233],"type":"Point"}
}