{
  "type": "Feature",
  "properties": {
    "addr:full":"655 150th Ave SW Appleton MN 56208",
    "addr:housenumber":"655",
    "addr:postcode":"56208",
    "addr:street":"150Th Ave Sw",
    "iso:country":"US",
    "sg:address":"655 150th Ave SW",
    "sg:city":"Appleton",
    "sg:classifiers":[
        {
            "category":"Professional",
            "subcategory":"Business Services",
            "type":"Services"
        }
    ],
    "sg:phone":"+1 320 394 2489",
    "sg:postcode":"56208",
    "sg:province":"MN",
    "sg:tags":[
        "auctioneer"
    ],
    "sg:website":"www.brownandbaker.com",
    "wof:name":"Brown & Baker Auction Svc",
    "wof:placetype":"venue"
},
  "geometry": {"coordinates":[-95.87841,45.224787],"type":"Point"}
}