{
  "type": "Feature",
  "properties": {
    "addr:full":"4418 W Lake Harriet Pkwy # 205 Minneapolis MN 55410",
    "addr:housenumber":"4418",
    "addr:postcode":"55410",
    "addr:street":"W Lake Harriet Pkwy # 205",
    "iso:country":"US",
    "sg:address":"4418 W Lake Harriet Pkwy # 205",
    "sg:city":"Minneapolis",
    "sg:classifiers":[
        {
            "category":"Social Services",
            "subcategory":"Child Care",
            "type":"Services"
        }
    ],
    "sg:phone":"+1 612 327 4126",
    "sg:postcode":"55410",
    "sg:province":"MN",
    "sg:tags":[
        "sitting"
    ],
    "wof:name":"Babysit Central",
    "wof:placetype":"venue"
},
  "geometry": {"coordinates":[-93.311989,44.922508],"type":"Point"}
}