{
  "type": "Feature",
  "properties": {
    "iso:country":"US",
    "sg:address":"1910 W Superior St",
    "sg:city":"Duluth",
    "sg:classifiers":[
        {
            "category":"Shopping",
            "subcategory":"Clothing, Apparel, & Fashions",
            "type":"Retail Goods"
        }
    ],
    "sg:phone":"+1 218 727 1333",
    "sg:postcode":"55806",
    "sg:province":"MN",
    "sg:tags":[
        "furnishing"
    ],
    "wof:name":"Minnesota Surplus & Outfitters",
    "wof:placetype":"venue"
},
  "geometry": {"coordinates":[-92.122888,46.767944],"type":"Point"}
}