{
  "type": "Feature",
  "properties": {
    "addr:full":"11301 Lake Olaf Rd SW Lowry MN 56349",
    "addr:housenumber":"11301",
    "addr:postcode":"56349",
    "addr:street":"Lake Olaf Rd Sw",
    "iso:country":"US",
    "sg:address":"11301 Lake Olaf Rd SW",
    "sg:city":"Lowry",
    "sg:classifiers":[
        {
            "category":"Manufacturing",
            "subcategory":"Retail Goods",
            "type":"Manufacturing & Wholesale Goods"
        }
    ],
    "sg:phone":"+1 320 283 5553",
    "sg:postcode":"56349",
    "sg:province":"MN",
    "sg:tags":[
        "product",
        "mfg"
    ],
    "wof:name":"Reece Industries Inc",
    "wof:placetype":"venue"
},
  "geometry": {"coordinates":[-95.548146,45.763118],"type":"Point"}
}