{
  "type": "Feature",
  "properties": {
    "addr:full":"1880 Newport St Maple Plain MN 55359",
    "addr:housenumber":"1880",
    "addr:postcode":"55359",
    "addr:street":"Newport St;Plain",
    "iso:country":"US",
    "sg:address":"1880 Newport St",
    "sg:city":"Maple Plain",
    "sg:classifiers":[
        {
            "category":"Professional",
            "subcategory":"Business Services",
            "type":"Services"
        }
    ],
    "sg:phone":"+1 763 479 1580",
    "sg:postcode":"55359",
    "sg:province":"MN",
    "wof:name":"McKown Home Inspection Service",
    "wof:placetype":"venue"
},
  "geometry": {"coordinates":[-93.65656799999999,45.012781],"type":"Point"}
}