{
  "type": "Feature",
  "properties": {
    "iso:country":"US",
    "sg:address":"2304 Emerson Ave N",
    "sg:city":"Minneapolis",
    "sg:classifiers":[
        {
            "category":"Social Services",
            "subcategory":"Child Care",
            "type":"Services"
        }
    ],
    "sg:phone":"+1 612 287 9775",
    "sg:postcode":"55411",
    "sg:province":"MN",
    "sg:tags":[
        "day"
    ],
    "wof:name":"Agape 24 Hour Preschool Daycare",
    "wof:placetype":"venue"
},
  "geometry": {"coordinates":[-93.29389999999999,45.0028],"type":"Point"}
}