{
  "type": "Feature",
  "properties": {
    "iso:country":"US",
    "sg:address":"1110 Nicollet Ave",
    "sg:city":"Minneapolis",
    "sg:classifiers":[
        {
            "category":"Bars & Pubs",
            "type":"Food & Drink"
        },
        {
            "category":"Restaurant",
            "type":"Food & Drink"
        }
    ],
    "sg:phone":"+1 612 332 3908",
    "sg:postcode":"55403",
    "sg:province":"MN",
    "sg:tags":[
        "british"
    ],
    "sg:website":"www.britspub.com",
    "wof:name":"Brit's Pub & Eating Establishment",
    "wof:placetype":"venue"
},
  "geometry": {"coordinates":[-93.276398,44.972198],"type":"Point"}
}