{
  "type": "Feature",
  "properties": {
    "iso:country":"US",
    "sg:address":"2 Appletree Sq",
    "sg:city":"Minneapolis",
    "sg:classifiers":[
        {
            "category":"Professional",
            "subcategory":"Accounting & Tax Preparation",
            "type":"Services"
        }
    ],
    "sg:phone":"+1 952 938 8320",
    "sg:postcode":"55425",
    "sg:province":"MN",
    "sg:tags":[
        "accountant"
    ],
    "wof:name":"Sitter & Assoc PA",
    "wof:placetype":"venue"
},
  "geometry": {"coordinates":[-93.22119000000001,44.857265],"type":"Point"}
}