{
  "type": "Feature",
  "properties": {
    "iso:country":"US",
    "sg:address":"13357 Quincy St NE",
    "sg:city":"Andover",
    "sg:classifiers":[
        {
            "category":"Professional",
            "type":"Services"
        },
        {
            "category":"Wholesale",
            "subcategory":"Machinery & Supplies",
            "type":"Manufacturing & Wholesale Goods"
        }
    ],
    "sg:phone":"+1 763 767 0048",
    "sg:postcode":"55304",
    "sg:province":"MN",
    "sg:tags":[
        "machine",
        "equipment",
        "part",
        "industrial",
        "retailer"
    ],
    "wof:name":"Down Sprues Specialties",
    "wof:placetype":"venue"
},
  "geometry": {"coordinates":[-93.251542,45.212434],"type":"Point"}
}