{
  "type": "Feature",
  "properties": {
    "iso:country":"US",
    "sg:address":"598 Dayton Ave",
    "sg:city":"St Paul",
    "sg:classifiers":[
        {
            "category":"Real Estate",
            "subcategory":"Architect",
            "type":"Services"
        }
    ],
    "sg:phone":"+1 651 310 0023",
    "sg:postcode":"55102",
    "sg:province":"MN",
    "wof:name":"Architecture Outsource",
    "wof:placetype":"venue"
},
  "geometry": {"coordinates":[-93.12506,44.947337],"type":"Point"}
}