{
  "type": "Feature",
  "properties": {
    "iso:country":"US",
    "sg:address":"2619 Ridge Ct",
    "sg:city":"Saint Paul",
    "sg:classifiers":[
        {
            "category":"Manufacturing",
            "subcategory":"Chemicals & Compounds",
            "type":"Manufacturing & Wholesale Goods"
        }
    ],
    "sg:phone":"+1 612 429 5629",
    "sg:postcode":"55110",
    "sg:province":"MN",
    "sg:tags":[
        "preparation",
        "pharmaceutical",
        "mfg"
    ],
    "wof:name":"Eli Lilly and Company",
    "wof:placetype":"venue"
},
  "geometry": {"coordinates":[-92.987116,45.105646],"type":"Point"}
}