{
  "type": "Feature",
  "properties": {
    "addr:full":"52 Links Ln Winona MN 55987",
    "addr:housenumber":"52",
    "addr:postcode":"55987",
    "addr:street":"Links Ln",
    "iso:country":"US",
    "sg:address":"52 Links Ln",
    "sg:city":"Winona",
    "sg:classifiers":[
        {
            "category":"Real Estate",
            "subcategory":"Real Estate Operator",
            "type":"Services"
        }
    ],
    "sg:phone":"+1 507 453 0523",
    "sg:postcode":"55987",
    "sg:province":"MN",
    "sg:tags":[
        "apartment"
    ],
    "wof:name":"Valley Manor",
    "wof:placetype":"venue"
},
  "geometry": {"coordinates":[-91.608311,44.018118],"type":"Point"}
}