{
  "type": "Feature",
  "properties": {
    "addr:full":"11950 Co Rd 30 Waconia MN 55387",
    "addr:housenumber":"11950;30",
    "addr:postcode":"55387",
    "addr:street":"Co Rd",
    "iso:country":"US",
    "sg:address":"11950 Co Rd 30",
    "sg:city":"Waconia",
    "sg:classifiers":[
        {
            "category":"Food & Beverages",
            "subcategory":"Specialty",
            "type":"Retail Goods"
        }
    ],
    "sg:phone":"+1 952 368 3555",
    "sg:postcode":"55387",
    "sg:province":"MN",
    "wof:name":"Wanda S Wellness",
    "wof:placetype":"venue"
},
  "geometry": {"coordinates":[-93.825909,44.868019],"type":"Point"}
}