{
  "type": "Feature",
  "properties": {
    "iso:country":"US",
    "sg:address":"228 S Main St",
    "sg:city":"Le Sueur",
    "sg:classifiers":[
        {
            "category":"Professional",
            "subcategory":"Lawyer & Legal Services",
            "type":"Services"
        }
    ],
    "sg:phone":"+1 507 665 6444",
    "sg:postcode":"56058",
    "sg:province":"MN",
    "sg:tags":[
        "attorney"
    ],
    "wof:name":"Glaeser Law Office",
    "wof:placetype":"venue"
},
  "geometry": {"coordinates":[-93.917027,44.459544],"type":"Point"}
}