{
  "type": "Feature",
  "properties": {
    "addr:full":"2385 Hennepin Ave N Glencoe MN 55336",
    "addr:housenumber":"2385",
    "addr:postcode":"55336",
    "addr:street":"Hennepin Ave N",
    "iso:country":"US",
    "sg:address":"2385 Hennepin Ave N",
    "sg:city":"Glencoe",
    "sg:classifiers":[
        {
            "category":"Government",
            "subcategory":"Office",
            "type":"Public Place"
        }
    ],
    "sg:phone":"+1 320 864 1260",
    "sg:postcode":"55336",
    "sg:province":"MN",
    "sg:tags":[
        "executive"
    ],
    "wof:name":"County of McLeod",
    "wof:placetype":"venue"
},
  "geometry": {"coordinates":[-94.15173,44.784245],"type":"Point"}
}