{
  "type": "Feature",
  "properties": {
    "iso:country":"US",
    "sg:address":"2320 Lexington Ave S",
    "sg:city":"Saint Paul",
    "sg:classifiers":[
        {
            "category":"Real Estate",
            "subcategory":"Real Estate Agent",
            "type":"Services"
        }
    ],
    "sg:phone":"+1 651 452 8826",
    "sg:postcode":"55120",
    "sg:province":"MN",
    "wof:name":"Condor Corp",
    "wof:placetype":"venue"
},
  "geometry": {"coordinates":[-93.14673500000001,44.872517],"type":"Point"}
}