{
  "type": "Feature",
  "properties": {
    "addr:full":"12007 200th St Red Lake Falls MN 56726",
    "addr:housenumber":"12007",
    "addr:postcode":"56726",
    "addr:street":"200Th St",
    "iso:country":"US",
    "sg:address":"12007 200th St",
    "sg:city":"Red Lake Falls",
    "sg:classifiers":[
        {
            "category":"Restaurant",
            "type":"Food & Drink"
        }
    ],
    "sg:phone":"+1 218 253 2986",
    "sg:postcode":"56726",
    "sg:province":"MN",
    "sg:tags":[
        "eating"
    ],
    "wof:name":"In Uncle Bills Drive Inc",
    "wof:placetype":"venue"
},
  "geometry": {"coordinates":[-96.343717,48.689115],"type":"Point"}
}