{
  "type": "Feature",
  "properties": {
    "addr:full":"227 3rd St Tracy MN 56175",
    "addr:housenumber":"227",
    "addr:postcode":"56175",
    "addr:street":"3Rd St",
    "iso:country":"US",
    "sg:address":"227 3rd St",
    "sg:city":"Tracy",
    "sg:classifiers":[
        {
            "category":"Professional",
            "subcategory":"Lawyer & Legal Services",
            "type":"Services"
        }
    ],
    "sg:phone":"+1 507 629 3820",
    "sg:postcode":"56175",
    "sg:province":"MN",
    "sg:tags":[
        "attorney"
    ],
    "wof:name":"James E KERR & Assoc",
    "wof:placetype":"venue"
},
  "geometry": {"coordinates":[-95.619169,44.233447],"type":"Point"}
}