{
  "type": "Feature",
  "properties": {
    "iso:country":"US",
    "sg:address":"14321 Sorrel Way",
    "sg:city":"Eden Prairie",
    "sg:classifiers":[
        {
            "category":"Professional",
            "type":"Services"
        }
    ],
    "sg:phone":"+1 952 942 8586",
    "sg:postcode":"55347",
    "sg:province":"MN",
    "wof:name":"Aliant Corporate Tech Inc",
    "wof:placetype":"venue"
},
  "geometry": {"coordinates":[-93.457489,44.85012],"type":"Point"}
}