{
  "type": "Feature",
  "properties": {
    "addr:full":"524 W Monroe Ave Mahnomen MN 56557",
    "addr:housenumber":"524",
    "addr:postcode":"56557",
    "addr:street":"W Monroe Ave",
    "iso:country":"US",
    "sg:address":"524 W Monroe Ave",
    "sg:city":"Mahnomen",
    "sg:classifiers":[
        {
            "category":"Organizations",
            "subcategory":"Religious Organization",
            "type":"Services"
        }
    ],
    "sg:phone":"+1 218 935 2456",
    "sg:postcode":"56557",
    "sg:province":"MN",
    "sg:tags":[
        "church"
    ],
    "wof:name":"Bethlehem Lutheran Church",
    "wof:placetype":"venue"
},
  "geometry": {"coordinates":[-95.97427,47.315171],"type":"Point"}
}