{
  "type": "Feature",
  "properties": {
    "addr:full":"225 N Benton Dr Sauk Rapids MN 56379",
    "addr:housenumber":"225",
    "addr:postcode":"56379",
    "addr:street":"N Benton Dr Sauk",
    "iso:country":"US",
    "sg:address":"225 N Benton Dr",
    "sg:city":"Sauk Rapids",
    "sg:classifiers":[
        {
            "category":"Real Estate",
            "subcategory":"Real Estate Agent",
            "type":"Services"
        },
        {
            "category":"Professional",
            "subcategory":"Business Services",
            "type":"Services"
        }
    ],
    "sg:phone":"+1 320 240 0406",
    "sg:postcode":"56379",
    "sg:province":"MN",
    "sg:tags":[
        "appraiser"
    ],
    "wof:name":"Mid States Appraisal",
    "wof:placetype":"venue"
},
  "geometry": {"coordinates":[-94.198077,45.618254],"type":"Point"}
}