{
  "type": "Feature",
  "properties": {
    "addr:full":"151 Silver Lake Rd NW Saint Paul MN 55112",
    "addr:housenumber":"151",
    "addr:postcode":"55112",
    "addr:street":"Silver Lake Rd Nw",
    "iso:country":"US",
    "sg:address":"151 Silver Lake Rd NW",
    "sg:city":"Saint Paul",
    "sg:classifiers":[
        {
            "category":"Wholesale",
            "subcategory":"Stationery",
            "type":"Manufacturing & Wholesale Goods"
        }
    ],
    "sg:phone":"+1 651 633 6511",
    "sg:postcode":"55112",
    "sg:province":"MN",
    "sg:tags":[
        "supply"
    ],
    "wof:name":"Turgeon Business Systems Co",
    "wof:placetype":"venue"
},
  "geometry": {"coordinates":[-93.218192,45.052738],"type":"Point"}
}