{
  "type": "Feature",
  "properties": {
    "iso:country":"US",
    "sg:address":"3435 Kilmer Ln N",
    "sg:city":"Minneapolis",
    "sg:classifiers":[
        {
            "category":"Manufacturing",
            "subcategory":"Building Materials",
            "type":"Manufacturing & Wholesale Goods"
        }
    ],
    "sg:phone":"+1 763 525 9645",
    "sg:postcode":"55441",
    "sg:province":"MN",
    "sg:tags":[
        "manufacture"
    ],
    "wof:name":"Hardwood Manufacturing Inc",
    "wof:placetype":"venue"
},
  "geometry": {"coordinates":[-93.40246999999999,45.019793],"type":"Point"}
}