{
  "type": "Feature",
  "properties": {
    "iso:country":"US",
    "sg:address":"451 Railroad Ave",
    "sg:city":"Albany",
    "sg:classifiers":[
        {
            "category":"Restaurant",
            "type":"Food & Drink"
        }
    ],
    "sg:phone":"+1 320 845 2787",
    "sg:postcode":"56307",
    "sg:province":"MN",
    "sg:tags":[
        "banquet",
        "rooms"
    ],
    "wof:name":"Paul's PAR-A-Dice",
    "wof:placetype":"venue"
},
  "geometry": {"coordinates":[-94.56850799999999,45.62997],"type":"Point"}
}