{
  "type": "Feature",
  "properties": {
    "addr:full":"6514 Quebec Ave N Minneapolis MN 55428",
    "addr:housenumber":"6514",
    "addr:postcode":"55428",
    "addr:street":"Quebec Ave N",
    "iso:country":"US",
    "sg:address":"6514 Quebec Ave N",
    "sg:city":"Minneapolis",
    "sg:classifiers":[
        {
            "category":"Professional",
            "subcategory":"Business Services",
            "type":"Services"
        }
    ],
    "sg:phone":"+1 763 535 2780",
    "sg:postcode":"55428",
    "sg:province":"MN",
    "sg:tags":[
        "embroidery"
    ],
    "wof:name":"Names Indeed Custom Embroidery",
    "wof:placetype":"venue"
},
  "geometry": {"coordinates":[-93.37827799999999,45.075553],"type":"Point"}
}