{
  "type": "Feature",
  "properties": {
    "addr:full":"141 145th Ln NE Ham Lake MN 55304",
    "addr:housenumber":"141",
    "addr:postcode":"55304",
    "addr:street":"145Th Ln Ne",
    "iso:country":"US",
    "sg:address":"141 145th Ln NE",
    "sg:city":"Ham Lake",
    "sg:classifiers":[
        {
            "category":"Building & Trades",
            "subcategory":"Construction",
            "type":"Services"
        }
    ],
    "sg:phone":"+1 763 413 1617",
    "sg:postcode":"55304",
    "sg:province":"MN",
    "sg:tags":[
        "home",
        "builder"
    ],
    "wof:name":"Medalist Homes Inc",
    "wof:placetype":"venue"
},
  "geometry": {"coordinates":[-93.26455,45.234359],"type":"Point"}
}