{
  "type": "Feature",
  "properties": {
    "iso:country":"US",
    "sg:address":"7308 Aspen Ln N",
    "sg:city":"Brooklyn Park",
    "sg:classifiers":[
        {
            "category":"Home & Garden",
            "subcategory":"Building Materials",
            "type":"Retail Goods"
        }
    ],
    "sg:phone":"+1 763 315 9341",
    "sg:postcode":"55428",
    "sg:province":"MN",
    "wof:name":"Pentstar Corp",
    "wof:placetype":"venue"
},
  "geometry": {"coordinates":[-93.388784,45.090684],"type":"Point"}
}