{
  "type": "Feature",
  "properties": {
    "addr:full":"1429 Gilmore Ave Winona MN 55987",
    "addr:housenumber":"1429",
    "addr:postcode":"55987",
    "addr:street":"Gilmore Ave",
    "iso:country":"US",
    "sg:address":"1429 Gilmore Ave",
    "sg:city":"Winona",
    "sg:classifiers":[
        {
            "category":"Travel",
            "subcategory":"Hotels & Motels",
            "type":"Entertainment"
        }
    ],
    "sg:phone":"+1 507 454 5920",
    "sg:postcode":"55987",
    "sg:province":"MN",
    "wof:name":"El Rancho Motel",
    "wof:placetype":"venue"
},
  "geometry": {"coordinates":[-91.674983,44.048634],"type":"Point"}
}