{
  "type": "Feature",
  "properties": {
    "iso:country":"US",
    "sg:address":"5615 Manitou Rd",
    "sg:city":"Excelsior",
    "sg:classifiers":[
        {
            "category":"Personal",
            "subcategory":"Day Spa",
            "type":"Services"
        }
    ],
    "sg:phone":"+1 952 474 4412",
    "sg:postcode":"55331",
    "sg:province":"MN",
    "sg:website":"www.sanctuaryspa.com",
    "wof:name":"Sanctuary Salonspa",
    "wof:placetype":"venue"
},
  "geometry": {"coordinates":[-93.589175,44.90247],"type":"Point"}
}