{
  "type": "Feature",
  "properties": {
    "iso:country":"US",
    "sg:address":"2510 7th Ave E",
    "sg:city":"North St Paul",
    "sg:classifiers":[
        {
            "category":"Insurance",
            "subcategory":"Insurance Agent",
            "type":"Services"
        }
    ],
    "sg:phone":"+1 651 770 4848",
    "sg:postcode":"55109",
    "sg:province":"MN",
    "wof:name":"Martin A Greis",
    "wof:placetype":"venue"
},
  "geometry": {"coordinates":[-92.992344,45.012263],"type":"Point"}
}