{
  "type": "Feature",
  "properties": {
    "addr:full":"2795 Pilot Knob Rd Eagan MN 55121",
    "addr:housenumber":"2795",
    "addr:postcode":"55121",
    "addr:street":"Pilot Knob Rd",
    "iso:country":"US",
    "sg:address":"2795 Pilot Knob Rd",
    "sg:city":"Eagan",
    "sg:classifiers":[
        {
            "category":"Health Services",
            "subcategory":"Health Practitioner",
            "type":"Services"
        }
    ],
    "sg:phone":"+1 651 994 9644",
    "sg:postcode":"55121",
    "sg:province":"MN",
    "sg:tags":[
        "occupational",
        "therapist"
    ],
    "sg:website":"www.childrenstherapyctr.com",
    "wof:name":"Children's Therapy Ctr LLC",
    "wof:placetype":"venue"
},
  "geometry": {"coordinates":[-93.167417,44.857445],"type":"Point"}
}