{
  "type": "Feature",
  "properties": {
    "addr:full":"325 W Laurel Ave St Paul MN 55102",
    "addr:housenumber":"325",
    "addr:postcode":"55102",
    "addr:street":"W Laurel Ave",
    "iso:country":"US",
    "sg:address":"325 W Laurel Ave",
    "sg:city":"St Paul",
    "sg:classifiers":[
        {
            "category":"Freight",
            "type":"Transportation"
        }
    ],
    "sg:phone":"+1 651 298 4211",
    "sg:postcode":"55102",
    "sg:province":"MN",
    "sg:tags":[
        "warehouse"
    ],
    "wof:name":"Public Housing Agency-St Paul",
    "wof:placetype":"venue"
},
  "geometry": {"coordinates":[-93.114524,44.945464],"type":"Point"}
}