{
  "type": "Feature",
  "properties": {
    "iso:country":"US",
    "sg:address":"615 Washington St NE",
    "sg:city":"Minneapolis",
    "sg:classifiers":[
        {
            "category":"Banks & Credit Unions",
            "subcategory":"Bank",
            "type":"Services"
        }
    ],
    "sg:phone":"+1 612 331 3639",
    "sg:postcode":"55413",
    "sg:province":"MN",
    "sg:tags":[
        "federal",
        "savings"
    ],
    "wof:name":"TCF National Bank",
    "wof:placetype":"venue"
},
  "geometry": {"coordinates":[-93.25744,44.995384],"type":"Point"}
}