{
  "type": "Feature",
  "properties": {
    "iso:country":"US",
    "sg:address":"1515 E 66th St",
    "sg:city":"Minneapolis",
    "sg:classifiers":[
        {
            "category":"Social Services",
            "type":"Services"
        }
    ],
    "sg:phone":"+1 612 798 4332",
    "sg:postcode":"55423",
    "sg:province":"MN",
    "sg:tags":[
        "human",
        "welfare"
    ],
    "wof:name":"World Relief Of Minnesota",
    "wof:placetype":"venue"
},
  "geometry": {"coordinates":[-93.253215,44.883511],"type":"Point"}
}