{
  "type": "Feature",
  "properties": {
    "addr:full":"3008 9th Ave NW Rochester MN 55901",
    "addr:housenumber":"3008",
    "addr:postcode":"55901",
    "addr:street":"9Th Ave Nw",
    "iso:country":"US",
    "sg:address":"3008 9th Ave NW",
    "sg:city":"Rochester",
    "sg:classifiers":[
        {
            "category":"Real Estate",
            "subcategory":"Real Estate Agent",
            "type":"Services"
        }
    ],
    "sg:phone":"+1 507 282 8620",
    "sg:postcode":"55901",
    "sg:province":"MN",
    "wof:name":"Muldrow Properties LLC",
    "wof:placetype":"venue"
},
  "geometry": {"coordinates":[-92.476131,44.055615],"type":"Point"}
}