{
  "type": "Feature",
  "properties": {
    "addr:full":"3101 Spring St NE Minneapolis MN 55413",
    "addr:housenumber":"3101",
    "addr:postcode":"55413",
    "addr:street":"Spring St Ne",
    "iso:country":"US",
    "sg:address":"3101 Spring St NE",
    "sg:city":"Minneapolis",
    "sg:classifiers":[
        {
            "category":"Wholesale",
            "subcategory":"Machinery & Supplies",
            "type":"Manufacturing & Wholesale Goods"
        }
    ],
    "sg:phone":"+1 612 331 8550",
    "sg:postcode":"55413",
    "sg:province":"MN",
    "sg:tags":[
        "pet",
        "industrial",
        "trade",
        "special",
        "contractor"
    ],
    "wof:name":"Zahl Petroleum Maintenance Co",
    "wof:placetype":"venue"
},
  "geometry": {"coordinates":[-93.21811700000001,44.995178],"type":"Point"}
}