{
  "type": "Feature",
  "properties": {
    "iso:country":"US",
    "sg:address":"3400 Co Rd 101",
    "sg:city":"Wayzata",
    "sg:classifiers":[
        {
            "category":"Personal",
            "subcategory":"Beauty Salon",
            "type":"Services"
        },
        {
            "category":"Personal",
            "subcategory":"Barber",
            "type":"Services"
        }
    ],
    "sg:phone":"+1 952 473 0283",
    "sg:postcode":"55391",
    "sg:province":"MN",
    "sg:tags":[
        "shop"
    ],
    "wof:name":"Minnehaven Barbers Inc",
    "wof:placetype":"venue"
},
  "geometry": {"coordinates":[-93.50232699999999,44.940433],"type":"Point"}
}