{
  "type": "Feature",
  "properties": {
    "addr:full":"1420 81st St Victoria MN 55386",
    "addr:housenumber":"1420",
    "addr:postcode":"55386",
    "addr:street":"81St St",
    "iso:country":"US",
    "sg:address":"1420 81st St",
    "sg:city":"Victoria",
    "sg:classifiers":[
        {
            "category":"Retail",
            "subcategory":"Repair Shop",
            "type":"Services"
        }
    ],
    "sg:phone":"+1 952 443 2941",
    "sg:postcode":"55386",
    "sg:province":"MN",
    "wof:name":"Olson Kenneth J Rpt",
    "wof:placetype":"venue"
},
  "geometry": {"coordinates":[-93.653829,44.858158],"type":"Point"}
}