{
  "type": "Feature",
  "properties": {
    "iso:country":"US",
    "sg:address":"12690 Riverdale Blvd NW",
    "sg:city":"Minneapolis",
    "sg:classifiers":[
        {
            "category":"Shopping",
            "subcategory":"Stationery & Office Supplies",
            "type":"Retail Goods"
        },
        {
            "category":"Manufacturing",
            "subcategory":"Rubber & Plastics",
            "type":"Manufacturing & Wholesale Goods"
        },
        {
            "category":"Shopping",
            "subcategory":"Crafts & Fabrics",
            "type":"Retail Goods"
        }
    ],
    "sg:phone":"+1 763 712 9201",
    "sg:postcode":"55448",
    "sg:province":"MN",
    "sg:tags":[
        "stamp",
        "equipment",
        "art",
        "store"
    ],
    "wof:name":"Archivers",
    "wof:placetype":"venue"
},
  "geometry": {"coordinates":[-93.35099200000001,45.200563],"type":"Point"}
}