{
  "type": "Feature",
  "properties": {
    "iso:country":"US",
    "sg:address":"12501 Nicollet Ave",
    "sg:city":"Burnsville",
    "sg:classifiers":[
        {
            "category":"Ice Cream",
            "type":"Food & Drink"
        }
    ],
    "sg:phone":"+1 952 808 3686",
    "sg:postcode":"55337",
    "sg:province":"MN",
    "sg:tags":[
        "frozen",
        "yogurt"
    ],
    "wof:name":"Double Dip Ice Cream & Sandwich Shop",
    "wof:placetype":"venue"
},
  "geometry": {"coordinates":[-93.277631,44.774202],"type":"Point"}
}