{
  "type": "Feature",
  "properties": {
    "addr:full":"9612 Yukon Cir S Minneapolis MN 55438",
    "addr:housenumber":"9612",
    "addr:postcode":"55438",
    "addr:street":"Yukon Cir S",
    "iso:country":"US",
    "sg:address":"9612 Yukon Cir S",
    "sg:city":"Minneapolis",
    "sg:classifiers":[
        {
            "category":"Wholesale",
            "subcategory":"Electrical",
            "type":"Manufacturing & Wholesale Goods"
        }
    ],
    "sg:phone":"+1 952 941 1333",
    "sg:postcode":"55438",
    "sg:province":"MN",
    "sg:tags":[
        "equipment",
        "electronic",
        "supply"
    ],
    "wof:name":"Universal Instruments",
    "wof:placetype":"venue"
},
  "geometry": {"coordinates":[-93.391758,44.828401],"type":"Point"}
}