{
  "type": "Feature",
  "properties": {
    "iso:country":"US",
    "sg:address":"3000 N Chestnut St Ste 10",
    "sg:city":"Chaska",
    "sg:classifiers":[
        {
            "category":"Social Services",
            "subcategory":"Child Care",
            "type":"Services"
        }
    ],
    "sg:phone":"+1 952 403 3980",
    "sg:postcode":"55318",
    "sg:province":"MN",
    "sg:tags":[
        "day"
    ],
    "wof:name":"St Francis Capable Kids",
    "wof:placetype":"venue"
},
  "geometry": {"coordinates":[-93.602501,44.8214],"type":"Point"}
}