{
  "type": "Feature",
  "properties": {
    "iso:country":"US",
    "sg:address":"7231 Lewis Ridge Pkwy",
    "sg:city":"Minneapolis",
    "sg:classifiers":[
        {
            "category":"Shopping",
            "subcategory":"Jewelry",
            "type":"Retail Goods"
        }
    ],
    "sg:phone":"+1 952 903 9543",
    "sg:postcode":"55439",
    "sg:province":"MN",
    "sg:tags":[
        "jeweler"
    ],
    "wof:name":"Great Beads",
    "wof:placetype":"venue"
},
  "geometry": {"coordinates":[-93.366519,44.871514],"type":"Point"}
}