{
  "type": "Feature",
  "properties": {
    "iso:country":"US",
    "sg:address":"6514 81st St S",
    "sg:city":"Cottage Grove",
    "sg:classifiers":[
        {
            "category":"Professional",
            "subcategory":"Accounting & Tax Preparation",
            "type":"Services"
        }
    ],
    "sg:phone":"+1 651 458 9783",
    "sg:postcode":"55016",
    "sg:province":"MN",
    "sg:tags":[
        "accountant"
    ],
    "wof:name":"Richard J Burgmeir CPA",
    "wof:placetype":"venue"
},
  "geometry": {"coordinates":[-92.97260199999999,44.831963],"type":"Point"}
}