{
  "type": "Feature",
  "properties": {
    "addr:full":"201 9th Ave SW St Paul MN 55112",
    "addr:housenumber":"201",
    "addr:postcode":"55112",
    "addr:street":"9Th Ave Sw",
    "iso:country":"US",
    "sg:address":"201 9th Ave SW",
    "sg:city":"St Paul",
    "sg:classifiers":[
        {
            "category":"Freight",
            "type":"Transportation"
        },
        {
            "category":"Professional",
            "subcategory":"Business Services",
            "type":"Services"
        }
    ],
    "sg:phone":"+1 651 631 8663",
    "sg:postcode":"55112",
    "sg:province":"MN",
    "sg:tags":[
        "record",
        "document",
        "storage",
        "retrieval"
    ],
    "sg:website":"www.bdrs.com",
    "wof:name":"Business Data Record Services",
    "wof:placetype":"venue"
},
  "geometry": {"coordinates":[-93.20021699999999,45.047243],"type":"Point"}
}