{
  "type": "Feature",
  "properties": {
    "addr:full":"10527 165th St W Lakeville MN 55044",
    "addr:housenumber":"10527",
    "addr:postcode":"55044",
    "addr:street":"165Th St W",
    "iso:country":"US",
    "sg:address":"10527 165th St W",
    "sg:city":"Lakeville",
    "sg:classifiers":[
        {
            "category":"Banks & Credit Unions",
            "subcategory":"Investment Brokerage",
            "type":"Services"
        },
        {
            "category":"Professional",
            "subcategory":"Business Services",
            "type":"Services"
        }
    ],
    "sg:phone":"+1 952 564 6350",
    "sg:postcode":"55044",
    "sg:province":"MN",
    "sg:tags":[
        "broker",
        "commodity"
    ],
    "wof:name":"Jmg Net-Worth, Corp.",
    "wof:placetype":"venue"
},
  "geometry": {"coordinates":[-93.276112,44.710209],"type":"Point"}
}