{
  "type": "Feature",
  "properties": {
    "addr:full":"150 River Rd S Delano MN 55328",
    "addr:housenumber":"150",
    "addr:postcode":"55328",
    "addr:street":"River Rd S",
    "iso:country":"US",
    "sg:address":"150 River Rd S",
    "sg:city":"Delano",
    "sg:classifiers":[
        {
            "category":"Food & Beverages",
            "subcategory":"Meat & Fish",
            "type":"Retail Goods"
        }
    ],
    "sg:phone":"+1 763 972 2261",
    "sg:postcode":"55328",
    "sg:province":"MN",
    "wof:name":"Rieder Meat Market",
    "wof:placetype":"venue"
},
  "geometry": {"coordinates":[-93.79131099999999,45.03924],"type":"Point"}
}