{
  "type": "Feature",
  "properties": {
    "addr:full":"2360 Red Leaf Ct Windom MN 56101",
    "addr:housenumber":"2360",
    "addr:postcode":"56101",
    "addr:street":"Red Leaf Ct",
    "iso:country":"US",
    "sg:address":"2360 Red Leaf Ct",
    "sg:city":"Windom",
    "sg:classifiers":[
        {
            "category":"Farming",
            "subcategory":"Fish & Marine Products",
            "type":"Manufacturing & Wholesale Goods"
        },
        {
            "category":"Museum",
            "subcategory":"Aquarium",
            "type":"Entertainment"
        }
    ],
    "sg:phone":"+1 507 831 1177",
    "sg:postcode":"56101",
    "sg:province":"MN",
    "sg:tags":[
        "tropical",
        "supply"
    ],
    "wof:name":"Tropical Paradise",
    "wof:placetype":"venue"
},
  "geometry": {"coordinates":[-95.14117,43.882806],"type":"Point"}
}