{
  "type": "Feature",
  "properties": {
    "iso:country":"US",
    "sg:address":"808 Old Settlers Trl",
    "sg:city":"Hopkins",
    "sg:classifiers":[
        {
            "category":"Professional",
            "subcategory":"Management & Consulting",
            "type":"Services"
        }
    ],
    "sg:phone":"+1 612 579 8384",
    "sg:postcode":"55343",
    "sg:province":"MN",
    "sg:tags":[
        "strategic"
    ],
    "wof:name":"Tdvh Holdings Inc",
    "wof:placetype":"venue"
},
  "geometry": {"coordinates":[-93.40996,44.908211],"type":"Point"}
}