{
  "type": "Feature",
  "properties": {
    "iso:country":"US",
    "sg:address":"4554 Chicago Ave",
    "sg:city":"Minneapolis",
    "sg:classifiers":[
        {
            "category":"Autos & Motor Vehicles",
            "subcategory":"Fuel & Gas Station",
            "type":"Retail Goods"
        },
        {
            "category":"Autos & Motor Vehicles",
            "subcategory":"Auto Supplies",
            "type":"Retail Goods"
        },
        {
            "category":"Retail",
            "subcategory":"Auto Repair",
            "type":"Services"
        }
    ],
    "sg:phone":"+1 612 823 7100",
    "sg:postcode":"55407",
    "sg:province":"MN",
    "sg:tags":[
        "tire"
    ],
    "wof:name":"Ta's Automotive Inc",
    "wof:placetype":"venue"
},
  "geometry": {"coordinates":[-93.262703,44.919998],"type":"Point"}
}