{
  "type": "Feature",
  "properties": {
    "iso:country":"US",
    "sg:address":"18636 Iris Rd",
    "sg:city":"Silver Lake",
    "sg:phone":"+1 320 327 2522",
    "sg:postcode":"55381",
    "sg:province":"MN",
    "sg:tags":[
        "farm",
        "field",
        "crop"
    ],
    "wof:name":"Cheryl L Knudson",
    "wof:placetype":"venue"
},
  "geometry": {"coordinates":[-94.19723500000001,44.889121],"type":"Point"}
}