{
  "type": "Feature",
  "properties": {
    "addr:full":"19155 Manchester St Minnetonka MN 55345",
    "addr:housenumber":"19155",
    "addr:postcode":"55345",
    "addr:street":"Manchester St",
    "iso:country":"US",
    "sg:address":"19155 Manchester St",
    "sg:city":"Minnetonka",
    "sg:classifiers":[
        {
            "category":"Food & Beverages",
            "subcategory":"Groceries & Convenience Stores",
            "type":"Retail Goods"
        }
    ],
    "sg:phone":"+1 952 470 7919",
    "sg:postcode":"55345",
    "sg:province":"MN",
    "sg:tags":[
        "juice"
    ],
    "wof:name":"Creative Juice Works Inc",
    "wof:placetype":"venue"
},
  "geometry": {"coordinates":[-93.522386,44.896161],"type":"Point"}
}