{
  "type": "Feature",
  "properties": {
    "iso:country":"US",
    "sg:address":"20737 Akin Rd",
    "sg:city":"Farmington",
    "sg:classifiers":[
        {
            "category":"Professional",
            "type":"Services"
        }
    ],
    "sg:phone":"+1 651 463 8684",
    "sg:postcode":"55024",
    "sg:province":"MN",
    "wof:name":"Reisinger Danie",
    "wof:placetype":"venue"
},
  "geometry": {"coordinates":[-93.160105,44.652564],"type":"Point"}
}