{
  "type": "Feature",
  "properties": {
    "addr:full":"20737 Akin Rd Farmington MN 55024",
    "addr:postcode":"20737;55024",
    "addr:street":"Akin Rd",
    "iso:country":"US",
    "sg:address":"20737 Akin Rd",
    "sg:city":"Farmington",
    "sg:classifiers":[
        {
            "category":"Professional",
            "type":"Services"
        }
    ],
    "sg:phone":"+1 651 463 8684",
    "sg:postcode":"55024",
    "sg:province":"MN",
    "wof:name":"Reisinger Danie",
    "wof:placetype":"venue"
},
  "geometry": {"coordinates":[-93.160105,44.652564],"type":"Point"}
}