{
  "type": "Feature",
  "properties": {
    "addr:full":"15100 Cedar Ave Apple Valley MN 55124",
    "addr:housenumber":"15100",
    "addr:postcode":"55124",
    "addr:street":"Cedar Ave",
    "iso:country":"US",
    "sg:address":"15100 Cedar Ave",
    "sg:city":"Apple Valley",
    "sg:classifiers":[
        {
            "category":"Ice Cream",
            "type":"Food & Drink"
        }
    ],
    "sg:menulink":"http://www.allmenus.com/mn/apple-valley/184893-cold-stone-creamery/menu/",
    "sg:phone":"+1 952 432 3739",
    "sg:postcode":"55124",
    "sg:province":"MN",
    "sg:tags":[
        "smoothy",
        "juice",
        "american"
    ],
    "wof:name":"Cold Stone Creamery",
    "wof:placetype":"venue"
},
  "geometry": {"coordinates":[-93.21760500000001,44.730217],"type":"Point"}
}