{
  "type": "Feature",
  "properties": {
    "addr:full":"13603 Grand Ave Burnsville MN 55337",
    "addr:housenumber":"13603",
    "addr:postcode":"55337",
    "addr:street":"Grand Ave",
    "iso:country":"US",
    "sg:address":"13603 Grand Ave",
    "sg:city":"Burnsville",
    "sg:classifiers":[
        {
            "category":"Professional",
            "subcategory":"Lawyer & Legal Services",
            "type":"Services"
        }
    ],
    "sg:phone":"+1 952 894 3959",
    "sg:postcode":"55337",
    "sg:province":"MN",
    "wof:name":"Robert M Wasilensky",
    "wof:placetype":"venue"
},
  "geometry": {"coordinates":[-93.28671799999999,44.756019],"type":"Point"}
}