{
  "type": "Feature",
  "properties": {
    "iso:country":"US",
    "sg:address":"1764 Hampshire Ave",
    "sg:city":"St Paul",
    "sg:classifiers":[
        {
            "category":"Travel",
            "subcategory":"Campground",
            "type":"Entertainment"
        }
    ],
    "sg:phone":"+1 651 695 1988",
    "sg:postcode":"55116",
    "sg:province":"MN",
    "sg:tags":[
        "camp"
    ],
    "wof:name":"Grandkidsandme",
    "wof:placetype":"venue"
},
  "geometry": {"coordinates":[-93.175887,44.911419],"type":"Point"}
}