{
  "type": "Feature",
  "properties": {
    "addr:full":"67517 270th Ave Kasson MN 55944",
    "addr:housenumber":"67517",
    "addr:postcode":"55944",
    "addr:street":"270Th Ave",
    "iso:country":"US",
    "sg:address":"67517 270th Ave",
    "sg:city":"Kasson",
    "sg:classifiers":[
        {
            "category":"Building & Trades",
            "subcategory":"Construction",
            "type":"Services"
        }
    ],
    "sg:phone":"+1 507 365 8494",
    "sg:postcode":"55944",
    "sg:province":"MN",
    "sg:tags":[
        "carpentry",
        "contractor"
    ],
    "wof:name":"Daryl A Smith",
    "wof:placetype":"venue"
},
  "geometry": {"coordinates":[-92.698196,43.969924],"type":"Point"}
}