{
  "type": "Feature",
  "properties": {
    "addr:full":"1795 Radio Dr St Paul MN 55125",
    "addr:housenumber":"1795",
    "addr:postcode":"55125",
    "addr:street":"Radio Dr",
    "iso:country":"US",
    "sg:address":"1795 Radio Dr",
    "sg:city":"St Paul",
    "sg:classifiers":[
        {
            "category":"Banks & Credit Unions",
            "subcategory":"Bank",
            "type":"Services"
        }
    ],
    "sg:phone":"+1 651 735 3781",
    "sg:postcode":"55125",
    "sg:province":"MN",
    "sg:tags":[
        "financing"
    ],
    "wof:name":"Wells Fargo Financial",
    "wof:placetype":"venue"
},
  "geometry": {"coordinates":[-92.933998,44.920456],"type":"Point"}
}