{
  "type": "Feature",
  "properties": {
    "iso:country":"US",
    "sg:address":"3550 W 145th St",
    "sg:city":"Burnsville",
    "sg:classifiers":[
        {
            "category":"Education",
            "subcategory":"Kindergarten",
            "type":"Public Place"
        }
    ],
    "sg:phone":"+1 952 746 3344",
    "sg:postcode":"55306",
    "sg:province":"MN",
    "sg:tags":[
        "school",
        "driving"
    ],
    "wof:name":"1st Class Driving School",
    "wof:placetype":"venue"
},
  "geometry": {"coordinates":[-93.325355,44.740348],"type":"Point"}
}