{
  "type": "Feature",
  "properties": {
    "addr:full":"800 N Shore Dr Waverly MN 55390",
    "addr:housenumber":"800",
    "addr:postcode":"55390",
    "addr:street":"N Shore Dr",
    "iso:country":"US",
    "sg:address":"800 N Shore Dr",
    "sg:city":"Waverly",
    "sg:classifiers":[
        {
            "category":"Building & Trades",
            "subcategory":"Construction",
            "type":"Services"
        }
    ],
    "sg:phone":"+1 763 658 7045",
    "sg:postcode":"55390",
    "sg:province":"MN",
    "wof:name":"Chase Communications",
    "wof:placetype":"venue"
},
  "geometry": {"coordinates":[-93.97252,45.081065],"type":"Point"}
}