{
  "type": "Feature",
  "properties": {
    "iso:country":"US",
    "sg:address":"210 N 2nd St Ste 70",
    "sg:city":"Minneapolis",
    "sg:classifiers":[
        {
            "category":"Professional",
            "subcategory":"Lawyer & Legal Services",
            "type":"Services"
        }
    ],
    "sg:phone":"+1 612 370 1406",
    "sg:postcode":"55401",
    "sg:province":"MN",
    "wof:name":"Vanderhyde Blake Atty",
    "wof:placetype":"venue"
},
  "geometry": {"coordinates":[-93.270127,44.984744],"type":"Point"}
}