{
  "type": "Feature",
  "properties": {
    "iso:country":"US",
    "sg:address":"221 Mineral Springs Rd",
    "sg:city":"Owatonna",
    "sg:classifiers":[
        {
            "category":"Fast Food",
            "type":"Food & Drink"
        },
        {
            "category":"Restaurant",
            "type":"Food & Drink"
        },
        {
            "category":"Professional",
            "type":"Services"
        }
    ],
    "sg:phone":"+1 507 451 3030",
    "sg:postcode":"55060",
    "sg:province":"MN",
    "sg:tags":[
        "delivery",
        "take",
        "pizza"
    ],
    "sg:website":"http://www.dominospizza.com",
    "wof:name":"Domino's Pizza",
    "wof:placetype":"venue"
},
  "geometry": {"coordinates":[-93.220479,44.088999],"type":"Point"}
}