{
  "type": "Feature",
  "properties": {
    "addr:full":"112 Pine Bend Ave Spring Valley MN 55975",
    "addr:housenumber":"112",
    "addr:postcode":"55975",
    "addr:street":"Pine Bend Ave",
    "iso:country":"US",
    "sg:address":"112 Pine Bend Ave",
    "sg:city":"Spring Valley",
    "sg:classifiers":[
        {
            "category":"Professional",
            "type":"Services"
        }
    ],
    "sg:phone":"+1 507 346 7940",
    "sg:postcode":"55975",
    "sg:province":"MN",
    "wof:name":"Hendermax Inc",
    "wof:placetype":"venue"
},
  "geometry": {"coordinates":[-92.390806,43.691932],"type":"Point"}
}