{
  "type": "Feature",
  "properties": {
    "addr:full":"2581 Cleveland Ave N Roseville MN 55113",
    "addr:housenumber":"2581",
    "addr:postcode":"55113",
    "addr:street":"Cleveland Ave N",
    "iso:country":"US",
    "sg:address":"2581 Cleveland Ave N",
    "sg:city":"Roseville",
    "sg:classifiers":[
        {
            "category":"Retail",
            "subcategory":"Veterinary Services",
            "type":"Services"
        }
    ],
    "sg:phone":"+1 651 633 5700",
    "sg:postcode":"55113",
    "sg:province":"MN",
    "sg:tags":[
        "veterinarian"
    ],
    "wof:name":"Suburban Animal Hospital",
    "wof:placetype":"venue"
},
  "geometry": {"coordinates":[-93.187347,45.018698],"type":"Point"}
}