{
  "type": "Feature",
  "properties": {
    "iso:country":"US",
    "sg:address":"6625 Lyndale Ave S",
    "sg:city":"Minneapolis",
    "sg:classifiers":[
        {
            "category":"Professional",
            "subcategory":"Lawyer & Legal Services",
            "type":"Services"
        }
    ],
    "sg:phone":"+1 612 861 3331",
    "sg:postcode":"55423",
    "sg:province":"MN",
    "sg:tags":[
        "law"
    ],
    "wof:name":"Orlins Law Office",
    "wof:placetype":"venue"
},
  "geometry": {"coordinates":[-93.28663899999999,44.883285],"type":"Point"}
}