{
  "type": "Feature",
  "properties": {
    "iso:country":"US",
    "sg:address":"321 Nokomis St",
    "sg:city":"Alexandria",
    "sg:classifiers":[
        {
            "category":"Building & Trades",
            "subcategory":"Construction",
            "type":"Services"
        }
    ],
    "sg:phone":"+1 320 762 5447",
    "sg:postcode":"56308",
    "sg:province":"MN",
    "sg:tags":[
        "contractor",
        "glazier",
        "glazing"
    ],
    "sg:website":"http://www.alexglassandglazing.com",
    "wof:name":"Alex Glass And Glazing",
    "wof:placetype":"venue"
},
  "geometry": {"coordinates":[-95.366647,45.889014],"type":"Point"}
}