{
  "type": "Feature",
  "properties": {
    "iso:country":"US",
    "sg:address":"4215 Cooke St",
    "sg:city":"Duluth",
    "sg:phone":"+1 218 525 4258",
    "sg:postcode":"55804",
    "sg:province":"MN",
    "sg:tags":[
        "farm",
        "grain",
        "cash"
    ],
    "wof:name":"Lingua Kinetica",
    "wof:placetype":"venue"
},
  "geometry": {"coordinates":[-92.03693,46.831416],"type":"Point"}
}