{
  "type": "Feature",
  "properties": {
    "addr:full":"4402 Cooke St Duluth MN 55804",
    "addr:housenumber":"4402",
    "addr:postcode":"55804",
    "addr:street":"Cooke St",
    "iso:country":"US",
    "sg:address":"4402 Cooke St",
    "sg:city":"Duluth",
    "sg:classifiers":[
        {
            "category":"Professional",
            "type":"Services"
        }
    ],
    "sg:phone":"+1 218 525 1046",
    "sg:postcode":"55804",
    "sg:province":"MN",
    "wof:name":"Alabsi Mustafa",
    "wof:placetype":"venue"
},
  "geometry": {"coordinates":[-92.033051,46.83128],"type":"Point"}
}