{
  "type": "Feature",
  "properties": {
    "addr:full":"1543 Como Ave St Paul MN 55108",
    "addr:housenumber":"1543",
    "addr:postcode":"55108",
    "addr:street":"Como Ave",
    "iso:country":"US",
    "sg:address":"1543 Como Ave",
    "sg:city":"St Paul",
    "sg:classifiers":[
        {
            "category":"Professional",
            "type":"Services"
        }
    ],
    "sg:phone":"+1 651 646 8819",
    "sg:postcode":"55108",
    "sg:province":"MN",
    "sg:tags":[
        "establishment"
    ],
    "wof:name":"Rosso & Seierstad Pa",
    "wof:placetype":"venue"
},
  "geometry": {"coordinates":[-93.165505,44.9774],"type":"Point"}
}