{
  "type": "Feature",
  "properties": {
    "iso:country":"US",
    "sg:address":"15020 Glazier Ave",
    "sg:city":"Apple Valley",
    "sg:classifiers":[
        {
            "category":"Restaurant",
            "type":"Food & Drink"
        }
    ],
    "sg:menulink":"http://www.allmenus.com/mn/apple-valley/56819-grizzlys/menu/",
    "sg:phone":"+1 952 431 3216",
    "sg:postcode":"55124",
    "sg:province":"MN",
    "sg:tags":[
        "american"
    ],
    "wof:name":"Grizzly's",
    "wof:placetype":"venue"
},
  "geometry": {"coordinates":[-93.214305,44.732752],"type":"Point"}
}