{
  "type": "Feature",
  "properties": {
    "addr:full":"21469 Tower Rd Emily MN 56447",
    "addr:housenumber":"21469",
    "addr:postcode":"56447",
    "addr:street":"Tower Rd",
    "iso:country":"US",
    "sg:address":"21469 Tower Rd",
    "sg:city":"Emily",
    "sg:classifiers":[
        {
            "category":"Freight",
            "type":"Transportation"
        }
    ],
    "sg:phone":"+1 218 763 3228",
    "sg:postcode":"56447",
    "sg:province":"MN",
    "sg:tags":[
        "trucking"
    ],
    "wof:name":"North Central Transfer Inc",
    "wof:placetype":"venue"
},
  "geometry": {"coordinates":[-93.949826,46.678906],"type":"Point"}
}