{
  "type": "Feature",
  "properties": {
    "iso:country":"US",
    "sg:address":"121 Railroad St",
    "sg:city":"Lake Crystal",
    "sg:classifiers":[
        {
            "category":"Building & Trades",
            "subcategory":"Construction",
            "type":"Services"
        }
    ],
    "sg:phone":"+1 507 947 3389",
    "sg:postcode":"56055",
    "sg:province":"MN",
    "sg:tags":[
        "contractor"
    ],
    "wof:name":"Jenkins Insulation",
    "wof:placetype":"venue"
},
  "geometry": {"coordinates":[-94.198919,44.195453],"type":"Point"}
}