{
  "type": "Feature",
  "properties": {
    "addr:full":"2382 Leibel St White Bear Lake MN 55110",
    "addr:housenumber":"2382",
    "addr:postcode":"55110",
    "addr:street":"Leibel St",
    "iso:country":"US",
    "sg:address":"2382 Leibel St",
    "sg:city":"White Bear Lake",
    "sg:classifiers":[
        {
            "category":"Building & Trades",
            "subcategory":"Construction",
            "type":"Services"
        }
    ],
    "sg:phone":"+1 651 762 2500",
    "sg:postcode":"55110",
    "sg:province":"MN",
    "sg:tags":[
        "sewer",
        "contractor"
    ],
    "wof:name":"Capra's Utilities",
    "wof:placetype":"venue"
},
  "geometry": {"coordinates":[-92.997849,45.121821],"type":"Point"}
}