{
  "type": "Feature",
  "properties": {
    "addr:full":"1871 Woodstone Dr Victoria MN 55386",
    "addr:housenumber":"1871",
    "addr:postcode":"55386",
    "addr:street":"Woodstone Dr",
    "iso:country":"US",
    "sg:address":"1871 Woodstone Dr",
    "sg:city":"Victoria",
    "sg:classifiers":[
        {
            "category":"Professional",
            "subcategory":"Business Services",
            "type":"Services"
        }
    ],
    "sg:phone":"+1 952 443 3602",
    "sg:postcode":"55386",
    "sg:province":"MN",
    "wof:name":"Pet Ventures Inc",
    "wof:placetype":"venue"
},
  "geometry": {"coordinates":[-93.66567999999999,44.849626],"type":"Point"}
}