{
  "type": "Feature",
  "properties": {
    "iso:country":"US",
    "sg:address":"2730 1st Ave",
    "sg:city":"Hibbing",
    "sg:classifiers":[
        {
            "category":"Shopping",
            "subcategory":"Bicycles & Sporting Goods",
            "type":"Retail Goods"
        }
    ],
    "sg:phone":"+1 218 262 4626",
    "sg:postcode":"55746",
    "sg:province":"MN",
    "sg:tags":[
        "repair",
        "sport"
    ],
    "wof:name":"Modich Northland Sports",
    "wof:placetype":"venue"
},
  "geometry": {"coordinates":[-92.94165099999999,47.418805],"type":"Point"}
}