{
  "type": "Feature",
  "properties": {
    "addr:full":"1629 Birch Ln NE Bemidji MN 56601",
    "addr:housenumber":"1629",
    "addr:postcode":"56601",
    "addr:street":"Birch Ln Ne",
    "iso:country":"US",
    "sg:address":"1629 Birch Ln NE",
    "sg:city":"Bemidji",
    "sg:classifiers":[
        {
            "category":"Wholesale",
            "subcategory":"Toys & Hobbies",
            "type":"Manufacturing & Wholesale Goods"
        }
    ],
    "sg:phone":"+1 218 759 3069",
    "sg:postcode":"56601",
    "sg:province":"MN",
    "sg:tags":[
        "wholesaler"
    ],
    "wof:name":"Studio",
    "wof:placetype":"venue"
},
  "geometry": {"coordinates":[-94.87520600000001,47.48482],"type":"Point"}
}