{
  "type": "Feature",
  "properties": {
    "iso:country":"US",
    "sg:address":"701 4th Ave S",
    "sg:city":"Minneapolis",
    "sg:classifiers":[
        {
            "category":"Banks & Credit Unions",
            "subcategory":"Bank",
            "type":"Services"
        }
    ],
    "sg:phone":"+1 612 337 9520",
    "sg:postcode":"55415",
    "sg:province":"MN",
    "wof:name":"Bank One",
    "wof:placetype":"venue"
},
  "geometry": {"coordinates":[-93.26759199999999,44.973621],"type":"Point"}
}