{
  "type": "Feature",
  "properties": {
    "addr:full":"2729 2nd Ave E Internatl Falls MN 56649",
    "addr:housenumber":"2729",
    "addr:postcode":"56649",
    "addr:street":"2Nd Ave E Internatl",
    "iso:country":"US",
    "sg:address":"2729 2nd Ave E",
    "sg:city":"Internatl Falls",
    "sg:classifiers":[
        {
            "category":"Organizations",
            "subcategory":"Labor Organization",
            "type":"Services"
        }
    ],
    "sg:phone":"+1 218 285 3666",
    "sg:postcode":"56649",
    "sg:province":"MN",
    "wof:name":"Plumbers & Fitters Local Union",
    "wof:placetype":"venue"
},
  "geometry": {"coordinates":[-93.396486,48.574406],"type":"Point"}
}