{
  "type": "Feature",
  "properties": {
    "addr:full":"2830 N Pine Creek Rd La Crescent MN 55947",
    "addr:housenumber":"2830",
    "addr:postcode":"55947",
    "addr:street":"N Pine Creek Rd",
    "iso:country":"US",
    "sg:address":"2830 N Pine Creek Rd",
    "sg:city":"La Crescent",
    "sg:classifiers":[
        {
            "category":"Retail",
            "subcategory":"Auto Repair",
            "type":"Services"
        }
    ],
    "sg:phone":"+1 507 895 6766",
    "sg:postcode":"55947",
    "sg:province":"MN",
    "sg:tags":[
        "automotive",
        "general"
    ],
    "wof:name":"Pine Creek Auto Inc",
    "wof:placetype":"venue"
},
  "geometry": {"coordinates":[-91.342625,43.833243],"type":"Point"}
}