{
  "type": "Feature",
  "properties": {
    "addr:full":"11211 Co Rd 37 NW Annandale MN 55302",
    "addr:housenumber":"11211;37",
    "addr:postcode":"55302",
    "addr:street":"Co Rd",
    "iso:country":"US",
    "sg:address":"11211 Co Rd 37 NW",
    "sg:city":"Annandale",
    "sg:classifiers":[
        {
            "category":"Building & Trades",
            "subcategory":"Construction",
            "type":"Services"
        }
    ],
    "sg:phone":"+1 320 274 5787",
    "sg:postcode":"55302",
    "sg:province":"MN",
    "sg:tags":[
        "painter"
    ],
    "wof:name":"Smith Painting & Decorating",
    "wof:placetype":"venue"
},
  "geometry": {"coordinates":[-94.119186,45.205057],"type":"Point"}
}