{
  "type": "Feature",
  "properties": {
    "addr:full":"3001 Hennepin Ave Minneapolis MN 55408",
    "addr:housenumber":"3001",
    "addr:postcode":"55408",
    "addr:street":"Hennepin Ave",
    "iso:country":"US",
    "sg:address":"3001 Hennepin Ave",
    "sg:city":"Minneapolis",
    "sg:classifiers":[
        {
            "category":"Restaurant",
            "type":"Food & Drink"
        }
    ],
    "sg:phone":"+1 612 822 7787",
    "sg:postcode":"55408",
    "sg:province":"MN",
    "sg:tags":[
        "sushi",
        "bar"
    ],
    "wof:name":"Sushi Tango",
    "wof:placetype":"venue"
},
  "geometry": {"coordinates":[-93.297217,44.947187],"type":"Point"}
}