{
  "type": "Feature",
  "properties": {
    "iso:country":"US",
    "sg:address":"33804 Mountain Ash Dr",
    "sg:city":"Hill City",
    "sg:classifiers":[
        {
            "category":"Travel",
            "subcategory":"Hotels & Motels",
            "type":"Entertainment"
        }
    ],
    "sg:phone":"+1 218 697 8119",
    "sg:postcode":"55748",
    "sg:province":"MN",
    "sg:tags":[
        "resort"
    ],
    "wof:name":"Northwoods Retreat",
    "wof:placetype":"venue"
},
  "geometry": {"coordinates":[-93.58041900000001,47.04381],"type":"Point"}
}