{
  "type": "Feature",
  "properties": {
    "addr:full":"38 McLeod Ave NE Hutchinson MN 55350",
    "addr:housenumber":"38",
    "addr:postcode":"55350",
    "addr:street":"Mcleod Ave Ne",
    "iso:country":"US",
    "sg:address":"38 McLeod Ave NE",
    "sg:city":"Hutchinson",
    "sg:classifiers":[
        {
            "category":"Professional",
            "type":"Services"
        }
    ],
    "sg:phone":"+1 320 587 3756",
    "sg:postcode":"55350",
    "sg:province":"MN",
    "wof:name":"Wooster Technical Services",
    "wof:placetype":"venue"
},
  "geometry": {"coordinates":[-94.366497,44.899555],"type":"Point"}
}