{
  "type": "Feature",
  "properties": {
    "iso:country":"US",
    "sg:address":"11543 42nd St",
    "sg:city":"Clear Lake",
    "sg:classifiers":[
        {
            "category":"Manufacturing",
            "subcategory":"Signs",
            "type":"Manufacturing & Wholesale Goods"
        }
    ],
    "sg:phone":"+1 320 743 3760",
    "sg:postcode":"55319",
    "sg:province":"MN",
    "sg:tags":[
        "specialty",
        "mfg"
    ],
    "wof:name":"Perkins Signs and Graphics",
    "wof:placetype":"venue"
},
  "geometry": {"coordinates":[-93.923039,45.508241],"type":"Point"}
}