{
  "type": "Feature",
  "properties": {
    "iso:country":"US",
    "sg:address":"2311 10th Ave S",
    "sg:city":"Saint Cloud",
    "sg:classifiers":[
        {
            "category":"Professional",
            "subcategory":"Business Services",
            "type":"Services"
        }
    ],
    "sg:phone":"+1 320 290 0420",
    "sg:postcode":"56301",
    "sg:province":"MN",
    "wof:name":"Message Program",
    "wof:placetype":"venue"
},
  "geometry": {"coordinates":[-94.162948,45.533272],"type":"Point"}
}