{
  "type": "Feature",
  "properties": {
    "iso:country":"US",
    "sg:address":"6240 US Hwy 12",
    "sg:city":"Maple Plain",
    "sg:classifiers":[
        {
            "category":"Building & Trades",
            "subcategory":"Construction",
            "type":"Services"
        }
    ],
    "sg:phone":"+1 763 479 1797",
    "sg:postcode":"55359",
    "sg:province":"MN",
    "sg:tags":[
        "water",
        "well",
        "pump",
        "e",
        "drilling"
    ],
    "wof:name":"STEVENS DRILLING & ENVIRONMENT",
    "wof:placetype":"venue"
},
  "geometry": {"coordinates":[-93.682773,45.009373],"type":"Point"}
}