{
  "type": "Feature",
  "properties": {
    "addr:full":"4 Park Ln Minneapolis MN 55416",
    "addr:housenumber":"4",
    "addr:postcode":"55416",
    "addr:street":"Park Ln",
    "iso:country":"US",
    "sg:address":"4 Park Ln",
    "sg:city":"Minneapolis",
    "sg:classifiers":[
        {
            "category":"Bakery",
            "type":"Food & Drink"
        }
    ],
    "sg:phone":"+1 612 920 7537",
    "sg:postcode":"55416",
    "sg:province":"MN",
    "wof:name":"Mary L Schwebel",
    "wof:placetype":"venue"
},
  "geometry": {"coordinates":[-93.31881,44.956039],"type":"Point"}
}