{
  "type": "Feature",
  "properties": {
    "iso:country":"US",
    "sg:address":"2450 Childs Rd",
    "sg:city":"St Paul",
    "sg:classifiers":[
        {
            "category":"Shopping",
            "subcategory":"Discount & Variety Stores",
            "type":"Retail Goods"
        },
        {
            "category":"Building & Trades",
            "subcategory":"Electrical",
            "type":"Services"
        }
    ],
    "sg:phone":"+1 651 774 0565",
    "sg:postcode":"55106",
    "sg:province":"MN",
    "sg:tags":[
        "general",
        "electric",
        "merchandise",
        "contractor"
    ],
    "wof:name":"Premier Electric",
    "wof:placetype":"venue"
},
  "geometry": {"coordinates":[-93.047264,44.921736],"type":"Point"}
}