{
  "type": "Feature",
  "properties": {
    "addr:full":"5970 US Hwy 61 White Bear Lake MN 55110",
    "addr:housenumber":"5970",
    "addr:postcode":"55110",
    "addr:street":"Us Hwy 61",
    "iso:country":"US",
    "sg:address":"5970 US Hwy 61",
    "sg:city":"White Bear Lake",
    "sg:classifiers":[
        {
            "category":"Food & Beverages",
            "subcategory":"Groceries & Convenience Stores",
            "type":"Retail Goods"
        }
    ],
    "sg:phone":"+1 651 426 6887",
    "sg:postcode":"55110",
    "sg:province":"MN",
    "wof:name":"Bartness Inc",
    "wof:placetype":"venue"
},
  "geometry": {"coordinates":[-93.003146,45.12203],"type":"Point"}
}