{
  "type": "Feature",
  "properties": {
    "iso:country":"US",
    "sg:address":"2835 Central Ave NE",
    "sg:city":"Minneapolis",
    "sg:classifiers":[
        {
            "category":"Professional",
            "subcategory":"Management & Consulting",
            "type":"Services"
        }
    ],
    "sg:phone":"+1 612 788 2130",
    "sg:postcode":"55418",
    "sg:province":"MN",
    "wof:name":"S & J Ventures",
    "wof:placetype":"venue"
},
  "geometry": {"coordinates":[-93.24742000000001,45.019751],"type":"Point"}
}