{
  "type": "Feature",
  "properties": {
    "iso:country":"US",
    "sg:address":"11047 57th Ave SW",
    "sg:city":"Pillager",
    "sg:classifiers":[
        {
            "category":"Farming",
            "subcategory":"Livestock Farm",
            "type":"Manufacturing & Wholesale Goods"
        }
    ],
    "sg:phone":"+1 218 746 3197",
    "sg:postcode":"56473",
    "sg:province":"MN",
    "sg:tags":[
        "hog"
    ],
    "wof:name":"Pine Ridge Pork",
    "wof:placetype":"venue"
},
  "geometry": {"coordinates":[-94.581005,46.403825],"type":"Point"}
}