{
  "type": "Feature",
  "properties": {
    "iso:country":"US",
    "sg:address":"3824 42nd Ave S",
    "sg:city":"Minneapolis",
    "sg:classifiers":[
        {
            "category":"Communications",
            "subcategory":"Film & Video Production",
            "type":"Services"
        }
    ],
    "sg:phone":"+1 612 729 0648",
    "sg:postcode":"55406",
    "sg:province":"MN",
    "sg:tags":[
        "tv",
        "radio",
        "services-commercial",
        "companies-film"
    ],
    "wof:name":"Thompson Production",
    "wof:placetype":"venue"
},
  "geometry": {"coordinates":[-93.212765,44.933835],"type":"Point"}
}