{
  "type": "Feature",
  "properties": {
    "iso:country":"US",
    "sg:address":"794 Stoughton Ave",
    "sg:city":"Chaska",
    "sg:classifiers":[
        {
            "category":"Building & Trades",
            "subcategory":"Construction",
            "type":"Services"
        }
    ],
    "sg:phone":"+1 952 368 3200",
    "sg:postcode":"55318",
    "sg:province":"MN",
    "sg:tags":[
        "concrete",
        "contractor"
    ],
    "wof:name":"AAA Concrete & Masonry",
    "wof:placetype":"venue"
},
  "geometry": {"coordinates":[-93.59363999999999,44.791903],"type":"Point"}
}