{
  "type": "Feature",
  "properties": {
    "addr:full":"3830 Rustic Pl Saint Paul MN 55126",
    "addr:housenumber":"3830",
    "addr:postcode":"55126",
    "addr:street":"Rustic Pl",
    "iso:country":"US",
    "sg:address":"3830 Rustic Pl",
    "sg:city":"Saint Paul",
    "sg:classifiers":[
        {
            "category":"Professional",
            "subcategory":"Computer Services",
            "type":"Services"
        }
    ],
    "sg:phone":"+1 651 482 9680",
    "sg:postcode":"55126",
    "sg:province":"MN",
    "sg:tags":[
        "integrate",
        "communications",
        "net",
        "existing"
    ],
    "wof:name":"Thom Tech",
    "wof:placetype":"venue"
},
  "geometry": {"coordinates":[-93.107626,45.051888],"type":"Point"}
}