{
  "type": "Feature",
  "properties": {
    "iso:country":"US",
    "sg:address":"17715 380th St",
    "sg:city":"Mcgregor",
    "sg:classifiers":[
        {
            "category":"Government",
            "subcategory":"Office",
            "type":"Public Place"
        }
    ],
    "sg:phone":"+1 218 768 4481",
    "sg:postcode":"55760",
    "sg:province":"MN",
    "wof:name":"Aitkin County Highway Garage",
    "wof:placetype":"venue"
},
  "geometry": {"coordinates":[-93.23516100000001,46.563555],"type":"Point"}
}