{
  "type": "Feature",
  "properties": {
    "addr:full":"1160 Richland Ave Saint Charles MN 55972",
    "addr:housenumber":"1160",
    "addr:postcode":"55972",
    "addr:street":"Richland Ave",
    "iso:country":"US",
    "sg:address":"1160 Richland Ave",
    "sg:city":"Saint Charles",
    "sg:classifiers":[
        {
            "category":"Real Estate",
            "subcategory":"Real Estate Operator",
            "type":"Services"
        }
    ],
    "sg:phone":"+1 507 932 3135",
    "sg:postcode":"55972",
    "sg:province":"MN",
    "sg:tags":[
        "property",
        "lessor"
    ],
    "wof:name":"Carl Benedett",
    "wof:placetype":"venue"
},
  "geometry": {"coordinates":[-92.06204,43.967671],"type":"Point"}
}