{
  "type": "Feature",
  "properties": {
    "addr:full":"975 Millwood Ave Saint Paul MN 55113",
    "addr:housenumber":"975",
    "addr:postcode":"55113",
    "addr:street":"Millwood Ave",
    "iso:country":"US",
    "sg:address":"975 Millwood Ave",
    "sg:city":"Saint Paul",
    "sg:classifiers":[
        {
            "category":"Professional",
            "type":"Services"
        }
    ],
    "sg:phone":"+1 651 484 6779",
    "sg:postcode":"55113",
    "sg:province":"MN",
    "wof:name":"Millwood Originals",
    "wof:placetype":"venue"
},
  "geometry": {"coordinates":[-93.138757,45.029917],"type":"Point"}
}