{
  "type": "Feature",
  "properties": {
    "iso:country":"US",
    "sg:address":"1376 Hickory St",
    "sg:city":"Ogilvie",
    "sg:classifiers":[
        {
            "category":"Manufacturing",
            "subcategory":"Tools & Machinery",
            "type":"Manufacturing & Wholesale Goods"
        },
        {
            "category":"Autos & Motor Vehicles",
            "subcategory":"Fuel & Gas Station",
            "type":"Retail Goods"
        }
    ],
    "sg:phone":"+1 320 679 4388",
    "sg:postcode":"56358",
    "sg:province":"MN",
    "sg:tags":[
        "molds-wholesale",
        "mold",
        "manufacturer"
    ],
    "wof:name":"White Tail Tool, Inc",
    "wof:placetype":"venue"
},
  "geometry": {"coordinates":[-93.358238,45.785106],"type":"Point"}
}