{
  "type": "Feature",
  "properties": {
    "addr:full":"31902 Robinhood Ln Pequot Lakes MN 56472",
    "addr:postcode":"31902;56472",
    "addr:street":"Robinhood Ln",
    "iso:country":"US",
    "sg:address":"31902 Robinhood Ln",
    "sg:city":"Pequot Lakes",
    "sg:classifiers":[
        {
            "category":"Professional",
            "subcategory":"Business Services",
            "type":"Services"
        }
    ],
    "sg:phone":"+1 218 568 7240",
    "sg:postcode":"56472",
    "sg:province":"MN",
    "wof:name":"Ras Enterprises",
    "wof:placetype":"venue"
},
  "geometry": {"coordinates":[-94.259575,46.615312],"type":"Point"}
}