{
  "type": "Feature",
  "properties": {
    "iso:country":"US",
    "sg:address":"1929 S Cedar Ave",
    "sg:city":"Owatonna",
    "sg:classifiers":[
        {
            "category":"Health Services",
            "subcategory":"Health Practitioner",
            "type":"Services"
        }
    ],
    "sg:phone":"+1 507 451 7888",
    "sg:postcode":"55060",
    "sg:province":"MN",
    "wof:name":"Anne Rpt Lamb",
    "wof:placetype":"venue"
},
  "geometry": {"coordinates":[-93.22601299999999,44.064306],"type":"Point"}
}