{
  "type": "Feature",
  "properties": {
    "addr:full":"27594 Youngston Dr NE Isanti MN 55040",
    "addr:postcode":"27594;55040",
    "addr:street":"Youngston Dr Ne",
    "iso:country":"US",
    "sg:address":"27594 Youngston Dr NE",
    "sg:city":"Isanti",
    "sg:classifiers":[
        {
            "category":"Building & Trades",
            "subcategory":"Construction",
            "type":"Services"
        }
    ],
    "sg:phone":"+1 763 444 5720",
    "sg:postcode":"55040",
    "sg:province":"MN",
    "sg:tags":[
        "concrete",
        "contractor"
    ],
    "wof:name":"Pankan Bob Jr Con Masnry Contr",
    "wof:placetype":"venue"
},
  "geometry": {"coordinates":[-93.13650699999999,45.469966],"type":"Point"}
}