{
  "type": "Feature",
  "properties": {
    "addr:full":"7616 Currell Blvd St Paul MN 55125",
    "addr:housenumber":"7616",
    "addr:postcode":"55125",
    "addr:street":"Currell Blvd",
    "iso:country":"US",
    "sg:address":"7616 Currell Blvd",
    "sg:city":"St Paul",
    "sg:classifiers":[
        {
            "category":"Social Services",
            "type":"Services"
        }
    ],
    "sg:phone":"+1 651 739 9742",
    "sg:postcode":"55125",
    "sg:province":"MN",
    "sg:tags":[
        "counseling"
    ],
    "wof:name":"Growth Dynamics Counseling Cli",
    "wof:placetype":"venue"
},
  "geometry": {"coordinates":[-92.95106199999999,44.924583],"type":"Point"}
}