{
  "type": "Feature",
  "properties": {
    "iso:country":"US",
    "sg:address":"4841 Diane Dr",
    "sg:city":"Hopkins",
    "sg:classifiers":[
        {
            "category":"Professional",
            "subcategory":"Computer Services",
            "type":"Services"
        }
    ],
    "sg:phone":"+1 952 933 6555",
    "sg:postcode":"55343",
    "sg:province":"MN",
    "sg:tags":[
        "programing",
        "custom"
    ],
    "wof:name":"B & H Computer Svc",
    "wof:placetype":"venue"
},
  "geometry": {"coordinates":[-93.43324800000001,44.915288],"type":"Point"}
}