{
  "type": "Feature",
  "properties": {
    "addr:full":"7964 Brooklyn Blvd Minneapolis MN 55445",
    "addr:housenumber":"7964",
    "addr:postcode":"55445",
    "addr:street":"Brooklyn Blvd",
    "iso:country":"US",
    "sg:address":"7964 Brooklyn Blvd",
    "sg:city":"Minneapolis",
    "sg:classifiers":[
        {
            "category":"Manufacturing",
            "subcategory":"Buildings",
            "type":"Manufacturing & Wholesale Goods"
        },
        {
            "category":"Building & Trades",
            "subcategory":"Construction",
            "type":"Services"
        }
    ],
    "sg:phone":"+1 763 566 2808",
    "sg:postcode":"55445",
    "sg:province":"MN",
    "sg:tags":[
        "roofing",
        "industrial",
        "builder",
        "specialty",
        "contractor",
        "heating",
        "contractors-commercial",
        "home"
    ],
    "wof:name":"Pro-Pride Contractors",
    "wof:placetype":"venue"
},
  "geometry": {"coordinates":[-93.37498600000001,45.09456],"type":"Point"}
}