{
  "type": "Feature",
  "properties": {
    "iso:country":"US",
    "sg:address":"7251 135th St SW",
    "sg:city":"Raymond",
    "sg:classifiers":[
        {
            "category":"Real Estate",
            "subcategory":"Real Estate Operator",
            "type":"Services"
        }
    ],
    "sg:phone":"+1 320 967 4396",
    "sg:postcode":"56282",
    "sg:province":"MN",
    "sg:tags":[
        "property",
        "lessor"
    ],
    "wof:name":"Ryks Melbourne",
    "wof:placetype":"venue"
},
  "geometry": {"coordinates":[-95.227858,45.051768],"type":"Point"}
}