{
  "type": "Feature",
  "properties": {
    "iso:country":"US",
    "sg:address":"7204 Washington Ave S",
    "sg:city":"Eden Prairie",
    "sg:classifiers":[
        {
            "category":"Autos & Motor Vehicles",
            "subcategory":"Automobile Sales",
            "type":"Retail Goods"
        }
    ],
    "sg:phone":"+1 952 942 5161",
    "sg:postcode":"55344",
    "sg:province":"MN",
    "sg:tags":[
        "car",
        "dealer"
    ],
    "wof:name":"Crosstown Luxury Motors",
    "wof:placetype":"venue"
},
  "geometry": {"coordinates":[-93.398438,44.86911],"type":"Point"}
}