{
  "type": "Feature",
  "properties": {
    "iso:country":"US",
    "sg:address":"1505 9th St SE",
    "sg:city":"Willmar",
    "sg:classifiers":[
        {
            "category":"Social Services",
            "subcategory":"Child Care",
            "type":"Services"
        }
    ],
    "sg:phone":"+1 320 235 0296",
    "sg:postcode":"56201",
    "sg:province":"MN",
    "sg:tags":[
        "day",
        "provides"
    ],
    "wof:name":"Darlene K Welch",
    "wof:placetype":"venue"
},
  "geometry": {"coordinates":[-95.031751,45.106396],"type":"Point"}
}