{
  "type": "Feature",
  "properties": {
    "iso:country":"US",
    "sg:address":"125 Main St",
    "sg:city":"Bowlus",
    "sg:classifiers":[
        {
            "category":"Retail",
            "subcategory":"Auto Repair",
            "type":"Services"
        }
    ],
    "sg:phone":"+1 320 584 5457",
    "sg:postcode":"56314",
    "sg:province":"MN",
    "sg:tags":[
        "repairing",
        "automobile"
    ],
    "wof:name":"Bowlus Auto Ctr",
    "wof:placetype":"venue"
},
  "geometry": {"coordinates":[-94.40417600000001,45.822032],"type":"Point"}
}