{
  "type": "Feature",
  "properties": {
    "iso:country":"US",
    "sg:address":"14560 Pennock Ave",
    "sg:city":"Saint Paul",
    "sg:classifiers":[
        {
            "category":"Retail",
            "subcategory":"Funeral Services",
            "type":"Services"
        }
    ],
    "sg:phone":"+1 952 432 2001",
    "sg:postcode":"55124",
    "sg:province":"MN",
    "sg:tags":[
        "director",
        "cemetery"
    ],
    "sg:website":"www.whitefuneralhomes.com",
    "wof:name":"White Funeral Home",
    "wof:placetype":"venue"
},
  "geometry": {"coordinates":[-93.2229,44.737499],"type":"Point"}
}