{
  "type": "Feature",
  "properties": {
    "addr:full":"85 Vadnais Blvd St Paul MN 55127",
    "addr:housenumber":"85",
    "addr:postcode":"55127",
    "addr:street":"Vadnais Blvd",
    "iso:country":"US",
    "sg:address":"85 Vadnais Blvd",
    "sg:city":"St Paul",
    "sg:classifiers":[
        {
            "category":"Government",
            "subcategory":"Office",
            "type":"Public Place"
        }
    ],
    "sg:phone":"+1 651 766 4150",
    "sg:postcode":"55127",
    "sg:province":"MN",
    "sg:tags":[
        "village"
    ],
    "wof:name":"St Paul Watershed Operations",
    "wof:placetype":"venue"
},
  "geometry": {"coordinates":[-93.097402,45.046747],"type":"Point"}
}