{
  "type": "Feature",
  "properties": {
    "addr:full":"3500 Emerson Ave S # 104 Minneapolis MN 55408",
    "addr:housenumber":"3500",
    "addr:postcode":"55408",
    "addr:street":"Emerson Ave S # 104",
    "iso:country":"US",
    "sg:address":"3500 Emerson Ave S # 104",
    "sg:city":"Minneapolis",
    "sg:classifiers":[
        {
            "category":"Real Estate",
            "subcategory":"Real Estate Services",
            "type":"Services"
        },
        {
            "category":"Banks & Credit Unions",
            "subcategory":"Bank",
            "type":"Services"
        },
        {
            "category":"Banks & Credit Unions",
            "subcategory":"Financial Services",
            "type":"Services"
        }
    ],
    "sg:phone":"+1 612 822 7463",
    "sg:postcode":"55408",
    "sg:province":"MN",
    "sg:tags":[
        "investment",
        "bond",
        "management",
        "broker",
        "stock"
    ],
    "wof:name":"Smith Sturm Investment Co",
    "wof:placetype":"venue"
},
  "geometry": {"coordinates":[-93.294571,44.939491],"type":"Point"}
}