{
  "type": "Feature",
  "properties": {
    "addr:full":"5720 Green Circle Dr Hopkins MN 55343",
    "addr:housenumber":"5720",
    "addr:postcode":"dr;55343",
    "addr:street":"Green Circle",
    "iso:country":"US",
    "sg:address":"5720 Green Circle Dr",
    "sg:city":"Hopkins",
    "sg:classifiers":[
        {
            "category":"Utilities",
            "subcategory":"Telephone",
            "type":"Services"
        }
    ],
    "sg:phone":"+1 952 345 0130",
    "sg:postcode":"55343",
    "sg:province":"MN",
    "sg:tags":[
        "communications"
    ],
    "wof:name":"Bytex Corp",
    "wof:placetype":"venue"
},
  "geometry": {"coordinates":[-93.40765399999999,44.902093],"type":"Point"}
}