{
  "type": "Feature",
  "properties": {
    "addr:full":"119 Aspen Ave NE Buffalo MN 55313",
    "addr:housenumber":"119",
    "addr:postcode":"55313",
    "addr:street":"Aspen Ave Ne",
    "iso:country":"US",
    "sg:address":"119 Aspen Ave NE",
    "sg:city":"Buffalo",
    "sg:classifiers":[
        {
            "category":"Social Services",
            "subcategory":"Child Care",
            "type":"Services"
        }
    ],
    "sg:phone":"+1 763 682 3540",
    "sg:postcode":"55313",
    "sg:province":"MN",
    "sg:tags":[
        "day"
    ],
    "wof:name":"Debbie M Ebert",
    "wof:placetype":"venue"
},
  "geometry": {"coordinates":[-93.856655,45.175732],"type":"Point"}
}