{
  "type": "Feature",
  "properties": {
    "iso:country":"US",
    "sg:address":"248 5th Ave SE",
    "sg:city":"Minneapolis",
    "sg:classifiers":[
        {
            "category":"Home & Garden",
            "subcategory":"Building Materials",
            "type":"Retail Goods"
        },
        {
            "category":"Building & Trades",
            "subcategory":"Construction",
            "type":"Services"
        },
        {
            "category":"Manufacturing",
            "subcategory":"Building Materials",
            "type":"Manufacturing & Wholesale Goods"
        }
    ],
    "sg:phone":"+1 763 493 0469",
    "sg:postcode":"55414",
    "sg:province":"MN",
    "sg:tags":[
        "roofing",
        "gutter",
        "sheet",
        "work",
        "metal",
        "contractor",
        "downspouts",
        "siding"
    ],
    "wof:name":"Pentar Seamless Gutters",
    "wof:placetype":"venue"
},
  "geometry": {"coordinates":[-93.249493,44.98396],"type":"Point"}
}