{
  "type": "Feature",
  "properties": {
    "iso:country":"US",
    "sg:address":"402 E Howard St",
    "sg:city":"Hibbing",
    "sg:classifiers":[
        {
            "category":"Shopping",
            "subcategory":"Jewelry",
            "type":"Retail Goods"
        }
    ],
    "sg:phone":"+1 218 263 7766",
    "sg:postcode":"55746",
    "sg:province":"MN",
    "sg:tags":[
        "jeweler"
    ],
    "wof:name":"Teske's Jewelry Store",
    "wof:placetype":"venue"
},
  "geometry": {"coordinates":[-92.937871,47.427401],"type":"Point"}
}