{
  "type": "Feature",
  "properties": {
    "addr:full":"205 S Washington Ave Albert Lea MN 56007",
    "addr:housenumber":"205",
    "addr:postcode":"56007",
    "addr:street":"S Washington Ave",
    "iso:country":"US",
    "sg:address":"205 S Washington Ave",
    "sg:city":"Albert Lea",
    "sg:classifiers":[
        {
            "category":"Real Estate",
            "subcategory":"Real Estate Services",
            "type":"Services"
        }
    ],
    "sg:phone":"+1 507 373 9001",
    "sg:postcode":"56007",
    "sg:province":"MN",
    "wof:name":"Albert Lea Abstract Co",
    "wof:placetype":"venue"
},
  "geometry": {"coordinates":[-93.369946,43.648771],"type":"Point"}
}