{
  "type": "Feature",
  "properties": {
    "addr:full":"20613 160th St Hutchinson MN 55350",
    "addr:housenumber":"20613",
    "addr:postcode":"55350",
    "addr:street":"160Th St",
    "iso:country":"US",
    "sg:address":"20613 160th St",
    "sg:city":"Hutchinson",
    "sg:phone":"+1 320 587 6370",
    "sg:postcode":"55350",
    "sg:province":"MN",
    "sg:tags":[
        "farm",
        "corn"
    ],
    "wof:name":"Robert Pofahl",
    "wof:placetype":"venue"
},
  "geometry": {"coordinates":[-94.397346,44.848644],"type":"Point"}
}