{
  "type": "Feature",
  "properties": {
    "iso:country":"US",
    "sg:address":"8590 Magnolia Trl",
    "sg:city":"Eden Prairie",
    "sg:classifiers":[
        {
            "category":"Professional",
            "type":"Services"
        }
    ],
    "sg:phone":"+1 952 942 5119",
    "sg:postcode":"55344",
    "sg:province":"MN",
    "wof:name":"Dit LLC",
    "wof:placetype":"venue"
},
  "geometry": {"coordinates":[-93.44515199999999,44.847642],"type":"Point"}
}