{
  "type": "Feature",
  "properties": {
    "addr:full":"620 S Broadway Ave Albert Lea MN 56007",
    "addr:housenumber":"620",
    "addr:postcode":"56007",
    "addr:street":"S Broadway Ave",
    "iso:country":"US",
    "sg:address":"620 S Broadway Ave",
    "sg:city":"Albert Lea",
    "sg:classifiers":[
        {
            "category":"Manufacturing",
            "subcategory":"Tools & Machinery",
            "type":"Manufacturing & Wholesale Goods"
        }
    ],
    "sg:phone":"+1 507 373 3996",
    "sg:postcode":"56007",
    "sg:province":"MN",
    "sg:tags":[
        "pump"
    ],
    "wof:name":"V-Ram Solids",
    "wof:placetype":"venue"
},
  "geometry": {"coordinates":[-93.368762,43.644563],"type":"Point"}
}