{
  "type": "Feature",
  "properties": {
    "iso:country":"US",
    "sg:address":"6624 76th Ave N",
    "sg:city":"Minneapolis",
    "sg:classifiers":[
        {
            "category":"Home & Garden",
            "subcategory":"Furniture",
            "type":"Retail Goods"
        }
    ],
    "sg:phone":"+1 763 560 1819",
    "sg:postcode":"55428",
    "sg:province":"MN",
    "wof:name":"Albright S Custom Furniture",
    "wof:placetype":"venue"
},
  "geometry": {"coordinates":[-93.365404,45.092733],"type":"Point"}
}