{
  "type": "Feature",
  "properties": {
    "iso:country":"US",
    "sg:address":"16116 Xenia St NW",
    "sg:city":"Anoka",
    "sg:classifiers":[
        {
            "category":"Insurance",
            "subcategory":"Life Insurance",
            "type":"Services"
        }
    ],
    "sg:phone":"+1 763 427 4261",
    "sg:postcode":"55304",
    "sg:province":"MN",
    "sg:tags":[
        "annuity",
        "health"
    ],
    "wof:name":"Aid Assoc For Lutherans",
    "wof:placetype":"venue"
},
  "geometry": {"coordinates":[-93.361999,45.26462],"type":"Point"}
}