{
  "type": "Feature",
  "properties": {
    "iso:country":"US",
    "sg:address":"10608 Jefferson Hwy",
    "sg:city":"Minneapolis",
    "sg:classifiers":[
        {
            "category":"Home & Garden",
            "subcategory":"Garden Supply",
            "type":"Retail Goods"
        }
    ],
    "sg:phone":"+1 763 493 9219",
    "sg:postcode":"55445",
    "sg:province":"MN",
    "sg:tags":[
        "nurseryman"
    ],
    "wof:name":"Jefferson Tree Farm",
    "wof:placetype":"venue"
},
  "geometry": {"coordinates":[-93.398802,45.143029],"type":"Point"}
}