{
  "type": "Feature",
  "properties": {
    "addr:full":"830 Minnesota Ave S Aitkin MN 56431",
    "addr:housenumber":"830",
    "addr:postcode":"56431",
    "addr:street":"Minnesota Ave S Aitkin",
    "iso:country":"US",
    "sg:address":"830 Minnesota Ave S",
    "sg:city":"Aitkin",
    "sg:classifiers":[
        {
            "category":"Freight",
            "type":"Transportation"
        }
    ],
    "sg:phone":"+1 218 927 7927",
    "sg:postcode":"56431",
    "sg:province":"MN",
    "sg:tags":[
        "commercial",
        "storage"
    ],
    "wof:name":"Aitkin Mini Storage",
    "wof:placetype":"venue"
},
  "geometry": {"coordinates":[-93.70702,46.522404],"type":"Point"}
}