{
  "type": "Feature",
  "properties": {
    "iso:country":"US",
    "sg:address":"301 N Ramsey Ave",
    "sg:city":"Litchfield",
    "sg:classifiers":[
        {
            "category":"Banks & Credit Unions",
            "subcategory":"Bank",
            "type":"Services"
        }
    ],
    "sg:phone":"+1 320 693 3255",
    "sg:postcode":"55355",
    "sg:province":"MN",
    "sg:website":"www.centernationalbank.com",
    "wof:name":"Center National Bank",
    "wof:placetype":"venue"
},
  "geometry": {"coordinates":[-94.529591,45.129838],"type":"Point"}
}