{
  "type": "Feature",
  "properties": {
    "iso:country":"US",
    "sg:address":"1539 Grand Ave",
    "sg:city":"St Paul",
    "sg:classifiers":[
        {
            "category":"Professional",
            "subcategory":"Lawyer & Legal Services",
            "type":"Services"
        }
    ],
    "sg:phone":"+1 651 699 5472",
    "sg:postcode":"55105",
    "sg:province":"MN",
    "sg:tags":[
        "attorney"
    ],
    "wof:name":"Tarrant Drummer Liska Pllc",
    "wof:placetype":"venue"
},
  "geometry": {"coordinates":[-93.166439,44.940137],"type":"Point"}
}