{
  "type": "Feature",
  "properties": {
    "addr:full":"7617 59th Ave N Minneapolis MN 55428",
    "addr:housenumber":"7617",
    "addr:postcode":"55428",
    "addr:street":"59Th Ave N",
    "iso:country":"US",
    "sg:address":"7617 59th Ave N",
    "sg:city":"Minneapolis",
    "sg:classifiers":[
        {
            "category":"Freight",
            "type":"Transportation"
        }
    ],
    "sg:phone":"+1 612 701 5746",
    "sg:postcode":"55428",
    "sg:province":"MN",
    "sg:tags":[
        "operator",
        "local",
        "trucking"
    ],
    "wof:name":"Williams Trucking",
    "wof:placetype":"venue"
},
  "geometry": {"coordinates":[-93.37824500000001,45.060412],"type":"Point"}
}