{
  "type": "Feature",
  "properties": {
    "addr:full":"109 E Mill St Hinckley MN 55060",
    "addr:housenumber":"109",
    "addr:postcode":"55060",
    "addr:street":"E Mill St",
    "iso:country":"US",
    "sg:address":"109 E Mill St",
    "sg:city":"Hinckley",
    "sg:classifiers":[
        {
            "category":"Professional",
            "subcategory":"Business Services",
            "type":"Services"
        }
    ],
    "sg:phone":"+1 320 384 0126",
    "sg:postcode":"55060",
    "sg:province":"MN",
    "sg:tags":[
        "information",
        "bureau",
        "convention"
    ],
    "sg:website":"www.hinckleymn.com",
    "wof:name":"Hinckley Convention & Visitors",
    "wof:placetype":"venue"
},
  "geometry": {"coordinates":[-93.22526999999999,44.082669],"type":"Point"}
}