{
  "type": "Feature",
  "properties": {
    "iso:country":"US",
    "sg:address":"1400 S Valley St",
    "sg:city":"New Ulm",
    "sg:classifiers":[
        {
            "category":"Wholesale",
            "subcategory":"Petroleum",
            "type":"Manufacturing & Wholesale Goods"
        }
    ],
    "sg:phone":"+1 507 354 6414",
    "sg:postcode":"56073",
    "sg:province":"MN",
    "sg:tags":[
        "product"
    ],
    "wof:name":"Harmening Oil & Trucking Inc",
    "wof:placetype":"venue"
},
  "geometry": {"coordinates":[-94.441715,44.301432],"type":"Point"}
}