{
  "type": "Feature",
  "properties": {
    "addr:full":"18393 78th Ave Kimball MN 55353",
    "addr:housenumber":"18393",
    "addr:postcode":"55353",
    "addr:street":"78Th Ave",
    "iso:country":"US",
    "sg:address":"18393 78th Ave",
    "sg:city":"Kimball",
    "sg:classifiers":[
        {
            "category":"Farming",
            "subcategory":"Dairy Farm",
            "type":"Manufacturing & Wholesale Goods"
        }
    ],
    "sg:phone":"+1 320 398 8052",
    "sg:postcode":"55353",
    "sg:province":"MN",
    "sg:tags":[
        "field",
        "corn",
        "grain",
        "cash",
        "crop"
    ],
    "wof:name":"Roger Hennen",
    "wof:placetype":"venue"
},
  "geometry": {"coordinates":[-94.271738,45.398528],"type":"Point"}
}