{
  "type": "Feature",
  "properties": {
    "addr:full":"8122 Bloomington Ave S Minneapolis MN 55425",
    "addr:housenumber":"8122",
    "addr:postcode":"55425",
    "addr:street":"Bloomington Ave S",
    "iso:country":"US",
    "sg:address":"8122 Bloomington Ave S",
    "sg:city":"Minneapolis",
    "sg:classifiers":[
        {
            "category":"Building & Trades",
            "subcategory":"Cleaning & Sanitation",
            "type":"Services"
        }
    ],
    "sg:phone":"+1 952 854 8203",
    "sg:postcode":"55425",
    "sg:province":"MN",
    "sg:tags":[
        "janitorial"
    ],
    "wof:name":"Contract Cleaning Specialists",
    "wof:placetype":"venue"
},
  "geometry": {"coordinates":[-93.25299699999999,44.85541],"type":"Point"}
}