{
  "type": "Feature",
  "properties": {
    "iso:country":"US",
    "sg:address":"141 Broadway St W",
    "sg:city":"Monticello",
    "sg:classifiers":[
        {
            "category":"Shopping",
            "subcategory":"Computers & Home Electronics",
            "type":"Retail Goods"
        }
    ],
    "sg:phone":"+1 763 295 1110",
    "sg:postcode":"55362",
    "sg:province":"MN",
    "sg:tags":[
        "equipment",
        "satellite",
        "system"
    ],
    "wof:name":"Procomm Inc",
    "wof:placetype":"venue"
},
  "geometry": {"coordinates":[-93.795107,45.306048],"type":"Point"}
}