{
  "type": "Feature",
  "properties": {
    "addr:full":"1304 Oak St Brainerd MN 56401",
    "addr:housenumber":"1304",
    "addr:postcode":"56401",
    "addr:street":"Oak St",
    "iso:country":"US",
    "sg:address":"1304 Oak St",
    "sg:city":"Brainerd",
    "sg:classifiers":[
        {
            "category":"Wholesale",
            "subcategory":"Non-durable Goods",
            "type":"Manufacturing & Wholesale Goods"
        }
    ],
    "sg:phone":"+1 218 824 0663",
    "sg:postcode":"56401",
    "sg:province":"MN",
    "sg:tags":[
        "dry",
        "goods-wholesale"
    ],
    "wof:name":"Tactical Supply",
    "wof:placetype":"venue"
},
  "geometry": {"coordinates":[-94.18971999999999,46.352551],"type":"Point"}
}