{
  "type": "Feature",
  "properties": {
    "iso:country":"US",
    "sg:address":"295 N Maria Ave",
    "sg:city":"Saint Paul",
    "sg:classifiers":[
        {
            "category":"Professional",
            "subcategory":"Lawyer & Legal Services",
            "type":"Services"
        }
    ],
    "sg:phone":"+1 651 552 6088",
    "sg:postcode":"55106",
    "sg:province":"MN",
    "wof:name":"Cean F Shands Attorney",
    "wof:placetype":"venue"
},
  "geometry": {"coordinates":[-93.06965099999999,44.954274],"type":"Point"}
}