{
  "type": "Feature",
  "properties": {
    "iso:country":"US",
    "sg:address":"114 W 1st St",
    "sg:city":"Duluth",
    "sg:classifiers":[
        {
            "category":"Restaurant",
            "type":"Food & Drink"
        }
    ],
    "sg:phone":"+1 218 733 9774",
    "sg:postcode":"55802",
    "sg:province":"MN",
    "sg:tags":[
        "eating"
    ],
    "wof:name":"Thi MAI",
    "wof:placetype":"venue"
},
  "geometry": {"coordinates":[-92.101624,46.785797],"type":"Point"}
}