{
  "type": "Feature",
  "properties": {
    "iso:country":"US",
    "sg:address":"4205 Lancaster Ln N",
    "sg:city":"Minneapolis",
    "sg:classifiers":[
        {
            "category":"Insurance",
            "subcategory":"Insurance Agent",
            "type":"Services"
        },
        {
            "category":"Insurance",
            "subcategory":"Hazard Insurance",
            "type":"Services"
        },
        {
            "category":"Insurance",
            "subcategory":"Title Insurance",
            "type":"Services"
        }
    ],
    "sg:phone":"+1 763 559 1477",
    "sg:postcode":"55441",
    "sg:province":"MN",
    "sg:tags":[
        "auto",
        "homeowner"
    ],
    "sg:website":"http://apps.amfam.com/agentlocator/RSVENDSE?sourceid=yp3",
    "wof:name":"American Family Insurance- Randy Svendsen",
    "wof:placetype":"venue"
},
  "geometry": {"coordinates":[-93.405911,45.032399],"type":"Point"}
}