{
  "type": "Feature",
  "properties": {
    "iso:country":"US",
    "sg:address":"8569 Shadow Creek Dr",
    "sg:city":"Osseo",
    "sg:classifiers":[
        {
            "category":"Professional",
            "subcategory":"Management & Consulting",
            "type":"Services"
        }
    ],
    "sg:phone":"+1 763 494 4408",
    "sg:postcode":"55311",
    "sg:province":"MN",
    "wof:name":"Shadow Creek Consulting",
    "wof:placetype":"venue"
},
  "geometry": {"coordinates":[-93.477425,45.110651],"type":"Point"}
}