{
  "type": "Feature",
  "properties": {
    "iso:country":"US",
    "sg:address":"8530 Edinburgh Center Dr",
    "sg:city":"Minneapolis",
    "sg:classifiers":[
        {
            "category":"Restaurant",
            "type":"Food & Drink"
        }
    ],
    "sg:menulink":"http://www.allmenus.com/mn/brooklyn-park/208816-taco-bell/menu/",
    "sg:phone":"+1 763 315 2929",
    "sg:postcode":"55443",
    "sg:province":"MN",
    "sg:tags":[
        "mexican"
    ],
    "wof:name":"Taco Bell",
    "wof:placetype":"venue"
},
  "geometry": {"coordinates":[-93.30243900000001,45.110124],"type":"Point"}
}