{
  "type": "Feature",
  "properties": {
    "iso:country":"US",
    "sg:address":"26109 190th St",
    "sg:city":"Fergus Falls",
    "sg:classifiers":[
        {
            "category":"Food & Beverages",
            "subcategory":"Bakery",
            "type":"Retail Goods"
        }
    ],
    "sg:phone":"+1 218 826 7376",
    "sg:postcode":"56537",
    "sg:province":"MN",
    "wof:name":"3 D Mini Donuts",
    "wof:placetype":"venue"
},
  "geometry": {"coordinates":[-95.944046,46.239572],"type":"Point"}
}