{
  "type": "Feature",
  "properties": {
    "iso:country":"US",
    "sg:address":"21584 446th St",
    "sg:city":"Le Center",
    "sg:classifiers":[
        {
            "category":"Freight",
            "type":"Transportation"
        }
    ],
    "sg:phone":"+1 507 357 6513",
    "sg:postcode":"56057",
    "sg:province":"MN",
    "sg:tags":[
        "operator",
        "trucking"
    ],
    "wof:name":"Leroy Kolander Trucking",
    "wof:placetype":"venue"
},
  "geometry": {"coordinates":[-93.703822,44.304763],"type":"Point"}
}