{
  "type": "Feature",
  "properties": {
    "addr:full":"290 N 7th St Minneapolis MN 55403",
    "addr:housenumber":"290",
    "addr:postcode":"55403",
    "addr:street":"N 7Th St",
    "iso:country":"US",
    "sg:address":"290 N 7th St",
    "sg:city":"Minneapolis",
    "sg:classifiers":[
        {
            "category":"Arena",
            "subcategory":"Sports Club",
            "type":"Entertainment"
        }
    ],
    "sg:phone":"+1 612 659 3576",
    "sg:postcode":"55403",
    "sg:province":"MN",
    "sg:tags":[
        "ticket",
        "sale"
    ],
    "wof:name":"Twins Ballpark",
    "wof:placetype":"venue"
},
  "geometry": {"coordinates":[-93.278374,44.980639],"type":"Point"}
}