{
  "type": "Feature",
  "properties": {
    "addr:full":"3124 Garfield Ave Minneapolis MN 55408",
    "addr:housenumber":"3124",
    "addr:postcode":"55408",
    "addr:street":"Garfield Ave",
    "iso:country":"US",
    "sg:address":"3124 Garfield Ave",
    "sg:city":"Minneapolis",
    "sg:classifiers":[
        {
            "category":"Social Services",
            "subcategory":"Job Training",
            "type":"Services"
        }
    ],
    "sg:phone":"+1 612 822 5255",
    "sg:postcode":"55408",
    "sg:province":"MN",
    "sg:tags":[
        "rehabilitation"
    ],
    "wof:name":"Progressive Rehabilitation",
    "wof:placetype":"venue"
},
  "geometry": {"coordinates":[-93.286936,44.9452],"type":"Point"}
}