{
  "type": "Feature",
  "properties": {
    "addr:full":"9540 Co Rd 135 Young America MN 55397",
    "addr:housenumber":"9540;135",
    "addr:postcode":"55397",
    "addr:street":"Co Rd",
    "iso:country":"US",
    "sg:address":"9540 Co Rd 135",
    "sg:city":"Young America",
    "sg:classifiers":[
        {
            "category":"Farming",
            "subcategory":"Farm",
            "type":"Manufacturing & Wholesale Goods"
        }
    ],
    "sg:phone":"+1 952 467 2102",
    "sg:postcode":"55397",
    "sg:province":"MN",
    "sg:tags":[
        "crop",
        "general"
    ],
    "wof:name":"William M Lueth Farm",
    "wof:placetype":"venue"
},
  "geometry": {"coordinates":[-93.92922,44.83054],"type":"Point"}
}