{
  "type": "Feature",
  "properties": {
    "addr:full":"120 Elton Hills Dr NW Rochester MN 55901",
    "addr:housenumber":"120",
    "addr:postcode":"55901",
    "addr:street":"Elton Hills Dr Nw",
    "iso:country":"US",
    "sg:address":"120 Elton Hills Dr NW",
    "sg:city":"Rochester",
    "sg:classifiers":[
        {
            "category":"Professional",
            "type":"Services"
        },
        {
            "category":"Coffee & Tea",
            "type":"Food & Drink"
        },
        {
            "category":"Restaurant",
            "type":"Food & Drink"
        }
    ],
    "sg:phone":"+1 507 285 4991",
    "sg:postcode":"55901",
    "sg:province":"MN",
    "sg:tags":[
        "shop",
        "espresso",
        "caterer"
    ],
    "wof:name":"Dunn Bros Coffee",
    "wof:placetype":"venue"
},
  "geometry": {"coordinates":[-92.463351,44.042213],"type":"Point"}
}