{
  "type": "Feature",
  "properties": {
    "iso:country":"US",
    "sg:address":"27380 Lofton Ave",
    "sg:city":"Chisago City",
    "sg:classifiers":[
        {
            "category":"Manufacturing",
            "subcategory":"Tools & Machinery",
            "type":"Manufacturing & Wholesale Goods"
        }
    ],
    "sg:phone":"+1 651 257 6525",
    "sg:postcode":"55013",
    "sg:province":"MN",
    "sg:tags":[
        "shop",
        "job"
    ],
    "wof:name":"H & L Machine",
    "wof:placetype":"venue"
},
  "geometry": {"coordinates":[-92.881879,45.343229],"type":"Point"}
}