{
  "type": "Feature",
  "properties": {
    "addr:full":"1013 10th St Clarkfield MN 56223",
    "addr:housenumber":"1013",
    "addr:postcode":"56223",
    "addr:street":"10Th St",
    "iso:country":"US",
    "sg:address":"1013 10th St",
    "sg:city":"Clarkfield",
    "sg:classifiers":[
        {
            "category":"Professional",
            "subcategory":"Management & Consulting",
            "type":"Services"
        }
    ],
    "sg:phone":"+1 320 669 3300",
    "sg:postcode":"56223",
    "sg:province":"MN",
    "sg:tags":[
        "consultant",
        "business"
    ],
    "wof:name":"Exetare Partnership",
    "wof:placetype":"venue"
},
  "geometry": {"coordinates":[-95.804428,44.791077],"type":"Point"}
}