{
  "type": "Feature",
  "properties": {
    "iso:country":"US",
    "sg:address":"2755 Woodbury Dr",
    "sg:city":"Saint Paul",
    "sg:classifiers":[
        {
            "category":"Professional",
            "subcategory":"Detective & Security Services",
            "type":"Services"
        },
        {
            "category":"Wholesale",
            "subcategory":"Electrical",
            "type":"Manufacturing & Wholesale Goods"
        }
    ],
    "sg:phone":"+1 651 730 1055",
    "sg:postcode":"55129",
    "sg:province":"MN",
    "sg:tags":[
        "alarm",
        "burglar",
        "system"
    ],
    "wof:name":"Innovative Home Systems",
    "wof:placetype":"venue"
},
  "geometry": {"coordinates":[-92.90334300000001,44.909021],"type":"Point"}
}