{
  "type": "Feature",
  "properties": {
    "iso:country":"US",
    "sg:address":"1112 8th St N",
    "sg:city":"Moorhead",
    "sg:classifiers":[
        {
            "category":"Social Services",
            "subcategory":"Child Care",
            "type":"Services"
        }
    ],
    "sg:phone":"+1 218 233 8290",
    "sg:postcode":"56560",
    "sg:province":"MN",
    "sg:tags":[
        "daycare"
    ],
    "wof:name":"Eileens Daycare",
    "wof:placetype":"venue"
},
  "geometry": {"coordinates":[-96.767698,46.888861],"type":"Point"}
}