{
  "type": "Feature",
  "properties": {
    "addr:full":"5123 W 98th St Minneapolis MN 55437",
    "addr:housenumber":"5123",
    "addr:postcode":"55437",
    "addr:street":"W 98Th St",
    "iso:country":"US",
    "sg:address":"5123 W 98th St",
    "sg:city":"Minneapolis",
    "sg:classifiers":[
        {
            "category":"Shopping",
            "subcategory":"Bicycles & Sporting Goods",
            "type":"Retail Goods"
        }
    ],
    "sg:phone":"+1 952 828 9554",
    "sg:postcode":"55437",
    "sg:province":"MN",
    "sg:tags":[
        "tackle",
        "fishing"
    ],
    "sg:website":"www.bentleysoutfitters.com",
    "wof:name":"Bentley's Outfitters",
    "wof:placetype":"venue"
},
  "geometry": {"coordinates":[-93.349993,44.825825],"type":"Point"}
}