{
  "type": "Feature",
  "properties": {
    "iso:country":"US",
    "sg:address":"9191 Davenport St NE",
    "sg:city":"Minneapolis",
    "sg:classifiers":[
        {
            "category":"Retail",
            "subcategory":"Auto Repair",
            "type":"Services"
        }
    ],
    "sg:phone":"+1 763 784 7554",
    "sg:postcode":"55449",
    "sg:province":"MN",
    "sg:tags":[
        "repairing",
        "automobile"
    ],
    "wof:name":"C R Auto Repair",
    "wof:placetype":"venue"
},
  "geometry": {"coordinates":[-93.230251,45.137153],"type":"Point"}
}