{
  "type": "Feature",
  "properties": {
    "addr:full":"15129 Co Rd 37 NW Annandale MN 55302",
    "addr:housenumber":"15129;37",
    "addr:postcode":"55302",
    "addr:street":"Co Rd",
    "iso:country":"US",
    "sg:address":"15129 Co Rd 37 NW",
    "sg:city":"Annandale",
    "sg:phone":"+1 320 286 2430",
    "sg:postcode":"55302",
    "sg:province":"MN",
    "sg:tags":[
        "farm",
        "field",
        "corn",
        "crop"
    ],
    "wof:name":"E and F Farm",
    "wof:placetype":"venue"
},
  "geometry": {"coordinates":[-94.19914199999999,45.200406],"type":"Point"}
}