{
  "type": "Feature",
  "properties": {
    "addr:full":"397 5th Ave N Bayport MN 55003",
    "addr:housenumber":"397",
    "addr:postcode":"55003",
    "addr:street":"5Th Ave N",
    "iso:country":"US",
    "sg:address":"397 5th Ave N",
    "sg:city":"Bayport",
    "sg:classifiers":[
        {
            "category":"Retail",
            "subcategory":"Auto Repair",
            "type":"Services"
        }
    ],
    "sg:phone":"+1 651 430 2792",
    "sg:postcode":"55003",
    "sg:province":"MN",
    "sg:tags":[
        "repairing",
        "transmission",
        "general",
        "automobile"
    ],
    "wof:name":"J R Transmissions & Gen Repair",
    "wof:placetype":"venue"
},
  "geometry": {"coordinates":[-92.782584,45.021435],"type":"Point"}
}