{
  "type": "Feature",
  "properties": {
    "iso:country":"US",
    "sg:address":"4130 Blackhawk Rd",
    "sg:city":"St Paul",
    "sg:classifiers":[
        {
            "category":"Personal",
            "subcategory":"Beauty Salon",
            "type":"Services"
        }
    ],
    "sg:phone":"+1 651 454 5496",
    "sg:postcode":"55122",
    "sg:province":"MN",
    "wof:name":"Cuts",
    "wof:placetype":"venue"
},
  "geometry": {"coordinates":[-93.194694,44.807067],"type":"Point"}
}