{
  "type": "Feature",
  "properties": {
    "iso:country":"US",
    "sg:address":"4769 Campbell Ave",
    "sg:city":"St Paul",
    "sg:classifiers":[
        {
            "category":"Restaurant",
            "type":"Food & Drink"
        }
    ],
    "sg:phone":"+1 651 407 6438",
    "sg:postcode":"55110",
    "sg:province":"MN",
    "sg:tags":[
        "caterer"
    ],
    "wof:name":"Margaux Limited",
    "wof:placetype":"venue"
},
  "geometry": {"coordinates":[-93.01843100000001,45.086087],"type":"Point"}
}