{
  "type": "Feature",
  "properties": {
    "iso:country":"US",
    "sg:address":"4118 83rd Ave N",
    "sg:city":"Minneapolis",
    "sg:classifiers":[
        {
            "category":"Building & Trades",
            "subcategory":"Construction",
            "type":"Services"
        }
    ],
    "sg:phone":"+1 763 424 9225",
    "sg:postcode":"55443",
    "sg:province":"MN",
    "sg:tags":[
        "garage",
        "door",
        "installation"
    ],
    "wof:name":"Andersen Garage Doors Inc",
    "wof:placetype":"venue"
},
  "geometry": {"coordinates":[-93.335413,45.105346],"type":"Point"}
}