{
  "type": "Feature",
  "properties": {
    "iso:country":"US",
    "sg:address":"2145 Commerce Blvd",
    "sg:city":"Mound",
    "sg:classifiers":[
        {
            "category":"Restaurant",
            "type":"Food & Drink"
        }
    ],
    "sg:menulink":"http://www.allmenus.com/mn/mound/151240-subway/menu/",
    "sg:phone":"+1 952 472 0850",
    "sg:postcode":"55364",
    "sg:province":"MN",
    "sg:tags":[
        "american",
        "sandwich"
    ],
    "wof:name":"Subway",
    "wof:placetype":"venue"
},
  "geometry": {"coordinates":[-93.666178,44.939438],"type":"Point"}
}