{
  "type": "Feature",
  "properties": {
    "addr:full":"7208 Bristol Cir Minneapolis MN 55435",
    "addr:housenumber":"7208",
    "addr:postcode":"55435",
    "addr:street":"Bristol Cir",
    "iso:country":"US",
    "sg:address":"7208 Bristol Cir",
    "sg:city":"Minneapolis",
    "sg:classifiers":[
        {
            "category":"Social Services",
            "subcategory":"Job Training",
            "type":"Services"
        }
    ],
    "sg:phone":"+1 952 835 0516",
    "sg:postcode":"55435",
    "sg:province":"MN",
    "sg:tags":[
        "sales"
    ],
    "wof:name":"People Help Inc",
    "wof:placetype":"venue"
},
  "geometry": {"coordinates":[-93.33184799999999,44.872145],"type":"Point"}
}