{
  "type": "Feature",
  "properties": {
    "iso:country":"US",
    "sg:address":"500 Raintree Rd",
    "sg:city":"Mankato",
    "sg:classifiers":[
        {
            "category":"Home & Garden",
            "subcategory":"Furniture",
            "type":"Retail Goods"
        }
    ],
    "sg:phone":"+1 507 625 6236",
    "sg:postcode":"56001",
    "sg:province":"MN",
    "sg:website":"www.bedpostfurniture.com",
    "wof:name":"Bedpost Furniture",
    "wof:placetype":"venue"
},
  "geometry": {"coordinates":[-93.956435,44.169466],"type":"Point"}
}