{
  "type": "Feature",
  "properties": {
    "iso:country":"US",
    "sg:address":"3209 Snelling Ave S",
    "sg:city":"Minneapolis",
    "sg:classifiers":[
        {
            "category":"Professional",
            "subcategory":"Business Services",
            "type":"Services"
        }
    ],
    "sg:phone":"+1 612 396 6433",
    "sg:postcode":"55406",
    "sg:province":"MN",
    "wof:name":"Shaw Design Associates",
    "wof:placetype":"venue"
},
  "geometry": {"coordinates":[-93.232072,44.943129],"type":"Point"}
}