{
  "type": "Feature",
  "properties": {
    "addr:full":"407 Lake St E Wayzata MN 55391",
    "addr:housenumber":"407",
    "addr:postcode":"55391",
    "addr:street":"Lake St E",
    "iso:country":"US",
    "sg:address":"407 Lake St E",
    "sg:city":"Wayzata",
    "sg:classifiers":[
        {
            "category":"Organizations",
            "subcategory":"Community Association",
            "type":"Services"
        }
    ],
    "sg:phone":"+1 952 473 6663",
    "sg:postcode":"55391",
    "sg:province":"MN",
    "wof:name":"Wayzata Masonic Lodge",
    "wof:placetype":"venue"
},
  "geometry": {"coordinates":[-93.515109,44.97001],"type":"Point"}
}