{
  "type": "Feature",
  "properties": {
    "iso:country":"US",
    "sg:address":"1254 Lake Ave",
    "sg:city":"Fairmont",
    "sg:classifiers":[
        {
            "category":"Professional",
            "subcategory":"Accounting & Tax Preparation",
            "type":"Services"
        }
    ],
    "sg:phone":"+1 507 238 9028",
    "sg:postcode":"56031",
    "sg:province":"MN",
    "sg:tags":[
        "accountant"
    ],
    "wof:name":"Ronald J Arens CPA",
    "wof:placetype":"venue"
},
  "geometry": {"coordinates":[-94.485045,43.659356],"type":"Point"}
}