{
  "type": "Feature",
  "properties": {
    "iso:country":"US",
    "sg:address":"203 Jackson St",
    "sg:city":"Anoka",
    "sg:classifiers":[
        {
            "category":"Shopping",
            "subcategory":"Used Merchandise",
            "type":"Retail Goods"
        }
    ],
    "sg:phone":"+1 763 506 0562",
    "sg:postcode":"55303",
    "sg:province":"MN",
    "wof:name":"Artique Inc",
    "wof:placetype":"venue"
},
  "geometry": {"coordinates":[-93.388278,45.198712],"type":"Point"}
}