{
  "type": "Feature",
  "properties": {
    "iso:country":"US",
    "sg:address":"10635 Railroad Ave",
    "sg:city":"Chisago City",
    "sg:classifiers":[
        {
            "category":"Shopping",
            "subcategory":"Used Merchandise",
            "type":"Retail Goods"
        }
    ],
    "sg:phone":"+1 651 257 8325",
    "sg:postcode":"55013",
    "sg:province":"MN",
    "sg:tags":[
        "antique"
    ],
    "wof:name":"Chisago Antiques",
    "wof:placetype":"venue"
},
  "geometry": {"coordinates":[-92.890731,45.372437],"type":"Point"}
}