{
  "type": "Feature",
  "properties": {
    "addr:full":"297 Hwy 10 S Motley MN 56466",
    "addr:housenumber":"297",
    "addr:postcode":"56466",
    "addr:street":"Hwy 10 S",
    "iso:country":"US",
    "sg:address":"297 Hwy 10 S",
    "sg:city":"Motley",
    "sg:classifiers":[
        {
            "category":"Freight",
            "type":"Transportation"
        }
    ],
    "sg:phone":"+1 218 352 6355",
    "sg:postcode":"56466",
    "sg:province":"MN",
    "sg:tags":[
        "special"
    ],
    "wof:name":"Q & J Mini Storage",
    "wof:placetype":"venue"
},
  "geometry": {"coordinates":[-94.646564,46.334638],"type":"Point"}
}