{
  "type": "Feature",
  "properties": {
    "addr:full":"8365 Sunset Rd NE Minneapolis MN 55432",
    "addr:housenumber":"8365",
    "addr:postcode":"55432",
    "addr:street":"Sunset Rd Ne",
    "iso:country":"US",
    "sg:address":"8365 Sunset Rd NE",
    "sg:city":"Minneapolis",
    "sg:classifiers":[
        {
            "category":"Home & Garden",
            "subcategory":"Hardware",
            "type":"Retail Goods"
        }
    ],
    "sg:phone":"+1 763 784 3966",
    "sg:postcode":"55432",
    "sg:province":"MN",
    "sg:tags":[
        "measuring",
        "device"
    ],
    "sg:website":"http://www.internationaldyno.com",
    "wof:name":"International Dyno Corp",
    "wof:placetype":"venue"
},
  "geometry": {"coordinates":[-93.231584,45.119132],"type":"Point"}
}