{
  "type": "Feature",
  "properties": {
    "iso:country":"US",
    "sg:address":"733 Grand Ave",
    "sg:city":"St Paul",
    "sg:classifiers":[
        {
            "category":"Shopping",
            "subcategory":"Department Store",
            "type":"Retail Goods"
        }
    ],
    "sg:phone":"+1 651 228 1737",
    "sg:postcode":"55105",
    "sg:province":"MN",
    "sg:tags":[
        "shop"
    ],
    "sg:website":"www.pier1.com",
    "wof:name":"Pier 1 Imports",
    "wof:placetype":"venue"
},
  "geometry": {"coordinates":[-93.129689,44.939982],"type":"Point"}
}