{
  "type": "Feature",
  "properties": {
    "addr:full":"10901 Bren Rd E Hopkins MN 55343",
    "addr:housenumber":"10901",
    "addr:postcode":"55343",
    "addr:street":"Bren Rd E",
    "iso:country":"US",
    "sg:address":"10901 Bren Rd E",
    "sg:city":"Hopkins",
    "sg:classifiers":[
        {
            "category":"Banks & Credit Unions",
            "subcategory":"Bank",
            "type":"Services"
        }
    ],
    "sg:phone":"+1 952 935 1033",
    "sg:postcode":"55343",
    "sg:province":"MN",
    "wof:name":"Wells Fargo Bank",
    "wof:placetype":"venue"
},
  "geometry": {"coordinates":[-93.414795,44.899193],"type":"Point"}
}