{
  "type": "Feature",
  "properties": {
    "iso:country":"US",
    "sg:address":"1262 County Road 42 W",
    "sg:city":"Burnsville",
    "sg:classifiers":[
        {
            "category":"Personal",
            "type":"Services"
        }
    ],
    "sg:phone":"+1 952 435 6757",
    "sg:postcode":"55337",
    "sg:province":"MN",
    "sg:tags":[
        "sewing",
        "alteration"
    ],
    "wof:name":"Greg's Tailors",
    "wof:placetype":"venue"
},
  "geometry": {"coordinates":[-93.295502,44.7467],"type":"Point"}
}