{
  "type": "Feature",
  "properties": {
    "addr:full":"11580 Hanson Blvd NW Coon Rapids MN 55433",
    "addr:housenumber":"11580",
    "addr:postcode":"55433",
    "addr:street":"Hanson Blvd Nw",
    "iso:country":"US",
    "sg:address":"11580 Hanson Blvd NW",
    "sg:city":"Coon Rapids",
    "sg:classifiers":[
        {
            "category":"Building & Trades",
            "subcategory":"Locksmith",
            "type":"Services"
        }
    ],
    "sg:phone":"+1 651 222 9842",
    "sg:postcode":"55433",
    "sg:province":"MN",
    "sg:tags":[
        "key"
    ],
    "wof:name":"24 Hour Emergency Locksmith",
    "wof:placetype":"venue"
},
  "geometry": {"coordinates":[-93.316913,45.180424],"type":"Point"}
}