{
  "type": "Feature",
  "properties": {
    "addr:full":"1801 Nicollet Ave Minneapolis MN 55403",
    "addr:housenumber":"1801",
    "addr:postcode":"55403",
    "addr:street":"Nicollet Ave",
    "iso:country":"US",
    "sg:address":"1801 Nicollet Ave",
    "sg:city":"Minneapolis",
    "sg:classifiers":[
        {
            "category":"Professional",
            "subcategory":"Lawyer & Legal Services",
            "type":"Services"
        }
    ],
    "sg:phone":"+1 612 863 1024",
    "sg:postcode":"55403",
    "sg:province":"MN",
    "wof:name":"Minnesota Agent Opportunity",
    "wof:placetype":"venue"
},
  "geometry": {"coordinates":[-93.277817,44.964195],"type":"Point"}
}