{
  "type": "Feature",
  "properties": {
    "addr:full":"1006 Rosehill Dr Albert Lea MN 56007",
    "addr:housenumber":"1006",
    "addr:postcode":"56007",
    "addr:street":"Rosehill Dr",
    "iso:country":"US",
    "sg:address":"1006 Rosehill Dr",
    "sg:city":"Albert Lea",
    "sg:classifiers":[
        {
            "category":"Organizations",
            "subcategory":"Community Association",
            "type":"Services"
        }
    ],
    "sg:phone":"+1 507 373 3908",
    "sg:postcode":"56007",
    "sg:province":"MN",
    "wof:name":"Association WA Tan Ye Clubs",
    "wof:placetype":"venue"
},
  "geometry": {"coordinates":[-93.387962,43.639767],"type":"Point"}
}