{
  "type": "Feature",
  "properties": {
    "iso:country":"US",
    "sg:address":"6641 Lake Blvd",
    "sg:city":"Forest Lake",
    "sg:classifiers":[
        {
            "category":"Real Estate",
            "subcategory":"Surveying",
            "type":"Services"
        }
    ],
    "sg:phone":"+1 651 464 3130",
    "sg:postcode":"55025",
    "sg:province":"MN",
    "sg:tags":[
        "surveyor"
    ],
    "sg:website":"www.mfra.com",
    "wof:name":"Hult & Assoc Inc",
    "wof:placetype":"venue"
},
  "geometry": {"coordinates":[-92.96884900000001,45.301721],"type":"Point"}
}