{
  "type": "Feature",
  "properties": {
    "iso:country":"US",
    "sg:address":"14770 Martin Dr",
    "sg:city":"Eden Prairie",
    "sg:classifiers":[
        {
            "category":"Autos & Motor Vehicles",
            "subcategory":"Motorcycle Sales",
            "type":"Retail Goods"
        }
    ],
    "sg:phone":"+1 952 476 2429",
    "sg:postcode":"55344",
    "sg:province":"MN",
    "wof:name":"Mototricks",
    "wof:placetype":"venue"
},
  "geometry": {"coordinates":[-93.464625,44.863487],"type":"Point"}
}