{
  "type": "Feature",
  "properties": {
    "iso:country":"US",
    "sg:address":"5429 13th Ave S",
    "sg:city":"Minneapolis",
    "sg:classifiers":[
        {
            "category":"Science Facility",
            "type":"Public Place"
        }
    ],
    "sg:phone":"+1 612 759 2571",
    "sg:postcode":"55417",
    "sg:province":"MN",
    "sg:tags":[
        "development",
        "laboratories-research"
    ],
    "wof:name":"Nicole Lunning",
    "wof:placetype":"venue"
},
  "geometry": {"coordinates":[-93.2563,44.904736],"type":"Point"}
}