{
  "type": "Feature",
  "properties": {
    "addr:full":"2127 Mapleview Ave Maplewood MN 55109",
    "addr:housenumber":"2127",
    "addr:postcode":"55109",
    "addr:street":"Mapleview Ave",
    "iso:country":"US",
    "sg:address":"2127 Mapleview Ave",
    "sg:city":"Maplewood",
    "sg:classifiers":[
        {
            "category":"Building & Trades",
            "subcategory":"Construction",
            "type":"Services"
        }
    ],
    "sg:phone":"+1 651 247 6318",
    "sg:postcode":"55109",
    "sg:province":"MN",
    "sg:tags":[
        "framing",
        "contractor"
    ],
    "wof:name":"North Framing & Design",
    "wof:placetype":"venue"
},
  "geometry": {"coordinates":[-93.01145,45.027268],"type":"Point"}
}