{
  "type": "Feature",
  "properties": {
    "iso:country":"US",
    "sg:address":"35002 Co Rd 39",
    "sg:city":"Pequot Lakes",
    "sg:classifiers":[
        {
            "category":"Restaurant",
            "type":"Food & Drink"
        }
    ],
    "sg:phone":"+1 218 543 4117",
    "sg:postcode":"56472",
    "sg:province":"MN",
    "sg:tags":[
        "liquor",
        "retail",
        "bar",
        "store"
    ],
    "wof:name":"Old Mlwaukee CLB Saloon Eatery",
    "wof:placetype":"venue"
},
  "geometry": {"coordinates":[-94.19914900000001,46.662112],"type":"Point"}
}