{
  "type": "Feature",
  "properties": {
    "addr:full":"5545 Malibu Dr Minneapolis MN 55436",
    "addr:housenumber":"5545",
    "addr:postcode":"55436",
    "addr:street":"Malibu Dr",
    "iso:country":"US",
    "sg:address":"5545 Malibu Dr",
    "sg:city":"Minneapolis",
    "sg:classifiers":[
        {
            "category":"Professional",
            "subcategory":"Detective & Security Services",
            "type":"Services"
        }
    ],
    "sg:phone":"+1 952 930 3079",
    "sg:postcode":"55436",
    "sg:province":"MN",
    "sg:tags":[
        "information",
        "bureau"
    ],
    "wof:name":"Webfeet Internet Services Inc",
    "wof:placetype":"venue"
},
  "geometry": {"coordinates":[-93.39924600000001,44.904732],"type":"Point"}
}