{
  "type": "Feature",
  "properties": {
    "iso:country":"US",
    "sg:address":"37589 State Hwy 56",
    "sg:city":"Dennison",
    "sg:phone":"+1 507 789 6715",
    "sg:postcode":"55018",
    "sg:province":"MN",
    "sg:tags":[
        "farm",
        "grain",
        "cash"
    ],
    "wof:name":"Underdahl Farms",
    "wof:placetype":"venue"
},
  "geometry": {"coordinates":[-92.97973399999999,44.406808],"type":"Point"}
}