{
  "type": "Feature",
  "properties": {
    "iso:country":"US",
    "sg:address":"7259 Savanna Ct",
    "sg:city":"Circle Pines",
    "sg:classifiers":[
        {
            "category":"Professional",
            "type":"Services"
        }
    ],
    "sg:phone":"+1 651 784 7516",
    "sg:postcode":"55014",
    "sg:province":"MN",
    "wof:name":"Dwamina Group Inc",
    "wof:placetype":"venue"
},
  "geometry": {"coordinates":[-93.13609099999999,45.170577],"type":"Point"}
}