{
  "type": "Feature",
  "properties": {
    "addr:full":"624 W 54th St Minneapolis MN 55419",
    "addr:housenumber":"624",
    "addr:postcode":"55419",
    "addr:street":"W 54Th St",
    "iso:country":"US",
    "sg:address":"624 W 54th St",
    "sg:city":"Minneapolis",
    "sg:classifiers":[
        {
            "category":"Museum",
            "type":"Entertainment"
        }
    ],
    "sg:phone":"+1 612 293 5507",
    "sg:postcode":"55419",
    "sg:province":"MN",
    "sg:tags":[
        "information",
        "art"
    ],
    "wof:name":"Praxis Healing Arts",
    "wof:placetype":"venue"
},
  "geometry": {"coordinates":[-93.287342,44.905079],"type":"Point"}
}