{
  "type": "Feature",
  "properties": {
    "addr:full":"4001 Peavey Rd Chaska MN 55318",
    "addr:housenumber":"4001",
    "addr:postcode":"55318",
    "addr:street":"Peavey Rd",
    "iso:country":"US",
    "sg:address":"4001 Peavey Rd",
    "sg:city":"Chaska",
    "sg:classifiers":[
        {
            "category":"Wholesale",
            "subcategory":"Durable Goods & Equipment",
            "type":"Manufacturing & Wholesale Goods"
        }
    ],
    "sg:phone":"+1 952 448 1750",
    "sg:postcode":"55318",
    "sg:province":"MN",
    "sg:tags":[
        "representative",
        "manufacturer"
    ],
    "wof:name":"Mc Laughlin Gormley & King Co",
    "wof:placetype":"venue"
},
  "geometry": {"coordinates":[-93.594858,44.853098],"type":"Point"}
}