{
  "type": "Feature",
  "properties": {
    "iso:country":"US",
    "sg:address":"7001 Springhill Cir",
    "sg:city":"Eden Prairie",
    "sg:classifiers":[
        {
            "category":"Health Services",
            "subcategory":"Health Practitioner",
            "type":"Services"
        }
    ],
    "sg:phone":"+1 952 937 5684",
    "sg:postcode":"55346",
    "sg:province":"MN",
    "wof:name":"Rehab Services",
    "wof:placetype":"venue"
},
  "geometry": {"coordinates":[-93.46893300000001,44.874331],"type":"Point"}
}