{
  "type": "Feature",
  "properties": {
    "addr:full":"602 Quant Ave N Lakeland MN 55043",
    "addr:housenumber":"602",
    "addr:postcode":"55043",
    "addr:street":"Quant Ave N",
    "iso:country":"US",
    "sg:address":"602 Quant Ave N",
    "sg:city":"Lakeland",
    "sg:classifiers":[
        {
            "category":"Professional",
            "subcategory":"Business Services",
            "type":"Services"
        }
    ],
    "sg:phone":"+1 651 436 6177",
    "sg:postcode":"55043",
    "sg:province":"MN",
    "wof:name":"Ranmar Associates Inc",
    "wof:placetype":"venue"
},
  "geometry": {"coordinates":[-92.77527499999999,44.95733],"type":"Point"}
}