{
  "type": "Feature",
  "properties": {
    "iso:country":"US",
    "sg:address":"3433 Broadway St NE # 501",
    "sg:city":"Minneapolis",
    "sg:classifiers":[
        {
            "category":"Real Estate",
            "subcategory":"Real Estate Services",
            "type":"Services"
        },
        {
            "category":"Banks & Credit Unions",
            "subcategory":"Financial Services",
            "type":"Services"
        }
    ],
    "sg:phone":"+1 612 767 3854",
    "sg:postcode":"55413",
    "sg:province":"MN",
    "sg:tags":[
        "buyer",
        "broker",
        "mortgage"
    ],
    "wof:name":"Webdigs.Com",
    "wof:placetype":"venue"
},
  "geometry": {"coordinates":[-93.2136,45.000431],"type":"Point"}
}