{
  "type": "Feature",
  "properties": {
    "iso:country":"US",
    "sg:address":"305 Montana Ave W",
    "sg:city":"Atwater",
    "sg:classifiers":[
        {
            "category":"Manufacturing",
            "subcategory":"Tools & Machinery",
            "type":"Manufacturing & Wholesale Goods"
        }
    ],
    "sg:phone":"+1 320 974 8661",
    "sg:postcode":"56209",
    "sg:province":"MN",
    "sg:tags":[
        "control",
        "industrial",
        "relay",
        "mfg",
        "printed",
        "circuit",
        "boar"
    ],
    "wof:name":"Solid State Time Company",
    "wof:placetype":"venue"
},
  "geometry": {"coordinates":[-94.780141,45.130741],"type":"Point"}
}