{
  "type": "Feature",
  "properties": {
    "iso:country":"US",
    "sg:address":"10921 Excelsior Blvd",
    "sg:city":"Hopkins",
    "sg:classifiers":[
        {
            "category":"Building & Trades",
            "subcategory":"Construction",
            "type":"Services"
        }
    ],
    "sg:phone":"+1 952 908 3157",
    "sg:postcode":"55343",
    "sg:province":"MN",
    "sg:tags":[
        "door",
        "mfg",
        "screen",
        "contractor",
        "window",
        "an"
    ],
    "wof:name":"Acme General Contg & GL Svc",
    "wof:placetype":"venue"
},
  "geometry": {"coordinates":[-93.420006,44.920774],"type":"Point"}
}