{
  "type": "Feature",
  "properties": {
    "addr:full":"505 E Main St Luverne MN 56156",
    "addr:housenumber":"505",
    "addr:postcode":"56156",
    "addr:street":"E Main St",
    "iso:country":"US",
    "sg:address":"505 E Main St",
    "sg:city":"Luverne",
    "sg:classifiers":[
        {
            "category":"Manufacturing",
            "subcategory":"Tools & Machinery",
            "type":"Manufacturing & Wholesale Goods"
        },
        {
            "category":"Wholesale",
            "subcategory":"Auto Parts",
            "type":"Manufacturing & Wholesale Goods"
        }
    ],
    "sg:phone":"+1 507 283 2371",
    "sg:postcode":"56156",
    "sg:province":"MN",
    "sg:tags":[
        "shop",
        "machine",
        "ind",
        "supply",
        "mfg"
    ],
    "wof:name":"Sturdevant's Auto Parts",
    "wof:placetype":"venue"
},
  "geometry": {"coordinates":[-96.203851,43.654224],"type":"Point"}
}