{
  "type": "Feature",
  "properties": {
    "addr:full":"4576 58th Ave N Apt 280 Minneapolis MN 55429",
    "addr:housenumber":"4576;280",
    "addr:postcode":"55429",
    "addr:street":"58Th Ave N Apt",
    "iso:country":"US",
    "sg:address":"4576 58th Ave N Apt 280",
    "sg:city":"Minneapolis",
    "sg:classifiers":[
        {
            "category":"Bars & Pubs",
            "type":"Food & Drink"
        },
        {
            "category":"Restaurant",
            "type":"Food & Drink"
        }
    ],
    "sg:phone":"+1 763 537 9160",
    "sg:postcode":"55429",
    "sg:province":"MN",
    "sg:tags":[
        "brew"
    ],
    "wof:name":"Lowry Pub",
    "wof:placetype":"venue"
},
  "geometry": {"coordinates":[-93.339339,45.059825],"type":"Point"}
}