{
  "type": "Feature",
  "properties": {
    "iso:country":"US",
    "sg:address":"2282 Carter Ave",
    "sg:city":"Saint Paul",
    "sg:classifiers":[
        {
            "category":"Professional",
            "type":"Services"
        }
    ],
    "sg:phone":"+1 651 641 1004",
    "sg:postcode":"55108",
    "sg:province":"MN",
    "wof:name":"Inland Hills Company",
    "wof:placetype":"venue"
},
  "geometry": {"coordinates":[-93.195217,44.981294],"type":"Point"}
}