{
  "type": "Feature",
  "properties": {
    "iso:country":"US",
    "sg:address":"3105 Rhode Island Ave S",
    "sg:city":"Minneapolis",
    "sg:classifiers":[
        {
            "category":"Building & Trades",
            "subcategory":"Cleaning & Sanitation",
            "type":"Services"
        },
        {
            "category":"Banks & Credit Unions",
            "subcategory":"Bank",
            "type":"Services"
        },
        {
            "category":"Home & Garden",
            "subcategory":"Building Materials",
            "type":"Retail Goods"
        },
        {
            "category":"Building & Trades",
            "subcategory":"Construction",
            "type":"Services"
        }
    ],
    "sg:phone":"+1 952 920 6101",
    "sg:postcode":"55426",
    "sg:province":"MN",
    "sg:tags":[
        "roofing",
        "gutter",
        "cover",
        "contractor",
        "downspouts",
        "industrial",
        "contractors-commercial"
    ],
    "sg:website":"http://www.apexcustomgutters.com",
    "wof:name":"Apex Custom Gutters",
    "wof:placetype":"venue"
},
  "geometry": {"coordinates":[-93.378353,44.946974],"type":"Point"}
}