{
  "type": "Feature",
  "properties": {
    "addr:full":"67987 270th Ave Kasson MN 55944",
    "addr:housenumber":"67987",
    "addr:postcode":"55944",
    "addr:street":"270Th Ave",
    "iso:country":"US",
    "sg:address":"67987 270th Ave",
    "sg:city":"Kasson",
    "sg:phone":"+1 507 365 8911",
    "sg:postcode":"55944",
    "sg:province":"MN",
    "sg:tags":[
        "farm",
        "corn",
        "soybean"
    ],
    "wof:name":"Sterling Ness",
    "wof:placetype":"venue"
},
  "geometry": {"coordinates":[-92.698286,43.954608],"type":"Point"}
}