{
  "type": "Feature",
  "properties": {
    "addr:full":"100 Chenevert Ave Marble MN 55709",
    "addr:housenumber":"100",
    "addr:postcode":"55709",
    "addr:street":"Chenevert Ave",
    "iso:country":"US",
    "sg:address":"100 Chenevert Ave",
    "sg:city":"Marble",
    "sg:classifiers":[
        {
            "category":"Government",
            "subcategory":"Office",
            "type":"Public Place"
        }
    ],
    "sg:phone":"+1 218 247 7191",
    "sg:postcode":"55709",
    "sg:province":"MN",
    "sg:tags":[
        "village"
    ],
    "wof:name":"Greenway Twp Shed",
    "wof:placetype":"venue"
},
  "geometry": {"coordinates":[-93.31057,47.31516],"type":"Point"}
}