{
  "type": "Feature",
  "properties": {
    "iso:country":"US",
    "sg:address":"336 Aspen St W",
    "sg:city":"Cambridge",
    "sg:classifiers":[
        {
            "category":"Building & Trades",
            "subcategory":"Construction",
            "type":"Services"
        }
    ],
    "sg:phone":"+1 763 552 4050",
    "sg:postcode":"55082",
    "sg:province":"MN",
    "sg:tags":[
        "house"
    ],
    "wof:name":"Marathon Homes",
    "wof:placetype":"venue"
},
  "geometry": {"coordinates":[-92.81415800000001,45.064143],"type":"Point"}
}