{
  "type": "Feature",
  "properties": {
    "addr:full":"67 Jasper St Tower MN 55790",
    "addr:housenumber":"67",
    "addr:postcode":"55790",
    "addr:street":"Jasper St",
    "iso:country":"US",
    "sg:address":"67 Jasper St",
    "sg:city":"Tower",
    "sg:classifiers":[
        {
            "category":"Wholesale",
            "subcategory":"Auto Parts",
            "type":"Manufacturing & Wholesale Goods"
        }
    ],
    "sg:phone":"+1 218 753 3226",
    "sg:postcode":"55790",
    "sg:province":"MN",
    "sg:tags":[
        "supply"
    ],
    "wof:name":"Tartan Transportation System",
    "wof:placetype":"venue"
},
  "geometry": {"coordinates":[-92.22712799999999,47.814932],"type":"Point"}
}