{
  "type": "Feature",
  "properties": {
    "iso:country":"US",
    "sg:address":"615 S Ash St",
    "sg:city":"Crookston",
    "sg:classifiers":[
        {
            "category":"Personal",
            "subcategory":"Beauty Salon",
            "type":"Services"
        }
    ],
    "sg:phone":"+1 218 281 4655",
    "sg:postcode":"56716",
    "sg:province":"MN",
    "sg:tags":[
        "shop"
    ],
    "wof:name":"Pat's Hair Corner",
    "wof:placetype":"venue"
},
  "geometry": {"coordinates":[-96.608908,47.767325],"type":"Point"}
}