{
  "type": "Feature",
  "properties": {
    "addr:full":"7280 Commerce Cir E Minneapolis MN 55432",
    "addr:housenumber":"7280",
    "addr:postcode":"55432",
    "addr:street":"Commerce Cir E",
    "iso:country":"US",
    "sg:address":"7280 Commerce Cir E",
    "sg:city":"Minneapolis",
    "sg:classifiers":[
        {
            "category":"Manufacturing",
            "subcategory":"Metals",
            "type":"Manufacturing & Wholesale Goods"
        },
        {
            "category":"Manufacturing",
            "subcategory":"Tools & Machinery",
            "type":"Manufacturing & Wholesale Goods"
        }
    ],
    "sg:phone":"+1 763 572 0607",
    "sg:postcode":"55432",
    "sg:province":"MN",
    "sg:tags":[
        "finisher"
    ],
    "sg:website":"www.americanbrightworks.com",
    "wof:name":"American Bright Works",
    "wof:placetype":"venue"
},
  "geometry": {"coordinates":[-93.265091,45.100272],"type":"Point"}
}