{
  "type": "Feature",
  "properties": {
    "addr:full":"631 Ferry St Le Sueur MN 56058",
    "addr:housenumber":"631",
    "addr:postcode":"56058",
    "addr:street":"Ferry St",
    "iso:country":"US",
    "sg:address":"631 Ferry St",
    "sg:city":"Le Sueur",
    "sg:classifiers":[
        {
            "category":"Building & Trades",
            "subcategory":"Construction",
            "type":"Services"
        }
    ],
    "sg:phone":"+1 507 665 4994",
    "sg:postcode":"56058",
    "sg:province":"MN",
    "sg:tags":[
        "floor",
        "laying",
        "contractor"
    ],
    "wof:name":"Carpet By James",
    "wof:placetype":"venue"
},
  "geometry": {"coordinates":[-93.90978200000001,44.457633],"type":"Point"}
}