{
  "type": "Feature",
  "properties": {
    "addr:full":"325 Wise Ave Wayzata MN 55391",
    "addr:housenumber":"325",
    "addr:postcode":"55391",
    "addr:street":"Wise Ave",
    "iso:country":"US",
    "sg:address":"325 Wise Ave",
    "sg:city":"Wayzata",
    "sg:classifiers":[
        {
            "category":"Professional",
            "subcategory":"Management & Consulting",
            "type":"Services"
        },
        {
            "category":"Professional",
            "subcategory":"Advertising",
            "type":"Services"
        }
    ],
    "sg:phone":"+1 952 473 2308",
    "sg:postcode":"55391",
    "sg:province":"MN",
    "sg:tags":[
        "business",
        "consultant",
        "agency",
        "sales",
        "relation",
        "promotion",
        "public"
    ],
    "sg:website":"www.grant-palombo.com",
    "wof:name":"Grant & Palombo Marketing Svc",
    "wof:placetype":"venue"
},
  "geometry": {"coordinates":[-93.503136,44.96757],"type":"Point"}
}