{
  "type": "Feature",
  "properties": {
    "addr:full":"1075 W 7th St Winona MN 55987",
    "addr:housenumber":"1075",
    "addr:postcode":"55987",
    "addr:street":"W 7Th St",
    "iso:country":"US",
    "sg:address":"1075 W 7th St",
    "sg:city":"Winona",
    "sg:classifiers":[
        {
            "category":"Professional",
            "subcategory":"Management & Consulting",
            "type":"Services"
        }
    ],
    "sg:phone":"+1 507 452 4409",
    "sg:postcode":"55987",
    "sg:province":"MN",
    "sg:tags":[
        "communications",
        "publishing",
        "internet"
    ],
    "wof:name":"Minnstar Services System",
    "wof:placetype":"venue"
},
  "geometry": {"coordinates":[-91.665378,44.052064],"type":"Point"}
}