{
  "type": "Feature",
  "properties": {
    "addr:full":"6500 E Frontage Rd Medford MN 55049",
    "addr:housenumber":"6500",
    "addr:postcode":"55049",
    "addr:street":"E Frontage Rd",
    "iso:country":"US",
    "sg:address":"6500 E Frontage Rd",
    "sg:city":"Medford",
    "sg:classifiers":[
        {
            "category":"Home & Garden",
            "subcategory":"Furniture",
            "type":"Retail Goods"
        }
    ],
    "sg:phone":"+1 507 455 3000",
    "sg:postcode":"55049",
    "sg:province":"MN",
    "wof:name":"Furniture Outlet USA",
    "wof:placetype":"venue"
},
  "geometry": {"coordinates":[-93.256919,44.154338],"type":"Point"}
}