{
  "type": "Feature",
  "properties": {
    "iso:country":"US",
    "sg:address":"23240 Itasca Ave N",
    "sg:city":"Forest Lake",
    "sg:classifiers":[
        {
            "category":"Professional",
            "type":"Services"
        }
    ],
    "sg:phone":"+1 651 466 0646",
    "sg:postcode":"55025",
    "sg:province":"MN",
    "wof:name":"Brud Company",
    "wof:placetype":"venue"
},
  "geometry": {"coordinates":[-92.93088299999999,45.284997],"type":"Point"}
}