{
  "type": "Feature",
  "properties": {
    "addr:full":"1484 Branston St St Paul MN 55108",
    "addr:housenumber":"1484",
    "addr:postcode":"55108",
    "addr:street":"Branston St",
    "iso:country":"US",
    "sg:address":"1484 Branston St",
    "sg:city":"St Paul",
    "sg:classifiers":[
        {
            "category":"Organizations",
            "subcategory":"Religious Organization",
            "type":"Services"
        }
    ],
    "sg:phone":"+1 651 646 3484",
    "sg:postcode":"55108",
    "sg:province":"MN",
    "sg:tags":[
        "clergy"
    ],
    "wof:name":"Frederick J Gaiser",
    "wof:placetype":"venue"
},
  "geometry": {"coordinates":[-93.195663,44.985556],"type":"Point"}
}