{
  "type": "Feature",
  "properties": {
    "iso:country":"US",
    "sg:address":"11740 Lockridge Ave N",
    "sg:city":"Stillwater",
    "sg:classifiers":[
        {
            "category":"Banks & Credit Unions",
            "subcategory":"Bank",
            "type":"Services"
        }
    ],
    "sg:phone":"+1 651 439 2817",
    "sg:postcode":"55082",
    "sg:province":"MN",
    "sg:tags":[
        "broker",
        "mortgage"
    ],
    "wof:name":"Resource Financial Inc",
    "wof:placetype":"venue"
},
  "geometry": {"coordinates":[-92.87362,45.116921],"type":"Point"}
}