{
  "type": "Feature",
  "properties": {
    "addr:full":"710 9th Ave NE Waseca MN 56093",
    "addr:housenumber":"710",
    "addr:postcode":"56093",
    "addr:street":"9Th Ave Ne",
    "iso:country":"US",
    "sg:address":"710 9th Ave NE",
    "sg:city":"Waseca",
    "sg:classifiers":[
        {
            "category":"Building & Trades",
            "subcategory":"Construction",
            "type":"Services"
        }
    ],
    "sg:phone":"+1 507 833 5356",
    "sg:postcode":"56093",
    "sg:province":"MN",
    "sg:tags":[
        "house"
    ],
    "wof:name":"Kalbow Construction",
    "wof:placetype":"venue"
},
  "geometry": {"coordinates":[-93.499011,44.086455],"type":"Point"}
}