{
  "type": "Feature",
  "properties": {
    "iso:country":"US",
    "sg:address":"21475 Morristown Blvd",
    "sg:city":"Faribault",
    "sg:classifiers":[
        {
            "category":"Insurance",
            "subcategory":"Hazard Insurance",
            "type":"Services"
        }
    ],
    "sg:phone":"+1 507 334 3395",
    "sg:postcode":"55021",
    "sg:province":"MN",
    "sg:tags":[
        "commercial",
        "business"
    ],
    "wof:name":"Krenz Insurance Agency",
    "wof:placetype":"venue"
},
  "geometry": {"coordinates":[-93.332178,44.279768],"type":"Point"}
}