{
  "type": "Feature",
  "properties": {
    "addr:full":"24580 104th St Zimmerman MN 55398",
    "addr:housenumber":"24580",
    "addr:postcode":"55398",
    "addr:street":"104Th St",
    "iso:country":"US",
    "sg:address":"24580 104th St",
    "sg:city":"Zimmerman",
    "sg:classifiers":[
        {
            "category":"Retail",
            "subcategory":"Auto Repair",
            "type":"Services"
        }
    ],
    "sg:phone":"+1 763 856 3426",
    "sg:postcode":"55398",
    "sg:province":"MN",
    "sg:tags":[
        "body",
        "automobile",
        "painting"
    ],
    "wof:name":"Woodruff's Auto Body",
    "wof:placetype":"venue"
},
  "geometry": {"coordinates":[-93.530776,45.419068],"type":"Point"}
}