{
  "type": "Feature",
  "properties": {
    "addr:full":"224 E Central Entrance Duluth MN 55811",
    "addr:housenumber":"224",
    "addr:postcode":"55811",
    "addr:street":"E Central Entrance",
    "iso:country":"US",
    "sg:address":"224 E Central Entrance",
    "sg:city":"Duluth",
    "sg:classifiers":[
        {
            "category":"Health Services",
            "subcategory":"Health Practitioner",
            "type":"Services"
        }
    ],
    "sg:phone":"+1 218 723 7880",
    "sg:postcode":"55811",
    "sg:province":"MN",
    "wof:name":"Hearing Associates",
    "wof:placetype":"venue"
},
  "geometry": {"coordinates":[-92.127996,46.800281],"type":"Point"}
}