{
  "type": "Feature",
  "properties": {
    "iso:country":"US",
    "sg:address":"37720 210th St",
    "sg:city":"Lamberton",
    "sg:classifiers":[
        {
            "category":"Wholesale",
            "subcategory":"Farm Supplies",
            "type":"Manufacturing & Wholesale Goods"
        },
        {
            "category":"Farming",
            "subcategory":"Farm",
            "type":"Manufacturing & Wholesale Goods"
        }
    ],
    "sg:phone":"+1 507 752 7992",
    "sg:postcode":"56152",
    "sg:province":"MN",
    "sg:tags":[
        "grain"
    ],
    "wof:name":"Russ Derickson",
    "wof:placetype":"venue"
},
  "geometry": {"coordinates":[-95.327252,44.180994],"type":"Point"}
}