{
  "type": "Feature",
  "properties": {
    "iso:country":"US",
    "sg:address":"4181 W Broadway Ave",
    "sg:city":"Minneapolis",
    "sg:classifiers":[
        {
            "category":"Professional",
            "subcategory":"Advertising",
            "type":"Services"
        }
    ],
    "sg:phone":"+1 763 504 0100",
    "sg:postcode":"55422",
    "sg:province":"MN",
    "sg:tags":[
        "counselor"
    ],
    "wof:name":"Steinhauser Creative Group",
    "wof:placetype":"venue"
},
  "geometry": {"coordinates":[-93.33895,45.03075],"type":"Point"}
}