{
  "type": "Feature",
  "properties": {
    "addr:full":"110 Riverview Blvd International Falls MN 56649",
    "addr:housenumber":"110",
    "addr:postcode":"56649",
    "addr:street":"Riverview Blvd International",
    "iso:country":"US",
    "sg:address":"110 Riverview Blvd",
    "sg:city":"International Falls",
    "sg:classifiers":[
        {
            "category":"Freight",
            "type":"Transportation"
        }
    ],
    "sg:phone":"+1 218 283 4770",
    "sg:postcode":"56649",
    "sg:province":"MN",
    "sg:tags":[
        "operator",
        "trucking"
    ],
    "wof:name":"Rdk Transporation Inc",
    "wof:placetype":"venue"
},
  "geometry": {"coordinates":[-93.427277,48.598764],"type":"Point"}
}