{
  "type": "Feature",
  "properties": {
    "addr:full":"17770 State 34 Park Rapids MN 56470",
    "addr:housenumber":"17770;34",
    "addr:postcode":"56470",
    "addr:street":"State",
    "iso:country":"US",
    "sg:address":"17770 State 34",
    "sg:city":"Park Rapids",
    "sg:classifiers":[
        {
            "category":"Building & Trades",
            "subcategory":"Plumbing",
            "type":"Services"
        }
    ],
    "sg:phone":"+1 218 732 5570",
    "sg:postcode":"56470",
    "sg:province":"MN",
    "sg:tags":[
        "contractor"
    ],
    "wof:name":"Denman Sewer Service",
    "wof:placetype":"venue"
},
  "geometry": {"coordinates":[-94.99722199999999,46.929578],"type":"Point"}
}