{
  "type": "Feature",
  "properties": {
    "addr:full":"4220 Wedgewood Ln N Minneapolis MN 55442",
    "addr:housenumber":"4220",
    "addr:postcode":"55442",
    "addr:street":"Wedgewood Ln N",
    "iso:country":"US",
    "sg:address":"4220 Wedgewood Ln N",
    "sg:city":"Minneapolis",
    "sg:classifiers":[
        {
            "category":"Building & Trades",
            "subcategory":"Construction",
            "type":"Services"
        }
    ],
    "sg:phone":"+1 763 557 4966",
    "sg:postcode":"55442",
    "sg:province":"MN",
    "sg:tags":[
        "hanging",
        "contractor"
    ],
    "wof:name":"Decorating Dennis Painting",
    "wof:placetype":"venue"
},
  "geometry": {"coordinates":[-93.449935,45.033286],"type":"Point"}
}