{
  "type": "Feature",
  "properties": {
    "iso:country":"US",
    "sg:address":"1852 Grand Ave",
    "sg:city":"Saint Paul",
    "sg:classifiers":[
        {
            "category":"Personal",
            "subcategory":"Barber",
            "type":"Services"
        }
    ],
    "sg:phone":"+1 651 698 4400",
    "sg:postcode":"55105",
    "sg:province":"MN",
    "wof:name":"Grandview Barber Shop",
    "wof:placetype":"venue"
},
  "geometry": {"coordinates":[-93.17849699999999,44.940201],"type":"Point"}
}