{
  "type": "Feature",
  "properties": {
    "addr:full":"880 W 78th St Excelsior MN 55331",
    "addr:housenumber":"880",
    "addr:postcode":"55331",
    "addr:street":"W 78Th St",
    "iso:country":"US",
    "sg:address":"880 W 78th St",
    "sg:city":"Excelsior",
    "sg:classifiers":[
        {
            "category":"Professional",
            "subcategory":"Printing & Photocopies",
            "type":"Services"
        }
    ],
    "sg:phone":"+1 952 474 0123",
    "sg:postcode":"55331",
    "sg:province":"MN",
    "wof:name":"Kinko's",
    "wof:placetype":"venue"
},
  "geometry": {"coordinates":[-93.576401,44.899101],"type":"Point"}
}