{
  "type": "Feature",
  "properties": {
    "addr:full":"124 Colfax Ave SW Wadena MN 56482",
    "addr:housenumber":"124",
    "addr:postcode":"56482",
    "addr:street":"Colfax Ave Sw",
    "iso:country":"US",
    "sg:address":"124 Colfax Ave SW",
    "sg:city":"Wadena",
    "sg:classifiers":[
        {
            "category":"Professional",
            "type":"Services"
        }
    ],
    "sg:phone":"+1 218 631 3026",
    "sg:postcode":"56482",
    "sg:province":"MN",
    "sg:tags":[
        "establishment"
    ],
    "wof:name":"Dew Enterprises",
    "wof:placetype":"venue"
},
  "geometry": {"coordinates":[-95.13999099999999,46.439941],"type":"Point"}
}