{
  "type": "Feature",
  "properties": {
    "addr:full":"1009 Gramsey Pl Burnsville MN 55306",
    "addr:housenumber":"1009",
    "addr:postcode":"55306",
    "addr:street":"Gramsey Pl",
    "iso:country":"US",
    "sg:address":"1009 Gramsey Pl",
    "sg:city":"Burnsville",
    "sg:classifiers":[
        {
            "category":"Manufacturing",
            "subcategory":"Toys & Sporting Goods",
            "type":"Manufacturing & Wholesale Goods"
        }
    ],
    "sg:phone":"+1 952 953 0999",
    "sg:postcode":"55306",
    "sg:province":"MN",
    "sg:tags":[
        "mfg"
    ],
    "wof:name":"Five Aces Custom Clubs",
    "wof:placetype":"venue"
},
  "geometry": {"coordinates":[-93.259075,44.730692],"type":"Point"}
}