{
  "type": "Feature",
  "properties": {
    "addr:full":"14567 Goodwin Ave Hastings MN 55033",
    "addr:housenumber":"14567",
    "addr:postcode":"55033",
    "addr:street":"Goodwin Ave",
    "iso:country":"US",
    "sg:address":"14567 Goodwin Ave",
    "sg:city":"Hastings",
    "sg:classifiers":[
        {
            "category":"Real Estate",
            "subcategory":"Architect",
            "type":"Services"
        }
    ],
    "sg:phone":"+1 651 480 2123",
    "sg:postcode":"55033",
    "sg:province":"MN",
    "wof:name":"Brian Welman Training Center",
    "wof:placetype":"venue"
},
  "geometry": {"coordinates":[-92.953785,44.737676],"type":"Point"}
}