{
  "type": "Feature",
  "properties": {
    "addr:full":"122 1st Ave SE Little Falls MN 56345",
    "addr:housenumber":"122",
    "addr:postcode":"56345",
    "addr:street":"1St Ave Se",
    "iso:country":"US",
    "sg:address":"122 1st Ave SE",
    "sg:city":"Little Falls",
    "sg:classifiers":[
        {
            "category":"Building & Trades",
            "subcategory":"Electrical",
            "type":"Services"
        }
    ],
    "sg:phone":"+1 320 632 8886",
    "sg:postcode":"56345",
    "sg:province":"MN",
    "sg:tags":[
        "electric",
        "contractor"
    ],
    "wof:name":"Hauer Brothers Electric",
    "wof:placetype":"venue"
},
  "geometry": {"coordinates":[-94.362517,45.975218],"type":"Point"}
}