{
  "type": "Feature",
  "properties": {
    "addr:full":"3533 W 70th St Edina MN 55435",
    "addr:housenumber":"3533",
    "addr:postcode":"55435",
    "addr:street":"W 70Th St",
    "iso:country":"US",
    "sg:address":"3533 W 70th St",
    "sg:city":"Edina",
    "sg:classifiers":[
        {
            "category":"Home & Garden",
            "subcategory":"Household Appliances",
            "type":"Retail Goods"
        }
    ],
    "sg:phone":"+1 612 920 0640",
    "sg:postcode":"55435",
    "sg:province":"MN",
    "sg:website":"www.warnerstellian.com",
    "wof:name":"Warner's Stellian Appliance",
    "wof:placetype":"venue"
},
  "geometry": {"coordinates":[-93.326533,44.876268],"type":"Point"}
}