{
  "type": "Feature",
  "properties": {
    "iso:country":"US",
    "sg:address":"9000 Chicago Ave S",
    "sg:city":"Minneapolis",
    "sg:classifiers":[
        {
            "category":"Arena",
            "subcategory":"Sports Club",
            "type":"Entertainment"
        }
    ],
    "sg:phone":"+1 952 854 2836",
    "sg:postcode":"55420",
    "sg:province":"MN",
    "sg:tags":[
        "ticket",
        "sale"
    ],
    "wof:name":"Boss",
    "wof:placetype":"venue"
},
  "geometry": {"coordinates":[-93.263184,44.840729],"type":"Point"}
}