{
  "type": "Feature",
  "properties": {
    "iso:country":"US",
    "sg:address":"1931 15th St NE",
    "sg:city":"Sauk Rapids",
    "sg:classifiers":[
        {
            "category":"Building & Trades",
            "subcategory":"Construction",
            "type":"Services"
        }
    ],
    "sg:phone":"+1 320 252 3070",
    "sg:postcode":"56379",
    "sg:province":"MN",
    "sg:tags":[
        "contractor"
    ],
    "wof:name":"Kurt J Schimnich Construction",
    "wof:placetype":"venue"
},
  "geometry": {"coordinates":[-94.124385,45.588437],"type":"Point"}
}