{
  "type": "Feature",
  "properties": {
    "iso:country":"US",
    "sg:address":"928 E 4th St",
    "sg:city":"Duluth",
    "sg:classifiers":[
        {
            "category":"Organizations",
            "subcategory":"Professional Association",
            "type":"Services"
        }
    ],
    "sg:phone":"+1 218 724 8512",
    "sg:postcode":"55805",
    "sg:province":"MN",
    "sg:tags":[
        "business"
    ],
    "wof:name":"Hillside Business Assoc",
    "wof:placetype":"venue"
},
  "geometry": {"coordinates":[-92.090354,46.79882],"type":"Point"}
}