{
  "type": "Feature",
  "properties": {
    "addr:full":"9087 SW 37th Ave Hope MN 56026",
    "addr:housenumber":"9087",
    "addr:postcode":"56026",
    "addr:street":"Sw 37Th Ave",
    "iso:country":"US",
    "sg:address":"9087 SW 37th Ave",
    "sg:city":"Hope",
    "sg:classifiers":[
        {
            "category":"Banks & Credit Unions",
            "subcategory":"Bank",
            "type":"Services"
        }
    ],
    "sg:phone":"+1 507 451 5818",
    "sg:postcode":"56026",
    "sg:province":"MN",
    "wof:name":"First National Bank",
    "wof:placetype":"venue"
},
  "geometry": {"coordinates":[-93.276194,43.960197],"type":"Point"}
}