{
  "type": "Feature",
  "properties": {
    "addr:full":"255 Oakwood Rd Hopkins MN 55343",
    "addr:housenumber":"255",
    "addr:postcode":"55343",
    "addr:street":"Oakwood Rd",
    "iso:country":"US",
    "sg:address":"255 Oakwood Rd",
    "sg:city":"Hopkins",
    "sg:classifiers":[
        {
            "category":"Manufacturing",
            "subcategory":"Paper Products",
            "type":"Manufacturing & Wholesale Goods"
        }
    ],
    "sg:phone":"+1 952 945 9516",
    "sg:postcode":"55343",
    "sg:province":"MN",
    "sg:tags":[
        "sanitary",
        "mfg"
    ],
    "wof:name":"Parentprops Inc",
    "wof:placetype":"venue"
},
  "geometry": {"coordinates":[-93.38198800000001,44.921632],"type":"Point"}
}