{
  "type": "Feature",
  "properties": {
    "addr:full":"104 Co Hwy 82 Ashby MN 56309",
    "addr:housenumber":"104",
    "addr:postcode":"56309",
    "addr:street":"Co Hwy 82",
    "iso:country":"US",
    "sg:address":"104 Co Hwy 82",
    "sg:city":"Ashby",
    "sg:classifiers":[
        {
            "category":"Building & Trades",
            "subcategory":"Plumbing",
            "type":"Services"
        }
    ],
    "sg:phone":"+1 218 747 2909",
    "sg:postcode":"56309",
    "sg:province":"MN",
    "sg:tags":[
        "heating",
        "contractor"
    ],
    "wof:name":"Country Heating & Air Cond",
    "wof:placetype":"venue"
},
  "geometry": {"coordinates":[-95.818814,46.093468],"type":"Point"}
}