{
  "type": "Feature",
  "properties": {
    "addr:full":"41562 Bur Oak Hills Rd Pelican Rapids MN 56572",
    "addr:postcode":"41562;56572",
    "addr:street":"Bur Oak Hills Rd",
    "iso:country":"US",
    "sg:address":"41562 Bur Oak Hills Rd",
    "sg:city":"Pelican Rapids",
    "sg:classifiers":[
        {
            "category":"Retail",
            "subcategory":"Auto Repair",
            "type":"Services"
        }
    ],
    "sg:phone":"+1 218 863 7831",
    "sg:postcode":"56572",
    "sg:province":"MN",
    "sg:tags":[
        "repairing",
        "automobile"
    ],
    "wof:name":"Bauman Repair Inc",
    "wof:placetype":"venue"
},
  "geometry": {"coordinates":[-96.061453,46.564376],"type":"Point"}
}