{
  "type": "Feature",
  "properties": {
    "iso:country":"US",
    "sg:address":"205 3rd St NW",
    "sg:city":"Twin Valley",
    "sg:classifiers":[
        {
            "category":"Social Services",
            "subcategory":"Adult Care",
            "type":"Services"
        }
    ],
    "sg:phone":"+1 218 584 5183",
    "sg:postcode":"56584",
    "sg:province":"MN",
    "sg:tags":[
        "home",
        "residential"
    ],
    "wof:name":"Normandy",
    "wof:placetype":"venue"
},
  "geometry": {"coordinates":[-96.262663,47.260902],"type":"Point"}
}