{
  "type": "Feature",
  "properties": {
    "addr:full":"1 W 4th St Winona MN 55987",
    "addr:housenumber":"1",
    "addr:postcode":"55987",
    "addr:street":"W 4Th St",
    "iso:country":"US",
    "sg:address":"1 W 4th St",
    "sg:city":"Winona",
    "sg:classifiers":[
        {
            "category":"Real Estate",
            "subcategory":"Real Estate Agent",
            "type":"Services"
        }
    ],
    "sg:phone":"+1 507 452 2333",
    "sg:postcode":"55987",
    "sg:province":"MN",
    "sg:tags":[
        "appraiser"
    ],
    "wof:name":"Jaastad Property Appraisals",
    "wof:placetype":"venue"
},
  "geometry": {"coordinates":[-91.63825,44.051759],"type":"Point"}
}