{
  "type": "Feature",
  "properties": {
    "iso:country":"US",
    "sg:address":"13779 245th St",
    "sg:city":"Hutchinson",
    "sg:classifiers":[
        {
            "category":"Building & Trades",
            "subcategory":"Construction",
            "type":"Services"
        }
    ],
    "sg:phone":"+1 320 587 9269",
    "sg:postcode":"55350",
    "sg:province":"MN",
    "sg:tags":[
        "excavation",
        "contractor"
    ],
    "wof:name":"Nygaard Excavating & Septic",
    "wof:placetype":"venue"
},
  "geometry": {"coordinates":[-94.268788,44.97198],"type":"Point"}
}