{
  "type": "Feature",
  "properties": {
    "iso:country":"US",
    "sg:address":"4190 River Rd",
    "sg:city":"Grand Rapids",
    "sg:classifiers":[
        {
            "category":"Professional",
            "subcategory":"Management & Consulting",
            "type":"Services"
        }
    ],
    "sg:phone":"+1 218 326 6990",
    "sg:postcode":"55744",
    "sg:province":"MN",
    "wof:name":"Itasca Utilities Shop",
    "wof:placetype":"venue"
},
  "geometry": {"coordinates":[-93.47989,47.197694],"type":"Point"}
}