{
  "type": "Feature",
  "properties": {
    "iso:country":"US",
    "sg:address":"1436 280th St S",
    "sg:city":"Hawley",
    "sg:classifiers":[
        {
            "category":"Building & Trades",
            "subcategory":"Electrical",
            "type":"Services"
        }
    ],
    "sg:phone":"+1 218 238 5519",
    "sg:postcode":"56549",
    "sg:province":"MN",
    "sg:tags":[
        "electric",
        "contractor"
    ],
    "wof:name":"Knutson Electric",
    "wof:placetype":"venue"
},
  "geometry": {"coordinates":[-96.217664,46.862779],"type":"Point"}
}