{
  "type": "Feature",
  "properties": {
    "iso:country":"US",
    "sg:address":"515 N Broadway",
    "sg:city":"Rochester",
    "sg:classifiers":[
        {
            "category":"Autos & Motor Vehicles",
            "subcategory":"Auto Supplies",
            "type":"Retail Goods"
        }
    ],
    "sg:phone":"+1 507 424 3236",
    "sg:postcode":"55906",
    "sg:province":"MN",
    "sg:tags":[
        "equipment",
        "racing",
        "car",
        "automobile"
    ],
    "wof:name":"Speed King Performance Inc",
    "wof:placetype":"venue"
},
  "geometry": {"coordinates":[-92.463086,44.029292],"type":"Point"}
}