{
  "type": "Feature",
  "properties": {
    "addr:full":"7400 Lyndale Ave S Minneapolis MN 55423",
    "addr:housenumber":"7400",
    "addr:postcode":"55423",
    "addr:street":"Lyndale Ave S",
    "iso:country":"US",
    "sg:address":"7400 Lyndale Ave S",
    "sg:city":"Minneapolis",
    "sg:classifiers":[
        {
            "category":"Professional",
            "subcategory":"Lawyer & Legal Services",
            "type":"Services"
        }
    ],
    "sg:phone":"+1 612 869 8880",
    "sg:postcode":"55423",
    "sg:province":"MN",
    "wof:name":"Levin Roares & Aspnes Corp",
    "wof:placetype":"venue"
},
  "geometry": {"coordinates":[-93.288399,44.867306],"type":"Point"}
}