{
  "type": "Feature",
  "properties": {
    "addr:full":"1389 Roland Rd Cloquet MN 55720",
    "addr:housenumber":"1389",
    "addr:postcode":"55720",
    "addr:street":"Roland Rd",
    "iso:country":"US",
    "sg:address":"1389 Roland Rd",
    "sg:city":"Cloquet",
    "sg:classifiers":[
        {
            "category":"Banks & Credit Unions",
            "subcategory":"Investment Brokerage",
            "type":"Services"
        }
    ],
    "sg:phone":"+1 218 879 1924",
    "sg:postcode":"55720",
    "sg:province":"MN",
    "sg:tags":[
        "advisory"
    ],
    "wof:name":"Barto Family Investments",
    "wof:placetype":"venue"
},
  "geometry": {"coordinates":[-92.449912,46.686443],"type":"Point"}
}