{
  "type": "Feature",
  "properties": {
    "iso:country":"US",
    "sg:address":"18 1st Ave SE",
    "sg:city":"Rochester",
    "sg:classifiers":[
        {
            "category":"Professional",
            "type":"Services"
        }
    ],
    "sg:phone":"+1 507 252 1111",
    "sg:postcode":"55904",
    "sg:province":"MN",
    "sg:tags":[
        "establishment"
    ],
    "wof:name":"Cityline",
    "wof:placetype":"venue"
},
  "geometry": {"coordinates":[-92.461456,44.022678],"type":"Point"}
}