{
  "type": "Feature",
  "properties": {
    "iso:country":"US",
    "sg:address":"1415 Sundby Rd",
    "sg:city":"Duluth",
    "sg:classifiers":[
        {
            "category":"Health Services",
            "subcategory":"Dentist",
            "type":"Services"
        }
    ],
    "sg:phone":"+1 218 722 1070",
    "sg:postcode":"55811",
    "sg:province":"MN",
    "sg:tags":[
        "dentists-cosmetic",
        "dentistry"
    ],
    "sg:website":"http://www.millerhilldental.com",
    "wof:name":"Miller Hill Dental",
    "wof:placetype":"venue"
},
  "geometry": {"coordinates":[-92.165313,46.8108],"type":"Point"}
}