{
  "type": "Feature",
  "properties": {
    "iso:country":"US",
    "sg:address":"5455 180th St W",
    "sg:city":"Farmington",
    "sg:classifiers":[
        {
            "category":"Building & Trades",
            "subcategory":"Plumbing",
            "type":"Services"
        }
    ],
    "sg:phone":"+1 952 469 4000",
    "sg:postcode":"55024",
    "sg:province":"MN",
    "sg:tags":[
        "contractor"
    ],
    "wof:name":"Accredited Plumbing & Repair",
    "wof:placetype":"venue"
},
  "geometry": {"coordinates":[-93.175246,44.688346],"type":"Point"}
}