{
  "type": "Feature",
  "properties": {
    "addr:full":"609 SE 98th St Owatonna MN 55060",
    "addr:housenumber":"609",
    "addr:postcode":"55060",
    "addr:street":"Se 98Th St",
    "iso:country":"US",
    "sg:address":"609 SE 98th St",
    "sg:city":"Owatonna",
    "sg:phone":"+1 507 444 9626",
    "sg:postcode":"55060",
    "sg:province":"MN",
    "sg:tags":[
        "farm",
        "corn",
        "soybean"
    ],
    "wof:name":"Daniel Kasper",
    "wof:placetype":"venue"
},
  "geometry": {"coordinates":[-93.20599199999999,43.949926],"type":"Point"}
}