{
  "type": "Feature",
  "properties": {
    "iso:country":"US",
    "sg:address":"110 Willow St S",
    "sg:city":"Onamia",
    "sg:classifiers":[
        {
            "category":"Wholesale",
            "subcategory":"Apparel",
            "type":"Manufacturing & Wholesale Goods"
        }
    ],
    "sg:phone":"+1 320 532 3126",
    "sg:postcode":"56378",
    "sg:province":"MN",
    "sg:tags":[
        "t"
    ],
    "sg:website":"www.noblewear.com",
    "wof:name":"Noble Wear",
    "wof:placetype":"venue"
},
  "geometry": {"coordinates":[-94.959896,45.739069],"type":"Point"}
}