{
  "type": "Feature",
  "properties": {
    "iso:country":"US",
    "sg:address":"3521 Hwy 210 SW",
    "sg:city":"Pillager",
    "sg:classifiers":[
        {
            "category":"Home & Garden",
            "subcategory":"Furniture",
            "type":"Retail Goods"
        }
    ],
    "sg:phone":"+1 218 822 4224",
    "sg:postcode":"56473",
    "sg:province":"MN",
    "wof:name":"Tank's Furniture Clearance Ctr",
    "wof:placetype":"venue"
},
  "geometry": {"coordinates":[-94.465885,46.333958],"type":"Point"}
}