{
  "type": "Feature",
  "properties": {
    "addr:full":"424 20th S St New Ulm MN 56073",
    "addr:housenumber":"424",
    "addr:postcode":"56073",
    "addr:street":"20Th S St",
    "iso:country":"US",
    "sg:address":"424 20th S St",
    "sg:city":"New Ulm",
    "sg:classifiers":[
        {
            "category":"Travel",
            "subcategory":"Hotels & Motels",
            "type":"Entertainment"
        }
    ],
    "sg:phone":"+1 507 354 9800",
    "sg:postcode":"56073",
    "sg:province":"MN",
    "wof:name":"Microtel Inns & Suites",
    "wof:placetype":"venue"
},
  "geometry": {"coordinates":[-94.439543,44.294134],"type":"Point"}
}