{
  "type": "Feature",
  "properties": {
    "addr:full":"11512 Crow-Hassan Park Rd Hanover MN 55341",
    "addr:postcode":"11512;55341",
    "addr:street":"Park Rd",
    "iso:country":"US",
    "sg:address":"11512 Crow-Hassan Park Rd",
    "sg:city":"Hanover",
    "sg:classifiers":[
        {
            "category":"Building & Trades",
            "subcategory":"Construction",
            "type":"Services"
        }
    ],
    "sg:phone":"+1 763 498 8607",
    "sg:postcode":"55341",
    "sg:province":"MN",
    "sg:tags":[
        "cont",
        "family",
        "builder",
        "contractor",
        "framing",
        "home",
        "general"
    ],
    "sg:website":"www.jphillipsconstruction.com",
    "wof:name":"J Phillips Construction Inc",
    "wof:placetype":"venue"
},
  "geometry": {"coordinates":[-93.63545999999999,45.158156],"type":"Point"}
}