{
  "type": "Feature",
  "properties": {
    "iso:country":"US",
    "sg:address":"915 32nd Ave S",
    "sg:city":"Moorhead",
    "sg:classifiers":[
        {
            "category":"Professional",
            "type":"Services"
        }
    ],
    "sg:phone":"+1 218 287 1631",
    "sg:postcode":"56560",
    "sg:province":"MN",
    "sg:tags":[
        "establishment"
    ],
    "wof:name":"Sd Rapid City Mssn",
    "wof:placetype":"venue"
},
  "geometry": {"coordinates":[-96.763249,46.841858],"type":"Point"}
}