{
  "type": "Feature",
  "properties": {
    "addr:full":"712 Country Pl Burnsville MN 55337",
    "addr:housenumber":"712",
    "addr:postcode":"55337",
    "addr:street":"Country Pl",
    "iso:country":"US",
    "sg:address":"712 Country Pl",
    "sg:city":"Burnsville",
    "sg:classifiers":[
        {
            "category":"Home & Garden",
            "subcategory":"Furniture",
            "type":"Retail Goods"
        }
    ],
    "sg:phone":"+1 952 898 9146",
    "sg:postcode":"55337",
    "sg:province":"MN",
    "wof:name":"Woodworks Rustic Furniture",
    "wof:placetype":"venue"
},
  "geometry": {"coordinates":[-93.264196,44.753967],"type":"Point"}
}