{
  "type": "Feature",
  "properties": {
    "addr:full":"800 Transfer Rd Saint Paul MN 55114",
    "addr:housenumber":"800",
    "addr:postcode":"55114",
    "addr:street":"Transfer Rd",
    "iso:country":"US",
    "sg:address":"800 Transfer Rd",
    "sg:city":"Saint Paul",
    "sg:classifiers":[
        {
            "category":"Shopping",
            "type":"Retail Goods"
        }
    ],
    "sg:phone":"+1 651 644 4222",
    "sg:postcode":"55114",
    "sg:province":"MN",
    "sg:tags":[
        "merchandise"
    ],
    "wof:name":"Art Direct",
    "wof:placetype":"venue"
},
  "geometry": {"coordinates":[-93.184426,44.96838],"type":"Point"}
}