{
  "type": "Feature",
  "properties": {
    "addr:full":"721 Custer St South Haven MN 55382",
    "addr:housenumber":"721",
    "addr:postcode":"55382",
    "addr:street":"Custer St;Haven",
    "iso:country":"US",
    "sg:address":"721 Custer St",
    "sg:city":"South Haven",
    "sg:classifiers":[
        {
            "category":"Retail",
            "subcategory":"Repair Shop",
            "type":"Services"
        }
    ],
    "sg:phone":"+1 320 236 2294",
    "sg:postcode":"55382",
    "sg:province":"MN",
    "sg:tags":[
        "upholsterer"
    ],
    "wof:name":"Little-Wing Upholstery",
    "wof:placetype":"venue"
},
  "geometry": {"coordinates":[-94.223094,45.292766],"type":"Point"}
}