{
  "type": "Feature",
  "properties": {
    "addr:full":"14511 Lake Street Ext Minnetonka MN 55345",
    "addr:housenumber":"14511",
    "addr:postcode":"55345",
    "addr:street":"Lake Street Ext",
    "iso:country":"US",
    "sg:address":"14511 Lake Street Ext",
    "sg:city":"Minnetonka",
    "sg:classifiers":[
        {
            "category":"Communications",
            "subcategory":"Film & Video Production",
            "type":"Services"
        }
    ],
    "sg:phone":"+1 952 933 4045",
    "sg:postcode":"55345",
    "sg:province":"MN",
    "wof:name":"Edit Ink",
    "wof:placetype":"venue"
},
  "geometry": {"coordinates":[-93.464795,44.927219],"type":"Point"}
}