{
  "type": "Feature",
  "properties": {
    "addr:full":"20686 Holyoke Ave Lakeville MN 55044",
    "addr:postcode":"20686;55044",
    "addr:street":"Holyoke Ave",
    "iso:country":"US",
    "sg:address":"20686 Holyoke Ave",
    "sg:city":"Lakeville",
    "sg:classifiers":[
        {
            "category":"Professional",
            "subcategory":"Lawyer & Legal Services",
            "type":"Services"
        }
    ],
    "sg:phone":"+1 952 469 4948",
    "sg:postcode":"55044",
    "sg:province":"MN",
    "sg:tags":[
        "attorney"
    ],
    "wof:name":"R Glenn Nord & Assoc",
    "wof:placetype":"venue"
},
  "geometry": {"coordinates":[-93.242718,44.64993],"type":"Point"}
}