{
  "type": "Feature",
  "properties": {
    "addr:full":"2221 University Ave SE Minneapolis MN 55414",
    "addr:housenumber":"2221",
    "addr:postcode":"55414",
    "addr:street":"University Ave Se",
    "iso:country":"US",
    "sg:address":"2221 University Ave SE",
    "sg:city":"Minneapolis",
    "sg:classifiers":[
        {
            "category":"Travel",
            "subcategory":"Travel Agent",
            "type":"Entertainment"
        }
    ],
    "sg:phone":"+1 612 872 4931",
    "sg:postcode":"55414",
    "sg:province":"MN",
    "sg:tags":[
        "agency",
        "services-commercial"
    ],
    "sg:website":"http://www.gttglobal.com",
    "wof:name":"Usa Gateway Travel Services",
    "wof:placetype":"venue"
},
  "geometry": {"coordinates":[-93.223618,44.974414],"type":"Point"}
}