{
  "type": "Feature",
  "properties": {
    "addr:full":"50 10th St S Minneapolis MN 55403",
    "addr:housenumber":"50",
    "addr:postcode":"55403",
    "addr:street":"10Th St S",
    "iso:country":"US",
    "sg:address":"50 10th St S",
    "sg:city":"Minneapolis",
    "sg:classifiers":[
        {
            "category":"Wholesale",
            "subcategory":"Durable Goods & Equipment",
            "type":"Manufacturing & Wholesale Goods"
        }
    ],
    "sg:phone":"+1 612 339 3438",
    "sg:postcode":"55403",
    "sg:province":"MN",
    "sg:tags":[
        "representative",
        "manufacturer"
    ],
    "wof:name":"R S Peterson Sales Inc",
    "wof:placetype":"venue"
},
  "geometry": {"coordinates":[-93.274823,44.974128],"type":"Point"}
}