{
  "type": "Feature",
  "properties": {
    "addr:full":"41906 Co Rd 122 Frazee MN 56544",
    "addr:housenumber":"41906;122",
    "addr:postcode":"56544",
    "addr:street":"Co Rd",
    "iso:country":"US",
    "sg:address":"41906 Co Rd 122",
    "sg:city":"Frazee",
    "sg:classifiers":[
        {
            "category":"Building & Trades",
            "subcategory":"Landscaping Services",
            "type":"Services"
        }
    ],
    "sg:phone":"+1 218 334 5268",
    "sg:postcode":"56544",
    "sg:province":"MN",
    "sg:tags":[
        "tree"
    ],
    "wof:name":"Shipman's Tree Svc",
    "wof:placetype":"venue"
},
  "geometry": {"coordinates":[-95.514673,46.789594],"type":"Point"}
}