{
  "type": "Feature",
  "properties": {
    "addr:full":"100 Fuller St S Shakopee MN 55379",
    "addr:housenumber":"100",
    "addr:postcode":"55379",
    "addr:street":"Fuller St S",
    "iso:country":"US",
    "sg:address":"100 Fuller St S",
    "sg:city":"Shakopee",
    "sg:classifiers":[
        {
            "category":"Professional",
            "subcategory":"Employment Agencies",
            "type":"Services"
        }
    ],
    "sg:phone":"+1 952 496 3030",
    "sg:postcode":"55379",
    "sg:province":"MN",
    "sg:tags":[
        "help",
        "contractor"
    ],
    "wof:name":"Sales Consultants",
    "wof:placetype":"venue"
},
  "geometry": {"coordinates":[-93.528128,44.798075],"type":"Point"}
}