{
  "type": "Feature",
  "properties": {
    "addr:full":"179 Exeter Pl Saint Paul MN 55104",
    "addr:housenumber":"179",
    "addr:postcode":"55104",
    "addr:street":"Exeter Pl",
    "iso:country":"US",
    "sg:address":"179 Exeter Pl",
    "sg:city":"Saint Paul",
    "sg:classifiers":[
        {
            "category":"Retail",
            "subcategory":"Portrait Studio",
            "type":"Services"
        }
    ],
    "sg:phone":"+1 651 645 1370",
    "sg:postcode":"55104",
    "sg:province":"MN",
    "sg:tags":[
        "laboratory",
        "photofinishing",
        "photo"
    ],
    "wof:name":"Skjold Photography Inc",
    "wof:placetype":"venue"
},
  "geometry": {"coordinates":[-93.19455499999999,44.946479],"type":"Point"}
}