{
  "type": "Feature",
  "properties": {
    "addr:full":"903 Main Ave Moorhead MN 56560",
    "addr:housenumber":"903",
    "addr:postcode":"56560",
    "addr:street":"Main Ave",
    "iso:country":"US",
    "sg:address":"903 Main Ave",
    "sg:city":"Moorhead",
    "sg:classifiers":[
        {
            "category":"Autos & Motor Vehicles",
            "subcategory":"Fuel & Gas Station",
            "type":"Retail Goods"
        }
    ],
    "sg:phone":"+1 218 233 1408",
    "sg:postcode":"56560",
    "sg:province":"MN",
    "sg:tags":[
        "station",
        "gasoline"
    ],
    "wof:name":"Gas Stop",
    "wof:placetype":"venue"
},
  "geometry": {"coordinates":[-96.764849,46.873707],"type":"Point"}
}