{
  "type": "Feature",
  "properties": {
    "addr:full":"3351 Round Lake Blvd NW Anoka MN 55303",
    "addr:housenumber":"3351",
    "addr:postcode":"55303",
    "addr:street":"Round Lake Blvd Nw",
    "iso:country":"US",
    "sg:address":"3351 Round Lake Blvd NW",
    "sg:city":"Anoka",
    "sg:classifiers":[
        {
            "category":"Real Estate",
            "subcategory":"Real Estate Services",
            "type":"Services"
        },
        {
            "category":"Real Estate",
            "subcategory":"Real Estate Agent",
            "type":"Services"
        }
    ],
    "sg:phone":"+1 763 300 3170",
    "sg:postcode":"55303",
    "sg:province":"MN",
    "sg:tags":[
        "buyer",
        "broker"
    ],
    "wof:name":"Tiffany Larson Realty",
    "wof:placetype":"venue"
},
  "geometry": {"coordinates":[-93.35755899999999,45.215462],"type":"Point"}
}