{
  "type": "Feature",
  "properties": {
    "iso:country":"US",
    "sg:address":"15713 Elodie Ln",
    "sg:city":"Minnetonka",
    "sg:classifiers":[
        {
            "category":"Manufacturing",
            "subcategory":"Tools & Machinery",
            "type":"Manufacturing & Wholesale Goods"
        }
    ],
    "sg:phone":"+1 952 975 9203",
    "sg:postcode":"55345",
    "sg:province":"MN",
    "sg:tags":[
        "photographic",
        "mfg"
    ],
    "wof:name":"Illunis LLC",
    "wof:placetype":"venue"
},
  "geometry": {"coordinates":[-93.480104,44.908153],"type":"Point"}
}