{
  "type": "Feature",
  "properties": {
    "iso:country":"US",
    "sg:address":"3696 Edgerton St",
    "sg:city":"St Paul",
    "sg:classifiers":[
        {
            "category":"Building & Trades",
            "subcategory":"Cleaning & Sanitation",
            "type":"Services"
        }
    ],
    "sg:phone":"+1 651 426 8005",
    "sg:postcode":"55127",
    "sg:province":"MN",
    "sg:tags":[
        "snow",
        "removal"
    ],
    "wof:name":"Jacobsen Removal",
    "wof:placetype":"venue"
},
  "geometry": {"coordinates":[-93.0765,45.053252],"type":"Point"}
}