{
  "type": "Feature",
  "properties": {
    "iso:country":"US",
    "sg:address":"1149 Whitewater Ave",
    "sg:city":"Saint Charles",
    "sg:classifiers":[
        {
            "category":"Shopping",
            "subcategory":"Clothing, Apparel, & Fashions",
            "type":"Retail Goods"
        }
    ],
    "sg:phone":"+1 507 932 6813",
    "sg:postcode":"55972",
    "sg:province":"MN",
    "wof:name":"Latino Wear",
    "wof:placetype":"venue"
},
  "geometry": {"coordinates":[-92.064814,43.967292],"type":"Point"}
}