{
  "type": "Feature",
  "properties": {
    "iso:country":"US",
    "sg:address":"6916 Langford Ct",
    "sg:city":"Minneapolis",
    "sg:classifiers":[
        {
            "category":"Building & Trades",
            "subcategory":"Construction",
            "type":"Services"
        }
    ],
    "sg:phone":"+1 952 936 7624",
    "sg:postcode":"55436",
    "sg:province":"MN",
    "sg:tags":[
        "home",
        "builder"
    ],
    "wof:name":"Manor Homes Of Edina",
    "wof:placetype":"venue"
},
  "geometry": {"coordinates":[-93.397746,44.89518],"type":"Point"}
}