{
  "type": "Feature",
  "properties": {
    "addr:full":"12984 Nicollet Ave Burnsville MN 55337",
    "addr:housenumber":"12984",
    "addr:postcode":"55337",
    "addr:street":"Nicollet Ave",
    "iso:country":"US",
    "sg:address":"12984 Nicollet Ave",
    "sg:city":"Burnsville",
    "sg:classifiers":[
        {
            "category":"Professional",
            "type":"Services"
        }
    ],
    "sg:phone":"+1 952 736 3708",
    "sg:postcode":"55337",
    "sg:province":"MN",
    "wof:name":"Keebers Pretzels",
    "wof:placetype":"venue"
},
  "geometry": {"coordinates":[-93.277811,44.770262],"type":"Point"}
}