{
  "type": "Feature",
  "properties": {
    "iso:country":"US",
    "sg:address":"401 Mound Ave",
    "sg:city":"Balaton",
    "sg:phone":"+1 507 734 4422",
    "sg:postcode":"56115",
    "sg:province":"MN",
    "sg:tags":[
        "farm",
        "field",
        "corn",
        "soybean",
        "crop"
    ],
    "wof:name":"Loren Dunteman",
    "wof:placetype":"venue"
},
  "geometry": {"coordinates":[-95.87402899999999,44.230799],"type":"Point"}
}