{
  "type": "Feature",
  "properties": {
    "addr:full":"26202 Hale Ct Wyoming MN 55092",
    "addr:housenumber":"26202",
    "addr:postcode":"55092",
    "addr:street":"Hale Ct",
    "iso:country":"US",
    "sg:address":"26202 Hale Ct",
    "sg:city":"Wyoming",
    "sg:classifiers":[
        {
            "category":"Shopping",
            "subcategory":"Catalog Store",
            "type":"Retail Goods"
        }
    ],
    "sg:phone":"+1 651 208 3438",
    "sg:postcode":"55092",
    "sg:province":"MN",
    "sg:tags":[
        "mail",
        "order"
    ],
    "wof:name":"Area 14",
    "wof:placetype":"venue"
},
  "geometry": {"coordinates":[-92.959788,45.328711],"type":"Point"}
}