{
  "type": "Feature",
  "properties": {
    "iso:country":"US",
    "sg:address":"1115 Vicksburg Ln N # 10",
    "sg:city":"Minneapolis",
    "sg:classifiers":[
        {
            "category":"Health Services",
            "subcategory":"Chiropractor",
            "type":"Services"
        }
    ],
    "sg:phone":"+1 763 473 7000",
    "sg:postcode":"55447",
    "sg:province":"MN",
    "sg:tags":[
        "chiropractic"
    ],
    "wof:name":"Goebel Chiropractic Famil",
    "wof:placetype":"venue"
},
  "geometry": {"coordinates":[-93.481432,44.991906],"type":"Point"}
}