{
  "type": "Feature",
  "properties": {
    "addr:full":"90 W 4th St St Paul MN 55102",
    "addr:housenumber":"90",
    "addr:postcode":"55102",
    "addr:street":"W 4Th St",
    "iso:country":"US",
    "sg:address":"90 W 4th St",
    "sg:city":"St Paul",
    "sg:classifiers":[
        {
            "category":"Restaurant",
            "type":"Food & Drink"
        }
    ],
    "sg:phone":"+1 651 222 7330",
    "sg:postcode":"55102",
    "sg:province":"MN",
    "sg:tags":[
        "shop",
        "coffee"
    ],
    "wof:name":"Blue Bell Zelda's",
    "wof:placetype":"venue"
},
  "geometry": {"coordinates":[-93.09738400000001,44.944078],"type":"Point"}
}