{
  "type": "Feature",
  "properties": {
    "addr:full":"111 W Vine St Owatonna MN 55060",
    "addr:housenumber":"111",
    "addr:postcode":"55060",
    "addr:street":"W Vine St",
    "iso:country":"US",
    "sg:address":"111 W Vine St",
    "sg:city":"Owatonna",
    "sg:classifiers":[
        {
            "category":"Professional",
            "type":"Services"
        },
        {
            "category":"Wholesale",
            "subcategory":"Jewelry",
            "type":"Manufacturing & Wholesale Goods"
        }
    ],
    "sg:phone":"+1 507 455 0115",
    "sg:postcode":"55060",
    "sg:province":"MN",
    "sg:tags":[
        "beads"
    ],
    "wof:name":"Bead Avenue",
    "wof:placetype":"venue"
},
  "geometry": {"coordinates":[-93.226174,44.08571],"type":"Point"}
}