{
  "type": "Feature",
  "properties": {
    "iso:country":"US",
    "sg:address":"150 Bissen St",
    "sg:city":"Caledonia",
    "sg:classifiers":[
        {
            "category":"Freight",
            "type":"Transportation"
        }
    ],
    "sg:phone":"+1 507 725 2938",
    "sg:postcode":"55921",
    "sg:province":"MN",
    "sg:tags":[
        "trucking"
    ],
    "wof:name":"Comstock Trucking",
    "wof:placetype":"venue"
},
  "geometry": {"coordinates":[-91.502472,43.628777],"type":"Point"}
}