{
  "type": "Feature",
  "properties": {
    "iso:country":"US",
    "sg:address":"255 W Robie St",
    "sg:city":"Saint Paul",
    "sg:classifiers":[
        {
            "category":"Building & Trades",
            "subcategory":"Construction",
            "type":"Services"
        }
    ],
    "sg:phone":"+1 612 384 6869",
    "sg:postcode":"55107",
    "sg:province":"MN",
    "sg:tags":[
        "home",
        "repair"
    ],
    "wof:name":"Joseph Huncha",
    "wof:placetype":"venue"
},
  "geometry": {"coordinates":[-93.09554,44.930525],"type":"Point"}
}