{
  "type": "Feature",
  "properties": {
    "iso:country":"US",
    "sg:address":"1107 Hazeltine Blvd",
    "sg:city":"Chaska",
    "sg:classifiers":[
        {
            "category":"Manufacturing",
            "subcategory":"Printing",
            "type":"Manufacturing & Wholesale Goods"
        }
    ],
    "sg:phone":"+1 952 448 8816",
    "sg:postcode":"55318",
    "sg:province":"MN",
    "sg:tags":[
        "magazine",
        "only",
        "periodical",
        "publishing"
    ],
    "wof:name":"Minnesota Insurance Magazine",
    "wof:placetype":"venue"
},
  "geometry": {"coordinates":[-93.600819,44.835539],"type":"Point"}
}