{
  "type": "Feature",
  "properties": {
    "iso:country":"US",
    "sg:address":"12954 8th Ave N",
    "sg:city":"Zimmerman",
    "sg:classifiers":[
        {
            "category":"Professional",
            "subcategory":"Computer Services",
            "type":"Services"
        }
    ],
    "sg:phone":"+1 763 856 0895",
    "sg:postcode":"55398",
    "sg:province":"MN",
    "sg:tags":[
        "programming"
    ],
    "wof:name":"Northern Data Solutions",
    "wof:placetype":"venue"
},
  "geometry": {"coordinates":[-93.59673100000001,45.449495],"type":"Point"}
}