{
  "type": "Feature",
  "properties": {
    "iso:country":"US",
    "sg:address":"11431 Gladiola St NW",
    "sg:city":"Minneapolis",
    "sg:classifiers":[
        {
            "category":"Building & Trades",
            "subcategory":"Construction",
            "type":"Services"
        }
    ],
    "sg:phone":"+1 612 991 2411",
    "sg:postcode":"55433",
    "sg:province":"MN",
    "sg:tags":[
        "excavation",
        "contractor"
    ],
    "wof:name":"Emmans Inc",
    "wof:placetype":"venue"
},
  "geometry": {"coordinates":[-93.341857,45.177666],"type":"Point"}
}