{
  "type": "Feature",
  "properties": {
    "iso:country":"US",
    "sg:address":"130 Lake Street West",
    "sg:city":"Wayzata",
    "sg:classifiers":[
        {
            "category":"Professional",
            "subcategory":"Computer Services",
            "type":"Services"
        }
    ],
    "sg:phone":"+1 612 326 5322",
    "sg:postcode":"55391",
    "sg:province":"MN",
    "sg:tags":[
        "1",
        "dollar",
        "donate",
        "charity",
        "new",
        "technology",
        "application",
        "start-up",
        "global",
        "usa",
        "movement",
        "one",
        "money",
        "one-dollar",
        "donate-one"
    ],
    "sg:website":"http://www.1dollarclub.org",
    "wof:name":"1DollarClub.org",
    "wof:placetype":"venue"
},
  "geometry": {"coordinates":[-93.525452,44.970974],"type":"Point"}
}