{
  "type": "Feature",
  "properties": {
    "addr:full":"11600 95th Ave N Osseo MN 55369",
    "addr:housenumber":"11600",
    "addr:postcode":"55369",
    "addr:street":"95Th Ave N",
    "iso:country":"US",
    "sg:address":"11600 95th Ave N",
    "sg:city":"Osseo",
    "sg:classifiers":[
        {
            "category":"Manufacturing",
            "subcategory":"Printing",
            "type":"Manufacturing & Wholesale Goods"
        }
    ],
    "sg:phone":"+1 763 424 6621",
    "sg:postcode":"55369",
    "sg:province":"MN",
    "sg:tags":[
        "commercial",
        "mfg"
    ],
    "wof:name":"Northland Litho Services",
    "wof:placetype":"venue"
},
  "geometry": {"coordinates":[-93.426716,45.127237],"type":"Point"}
}