{
  "type": "Feature",
  "properties": {
    "iso:country":"US",
    "sg:address":"106 Bloomer St E",
    "sg:city":"Morristown",
    "sg:classifiers":[
        {
            "category":"Autos & Motor Vehicles",
            "subcategory":"Recreational Vehicle Sales",
            "type":"Retail Goods"
        }
    ],
    "sg:phone":"+1 507 685 4236",
    "sg:postcode":"55052",
    "sg:province":"MN",
    "sg:tags":[
        "canopy",
        "shell",
        "truck",
        "cap"
    ],
    "wof:name":"Leppert's Camper Supply",
    "wof:placetype":"venue"
},
  "geometry": {"coordinates":[-93.44300800000001,44.228489],"type":"Point"}
}