{
  "type": "Feature",
  "properties": {
    "addr:full":"5124 132nd St SW Pillager MN 56473",
    "addr:housenumber":"5124",
    "addr:postcode":"56473",
    "addr:street":"132Nd St Sw",
    "iso:country":"US",
    "sg:address":"5124 132nd St SW",
    "sg:city":"Pillager",
    "sg:classifiers":[
        {
            "category":"Farming",
            "subcategory":"Livestock Farm",
            "type":"Manufacturing & Wholesale Goods"
        }
    ],
    "sg:phone":"+1 218 746 3701",
    "sg:postcode":"56473",
    "sg:province":"MN",
    "sg:tags":[
        "beef",
        "feedlot",
        "cattle"
    ],
    "wof:name":"J Carlson",
    "wof:placetype":"venue"
},
  "geometry": {"coordinates":[-94.547881,46.325984],"type":"Point"}
}