{
  "type": "Feature",
  "properties": {
    "addr:full":"9492 Magnolia Way N Osseo MN 55369",
    "addr:housenumber":"9492",
    "addr:postcode":"55369",
    "addr:street":"Magnolia Way N",
    "iso:country":"US",
    "sg:address":"9492 Magnolia Way N",
    "sg:city":"Osseo",
    "sg:classifiers":[
        {
            "category":"Cinema",
            "subcategory":"Movie Rental",
            "type":"Entertainment"
        }
    ],
    "sg:phone":"+1 763 370 3239",
    "sg:postcode":"55369",
    "sg:province":"MN",
    "sg:tags":[
        "leasing",
        "video",
        "disc",
        "tape"
    ],
    "wof:name":"Betsy's Dreamworks",
    "wof:placetype":"venue"
},
  "geometry": {"coordinates":[-93.439167,45.126297],"type":"Point"}
}