{
  "type": "Feature",
  "properties": {
    "addr:full":"9133 Co Rd 16 SE Delano MN 55328",
    "addr:housenumber":"9133;16",
    "addr:postcode":"55328",
    "addr:street":"Co Rd;Se Delano",
    "iso:country":"US",
    "sg:address":"9133 Co Rd 16 SE",
    "sg:city":"Delano",
    "sg:classifiers":[
        {
            "category":"Building & Trades",
            "subcategory":"Landscaping Services",
            "type":"Services"
        }
    ],
    "sg:phone":"+1 612 369 1006",
    "sg:postcode":"55328",
    "sg:province":"MN",
    "sg:tags":[
        "lawn",
        "maintenance",
        "grounds"
    ],
    "wof:name":"Pro Advantage Lawn & Landscape",
    "wof:placetype":"venue"
},
  "geometry": {"coordinates":[-93.801177,45.019992],"type":"Point"}
}