{
  "type": "Feature",
  "properties": {
    "iso:country":"US",
    "sg:address":"521 US Hwy 2",
    "sg:city":"Cohasset",
    "sg:classifiers":[
        {
            "category":"Freight",
            "type":"Transportation"
        }
    ],
    "sg:phone":"+1 218 328 6544",
    "sg:postcode":"55721",
    "sg:province":"MN",
    "sg:tags":[
        "trucking"
    ],
    "wof:name":"Smithway Motor Xpress Inc",
    "wof:placetype":"venue"
},
  "geometry": {"coordinates":[-93.62509,47.264919],"type":"Point"}
}