{
  "type": "Feature",
  "properties": {
    "iso:country":"US",
    "sg:address":"915 Lakewood Hills Rd N",
    "sg:city":"Saint Paul",
    "sg:classifiers":[
        {
            "category":"Professional",
            "subcategory":"Secretarial Services",
            "type":"Services"
        }
    ],
    "sg:phone":"+1 651 405 1177",
    "sg:postcode":"55123",
    "sg:province":"MN",
    "sg:tags":[
        "reporting"
    ],
    "wof:name":"Hanlon Court Reporting",
    "wof:placetype":"venue"
},
  "geometry": {"coordinates":[-93.13327,44.791205],"type":"Point"}
}