{
  "type": "Feature",
  "properties": {
    "iso:country":"US",
    "sg:address":"130 W 1st St",
    "sg:city":"Duluth",
    "sg:classifiers":[
        {
            "category":"Manufacturing",
            "subcategory":"Apparel",
            "type":"Manufacturing & Wholesale Goods"
        }
    ],
    "sg:phone":"+1 218 727 5054",
    "sg:postcode":"55802",
    "sg:province":"MN",
    "sg:tags":[
        "window",
        "treatment",
        "mfg"
    ],
    "wof:name":"Belanger Interior Design",
    "wof:placetype":"venue"
},
  "geometry": {"coordinates":[-92.10140800000001,46.785955],"type":"Point"}
}