{
  "type": "Feature",
  "properties": {
    "addr:full":"4059 Chicago Ave S Minneapolis MN 55407",
    "addr:housenumber":"4059",
    "addr:postcode":"55407",
    "addr:street":"Chicago Ave S",
    "iso:country":"US",
    "sg:address":"4059 Chicago Ave S",
    "sg:city":"Minneapolis",
    "sg:classifiers":[
        {
            "category":"Personal",
            "subcategory":"Beauty Salon",
            "type":"Services"
        }
    ],
    "sg:phone":"+1 612 821 9085",
    "sg:postcode":"55407",
    "sg:province":"MN",
    "sg:tags":[
        "shop"
    ],
    "wof:name":"K Simone Salon",
    "wof:placetype":"venue"
},
  "geometry": {"coordinates":[-93.262416,44.929812],"type":"Point"}
}