{
  "type": "Feature",
  "properties": {
    "iso:country":"US",
    "sg:address":"28965 Harry Ave",
    "sg:city":"Randolph",
    "sg:phone":"+1 507 263 2177",
    "sg:postcode":"55065",
    "sg:province":"MN",
    "sg:tags":[
        "farm",
        "corn"
    ],
    "wof:name":"Edward Gergen",
    "wof:placetype":"venue"
},
  "geometry": {"coordinates":[-92.93924,44.53241],"type":"Point"}
}