{
  "type": "Feature",
  "properties": {
    "iso:country":"US",
    "sg:address":"50 Teton Ln",
    "sg:city":"Mankato",
    "sg:classifiers":[
        {
            "category":"Social Services",
            "subcategory":"Adult Care",
            "type":"Services"
        }
    ],
    "sg:phone":"+1 507 388 6354",
    "sg:postcode":"56001",
    "sg:province":"MN",
    "sg:tags":[
        "residential",
        "aged",
        "homes-institutional"
    ],
    "wof:name":"Realife Cooperative Of Mankato Inc",
    "wof:placetype":"venue"
},
  "geometry": {"coordinates":[-93.960922,44.170933],"type":"Point"}
}