{
  "type": "Feature",
  "properties": {
    "iso:country":"US",
    "sg:address":"11337 Flintwood St NW",
    "sg:city":"Coon Rapids",
    "sg:classifiers":[
        {
            "category":"Social Services",
            "subcategory":"Child Care",
            "type":"Services"
        }
    ],
    "sg:phone":"+1 763 780 5111",
    "sg:postcode":"55448",
    "sg:province":"MN",
    "wof:name":"Salem Montessori School",
    "wof:placetype":"venue"
},
  "geometry": {"coordinates":[-93.274747,45.176445],"type":"Point"}
}