{
  "type": "Feature",
  "properties": {
    "iso:country":"US",
    "sg:address":"110 1st St S",
    "sg:city":"Montgomery",
    "sg:classifiers":[
        {
            "category":"Professional",
            "type":"Services"
        }
    ],
    "sg:phone":"+1 507 364 7417",
    "sg:postcode":"56069",
    "sg:province":"MN",
    "sg:tags":[
        "establishment"
    ],
    "wof:name":"Potential Unlimited Montgomery",
    "wof:placetype":"venue"
},
  "geometry": {"coordinates":[-93.581205,44.438692],"type":"Point"}
}