{
  "type": "Feature",
  "properties": {
    "iso:country":"US",
    "sg:address":"11345 Robinson Dr NW",
    "sg:city":"Minneapolis",
    "sg:classifiers":[
        {
            "category":"Education",
            "subcategory":"School",
            "type":"Public Place"
        }
    ],
    "sg:phone":"+1 763 757 5231",
    "sg:postcode":"55433",
    "sg:province":"MN",
    "sg:tags":[
        "high",
        "middle",
        "elementary"
    ],
    "wof:name":"Northwest Passage High School",
    "wof:placetype":"venue"
},
  "geometry": {"coordinates":[-93.30868599999999,45.177381],"type":"Point"}
}