{
  "type": "Feature",
  "properties": {
    "addr:full":"373 4th Ave S St Cloud MN 56301",
    "addr:housenumber":"373",
    "addr:postcode":"56301",
    "addr:street":"4Th Ave S",
    "iso:country":"US",
    "sg:address":"373 4th Ave S",
    "sg:city":"St Cloud",
    "sg:classifiers":[
        {
            "category":"Organizations",
            "subcategory":"Religious Organization",
            "type":"Services"
        }
    ],
    "sg:phone":"+1 320 230 4393",
    "sg:postcode":"56301",
    "sg:province":"MN",
    "sg:tags":[
        "church"
    ],
    "wof:name":"Nu Way Missionary Bapt Church",
    "wof:placetype":"venue"
},
  "geometry": {"coordinates":[-94.15331999999999,45.556506],"type":"Point"}
}