{
  "type": "Feature",
  "properties": {
    "addr:full":"1800 Mainstreet Hopkins MN 55343",
    "addr:housenumber":"1800",
    "addr:postcode":"55343",
    "addr:street":"Mainstreet",
    "iso:country":"US",
    "sg:address":"1800 Mainstreet",
    "sg:city":"Hopkins",
    "sg:classifiers":[
        {
            "category":"Ice Cream",
            "type":"Food & Drink"
        }
    ],
    "sg:menulink":"http://www.allmenus.com/mn/hopkins/168293-dairy-queen/menu/",
    "sg:phone":"+1 952 930 0202",
    "sg:postcode":"55343",
    "sg:province":"MN",
    "sg:tags":[
        "burger",
        "american"
    ],
    "wof:name":"Dairy Queen",
    "wof:placetype":"venue"
},
  "geometry": {"coordinates":[-93.423205,44.924008],"type":"Point"}
}