{
  "type": "Feature",
  "properties": {
    "addr:full":"5229 2nd Ave S Minneapolis MN 55419",
    "addr:housenumber":"5229",
    "addr:postcode":"55419",
    "addr:street":"2Nd Ave S",
    "iso:country":"US",
    "sg:address":"5229 2nd Ave S",
    "sg:city":"Minneapolis",
    "sg:classifiers":[
        {
            "category":"Professional",
            "subcategory":"Business Services",
            "type":"Services"
        }
    ],
    "sg:phone":"+1 612 827 6182",
    "sg:postcode":"55419",
    "sg:province":"MN",
    "wof:name":"Dpf Enterprises",
    "wof:placetype":"venue"
},
  "geometry": {"coordinates":[-93.27413900000001,44.907515],"type":"Point"}
}