{
  "type": "Feature",
  "properties": {
    "addr:full":"24700 Wiltsey Ln Excelsior MN 55331",
    "addr:housenumber":"24700",
    "addr:postcode":"55331",
    "addr:street":"Wiltsey Ln",
    "iso:country":"US",
    "sg:address":"24700 Wiltsey Ln",
    "sg:city":"Excelsior",
    "sg:classifiers":[
        {
            "category":"Arts & Performance",
            "subcategory":"Theater",
            "type":"Entertainment"
        }
    ],
    "sg:phone":"+1 952 470 6690",
    "sg:postcode":"55331",
    "sg:province":"MN",
    "sg:tags":[
        "bureau"
    ],
    "wof:name":"AFFT Entertainment",
    "wof:placetype":"venue"
},
  "geometry": {"coordinates":[-93.593811,44.891912],"type":"Point"}
}