{
  "type": "Feature",
  "properties": {
    "addr:full":"1563 Ashland Ave St Paul MN 55104",
    "addr:housenumber":"1563",
    "addr:postcode":"55104",
    "addr:street":"Ashland Ave",
    "iso:country":"US",
    "sg:address":"1563 Ashland Ave",
    "sg:city":"St Paul",
    "sg:classifiers":[
        {
            "category":"Professional",
            "subcategory":"Computer Services",
            "type":"Services"
        }
    ],
    "sg:phone":"+1 651 647 9287",
    "sg:postcode":"55104",
    "sg:province":"MN",
    "sg:tags":[
        "datum"
    ],
    "wof:name":"Hennessy Interactive",
    "wof:placetype":"venue"
},
  "geometry": {"coordinates":[-93.165668,44.944027],"type":"Point"}
}