{
  "type": "Feature",
  "properties": {
    "addr:full":"260 Broadway Ave S Cokato MN 55321",
    "addr:housenumber":"260",
    "addr:postcode":"55321",
    "addr:street":"Broadway Ave S Cokato",
    "iso:country":"US",
    "sg:address":"260 Broadway Ave S",
    "sg:city":"Cokato",
    "sg:classifiers":[
        {
            "category":"Wholesale",
            "subcategory":"Meat",
            "type":"Manufacturing & Wholesale Goods"
        }
    ],
    "sg:phone":"+1 320 286 2713",
    "sg:postcode":"55321",
    "sg:province":"MN",
    "sg:tags":[
        "butchering"
    ],
    "wof:name":"White Front Locker Svc",
    "wof:placetype":"venue"
},
  "geometry": {"coordinates":[-94.190184,45.076904],"type":"Point"}
}