{
  "type": "Feature",
  "properties": {
    "addr:full":"45427 640th Ave Fairfax MN 55332",
    "addr:housenumber":"45427",
    "addr:postcode":"55332",
    "addr:street":"640Th Ave",
    "iso:country":"US",
    "sg:address":"45427 640th Ave",
    "sg:city":"Fairfax",
    "sg:phone":"+1 507 426 7676",
    "sg:postcode":"55332",
    "sg:province":"MN",
    "sg:tags":[
        "farm",
        "grain",
        "cash"
    ],
    "wof:name":"Ralph and Rodney Schefus",
    "wof:placetype":"venue"
},
  "geometry": {"coordinates":[-94.7569,44.514116],"type":"Point"}
}