{
  "type": "Feature",
  "properties": {
    "addr:full":"111 S State St Waseca MN 56093",
    "addr:housenumber":"111",
    "addr:postcode":"56093",
    "addr:street":"S State St",
    "iso:country":"US",
    "sg:address":"111 S State St",
    "sg:city":"Waseca",
    "sg:classifiers":[
        {
            "category":"Professional",
            "subcategory":"Business Services",
            "type":"Services"
        }
    ],
    "sg:phone":"+1 507 833 9101",
    "sg:postcode":"56093",
    "sg:province":"MN",
    "sg:tags":[
        "information",
        "bureau",
        "convention"
    ],
    "wof:name":"Waseca Area Tourism & Visitors",
    "wof:placetype":"venue"
},
  "geometry": {"coordinates":[-93.50735,44.077498],"type":"Point"}
}