{
  "type": "Feature",
  "properties": {
    "addr:full":"111 East Ave Saint Paul MN 55115",
    "addr:housenumber":"111",
    "addr:postcode":"55115",
    "addr:street":"East Ave",
    "iso:country":"US",
    "sg:address":"111 East Ave",
    "sg:city":"Saint Paul",
    "sg:classifiers":[
        {
            "category":"Social Services",
            "subcategory":"Adult Care",
            "type":"Services"
        }
    ],
    "sg:phone":"+1 651 653 0645",
    "sg:postcode":"55115",
    "sg:province":"MN",
    "sg:tags":[
        "residential"
    ],
    "wof:name":"New Perspective of Minnesota",
    "wof:placetype":"venue"
},
  "geometry": {"coordinates":[-92.949943,45.058491],"type":"Point"}
}