{
  "type": "Feature",
  "properties": {
    "addr:full":"800 Riverside Dr SE Saint Cloud MN 56304",
    "addr:housenumber":"800",
    "addr:postcode":"56304",
    "addr:street":"Riverside Dr Se",
    "iso:country":"US",
    "sg:address":"800 Riverside Dr SE",
    "sg:city":"Saint Cloud",
    "sg:classifiers":[
        {
            "category":"Farming",
            "subcategory":"Farm",
            "type":"Manufacturing & Wholesale Goods"
        }
    ],
    "sg:phone":"+1 320 252 0912",
    "sg:postcode":"56304",
    "sg:province":"MN",
    "sg:tags":[
        "crop",
        "general"
    ],
    "wof:name":"Didier Ltd Partnership",
    "wof:placetype":"venue"
},
  "geometry": {"coordinates":[-94.146433,45.558483],"type":"Point"}
}