{
  "type": "Feature",
  "properties": {
    "iso:country":"US",
    "sg:address":"15497 State Hwy 371",
    "sg:city":"Brainerd",
    "sg:classifiers":[
        {
            "category":"Home & Garden",
            "subcategory":"Garden Supply",
            "type":"Retail Goods"
        }
    ],
    "sg:phone":"+1 218 829 6419",
    "sg:postcode":"56401",
    "sg:province":"MN",
    "wof:name":"Moonlite Nursery",
    "wof:placetype":"venue"
},
  "geometry": {"coordinates":[-94.247488,46.374901],"type":"Point"}
}