{
  "type": "Feature",
  "properties": {
    "addr:full":"6365 Jackson St NE Minneapolis MN 55432",
    "addr:housenumber":"6365",
    "addr:postcode":"55432",
    "addr:street":"Jackson St Ne",
    "iso:country":"US",
    "sg:address":"6365 Jackson St NE",
    "sg:city":"Minneapolis",
    "sg:classifiers":[
        {
            "category":"Organizations",
            "subcategory":"Membership Organization",
            "type":"Services"
        }
    ],
    "sg:phone":"+1 763 574 7400",
    "sg:postcode":"55432",
    "sg:province":"MN",
    "sg:tags":[
        "environmental",
        "ecological",
        "conservation"
    ],
    "wof:name":"Windstar Minnesota Connection",
    "wof:placetype":"venue"
},
  "geometry": {"coordinates":[-93.250488,45.083829],"type":"Point"}
}