{
  "type": "Feature",
  "properties": {
    "addr:full":"5368 German Lake Rd NW Isanti MN 55040",
    "addr:housenumber":"5368",
    "addr:postcode":"55040",
    "addr:street":"German Lake Rd Nw Isanti",
    "iso:country":"US",
    "sg:address":"5368 German Lake Rd NW",
    "sg:city":"Isanti",
    "sg:classifiers":[
        {
            "category":"Building & Trades",
            "subcategory":"Electrical",
            "type":"Services"
        }
    ],
    "sg:phone":"+1 763 444 6789",
    "sg:postcode":"55040",
    "sg:province":"MN",
    "sg:tags":[
        "electrician",
        "contractor"
    ],
    "wof:name":"Boyum Electric",
    "wof:placetype":"venue"
},
  "geometry": {"coordinates":[-93.403274,45.467752],"type":"Point"}
}