{
  "type": "Feature",
  "properties": {
    "iso:country":"US",
    "sg:address":"1802 E 2nd St",
    "sg:city":"Duluth",
    "sg:classifiers":[
        {
            "category":"Real Estate",
            "subcategory":"Real Estate Operator",
            "type":"Services"
        }
    ],
    "sg:phone":"+1 218 724 2021",
    "sg:postcode":"55812",
    "sg:province":"MN",
    "sg:tags":[
        "apartment"
    ],
    "wof:name":"Endion School Apartments",
    "wof:placetype":"venue"
},
  "geometry": {"coordinates":[-92.076736,46.806383],"type":"Point"}
}