{
  "type": "Feature",
  "properties": {
    "addr:full":"8366 Robert St Babbitt MN 55706",
    "addr:housenumber":"8366",
    "addr:postcode":"55706",
    "addr:street":"Robert St",
    "iso:country":"US",
    "sg:address":"8366 Robert St",
    "sg:city":"Babbitt",
    "sg:classifiers":[
        {
            "category":"Personal",
            "subcategory":"Beauty Salon",
            "type":"Services"
        }
    ],
    "sg:phone":"+1 218 827 2673",
    "sg:postcode":"55706",
    "sg:province":"MN",
    "wof:name":"Jeannettes Beauty in the Pines",
    "wof:placetype":"venue"
},
  "geometry": {"coordinates":[-91.963694,47.718602],"type":"Point"}
}