{
  "type": "Feature",
  "properties": {
    "iso:country":"US",
    "sg:address":"101 Minnesota Ave S",
    "sg:city":"Aitkin",
    "sg:classifiers":[
        {
            "category":"Building & Trades",
            "subcategory":"Landscaping Services",
            "type":"Services"
        }
    ],
    "sg:phone":"+1 218 927 3481",
    "sg:postcode":"56431",
    "sg:province":"MN",
    "sg:tags":[
        "lawn",
        "maintenance",
        "grounds"
    ],
    "wof:name":"Mike's Lawn Svc",
    "wof:placetype":"venue"
},
  "geometry": {"coordinates":[-93.70725400000001,46.529236],"type":"Point"}
}