{
  "type": "Feature",
  "properties": {
    "addr:full":"7341 Symphony St NE Minneapolis MN 55432",
    "addr:housenumber":"7341",
    "addr:postcode":"55432",
    "addr:street":"Symphony St Ne",
    "iso:country":"US",
    "sg:address":"7341 Symphony St NE",
    "sg:city":"Minneapolis",
    "sg:classifiers":[
        {
            "category":"Social Services",
            "subcategory":"Child Care",
            "type":"Services"
        }
    ],
    "sg:phone":"+1 763 784 8094",
    "sg:postcode":"55432",
    "sg:province":"MN",
    "sg:tags":[
        "daycare",
        "provider"
    ],
    "wof:name":"Mathisen Marguerite",
    "wof:placetype":"venue"
},
  "geometry": {"coordinates":[-93.26185700000001,45.100704],"type":"Point"}
}