{
  "type": "Feature",
  "properties": {
    "iso:country":"US",
    "sg:address":"1986 Mathias Rd",
    "sg:city":"Shakopee",
    "sg:classifiers":[
        {
            "category":"Professional",
            "subcategory":"Business Services",
            "type":"Services"
        }
    ],
    "sg:phone":"+1 952 403 9624",
    "sg:postcode":"55379",
    "sg:province":"MN",
    "wof:name":"Rudra Enterprises LLC",
    "wof:placetype":"venue"
},
  "geometry": {"coordinates":[-93.493376,44.76911],"type":"Point"}
}