{
  "type": "Feature",
  "properties": {
    "addr:full":"13632 Hwy 238 Little Falls MN 56345",
    "addr:housenumber":"13632",
    "addr:postcode":"56345",
    "addr:street":"Hwy 238",
    "iso:country":"US",
    "sg:address":"13632 Hwy 238",
    "sg:city":"Little Falls",
    "sg:classifiers":[
        {
            "category":"Farming",
            "subcategory":"Poultry Farm",
            "type":"Manufacturing & Wholesale Goods"
        }
    ],
    "sg:phone":"+1 320 632 8091",
    "sg:postcode":"56345",
    "sg:province":"MN",
    "sg:tags":[
        "hatchery"
    ],
    "wof:name":"James Wielinski",
    "wof:placetype":"venue"
},
  "geometry": {"coordinates":[-94.410636,45.947897],"type":"Point"}
}