{
  "type": "Feature",
  "properties": {
    "addr:full":"8100 82nd Ave N Minneapolis MN 55445",
    "addr:housenumber":"8100",
    "addr:postcode":"55445",
    "addr:street":"82Nd Ave N",
    "iso:country":"US",
    "sg:address":"8100 82nd Ave N",
    "sg:city":"Minneapolis",
    "sg:classifiers":[
        {
            "category":"Social Services",
            "subcategory":"Child Care",
            "type":"Services"
        }
    ],
    "sg:phone":"+1 763 425 4080",
    "sg:postcode":"55445",
    "sg:province":"MN",
    "sg:tags":[
        "daycare",
        "provider"
    ],
    "wof:name":"Mary Sodern",
    "wof:placetype":"venue"
},
  "geometry": {"coordinates":[-93.384666,45.103166],"type":"Point"}
}