{
  "type": "Feature",
  "properties": {
    "iso:country":"US",
    "sg:address":"110 Vermillion St",
    "sg:city":"Hastings",
    "sg:classifiers":[
        {
            "category":"Shopping",
            "subcategory":"Gifts & Souvenirs",
            "type":"Retail Goods"
        }
    ],
    "sg:phone":"+1 651 437 1444",
    "sg:postcode":"55033",
    "sg:province":"MN",
    "sg:tags":[
        "shop"
    ],
    "wof:name":"Meloy Park Florist",
    "wof:placetype":"venue"
},
  "geometry": {"coordinates":[-92.85258899999999,44.745038],"type":"Point"}
}