{
  "type": "Feature",
  "properties": {
    "addr:full":"15302 Buzzle Rd NW Shevlin MN 56676",
    "addr:housenumber":"15302",
    "addr:postcode":"56676",
    "addr:street":"Buzzle Rd Nw Shevlin",
    "iso:country":"US",
    "sg:address":"15302 Buzzle Rd NW",
    "sg:city":"Shevlin",
    "sg:classifiers":[
        {
            "category":"Farming",
            "subcategory":"Dairy Farm",
            "type":"Manufacturing & Wholesale Goods"
        }
    ],
    "sg:phone":"+1 218 243 2776",
    "sg:postcode":"56676",
    "sg:province":"MN",
    "wof:name":"Tim Lewis",
    "wof:placetype":"venue"
},
  "geometry": {"coordinates":[-95.07750799999999,47.616067],"type":"Point"}
}