{
  "type": "Feature",
  "properties": {
    "addr:full":"5556 1st Ave S Minneapolis MN 55419",
    "addr:housenumber":"5556",
    "addr:postcode":"55419",
    "addr:street":"1St Ave S",
    "iso:country":"US",
    "sg:address":"5556 1st Ave S",
    "sg:city":"Minneapolis",
    "sg:classifiers":[
        {
            "category":"Retail",
            "subcategory":"Portrait Studio",
            "type":"Services"
        }
    ],
    "sg:phone":"+1 612 929 6339",
    "sg:postcode":"55419",
    "sg:province":"MN",
    "sg:tags":[
        "photographer",
        "wedding"
    ],
    "wof:name":"Image Werks",
    "wof:placetype":"venue"
},
  "geometry": {"coordinates":[-93.276869,44.903203],"type":"Point"}
}