{
  "type": "Feature",
  "properties": {
    "addr:full":"108 4th St NW Faribault MN 55021",
    "addr:housenumber":"108",
    "addr:postcode":"55021",
    "addr:street":"4Th St Nw",
    "iso:country":"US",
    "sg:address":"108 4th St NW",
    "sg:city":"Faribault",
    "sg:classifiers":[
        {
            "category":"Restaurant",
            "type":"Food & Drink"
        }
    ],
    "sg:phone":"+1 507 332 6701",
    "sg:postcode":"55021",
    "sg:province":"MN",
    "sg:tags":[
        "eating"
    ],
    "wof:name":"Basilleo's Pizza Restaurant",
    "wof:placetype":"venue"
},
  "geometry": {"coordinates":[-93.270028,44.294827],"type":"Point"}
}