{
  "type": "Feature",
  "properties": {
    "iso:country":"US",
    "sg:address":"1745 Hale Ave N",
    "sg:city":"Saint Paul",
    "sg:classifiers":[
        {
            "category":"Social Services",
            "subcategory":"Child Care",
            "type":"Services"
        }
    ],
    "sg:phone":"+1 651 735 6409",
    "sg:postcode":"55128",
    "sg:province":"MN",
    "sg:tags":[
        "day"
    ],
    "wof:name":"Marys Little Lambs",
    "wof:placetype":"venue"
},
  "geometry": {"coordinates":[-92.96170499999999,44.974527],"type":"Point"}
}