{
  "type": "Feature",
  "properties": {
    "addr:full":"4241 Nancy Pl Saint Paul MN 55126",
    "addr:housenumber":"4241",
    "addr:postcode":"55126",
    "addr:street":"Nancy Pl",
    "iso:country":"US",
    "sg:address":"4241 Nancy Pl",
    "sg:city":"Saint Paul",
    "sg:classifiers":[
        {
            "category":"Professional",
            "subcategory":"Business Services",
            "type":"Services"
        }
    ],
    "sg:phone":"+1 651 481 0780",
    "sg:postcode":"55126",
    "sg:province":"MN",
    "sg:tags":[
        "translation"
    ],
    "wof:name":"David Shahin",
    "wof:placetype":"venue"
},
  "geometry": {"coordinates":[-93.139279,45.067665],"type":"Point"}
}