{
  "type": "Feature",
  "properties": {
    "iso:country":"US",
    "sg:address":"765 Old Crystal Bay Rd N",
    "sg:city":"Long Lake",
    "sg:classifiers":[
        {
            "category":"Education",
            "subcategory":"School",
            "type":"Public Place"
        }
    ],
    "sg:phone":"+1 952 449 8480",
    "sg:postcode":"55356",
    "sg:province":"MN",
    "wof:name":"Schumann Elementary School",
    "wof:placetype":"venue"
},
  "geometry": {"coordinates":[-93.594236,44.99718],"type":"Point"}
}