{
  "type": "Feature",
  "properties": {
    "addr:full":"1908 Rice St St Paul MN 55117",
    "addr:housenumber":"1908",
    "addr:postcode":"55117",
    "addr:street":"Rice St",
    "iso:country":"US",
    "sg:address":"1908 Rice St",
    "sg:city":"St Paul",
    "sg:classifiers":[
        {
            "category":"Autos & Motor Vehicles",
            "subcategory":"Automobile Sales",
            "type":"Retail Goods"
        }
    ],
    "sg:phone":"+1 651 487 1000",
    "sg:postcode":"55117",
    "sg:province":"MN",
    "sg:tags":[
        "car",
        "dealer"
    ],
    "wof:name":"Car Hop",
    "wof:placetype":"venue"
},
  "geometry": {"coordinates":[-93.105808,44.997593],"type":"Point"}
}