{
  "type": "Feature",
  "properties": {
    "iso:country":"US",
    "sg:address":"4696 Trading Post Trl S",
    "sg:city":"Afton",
    "sg:classifiers":[
        {
            "category":"Professional",
            "type":"Services"
        }
    ],
    "sg:phone":"+1 651 436 1041",
    "sg:postcode":"55001",
    "sg:province":"MN",
    "wof:name":"Clnmn Inc",
    "wof:placetype":"venue"
},
  "geometry": {"coordinates":[-92.811812,44.880515],"type":"Point"}
}