{
  "type": "Feature",
  "properties": {
    "iso:country":"US",
    "sg:address":"701 4th Ave S",
    "sg:city":"Minneapolis",
    "sg:classifiers":[
        {
            "category":"Professional",
            "subcategory":"Employment Agencies",
            "type":"Services"
        }
    ],
    "sg:phone":"+1 612 339 6060",
    "sg:postcode":"55415",
    "sg:province":"MN",
    "sg:tags":[
        "consultant",
        "search",
        "executive"
    ],
    "sg:website":"www.rthompassoc.com",
    "wof:name":"Richard Thompson Assoc",
    "wof:placetype":"venue"
},
  "geometry": {"coordinates":[-93.26759199999999,44.973621],"type":"Point"}
}