{
  "type": "Feature",
  "properties": {
    "iso:country":"US",
    "sg:address":"137 Access Way",
    "sg:city":"Spicer",
    "sg:classifiers":[
        {
            "category":"Restaurant",
            "type":"Food & Drink"
        },
        {
            "category":"Ice Cream",
            "type":"Food & Drink"
        }
    ],
    "sg:menulink":"http://www.allmenus.com/mn/spicer/167950-dairy-queen/menu/",
    "sg:phone":"+1 320 796 2010",
    "sg:postcode":"56288",
    "sg:province":"MN",
    "sg:tags":[
        "burger",
        "american",
        "ice",
        "cream"
    ],
    "wof:name":"Dairy Queen",
    "wof:placetype":"venue"
},
  "geometry": {"coordinates":[-94.939443,45.230717],"type":"Point"}
}