{
  "type": "Feature",
  "properties": {
    "addr:full":"321 Church St Marshall MN 56258",
    "addr:housenumber":"321",
    "addr:postcode":"56258",
    "addr:street":"Church St",
    "iso:country":"US",
    "sg:address":"321 Church St",
    "sg:city":"Marshall",
    "sg:classifiers":[
        {
            "category":"Freight",
            "type":"Transportation"
        }
    ],
    "sg:phone":"+1 320 695 2217",
    "sg:postcode":"56258",
    "sg:province":"MN",
    "sg:tags":[
        "trucking"
    ],
    "wof:name":"Thunderbird Transport",
    "wof:placetype":"venue"
},
  "geometry": {"coordinates":[-95.780621,44.447305],"type":"Point"}
}