{
  "type": "Feature",
  "properties": {
    "addr:full":"18267 Italy Ave Lakeville MN 55044",
    "addr:postcode":"18267;55044",
    "addr:street":"Italy Ave",
    "iso:country":"US",
    "sg:address":"18267 Italy Ave",
    "sg:city":"Lakeville",
    "sg:classifiers":[
        {
            "category":"Building & Trades",
            "subcategory":"Construction",
            "type":"Services"
        }
    ],
    "sg:phone":"+1 952 892 6015",
    "sg:postcode":"55044",
    "sg:province":"MN",
    "sg:tags":[
        "contractor"
    ],
    "wof:name":"Bradach Roofing",
    "wof:placetype":"venue"
},
  "geometry": {"coordinates":[-93.264461,44.684564],"type":"Point"}
}