{
  "type": "Feature",
  "properties": {
    "addr:full":"17 7th St W Saint Paul MN 55102",
    "addr:housenumber":"17",
    "addr:postcode":"55102",
    "addr:street":"7Th St W",
    "iso:country":"US",
    "sg:address":"17 7th St W",
    "sg:city":"Saint Paul",
    "sg:classifiers":[
        {
            "category":"Professional",
            "type":"Services"
        }
    ],
    "sg:phone":"+1 651 848 0806",
    "sg:postcode":"55102",
    "sg:province":"MN",
    "wof:name":"Brave New Workshop",
    "wof:placetype":"venue"
},
  "geometry": {"coordinates":[-93.09771499999999,44.947992],"type":"Point"}
}