{
  "type": "Feature",
  "properties": {
    "addr:full":"1000 Lakeshore Dr Moose Lake MN 55767",
    "addr:housenumber":"1000",
    "addr:postcode":"55767",
    "addr:street":"Lakeshore Dr",
    "iso:country":"US",
    "sg:address":"1000 Lakeshore Dr",
    "sg:city":"Moose Lake",
    "sg:classifiers":[
        {
            "category":"Government",
            "subcategory":"Office",
            "type":"Public Place"
        }
    ],
    "sg:phone":"+1 218 485 4411",
    "sg:postcode":"55767",
    "sg:province":"MN",
    "sg:tags":[
        "administration",
        "social",
        "resource",
        "human",
        "income"
    ],
    "wof:name":"Cooperative Vocational Reh",
    "wof:placetype":"venue"
},
  "geometry": {"coordinates":[-92.76186800000001,46.436904],"type":"Point"}
}