{
  "type": "Feature",
  "properties": {
    "iso:country":"US",
    "sg:address":"2510 Timberlea Dr",
    "sg:city":"St Paul",
    "sg:classifiers":[
        {
            "category":"Freight",
            "type":"Transportation"
        }
    ],
    "sg:phone":"+1 651 247 1463",
    "sg:postcode":"55125",
    "sg:province":"MN",
    "sg:tags":[
        "trucking"
    ],
    "wof:name":"Karraz Trucking",
    "wof:placetype":"venue"
},
  "geometry": {"coordinates":[-92.944025,44.91213],"type":"Point"}
}