{
  "type": "Feature",
  "properties": {
    "addr:full":"3065 Centre Pointe Dr Saint Paul MN 55113",
    "addr:housenumber":"3065",
    "addr:postcode":"55113",
    "addr:street":"Centre Pointe Dr",
    "iso:country":"US",
    "sg:address":"3065 Centre Pointe Dr",
    "sg:city":"Saint Paul",
    "sg:classifiers":[
        {
            "category":"Building & Trades",
            "subcategory":"Construction",
            "type":"Services"
        }
    ],
    "sg:phone":"+1 651 638 0500",
    "sg:postcode":"55113",
    "sg:province":"MN",
    "sg:tags":[
        "house",
        "builder",
        "operative"
    ],
    "wof:name":"Rottlund Homes",
    "wof:placetype":"venue"
},
  "geometry": {"coordinates":[-93.189583,45.032517],"type":"Point"}
}