{
  "type": "Feature",
  "properties": {
    "iso:country":"US",
    "sg:address":"1431 E Superior St",
    "sg:city":"Duluth",
    "sg:classifiers":[
        {
            "category":"Retail",
            "subcategory":"Animal Services",
            "type":"Services"
        }
    ],
    "sg:phone":"+1 218 728 0869",
    "sg:postcode":"55805",
    "sg:province":"MN",
    "wof:name":"Designer Dogs",
    "wof:placetype":"venue"
},
  "geometry": {"coordinates":[-92.08076800000001,46.800278],"type":"Point"}
}