{
  "type": "Feature",
  "properties": {
    "iso:country":"US",
    "sg:address":"602 1st St",
    "sg:city":"Princeton",
    "sg:classifiers":[
        {
            "category":"Building & Trades",
            "subcategory":"Construction",
            "type":"Services"
        }
    ],
    "sg:phone":"+1 763 389 2980",
    "sg:postcode":"55371",
    "sg:province":"MN",
    "sg:tags":[
        "general",
        "contractor"
    ],
    "sg:website":"www.howardhomesinc.com",
    "wof:name":"Howard Homes Inc",
    "wof:placetype":"venue"
},
  "geometry": {"coordinates":[-93.582425,45.569806],"type":"Point"}
}