{
  "type": "Feature",
  "properties": {
    "iso:country":"US",
    "sg:address":"1115 Flintwood St",
    "sg:city":"Isanti",
    "sg:classifiers":[
        {
            "category":"Transit Center",
            "subcategory":"Freight",
            "type":"Transportation"
        },
        {
            "category":"Freight",
            "type":"Transportation"
        }
    ],
    "sg:phone":"+1 763 286 5440",
    "sg:postcode":"55040",
    "sg:province":"MN",
    "sg:tags":[
        "local",
        "trucking-motor",
        "trucking"
    ],
    "wof:name":"Schleicher Trucking",
    "wof:placetype":"venue"
},
  "geometry": {"coordinates":[-93.26201500000001,45.481302],"type":"Point"}
}