{
  "type": "Feature",
  "properties": {
    "addr:full":"4601 Excelsior Blvd Minneapolis MN 55416",
    "addr:housenumber":"4601",
    "addr:postcode":"55416",
    "addr:street":"Excelsior Blvd",
    "iso:country":"US",
    "sg:address":"4601 Excelsior Blvd",
    "sg:city":"Minneapolis",
    "sg:classifiers":[
        {
            "category":"Health Services",
            "subcategory":"Health Practitioner",
            "type":"Services"
        }
    ],
    "sg:phone":"+1 952 927 0170",
    "sg:postcode":"55416",
    "sg:province":"MN",
    "wof:name":"Park Psychotherapy & Consultin",
    "wof:placetype":"venue"
},
  "geometry": {"coordinates":[-93.337431,44.934108],"type":"Point"}
}