{
  "type": "Feature",
  "properties": {
    "addr:full":"412 W Main St Adams MN 55909",
    "addr:housenumber":"412",
    "addr:postcode":"55909",
    "addr:street":"W Main St",
    "iso:country":"US",
    "sg:address":"412 W Main St",
    "sg:city":"Adams",
    "sg:classifiers":[
        {
            "category":"Organizations",
            "subcategory":"Religious Organization",
            "type":"Services"
        }
    ],
    "sg:phone":"+1 507 582 3321",
    "sg:postcode":"55909",
    "sg:province":"MN",
    "sg:tags":[
        "church"
    ],
    "wof:name":"Sacred Heart Church",
    "wof:placetype":"venue"
},
  "geometry": {"coordinates":[-92.71979899999999,43.565481],"type":"Point"}
}