{
  "type": "Feature",
  "properties": {
    "addr:full":"5500 Stevens Ave S Minneapolis MN 55419",
    "addr:housenumber":"5500",
    "addr:postcode":"55419",
    "addr:street":"Stevens Ave S",
    "iso:country":"US",
    "sg:address":"5500 Stevens Ave S",
    "sg:city":"Minneapolis",
    "sg:classifiers":[
        {
            "category":"Museum",
            "type":"Entertainment"
        }
    ],
    "sg:phone":"+1 612 821 9045",
    "sg:postcode":"55419",
    "sg:province":"MN",
    "wof:name":"Museum Of Russian Art",
    "wof:placetype":"venue"
},
  "geometry": {"coordinates":[-93.27552799999999,44.901534],"type":"Point"}
}