{
  "type": "Feature",
  "properties": {
    "addr:city":"Minneapolis",
    "addr:full":"5500 Stevens Ave South Minneapolis, Mn 55419-1933",
    "addr:house_number":"5500",
    "addr:housenumber":"5500",
    "addr:phone":"+1 612-821-9045",
    "addr:postcode":"55419-1933",
    "addr:road":"Stevens Ave South",
    "addr:state":"MN",
    "addr:street":"Stevens Ave S",
    "iso:country":"US",
    "sg:address":"5500 Stevens Ave S",
    "sg:city":"Minneapolis",
    "sg:classifiers":[
        {
            "category":"Museum",
            "type":"Entertainment"
        }
    ],
    "sg:phone":"+1 612 821 9045",
    "sg:postcode":"55419",
    "sg:province":"MN",
    "wof:airports":[
        102531131
    ],
    "wof:name":"Museum Of Russian Art",
    "wof:placetype":"venue"
},
  "geometry": {"coordinates":[-93.27588,44.90245],"type":"Point"}
}