{
  "type": "Feature",
  "properties": {
    "addr:full":"4725 Excelsior Blvd Minneapolis MN 55416",
    "addr:housenumber":"4725",
    "addr:postcode":"55416",
    "addr:street":"Excelsior Blvd",
    "iso:country":"US",
    "sg:address":"4725 Excelsior Blvd",
    "sg:city":"Minneapolis",
    "sg:classifiers":[
        {
            "category":"Professional",
            "subcategory":"Accounting & Tax Preparation",
            "type":"Services"
        }
    ],
    "sg:phone":"+1 952 922 7989",
    "sg:postcode":"55416",
    "sg:province":"MN",
    "sg:tags":[
        "accountant"
    ],
    "wof:name":"Francis J Griffin CPA",
    "wof:placetype":"venue"
},
  "geometry": {"coordinates":[-93.338836,44.933643],"type":"Point"}
}