{
  "type": "Feature",
  "properties": {
    "iso:country":"US",
    "sg:address":"1710 Plymouth Ave N # 207",
    "sg:city":"Minneapolis",
    "sg:classifiers":[
        {
            "category":"Building & Trades",
            "subcategory":"Landscaping Services",
            "type":"Services"
        },
        {
            "category":"Social Services",
            "subcategory":"Retirement Home",
            "type":"Services"
        }
    ],
    "sg:phone":"+1 612 522 4038",
    "sg:postcode":"55411",
    "sg:province":"MN",
    "sg:tags":[
        "convalescent",
        "aged",
        "nursing",
        "homes-institutional"
    ],
    "wof:name":"Rainbow Terrace",
    "wof:placetype":"venue"
},
  "geometry": {"coordinates":[-93.302074,44.991508],"type":"Point"}
}