{
  "type": "Feature",
  "properties": {
    "iso:country":"US",
    "sg:address":"2648 W Broadway Ave",
    "sg:city":"Minneapolis",
    "sg:classifiers":[
        {
            "category":"Organizations",
            "subcategory":"Professional Association",
            "type":"Services"
        }
    ],
    "sg:phone":"+1 612 302 9048",
    "sg:postcode":"55411",
    "sg:province":"MN",
    "wof:name":"Lao PTA",
    "wof:placetype":"venue"
},
  "geometry": {"coordinates":[-93.314138,45.008534],"type":"Point"}
}