{
  "type": "Feature",
  "properties": {
    "addr:full":"9000 382nd Ave Blue Earth MN 56013",
    "addr:housenumber":"9000",
    "addr:postcode":"56013",
    "addr:street":"382Nd Ave",
    "iso:country":"US",
    "sg:address":"9000 382nd Ave",
    "sg:city":"Blue Earth",
    "sg:classifiers":[
        {
            "category":"Manufacturing",
            "subcategory":"Food",
            "type":"Manufacturing & Wholesale Goods"
        }
    ],
    "sg:phone":"+1 507 526 3296",
    "sg:postcode":"56013",
    "sg:province":"MN",
    "sg:tags":[
        "farm",
        "raw",
        "animal",
        "mfg"
    ],
    "sg:website":"www.darlingii.com",
    "wof:name":"Darling International Inc",
    "wof:placetype":"venue"
},
  "geometry": {"coordinates":[-94.104044,43.616344],"type":"Point"}
}