{
  "type": "Feature",
  "properties": {
    "iso:country":"US",
    "sg:address":"1087 Arcade St",
    "sg:city":"St Paul",
    "sg:classifiers":[
        {
            "category":"Professional",
            "type":"Services"
        },
        {
            "category":"Personal",
            "subcategory":"Tanning Parlor",
            "type":"Services"
        }
    ],
    "sg:phone":"+1 651 495 0338",
    "sg:postcode":"55106",
    "sg:province":"MN",
    "sg:tags":[
        "salon"
    ],
    "wof:name":"Electric Beach Tanning",
    "wof:placetype":"venue"
},
  "geometry": {"coordinates":[-93.066033,44.974731],"type":"Point"}
}