{
  "type": "Feature",
  "properties": {
    "addr:full":"1080 71st St Slayton MN 56172",
    "addr:housenumber":"1080",
    "addr:postcode":"56172",
    "addr:street":"71St St",
    "iso:country":"US",
    "sg:address":"1080 71st St",
    "sg:city":"Slayton",
    "sg:classifiers":[
        {
            "category":"Government",
            "subcategory":"Office",
            "type":"Public Place"
        }
    ],
    "sg:phone":"+1 507 836 6075",
    "sg:postcode":"56172",
    "sg:province":"MN",
    "sg:tags":[
        "county",
        "program"
    ],
    "wof:name":"Murray County Sanitary Lndfll",
    "wof:placetype":"venue"
},
  "geometry": {"coordinates":[-95.847539,43.949804],"type":"Point"}
}