{
  "type": "Feature",
  "properties": {
    "addr:full":"6125 Blue Circle Dr Hopkins MN 55343",
    "addr:housenumber":"6125",
    "addr:postcode":"55343",
    "addr:street":"Blue Circle Dr",
    "iso:country":"US",
    "sg:address":"6125 Blue Circle Dr",
    "sg:city":"Hopkins",
    "sg:classifiers":[
        {
            "category":"Real Estate",
            "subcategory":"Developer",
            "type":"Services"
        }
    ],
    "sg:phone":"+1 952 933 0409",
    "sg:postcode":"55343",
    "sg:province":"MN",
    "wof:name":"DECOM Corp",
    "wof:placetype":"venue"
},
  "geometry": {"coordinates":[-93.406837,44.89194],"type":"Point"}
}