{
  "type": "Feature",
  "properties": {
    "addr:full":"617 Hwy 55 W Buffalo MN 55313",
    "addr:housenumber":"617",
    "addr:postcode":"55313",
    "addr:street":"Hwy 55 W",
    "iso:country":"US",
    "sg:address":"617 Hwy 55 W",
    "sg:city":"Buffalo",
    "sg:classifiers":[
        {
            "category":"Banks & Credit Unions",
            "subcategory":"Bank",
            "type":"Services"
        }
    ],
    "sg:phone":"+1 763 682 3332",
    "sg:postcode":"55313",
    "sg:province":"MN",
    "sg:tags":[
        "loan",
        "real estate"
    ],
    "wof:name":"Midwest Residential Mtg",
    "wof:placetype":"venue"
},
  "geometry": {"coordinates":[-93.867898,45.178043],"type":"Point"}
}