{
  "type": "Feature",
  "properties": {
    "addr:full":"66095 270th Ave Kasson MN 55944",
    "addr:housenumber":"66095",
    "addr:postcode":"55944",
    "addr:street":"270Th Ave",
    "iso:country":"US",
    "sg:address":"66095 270th Ave",
    "sg:city":"Kasson",
    "sg:classifiers":[
        {
            "category":"Farming",
            "subcategory":"Dairy Farm",
            "type":"Manufacturing & Wholesale Goods"
        }
    ],
    "sg:phone":"+1 507 634 4398",
    "sg:postcode":"55944",
    "sg:province":"MN",
    "wof:name":"Maderys Holsteins",
    "wof:placetype":"venue"
},
  "geometry": {"coordinates":[-92.698161,43.980079],"type":"Point"}
}