{
  "type": "Feature",
  "properties": {
    "iso:country":"US",
    "sg:address":"819 Whitewater Ave",
    "sg:city":"St Charles",
    "sg:classifiers":[
        {
            "category":"Professional",
            "subcategory":"Accounting & Tax Preparation",
            "type":"Services"
        }
    ],
    "sg:phone":"+1 507 932 3010",
    "sg:postcode":"55972",
    "sg:province":"MN",
    "sg:tags":[
        "firm",
        "accountant"
    ],
    "sg:website":"www.wolterandraak.com",
    "wof:name":"Wolter & Raak LTD",
    "wof:placetype":"venue"
},
  "geometry": {"coordinates":[-92.06489999999999,43.96919],"type":"Point"}
}