{
  "type": "Feature",
  "properties": {
    "addr:full":"320 12th St SE Rochester MN 55904",
    "addr:housenumber":"320",
    "addr:postcode":"55904",
    "addr:street":"12Th St Se",
    "iso:country":"US",
    "sg:address":"320 12th St SE",
    "sg:city":"Rochester",
    "sg:classifiers":[
        {
            "category":"Restaurant",
            "type":"Food & Drink"
        },
        {
            "category":"Ice Cream",
            "type":"Food & Drink"
        }
    ],
    "sg:menulink":"http://www.allmenus.com/mn/rochester/167911-dairy-queen/menu/",
    "sg:phone":"+1 507 282 8633",
    "sg:postcode":"55904",
    "sg:province":"MN",
    "sg:tags":[
        "burger",
        "american",
        "ice",
        "cream"
    ],
    "wof:name":"Dairy Queen",
    "wof:placetype":"venue"
},
  "geometry": {"coordinates":[-92.458488,44.006987],"type":"Point"}
}