{
  "type": "Feature",
  "properties": {
    "addr:full":"150 S 5th St Ste 2800 Minneapolis MN 55402",
    "addr:housenumber":"150",
    "addr:postcode":"2800;55402",
    "addr:street":"S 5Th St Ste",
    "iso:country":"US",
    "sg:address":"150 S 5th St Ste 2800",
    "sg:city":"Minneapolis",
    "sg:classifiers":[
        {
            "category":"Insurance",
            "subcategory":"Hazard Insurance",
            "type":"Services"
        }
    ],
    "sg:phone":"+1 612 349 2400",
    "sg:postcode":"55402",
    "sg:province":"MN",
    "sg:tags":[
        "commercial",
        "business"
    ],
    "sg:website":"http://www.csdz.com",
    "wof:name":"Cobb Strecker Dunphy & Zimmermann Inc",
    "wof:placetype":"venue"
},
  "geometry": {"coordinates":[-93.268174,44.977762],"type":"Point"}
}