{
  "type": "Feature",
  "properties": {
    "addr:full":"219 6th Ave N Waite Park MN 56387",
    "addr:housenumber":"219",
    "addr:postcode":"56387",
    "addr:street":"6Th Ave N",
    "iso:country":"US",
    "sg:address":"219 6th Ave N",
    "sg:city":"Waite Park",
    "sg:classifiers":[
        {
            "category":"Building & Trades",
            "subcategory":"Electrical",
            "type":"Services"
        }
    ],
    "sg:phone":"+1 320 259 1986",
    "sg:postcode":"56387",
    "sg:province":"MN",
    "sg:tags":[
        "electrical",
        "contractor",
        "commercial",
        "residential"
    ],
    "wof:name":"Karens Electric Inc",
    "wof:placetype":"venue"
},
  "geometry": {"coordinates":[-94.224158,45.558598],"type":"Point"}
}