{
  "type": "Feature",
  "properties": {
    "addr:full":"21616 Helena Blvd Jordan MN 55352",
    "addr:housenumber":"21616",
    "addr:postcode":"55352",
    "addr:street":"Helena Blvd",
    "iso:country":"US",
    "sg:address":"21616 Helena Blvd",
    "sg:city":"Jordan",
    "sg:classifiers":[
        {
            "category":"Farming",
            "subcategory":"Dairy Farm",
            "type":"Manufacturing & Wholesale Goods"
        }
    ],
    "sg:phone":"+1 952 492 6942",
    "sg:postcode":"55352",
    "sg:province":"MN",
    "wof:name":"Martin Huss",
    "wof:placetype":"venue"
},
  "geometry": {"coordinates":[-93.61662200000001,44.636085],"type":"Point"}
}