{
  "type": "Feature",
  "properties": {
    "addr:full":"212 2nd St SE Minneapolis MN 55414",
    "addr:housenumber":"212",
    "addr:postcode":"55414",
    "addr:street":"2Nd St Se",
    "iso:country":"US",
    "sg:address":"212 2nd St SE",
    "sg:city":"Minneapolis",
    "sg:classifiers":[
        {
            "category":"Professional",
            "subcategory":"Credit Reporting & Collection",
            "type":"Services"
        }
    ],
    "sg:phone":"+1 612 331 6568",
    "sg:postcode":"55414",
    "sg:province":"MN",
    "sg:tags":[
        "selling",
        "purchasing",
        "debt"
    ],
    "wof:name":"Big Ten Capital",
    "wof:placetype":"venue"
},
  "geometry": {"coordinates":[-93.252906,44.984715],"type":"Point"}
}