{
  "type": "Feature",
  "properties": {
    "iso:country":"US",
    "sg:address":"12247 Radisson Rd NE",
    "sg:city":"Minneapolis",
    "sg:classifiers":[
        {
            "category":"Shopping",
            "subcategory":"Bicycles & Sporting Goods",
            "type":"Retail Goods"
        }
    ],
    "sg:phone":"+1 763 757 0797",
    "sg:postcode":"55449",
    "sg:province":"MN",
    "wof:name":"K&L Sporting Goods",
    "wof:placetype":"venue"
},
  "geometry": {"coordinates":[-93.218827,45.192127],"type":"Point"}
}