{
  "type": "Feature",
  "properties": {
    "iso:country":"US",
    "sg:address":"12148 Bayberry Dr",
    "sg:city":"Menahga",
    "sg:classifiers":[
        {
            "category":"Travel",
            "subcategory":"Hotels & Motels",
            "type":"Entertainment"
        }
    ],
    "sg:phone":"+1 218 732 5017",
    "sg:postcode":"56464",
    "sg:province":"MN",
    "sg:tags":[
        "operation"
    ],
    "wof:name":"Pleasant Ridge Resort",
    "wof:placetype":"venue"
},
  "geometry": {"coordinates":[-94.882417,46.834042],"type":"Point"}
}