{
  "type": "Feature",
  "properties": {
    "addr:full":"5212 Clear Spring Dr Minnetonka MN 55345",
    "addr:housenumber":"5212",
    "addr:postcode":"55345",
    "addr:street":"Clear Spring Dr",
    "iso:country":"US",
    "sg:address":"5212 Clear Spring Dr",
    "sg:city":"Minnetonka",
    "sg:classifiers":[
        {
            "category":"Wholesale",
            "subcategory":"Machinery & Supplies",
            "type":"Manufacturing & Wholesale Goods"
        }
    ],
    "sg:phone":"+1 952 935 8484",
    "sg:postcode":"55345",
    "sg:province":"MN",
    "sg:tags":[
        "equipment",
        "welding"
    ],
    "wof:name":"T R Erickson Co",
    "wof:placetype":"venue"
},
  "geometry": {"coordinates":[-93.495164,44.909041],"type":"Point"}
}