{
  "type": "Feature",
  "properties": {
    "iso:country":"US",
    "sg:address":"171 Cheshire Ln N Ste 500",
    "sg:city":"Minneapolis",
    "sg:classifiers":[
        {
            "category":"Shopping",
            "subcategory":"Crafts & Fabrics",
            "type":"Retail Goods"
        }
    ],
    "sg:phone":"+1 763 432 4065",
    "sg:postcode":"55441",
    "sg:province":"MN",
    "sg:tags":[
        "supplies-wholesale",
        "manufacturer",
        "art",
        "supply"
    ],
    "wof:name":"Creative Funworks",
    "wof:placetype":"venue"
},
  "geometry": {"coordinates":[-93.456232,44.980089],"type":"Point"}
}