{
  "type": "Feature",
  "properties": {
    "addr:full":"8120 Penn Ave S Bloomington MN 55431",
    "addr:housenumber":"8120",
    "addr:postcode":"55431",
    "addr:street":"Penn Ave S",
    "iso:country":"US",
    "sg:address":"8120 Penn Ave S",
    "sg:city":"Bloomington",
    "sg:classifiers":[
        {
            "category":"Professional",
            "subcategory":"Detective & Security Services",
            "type":"Services"
        }
    ],
    "sg:phone":"+1 952 474 3317",
    "sg:postcode":"55431",
    "sg:province":"MN",
    "sg:tags":[
        "guard",
        "patrol"
    ],
    "wof:name":"Kleinberg Protective Agency",
    "wof:placetype":"venue"
},
  "geometry": {"coordinates":[-93.308842,44.855943],"type":"Point"}
}