{
  "type": "Feature",
  "properties": {
    "addr:full":"2255 49th Ave N Minneapolis MN 55430",
    "addr:housenumber":"2255",
    "addr:postcode":"55430",
    "addr:street":"49Th Ave N",
    "iso:country":"US",
    "sg:address":"2255 49th Ave N",
    "sg:city":"Minneapolis",
    "sg:classifiers":[
        {
            "category":"Shopping",
            "subcategory":"Computers & Home Electronics",
            "type":"Retail Goods"
        },
        {
            "category":"Professional",
            "subcategory":"Computer Services",
            "type":"Services"
        }
    ],
    "sg:phone":"+1 612 521 5543",
    "sg:postcode":"55430",
    "sg:province":"MN",
    "sg:tags":[
        "parts",
        "supply"
    ],
    "wof:name":"Midwest Mac Parts Inc",
    "wof:placetype":"venue"
},
  "geometry": {"coordinates":[-93.310036,45.043864],"type":"Point"}
}