{
  "type": "Feature",
  "properties": {
    "addr:full":"10550 Co Rd 81 Maple Grove MN 55369",
    "addr:housenumber":"10550;81",
    "addr:postcode":"55369",
    "addr:street":"Co Rd",
    "iso:country":"US",
    "sg:address":"10550 Co Rd 81",
    "sg:city":"Maple Grove",
    "sg:classifiers":[
        {
            "category":"Professional",
            "subcategory":"Testing Lab",
            "type":"Services"
        },
        {
            "category":"Manufacturing",
            "subcategory":"Tools & Machinery",
            "type":"Manufacturing & Wholesale Goods"
        }
    ],
    "sg:phone":"+1 763 493 0026",
    "sg:postcode":"55369",
    "sg:province":"MN",
    "sg:tags":[
        "industry",
        "calibration",
        "mfg"
    ],
    "wof:name":"Alliance Metrology",
    "wof:placetype":"venue"
},
  "geometry": {"coordinates":[-93.41640099999999,45.120487],"type":"Point"}
}