{
  "type": "Feature",
  "properties": {
    "addr:full":"17616 Highway 65 NE Andover MN 55304",
    "addr:housenumber":"17616",
    "addr:postcode":"55304",
    "addr:street":"Highway 65 Ne",
    "iso:country":"US",
    "sg:address":"17616 Highway 65 NE",
    "sg:city":"Andover",
    "sg:classifiers":[
        {
            "category":"Shopping",
            "subcategory":"Party Supplies",
            "type":"Retail Goods"
        },
        {
            "category":"Building & Trades",
            "subcategory":"Plumbing",
            "type":"Services"
        },
        {
            "category":"Home & Garden",
            "subcategory":"Hardware",
            "type":"Retail Goods"
        },
        {
            "category":"Utilities",
            "subcategory":"Sewage",
            "type":"Services"
        },
        {
            "category":"Building & Trades",
            "subcategory":"Cleaning & Sanitation",
            "type":"Services"
        }
    ],
    "sg:phone":"+1 763 434 5442",
    "sg:postcode":"55304",
    "sg:province":"MN",
    "sg:tags":[
        "tank",
        "toilets-portable",
        "septic",
        "system",
        "contractor",
        "sewer",
        "tanks-treatment",
        "store"
    ],
    "wof:name":"Soderville Septic Tank Service",
    "wof:placetype":"venue"
},
  "geometry": {"coordinates":[-93.235437,45.269825],"type":"Point"}
}