{
  "type": "Feature",
  "properties": {
    "iso:country":"US",
    "sg:address":"2995 60th St NW",
    "sg:city":"Willmar",
    "sg:phone":"+1 320 235 5336",
    "sg:postcode":"56201",
    "sg:province":"MN",
    "sg:tags":[
        "farm",
        "corn"
    ],
    "wof:name":"Edwin Wallentine",
    "wof:placetype":"venue"
},
  "geometry": {"coordinates":[-95.12408600000001,45.146065],"type":"Point"}
}