{
  "type": "Feature",
  "properties": {
    "addr:full":"38598 Co Rd 152 Albany MN 56307",
    "addr:housenumber":"38598;152",
    "addr:postcode":"56307",
    "addr:street":"Co Rd",
    "iso:country":"US",
    "sg:address":"38598 Co Rd 152",
    "sg:city":"Albany",
    "sg:classifiers":[
        {
            "category":"Retail",
            "subcategory":"Animal Services",
            "type":"Services"
        }
    ],
    "sg:phone":"+1 320 845 4628",
    "sg:postcode":"56307",
    "sg:province":"MN",
    "wof:name":"Paws Barber Shop",
    "wof:placetype":"venue"
},
  "geometry": {"coordinates":[-94.55229,45.681718],"type":"Point"}
}