{
  "type": "Feature",
  "properties": {
    "iso:country":"US",
    "sg:address":"509 Co Rd 42 E",
    "sg:city":"Burnsville",
    "sg:classifiers":[
        {
            "category":"Food & Beverages",
            "subcategory":"Specialty",
            "type":"Retail Goods"
        }
    ],
    "sg:phone":"+1 952 898 6690",
    "sg:postcode":"55306",
    "sg:province":"MN",
    "sg:tags":[
        "vitamin"
    ],
    "wof:name":"U S Health & Nutrition",
    "wof:placetype":"venue"
},
  "geometry": {"coordinates":[-93.27260099999999,44.7414],"type":"Point"}
}