{
  "type": "Feature",
  "properties": {
    "addr:full":"262 2nd Ave NE Trimont MN 56176",
    "addr:housenumber":"262",
    "addr:postcode":"56176",
    "addr:street":"2Nd Ave Ne",
    "iso:country":"US",
    "sg:address":"262 2nd Ave NE",
    "sg:city":"Trimont",
    "sg:classifiers":[
        {
            "category":"Social Services",
            "subcategory":"Child Care",
            "type":"Services"
        }
    ],
    "sg:phone":"+1 507 639 3825",
    "sg:postcode":"56176",
    "sg:province":"MN",
    "sg:tags":[
        "daycare",
        "provider"
    ],
    "wof:name":"Peggy Rankin",
    "wof:placetype":"venue"
},
  "geometry": {"coordinates":[-94.711484,43.764931],"type":"Point"}
}