{
  "type": "Feature",
  "properties": {
    "addr:full":"9361 230th St E Lakeville MN 55044",
    "addr:housenumber":"9361",
    "addr:postcode":"55044",
    "addr:street":"230Th St E",
    "iso:country":"US",
    "sg:address":"9361 230th St E",
    "sg:city":"Lakeville",
    "sg:classifiers":[
        {
            "category":"Retail",
            "subcategory":"Animal Services",
            "type":"Services"
        }
    ],
    "sg:phone":"+1 952 461 2003",
    "sg:postcode":"55044",
    "sg:province":"MN",
    "wof:name":"Rolling Hills Kennel",
    "wof:placetype":"venue"
},
  "geometry": {"coordinates":[-93.332441,44.61629],"type":"Point"}
}