{
  "type": "Feature",
  "properties": {
    "addr:full":"27605 Pillsbury Ave Lakeville MN 55044",
    "addr:postcode":"27605;55044",
    "addr:street":"Pillsbury Ave",
    "iso:country":"US",
    "sg:address":"27605 Pillsbury Ave",
    "sg:city":"Lakeville",
    "sg:classifiers":[
        {
            "category":"Farming",
            "subcategory":"Dairy Farm",
            "type":"Manufacturing & Wholesale Goods"
        }
    ],
    "sg:phone":"+1 952 461 2890",
    "sg:postcode":"55044",
    "sg:province":"MN",
    "wof:name":"B Mohn",
    "wof:placetype":"venue"
},
  "geometry": {"coordinates":[-93.28321699999999,44.544939],"type":"Point"}
}