{
  "type": "Feature",
  "properties": {
    "addr:full":"14120 Commerce Ave NE Ste 300 Prior Lake MN 55372",
    "addr:housenumber":"14120",
    "addr:postcode":"55372",
    "addr:street":"Commerce Ave Ne Ste 300",
    "iso:country":"US",
    "sg:address":"14120 Commerce Ave NE Ste 300",
    "sg:city":"Prior Lake",
    "sg:classifiers":[
        {
            "category":"Health Services",
            "subcategory":"Doctor",
            "type":"Services"
        },
        {
            "category":"Health Services",
            "subcategory":"Dentist",
            "type":"Services"
        }
    ],
    "sg:phone":"+1 952 447 1080",
    "sg:postcode":"55372",
    "sg:province":"MN",
    "sg:tags":[
        "surgeon",
        "oral",
        "orthodontist"
    ],
    "wof:name":"Puffer Charles W DDS",
    "wof:placetype":"venue"
},
  "geometry": {"coordinates":[-93.380844,44.744315],"type":"Point"}
}