{
  "type": "Feature",
  "properties": {
    "addr:full":"26643 Glen Oak Dr Wyoming MN 55092",
    "addr:housenumber":"26643",
    "addr:postcode":"55092",
    "addr:street":"Glen Oak Dr",
    "iso:country":"US",
    "sg:address":"26643 Glen Oak Dr",
    "sg:city":"Wyoming",
    "sg:classifiers":[
        {
            "category":"Building & Trades",
            "subcategory":"Plumbing",
            "type":"Services"
        }
    ],
    "sg:phone":"+1 651 462 0049",
    "sg:postcode":"55092",
    "sg:province":"MN",
    "sg:tags":[
        "contractor"
    ],
    "wof:name":"Timothy J Menne",
    "wof:placetype":"venue"
},
  "geometry": {"coordinates":[-92.981353,45.334868],"type":"Point"}
}