{
  "type": "Feature",
  "properties": {
    "iso:country":"US",
    "sg:address":"2500 McMenemy St",
    "sg:city":"Little Canada",
    "sg:classifiers":[
        {
            "category":"Building & Trades",
            "subcategory":"Electrical",
            "type":"Services"
        }
    ],
    "sg:phone":"+1 651 484 5905",
    "sg:postcode":"55117",
    "sg:province":"MN",
    "sg:tags":[
        "electrical",
        "electric",
        "contractor"
    ],
    "wof:name":"Roseville Electric Inc",
    "wof:placetype":"venue"
},
  "geometry": {"coordinates":[-93.084262,45.018446],"type":"Point"}
}