{
  "type": "Feature",
  "properties": {
    "addr:full":"1955 1st Ave N Windom MN 56101",
    "addr:housenumber":"1955",
    "addr:postcode":"56101",
    "addr:street":"1St Ave N",
    "iso:country":"US",
    "sg:address":"1955 1st Ave N",
    "sg:city":"Windom",
    "sg:classifiers":[
        {
            "category":"Travel",
            "subcategory":"Hotels & Motels",
            "type":"Entertainment"
        }
    ],
    "sg:phone":"+1 507 831 1809",
    "sg:postcode":"56101",
    "sg:province":"MN",
    "sg:website":"http://www.guardianinn.com",
    "wof:name":"Guardian Inn",
    "wof:placetype":"venue"
},
  "geometry": {"coordinates":[-95.11223,43.876772],"type":"Point"}
}