{
  "type": "Feature",
  "properties": {
    "addr:full":"915 Co Rd 42 W Burnsville MN 55306",
    "addr:housenumber":"915;42",
    "addr:postcode":"55306",
    "addr:street":"Co Rd;W",
    "iso:country":"US",
    "sg:address":"915 Co Rd 42 W",
    "sg:city":"Burnsville",
    "sg:classifiers":[
        {
            "category":"Utilities",
            "subcategory":"Mobile Phone",
            "type":"Services"
        }
    ],
    "sg:phone":"+1 952 898 7575",
    "sg:postcode":"55306",
    "sg:province":"MN",
    "sg:tags":[
        "telephone",
        "cellular"
    ],
    "wof:name":"T-Mobile",
    "wof:placetype":"venue"
},
  "geometry": {"coordinates":[-93.28886799999999,44.746413],"type":"Point"}
}