{
  "type": "Feature",
  "properties": {
    "addr:full":"12376 100th St Hoffman MN 56361",
    "addr:housenumber":"12376",
    "addr:postcode":"56361",
    "addr:street":"100Th St",
    "iso:country":"US",
    "sg:address":"12376 100th St",
    "sg:city":"Hoffman",
    "sg:classifiers":[
        {
            "category":"Farming",
            "subcategory":"Livestock Farm",
            "type":"Manufacturing & Wholesale Goods"
        }
    ],
    "sg:phone":"+1 320 986 2637",
    "sg:postcode":"56361",
    "sg:province":"MN",
    "sg:tags":[
        "beef",
        "feedlot",
        "cattle"
    ],
    "wof:name":"Evan Yochim",
    "wof:placetype":"venue"
},
  "geometry": {"coordinates":[-95.210447,46.107061],"type":"Point"}
}