{
  "type": "Feature",
  "properties": {
    "addr:full":"16921 Bainbridge Dr Eden Prairie MN 55347",
    "addr:housenumber":"16921",
    "addr:postcode":"55347",
    "addr:street":"Bainbridge Dr",
    "iso:country":"US",
    "sg:address":"16921 Bainbridge Dr",
    "sg:city":"Eden Prairie",
    "sg:classifiers":[
        {
            "category":"Professional",
            "subcategory":"Management & Consulting",
            "type":"Services"
        }
    ],
    "sg:phone":"+1 952 934 8251",
    "sg:postcode":"55347",
    "sg:province":"MN",
    "sg:tags":[
        "business"
    ],
    "wof:name":"J S K Consulting Inc",
    "wof:placetype":"venue"
},
  "geometry": {"coordinates":[-93.495656,44.844221],"type":"Point"}
}