{
  "type": "Feature",
  "properties": {
    "addr:full":"5855 Neal Ave N Oak Park Heights MN 55082",
    "addr:housenumber":"5855",
    "addr:postcode":"55082",
    "addr:street":"Neal Ave N",
    "iso:country":"US",
    "sg:address":"5855 Neal Ave N",
    "sg:city":"Oak Park Heights",
    "sg:classifiers":[
        {
            "category":"Personal",
            "subcategory":"Tanning Parlor",
            "type":"Services"
        }
    ],
    "sg:phone":"+1 651 439 3603",
    "sg:postcode":"55082",
    "sg:province":"MN",
    "sg:tags":[
        "salon"
    ],
    "wof:name":"Perfect Tan",
    "wof:placetype":"venue"
},
  "geometry": {"coordinates":[-92.847821,45.032475],"type":"Point"}
}