{
  "type": "Feature",
  "properties": {
    "iso:country":"US",
    "sg:address":"14041 Burnhaven Dr",
    "sg:city":"Burnsville",
    "sg:classifiers":[
        {
            "category":"Insurance",
            "subcategory":"Insurance Agent",
            "type":"Services"
        }
    ],
    "sg:phone":"+1 952 898 1883",
    "sg:postcode":"55337",
    "sg:province":"MN",
    "wof:name":"Primerica Financial Svc",
    "wof:placetype":"venue"
},
  "geometry": {"coordinates":[-93.293577,44.746937],"type":"Point"}
}