{
  "type": "Feature",
  "properties": {
    "addr:full":"3401 State Hwy 21 Faribault MN 55021",
    "addr:housenumber":"3401",
    "addr:postcode":"55021",
    "addr:street":"State Hwy 21",
    "iso:country":"US",
    "sg:address":"3401 State Hwy 21",
    "sg:city":"Faribault",
    "sg:classifiers":[
        {
            "category":"Airport",
            "type":"Transportation"
        }
    ],
    "sg:phone":"+1 507 332 0140",
    "sg:postcode":"55021",
    "sg:province":"MN",
    "sg:tags":[
        "executive"
    ],
    "wof:name":"Quality Aviation Inc",
    "wof:placetype":"venue"
},
  "geometry": {"coordinates":[-93.33961499999999,44.348637],"type":"Point"}
}