{
  "type": "Feature",
  "properties": {
    "iso:country":"US",
    "sg:address":"1740 E 4th St",
    "sg:city":"Saint Paul",
    "sg:classifiers":[
        {
            "category":"Organizations",
            "subcategory":"Membership Organization",
            "type":"Services"
        }
    ],
    "sg:phone":"+1 651 778 1597",
    "sg:postcode":"55106",
    "sg:province":"MN",
    "wof:name":"American Childrens Fund Inc",
    "wof:placetype":"venue"
},
  "geometry": {"coordinates":[-93.02573,44.958505],"type":"Point"}
}