{
  "type": "Feature",
  "properties": {
    "addr:full":"25039 Tame Fish Lake Rd Deerwood MN 56444",
    "addr:postcode":"25039;56444",
    "addr:street":"Fish Lake Rd",
    "iso:country":"US",
    "sg:address":"25039 Tame Fish Lake Rd",
    "sg:city":"Deerwood",
    "sg:classifiers":[
        {
            "category":"Travel",
            "subcategory":"Hotels & Motels",
            "type":"Entertainment"
        },
        {
            "category":"Travel",
            "subcategory":"Resort",
            "type":"Entertainment"
        }
    ],
    "sg:phone":"+1 218 678 2885",
    "sg:postcode":"56444",
    "sg:province":"MN",
    "sg:tags":[
        "lodging"
    ],
    "sg:website":"http://www.ruttgers.com",
    "wof:name":"Ruttger's Bay Lake Lodge",
    "wof:placetype":"venue"
},
  "geometry": {"coordinates":[-93.862739,46.410239],"type":"Point"}
}