{
  "type": "Feature",
  "properties": {
    "iso:country":"US",
    "sg:address":"2789 Clearwater Rd",
    "sg:city":"St Cloud",
    "sg:classifiers":[
        {
            "category":"Manufacturing",
            "subcategory":"Electronics",
            "type":"Manufacturing & Wholesale Goods"
        },
        {
            "category":"Wholesale",
            "subcategory":"Durable Goods & Equipment",
            "type":"Manufacturing & Wholesale Goods"
        }
    ],
    "sg:phone":"+1 320 654 0551",
    "sg:postcode":"56301",
    "sg:province":"MN",
    "sg:tags":[
        "salon",
        "distributor",
        "system",
        "lotion",
        "to",
        "tanning",
        "telephone"
    ],
    "wof:name":"T W Enterprises Ltd",
    "wof:placetype":"venue"
},
  "geometry": {"coordinates":[-94.159632,45.525586],"type":"Point"}
}