{
  "type": "Feature",
  "properties": {
    "addr:full":"11789 Hillside Rd Brownsville MN 55919",
    "addr:housenumber":"11789",
    "addr:postcode":"55919",
    "addr:street":"Hillside Rd",
    "iso:country":"US",
    "sg:address":"11789 Hillside Rd",
    "sg:city":"Brownsville",
    "sg:classifiers":[
        {
            "category":"Farming",
            "subcategory":"Livestock Farm",
            "type":"Manufacturing & Wholesale Goods"
        }
    ],
    "sg:phone":"+1 507 482 6859",
    "sg:postcode":"55919",
    "sg:province":"MN",
    "sg:tags":[
        "equine"
    ],
    "wof:name":"Hillside Stables Farm",
    "wof:placetype":"venue"
},
  "geometry": {"coordinates":[-91.292951,43.677347],"type":"Point"}
}