{
  "type": "Feature",
  "properties": {
    "addr:full":"2900 5th Ave S Minneapolis MN 55408",
    "addr:housenumber":"2900",
    "addr:postcode":"55408",
    "addr:street":"5Th Ave S",
    "iso:country":"US",
    "sg:address":"2900 5th Ave S",
    "sg:city":"Minneapolis",
    "sg:classifiers":[
        {
            "category":"Wholesale",
            "subcategory":"Machinery & Supplies",
            "type":"Manufacturing & Wholesale Goods"
        },
        {
            "category":"Ice Cream",
            "type":"Food & Drink"
        },
        {
            "category":"Food & Beverages",
            "subcategory":"Liquor & Beverages",
            "type":"Retail Goods"
        }
    ],
    "sg:phone":"+1 612 824 9600",
    "sg:postcode":"55408",
    "sg:province":"MN",
    "sg:tags":[
        "dry",
        "machine",
        "making",
        "equipment"
    ],
    "sg:website":"http://www.shamrockgroup.net",
    "wof:name":"Ace Ice Company",
    "wof:placetype":"venue"
},
  "geometry": {"coordinates":[-93.269012,44.950069],"type":"Point"}
}