{
  "type": "Feature",
  "properties": {
    "addr:full":"12732 260th St E Cannon Falls MN 55009",
    "addr:housenumber":"12732",
    "addr:postcode":"55009",
    "addr:street":"260Th St E",
    "iso:country":"US",
    "sg:address":"12732 260th St E",
    "sg:city":"Cannon Falls",
    "sg:classifiers":[
        {
            "category":"Farming",
            "subcategory":"Dairy Farm",
            "type":"Manufacturing & Wholesale Goods"
        }
    ],
    "sg:phone":"+1 507 263 2737",
    "sg:postcode":"55009",
    "sg:province":"MN",
    "wof:name":"John & James Weber",
    "wof:placetype":"venue"
},
  "geometry": {"coordinates":[-92.838076,44.571352],"type":"Point"}
}