{
  "type": "Feature",
  "properties": {
    "iso:country":"US",
    "sg:address":"963 91st Ave NE",
    "sg:city":"Minneapolis",
    "sg:classifiers":[
        {
            "category":"Social Services",
            "subcategory":"Child Care",
            "type":"Services"
        }
    ],
    "sg:phone":"+1 763 786 9342",
    "sg:postcode":"55434",
    "sg:province":"MN",
    "sg:tags":[
        "daycare",
        "provider"
    ],
    "wof:name":"Michelle Schuchard",
    "wof:placetype":"venue"
},
  "geometry": {"coordinates":[-93.246469,45.135542],"type":"Point"}
}