{
  "type": "Feature",
  "properties": {
    "iso:country":"US",
    "sg:address":"1342 Colorado Ave S",
    "sg:city":"Minneapolis",
    "sg:classifiers":[
        {
            "category":"Shopping",
            "subcategory":"Computers & Home Electronics",
            "type":"Retail Goods"
        }
    ],
    "sg:phone":"+1 952 544 0978",
    "sg:postcode":"55416",
    "sg:province":"MN",
    "sg:tags":[
        "equipment",
        "electronic",
        "supply"
    ],
    "wof:name":"Us Electronics Inc",
    "wof:placetype":"venue"
},
  "geometry": {"coordinates":[-93.359449,44.969464],"type":"Point"}
}