{
  "type": "Feature",
  "properties": {
    "iso:country":"US",
    "sg:address":"310 14th St",
    "sg:city":"Kerkhoven",
    "sg:classifiers":[
        {
            "category":"Real Estate",
            "subcategory":"Real Estate Agent",
            "type":"Services"
        }
    ],
    "sg:phone":"+1 320 264 3500",
    "sg:postcode":"56252",
    "sg:province":"MN",
    "wof:name":"Alliance Land Co",
    "wof:placetype":"venue"
},
  "geometry": {"coordinates":[-95.323453,45.190058],"type":"Point"}
}