{
  "type": "Feature",
  "properties": {
    "addr:full":"4925 State Hwy 27 E Alexandria MN 56308",
    "addr:housenumber":"4925",
    "addr:postcode":"56308",
    "addr:street":"State Hwy 27 E",
    "iso:country":"US",
    "sg:address":"4925 State Hwy 27 E",
    "sg:city":"Alexandria",
    "sg:classifiers":[
        {
            "category":"Home & Garden",
            "subcategory":"Building Materials",
            "type":"Retail Goods"
        }
    ],
    "sg:phone":"+1 320 763 3667",
    "sg:postcode":"56308",
    "sg:province":"MN",
    "wof:name":"Lakes Area Garage Door Co",
    "wof:placetype":"venue"
},
  "geometry": {"coordinates":[-95.30605199999999,45.885637],"type":"Point"}
}