{
  "type": "Feature",
  "properties": {
    "addr:full":"27767 Co Rd 87 Long Prairie MN 56347",
    "addr:housenumber":"27767;87",
    "addr:postcode":"56347",
    "addr:street":"Co Rd",
    "iso:country":"US",
    "sg:address":"27767 Co Rd 87",
    "sg:city":"Long Prairie",
    "sg:phone":"+1 320 732 3268",
    "sg:postcode":"56347",
    "sg:province":"MN",
    "sg:tags":[
        "beef",
        "farm",
        "corn",
        "field",
        "soybean",
        "cattle",
        "feedlot"
    ],
    "wof:name":"Glen Pesta",
    "wof:placetype":"venue"
},
  "geometry": {"coordinates":[-95.001172,46.024417],"type":"Point"}
}