{
  "type": "Feature",
  "properties": {
    "addr:full":"151 18th St SW Owatonna MN 55060",
    "addr:housenumber":"151",
    "addr:postcode":"55060",
    "addr:street":"18Th St Sw",
    "iso:country":"US",
    "sg:address":"151 18th St SW",
    "sg:city":"Owatonna",
    "sg:classifiers":[
        {
            "category":"Home & Garden",
            "subcategory":"Building Materials",
            "type":"Retail Goods"
        }
    ],
    "sg:phone":"+1 507 451 2899",
    "sg:postcode":"55060",
    "sg:province":"MN",
    "sg:tags":[
        "door"
    ],
    "wof:name":"All Star Garage Door LLC",
    "wof:placetype":"venue"
},
  "geometry": {"coordinates":[-93.228503,44.066138],"type":"Point"}
}