{
  "type": "Feature",
  "properties": {
    "addr:full":"519 Madison Ave SW Eyota MN 55934",
    "addr:housenumber":"519",
    "addr:postcode":"55934",
    "addr:street":"Madison Ave Sw",
    "iso:country":"US",
    "sg:address":"519 Madison Ave SW",
    "sg:city":"Eyota",
    "sg:classifiers":[
        {
            "category":"Building & Trades",
            "subcategory":"Construction",
            "type":"Services"
        }
    ],
    "sg:phone":"+1 507 545 2664",
    "sg:postcode":"55934",
    "sg:province":"MN",
    "sg:tags":[
        "siding",
        "contractor"
    ],
    "wof:name":"B K Construction",
    "wof:placetype":"venue"
},
  "geometry": {"coordinates":[-92.235331,43.984441],"type":"Point"}
}