{
  "type": "Feature",
  "properties": {
    "addr:full":"19400 State Hwy 7 Excelsior MN 55331",
    "addr:housenumber":"19400",
    "addr:postcode":"55331",
    "addr:street":"State Hwy 7",
    "iso:country":"US",
    "sg:address":"19400 State Hwy 7",
    "sg:city":"Excelsior",
    "sg:classifiers":[
        {
            "category":"Real Estate",
            "subcategory":"Real Estate Agent",
            "type":"Services"
        }
    ],
    "sg:phone":"+1 952 470 2556",
    "sg:postcode":"55331",
    "sg:province":"MN",
    "wof:name":"Real Estate Team Resource",
    "wof:placetype":"venue"
},
  "geometry": {"coordinates":[-93.525605,44.910556],"type":"Point"}
}