{
  "type": "Feature",
  "properties": {
    "iso:country":"US",
    "sg:address":"8499 Heron Ave S",
    "sg:city":"Cottage Grove",
    "sg:classifiers":[
        {
            "category":"Professional",
            "subcategory":"Management & Consulting",
            "type":"Services"
        }
    ],
    "sg:phone":"+1 651 458 3976",
    "sg:postcode":"55016",
    "sg:province":"MN",
    "sg:tags":[
        "business"
    ],
    "wof:name":"Tschida Consulting Inc",
    "wof:placetype":"venue"
},
  "geometry": {"coordinates":[-92.951093,44.825702],"type":"Point"}
}