{
  "type": "Feature",
  "properties": {
    "addr:full":"138 W William St Albert Lea MN 56007",
    "addr:housenumber":"138",
    "addr:postcode":"56007",
    "addr:street":"W William St",
    "iso:country":"US",
    "sg:address":"138 W William St",
    "sg:city":"Albert Lea",
    "sg:classifiers":[
        {
            "category":"Retail",
            "subcategory":"Repair Shop",
            "type":"Services"
        }
    ],
    "sg:phone":"+1 507 373 6022",
    "sg:postcode":"56007",
    "sg:province":"MN",
    "sg:tags":[
        "electrical"
    ],
    "wof:name":"TNT Used Appliances",
    "wof:placetype":"venue"
},
  "geometry": {"coordinates":[-93.36965499999999,43.648887],"type":"Point"}
}