{
  "type": "Feature",
  "properties": {
    "iso:country":"US",
    "sg:address":"1441 85th Ave NE",
    "sg:city":"Blaine",
    "sg:classifiers":[
        {
            "category":"Autos & Motor Vehicles",
            "subcategory":"Motorcycle Sales",
            "type":"Retail Goods"
        }
    ],
    "sg:phone":"+1 763 786 9079",
    "sg:postcode":"55449",
    "sg:province":"MN",
    "sg:tags":[
        "repair",
        "scooter"
    ],
    "sg:website":"www.tcharley.com",
    "wof:name":"Twin Cities Harley Davidson N",
    "wof:placetype":"venue"
},
  "geometry": {"coordinates":[-93.233745,45.124635],"type":"Point"}
}