{
  "type": "Feature",
  "properties": {
    "addr:full":"6459 Craig Dr Eden Prairie MN 55346",
    "addr:housenumber":"6459",
    "addr:postcode":"55346",
    "addr:street":"Craig Dr",
    "iso:country":"US",
    "sg:address":"6459 Craig Dr",
    "sg:city":"Eden Prairie",
    "sg:classifiers":[
        {
            "category":"Insurance",
            "subcategory":"Insurance Agent",
            "type":"Services"
        }
    ],
    "sg:phone":"+1 952 974 9543",
    "sg:postcode":"55346",
    "sg:province":"MN",
    "sg:tags":[
        "investor"
    ],
    "wof:name":"Golden Gate Investments LLC",
    "wof:placetype":"venue"
},
  "geometry": {"coordinates":[-93.49435099999999,44.886522],"type":"Point"}
}