{
  "type": "Feature",
  "properties": {
    "addr:full":"2513 Darling Dr NW Alexandria MN 56308",
    "addr:housenumber":"2513",
    "addr:postcode":"56308",
    "addr:street":"Darling Dr Nw",
    "iso:country":"US",
    "sg:address":"2513 Darling Dr NW",
    "sg:city":"Alexandria",
    "sg:classifiers":[
        {
            "category":"Retail",
            "subcategory":"Repair Shop",
            "type":"Services"
        }
    ],
    "sg:phone":"+1 320 846 8248",
    "sg:postcode":"56308",
    "sg:province":"MN",
    "sg:tags":[
        "television",
        "radio"
    ],
    "wof:name":"Star Electronic Svc",
    "wof:placetype":"venue"
},
  "geometry": {"coordinates":[-95.38104199999999,45.917644],"type":"Point"}
}