{
  "type": "Feature",
  "properties": {
    "iso:country":"US",
    "sg:address":"1124 Sherman St",
    "sg:city":"Jackson",
    "sg:classifiers":[
        {
            "category":"Organizations",
            "subcategory":"Community Association",
            "type":"Services"
        }
    ],
    "sg:phone":"+1 507 847 4604",
    "sg:postcode":"56143",
    "sg:province":"MN",
    "wof:name":"Kiwanis International Inc",
    "wof:placetype":"venue"
},
  "geometry": {"coordinates":[-94.99897,43.621672],"type":"Point"}
}