{
  "type": "Feature",
  "properties": {
    "iso:country":"US",
    "sg:address":"1572 61st Ave NE",
    "sg:city":"Minneapolis",
    "sg:classifiers":[
        {
            "category":"Insurance",
            "subcategory":"Insurance Agent",
            "type":"Services"
        }
    ],
    "sg:phone":"+1 763 571 6359",
    "sg:postcode":"55432",
    "sg:province":"MN",
    "sg:tags":[
        "adjuster"
    ],
    "wof:name":"Central Auto Appraisal",
    "wof:placetype":"venue"
},
  "geometry": {"coordinates":[-93.230322,45.078732],"type":"Point"}
}