{
  "type": "Feature",
  "properties": {
    "addr:full":"3141 35th Ave S Minneapolis MN 55406",
    "addr:housenumber":"3141",
    "addr:postcode":"55406",
    "addr:street":"35Th Ave S",
    "iso:country":"US",
    "sg:address":"3141 35th Ave S",
    "sg:city":"Minneapolis",
    "sg:classifiers":[
        {
            "category":"Health Services",
            "subcategory":"Clinic",
            "type":"Services"
        }
    ],
    "sg:phone":"+1 612 722 2721",
    "sg:postcode":"55406",
    "sg:province":"MN",
    "sg:tags":[
        "home"
    ],
    "wof:name":"Safe Home Healthcare Svc Inc",
    "wof:placetype":"venue"
},
  "geometry": {"coordinates":[-93.221588,44.945745],"type":"Point"}
}