{
  "type": "Feature",
  "properties": {
    "addr:full":"3817 47th Ave S Minneapolis MN 55406",
    "addr:housenumber":"3817",
    "addr:postcode":"55406",
    "addr:street":"47Th Ave S",
    "iso:country":"US",
    "sg:address":"3817 47th Ave S",
    "sg:city":"Minneapolis",
    "sg:classifiers":[
        {
            "category":"Home & Garden",
            "subcategory":"Garden Supply",
            "type":"Retail Goods"
        }
    ],
    "sg:phone":"+1 612 824 7688",
    "sg:postcode":"55406",
    "sg:province":"MN",
    "sg:tags":[
        "bulb",
        "seed"
    ],
    "wof:name":"Greenhouse",
    "wof:placetype":"venue"
},
  "geometry": {"coordinates":[-93.206397,44.934151],"type":"Point"}
}