{
  "type": "Feature",
  "properties": {
    "addr:full":"8117 Vincent Ave N Minneapolis MN 55444",
    "addr:housenumber":"8117",
    "addr:postcode":"55444",
    "addr:street":"Vincent Ave N",
    "iso:country":"US",
    "sg:address":"8117 Vincent Ave N",
    "sg:city":"Minneapolis",
    "sg:classifiers":[
        {
            "category":"Professional",
            "subcategory":"Employment Agencies",
            "type":"Services"
        }
    ],
    "sg:phone":"+1 763 560 4272",
    "sg:postcode":"55444",
    "sg:province":"MN",
    "sg:tags":[
        "help",
        "supply"
    ],
    "wof:name":"Leland D Dexter",
    "wof:placetype":"venue"
},
  "geometry": {"coordinates":[-93.316716,45.102521],"type":"Point"}
}