{
  "type": "Feature",
  "properties": {
    "iso:country":"US",
    "sg:address":"2924 Anthony Ln",
    "sg:city":"Minneapolis",
    "sg:classifiers":[
        {
            "category":"Banks & Credit Unions",
            "subcategory":"Investment Brokerage",
            "type":"Services"
        }
    ],
    "sg:phone":"+1 612 789 9193",
    "sg:postcode":"55418",
    "sg:province":"MN",
    "sg:tags":[
        "advisory"
    ],
    "wof:name":"Brad Timmons",
    "wof:placetype":"venue"
},
  "geometry": {"coordinates":[-93.20851500000001,45.022202],"type":"Point"}
}