{
  "type": "Feature",
  "properties": {
    "iso:country":"US",
    "sg:address":"13404 Hynes Rd",
    "sg:city":"Rogers",
    "sg:classifiers":[
        {
            "category":"Social Services",
            "subcategory":"Child Care",
            "type":"Services"
        }
    ],
    "sg:phone":"+1 763 428 9790",
    "sg:postcode":"55374",
    "sg:province":"MN",
    "sg:tags":[
        "daycare",
        "provider"
    ],
    "wof:name":"Beths Day Care",
    "wof:placetype":"venue"
},
  "geometry": {"coordinates":[-93.573409,45.199164],"type":"Point"}
}