{
  "type": "Feature",
  "properties": {
    "addr:full":"1221 7th Ave N Minneapolis MN 55411",
    "addr:housenumber":"1221",
    "addr:postcode":"55411",
    "addr:street":"7Th Ave N",
    "iso:country":"US",
    "sg:address":"1221 7th Ave N",
    "sg:city":"Minneapolis",
    "sg:classifiers":[
        {
            "category":"Organizations",
            "subcategory":"Religious Organization",
            "type":"Services"
        }
    ],
    "sg:phone":"+1 612 374 4711",
    "sg:postcode":"55411",
    "sg:province":"MN",
    "sg:tags":[
        "church"
    ],
    "wof:name":"Wayman A M E Church",
    "wof:placetype":"venue"
},
  "geometry": {"coordinates":[-93.29702399999999,44.985092],"type":"Point"}
}