{
  "type": "Feature",
  "properties": {
    "iso:country":"US",
    "sg:address":"14777 Forest Blvd N",
    "sg:city":"Hugo",
    "sg:classifiers":[
        {
            "category":"Restaurant",
            "type":"Food & Drink"
        }
    ],
    "sg:phone":"+1 651 426 0916",
    "sg:postcode":"55110",
    "sg:province":"MN",
    "sg:tags":[
        "eating"
    ],
    "wof:name":"Riccis Pizzeria",
    "wof:placetype":"venue"
},
  "geometry": {"coordinates":[-92.991997,45.164154],"type":"Point"}
}