{
  "type": "Feature",
  "properties": {
    "addr:full":"705 Schooners End Sauk Rapids MN 56379",
    "addr:housenumber":"705",
    "addr:postcode":"56379",
    "addr:street":"Schooners End",
    "iso:country":"US",
    "sg:address":"705 Schooners End",
    "sg:city":"Sauk Rapids",
    "sg:classifiers":[
        {
            "category":"Banks & Credit Unions",
            "subcategory":"Bank",
            "type":"Services"
        }
    ],
    "sg:phone":"+1 320 253 7277",
    "sg:postcode":"56379",
    "sg:province":"MN",
    "sg:tags":[
        "loan",
        "broker"
    ],
    "wof:name":"Joy Benjamin Remer",
    "wof:placetype":"venue"
},
  "geometry": {"coordinates":[-94.166517,45.607195],"type":"Point"}
}