{
  "type": "Feature",
  "properties": {
    "addr:full":"3560 265th Ave Cottonwood MN 56229",
    "addr:housenumber":"3560",
    "addr:postcode":"56229",
    "addr:street":"265Th Ave",
    "iso:country":"US",
    "sg:address":"3560 265th Ave",
    "sg:city":"Cottonwood",
    "sg:classifiers":[
        {
            "category":"Home & Garden",
            "subcategory":"Garden Supply",
            "type":"Retail Goods"
        }
    ],
    "sg:phone":"+1 507 423 6482",
    "sg:postcode":"56229",
    "sg:province":"MN",
    "sg:tags":[
        "nurseryman"
    ],
    "sg:website":"www.mohnseed.com",
    "wof:name":"Mohn Seed Co",
    "wof:placetype":"venue"
},
  "geometry": {"coordinates":[-95.75741600000001,44.570961],"type":"Point"}
}