{
  "type": "Feature",
  "properties": {
    "iso:country":"US",
    "sg:address":"17569 235th Ave",
    "sg:city":"Pierz",
    "sg:classifiers":[
        {
            "category":"Building & Trades",
            "subcategory":"Landscaping Services",
            "type":"Services"
        }
    ],
    "sg:phone":"+1 320 630 8222",
    "sg:postcode":"56364",
    "sg:province":"MN",
    "sg:tags":[
        "tree",
        "stump",
        "grinding",
        "removal"
    ],
    "wof:name":"Vince'stree & Landscape",
    "wof:placetype":"venue"
},
  "geometry": {"coordinates":[-94.16741,46.019006],"type":"Point"}
}