{
  "type": "Feature",
  "properties": {
    "iso:country":"US",
    "sg:address":"29805 141st Ave",
    "sg:city":"New Prague",
    "sg:classifiers":[
        {
            "category":"Building & Trades",
            "subcategory":"Electrical",
            "type":"Services"
        }
    ],
    "sg:phone":"+1 952 758 4365",
    "sg:postcode":"56071",
    "sg:province":"MN",
    "sg:tags":[
        "electrical",
        "contractor"
    ],
    "wof:name":"Widmer Electric Inc",
    "wof:placetype":"venue"
},
  "geometry": {"coordinates":[-93.544676,44.516182],"type":"Point"}
}