{
  "type": "Feature",
  "properties": {
    "addr:full":"51 E Front St Winona MN 55987",
    "addr:housenumber":"51",
    "addr:postcode":"55987",
    "addr:street":"E Front St",
    "iso:country":"US",
    "sg:address":"51 E Front St",
    "sg:city":"Winona",
    "sg:classifiers":[
        {
            "category":"Insurance",
            "subcategory":"Insurance Agent",
            "type":"Services"
        }
    ],
    "sg:phone":"+1 507 454 2571",
    "sg:postcode":"55987",
    "sg:province":"MN",
    "wof:name":"Custard Insurance Adjusters",
    "wof:placetype":"venue"
},
  "geometry": {"coordinates":[-91.634685,44.05457],"type":"Point"}
}