{
  "type": "Feature",
  "properties": {
    "iso:country":"US",
    "sg:address":"21030 Co Hwy 4",
    "sg:city":"Pelican Rapids",
    "sg:classifiers":[
        {
            "category":"Insurance",
            "subcategory":"Insurance Agent",
            "type":"Services"
        }
    ],
    "sg:phone":"+1 218 863 7611",
    "sg:postcode":"56572",
    "sg:province":"MN",
    "wof:name":"William Albright Jr Insurance",
    "wof:placetype":"venue"
},
  "geometry": {"coordinates":[-96.032082,46.600805],"type":"Point"}
}