{
  "type": "Feature",
  "properties": {
    "addr:full":"6917 Hickory Dr NE Minneapolis MN 55432",
    "addr:housenumber":"6917",
    "addr:postcode":"55432",
    "addr:street":"Hickory Dr Ne",
    "iso:country":"US",
    "sg:address":"6917 Hickory Dr NE",
    "sg:city":"Minneapolis",
    "sg:classifiers":[
        {
            "category":"Personal",
            "subcategory":"Beauty Salon",
            "type":"Services"
        }
    ],
    "sg:phone":"+1 763 571 7353",
    "sg:postcode":"55432",
    "sg:province":"MN",
    "wof:name":"Style Monkeys",
    "wof:placetype":"venue"
},
  "geometry": {"coordinates":[-93.273763,45.093929],"type":"Point"}
}