{
  "type": "Feature",
  "properties": {
    "addr:full":"104 N Garden Minneapolis MN 55425",
    "addr:housenumber":"104",
    "addr:postcode":"55425",
    "addr:street":"N Garden",
    "iso:country":"US",
    "sg:address":"104 N Garden",
    "sg:city":"Minneapolis",
    "sg:classifiers":[
        {
            "category":"Shopping",
            "subcategory":"Clothing, Apparel, & Fashions",
            "type":"Retail Goods"
        }
    ],
    "sg:phone":"+1 952 814 3546",
    "sg:postcode":"55425",
    "sg:province":"MN",
    "sg:tags":[
        "apparel",
        "accessory",
        "women's"
    ],
    "sg:website":"http://www.bebe.com",
    "wof:name":"Bebe",
    "wof:placetype":"venue"
},
  "geometry": {"coordinates":[-93.240576,44.85608],"type":"Point"}
}