{
  "type": "Feature",
  "properties": {
    "addr:full":"920 Selby Ave St Paul MN 55104",
    "addr:housenumber":"920",
    "addr:postcode":"55104",
    "addr:street":"Selby Ave",
    "iso:country":"US",
    "sg:address":"920 Selby Ave",
    "sg:city":"St Paul",
    "sg:classifiers":[
        {
            "category":"Shopping",
            "subcategory":"Florist",
            "type":"Retail Goods"
        }
    ],
    "sg:phone":"+1 651 487 8122",
    "sg:postcode":"55104",
    "sg:province":"MN",
    "sg:tags":[
        "clothing"
    ],
    "sg:website":"www.bouquetsbycarolyn.com",
    "wof:name":"Bouquet's By Carolyn",
    "wof:placetype":"venue"
},
  "geometry": {"coordinates":[-93.141542,44.946605],"type":"Point"}
}