{
  "type": "Feature",
  "properties": {
    "addr:full":"7767 Main St N Osseo MN 55369",
    "addr:housenumber":"7767",
    "addr:postcode":"55369",
    "addr:street":"Main St N",
    "iso:country":"US",
    "sg:address":"7767 Main St N",
    "sg:city":"Osseo",
    "sg:classifiers":[
        {
            "category":"Restaurant",
            "type":"Food & Drink"
        }
    ],
    "sg:menulink":"http://www.allmenus.com/mn/maple-grove/56688-leeann-chin/menu/",
    "sg:phone":"+1 763 420 2116",
    "sg:postcode":"55369",
    "sg:province":"MN",
    "sg:tags":[
        "asian",
        "chinese"
    ],
    "wof:name":"Leeann Chin",
    "wof:placetype":"venue"
},
  "geometry": {"coordinates":[-93.44147100000001,45.091991],"type":"Point"}
}