{
  "type": "Feature",
  "properties": {
    "addr:full":"26298 Bear Rd Cushing MN 56443",
    "addr:housenumber":"26298",
    "addr:postcode":"56443",
    "addr:street":"Bear Rd",
    "iso:country":"US",
    "sg:address":"26298 Bear Rd",
    "sg:city":"Cushing",
    "sg:classifiers":[
        {
            "category":"Organizations",
            "subcategory":"Religious Organization",
            "type":"Services"
        }
    ],
    "sg:phone":"+1 320 749 2583",
    "sg:postcode":"56443",
    "sg:province":"MN",
    "sg:tags":[
        "church"
    ],
    "wof:name":"Cushing Baptist Church",
    "wof:placetype":"venue"
},
  "geometry": {"coordinates":[-94.571602,46.142074],"type":"Point"}
}