{
  "type": "Feature",
  "properties": {
    "addr:full":"44446 McGowan Estates Rd Ottertail MN 56571",
    "addr:postcode":"44446;56571",
    "addr:street":"Mcgowan Estates Rd",
    "iso:country":"US",
    "sg:address":"44446 McGowan Estates Rd",
    "sg:city":"Ottertail",
    "sg:classifiers":[
        {
            "category":"Insurance",
            "subcategory":"Insurance Agent",
            "type":"Services"
        }
    ],
    "sg:phone":"+1 218 346 6195",
    "sg:postcode":"56571",
    "sg:province":"MN",
    "wof:name":"Strickland Insurance",
    "wof:placetype":"venue"
},
  "geometry": {"coordinates":[-95.564223,46.496201],"type":"Point"}
}