{
  "type": "Feature",
  "properties": {
    "addr:full":"1750 Weir Dr Saint Paul MN 55125",
    "addr:housenumber":"1750",
    "addr:postcode":"55125",
    "addr:street":"Weir Dr",
    "iso:country":"US",
    "sg:address":"1750 Weir Dr",
    "sg:city":"Saint Paul",
    "sg:classifiers":[
        {
            "category":"Shopping",
            "subcategory":"Gifts & Souvenirs",
            "type":"Retail Goods"
        }
    ],
    "sg:phone":"+1 651 731 3300",
    "sg:postcode":"55125",
    "sg:province":"MN",
    "wof:name":"More Than Gifts",
    "wof:placetype":"venue"
},
  "geometry": {"coordinates":[-92.974986,44.92357],"type":"Point"}
}