{
  "type": "Feature",
  "properties": {
    "iso:country":"US",
    "sg:address":"5575 US Hwy 169",
    "sg:city":"Minneapolis",
    "sg:classifiers":[
        {
            "category":"Building & Trades",
            "subcategory":"Construction",
            "type":"Services"
        }
    ],
    "sg:phone":"+1 763 478 8507",
    "sg:postcode":"55442",
    "sg:province":"MN",
    "sg:tags":[
        "contractor"
    ],
    "wof:name":"Diversified Wall Systems LLC",
    "wof:placetype":"venue"
},
  "geometry": {"coordinates":[-93.400716,45.054384],"type":"Point"}
}