{
  "type": "Feature",
  "properties": {
    "addr:full":"705 6th St S Breckenridge MN 56520",
    "addr:housenumber":"705",
    "addr:postcode":"56520",
    "addr:street":"6Th St S",
    "iso:country":"US",
    "sg:address":"705 6th St S",
    "sg:city":"Breckenridge",
    "sg:classifiers":[
        {
            "category":"Social Services",
            "subcategory":"Child Care",
            "type":"Services"
        }
    ],
    "sg:phone":"+1 218 643 8604",
    "sg:postcode":"56520",
    "sg:province":"MN",
    "sg:tags":[
        "daycare",
        "provider"
    ],
    "wof:name":"Deborah Pierce",
    "wof:placetype":"venue"
},
  "geometry": {"coordinates":[-96.586634,46.256106],"type":"Point"}
}