{
  "type": "Feature",
  "properties": {
    "iso:country":"US",
    "sg:address":"5004 Edinbrook Ln",
    "sg:city":"Edina",
    "sg:classifiers":[
        {
            "category":"Health Services",
            "subcategory":"Hospital",
            "type":"Services"
        }
    ],
    "sg:phone":"+1 952 920 4204",
    "sg:postcode":"55436",
    "sg:province":"MN",
    "sg:tags":[
        "mental",
        "psychiatric"
    ],
    "wof:name":"Edinbrooks House",
    "wof:placetype":"venue"
},
  "geometry": {"coordinates":[-93.351722,44.915539],"type":"Point"}
}