{
  "type": "Feature",
  "properties": {
    "addr:full":"4816 Columbus Ave S Minneapolis MN 55417",
    "addr:housenumber":"4816",
    "addr:postcode":"55417",
    "addr:street":"Columbus Ave S",
    "iso:country":"US",
    "sg:address":"4816 Columbus Ave S",
    "sg:city":"Minneapolis",
    "sg:classifiers":[
        {
            "category":"Autos & Motor Vehicles",
            "subcategory":"Auto Supplies",
            "type":"Retail Goods"
        }
    ],
    "sg:phone":"+1 612 325 1931",
    "sg:postcode":"55417",
    "sg:province":"MN",
    "sg:tags":[
        "part"
    ],
    "sg:website":"www.sellusaoil.com",
    "wof:name":"Amsoil",
    "wof:placetype":"venue"
},
  "geometry": {"coordinates":[-93.263937,44.915788],"type":"Point"}
}