{
  "type": "Feature",
  "properties": {
    "iso:country":"US",
    "sg:address":"9634 Gamma Rd",
    "sg:city":"Ray",
    "sg:classifiers":[
        {
            "category":"Shopping",
            "subcategory":"Bicycles & Sporting Goods",
            "type":"Retail Goods"
        }
    ],
    "sg:phone":"+1 218 875 2281",
    "sg:postcode":"56669",
    "sg:province":"MN",
    "sg:tags":[
        "bait",
        "fishing"
    ],
    "wof:name":"Bait N Bite",
    "wof:placetype":"venue"
},
  "geometry": {"coordinates":[-93.04885899999999,48.423898],"type":"Point"}
}