{
  "type": "Feature",
  "properties": {
    "addr:full":"7555 Cloman Way E Inver Grove Hts MN 55076",
    "addr:housenumber":"7555",
    "addr:postcode":"55076",
    "addr:street":"Cloman Way E",
    "iso:country":"US",
    "sg:address":"7555 Cloman Way E",
    "sg:city":"Inver Grove Hts",
    "sg:classifiers":[
        {
            "category":"Health Services",
            "subcategory":"Doctor",
            "type":"Services"
        }
    ],
    "sg:phone":"+1 651 455 2644",
    "sg:postcode":"55076",
    "sg:province":"MN",
    "sg:tags":[
        "dentist"
    ],
    "wof:name":"Gary L Bergh DDS PA",
    "wof:placetype":"venue"
},
  "geometry": {"coordinates":[-93.03256500000001,44.840214],"type":"Point"}
}