{
  "type": "Feature",
  "properties": {
    "addr:full":"44789 Co Rd 2 Roseau MN 56751",
    "addr:postcode":"44789;56751",
    "addr:street":"Co Rd 2",
    "iso:country":"US",
    "sg:address":"44789 Co Rd 2",
    "sg:city":"Roseau",
    "sg:classifiers":[
        {
            "category":"Organizations",
            "subcategory":"Religious Organization",
            "type":"Services"
        }
    ],
    "sg:phone":"+1 218 463 3405",
    "sg:postcode":"56751",
    "sg:province":"MN",
    "wof:name":"Roseau Community Church",
    "wof:placetype":"venue"
},
  "geometry": {"coordinates":[-95.63768,48.776494],"type":"Point"}
}