{
  "type": "Feature",
  "properties": {
    "iso:country":"US",
    "sg:address":"39226 109th Ave",
    "sg:city":"Menahga",
    "sg:classifiers":[
        {
            "category":"Manufacturing",
            "subcategory":"Buildings",
            "type":"Manufacturing & Wholesale Goods"
        },
        {
            "category":"Building & Trades",
            "subcategory":"Construction",
            "type":"Services"
        }
    ],
    "sg:phone":"+1 218 564 4162",
    "sg:postcode":"56464",
    "sg:province":"MN",
    "sg:tags":[
        "home",
        "builder",
        "carpenter",
        "contractor"
    ],
    "sg:website":"http://www.carlson.com",
    "wof:name":"Carlson Companies",
    "wof:placetype":"venue"
},
  "geometry": {"coordinates":[-95.143575,46.793186],"type":"Point"}
}