{
  "type": "Feature",
  "properties": {
    "addr:full":"111506 Bender Ct Chaska MN 55318",
    "addr:housenumber":"111506",
    "addr:postcode":"55318",
    "addr:street":"Bender Ct",
    "iso:country":"US",
    "sg:address":"111506 Bender Ct",
    "sg:city":"Chaska",
    "sg:classifiers":[
        {
            "category":"Building & Trades",
            "subcategory":"Construction",
            "type":"Services"
        }
    ],
    "sg:phone":"+1 952 448 7559",
    "sg:postcode":"55318",
    "sg:province":"MN",
    "sg:tags":[
        "contractor"
    ],
    "wof:name":"Koprucki Bruce G & Jean M",
    "wof:placetype":"venue"
},
  "geometry": {"coordinates":[-93.603798,44.821602],"type":"Point"}
}