{
  "type": "Feature",
  "properties": {
    "addr:full":"1 Carlson Pkwy N Minneapolis MN 55447",
    "addr:housenumber":"1",
    "addr:postcode":"55447",
    "addr:street":"Carlson Pkwy N",
    "iso:country":"US",
    "sg:address":"1 Carlson Pkwy N",
    "sg:city":"Minneapolis",
    "sg:classifiers":[
        {
            "category":"Professional",
            "subcategory":"Engineering",
            "type":"Services"
        }
    ],
    "sg:phone":"+1 763 475 0010",
    "sg:postcode":"55447",
    "sg:province":"MN",
    "sg:tags":[
        "engineer"
    ],
    "sg:website":"www.srfconsulting.com",
    "wof:name":"SRF Consulting Group Inc",
    "wof:placetype":"venue"
},
  "geometry": {"coordinates":[-93.46302799999999,44.981533],"type":"Point"}
}