{
  "type": "Feature",
  "properties": {
    "iso:country":"US",
    "sg:address":"3651 State Hwy 38",
    "sg:city":"Grand Rapids",
    "sg:classifiers":[
        {
            "category":"Wholesale",
            "subcategory":"Auto Parts",
            "type":"Manufacturing & Wholesale Goods"
        }
    ],
    "sg:phone":"+1 218 326 3704",
    "sg:postcode":"55744",
    "sg:province":"MN",
    "wof:name":"Longries",
    "wof:placetype":"venue"
},
  "geometry": {"coordinates":[-93.533339,47.26838],"type":"Point"}
}