{
  "type": "Feature",
  "properties": {
    "addr:full":"4100 208th St W Farmington MN 55024",
    "addr:housenumber":"4100",
    "addr:postcode":"55024",
    "addr:street":"208Th St W",
    "iso:country":"US",
    "sg:address":"4100 208th St W",
    "sg:city":"Farmington",
    "sg:classifiers":[
        {
            "category":"Education",
            "subcategory":"School",
            "type":"Public Place"
        }
    ],
    "sg:phone":"+1 651 460 1601",
    "sg:postcode":"55024",
    "sg:province":"MN",
    "sg:website":"www.farmington.k12.mn.us",
    "wof:name":"Farmington Middle School East",
    "wof:placetype":"venue"
},
  "geometry": {"coordinates":[-93.14747199999999,44.647608],"type":"Point"}
}