{
  "type": "Feature",
  "properties": {
    "addr:full":"90 Oakview Pl Owatonna MN 55060",
    "addr:housenumber":"90",
    "addr:postcode":"55060",
    "addr:street":"Oakview Pl",
    "iso:country":"US",
    "sg:address":"90 Oakview Pl",
    "sg:city":"Owatonna",
    "sg:classifiers":[
        {
            "category":"Personal",
            "type":"Services"
        }
    ],
    "sg:phone":"+1 507 455 9082",
    "sg:postcode":"55060",
    "sg:province":"MN",
    "wof:name":"Big Jeffs Tattoo",
    "wof:placetype":"venue"
},
  "geometry": {"coordinates":[-93.217968,44.071582],"type":"Point"}
}