{
  "type": "Feature",
  "properties": {
    "iso:country":"US",
    "sg:address":"201 N Main St",
    "sg:city":"Stewartville",
    "sg:classifiers":[
        {
            "category":"Government",
            "subcategory":"Post Office",
            "type":"Public Place"
        }
    ],
    "sg:phone":"+1 507 533 4371",
    "sg:postcode":"55976",
    "sg:province":"MN",
    "wof:name":"Stewartville Post Office",
    "wof:placetype":"venue"
},
  "geometry": {"coordinates":[-92.48848,43.85667],"type":"Point"}
}