{
  "type": "Feature",
  "properties": {
    "addr:full":"711 5th St SW St Paul MN 55112",
    "addr:housenumber":"711",
    "addr:postcode":"55112",
    "addr:street":"5Th St Sw",
    "iso:country":"US",
    "sg:address":"711 5th St SW",
    "sg:city":"St Paul",
    "sg:classifiers":[
        {
            "category":"Wholesale",
            "subcategory":"Machinery & Supplies",
            "type":"Manufacturing & Wholesale Goods"
        }
    ],
    "sg:phone":"+1 651 697 0722",
    "sg:postcode":"55112",
    "sg:province":"MN",
    "sg:tags":[
        "printer",
        "cartridge"
    ],
    "wof:name":"Ennovation Graphic Systems",
    "wof:placetype":"venue"
},
  "geometry": {"coordinates":[-93.196708,45.041395],"type":"Point"}
}