{
  "type": "Feature",
  "properties": {
    "iso:country":"US",
    "sg:address":"565 Merriman Dr",
    "sg:city":"Delano",
    "sg:classifiers":[
        {
            "category":"Building & Trades",
            "subcategory":"Construction",
            "type":"Services"
        }
    ],
    "sg:phone":"+1 763 972 6593",
    "sg:postcode":"55328",
    "sg:province":"MN",
    "sg:tags":[
        "house"
    ],
    "wof:name":"Distinctive Homes & Remodeling",
    "wof:placetype":"venue"
},
  "geometry": {"coordinates":[-93.79946099999999,45.04475],"type":"Point"}
}