{
  "type": "Feature",
  "properties": {
    "addr:full":"723 S Woodlawn Ave Saint Paul MN 55116",
    "addr:housenumber":"723",
    "addr:postcode":"55116",
    "addr:street":"S Woodlawn Ave",
    "iso:country":"US",
    "sg:address":"723 S Woodlawn Ave",
    "sg:city":"Saint Paul",
    "sg:classifiers":[
        {
            "category":"Museum",
            "type":"Entertainment"
        }
    ],
    "sg:phone":"+1 651 698 4011",
    "sg:postcode":"55116",
    "sg:province":"MN",
    "sg:tags":[
        "gallery"
    ],
    "wof:name":"Music Museum of Minnesota",
    "wof:placetype":"venue"
},
  "geometry": {"coordinates":[-93.197062,44.91794],"type":"Point"}
}