{
  "type": "Feature",
  "properties": {
    "iso:country":"US",
    "sg:address":"1204 Paul Bunyan Dr NW",
    "sg:city":"Bemidji",
    "sg:classifiers":[
        {
            "category":"Real Estate",
            "subcategory":"Real Estate Agent",
            "type":"Services"
        }
    ],
    "sg:phone":"+1 218 444 0569",
    "sg:postcode":"56601",
    "sg:province":"MN",
    "wof:name":"Help U Sell",
    "wof:placetype":"venue"
},
  "geometry": {"coordinates":[-94.897966,47.492151],"type":"Point"}
}