{
  "type": "Feature",
  "properties": {
    "iso:country":"US",
    "sg:address":"2024 Lark Ln NW",
    "sg:city":"Stewartville",
    "sg:classifiers":[
        {
            "category":"Shopping",
            "subcategory":"Gifts & Souvenirs",
            "type":"Retail Goods"
        }
    ],
    "sg:phone":"+1 507 533 9195",
    "sg:postcode":"55976",
    "sg:province":"MN",
    "wof:name":"Gift Center",
    "wof:placetype":"venue"
},
  "geometry": {"coordinates":[-92.496567,43.871811],"type":"Point"}
}