{
  "type": "Feature",
  "properties": {
    "iso:country":"US",
    "sg:address":"10391 Golden Spike Rd NE",
    "sg:city":"Gilman",
    "sg:classifiers":[
        {
            "category":"Education",
            "subcategory":"Dance Studio",
            "type":"Public Place"
        }
    ],
    "sg:phone":"+1 320 387 3009",
    "sg:postcode":"56333",
    "sg:province":"MN",
    "sg:tags":[
        "instruction",
        "dancing"
    ],
    "wof:name":"Just For KIX Inc",
    "wof:placetype":"venue"
},
  "geometry": {"coordinates":[-93.94767299999999,45.735457],"type":"Point"}
}