{
  "type": "Feature",
  "properties": {
    "addr:full":"2935 Pierce St NE Minneapolis MN 55418",
    "addr:housenumber":"2935",
    "addr:postcode":"55418",
    "addr:street":"Pierce St Ne",
    "iso:country":"US",
    "sg:address":"2935 Pierce St NE",
    "sg:city":"Minneapolis",
    "sg:classifiers":[
        {
            "category":"Professional",
            "subcategory":"Art Services",
            "type":"Services"
        }
    ],
    "sg:phone":"+1 612 789 3192",
    "sg:postcode":"55418",
    "sg:province":"MN",
    "sg:tags":[
        "designer",
        "display",
        "producer"
    ],
    "wof:name":"Dan's Design",
    "wof:placetype":"venue"
},
  "geometry": {"coordinates":[-93.24095199999999,45.021047],"type":"Point"}
}