{
  "type": "Feature",
  "properties": {
    "addr:full":"9395 9th St NE St Michael MN 55376",
    "addr:housenumber":"9395",
    "addr:postcode":"55376",
    "addr:street":"9Th St Ne St",
    "iso:country":"US",
    "sg:address":"9395 9th St NE",
    "sg:city":"St Michael",
    "sg:classifiers":[
        {
            "category":"Building & Trades",
            "subcategory":"Landscaping Services",
            "type":"Services"
        }
    ],
    "sg:phone":"+1 763 497 5121",
    "sg:postcode":"55376",
    "sg:province":"MN",
    "sg:tags":[
        "lawn",
        "maintenance",
        "grounds"
    ],
    "wof:name":"Loch's Lawn & Landscaping Inc",
    "wof:placetype":"venue"
},
  "geometry": {"coordinates":[-93.69825899999999,45.167232],"type":"Point"}
}