{
  "type": "Feature",
  "properties": {
    "addr:full":"45501 Co Rd 133 Deer River MN 56636",
    "addr:housenumber":"45501",
    "addr:postcode":"56636",
    "addr:street":"Co Rd 133 Deer",
    "iso:country":"US",
    "sg:address":"45501 Co Rd 133",
    "sg:city":"Deer River",
    "sg:classifiers":[
        {
            "category":"Building & Trades",
            "subcategory":"Construction",
            "type":"Services"
        }
    ],
    "sg:phone":"+1 218 832 3603",
    "sg:postcode":"56636",
    "sg:province":"MN",
    "sg:tags":[
        "general",
        "contractor"
    ],
    "wof:name":"Curt Barrett Construction",
    "wof:placetype":"venue"
},
  "geometry": {"coordinates":[-93.820863,47.542407],"type":"Point"}
}