{
  "type": "Feature",
  "properties": {
    "iso:country":"US",
    "sg:address":"920 Apollo Rd",
    "sg:city":"Eagan",
    "sg:classifiers":[
        {
            "category":"Manufacturing",
            "subcategory":"Building Materials",
            "type":"Manufacturing & Wholesale Goods"
        },
        {
            "category":"Building & Trades",
            "subcategory":"Construction",
            "type":"Services"
        }
    ],
    "sg:phone":"+1 651 379 4622",
    "sg:postcode":"55121",
    "sg:province":"MN",
    "sg:tags":[
        "contractor"
    ],
    "sg:website":"www.strukturoc.com",
    "wof:name":"Transamerican Strukturoc",
    "wof:placetype":"venue"
},
  "geometry": {"coordinates":[-93.13126699999999,44.84503],"type":"Point"}
}