{
  "type": "Feature",
  "properties": {
    "addr:full":"905 Grant Ave SE Bemidji MN 56601",
    "addr:housenumber":"905",
    "addr:postcode":"56601",
    "addr:street":"Grant Ave Se",
    "iso:country":"US",
    "sg:address":"905 Grant Ave SE",
    "sg:city":"Bemidji",
    "sg:classifiers":[
        {
            "category":"Education",
            "subcategory":"Vocational School",
            "type":"Public Place"
        }
    ],
    "sg:phone":"+1 218 755 4594",
    "sg:postcode":"56601",
    "sg:province":"MN",
    "sg:tags":[
        "technical",
        "industrial",
        "business",
        "trade"
    ],
    "wof:name":"North Country Vocational Cooperative Center",
    "wof:placetype":"venue"
},
  "geometry": {"coordinates":[-94.85312399999999,47.453361],"type":"Point"}
}