{
  "type": "Feature",
  "properties": {
    "iso:country":"US",
    "sg:address":"3563 Co Rd 21",
    "sg:city":"Internatl Falls",
    "sg:classifiers":[
        {
            "category":"Insurance",
            "subcategory":"Insurance Agent",
            "type":"Services"
        }
    ],
    "sg:phone":"+1 218 286 5508",
    "sg:postcode":"56649",
    "sg:province":"MN",
    "wof:name":"Briese Insurance",
    "wof:placetype":"venue"
},
  "geometry": {"coordinates":[-93.36148,48.60667],"type":"Point"}
}