{
  "type": "Feature",
  "properties": {
    "addr:full":"3563 Co Rd 21 Internatl Falls MN 56649",
    "addr:housenumber":"3563;21",
    "addr:postcode":"56649",
    "addr:street":"Co Rd;Falls",
    "iso:country":"US",
    "sg:address":"3563 Co Rd 21",
    "sg:city":"Internatl Falls",
    "sg:classifiers":[
        {
            "category":"Insurance",
            "subcategory":"Insurance Agent",
            "type":"Services"
        }
    ],
    "sg:phone":"+1 218 286 5508",
    "sg:postcode":"56649",
    "sg:province":"MN",
    "wof:name":"Briese Insurance",
    "wof:placetype":"venue"
},
  "geometry": {"coordinates":[-93.36148,48.60667],"type":"Point"}
}