{
  "type": "Feature",
  "properties": {
    "addr:full":"629 N 11th St Montevideo MN 56265",
    "addr:housenumber":"629",
    "addr:postcode":"56265",
    "addr:street":"N 11Th St",
    "iso:country":"US",
    "sg:address":"629 N 11th St",
    "sg:city":"Montevideo",
    "sg:classifiers":[
        {
            "category":"Government",
            "subcategory":"Office",
            "type":"Public Place"
        }
    ],
    "sg:phone":"+1 320 269 7447",
    "sg:postcode":"56265",
    "sg:province":"MN",
    "sg:tags":[
        "executive"
    ],
    "wof:name":"County of Chippewa",
    "wof:placetype":"venue"
},
  "geometry": {"coordinates":[-95.7136,44.950127],"type":"Point"}
}