{
  "type": "Feature",
  "properties": {
    "addr:full":"8023 50th Ave NE Elgin MN 55932",
    "addr:housenumber":"8023",
    "addr:postcode":"55932",
    "addr:street":"50Th Ave Ne",
    "iso:country":"US",
    "sg:address":"8023 50th Ave NE",
    "sg:city":"Elgin",
    "sg:phone":"+1 507 282 3697",
    "sg:postcode":"55932",
    "sg:province":"MN",
    "sg:tags":[
        "farm",
        "corn"
    ],
    "wof:name":"Franklin OHM",
    "wof:placetype":"venue"
},
  "geometry": {"coordinates":[-92.37912,44.115494],"type":"Point"}
}