{
  "type": "Feature",
  "properties": {
    "addr:full":"3620 3rd St N Saint Cloud MN 56303",
    "addr:housenumber":"3620",
    "addr:postcode":"56303",
    "addr:street":"3Rd St N",
    "iso:country":"US",
    "sg:address":"3620 3rd St N",
    "sg:city":"Saint Cloud",
    "sg:classifiers":[
        {
            "category":"Professional",
            "subcategory":"Management & Consulting",
            "type":"Services"
        }
    ],
    "sg:phone":"+1 320 253 8881",
    "sg:postcode":"56303",
    "sg:province":"MN",
    "wof:name":"S B R Motel Management",
    "wof:placetype":"venue"
},
  "geometry": {"coordinates":[-94.203138,45.558534],"type":"Point"}
}