{
  "type": "Feature",
  "properties": {
    "addr:full":"13645 Co Rd 2 Osakis MN 56360",
    "addr:housenumber":"13645",
    "addr:postcode":"56360",
    "addr:street":"Co Rd 2",
    "iso:country":"US",
    "sg:address":"13645 Co Rd 2",
    "sg:city":"Osakis",
    "sg:classifiers":[
        {
            "category":"Travel",
            "subcategory":"Hotels & Motels",
            "type":"Entertainment"
        }
    ],
    "sg:phone":"+1 320 859 2247",
    "sg:postcode":"56360",
    "sg:province":"MN",
    "sg:tags":[
        "resort"
    ],
    "wof:name":"Jim & Betty's Trailer Court",
    "wof:placetype":"venue"
},
  "geometry": {"coordinates":[-95.092392,45.827794],"type":"Point"}
}