{
  "type": "Feature",
  "properties": {
    "addr:full":"10008 Monticello Ln N Osseo MN 55369",
    "addr:housenumber":"10008",
    "addr:postcode":"55369",
    "addr:street":"Monticello Ln N",
    "iso:country":"US",
    "sg:address":"10008 Monticello Ln N",
    "sg:city":"Osseo",
    "sg:classifiers":[
        {
            "category":"Professional",
            "subcategory":"Business Services",
            "type":"Services"
        }
    ],
    "sg:phone":"+1 763 425 5539",
    "sg:postcode":"55369",
    "sg:province":"MN",
    "sg:tags":[
        "consulting",
        "management"
    ],
    "wof:name":"Primerica",
    "wof:placetype":"venue"
},
  "geometry": {"coordinates":[-93.402376,45.136307],"type":"Point"}
}