{
  "type": "Feature",
  "properties": {
    "addr:full":"5917 Zenith Ave S Edina MN 55410",
    "addr:housenumber":"5917",
    "addr:postcode":"55410",
    "addr:street":"Zenith Ave S",
    "iso:country":"US",
    "sg:address":"5917 Zenith Ave S",
    "sg:city":"Edina",
    "sg:classifiers":[
        {
            "category":"Insurance",
            "subcategory":"Insurance Agent",
            "type":"Services"
        }
    ],
    "sg:phone":"+1 952 929 9119",
    "sg:postcode":"55410",
    "sg:province":"MN",
    "wof:name":"Long Term Care Assoc",
    "wof:placetype":"venue"
},
  "geometry": {"coordinates":[-93.321298,44.894707],"type":"Point"}
}