{
  "type": "Feature",
  "properties": {
    "iso:country":"US",
    "sg:address":"12225 W Savanna Rd",
    "sg:city":"Floodwood",
    "sg:classifiers":[
        {
            "category":"Social Services",
            "subcategory":"Child Care",
            "type":"Services"
        }
    ],
    "sg:phone":"+1 218 476 2929",
    "sg:postcode":"55736",
    "sg:province":"MN",
    "sg:tags":[
        "centers-adult",
        "day",
        "provider"
    ],
    "wof:name":"Cheryl J Heikkila",
    "wof:placetype":"venue"
},
  "geometry": {"coordinates":[-92.963206,47.098901],"type":"Point"}
}