{
  "type": "Feature",
  "properties": {
    "addr:full":"619 S 7th St Minneapolis MN 55415",
    "addr:housenumber":"619",
    "addr:postcode":"55415",
    "addr:street":"S 7Th St",
    "iso:country":"US",
    "sg:address":"619 S 7th St",
    "sg:city":"Minneapolis",
    "sg:classifiers":[
        {
            "category":"Retail",
            "subcategory":"Auto Repair",
            "type":"Services"
        }
    ],
    "sg:phone":"+1 612 333 1339",
    "sg:postcode":"55415",
    "sg:province":"MN",
    "sg:tags":[
        "body",
        "shop",
        "automobile",
        "painting",
        "repairing"
    ],
    "sg:website":"www.lehmansgarage.com",
    "wof:name":"Lehman's Garage, Inc",
    "wof:placetype":"venue"
},
  "geometry": {"coordinates":[-93.263246,44.972836],"type":"Point"}
}