{
  "type": "Feature",
  "properties": {
    "iso:country":"US",
    "sg:address":"416 2nd Ave",
    "sg:city":"Madison",
    "sg:classifiers":[
        {
            "category":"Social Services",
            "subcategory":"Child Care",
            "type":"Services"
        }
    ],
    "sg:phone":"+1 320 598 3049",
    "sg:postcode":"56256",
    "sg:province":"MN",
    "sg:tags":[
        "day",
        "provider"
    ],
    "wof:name":"Linda J Young",
    "wof:placetype":"venue"
},
  "geometry": {"coordinates":[-96.187344,45.013165],"type":"Point"}
}