{
  "type": "Feature",
  "properties": {
    "addr:full":"17865 Italy Path Lakeville MN 55044",
    "addr:postcode":"17865;55044",
    "addr:street":"Italy Path",
    "iso:country":"US",
    "sg:address":"17865 Italy Path",
    "sg:city":"Lakeville",
    "sg:classifiers":[
        {
            "category":"Wholesale",
            "subcategory":"Apparel",
            "type":"Manufacturing & Wholesale Goods"
        }
    ],
    "sg:phone":"+1 952 435 5294",
    "sg:postcode":"55044",
    "sg:province":"MN",
    "sg:tags":[
        "sportswear"
    ],
    "wof:name":"Peter Jackson Sales-Marketing",
    "wof:placetype":"venue"
},
  "geometry": {"coordinates":[-93.263384,44.691713],"type":"Point"}
}