{
  "type": "Feature",
  "properties": {
    "addr:full":"7416 James Ave N Minneapolis MN 55444",
    "addr:housenumber":"7416",
    "addr:postcode":"55444",
    "addr:street":"James Ave N",
    "iso:country":"US",
    "sg:address":"7416 James Ave N",
    "sg:city":"Minneapolis",
    "sg:classifiers":[
        {
            "category":"Social Services",
            "subcategory":"Child Care",
            "type":"Services"
        }
    ],
    "sg:phone":"+1 763 561 0233",
    "sg:postcode":"55444",
    "sg:province":"MN",
    "sg:tags":[
        "day"
    ],
    "wof:name":"Debra L Panek",
    "wof:placetype":"venue"
},
  "geometry": {"coordinates":[-93.303709,45.094263],"type":"Point"}
}