{
  "type": "Feature",
  "properties": {
    "addr:full":"229 3rd Ave NE Austin MN 55912",
    "addr:housenumber":"229",
    "addr:postcode":"55912",
    "addr:street":"3Rd Ave Ne",
    "iso:country":"US",
    "sg:address":"229 3rd Ave NE",
    "sg:city":"Austin",
    "sg:classifiers":[
        {
            "category":"Shopping",
            "subcategory":"Discount & Variety Stores",
            "type":"Retail Goods"
        }
    ],
    "sg:phone":"+1 507 434 7781",
    "sg:postcode":"55912",
    "sg:province":"MN",
    "sg:tags":[
        "merchandise",
        "general"
    ],
    "wof:name":"El Talacio De La Cumbia",
    "wof:placetype":"venue"
},
  "geometry": {"coordinates":[-92.97320999999999,43.66927],"type":"Point"}
}