{
  "type": "Feature",
  "properties": {
    "iso:country":"US",
    "sg:address":"22112 530th St",
    "sg:city":"West Concord",
    "sg:phone":"+1 507 527 2133",
    "sg:postcode":"55985",
    "sg:province":"MN",
    "sg:tags":[
        "farm",
        "corn",
        "soybean"
    ],
    "wof:name":"Kerry Glarner",
    "wof:placetype":"venue"
},
  "geometry": {"coordinates":[-92.795863,44.181498],"type":"Point"}
}