{
  "type": "Feature",
  "properties": {
    "addr:full":"811 3rd St Carlton MN 55718",
    "addr:housenumber":"811",
    "addr:postcode":"55718",
    "addr:street":"3Rd St",
    "iso:country":"US",
    "sg:address":"811 3rd St",
    "sg:city":"Carlton",
    "sg:classifiers":[
        {
            "category":"Health Services",
            "subcategory":"Nursing And Care Facility",
            "type":"Services"
        }
    ],
    "sg:phone":"+1 218 384 4258",
    "sg:postcode":"55718",
    "sg:province":"MN",
    "sg:tags":[
        "home",
        "convalescent"
    ],
    "wof:name":"Inter-Faith Care Ctr",
    "wof:placetype":"venue"
},
  "geometry": {"coordinates":[-92.42434900000001,46.670439],"type":"Point"}
}