{
  "type": "Feature",
  "properties": {
    "addr:full":"7710 Golden Triangle Dr Eden Prairie MN 55344",
    "addr:housenumber":"7710",
    "addr:postcode":"55344",
    "addr:street":"Golden Triangle Dr",
    "iso:country":"US",
    "sg:address":"7710 Golden Triangle Dr",
    "sg:city":"Eden Prairie",
    "sg:classifiers":[
        {
            "category":"Real Estate",
            "subcategory":"Architect",
            "type":"Services"
        }
    ],
    "sg:phone":"+1 952 943 9660",
    "sg:postcode":"55344",
    "sg:province":"MN",
    "sg:tags":[
        "firm",
        "architectural"
    ],
    "wof:name":"Edward Farr Architects Inc",
    "wof:placetype":"venue"
},
  "geometry": {"coordinates":[-93.406025,44.862839],"type":"Point"}
}