{
  "type": "Feature",
  "properties": {
    "iso:country":"US",
    "sg:address":"5432 43rd Ave S",
    "sg:city":"Minneapolis",
    "sg:classifiers":[
        {
            "category":"Building & Trades",
            "subcategory":"Construction",
            "type":"Services"
        }
    ],
    "sg:phone":"+1 612 727 2866",
    "sg:postcode":"55417",
    "sg:province":"MN",
    "sg:tags":[
        "house"
    ],
    "wof:name":"James P Papke",
    "wof:placetype":"venue"
},
  "geometry": {"coordinates":[-93.211502,44.904177],"type":"Point"}
}