{
  "type": "Feature",
  "properties": {
    "iso:country":"US",
    "sg:address":"733 E Academy St",
    "sg:city":"Owatonna",
    "sg:phone":"+1 507 451 0938",
    "sg:postcode":"55060",
    "sg:province":"MN",
    "sg:tags":[
        "farm",
        "soybean"
    ],
    "wof:name":"James Hammann",
    "wof:placetype":"venue"
},
  "geometry": {"coordinates":[-93.210649,44.081399],"type":"Point"}
}