{
  "type": "Feature",
  "properties": {
    "addr:full":"4940 Viking Dr Minneapolis MN 55435",
    "addr:housenumber":"4940",
    "addr:postcode":"55435",
    "addr:street":"Viking Dr",
    "iso:country":"US",
    "sg:address":"4940 Viking Dr",
    "sg:city":"Minneapolis",
    "sg:classifiers":[
        {
            "category":"Real Estate",
            "subcategory":"Real Estate Agent",
            "type":"Services"
        }
    ],
    "sg:phone":"+1 952 831 3300",
    "sg:postcode":"55435",
    "sg:province":"MN",
    "sg:website":"http://www.calhouncompanies.com",
    "wof:name":"Calhoun Companies",
    "wof:placetype":"venue"
},
  "geometry": {"coordinates":[-93.34584700000001,44.861974],"type":"Point"}
}