{
  "type": "Feature",
  "properties": {
    "addr:full":"4276 165th Ave NW Anoka MN 55304",
    "addr:housenumber":"4276",
    "addr:postcode":"55304",
    "addr:street":"165Th Ave Nw",
    "iso:country":"US",
    "sg:address":"4276 165th Ave NW",
    "sg:city":"Anoka",
    "sg:classifiers":[
        {
            "category":"Wholesale",
            "subcategory":"Metals & Minerals",
            "type":"Manufacturing & Wholesale Goods"
        }
    ],
    "sg:phone":"+1 763 421 6098",
    "sg:postcode":"55304",
    "sg:province":"MN",
    "sg:tags":[
        "steel",
        "broker",
        "manufacturer"
    ],
    "wof:name":"All Metal Supply Inc",
    "wof:placetype":"venue"
},
  "geometry": {"coordinates":[-93.371983,45.270174],"type":"Point"}
}