{
  "type": "Feature",
  "properties": {
    "addr:full":"5250 US Hwy 61 Saint Paul MN 55110",
    "addr:housenumber":"5250",
    "addr:postcode":"55110",
    "addr:street":"Us Hwy 61",
    "iso:country":"US",
    "sg:address":"5250 US Hwy 61",
    "sg:city":"Saint Paul",
    "sg:classifiers":[
        {
            "category":"Home & Garden",
            "subcategory":"Carpets & Floor Coverings",
            "type":"Retail Goods"
        }
    ],
    "sg:phone":"+1 651 762 1595",
    "sg:postcode":"55110",
    "sg:province":"MN",
    "wof:name":"Catalina Carpets",
    "wof:placetype":"venue"
},
  "geometry": {"coordinates":[-93.001604,45.101582],"type":"Point"}
}