{
  "type": "Feature",
  "properties": {
    "addr:full":"3658 Woodthrush Ct Saint Paul MN 55123",
    "addr:postcode":"3658;55123",
    "addr:street":"Woodthrush Ct",
    "iso:country":"US",
    "sg:address":"3658 Woodthrush Ct",
    "sg:city":"Saint Paul",
    "sg:classifiers":[
        {
            "category":"Professional",
            "subcategory":"Business Services",
            "type":"Services"
        }
    ],
    "sg:phone":"+1 651 686 6264",
    "sg:postcode":"55123",
    "sg:province":"MN",
    "sg:tags":[
        "computer",
        "related"
    ],
    "wof:name":"Olsen & Associates Wayne S",
    "wof:placetype":"venue"
},
  "geometry": {"coordinates":[-93.15300499999999,44.824244],"type":"Point"}
}