{
  "type": "Feature",
  "properties": {
    "addr:full":"702 2nd St NE Aitkin MN 56431",
    "addr:housenumber":"702",
    "addr:postcode":"56431",
    "addr:street":"2Nd St Ne",
    "iso:country":"US",
    "sg:address":"702 2nd St NE",
    "sg:city":"Aitkin",
    "sg:classifiers":[
        {
            "category":"Farming",
            "subcategory":"Farm",
            "type":"Manufacturing & Wholesale Goods"
        }
    ],
    "sg:phone":"+1 218 927 3320",
    "sg:postcode":"56431",
    "sg:province":"MN",
    "wof:name":"Thompson Farms",
    "wof:placetype":"venue"
},
  "geometry": {"coordinates":[-93.69604,46.533449],"type":"Point"}
}