{
  "type": "Feature",
  "properties": {
    "addr:full":"3453 Zimmerman Rd Duluth MN 55804",
    "addr:housenumber":"3453",
    "addr:postcode":"55804",
    "addr:street":"Zimmerman Rd",
    "iso:country":"US",
    "sg:address":"3453 Zimmerman Rd",
    "sg:city":"Duluth",
    "sg:classifiers":[
        {
            "category":"Utilities",
            "subcategory":"Sewage",
            "type":"Services"
        },
        {
            "category":"Building & Trades",
            "subcategory":"Plumbing",
            "type":"Services"
        },
        {
            "category":"Building & Trades",
            "subcategory":"Construction",
            "type":"Services"
        },
        {
            "category":"Building & Trades",
            "subcategory":"Cleaning & Sanitation",
            "type":"Services"
        }
    ],
    "sg:phone":"+1 218 525 2331",
    "sg:postcode":"55804",
    "sg:province":"MN",
    "sg:tags":[
        "cleaner",
        "excavation",
        "repairer",
        "specialty",
        "system",
        "contractor",
        "heating",
        "plumbing-drain",
        "air conditioning",
        "sewer"
    ],
    "sg:website":"http://www.levinecontractors.com",
    "wof:name":"Levine & Son, Inc",
    "wof:placetype":"venue"
},
  "geometry": {"coordinates":[-92.047978,46.930908],"type":"Point"}
}