{
  "type": "Feature",
  "properties": {
    "iso:country":"US",
    "sg:address":"390 93rd Ave NW",
    "sg:city":"Minneapolis",
    "sg:classifiers":[
        {
            "category":"Wholesale",
            "subcategory":"Office Equipment",
            "type":"Manufacturing & Wholesale Goods"
        }
    ],
    "sg:phone":"+1 763 717 1710",
    "sg:postcode":"55433",
    "sg:province":"MN",
    "sg:tags":[
        "equipment-wholesale",
        "manufacturer",
        "furniture"
    ],
    "sg:website":"http://www.oebinc.com",
    "wof:name":"O E B",
    "wof:placetype":"venue"
},
  "geometry": {"coordinates":[-93.277592,45.138524],"type":"Point"}
}