{
  "type": "Feature",
  "properties": {
    "addr:full":"1009 Main St E Wabasha MN 55981",
    "addr:housenumber":"1009",
    "addr:postcode":"55981",
    "addr:street":"Main St E",
    "iso:country":"US",
    "sg:address":"1009 Main St E",
    "sg:city":"Wabasha",
    "sg:classifiers":[
        {
            "category":"Building & Trades",
            "subcategory":"Equipment Rental",
            "type":"Services"
        }
    ],
    "sg:phone":"+1 651 565 3376",
    "sg:postcode":"55981",
    "sg:province":"MN",
    "wof:name":"Great River Houseboat Rental",
    "wof:placetype":"venue"
},
  "geometry": {"coordinates":[-92.021378,44.379152],"type":"Point"}
}