{
  "type": "Feature",
  "properties": {
    "iso:country":"US",
    "sg:address":"4986 Xylon Ave N",
    "sg:city":"Minneapolis",
    "sg:classifiers":[
        {
            "category":"Autos & Motor Vehicles",
            "subcategory":"Automobile Sales",
            "type":"Retail Goods"
        }
    ],
    "sg:phone":"+1 763 537 8600",
    "sg:postcode":"55428",
    "sg:province":"MN",
    "sg:tags":[
        "new",
        "car"
    ],
    "wof:name":"Automotive Buyer's Assistance",
    "wof:placetype":"venue"
},
  "geometry": {"coordinates":[-93.384671,45.045357],"type":"Point"}
}