{
  "type": "Feature",
  "properties": {
    "addr:full":"4820 Park Glen Rd Minneapolis MN 55416",
    "addr:housenumber":"4820",
    "addr:postcode":"55416",
    "addr:street":"Park Glen Rd",
    "iso:country":"US",
    "sg:address":"4820 Park Glen Rd",
    "sg:city":"Minneapolis",
    "sg:classifiers":[
        {
            "category":"Wholesale",
            "subcategory":"Medical Equipment & Supplies",
            "type":"Manufacturing & Wholesale Goods"
        },
        {
            "category":"Building & Trades",
            "subcategory":"Equipment Rental",
            "type":"Services"
        }
    ],
    "sg:phone":"+1 952 920 0460",
    "sg:postcode":"55416",
    "sg:province":"MN",
    "sg:tags":[
        "physician",
        "surgeon",
        "m"
    ],
    "wof:name":"Liberty Oxygen & Home Care Inc",
    "wof:placetype":"venue"
},
  "geometry": {"coordinates":[-93.342842,44.941624],"type":"Point"}
}