{
  "type": "Feature",
  "properties": {
    "iso:country":"US",
    "sg:address":"5175 260th St",
    "sg:city":"Wyoming",
    "sg:classifiers":[
        {
            "category":"Manufacturing",
            "subcategory":"Glass & Minerals",
            "type":"Manufacturing & Wholesale Goods"
        }
    ],
    "sg:phone":"+1 651 462 5313",
    "sg:postcode":"55092",
    "sg:province":"MN",
    "sg:tags":[
        "fabricator",
        "fiber"
    ],
    "sg:website":"www.sunrisefiberglass.com",
    "wof:name":"Sunrise Fiberglass Corp",
    "wof:placetype":"venue"
},
  "geometry": {"coordinates":[-93.001132,45.325635],"type":"Point"}
}