{
  "type": "Feature",
  "properties": {
    "iso:country":"US",
    "sg:address":"1211 1st Ave NE",
    "sg:city":"Austin",
    "sg:classifiers":[
        {
            "category":"Taxi",
            "type":"Transportation"
        }
    ],
    "sg:phone":"+1 507 434 9689",
    "sg:postcode":"55912",
    "sg:province":"MN",
    "sg:tags":[
        "taxicab"
    ],
    "wof:name":"A B Taxi",
    "wof:placetype":"venue"
},
  "geometry": {"coordinates":[-92.958673,43.667754],"type":"Point"}
}