{
  "type": "Feature",
  "properties": {
    "iso:country":"US",
    "sg:address":"600 Hoover St NE",
    "sg:city":"Minneapolis",
    "sg:classifiers":[
        {
            "category":"Manufacturing",
            "subcategory":"Petroleum Products",
            "type":"Manufacturing & Wholesale Goods"
        }
    ],
    "sg:phone":"+1 612 623 1588",
    "sg:postcode":"55413",
    "sg:province":"MN",
    "sg:tags":[
        "contract"
    ],
    "wof:name":"Gresen Manufacturing",
    "wof:placetype":"venue"
},
  "geometry": {"coordinates":[-93.21772,44.995258],"type":"Point"}
}