{
  "type": "Feature",
  "properties": {
    "addr:full":"190 Central Ave S Milaca MN 56353",
    "addr:housenumber":"190",
    "addr:postcode":"56353",
    "addr:street":"Central Ave S Milaca",
    "iso:country":"US",
    "sg:address":"190 Central Ave S",
    "sg:city":"Milaca",
    "sg:classifiers":[
        {
            "category":"Insurance",
            "subcategory":"Insurance Agent",
            "type":"Services"
        }
    ],
    "sg:phone":"+1 320 983 6444",
    "sg:postcode":"56353",
    "sg:province":"MN",
    "wof:name":"Citizens Insurance Co",
    "wof:placetype":"venue"
},
  "geometry": {"coordinates":[-93.651439,45.753886],"type":"Point"}
}