{
  "type": "Feature",
  "properties": {
    "addr:full":"5285 Miller Trunk Hwy Duluth MN 55811",
    "addr:housenumber":"5285",
    "addr:postcode":"55811",
    "addr:street":"Miller Trunk Hwy",
    "iso:country":"US",
    "sg:address":"5285 Miller Trunk Hwy",
    "sg:city":"Duluth",
    "sg:classifiers":[
        {
            "category":"Retail",
            "subcategory":"Veterinary Services",
            "type":"Services"
        }
    ],
    "sg:phone":"+1 218 729 7959",
    "sg:postcode":"55811",
    "sg:province":"MN",
    "sg:tags":[
        "veterinarian"
    ],
    "wof:name":"Miller Trunk Veterinary Clinic",
    "wof:placetype":"venue"
},
  "geometry": {"coordinates":[-92.229302,46.83675],"type":"Point"}
}