{
  "type": "Feature",
  "properties": {
    "addr:full":"208 Cofield St Raymond MN 56282",
    "addr:housenumber":"208",
    "addr:postcode":"56282",
    "addr:street":"Cofield St",
    "iso:country":"US",
    "sg:address":"208 Cofield St",
    "sg:city":"Raymond",
    "sg:classifiers":[
        {
            "category":"Government",
            "subcategory":"Office",
            "type":"Public Place"
        }
    ],
    "sg:phone":"+1 320 967 4226",
    "sg:postcode":"56282",
    "sg:province":"MN",
    "sg:tags":[
        "village"
    ],
    "wof:name":"Raymond City Office",
    "wof:placetype":"venue"
},
  "geometry": {"coordinates":[-95.239965,45.017171],"type":"Point"}
}