{
  "type": "Feature",
  "properties": {
    "iso:country":"US",
    "sg:address":"6100 389th St",
    "sg:city":"Saint Cloud",
    "sg:classifiers":[
        {
            "category":"Social Services",
            "subcategory":"Child Care",
            "type":"Services"
        }
    ],
    "sg:phone":"+1 320 255 0402",
    "sg:postcode":"56377",
    "sg:province":"MN",
    "sg:tags":[
        "day",
        "provider"
    ],
    "wof:name":"Larson Daycare",
    "wof:placetype":"venue"
},
  "geometry": {"coordinates":[-94.235687,45.686664],"type":"Point"}
}