{
  "type": "Feature",
  "properties": {
    "iso:country":"US",
    "sg:address":"10130 32nd Ave N",
    "sg:city":"Minneapolis",
    "sg:classifiers":[
        {
            "category":"Professional",
            "type":"Services"
        }
    ],
    "sg:phone":"+1 763 541 4920",
    "sg:postcode":"55441",
    "sg:province":"MN",
    "wof:name":"Julie Serbers Music Studio",
    "wof:placetype":"venue"
},
  "geometry": {"coordinates":[-93.410388,45.016422],"type":"Point"}
}