{
  "type": "Feature",
  "properties": {
    "addr:full":"11382 Burr Ridge Ln Eden Prairie MN 55347",
    "addr:housenumber":"11382",
    "addr:postcode":"55347",
    "addr:street":"Burr Ridge Ln",
    "iso:country":"US",
    "sg:address":"11382 Burr Ridge Ln",
    "sg:city":"Eden Prairie",
    "sg:classifiers":[
        {
            "category":"Professional",
            "subcategory":"Management & Consulting",
            "type":"Services"
        },
        {
            "category":"Manufacturing",
            "subcategory":"Tools & Machinery",
            "type":"Manufacturing & Wholesale Goods"
        }
    ],
    "sg:phone":"+1 952 995 9502",
    "sg:postcode":"55347",
    "sg:province":"MN",
    "sg:tags":[
        "distributor",
        "consultant",
        "automation"
    ],
    "wof:name":"Automation & Control Sys Sups",
    "wof:placetype":"venue"
},
  "geometry": {"coordinates":[-93.421426,44.818478],"type":"Point"}
}