{
  "type": "Feature",
  "properties": {
    "addr:full":"1372 Knollwood Ln Saint Paul MN 55118",
    "addr:housenumber":"1372",
    "addr:postcode":"55118",
    "addr:street":"Knollwood Ln",
    "iso:country":"US",
    "sg:address":"1372 Knollwood Ln",
    "sg:city":"Saint Paul",
    "sg:classifiers":[
        {
            "category":"Professional",
            "type":"Services"
        }
    ],
    "sg:phone":"+1 651 686 7875",
    "sg:postcode":"55118",
    "sg:province":"MN",
    "wof:name":"Traditions of Land Inc",
    "wof:placetype":"venue"
},
  "geometry": {"coordinates":[-93.12298199999999,44.903054],"type":"Point"}
}