{
  "type": "Feature",
  "properties": {
    "addr:full":"17472 Goodland Path Lakeville MN 55044",
    "addr:postcode":"17472;55044",
    "addr:street":"Goodland Path",
    "iso:country":"US",
    "sg:address":"17472 Goodland Path",
    "sg:city":"Lakeville",
    "sg:classifiers":[
        {
            "category":"Wholesale",
            "subcategory":"Hardware",
            "type":"Manufacturing & Wholesale Goods"
        }
    ],
    "sg:phone":"+1 952 431 2224",
    "sg:postcode":"55044",
    "sg:province":"MN",
    "sg:tags":[
        "plumbing",
        "merchandise"
    ],
    "wof:name":"Water Filtration & Cond",
    "wof:placetype":"venue"
},
  "geometry": {"coordinates":[-93.226366,44.695472],"type":"Point"}
}