{
  "type": "Feature",
  "properties": {
    "iso:country":"US",
    "sg:address":"12176 W Fine Lakes Rd",
    "sg:city":"Floodwood",
    "sg:classifiers":[
        {
            "category":"Shopping",
            "subcategory":"Clothing, Apparel, & Fashions",
            "type":"Retail Goods"
        }
    ],
    "sg:phone":"+1 218 476 2727",
    "sg:postcode":"55736",
    "sg:province":"MN",
    "wof:name":"Designing Woman",
    "wof:placetype":"venue"
},
  "geometry": {"coordinates":[-92.960763,46.91076],"type":"Point"}
}