{
  "type": "Feature",
  "properties": {
    "iso:country":"US",
    "sg:address":"299 5th Ave SW # 200",
    "sg:city":"Saint Paul",
    "sg:classifiers":[
        {
            "category":"Retail",
            "subcategory":"Auto Repair",
            "type":"Services"
        }
    ],
    "sg:phone":"+1 651 766 0927",
    "sg:postcode":"55112",
    "sg:province":"MN",
    "wof:name":"Fuhr Enterprises",
    "wof:placetype":"venue"
},
  "geometry": {"coordinates":[-93.19319900000001,45.048302],"type":"Point"}
}