{
  "type": "Feature",
  "properties": {
    "iso:country":"US",
    "sg:address":"18656 Primrose Rd NE",
    "sg:city":"Miltona",
    "sg:phone":"+1 218 943 4614",
    "sg:postcode":"56354",
    "sg:province":"MN",
    "sg:tags":[
        "farm",
        "corn",
        "grain",
        "cash"
    ],
    "wof:name":"Darrel Pexsa",
    "wof:placetype":"venue"
},
  "geometry": {"coordinates":[-95.24997,46.092119],"type":"Point"}
}