{
  "type": "Feature",
  "properties": {
    "addr:full":"11500 State Hwy 18 Finlayson MN 55735",
    "addr:housenumber":"11500",
    "addr:postcode":"55735",
    "addr:street":"State Hwy 18 Finlayson",
    "iso:country":"US",
    "sg:address":"11500 State Hwy 18",
    "sg:city":"Finlayson",
    "sg:classifiers":[
        {
            "category":"Wholesale",
            "subcategory":"Electrical",
            "type":"Manufacturing & Wholesale Goods"
        }
    ],
    "sg:phone":"+1 320 233 7302",
    "sg:postcode":"55735",
    "sg:province":"MN",
    "sg:tags":[
        "repair",
        "electronic"
    ],
    "wof:name":"Pine Lake Communications",
    "wof:placetype":"venue"
},
  "geometry": {"coordinates":[-93.087169,46.216193],"type":"Point"}
}