{
  "type": "Feature",
  "properties": {
    "addr:full":"1529 Old W Main St Red Wing MN 55066",
    "addr:housenumber":"1529",
    "addr:postcode":"55066",
    "addr:street":"Old W Main St",
    "iso:country":"US",
    "sg:address":"1529 Old W Main St",
    "sg:city":"Red Wing",
    "sg:classifiers":[
        {
            "category":"Professional",
            "type":"Services"
        }
    ],
    "sg:phone":"+1 651 388 6584",
    "sg:postcode":"55066",
    "sg:province":"MN",
    "wof:name":"Goodhue County Democrats",
    "wof:placetype":"venue"
},
  "geometry": {"coordinates":[-92.549142,44.563039],"type":"Point"}
}