{
  "type": "Feature",
  "properties": {
    "addr:full":"201 W Burnsville Pkwy Burnsville MN 55337",
    "addr:housenumber":"201",
    "addr:postcode":"55337",
    "addr:street":"W Burnsville Pkwy",
    "iso:country":"US",
    "sg:address":"201 W Burnsville Pkwy",
    "sg:city":"Burnsville",
    "sg:classifiers":[
        {
            "category":"Personal",
            "subcategory":"Beauty Salon",
            "type":"Services"
        }
    ],
    "sg:phone":"+1 952 912 0700",
    "sg:postcode":"55337",
    "sg:province":"MN",
    "sg:tags":[
        "spa",
        "day"
    ],
    "sg:website":"www.shadyoakplace.com",
    "wof:name":"Shady Oak Place",
    "wof:placetype":"venue"
},
  "geometry": {"coordinates":[-93.280603,44.771526],"type":"Point"}
}