{
  "type": "Feature",
  "properties": {
    "addr:full":"161 Centre St E Vesta MN 56292",
    "addr:housenumber":"161",
    "addr:postcode":"56292",
    "addr:street":"Centre St E Vesta",
    "iso:country":"US",
    "sg:address":"161 Centre St E",
    "sg:city":"Vesta",
    "sg:classifiers":[
        {
            "category":"Wholesale",
            "subcategory":"Meat",
            "type":"Manufacturing & Wholesale Goods"
        }
    ],
    "sg:phone":"+1 507 762 3303",
    "sg:postcode":"56292",
    "sg:province":"MN",
    "sg:tags":[
        "packer",
        "equipment",
        "supply"
    ],
    "wof:name":"Vesta Processing & Meat Services",
    "wof:placetype":"venue"
},
  "geometry": {"coordinates":[-95.417438,44.507799],"type":"Point"}
}