{
  "type": "Feature",
  "properties": {
    "iso:country":"US",
    "sg:address":"130 N Garden",
    "sg:city":"Minneapolis",
    "sg:classifiers":[
        {
            "category":"Restaurant",
            "type":"Food & Drink"
        }
    ],
    "sg:phone":"+1 952 854 0200",
    "sg:postcode":"55425",
    "sg:province":"MN",
    "sg:tags":[
        "grill",
        "bar"
    ],
    "wof:name":"Twin City Grill",
    "wof:placetype":"venue"
},
  "geometry": {"coordinates":[-93.240588,44.856073],"type":"Point"}
}