{
  "type": "Feature",
  "properties": {
    "addr:full":"11331 Highway 15 Brownton MN 55312",
    "addr:housenumber":"11331",
    "addr:postcode":"55312",
    "addr:street":"Highway 15 Brownton",
    "iso:country":"US",
    "sg:address":"11331 Highway 15",
    "sg:city":"Brownton",
    "sg:classifiers":[
        {
            "category":"Restaurant",
            "type":"Food & Drink"
        }
    ],
    "sg:phone":"+1 320 328 4111",
    "sg:postcode":"55312",
    "sg:province":"MN",
    "sg:tags":[
        "american"
    ],
    "wof:name":"Lake Marion Supper Club",
    "wof:placetype":"venue"
},
  "geometry": {"coordinates":[-94.375393,44.779431],"type":"Point"}
}