{
  "type": "Feature",
  "properties": {
    "iso:country":"US",
    "sg:address":"11520 Kelly Ave",
    "sg:city":"Cologne",
    "sg:classifiers":[
        {
            "category":"Utilities",
            "subcategory":"Water",
            "type":"Services"
        },
        {
            "category":"Building & Trades",
            "subcategory":"Plumbing",
            "type":"Services"
        },
        {
            "category":"Home & Garden",
            "subcategory":"Hardware",
            "type":"Retail Goods"
        }
    ],
    "sg:phone":"+1 952 466 5669",
    "sg:postcode":"55322",
    "sg:province":"MN",
    "sg:tags":[
        "filtration",
        "softening",
        "supply",
        "work",
        "purification",
        "equipment",
        "conditioning"
    ],
    "wof:name":"Tim Vos",
    "wof:placetype":"venue"
},
  "geometry": {"coordinates":[-93.724954,44.79516],"type":"Point"}
}