{
  "type": "Feature",
  "properties": {
    "iso:country":"US",
    "sg:address":"800 E 21st St",
    "sg:city":"Hibbing",
    "sg:classifiers":[
        {
            "category":"Education",
            "subcategory":"Special Training",
            "type":"Public Place"
        }
    ],
    "sg:phone":"+1 218 262 0417",
    "sg:postcode":"55746",
    "sg:province":"MN",
    "sg:tags":[
        "center"
    ],
    "wof:name":"Hibbing Community Education",
    "wof:placetype":"venue"
},
  "geometry": {"coordinates":[-92.93245,47.426235],"type":"Point"}
}