{
  "type": "Feature",
  "properties": {
    "iso:country":"US",
    "sg:address":"3954 Wooddale Ave S",
    "sg:city":"St Louis Park",
    "sg:classifiers":[
        {
            "category":"Health Services",
            "subcategory":"Chiropractor",
            "type":"Services"
        }
    ],
    "sg:phone":"+1 952 927 8687",
    "sg:postcode":"55416",
    "sg:province":"MN",
    "wof:name":"Spine Care Publications",
    "wof:placetype":"venue"
},
  "geometry": {"coordinates":[-93.347319,44.929878],"type":"Point"}
}