{
  "type": "Feature",
  "properties": {
    "addr:full":"2846 Princeton Ave Minneapolis MN 55416",
    "addr:housenumber":"2846",
    "addr:postcode":"55416",
    "addr:street":"Princeton Ave",
    "iso:country":"US",
    "sg:address":"2846 Princeton Ave",
    "sg:city":"Minneapolis",
    "sg:classifiers":[
        {
            "category":"Shopping",
            "subcategory":"Music",
            "type":"Retail Goods"
        }
    ],
    "sg:phone":"+1 952 929 4383",
    "sg:postcode":"55416",
    "sg:province":"MN",
    "sg:tags":[
        "store"
    ],
    "wof:name":"Ezekiel Records & Creative Gro",
    "wof:placetype":"venue"
},
  "geometry": {"coordinates":[-93.341633,44.951237],"type":"Point"}
}