{
  "type": "Feature",
  "properties": {
    "addr:full":"505 W Front St Albert Lea MN 56007",
    "addr:housenumber":"505",
    "addr:postcode":"56007",
    "addr:street":"W Front St",
    "iso:country":"US",
    "sg:address":"505 W Front St",
    "sg:city":"Albert Lea",
    "sg:classifiers":[
        {
            "category":"Manufacturing",
            "subcategory":"Tools & Machinery",
            "type":"Manufacturing & Wholesale Goods"
        }
    ],
    "sg:phone":"+1 507 377 8910",
    "sg:postcode":"56007",
    "sg:province":"MN",
    "sg:tags":[
        "industrial",
        "m",
        "mfg"
    ],
    "wof:name":"EXACT MANUFACTURING DIVISION",
    "wof:placetype":"venue"
},
  "geometry": {"coordinates":[-93.37430000000001,43.643512],"type":"Point"}
}