{
  "type": "Feature",
  "properties": {
    "addr:full":"1975 Co Rd B W Saint Paul MN 55113",
    "addr:housenumber":"1975",
    "addr:postcode":"55113",
    "addr:street":"Co Rd;W",
    "iso:country":"US",
    "sg:address":"1975 Co Rd B W",
    "sg:city":"Saint Paul",
    "sg:classifiers":[
        {
            "category":"Manufacturing",
            "subcategory":"Toys & Sporting Goods",
            "type":"Manufacturing & Wholesale Goods"
        }
    ],
    "sg:phone":"+1 651 639 1905",
    "sg:postcode":"55113",
    "sg:province":"MN",
    "sg:tags":[
        "game",
        "boardgames",
        "mfg"
    ],
    "wof:name":"Fantasy Flight Games",
    "wof:placetype":"venue"
},
  "geometry": {"coordinates":[-93.18692900000001,45.006197],"type":"Point"}
}