{
  "type": "Feature",
  "properties": {
    "addr:full":"28084 State Hwy 264 Round Lake MN 56167",
    "addr:housenumber":"28084",
    "addr:postcode":"56167",
    "addr:street":"State Hwy 264",
    "iso:country":"US",
    "sg:address":"28084 State Hwy 264",
    "sg:city":"Round Lake",
    "sg:classifiers":[
        {
            "category":"Farming",
            "subcategory":"Farm",
            "type":"Manufacturing & Wholesale Goods"
        }
    ],
    "sg:phone":"+1 507 945 8384",
    "sg:postcode":"56167",
    "sg:province":"MN",
    "sg:tags":[
        "crop",
        "general"
    ],
    "wof:name":"David Robinson",
    "wof:placetype":"venue"
},
  "geometry": {"coordinates":[-95.454454,43.585575],"type":"Point"}
}