{
  "type": "Feature",
  "properties": {
    "iso:country":"US",
    "sg:address":"9120 Baltimore St NE",
    "sg:city":"Minneapolis",
    "sg:classifiers":[
        {
            "category":"Health Services",
            "subcategory":"Doctor",
            "type":"Services"
        }
    ],
    "sg:phone":"+1 763 786 1560",
    "sg:postcode":"55449",
    "sg:province":"MN",
    "sg:tags":[
        "dentist",
        "dentists-endodontists"
    ],
    "sg:website":"http://www.northparkdental.com",
    "wof:name":"Northpark Dental",
    "wof:placetype":"venue"
},
  "geometry": {"coordinates":[-93.233467,45.136289],"type":"Point"}
}