{
  "type": "Feature",
  "properties": {
    "addr:full":"16597 Harwell Ave Lakeville MN 55044",
    "addr:housenumber":"16597",
    "addr:postcode":"55044",
    "addr:street":"Harwell Ave",
    "iso:country":"US",
    "sg:address":"16597 Harwell Ave",
    "sg:city":"Lakeville",
    "sg:classifiers":[
        {
            "category":"Social Services",
            "subcategory":"Child Care",
            "type":"Services"
        }
    ],
    "sg:phone":"+1 952 891 2431",
    "sg:postcode":"55044",
    "sg:province":"MN",
    "sg:tags":[
        "day"
    ],
    "wof:name":"Cheryl A Lott",
    "wof:placetype":"venue"
},
  "geometry": {"coordinates":[-93.229811,44.708155],"type":"Point"}
}