{
  "type": "Feature",
  "properties": {
    "addr:full":"11095 Viking Dr Eden Prairie MN 55344",
    "addr:housenumber":"11095",
    "addr:postcode":"55344",
    "addr:street":"Viking Dr",
    "iso:country":"US",
    "sg:address":"11095 Viking Dr",
    "sg:city":"Eden Prairie",
    "sg:classifiers":[
        {
            "category":"Shopping",
            "subcategory":"Gifts & Souvenirs",
            "type":"Retail Goods"
        }
    ],
    "sg:phone":"+1 952 944 6179",
    "sg:postcode":"55344",
    "sg:province":"MN",
    "sg:tags":[
        "shop"
    ],
    "wof:name":"Garden Court Gift Shop",
    "wof:placetype":"venue"
},
  "geometry": {"coordinates":[-93.419669,44.862851],"type":"Point"}
}