{
  "type": "Feature",
  "properties": {
    "addr:full":"5809 73rd Ave N Minneapolis MN 55429",
    "addr:housenumber":"5809",
    "addr:postcode":"55429",
    "addr:street":"73Rd Ave N",
    "iso:country":"US",
    "sg:address":"5809 73rd Ave N",
    "sg:city":"Minneapolis",
    "sg:classifiers":[
        {
            "category":"Freight",
            "type":"Transportation"
        }
    ],
    "sg:phone":"+1 612 272 8438",
    "sg:postcode":"55429",
    "sg:province":"MN",
    "sg:tags":[
        "mover"
    ],
    "wof:name":"Kaba Moving Express",
    "wof:placetype":"venue"
},
  "geometry": {"coordinates":[-93.352249,45.087189],"type":"Point"}
}