{
  "type": "Feature",
  "properties": {
    "addr:full":"7145 E Point Douglas Rd S Cottage Grove MN 55016",
    "addr:housenumber":"7145",
    "addr:postcode":"55016",
    "addr:street":"E Point Douglas Rd S",
    "iso:country":"US",
    "sg:address":"7145 E Point Douglas Rd S",
    "sg:city":"Cottage Grove",
    "sg:classifiers":[
        {
            "category":"Coffee & Tea",
            "type":"Food & Drink"
        }
    ],
    "sg:menulink":"http://www.allmenus.com/mn/cottage-grove/58515-caribou-coffee/menu/",
    "sg:phone":"+1 651 768 0794",
    "sg:postcode":"55016",
    "sg:province":"MN",
    "sg:tags":[
        "american"
    ],
    "wof:name":"Caribou Coffee",
    "wof:placetype":"venue"
},
  "geometry": {"coordinates":[-92.960427,44.832749],"type":"Point"}
}