{
  "type": "Feature",
  "properties": {
    "iso:country":"US",
    "sg:address":"124 Front St S",
    "sg:city":"Barnesville",
    "sg:classifiers":[
        {
            "category":"Shopping",
            "subcategory":"Florist",
            "type":"Retail Goods"
        }
    ],
    "sg:phone":"+1 218 354 2397",
    "sg:postcode":"56514",
    "sg:province":"MN",
    "wof:name":"Little Shop Of Flowers",
    "wof:placetype":"venue"
},
  "geometry": {"coordinates":[-96.419974,46.653109],"type":"Point"}
}