{
  "type": "Feature",
  "properties": {
    "addr:full":"124 Front St S Barnesville MN 56514",
    "addr:housenumber":"124",
    "addr:postcode":"56514",
    "addr:street":"Front St S Barnesville",
    "iso:country":"US",
    "sg:address":"124 Front St S",
    "sg:city":"Barnesville",
    "sg:classifiers":[
        {
            "category":"Shopping",
            "subcategory":"Florist",
            "type":"Retail Goods"
        }
    ],
    "sg:phone":"+1 218 354 2397",
    "sg:postcode":"56514",
    "sg:province":"MN",
    "wof:name":"Little Shop Of Flowers",
    "wof:placetype":"venue"
},
  "geometry": {"coordinates":[-96.419974,46.653109],"type":"Point"}
}