{
  "type": "Feature",
  "properties": {
    "iso:country":"US",
    "sg:address":"1502 Co Rd 42 E",
    "sg:city":"Burnsville",
    "sg:classifiers":[
        {
            "category":"Freight",
            "type":"Transportation"
        }
    ],
    "sg:phone":"+1 952 891 8181",
    "sg:postcode":"55337",
    "sg:province":"MN",
    "sg:tags":[
        "delivery"
    ],
    "sg:website":"www.deliveryman.us",
    "wof:name":"Special Delivery",
    "wof:placetype":"venue"
},
  "geometry": {"coordinates":[-93.25340300000001,44.733471],"type":"Point"}
}