{
  "type": "Feature",
  "properties": {
    "addr:full":"1025 Crystal Lake Rd E Burnsville MN 55306",
    "addr:housenumber":"1025",
    "addr:postcode":"55306",
    "addr:street":"Crystal Lake Rd E",
    "iso:country":"US",
    "sg:address":"1025 Crystal Lake Rd E",
    "sg:city":"Burnsville",
    "sg:classifiers":[
        {
            "category":"Shopping",
            "subcategory":"Hobbies, Toys, & Games",
            "type":"Retail Goods"
        }
    ],
    "sg:phone":"+1 952 892 7529",
    "sg:postcode":"55306",
    "sg:province":"MN",
    "wof:name":"Discovery Toys",
    "wof:placetype":"venue"
},
  "geometry": {"coordinates":[-93.26253800000001,44.726499],"type":"Point"}
}