{
  "type": "Feature",
  "properties": {
    "iso:country":"US",
    "sg:address":"14641 57th St N",
    "sg:city":"Stillwater",
    "sg:classifiers":[
        {
            "category":"Autos & Motor Vehicles",
            "subcategory":"Automobile Sales",
            "type":"Retail Goods"
        }
    ],
    "sg:phone":"+1 651 439 4762",
    "sg:postcode":"55082",
    "sg:province":"MN",
    "sg:tags":[
        "used"
    ],
    "wof:name":"River Valley Auto Sales",
    "wof:placetype":"venue"
},
  "geometry": {"coordinates":[-92.811813,45.031834],"type":"Point"}
}