{
  "type": "Feature",
  "properties": {
    "addr:full":"14180 182nd St Belle Plaine MN 56011",
    "addr:housenumber":"14180",
    "addr:postcode":"56011",
    "addr:street":"182Nd St;Plaine",
    "iso:country":"US",
    "sg:address":"14180 182nd St",
    "sg:city":"Belle Plaine",
    "sg:classifiers":[
        {
            "category":"Professional",
            "type":"Services"
        }
    ],
    "sg:phone":"+1 952 467 2807",
    "sg:postcode":"56011",
    "sg:province":"MN",
    "wof:name":"Alvin Gohlke",
    "wof:placetype":"venue"
},
  "geometry": {"coordinates":[-93.882407,44.673506],"type":"Point"}
}