{
  "type": "Feature",
  "properties": {
    "iso:country":"US",
    "sg:address":"18 4th St NE",
    "sg:city":"East Grand Forks",
    "sg:classifiers":[
        {
            "category":"Manufacturing",
            "subcategory":"Food",
            "type":"Manufacturing & Wholesale Goods"
        }
    ],
    "sg:phone":"+1 218 773 9174",
    "sg:postcode":"56721",
    "sg:province":"MN",
    "sg:tags":[
        "sugar"
    ],
    "wof:name":"American Crystal Sugar Co",
    "wof:placetype":"venue"
},
  "geometry": {"coordinates":[-97.018647,47.927986],"type":"Point"}
}