{
  "type": "Feature",
  "properties": {
    "addr:full":"201 W Burnsville Pkwy # 152 Burnsville MN 55337",
    "addr:housenumber":"201",
    "addr:postcode":"55337",
    "addr:street":"W Burnsville Pkwy # 152",
    "iso:country":"US",
    "sg:address":"201 W Burnsville Pkwy # 152",
    "sg:city":"Burnsville",
    "sg:classifiers":[
        {
            "category":"Professional",
            "subcategory":"Accounting & Tax Preparation",
            "type":"Services"
        }
    ],
    "sg:phone":"+1 952 890 0438",
    "sg:postcode":"55337",
    "sg:province":"MN",
    "sg:tags":[
        "return",
        "preparation-business"
    ],
    "sg:website":"http://www.bbrinkfinancials.com",
    "wof:name":"B Brink Financial Ltd",
    "wof:placetype":"venue"
},
  "geometry": {"coordinates":[-93.280385,44.771603],"type":"Point"}
}