{
  "type": "Feature",
  "properties": {
    "addr:full":"5896 Holly Ln Duluth MN 55811",
    "addr:housenumber":"5896",
    "addr:postcode":"55811",
    "addr:street":"Holly Ln",
    "iso:country":"US",
    "sg:address":"5896 Holly Ln",
    "sg:city":"Duluth",
    "sg:classifiers":[
        {
            "category":"Professional",
            "subcategory":"Advertising",
            "type":"Services"
        }
    ],
    "sg:phone":"+1 218 729 8919",
    "sg:postcode":"55811",
    "sg:province":"MN",
    "sg:tags":[
        "agency"
    ],
    "wof:name":"Adventure Advertising",
    "wof:placetype":"venue"
},
  "geometry": {"coordinates":[-92.298357,46.894238],"type":"Point"}
}