{
  "type": "Feature",
  "properties": {
    "iso:country":"US",
    "sg:address":"330 S Broadway",
    "sg:city":"Rochester",
    "sg:classifiers":[
        {
            "category":"Professional",
            "subcategory":"Lawyer & Legal Services",
            "type":"Services"
        }
    ],
    "sg:phone":"+1 507 288 9122",
    "sg:postcode":"55904",
    "sg:province":"MN",
    "sg:tags":[
        "damage",
        "attorney",
        "accident",
        "family",
        "personal",
        "automobile",
        "practice",
        "worker",
        "compensation",
        "labor",
        "wrongful",
        "property",
        "benefit",
        "death",
        "employee",
        "injury",
        "criminal",
        "employment",
        "law"
    ],
    "sg:website":"http://www.pattersondahlberg.com",
    "wof:name":"Patterson Dahlberg Injury Lawyers",
    "wof:placetype":"venue"
},
  "geometry": {"coordinates":[-92.462942,44.020074],"type":"Point"}
}