{
  "type": "Feature",
  "properties": {
    "addr:full":"4313 Thornhill Ln Saint Paul MN 55127",
    "addr:housenumber":"4313",
    "addr:postcode":"55127",
    "addr:street":"Thornhill Ln",
    "iso:country":"US",
    "sg:address":"4313 Thornhill Ln",
    "sg:city":"Saint Paul",
    "sg:classifiers":[
        {
            "category":"Professional",
            "subcategory":"Management & Consulting",
            "type":"Services"
        }
    ],
    "sg:phone":"+1 651 653 9045",
    "sg:postcode":"55127",
    "sg:province":"MN",
    "wof:name":"Ann Holly Enterprises Inc",
    "wof:placetype":"venue"
},
  "geometry": {"coordinates":[-93.06336,45.07198],"type":"Point"}
}