{
  "type": "Feature",
  "properties": {
    "iso:country":"US",
    "sg:address":"14075 Ramsey Blvd NW",
    "sg:city":"Anoka",
    "sg:classifiers":[
        {
            "category":"Food & Beverages",
            "subcategory":"Groceries & Convenience Stores",
            "type":"Retail Goods"
        }
    ],
    "sg:phone":"+1 763 421 3075",
    "sg:postcode":"55303",
    "sg:province":"MN",
    "sg:website":"www.holidaystationstores.com",
    "wof:name":"Holiday Station Store",
    "wof:placetype":"venue"
},
  "geometry": {"coordinates":[-93.44901900000001,45.225824],"type":"Point"}
}