{
  "type": "Feature",
  "properties": {
    "iso:country":"US",
    "sg:address":"2520 Broadway St",
    "sg:city":"Roseville",
    "sg:classifiers":[
        {
            "category":"Retail",
            "subcategory":"Auto Rental",
            "type":"Services"
        }
    ],
    "sg:phone":"+1 651 631 1581",
    "sg:postcode":"55113",
    "sg:province":"MN",
    "sg:tags":[
        "renting",
        "automobile",
        "passenger",
        "car"
    ],
    "wof:name":"Enterprise Rent-A-Car",
    "wof:placetype":"venue"
},
  "geometry": {"coordinates":[-93.20737699999999,45.000497],"type":"Point"}
}