{
  "type": "Feature",
  "properties": {
    "addr:full":"14769 US Hwy 169 Vernon Center MN 56090",
    "addr:housenumber":"14769",
    "addr:postcode":"56090",
    "addr:street":"Us Hwy 169 Vernon Center",
    "iso:country":"US",
    "sg:address":"14769 US Hwy 169",
    "sg:city":"Vernon Center",
    "sg:phone":"+1 507 549 3886",
    "sg:postcode":"56090",
    "sg:province":"MN",
    "sg:tags":[
        "farm",
        "corn",
        "soybean"
    ],
    "wof:name":"Doyen Orrin",
    "wof:placetype":"venue"
},
  "geometry": {"coordinates":[-94.168871,43.977769],"type":"Point"}
}