{
  "type": "Feature",
  "properties": {
    "addr:full":"11511 95th Ave N Maple Grove MN 55369",
    "addr:housenumber":"11511",
    "addr:postcode":"55369",
    "addr:street":"95Th Ave N",
    "iso:country":"US",
    "sg:address":"11511 95th Ave N",
    "sg:city":"Maple Grove",
    "sg:classifiers":[
        {
            "category":"Manufacturing",
            "subcategory":"Tools & Machinery",
            "type":"Manufacturing & Wholesale Goods"
        },
        {
            "category":"Manufacturing",
            "subcategory":"Furniture",
            "type":"Manufacturing & Wholesale Goods"
        }
    ],
    "sg:phone":"+1 763 494 6969",
    "sg:postcode":"55369",
    "sg:province":"MN",
    "sg:tags":[
        "physician",
        "mfg",
        "fiberglass",
        "table",
        "surgeon",
        "store"
    ],
    "sg:website":"www.spacetables.com",
    "wof:name":"Space Tables Inc",
    "wof:placetype":"venue"
},
  "geometry": {"coordinates":[-93.427802,45.127059],"type":"Point"}
}