{
  "type": "Feature",
  "properties": {
    "addr:full":"4837 White Bear Pkwy White Bear Lake MN 55110",
    "addr:housenumber":"4837",
    "addr:postcode":"55110",
    "addr:street":"White Bear Pkwy",
    "iso:country":"US",
    "sg:address":"4837 White Bear Pkwy",
    "sg:city":"White Bear Lake",
    "sg:classifiers":[
        {
            "category":"Manufacturing",
            "subcategory":"Tools & Machinery",
            "type":"Manufacturing & Wholesale Goods"
        }
    ],
    "sg:phone":"+1 651 407 1060",
    "sg:postcode":"55110",
    "sg:province":"MN",
    "wof:name":"Prime Yield Systems",
    "wof:placetype":"venue"
},
  "geometry": {"coordinates":[-93.045163,45.089051],"type":"Point"}
}