{
  "type": "Feature",
  "properties": {
    "addr:full":"230 Fern St N Cambridge MN 55008",
    "addr:housenumber":"230",
    "addr:postcode":"55008",
    "addr:street":"Fern St N",
    "iso:country":"US",
    "sg:address":"230 Fern St N",
    "sg:city":"Cambridge",
    "sg:classifiers":[
        {
            "category":"Organizations",
            "subcategory":"Religious Organization",
            "type":"Services"
        }
    ],
    "sg:phone":"+1 763 689 1221",
    "sg:postcode":"55008",
    "sg:province":"MN",
    "wof:name":"Christ King Catholic Church",
    "wof:placetype":"venue"
},
  "geometry": {"coordinates":[-93.233225,45.574366],"type":"Point"}
}