{
  "type": "Feature",
  "properties": {
    "iso:country":"US",
    "sg:address":"6530 115th Ave",
    "sg:city":"Clear Lake",
    "sg:classifiers":[
        {
            "category":"Building & Trades",
            "subcategory":"Construction",
            "type":"Services"
        }
    ],
    "sg:phone":"+1 320 743 4289",
    "sg:postcode":"55319",
    "sg:province":"MN",
    "sg:tags":[
        "house",
        "builder",
        "home"
    ],
    "wof:name":"Northern Flight Builders Inc",
    "wof:placetype":"venue"
},
  "geometry": {"coordinates":[-93.923498,45.474709],"type":"Point"}
}