{
  "type": "Feature",
  "properties": {
    "addr:full":"608 3rd St W Adrian MN 56110",
    "addr:housenumber":"608",
    "addr:postcode":"56110",
    "addr:street":"3Rd St W Adrian",
    "iso:country":"US",
    "sg:address":"608 3rd St W",
    "sg:city":"Adrian",
    "sg:classifiers":[
        {
            "category":"Retail",
            "subcategory":"Repair Shop",
            "type":"Services"
        }
    ],
    "sg:phone":"+1 507 483 2920",
    "sg:postcode":"56110",
    "sg:province":"MN",
    "sg:tags":[
        "television",
        "radio"
    ],
    "wof:name":"Don's Radio & Television",
    "wof:placetype":"venue"
},
  "geometry": {"coordinates":[-95.94152099999999,43.634157],"type":"Point"}
}