{
  "type": "Feature",
  "properties": {
    "addr:full":"348 2nd St SW Willmar MN 56201",
    "addr:housenumber":"348",
    "addr:postcode":"56201",
    "addr:street":"2Nd St Sw",
    "iso:country":"US",
    "sg:address":"348 2nd St SW",
    "sg:city":"Willmar",
    "sg:classifiers":[
        {
            "category":"Autos & Motor Vehicles",
            "subcategory":"Auto Supplies",
            "type":"Retail Goods"
        }
    ],
    "sg:phone":"+1 320 235 4455",
    "sg:postcode":"56201",
    "sg:province":"MN",
    "sg:tags":[
        "automobile",
        "parts",
        "accessory",
        "part",
        "accessories-wholesale",
        "manufacturer"
    ],
    "wof:name":"Gtc Auto Parts",
    "wof:placetype":"venue"
},
  "geometry": {"coordinates":[-95.04511599999999,45.121262],"type":"Point"}
}