{
  "type": "Feature",
  "properties": {
    "addr:full":"236 Concord Exchange S South St Paul MN 55075",
    "addr:housenumber":"236",
    "addr:postcode":"55075",
    "addr:street":"Concord Exchange S;St",
    "iso:country":"US",
    "sg:address":"236 Concord Exchange S",
    "sg:city":"South St Paul",
    "sg:classifiers":[
        {
            "category":"Government",
            "subcategory":"Post Office",
            "type":"Public Place"
        }
    ],
    "sg:phone":"+1 651 450 7548",
    "sg:postcode":"55075",
    "sg:province":"MN",
    "wof:name":"US Post Office",
    "wof:placetype":"venue"
},
  "geometry": {"coordinates":[-93.033863,44.890521],"type":"Point"}
}