{
  "type": "Feature",
  "properties": {
    "addr:full":"4651 15th Ave S Minneapolis MN 55407",
    "addr:housenumber":"4651",
    "addr:postcode":"55407",
    "addr:street":"15Th Ave S",
    "iso:country":"US",
    "sg:address":"4651 15th Ave S",
    "sg:city":"Minneapolis",
    "sg:classifiers":[
        {
            "category":"Communications",
            "subcategory":"Film & Video Production",
            "type":"Services"
        }
    ],
    "sg:phone":"+1 612 827 7651",
    "sg:postcode":"55407",
    "sg:province":"MN",
    "sg:tags":[
        "motion"
    ],
    "wof:name":"Chuck Wilkeerson",
    "wof:placetype":"venue"
},
  "geometry": {"coordinates":[-93.253614,44.918828],"type":"Point"}
}