{
  "type": "Feature",
  "properties": {
    "iso:country":"US",
    "sg:address":"18767 Bearpath Trl",
    "sg:city":"Eden Prairie",
    "sg:classifiers":[
        {
            "category":"Professional",
            "subcategory":"Management & Consulting",
            "type":"Services"
        }
    ],
    "sg:phone":"+1 952 975 0536",
    "sg:postcode":"55347",
    "sg:province":"MN",
    "sg:tags":[
        "consultant",
        "business"
    ],
    "wof:name":"Acuity Strategic Consulting",
    "wof:placetype":"venue"
},
  "geometry": {"coordinates":[-93.514923,44.840989],"type":"Point"}
}