{
  "type": "Feature",
  "properties": {
    "addr:full":"702 33rd Ave N St Cloud MN 56303",
    "addr:housenumber":"702",
    "addr:postcode":"56303",
    "addr:street":"33Rd Ave N",
    "iso:country":"US",
    "sg:address":"702 33rd Ave N",
    "sg:city":"St Cloud",
    "sg:classifiers":[
        {
            "category":"Food & Beverages",
            "subcategory":"Groceries & Convenience Stores",
            "type":"Retail Goods"
        }
    ],
    "sg:phone":"+1 320 253 7211",
    "sg:postcode":"56303",
    "sg:province":"MN",
    "sg:tags":[
        "station",
        "gasoline"
    ],
    "wof:name":"E Z Stop",
    "wof:placetype":"venue"
},
  "geometry": {"coordinates":[-94.198075,45.5658],"type":"Point"}
}