{
  "type": "Feature",
  "properties": {
    "iso:country":"US",
    "sg:address":"1131 6th St NW",
    "sg:city":"Rochester",
    "sg:classifiers":[
        {
            "category":"Health Services",
            "subcategory":"Dentist",
            "type":"Services"
        }
    ],
    "sg:phone":"+1 507 281 2433",
    "sg:postcode":"55901",
    "sg:province":"MN",
    "wof:name":"Reeve Family Dentistry",
    "wof:placetype":"venue"
},
  "geometry": {"coordinates":[-92.479214,44.029148],"type":"Point"}
}