{
  "type": "Feature",
  "properties": {
    "iso:country":"US",
    "sg:address":"1316 N Minnesota St",
    "sg:city":"New Ulm",
    "sg:classifiers":[
        {
            "category":"Education",
            "subcategory":"College",
            "type":"Public Place"
        }
    ],
    "sg:phone":"+1 507 359 4695",
    "sg:postcode":"56073",
    "sg:province":"MN",
    "wof:name":"Lafayette Charter",
    "wof:placetype":"venue"
},
  "geometry": {"coordinates":[-94.47176,44.326888],"type":"Point"}
}