{
  "type": "Feature",
  "properties": {
    "iso:country":"US",
    "sg:address":"309 Cross Ave N",
    "sg:city":"Crosby",
    "sg:classifiers":[
        {
            "category":"Home & Garden",
            "subcategory":"Garden Supply",
            "type":"Retail Goods"
        }
    ],
    "sg:phone":"+1 218 545 1117",
    "sg:postcode":"56441",
    "sg:province":"MN",
    "sg:tags":[
        "lawn",
        "mower"
    ],
    "wof:name":"Andrews Small Engine Sales",
    "wof:placetype":"venue"
},
  "geometry": {"coordinates":[-93.952196,46.486044],"type":"Point"}
}