{
  "type": "Feature",
  "properties": {
    "iso:country":"US",
    "sg:address":"25252 Co Rd 32",
    "sg:city":"Grove City",
    "sg:phone":"+1 320 857 2605",
    "sg:postcode":"56243",
    "sg:province":"MN",
    "sg:tags":[
        "farm",
        "grain",
        "cash"
    ],
    "wof:name":"Jerome Carlson Farm",
    "wof:placetype":"venue"
},
  "geometry": {"coordinates":[-94.65503699999999,45.11098],"type":"Point"}
}