{
  "type": "Feature",
  "properties": {
    "addr:full":"10535 Humboldt Ave S Bloomington MN 55431",
    "addr:housenumber":"10535",
    "addr:postcode":"55431",
    "addr:street":"Humboldt Ave S",
    "iso:country":"US",
    "sg:address":"10535 Humboldt Ave S",
    "sg:city":"Bloomington",
    "sg:classifiers":[
        {
            "category":"Organizations",
            "subcategory":"Religious Organization",
            "type":"Services"
        }
    ],
    "sg:phone":"+1 952 881 2559",
    "sg:postcode":"55431",
    "sg:province":"MN",
    "sg:tags":[
        "church"
    ],
    "wof:name":"Church Of God",
    "wof:placetype":"venue"
},
  "geometry": {"coordinates":[-93.298731,44.814071],"type":"Point"}
}