{
  "type": "Feature",
  "properties": {
    "addr:full":"17205 Co Rd 6 Plymouth MN 55447",
    "addr:housenumber":"17205",
    "addr:postcode":"55447",
    "addr:street":"Co Rd 6",
    "iso:country":"US",
    "sg:address":"17205 Co Rd 6",
    "sg:city":"Plymouth",
    "sg:classifiers":[
        {
            "category":"Organizations",
            "subcategory":"Religious Organization",
            "type":"Services"
        }
    ],
    "sg:phone":"+1 763 475 7100",
    "sg:postcode":"55447",
    "sg:province":"MN",
    "sg:tags":[
        "church"
    ],
    "sg:website":"www.spdlc.org",
    "wof:name":"St Philip The Deacon Luth Chr",
    "wof:placetype":"venue"
},
  "geometry": {"coordinates":[-93.500905,44.995367],"type":"Point"}
}