{
  "type": "Feature",
  "properties": {
    "addr:full":"3724 10th Ave S Minneapolis MN 55407",
    "addr:housenumber":"3724",
    "addr:postcode":"55407",
    "addr:street":"10Th Ave S",
    "iso:country":"US",
    "sg:address":"3724 10th Ave S",
    "sg:city":"Minneapolis",
    "sg:classifiers":[
        {
            "category":"Building & Trades",
            "subcategory":"Construction",
            "type":"Services"
        }
    ],
    "sg:phone":"+1 612 824 7940",
    "sg:postcode":"55407",
    "sg:province":"MN",
    "sg:tags":[
        "floor",
        "laying",
        "contractor"
    ],
    "wof:name":"Amish Flooring Co",
    "wof:placetype":"venue"
},
  "geometry": {"coordinates":[-93.260049,44.934585],"type":"Point"}
}