{
  "type": "Feature",
  "properties": {
    "iso:country":"US",
    "sg:address":"614 SW Park St",
    "sg:city":"Luverne",
    "sg:classifiers":[
        {
            "category":"Farming",
            "subcategory":"Farm",
            "type":"Manufacturing & Wholesale Goods"
        }
    ],
    "sg:phone":"+1 507 283 2973",
    "sg:postcode":"56156",
    "sg:province":"MN",
    "sg:tags":[
        "crop",
        "general"
    ],
    "wof:name":"Bill Weber",
    "wof:placetype":"venue"
},
  "geometry": {"coordinates":[-96.216424,43.647574],"type":"Point"}
}