{
  "type": "Feature",
  "properties": {
    "addr:full":"4099 NE 24th Ave Owatonna MN 55060",
    "addr:housenumber":"4099",
    "addr:postcode":"55060",
    "addr:street":"Ne 24Th Ave",
    "iso:country":"US",
    "sg:address":"4099 NE 24th Ave",
    "sg:city":"Owatonna",
    "sg:phone":"+1 507 451 8278",
    "sg:postcode":"55060",
    "sg:province":"MN",
    "sg:tags":[
        "farm",
        "corn",
        "soybean"
    ],
    "wof:name":"Kriesel John",
    "wof:placetype":"venue"
},
  "geometry": {"coordinates":[-93.186706,44.145188],"type":"Point"}
}