{
  "type": "Feature",
  "properties": {
    "addr:full":"3501 County Road 42 W Burnsville MN 55306",
    "addr:housenumber":"3501",
    "addr:postcode":"55306",
    "addr:street":"County Road 42 W",
    "iso:country":"US",
    "sg:address":"3501 County Road 42 W",
    "sg:city":"Burnsville",
    "sg:classifiers":[
        {
            "category":"Food & Beverages",
            "subcategory":"Candy",
            "type":"Retail Goods"
        }
    ],
    "sg:phone":"+1 952 890 0859",
    "sg:postcode":"55306",
    "sg:province":"MN",
    "sg:tags":[
        "store"
    ],
    "sg:website":"www.abdallahcandies.com",
    "wof:name":"Abdallah Candies and Gifts",
    "wof:placetype":"venue"
},
  "geometry": {"coordinates":[-93.323402,44.7463],"type":"Point"}
}