{
  "type": "Feature",
  "properties": {
    "iso:country":"US",
    "sg:address":"332 Vance Ave",
    "sg:city":"Erskine",
    "sg:classifiers":[
        {
            "category":"Organizations",
            "subcategory":"Religious Organization",
            "type":"Services"
        }
    ],
    "sg:phone":"+1 218 687 4035",
    "sg:postcode":"56535",
    "sg:province":"MN",
    "sg:tags":[
        "church"
    ],
    "wof:name":"Grace Lutheran Church-Erskine",
    "wof:placetype":"venue"
},
  "geometry": {"coordinates":[-96.011004,47.666339],"type":"Point"}
}