{
  "type": "Feature",
  "properties": {
    "iso:country":"US",
    "sg:address":"7895 180th St N",
    "sg:city":"Hugo",
    "sg:classifiers":[
        {
            "category":"Home & Garden",
            "subcategory":"Building Materials",
            "type":"Retail Goods"
        }
    ],
    "sg:phone":"+1 651 426 9982",
    "sg:postcode":"55038",
    "sg:province":"MN",
    "wof:name":"Polysteel Sup of Minneapolis",
    "wof:placetype":"venue"
},
  "geometry": {"coordinates":[-92.95104000000001,45.210368],"type":"Point"}
}