{
  "type": "Feature",
  "properties": {
    "addr:full":"1111 Cooper Ave S St Cloud MN 56301",
    "addr:housenumber":"1111",
    "addr:postcode":"56301",
    "addr:street":"Cooper Ave S",
    "iso:country":"US",
    "sg:address":"1111 Cooper Ave S",
    "sg:city":"St Cloud",
    "sg:classifiers":[
        {
            "category":"Organizations",
            "subcategory":"Religious Organization",
            "type":"Services"
        }
    ],
    "sg:phone":"+1 320 251 8524",
    "sg:postcode":"56301",
    "sg:province":"MN",
    "sg:tags":[
        "church"
    ],
    "wof:name":"Saint Johns Episcopal Church",
    "wof:placetype":"venue"
},
  "geometry": {"coordinates":[-94.17770299999999,45.546523],"type":"Point"}
}