{
  "type": "Feature",
  "properties": {
    "iso:country":"US",
    "sg:address":"4934 Logan Ave N",
    "sg:city":"Minneapolis",
    "sg:classifiers":[
        {
            "category":"Building & Trades",
            "subcategory":"Construction",
            "type":"Services"
        }
    ],
    "sg:phone":"+1 612 522 2556",
    "sg:postcode":"55430",
    "sg:province":"MN",
    "sg:tags":[
        "residential",
        "commercial",
        "remodeling"
    ],
    "wof:name":"D&R Builders",
    "wof:placetype":"venue"
},
  "geometry": {"coordinates":[-93.304143,45.045112],"type":"Point"}
}