{
  "type": "Feature",
  "properties": {
    "iso:country":"US",
    "sg:address":"1001 7th St N",
    "sg:city":"Sartell",
    "sg:classifiers":[
        {
            "category":"Restaurant",
            "type":"Food & Drink"
        }
    ],
    "sg:phone":"+1 320 240 0595",
    "sg:postcode":"56377",
    "sg:province":"MN",
    "sg:tags":[
        "eating"
    ],
    "wof:name":"Blimpie",
    "wof:placetype":"venue"
},
  "geometry": {"coordinates":[-94.22471899999999,45.629979],"type":"Point"}
}