{
  "type": "Feature",
  "properties": {
    "addr:full":"3989 Central Ave NE Minneapolis MN 55421",
    "addr:housenumber":"3989",
    "addr:postcode":"55421",
    "addr:street":"Central Ave Ne",
    "iso:country":"US",
    "sg:address":"3989 Central Ave NE",
    "sg:city":"Minneapolis",
    "sg:classifiers":[
        {
            "category":"Banks & Credit Unions",
            "subcategory":"Bank",
            "type":"Services"
        }
    ],
    "sg:phone":"+1 763 781 9499",
    "sg:postcode":"55421",
    "sg:province":"MN",
    "sg:tags":[
        "broker",
        "mortgage"
    ],
    "wof:name":"Financial Professionals Mortgage Corp",
    "wof:placetype":"venue"
},
  "geometry": {"coordinates":[-93.24720000000001,45.040798],"type":"Point"}
}