{
  "type": "Feature",
  "properties": {
    "iso:country":"US",
    "sg:address":"2119 110th Ln NW",
    "sg:city":"Minneapolis",
    "sg:classifiers":[
        {
            "category":"Professional",
            "subcategory":"Management & Consulting",
            "type":"Services"
        }
    ],
    "sg:phone":"+1 612 799 0197",
    "sg:postcode":"55433",
    "sg:province":"MN",
    "wof:name":"Care Partners Services",
    "wof:placetype":"venue"
},
  "geometry": {"coordinates":[-93.320036,45.171689],"type":"Point"}
}