{
  "type": "Feature",
  "properties": {
    "iso:country":"US",
    "sg:address":"656 Selby Ave",
    "sg:city":"St Paul",
    "sg:classifiers":[
        {
            "category":"Health Services",
            "subcategory":"Clinic",
            "type":"Services"
        },
        {
            "category":"Personal",
            "subcategory":"Beauty Salon",
            "type":"Services"
        }
    ],
    "sg:phone":"+1 651 222 3322",
    "sg:postcode":"55104",
    "sg:province":"MN",
    "sg:tags":[
        "shop",
        "holistic",
        "practitioner"
    ],
    "sg:website":"www.gatheringsalon.com",
    "wof:name":"Gathering Salon & Wellness Ctr",
    "wof:placetype":"venue"
},
  "geometry": {"coordinates":[-93.127706,44.946526],"type":"Point"}
}