{
  "type": "Feature",
  "properties": {
    "iso:country":"US",
    "sg:address":"1620 W 98th St",
    "sg:city":"Minneapolis",
    "sg:classifiers":[
        {
            "category":"Professional",
            "subcategory":"Accounting & Tax Preparation",
            "type":"Services"
        }
    ],
    "sg:phone":"+1 952 881 3893",
    "sg:postcode":"55431",
    "sg:province":"MN",
    "sg:tags":[
        "billing"
    ],
    "wof:name":"Truewell Inc Billing",
    "wof:placetype":"venue"
},
  "geometry": {"coordinates":[-93.30110000000001,44.826387],"type":"Point"}
}