{
  "type": "Feature",
  "properties": {
    "addr:full":"10502 573rd Ave Mapleton MN 56065",
    "addr:housenumber":"10502",
    "addr:postcode":"56065",
    "addr:street":"573Rd Ave",
    "iso:country":"US",
    "sg:address":"10502 573rd Ave",
    "sg:city":"Mapleton",
    "sg:classifiers":[
        {
            "category":"Professional",
            "subcategory":"Management & Consulting",
            "type":"Services"
        }
    ],
    "sg:phone":"+1 507 524 3289",
    "sg:postcode":"56065",
    "sg:province":"MN",
    "sg:tags":[
        "farm"
    ],
    "wof:name":"Severtson, Torres Farm",
    "wof:placetype":"venue"
},
  "geometry": {"coordinates":[-93.98833,43.858826],"type":"Point"}
}