{
  "type": "Feature",
  "properties": {
    "addr:full":"1 Main St W St Stephen MN 56375",
    "addr:housenumber":"1",
    "addr:postcode":"56375",
    "addr:street":"Main St W St Stephen",
    "iso:country":"US",
    "sg:address":"1 Main St W",
    "sg:city":"St Stephen",
    "sg:classifiers":[
        {
            "category":"Freight",
            "type":"Transportation"
        }
    ],
    "sg:phone":"+1 320 202 1232",
    "sg:postcode":"56375",
    "sg:province":"MN",
    "sg:tags":[
        "consultant"
    ],
    "wof:name":"Cutting Edge Logistics",
    "wof:placetype":"venue"
},
  "geometry": {"coordinates":[-94.27452,45.70286],"type":"Point"}
}