{
  "type": "Feature",
  "properties": {
    "iso:country":"US",
    "sg:address":"308 Benton St W",
    "sg:city":"Lake Benton",
    "sg:classifiers":[
        {
            "category":"Government",
            "subcategory":"Office",
            "type":"Public Place"
        }
    ],
    "sg:phone":"+1 507 368 9363",
    "sg:postcode":"56149",
    "sg:province":"MN",
    "sg:tags":[
        "state",
        "program"
    ],
    "wof:name":"Transportation Dept",
    "wof:placetype":"venue"
},
  "geometry": {"coordinates":[-96.29307300000001,44.261111],"type":"Point"}
}