{
  "type": "Feature",
  "properties": {
    "addr:full":"5955 Golden Valley Rd Ste 240 Minneapolis MN 55422",
    "addr:housenumber":"5955",
    "addr:postcode":"55422",
    "addr:street":"Golden Valley Rd Ste 240",
    "iso:country":"US",
    "sg:address":"5955 Golden Valley Rd Ste 240",
    "sg:city":"Minneapolis",
    "sg:classifiers":[
        {
            "category":"Sports & Exercise",
            "subcategory":"Gym",
            "type":"Entertainment"
        }
    ],
    "sg:phone":"+1 763 545 2505",
    "sg:postcode":"55422",
    "sg:province":"MN",
    "sg:tags":[
        "trainer"
    ],
    "wof:name":"Neta",
    "wof:placetype":"venue"
},
  "geometry": {"coordinates":[-93.355998,44.992451],"type":"Point"}
}