{
  "type": "Feature",
  "properties": {
    "iso:country":"US",
    "sg:address":"1600 Bavarian Shores Dr",
    "sg:city":"Chaska",
    "sg:classifiers":[
        {
            "category":"Professional",
            "subcategory":"Business Services",
            "type":"Services"
        }
    ],
    "sg:phone":"+1 952 443 3031",
    "sg:postcode":"55318",
    "sg:province":"MN",
    "wof:name":"Strategic Ventures LLC",
    "wof:placetype":"venue"
},
  "geometry": {"coordinates":[-93.63837599999999,44.840975],"type":"Point"}
}