{
  "type": "Feature",
  "properties": {
    "addr:full":"128 S Highland Ave New Ulm MN 56073",
    "addr:housenumber":"128",
    "addr:postcode":"56073",
    "addr:street":"S Highland Ave",
    "iso:country":"US",
    "sg:address":"128 S Highland Ave",
    "sg:city":"New Ulm",
    "sg:classifiers":[
        {
            "category":"Building & Trades",
            "subcategory":"Cleaning & Sanitation",
            "type":"Services"
        }
    ],
    "sg:phone":"+1 507 354 8656",
    "sg:postcode":"56073",
    "sg:province":"MN",
    "sg:tags":[
        "maintenance"
    ],
    "wof:name":"Schauer Enterprises",
    "wof:placetype":"venue"
},
  "geometry": {"coordinates":[-94.473957,44.303482],"type":"Point"}
}