{
  "type": "Feature",
  "properties": {
    "addr:full":"7870 University Ave NE Minneapolis MN 55432",
    "addr:housenumber":"7870",
    "addr:postcode":"55432",
    "addr:street":"University Ave Ne",
    "iso:country":"US",
    "sg:address":"7870 University Ave NE",
    "sg:city":"Minneapolis",
    "sg:classifiers":[
        {
            "category":"Real Estate",
            "subcategory":"Real Estate Agent",
            "type":"Services"
        }
    ],
    "sg:phone":"+1 763 502 8480",
    "sg:postcode":"55432",
    "sg:province":"MN",
    "wof:name":"Minnesota RE Specialists",
    "wof:placetype":"venue"
},
  "geometry": {"coordinates":[-93.26364,45.110541],"type":"Point"}
}