{
  "type": "Feature",
  "properties": {
    "addr:full":"531 2nd St E Hector MN 55342",
    "addr:housenumber":"531",
    "addr:postcode":"55342",
    "addr:street":"2Nd St E Hector",
    "iso:country":"US",
    "sg:address":"531 2nd St E",
    "sg:city":"Hector",
    "sg:phone":"+1 320 848 2885",
    "sg:postcode":"55342",
    "sg:province":"MN",
    "sg:tags":[
        "farm",
        "corn"
    ],
    "wof:name":"Brian Broderius",
    "wof:placetype":"venue"
},
  "geometry": {"coordinates":[-94.713475,44.740768],"type":"Point"}
}