{
  "type": "Feature",
  "properties": {
    "iso:country":"US",
    "sg:address":"101 7th Ave S",
    "sg:city":"St Cloud",
    "sg:classifiers":[
        {
            "category":"Building & Trades",
            "subcategory":"Construction",
            "type":"Services"
        }
    ],
    "sg:phone":"+1 320 240 3374",
    "sg:postcode":"56301",
    "sg:province":"MN",
    "sg:tags":[
        "contractor"
    ],
    "wof:name":"Regency Builders",
    "wof:placetype":"venue"
},
  "geometry": {"coordinates":[-94.15876799999999,45.558365],"type":"Point"}
}