{
  "type": "Feature",
  "properties": {
    "iso:country":"US",
    "sg:address":"216 E Main St",
    "sg:city":"Albert Lea",
    "sg:classifiers":[
        {
            "category":"Social Services",
            "type":"Services"
        }
    ],
    "sg:phone":"+1 507 377 0107",
    "sg:postcode":"56007",
    "sg:province":"MN",
    "sg:tags":[
        "counselor",
        "marriage",
        "family"
    ],
    "wof:name":"Teresa Anderson-Krull",
    "wof:placetype":"venue"
},
  "geometry": {"coordinates":[-93.36618900000001,43.647761],"type":"Point"}
}