{
  "type": "Feature",
  "properties": {
    "addr:full":"323 14th Ave SE St Cloud MN 56304",
    "addr:housenumber":"323",
    "addr:postcode":"56304",
    "addr:street":"14Th Ave Se",
    "iso:country":"US",
    "sg:address":"323 14th Ave SE",
    "sg:city":"St Cloud",
    "sg:classifiers":[
        {
            "category":"Social Services",
            "type":"Services"
        }
    ],
    "sg:phone":"+1 320 230 3490",
    "sg:postcode":"56304",
    "sg:province":"MN",
    "sg:tags":[
        "organization",
        "welfare"
    ],
    "wof:name":"St Margaret's Home",
    "wof:placetype":"venue"
},
  "geometry": {"coordinates":[-94.133304,45.565359],"type":"Point"}
}