{
  "type": "Feature",
  "properties": {
    "addr:full":"5075 20th St SE Maynard MN 56260",
    "addr:housenumber":"5075",
    "addr:postcode":"56260",
    "addr:street":"20Th St Se",
    "iso:country":"US",
    "sg:address":"5075 20th St SE",
    "sg:city":"Maynard",
    "sg:classifiers":[
        {
            "category":"Real Estate",
            "subcategory":"Real Estate Operator",
            "type":"Services"
        }
    ],
    "sg:phone":"+1 320 367 2512",
    "sg:postcode":"56260",
    "sg:province":"MN",
    "sg:tags":[
        "property",
        "lessor"
    ],
    "wof:name":"Niemeyer Aug",
    "wof:placetype":"venue"
},
  "geometry": {"coordinates":[-95.49277600000001,44.991976],"type":"Point"}
}