{
  "type": "Feature",
  "properties": {
    "iso:country":"US",
    "sg:address":"5205 Miller Trunk Hwy",
    "sg:city":"Duluth",
    "sg:classifiers":[
        {
            "category":"Building & Trades",
            "subcategory":"Plumbing",
            "type":"Services"
        }
    ],
    "sg:phone":"+1 218 729 0392",
    "sg:postcode":"55811",
    "sg:province":"MN",
    "sg:tags":[
        "contractor"
    ],
    "wof:name":"L & S Plbg & Htg of Hibbing",
    "wof:placetype":"venue"
},
  "geometry": {"coordinates":[-92.238077,46.836717],"type":"Point"}
}