{
  "type": "Feature",
  "properties": {
    "iso:country":"US",
    "sg:address":"816 E Main St",
    "sg:city":"Ada",
    "sg:classifiers":[
        {
            "category":"Government",
            "subcategory":"Office",
            "type":"Public Place"
        }
    ],
    "sg:phone":"+1 218 784 3733",
    "sg:postcode":"56510",
    "sg:province":"MN",
    "wof:name":"Deputy Registrar No 71",
    "wof:placetype":"venue"
},
  "geometry": {"coordinates":[-96.517833,47.304402],"type":"Point"}
}