{
  "type": "Feature",
  "properties": {
    "iso:country":"US",
    "sg:address":"1656 White Bear Ave N",
    "sg:city":"St Paul",
    "sg:classifiers":[
        {
            "category":"Food & Beverages",
            "subcategory":"Groceries & Convenience Stores",
            "type":"Retail Goods"
        }
    ],
    "sg:phone":"+1 651 644 6328",
    "sg:postcode":"55106",
    "sg:province":"MN",
    "sg:tags":[
        "grocer"
    ],
    "wof:name":"So Low Grocery Outlet",
    "wof:placetype":"venue"
},
  "geometry": {"coordinates":[-93.025147,44.991819],"type":"Point"}
}