{
  "type": "Feature",
  "properties": {
    "iso:country":"US",
    "sg:address":"307 Central Ave S",
    "sg:city":"Mapleton",
    "sg:classifiers":[
        {
            "category":"Real Estate",
            "subcategory":"Real Estate Operator",
            "type":"Services"
        }
    ],
    "sg:phone":"+1 507 524 3173",
    "sg:postcode":"56065",
    "sg:province":"MN",
    "sg:tags":[
        "property",
        "lessor"
    ],
    "wof:name":"Harlan Jaeger",
    "wof:placetype":"venue"
},
  "geometry": {"coordinates":[-93.958433,43.925232],"type":"Point"}
}