{
  "type": "Feature",
  "properties": {
    "iso:country":"US",
    "sg:address":"1145 Lime Tree Cir",
    "sg:city":"Saint Cloud",
    "sg:classifiers":[
        {
            "category":"Building & Trades",
            "subcategory":"Plumbing",
            "type":"Services"
        }
    ],
    "sg:phone":"+1 320 255 9807",
    "sg:postcode":"56301",
    "sg:province":"MN",
    "sg:tags":[
        "contractor"
    ],
    "wof:name":"Kieke Plumbing",
    "wof:placetype":"venue"
},
  "geometry": {"coordinates":[-94.163168,45.511459],"type":"Point"}
}