{
  "type": "Feature",
  "properties": {
    "addr:full":"14870 240th Ave New Richland MN 56072",
    "addr:housenumber":"14870",
    "addr:postcode":"56072",
    "addr:street":"240Th Ave",
    "iso:country":"US",
    "sg:address":"14870 240th Ave",
    "sg:city":"New Richland",
    "sg:phone":"+1 507 465 8057",
    "sg:postcode":"56072",
    "sg:province":"MN",
    "sg:tags":[
        "farm",
        "corn"
    ],
    "wof:name":"Q Unlimited",
    "wof:placetype":"venue"
},
  "geometry": {"coordinates":[-93.469227,43.90617],"type":"Point"}
}