{
  "type": "Feature",
  "properties": {
    "addr:full":"4937 Morgan Ave S Minneapolis MN 55419",
    "addr:housenumber":"4937",
    "addr:postcode":"55419",
    "addr:street":"Morgan Ave S",
    "iso:country":"US",
    "sg:address":"4937 Morgan Ave S",
    "sg:city":"Minneapolis",
    "sg:classifiers":[
        {
            "category":"Professional",
            "subcategory":"Business Services",
            "type":"Services"
        }
    ],
    "sg:phone":"+1 612 925 6897",
    "sg:postcode":"55419",
    "sg:province":"MN",
    "sg:tags":[
        "equipment",
        "electronic",
        "supplies-wholesale",
        "manufacturer"
    ],
    "sg:website":"http://www.designshare.com",
    "wof:name":"Design Share",
    "wof:placetype":"venue"
},
  "geometry": {"coordinates":[-93.304862,44.913503],"type":"Point"}
}