{
  "type": "Feature",
  "properties": {
    "iso:country":"US",
    "sg:address":"4851 Hamilton Rd",
    "sg:city":"Minnetonka",
    "sg:classifiers":[
        {
            "category":"Communications",
            "subcategory":"Film & Video Production",
            "type":"Services"
        }
    ],
    "sg:phone":"+1 952 931 3856",
    "sg:postcode":"55345",
    "sg:province":"MN",
    "sg:tags":[
        "motion"
    ],
    "wof:name":"Aspen Bodybuilding Productions",
    "wof:placetype":"venue"
},
  "geometry": {"coordinates":[-93.481978,44.914379],"type":"Point"}
}