{
  "type": "Feature",
  "properties": {
    "addr:full":"5867 15th St NW Rochester MN 55901",
    "addr:housenumber":"5867",
    "addr:postcode":"55901",
    "addr:street":"15Th St Nw",
    "iso:country":"US",
    "sg:address":"5867 15th St NW",
    "sg:city":"Rochester",
    "sg:classifiers":[
        {
            "category":"Bus Charters",
            "type":"Transportation"
        }
    ],
    "sg:phone":"+1 507 288 1329",
    "sg:postcode":"55901",
    "sg:province":"MN",
    "sg:tags":[
        "rental"
    ],
    "sg:website":"www.glennsmotorcoachtours.com",
    "wof:name":"Glenn's Motorcoach Charters",
    "wof:placetype":"venue"
},
  "geometry": {"coordinates":[-92.55404,44.0374],"type":"Point"}
}