{
  "type": "Feature",
  "properties": {
    "addr:full":"1435 W Albany Ave Saint Paul MN 55108",
    "addr:housenumber":"1435",
    "addr:postcode":"55108",
    "addr:street":"W Albany Ave",
    "iso:country":"US",
    "sg:address":"1435 W Albany Ave",
    "sg:city":"Saint Paul",
    "sg:classifiers":[
        {
            "category":"Arts & Performance",
            "subcategory":"Theater",
            "type":"Entertainment"
        }
    ],
    "sg:phone":"+1 651 592 3156",
    "sg:postcode":"55108",
    "sg:province":"MN",
    "sg:tags":[
        "group"
    ],
    "wof:name":"Johnny & Peaches Inc",
    "wof:placetype":"venue"
},
  "geometry": {"coordinates":[-93.160859,44.978351],"type":"Point"}
}