{
  "type": "Feature",
  "properties": {
    "addr:full":"1 Mc Glynn Dr Chanhassen MN 55317",
    "addr:housenumber":"1",
    "addr:postcode":"55317",
    "addr:street":"Mc Glynn Dr",
    "iso:country":"US",
    "sg:address":"1 Mc Glynn Dr",
    "sg:city":"Chanhassen",
    "sg:classifiers":[
        {
            "category":"Wholesale",
            "subcategory":"Groceries",
            "type":"Manufacturing & Wholesale Goods"
        }
    ],
    "sg:phone":"+1 952 474 4930",
    "sg:postcode":"55317",
    "sg:province":"MN",
    "sg:tags":[
        "baker"
    ],
    "wof:name":"Pillsbury Inc",
    "wof:placetype":"venue"
},
  "geometry": {"coordinates":[-93.564154,44.861213],"type":"Point"}
}