{
  "type": "Feature",
  "properties": {
    "addr:full":"432 State Hwy 25 Pierz MN 56364",
    "addr:housenumber":"432",
    "addr:postcode":"56364",
    "addr:street":"State Hwy 25 Pierz",
    "iso:country":"US",
    "sg:address":"432 State Hwy 25",
    "sg:city":"Pierz",
    "sg:classifiers":[
        {
            "category":"Freight",
            "type":"Transportation"
        }
    ],
    "sg:phone":"+1 320 277 3562",
    "sg:postcode":"56364",
    "sg:province":"MN",
    "sg:tags":[
        "truck"
    ],
    "wof:name":"Minn-Tex Express Inc",
    "wof:placetype":"venue"
},
  "geometry": {"coordinates":[-94.103455,45.973045],"type":"Point"}
}