{
  "type": "Feature",
  "properties": {
    "addr:full":"4601 Excelsior Blvd Minneapolis MN 55416",
    "addr:housenumber":"4601",
    "addr:postcode":"55416",
    "addr:street":"Excelsior Blvd",
    "iso:country":"US",
    "sg:address":"4601 Excelsior Blvd",
    "sg:city":"Minneapolis",
    "sg:classifiers":[
        {
            "category":"Wholesale",
            "subcategory":"Machinery & Supplies",
            "type":"Manufacturing & Wholesale Goods"
        }
    ],
    "sg:phone":"+1 952 929 2249",
    "sg:postcode":"55416",
    "sg:province":"MN",
    "sg:tags":[
        "equipment",
        "industrial",
        "cartridge",
        "printer"
    ],
    "wof:name":"Graphic Aids Inc",
    "wof:placetype":"venue"
},
  "geometry": {"coordinates":[-93.337431,44.934108],"type":"Point"}
}