{
  "type": "Feature",
  "properties": {
    "addr:full":"2600 46th St NE Longville MN 56655",
    "addr:housenumber":"2600",
    "addr:postcode":"56655",
    "addr:street":"46Th St Ne",
    "iso:country":"US",
    "sg:address":"2600 46th St NE",
    "sg:city":"Longville",
    "sg:classifiers":[
        {
            "category":"Real Estate",
            "subcategory":"Real Estate Agent",
            "type":"Services"
        }
    ],
    "sg:phone":"+1 218 363 2897",
    "sg:postcode":"56655",
    "sg:province":"MN",
    "sg:website":"www.rustysupnorth.com",
    "wof:name":"Rusty's Up North Realty",
    "wof:placetype":"venue"
},
  "geometry": {"coordinates":[-94.13991,46.970395],"type":"Point"}
}