{
  "type": "Feature",
  "properties": {
    "iso:country":"US",
    "sg:address":"12779 Emmer Pl",
    "sg:city":"St Paul",
    "sg:classifiers":[
        {
            "category":"Mining & Drilling",
            "type":"Manufacturing & Wholesale Goods"
        }
    ],
    "sg:phone":"+1 952 322 1514",
    "sg:postcode":"55124",
    "sg:province":"MN",
    "sg:tags":[
        "stone"
    ],
    "wof:name":"Applied Stone Inc",
    "wof:placetype":"venue"
},
  "geometry": {"coordinates":[-93.169403,44.758492],"type":"Point"}
}