{
  "type": "Feature",
  "properties": {
    "addr:full":"7021 12th Ave S Minneapolis MN 55423",
    "addr:housenumber":"7021",
    "addr:postcode":"55423",
    "addr:street":"12Th Ave S",
    "iso:country":"US",
    "sg:address":"7021 12th Ave S",
    "sg:city":"Minneapolis",
    "sg:classifiers":[
        {
            "category":"Professional",
            "type":"Services"
        }
    ],
    "sg:phone":"+1 952 893 1124",
    "sg:postcode":"55423",
    "sg:province":"MN",
    "wof:name":"Xerxes Corporation",
    "wof:placetype":"venue"
},
  "geometry": {"coordinates":[-93.257875,44.874876],"type":"Point"}
}