{
  "type": "Feature",
  "properties": {
    "addr:full":"912 Mendakota Ct Saint Paul MN 55120",
    "addr:housenumber":"912",
    "addr:postcode":"55120",
    "addr:street":"Mendakota Ct",
    "iso:country":"US",
    "sg:address":"912 Mendakota Ct",
    "sg:city":"Saint Paul",
    "sg:classifiers":[
        {
            "category":"Professional",
            "subcategory":"Computer Services",
            "type":"Services"
        }
    ],
    "sg:phone":"+1 651 688 3100",
    "sg:postcode":"55120",
    "sg:province":"MN",
    "sg:tags":[
        "communications",
        "support"
    ],
    "wof:name":"Hitech Innovations Inc",
    "wof:placetype":"venue"
},
  "geometry": {"coordinates":[-93.131175,44.878938],"type":"Point"}
}