{
  "type": "Feature",
  "properties": {
    "addr:full":"17800 Excelsior Blvd Ste 100 Minnetonka MN 55345",
    "addr:housenumber":"17800",
    "addr:postcode":"55345",
    "addr:street":"Excelsior Blvd Ste 100",
    "iso:country":"US",
    "sg:address":"17800 Excelsior Blvd Ste 100",
    "sg:city":"Minnetonka",
    "sg:classifiers":[
        {
            "category":"Professional",
            "subcategory":"Lawyer & Legal Services",
            "type":"Services"
        }
    ],
    "sg:phone":"+1 952 470 4550",
    "sg:postcode":"55345",
    "sg:province":"MN",
    "sg:tags":[
        "divorce",
        "law",
        "family"
    ],
    "sg:website":"www.schechtmanlaw.com",
    "wof:name":"Law Office",
    "wof:placetype":"venue"
},
  "geometry": {"coordinates":[-93.50574,44.909793],"type":"Point"}
}