{
  "type": "Feature",
  "properties": {
    "addr:full":"1117 7th Ave SW Rochester MN 55902",
    "addr:housenumber":"1117",
    "addr:postcode":"55902",
    "addr:street":"7Th Ave Sw",
    "iso:country":"US",
    "sg:address":"1117 7th Ave SW",
    "sg:city":"Rochester",
    "sg:classifiers":[
        {
            "category":"Shopping",
            "type":"Retail Goods"
        }
    ],
    "sg:phone":"+1 507 280 8402",
    "sg:postcode":"55902",
    "sg:province":"MN",
    "sg:tags":[
        "cosmetic",
        "perfume"
    ],
    "wof:name":"Mary Kay Cosmetics",
    "wof:placetype":"venue"
},
  "geometry": {"coordinates":[-92.472444,44.009711],"type":"Point"}
}