{
  "type": "Feature",
  "properties": {
    "iso:country":"US",
    "sg:address":"400 1st Ave N",
    "sg:city":"Minneapolis",
    "sg:classifiers":[
        {
            "category":"Professional",
            "subcategory":"Art Services",
            "type":"Services"
        }
    ],
    "sg:phone":"+1 612 630 1032",
    "sg:postcode":"55401",
    "sg:province":"MN",
    "sg:tags":[
        "photographer"
    ],
    "sg:website":"www.curtisjohnsonphoto.com",
    "wof:name":"Curtis Johnson & Assoc",
    "wof:placetype":"venue"
},
  "geometry": {"coordinates":[-93.27372,44.980453],"type":"Point"}
}