{
  "type": "Feature",
  "properties": {
    "addr:full":"818 W 3rd St Winona MN 55987",
    "addr:housenumber":"818",
    "addr:postcode":"55987",
    "addr:street":"W 3Rd St",
    "iso:country":"US",
    "sg:address":"818 W 3rd St",
    "sg:city":"Winona",
    "sg:classifiers":[
        {
            "category":"Wholesale",
            "subcategory":"Scrap",
            "type":"Manufacturing & Wholesale Goods"
        }
    ],
    "sg:phone":"+1 507 452 8242",
    "sg:postcode":"55987",
    "sg:province":"MN",
    "sg:tags":[
        "recycling",
        "center"
    ],
    "wof:name":"Matejka Recycling",
    "wof:placetype":"venue"
},
  "geometry": {"coordinates":[-91.660563,44.055914],"type":"Point"}
}