{
  "type": "Feature",
  "properties": {
    "addr:full":"12850 Bass Lake Rd Osseo MN 55369",
    "addr:housenumber":"12850",
    "addr:postcode":"55369",
    "addr:street":"Bass Lake Rd",
    "iso:country":"US",
    "sg:address":"12850 Bass Lake Rd",
    "sg:city":"Osseo",
    "sg:classifiers":[
        {
            "category":"Coffee & Tea",
            "type":"Food & Drink"
        },
        {
            "category":"Restaurant",
            "type":"Food & Drink"
        }
    ],
    "sg:menulink":"http://www.allmenus.com/mn/maple-grove/58585-caribou-coffee/menu/",
    "sg:phone":"+1 763 553 1293",
    "sg:postcode":"55369",
    "sg:province":"MN",
    "sg:tags":[
        "tea",
        "coffee",
        "american"
    ],
    "wof:name":"Caribou Coffee",
    "wof:placetype":"venue"
},
  "geometry": {"coordinates":[-93.443549,45.065359],"type":"Point"}
}