{
  "type": "Feature",
  "properties": {
    "iso:country":"US",
    "sg:address":"2209 Girard Ave N",
    "sg:city":"Minneapolis",
    "sg:classifiers":[
        {
            "category":"Building & Trades",
            "subcategory":"Construction",
            "type":"Services"
        }
    ],
    "sg:phone":"+1 763 755 8857",
    "sg:postcode":"55411",
    "sg:province":"MN",
    "sg:tags":[
        "general",
        "contractor"
    ],
    "wof:name":"Sammy's Construction Co",
    "wof:placetype":"venue"
},
  "geometry": {"coordinates":[-93.29715,45.002624],"type":"Point"}
}