{
  "type": "Feature",
  "properties": {
    "addr:full":"62674 240th St Madison Lake MN 56063",
    "addr:housenumber":"62674",
    "addr:postcode":"56063",
    "addr:street":"240Th St",
    "iso:country":"US",
    "sg:address":"62674 240th St",
    "sg:city":"Madison Lake",
    "sg:classifiers":[
        {
            "category":"Real Estate",
            "subcategory":"Real Estate Operator",
            "type":"Services"
        }
    ],
    "sg:phone":"+1 507 243 3629",
    "sg:postcode":"56063",
    "sg:province":"MN",
    "sg:tags":[
        "property",
        "lessor"
    ],
    "wof:name":"R Christensen",
    "wof:placetype":"venue"
},
  "geometry": {"coordinates":[-93.788608,44.232201],"type":"Point"}
}