{
  "type": "Feature",
  "properties": {
    "addr:full":"800 E 3rd St Fairmont MN 56031",
    "addr:housenumber":"800",
    "addr:postcode":"56031",
    "addr:street":"E 3Rd St",
    "iso:country":"US",
    "sg:address":"800 E 3rd St",
    "sg:city":"Fairmont",
    "sg:classifiers":[
        {
            "category":"Utilities",
            "type":"Services"
        },
        {
            "category":"Building & Trades",
            "subcategory":"Landscaping Services",
            "type":"Services"
        }
    ],
    "sg:phone":"+1 507 238 1793",
    "sg:postcode":"56031",
    "sg:province":"MN",
    "sg:tags":[
        "sanitary",
        "lawn",
        "maintenance",
        "grounds"
    ],
    "wof:name":"Andrews Lawn & Snow Service",
    "wof:placetype":"venue"
},
  "geometry": {"coordinates":[-94.45106199999999,43.654876],"type":"Point"}
}