{
  "type": "Feature",
  "properties": {
    "iso:country":"US",
    "sg:address":"6131 42nd Ave N",
    "sg:city":"Minneapolis",
    "sg:classifiers":[
        {
            "category":"Personal",
            "subcategory":"Barber",
            "type":"Services"
        }
    ],
    "sg:phone":"+1 763 535 5723",
    "sg:postcode":"55422",
    "sg:province":"MN",
    "wof:name":"Country Squire Barber Shop",
    "wof:placetype":"venue"
},
  "geometry": {"coordinates":[-93.358498,45.032501],"type":"Point"}
}