{
  "type": "Feature",
  "properties": {
    "iso:country":"US",
    "sg:address":"22465 Berring Ave",
    "sg:city":"Farmington",
    "sg:classifiers":[
        {
            "category":"Manufacturing",
            "subcategory":"Apparel",
            "type":"Manufacturing & Wholesale Goods"
        }
    ],
    "sg:phone":"+1 651 463 4510",
    "sg:postcode":"55024",
    "sg:province":"MN",
    "sg:tags":[
        "clothing",
        "mfg"
    ],
    "wof:name":"JG Wear",
    "wof:placetype":"venue"
},
  "geometry": {"coordinates":[-93.11413899999999,44.630066],"type":"Point"}
}