{
  "type": "Feature",
  "properties": {
    "iso:country":"US",
    "sg:address":"2020 Silver Bell Rd Ste 9",
    "sg:city":"Saint Paul",
    "sg:classifiers":[
        {
            "category":"Health Services",
            "subcategory":"Chiropractor",
            "type":"Services"
        }
    ],
    "sg:phone":"+1 651 452 7018",
    "sg:postcode":"55122",
    "sg:province":"MN",
    "wof:name":"Silver Bell Chiropractic",
    "wof:placetype":"venue"
},
  "geometry": {"coordinates":[-93.210899,44.821201],"type":"Point"}
}