{
  "type": "Feature",
  "properties": {
    "iso:country":"US",
    "sg:address":"601 13th Ave S",
    "sg:city":"Hopkins",
    "sg:classifiers":[
        {
            "category":"Manufacturing",
            "subcategory":"Metals",
            "type":"Manufacturing & Wholesale Goods"
        }
    ],
    "sg:phone":"+1 952 933 8894",
    "sg:postcode":"55343",
    "sg:province":"MN",
    "sg:tags":[
        "metal-wholesale",
        "stamping",
        "manufacturer"
    ],
    "wof:name":"Four Star Stamping Inc",
    "wof:placetype":"venue"
},
  "geometry": {"coordinates":[-93.41692399999999,44.91502],"type":"Point"}
}