{
  "type": "Feature",
  "properties": {
    "iso:country":"US",
    "sg:address":"601 Carlson Pkwy S",
    "sg:city":"Minnetonka",
    "sg:classifiers":[
        {
            "category":"Manufacturing",
            "subcategory":"Retail Goods",
            "type":"Manufacturing & Wholesale Goods"
        }
    ],
    "sg:phone":"+1 952 449 6665",
    "sg:postcode":"55305",
    "sg:province":"MN",
    "sg:tags":[
        "manufacturer"
    ],
    "wof:name":"Popular Content Industries",
    "wof:placetype":"venue"
},
  "geometry": {"coordinates":[-93.469363,44.974638],"type":"Point"}
}