{
  "type": "Feature",
  "properties": {
    "addr:full":"27502 63rd St Royalton MN 56373",
    "addr:housenumber":"27502",
    "addr:postcode":"56373",
    "addr:street":"63Rd St",
    "iso:country":"US",
    "sg:address":"27502 63rd St",
    "sg:city":"Royalton",
    "sg:classifiers":[
        {
            "category":"Farming",
            "subcategory":"Farm & Veterinary Services",
            "type":"Manufacturing & Wholesale Goods"
        }
    ],
    "sg:phone":"+1 320 468 0168",
    "sg:postcode":"56373",
    "sg:province":"MN",
    "sg:tags":[
        "livestock"
    ],
    "wof:name":"Shawns Custom Hoof Care",
    "wof:placetype":"venue"
},
  "geometry": {"coordinates":[-94.092006,45.854356],"type":"Point"}
}