{
  "type": "Feature",
  "properties": {
    "iso:country":"US",
    "sg:address":"110 W 1st St",
    "sg:city":"Hills",
    "sg:phone":"+1 507 962 3210",
    "sg:postcode":"56138",
    "sg:province":"MN",
    "sg:tags":[
        "oil"
    ],
    "wof:name":"Sundem Oil Co & Tank Wagon Svc",
    "wof:placetype":"venue"
},
  "geometry": {"coordinates":[-96.359604,43.529395],"type":"Point"}
}