{
  "type": "Feature",
  "properties": {
    "addr:full":"8658 Upland Ln N Osseo MN 55311",
    "addr:housenumber":"8658",
    "addr:postcode":"55311",
    "addr:street":"Upland Ln N",
    "iso:country":"US",
    "sg:address":"8658 Upland Ln N",
    "sg:city":"Osseo",
    "sg:classifiers":[
        {
            "category":"Professional",
            "subcategory":"Business Services",
            "type":"Services"
        }
    ],
    "sg:phone":"+1 763 494 4885",
    "sg:postcode":"55311",
    "sg:province":"MN",
    "sg:tags":[
        "printing"
    ],
    "wof:name":"Outback International Inc",
    "wof:placetype":"venue"
},
  "geometry": {"coordinates":[-93.481284,45.111128],"type":"Point"}
}