{
  "type": "Feature",
  "properties": {
    "iso:country":"US",
    "sg:address":"1336 Sibley Memorial Hwy",
    "sg:city":"Mendota",
    "sg:classifiers":[
        {
            "category":"Government",
            "subcategory":"Post Office",
            "type":"Public Place"
        }
    ],
    "sg:phone":"+1 651 000 1111",
    "sg:postcode":"55150",
    "sg:province":"MN",
    "wof:name":"US Post Office",
    "wof:placetype":"venue"
},
  "geometry": {"coordinates":[-93.16005800000001,44.888474],"type":"Point"}
}