{
  "type": "Feature",
  "properties": {
    "iso:country":"US",
    "sg:address":"4011 Bemidji Ave N",
    "sg:city":"Bemidji",
    "sg:classifiers":[
        {
            "category":"Manufacturing",
            "subcategory":"Glass & Minerals",
            "type":"Manufacturing & Wholesale Goods"
        }
    ],
    "sg:phone":"+1 218 751 3992",
    "sg:postcode":"56601",
    "sg:province":"MN",
    "sg:tags":[
        "ready"
    ],
    "wof:name":"Bauerly Co",
    "wof:placetype":"venue"
},
  "geometry": {"coordinates":[-94.87491,47.507342],"type":"Point"}
}