{
  "type": "Feature",
  "properties": {
    "addr:full":"157 Roosevelt Rd St Cloud MN 56301",
    "addr:housenumber":"157",
    "addr:postcode":"56301",
    "addr:street":"Roosevelt Rd",
    "iso:country":"US",
    "sg:address":"157 Roosevelt Rd",
    "sg:city":"St Cloud",
    "sg:classifiers":[
        {
            "category":"Social Services",
            "type":"Services"
        }
    ],
    "sg:phone":"+1 320 229 4584",
    "sg:postcode":"56301",
    "sg:province":"MN",
    "sg:tags":[
        "organization",
        "welfare"
    ],
    "wof:name":"Aging Service-Catholic Charity",
    "wof:placetype":"venue"
},
  "geometry": {"coordinates":[-94.188946,45.549897],"type":"Point"}
}