{
  "type": "Feature",
  "properties": {
    "addr:full":"1002 9th Ave N Princeton MN 55371",
    "addr:housenumber":"1002",
    "addr:postcode":"55371",
    "addr:street":"9Th Ave N",
    "iso:country":"US",
    "sg:address":"1002 9th Ave N",
    "sg:city":"Princeton",
    "sg:classifiers":[
        {
            "category":"Education",
            "subcategory":"Special Training",
            "type":"Public Place"
        }
    ],
    "sg:phone":"+1 763 631 2623",
    "sg:postcode":"55371",
    "sg:province":"MN",
    "sg:tags":[
        "school",
        "instruction",
        "driving",
        "vehicle"
    ],
    "wof:name":"Go Driving School Inc",
    "wof:placetype":"venue"
},
  "geometry": {"coordinates":[-93.58612100000001,45.583385],"type":"Point"}
}