{
  "type": "Feature",
  "properties": {
    "iso:country":"US",
    "sg:address":"912 Woodlawn Ave",
    "sg:city":"Le Sueur",
    "sg:classifiers":[
        {
            "category":"Professional",
            "subcategory":"Accounting & Tax Preparation",
            "type":"Services"
        }
    ],
    "sg:phone":"+1 507 665 3481",
    "sg:postcode":"56058",
    "sg:province":"MN",
    "wof:name":"Sqs Inc",
    "wof:placetype":"venue"
},
  "geometry": {"coordinates":[-93.918085,44.449806],"type":"Point"}
}