{
  "type": "Feature",
  "properties": {
    "addr:full":"404 State Hwy 22 Mapleton MN 56065",
    "addr:housenumber":"404",
    "addr:postcode":"56065",
    "addr:street":"State Hwy 22",
    "iso:country":"US",
    "sg:address":"404 State Hwy 22",
    "sg:city":"Mapleton",
    "sg:classifiers":[
        {
            "category":"Wholesale",
            "subcategory":"Farm Supplies",
            "type":"Manufacturing & Wholesale Goods"
        }
    ],
    "sg:phone":"+1 507 524 3717",
    "sg:postcode":"56065",
    "sg:province":"MN",
    "sg:tags":[
        "fertilizer"
    ],
    "sg:website":"www.wfsag.com",
    "wof:name":"Watonwan Farm Svc",
    "wof:placetype":"venue"
},
  "geometry": {"coordinates":[-93.945429,43.92334],"type":"Point"}
}