{
  "type": "Feature",
  "properties": {
    "addr:full":"2800 Patton Rd St Paul MN 55113",
    "addr:housenumber":"2800",
    "addr:postcode":"55113",
    "addr:street":"Patton Rd",
    "iso:country":"US",
    "sg:address":"2800 Patton Rd",
    "sg:city":"St Paul",
    "sg:classifiers":[
        {
            "category":"Professional",
            "subcategory":"Research",
            "type":"Services"
        }
    ],
    "sg:phone":"+1 651 639 8816",
    "sg:postcode":"55113",
    "sg:province":"MN",
    "sg:tags":[
        "development",
        "laboratory"
    ],
    "sg:website":"www.integonline.com",
    "wof:name":"Integ Inc",
    "wof:placetype":"venue"
},
  "geometry": {"coordinates":[-93.20647,45.021771],"type":"Point"}
}