{
  "type": "Feature",
  "properties": {
    "iso:country":"US",
    "sg:address":"625 E Nicollet Blvd Ste 300",
    "sg:city":"Burnsville",
    "sg:classifiers":[
        {
            "category":"Health Services",
            "subcategory":"Dentist",
            "type":"Services"
        }
    ],
    "sg:phone":"+1 952 435 0350",
    "sg:postcode":"55337",
    "sg:province":"MN",
    "sg:tags":[
        "orthodontist"
    ],
    "wof:name":"Rohrer Charles O DDS PA",
    "wof:placetype":"venue"
},
  "geometry": {"coordinates":[-93.270798,44.750099],"type":"Point"}
}