{
  "type": "Feature",
  "properties": {
    "addr:full":"1615 5th St S Hopkins MN 55343",
    "addr:housenumber":"1615",
    "addr:postcode":"55343",
    "addr:street":"5Th St S",
    "iso:country":"US",
    "sg:address":"1615 5th St S",
    "sg:city":"Hopkins",
    "sg:classifiers":[
        {
            "category":"Wholesale",
            "subcategory":"Durable Goods & Equipment",
            "type":"Manufacturing & Wholesale Goods"
        }
    ],
    "sg:phone":"+1 952 938 5170",
    "sg:postcode":"55343",
    "sg:province":"MN",
    "sg:tags":[
        "representative",
        "manufacturer"
    ],
    "wof:name":"Ritten & Assoc",
    "wof:placetype":"venue"
},
  "geometry": {"coordinates":[-93.422495,44.916688],"type":"Point"}
}