{
  "type": "Feature",
  "properties": {
    "addr:full":"2406 Irvine Ave NW Bemidji MN 56601",
    "addr:housenumber":"2406",
    "addr:postcode":"56601",
    "addr:street":"Irvine Ave Nw",
    "iso:country":"US",
    "sg:address":"2406 Irvine Ave NW",
    "sg:city":"Bemidji",
    "sg:classifiers":[
        {
            "category":"Retail",
            "subcategory":"Car Wash",
            "type":"Services"
        }
    ],
    "sg:phone":"+1 218 759 3008",
    "sg:postcode":"56601",
    "sg:province":"MN",
    "sg:tags":[
        "automobile",
        "detail",
        "clean"
    ],
    "wof:name":"Colors On Wheels",
    "wof:placetype":"venue"
},
  "geometry": {"coordinates":[-94.88526899999999,47.491576],"type":"Point"}
}