{
  "type": "Feature",
  "properties": {
    "addr:full":"203 10th St S Sauk Centre MN 56378",
    "addr:housenumber":"203",
    "addr:postcode":"56378",
    "addr:street":"10Th St S",
    "iso:country":"US",
    "sg:address":"203 10th St S",
    "sg:city":"Sauk Centre",
    "sg:classifiers":[
        {
            "category":"Retail",
            "subcategory":"Auto Rental",
            "type":"Services"
        }
    ],
    "sg:phone":"+1 320 352 6561",
    "sg:postcode":"56378",
    "sg:province":"MN",
    "sg:tags":[
        "passenger",
        "car"
    ],
    "wof:name":"Rent A Ford Car",
    "wof:placetype":"venue"
},
  "geometry": {"coordinates":[-94.95012699999999,45.727015],"type":"Point"}
}