{
  "type": "Feature",
  "properties": {
    "addr:full":"122 W Columbia Ct Chaska MN 55318",
    "addr:housenumber":"122",
    "addr:postcode":"55318",
    "addr:street":"W Columbia Ct",
    "iso:country":"US",
    "sg:address":"122 W Columbia Ct",
    "sg:city":"Chaska",
    "sg:classifiers":[
        {
            "category":"Manufacturing",
            "subcategory":"Metals",
            "type":"Manufacturing & Wholesale Goods"
        }
    ],
    "sg:phone":"+1 952 448 3533",
    "sg:postcode":"55318",
    "sg:province":"MN",
    "sg:tags":[
        "extruded",
        "product",
        "extrusion",
        "aluminum",
        "mfg"
    ],
    "sg:website":"www.crownextrusions.com",
    "wof:name":"Crown Extrusions Inc",
    "wof:placetype":"venue"
},
  "geometry": {"coordinates":[-93.59465400000001,44.84473],"type":"Point"}
}