{
  "type": "Feature",
  "properties": {
    "iso:country":"US",
    "sg:address":"8260 Arthur St NE",
    "sg:city":"Minneapolis",
    "sg:classifiers":[
        {
            "category":"Shopping",
            "subcategory":"Computers & Home Electronics",
            "type":"Retail Goods"
        }
    ],
    "sg:phone":"+1 763 784 6950",
    "sg:postcode":"55432",
    "sg:province":"MN",
    "sg:tags":[
        "equipment",
        "satellite",
        "system"
    ],
    "wof:name":"Superior Satellite",
    "wof:placetype":"venue"
},
  "geometry": {"coordinates":[-93.23299900000001,45.11788],"type":"Point"}
}