{
  "type": "Feature",
  "properties": {
    "iso:country":"US",
    "sg:address":"18080 39th Pl N",
    "sg:city":"Minneapolis",
    "sg:classifiers":[
        {
            "category":"Insurance",
            "subcategory":"Insurance Agent",
            "type":"Services"
        }
    ],
    "sg:phone":"+1 763 478 4607",
    "sg:postcode":"55446",
    "sg:province":"MN",
    "wof:name":"Mathwig Insurance Agency",
    "wof:placetype":"venue"
},
  "geometry": {"coordinates":[-93.507682,45.02787],"type":"Point"}
}