{
  "type": "Feature",
  "properties": {
    "iso:country":"US",
    "sg:address":"33774 Co Hwy 12",
    "sg:city":"Battle Lake",
    "sg:classifiers":[
        {
            "category":"Building & Trades",
            "subcategory":"Landscaping Services",
            "type":"Services"
        }
    ],
    "sg:phone":"+1 218 747 2052",
    "sg:postcode":"56515",
    "sg:province":"MN",
    "sg:tags":[
        "lawn",
        "maintenance",
        "grounds"
    ],
    "wof:name":"Brian's Lawn Care",
    "wof:placetype":"venue"
},
  "geometry": {"coordinates":[-95.782837,46.179929],"type":"Point"}
}