{
  "type": "Feature",
  "properties": {
    "iso:country":"US",
    "sg:address":"1009 1st Ave",
    "sg:city":"Gibbon",
    "sg:classifiers":[
        {
            "category":"Shopping",
            "type":"Retail Goods"
        }
    ],
    "sg:phone":"+1 507 834 6791",
    "sg:postcode":"55335",
    "sg:province":"MN",
    "sg:tags":[
        "picture",
        "frame"
    ],
    "wof:name":"P & J's Framing & Gifts",
    "wof:placetype":"venue"
},
  "geometry": {"coordinates":[-94.526572,44.533645],"type":"Point"}
}