{
  "type": "Feature",
  "properties": {
    "addr:full":"1618 Central Ave NE Minneapolis MN 55413",
    "addr:housenumber":"1618",
    "addr:postcode":"55413",
    "addr:street":"Central Ave Ne",
    "iso:country":"US",
    "sg:address":"1618 Central Ave NE",
    "sg:city":"Minneapolis",
    "sg:classifiers":[
        {
            "category":"Food & Beverages",
            "subcategory":"Specialty",
            "type":"Retail Goods"
        },
        {
            "category":"Restaurant",
            "type":"Food & Drink"
        }
    ],
    "sg:phone":"+1 612 789 5282",
    "sg:postcode":"55413",
    "sg:province":"MN",
    "sg:tags":[
        "shop",
        "tea",
        "coffee",
        "eating"
    ],
    "wof:name":"Diamonds Coffee Shoppe",
    "wof:placetype":"venue"
},
  "geometry": {"coordinates":[-93.24736,45.003625],"type":"Point"}
}