{
  "type": "Feature",
  "properties": {
    "addr:full":"2727 Minnehaha Ave Minneapolis MN 55406",
    "addr:housenumber":"2727",
    "addr:postcode":"55406",
    "addr:street":"Minnehaha Ave",
    "iso:country":"US",
    "sg:address":"2727 Minnehaha Ave",
    "sg:city":"Minneapolis",
    "sg:classifiers":[
        {
            "category":"Retail",
            "subcategory":"Auto Repair",
            "type":"Services"
        }
    ],
    "sg:phone":"+1 651 739 4940",
    "sg:postcode":"55406",
    "sg:province":"MN",
    "wof:name":"Maplewood Auto Service Century",
    "wof:placetype":"venue"
},
  "geometry": {"coordinates":[-93.236684,44.952417],"type":"Point"}
}