{
  "type": "Feature",
  "properties": {
    "addr:full":"222 S Paffrath Ave Springfield MN 56087",
    "addr:housenumber":"222",
    "addr:postcode":"56087",
    "addr:street":"S Paffrath Ave",
    "iso:country":"US",
    "sg:address":"222 S Paffrath Ave",
    "sg:city":"Springfield",
    "sg:classifiers":[
        {
            "category":"Freight",
            "type":"Transportation"
        }
    ],
    "sg:phone":"+1 507 723 4279",
    "sg:postcode":"56087",
    "sg:province":"MN",
    "sg:tags":[
        "livestock",
        "hauling"
    ],
    "wof:name":"Halter Trucking Inc",
    "wof:placetype":"venue"
},
  "geometry": {"coordinates":[-94.986315,44.236626],"type":"Point"}
}