{
  "type": "Feature",
  "properties": {
    "iso:country":"US",
    "sg:address":"1886 Berkshire Ln N",
    "sg:city":"Plymouth",
    "sg:classifiers":[
        {
            "category":"Building & Trades",
            "subcategory":"Construction",
            "type":"Services"
        }
    ],
    "sg:phone":"+1 763 559 3734",
    "sg:postcode":"55441",
    "sg:province":"MN",
    "sg:tags":[
        "general",
        "contractor"
    ],
    "wof:name":"Gridor Contractor Inc",
    "wof:placetype":"venue"
},
  "geometry": {"coordinates":[-93.45701200000001,45.000074],"type":"Point"}
}