{
  "type": "Feature",
  "properties": {
    "iso:country":"US",
    "sg:address":"702 2nd Ave N",
    "sg:city":"Wheaton",
    "sg:classifiers":[
        {
            "category":"Government",
            "subcategory":"Office",
            "type":"Public Place"
        }
    ],
    "sg:phone":"+1 320 563 4616",
    "sg:postcode":"56296",
    "sg:province":"MN",
    "sg:tags":[
        "county",
        "taxation"
    ],
    "wof:name":"Traverse County Treasurer",
    "wof:placetype":"venue"
},
  "geometry": {"coordinates":[-96.49403,45.806204],"type":"Point"}
}