{
  "type": "Feature",
  "properties": {
    "iso:country":"US",
    "sg:address":"710 1st St W",
    "sg:city":"Park Rapids",
    "sg:classifiers":[
        {
            "category":"Retail",
            "subcategory":"Funeral Services",
            "type":"Services"
        }
    ],
    "sg:phone":"+1 218 732 7264",
    "sg:postcode":"56470",
    "sg:province":"MN",
    "sg:tags":[
        "director",
        "merchandise"
    ],
    "wof:name":"Cease Family Funeral Home",
    "wof:placetype":"venue"
},
  "geometry": {"coordinates":[-95.06783,46.921983],"type":"Point"}
}