{
  "type": "Feature",
  "properties": {
    "iso:country":"US",
    "sg:address":"16184 Brittany Oaks Cir",
    "sg:city":"Paynesville",
    "sg:classifiers":[
        {
            "category":"Building & Trades",
            "subcategory":"Plumbing",
            "type":"Services"
        }
    ],
    "sg:phone":"+1 320 243 4219",
    "sg:postcode":"56362",
    "sg:province":"MN",
    "sg:tags":[
        "contractor"
    ],
    "wof:name":"S & S Plumbing & Heating",
    "wof:placetype":"venue"
},
  "geometry": {"coordinates":[-94.699708,45.356714],"type":"Point"}
}