{
  "type": "Feature",
  "properties": {
    "iso:country":"US",
    "sg:address":"1307 Black Oak Ave",
    "sg:city":"Montevideo",
    "sg:classifiers":[
        {
            "category":"Restaurant",
            "type":"Food & Drink"
        }
    ],
    "sg:phone":"+1 320 269 6282",
    "sg:postcode":"56265",
    "sg:province":"MN",
    "sg:tags":[
        "eating"
    ],
    "wof:name":"Arts Dairy Freeze",
    "wof:placetype":"venue"
},
  "geometry": {"coordinates":[-95.710351,44.948983],"type":"Point"}
}