{
  "type": "Feature",
  "properties": {
    "addr:full":"9301 Cedar St Monticello MN 55362",
    "addr:housenumber":"9301",
    "addr:postcode":"55362",
    "addr:street":"Cedar St",
    "iso:country":"US",
    "sg:address":"9301 Cedar St",
    "sg:city":"Monticello",
    "sg:classifiers":[
        {
            "category":"Restaurant",
            "type":"Food & Drink"
        }
    ],
    "sg:phone":"+1 763 295 8300",
    "sg:postcode":"55362",
    "sg:province":"MN",
    "sg:tags":[
        "pan",
        "buffet",
        "chinese",
        "asian"
    ],
    "sg:website":"http://www.chinabuffet.net/",
    "wof:name":"China Buffet",
    "wof:placetype":"venue"
},
  "geometry": {"coordinates":[-93.803337,45.286652],"type":"Point"}
}