{
  "type": "Feature",
  "properties": {
    "addr:full":"775 53rd Ave NE Fridley MN 55421",
    "addr:housenumber":"775",
    "addr:postcode":"55421",
    "addr:street":"53Rd Ave Ne",
    "iso:country":"US",
    "sg:address":"775 53rd Ave NE",
    "sg:city":"Fridley",
    "sg:classifiers":[
        {
            "category":"Wholesale",
            "subcategory":"Construction Materials",
            "type":"Manufacturing & Wholesale Goods"
        }
    ],
    "sg:phone":"+1 763 571 7161",
    "sg:postcode":"55421",
    "sg:province":"MN",
    "sg:tags":[
        "equipment",
        "maker",
        "cabinet"
    ],
    "wof:name":"Creative Wood Products",
    "wof:placetype":"venue"
},
  "geometry": {"coordinates":[-93.250534,45.064462],"type":"Point"}
}