{
  "type": "Feature",
  "properties": {
    "iso:country":"US",
    "sg:address":"202 Main St S",
    "sg:city":"Lonsdale",
    "sg:classifiers":[
        {
            "category":"Building & Trades",
            "subcategory":"Plumbing",
            "type":"Services"
        },
        {
            "category":"Building & Trades",
            "subcategory":"Construction",
            "type":"Services"
        }
    ],
    "sg:phone":"+1 507 744 2393",
    "sg:postcode":"55046",
    "sg:province":"MN",
    "sg:tags":[
        "plumber",
        "industrial",
        "system",
        "specialty",
        "heating",
        "contractors-commercial",
        "contractor",
        "air conditioning"
    ],
    "wof:name":"Smisek's Plumbing And Heating",
    "wof:placetype":"venue"
},
  "geometry": {"coordinates":[-93.42858099999999,44.479615],"type":"Point"}
}