{
  "type": "Feature",
  "properties": {
    "addr:full":"833 Gateway Dr NE East Grand Forks MN 56721",
    "addr:housenumber":"833",
    "addr:postcode":"56721",
    "addr:street":"Gateway Dr Ne",
    "iso:country":"US",
    "sg:address":"833 Gateway Dr NE",
    "sg:city":"East Grand Forks",
    "sg:classifiers":[
        {
            "category":"Home & Garden",
            "subcategory":"Garden Supply",
            "type":"Retail Goods"
        }
    ],
    "sg:phone":"+1 701 746 4300",
    "sg:postcode":"56721",
    "sg:province":"MN",
    "sg:tags":[
        "nurseryman"
    ],
    "wof:name":"Pioneer Peat Inc",
    "wof:placetype":"venue"
},
  "geometry": {"coordinates":[-97.009328,47.938423],"type":"Point"}
}