{
  "type": "Feature",
  "properties": {
    "addr:full":"12391 85th Ave NE Foley MN 56329",
    "addr:housenumber":"12391",
    "addr:postcode":"56329",
    "addr:street":"85Th Ave Ne",
    "iso:country":"US",
    "sg:address":"12391 85th Ave NE",
    "sg:city":"Foley",
    "sg:classifiers":[
        {
            "category":"Real Estate",
            "subcategory":"Real Estate Operator",
            "type":"Services"
        }
    ],
    "sg:phone":"+1 320 387 2779",
    "sg:postcode":"56329",
    "sg:province":"MN",
    "sg:tags":[
        "property",
        "lessor"
    ],
    "wof:name":"Gerald Westra",
    "wof:placetype":"venue"
},
  "geometry": {"coordinates":[-93.986435,45.750091],"type":"Point"}
}