{
  "type": "Feature",
  "properties": {
    "addr:full":"4550 Central Ave NE Lot 1527 Minneapolis MN 55421",
    "addr:housenumber":"4550;1527",
    "addr:postcode":"55421",
    "addr:street":"Central Ave Ne Lot",
    "iso:country":"US",
    "sg:address":"4550 Central Ave NE Lot 1527",
    "sg:city":"Minneapolis",
    "sg:classifiers":[
        {
            "category":"Health Services",
            "subcategory":"Chiropractor",
            "type":"Services"
        }
    ],
    "sg:phone":"+1 763 571 7520",
    "sg:postcode":"55421",
    "sg:province":"MN",
    "sg:tags":[
        "chiropractic"
    ],
    "wof:name":"Joy Chiropractic Pa Inc",
    "wof:placetype":"venue"
},
  "geometry": {"coordinates":[-93.247578,45.051058],"type":"Point"}
}