{
  "type": "Feature",
  "properties": {
    "addr:full":"1005 E Blue Earth Ave Fairmont MN 56031",
    "addr:housenumber":"1005",
    "addr:postcode":"56031",
    "addr:street":"E Blue Earth Ave",
    "iso:country":"US",
    "sg:address":"1005 E Blue Earth Ave",
    "sg:city":"Fairmont",
    "sg:classifiers":[
        {
            "category":"Building & Trades",
            "subcategory":"Construction",
            "type":"Services"
        }
    ],
    "sg:phone":"+1 507 238 2098",
    "sg:postcode":"56031",
    "sg:province":"MN",
    "sg:tags":[
        "carpentry",
        "contractor"
    ],
    "wof:name":"Midwest Garage Doors",
    "wof:placetype":"venue"
},
  "geometry": {"coordinates":[-94.44743699999999,43.652242],"type":"Point"}
}