{
  "type": "Feature",
  "properties": {
    "addr:full":"6953 Washington Ave S Minneapolis MN 55439",
    "addr:housenumber":"6953",
    "addr:postcode":"55439",
    "addr:street":"Washington Ave S",
    "iso:country":"US",
    "sg:address":"6953 Washington Ave S",
    "sg:city":"Minneapolis",
    "sg:classifiers":[
        {
            "category":"Wholesale",
            "subcategory":"Farm Supplies",
            "type":"Manufacturing & Wholesale Goods"
        }
    ],
    "sg:phone":"+1 952 942 9282",
    "sg:postcode":"55439",
    "sg:province":"MN",
    "wof:name":"Lesco Service Center 416",
    "wof:placetype":"venue"
},
  "geometry": {"coordinates":[-93.399502,44.877543],"type":"Point"}
}