{
  "type": "Feature",
  "properties": {
    "addr:full":"3010 80th St SE Maynard MN 56260",
    "addr:housenumber":"3010",
    "addr:postcode":"56260",
    "addr:street":"80Th St Se",
    "iso:country":"US",
    "sg:address":"3010 80th St SE",
    "sg:city":"Maynard",
    "sg:phone":"+1 320 367 2982",
    "sg:postcode":"56260",
    "sg:province":"MN",
    "sg:tags":[
        "farm",
        "corn",
        "beet",
        "soybean"
    ],
    "wof:name":"Charles Hinderks",
    "wof:placetype":"venue"
},
  "geometry": {"coordinates":[-95.534066,44.905336],"type":"Point"}
}