{
  "type": "Feature",
  "properties": {
    "addr:full":"1404 Marie Ave Albert Lea MN 56007",
    "addr:housenumber":"1404",
    "addr:postcode":"56007",
    "addr:street":"Marie Ave",
    "iso:country":"US",
    "sg:address":"1404 Marie Ave",
    "sg:city":"Albert Lea",
    "sg:classifiers":[
        {
            "category":"Cinema",
            "subcategory":"Movie Rental",
            "type":"Entertainment"
        }
    ],
    "sg:phone":"+1 507 373 5890",
    "sg:postcode":"56007",
    "sg:province":"MN",
    "sg:tags":[
        "video",
        "tape"
    ],
    "wof:name":"Remembrance Video",
    "wof:placetype":"venue"
},
  "geometry": {"coordinates":[-93.364265,43.66173],"type":"Point"}
}