{
  "type": "Feature",
  "properties": {
    "iso:country":"US",
    "sg:address":"560 Central Ave N",
    "sg:city":"Milaca",
    "sg:classifiers":[
        {
            "category":"Home & Garden",
            "subcategory":"Hardware",
            "type":"Retail Goods"
        }
    ],
    "sg:phone":"+1 320 982 3877",
    "sg:postcode":"56353",
    "sg:province":"MN",
    "sg:tags":[
        "saw"
    ],
    "wof:name":"Pro Edge Tool & Power Equip",
    "wof:placetype":"venue"
},
  "geometry": {"coordinates":[-93.652879,45.759894],"type":"Point"}
}