{
  "type": "Feature",
  "properties": {
    "iso:country":"US",
    "sg:address":"5660 Westbrook Rd",
    "sg:city":"Minneapolis",
    "sg:classifiers":[
        {
            "category":"Professional",
            "subcategory":"Management & Consulting",
            "type":"Services"
        }
    ],
    "sg:phone":"+1 763 545 9149",
    "sg:postcode":"55422",
    "sg:province":"MN",
    "sg:tags":[
        "business"
    ],
    "wof:name":"Lofquist Consulting Services",
    "wof:placetype":"venue"
},
  "geometry": {"coordinates":[-93.35183000000001,45.002673],"type":"Point"}
}