{
  "type": "Feature",
  "properties": {
    "addr:full":"108 S Main St Altura MN 55910",
    "addr:housenumber":"108",
    "addr:postcode":"55910",
    "addr:street":"S Main St",
    "iso:country":"US",
    "sg:address":"108 S Main St",
    "sg:city":"Altura",
    "sg:classifiers":[
        {
            "category":"Professional",
            "subcategory":"Accounting & Tax Preparation",
            "type":"Services"
        }
    ],
    "sg:phone":"+1 507 251 8119",
    "sg:postcode":"55910",
    "sg:province":"MN",
    "sg:tags":[
        "firm"
    ],
    "wof:name":"Donna L Loeffler CPA",
    "wof:placetype":"venue"
},
  "geometry": {"coordinates":[-91.939646,44.070227],"type":"Point"}
}