{
  "type": "Feature",
  "properties": {
    "addr:full":"612 11th Ave S Hopkins MN 55343",
    "addr:housenumber":"612",
    "addr:postcode":"55343",
    "addr:street":"11Th Ave S",
    "iso:country":"US",
    "sg:address":"612 11th Ave S",
    "sg:city":"Hopkins",
    "sg:classifiers":[
        {
            "category":"Real Estate",
            "subcategory":"Real Estate Agent",
            "type":"Services"
        }
    ],
    "sg:phone":"+1 952 930 9850",
    "sg:postcode":"55343",
    "sg:province":"MN",
    "wof:name":"Ocean Realty",
    "wof:placetype":"venue"
},
  "geometry": {"coordinates":[-93.41435300000001,44.915092],"type":"Point"}
}