{
  "type": "Feature",
  "properties": {
    "addr:full":"215 Goodyear Ave Mankato MN 56001",
    "addr:housenumber":"215",
    "addr:postcode":"56001",
    "addr:street":"Goodyear Ave",
    "iso:country":"US",
    "sg:address":"215 Goodyear Ave",
    "sg:city":"Mankato",
    "sg:classifiers":[
        {
            "category":"Personal",
            "subcategory":"Beauty Salon",
            "type":"Services"
        }
    ],
    "sg:phone":"+1 507 387 1136",
    "sg:postcode":"56001",
    "sg:province":"MN",
    "sg:tags":[
        "shop"
    ],
    "wof:name":"Lisa's Styling Studio",
    "wof:placetype":"venue"
},
  "geometry": {"coordinates":[-93.97683499999999,44.173964],"type":"Point"}
}