{
  "type": "Feature",
  "properties": {
    "iso:country":"US",
    "sg:address":"340 1st Pl SW",
    "sg:city":"Oronoco",
    "sg:classifiers":[
        {
            "category":"Building & Trades",
            "subcategory":"Pest Control",
            "type":"Services"
        }
    ],
    "sg:phone":"+1 507 367 2361",
    "sg:postcode":"55960",
    "sg:province":"MN",
    "wof:name":"A-One Animal Control",
    "wof:placetype":"venue"
},
  "geometry": {"coordinates":[-92.540468,44.158296],"type":"Point"}
}