{
  "type": "Feature",
  "properties": {
    "addr:full":"33480 Skogman Lake Rd NE Cambridge MN 55008",
    "addr:postcode":"33480;55008",
    "addr:street":"Skogman Lake Rd Ne",
    "iso:country":"US",
    "sg:address":"33480 Skogman Lake Rd NE",
    "sg:city":"Cambridge",
    "sg:classifiers":[
        {
            "category":"Building & Trades",
            "subcategory":"Construction",
            "type":"Services"
        }
    ],
    "sg:phone":"+1 763 689 9132",
    "sg:postcode":"55008",
    "sg:province":"MN",
    "sg:tags":[
        "house"
    ],
    "wof:name":"Reliant Builders Inc",
    "wof:placetype":"venue"
},
  "geometry": {"coordinates":[-93.14246300000001,45.577395],"type":"Point"}
}