{
  "type": "Feature",
  "properties": {
    "iso:country":"US",
    "sg:address":"7408 Oaklawn Ave",
    "sg:city":"Minneapolis",
    "sg:classifiers":[
        {
            "category":"Professional",
            "subcategory":"Business Services",
            "type":"Services"
        }
    ],
    "sg:phone":"+1 952 820 8327",
    "sg:postcode":"55435",
    "sg:province":"MN",
    "wof:name":"Connie Knapp Interior Design",
    "wof:placetype":"venue"
},
  "geometry": {"coordinates":[-93.337279,44.869219],"type":"Point"}
}