{
  "type": "Feature",
  "properties": {
    "iso:country":"US",
    "sg:address":"613 Roosevelt Rd SE",
    "sg:city":"Bemidji",
    "sg:classifiers":[
        {
            "category":"Professional",
            "subcategory":"Accounting & Tax Preparation",
            "type":"Services"
        }
    ],
    "sg:phone":"+1 218 755 1040",
    "sg:postcode":"56601",
    "sg:province":"MN",
    "sg:tags":[
        "accountant"
    ],
    "wof:name":"Gerald R Smith CPA",
    "wof:placetype":"venue"
},
  "geometry": {"coordinates":[-94.85925,47.453729],"type":"Point"}
}