{
  "type": "Feature",
  "properties": {
    "addr:full":"150 E Sharon St Le Center MN 56057",
    "addr:housenumber":"150",
    "addr:postcode":"56057",
    "addr:street":"E Sharon St",
    "iso:country":"US",
    "sg:address":"150 E Sharon St",
    "sg:city":"Le Center",
    "sg:classifiers":[
        {
            "category":"Manufacturing",
            "subcategory":"Furniture",
            "type":"Manufacturing & Wholesale Goods"
        }
    ],
    "sg:phone":"+1 507 357 4447",
    "sg:postcode":"56057",
    "sg:province":"MN",
    "sg:tags":[
        "household",
        "wood",
        "mfg"
    ],
    "wof:name":"Rainbow Woods Inc",
    "wof:placetype":"venue"
},
  "geometry": {"coordinates":[-93.729732,44.388296],"type":"Point"}
}