{
  "type": "Feature",
  "properties": {
    "addr:full":"521 Folz Blvd Moose Lake MN 55767",
    "addr:housenumber":"521",
    "addr:postcode":"55767",
    "addr:street":"Folz Blvd",
    "iso:country":"US",
    "sg:address":"521 Folz Blvd",
    "sg:city":"Moose Lake",
    "sg:classifiers":[
        {
            "category":"Shopping",
            "type":"Retail Goods"
        }
    ],
    "sg:phone":"+1 218 485 0478",
    "sg:postcode":"55767",
    "sg:province":"MN",
    "sg:tags":[
        "picture",
        "frame"
    ],
    "wof:name":"Blacklock Gallery & Framing St",
    "wof:placetype":"venue"
},
  "geometry": {"coordinates":[-92.76321900000001,46.454429],"type":"Point"}
}