{
  "type": "Feature",
  "properties": {
    "addr:full":"6500 Zane Ave N Minneapolis MN 55429",
    "addr:housenumber":"6500",
    "addr:postcode":"55429",
    "addr:street":"Zane Ave N",
    "iso:country":"US",
    "sg:address":"6500 Zane Ave N",
    "sg:city":"Minneapolis",
    "sg:classifiers":[
        {
            "category":"Wholesale",
            "subcategory":"Durable Goods & Equipment",
            "type":"Manufacturing & Wholesale Goods"
        }
    ],
    "sg:phone":"+1 763 535 2772",
    "sg:postcode":"55429",
    "sg:province":"MN",
    "wof:name":"Bens Wholesale Inc",
    "wof:placetype":"venue"
},
  "geometry": {"coordinates":[-93.35553400000001,45.074687],"type":"Point"}
}