{
  "type": "Feature",
  "properties": {
    "addr:full":"11300 Hampshire Ave S Minneapolis MN 55438",
    "addr:housenumber":"11300",
    "addr:postcode":"55438",
    "addr:street":"Hampshire Ave S",
    "iso:country":"US",
    "sg:address":"11300 Hampshire Ave S",
    "sg:city":"Minneapolis",
    "sg:classifiers":[
        {
            "category":"Manufacturing",
            "subcategory":"Wood Products",
            "type":"Manufacturing & Wholesale Goods"
        }
    ],
    "sg:phone":"+1 952 943 8474",
    "sg:postcode":"55438",
    "sg:province":"MN",
    "wof:name":"Hadley Holding Corporation",
    "wof:placetype":"venue"
},
  "geometry": {"coordinates":[-93.36894100000001,44.80083],"type":"Point"}
}