{
  "type": "Feature",
  "properties": {
    "iso:country":"US",
    "sg:address":"6000 Bass Lake Rd Ste 200",
    "sg:city":"Minneapolis",
    "sg:classifiers":[
        {
            "category":"Real Estate",
            "subcategory":"Real Estate Services",
            "type":"Services"
        },
        {
            "category":"Real Estate",
            "subcategory":"Real Estate Agent",
            "type":"Services"
        }
    ],
    "sg:phone":"+1 612 414 5055",
    "sg:postcode":"55429",
    "sg:province":"MN",
    "sg:tags":[
        "management"
    ],
    "wof:name":"Ftk Properties, Inc.",
    "wof:placetype":"venue"
},
  "geometry": {"coordinates":[-93.356514,45.054626],"type":"Point"}
}