{
  "type": "Feature",
  "properties": {
    "iso:country":"US",
    "sg:address":"5001 W 82nd St",
    "sg:city":"Minneapolis",
    "sg:phone":"+1 952 835 1901",
    "sg:postcode":"55437",
    "sg:province":"MN",
    "sg:website":"http://www.etkelly.com",
    "wof:name":"Et Kelly & Assoc",
    "wof:placetype":"venue"
},
  "geometry": {"coordinates":[-93.342159,44.85474],"type":"Point"}
}