{
  "type": "Feature",
  "properties": {
    "iso:country":"US",
    "sg:address":"13993 Anderson Lakes Pkwy",
    "sg:city":"Eden Prairie",
    "sg:classifiers":[
        {
            "category":"Restaurant",
            "type":"Food & Drink"
        }
    ],
    "sg:menulink":"http://www.allmenus.com/mn/eden-prairie/58398-dominos-pizza/menu/",
    "sg:phone":"+1 952 949 3030",
    "sg:postcode":"55344",
    "sg:province":"MN",
    "sg:tags":[
        "american",
        "wing",
        "pizza"
    ],
    "wof:name":"Domino's Pizza",
    "wof:placetype":"venue"
},
  "geometry": {"coordinates":[-93.454379,44.852905],"type":"Point"}
}