{
  "type": "Feature",
  "properties": {
    "addr:full":"546 Hiawatha Ave Saint Paul MN 55118",
    "addr:housenumber":"546",
    "addr:postcode":"55118",
    "addr:street":"Hiawatha Ave",
    "iso:country":"US",
    "sg:address":"546 Hiawatha Ave",
    "sg:city":"Saint Paul",
    "sg:classifiers":[
        {
            "category":"Professional",
            "subcategory":"Business Services",
            "type":"Services"
        }
    ],
    "sg:phone":"+1 651 442 0833",
    "sg:postcode":"55118",
    "sg:province":"MN",
    "sg:tags":[
        "arbitration"
    ],
    "wof:name":"George Steven Hoffmeyer",
    "wof:placetype":"venue"
},
  "geometry": {"coordinates":[-93.107911,44.918463],"type":"Point"}
}