{
  "type": "Feature",
  "properties": {
    "addr:full":"19086 Jacobs Ave Faribault MN 55021",
    "addr:housenumber":"19086",
    "addr:postcode":"55021",
    "addr:street":"Jacobs Ave",
    "iso:country":"US",
    "sg:address":"19086 Jacobs Ave",
    "sg:city":"Faribault",
    "sg:classifiers":[
        {
            "category":"Organizations",
            "subcategory":"Religious Organization",
            "type":"Services"
        }
    ],
    "sg:phone":"+1 507 334 6098",
    "sg:postcode":"55021",
    "sg:province":"MN",
    "sg:tags":[
        "church"
    ],
    "wof:name":"Nerstrand United Methodist Ch",
    "wof:placetype":"venue"
},
  "geometry": {"coordinates":[-93.101302,44.311179],"type":"Point"}
}