{
  "type": "Feature",
  "properties": {
    "addr:full":"3915 Xerxes Ave S Minneapolis MN 55410",
    "addr:housenumber":"3915",
    "addr:postcode":"55410",
    "addr:street":"Xerxes Ave S",
    "iso:country":"US",
    "sg:address":"3915 Xerxes Ave S",
    "sg:city":"Minneapolis",
    "sg:classifiers":[
        {
            "category":"Professional",
            "subcategory":"Computer Services",
            "type":"Services"
        }
    ],
    "sg:phone":"+1 612 926 6957",
    "sg:postcode":"55410",
    "sg:province":"MN",
    "sg:tags":[
        "web",
        "designer",
        "consultant",
        "system",
        "site",
        "design",
        "software"
    ],
    "wof:name":"Quintility Corporation",
    "wof:placetype":"venue"
},
  "geometry": {"coordinates":[-93.318816,44.932039],"type":"Point"}
}