{
  "type": "Feature",
  "properties": {
    "iso:country":"US",
    "sg:address":"856 Jackson St",
    "sg:city":"St Paul",
    "sg:classifiers":[
        {
            "category":"Retail",
            "subcategory":"Repair Shop",
            "type":"Services"
        }
    ],
    "sg:phone":"+1 651 298 9129",
    "sg:postcode":"55117",
    "sg:province":"MN",
    "sg:tags":[
        "repairing",
        "lawn",
        "mower"
    ],
    "wof:name":"Joe's Small Engine Repair",
    "wof:placetype":"venue"
},
  "geometry": {"coordinates":[-93.096283,44.966937],"type":"Point"}
}