{
  "type": "Feature",
  "properties": {
    "addr:full":"100 Jefferson St SE Hutchinson MN 55350",
    "addr:housenumber":"100",
    "addr:postcode":"55350",
    "addr:street":"Jefferson St Se",
    "iso:country":"US",
    "sg:address":"100 Jefferson St SE",
    "sg:city":"Hutchinson",
    "sg:classifiers":[
        {
            "category":"Communications",
            "subcategory":"Television Station",
            "type":"Services"
        }
    ],
    "sg:phone":"+1 320 587 3113",
    "sg:postcode":"55350",
    "sg:province":"MN",
    "sg:tags":[
        "access",
        "public",
        "cable",
        "channel"
    ],
    "wof:name":"Channel 10",
    "wof:placetype":"venue"
},
  "geometry": {"coordinates":[-94.36643599999999,44.891132],"type":"Point"}
}