{
  "type": "Feature",
  "properties": {
    "iso:country":"US",
    "sg:address":"1101 4th Ave S",
    "sg:city":"Minneapolis",
    "sg:classifiers":[
        {
            "category":"Travel",
            "subcategory":"Hotels & Motels",
            "type":"Entertainment"
        }
    ],
    "sg:phone":"+1 612 339 6633",
    "sg:postcode":"55404",
    "sg:province":"MN",
    "sg:website":"www.minneapolisdowntown.hgi.com",
    "wof:name":"Hilton Garden Inn",
    "wof:placetype":"venue"
},
  "geometry": {"coordinates":[-93.270101,44.970691],"type":"Point"}
}