{
  "type": "Feature",
  "properties": {
    "addr:full":"2751 Hennepin Ave S Ste 174 Minneapolis MN 55408",
    "addr:housenumber":"2751",
    "addr:postcode":"55408",
    "addr:street":"Hennepin Ave S Ste 174",
    "iso:country":"US",
    "sg:address":"2751 Hennepin Ave S Ste 174",
    "sg:city":"Minneapolis",
    "sg:classifiers":[
        {
            "category":"Retail",
            "subcategory":"Auto Repair",
            "type":"Services"
        }
    ],
    "sg:phone":"+1 888 231 7964",
    "sg:postcode":"55408",
    "sg:province":"MN",
    "sg:website":"www.lemonsquad.com",
    "wof:name":"Lemon Squad Used Car Inspections",
    "wof:placetype":"venue"
},
  "geometry": {"coordinates":[-93.298191,44.952318],"type":"Point"}
}