{
  "type": "Feature",
  "properties": {
    "iso:country":"US",
    "sg:address":"10919 33rd Street Ln N",
    "sg:city":"Lake Elmo",
    "sg:classifiers":[
        {
            "category":"Organizations",
            "subcategory":"Membership Organization",
            "type":"Services"
        }
    ],
    "sg:phone":"+1 651 779 2345",
    "sg:postcode":"55042",
    "sg:province":"MN",
    "wof:name":"Stranger Investment Club",
    "wof:placetype":"venue"
},
  "geometry": {"coordinates":[-92.88500500000001,44.99626],"type":"Point"}
}