{
  "type": "Feature",
  "properties": {
    "addr:full":"2898 Co Rd 103 Barnum MN 55707",
    "addr:housenumber":"2898",
    "addr:postcode":"55707",
    "addr:street":"Co Rd 103",
    "iso:country":"US",
    "sg:address":"2898 Co Rd 103",
    "sg:city":"Barnum",
    "sg:classifiers":[
        {
            "category":"Education",
            "subcategory":"School",
            "type":"Public Place"
        },
        {
            "category":"Personal",
            "subcategory":"Beauty Salon",
            "type":"Services"
        }
    ],
    "sg:phone":"+1 218 384 9294",
    "sg:postcode":"55707",
    "sg:province":"MN",
    "sg:tags":[
        "aromatherapy"
    ],
    "wof:name":"Birch Hill Happenings Armthrpy",
    "wof:placetype":"venue"
},
  "geometry": {"coordinates":[-92.465171,46.562506],"type":"Point"}
}