{
  "type": "Feature",
  "properties": {
    "addr:full":"20048 Rushmeyer Lake Rd Albany MN 56307",
    "addr:postcode":"20048;56307",
    "addr:street":"Rushmeyer Lake Rd",
    "iso:country":"US",
    "sg:address":"20048 Rushmeyer Lake Rd",
    "sg:city":"Albany",
    "sg:classifiers":[
        {
            "category":"Shopping",
            "subcategory":"Bicycles & Sporting Goods",
            "type":"Retail Goods"
        }
    ],
    "sg:phone":"+1 320 845 4261",
    "sg:postcode":"56307",
    "sg:province":"MN",
    "wof:name":"Lake View Tackle",
    "wof:placetype":"venue"
},
  "geometry": {"coordinates":[-94.51449,45.626906],"type":"Point"}
}