{
  "type": "Feature",
  "properties": {
    "iso:country":"US",
    "sg:address":"4283 Lakeland Ave N",
    "sg:city":"Minneapolis",
    "sg:classifiers":[
        {
            "category":"Personal",
            "subcategory":"Beauty Salon",
            "type":"Services"
        }
    ],
    "sg:phone":"+1 763 533 5618",
    "sg:postcode":"55422",
    "sg:province":"MN",
    "sg:tags":[
        "shop"
    ],
    "wof:name":"Kathys Kut & Kurl Beauty Shop",
    "wof:placetype":"venue"
},
  "geometry": {"coordinates":[-93.33999900000001,45.033038],"type":"Point"}
}