{
  "type": "Feature",
  "properties": {
    "addr:full":"125 S State St New Ulm MN 56073",
    "addr:housenumber":"125",
    "addr:postcode":"56073",
    "addr:street":"S State St",
    "iso:country":"US",
    "sg:address":"125 S State St",
    "sg:city":"New Ulm",
    "sg:classifiers":[
        {
            "category":"Health Services",
            "subcategory":"Nursing And Care Facility",
            "type":"Services"
        }
    ],
    "sg:phone":"+1 507 354 5276",
    "sg:postcode":"56073",
    "sg:province":"MN",
    "wof:name":"State Street Board & Lodging",
    "wof:placetype":"venue"
},
  "geometry": {"coordinates":[-94.460515,44.310687],"type":"Point"}
}