{
  "type": "Feature",
  "properties": {
    "iso:country":"US",
    "sg:address":"4029 5th St NW",
    "sg:city":"Rochester",
    "sg:classifiers":[
        {
            "category":"Professional",
            "subcategory":"Accounting & Tax Preparation",
            "type":"Services"
        }
    ],
    "sg:phone":"+1 507 288 8882",
    "sg:postcode":"55901",
    "sg:province":"MN",
    "wof:name":"Smith Schaffer & Associates",
    "wof:placetype":"venue"
},
  "geometry": {"coordinates":[-92.523122,44.029525],"type":"Point"}
}