{
  "type": "Feature",
  "properties": {
    "addr:full":"9123 Norman Ridge Cir Minneapolis MN 55437",
    "addr:housenumber":"9123",
    "addr:postcode":"55437",
    "addr:street":"Norman Ridge Cir",
    "iso:country":"US",
    "sg:address":"9123 Norman Ridge Cir",
    "sg:city":"Minneapolis",
    "sg:classifiers":[
        {
            "category":"Shopping",
            "subcategory":"Bicycles & Sporting Goods",
            "type":"Retail Goods"
        }
    ],
    "sg:phone":"+1 952 831 2393",
    "sg:postcode":"55437",
    "sg:province":"MN",
    "wof:name":"Perkins Dry Goods",
    "wof:placetype":"venue"
},
  "geometry": {"coordinates":[-93.359032,44.837391],"type":"Point"}
}