{
  "type": "Feature",
  "properties": {
    "iso:country":"US",
    "sg:address":"9733 Mill Creek Dr",
    "sg:city":"Eden Prairie",
    "sg:classifiers":[
        {
            "category":"Professional",
            "subcategory":"Management & Consulting",
            "type":"Services"
        }
    ],
    "sg:phone":"+1 952 941 1796",
    "sg:postcode":"55347",
    "sg:province":"MN",
    "wof:name":"Industrial Devolepment Svcs",
    "wof:placetype":"venue"
},
  "geometry": {"coordinates":[-93.42465300000001,44.827267],"type":"Point"}
}