{
  "type": "Feature",
  "properties": {
    "addr:full":"15500 Wayzata Blvd Wayzata MN 55391",
    "addr:housenumber":"15500",
    "addr:postcode":"55391",
    "addr:street":"Wayzata Blvd",
    "iso:country":"US",
    "sg:address":"15500 Wayzata Blvd",
    "sg:city":"Wayzata",
    "sg:classifiers":[
        {
            "category":"Health Services",
            "subcategory":"Clinic",
            "type":"Services"
        }
    ],
    "sg:phone":"+1 952 473 1177",
    "sg:postcode":"55391",
    "sg:province":"MN",
    "sg:tags":[
        "home",
        "care"
    ],
    "wof:name":"Home Care Connections PCA Inc",
    "wof:placetype":"venue"
},
  "geometry": {"coordinates":[-93.47614799999999,44.971471],"type":"Point"}
}