{
  "type": "Feature",
  "properties": {
    "iso:country":"US",
    "sg:address":"533 19th St SW",
    "sg:city":"Forest Lake",
    "sg:classifiers":[
        {
            "category":"Autos & Motor Vehicles",
            "subcategory":"Automobile Sales",
            "type":"Retail Goods"
        }
    ],
    "sg:phone":"+1 651 464 1400",
    "sg:postcode":"55025",
    "sg:province":"MN",
    "sg:tags":[
        "new",
        "used"
    ],
    "wof:name":"Wally McCarthys Chevrolet-Cad",
    "wof:placetype":"venue"
},
  "geometry": {"coordinates":[-93.00741600000001,45.275246],"type":"Point"}
}