{
  "type": "Feature",
  "properties": {
    "iso:country":"US",
    "sg:address":"2908 Eagle Dr",
    "sg:city":"Moorhead",
    "sg:classifiers":[
        {
            "category":"Shopping",
            "subcategory":"Used Merchandise",
            "type":"Retail Goods"
        }
    ],
    "sg:phone":"+1 218 287 1338",
    "sg:postcode":"56560",
    "sg:province":"MN",
    "wof:name":"Antiques By Burton",
    "wof:placetype":"venue"
},
  "geometry": {"coordinates":[-96.734402,46.872729],"type":"Point"}
}