{
  "type": "Feature",
  "properties": {
    "iso:country":"US",
    "sg:address":"4013 E County Line Rd",
    "sg:city":"Saint Paul",
    "sg:classifiers":[
        {
            "category":"Professional",
            "subcategory":"Business Services",
            "type":"Services"
        }
    ],
    "sg:phone":"+1 651 653 0750",
    "sg:postcode":"55110",
    "sg:province":"MN",
    "wof:name":"Designwrght Intr Dsign Studios",
    "wof:placetype":"venue"
},
  "geometry": {"coordinates":[-92.984843,45.061874],"type":"Point"}
}