{
  "type": "Feature",
  "properties": {
    "iso:country":"US",
    "sg:address":"1266 1st Ave E",
    "sg:city":"Shakopee",
    "sg:classifiers":[
        {
            "category":"Retail",
            "subcategory":"Event Space",
            "type":"Services"
        },
        {
            "category":"Organizations",
            "subcategory":"Membership Organization",
            "type":"Services"
        }
    ],
    "sg:phone":"+1 952 445 5253",
    "sg:postcode":"55379",
    "sg:province":"MN",
    "sg:tags":[
        "facility",
        "veteran",
        "banquet",
        "reception",
        "military",
        "hall"
    ],
    "sg:website":"http://www.legion.org",
    "wof:name":"American Legion Post No 2",
    "wof:placetype":"venue"
},
  "geometry": {"coordinates":[-93.51047,44.800629],"type":"Point"}
}