{
  "type": "Feature",
  "properties": {
    "addr:full":"3 Thomson Rd Esko MN 55733",
    "addr:housenumber":"3",
    "addr:postcode":"55733",
    "addr:street":"Thomson Rd",
    "iso:country":"US",
    "sg:address":"3 Thomson Rd",
    "sg:city":"Esko",
    "sg:classifiers":[
        {
            "category":"Banks & Credit Unions",
            "subcategory":"Bank",
            "type":"Services"
        }
    ],
    "sg:phone":"+1 218 879 7388",
    "sg:postcode":"55733",
    "sg:province":"MN",
    "wof:name":"Republic Bank",
    "wof:placetype":"venue"
},
  "geometry": {"coordinates":[-92.363276,46.705811],"type":"Point"}
}