{
  "type": "Feature",
  "properties": {
    "addr:full":"3465 Quarry Rd NE Sauk Rapids MN 56379",
    "addr:housenumber":"3465",
    "addr:postcode":"56379",
    "addr:street":"Quarry Rd Ne",
    "iso:country":"US",
    "sg:address":"3465 Quarry Rd NE",
    "sg:city":"Sauk Rapids",
    "sg:classifiers":[
        {
            "category":"Social Services",
            "subcategory":"Child Care",
            "type":"Services"
        }
    ],
    "sg:phone":"+1 320 259 0720",
    "sg:postcode":"56379",
    "sg:province":"MN",
    "sg:tags":[
        "daycare",
        "provider"
    ],
    "wof:name":"Tina Douvier",
    "wof:placetype":"venue"
},
  "geometry": {"coordinates":[-94.156122,45.614149],"type":"Point"}
}