{
  "type": "Feature",
  "properties": {
    "addr:full":"12750 Nicollet Ave Ste 300 Burnsville MN 55337",
    "addr:housenumber":"12750",
    "addr:postcode":"55337",
    "addr:street":"Nicollet Ave Ste 300",
    "iso:country":"US",
    "sg:address":"12750 Nicollet Ave Ste 300",
    "sg:city":"Burnsville",
    "sg:classifiers":[
        {
            "category":"Banks & Credit Unions",
            "subcategory":"Financial Services",
            "type":"Services"
        }
    ],
    "sg:phone":"+1 952 895 5200",
    "sg:postcode":"55337",
    "sg:province":"MN",
    "sg:tags":[
        "broker",
        "mortgage"
    ],
    "wof:name":"Nichols Financial Services Company",
    "wof:placetype":"venue"
},
  "geometry": {"coordinates":[-93.27788099999999,44.772512],"type":"Point"}
}