{
  "type": "Feature",
  "properties": {
    "addr:full":"10033 Nord Rd Minneapolis MN 55437",
    "addr:housenumber":"10033",
    "addr:postcode":"55437",
    "addr:street":"Nord Rd",
    "iso:country":"US",
    "sg:address":"10033 Nord Rd",
    "sg:city":"Minneapolis",
    "sg:classifiers":[
        {
            "category":"Wholesale",
            "subcategory":"Metals & Minerals",
            "type":"Manufacturing & Wholesale Goods"
        }
    ],
    "sg:phone":"+1 952 831 8896",
    "sg:postcode":"55437",
    "sg:province":"MN",
    "sg:tags":[
        "center"
    ],
    "wof:name":"Continental International Co",
    "wof:placetype":"venue"
},
  "geometry": {"coordinates":[-93.344933,44.821523],"type":"Point"}
}