{
  "type": "Feature",
  "properties": {
    "addr:full":"10 17th Ave SW Rochester MN 55901",
    "addr:housenumber":"10",
    "addr:postcode":"55901",
    "addr:street":"17Th Ave Sw",
    "iso:country":"US",
    "sg:address":"10 17th Ave SW",
    "sg:city":"Rochester",
    "sg:classifiers":[
        {
            "category":"Wholesale",
            "subcategory":"Painting Supplies",
            "type":"Manufacturing & Wholesale Goods"
        },
        {
            "category":"Retail",
            "subcategory":"Repair Shop",
            "type":"Services"
        },
        {
            "category":"Home & Garden",
            "subcategory":"Hardware",
            "type":"Retail Goods"
        },
        {
            "category":"Home & Garden",
            "subcategory":"Building Materials",
            "type":"Retail Goods"
        },
        {
            "category":"Wholesale",
            "subcategory":"Hardware",
            "type":"Manufacturing & Wholesale Goods"
        },
        {
            "category":"Home & Garden",
            "subcategory":"Garden Supply",
            "type":"Retail Goods"
        }
    ],
    "sg:phone":"+1 507 289 3321",
    "sg:postcode":"55901",
    "sg:province":"MN",
    "sg:tags":[
        "renting",
        "lawn",
        "outdoor",
        "power",
        "equipment",
        "equipment-sales",
        "landscaping",
        "saw",
        "paint",
        "store"
    ],
    "sg:website":"http://www.stihldealer.net/default-dealer-044448.aspx",
    "wof:name":"Arrow Ace Hardware-Rochester",
    "wof:placetype":"venue"
},
  "geometry": {"coordinates":[-92.487559,44.02351],"type":"Point"}
}