{
  "type": "Feature",
  "properties": {
    "iso:country":"US",
    "sg:address":"505 Merriman Dr",
    "sg:city":"Delano",
    "sg:classifiers":[
        {
            "category":"Recreation",
            "type":"Entertainment"
        }
    ],
    "sg:phone":"+1 763 972 3640",
    "sg:postcode":"55328",
    "sg:province":"MN",
    "wof:name":"Stewarts Crafts",
    "wof:placetype":"venue"
},
  "geometry": {"coordinates":[-93.79938900000001,45.043589],"type":"Point"}
}