{
  "type": "Feature",
  "properties": {
    "iso:country":"US",
    "sg:address":"1020 W Broadway Ave",
    "sg:city":"Minneapolis",
    "sg:classifiers":[
        {
            "category":"Health Services",
            "subcategory":"Dentist",
            "type":"Services"
        }
    ],
    "sg:phone":"+1 612 302 8200",
    "sg:postcode":"55411",
    "sg:province":"MN",
    "wof:name":"Ump Broadway Family",
    "wof:placetype":"venue"
},
  "geometry": {"coordinates":[-93.29289300000001,44.999152],"type":"Point"}
}