{
  "type": "Feature",
  "properties": {
    "addr:full":"1748 Lexington Ave N Saint Paul MN 55113",
    "addr:housenumber":"1748",
    "addr:postcode":"55113",
    "addr:street":"Lexington Ave N",
    "iso:country":"US",
    "sg:address":"1748 Lexington Ave N",
    "sg:city":"Saint Paul",
    "sg:classifiers":[
        {
            "category":"Restaurant",
            "type":"Food & Drink"
        }
    ],
    "sg:phone":"+1 651 488 5585",
    "sg:postcode":"55113",
    "sg:province":"MN",
    "sg:tags":[
        "drinking",
        "eating"
    ],
    "wof:name":"Earls Mister Pizza",
    "wof:placetype":"venue"
},
  "geometry": {"coordinates":[-93.14635699999999,44.994705],"type":"Point"}
}