{
  "type": "Feature",
  "properties": {
    "iso:country":"US",
    "sg:address":"11000 Territorial Dr",
    "sg:city":"Burnsville",
    "sg:classifiers":[
        {
            "category":"Sports & Exercise",
            "subcategory":"Swimming Pool",
            "type":"Entertainment"
        }
    ],
    "sg:phone":"+1 612 860 6680",
    "sg:postcode":"55337",
    "sg:province":"MN",
    "sg:tags":[
        "diving",
        "instruction"
    ],
    "wof:name":"Shirk Diving",
    "wof:placetype":"venue"
},
  "geometry": {"coordinates":[-93.248108,44.803638],"type":"Point"}
}