{
  "type": "Feature",
  "properties": {
    "iso:country":"US",
    "sg:address":"530 Central Ave",
    "sg:city":"Osseo",
    "sg:classifiers":[
        {
            "category":"Insurance",
            "subcategory":"Insurance Agent",
            "type":"Services"
        }
    ],
    "sg:phone":"+1 763 424 3959",
    "sg:postcode":"55369",
    "sg:province":"MN",
    "wof:name":"Becky Meierhofer Insurance",
    "wof:placetype":"venue"
},
  "geometry": {"coordinates":[-93.402022,45.121798],"type":"Point"}
}