{
  "type": "Feature",
  "properties": {
    "addr:full":"4695 32nd Ave SW Pequot Lakes MN 56472",
    "addr:housenumber":"4695",
    "addr:postcode":"56472",
    "addr:street":"32Nd Ave Sw Pequot",
    "iso:country":"US",
    "sg:address":"4695 32nd Ave SW",
    "sg:city":"Pequot Lakes",
    "sg:classifiers":[
        {
            "category":"Farming",
            "subcategory":"Dairy Farm",
            "type":"Manufacturing & Wholesale Goods"
        }
    ],
    "sg:phone":"+1 218 568 5139",
    "sg:postcode":"56472",
    "sg:province":"MN",
    "wof:name":"Wolkenhauer Dairy",
    "wof:placetype":"venue"
},
  "geometry": {"coordinates":[-94.45047599999999,46.633603],"type":"Point"}
}