{
  "type": "Feature",
  "properties": {
    "addr:full":"4456 57th St NW Rochester MN 55901",
    "addr:housenumber":"4456",
    "addr:postcode":"55901",
    "addr:street":"57Th St Nw",
    "iso:country":"US",
    "sg:address":"4456 57th St NW",
    "sg:city":"Rochester",
    "sg:classifiers":[
        {
            "category":"Shopping",
            "subcategory":"Beauty & Cosmetics",
            "type":"Retail Goods"
        }
    ],
    "sg:phone":"+1 507 289 4754",
    "sg:postcode":"55901",
    "sg:province":"MN",
    "sg:tags":[
        "merchandise"
    ],
    "wof:name":"Howard Merle Agency",
    "wof:placetype":"venue"
},
  "geometry": {"coordinates":[-92.52928300000001,44.082099],"type":"Point"}
}