{
  "type": "Feature",
  "properties": {
    "iso:country":"US",
    "sg:address":"5509 Eden Prairie Rd",
    "sg:city":"Minnetonka",
    "sg:classifiers":[
        {
            "category":"Health Services",
            "subcategory":"Doctor",
            "type":"Services"
        }
    ],
    "sg:phone":"+1 952 935 2332",
    "sg:postcode":"55345",
    "sg:province":"MN",
    "wof:name":"Gregory A Olson DDS",
    "wof:placetype":"venue"
},
  "geometry": {"coordinates":[-93.465187,44.902939],"type":"Point"}
}