{
  "type": "Feature",
  "properties": {
    "addr:full":"202 N Broadway Rochester MN 55906",
    "addr:housenumber":"202",
    "addr:postcode":"55906",
    "addr:street":"N Broadway",
    "iso:country":"US",
    "sg:address":"202 N Broadway",
    "sg:city":"Rochester",
    "sg:classifiers":[
        {
            "category":"Shopping",
            "subcategory":"Pharmacy",
            "type":"Retail Goods"
        }
    ],
    "sg:phone":"+1 507 288 6463",
    "sg:postcode":"55906",
    "sg:province":"MN",
    "wof:name":"Medicine Shoppe Pharmacy",
    "wof:placetype":"venue"
},
  "geometry": {"coordinates":[-92.462954,44.025723],"type":"Point"}
}