{
  "type": "Feature",
  "properties": {
    "addr:full":"21500 County 18 Blvd Welch MN 55089",
    "addr:housenumber":"21500",
    "addr:postcode":"55089",
    "addr:street":"County 18 Blvd",
    "iso:country":"US",
    "sg:address":"21500 County 18 Blvd",
    "sg:city":"Welch",
    "sg:classifiers":[
        {
            "category":"Shopping",
            "subcategory":"Florist",
            "type":"Retail Goods"
        }
    ],
    "sg:phone":"+1 651 385 7673",
    "sg:postcode":"55089",
    "sg:province":"MN",
    "wof:name":"Christy & Carol's Creative",
    "wof:placetype":"venue"
},
  "geometry": {"coordinates":[-92.67663,44.641532],"type":"Point"}
}