{
  "type": "Feature",
  "properties": {
    "addr:full":"2171 106th Ln NE Blaine MN 55449",
    "addr:housenumber":"2171",
    "addr:postcode":"55449",
    "addr:street":"106Th Ln Ne",
    "iso:country":"US",
    "sg:address":"2171 106th Ln NE",
    "sg:city":"Blaine",
    "sg:classifiers":[
        {
            "category":"Manufacturing",
            "subcategory":"Metals",
            "type":"Manufacturing & Wholesale Goods"
        }
    ],
    "sg:phone":"+1 763 784 6005",
    "sg:postcode":"55449",
    "sg:province":"MN",
    "sg:tags":[
        "plating",
        "finishing",
        "custom"
    ],
    "wof:name":"Deters Custom Metal Polishing",
    "wof:placetype":"venue"
},
  "geometry": {"coordinates":[-93.215135,45.163772],"type":"Point"}
}