{
  "type": "Feature",
  "properties": {
    "iso:country":"US",
    "sg:address":"519 N Nicollet St",
    "sg:city":"Blue Earth",
    "sg:classifiers":[
        {
            "category":"Personal",
            "subcategory":"Beauty Salon",
            "type":"Services"
        }
    ],
    "sg:phone":"+1 507 526 5170",
    "sg:postcode":"56013",
    "sg:province":"MN",
    "sg:tags":[
        "shop",
        "barber"
    ],
    "wof:name":"Kathys Beauty Salon",
    "wof:placetype":"venue"
},
  "geometry": {"coordinates":[-94.10408700000001,43.643645],"type":"Point"}
}