{
  "type": "Feature",
  "properties": {
    "addr:full":"256 Water St Excelsior MN 55331",
    "addr:housenumber":"256",
    "addr:postcode":"55331",
    "addr:street":"Water St",
    "iso:country":"US",
    "sg:address":"256 Water St",
    "sg:city":"Excelsior",
    "sg:classifiers":[
        {
            "category":"Shopping",
            "subcategory":"Gifts & Souvenirs",
            "type":"Retail Goods"
        }
    ],
    "sg:phone":"+1 952 474 2144",
    "sg:postcode":"55331",
    "sg:province":"MN",
    "sg:tags":[
        "shop"
    ],
    "wof:name":"China & Crystal Ctr",
    "wof:placetype":"venue"
},
  "geometry": {"coordinates":[-93.566706,44.902791],"type":"Point"}
}