{
  "type": "Feature",
  "properties": {
    "addr:full":"17073 Co Hwy 44 South Haven MN 55382",
    "addr:housenumber":"17073",
    "addr:postcode":"55382",
    "addr:street":"Co Hwy 44;Haven",
    "iso:country":"US",
    "sg:address":"17073 Co Hwy 44",
    "sg:city":"South Haven",
    "sg:phone":"+1 320 558 2858",
    "sg:postcode":"55382",
    "sg:province":"MN",
    "sg:tags":[
        "farm",
        "corn"
    ],
    "wof:name":"Donald Kalla",
    "wof:placetype":"venue"
},
  "geometry": {"coordinates":[-94.09712500000001,45.373712],"type":"Point"}
}