{
  "type": "Feature",
  "properties": {
    "addr:full":"9473 Garland Ave Osseo MN 55311",
    "addr:housenumber":"9473",
    "addr:postcode":"55311",
    "addr:street":"Garland Ave",
    "iso:country":"US",
    "sg:address":"9473 Garland Ave",
    "sg:city":"Osseo",
    "sg:classifiers":[
        {
            "category":"Banks & Credit Unions",
            "subcategory":"Financial Services",
            "type":"Services"
        }
    ],
    "sg:phone":"+1 763 420 0282",
    "sg:postcode":"55311",
    "sg:province":"MN",
    "sg:tags":[
        "broker",
        "mortgage"
    ],
    "sg:website":"www.mortgagecapitalmn.com",
    "wof:name":"Mortgage Capital",
    "wof:placetype":"venue"
},
  "geometry": {"coordinates":[-93.495794,45.126198],"type":"Point"}
}