{
  "type": "Feature",
  "properties": {
    "iso:country":"US",
    "sg:address":"5530 Old Viking Blvd NW",
    "sg:city":"Anoka",
    "sg:classifiers":[
        {
            "category":"Health Services",
            "subcategory":"Chiropractor",
            "type":"Services"
        }
    ],
    "sg:phone":"+1 763 754 7368",
    "sg:postcode":"55303",
    "sg:province":"MN",
    "wof:name":"Foss Inc DC",
    "wof:placetype":"venue"
},
  "geometry": {"coordinates":[-93.40716500000001,45.334866],"type":"Point"}
}