{
  "type": "Feature",
  "properties": {
    "addr:full":"3129 39th Ave S Minneapolis MN 55406",
    "addr:housenumber":"3129",
    "addr:postcode":"55406",
    "addr:street":"39Th Ave S",
    "iso:country":"US",
    "sg:address":"3129 39th Ave S",
    "sg:city":"Minneapolis",
    "sg:classifiers":[
        {
            "category":"Building & Trades",
            "subcategory":"Construction",
            "type":"Services"
        }
    ],
    "sg:phone":"+1 612 721 3827",
    "sg:postcode":"55406",
    "sg:province":"MN",
    "sg:tags":[
        "contractor"
    ],
    "wof:name":"Roesner Brothers Masonry",
    "wof:placetype":"venue"
},
  "geometry": {"coordinates":[-93.216477,44.945539],"type":"Point"}
}