{
  "type": "Feature",
  "properties": {
    "iso:country":"US",
    "sg:address":"2578 7th Ave E",
    "sg:city":"North St Paul",
    "sg:classifiers":[
        {
            "category":"Building & Trades",
            "subcategory":"Construction",
            "type":"Services"
        }
    ],
    "sg:phone":"+1 651 779 0218",
    "sg:postcode":"55109",
    "sg:province":"MN",
    "sg:tags":[
        "home",
        "general",
        "remodeling",
        "family",
        "contractor"
    ],
    "sg:website":"www.rossbachconst.com",
    "wof:name":"Rossbach Construction Inc",
    "wof:placetype":"venue"
},
  "geometry": {"coordinates":[-92.99087400000001,45.012755],"type":"Point"}
}