{
  "type": "Feature",
  "properties": {
    "iso:country":"US",
    "sg:address":"10 S 5th St",
    "sg:city":"Minneapolis",
    "sg:classifiers":[
        {
            "category":"Banks & Credit Unions",
            "subcategory":"Bank",
            "type":"Services"
        }
    ],
    "sg:phone":"+1 612 455 3960",
    "sg:postcode":"55415",
    "sg:province":"MN",
    "sg:tags":[
        "loan"
    ],
    "wof:name":"Equity Broadcasting Corp",
    "wof:placetype":"venue"
},
  "geometry": {"coordinates":[-93.271186,44.979255],"type":"Point"}
}