{
  "type": "Feature",
  "properties": {
    "iso:country":"US",
    "sg:address":"7636 Executive Dr",
    "sg:city":"Eden Prairie",
    "sg:classifiers":[
        {
            "category":"Wholesale",
            "subcategory":"Medical Equipment & Supplies",
            "type":"Manufacturing & Wholesale Goods"
        }
    ],
    "sg:phone":"+1 952 934 3111",
    "sg:postcode":"55344",
    "sg:province":"MN",
    "sg:tags":[
        "aids",
        "hearing"
    ],
    "sg:website":"www.avrsono.com",
    "wof:name":"AVR Sonovation",
    "wof:placetype":"venue"
},
  "geometry": {"coordinates":[-93.45008,44.865043],"type":"Point"}
}