{
  "type": "Feature",
  "properties": {
    "addr:full":"3515 Hennepin Ave Minneapolis MN 55408",
    "addr:housenumber":"3515",
    "addr:postcode":"55408",
    "addr:street":"Hennepin Ave",
    "iso:country":"US",
    "sg:address":"3515 Hennepin Ave",
    "sg:city":"Minneapolis",
    "sg:classifiers":[
        {
            "category":"Personal",
            "subcategory":"Skin Care",
            "type":"Services"
        },
        {
            "category":"Personal",
            "subcategory":"Nail Salon",
            "type":"Services"
        }
    ],
    "sg:phone":"+1 612 825 6830",
    "sg:postcode":"55408",
    "sg:province":"MN",
    "wof:name":"Ophelia's Salon",
    "wof:placetype":"venue"
},
  "geometry": {"coordinates":[-93.298401,44.939301],"type":"Point"}
}