{
  "type": "Feature",
  "properties": {
    "addr:full":"2820 33rd Ave S Minneapolis MN 55406",
    "addr:housenumber":"2820",
    "addr:postcode":"55406",
    "addr:street":"33Rd Ave S",
    "iso:country":"US",
    "sg:address":"2820 33rd Ave S",
    "sg:city":"Minneapolis",
    "sg:classifiers":[
        {
            "category":"Manufacturing",
            "subcategory":"Motor Vehicles & Parts",
            "type":"Manufacturing & Wholesale Goods"
        }
    ],
    "sg:phone":"+1 612 722 8728",
    "sg:postcode":"55406",
    "sg:province":"MN",
    "sg:tags":[
        "mfg"
    ],
    "wof:name":"Bonjour Inc",
    "wof:placetype":"venue"
},
  "geometry": {"coordinates":[-93.22437499999999,44.950539],"type":"Point"}
}