{
  "type": "Feature",
  "properties": {
    "addr:full":"15 Brentwood Ave Excelsior MN 55331",
    "addr:housenumber":"15",
    "addr:postcode":"55331",
    "addr:street":"Brentwood Ave",
    "iso:country":"US",
    "sg:address":"15 Brentwood Ave",
    "sg:city":"Excelsior",
    "sg:classifiers":[
        {
            "category":"Building & Trades",
            "subcategory":"Landscaping Services",
            "type":"Services"
        }
    ],
    "sg:phone":"+1 952 474 2260",
    "sg:postcode":"55331",
    "sg:province":"MN",
    "sg:tags":[
        "landscape",
        "contractor"
    ],
    "sg:website":"www.lan-de-con.com",
    "wof:name":"Lan-De-Con Inc",
    "wof:placetype":"venue"
},
  "geometry": {"coordinates":[-93.590469,44.905522],"type":"Point"}
}