{
  "type": "Feature",
  "properties": {
    "addr:full":"11475 Marketplace Dr N Champlin MN 55316",
    "addr:housenumber":"11475",
    "addr:postcode":"55316",
    "addr:street":"Marketplace Dr N",
    "iso:country":"US",
    "sg:address":"11475 Marketplace Dr N",
    "sg:city":"Champlin",
    "sg:classifiers":[
        {
            "category":"Building & Trades",
            "subcategory":"Construction",
            "type":"Services"
        }
    ],
    "sg:phone":"+1 763 323 4792",
    "sg:postcode":"55316",
    "sg:province":"MN",
    "sg:tags":[
        "house"
    ],
    "wof:name":"Cs McCrossan Contruction Co",
    "wof:placetype":"venue"
},
  "geometry": {"coordinates":[-93.390987,45.161546],"type":"Point"}
}