{
  "type": "Feature",
  "properties": {
    "iso:country":"US",
    "sg:address":"81 9th St S",
    "sg:city":"Minneapolis",
    "sg:classifiers":[
        {
            "category":"Professional",
            "type":"Services"
        },
        {
            "category":"Organizations",
            "subcategory":"Community Association",
            "type":"Services"
        }
    ],
    "sg:phone":"+1 612 343 4827",
    "sg:postcode":"55402",
    "sg:province":"MN",
    "sg:tags":[
        "establishment"
    ],
    "wof:name":"Mentoring Partnership Of Mn",
    "wof:placetype":"venue"
},
  "geometry": {"coordinates":[-93.273027,44.974538],"type":"Point"}
}