{
  "type": "Feature",
  "properties": {
    "iso:country":"US",
    "sg:address":"601 N Columbia Ave",
    "sg:city":"Fulda",
    "sg:classifiers":[
        {
            "category":"Insurance",
            "subcategory":"Insurance Agent",
            "type":"Services"
        }
    ],
    "sg:phone":"+1 507 425 3190",
    "sg:postcode":"56131",
    "sg:province":"MN",
    "wof:name":"Farmers Alliance Crop Ins",
    "wof:placetype":"venue"
},
  "geometry": {"coordinates":[-95.59724,43.875399],"type":"Point"}
}