{
  "type": "Feature",
  "properties": {
    "addr:full":"104 2nd Ave NW Mapleton MN 56065",
    "addr:housenumber":"104",
    "addr:postcode":"56065",
    "addr:street":"2Nd Ave Nw",
    "iso:country":"US",
    "sg:address":"104 2nd Ave NW",
    "sg:city":"Mapleton",
    "sg:classifiers":[
        {
            "category":"Government",
            "subcategory":"Office",
            "type":"Public Place"
        }
    ],
    "sg:phone":"+1 507 524 3492",
    "sg:postcode":"56065",
    "sg:province":"MN",
    "sg:tags":[
        "township",
        "government-city",
        "village"
    ],
    "wof:name":"Mapleton Treasurer",
    "wof:placetype":"venue"
},
  "geometry": {"coordinates":[-93.961259,43.927781],"type":"Point"}
}