{
  "type": "Feature",
  "properties": {
    "iso:country":"US",
    "sg:address":"1439 Highview Ave",
    "sg:city":"Saint Paul",
    "sg:classifiers":[
        {
            "category":"Manufacturing",
            "subcategory":"Apparel",
            "type":"Manufacturing & Wholesale Goods"
        }
    ],
    "sg:phone":"+1 651 452 4020",
    "sg:postcode":"55121",
    "sg:province":"MN",
    "sg:tags":[
        "coat",
        "hood",
        "for",
        "mfg"
    ],
    "wof:name":"Arctichood Inc",
    "wof:placetype":"venue"
},
  "geometry": {"coordinates":[-93.169173,44.854383],"type":"Point"}
}