{
  "type": "Feature",
  "properties": {
    "iso:country":"US",
    "sg:address":"26189 President Dr NW",
    "sg:city":"Shevlin",
    "sg:classifiers":[
        {
            "category":"Internet Cafe",
            "subcategory":"None",
            "type":"Food & Drink"
        },
        {
            "category":"Professional",
            "subcategory":"Computer Services",
            "type":"Services"
        }
    ],
    "sg:phone":"+1 218 243 2720",
    "sg:postcode":"56676",
    "sg:province":"MN",
    "sg:tags":[
        "product",
        "designer",
        "network",
        "consultant",
        "system",
        "design",
        "software"
    ],
    "wof:name":"Pinewood Data Services",
    "wof:placetype":"venue"
},
  "geometry": {"coordinates":[-95.189284,47.746106],"type":"Point"}
}