{
  "type": "Feature",
  "properties": {
    "addr:full":"504 E Main St Melrose MN 56352",
    "addr:housenumber":"504",
    "addr:postcode":"56352",
    "addr:street":"E Main St",
    "iso:country":"US",
    "sg:address":"504 E Main St",
    "sg:city":"Melrose",
    "sg:classifiers":[
        {
            "category":"Personal",
            "subcategory":"Massage",
            "type":"Services"
        },
        {
            "category":"Wholesale",
            "subcategory":"Non-durable Goods",
            "type":"Manufacturing & Wholesale Goods"
        },
        {
            "category":"Personal",
            "subcategory":"Barber",
            "type":"Services"
        },
        {
            "category":"Personal",
            "subcategory":"Beauty Salon",
            "type":"Services"
        }
    ],
    "sg:phone":"+1 320 256 4772",
    "sg:postcode":"56352",
    "sg:province":"MN",
    "sg:tags":[
        "equipment",
        "manufacturer",
        "supplies-wholesale",
        "salons-equipment",
        "supply"
    ],
    "wof:name":"H2o Day Spa",
    "wof:placetype":"venue"
},
  "geometry": {"coordinates":[-94.807349,45.674869],"type":"Point"}
}