{
  "type": "Feature",
  "properties": {
    "iso:country":"US",
    "sg:address":"42327 Co Hwy 38",
    "sg:city":"Clitherall",
    "sg:phone":"+1 218 864 5195",
    "sg:postcode":"56524",
    "sg:province":"MN",
    "sg:tags":[
        "farm",
        "corn"
    ],
    "wof:name":"Ralph Hanson",
    "wof:placetype":"venue"
},
  "geometry": {"coordinates":[-95.608362,46.13662],"type":"Point"}
}