{
  "type": "Feature",
  "properties": {
    "addr:full":"1900 Minnesota Ave Benson MN 56215",
    "addr:housenumber":"1900",
    "addr:postcode":"56215",
    "addr:street":"Minnesota Ave",
    "iso:country":"US",
    "sg:address":"1900 Minnesota Ave",
    "sg:city":"Benson",
    "sg:classifiers":[
        {
            "category":"Utilities",
            "subcategory":"Telephone",
            "type":"Services"
        }
    ],
    "sg:phone":"+1 320 843 2246",
    "sg:postcode":"56215",
    "sg:province":"MN",
    "sg:tags":[
        "company"
    ],
    "wof:name":"Alpha Telcom-Pamida Store",
    "wof:placetype":"venue"
},
  "geometry": {"coordinates":[-95.61056499999999,45.310748],"type":"Point"}
}