{
  "type": "Feature",
  "properties": {
    "iso:country":"US",
    "sg:address":"7241 University Ave NE",
    "sg:city":"Minneapolis",
    "sg:classifiers":[
        {
            "category":"Wholesale",
            "subcategory":"Medical Equipment & Supplies",
            "type":"Manufacturing & Wholesale Goods"
        },
        {
            "category":"Social Services",
            "type":"Services"
        },
        {
            "category":"Health Services",
            "subcategory":"Medical Lab",
            "type":"Services"
        },
        {
            "category":"Retail",
            "subcategory":"Repair Shop",
            "type":"Services"
        },
        {
            "category":"Building & Trades",
            "subcategory":"Construction",
            "type":"Services"
        },
        {
            "category":"Wholesale",
            "subcategory":"Motor Vehicles",
            "type":"Manufacturing & Wholesale Goods"
        },
        {
            "category":"Shopping",
            "subcategory":"Pharmacy",
            "type":"Retail Goods"
        }
    ],
    "sg:phone":"+1 763 571 1343",
    "sg:postcode":"55432",
    "sg:province":"MN",
    "sg:tags":[
        "product",
        "wheelchair",
        "ramp",
        "developmentally",
        "disabled",
        "lift",
        "need",
        "home",
        "scooter",
        "special",
        "care"
    ],
    "sg:website":"http://www.thescooterstore.com/",
    "wof:name":"The SCOOTER Store",
    "wof:placetype":"venue"
},
  "geometry": {"coordinates":[-93.26357299999999,45.107616],"type":"Point"}
}