{
  "type": "Feature",
  "properties": {
    "addr:full":"97 10th Ave S Waite Park MN 56387",
    "addr:housenumber":"97",
    "addr:postcode":"56387",
    "addr:street":"10Th Ave S Waite Park",
    "iso:country":"US",
    "sg:address":"97 10th Ave S",
    "sg:city":"Waite Park",
    "sg:classifiers":[
        {
            "category":"Personal",
            "subcategory":"Beauty Salon",
            "type":"Services"
        }
    ],
    "sg:phone":"+1 320 253 3070",
    "sg:postcode":"56387",
    "sg:province":"MN",
    "sg:tags":[
        "shop"
    ],
    "wof:name":"Avanti Salon",
    "wof:placetype":"venue"
},
  "geometry": {"coordinates":[-94.229418,45.55211],"type":"Point"}
}