{
  "type": "Feature",
  "properties": {
    "iso:country":"US",
    "sg:address":"1513 N Payne St",
    "sg:city":"New Ulm",
    "sg:classifiers":[
        {
            "category":"Real Estate",
            "subcategory":"Real Estate Operator",
            "type":"Services"
        }
    ],
    "sg:phone":"+1 507 359 9471",
    "sg:postcode":"56073",
    "sg:province":"MN",
    "sg:tags":[
        "building",
        "apartment"
    ],
    "wof:name":"Hillside Manor Apartments",
    "wof:placetype":"venue"
},
  "geometry": {"coordinates":[-94.482102,44.324752],"type":"Point"}
}