{
  "type": "Feature",
  "properties": {
    "addr:full":"110 58th Ave NE Minneapolis MN 55432",
    "addr:housenumber":"110",
    "addr:postcode":"55432",
    "addr:street":"58Th Ave Ne",
    "iso:country":"US",
    "sg:address":"110 58th Ave NE",
    "sg:city":"Minneapolis",
    "sg:classifiers":[
        {
            "category":"Utilities",
            "subcategory":"Mobile Phone",
            "type":"Services"
        }
    ],
    "sg:phone":"+1 763 571 1050",
    "sg:postcode":"55432",
    "sg:province":"MN",
    "sg:tags":[
        "telephone",
        "cellular"
    ],
    "wof:name":"Cellular Installations Unltd",
    "wof:placetype":"venue"
},
  "geometry": {"coordinates":[-93.266972,45.073362],"type":"Point"}
}