{
  "type": "Feature",
  "properties": {
    "iso:country":"US",
    "sg:address":"6450 120th St NW",
    "sg:city":"Pine Island",
    "sg:classifiers":[
        {
            "category":"Travel",
            "subcategory":"Campground",
            "type":"Entertainment"
        }
    ],
    "sg:phone":"+1 507 356 8594",
    "sg:postcode":"55963",
    "sg:province":"MN",
    "wof:name":"Hidden Meadows Rv Park",
    "wof:placetype":"venue"
},
  "geometry": {"coordinates":[-92.565333,44.173074],"type":"Point"}
}