{
  "type": "Feature",
  "properties": {
    "addr:full":"10340 Baltimore St NE Minneapolis MN 55449",
    "addr:housenumber":"10340",
    "addr:postcode":"55449",
    "addr:street":"Baltimore St Ne",
    "iso:country":"US",
    "sg:address":"10340 Baltimore St NE",
    "sg:city":"Minneapolis",
    "sg:classifiers":[
        {
            "category":"Professional",
            "subcategory":"Accounting & Tax Preparation",
            "type":"Services"
        },
        {
            "category":"Banks & Credit Unions",
            "subcategory":"Financial Services",
            "type":"Services"
        }
    ],
    "sg:phone":"+1 763 780 9431",
    "sg:postcode":"55449",
    "sg:province":"MN",
    "sg:tags":[
        "return",
        "preparation-business",
        "taxes-consultants",
        "loan",
        "reporting",
        "representative",
        "alternative",
        "bookkeeping"
    ],
    "sg:website":"http://www.hrblock.com",
    "wof:name":"H&R Block",
    "wof:placetype":"venue"
},
  "geometry": {"coordinates":[-93.233467,45.158692],"type":"Point"}
}