{
  "type": "Feature",
  "properties": {
    "addr:full":"781 Barge Channel Rd St Paul MN 55107",
    "addr:housenumber":"781",
    "addr:postcode":"55107",
    "addr:street":"Barge Channel Rd",
    "iso:country":"US",
    "sg:address":"781 Barge Channel Rd",
    "sg:city":"St Paul",
    "sg:classifiers":[
        {
            "category":"Autos & Motor Vehicles",
            "subcategory":"Boat Sales",
            "type":"Retail Goods"
        }
    ],
    "sg:phone":"+1 651 602 0347",
    "sg:postcode":"55107",
    "sg:province":"MN",
    "sg:tags":[
        "equipment",
        "marine",
        "supply"
    ],
    "sg:website":"www.lsmarine.com",
    "wof:name":"L & S Ind & Marine Inc",
    "wof:placetype":"venue"
},
  "geometry": {"coordinates":[-93.058125,44.921918],"type":"Point"}
}