{
  "type": "Feature",
  "properties": {
    "addr:full":"30 S 7th St Ste 500 Minneapolis MN 55402",
    "addr:housenumber":"30",
    "addr:postcode":"55402",
    "addr:street":"S 7Th St Ste 500",
    "iso:country":"US",
    "sg:address":"30 S 7th St Ste 500",
    "sg:city":"Minneapolis",
    "sg:classifiers":[
        {
            "category":"Travel",
            "subcategory":"Travel Agent",
            "type":"Entertainment"
        }
    ],
    "sg:phone":"+1 612 339 0994",
    "sg:postcode":"55402",
    "sg:province":"MN",
    "sg:tags":[
        "agency",
        "services-commercial"
    ],
    "wof:name":"Travel Traders",
    "wof:placetype":"venue"
},
  "geometry": {"coordinates":[-93.27306,44.977231],"type":"Point"}
}