{
  "type": "Feature",
  "properties": {
    "iso:country":"US",
    "sg:address":"125 W Main St",
    "sg:city":"Caledonia",
    "sg:classifiers":[
        {
            "category":"Shopping",
            "subcategory":"Used Merchandise",
            "type":"Retail Goods"
        }
    ],
    "sg:phone":"+1 507 724 5434",
    "sg:postcode":"55921",
    "sg:province":"MN",
    "wof:name":"Maybes",
    "wof:placetype":"venue"
},
  "geometry": {"coordinates":[-91.497891,43.634542],"type":"Point"}
}