{
  "type": "Feature",
  "properties": {
    "addr:full":"105 E Myrtle St Duluth MN 55811",
    "addr:housenumber":"105",
    "addr:postcode":"55811",
    "addr:street":"E Myrtle St",
    "iso:country":"US",
    "sg:address":"105 E Myrtle St",
    "sg:city":"Duluth",
    "sg:classifiers":[
        {
            "category":"Shopping",
            "subcategory":"Florist",
            "type":"Retail Goods"
        }
    ],
    "sg:phone":"+1 218 727 4286",
    "sg:postcode":"55811",
    "sg:province":"MN",
    "wof:name":"Flowers On Rocks",
    "wof:placetype":"venue"
},
  "geometry": {"coordinates":[-92.126257,46.80133],"type":"Point"}
}