{
  "type": "Feature",
  "properties": {
    "addr:full":"541 Washington Ave Villard MN 56385",
    "addr:housenumber":"541",
    "addr:postcode":"56385",
    "addr:street":"Washington Ave Villard",
    "iso:country":"US",
    "sg:address":"541 Washington Ave",
    "sg:city":"Villard",
    "sg:classifiers":[
        {
            "category":"Banks & Credit Unions",
            "subcategory":"Bank",
            "type":"Services"
        }
    ],
    "sg:phone":"+1 320 554 2984",
    "sg:postcode":"56385",
    "sg:province":"MN",
    "wof:name":"Eagle Bank",
    "wof:placetype":"venue"
},
  "geometry": {"coordinates":[-95.268997,45.712196],"type":"Point"}
}