{
  "type": "Feature",
  "properties": {
    "addr:full":"30092 Back Lake Rd Dalton MN 56324",
    "addr:housenumber":"30092",
    "addr:postcode":"56324",
    "addr:street":"Back Lake Rd",
    "iso:country":"US",
    "sg:address":"30092 Back Lake Rd",
    "sg:city":"Dalton",
    "sg:classifiers":[
        {
            "category":"Insurance",
            "subcategory":"Insurance Agent",
            "type":"Services"
        }
    ],
    "sg:phone":"+1 218 589 8940",
    "sg:postcode":"56324",
    "sg:province":"MN",
    "sg:tags":[
        "carrie"
    ],
    "wof:name":"Kirby Greene Insurance Agency",
    "wof:placetype":"venue"
},
  "geometry": {"coordinates":[-95.86183699999999,46.199037],"type":"Point"}
}