{
  "type": "Feature",
  "properties": {
    "iso:country":"US",
    "sg:address":"10251 Gilbert Trl",
    "sg:city":"Brainerd",
    "sg:classifiers":[
        {
            "category":"Banks & Credit Unions",
            "subcategory":"Financial Services",
            "type":"Services"
        }
    ],
    "sg:phone":"+1 218 828 9832",
    "sg:postcode":"56401",
    "sg:province":"MN",
    "sg:tags":[
        "investor"
    ],
    "wof:name":"Lorimor Investments Inc",
    "wof:placetype":"venue"
},
  "geometry": {"coordinates":[-94.186511,46.394027],"type":"Point"}
}