{
  "type": "Feature",
  "properties": {
    "iso:country":"US",
    "sg:address":"6873 Clayton Ave E",
    "sg:city":"Inver Grove Heights",
    "sg:classifiers":[
        {
            "category":"Professional",
            "subcategory":"Management & Consulting",
            "type":"Services"
        }
    ],
    "sg:phone":"+1 651 455 0896",
    "sg:postcode":"55076",
    "sg:province":"MN",
    "sg:tags":[
        "transportation"
    ],
    "wof:name":"Proconsul Inc",
    "wof:placetype":"venue"
},
  "geometry": {"coordinates":[-93.034762,44.850211],"type":"Point"}
}