{
  "type": "Feature",
  "properties": {
    "addr:full":"7233 Upton Ave S Minneapolis MN 55423",
    "addr:housenumber":"7233",
    "addr:postcode":"55423",
    "addr:street":"Upton Ave S",
    "iso:country":"US",
    "sg:address":"7233 Upton Ave S",
    "sg:city":"Minneapolis",
    "sg:classifiers":[
        {
            "category":"Building & Trades",
            "subcategory":"Construction",
            "type":"Services"
        }
    ],
    "sg:phone":"+1 612 869 8249",
    "sg:postcode":"55423",
    "sg:province":"MN",
    "sg:tags":[
        "house"
    ],
    "wof:name":"Justus Builders",
    "wof:placetype":"venue"
},
  "geometry": {"coordinates":[-93.31490100000001,44.871516],"type":"Point"}
}