{
  "type": "Feature",
  "properties": {
    "iso:country":"US",
    "sg:address":"33 S 6th St Ste 4100",
    "sg:city":"Minneapolis",
    "sg:classifiers":[
        {
            "category":"Professional",
            "subcategory":"Lawyer & Legal Services",
            "type":"Services"
        }
    ],
    "sg:phone":"+1 612 630 5177",
    "sg:postcode":"55402",
    "sg:province":"MN",
    "wof:name":"Butler William B Pllc",
    "wof:placetype":"venue"
},
  "geometry": {"coordinates":[-93.272598,44.978401],"type":"Point"}
}