{
  "type": "Feature",
  "properties": {
    "addr:full":"2540 Sunny Meadow Ln Red Wing MN 55066",
    "addr:housenumber":"2540",
    "addr:postcode":"55066",
    "addr:street":"Sunny Meadow Ln",
    "iso:country":"US",
    "sg:address":"2540 Sunny Meadow Ln",
    "sg:city":"Red Wing",
    "sg:classifiers":[
        {
            "category":"Social Services",
            "subcategory":"Child Care",
            "type":"Services"
        }
    ],
    "sg:phone":"+1 651 388 2475",
    "sg:postcode":"55066",
    "sg:province":"MN",
    "sg:tags":[
        "day"
    ],
    "wof:name":"Kristies Daycare",
    "wof:placetype":"venue"
},
  "geometry": {"coordinates":[-92.53545200000001,44.531211],"type":"Point"}
}