{
  "type": "Feature",
  "properties": {
    "addr:full":"52947 Deerwood Trl Mankato MN 56003",
    "addr:housenumber":"52947",
    "addr:postcode":"56003",
    "addr:street":"Deerwood Trl",
    "iso:country":"US",
    "sg:address":"52947 Deerwood Trl",
    "sg:city":"Mankato",
    "sg:classifiers":[
        {
            "category":"Retail",
            "subcategory":"Repair Shop",
            "type":"Services"
        }
    ],
    "sg:phone":"+1 507 947 3278",
    "sg:postcode":"56003",
    "sg:province":"MN",
    "sg:tags":[
        "refinishing",
        "furniture"
    ],
    "wof:name":"Furniture Medic Inc",
    "wof:placetype":"venue"
},
  "geometry": {"coordinates":[-94.1062,44.1838],"type":"Point"}
}