{
  "type": "Feature",
  "properties": {
    "iso:country":"US",
    "sg:address":"324 W Superior St Suite 1130",
    "sg:city":"Duluth",
    "sg:classifiers":[
        {
            "category":"Health Services",
            "subcategory":"Dentist",
            "type":"Services"
        }
    ],
    "sg:phone":"+1 218 722 1949",
    "sg:postcode":"55802",
    "sg:province":"MN",
    "sg:website":"http://www.pattersonfamilydental.com",
    "wof:name":"Patterson Family Dental",
    "wof:placetype":"venue"
},
  "geometry": {"coordinates":[-92.102183,46.783845],"type":"Point"}
}