{
  "type": "Feature",
  "properties": {
    "iso:country":"US",
    "sg:address":"405 E Superior St",
    "sg:city":"Duluth",
    "sg:classifiers":[
        {
            "category":"Organizations",
            "subcategory":"Membership Organization",
            "type":"Services"
        }
    ],
    "sg:phone":"+1 218 722 8654",
    "sg:postcode":"55802",
    "sg:province":"MN",
    "wof:name":"Vietnam Vets Ctr",
    "wof:placetype":"venue"
},
  "geometry": {"coordinates":[-92.092349,46.791812],"type":"Point"}
}