{
  "type": "Feature",
  "properties": {
    "addr:full":"20851 Commerce Blvd Rogers MN 55374",
    "addr:housenumber":"20851",
    "addr:postcode":"55374",
    "addr:street":"Commerce Blvd",
    "iso:country":"US",
    "sg:address":"20851 Commerce Blvd",
    "sg:city":"Rogers",
    "sg:classifiers":[
        {
            "category":"Wholesale",
            "subcategory":"Electrical",
            "type":"Manufacturing & Wholesale Goods"
        }
    ],
    "sg:phone":"+1 763 428 6090",
    "sg:postcode":"55374",
    "sg:province":"MN",
    "sg:tags":[
        "supply",
        "sign"
    ],
    "wof:name":"Signs Plus Banners",
    "wof:placetype":"venue"
},
  "geometry": {"coordinates":[-93.543679,45.193363],"type":"Point"}
}