{
  "type": "Feature",
  "properties": {
    "addr:full":"950 Nicollet Mall Minneapolis MN 55403",
    "addr:housenumber":"950",
    "addr:postcode":"55403",
    "addr:street":"Nicollet Mall",
    "iso:country":"US",
    "sg:address":"950 Nicollet Mall",
    "sg:city":"Minneapolis",
    "sg:classifiers":[
        {
            "category":"Shopping",
            "subcategory":"Florist",
            "type":"Retail Goods"
        }
    ],
    "sg:phone":"+1 612 746 4500",
    "sg:postcode":"55403",
    "sg:province":"MN",
    "sg:website":"tommycarvers.com",
    "wof:name":"Tommy Carvers Garden of Flowers",
    "wof:placetype":"venue"
},
  "geometry": {"coordinates":[-93.2743,44.974499],"type":"Point"}
}