{
  "type": "Feature",
  "properties": {
    "iso:country":"US",
    "sg:address":"425 W Sanborn St",
    "sg:city":"Springfield",
    "sg:classifiers":[
        {
            "category":"Social Services",
            "subcategory":"Child Care",
            "type":"Services"
        }
    ],
    "sg:phone":"+1 507 723 6441",
    "sg:postcode":"56087",
    "sg:province":"MN",
    "sg:tags":[
        "day",
        "provides"
    ],
    "wof:name":"Cynthia S Schnobrich",
    "wof:placetype":"venue"
},
  "geometry": {"coordinates":[-94.982619,44.241901],"type":"Point"}
}