{
  "type": "Feature",
  "properties": {
    "iso:country":"US",
    "sg:address":"15035 Spruce Hill Park Rd NE",
    "sg:city":"Miltona",
    "sg:classifiers":[
        {
            "category":"Farming",
            "subcategory":"Dairy Farm",
            "type":"Manufacturing & Wholesale Goods"
        }
    ],
    "sg:phone":"+1 218 943 5581",
    "sg:postcode":"56354",
    "sg:province":"MN",
    "wof:name":"David Lusty",
    "wof:placetype":"venue"
},
  "geometry": {"coordinates":[-95.20877400000001,46.038424],"type":"Point"}
}