{
  "type": "Feature",
  "properties": {
    "iso:country":"US",
    "sg:address":"18137 655th Ave",
    "sg:city":"Darwin",
    "sg:phone":"+1 320 275 2949",
    "sg:postcode":"55324",
    "sg:province":"MN",
    "sg:tags":[
        "farm",
        "corn",
        "soybean"
    ],
    "wof:name":"Stan Radunz",
    "wof:placetype":"venue"
},
  "geometry": {"coordinates":[-94.45023,45.009092],"type":"Point"}
}