{
  "type": "Feature",
  "properties": {
    "addr:full":"1175 240th St Ormsby MN 56162",
    "addr:housenumber":"1175",
    "addr:postcode":"56162",
    "addr:street":"240Th St",
    "iso:country":"US",
    "sg:address":"1175 240th St",
    "sg:city":"Ormsby",
    "sg:phone":"+1 507 639 3055",
    "sg:postcode":"56162",
    "sg:province":"MN",
    "sg:tags":[
        "farm",
        "corn",
        "soybean"
    ],
    "wof:name":"Donald Winkelman",
    "wof:placetype":"venue"
},
  "geometry": {"coordinates":[-94.64645299999999,43.833888],"type":"Point"}
}