{
  "type": "Feature",
  "properties": {
    "addr:full":"275 Market St Minneapolis MN 55405",
    "addr:housenumber":"275",
    "addr:postcode":"55405",
    "addr:street":"Market St",
    "iso:country":"US",
    "sg:address":"275 Market St",
    "sg:city":"Minneapolis",
    "sg:classifiers":[
        {
            "category":"Wholesale",
            "subcategory":"Furniture",
            "type":"Manufacturing & Wholesale Goods"
        }
    ],
    "sg:phone":"+1 612 746 3484",
    "sg:postcode":"55405",
    "sg:province":"MN",
    "wof:name":"Fine Lines Furniture Showroom",
    "wof:placetype":"venue"
},
  "geometry": {"coordinates":[-93.289587,44.979969],"type":"Point"}
}