{
  "type": "Feature",
  "properties": {
    "iso:country":"US",
    "sg:address":"811 Center Ave S",
    "sg:city":"Hayfield",
    "sg:classifiers":[
        {
            "category":"Building & Trades",
            "subcategory":"Construction",
            "type":"Services"
        }
    ],
    "sg:phone":"+1 507 477 2268",
    "sg:postcode":"55940",
    "sg:province":"MN",
    "sg:tags":[
        "house"
    ],
    "wof:name":"Martin John",
    "wof:placetype":"venue"
},
  "geometry": {"coordinates":[-92.84768,43.882177],"type":"Point"}
}