{
  "type": "Feature",
  "properties": {
    "addr:full":"3174 194th Ave NW Cedar MN 55011",
    "addr:housenumber":"3174",
    "addr:postcode":"55011",
    "addr:street":"194Th Ave Nw Cedar",
    "iso:country":"US",
    "sg:address":"3174 194th Ave NW",
    "sg:city":"Cedar",
    "sg:classifiers":[
        {
            "category":"Building & Trades",
            "subcategory":"Construction",
            "type":"Services"
        }
    ],
    "sg:phone":"+1 763 753 6259",
    "sg:postcode":"55011",
    "sg:province":"MN",
    "sg:tags":[
        "hanging",
        "contractor"
    ],
    "wof:name":"C&C Painting",
    "wof:placetype":"venue"
},
  "geometry": {"coordinates":[-93.34679,45.32171],"type":"Point"}
}