{
  "type": "Feature",
  "properties": {
    "iso:country":"US",
    "sg:address":"5724 Huntington St",
    "sg:city":"Duluth",
    "sg:classifiers":[
        {
            "category":"Home & Garden",
            "subcategory":"Home Furnishings",
            "type":"Retail Goods"
        }
    ],
    "sg:phone":"+1 218 624 8337",
    "sg:postcode":"55807",
    "sg:province":"MN",
    "sg:tags":[
        "quilting"
    ],
    "wof:name":"Cindy's Creative Quilting",
    "wof:placetype":"venue"
},
  "geometry": {"coordinates":[-92.17171999999999,46.747405],"type":"Point"}
}