{
  "type": "Feature",
  "properties": {
    "addr:full":"27961 Navaho Ave Belle Plaine MN 56011",
    "addr:housenumber":"27961",
    "addr:postcode":"56011",
    "addr:street":"Navaho Ave Belle Plaine",
    "iso:country":"US",
    "sg:address":"27961 Navaho Ave",
    "sg:city":"Belle Plaine",
    "sg:classifiers":[
        {
            "category":"Freight",
            "type":"Transportation"
        }
    ],
    "sg:phone":"+1 507 665 6109",
    "sg:postcode":"56011",
    "sg:province":"MN",
    "sg:tags":[
        "trucking"
    ],
    "wof:name":"J D Andrews Trucking",
    "wof:placetype":"venue"
},
  "geometry": {"coordinates":[-93.778307,44.543751],"type":"Point"}
}