{
  "type": "Feature",
  "properties": {
    "iso:country":"US",
    "sg:address":"5930 Earle Brown Dr",
    "sg:city":"Minneapolis",
    "sg:classifiers":[
        {
            "category":"Food & Beverages",
            "subcategory":"Supermarket",
            "type":"Retail Goods"
        }
    ],
    "sg:phone":"+1 763 566 4830",
    "sg:postcode":"55430",
    "sg:province":"MN",
    "sg:tags":[
        "super",
        "store"
    ],
    "sg:website":"http://www.kmart.com",
    "wof:name":"Kmart",
    "wof:placetype":"venue"
},
  "geometry": {"coordinates":[-93.306302,45.063369],"type":"Point"}
}