{
  "type": "Feature",
  "properties": {
    "addr:full":"640 E 11th St Albert Lea MN 56007",
    "addr:housenumber":"640",
    "addr:postcode":"56007",
    "addr:street":"E 11Th St",
    "iso:country":"US",
    "sg:address":"640 E 11th St",
    "sg:city":"Albert Lea",
    "sg:classifiers":[
        {
            "category":"Wholesale",
            "subcategory":"Hardware",
            "type":"Manufacturing & Wholesale Goods"
        }
    ],
    "sg:phone":"+1 507 373 1155",
    "sg:postcode":"56007",
    "sg:province":"MN",
    "sg:tags":[
        "plumbing",
        "supply"
    ],
    "wof:name":"Albert Lea Winnelson",
    "wof:placetype":"venue"
},
  "geometry": {"coordinates":[-93.360297,43.629586],"type":"Point"}
}