{
  "type": "Feature",
  "properties": {
    "addr:full":"625 S Sibley Ave Litchfield MN 55355",
    "addr:housenumber":"625",
    "addr:postcode":"55355",
    "addr:street":"S Sibley Ave",
    "iso:country":"US",
    "sg:address":"625 S Sibley Ave",
    "sg:city":"Litchfield",
    "sg:classifiers":[
        {
            "category":"Shopping",
            "subcategory":"Pharmacy",
            "type":"Retail Goods"
        }
    ],
    "sg:phone":"+1 320 693 7985",
    "sg:postcode":"55355",
    "sg:province":"MN",
    "wof:name":"Litchfield Healthmart Pharmacy",
    "wof:placetype":"venue"
},
  "geometry": {"coordinates":[-94.52796600000001,45.119854],"type":"Point"}
}