{
  "type": "Feature",
  "properties": {
    "addr:full":"41017 60th St Blue Earth MN 56013",
    "addr:housenumber":"41017",
    "addr:postcode":"56013",
    "addr:street":"60Th St",
    "iso:country":"US",
    "sg:address":"41017 60th St",
    "sg:city":"Blue Earth",
    "sg:classifiers":[
        {
            "category":"Retail",
            "subcategory":"Auto Repair",
            "type":"Services"
        }
    ],
    "sg:phone":"+1 507 526 2754",
    "sg:postcode":"56013",
    "sg:province":"MN",
    "sg:tags":[
        "general"
    ],
    "wof:name":"Rick Sunken Repair",
    "wof:placetype":"venue"
},
  "geometry": {"coordinates":[-94.03709600000001,43.572413],"type":"Point"}
}