{
  "type": "Feature",
  "properties": {
    "iso:country":"US",
    "sg:address":"1842 26th Ave NW",
    "sg:city":"Saint Paul",
    "sg:classifiers":[
        {
            "category":"Professional",
            "subcategory":"Business Services",
            "type":"Services"
        }
    ],
    "sg:phone":"+1 651 633 7854",
    "sg:postcode":"55112",
    "sg:province":"MN",
    "wof:name":"Decorating Den",
    "wof:placetype":"venue"
},
  "geometry": {"coordinates":[-93.220298,45.079326],"type":"Point"}
}