{
  "type": "Feature",
  "properties": {
    "addr:full":"1382 Arlington Ave E Saint Paul MN 55106",
    "addr:housenumber":"1382",
    "addr:postcode":"55106",
    "addr:street":"Arlington Ave E",
    "iso:country":"US",
    "sg:address":"1382 Arlington Ave E",
    "sg:city":"Saint Paul",
    "sg:classifiers":[
        {
            "category":"Retail",
            "subcategory":"Repair Shop",
            "type":"Services"
        }
    ],
    "sg:phone":"+1 651 776 4540",
    "sg:postcode":"55106",
    "sg:province":"MN",
    "wof:name":"Franks Sharpening Services",
    "wof:placetype":"venue"
},
  "geometry": {"coordinates":[-93.04253,44.984708],"type":"Point"}
}