{
  "type": "Feature",
  "properties": {
    "addr:full":"7925 Co Rd 110 W Mound MN 55364",
    "addr:housenumber":"7925",
    "addr:postcode":"55364",
    "addr:street":"Co Rd 110 W Mound",
    "iso:country":"US",
    "sg:address":"7925 Co Rd 110 W",
    "sg:city":"Mound",
    "sg:classifiers":[
        {
            "category":"Personal",
            "subcategory":"Beauty Salon",
            "type":"Services"
        }
    ],
    "sg:phone":"+1 952 446 9219",
    "sg:postcode":"55364",
    "sg:province":"MN",
    "sg:tags":[
        "shop"
    ],
    "wof:name":"Hair In City",
    "wof:placetype":"venue"
},
  "geometry": {"coordinates":[-93.724839,44.922291],"type":"Point"}
}