{
  "type": "Feature",
  "properties": {
    "iso:country":"US",
    "sg:address":"1303 Smith Ave",
    "sg:city":"Worthington",
    "sg:classifiers":[
        {
            "category":"Building & Trades",
            "subcategory":"Plumbing",
            "type":"Services"
        }
    ],
    "sg:phone":"+1 507 376 4071",
    "sg:postcode":"56187",
    "sg:province":"MN",
    "sg:tags":[
        "plumbing",
        "contractor"
    ],
    "wof:name":"Phil's Plumbing",
    "wof:placetype":"venue"
},
  "geometry": {"coordinates":[-95.595043,43.628397],"type":"Point"}
}