{
  "type": "Feature",
  "properties": {
    "iso:country":"US",
    "sg:address":"5701 Kentucky Ave N # 155",
    "sg:city":"Minneapolis",
    "sg:classifiers":[
        {
            "category":"Real Estate",
            "subcategory":"Real Estate Services",
            "type":"Services"
        },
        {
            "category":"Real Estate",
            "subcategory":"Real Estate Agent",
            "type":"Services"
        }
    ],
    "sg:phone":"+1 763 537 6422",
    "sg:postcode":"55428",
    "sg:province":"MN",
    "sg:tags":[
        "management"
    ],
    "wof:name":"Certified Home Closers Inc",
    "wof:placetype":"venue"
},
  "geometry": {"coordinates":[-93.369629,45.055988],"type":"Point"}
}