{
  "type": "Feature",
  "properties": {
    "iso:country":"US",
    "sg:address":"9950 245th St E",
    "sg:city":"Lakeville",
    "sg:classifiers":[
        {
            "category":"Wholesale",
            "subcategory":"Construction Materials",
            "type":"Manufacturing & Wholesale Goods"
        }
    ],
    "sg:phone":"+1 952 469 3123",
    "sg:postcode":"55044",
    "sg:province":"MN",
    "sg:tags":[
        "pallet",
        "skid"
    ],
    "wof:name":"G N C Pallett",
    "wof:placetype":"venue"
},
  "geometry": {"coordinates":[-93.312484,44.59486],"type":"Point"}
}