{
  "type": "Feature",
  "properties": {
    "addr:full":"9950 245th St E Lakeville MN 55044",
    "addr:housenumber":"9950",
    "addr:postcode":"55044",
    "addr:street":"245Th St E",
    "iso:country":"US",
    "sg:address":"9950 245th St E",
    "sg:city":"Lakeville",
    "sg:classifiers":[
        {
            "category":"Wholesale",
            "subcategory":"Construction Materials",
            "type":"Manufacturing & Wholesale Goods"
        }
    ],
    "sg:phone":"+1 952 469 3123",
    "sg:postcode":"55044",
    "sg:province":"MN",
    "sg:tags":[
        "pallet",
        "skid"
    ],
    "wof:name":"G N C Pallett",
    "wof:placetype":"venue"
},
  "geometry": {"coordinates":[-93.312484,44.59486],"type":"Point"}
}