{
  "type": "Feature",
  "properties": {
    "addr:full":"3225 Co Rd 4 SW Alexandria MN 56308",
    "addr:housenumber":"3225",
    "addr:postcode":"56308",
    "addr:street":"Co Rd 4 Sw",
    "iso:country":"US",
    "sg:address":"3225 Co Rd 4 SW",
    "sg:city":"Alexandria",
    "sg:phone":"+1 320 763 7861",
    "sg:postcode":"56308",
    "sg:province":"MN",
    "sg:tags":[
        "farm",
        "soybean"
    ],
    "wof:name":"Warren Engelbrecht",
    "wof:placetype":"venue"
},
  "geometry": {"coordinates":[-95.424989,45.802439],"type":"Point"}
}