{
  "type": "Feature",
  "properties": {
    "iso:country":"US",
    "sg:address":"1489 N Holton St",
    "sg:city":"St Paul",
    "sg:classifiers":[
        {
            "category":"Building & Trades",
            "subcategory":"Construction",
            "type":"Services"
        }
    ],
    "sg:phone":"+1 651 642 0128",
    "sg:postcode":"55108",
    "sg:province":"MN",
    "sg:tags":[
        "repairing",
        "remodeling",
        "contractor"
    ],
    "wof:name":"Joe Hamel Co",
    "wof:placetype":"venue"
},
  "geometry": {"coordinates":[-93.160601,44.984803],"type":"Point"}
}