{
  "type": "Feature",
  "properties": {
    "addr:full":"19007 270th St Fergus Falls MN 56537",
    "addr:housenumber":"19007",
    "addr:postcode":"56537",
    "addr:street":"270Th St",
    "iso:country":"US",
    "sg:address":"19007 270th St",
    "sg:city":"Fergus Falls",
    "sg:classifiers":[
        {
            "category":"Farming",
            "subcategory":"Dairy Farm",
            "type":"Manufacturing & Wholesale Goods"
        }
    ],
    "sg:phone":"+1 218 736 5366",
    "sg:postcode":"56537",
    "sg:province":"MN",
    "wof:name":"Tungseth Farm",
    "wof:placetype":"venue"
},
  "geometry": {"coordinates":[-96.09263799999999,46.354928],"type":"Point"}
}