{
  "type": "Feature",
  "properties": {
    "addr:full":"8936 Lyndale Ave S Bloomington MN 55420",
    "addr:housenumber":"8936",
    "addr:postcode":"55420",
    "addr:street":"Lyndale Ave S",
    "iso:country":"US",
    "sg:address":"8936 Lyndale Ave S",
    "sg:city":"Bloomington",
    "sg:classifiers":[
        {
            "category":"Personal",
            "subcategory":"Beauty Salon",
            "type":"Services"
        }
    ],
    "sg:phone":"+1 952 881 7423",
    "sg:postcode":"55420",
    "sg:province":"MN",
    "wof:name":"Looks With Style",
    "wof:placetype":"venue"
},
  "geometry": {"coordinates":[-93.288653,44.841827],"type":"Point"}
}