{
  "type": "Feature",
  "properties": {
    "iso:country":"US",
    "sg:address":"Coffman Memorial Union 300 Washington Ave SE",
    "sg:city":"Minneapolis",
    "sg:classifiers":[
        {
            "category":"Shopping",
            "subcategory":"Books",
            "type":"Retail Goods"
        },
        {
            "category":"Education",
            "subcategory":"University",
            "type":"Public Place"
        }
    ],
    "sg:phone":"+1 612 625 6000",
    "sg:postcode":"55455",
    "sg:province":"MN",
    "sg:tags":[
        "bookstore",
        "college",
        "store"
    ],
    "sg:website":"www.bookstores.umn.edu/",
    "wof:name":"University of Minnesota Bookstore",
    "wof:placetype":"venue"
},
  "geometry": {"coordinates":[-93.235388,44.973163],"type":"Point"}
}