{
  "type": "Feature",
  "properties": {
    "addr:full":"202 Main St S Pierz MN 56364",
    "addr:housenumber":"202",
    "addr:postcode":"56364",
    "addr:street":"Main St S Pierz",
    "iso:country":"US",
    "sg:address":"202 Main St S",
    "sg:city":"Pierz",
    "sg:classifiers":[
        {
            "category":"Retail",
            "subcategory":"Funeral Services",
            "type":"Services"
        }
    ],
    "sg:phone":"+1 320 468 6453",
    "sg:postcode":"56364",
    "sg:province":"MN",
    "sg:tags":[
        "director"
    ],
    "wof:name":"Shelley-Virnig Funeral Chapel",
    "wof:placetype":"venue"
},
  "geometry": {"coordinates":[-94.10336100000001,45.977158],"type":"Point"}
}