{
  "type": "Feature",
  "properties": {
    "iso:country":"US",
    "sg:address":"434 Lake St",
    "sg:city":"Excelsior",
    "sg:classifiers":[
        {
            "category":"Personal",
            "subcategory":"Beauty Salon",
            "type":"Services"
        }
    ],
    "sg:phone":"+1 952 380 5040",
    "sg:postcode":"55331",
    "sg:province":"MN",
    "sg:tags":[
        "spa"
    ],
    "wof:name":"Taglio-Cut Style Design",
    "wof:placetype":"venue"
},
  "geometry": {"coordinates":[-93.576401,44.899101],"type":"Point"}
}