{
  "type": "Feature",
  "properties": {
    "iso:country":"US",
    "sg:address":"141 Fillmore St W",
    "sg:city":"Preston",
    "sg:classifiers":[
        {
            "category":"Professional",
            "subcategory":"Lawyer & Legal Services",
            "type":"Services"
        }
    ],
    "sg:phone":"+1 507 765 3600",
    "sg:postcode":"55965",
    "sg:province":"MN",
    "sg:tags":[
        "attorney",
        "practice"
    ],
    "wof:name":"Law Office Of Scott K Springer",
    "wof:placetype":"venue"
},
  "geometry": {"coordinates":[-92.083389,43.670311],"type":"Point"}
}