{
  "type": "Feature",
  "properties": {
    "addr:full":"151 Silver Lake Rd NW Ste 10 Saint Paul MN 55112",
    "addr:housenumber":"151;10",
    "addr:postcode":"55112",
    "addr:street":"Silver Lake Rd Nw Ste",
    "iso:country":"US",
    "sg:address":"151 Silver Lake Rd NW Ste 10",
    "sg:city":"Saint Paul",
    "sg:classifiers":[
        {
            "category":"Professional",
            "subcategory":"Employment Agencies",
            "type":"Services"
        }
    ],
    "sg:phone":"+1 651 697 0334",
    "sg:postcode":"55112",
    "sg:province":"MN",
    "wof:name":"Solutions Operations & Maintenance",
    "wof:placetype":"venue"
},
  "geometry": {"coordinates":[-93.21820099999999,45.051899],"type":"Point"}
}