{
  "type": "Feature",
  "properties": {
    "addr:full":"1220 Co Rd E W Saint Paul MN 55112",
    "addr:housenumber":"1220",
    "addr:postcode":"55112",
    "addr:street":"Co Rd E W",
    "iso:country":"US",
    "sg:address":"1220 Co Rd E W",
    "sg:city":"Saint Paul",
    "sg:classifiers":[
        {
            "category":"Banks & Credit Unions",
            "subcategory":"Bank",
            "type":"Services"
        }
    ],
    "sg:phone":"+1 651 490 2666",
    "sg:postcode":"55112",
    "sg:province":"MN",
    "sg:tags":[
        "national",
        "commercial"
    ],
    "wof:name":"Wells Fargo",
    "wof:placetype":"venue"
},
  "geometry": {"coordinates":[-93.204131,45.050245],"type":"Point"}
}