{
  "type": "Feature",
  "properties": {
    "addr:full":"7201 85th Ave Princeton MN 55371",
    "addr:housenumber":"7201",
    "addr:postcode":"55371",
    "addr:street":"85Th Ave",
    "iso:country":"US",
    "sg:address":"7201 85th Ave",
    "sg:city":"Princeton",
    "sg:classifiers":[
        {
            "category":"Retail",
            "subcategory":"Auto Repair",
            "type":"Services"
        }
    ],
    "sg:phone":"+1 763 389 8462",
    "sg:postcode":"55371",
    "sg:province":"MN",
    "sg:tags":[
        "general"
    ],
    "wof:name":"John Hulett Auto Repair",
    "wof:placetype":"venue"
},
  "geometry": {"coordinates":[-93.585611,45.648487],"type":"Point"}
}