{
  "type": "Feature",
  "properties": {
    "addr:full":"538 25th Ave N St Cloud MN 56303",
    "addr:housenumber":"538",
    "addr:postcode":"56303",
    "addr:street":"25Th Ave N",
    "iso:country":"US",
    "sg:address":"538 25th Ave N",
    "sg:city":"St Cloud",
    "sg:classifiers":[
        {
            "category":"Home & Garden",
            "subcategory":"Building Materials",
            "type":"Retail Goods"
        }
    ],
    "sg:phone":"+1 320 255 5525",
    "sg:postcode":"56303",
    "sg:province":"MN",
    "sg:tags":[
        "windows"
    ],
    "wof:name":"Window World",
    "wof:placetype":"venue"
},
  "geometry": {"coordinates":[-94.187794,45.563443],"type":"Point"}
}