{
  "type": "Feature",
  "properties": {
    "iso:country":"US",
    "sg:address":"2000 Plymouth Rd",
    "sg:city":"Hopkins",
    "sg:classifiers":[
        {
            "category":"Professional",
            "subcategory":"Employment Agencies",
            "type":"Services"
        }
    ],
    "sg:phone":"+1 763 546 1100",
    "sg:postcode":"55305",
    "sg:province":"MN",
    "sg:tags":[
        "supply",
        "help",
        "contractor"
    ],
    "wof:name":"Right Staff",
    "wof:placetype":"venue"
},
  "geometry": {"coordinates":[-93.442291,44.961963],"type":"Point"}
}