{
  "type": "Feature",
  "properties": {
    "iso:country":"US",
    "sg:address":"5255 Edina Industrial Blvd",
    "sg:city":"Edina",
    "sg:classifiers":[
        {
            "category":"Professional",
            "subcategory":"Management & Consulting",
            "type":"Services"
        },
        {
            "category":"Wholesale",
            "subcategory":"Durable Goods & Equipment",
            "type":"Manufacturing & Wholesale Goods"
        }
    ],
    "sg:phone":"+1 952 832 9100",
    "sg:postcode":"55439",
    "sg:province":"MN",
    "sg:tags":[
        "representative",
        "manufacturer"
    ],
    "wof:name":"Midwest Group Inc",
    "wof:placetype":"venue"
},
  "geometry": {"coordinates":[-93.35892,44.863148],"type":"Point"}
}