{
  "type": "Feature",
  "properties": {
    "addr:full":"1405 78th St Victoria MN 55386",
    "addr:housenumber":"1405",
    "addr:postcode":"55386",
    "addr:street":"78Th St",
    "iso:country":"US",
    "sg:address":"1405 78th St",
    "sg:city":"Victoria",
    "sg:classifiers":[
        {
            "category":"Insurance",
            "subcategory":"Insurance Agent",
            "type":"Services"
        }
    ],
    "sg:phone":"+1 952 443 2131",
    "sg:postcode":"55386",
    "sg:province":"MN",
    "wof:name":"Thrivent Financial-Lutherans",
    "wof:placetype":"venue"
},
  "geometry": {"coordinates":[-93.652608,44.863187],"type":"Point"}
}