{
  "type": "Feature",
  "properties": {
    "addr:full":"3829 W Broadway Ave Minneapolis MN 55422",
    "addr:housenumber":"3829",
    "addr:postcode":"55422",
    "addr:street":"W Broadway Ave",
    "iso:country":"US",
    "sg:address":"3829 W Broadway Ave",
    "sg:city":"Minneapolis",
    "sg:classifiers":[
        {
            "category":"Retail",
            "subcategory":"Laundry & Dry Cleaning",
            "type":"Services"
        }
    ],
    "sg:phone":"+1 952 942 7488",
    "sg:postcode":"55422",
    "sg:province":"MN",
    "sg:tags":[
        "cleaners",
        "rug",
        "carpet"
    ],
    "wof:name":"American Carpet & Upholstery",
    "wof:placetype":"venue"
},
  "geometry": {"coordinates":[-93.330782,45.023829],"type":"Point"}
}