{
  "type": "Feature",
  "properties": {
    "addr:full":"4276 W Lake St Pequot Lakes MN 56472",
    "addr:housenumber":"4276",
    "addr:postcode":"56472",
    "addr:street":"W Lake St",
    "iso:country":"US",
    "sg:address":"4276 W Lake St",
    "sg:city":"Pequot Lakes",
    "sg:classifiers":[
        {
            "category":"Professional",
            "subcategory":"Business Services",
            "type":"Services"
        }
    ],
    "sg:phone":"+1 218 568 4015",
    "sg:postcode":"56472",
    "sg:province":"MN",
    "wof:name":"Kinship Partners",
    "wof:placetype":"venue"
},
  "geometry": {"coordinates":[-94.31289200000001,46.599217],"type":"Point"}
}