{
  "type": "Feature",
  "properties": {
    "addr:full":"100 6th St N Minneapolis MN 55403",
    "addr:housenumber":"100",
    "addr:postcode":"55403",
    "addr:street":"6Th St N",
    "iso:country":"US",
    "sg:address":"100 6th St N",
    "sg:city":"Minneapolis",
    "sg:classifiers":[
        {
            "category":"Professional",
            "subcategory":"Lawyer & Legal Services",
            "type":"Services"
        }
    ],
    "sg:phone":"+1 612 573 3000",
    "sg:postcode":"55403",
    "sg:province":"MN",
    "sg:tags":[
        "attorney"
    ],
    "sg:website":"www.tapg-law.com",
    "wof:name":"Terhaar Archibald Pfefferle",
    "wof:placetype":"venue"
},
  "geometry": {"coordinates":[-93.27597799999999,44.980438],"type":"Point"}
}