{
  "type": "Feature",
  "properties": {
    "iso:country":"US",
    "sg:address":"22164 Red Oak Dr",
    "sg:city":"Rogers",
    "sg:classifiers":[
        {
            "category":"Professional",
            "subcategory":"Management & Consulting",
            "type":"Services"
        }
    ],
    "sg:phone":"+1 763 428 8382",
    "sg:postcode":"55374",
    "sg:province":"MN",
    "sg:tags":[
        "business"
    ],
    "wof:name":"3ml Consulting",
    "wof:placetype":"venue"
},
  "geometry": {"coordinates":[-93.56102,45.178957],"type":"Point"}
}