{
  "type": "Feature",
  "properties": {
    "iso:country":"US",
    "sg:address":"2922 Bryant Ave S",
    "sg:city":"Minneapolis",
    "sg:classifiers":[
        {
            "category":"Personal",
            "subcategory":"Beauty Salon",
            "type":"Services"
        }
    ],
    "sg:phone":"+1 612 824 7368",
    "sg:postcode":"55408",
    "sg:province":"MN",
    "sg:tags":[
        "nail"
    ],
    "sg:website":"salonpremiere.com",
    "wof:name":"Salon Premiere",
    "wof:placetype":"venue"
},
  "geometry": {"coordinates":[-93.29065,44.94924],"type":"Point"}
}