{
  "type": "Feature",
  "properties": {
    "iso:country":"US",
    "sg:address":"17132 Co Rd 24",
    "sg:city":"Brainerd",
    "sg:classifiers":[
        {
            "category":"Building & Trades",
            "subcategory":"Landscaping Services",
            "type":"Services"
        }
    ],
    "sg:phone":"+1 218 829 8101",
    "sg:postcode":"56401",
    "sg:province":"MN",
    "sg:tags":[
        "landscape",
        "contractor"
    ],
    "wof:name":"Erickson's Landscape & Nursery",
    "wof:placetype":"venue"
},
  "geometry": {"coordinates":[-94.032678,46.325323],"type":"Point"}
}