{
  "type": "Feature",
  "properties": {
    "addr:full":"24742 Co Rd 1 Zimmerman MN 55398",
    "addr:housenumber":"24742;1",
    "addr:postcode":"55398",
    "addr:street":"Co Rd",
    "iso:country":"US",
    "sg:address":"24742 Co Rd 1",
    "sg:city":"Zimmerman",
    "sg:classifiers":[
        {
            "category":"Autos & Motor Vehicles",
            "subcategory":"Auto Supplies",
            "type":"Retail Goods"
        }
    ],
    "sg:phone":"+1 763 241 9844",
    "sg:postcode":"55398",
    "sg:province":"MN",
    "wof:name":"Ron Jones Racing",
    "wof:placetype":"venue"
},
  "geometry": {"coordinates":[-93.63247,45.41842],"type":"Point"}
}