{
  "type": "Feature",
  "properties": {
    "iso:country":"US",
    "sg:address":"45967 State Hwy 56",
    "sg:city":"Kenyon",
    "sg:classifiers":[
        {
            "category":"Real Estate",
            "subcategory":"Surveying",
            "type":"Services"
        }
    ],
    "sg:phone":"+1 507 789 5366",
    "sg:postcode":"55946",
    "sg:province":"MN",
    "wof:name":"Surveying Rapp Land",
    "wof:placetype":"venue"
},
  "geometry": {"coordinates":[-92.979771,44.28417],"type":"Point"}
}