{
  "type": "Feature",
  "properties": {
    "addr:full":"1631 E 79th St Minneapolis MN 55425",
    "addr:housenumber":"1631",
    "addr:postcode":"55425",
    "addr:street":"E 79Th St",
    "iso:country":"US",
    "sg:address":"1631 E 79th St",
    "sg:city":"Minneapolis",
    "sg:classifiers":[
        {
            "category":"Local Transit",
            "type":"Transportation"
        }
    ],
    "sg:phone":"+1 952 854 5007",
    "sg:postcode":"55425",
    "sg:province":"MN",
    "sg:tags":[
        "ambulance"
    ],
    "wof:name":"Tran By Health Ride",
    "wof:placetype":"venue"
},
  "geometry": {"coordinates":[-93.24914099999999,44.859844],"type":"Point"}
}