{
  "type": "Feature",
  "properties": {
    "addr:full":"11564 Nickel Ave Brownton MN 55312",
    "addr:housenumber":"11564",
    "addr:postcode":"55312",
    "addr:street":"Nickel Ave",
    "iso:country":"US",
    "sg:address":"11564 Nickel Ave",
    "sg:city":"Brownton",
    "sg:classifiers":[
        {
            "category":"Building & Trades",
            "subcategory":"Construction",
            "type":"Services"
        }
    ],
    "sg:phone":"+1 320 864 6618",
    "sg:postcode":"55312",
    "sg:province":"MN",
    "sg:tags":[
        "house"
    ],
    "wof:name":"M&M Construction",
    "wof:placetype":"venue"
},
  "geometry": {"coordinates":[-94.30500499999999,44.776301],"type":"Point"}
}