{
  "type": "Feature",
  "properties": {
    "iso:country":"US",
    "sg:address":"2517 14th St S",
    "sg:city":"Saint Cloud",
    "sg:classifiers":[
        {
            "category":"Retail",
            "subcategory":"Repair Shop",
            "type":"Services"
        }
    ],
    "sg:phone":"+1 320 251 2210",
    "sg:postcode":"56301",
    "sg:province":"MN",
    "wof:name":"Precision Piano",
    "wof:placetype":"venue"
},
  "geometry": {"coordinates":[-94.191463,45.545058],"type":"Point"}
}