{
  "type": "Feature",
  "properties": {
    "iso:country":"US",
    "sg:address":"372 140th Ave",
    "sg:city":"Steen",
    "sg:classifiers":[
        {
            "category":"Farming",
            "subcategory":"Livestock Farm",
            "type":"Manufacturing & Wholesale Goods"
        }
    ],
    "sg:phone":"+1 507 283 2226",
    "sg:postcode":"56141",
    "sg:province":"MN",
    "sg:tags":[
        "corn",
        "beef",
        "feedlot",
        "cattle"
    ],
    "wof:name":"Larry Bosch",
    "wof:placetype":"venue"
},
  "geometry": {"coordinates":[-95.78392599999999,43.906267],"type":"Point"}
}