{
  "type": "Feature",
  "properties": {
    "iso:country":"US",
    "sg:address":"4801 American Blvd W",
    "sg:city":"Minneapolis",
    "sg:classifiers":[
        {
            "category":"Autos & Motor Vehicles",
            "subcategory":"Automobile Sales",
            "type":"Retail Goods"
        },
        {
            "category":"Autos & Motor Vehicles",
            "subcategory":"Auto Supplies",
            "type":"Retail Goods"
        },
        {
            "category":"Retail",
            "subcategory":"Auto Repair",
            "type":"Services"
        }
    ],
    "sg:phone":"+1 952 567 2100",
    "sg:postcode":"55437",
    "sg:province":"MN",
    "sg:tags":[
        "used",
        "leasing",
        "car",
        "accessory",
        "part",
        "truck",
        "new"
    ],
    "sg:website":"http://www.feldmannnissan.com/",
    "wof:name":"Feldmann Imports",
    "wof:placetype":"venue"
},
  "geometry": {"coordinates":[-93.340508,44.85788],"type":"Point"}
}