{
  "type": "Feature",
  "properties": {
    "iso:country":"US",
    "sg:address":"1023 Atlantic Ave",
    "sg:city":"Thief River Fls",
    "sg:classifiers":[
        {
            "category":"Wholesale",
            "subcategory":"Electrical",
            "type":"Manufacturing & Wholesale Goods"
        },
        {
            "category":"Shopping",
            "subcategory":"Computers & Home Electronics",
            "type":"Retail Goods"
        }
    ],
    "sg:phone":"+1 218 681 1856",
    "sg:postcode":"56701",
    "sg:province":"MN",
    "sg:tags":[
        "communication",
        "radio",
        "system",
        "repair"
    ],
    "wof:name":"D & J Radio Sales & Service",
    "wof:placetype":"venue"
},
  "geometry": {"coordinates":[-96.17688200000001,48.126947],"type":"Point"}
}