{
  "type": "Feature",
  "properties": {
    "addr:full":"2101 Gorton Ave NW Willmar MN 56201",
    "addr:housenumber":"2101",
    "addr:postcode":"56201",
    "addr:street":"Gorton Ave Nw",
    "iso:country":"US",
    "sg:address":"2101 Gorton Ave NW",
    "sg:city":"Willmar",
    "sg:classifiers":[
        {
            "category":"Retail",
            "subcategory":"Laundry & Dry Cleaning",
            "type":"Services"
        },
        {
            "category":"Retail",
            "subcategory":"Repair Shop",
            "type":"Services"
        },
        {
            "category":"Building & Trades",
            "subcategory":"Construction",
            "type":"Services"
        },
        {
            "category":"Building & Trades",
            "subcategory":"Cleaning & Sanitation",
            "type":"Services"
        }
    ],
    "sg:phone":"+1 320 235 2151",
    "sg:postcode":"56201",
    "sg:province":"MN",
    "sg:tags":[
        "cleaner",
        "specialty",
        "duct",
        "house",
        "heating",
        "system",
        "air conditioning",
        "contractor",
        "freezers-repair",
        "refrigerator"
    ],
    "wof:name":"Chappell Central Inc",
    "wof:placetype":"venue"
},
  "geometry": {"coordinates":[-95.06955000000001,45.12244],"type":"Point"}
}