{
  "type": "Feature",
  "properties": {
    "iso:country":"US",
    "sg:address":"2401 W Broadway Ave",
    "sg:city":"Minneapolis",
    "sg:classifiers":[
        {
            "category":"Autos & Motor Vehicles",
            "subcategory":"Auto Supplies",
            "type":"Retail Goods"
        }
    ],
    "sg:phone":"+1 612 588 7630",
    "sg:postcode":"55411",
    "sg:province":"MN",
    "sg:tags":[
        "tire"
    ],
    "wof:name":"Rusty's Tire",
    "wof:placetype":"venue"
},
  "geometry": {"coordinates":[-93.311206,45.005606],"type":"Point"}
}