{
  "type": "Feature",
  "properties": {
    "addr:full":"16278 Florida Way W Rosemount MN 55068",
    "addr:postcode":"16278;55068",
    "addr:street":"Florida Way W",
    "iso:country":"US",
    "sg:address":"16278 Florida Way W",
    "sg:city":"Rosemount",
    "sg:classifiers":[
        {
            "category":"Building & Trades",
            "subcategory":"Construction",
            "type":"Services"
        }
    ],
    "sg:phone":"+1 952 882 9805",
    "sg:postcode":"55068",
    "sg:province":"MN",
    "sg:tags":[
        "general",
        "contractor"
    ],
    "wof:name":"Centennial Construction Co",
    "wof:placetype":"venue"
},
  "geometry": {"coordinates":[-93.20079800000001,44.713621],"type":"Point"}
}