{
  "type": "Feature",
  "properties": {
    "iso:country":"US",
    "sg:address":"10756 France Ave S",
    "sg:city":"Minneapolis",
    "sg:classifiers":[
        {
            "category":"Recreation",
            "type":"Entertainment"
        }
    ],
    "sg:phone":"+1 612 875 4027",
    "sg:postcode":"55431",
    "sg:province":"MN",
    "sg:tags":[
        "martial",
        "arts",
        "instruction"
    ],
    "wof:name":"True Tae KWON Do",
    "wof:placetype":"venue"
},
  "geometry": {"coordinates":[-93.329615,44.809617],"type":"Point"}
}