{
  "type": "Feature",
  "properties": {
    "iso:country":"US",
    "sg:address":"32317 440th St",
    "sg:city":"Fosston",
    "sg:classifiers":[
        {
            "category":"Professional",
            "type":"Services"
        }
    ],
    "sg:phone":"+1 218 435 2117",
    "sg:postcode":"56587",
    "sg:province":"MN",
    "sg:tags":[
        "establishment"
    ],
    "wof:name":"L & K Enterprise Inc",
    "wof:placetype":"venue"
},
  "geometry": {"coordinates":[-95.818156,46.600461],"type":"Point"}
}