{
  "type": "Feature",
  "properties": {
    "iso:country":"US",
    "sg:address":"10890 Butternut St NW",
    "sg:city":"Minneapolis",
    "sg:classifiers":[
        {
            "category":"Retail",
            "subcategory":"Repair Shop",
            "type":"Services"
        }
    ],
    "sg:phone":"+1 763 862 1049",
    "sg:postcode":"55448",
    "sg:province":"MN",
    "wof:name":"Good Old Fashioned Cleaning",
    "wof:placetype":"venue"
},
  "geometry": {"coordinates":[-93.269795,45.168155],"type":"Point"}
}