{
  "type": "Feature",
  "properties": {
    "addr:full":"3800 Meadow Ln Excelsior MN 55331",
    "addr:housenumber":"3800",
    "addr:postcode":"55331",
    "addr:street":"Meadow Ln",
    "iso:country":"US",
    "sg:address":"3800 Meadow Ln",
    "sg:city":"Excelsior",
    "sg:classifiers":[
        {
            "category":"Professional",
            "subcategory":"Management & Consulting",
            "type":"Services"
        }
    ],
    "sg:phone":"+1 952 470 2113",
    "sg:postcode":"55331",
    "sg:province":"MN",
    "sg:tags":[
        "marketing",
        "program"
    ],
    "wof:name":"Dunhill Marketing",
    "wof:placetype":"venue"
},
  "geometry": {"coordinates":[-93.617124,44.889773],"type":"Point"}
}