{
  "type": "Feature",
  "properties": {
    "addr:full":"1539 Grand Ave St Paul MN 55105",
    "addr:housenumber":"1539",
    "addr:postcode":"55105",
    "addr:street":"Grand Ave",
    "iso:country":"US",
    "sg:address":"1539 Grand Ave",
    "sg:city":"St Paul",
    "sg:classifiers":[
        {
            "category":"Wholesale",
            "subcategory":"Durable Goods & Equipment",
            "type":"Manufacturing & Wholesale Goods"
        }
    ],
    "sg:phone":"+1 651 698 0200",
    "sg:postcode":"55105",
    "sg:province":"MN",
    "sg:tags":[
        "importer"
    ],
    "wof:name":"Nativa Yerba Mate Inc",
    "wof:placetype":"venue"
},
  "geometry": {"coordinates":[-93.166439,44.940137],"type":"Point"}
}