{
  "type": "Feature",
  "properties": {
    "iso:country":"US",
    "sg:address":"14391 160th St",
    "sg:city":"Villard",
    "sg:classifiers":[
        {
            "category":"Farming",
            "subcategory":"Dairy Farm",
            "type":"Manufacturing & Wholesale Goods"
        }
    ],
    "sg:phone":"+1 320 554 6131",
    "sg:postcode":"56385",
    "sg:province":"MN",
    "wof:name":"Rajdl Duwayne",
    "wof:placetype":"venue"
},
  "geometry": {"coordinates":[-95.23126999999999,45.671793],"type":"Point"}
}