{
  "type": "Feature",
  "properties": {
    "iso:country":"US",
    "sg:address":"248 7th Ave S",
    "sg:city":"South Saint Paul",
    "sg:classifiers":[
        {
            "category":"Social Services",
            "subcategory":"Child Care",
            "type":"Services"
        }
    ],
    "sg:phone":"+1 651 455 5010",
    "sg:postcode":"55075",
    "sg:province":"MN",
    "sg:tags":[
        "daycare",
        "provider"
    ],
    "wof:name":"Karla M Quinnell",
    "wof:placetype":"venue"
},
  "geometry": {"coordinates":[-93.04244799999999,44.887958],"type":"Point"}
}