{
  "type": "Feature",
  "properties": {
    "iso:country":"US",
    "sg:address":"2422 Ridgeway Ave NW",
    "sg:city":"Bemidji",
    "sg:classifiers":[
        {
            "category":"Travel",
            "subcategory":"Hotels & Motels",
            "type":"Entertainment"
        },
        {
            "category":"Retail",
            "subcategory":"Event Space",
            "type":"Services"
        }
    ],
    "sg:phone":"+1 800 345 8082",
    "sg:postcode":"56601",
    "sg:province":"MN",
    "sg:tags":[
        "facility",
        "banquet",
        "reception",
        "lodging",
        "corporate",
        "hall"
    ],
    "sg:website":"http://ad.doubleclick.net/clk;222816988;46581822;v?http://www.hiexpress.com/redirect?path=hd&brandCode=ex&hotelCode=bjiex&_PMID=99601036&cm_mmc=mdpr-_-yellowpages-_-ex-_-bjiex",
    "wof:name":"Holiday Inn Express Bemidji",
    "wof:placetype":"venue"
},
  "geometry": {"coordinates":[-94.89600799999999,47.491765],"type":"Point"}
}