{
  "type": "Feature",
  "properties": {
    "iso:country":"US",
    "sg:address":"615 1st Ave NE Suite 320",
    "sg:city":"Minneapolis",
    "sg:classifiers":[
        {
            "category":"Professional",
            "subcategory":"Art Services",
            "type":"Services"
        },
        {
            "category":"Communications",
            "type":"Services"
        },
        {
            "category":"Communications",
            "subcategory":"Television Station",
            "type":"Services"
        }
    ],
    "sg:phone":"+1 612 331 3586",
    "sg:postcode":"55413",
    "sg:province":"MN",
    "sg:tags":[
        "web",
        "graphic",
        "design"
    ],
    "sg:website":"linnihanfoy.com",
    "wof:name":"Linnihan Foy Advertising",
    "wof:placetype":"venue"
},
  "geometry": {"coordinates":[-93.25245200000001,44.991241],"type":"Point"}
}