{
  "type": "Feature",
  "properties": {
    "addr:full":"11 Mogren Hl Kenyon MN 55946",
    "addr:housenumber":"11",
    "addr:postcode":"55946",
    "addr:street":"Mogren Hl Kenyon",
    "iso:country":"US",
    "sg:address":"11 Mogren Hl",
    "sg:city":"Kenyon",
    "sg:classifiers":[
        {
            "category":"Wholesale",
            "subcategory":"Construction Materials",
            "type":"Manufacturing & Wholesale Goods"
        }
    ],
    "sg:phone":"+1 507 789 5011",
    "sg:postcode":"55946",
    "sg:province":"MN",
    "sg:tags":[
        "equipment",
        "masonry",
        "supply"
    ],
    "wof:name":"Kern Consulting & Management Inc",
    "wof:placetype":"venue"
},
  "geometry": {"coordinates":[-92.984921,44.275584],"type":"Point"}
}