{
  "type": "Feature",
  "properties": {
    "iso:country":"US",
    "sg:address":"14387 290th Ave",
    "sg:city":"Lowry",
    "sg:phone":"+1 320 283 5345",
    "sg:postcode":"56349",
    "sg:province":"MN",
    "sg:tags":[
        "farm",
        "corn"
    ],
    "wof:name":"Femrite Gurvin",
    "wof:placetype":"venue"
},
  "geometry": {"coordinates":[-95.53066200000001,45.689305],"type":"Point"}
}