{
  "type": "Feature",
  "properties": {
    "addr:full":"3230 Gorham Ave Ste 1 Minneapolis MN 55426",
    "addr:housenumber":"3230",
    "addr:postcode":"55426",
    "addr:street":"Gorham Ave Ste 1",
    "iso:country":"US",
    "sg:address":"3230 Gorham Ave Ste 1",
    "sg:city":"Minneapolis",
    "sg:classifiers":[
        {
            "category":"Government",
            "subcategory":"Fire Station",
            "type":"Public Place"
        }
    ],
    "sg:phone":"+1 952 848 0984",
    "sg:postcode":"55426",
    "sg:province":"MN",
    "sg:tags":[
        "relief",
        "recovery",
        "disaster"
    ],
    "wof:name":"Great Northern Resources Inc",
    "wof:placetype":"venue"
},
  "geometry": {"coordinates":[-93.370328,44.944416],"type":"Point"}
}