{
  "type": "Feature",
  "properties": {
    "iso:country":"US",
    "sg:address":"1450 81st St",
    "sg:city":"Victoria",
    "sg:classifiers":[
        {
            "category":"Building & Trades",
            "subcategory":"Construction",
            "type":"Services"
        }
    ],
    "sg:phone":"+1 952 443 2529",
    "sg:postcode":"55386",
    "sg:province":"MN",
    "sg:tags":[
        "house"
    ],
    "wof:name":"Anthony L Schrempp",
    "wof:placetype":"venue"
},
  "geometry": {"coordinates":[-93.657624,44.857695],"type":"Point"}
}