{
  "type": "Feature",
  "properties": {
    "addr:full":"10301 Bren Rd W Hopkins MN 55343",
    "addr:housenumber":"10301",
    "addr:postcode":"55343",
    "addr:street":"Bren Rd W",
    "iso:country":"US",
    "sg:address":"10301 Bren Rd W",
    "sg:city":"Hopkins",
    "sg:classifiers":[
        {
            "category":"Wholesale",
            "subcategory":"Stationery",
            "type":"Manufacturing & Wholesale Goods"
        }
    ],
    "sg:phone":"+1 952 933 0990",
    "sg:postcode":"55343",
    "sg:province":"MN",
    "sg:tags":[
        "supply"
    ],
    "wof:name":"Asset Management Group Inc",
    "wof:placetype":"venue"
},
  "geometry": {"coordinates":[-93.40849300000001,44.899529],"type":"Point"}
}