{
  "type": "Feature",
  "properties": {
    "addr:full":"222 W Wabasha St Winona MN 55987",
    "addr:housenumber":"222",
    "addr:postcode":"55987",
    "addr:street":"W Wabasha St",
    "iso:country":"US",
    "sg:address":"222 W Wabasha St",
    "sg:city":"Winona",
    "sg:classifiers":[
        {
            "category":"Building & Trades",
            "subcategory":"Construction",
            "type":"Services"
        }
    ],
    "sg:phone":"+1 507 452 0803",
    "sg:postcode":"55987",
    "sg:province":"MN",
    "sg:tags":[
        "hanging",
        "contractor"
    ],
    "wof:name":"Roberts Wallpaper & Paint",
    "wof:placetype":"venue"
},
  "geometry": {"coordinates":[-91.64336900000001,44.049846],"type":"Point"}
}