{
  "type": "Feature",
  "properties": {
    "iso:country":"US",
    "sg:address":"3982 Kindred Way",
    "sg:city":"Lake Elmo",
    "sg:classifiers":[
        {
            "category":"Banks & Credit Unions",
            "subcategory":"Bank",
            "type":"Services"
        }
    ],
    "sg:phone":"+1 651 773 5120",
    "sg:postcode":"55042",
    "sg:province":"MN",
    "sg:tags":[
        "mortgage"
    ],
    "wof:name":"Mortgage Masters MN",
    "wof:placetype":"venue"
},
  "geometry": {"coordinates":[-92.896016,45.01153],"type":"Point"}
}