{
  "type": "Feature",
  "properties": {
    "addr:full":"9115 Victoria Dr Eden Prairie MN 55347",
    "addr:housenumber":"9115",
    "addr:postcode":"55347",
    "addr:street":"Victoria Dr",
    "iso:country":"US",
    "sg:address":"9115 Victoria Dr",
    "sg:city":"Eden Prairie",
    "sg:classifiers":[
        {
            "category":"Professional",
            "subcategory":"Management & Consulting",
            "type":"Services"
        }
    ],
    "sg:phone":"+1 952 949 6670",
    "sg:postcode":"55347",
    "sg:province":"MN",
    "wof:name":"Clinton Consulting Inc",
    "wof:placetype":"venue"
},
  "geometry": {"coordinates":[-93.464302,44.840664],"type":"Point"}
}