{
  "type": "Feature",
  "properties": {
    "addr:full":"9823 Hwy 115 Randall MN 56475",
    "addr:housenumber":"9823",
    "addr:postcode":"56475",
    "addr:street":"Hwy 115",
    "iso:country":"US",
    "sg:address":"9823 Hwy 115",
    "sg:city":"Randall",
    "sg:classifiers":[
        {
            "category":"Professional",
            "type":"Services"
        }
    ],
    "sg:phone":"+1 320 749 2629",
    "sg:postcode":"56475",
    "sg:province":"MN",
    "wof:name":"Little Elk Poultry Inc",
    "wof:placetype":"venue"
},
  "geometry": {"coordinates":[-94.456324,46.085592],"type":"Point"}
}