{
  "type": "Feature",
  "properties": {
    "iso:country":"US",
    "sg:address":"1451 Pulaski Rd",
    "sg:city":"Buffalo",
    "sg:classifiers":[
        {
            "category":"Building & Trades",
            "subcategory":"Electrical",
            "type":"Services"
        }
    ],
    "sg:phone":"+1 763 682 6034",
    "sg:postcode":"55313",
    "sg:province":"MN",
    "sg:tags":[
        "electrician"
    ],
    "wof:name":"Mad Dog Security Inc",
    "wof:placetype":"venue"
},
  "geometry": {"coordinates":[-93.85614099999999,45.188333],"type":"Point"}
}