{
  "type": "Feature",
  "properties": {
    "addr:full":"702 3rd St S Ellendale MN 56026",
    "addr:housenumber":"702",
    "addr:postcode":"56026",
    "addr:street":"3Rd St S",
    "iso:country":"US",
    "sg:address":"702 3rd St S",
    "sg:city":"Ellendale",
    "sg:classifiers":[
        {
            "category":"Organizations",
            "subcategory":"Religious Organization",
            "type":"Services"
        }
    ],
    "sg:phone":"+1 507 684 3421",
    "sg:postcode":"56026",
    "sg:province":"MN",
    "sg:tags":[
        "church"
    ],
    "wof:name":"Assembly Of God Church",
    "wof:placetype":"venue"
},
  "geometry": {"coordinates":[-93.302048,43.870892],"type":"Point"}
}