{
  "type": "Feature",
  "properties": {
    "iso:country":"US",
    "sg:address":"1769 Lexington Ave N",
    "sg:city":"Saint Paul",
    "sg:classifiers":[
        {
            "category":"Shopping",
            "type":"Retail Goods"
        }
    ],
    "sg:phone":"+1 612 801 2222",
    "sg:postcode":"55113",
    "sg:province":"MN",
    "sg:tags":[
        "internet"
    ],
    "wof:name":"Pdi Financial",
    "wof:placetype":"venue"
},
  "geometry": {"coordinates":[-93.146511,44.994214],"type":"Point"}
}