{
  "type": "Feature",
  "properties": {
    "addr:full":"10723 Co Rd 11 NE Elgin MN 55932",
    "addr:housenumber":"10723;11",
    "addr:postcode":"55932",
    "addr:street":"Co Rd;Ne Elgin",
    "iso:country":"US",
    "sg:address":"10723 Co Rd 11 NE",
    "sg:city":"Elgin",
    "sg:phone":"+1 507 876 2256",
    "sg:postcode":"55932",
    "sg:province":"MN",
    "sg:tags":[
        "farm",
        "corn",
        "soybean"
    ],
    "wof:name":"Andy Hart",
    "wof:placetype":"venue"
},
  "geometry": {"coordinates":[-92.359109,44.149733],"type":"Point"}
}