{
  "type": "Feature",
  "properties": {
    "iso:country":"US",
    "sg:address":"46763 280th St NW",
    "sg:city":"Alvarado",
    "sg:phone":"+1 218 695 3298",
    "sg:postcode":"56710",
    "sg:province":"MN",
    "sg:tags":[
        "farm",
        "grain",
        "wheat",
        "cash",
        "beet"
    ],
    "wof:name":"Marvin Swanson",
    "wof:placetype":"venue"
},
  "geometry": {"coordinates":[-97.05906299999999,48.282142],"type":"Point"}
}