{
  "type": "Feature",
  "properties": {
    "addr:full":"4945 S Savanna Rd Floodwood MN 55736",
    "addr:housenumber":"4945",
    "addr:postcode":"55736",
    "addr:street":"S Savanna Rd",
    "iso:country":"US",
    "sg:address":"4945 S Savanna Rd",
    "sg:city":"Floodwood",
    "sg:classifiers":[
        {
            "category":"Manufacturing",
            "subcategory":"Lumber",
            "type":"Manufacturing & Wholesale Goods"
        }
    ],
    "sg:phone":"+1 218 476 2274",
    "sg:postcode":"55736",
    "sg:province":"MN",
    "sg:tags":[
        "logging"
    ],
    "wof:name":"Sandstrom Logging",
    "wof:placetype":"venue"
},
  "geometry": {"coordinates":[-92.95360100000001,46.870574],"type":"Point"}
}