{
  "type": "Feature",
  "properties": {
    "iso:country":"US",
    "sg:address":"6408 Kurtz Ln",
    "sg:city":"Eden Prairie",
    "sg:classifiers":[
        {
            "category":"Building & Trades",
            "subcategory":"Cleaning & Sanitation",
            "type":"Services"
        }
    ],
    "sg:phone":"+1 952 937 8777",
    "sg:postcode":"55346",
    "sg:province":"MN",
    "sg:tags":[
        "janitor"
    ],
    "wof:name":"Sulco Cleaning Svc",
    "wof:placetype":"venue"
},
  "geometry": {"coordinates":[-93.47191100000001,44.884567],"type":"Point"}
}