{
  "type": "Feature",
  "properties": {
    "addr:full":"7701 147th St W St Paul MN 55124",
    "addr:housenumber":"7701",
    "addr:postcode":"55124",
    "addr:street":"147Th St W",
    "iso:country":"US",
    "sg:address":"7701 147th St W",
    "sg:city":"St Paul",
    "sg:classifiers":[
        {
            "category":"Personal",
            "subcategory":"Beauty Salon",
            "type":"Services"
        }
    ],
    "sg:phone":"+1 952 432 7737",
    "sg:postcode":"55124",
    "sg:province":"MN",
    "sg:tags":[
        "shop"
    ],
    "wof:name":"Shear Thing",
    "wof:placetype":"venue"
},
  "geometry": {"coordinates":[-93.2223,44.735245],"type":"Point"}
}