{
  "type": "Feature",
  "properties": {
    "addr:full":"10436 Waltz Rd Ray MN 56669",
    "addr:housenumber":"10436",
    "addr:postcode":"56669",
    "addr:street":"Waltz Rd",
    "iso:country":"US",
    "sg:address":"10436 Waltz Rd",
    "sg:city":"Ray",
    "sg:classifiers":[
        {
            "category":"Travel",
            "subcategory":"Hotels & Motels",
            "type":"Entertainment"
        }
    ],
    "sg:phone":"+1 218 875 2131",
    "sg:postcode":"56669",
    "sg:province":"MN",
    "sg:tags":[
        "resort"
    ],
    "wof:name":"Voyageur Park Lodge",
    "wof:placetype":"venue"
},
  "geometry": {"coordinates":[-93.06471999999999,48.477679],"type":"Point"}
}