{
  "type": "Feature",
  "properties": {
    "addr:full":"743 N 4th St La Crescent MN 55947",
    "addr:housenumber":"743",
    "addr:postcode":"55947",
    "addr:street":"N 4Th St;Crescent",
    "iso:country":"US",
    "sg:address":"743 N 4th St",
    "sg:city":"La Crescent",
    "sg:classifiers":[
        {
            "category":"Real Estate",
            "subcategory":"Real Estate Agent",
            "type":"Services"
        }
    ],
    "sg:phone":"+1 507 895 8848",
    "sg:postcode":"55947",
    "sg:province":"MN",
    "wof:name":"Apple Bee Letters Inc",
    "wof:placetype":"venue"
},
  "geometry": {"coordinates":[-91.31333600000001,43.838511],"type":"Point"}
}