{
  "type": "Feature",
  "properties": {
    "iso:country":"US",
    "sg:address":"775 70th St SW",
    "sg:city":"Danvers",
    "sg:classifiers":[
        {
            "category":"Farming",
            "subcategory":"Livestock Farm",
            "type":"Manufacturing & Wholesale Goods"
        }
    ],
    "sg:phone":"+1 320 567 2176",
    "sg:postcode":"56231",
    "sg:province":"MN",
    "sg:tags":[
        "feeding"
    ],
    "wof:name":"Rodney Lye",
    "wof:placetype":"venue"
},
  "geometry": {"coordinates":[-95.734669,45.22397],"type":"Point"}
}