{
  "type": "Feature",
  "properties": {
    "addr:full":"16233 Co Rd 30 SW Cokato MN 55321",
    "addr:housenumber":"16233",
    "addr:postcode":"55321",
    "addr:street":"Co Rd 30 Sw",
    "iso:country":"US",
    "sg:address":"16233 Co Rd 30 SW",
    "sg:city":"Cokato",
    "sg:classifiers":[
        {
            "category":"Organizations",
            "subcategory":"Religious Organization",
            "type":"Services"
        }
    ],
    "sg:phone":"+1 320 286 2024",
    "sg:postcode":"55321",
    "sg:province":"MN",
    "wof:name":"Cokato Laestadian Lutheran",
    "wof:placetype":"venue"
},
  "geometry": {"coordinates":[-94.21924,45.036467],"type":"Point"}
}