{
  "type": "Feature",
  "properties": {
    "addr:full":"200 Western Ave NW Faribault MN 55021",
    "addr:housenumber":"200",
    "addr:postcode":"55021",
    "addr:street":"Western Ave Nw",
    "iso:country":"US",
    "sg:address":"200 Western Ave NW",
    "sg:city":"Faribault",
    "sg:classifiers":[
        {
            "category":"Shopping",
            "subcategory":"Discount & Variety Stores",
            "type":"Retail Goods"
        }
    ],
    "sg:phone":"+1 507 334 1510",
    "sg:postcode":"55021",
    "sg:province":"MN",
    "wof:name":"Big Lots",
    "wof:placetype":"venue"
},
  "geometry": {"coordinates":[-93.30297299999999,44.292096],"type":"Point"}
}