{
  "type": "Feature",
  "properties": {
    "addr:full":"104 6th St Brownsville MN 55919",
    "addr:housenumber":"104",
    "addr:postcode":"55919",
    "addr:street":"6Th St",
    "iso:country":"US",
    "sg:address":"104 6th St",
    "sg:city":"Brownsville",
    "sg:classifiers":[
        {
            "category":"Government",
            "subcategory":"Office",
            "type":"Public Place"
        }
    ],
    "sg:phone":"+1 507 482 6732",
    "sg:postcode":"55919",
    "sg:province":"MN",
    "sg:tags":[
        "city"
    ],
    "wof:name":"Brownsville City Clerk",
    "wof:placetype":"venue"
},
  "geometry": {"coordinates":[-91.27865799999999,43.694453],"type":"Point"}
}