{
  "type": "Feature",
  "properties": {
    "addr:full":"2825 Fairview Ave N Roseville MN 55113",
    "addr:housenumber":"2825",
    "addr:postcode":"55113",
    "addr:street":"Fairview Ave N",
    "iso:country":"US",
    "sg:address":"2825 Fairview Ave N",
    "sg:city":"Roseville",
    "sg:classifiers":[
        {
            "category":"Education",
            "subcategory":"School",
            "type":"Public Place"
        },
        {
            "category":"Social Services",
            "type":"Services"
        }
    ],
    "sg:phone":"+1 651 636 3343",
    "sg:postcode":"55113",
    "sg:province":"MN",
    "sg:tags":[
        "organization",
        "welfare",
        "day",
        "care",
        "child"
    ],
    "wof:name":"Northeast Contemporary Svc Inc",
    "wof:placetype":"venue"
},
  "geometry": {"coordinates":[-93.17734799999999,45.026407],"type":"Point"}
}