{
  "type": "Feature",
  "properties": {
    "iso:country":"US",
    "sg:address":"208 5th St N",
    "sg:city":"Breckenridge",
    "sg:classifiers":[
        {
            "category":"Shopping",
            "subcategory":"Shoes",
            "type":"Retail Goods"
        }
    ],
    "sg:phone":"+1 218 643 8616",
    "sg:postcode":"56520",
    "sg:province":"MN",
    "wof:name":"Country Cobbler",
    "wof:placetype":"venue"
},
  "geometry": {"coordinates":[-96.587875,46.26571],"type":"Point"}
}