{
  "type": "Feature",
  "properties": {
    "iso:country":"US",
    "sg:address":"761 Duluth St",
    "sg:city":"St Paul",
    "sg:classifiers":[
        {
            "category":"Professional",
            "type":"Services"
        }
    ],
    "sg:phone":"+1 651 776 1073",
    "sg:postcode":"55106",
    "sg:province":"MN",
    "sg:tags":[
        "establishment"
    ],
    "wof:name":"Mi Pueblito",
    "wof:placetype":"venue"
},
  "geometry": {"coordinates":[-93.050854,44.964586],"type":"Point"}
}