{
  "type": "Feature",
  "properties": {
    "iso:country":"US",
    "sg:address":"14523 140th St",
    "sg:city":"Walnut Grove",
    "sg:classifiers":[
        {
            "category":"Farming",
            "subcategory":"Livestock Farm",
            "type":"Manufacturing & Wholesale Goods"
        }
    ],
    "sg:phone":"+1 507 859 2330",
    "sg:postcode":"56180",
    "sg:province":"MN",
    "sg:tags":[
        "hog",
        "corn",
        "or",
        "feedlot"
    ],
    "wof:name":"George Landuyt",
    "wof:placetype":"venue"
},
  "geometry": {"coordinates":[-95.507929,44.2537],"type":"Point"}
}