{
  "type": "Feature",
  "properties": {
    "addr:full":"23814 Wheeler Lk Rd Detroit Lakes MN 56501",
    "addr:housenumber":"23814",
    "addr:postcode":"56501",
    "addr:street":"Wheeler Lk Rd",
    "iso:country":"US",
    "sg:address":"23814 Wheeler Lk Rd",
    "sg:city":"Detroit Lakes",
    "sg:classifiers":[
        {
            "category":"Retail",
            "subcategory":"Auto Repair",
            "type":"Services"
        }
    ],
    "sg:phone":"+1 218 847 1190",
    "sg:postcode":"56501",
    "sg:province":"MN",
    "sg:tags":[
        "body",
        "automobile",
        "painting"
    ],
    "wof:name":"D & K Auto Body",
    "wof:placetype":"venue"
},
  "geometry": {"coordinates":[-95.906042,46.876685],"type":"Point"}
}