{
  "type": "Feature",
  "properties": {
    "addr:full":"7636 160th St W Lakeville MN 55044",
    "addr:housenumber":"7636",
    "addr:postcode":"55044",
    "addr:street":"160Th St W",
    "iso:country":"US",
    "sg:address":"7636 160th St W",
    "sg:city":"Lakeville",
    "sg:classifiers":[
        {
            "category":"Shopping",
            "subcategory":"Department Store",
            "type":"Retail Goods"
        },
        {
            "category":"Personal",
            "subcategory":"Barber",
            "type":"Services"
        }
    ],
    "sg:phone":"+1 952 432 3990",
    "sg:postcode":"55044",
    "sg:province":"MN",
    "sg:website":"www.tradesecret.com",
    "wof:name":"Trade Secret",
    "wof:placetype":"venue"
},
  "geometry": {"coordinates":[-93.220313,44.717213],"type":"Point"}
}