{
  "type": "Feature",
  "properties": {
    "iso:country":"US",
    "sg:address":"14551 Lake Dr NE",
    "sg:city":"Forest Lake",
    "sg:classifiers":[
        {
            "category":"Building & Trades",
            "subcategory":"Construction",
            "type":"Services"
        }
    ],
    "sg:phone":"+1 651 464 6802",
    "sg:postcode":"55025",
    "sg:province":"MN",
    "sg:tags":[
        "excavation",
        "excavating",
        "contractor"
    ],
    "wof:name":"North Pine Aggregate Inc",
    "wof:placetype":"venue"
},
  "geometry": {"coordinates":[-93.083786,45.233618],"type":"Point"}
}