{
  "type": "Feature",
  "properties": {
    "addr:full":"52250 127th St Amboy MN 56010",
    "addr:housenumber":"52250",
    "addr:postcode":"56010",
    "addr:street":"127Th St",
    "iso:country":"US",
    "sg:address":"52250 127th St",
    "sg:city":"Amboy",
    "sg:phone":"+1 507 674 3503",
    "sg:postcode":"56010",
    "sg:province":"MN",
    "sg:tags":[
        "farm",
        "corn",
        "soybean"
    ],
    "wof:name":"Keith Wendt",
    "wof:placetype":"venue"
},
  "geometry": {"coordinates":[-94.191197,43.920431],"type":"Point"}
}