{
  "type": "Feature",
  "properties": {
    "iso:country":"US",
    "sg:address":"219 N Garden",
    "sg:city":"Minneapolis",
    "sg:classifiers":[
        {
            "category":"Shopping",
            "subcategory":"Beauty & Cosmetics",
            "type":"Retail Goods"
        }
    ],
    "sg:phone":"+1 952 851 0790",
    "sg:postcode":"55425",
    "sg:province":"MN",
    "sg:tags":[
        "perfume"
    ],
    "sg:website":"http://www.perfumania.com",
    "wof:name":"Perfumania",
    "wof:placetype":"venue"
},
  "geometry": {"coordinates":[-93.24091199999999,44.856034],"type":"Point"}
}