{
  "type": "Feature",
  "properties": {
    "iso:country":"US",
    "sg:address":"526 Elm St S",
    "sg:city":"Sauk Centre",
    "sg:classifiers":[
        {
            "category":"Restaurant",
            "type":"Food & Drink"
        }
    ],
    "sg:phone":"+1 320 352 6853",
    "sg:postcode":"56378",
    "sg:province":"MN",
    "sg:tags":[
        "eating"
    ],
    "wof:name":"Dong Ding Cafe",
    "wof:placetype":"venue"
},
  "geometry": {"coordinates":[-94.955123,45.734346],"type":"Point"}
}