{
  "type": "Feature",
  "properties": {
    "addr:full":"21640 150th Ave NE Thief River Falls MN 56701",
    "addr:housenumber":"21640",
    "addr:postcode":"56701",
    "addr:street":"150Th Ave Ne",
    "iso:country":"US",
    "sg:address":"21640 150th Ave NE",
    "sg:city":"Thief River Falls",
    "sg:classifiers":[
        {
            "category":"Real Estate",
            "subcategory":"Real Estate Operator",
            "type":"Services"
        }
    ],
    "sg:phone":"+1 218 681 2997",
    "sg:postcode":"56701",
    "sg:province":"MN",
    "sg:tags":[
        "property",
        "lessor"
    ],
    "wof:name":"Arnold Boman",
    "wof:placetype":"venue"
},
  "geometry": {"coordinates":[-96.15102,48.188686],"type":"Point"}
}