{
  "type": "Feature",
  "properties": {
    "addr:full":"40712 Verdin St NW Braham MN 55006",
    "addr:postcode":"40712;55006",
    "addr:street":"Verdin St Nw",
    "iso:country":"US",
    "sg:address":"40712 Verdin St NW",
    "sg:city":"Braham",
    "sg:classifiers":[
        {
            "category":"Shopping",
            "subcategory":"Discount & Variety Stores",
            "type":"Retail Goods"
        },
        {
            "category":"Shopping",
            "subcategory":"Bicycles & Sporting Goods",
            "type":"Retail Goods"
        }
    ],
    "sg:phone":"+1 320 396 4918",
    "sg:postcode":"55006",
    "sg:province":"MN",
    "sg:tags":[
        "merchandise",
        "general"
    ],
    "wof:name":"Double U Tack & Trading Post",
    "wof:placetype":"venue"
},
  "geometry": {"coordinates":[-93.32756500000001,45.707767],"type":"Point"}
}