{
  "type": "Feature",
  "properties": {
    "iso:country":"US",
    "sg:address":"208 3rd Ave NW",
    "sg:city":"East Grand Forks",
    "sg:classifiers":[
        {
            "category":"Professional",
            "subcategory":"Lawyer & Legal Services",
            "type":"Services"
        }
    ],
    "sg:phone":"+1 218 773 7575",
    "sg:postcode":"56721",
    "sg:province":"MN",
    "sg:tags":[
        "attorney"
    ],
    "wof:name":"Raymond J German LTD",
    "wof:placetype":"venue"
},
  "geometry": {"coordinates":[-97.024449,47.928315],"type":"Point"}
}