{
  "type": "Feature",
  "properties": {
    "addr:full":"222 2nd Ave SE Perham MN 56573",
    "addr:housenumber":"222",
    "addr:postcode":"56573",
    "addr:street":"2Nd Ave Se",
    "iso:country":"US",
    "sg:address":"222 2nd Ave SE",
    "sg:city":"Perham",
    "sg:classifiers":[
        {
            "category":"Government",
            "subcategory":"Office",
            "type":"Public Place"
        }
    ],
    "sg:phone":"+1 218 346 2050",
    "sg:postcode":"56573",
    "sg:province":"MN",
    "sg:tags":[
        "federal"
    ],
    "wof:name":"Natural Resources Conservation",
    "wof:placetype":"venue"
},
  "geometry": {"coordinates":[-95.572839,46.592614],"type":"Point"}
}