{
  "type": "Feature",
  "properties": {
    "iso:country":"US",
    "sg:address":"5329 France Ave S",
    "sg:city":"Minneapolis",
    "sg:classifiers":[
        {
            "category":"Personal",
            "type":"Services"
        },
        {
            "category":"Professional",
            "subcategory":"Art Services",
            "type":"Services"
        },
        {
            "category":"Professional",
            "subcategory":"Printing & Photocopies",
            "type":"Services"
        }
    ],
    "sg:phone":"+1 612 927 5953",
    "sg:postcode":"55410",
    "sg:province":"MN",
    "sg:tags":[
        "photography",
        "videography",
        "photographers-commercial",
        "wedding"
    ],
    "wof:name":"Rummelhoff Tim Photography",
    "wof:placetype":"venue"
},
  "geometry": {"coordinates":[-93.329018,44.906538],"type":"Point"}
}