{
  "type": "Feature",
  "properties": {
    "addr:full":"27818 Kenwood Ave Redwood Falls MN 56283",
    "addr:housenumber":"27818",
    "addr:postcode":"56283",
    "addr:street":"Kenwood Ave",
    "iso:country":"US",
    "sg:address":"27818 Kenwood Ave",
    "sg:city":"Redwood Falls",
    "sg:classifiers":[
        {
            "category":"Farming",
            "subcategory":"Livestock Farm",
            "type":"Manufacturing & Wholesale Goods"
        }
    ],
    "sg:phone":"+1 507 644 3806",
    "sg:postcode":"56283",
    "sg:province":"MN",
    "sg:tags":[
        "hog",
        "or",
        "feedlot"
    ],
    "wof:name":"Chris Christensen",
    "wof:placetype":"venue"
},
  "geometry": {"coordinates":[-95.189393,44.453427],"type":"Point"}
}