{
  "type": "Feature",
  "properties": {
    "iso:country":"US",
    "sg:address":"10262 Hawthorne Rd NW",
    "sg:city":"Rice",
    "sg:classifiers":[
        {
            "category":"Building & Trades",
            "subcategory":"Construction",
            "type":"Services"
        }
    ],
    "sg:phone":"+1 320 393 4908",
    "sg:postcode":"56367",
    "sg:province":"MN",
    "sg:tags":[
        "house"
    ],
    "wof:name":"Solo Design Studio",
    "wof:placetype":"venue"
},
  "geometry": {"coordinates":[-94.18387199999999,45.717575],"type":"Point"}
}