{
  "type": "Feature",
  "properties": {
    "iso:country":"US",
    "sg:address":"403 W 7th Ave",
    "sg:city":"Ellsworth",
    "sg:classifiers":[
        {
            "category":"Farming",
            "subcategory":"Livestock Farm",
            "type":"Manufacturing & Wholesale Goods"
        }
    ],
    "sg:phone":"+1 507 967 2412",
    "sg:postcode":"56129",
    "sg:province":"MN",
    "sg:tags":[
        "beef",
        "feedlot",
        "cattle"
    ],
    "wof:name":"Glenn Meester",
    "wof:placetype":"venue"
},
  "geometry": {"coordinates":[-96.022099,43.514552],"type":"Point"}
}