{
  "type": "Feature",
  "properties": {
    "iso:country":"US",
    "sg:address":"6900 Wedgwood Rd",
    "sg:city":"Maple Grove",
    "sg:classifiers":[
        {
            "category":"Banks & Credit Unions",
            "subcategory":"Bank",
            "type":"Services"
        }
    ],
    "sg:phone":"+1 763 420 2188",
    "sg:postcode":"55311",
    "sg:province":"MN",
    "sg:tags":[
        "loan",
        "real estate"
    ],
    "wof:name":"Minnesota Mortgage Financial",
    "wof:placetype":"venue"
},
  "geometry": {"coordinates":[-93.449754,45.080093],"type":"Point"}
}