{
  "type": "Feature",
  "properties": {
    "iso:country":"US",
    "sg:address":"3464 Owasso St",
    "sg:city":"St Paul",
    "sg:classifiers":[
        {
            "category":"Manufacturing",
            "subcategory":"Printing",
            "type":"Manufacturing & Wholesale Goods"
        }
    ],
    "sg:phone":"+1 651 484 9533",
    "sg:postcode":"55126",
    "sg:province":"MN",
    "sg:tags":[
        "printer"
    ],
    "wof:name":"QSI Print & Promotions",
    "wof:placetype":"venue"
},
  "geometry": {"coordinates":[-93.12907800000001,45.043686],"type":"Point"}
}