{
  "type": "Feature",
  "properties": {
    "iso:country":"US",
    "sg:address":"541 W 98th St",
    "sg:city":"Minneapolis",
    "sg:classifiers":[
        {
            "category":"Arena",
            "subcategory":"Sports Club",
            "type":"Entertainment"
        }
    ],
    "sg:phone":"+1 952 820 9444",
    "sg:postcode":"55420",
    "sg:province":"MN",
    "wof:name":"Bloomngton Junior Soccer Clubs",
    "wof:placetype":"venue"
},
  "geometry": {"coordinates":[-93.28658799999999,44.826214],"type":"Point"}
}