{
  "type": "Feature",
  "properties": {
    "addr:full":"555 Nicollet Mall Minneapolis MN 55402",
    "addr:housenumber":"555",
    "addr:postcode":"55402",
    "addr:street":"Nicollet Mall",
    "iso:country":"US",
    "sg:address":"555 Nicollet Mall",
    "sg:city":"Minneapolis",
    "sg:classifiers":[
        {
            "category":"Restaurant",
            "type":"Food & Drink"
        }
    ],
    "sg:menulink":"http://www.allmenus.com/mn/minneapolis/193985-mcdonalds/menu/",
    "sg:postcode":"55402",
    "sg:province":"MN",
    "sg:tags":[
        "burger",
        "american"
    ],
    "wof:name":"McDonald's",
    "wof:placetype":"venue"
},
  "geometry": {"coordinates":[-93.27121200000001,44.978065],"type":"Point"}
}