{
  "type": "Feature",
  "properties": {
    "addr:full":"3553 Lexington Ave N St Paul MN 55126",
    "addr:housenumber":"3553",
    "addr:postcode":"55126",
    "addr:street":"Lexington Ave N",
    "iso:country":"US",
    "sg:address":"3553 Lexington Ave N",
    "sg:city":"St Paul",
    "sg:classifiers":[
        {
            "category":"Personal",
            "subcategory":"Beauty Salon",
            "type":"Services"
        }
    ],
    "sg:phone":"+1 651 481 0162",
    "sg:postcode":"55126",
    "sg:province":"MN",
    "sg:tags":[
        "shop"
    ],
    "wof:name":"Hair Expressions",
    "wof:placetype":"venue"
},
  "geometry": {"coordinates":[-93.14713,45.048039],"type":"Point"}
}