{
  "type": "Feature",
  "properties": {
    "iso:country":"US",
    "sg:address":"19494 Co Rd 45",
    "sg:city":"Clearwater",
    "sg:classifiers":[
        {
            "category":"Building & Trades",
            "subcategory":"Plumbing",
            "type":"Services"
        }
    ],
    "sg:phone":"+1 320 558 4542",
    "sg:postcode":"55320",
    "sg:province":"MN",
    "sg:tags":[
        "septic"
    ],
    "wof:name":"Storms Pumping Svc",
    "wof:placetype":"venue"
},
  "geometry": {"coordinates":[-94.131417,45.40331],"type":"Point"}
}