{
  "type": "Feature",
  "properties": {
    "addr:full":"8890 Excelsior Blvd Hopkins MN 55343",
    "addr:housenumber":"8890",
    "addr:postcode":"55343",
    "addr:street":"Excelsior Blvd",
    "iso:country":"US",
    "sg:address":"8890 Excelsior Blvd",
    "sg:city":"Hopkins",
    "sg:classifiers":[
        {
            "category":"Home & Garden",
            "subcategory":"Building Materials",
            "type":"Retail Goods"
        }
    ],
    "sg:phone":"+1 952 935 3345",
    "sg:postcode":"55343",
    "sg:province":"MN",
    "sg:tags":[
        "paint",
        "wallpaper"
    ],
    "wof:name":"Koss Paint Co Inc",
    "wof:placetype":"venue"
},
  "geometry": {"coordinates":[-93.391693,44.924831],"type":"Point"}
}