{
  "type": "Feature",
  "properties": {
    "addr:full":"6226 Bass Lake Rd Crystal MN 55429",
    "addr:housenumber":"6226",
    "addr:postcode":"55429",
    "addr:street":"Bass Lake Rd",
    "iso:country":"US",
    "sg:address":"6226 Bass Lake Rd",
    "sg:city":"Crystal",
    "sg:classifiers":[
        {
            "category":"Social Services",
            "subcategory":"Child Care",
            "type":"Services"
        }
    ],
    "sg:phone":"+1 763 533 0169",
    "sg:postcode":"55429",
    "sg:province":"MN",
    "sg:website":"www.littlefolksdaycare.com",
    "wof:name":"Little Folks Robbinsdale Inc",
    "wof:placetype":"venue"
},
  "geometry": {"coordinates":[-93.35993000000001,45.05472],"type":"Point"}
}