{
  "type": "Feature",
  "properties": {
    "addr:full":"2629 Clearwater Rd St Cloud MN 56301",
    "addr:housenumber":"2629",
    "addr:postcode":"56301",
    "addr:street":"Clearwater Rd",
    "iso:country":"US",
    "sg:address":"2629 Clearwater Rd",
    "sg:city":"St Cloud",
    "sg:classifiers":[
        {
            "category":"Wholesale",
            "subcategory":"Auto Parts",
            "type":"Manufacturing & Wholesale Goods"
        }
    ],
    "sg:phone":"+1 320 251 7252",
    "sg:postcode":"56301",
    "sg:province":"MN",
    "sg:tags":[
        "truck",
        "accessory"
    ],
    "sg:website":"www.northcentraltruck.com",
    "wof:name":"North Central Truck Equipment",
    "wof:placetype":"venue"
},
  "geometry": {"coordinates":[-94.16026100000001,45.52864],"type":"Point"}
}