{
  "type": "Feature",
  "properties": {
    "iso:country":"US",
    "sg:address":"571 3rd Ave",
    "sg:city":"Newport",
    "sg:classifiers":[
        {
            "category":"Social Services",
            "subcategory":"Child Care",
            "type":"Services"
        }
    ],
    "sg:phone":"+1 651 493 9516",
    "sg:postcode":"55055",
    "sg:province":"MN",
    "sg:tags":[
        "day"
    ],
    "wof:name":"Andrea Morse",
    "wof:placetype":"venue"
},
  "geometry": {"coordinates":[-93.00510300000001,44.860649],"type":"Point"}
}