{
  "type": "Feature",
  "properties": {
    "addr:full":"7801 Lyndale Ave S Minneapolis MN 55420",
    "addr:housenumber":"7801",
    "addr:postcode":"55420",
    "addr:street":"Lyndale Ave S",
    "iso:country":"US",
    "sg:address":"7801 Lyndale Ave S",
    "sg:city":"Minneapolis",
    "sg:classifiers":[
        {
            "category":"Autos & Motor Vehicles",
            "subcategory":"Automobile Sales",
            "type":"Retail Goods"
        }
    ],
    "sg:phone":"+1 952 890 7370",
    "sg:postcode":"55420",
    "sg:province":"MN",
    "wof:name":"Motors Management Corporation",
    "wof:placetype":"venue"
},
  "geometry": {"coordinates":[-93.288443,44.859381],"type":"Point"}
}