{
  "type": "Feature",
  "properties": {
    "addr:full":"13534 14th St NE Eyota MN 55934",
    "addr:housenumber":"13534",
    "addr:postcode":"55934",
    "addr:street":"14Th St Ne",
    "iso:country":"US",
    "sg:address":"13534 14th St NE",
    "sg:city":"Eyota",
    "sg:classifiers":[
        {
            "category":"Farming",
            "subcategory":"Dairy Farm",
            "type":"Manufacturing & Wholesale Goods"
        }
    ],
    "sg:phone":"+1 507 545 2743",
    "sg:postcode":"55934",
    "sg:province":"MN",
    "wof:name":"Mark Shea",
    "wof:placetype":"venue"
},
  "geometry": {"coordinates":[-92.216616,44.035199],"type":"Point"}
}