{
  "type": "Feature",
  "properties": {
    "addr:full":"15177 Patricia Ct Eden Prairie MN 55346",
    "addr:housenumber":"15177",
    "addr:postcode":"55346",
    "addr:street":"Patricia Ct",
    "iso:country":"US",
    "sg:address":"15177 Patricia Ct",
    "sg:city":"Eden Prairie",
    "sg:classifiers":[
        {
            "category":"Wholesale",
            "subcategory":"Computers",
            "type":"Manufacturing & Wholesale Goods"
        }
    ],
    "sg:phone":"+1 952 974 3866",
    "sg:postcode":"55346",
    "sg:province":"MN",
    "sg:website":"www.itsalesinc.com",
    "wof:name":"It Sales Inc",
    "wof:placetype":"venue"
},
  "geometry": {"coordinates":[-93.46943400000001,44.88155],"type":"Point"}
}