{
  "type": "Feature",
  "properties": {
    "addr:full":"501 S Washington Ave 3rd Fl Minneapolis MN 55415",
    "addr:housenumber":"501;3rd",
    "addr:postcode":"55415",
    "addr:street":"S Washington Ave;Fl",
    "iso:country":"US",
    "sg:address":"501 S Washington Ave 3rd Fl",
    "sg:city":"Minneapolis",
    "sg:classifiers":[
        {
            "category":"Sports & Exercise",
            "subcategory":"Gym",
            "type":"Entertainment"
        }
    ],
    "sg:phone":"+1 612 767 4415",
    "sg:postcode":"55415",
    "sg:province":"MN",
    "sg:website":"www.501spin.com",
    "wof:name":"501 SP1N",
    "wof:placetype":"venue"
},
  "geometry": {"coordinates":[-93.260903,44.978542],"type":"Point"}
}