{
  "type": "Feature",
  "properties": {
    "iso:country":"US",
    "sg:address":"6699 Hwy 169",
    "sg:city":"Tower",
    "sg:classifiers":[
        {
            "category":"Restaurant",
            "type":"Food & Drink"
        }
    ],
    "sg:phone":"+1 218 749 2460",
    "sg:postcode":"55790",
    "sg:province":"MN",
    "wof:name":"Black Bear Cafe",
    "wof:placetype":"venue"
},
  "geometry": {"coordinates":[-92.39542,47.729618],"type":"Point"}
}