{
  "type": "Feature",
  "properties": {
    "iso:country":"US",
    "sg:address":"320 Vermillion St",
    "sg:city":"Hastings",
    "sg:classifiers":[
        {
            "category":"Retail",
            "subcategory":"Auto Repair",
            "type":"Services"
        }
    ],
    "sg:phone":"+1 651 437 6400",
    "sg:postcode":"55033",
    "sg:province":"MN",
    "sg:tags":[
        "general",
        "supply"
    ],
    "wof:name":"Downtown Tire & Auto Inc",
    "wof:placetype":"venue"
},
  "geometry": {"coordinates":[-92.852447,44.742965],"type":"Point"}
}