{
  "type": "Feature",
  "properties": {
    "iso:country":"US",
    "sg:address":"7701 France Ave S",
    "sg:city":"Minneapolis",
    "sg:classifiers":[
        {
            "category":"Health Services",
            "subcategory":"Health Practitioner",
            "type":"Services"
        }
    ],
    "sg:phone":"+1 952 841 6402",
    "sg:postcode":"55435",
    "sg:province":"MN",
    "sg:tags":[
        "nurse",
        "registry"
    ],
    "wof:name":"Blackwell Igbanugo Nurse Sltns",
    "wof:placetype":"venue"
},
  "geometry": {"coordinates":[-93.32886499999999,44.860512],"type":"Point"}
}