{
  "type": "Feature",
  "properties": {
    "addr:full":"6814 Humboldt Ave S Minneapolis MN 55423",
    "addr:housenumber":"6814",
    "addr:postcode":"55423",
    "addr:street":"Humboldt Ave S",
    "iso:country":"US",
    "sg:address":"6814 Humboldt Ave S",
    "sg:city":"Minneapolis",
    "sg:classifiers":[
        {
            "category":"Professional",
            "type":"Services"
        }
    ],
    "sg:phone":"+1 612 861 4567",
    "sg:postcode":"55423",
    "sg:province":"MN",
    "wof:name":"Navirondo Community Organizati",
    "wof:placetype":"venue"
},
  "geometry": {"coordinates":[-93.29855999999999,44.878348],"type":"Point"}
}