{
  "type": "Feature",
  "properties": {
    "addr:full":"10468 Shady Ln Brainerd MN 56401",
    "addr:housenumber":"10468",
    "addr:postcode":"56401",
    "addr:street":"Shady Ln",
    "iso:country":"US",
    "sg:address":"10468 Shady Ln",
    "sg:city":"Brainerd",
    "sg:classifiers":[
        {
            "category":"Manufacturing",
            "subcategory":"Printing",
            "type":"Manufacturing & Wholesale Goods"
        }
    ],
    "sg:phone":"+1 218 828 8277",
    "sg:postcode":"56401",
    "sg:province":"MN",
    "sg:tags":[
        "publishing"
    ],
    "wof:name":"Almega Music",
    "wof:placetype":"venue"
},
  "geometry": {"coordinates":[-94.34173800000001,46.425255],"type":"Point"}
}