{
  "type": "Feature",
  "properties": {
    "addr:full":"603 15th St NW Rochester MN 55901",
    "addr:housenumber":"603",
    "addr:postcode":"55901",
    "addr:street":"15Th St Nw",
    "iso:country":"US",
    "sg:address":"603 15th St NW",
    "sg:city":"Rochester",
    "sg:classifiers":[
        {
            "category":"Education",
            "subcategory":"Library",
            "type":"Public Place"
        }
    ],
    "sg:phone":"+1 507 282 5025",
    "sg:postcode":"55901",
    "sg:province":"MN",
    "sg:tags":[
        "contracting"
    ],
    "wof:name":"Allen Dollerschell",
    "wof:placetype":"venue"
},
  "geometry": {"coordinates":[-92.47126400000001,44.03693],"type":"Point"}
}