{
  "type": "Feature",
  "properties": {
    "iso:country":"US",
    "sg:address":"4381 Highway 13 W",
    "sg:city":"Savage",
    "sg:classifiers":[
        {
            "category":"Restaurant",
            "type":"Food & Drink"
        }
    ],
    "sg:menulink":"http://www.allmenus.com/mn/savage/57497-pizza-man/menu/",
    "sg:phone":"+1 952 894 2202",
    "sg:postcode":"55378",
    "sg:province":"MN",
    "sg:tags":[
        "american",
        "pizza"
    ],
    "wof:name":"Pizza Man",
    "wof:placetype":"venue"
},
  "geometry": {"coordinates":[-93.33581599999999,44.77902],"type":"Point"}
}