{
  "type": "Feature",
  "properties": {
    "addr:full":"3311 Vale Cir SW Prior Lake MN 55372",
    "addr:housenumber":"3311",
    "addr:postcode":"55372",
    "addr:street":"Vale Cir Sw Prior",
    "iso:country":"US",
    "sg:address":"3311 Vale Cir SW",
    "sg:city":"Prior Lake",
    "sg:classifiers":[
        {
            "category":"Building & Trades",
            "subcategory":"Construction",
            "type":"Services"
        }
    ],
    "sg:phone":"+1 952 226 2699",
    "sg:postcode":"55372",
    "sg:province":"MN",
    "sg:tags":[
        "house"
    ],
    "wof:name":"M Larson Construction",
    "wof:placetype":"venue"
},
  "geometry": {"coordinates":[-93.453963,44.703841],"type":"Point"}
}