{
  "type": "Feature",
  "properties": {
    "addr:full":"501 Inglewood Dr N Baxter MN 56425",
    "addr:housenumber":"501",
    "addr:postcode":"56425",
    "addr:street":"Inglewood Dr N",
    "iso:country":"US",
    "sg:address":"501 Inglewood Dr N",
    "sg:city":"Baxter",
    "sg:classifiers":[
        {
            "category":"Building & Trades",
            "subcategory":"Cleaning & Sanitation",
            "type":"Services"
        }
    ],
    "sg:phone":"+1 218 855 1019",
    "sg:postcode":"56425",
    "sg:province":"MN",
    "sg:tags":[
        "co",
        "maintenance",
        "hanging"
    ],
    "wof:name":"Northland Cabin Care",
    "wof:placetype":"venue"
},
  "geometry": {"coordinates":[-94.26558,46.357179],"type":"Point"}
}