{
  "type": "Feature",
  "properties": {
    "addr:full":"305 8th St S Delano MN 55328",
    "addr:housenumber":"305",
    "addr:postcode":"55328",
    "addr:street":"8Th St S",
    "iso:country":"US",
    "sg:address":"305 8th St S",
    "sg:city":"Delano",
    "sg:classifiers":[
        {
            "category":"Insurance",
            "subcategory":"Insurance Agent",
            "type":"Services"
        }
    ],
    "sg:phone":"+1 763 972 3323",
    "sg:postcode":"55328",
    "sg:province":"MN",
    "wof:name":"Crow River Insurance Svc",
    "wof:placetype":"venue"
},
  "geometry": {"coordinates":[-93.777579,45.036556],"type":"Point"}
}