{
  "type": "Feature",
  "properties": {
    "addr:full":"2674 6th Ave Saint Paul MN 55109",
    "addr:housenumber":"2674",
    "addr:postcode":"55109",
    "addr:street":"6Th Ave",
    "iso:country":"US",
    "sg:address":"2674 6th Ave",
    "sg:city":"Saint Paul",
    "sg:classifiers":[
        {
            "category":"Social Services",
            "subcategory":"Child Care",
            "type":"Services"
        }
    ],
    "sg:phone":"+1 651 777 7443",
    "sg:postcode":"55109",
    "sg:province":"MN",
    "sg:tags":[
        "day"
    ],
    "wof:name":"Howard Claire Day Care",
    "wof:placetype":"venue"
},
  "geometry": {"coordinates":[-92.98879700000001,45.012031],"type":"Point"}
}