{
  "type": "Feature",
  "properties": {
    "iso:country":"US",
    "sg:address":"16677 Duluth Ave SE",
    "sg:city":"Prior Lake",
    "sg:classifiers":[
        {
            "category":"Insurance",
            "subcategory":"Insurance Agent",
            "type":"Services"
        }
    ],
    "sg:phone":"+1 952 226 6066",
    "sg:postcode":"55372",
    "sg:province":"MN",
    "wof:name":"Larson Joel Miller Hartwig Ins",
    "wof:placetype":"venue"
},
  "geometry": {"coordinates":[-93.429714,44.708608],"type":"Point"}
}