{
  "type": "Feature",
  "properties": {
    "iso:country":"US",
    "sg:address":"3670 Aquila Ave S",
    "sg:city":"St Louis Park",
    "sg:classifiers":[
        {
            "category":"Banks & Credit Unions",
            "subcategory":"Bank",
            "type":"Services"
        }
    ],
    "sg:phone":"+1 952 930 0700",
    "sg:postcode":"55426",
    "sg:province":"MN",
    "sg:website":"www.recu.com",
    "wof:name":"Retail Employees Credit Union",
    "wof:placetype":"venue"
},
  "geometry": {"coordinates":[-93.386814,44.936093],"type":"Point"}
}