{
  "type": "Feature",
  "properties": {
    "iso:country":"US",
    "sg:address":"800 White Bear Ave N",
    "sg:city":"Saint Paul",
    "sg:classifiers":[
        {
            "category":"Shopping",
            "subcategory":"Computers & Home Electronics",
            "type":"Retail Goods"
        }
    ],
    "sg:phone":"+1 651 731 3603",
    "sg:postcode":"55106",
    "sg:province":"MN",
    "sg:tags":[
        "household",
        "appliance"
    ],
    "wof:name":"Plaza TV & Appliance",
    "wof:placetype":"venue"
},
  "geometry": {"coordinates":[-93.02523100000001,44.965245],"type":"Point"}
}