{
  "type": "Feature",
  "properties": {
    "addr:full":"1785 Market Blvd Hastings MN 55033",
    "addr:housenumber":"1785",
    "addr:postcode":"55033",
    "addr:street":"Market Blvd",
    "iso:country":"US",
    "sg:address":"1785 Market Blvd",
    "sg:city":"Hastings",
    "sg:classifiers":[
        {
            "category":"Shopping",
            "subcategory":"Clothing, Apparel, & Fashions",
            "type":"Retail Goods"
        }
    ],
    "sg:phone":"+1 651 437 2166",
    "sg:postcode":"55033",
    "sg:province":"MN",
    "sg:tags":[
        "apparel",
        "women's"
    ],
    "sg:website":"http://www.maurices.com",
    "wof:name":"Maurices",
    "wof:placetype":"venue"
},
  "geometry": {"coordinates":[-92.891774,44.73723],"type":"Point"}
}