{
  "type": "Feature",
  "properties": {
    "iso:country":"US",
    "sg:address":"400 S 4th St Ste 1000",
    "sg:city":"Minneapolis",
    "sg:classifiers":[
        {
            "category":"Manufacturing",
            "subcategory":"Chemicals & Compounds",
            "type":"Manufacturing & Wholesale Goods"
        }
    ],
    "sg:phone":"+1 612 333 4000",
    "sg:postcode":"55415",
    "sg:province":"MN",
    "sg:tags":[
        "chemicals-wholesale",
        "manufacturer"
    ],
    "sg:website":"http://www.globalethanolservices.com",
    "wof:name":"Global Ethanol",
    "wof:placetype":"venue"
},
  "geometry": {"coordinates":[-93.264343,44.977482],"type":"Point"}
}