{
  "type": "Feature",
  "properties": {
    "addr:full":"9099 Briarglen Rd Eden Prairie MN 55347",
    "addr:housenumber":"9099",
    "addr:postcode":"55347",
    "addr:street":"Briarglen Rd",
    "iso:country":"US",
    "sg:address":"9099 Briarglen Rd",
    "sg:city":"Eden Prairie",
    "sg:classifiers":[
        {
            "category":"Manufacturing",
            "subcategory":"Metals",
            "type":"Manufacturing & Wholesale Goods"
        }
    ],
    "sg:phone":"+1 952 974 2876",
    "sg:postcode":"55347",
    "sg:province":"MN",
    "wof:name":"A & E Metal Finishing Inc",
    "wof:placetype":"venue"
},
  "geometry": {"coordinates":[-93.49782500000001,44.84063],"type":"Point"}
}