{
  "type": "Feature",
  "properties": {
    "addr:full":"6500 Nordic Dr Minneapolis MN 55439",
    "addr:housenumber":"6500",
    "addr:postcode":"55439",
    "addr:street":"Nordic Dr",
    "iso:country":"US",
    "sg:address":"6500 Nordic Dr",
    "sg:city":"Minneapolis",
    "sg:classifiers":[
        {
            "category":"Professional",
            "subcategory":"Business Services",
            "type":"Services"
        }
    ],
    "sg:phone":"+1 952 944 2325",
    "sg:postcode":"55439",
    "sg:province":"MN",
    "wof:name":"E Associates",
    "wof:placetype":"venue"
},
  "geometry": {"coordinates":[-93.379959,44.882587],"type":"Point"}
}