{
  "type": "Feature",
  "properties": {
    "addr:full":"410 31st St Chandler MN 56122",
    "addr:housenumber":"410",
    "addr:postcode":"56122",
    "addr:street":"31St St",
    "iso:country":"US",
    "sg:address":"410 31st St",
    "sg:city":"Chandler",
    "sg:phone":"+1 507 443 6471",
    "sg:postcode":"56122",
    "sg:province":"MN",
    "sg:tags":[
        "farm",
        "corn",
        "soybean"
    ],
    "wof:name":"Green John",
    "wof:placetype":"venue"
},
  "geometry": {"coordinates":[-95.98257,43.892399],"type":"Point"}
}