{
  "type": "Feature",
  "properties": {
    "iso:country":"US",
    "sg:address":"4063 85th Ave N",
    "sg:city":"Minneapolis",
    "sg:classifiers":[
        {
            "category":"Social Services",
            "type":"Services"
        }
    ],
    "sg:phone":"+1 763 786 6449",
    "sg:postcode":"55443",
    "sg:province":"MN",
    "sg:tags":[
        "organization",
        "welfare"
    ],
    "sg:website":"www.lssmn.org",
    "wof:name":"Lutheran Social Svc",
    "wof:placetype":"venue"
},
  "geometry": {"coordinates":[-93.329779,45.1088],"type":"Point"}
}