{
  "type": "Feature",
  "properties": {
    "iso:country":"US",
    "sg:address":"25 E 1st St",
    "sg:city":"Zumbrota",
    "sg:classifiers":[
        {
            "category":"Organizations",
            "subcategory":"Community Association",
            "type":"Services"
        }
    ],
    "sg:phone":"+1 507 732 5411",
    "sg:postcode":"55992",
    "sg:province":"MN",
    "sg:tags":[
        "club"
    ],
    "wof:name":"Veterans Of Foreign Wars",
    "wof:placetype":"venue"
},
  "geometry": {"coordinates":[-92.668964,44.295722],"type":"Point"}
}