{
  "type": "Feature",
  "properties": {
    "addr:full":"102 Industrial Ln Edgerton MN 56187",
    "addr:housenumber":"102",
    "addr:postcode":"56187",
    "addr:street":"Industrial Ln",
    "iso:country":"US",
    "sg:address":"102 Industrial Ln",
    "sg:city":"Edgerton",
    "sg:classifiers":[
        {
            "category":"Freight",
            "type":"Transportation"
        }
    ],
    "sg:phone":"+1 507 442 5355",
    "sg:postcode":"56187",
    "sg:province":"MN",
    "sg:tags":[
        "dry",
        "bulk",
        "trucking"
    ],
    "wof:name":"Corbin Transport",
    "wof:placetype":"venue"
},
  "geometry": {"coordinates":[-95.612047,43.636515],"type":"Point"}
}