{
  "type": "Feature",
  "properties": {
    "addr:full":"2233 Hamline Ave N St Paul MN 55113",
    "addr:postcode":"2233;55113",
    "addr:street":"Hamline Ave N",
    "iso:country":"US",
    "sg:address":"2233 Hamline Ave N",
    "sg:city":"St Paul",
    "sg:classifiers":[
        {
            "category":"Personal",
            "subcategory":"Barber",
            "type":"Services"
        }
    ],
    "sg:phone":"+1 651 644 9791",
    "sg:postcode":"55113",
    "sg:province":"MN",
    "wof:name":"Sandy's Barber Shop",
    "wof:placetype":"venue"
},
  "geometry": {"coordinates":[-93.156696,45.007574],"type":"Point"}
}