{
  "type": "Feature",
  "properties": {
    "addr:full":"1350 7th St SW Willmar MN 56201",
    "addr:housenumber":"1350",
    "addr:postcode":"56201",
    "addr:street":"7Th St Sw",
    "iso:country":"US",
    "sg:address":"1350 7th St SW",
    "sg:city":"Willmar",
    "sg:classifiers":[
        {
            "category":"Wholesale",
            "subcategory":"Electrical",
            "type":"Manufacturing & Wholesale Goods"
        }
    ],
    "sg:phone":"+1 320 235 0630",
    "sg:postcode":"56201",
    "sg:province":"MN",
    "sg:tags":[
        "communication",
        "radio",
        "system"
    ],
    "wof:name":"Pete's Communications Inc",
    "wof:placetype":"venue"
},
  "geometry": {"coordinates":[-95.04967499999999,45.108815],"type":"Point"}
}