{
  "type": "Feature",
  "properties": {
    "addr:full":"5700 105th Ave N Minneapolis MN 55443",
    "addr:housenumber":"5700",
    "addr:postcode":"55443",
    "addr:street":"105Th Ave N",
    "iso:country":"US",
    "sg:address":"5700 105th Ave N",
    "sg:city":"Minneapolis",
    "sg:classifiers":[
        {
            "category":"Building & Trades",
            "subcategory":"Locksmith",
            "type":"Services"
        }
    ],
    "sg:phone":"+1 952 807 0059",
    "sg:postcode":"55443",
    "sg:province":"MN",
    "sg:tags":[
        "key"
    ],
    "wof:name":"A 24 Hour A Locksmith",
    "wof:placetype":"venue"
},
  "geometry": {"coordinates":[-93.35409300000001,45.143873],"type":"Point"}
}