{
  "type": "Feature",
  "properties": {
    "iso:country":"US",
    "sg:address":"2608 Hawthorne Ln",
    "sg:city":"Stillwater",
    "sg:classifiers":[
        {
            "category":"Building & Trades",
            "subcategory":"Construction",
            "type":"Services"
        }
    ],
    "sg:phone":"+1 651 439 4398",
    "sg:postcode":"55082",
    "sg:province":"MN",
    "sg:tags":[
        "contractor"
    ],
    "wof:name":"North End Contracting",
    "wof:placetype":"venue"
},
  "geometry": {"coordinates":[-92.840796,45.055265],"type":"Point"}
}