{
  "type": "Feature",
  "properties": {
    "addr:full":"7125 Bristol Blvd Minneapolis MN 55435",
    "addr:housenumber":"7125",
    "addr:postcode":"55435",
    "addr:street":"Bristol Blvd",
    "iso:country":"US",
    "sg:address":"7125 Bristol Blvd",
    "sg:city":"Minneapolis",
    "sg:classifiers":[
        {
            "category":"Professional",
            "subcategory":"Business Services",
            "type":"Services"
        }
    ],
    "sg:phone":"+1 952 927 0487",
    "sg:postcode":"55435",
    "sg:province":"MN",
    "wof:name":"House of History Intl",
    "wof:placetype":"venue"
},
  "geometry": {"coordinates":[-93.332167,44.873248],"type":"Point"}
}