{
  "type": "Feature",
  "properties": {
    "addr:full":"2213 5th St NW Saint Paul MN 55112",
    "addr:housenumber":"2213",
    "addr:postcode":"55112",
    "addr:street":"5Th St Nw",
    "iso:country":"US",
    "sg:address":"2213 5th St NW",
    "sg:city":"Saint Paul",
    "sg:classifiers":[
        {
            "category":"Restaurant",
            "type":"Food & Drink"
        }
    ],
    "sg:phone":"+1 651 636 0711",
    "sg:postcode":"55112",
    "sg:province":"MN",
    "sg:tags":[
        "eating"
    ],
    "wof:name":"Tab Restaurant Inc",
    "wof:placetype":"venue"
},
  "geometry": {"coordinates":[-93.215001,45.057233],"type":"Point"}
}