{
  "type": "Feature",
  "properties": {
    "iso:country":"US",
    "sg:address":"843 3rd St E",
    "sg:city":"Saint Paul",
    "sg:classifiers":[
        {
            "category":"Professional",
            "subcategory":"Business Services",
            "type":"Services"
        }
    ],
    "sg:phone":"+1 651 774 7379",
    "sg:postcode":"55106",
    "sg:province":"MN",
    "wof:name":"Purple Star Couture",
    "wof:placetype":"venue"
},
  "geometry": {"coordinates":[-93.064212,44.956803],"type":"Point"}
}