{
  "type": "Feature",
  "properties": {
    "addr:full":"3120 E 25th St Minneapolis MN 55406",
    "addr:housenumber":"3120",
    "addr:postcode":"55406",
    "addr:street":"E 25Th St",
    "iso:country":"US",
    "sg:address":"3120 E 25th St",
    "sg:city":"Minneapolis",
    "sg:classifiers":[
        {
            "category":"Professional",
            "subcategory":"Computer Services",
            "type":"Services"
        }
    ],
    "sg:phone":"+1 612 387 8003",
    "sg:postcode":"55406",
    "sg:province":"MN",
    "sg:tags":[
        "technical",
        "assistance",
        "support"
    ],
    "wof:name":"Blue Shfit",
    "wof:placetype":"venue"
},
  "geometry": {"coordinates":[-93.226659,44.957371],"type":"Point"}
}