{
  "type": "Feature",
  "properties": {
    "addr:full":"32055 Hemmingway Ave Stacy MN 55079",
    "addr:postcode":"32055;55079",
    "addr:street":"Hemmingway Ave",
    "iso:country":"US",
    "sg:address":"32055 Hemmingway Ave",
    "sg:city":"Stacy",
    "sg:classifiers":[
        {
            "category":"Organizations",
            "subcategory":"Community Association",
            "type":"Services"
        }
    ],
    "sg:phone":"+1 651 462 1803",
    "sg:postcode":"55079",
    "sg:province":"MN",
    "wof:name":"Minnesota Cutting Horse A",
    "wof:placetype":"venue"
},
  "geometry": {"coordinates":[-92.957975,45.410867],"type":"Point"}
}