{
  "type": "Feature",
  "properties": {
    "iso:country":"US",
    "sg:address":"10 Co St Aid Hwy 13",
    "sg:city":"Melrose",
    "sg:classifiers":[
        {
            "category":"Home & Garden",
            "subcategory":"Garden Supply",
            "type":"Retail Goods"
        }
    ],
    "sg:phone":"+1 320 987 3770",
    "sg:postcode":"56352",
    "sg:province":"MN",
    "sg:tags":[
        "bulb",
        "seed"
    ],
    "wof:name":"Ted Mc Carthy Inc",
    "wof:placetype":"venue"
},
  "geometry": {"coordinates":[-94.80767400000001,45.675228],"type":"Point"}
}