{
  "type": "Feature",
  "properties": {
    "addr:full":"511 Northern Hills Dr NE Rochester MN 55906",
    "addr:housenumber":"511",
    "addr:postcode":"55906",
    "addr:street":"Northern Hills Dr Ne",
    "iso:country":"US",
    "sg:address":"511 Northern Hills Dr NE",
    "sg:city":"Rochester",
    "sg:classifiers":[
        {
            "category":"Home & Garden",
            "subcategory":"Home Furnishings",
            "type":"Retail Goods"
        }
    ],
    "sg:phone":"+1 507 285 1900",
    "sg:postcode":"55906",
    "sg:province":"MN",
    "sg:tags":[
        "lighting",
        "furniture",
        "fixture",
        "light"
    ],
    "wof:name":"Northern Lights & Furnishings",
    "wof:placetype":"venue"
},
  "geometry": {"coordinates":[-92.45551,44.050159],"type":"Point"}
}