{
  "type": "Feature",
  "properties": {
    "iso:country":"US",
    "sg:address":"841 Forest Ave E",
    "sg:city":"Mora",
    "sg:classifiers":[
        {
            "category":"Real Estate",
            "subcategory":"Real Estate Agent",
            "type":"Services"
        }
    ],
    "sg:phone":"+1 320 679 1632",
    "sg:postcode":"55051",
    "sg:province":"MN",
    "wof:name":"Oakwood Property Management",
    "wof:placetype":"venue"
},
  "geometry": {"coordinates":[-93.285982,45.876146],"type":"Point"}
}