{
  "type": "Feature",
  "properties": {
    "iso:country":"US",
    "sg:address":"12301 Central Ave NE",
    "sg:city":"Blaine",
    "sg:classifiers":[
        {
            "category":"Professional",
            "subcategory":"Computer Services",
            "type":"Services"
        },
        {
            "category":"Shopping",
            "subcategory":"Computers & Home Electronics",
            "type":"Retail Goods"
        }
    ],
    "sg:phone":"+1 763 755 1402",
    "sg:postcode":"55434",
    "sg:province":"MN",
    "sg:tags":[
        "le",
        "for",
        "writes",
        "early",
        "need",
        "special",
        "software"
    ],
    "wof:name":"Marblesoft",
    "wof:placetype":"venue"
},
  "geometry": {"coordinates":[-93.234853,45.197176],"type":"Point"}
}