{
  "type": "Feature",
  "properties": {
    "iso:country":"US",
    "sg:address":"12901 Berkshire Dr",
    "sg:city":"Hopkins",
    "sg:classifiers":[
        {
            "category":"Real Estate",
            "subcategory":"Real Estate Agent",
            "type":"Services"
        },
        {
            "category":"Professional",
            "subcategory":"Business Services",
            "type":"Services"
        }
    ],
    "sg:phone":"+1 952 938 1358",
    "sg:postcode":"55343",
    "sg:province":"MN",
    "sg:tags":[
        "appraiser"
    ],
    "wof:name":"Great Lakes Appraisal Services",
    "wof:placetype":"venue"
},
  "geometry": {"coordinates":[-93.446485,44.923455],"type":"Point"}
}