{
  "type": "Feature",
  "properties": {
    "addr:full":"6805 Thomas Ave S Minneapolis MN 55423",
    "addr:housenumber":"6805",
    "addr:postcode":"55423",
    "addr:street":"Thomas Ave S",
    "iso:country":"US",
    "sg:address":"6805 Thomas Ave S",
    "sg:city":"Minneapolis",
    "sg:classifiers":[
        {
            "category":"Professional",
            "type":"Services"
        }
    ],
    "sg:phone":"+1 612 866 7065",
    "sg:postcode":"55423",
    "sg:province":"MN",
    "wof:name":"Ismist Recordings Inc",
    "wof:placetype":"venue"
},
  "geometry": {"coordinates":[-93.313607,44.878207],"type":"Point"}
}