{
  "type": "Feature",
  "properties": {
    "addr:full":"3907 Vincent Ave N Minneapolis MN 55412",
    "addr:housenumber":"3907",
    "addr:postcode":"55412",
    "addr:street":"Vincent Ave N",
    "iso:country":"US",
    "sg:address":"3907 Vincent Ave N",
    "sg:city":"Minneapolis",
    "sg:classifiers":[
        {
            "category":"Building & Trades",
            "subcategory":"Construction",
            "type":"Services"
        }
    ],
    "sg:phone":"+1 612 522 5938",
    "sg:postcode":"55412",
    "sg:province":"MN",
    "sg:tags":[
        "carpenter"
    ],
    "wof:name":"Nimz, Del",
    "wof:placetype":"venue"
},
  "geometry": {"coordinates":[-93.31601999999999,45.026012],"type":"Point"}
}