{
  "type": "Feature",
  "properties": {
    "addr:full":"233 Russell Ave S Minneapolis MN 55405",
    "addr:housenumber":"233",
    "addr:postcode":"55405",
    "addr:street":"Russell Ave S",
    "iso:country":"US",
    "sg:address":"233 Russell Ave S",
    "sg:city":"Minneapolis",
    "sg:classifiers":[
        {
            "category":"Social Services",
            "subcategory":"Child Care",
            "type":"Services"
        }
    ],
    "sg:phone":"+1 763 374 3379",
    "sg:postcode":"55405",
    "sg:province":"MN",
    "sg:tags":[
        "nursery",
        "day"
    ],
    "wof:name":"Arlene Tormanen",
    "wof:placetype":"venue"
},
  "geometry": {"coordinates":[-93.31089,44.974765],"type":"Point"}
}