{
  "type": "Feature",
  "properties": {
    "addr:full":"41233 200th St Springfield MN 56087",
    "addr:housenumber":"41233",
    "addr:postcode":"56087",
    "addr:street":"200Th St",
    "iso:country":"US",
    "sg:address":"41233 200th St",
    "sg:city":"Springfield",
    "sg:phone":"+1 507 723 6638",
    "sg:postcode":"56087",
    "sg:province":"MN",
    "sg:tags":[
        "farm",
        "corn",
        "soybean"
    ],
    "wof:name":"Mike Vanderwerf",
    "wof:placetype":"venue"
},
  "geometry": {"coordinates":[-95.007651,44.253562],"type":"Point"}
}