{
  "type": "Feature",
  "properties": {
    "iso:country":"US",
    "sg:address":"651 University Ave W",
    "sg:city":"St Paul",
    "sg:classifiers":[
        {
            "category":"Food & Beverages",
            "subcategory":"Groceries & Convenience Stores",
            "type":"Retail Goods"
        }
    ],
    "sg:phone":"+1 651 291 0846",
    "sg:postcode":"55104",
    "sg:province":"MN",
    "sg:tags":[
        "grocer"
    ],
    "wof:name":"Chouleng Asian Foods",
    "wof:placetype":"venue"
},
  "geometry": {"coordinates":[-93.12846999999999,44.955794],"type":"Point"}
}