{
  "type": "Feature",
  "properties": {
    "addr:full":"755 Tower Dr Hamel MN 55340",
    "addr:housenumber":"755",
    "addr:postcode":"55340",
    "addr:street":"Tower Dr Hamel",
    "iso:country":"US",
    "sg:address":"755 Tower Dr",
    "sg:city":"Hamel",
    "sg:classifiers":[
        {
            "category":"Wholesale",
            "subcategory":"Medical Equipment & Supplies",
            "type":"Manufacturing & Wholesale Goods"
        },
        {
            "category":"Wholesale",
            "subcategory":"Durable Goods & Equipment",
            "type":"Manufacturing & Wholesale Goods"
        }
    ],
    "sg:phone":"+1 763 478 6324",
    "sg:postcode":"55340",
    "sg:province":"MN",
    "sg:tags":[
        "professional",
        "optical"
    ],
    "wof:name":"Minneapolis Optical Case Co",
    "wof:placetype":"venue"
},
  "geometry": {"coordinates":[-93.54016799999999,45.044401],"type":"Point"}
}