{
  "type": "Feature",
  "properties": {
    "addr:full":"3332 W 56th St Minneapolis MN 55410",
    "addr:housenumber":"3332",
    "addr:postcode":"55410",
    "addr:street":"W 56Th St",
    "iso:country":"US",
    "sg:address":"3332 W 56th St",
    "sg:city":"Minneapolis",
    "sg:classifiers":[
        {
            "category":"Professional",
            "subcategory":"Management & Consulting",
            "type":"Services"
        }
    ],
    "sg:phone":"+1 952 926 5905",
    "sg:postcode":"55410",
    "sg:province":"MN",
    "wof:name":"KPMg",
    "wof:placetype":"venue"
},
  "geometry": {"coordinates":[-93.32317,44.901725],"type":"Point"}
}