{
  "type": "Feature",
  "properties": {
    "addr:full":"201 15th St NW Bemidji MN 56601",
    "addr:housenumber":"201",
    "addr:postcode":"56601",
    "addr:street":"15Th St Nw",
    "iso:country":"US",
    "sg:address":"201 15th St NW",
    "sg:city":"Bemidji",
    "sg:classifiers":[
        {
            "category":"Social Services",
            "subcategory":"Child Care",
            "type":"Services"
        }
    ],
    "sg:phone":"+1 218 333 3279",
    "sg:postcode":"56601",
    "sg:province":"MN",
    "wof:name":"Kids & Co",
    "wof:placetype":"venue"
},
  "geometry": {"coordinates":[-94.88278,47.482987],"type":"Point"}
}