{
  "type": "Feature",
  "properties": {
    "iso:country":"US",
    "sg:address":"1764 E Ivy Ave",
    "sg:city":"Saint Paul",
    "sg:classifiers":[
        {
            "category":"Building & Trades",
            "subcategory":"Construction",
            "type":"Services"
        }
    ],
    "sg:phone":"+1 651 774 0332",
    "sg:postcode":"55106",
    "sg:province":"MN",
    "sg:tags":[
        "house"
    ],
    "wof:name":"NJ Construction & Remodeling",
    "wof:placetype":"venue"
},
  "geometry": {"coordinates":[-93.02663200000001,44.981044],"type":"Point"}
}