{
  "type": "Feature",
  "properties": {
    "addr:full":"39249 Co Rd 257 Cohasset MN 55721",
    "addr:housenumber":"39249",
    "addr:postcode":"55721",
    "addr:street":"Co Rd 257",
    "iso:country":"US",
    "sg:address":"39249 Co Rd 257",
    "sg:city":"Cohasset",
    "sg:classifiers":[
        {
            "category":"Retail",
            "subcategory":"Repair Shop",
            "type":"Services"
        }
    ],
    "sg:phone":"+1 218 328 6157",
    "sg:postcode":"55721",
    "sg:province":"MN",
    "wof:name":"Adventure Taxidermy",
    "wof:placetype":"venue"
},
  "geometry": {"coordinates":[-93.691819,47.239387],"type":"Point"}
}