{
  "type": "Feature",
  "properties": {
    "addr:full":"17305 521st Ln Garden City MN 56034",
    "addr:housenumber":"17305",
    "addr:postcode":"56034",
    "addr:street":"521St Ln",
    "iso:country":"US",
    "sg:address":"17305 521st Ln",
    "sg:city":"Garden City",
    "sg:classifiers":[
        {
            "category":"Building & Trades",
            "subcategory":"Electrical",
            "type":"Services"
        }
    ],
    "sg:phone":"+1 507 546 3492",
    "sg:postcode":"56034",
    "sg:province":"MN",
    "sg:tags":[
        "electrical",
        "contractor"
    ],
    "wof:name":"Swanson & Sons Electric",
    "wof:placetype":"venue"
},
  "geometry": {"coordinates":[-94.188436,44.047236],"type":"Point"}
}