{
  "type": "Feature",
  "properties": {
    "addr:full":"141 Park St N Fairfax MN 55332",
    "addr:housenumber":"141",
    "addr:postcode":"55332",
    "addr:street":"Park St N",
    "iso:country":"US",
    "sg:address":"141 Park St N",
    "sg:city":"Fairfax",
    "sg:classifiers":[
        {
            "category":"Home & Garden",
            "subcategory":"Building Materials",
            "type":"Retail Goods"
        }
    ],
    "sg:phone":"+1 507 426 6050",
    "sg:postcode":"55332",
    "sg:province":"MN",
    "wof:name":"Clay Courtland Co",
    "wof:placetype":"venue"
},
  "geometry": {"coordinates":[-94.720725,44.530674],"type":"Point"}
}