{
  "type": "Feature",
  "properties": {
    "iso:country":"US",
    "sg:address":"1335 Co Rd G",
    "sg:city":"St Paul",
    "sg:classifiers":[
        {
            "category":"Retail",
            "subcategory":"Repair Shop",
            "type":"Services"
        }
    ],
    "sg:phone":"+1 651 426 0217",
    "sg:postcode":"55110",
    "sg:province":"MN",
    "sg:tags":[
        "upholsterer"
    ],
    "wof:name":"Tom's Upholstery",
    "wof:placetype":"venue"
},
  "geometry": {"coordinates":[-93.04433400000001,45.079317],"type":"Point"}
}