{
  "type": "Feature",
  "properties": {
    "iso:country":"US",
    "sg:address":"5312 Picha Rd",
    "sg:city":"Minnetonka",
    "sg:classifiers":[
        {
            "category":"Manufacturing",
            "subcategory":"Chemicals & Compounds",
            "type":"Manufacturing & Wholesale Goods"
        }
    ],
    "sg:phone":"+1 952 975 6054",
    "sg:postcode":"55345",
    "sg:province":"MN",
    "sg:tags":[
        "preparation",
        "pharmaceutical",
        "mfg"
    ],
    "wof:name":"Scherng-Plough Healthcare Pdts",
    "wof:placetype":"venue"
},
  "geometry": {"coordinates":[-93.488342,44.906782],"type":"Point"}
}