{
  "type": "Feature",
  "properties": {
    "addr:full":"2936 Kentucky Ave N Minneapolis MN 55427",
    "addr:housenumber":"2936",
    "addr:postcode":"55427",
    "addr:street":"Kentucky Ave N",
    "iso:country":"US",
    "sg:address":"2936 Kentucky Ave N",
    "sg:city":"Minneapolis",
    "sg:classifiers":[
        {
            "category":"Professional",
            "subcategory":"Management & Consulting",
            "type":"Services"
        }
    ],
    "sg:phone":"+1 763 545 0205",
    "sg:postcode":"55427",
    "sg:province":"MN",
    "sg:tags":[
        "sound",
        "system",
        "consultant"
    ],
    "wof:name":"Z-Sound",
    "wof:placetype":"venue"
},
  "geometry": {"coordinates":[-93.368988,45.010441],"type":"Point"}
}