{
  "type": "Feature",
  "properties": {
    "addr:full":"1015 State Hwy 29 N Alexandria MN 56308",
    "addr:housenumber":"1015",
    "addr:postcode":"56308",
    "addr:street":"State Hwy 29 N",
    "iso:country":"US",
    "sg:address":"1015 State Hwy 29 N",
    "sg:city":"Alexandria",
    "sg:classifiers":[
        {
            "category":"Wholesale",
            "subcategory":"Sporting Goods",
            "type":"Manufacturing & Wholesale Goods"
        }
    ],
    "sg:phone":"+1 320 762 1384",
    "sg:postcode":"56308",
    "sg:province":"MN",
    "sg:tags":[
        "course",
        "golf",
        "equipment"
    ],
    "wof:name":"Handicapping Plus",
    "wof:placetype":"venue"
},
  "geometry": {"coordinates":[-95.35623699999999,45.903451],"type":"Point"}
}