{
  "type": "Feature",
  "properties": {
    "iso:country":"US",
    "sg:address":"13005 55th Ave N",
    "sg:city":"Plymouth",
    "sg:classifiers":[
        {
            "category":"Building & Trades",
            "subcategory":"Construction",
            "type":"Services"
        }
    ],
    "sg:phone":"+1 763 559 4815",
    "sg:postcode":"55442",
    "sg:province":"MN",
    "sg:tags":[
        "home",
        "builder"
    ],
    "wof:name":"Vintage Builders Inc",
    "wof:placetype":"venue"
},
  "geometry": {"coordinates":[-93.44389,45.054084],"type":"Point"}
}