{
  "type": "Feature",
  "properties": {
    "addr:full":"3015 W Lincoln Ave Olivia MN 56277",
    "addr:housenumber":"3015",
    "addr:postcode":"56277",
    "addr:street":"W Lincoln Ave",
    "iso:country":"US",
    "sg:address":"3015 W Lincoln Ave",
    "sg:city":"Olivia",
    "sg:classifiers":[
        {
            "category":"Manufacturing",
            "subcategory":"Rubber & Plastics",
            "type":"Manufacturing & Wholesale Goods"
        }
    ],
    "sg:phone":"+1 320 523 1663",
    "sg:postcode":"56277",
    "sg:province":"MN",
    "sg:tags":[
        "product",
        "mfg"
    ],
    "wof:name":"Sunrise Packaging Inc",
    "wof:placetype":"venue"
},
  "geometry": {"coordinates":[-95.03303699999999,44.780748],"type":"Point"}
}