{
  "type": "Feature",
  "properties": {
    "addr:full":"23397 285th Ave Sleepy Eye MN 56085",
    "addr:housenumber":"23397",
    "addr:postcode":"56085",
    "addr:street":"285Th Ave",
    "iso:country":"US",
    "sg:address":"23397 285th Ave",
    "sg:city":"Sleepy Eye",
    "sg:classifiers":[
        {
            "category":"Professional",
            "subcategory":"Research",
            "type":"Services"
        }
    ],
    "sg:phone":"+1 507 794 6122",
    "sg:postcode":"56085",
    "sg:province":"MN",
    "sg:tags":[
        "biologist"
    ],
    "wof:name":"Joseph Hoffmann",
    "wof:placetype":"venue"
},
  "geometry": {"coordinates":[-94.75591799999999,44.308611],"type":"Point"}
}