{
  "type": "Feature",
  "properties": {
    "addr:full":"2832 41st Ave S Minneapolis MN 55406",
    "addr:housenumber":"2832",
    "addr:postcode":"55406",
    "addr:street":"41St Ave S",
    "iso:country":"US",
    "sg:address":"2832 41st Ave S",
    "sg:city":"Minneapolis",
    "sg:classifiers":[
        {
            "category":"Cinema",
            "subcategory":"Movie Rental",
            "type":"Entertainment"
        }
    ],
    "sg:phone":"+1 651 699 9019",
    "sg:postcode":"55406",
    "sg:province":"MN",
    "sg:tags":[
        "motion",
        "video",
        "production",
        "tape"
    ],
    "wof:name":"JC Productions",
    "wof:placetype":"venue"
},
  "geometry": {"coordinates":[-93.214083,44.950752],"type":"Point"}
}