{
  "type": "Feature",
  "properties": {
    "iso:country":"US",
    "sg:address":"10905 Valley View Rd",
    "sg:city":"Eden Prairie",
    "sg:classifiers":[
        {
            "category":"Wholesale",
            "subcategory":"Office Equipment",
            "type":"Manufacturing & Wholesale Goods"
        }
    ],
    "sg:phone":"+1 866 856 3000",
    "sg:postcode":"55344",
    "sg:province":"MN",
    "sg:tags":[
        "dictation"
    ],
    "wof:name":"Lanier Worldwide Inc",
    "wof:placetype":"venue"
},
  "geometry": {"coordinates":[-93.418783,44.865415],"type":"Point"}
}