{
  "type": "Feature",
  "properties": {
    "iso:country":"US",
    "sg:address":"2450 Nicollet Ave",
    "sg:city":"Minneapolis",
    "sg:phone":"+1 612 870 8000",
    "sg:postcode":"55404",
    "sg:province":"MN",
    "wof:name":"Yummy Chinese Restaurant",
    "wof:placetype":"venue"
},
  "geometry": {"coordinates":[-93.277828,44.958231],"type":"Point"}
}