{
  "type": "Feature",
  "properties": {
    "addr:full":"654 S Main St Zumbrota MN 55992",
    "addr:housenumber":"654",
    "addr:postcode":"55992",
    "addr:street":"S Main St",
    "iso:country":"US",
    "sg:address":"654 S Main St",
    "sg:city":"Zumbrota",
    "sg:classifiers":[
        {
            "category":"Shopping",
            "subcategory":"Florist",
            "type":"Retail Goods"
        }
    ],
    "sg:phone":"+1 507 732 7766",
    "sg:postcode":"55992",
    "sg:province":"MN",
    "wof:name":"Aster Hill Floral Shoppe",
    "wof:placetype":"venue"
},
  "geometry": {"coordinates":[-92.66919,44.291106],"type":"Point"}
}