{
  "type": "Feature",
  "properties": {
    "iso:country":"US",
    "sg:address":"5800 Baker Rd",
    "sg:city":"Minnetonka",
    "sg:classifiers":[
        {
            "category":"Professional",
            "subcategory":"Engineering",
            "type":"Services"
        }
    ],
    "sg:phone":"+1 952 448 9601",
    "sg:postcode":"55345",
    "sg:province":"MN",
    "sg:tags":[
        "engineer"
    ],
    "wof:name":"Havtek Structural",
    "wof:placetype":"venue"
},
  "geometry": {"coordinates":[-93.44740299999999,44.898804],"type":"Point"}
}