{
  "type": "Feature",
  "properties": {
    "iso:country":"US",
    "sg:address":"405 E Superior St",
    "sg:city":"Duluth",
    "sg:classifiers":[
        {
            "category":"Banks & Credit Unions",
            "subcategory":"Investment Brokerage",
            "type":"Services"
        }
    ],
    "sg:phone":"+1 218 625 1735",
    "sg:postcode":"55802",
    "sg:province":"MN",
    "sg:tags":[
        "consultant",
        "planning",
        "financial"
    ],
    "wof:name":"Waddell & Reed Inc",
    "wof:placetype":"venue"
},
  "geometry": {"coordinates":[-92.092349,46.791812],"type":"Point"}
}