{
  "type": "Feature",
  "properties": {
    "iso:country":"US",
    "sg:address":"210 Pleasant St",
    "sg:city":"Anoka",
    "sg:classifiers":[
        {
            "category":"Taxi",
            "type":"Transportation"
        }
    ],
    "sg:phone":"+1 763 506 0196",
    "sg:postcode":"55303",
    "sg:province":"MN",
    "sg:tags":[
        "taxicab"
    ],
    "wof:name":"All Ways Taxi",
    "wof:placetype":"venue"
},
  "geometry": {"coordinates":[-93.390944,45.206551],"type":"Point"}
}