{
  "type": "Feature",
  "properties": {
    "addr:full":"7597 Teal Bay St Paul MN 55125",
    "addr:housenumber":"7597",
    "addr:postcode":"55125",
    "addr:street":"Teal Bay",
    "iso:country":"US",
    "sg:address":"7597 Teal Bay",
    "sg:city":"St Paul",
    "sg:classifiers":[
        {
            "category":"Health Services",
            "subcategory":"Medical Lab",
            "type":"Services"
        }
    ],
    "sg:phone":"+1 651 739 8491",
    "sg:postcode":"55125",
    "sg:province":"MN",
    "sg:tags":[
        "x"
    ],
    "wof:name":"Chiropractic Radiology Cnslntg",
    "wof:placetype":"venue"
},
  "geometry": {"coordinates":[-92.952545,44.935202],"type":"Point"}
}