{
  "type": "Feature",
  "properties": {
    "addr:full":"710 W Lake St Minneapolis MN 55408",
    "addr:housenumber":"710",
    "addr:postcode":"55408",
    "addr:street":"W Lake St",
    "iso:country":"US",
    "sg:address":"710 W Lake St",
    "sg:city":"Minneapolis",
    "sg:classifiers":[
        {
            "category":"Shopping",
            "subcategory":"Bicycles & Sporting Goods",
            "type":"Retail Goods"
        }
    ],
    "sg:phone":"+1 612 822 2228",
    "sg:postcode":"55408",
    "sg:province":"MN",
    "sg:tags":[
        "bike"
    ],
    "sg:website":"www.penncycle.com",
    "wof:name":"Penn Cycle",
    "wof:placetype":"venue"
},
  "geometry": {"coordinates":[-93.289001,44.948502],"type":"Point"}
}