{
  "type": "Feature",
  "properties": {
    "addr:full":"2525 W Co Rd C Saint Paul MN 55113",
    "addr:housenumber":"2525",
    "addr:postcode":"55113",
    "addr:street":"W Co Rd C",
    "iso:country":"US",
    "sg:address":"2525 W Co Rd C",
    "sg:city":"Saint Paul",
    "sg:classifiers":[
        {
            "category":"Building & Trades",
            "subcategory":"Construction",
            "type":"Services"
        }
    ],
    "sg:phone":"+1 651 638 3993",
    "sg:postcode":"55113",
    "sg:province":"MN",
    "sg:tags":[
        "hanging",
        "contractor"
    ],
    "wof:name":"McCloskeys Painting",
    "wof:placetype":"venue"
},
  "geometry": {"coordinates":[-93.207165,45.020658],"type":"Point"}
}