{
  "type": "Feature",
  "properties": {
    "iso:country":"US",
    "sg:address":"1992 N Adolphus St",
    "sg:city":"Saint Paul",
    "sg:classifiers":[
        {
            "category":"Shopping",
            "subcategory":"Gifts & Souvenirs",
            "type":"Retail Goods"
        }
    ],
    "sg:phone":"+1 651 489 4459",
    "sg:postcode":"55117",
    "sg:province":"MN",
    "wof:name":"Dinamite Creations",
    "wof:placetype":"venue"
},
  "geometry": {"coordinates":[-93.09205,45.001758],"type":"Point"}
}