{
  "type": "Feature",
  "properties": {
    "iso:country":"US",
    "sg:address":"857 E Belleview St",
    "sg:city":"Winona",
    "sg:classifiers":[
        {
            "category":"Professional",
            "subcategory":"Management & Consulting",
            "type":"Services"
        }
    ],
    "sg:phone":"+1 507 452 8841",
    "sg:postcode":"55987",
    "sg:province":"MN",
    "wof:name":"Neato",
    "wof:placetype":"venue"
},
  "geometry": {"coordinates":[-91.620481,44.038619],"type":"Point"}
}