{
  "type": "Feature",
  "properties": {
    "addr:full":"246 9th St Windom MN 56101",
    "addr:housenumber":"246",
    "addr:postcode":"56101",
    "addr:street":"9Th St",
    "iso:country":"US",
    "sg:address":"246 9th St",
    "sg:city":"Windom",
    "sg:classifiers":[
        {
            "category":"Banks & Credit Unions",
            "subcategory":"Investment Brokerage",
            "type":"Services"
        }
    ],
    "sg:phone":"+1 507 831 2027",
    "sg:postcode":"56101",
    "sg:province":"MN",
    "sg:tags":[
        "stock",
        "bond"
    ],
    "wof:name":"Edward Jones Co",
    "wof:placetype":"venue"
},
  "geometry": {"coordinates":[-95.115476,43.865488],"type":"Point"}
}