{
  "type": "Feature",
  "properties": {
    "iso:country":"US",
    "sg:address":"9325 Garland Ln N",
    "sg:city":"Osseo",
    "sg:classifiers":[
        {
            "category":"Real Estate",
            "subcategory":"Real Estate Operator",
            "type":"Services"
        }
    ],
    "sg:phone":"+1 763 391 6330",
    "sg:postcode":"55311",
    "sg:province":"MN",
    "sg:tags":[
        "building",
        "apartment"
    ],
    "wof:name":"Glen Arbor Apts",
    "wof:placetype":"venue"
},
  "geometry": {"coordinates":[-93.49534800000001,45.122088],"type":"Point"}
}