{
  "type": "Feature",
  "properties": {
    "iso:country":"US",
    "sg:address":"1700 Hwy 36 W",
    "sg:city":"Roseville",
    "sg:classifiers":[
        {
            "category":"Professional",
            "subcategory":"Lawyer & Legal Services",
            "type":"Services"
        }
    ],
    "sg:phone":"+1 651 636 2849",
    "sg:postcode":"55113",
    "sg:province":"MN",
    "sg:tags":[
        "attorney"
    ],
    "wof:name":"Attorney's Title Of Roseville",
    "wof:placetype":"venue"
},
  "geometry": {"coordinates":[-93.171706,45.010265],"type":"Point"}
}