{
  "type": "Feature",
  "properties": {
    "addr:full":"6824 Medicine Lake Rd Minneapolis MN 55427",
    "addr:housenumber":"6824",
    "addr:postcode":"55427",
    "addr:street":"Medicine Lake Rd",
    "iso:country":"US",
    "sg:address":"6824 Medicine Lake Rd",
    "sg:city":"Minneapolis",
    "sg:classifiers":[
        {
            "category":"Social Services",
            "subcategory":"Child Care",
            "type":"Services"
        }
    ],
    "sg:phone":"+1 763 544 4741",
    "sg:postcode":"55427",
    "sg:province":"MN",
    "sg:tags":[
        "daycare",
        "provider"
    ],
    "wof:name":"Marlene Howell",
    "wof:placetype":"venue"
},
  "geometry": {"coordinates":[-93.367529,45.007386],"type":"Point"}
}