{
  "type": "Feature",
  "properties": {
    "addr:full":"16245 Hwy 23 NE Spicer MN 56288",
    "addr:housenumber":"16245",
    "addr:postcode":"56288",
    "addr:street":"Hwy 23 Ne",
    "iso:country":"US",
    "sg:address":"16245 Hwy 23 NE",
    "sg:city":"Spicer",
    "sg:classifiers":[
        {
            "category":"Freight",
            "type":"Transportation"
        }
    ],
    "sg:phone":"+1 320 354 2148",
    "sg:postcode":"56288",
    "sg:province":"MN",
    "sg:tags":[
        "commercial",
        "storage"
    ],
    "wof:name":"Mini Storage Svc",
    "wof:placetype":"venue"
},
  "geometry": {"coordinates":[-94.942244,45.282032],"type":"Point"}
}