{
  "type": "Feature",
  "properties": {
    "addr:full":"15612 Highway 7 Ste 331 Minnetonka MN 55345",
    "addr:housenumber":"15612",
    "addr:postcode":"55345",
    "addr:street":"Highway 7 Ste 331",
    "iso:country":"US",
    "sg:address":"15612 Highway 7 Ste 331",
    "sg:city":"Minnetonka",
    "sg:classifiers":[
        {
            "category":"Shopping",
            "subcategory":"Gifts & Souvenirs",
            "type":"Retail Goods"
        },
        {
            "category":"Manufacturing",
            "subcategory":"Retail Goods",
            "type":"Manufacturing & Wholesale Goods"
        }
    ],
    "sg:phone":"+1 612 940 4008",
    "sg:postcode":"55345",
    "sg:province":"MN",
    "sg:tags":[
        "shop",
        "giftware's-wholesale",
        "manufacturer"
    ],
    "wof:name":"Santa Society, Llc , The",
    "wof:placetype":"venue"
},
  "geometry": {"coordinates":[-93.47911999999999,44.920258],"type":"Point"}
}