{
  "type": "Feature",
  "properties": {
    "addr:full":"17160 Sunrise Ave SW Prior Lake MN 55372",
    "addr:housenumber":"17160",
    "addr:postcode":"55372",
    "addr:street":"Sunrise Ave Sw Prior",
    "iso:country":"US",
    "sg:address":"17160 Sunrise Ave SW",
    "sg:city":"Prior Lake",
    "sg:classifiers":[
        {
            "category":"Building & Trades",
            "subcategory":"Construction",
            "type":"Services"
        }
    ],
    "sg:phone":"+1 952 440 7027",
    "sg:postcode":"55372",
    "sg:province":"MN",
    "sg:tags":[
        "hanging",
        "contractor"
    ],
    "wof:name":"GK Painting",
    "wof:placetype":"venue"
},
  "geometry": {"coordinates":[-93.45402199999999,44.700304],"type":"Point"}
}