{
  "type": "Feature",
  "properties": {
    "addr:full":"116 1st Ave NW Osseo MN 55369",
    "addr:housenumber":"116",
    "addr:postcode":"55369",
    "addr:street":"1St Ave Nw",
    "iso:country":"US",
    "sg:address":"116 1st Ave NW",
    "sg:city":"Osseo",
    "sg:classifiers":[
        {
            "category":"Banks & Credit Unions",
            "subcategory":"Bank",
            "type":"Services"
        }
    ],
    "sg:phone":"+1 763 391 0255",
    "sg:postcode":"55369",
    "sg:province":"MN",
    "sg:tags":[
        "depository",
        "banking"
    ],
    "wof:name":"PRP Trader",
    "wof:placetype":"venue"
},
  "geometry": {"coordinates":[-93.40364099999999,45.118009],"type":"Point"}
}