{
  "type": "Feature",
  "properties": {
    "iso:country":"US",
    "sg:address":"620 Main St S",
    "sg:city":"Sauk Centre",
    "sg:classifiers":[
        {
            "category":"Real Estate",
            "subcategory":"Real Estate Agent",
            "type":"Services"
        }
    ],
    "sg:phone":"+1 320 351 7653",
    "sg:postcode":"56378",
    "sg:province":"MN",
    "sg:website":"www.neighborhoodrealtyonline.com",
    "wof:name":"Neighborhood Realty",
    "wof:placetype":"venue"
},
  "geometry": {"coordinates":[-94.951939,45.733059],"type":"Point"}
}