{
  "type": "Feature",
  "properties": {
    "iso:country":"US",
    "sg:address":"11 W Central St",
    "sg:city":"Springfield",
    "sg:classifiers":[
        {
            "category":"Retail",
            "subcategory":"Portrait Studio",
            "type":"Services"
        }
    ],
    "sg:phone":"+1 507 723 5558",
    "sg:postcode":"56087",
    "sg:province":"MN",
    "sg:tags":[
        "photo"
    ],
    "wof:name":"Stassen Photography",
    "wof:placetype":"venue"
},
  "geometry": {"coordinates":[-94.97608,44.238888],"type":"Point"}
}