{
  "type": "Feature",
  "properties": {
    "addr:full":"150 Eaton St St Paul MN 55107",
    "addr:housenumber":"150",
    "addr:postcode":"55107",
    "addr:street":"Eaton St",
    "iso:country":"US",
    "sg:address":"150 Eaton St",
    "sg:city":"St Paul",
    "sg:classifiers":[
        {
            "category":"Manufacturing",
            "subcategory":"Tools & Machinery",
            "type":"Manufacturing & Wholesale Goods"
        }
    ],
    "sg:phone":"+1 651 227 3337",
    "sg:postcode":"55107",
    "sg:province":"MN",
    "sg:tags":[
        "physician",
        "surgeon"
    ],
    "wof:name":"Nova Medical Inc",
    "wof:placetype":"venue"
},
  "geometry": {"coordinates":[-93.07751500000001,44.935374],"type":"Point"}
}