{
  "type": "Feature",
  "properties": {
    "addr:full":"3345 Wyoming Ave S Minneapolis MN 55426",
    "addr:housenumber":"3345",
    "addr:postcode":"55426",
    "addr:street":"Wyoming Ave S",
    "iso:country":"US",
    "sg:address":"3345 Wyoming Ave S",
    "sg:city":"Minneapolis",
    "sg:classifiers":[
        {
            "category":"Social Services",
            "subcategory":"Child Care",
            "type":"Services"
        }
    ],
    "sg:phone":"+1 952 938 9135",
    "sg:postcode":"55426",
    "sg:province":"MN",
    "sg:tags":[
        "daycare",
        "provider"
    ],
    "wof:name":"Linda Erickson",
    "wof:placetype":"venue"
},
  "geometry": {"coordinates":[-93.384505,44.943021],"type":"Point"}
}