{
  "type": "Feature",
  "properties": {
    "addr:full":"14710 County 12 Blvd Zumbrota MN 55992",
    "addr:housenumber":"14710",
    "addr:postcode":"55992",
    "addr:street":"County 12 Blvd",
    "iso:country":"US",
    "sg:address":"14710 County 12 Blvd",
    "sg:city":"Zumbrota",
    "sg:phone":"+1 507 732 7039",
    "sg:postcode":"55992",
    "sg:province":"MN",
    "sg:tags":[
        "farm",
        "corn"
    ],
    "wof:name":"Norris Bjorngaard",
    "wof:placetype":"venue"
},
  "geometry": {"coordinates":[-92.738021,44.260969],"type":"Point"}
}