{
  "type": "Feature",
  "properties": {
    "addr:full":"4327 Fox Ridge Ct Saint Paul MN 55122",
    "addr:housenumber":"4327",
    "addr:postcode":"55122",
    "addr:street":"Fox Ridge Ct",
    "iso:country":"US",
    "sg:address":"4327 Fox Ridge Ct",
    "sg:city":"Saint Paul",
    "sg:classifiers":[
        {
            "category":"Home & Garden",
            "subcategory":"Carpets & Floor Coverings",
            "type":"Retail Goods"
        }
    ],
    "sg:phone":"+1 651 405 8371",
    "sg:postcode":"55122",
    "sg:province":"MN",
    "wof:name":"Metro Carpet Outlet",
    "wof:placetype":"venue"
},
  "geometry": {"coordinates":[-93.199477,44.797889],"type":"Point"}
}