{
  "type": "Feature",
  "properties": {
    "iso:country":"US",
    "sg:address":"30103 US Hwy 71",
    "sg:city":"Redwood Falls",
    "sg:classifiers":[
        {
            "category":"Building & Trades",
            "subcategory":"Construction",
            "type":"Services"
        }
    ],
    "sg:phone":"+1 507 644 5596",
    "sg:postcode":"56283",
    "sg:province":"MN",
    "sg:tags":[
        "excavating",
        "contractor"
    ],
    "wof:name":"Schmidt Construction",
    "wof:placetype":"venue"
},
  "geometry": {"coordinates":[-95.117553,44.485387],"type":"Point"}
}