{
  "type": "Feature",
  "properties": {
    "iso:country":"US",
    "sg:address":"108 Marty Dr Ste 1",
    "sg:city":"Buffalo",
    "sg:classifiers":[
        {
            "category":"Organizations",
            "subcategory":"Professional Association",
            "type":"Services"
        }
    ],
    "sg:phone":"+1 763 682 2171",
    "sg:postcode":"55313",
    "sg:province":"MN",
    "sg:tags":[
        "business",
        "trade"
    ],
    "sg:website":"http://www.minnesotaturkeys.com",
    "wof:name":"Minnesota Turkey Growers Assoc",
    "wof:placetype":"venue"
},
  "geometry": {"coordinates":[-93.873453,45.192922],"type":"Point"}
}