{
  "type": "Feature",
  "properties": {
    "addr:full":"318 4th St NW Faribault MN 55021",
    "addr:housenumber":"318",
    "addr:postcode":"55021",
    "addr:street":"4Th St Nw",
    "iso:country":"US",
    "sg:address":"318 4th St NW",
    "sg:city":"Faribault",
    "sg:classifiers":[
        {
            "category":"Banks & Credit Unions",
            "subcategory":"Investment Brokerage",
            "type":"Services"
        }
    ],
    "sg:phone":"+1 507 332 2957",
    "sg:postcode":"55021",
    "sg:province":"MN",
    "sg:tags":[
        "security"
    ],
    "wof:name":"Edward Jones Co",
    "wof:placetype":"venue"
},
  "geometry": {"coordinates":[-93.274445,44.294779],"type":"Point"}
}