{
  "type": "Feature",
  "properties": {
    "addr:full":"20941 Edwards Ave Adrian MN 56110",
    "addr:housenumber":"20941",
    "addr:postcode":"56110",
    "addr:street":"Edwards Ave",
    "iso:country":"US",
    "sg:address":"20941 Edwards Ave",
    "sg:city":"Adrian",
    "sg:classifiers":[
        {
            "category":"Farming",
            "subcategory":"Livestock Farm",
            "type":"Manufacturing & Wholesale Goods"
        }
    ],
    "sg:phone":"+1 507 483 2555",
    "sg:postcode":"56110",
    "sg:province":"MN",
    "sg:tags":[
        "beef",
        "feedlot",
        "cattle"
    ],
    "wof:name":"Mark Hodapp",
    "wof:placetype":"venue"
},
  "geometry": {"coordinates":[-95.873103,43.689237],"type":"Point"}
}