{
  "type": "Feature",
  "properties": {
    "iso:country":"US",
    "sg:address":"813 W 36th St",
    "sg:city":"Minneapolis",
    "sg:classifiers":[
        {
            "category":"Restaurant",
            "type":"Food & Drink"
        }
    ],
    "sg:phone":"+1 612 825 3718",
    "sg:postcode":"55408",
    "sg:province":"MN",
    "sg:tags":[
        "breakfast",
        "brunch"
    ],
    "wof:name":"Our Kitchen",
    "wof:placetype":"venue"
},
  "geometry": {"coordinates":[-93.289902,44.937599],"type":"Point"}
}