{
  "type": "Feature",
  "properties": {
    "iso:country":"US",
    "sg:address":"4484 Chestnut Ln NE",
    "sg:city":"Prior Lake",
    "sg:classifiers":[
        {
            "category":"Professional",
            "subcategory":"Computer Services",
            "type":"Services"
        }
    ],
    "sg:phone":"+1 952 445 4361",
    "sg:postcode":"55372",
    "sg:province":"MN",
    "sg:tags":[
        "related"
    ],
    "wof:name":"Fetter Consulting Inc",
    "wof:placetype":"venue"
},
  "geometry": {"coordinates":[-93.43005599999999,44.737841],"type":"Point"}
}