{
  "type": "Feature",
  "properties": {
    "iso:country":"US",
    "sg:address":"240 Morgan Ave N",
    "sg:city":"Minneapolis",
    "sg:classifiers":[
        {
            "category":"Organizations",
            "subcategory":"Religious Organization",
            "type":"Services"
        }
    ],
    "sg:phone":"+1 612 287 8870",
    "sg:postcode":"55405",
    "sg:province":"MN",
    "sg:tags":[
        "church"
    ],
    "wof:name":"Pentecostal Assembly",
    "wof:placetype":"venue"
},
  "geometry": {"coordinates":[-93.30450399999999,44.979797],"type":"Point"}
}