{
  "type": "Feature",
  "properties": {
    "addr:full":"4416 Minnehaha Ave Minneapolis MN 55406",
    "addr:housenumber":"4416",
    "addr:postcode":"55406",
    "addr:street":"Minnehaha Ave",
    "iso:country":"US",
    "sg:address":"4416 Minnehaha Ave",
    "sg:city":"Minneapolis",
    "sg:classifiers":[
        {
            "category":"Professional",
            "subcategory":"Business Services",
            "type":"Services"
        }
    ],
    "sg:phone":"+1 612 722 2062",
    "sg:postcode":"55406",
    "sg:province":"MN",
    "sg:tags":[
        "estate"
    ],
    "wof:name":"Lyle Davis Assoc Estate & Mvng",
    "wof:placetype":"venue"
},
  "geometry": {"coordinates":[-93.216013,44.921815],"type":"Point"}
}