{
  "type": "Feature",
  "properties": {
    "addr:full":"521 Grant Ave Mankato MN 56003",
    "addr:housenumber":"521",
    "addr:postcode":"56003",
    "addr:street":"Grant Ave",
    "iso:country":"US",
    "sg:address":"521 Grant Ave",
    "sg:city":"Mankato",
    "sg:classifiers":[
        {
            "category":"Building & Trades",
            "subcategory":"Cleaning & Sanitation",
            "type":"Services"
        }
    ],
    "sg:phone":"+1 507 345 5395",
    "sg:postcode":"56003",
    "sg:province":"MN",
    "sg:tags":[
        "janitor",
        "maintenance"
    ],
    "wof:name":"Premium Commercial Services",
    "wof:placetype":"venue"
},
  "geometry": {"coordinates":[-94.014155,44.172702],"type":"Point"}
}