{
  "type": "Feature",
  "properties": {
    "addr:full":"6292 Petrie Ct NW Bemidji MN 56601",
    "addr:housenumber":"6292",
    "addr:postcode":"56601",
    "addr:street":"Petrie Ct Nw",
    "iso:country":"US",
    "sg:address":"6292 Petrie Ct NW",
    "sg:city":"Bemidji",
    "sg:classifiers":[
        {
            "category":"Building & Trades",
            "subcategory":"Plumbing",
            "type":"Services"
        }
    ],
    "sg:phone":"+1 218 759 7000",
    "sg:postcode":"56601",
    "sg:province":"MN",
    "sg:tags":[
        "heating",
        "contractor"
    ],
    "wof:name":"H & R Heating & Air Cond Inc",
    "wof:placetype":"venue"
},
  "geometry": {"coordinates":[-94.96122,47.613859],"type":"Point"}
}