{
  "type": "Feature",
  "properties": {
    "addr:full":"17751 Hwy 23 NE New London MN 56273",
    "addr:housenumber":"17751",
    "addr:postcode":"56273",
    "addr:street":"Hwy 23 Ne",
    "iso:country":"US",
    "sg:address":"17751 Hwy 23 NE",
    "sg:city":"New London",
    "sg:classifiers":[
        {
            "category":"Health Services",
            "subcategory":"Doctor",
            "type":"Services"
        }
    ],
    "sg:phone":"+1 320 354 4199",
    "sg:postcode":"56273",
    "sg:province":"MN",
    "sg:tags":[
        "medical"
    ],
    "wof:name":"Allergy Asthma Clnc Stvns Cmty",
    "wof:placetype":"venue"
},
  "geometry": {"coordinates":[-94.925298,45.297379],"type":"Point"}
}