{
  "type": "Feature",
  "properties": {
    "iso:country":"US",
    "sg:address":"4010 Shoreline Dr",
    "sg:city":"Spring Park",
    "sg:classifiers":[
        {
            "category":"Wholesale",
            "subcategory":"Machinery & Supplies",
            "type":"Manufacturing & Wholesale Goods"
        }
    ],
    "sg:phone":"+1 952 471 9641",
    "sg:postcode":"55384",
    "sg:province":"MN",
    "sg:tags":[
        "equipment",
        "hydraulic"
    ],
    "wof:name":"Tritec Marketing Co",
    "wof:placetype":"venue"
},
  "geometry": {"coordinates":[-93.625495,44.935006],"type":"Point"}
}