{
  "type": "Feature",
  "properties": {
    "iso:country":"US",
    "sg:address":"2097 Larpenteur Ave W",
    "sg:city":"Saint Paul",
    "sg:classifiers":[
        {
            "category":"Museum",
            "type":"Entertainment"
        }
    ],
    "sg:phone":"+1 651 646 8629",
    "sg:postcode":"55113",
    "sg:province":"MN",
    "sg:website":"www.rchs.com",
    "wof:name":"Gibbs Museum of Pioneer and Dakotah Life",
    "wof:placetype":"venue"
},
  "geometry": {"coordinates":[-93.190399,44.9916],"type":"Point"}
}