{
  "type": "Feature",
  "properties": {
    "iso:country":"US",
    "sg:address":"209 International Dr",
    "sg:city":"Red Lake Falls",
    "sg:classifiers":[
        {
            "category":"Real Estate",
            "subcategory":"Real Estate Operator",
            "type":"Services"
        }
    ],
    "sg:phone":"+1 218 253 2022",
    "sg:postcode":"56750",
    "sg:province":"MN",
    "sg:tags":[
        "building",
        "residential",
        "apartment",
        "care"
    ],
    "wof:name":"Housing Rdvelopment Authorithy",
    "wof:placetype":"venue"
},
  "geometry": {"coordinates":[-96.27874300000001,47.875052],"type":"Point"}
}