{
  "type": "Feature",
  "properties": {
    "addr:full":"9378 Preserve Trl Saint Paul MN 55125",
    "addr:housenumber":"9378",
    "addr:postcode":"55125",
    "addr:street":"Preserve Trl",
    "iso:country":"US",
    "sg:address":"9378 Preserve Trl",
    "sg:city":"Saint Paul",
    "sg:classifiers":[
        {
            "category":"Real Estate",
            "subcategory":"Real Estate Operator",
            "type":"Services"
        }
    ],
    "sg:phone":"+1 651 735 8884",
    "sg:postcode":"55125",
    "sg:province":"MN",
    "sg:tags":[
        "building",
        "nonresidential"
    ],
    "wof:name":"Casci Properties",
    "wof:placetype":"venue"
},
  "geometry": {"coordinates":[-92.915983,44.940043],"type":"Point"}
}