{
  "type": "Feature",
  "properties": {
    "addr:full":"402 55th St SW Montrose MN 55363",
    "addr:housenumber":"402",
    "addr:postcode":"55363",
    "addr:street":"55Th St Sw",
    "iso:country":"US",
    "sg:address":"402 55th St SW",
    "sg:city":"Montrose",
    "sg:phone":"+1 763 675 3613",
    "sg:postcode":"55363",
    "sg:province":"MN",
    "sg:tags":[
        "farm",
        "corn",
        "soybean"
    ],
    "wof:name":"Roger Johnson",
    "wof:placetype":"venue"
},
  "geometry": {"coordinates":[-93.903108,45.072237],"type":"Point"}
}