{
  "type": "Feature",
  "properties": {
    "addr:full":"44739 Yellow Pine Dr Perham MN 56573",
    "addr:housenumber":"44739",
    "addr:postcode":"56573",
    "addr:street":"Yellow Pine Dr",
    "iso:country":"US",
    "sg:address":"44739 Yellow Pine Dr",
    "sg:city":"Perham",
    "sg:classifiers":[
        {
            "category":"Professional",
            "type":"Services"
        }
    ],
    "sg:phone":"+1 218 346 6627",
    "sg:postcode":"56573",
    "sg:province":"MN",
    "sg:tags":[
        "establishment"
    ],
    "wof:name":"Schmidt & Schmidt",
    "wof:placetype":"venue"
},
  "geometry": {"coordinates":[-95.564245,46.61801],"type":"Point"}
}