{
  "type": "Feature",
  "properties": {
    "iso:country":"US",
    "sg:address":"6408 Willow Ln",
    "sg:city":"Minneapolis",
    "sg:classifiers":[
        {
            "category":"Professional",
            "subcategory":"Lawyer & Legal Services",
            "type":"Services"
        }
    ],
    "sg:phone":"+1 763 560 2122",
    "sg:postcode":"55430",
    "sg:province":"MN",
    "wof:name":"Suburban Middle Income Legal",
    "wof:placetype":"venue"
},
  "geometry": {"coordinates":[-93.284176,45.071141],"type":"Point"}
}