{
  "type": "Feature",
  "properties": {
    "addr:full":"9405 Medicine Lake Rd Golden Valley MN 55427",
    "addr:housenumber":"9405",
    "addr:postcode":"55427",
    "addr:street":"Medicine Lake Rd",
    "iso:country":"US",
    "sg:address":"9405 Medicine Lake Rd",
    "sg:city":"Golden Valley",
    "sg:classifiers":[
        {
            "category":"Autos & Motor Vehicles",
            "subcategory":"Fuel & Gas Station",
            "type":"Retail Goods"
        }
    ],
    "sg:phone":"+1 763 545 9001",
    "sg:postcode":"55427",
    "sg:province":"MN",
    "sg:tags":[
        "oil"
    ],
    "wof:name":"Medicine Lake Winner",
    "wof:placetype":"venue"
},
  "geometry": {"coordinates":[-93.39924600000001,45.007392],"type":"Point"}
}