{
  "type": "Feature",
  "properties": {
    "addr:full":"22083 Goodwill Dr Long Prairie MN 56347",
    "addr:postcode":"22083;56347",
    "addr:street":"Goodwill Dr",
    "iso:country":"US",
    "sg:address":"22083 Goodwill Dr",
    "sg:city":"Long Prairie",
    "sg:classifiers":[
        {
            "category":"Personal",
            "subcategory":"Beauty Salon",
            "type":"Services"
        }
    ],
    "sg:phone":"+1 320 732 2348",
    "sg:postcode":"56347",
    "sg:province":"MN",
    "wof:name":"New Image Hair Salon",
    "wof:placetype":"venue"
},
  "geometry": {"coordinates":[-94.879124,45.947794],"type":"Point"}
}