{
  "type": "Feature",
  "properties": {
    "addr:full":"2 Carlson Pkwy N Minneapolis MN 55447",
    "addr:housenumber":"2",
    "addr:postcode":"55447",
    "addr:street":"Carlson Pkwy N",
    "iso:country":"US",
    "sg:address":"2 Carlson Pkwy N",
    "sg:city":"Minneapolis",
    "sg:classifiers":[
        {
            "category":"Insurance",
            "subcategory":"Hazard Insurance",
            "type":"Services"
        }
    ],
    "sg:phone":"+1 763 249 2388",
    "sg:postcode":"55447",
    "sg:province":"MN",
    "sg:tags":[
        "credit"
    ],
    "wof:name":"Euler A C I",
    "wof:placetype":"venue"
},
  "geometry": {"coordinates":[-93.46302799999999,44.981533],"type":"Point"}
}