{
  "type": "Feature",
  "properties": {
    "addr:full":"25341 Island Lake Rd Cold Spring MN 56320",
    "addr:housenumber":"25341",
    "addr:postcode":"56320",
    "addr:street":"Island Lake Rd",
    "iso:country":"US",
    "sg:address":"25341 Island Lake Rd",
    "sg:city":"Cold Spring",
    "sg:classifiers":[
        {
            "category":"Farming",
            "subcategory":"Dairy Farm",
            "type":"Manufacturing & Wholesale Goods"
        }
    ],
    "sg:phone":"+1 320 685 8446",
    "sg:postcode":"56320",
    "sg:province":"MN",
    "wof:name":"Blonigen Farm",
    "wof:placetype":"venue"
},
  "geometry": {"coordinates":[-94.40458599999999,45.489516],"type":"Point"}
}