{
  "type": "Feature",
  "properties": {
    "addr:full":"500 2nd St Barrett MN 56311",
    "addr:housenumber":"500",
    "addr:postcode":"56311",
    "addr:street":"2Nd St",
    "iso:country":"US",
    "sg:address":"500 2nd St",
    "sg:city":"Barrett",
    "sg:classifiers":[
        {
            "category":"Government",
            "subcategory":"Fire Station",
            "type":"Public Place"
        }
    ],
    "sg:phone":"+1 320 528 6660",
    "sg:postcode":"56311",
    "sg:province":"MN",
    "sg:tags":[
        "department"
    ],
    "wof:name":"Barrett Fire Hall",
    "wof:placetype":"venue"
},
  "geometry": {"coordinates":[-95.88960899999999,45.9098],"type":"Point"}
}