{
  "type": "Feature",
  "properties": {
    "addr:full":"3005 37th Ave NE Minneapolis MN 55421",
    "addr:housenumber":"3005",
    "addr:postcode":"55421",
    "addr:street":"37Th Ave Ne",
    "iso:country":"US",
    "sg:address":"3005 37th Ave NE",
    "sg:city":"Minneapolis",
    "sg:classifiers":[
        {
            "category":"Retail",
            "subcategory":"Laundry & Dry Cleaning",
            "type":"Services"
        }
    ],
    "sg:phone":"+1 612 788 0547",
    "sg:postcode":"55421",
    "sg:province":"MN",
    "wof:name":"St Anthony Cleaners & Launderers Ltd",
    "wof:placetype":"venue"
},
  "geometry": {"coordinates":[-93.217499,45.035801],"type":"Point"}
}