{
  "type": "Feature",
  "properties": {
    "addr:full":"915 6th Ave NE Buffalo MN 55313",
    "addr:housenumber":"915",
    "addr:postcode":"55313",
    "addr:street":"6Th Ave Ne",
    "iso:country":"US",
    "sg:address":"915 6th Ave NE",
    "sg:city":"Buffalo",
    "sg:classifiers":[
        {
            "category":"Real Estate",
            "subcategory":"Real Estate Operator",
            "type":"Services"
        }
    ],
    "sg:phone":"+1 763 684 1888",
    "sg:postcode":"55313",
    "sg:province":"MN",
    "sg:tags":[
        "building",
        "apartment"
    ],
    "wof:name":"Evergreen Square",
    "wof:placetype":"venue"
},
  "geometry": {"coordinates":[-93.86814099999999,45.181155],"type":"Point"}
}