{
  "type": "Feature",
  "properties": {
    "iso:country":"US",
    "sg:address":"6737 Camden Ave N",
    "sg:city":"Minneapolis",
    "sg:classifiers":[
        {
            "category":"Shopping",
            "type":"Retail Goods"
        }
    ],
    "sg:phone":"+1 763 560 4959",
    "sg:postcode":"55430",
    "sg:province":"MN",
    "sg:tags":[
        "plant",
        "flower",
        "tree",
        "artificial"
    ],
    "wof:name":"Silk Garden",
    "wof:placetype":"venue"
},
  "geometry": {"coordinates":[-93.2899,45.077504],"type":"Point"}
}