{
  "type": "Feature",
  "properties": {
    "addr:full":"6710 Garfield Ave S Minneapolis MN 55423",
    "addr:housenumber":"6710",
    "addr:postcode":"55423",
    "addr:street":"Garfield Ave S",
    "iso:country":"US",
    "sg:address":"6710 Garfield Ave S",
    "sg:city":"Minneapolis",
    "sg:classifiers":[
        {
            "category":"Manufacturing",
            "subcategory":"Printing",
            "type":"Manufacturing & Wholesale Goods"
        }
    ],
    "sg:phone":"+1 612 861 1991",
    "sg:postcode":"55423",
    "sg:province":"MN",
    "sg:tags":[
        "multimedia"
    ],
    "wof:name":"Rickert Media",
    "wof:placetype":"venue"
},
  "geometry": {"coordinates":[-93.286332,44.881201],"type":"Point"}
}