{
  "type": "Feature",
  "properties": {
    "addr:full":"86798 527 St Buffalo Lake MN 55314",
    "addr:housenumber":"86798",
    "addr:postcode":"55314",
    "addr:street":"527 St",
    "iso:country":"US",
    "sg:address":"86798 527 St",
    "sg:city":"Buffalo Lake",
    "sg:classifiers":[
        {
            "category":"Farming",
            "subcategory":"Farm",
            "type":"Manufacturing & Wholesale Goods"
        }
    ],
    "sg:phone":"+1 320 833 2339",
    "sg:postcode":"55314",
    "sg:province":"MN",
    "sg:tags":[
        "crop",
        "general"
    ],
    "wof:name":"Bob Richards",
    "wof:placetype":"venue"
},
  "geometry": {"coordinates":[-94.615287,44.769375],"type":"Point"}
}