{
  "type": "Feature",
  "properties": {
    "iso:country":"US",
    "sg:address":"1565 82nd St W",
    "sg:city":"Inver Grove Hts",
    "sg:classifiers":[
        {
            "category":"Professional",
            "subcategory":"Accounting & Tax Preparation",
            "type":"Services"
        }
    ],
    "sg:phone":"+1 651 688 8141",
    "sg:postcode":"55077",
    "sg:province":"MN",
    "sg:tags":[
        "accountant"
    ],
    "wof:name":"Steven A Doyle LTD",
    "wof:placetype":"venue"
},
  "geometry": {"coordinates":[-93.099964,44.830003],"type":"Point"}
}