{
  "type": "Feature",
  "properties": {
    "iso:country":"US",
    "sg:address":"209 2nd St E",
    "sg:city":"Thief River Fls",
    "sg:classifiers":[
        {
            "category":"Personal",
            "subcategory":"Beauty Salon",
            "type":"Services"
        }
    ],
    "sg:phone":"+1 218 681 5330",
    "sg:postcode":"56701",
    "sg:province":"MN",
    "sg:tags":[
        "shop"
    ],
    "wof:name":"Stylon Chateau Beauty Salon",
    "wof:placetype":"venue"
},
  "geometry": {"coordinates":[-96.179903,48.118144],"type":"Point"}
}