{
  "type": "Feature",
  "properties": {
    "addr:full":"4009 Minnehaha Ave Minneapolis MN 55406",
    "addr:housenumber":"4009",
    "addr:postcode":"55406",
    "addr:street":"Minnehaha Ave",
    "iso:country":"US",
    "sg:address":"4009 Minnehaha Ave",
    "sg:city":"Minneapolis",
    "sg:classifiers":[
        {
            "category":"Professional",
            "subcategory":"Art Services",
            "type":"Services"
        }
    ],
    "sg:phone":"+1 612 729 1649",
    "sg:postcode":"55406",
    "sg:province":"MN",
    "sg:tags":[
        "design",
        "graphic",
        "printing",
        "commercial"
    ],
    "wof:name":"Visual Expressions",
    "wof:placetype":"venue"
},
  "geometry": {"coordinates":[-93.22054199999999,44.929772],"type":"Point"}
}