{
  "type": "Feature",
  "properties": {
    "iso:country":"US",
    "sg:address":"1600 Miller Trunk Hwy Ste 108",
    "sg:city":"Duluth",
    "sg:classifiers":[
        {
            "category":"Shopping",
            "subcategory":"Hobbies, Toys, & Games",
            "type":"Retail Goods"
        }
    ],
    "sg:phone":"+1 218 726 1360",
    "sg:postcode":"55811",
    "sg:province":"MN",
    "sg:tags":[
        "shop",
        "hobby",
        "model",
        "coin",
        "supply"
    ],
    "wof:name":"Collector's Connection",
    "wof:placetype":"venue"
},
  "geometry": {"coordinates":[-92.160721,46.806591],"type":"Point"}
}