{
  "type": "Feature",
  "properties": {
    "iso:country":"US",
    "sg:address":"522 Shadyway Rd",
    "sg:city":"Wayzata",
    "sg:classifiers":[
        {
            "category":"Health Services",
            "subcategory":"Nursing And Care Facility",
            "type":"Services"
        },
        {
            "category":"Social Services",
            "subcategory":"Retirement Home",
            "type":"Services"
        }
    ],
    "sg:phone":"+1 952 475 0205",
    "sg:postcode":"55391",
    "sg:province":"MN",
    "sg:tags":[
        "living",
        "assisted",
        "homes-intermediate"
    ],
    "wof:name":"Shadyway Group Home",
    "wof:placetype":"venue"
},
  "geometry": {"coordinates":[-93.50242799999999,44.977674],"type":"Point"}
}