{
  "type": "Feature",
  "properties": {
    "addr:full":"8483 27th St N Lake Elmo MN 55042",
    "addr:housenumber":"8483",
    "addr:postcode":"55042",
    "addr:street":"27Th St N",
    "iso:country":"US",
    "sg:address":"8483 27th St N",
    "sg:city":"Lake Elmo",
    "sg:classifiers":[
        {
            "category":"Professional",
            "subcategory":"Business Services",
            "type":"Services"
        }
    ],
    "sg:phone":"+1 651 407 0430",
    "sg:postcode":"55042",
    "sg:province":"MN",
    "wof:name":"Professional Transcription",
    "wof:placetype":"venue"
},
  "geometry": {"coordinates":[-92.934422,44.988213],"type":"Point"}
}