{
  "type": "Feature",
  "properties": {
    "addr:full":"6480 Carlson Dr Eden Prairie MN 55346",
    "addr:housenumber":"6480",
    "addr:postcode":"55346",
    "addr:street":"Carlson Dr",
    "iso:country":"US",
    "sg:address":"6480 Carlson Dr",
    "sg:city":"Eden Prairie",
    "sg:classifiers":[
        {
            "category":"Retail",
            "subcategory":"Auto Repair",
            "type":"Services"
        }
    ],
    "sg:phone":"+1 952 949 9633",
    "sg:postcode":"55346",
    "sg:province":"MN",
    "wof:name":"Terry's Automotive",
    "wof:placetype":"venue"
},
  "geometry": {"coordinates":[-93.455704,44.888302],"type":"Point"}
}