{
  "type": "Feature",
  "properties": {
    "addr:full":"13783 Ibis St NW Ste 600 Andover MN 55304",
    "addr:housenumber":"13783",
    "addr:postcode":"55304",
    "addr:street":"Ibis St Nw Ste 600",
    "iso:country":"US",
    "sg:address":"13783 Ibis St NW Ste 600",
    "sg:city":"Andover",
    "sg:classifiers":[
        {
            "category":"Arts & Performance",
            "subcategory":"Arts Center",
            "type":"Entertainment"
        }
    ],
    "sg:phone":"+1 763 433 9332",
    "sg:postcode":"55304",
    "sg:province":"MN",
    "sg:tags":[
        "performing"
    ],
    "wof:name":"Dancin'feet",
    "wof:placetype":"venue"
},
  "geometry": {"coordinates":[-93.309724,45.220701],"type":"Point"}
}