{
  "type": "Feature",
  "properties": {
    "addr:full":"63696 315th St Litchfield MN 55355",
    "addr:housenumber":"63696",
    "addr:postcode":"55355",
    "addr:street":"315Th St",
    "iso:country":"US",
    "sg:address":"63696 315th St",
    "sg:city":"Litchfield",
    "sg:classifiers":[
        {
            "category":"Building & Trades",
            "subcategory":"Construction",
            "type":"Services"
        }
    ],
    "sg:phone":"+1 320 857 2130",
    "sg:postcode":"55355",
    "sg:province":"MN",
    "sg:tags":[
        "house"
    ],
    "wof:name":"Randy Werner Construction",
    "wof:placetype":"venue"
},
  "geometry": {"coordinates":[-94.49211099999999,45.203215],"type":"Point"}
}