{
  "type": "Feature",
  "properties": {
    "iso:country":"US",
    "sg:address":"2567 Emerald Dr",
    "sg:city":"Mound",
    "sg:classifiers":[
        {
            "category":"Professional",
            "type":"Services"
        }
    ],
    "sg:phone":"+1 952 472 8197",
    "sg:postcode":"55364",
    "sg:province":"MN",
    "wof:name":"Katosoft LLC",
    "wof:placetype":"venue"
},
  "geometry": {"coordinates":[-93.653837,44.930601],"type":"Point"}
}