{
  "type": "Feature",
  "properties": {
    "addr:full":"5001 160th St W Rosemount MN 55068",
    "addr:housenumber":"5001",
    "addr:postcode":"55068",
    "addr:street":"160Th St W",
    "iso:country":"US",
    "sg:address":"5001 160th St W",
    "sg:city":"Rosemount",
    "sg:classifiers":[
        {
            "category":"Building & Trades",
            "subcategory":"Construction",
            "type":"Services"
        }
    ],
    "sg:phone":"+1 952 322 5959",
    "sg:postcode":"55068",
    "sg:province":"MN",
    "sg:tags":[
        "highway"
    ],
    "wof:name":"Midwest Concrete Specialties",
    "wof:placetype":"venue"
},
  "geometry": {"coordinates":[-93.17245200000001,44.717423],"type":"Point"}
}