{
  "type": "Feature",
  "properties": {
    "iso:country":"US",
    "sg:address":"211 E Clark St",
    "sg:city":"Albert Lea",
    "sg:classifiers":[
        {
            "category":"Building & Trades",
            "subcategory":"Cleaning & Sanitation",
            "type":"Services"
        },
        {
            "category":"Building & Trades",
            "subcategory":"Construction",
            "type":"Services"
        }
    ],
    "sg:phone":"+1 507 373 5224",
    "sg:postcode":"56007",
    "sg:province":"MN",
    "sg:tags":[
        "maintenance",
        "contractor"
    ],
    "wof:name":"Edgewater Park Maintence Bldg",
    "wof:placetype":"venue"
},
  "geometry": {"coordinates":[-93.367272,43.649825],"type":"Point"}
}