{
  "type": "Feature",
  "properties": {
    "iso:country":"US",
    "sg:address":"470 S 1st Ave",
    "sg:city":"Isanti",
    "sg:classifiers":[
        {
            "category":"Professional",
            "type":"Services"
        }
    ],
    "sg:phone":"+1 763 444 5861",
    "sg:postcode":"55040",
    "sg:province":"MN",
    "sg:tags":[
        "establishment"
    ],
    "wof:name":"Tractech",
    "wof:placetype":"venue"
},
  "geometry": {"coordinates":[-93.248706,45.487497],"type":"Point"}
}