{
  "type": "Feature",
  "properties": {
    "iso:country":"US",
    "sg:address":"2300 E 88th St",
    "sg:city":"Minneapolis",
    "sg:classifiers":[
        {
            "category":"Organizations",
            "subcategory":"Religious Organization",
            "type":"Services"
        }
    ],
    "sg:phone":"+1 952 854 5030",
    "sg:postcode":"55425",
    "sg:province":"MN",
    "sg:tags":[
        "christ",
        "churches-community"
    ],
    "sg:website":"www.peopleofpraise.org",
    "wof:name":"People Of Praise Christian Com",
    "wof:placetype":"venue"
},
  "geometry": {"coordinates":[-93.240488,44.844978],"type":"Point"}
}