{
  "type": "Feature",
  "properties": {
    "addr:full":"14283 225th Ave NE Hawick MN 56273",
    "addr:housenumber":"14283",
    "addr:postcode":"56273",
    "addr:street":"225Th Ave Ne",
    "iso:country":"US",
    "sg:address":"14283 225th Ave NE",
    "sg:city":"Hawick",
    "sg:classifiers":[
        {
            "category":"Building & Trades",
            "subcategory":"Construction",
            "type":"Services"
        },
        {
            "category":"Building & Trades",
            "subcategory":"Plumbing",
            "type":"Services"
        }
    ],
    "sg:phone":"+1 320 354 4823",
    "sg:postcode":"56273",
    "sg:province":"MN",
    "sg:tags":[
        "excavation",
        "tank",
        "septic",
        "contractor"
    ],
    "wof:name":"Strictly Dirt Excavating",
    "wof:placetype":"venue"
},
  "geometry": {"coordinates":[-94.84654500000001,45.340671],"type":"Point"}
}