{
  "type": "Feature",
  "properties": {
    "addr:full":"14730 15th St SW Cokato MN 55321",
    "addr:housenumber":"14730",
    "addr:postcode":"55321",
    "addr:street":"15Th St Sw",
    "iso:country":"US",
    "sg:address":"14730 15th St SW",
    "sg:city":"Cokato",
    "sg:classifiers":[
        {
            "category":"Wholesale",
            "subcategory":"Farm Supplies",
            "type":"Manufacturing & Wholesale Goods"
        }
    ],
    "sg:phone":"+1 320 286 5188",
    "sg:postcode":"55321",
    "sg:province":"MN",
    "wof:name":"Kevin Dahlman",
    "wof:placetype":"venue"
},
  "geometry": {"coordinates":[-94.190021,45.13043],"type":"Point"}
}