{
  "type": "Feature",
  "properties": {
    "iso:country":"US",
    "sg:address":"6102 Olson Memorial Hwy",
    "sg:city":"Golden Valley",
    "sg:classifiers":[
        {
            "category":"Wholesale",
            "subcategory":"Machinery & Supplies",
            "type":"Manufacturing & Wholesale Goods"
        }
    ],
    "sg:phone":"+1 763 542 2565",
    "sg:postcode":"55422",
    "sg:province":"MN",
    "sg:tags":[
        "equipment",
        "carpet",
        "establishment",
        "cleaning",
        "rug"
    ],
    "wof:name":"Northland Cleaning Products",
    "wof:placetype":"venue"
},
  "geometry": {"coordinates":[-93.360214,44.984671],"type":"Point"}
}