{
  "type": "Feature",
  "properties": {
    "addr:full":"325 Alliance Pl Rochester MN 55906",
    "addr:housenumber":"325",
    "addr:postcode":"55906",
    "addr:street":"Alliance Pl",
    "iso:country":"US",
    "sg:address":"325 Alliance Pl",
    "sg:city":"Rochester",
    "sg:classifiers":[
        {
            "category":"Building & Trades",
            "subcategory":"Construction",
            "type":"Services"
        }
    ],
    "sg:phone":"+1 507 536 4515",
    "sg:postcode":"55906",
    "sg:province":"MN",
    "sg:tags":[
        "concrete",
        "work"
    ],
    "wof:name":"Stone Skirt",
    "wof:placetype":"venue"
},
  "geometry": {"coordinates":[-92.457967,44.060933],"type":"Point"}
}