{
  "type": "Feature",
  "properties": {
    "iso:country":"US",
    "sg:address":"415 W 3rd St",
    "sg:city":"Red Wing",
    "sg:classifiers":[
        {
            "category":"Shopping",
            "subcategory":"Computers & Home Electronics",
            "type":"Retail Goods"
        }
    ],
    "sg:phone":"+1 651 388 9629",
    "sg:postcode":"55066",
    "sg:province":"MN",
    "wof:name":"Radio Shack",
    "wof:placetype":"venue"
},
  "geometry": {"coordinates":[-92.534125,44.565],"type":"Point"}
}