{
  "type": "Feature",
  "properties": {
    "iso:country":"US",
    "sg:address":"504 Main St S",
    "sg:city":"Austin",
    "sg:classifiers":[
        {
            "category":"Home & Garden",
            "subcategory":"Furniture",
            "type":"Retail Goods"
        }
    ],
    "sg:phone":"+1 507 433 8833",
    "sg:postcode":"55912",
    "sg:province":"MN",
    "wof:name":"Brick Furniture Store Inc",
    "wof:placetype":"venue"
},
  "geometry": {"coordinates":[-92.974951,43.662742],"type":"Point"}
}