{
  "type": "Feature",
  "properties": {
    "iso:country":"US",
    "sg:address":"52211 Rocky Ridge Rd",
    "sg:city":"Henning",
    "sg:classifiers":[
        {
            "category":"Utilities",
            "subcategory":"Refuse",
            "type":"Services"
        }
    ],
    "sg:phone":"+1 218 583 2129",
    "sg:postcode":"56551",
    "sg:province":"MN",
    "sg:tags":[
        "garbage",
        "collection"
    ],
    "wof:name":"Solid Waste Dept Ottertail Cty",
    "wof:placetype":"venue"
},
  "geometry": {"coordinates":[-95.39878,46.289326],"type":"Point"}
}