{
  "type": "Feature",
  "properties": {
    "iso:country":"US",
    "sg:address":"8505 Lyndale Ave S",
    "sg:city":"Minneapolis",
    "sg:classifiers":[
        {
            "category":"Personal",
            "subcategory":"Beauty Salon",
            "type":"Services"
        }
    ],
    "sg:phone":"+1 952 746 5956",
    "sg:postcode":"55420",
    "sg:province":"MN",
    "sg:tags":[
        "shop"
    ],
    "wof:name":"Season Nail",
    "wof:placetype":"venue"
},
  "geometry": {"coordinates":[-93.288483,44.848014],"type":"Point"}
}