{
  "type": "Feature",
  "properties": {
    "iso:country":"US",
    "sg:address":"18989 118th St",
    "sg:city":"Little Falls",
    "sg:classifiers":[
        {
            "category":"Building & Trades",
            "subcategory":"Construction",
            "type":"Services"
        }
    ],
    "sg:phone":"+1 320 632 2711",
    "sg:postcode":"56345",
    "sg:province":"MN",
    "sg:tags":[
        "floor",
        "laying",
        "contractor"
    ],
    "wof:name":"Van Norman Flr Cvg Instllation",
    "wof:placetype":"venue"
},
  "geometry": {"coordinates":[-94.26723200000001,45.933687],"type":"Point"}
}