{
  "type": "Feature",
  "properties": {
    "addr:full":"452 Northco Dr NE Minneapolis MN 55432",
    "addr:housenumber":"452",
    "addr:postcode":"55432",
    "addr:street":"Northco Dr Ne",
    "iso:country":"US",
    "sg:address":"452 Northco Dr NE",
    "sg:city":"Minneapolis",
    "sg:classifiers":[
        {
            "category":"Wholesale",
            "subcategory":"Medical Equipment & Supplies",
            "type":"Manufacturing & Wholesale Goods"
        }
    ],
    "sg:phone":"+1 763 398 3300",
    "sg:postcode":"55432",
    "sg:province":"MN",
    "sg:tags":[
        "dental"
    ],
    "sg:website":"www.dentalonsale.com",
    "wof:name":"Rjm Discount Dental Supply",
    "wof:placetype":"venue"
},
  "geometry": {"coordinates":[-93.260199,45.098852],"type":"Point"}
}