{
  "type": "Feature",
  "properties": {
    "iso:country":"US",
    "sg:address":"9348 Jonathan Rd",
    "sg:city":"Saint Paul",
    "sg:classifiers":[
        {
            "category":"Professional",
            "subcategory":"Business Services",
            "type":"Services"
        }
    ],
    "sg:phone":"+1 651 739 1614",
    "sg:postcode":"55125",
    "sg:province":"MN",
    "wof:name":"Leonard J Koehnen & Associates",
    "wof:placetype":"venue"
},
  "geometry": {"coordinates":[-92.915975,44.923427],"type":"Point"}
}