{
  "type": "Feature",
  "properties": {
    "iso:country":"US",
    "sg:address":"1145 Redding Ave",
    "sg:city":"Windom",
    "sg:classifiers":[
        {
            "category":"Professional",
            "subcategory":"Advertising",
            "type":"Services"
        }
    ],
    "sg:phone":"+1 507 831 4034",
    "sg:postcode":"56101",
    "sg:province":"MN",
    "wof:name":"Advertising Products Co",
    "wof:placetype":"venue"
},
  "geometry": {"coordinates":[-95.106557,43.868256],"type":"Point"}
}