{
  "type": "Feature",
  "properties": {
    "addr:full":"2057 Marshall Ave St Paul MN 55104",
    "addr:housenumber":"2057",
    "addr:postcode":"55104",
    "addr:street":"Marshall Ave",
    "iso:country":"US",
    "sg:address":"2057 Marshall Ave",
    "sg:city":"St Paul",
    "sg:classifiers":[
        {
            "category":"Food & Beverages",
            "subcategory":"Groceries & Convenience Stores",
            "type":"Retail Goods"
        }
    ],
    "sg:phone":"+1 651 646 1891",
    "sg:postcode":"55104",
    "sg:province":"MN",
    "wof:name":"Oasis Market",
    "wof:placetype":"venue"
},
  "geometry": {"coordinates":[-93.18628,44.948469],"type":"Point"}
}