{
  "type": "Feature",
  "properties": {
    "iso:country":"US",
    "sg:address":"9091 Co Rd 50",
    "sg:city":"Rockford",
    "sg:classifiers":[
        {
            "category":"Home & Garden",
            "subcategory":"Building Materials",
            "type":"Retail Goods"
        },
        {
            "category":"Manufacturing",
            "subcategory":"Rubber & Plastics",
            "type":"Manufacturing & Wholesale Goods"
        }
    ],
    "sg:phone":"+1 763 477 5854",
    "sg:postcode":"55373",
    "sg:province":"MN",
    "sg:tags":[
        "insulation",
        "heat",
        "foam",
        "mfg"
    ],
    "sg:website":"www.diversifoam.com",
    "wof:name":"Diversi Foam Products",
    "wof:placetype":"venue"
},
  "geometry": {"coordinates":[-93.747889,45.07804],"type":"Point"}
}