{
  "type": "Feature",
  "properties": {
    "iso:country":"US",
    "sg:address":"2129 131st Ave NW",
    "sg:city":"Minneapolis",
    "sg:classifiers":[
        {
            "category":"Social Services",
            "subcategory":"Child Care",
            "type":"Services"
        }
    ],
    "sg:phone":"+1 763 754 3172",
    "sg:postcode":"55448",
    "sg:province":"MN",
    "sg:tags":[
        "daycare",
        "provider"
    ],
    "wof:name":"Jill Frith",
    "wof:placetype":"venue"
},
  "geometry": {"coordinates":[-93.31873299999999,45.208431],"type":"Point"}
}