{
  "type": "Feature",
  "properties": {
    "addr:full":"2411 Central Ave NE Minneapolis MN 55418",
    "addr:housenumber":"2411",
    "addr:postcode":"55418",
    "addr:street":"Central Ave Ne",
    "iso:country":"US",
    "sg:address":"2411 Central Ave NE",
    "sg:city":"Minneapolis",
    "sg:classifiers":[
        {
            "category":"Restaurant",
            "type":"Food & Drink"
        }
    ],
    "sg:phone":"+1 612 789 1515",
    "sg:postcode":"55418",
    "sg:province":"MN",
    "wof:name":"LA Tortuga",
    "wof:placetype":"venue"
},
  "geometry": {"coordinates":[-93.24742000000001,45.01306],"type":"Point"}
}