{
  "type": "Feature",
  "properties": {
    "addr:full":"7085 140th Ave NE Kerkhoven MN 56252",
    "addr:housenumber":"7085",
    "addr:postcode":"56252",
    "addr:street":"140Th Ave Ne",
    "iso:country":"US",
    "sg:address":"7085 140th Ave NE",
    "sg:city":"Kerkhoven",
    "sg:classifiers":[
        {
            "category":"Farming",
            "subcategory":"Farm",
            "type":"Manufacturing & Wholesale Goods"
        }
    ],
    "sg:phone":"+1 320 264 5164",
    "sg:postcode":"56252",
    "sg:province":"MN",
    "sg:tags":[
        "crop",
        "general"
    ],
    "wof:name":"Edward Weiland",
    "wof:placetype":"venue"
},
  "geometry": {"coordinates":[-95.308511,45.137198],"type":"Point"}
}