{
  "type": "Feature",
  "properties": {
    "addr:full":"5488 McQuade Rd Duluth MN 55804",
    "addr:housenumber":"5488",
    "addr:postcode":"55804",
    "addr:street":"Mcquade Rd",
    "iso:country":"US",
    "sg:address":"5488 McQuade Rd",
    "sg:city":"Duluth",
    "sg:classifiers":[
        {
            "category":"Building & Trades",
            "subcategory":"Plumbing",
            "type":"Services"
        }
    ],
    "sg:phone":"+1 218 525 4572",
    "sg:postcode":"55804",
    "sg:province":"MN",
    "sg:tags":[
        "contractor"
    ],
    "wof:name":"Plumrite Plmbing",
    "wof:placetype":"venue"
},
  "geometry": {"coordinates":[-91.920765,46.908581],"type":"Point"}
}