{
  "type": "Feature",
  "properties": {
    "iso:country":"US",
    "sg:address":"366 Bench St",
    "sg:city":"Taylors Falls",
    "sg:classifiers":[
        {
            "category":"Shopping",
            "subcategory":"Computers & Home Electronics",
            "type":"Retail Goods"
        }
    ],
    "sg:phone":"+1 651 465 7373",
    "sg:postcode":"55084",
    "sg:province":"MN",
    "sg:tags":[
        "equipment",
        "dealer"
    ],
    "sg:website":"www.nci-st.com",
    "wof:name":"NCI Computer Systems",
    "wof:placetype":"venue"
},
  "geometry": {"coordinates":[-92.652575,45.403134],"type":"Point"}
}