{
  "type": "Feature",
  "properties": {
    "iso:country":"US",
    "sg:address":"301 Cedar Ave E",
    "sg:city":"Hector",
    "sg:classifiers":[
        {
            "category":"Organizations",
            "subcategory":"Religious Organization",
            "type":"Services"
        }
    ],
    "sg:phone":"+1 320 848 6437",
    "sg:postcode":"55342",
    "sg:province":"MN",
    "sg:tags":[
        "church"
    ],
    "wof:name":"St John's Catholic Church",
    "wof:placetype":"venue"
},
  "geometry": {"coordinates":[-94.712068,44.742962],"type":"Point"}
}