{
  "type": "Feature",
  "properties": {
    "iso:country":"US",
    "sg:address":"1020 E 2nd St",
    "sg:city":"Winona",
    "sg:classifiers":[
        {
            "category":"Wholesale",
            "subcategory":"Farm Supplies",
            "type":"Manufacturing & Wholesale Goods"
        }
    ],
    "sg:phone":"+1 507 452 2045",
    "sg:postcode":"55987",
    "sg:province":"MN",
    "sg:tags":[
        "fertilizer"
    ],
    "wof:name":"S T Svc Fertilizer Storage",
    "wof:placetype":"venue"
},
  "geometry": {"coordinates":[-91.611912,44.046649],"type":"Point"}
}