{
  "type": "Feature",
  "properties": {
    "iso:country":"US",
    "sg:address":"3901 Grand Ave",
    "sg:city":"Duluth",
    "sg:classifiers":[
        {
            "category":"Restaurant",
            "type":"Food & Drink"
        }
    ],
    "sg:phone":"+1 218 624 9090",
    "sg:postcode":"55807",
    "sg:province":"MN",
    "sg:tags":[
        "pizza",
        "italian"
    ],
    "sg:website":"http://www.vintageitalianpizza.com",
    "wof:name":"Vintage Italian Pizza V. I. P.",
    "wof:placetype":"venue"
},
  "geometry": {"coordinates":[-92.14994,46.752541],"type":"Point"}
}