{
  "type": "Feature",
  "properties": {
    "addr:full":"1549 Elrose Ct South St Paul MN 55075",
    "addr:housenumber":"1549",
    "addr:postcode":"55075",
    "addr:street":"Elrose Ct",
    "iso:country":"US",
    "sg:address":"1549 Elrose Ct",
    "sg:city":"South St Paul",
    "sg:classifiers":[
        {
            "category":"Wholesale",
            "subcategory":"Medical Equipment & Supplies",
            "type":"Manufacturing & Wholesale Goods"
        }
    ],
    "sg:phone":"+1 651 457 8888",
    "sg:postcode":"55075",
    "sg:province":"MN",
    "sg:tags":[
        "hospital"
    ],
    "wof:name":"Ace Medical Products Co",
    "wof:placetype":"venue"
},
  "geometry": {"coordinates":[-93.038068,44.864771],"type":"Point"}
}