{
  "type": "Feature",
  "properties": {
    "addr:full":"11350 Aquila Dr N Champlin MN 55316",
    "addr:housenumber":"11350",
    "addr:postcode":"55316",
    "addr:street":"Aquila Dr N",
    "iso:country":"US",
    "sg:address":"11350 Aquila Dr N",
    "sg:city":"Champlin",
    "sg:classifiers":[
        {
            "category":"Insurance",
            "subcategory":"Insurance Agent",
            "type":"Services"
        }
    ],
    "sg:phone":"+1 763 712 8840",
    "sg:postcode":"55316",
    "sg:province":"MN",
    "wof:name":"Moon Lai",
    "wof:placetype":"venue"
},
  "geometry": {"coordinates":[-93.38911,45.158803],"type":"Point"}
}