{
  "type": "Feature",
  "properties": {
    "addr:full":"925 Lake Ave Detroit Lakes MN 56501",
    "addr:housenumber":"925",
    "addr:postcode":"56501",
    "addr:street":"Lake Ave",
    "iso:country":"US",
    "sg:address":"925 Lake Ave",
    "sg:city":"Detroit Lakes",
    "sg:classifiers":[
        {
            "category":"Government",
            "subcategory":"Jail",
            "type":"Public Place"
        }
    ],
    "sg:phone":"+1 218 847 2939",
    "sg:postcode":"56501",
    "sg:province":"MN",
    "sg:tags":[
        "county",
        "govt",
        "institution"
    ],
    "wof:name":"Becker County Jail",
    "wof:placetype":"venue"
},
  "geometry": {"coordinates":[-95.84673600000001,46.816944],"type":"Point"}
}