{
  "type": "Feature",
  "properties": {
    "addr:full":"17635 3rd Ave N Minneapolis MN 55447",
    "addr:housenumber":"17635",
    "addr:postcode":"55447",
    "addr:street":"3Rd Ave N",
    "iso:country":"US",
    "sg:address":"17635 3rd Ave N",
    "sg:city":"Minneapolis",
    "sg:classifiers":[
        {
            "category":"Shopping",
            "subcategory":"Books",
            "type":"Retail Goods"
        }
    ],
    "sg:phone":"+1 763 475 2340",
    "sg:postcode":"55447",
    "sg:province":"MN",
    "sg:tags":[
        "dealer"
    ],
    "wof:name":"Twins Trivia Book",
    "wof:placetype":"venue"
},
  "geometry": {"coordinates":[-93.503783,44.981932],"type":"Point"}
}