{
  "type": "Feature",
  "properties": {
    "addr:full":"10565 University Ave NE Minneapolis MN 55434",
    "addr:housenumber":"10565",
    "addr:postcode":"55434",
    "addr:street":"University Ave Ne",
    "iso:country":"US",
    "sg:address":"10565 University Ave NE",
    "sg:city":"Minneapolis",
    "sg:classifiers":[
        {
            "category":"Restaurant",
            "type":"Food & Drink"
        }
    ],
    "sg:phone":"+1 763 757 2020",
    "sg:postcode":"55434",
    "sg:province":"MN",
    "sg:tags":[
        "pizza"
    ],
    "sg:website":"http://www.chanticlearpizza.com",
    "wof:name":"Chanticlear Pizza",
    "wof:placetype":"venue"
},
  "geometry": {"coordinates":[-93.266283,45.162506],"type":"Point"}
}