{
  "type": "Feature",
  "properties": {
    "iso:country":"US",
    "sg:address":"7200 France Ave S",
    "sg:city":"Minneapolis",
    "sg:classifiers":[
        {
            "category":"Organizations",
            "subcategory":"Membership Organization",
            "type":"Services"
        }
    ],
    "sg:phone":"+1 952 897 9093",
    "sg:postcode":"55435",
    "sg:province":"MN",
    "wof:name":"Minnesota Assn Nrse Ansthtists",
    "wof:placetype":"venue"
},
  "geometry": {"coordinates":[-93.328941,44.871105],"type":"Point"}
}