{
  "type": "Feature",
  "properties": {
    "addr:full":"82339 510th St Buffalo Lake MN 55314",
    "addr:housenumber":"82339",
    "addr:postcode":"55314",
    "addr:street":"510Th St",
    "iso:country":"US",
    "sg:address":"82339 510th St",
    "sg:city":"Buffalo Lake",
    "sg:classifiers":[
        {
            "category":"Professional",
            "subcategory":"Business Services",
            "type":"Services"
        }
    ],
    "sg:phone":"+1 320 833 5503",
    "sg:postcode":"55314",
    "sg:province":"MN",
    "wof:name":"Buffalo Lk Fscher- Auctnr Svce",
    "wof:placetype":"venue"
},
  "geometry": {"coordinates":[-94.65060200000001,44.777339],"type":"Point"}
}