{
  "type": "Feature",
  "properties": {
    "addr:full":"18588 Co Rd 21 Richmond MN 56368",
    "addr:housenumber":"18588;21",
    "addr:postcode":"56368",
    "addr:street":"Co Rd",
    "iso:country":"US",
    "sg:address":"18588 Co Rd 21",
    "sg:city":"Richmond",
    "sg:classifiers":[
        {
            "category":"Farming",
            "subcategory":"Dairy Farm",
            "type":"Manufacturing & Wholesale Goods"
        }
    ],
    "sg:phone":"+1 320 453 5213",
    "sg:postcode":"56368",
    "sg:province":"MN",
    "wof:name":"Ronald Steil",
    "wof:placetype":"venue"
},
  "geometry": {"coordinates":[-94.49435,45.369769],"type":"Point"}
}