{
  "type": "Feature",
  "properties": {
    "addr:full":"1435 W 31st St Minneapolis MN 55408",
    "addr:housenumber":"1435",
    "addr:postcode":"55408",
    "addr:street":"W 31St St",
    "iso:country":"US",
    "sg:address":"1435 W 31st St",
    "sg:city":"Minneapolis",
    "sg:classifiers":[
        {
            "category":"Professional",
            "type":"Services"
        }
    ],
    "sg:phone":"+1 612 824 9247",
    "sg:postcode":"55408",
    "sg:province":"MN",
    "wof:name":"Pro Studio Music",
    "wof:placetype":"venue"
},
  "geometry": {"coordinates":[-93.29905100000001,44.946502],"type":"Point"}
}