{
  "type": "Feature",
  "properties": {
    "iso:country":"US",
    "sg:address":"14949 Technology Dr",
    "sg:city":"Eden Prairie",
    "sg:classifiers":[
        {
            "category":"Manufacturing",
            "subcategory":"Tools & Machinery",
            "type":"Manufacturing & Wholesale Goods"
        }
    ],
    "sg:phone":"+1 952 949 2415",
    "sg:postcode":"55344",
    "sg:province":"MN",
    "sg:tags":[
        "humidifying",
        "apparatus"
    ],
    "sg:website":"www.dristeem.com",
    "wof:name":"Dri-Steem Humidifier Co",
    "wof:placetype":"venue"
},
  "geometry": {"coordinates":[-93.467624,44.857059],"type":"Point"}
}