{
  "type": "Feature",
  "properties": {
    "addr:full":"28140 Par Dr Zimmerman MN 55398",
    "addr:housenumber":"28140",
    "addr:postcode":"55398",
    "addr:street":"Par Dr",
    "iso:country":"US",
    "sg:address":"28140 Par Dr",
    "sg:city":"Zimmerman",
    "sg:classifiers":[
        {
            "category":"Freight",
            "type":"Transportation"
        }
    ],
    "sg:phone":"+1 763 856 5816",
    "sg:postcode":"55398",
    "sg:province":"MN",
    "sg:tags":[
        "operator",
        "local",
        "trucking"
    ],
    "wof:name":"Baldwin Trucking Inc",
    "wof:placetype":"venue"
},
  "geometry": {"coordinates":[-93.60296700000001,45.480621],"type":"Point"}
}