{
  "type": "Feature",
  "properties": {
    "iso:country":"US",
    "sg:address":"1307 Cloquet Ave",
    "sg:city":"Cloquet",
    "sg:classifiers":[
        {
            "category":"Government",
            "subcategory":"City Hall",
            "type":"Public Place"
        },
        {
            "category":"Government",
            "subcategory":"Office",
            "type":"Public Place"
        }
    ],
    "sg:phone":"+1 218 879 3347",
    "sg:postcode":"55720",
    "sg:province":"MN",
    "sg:tags":[
        "town",
        "township",
        "planner",
        "government-city",
        "village"
    ],
    "wof:name":"Cloquet Ambulance Service",
    "wof:placetype":"venue"
},
  "geometry": {"coordinates":[-92.462154,46.72191],"type":"Point"}
}