{
  "type": "Feature",
  "properties": {
    "iso:country":"US",
    "sg:address":"1000 Marnie St",
    "sg:city":"Maplewood",
    "sg:classifiers":[
        {
            "category":"Real Estate",
            "subcategory":"Real Estate Agent",
            "type":"Services"
        }
    ],
    "sg:phone":"+1 651 738 6935",
    "sg:postcode":"55119",
    "sg:province":"MN",
    "wof:name":"Lockner E Edward & Assoc",
    "wof:placetype":"venue"
},
  "geometry": {"coordinates":[-92.995812,44.910242],"type":"Point"}
}