{
  "type": "Feature",
  "properties": {
    "addr:full":"7936 Main St Osseo MN 55369",
    "addr:housenumber":"7936",
    "addr:postcode":"55369",
    "addr:street":"Main St",
    "iso:country":"US",
    "sg:address":"7936 Main St",
    "sg:city":"Osseo",
    "sg:classifiers":[
        {
            "category":"Personal",
            "subcategory":"Beauty Salon",
            "type":"Services"
        }
    ],
    "sg:phone":"+1 763 494 8558",
    "sg:postcode":"55369",
    "sg:province":"MN",
    "wof:name":"Haircolorxperts Of Maple Grove",
    "wof:placetype":"venue"
},
  "geometry": {"coordinates":[-93.441574,45.098488],"type":"Point"}
}