{
  "type": "Feature",
  "properties": {
    "addr:full":"1708 Harrison Ct Northfield MN 55057",
    "addr:housenumber":"1708",
    "addr:postcode":"55057",
    "addr:street":"Harrison Ct",
    "iso:country":"US",
    "sg:address":"1708 Harrison Ct",
    "sg:city":"Northfield",
    "sg:classifiers":[
        {
            "category":"Professional",
            "subcategory":"Advertising",
            "type":"Services"
        }
    ],
    "sg:phone":"+1 507 650 0069",
    "sg:postcode":"55057",
    "sg:province":"MN",
    "sg:tags":[
        "representative"
    ],
    "wof:name":"Tough Toons LLC",
    "wof:placetype":"venue"
},
  "geometry": {"coordinates":[-93.16916500000001,44.441291],"type":"Point"}
}