{
  "type": "Feature",
  "properties": {
    "iso:country":"US",
    "sg:address":"7980 Wedgewood Ln N",
    "sg:city":"Osseo",
    "sg:classifiers":[
        {
            "category":"Shopping",
            "subcategory":"Hobbies, Toys, & Games",
            "type":"Retail Goods"
        }
    ],
    "sg:phone":"+1 763 420 0909",
    "sg:postcode":"55369",
    "sg:province":"MN",
    "sg:tags":[
        "arts",
        "craft"
    ],
    "wof:name":"Michaels 2752",
    "wof:placetype":"venue"
},
  "geometry": {"coordinates":[-93.449517,45.099941],"type":"Point"}
}