{
  "type": "Feature",
  "properties": {
    "iso:country":"US",
    "sg:address":"1650 Cliff Rd E Ste 1",
    "sg:city":"Burnsville",
    "sg:classifiers":[
        {
            "category":"Real Estate",
            "subcategory":"Real Estate Services",
            "type":"Services"
        },
        {
            "category":"Real Estate",
            "subcategory":"Surveying",
            "type":"Services"
        },
        {
            "category":"Professional",
            "subcategory":"Business Services",
            "type":"Services"
        }
    ],
    "sg:phone":"+1 952 895 1195",
    "sg:postcode":"55337",
    "sg:province":"MN",
    "sg:tags":[
        "auction",
        "industrial",
        "appraisers-commercial",
        "appraiser"
    ],
    "wof:name":"Quality Appraisers Inc",
    "wof:placetype":"venue"
},
  "geometry": {"coordinates":[-93.250107,44.790478],"type":"Point"}
}