{
  "type": "Feature",
  "properties": {
    "iso:country":"US",
    "sg:address":"2000 1st Ave S",
    "sg:city":"Moorhead",
    "sg:classifiers":[
        {
            "category":"Retail",
            "subcategory":"Auto Repair",
            "type":"Services"
        }
    ],
    "sg:phone":"+1 218 233 6161",
    "sg:postcode":"56560",
    "sg:province":"MN",
    "sg:tags":[
        "repairing",
        "transmission",
        "general",
        "automobile"
    ],
    "wof:name":"A-1 Automotive Transm Svc",
    "wof:placetype":"venue"
},
  "geometry": {"coordinates":[-96.75116199999999,46.873719],"type":"Point"}
}