{
  "type": "Feature",
  "properties": {
    "iso:country":"US",
    "sg:address":"27085 Copperfield Rd",
    "sg:city":"Paynesville",
    "sg:classifiers":[
        {
            "category":"Retail",
            "subcategory":"Repair Shop",
            "type":"Services"
        }
    ],
    "sg:phone":"+1 320 243 7001",
    "sg:postcode":"56362",
    "sg:province":"MN",
    "sg:tags":[
        "welding"
    ],
    "wof:name":"David R Pelkey Welding",
    "wof:placetype":"venue"
},
  "geometry": {"coordinates":[-94.672962,45.365505],"type":"Point"}
}