{
  "type": "Feature",
  "properties": {
    "addr:full":"714 Sunnyside Dr Cloquet MN 55720",
    "addr:housenumber":"714",
    "addr:postcode":"55720",
    "addr:street":"Sunnyside Dr",
    "iso:country":"US",
    "sg:address":"714 Sunnyside Dr",
    "sg:city":"Cloquet",
    "sg:classifiers":[
        {
            "category":"Banks & Credit Unions",
            "subcategory":"Investment Brokerage",
            "type":"Services"
        },
        {
            "category":"Real Estate",
            "subcategory":"Developer",
            "type":"Services"
        }
    ],
    "sg:phone":"+1 218 879 1211",
    "sg:postcode":"55720",
    "sg:province":"MN",
    "sg:tags":[
        "investing"
    ],
    "wof:name":"East West Realty",
    "wof:placetype":"venue"
},
  "geometry": {"coordinates":[-92.461483,46.742149],"type":"Point"}
}