{
  "type": "Feature",
  "properties": {
    "iso:country":"US",
    "sg:address":"1399 Helmo Ave N",
    "sg:city":"Oakdale",
    "sg:classifiers":[
        {
            "category":"Personal",
            "subcategory":"Beauty Salon",
            "type":"Services"
        }
    ],
    "sg:phone":"+1 651 735 3177",
    "sg:postcode":"55128",
    "sg:province":"MN",
    "sg:tags":[
        "shop"
    ],
    "wof:name":"Studio 99",
    "wof:placetype":"venue"
},
  "geometry": {"coordinates":[-92.955496,44.969277],"type":"Point"}
}