{
  "type": "Feature",
  "properties": {
    "iso:country":"US",
    "sg:address":"111 Marquette Ave S",
    "sg:city":"Minneapolis",
    "sg:classifiers":[
        {
            "category":"Professional",
            "subcategory":"Lawyer & Legal Services",
            "type":"Services"
        }
    ],
    "sg:phone":"+1 612 338 8678",
    "sg:postcode":"55401",
    "sg:province":"MN",
    "wof:name":"Robert D Miller and Associates",
    "wof:placetype":"venue"
},
  "geometry": {"coordinates":[-93.26591500000001,44.982233],"type":"Point"}
}