{
  "type": "Feature",
  "properties": {
    "iso:country":"US",
    "sg:address":"27258 Co Hwy 83",
    "sg:city":"Battle Lake",
    "sg:classifiers":[
        {
            "category":"Building & Trades",
            "subcategory":"Construction",
            "type":"Services"
        }
    ],
    "sg:phone":"+1 218 495 2371",
    "sg:postcode":"56515",
    "sg:province":"MN",
    "wof:name":"Christensen Brothers",
    "wof:placetype":"venue"
},
  "geometry": {"coordinates":[-95.758357,46.356679],"type":"Point"}
}