{
  "type": "Feature",
  "properties": {
    "iso:country":"US",
    "sg:address":"7317 State Hwy 13",
    "sg:city":"Savage",
    "sg:classifiers":[
        {
            "category":"Freight",
            "type":"Transportation"
        }
    ],
    "sg:phone":"+1 952 890 8339",
    "sg:postcode":"55378",
    "sg:province":"MN",
    "sg:tags":[
        "operator",
        "trucking"
    ],
    "wof:name":"Meyer Trucking Inc",
    "wof:placetype":"venue"
},
  "geometry": {"coordinates":[-93.37093900000001,44.778395],"type":"Point"}
}