{
  "type": "Feature",
  "properties": {
    "addr:full":"7060 Valley Creek Rd St Paul MN 55125",
    "addr:housenumber":"7060",
    "addr:postcode":"55125",
    "addr:street":"Valley Creek Rd",
    "iso:country":"US",
    "sg:address":"7060 Valley Creek Rd",
    "sg:city":"St Paul",
    "sg:classifiers":[
        {
            "category":"Building & Trades",
            "subcategory":"Landscaping Services",
            "type":"Services"
        }
    ],
    "sg:phone":"+1 651 458 0778",
    "sg:postcode":"55125",
    "sg:province":"MN",
    "sg:tags":[
        "landscape",
        "contractor"
    ],
    "wof:name":"Valley Creek Lawn & Landscape",
    "wof:placetype":"venue"
},
  "geometry": {"coordinates":[-92.96401899999999,44.925127],"type":"Point"}
}