{
  "type": "Feature",
  "properties": {
    "iso:country":"US",
    "sg:address":"6037 14th Ave S",
    "sg:city":"Minneapolis",
    "sg:classifiers":[
        {
            "category":"Professional",
            "type":"Services"
        }
    ],
    "sg:phone":"+1 612 866 3107",
    "sg:postcode":"55417",
    "sg:province":"MN",
    "wof:name":"Our Time Is Your Time",
    "wof:placetype":"venue"
},
  "geometry": {"coordinates":[-93.25529899999999,44.893185],"type":"Point"}
}