{
  "type": "Feature",
  "properties": {
    "iso:country":"US",
    "sg:address":"408 5th Ave W",
    "sg:city":"Federal Dam",
    "sg:classifiers":[
        {
            "category":"Wholesale",
            "subcategory":"Machinery & Supplies",
            "type":"Manufacturing & Wholesale Goods"
        },
        {
            "category":"Wholesale",
            "subcategory":"Farm Supplies",
            "type":"Manufacturing & Wholesale Goods"
        }
    ],
    "sg:phone":"+1 218 654 3525",
    "sg:postcode":"56641",
    "sg:province":"MN",
    "sg:tags":[
        "bean"
    ],
    "wof:name":"Lake Of The Woods Wild Rice Co",
    "wof:placetype":"venue"
},
  "geometry": {"coordinates":[-94.220332,47.243086],"type":"Point"}
}