{
  "type": "Feature",
  "properties": {
    "iso:country":"US",
    "sg:address":"5900 Green Oak Dr",
    "sg:city":"Hopkins",
    "sg:classifiers":[
        {
            "category":"Communications",
            "type":"Services"
        }
    ],
    "sg:phone":"+1 952 944 9731",
    "sg:postcode":"55343",
    "sg:province":"MN",
    "sg:tags":[
        "communication"
    ],
    "wof:name":"Digital Mediacom Inc",
    "wof:placetype":"venue"
},
  "geometry": {"coordinates":[-93.409307,44.898168],"type":"Point"}
}