{
  "type": "Feature",
  "properties": {
    "iso:country":"US",
    "sg:address":"12905 State Hwy 55",
    "sg:city":"Minneapolis",
    "sg:classifiers":[
        {
            "category":"Wholesale",
            "subcategory":"Machinery & Supplies",
            "type":"Manufacturing & Wholesale Goods"
        }
    ],
    "sg:phone":"+1 763 519 1501",
    "sg:postcode":"55441",
    "sg:province":"MN",
    "sg:tags":[
        "bearing",
        "industrial",
        "mfg",
        "parts",
        "motor",
        "vehicle"
    ],
    "wof:name":"Industrial Supply Company Inc",
    "wof:placetype":"venue"
},
  "geometry": {"coordinates":[-93.443292,45.000467],"type":"Point"}
}