{
  "type": "Feature",
  "properties": {
    "iso:country":"US",
    "sg:address":"515 Virginia Ave",
    "sg:city":"Long Lake",
    "sg:classifiers":[
        {
            "category":"Professional",
            "subcategory":"Accounting & Tax Preparation",
            "type":"Services"
        }
    ],
    "sg:phone":"+1 952 473 0585",
    "sg:postcode":"55356",
    "sg:province":"MN",
    "wof:name":"Owen Smeby CPA",
    "wof:placetype":"venue"
},
  "geometry": {"coordinates":[-93.574449,44.987477],"type":"Point"}
}