{
  "type": "Feature",
  "properties": {
    "iso:country":"US",
    "sg:address":"926 Rice St",
    "sg:city":"Saint Paul",
    "sg:classifiers":[
        {
            "category":"Communications",
            "subcategory":"Film & Video Production",
            "type":"Services"
        }
    ],
    "sg:phone":"+1 651 487 7930",
    "sg:postcode":"55117",
    "sg:province":"MN",
    "sg:tags":[
        "motion"
    ],
    "wof:name":"New Grange Productions",
    "wof:placetype":"venue"
},
  "geometry": {"coordinates":[-93.105885,44.969424],"type":"Point"}
}