{
  "type": "Feature",
  "properties": {
    "addr:full":"1811 Quebec Ave N Minneapolis MN 55427",
    "addr:housenumber":"1811",
    "addr:postcode":"55427",
    "addr:street":"Quebec Ave N",
    "iso:country":"US",
    "sg:address":"1811 Quebec Ave N",
    "sg:city":"Minneapolis",
    "sg:classifiers":[
        {
            "category":"Utilities",
            "subcategory":"Mobile Phone",
            "type":"Services"
        }
    ],
    "sg:phone":"+1 952 994 0455",
    "sg:postcode":"55427",
    "sg:province":"MN",
    "sg:tags":[
        "wireless",
        "entertainment"
    ],
    "wof:name":"Mobilegearbiz",
    "wof:placetype":"venue"
},
  "geometry": {"coordinates":[-93.376637,44.997292],"type":"Point"}
}