{
  "type": "Feature",
  "properties": {
    "iso:country":"US",
    "sg:address":"5500 Cottonwood Ln SE",
    "sg:city":"Prior Lake",
    "sg:classifiers":[
        {
            "category":"Manufacturing",
            "subcategory":"Printing",
            "type":"Manufacturing & Wholesale Goods"
        }
    ],
    "sg:phone":"+1 952 226 1050",
    "sg:postcode":"55372",
    "sg:province":"MN",
    "sg:tags":[
        "printer",
        "commercial",
        "typesetting"
    ],
    "wof:name":"Apex Graphics",
    "wof:placetype":"venue"
},
  "geometry": {"coordinates":[-93.410473,44.705594],"type":"Point"}
}