{
  "type": "Feature",
  "properties": {
    "iso:country":"US",
    "sg:address":"5574 Nerstrand Blvd",
    "sg:city":"Faribault",
    "sg:classifiers":[
        {
            "category":"Farming",
            "subcategory":"Dairy Farm",
            "type":"Manufacturing & Wholesale Goods"
        }
    ],
    "sg:phone":"+1 507 334 5331",
    "sg:postcode":"55021",
    "sg:province":"MN",
    "sg:tags":[
        "field",
        "corn",
        "grain",
        "cash",
        "crop"
    ],
    "wof:name":"Allen Bauer",
    "wof:placetype":"venue"
},
  "geometry": {"coordinates":[-93.19032900000001,44.326941],"type":"Point"}
}