{
  "type": "Feature",
  "properties": {
    "addr:full":"2831 Hennepin Ave Minneapolis MN 55408",
    "addr:housenumber":"2831",
    "addr:postcode":"55408",
    "addr:street":"Hennepin Ave",
    "iso:country":"US",
    "sg:address":"2831 Hennepin Ave",
    "sg:city":"Minneapolis",
    "sg:classifiers":[
        {
            "category":"Wholesale",
            "subcategory":"Jewelry",
            "type":"Manufacturing & Wholesale Goods"
        },
        {
            "category":"Shopping",
            "subcategory":"Crafts & Fabrics",
            "type":"Retail Goods"
        }
    ],
    "sg:phone":"+1 612 879 8181",
    "sg:postcode":"55408",
    "sg:province":"MN",
    "sg:tags":[
        "beads-wholesale",
        "art",
        "manufacturer",
        "supply"
    ],
    "sg:website":"http://www.bobbybead.com",
    "wof:name":"Bobby Bead",
    "wof:placetype":"venue"
},
  "geometry": {"coordinates":[-93.298103,44.951],"type":"Point"}
}