{
  "type": "Feature",
  "properties": {
    "iso:country":"US",
    "sg:address":"6200 W Broadway Ave",
    "sg:city":"Brooklyn Park",
    "sg:classifiers":[
        {
            "category":"Banks & Credit Unions",
            "subcategory":"Bank",
            "type":"Services"
        }
    ],
    "sg:phone":"+1 763 535 1100",
    "sg:postcode":"55428",
    "sg:province":"MN",
    "sg:tags":[
        "loan",
        "real estate"
    ],
    "wof:name":"Everest Mortgage",
    "wof:placetype":"venue"
},
  "geometry": {"coordinates":[-93.375427,45.066956],"type":"Point"}
}