{
  "type": "Feature",
  "properties": {
    "iso:country":"US",
    "sg:address":"23070 N Lakeshore Dr",
    "sg:city":"Glenwood",
    "sg:classifiers":[
        {
            "category":"Professional",
            "subcategory":"Research",
            "type":"Services"
        }
    ],
    "sg:phone":"+1 320 634 4573",
    "sg:postcode":"56334",
    "sg:province":"MN",
    "sg:tags":[
        "commercial",
        "physical"
    ],
    "wof:name":"Dnr Fish Research",
    "wof:placetype":"venue"
},
  "geometry": {"coordinates":[-95.411322,45.654214],"type":"Point"}
}