{
  "type": "Feature",
  "properties": {
    "addr:full":"17647 Emery Ave Hastings MN 55033",
    "addr:housenumber":"17647",
    "addr:postcode":"55033",
    "addr:street":"Emery Ave",
    "iso:country":"US",
    "sg:address":"17647 Emery Ave",
    "sg:city":"Hastings",
    "sg:classifiers":[
        {
            "category":"Real Estate",
            "subcategory":"Real Estate Agent",
            "type":"Services"
        }
    ],
    "sg:phone":"+1 651 983 8617",
    "sg:postcode":"55033",
    "sg:province":"MN",
    "wof:name":"Reis Realty & Management",
    "wof:placetype":"venue"
},
  "geometry": {"coordinates":[-92.994713,44.697512],"type":"Point"}
}