{
  "type": "Feature",
  "properties": {
    "addr:full":"302 1st Ave SW Chisholm MN 55719",
    "addr:housenumber":"302",
    "addr:postcode":"55719",
    "addr:street":"1St Ave Sw",
    "iso:country":"US",
    "sg:address":"302 1st Ave SW",
    "sg:city":"Chisholm",
    "sg:classifiers":[
        {
            "category":"Organizations",
            "subcategory":"Religious Organization",
            "type":"Services"
        }
    ],
    "sg:phone":"+1 218 254 2251",
    "sg:postcode":"55719",
    "sg:province":"MN",
    "sg:tags":[
        "church"
    ],
    "wof:name":"Faith Lutheran Church",
    "wof:placetype":"venue"
},
  "geometry": {"coordinates":[-92.880484,47.486216],"type":"Point"}
}