{
  "type": "Feature",
  "properties": {
    "addr:full":"22222 State Hwy 91 Adrian MN 56110",
    "addr:housenumber":"22222",
    "addr:postcode":"56110",
    "addr:street":"State Hwy 91",
    "iso:country":"US",
    "sg:address":"22222 State Hwy 91",
    "sg:city":"Adrian",
    "sg:classifiers":[
        {
            "category":"Farming",
            "subcategory":"Livestock Farm",
            "type":"Manufacturing & Wholesale Goods"
        }
    ],
    "sg:phone":"+1 507 483 2394",
    "sg:postcode":"56110",
    "sg:province":"MN",
    "sg:tags":[
        "beef",
        "feedlot",
        "cattle"
    ],
    "wof:name":"Mark Bullerman",
    "wof:placetype":"venue"
},
  "geometry": {"coordinates":[-95.93311799999999,43.670908],"type":"Point"}
}