{
  "type": "Feature",
  "properties": {
    "addr:full":"7181 Robin Ln W Hugo MN 55038",
    "addr:housenumber":"7181",
    "addr:postcode":"55038",
    "addr:street":"Robin Ln W Hugo",
    "iso:country":"US",
    "sg:address":"7181 Robin Ln W",
    "sg:city":"Hugo",
    "sg:classifiers":[
        {
            "category":"Shopping",
            "type":"Retail Goods"
        }
    ],
    "sg:phone":"+1 651 340 4339",
    "sg:postcode":"55038",
    "sg:province":"MN",
    "sg:tags":[
        "merchandise"
    ],
    "wof:name":"Store Of The Century",
    "wof:placetype":"venue"
},
  "geometry": {"coordinates":[-93.042866,45.166586],"type":"Point"}
}