{
  "type": "Feature",
  "properties": {
    "addr:full":"1325 NW 4th St Grand Rapids MN 55744",
    "addr:housenumber":"1325",
    "addr:postcode":"55744",
    "addr:street":"Nw 4Th St",
    "iso:country":"US",
    "sg:address":"1325 NW 4th St",
    "sg:city":"Grand Rapids",
    "sg:classifiers":[
        {
            "category":"Retail",
            "subcategory":"Self-service Laundry",
            "type":"Services"
        }
    ],
    "sg:phone":"+1 218 326 1710",
    "sg:postcode":"55744",
    "sg:province":"MN",
    "sg:tags":[
        "carwash",
        "coin"
    ],
    "wof:name":"Cozy Free Soap Laundry",
    "wof:placetype":"venue"
},
  "geometry": {"coordinates":[-93.548433,47.236061],"type":"Point"}
}