{
  "type": "Feature",
  "properties": {
    "iso:country":"US",
    "sg:address":"6547 City West Pkwy",
    "sg:city":"Eden Prairie",
    "sg:classifiers":[
        {
            "category":"Wholesale",
            "subcategory":"Non-durable Goods",
            "type":"Manufacturing & Wholesale Goods"
        }
    ],
    "sg:phone":"+1 952 941 2188",
    "sg:postcode":"55344",
    "sg:province":"MN",
    "sg:tags":[
        "pet",
        "supply"
    ],
    "wof:name":"Hartz-Mountain Corp",
    "wof:placetype":"venue"
},
  "geometry": {"coordinates":[-93.414812,44.883474],"type":"Point"}
}