{
  "type": "Feature",
  "properties": {
    "addr:full":"4555 Erin Dr Ste 190 Saint Paul MN 55122",
    "addr:housenumber":"4555",
    "addr:postcode":"55122",
    "addr:street":"Erin Dr Ste 190",
    "iso:country":"US",
    "sg:address":"4555 Erin Dr Ste 190",
    "sg:city":"Saint Paul",
    "sg:classifiers":[
        {
            "category":"Health Services",
            "subcategory":"Doctor",
            "type":"Services"
        },
        {
            "category":"Health Services",
            "subcategory":"Dentist",
            "type":"Services"
        }
    ],
    "sg:phone":"+1 651 452 6933",
    "sg:postcode":"55122",
    "sg:province":"MN",
    "wof:name":"Dakota Valley Omssurgery",
    "wof:placetype":"venue"
},
  "geometry": {"coordinates":[-93.21959699999999,44.792599],"type":"Point"}
}