{
  "type": "Feature",
  "properties": {
    "addr:full":"16500 96th Ave N Maple Grove MN 55311",
    "addr:housenumber":"16500",
    "addr:postcode":"55311",
    "addr:street":"96Th Ave N",
    "iso:country":"US",
    "sg:address":"16500 96th Ave N",
    "sg:city":"Maple Grove",
    "sg:classifiers":[
        {
            "category":"Home & Garden",
            "subcategory":"Building Materials",
            "type":"Retail Goods"
        }
    ],
    "sg:phone":"+1 763 416 7000",
    "sg:postcode":"55311",
    "sg:province":"MN",
    "sg:tags":[
        "center"
    ],
    "wof:name":"Menards",
    "wof:placetype":"venue"
},
  "geometry": {"coordinates":[-93.487724,45.127583],"type":"Point"}
}