{
  "type": "Feature",
  "properties": {
    "addr:full":"237 Edgeview Dr Rollingstone MN 55969",
    "addr:housenumber":"237",
    "addr:postcode":"55969",
    "addr:street":"Edgeview Dr Rollingstone",
    "iso:country":"US",
    "sg:address":"237 Edgeview Dr",
    "sg:city":"Rollingstone",
    "sg:classifiers":[
        {
            "category":"Building & Trades",
            "subcategory":"Cleaning & Sanitation",
            "type":"Services"
        }
    ],
    "sg:phone":"+1 507 689 4111",
    "sg:postcode":"55969",
    "sg:province":"MN",
    "sg:tags":[
        "maintenance"
    ],
    "wof:name":"Spotless Cleaning",
    "wof:placetype":"venue"
},
  "geometry": {"coordinates":[-91.823869,44.098919],"type":"Point"}
}