{
  "type": "Feature",
  "properties": {
    "addr:full":"90 8th St N Breckenridge MN 56520",
    "addr:housenumber":"90",
    "addr:postcode":"56520",
    "addr:street":"8Th St N",
    "iso:country":"US",
    "sg:address":"90 8th St N",
    "sg:city":"Breckenridge",
    "sg:classifiers":[
        {
            "category":"Wholesale",
            "subcategory":"Farm Supplies",
            "type":"Manufacturing & Wholesale Goods"
        },
        {
            "category":"Freight",
            "type":"Transportation"
        }
    ],
    "sg:phone":"+1 218 643 8467",
    "sg:postcode":"56520",
    "sg:province":"MN",
    "sg:tags":[
        "mfg",
        "food",
        "elevator",
        "preparation",
        "grain",
        "crop"
    ],
    "sg:website":"www.sigcosun.com",
    "wof:name":"Sigco Sun Products Inc",
    "wof:placetype":"venue"
},
  "geometry": {"coordinates":[-96.583555,46.262743],"type":"Point"}
}