{
  "type": "Feature",
  "properties": {
    "iso:country":"US",
    "sg:address":"653 Concord St N",
    "sg:city":"South Saint Paul",
    "sg:classifiers":[
        {
            "category":"Building & Trades",
            "subcategory":"Equipment Rental",
            "type":"Services"
        }
    ],
    "sg:phone":"+1 651 451 2363",
    "sg:postcode":"55075",
    "sg:province":"MN",
    "sg:tags":[
        "consulting",
        "management"
    ],
    "wof:name":"Mervin Enterprises",
    "wof:placetype":"venue"
},
  "geometry": {"coordinates":[-93.043386,44.902274],"type":"Point"}
}