{
  "type": "Feature",
  "properties": {
    "addr:full":"5684 Mineral Ave Mountain Iron MN 55768",
    "addr:housenumber":"5684",
    "addr:postcode":"55768",
    "addr:street":"Mineral Ave",
    "iso:country":"US",
    "sg:address":"5684 Mineral Ave",
    "sg:city":"Mountain Iron",
    "sg:classifiers":[
        {
            "category":"Shopping",
            "type":"Retail Goods"
        }
    ],
    "sg:phone":"+1 218 735 8551",
    "sg:postcode":"55768",
    "sg:province":"MN",
    "sg:tags":[
        "trophy",
        "medal",
        "award"
    ],
    "wof:name":"Trophy Shop",
    "wof:placetype":"venue"
},
  "geometry": {"coordinates":[-92.61975700000001,47.527903],"type":"Point"}
}