{
  "type": "Feature",
  "properties": {
    "addr:full":"16015 State Hwy 66 Drayton MN 58225",
    "addr:housenumber":"16015",
    "addr:postcode":"58225",
    "addr:street":"State Hwy 66 Drayton",
    "iso:country":"US",
    "sg:address":"16015 State Hwy 66",
    "sg:city":"Drayton",
    "sg:classifiers":[
        {
            "category":"Autos & Motor Vehicles",
            "subcategory":"Automobile Sales",
            "type":"Retail Goods"
        }
    ],
    "sg:phone":"+1 701 454 6174",
    "sg:postcode":"58225",
    "sg:province":"MN",
    "sg:tags":[
        "truck"
    ],
    "wof:name":"Helm Truck Line",
    "wof:placetype":"venue"
},
  "geometry": {"coordinates":[-97.18838599999999,48.571306],"type":"Point"}
}