{
  "type": "Feature",
  "properties": {
    "addr:full":"5001 Drew Ave N Brooklyn Center MN 55429",
    "addr:housenumber":"5001",
    "addr:postcode":"55429",
    "addr:street":"Drew Ave N",
    "iso:country":"US",
    "sg:address":"5001 Drew Ave N",
    "sg:city":"Brooklyn Center",
    "sg:classifiers":[
        {
            "category":"Wholesale",
            "subcategory":"Durable Goods & Equipment",
            "type":"Manufacturing & Wholesale Goods"
        }
    ],
    "sg:phone":"+1 763 533 3360",
    "sg:postcode":"55429",
    "sg:province":"MN",
    "sg:tags":[
        "representative",
        "manufacturer"
    ],
    "wof:name":"Stoner & Assoc",
    "wof:placetype":"venue"
},
  "geometry": {"coordinates":[-93.327118,45.047745],"type":"Point"}
}