{
  "type": "Feature",
  "properties": {
    "addr:full":"315 Main Ave N Thief River Fls MN 56701",
    "addr:housenumber":"315",
    "addr:postcode":"56701",
    "addr:street":"Main Ave N Thief River Fls",
    "iso:country":"US",
    "sg:address":"315 Main Ave N",
    "sg:city":"Thief River Fls",
    "sg:classifiers":[
        {
            "category":"Utilities",
            "subcategory":"Cable",
            "type":"Services"
        }
    ],
    "sg:phone":"+1 218 681 3044",
    "sg:postcode":"56701",
    "sg:province":"MN",
    "sg:tags":[
        "television"
    ],
    "wof:name":"Sjoberg's Cable TV",
    "wof:placetype":"venue"
},
  "geometry": {"coordinates":[-96.181613,48.120037],"type":"Point"}
}