{
  "type": "Feature",
  "properties": {
    "addr:full":"5629 2nd Ave S Minneapolis MN 55419",
    "addr:housenumber":"5629",
    "addr:postcode":"55419",
    "addr:street":"2Nd Ave S",
    "iso:country":"US",
    "sg:address":"5629 2nd Ave S",
    "sg:city":"Minneapolis",
    "sg:classifiers":[
        {
            "category":"Shopping",
            "subcategory":"Florist",
            "type":"Retail Goods"
        }
    ],
    "sg:phone":"+1 612 598 3253",
    "sg:postcode":"55419",
    "sg:province":"MN",
    "sg:website":"http://www.thelatebloomer.com",
    "wof:name":"The Late Bloomer Inc",
    "wof:placetype":"venue"
},
  "geometry": {"coordinates":[-93.274332,44.901063],"type":"Point"}
}