{
  "type": "Feature",
  "properties": {
    "addr:full":"10982 Hwy 10 Little Falls MN 56345",
    "addr:housenumber":"10982",
    "addr:postcode":"56345",
    "addr:street":"Hwy 10",
    "iso:country":"US",
    "sg:address":"10982 Hwy 10",
    "sg:city":"Little Falls",
    "sg:classifiers":[
        {
            "category":"Autos & Motor Vehicles",
            "subcategory":"Motorcycle Sales",
            "type":"Retail Goods"
        }
    ],
    "sg:phone":"+1 320 616 9650",
    "sg:postcode":"56345",
    "sg:province":"MN",
    "sg:tags":[
        "scooter"
    ],
    "wof:name":"Larson Motor Sports",
    "wof:placetype":"venue"
},
  "geometry": {"coordinates":[-94.34616699999999,45.92108],"type":"Point"}
}