{
  "type": "Feature",
  "properties": {
    "iso:country":"US",
    "sg:address":"246 Main St S",
    "sg:city":"Hutchinson",
    "sg:classifiers":[
        {
            "category":"Health Services",
            "subcategory":"Clinic",
            "type":"Services"
        }
    ],
    "sg:phone":"+1 320 587 5162",
    "sg:postcode":"55350",
    "sg:province":"MN",
    "sg:tags":[
        "home",
        "care"
    ],
    "sg:website":"www.prhomecare.com",
    "wof:name":"Prairie River Home Care Inc",
    "wof:placetype":"venue"
},
  "geometry": {"coordinates":[-94.369332,44.889445],"type":"Point"}
}