{
  "type": "Feature",
  "properties": {
    "addr:full":"109 Birch Ave Ashby MN 56309",
    "addr:housenumber":"109",
    "addr:postcode":"56309",
    "addr:street":"Birch Ave",
    "iso:country":"US",
    "sg:address":"109 Birch Ave",
    "sg:city":"Ashby",
    "sg:classifiers":[
        {
            "category":"Home & Garden",
            "subcategory":"Building Materials",
            "type":"Retail Goods"
        }
    ],
    "sg:phone":"+1 218 747 2215",
    "sg:postcode":"56309",
    "sg:province":"MN",
    "sg:tags":[
        "lumber"
    ],
    "wof:name":"Lakeside Lumber",
    "wof:placetype":"venue"
},
  "geometry": {"coordinates":[-95.82087,46.096701],"type":"Point"}
}