{
  "type": "Feature",
  "properties": {
    "iso:country":"US",
    "sg:address":"815 Farrington St",
    "sg:city":"Saint Paul",
    "sg:classifiers":[
        {
            "category":"Manufacturing",
            "subcategory":"Metals",
            "type":"Manufacturing & Wholesale Goods"
        }
    ],
    "sg:phone":"+1 651 489 3924",
    "sg:postcode":"55117",
    "sg:province":"MN",
    "sg:tags":[
        "mfg",
        "furniture"
    ],
    "wof:name":"Cedar Perfections",
    "wof:placetype":"venue"
},
  "geometry": {"coordinates":[-93.11338000000001,44.964946],"type":"Point"}
}