{
  "type": "Feature",
  "properties": {
    "addr:full":"121 W Main St Spring Grove MN 55974",
    "addr:housenumber":"121",
    "addr:postcode":"55974",
    "addr:street":"W Main St",
    "iso:country":"US",
    "sg:address":"121 W Main St",
    "sg:city":"Spring Grove",
    "sg:classifiers":[
        {
            "category":"Building & Trades",
            "subcategory":"Construction",
            "type":"Services"
        }
    ],
    "sg:phone":"+1 507 498 3200",
    "sg:postcode":"55974",
    "sg:province":"MN",
    "sg:tags":[
        "handyman"
    ],
    "wof:name":"B's Handyman Svc",
    "wof:placetype":"venue"
},
  "geometry": {"coordinates":[-91.636427,43.560974],"type":"Point"}
}