{
  "type": "Feature",
  "properties": {
    "iso:country":"US",
    "sg:address":"4224 Minnetonka Blvd",
    "sg:city":"Minneapolis",
    "sg:classifiers":[
        {
            "category":"Personal",
            "subcategory":"Beauty Salon",
            "type":"Services"
        }
    ],
    "sg:phone":"+1 952 929 6030",
    "sg:postcode":"55416",
    "sg:province":"MN",
    "sg:tags":[
        "shop"
    ],
    "wof:name":"Salon Premiere",
    "wof:placetype":"venue"
},
  "geometry": {"coordinates":[-93.333674,44.948525],"type":"Point"}
}