{
  "type": "Feature",
  "properties": {
    "iso:country":"US",
    "sg:address":"224 Meadow Ln",
    "sg:city":"Le Sueur",
    "sg:classifiers":[
        {
            "category":"Building & Trades",
            "subcategory":"Construction",
            "type":"Services"
        }
    ],
    "sg:phone":"+1 507 665 3249",
    "sg:postcode":"56058",
    "sg:province":"MN",
    "sg:tags":[
        "house",
        "contractor"
    ],
    "wof:name":"Terry Slack Construction",
    "wof:placetype":"venue"
},
  "geometry": {"coordinates":[-93.915398,44.448692],"type":"Point"}
}