{
  "type": "Feature",
  "properties": {
    "addr:full":"5756 Lakeland Ave N Minneapolis MN 55429",
    "addr:housenumber":"5756",
    "addr:postcode":"55429",
    "addr:street":"Lakeland Ave N",
    "iso:country":"US",
    "sg:address":"5756 Lakeland Ave N",
    "sg:city":"Minneapolis",
    "sg:classifiers":[
        {
            "category":"Home & Garden",
            "subcategory":"Carpets & Floor Coverings",
            "type":"Retail Goods"
        }
    ],
    "sg:phone":"+1 763 535 2700",
    "sg:postcode":"55429",
    "sg:province":"MN",
    "sg:tags":[
        "dealer",
        "rug"
    ],
    "sg:website":"www.carpet-king.com",
    "wof:name":"Carpet King",
    "wof:placetype":"venue"
},
  "geometry": {"coordinates":[-93.35848900000001,45.055282],"type":"Point"}
}