{
  "type": "Feature",
  "properties": {
    "iso:country":"US",
    "sg:address":"4081 307th Ln NW",
    "sg:city":"Cambridge",
    "sg:classifiers":[
        {
            "category":"Home & Garden",
            "subcategory":"Household Appliances",
            "type":"Retail Goods"
        },
        {
            "category":"Building & Trades",
            "subcategory":"Construction",
            "type":"Services"
        }
    ],
    "sg:phone":"+1 763 444 3517",
    "sg:postcode":"55008",
    "sg:province":"MN",
    "sg:tags":[
        "major",
        "system",
        "appliances-small",
        "specialty",
        "heating",
        "contractor",
        "air conditioning"
    ],
    "sg:website":"http://www.deansheatingandac.com",
    "wof:name":"Dean's Heating & AC",
    "wof:placetype":"venue"
},
  "geometry": {"coordinates":[-93.369282,45.525845],"type":"Point"}
}