{
  "type": "Feature",
  "properties": {
    "addr:full":"3425 Dakota Ave S Minneapolis MN 55416",
    "addr:housenumber":"3425",
    "addr:postcode":"55416",
    "addr:street":"Dakota Ave S",
    "iso:country":"US",
    "sg:address":"3425 Dakota Ave S",
    "sg:city":"Minneapolis",
    "sg:classifiers":[
        {
            "category":"Manufacturing",
            "subcategory":"Motor Vehicles & Parts",
            "type":"Manufacturing & Wholesale Goods"
        }
    ],
    "sg:phone":"+1 952 928 8834",
    "sg:postcode":"55416",
    "sg:province":"MN",
    "sg:tags":[
        "screen",
        "printing",
        "contract",
        "embroidery"
    ],
    "wof:name":"Ace Dsign Prom Corp St Luis Pk",
    "wof:placetype":"venue"
},
  "geometry": {"coordinates":[-93.36069000000001,44.941394],"type":"Point"}
}