{
  "type": "Feature",
  "properties": {
    "iso:country":"US",
    "sg:address":"5753 Old Wayzata Blvd",
    "sg:city":"Minneapolis",
    "sg:classifiers":[
        {
            "category":"Real Estate",
            "subcategory":"Real Estate Agent",
            "type":"Services"
        }
    ],
    "sg:phone":"+1 952 767 5555",
    "sg:postcode":"55416",
    "sg:province":"MN",
    "wof:name":"Eagle Ridge Partners LLC",
    "wof:placetype":"venue"
},
  "geometry": {"coordinates":[-93.355473,44.97113],"type":"Point"}
}