{
  "type": "Feature",
  "properties": {
    "iso:country":"US",
    "sg:address":"1002 S Pokegama Ave",
    "sg:city":"Grand Rapids",
    "sg:classifiers":[
        {
            "category":"Restaurant",
            "type":"Food & Drink"
        }
    ],
    "sg:phone":"+1 218 327 7980",
    "sg:postcode":"55744",
    "sg:province":"MN",
    "sg:tags":[
        "eating"
    ],
    "wof:name":"A&W Restaurant",
    "wof:placetype":"venue"
},
  "geometry": {"coordinates":[-93.52862500000001,47.22012],"type":"Point"}
}