{
  "type": "Feature",
  "properties": {
    "iso:country":"US",
    "sg:address":"7200 Rolling Acres Rd",
    "sg:city":"Excelsior",
    "sg:classifiers":[
        {
            "category":"Organizations",
            "subcategory":"Non-profit Organization",
            "type":"Services"
        }
    ],
    "sg:phone":"+1 952 474 5974",
    "sg:postcode":"55331",
    "sg:province":"MN",
    "sg:tags":[
        "handicapped"
    ],
    "wof:name":"Rolling Acres",
    "wof:placetype":"venue"
},
  "geometry": {"coordinates":[-93.64054400000001,44.873477],"type":"Point"}
}