{
  "type": "Feature",
  "properties": {
    "iso:country":"US",
    "sg:address":"9733 Pleasant Grove NW",
    "sg:city":"Garfield",
    "sg:classifiers":[
        {
            "category":"Retail",
            "subcategory":"Repair Shop",
            "type":"Services"
        }
    ],
    "sg:phone":"+1 320 834 5050",
    "sg:postcode":"56332",
    "sg:province":"MN",
    "wof:name":"Mobile Mar Brandona Small Engs",
    "wof:placetype":"venue"
},
  "geometry": {"coordinates":[-95.47806,45.996748],"type":"Point"}
}