{
  "type": "Feature",
  "properties": {
    "iso:country":"US",
    "sg:address":"520 25th Ave N",
    "sg:city":"St Cloud",
    "sg:classifiers":[
        {
            "category":"Insurance",
            "subcategory":"Insurance Agent",
            "type":"Services"
        }
    ],
    "sg:phone":"+1 320 252 7200",
    "sg:postcode":"56303",
    "sg:province":"MN",
    "wof:name":"State Farm Insurance",
    "wof:placetype":"venue"
},
  "geometry": {"coordinates":[-94.187792,45.563701],"type":"Point"}
}