{
  "type": "Feature",
  "properties": {
    "addr:full":"50518 County 45 Bemidji MN 56601",
    "addr:housenumber":"50518",
    "addr:postcode":"56601",
    "addr:street":"County 45",
    "iso:country":"US",
    "sg:address":"50518 County 45",
    "sg:city":"Bemidji",
    "sg:classifiers":[
        {
            "category":"Wholesale",
            "subcategory":"Stationery",
            "type":"Manufacturing & Wholesale Goods"
        }
    ],
    "sg:phone":"+1 218 751 6144",
    "sg:postcode":"56601",
    "sg:province":"MN",
    "sg:tags":[
        "product",
        "paper"
    ],
    "wof:name":"Potlatch Corp",
    "wof:placetype":"venue"
},
  "geometry": {"coordinates":[-94.75590200000001,47.386001],"type":"Point"}
}