{
  "type": "Feature",
  "properties": {
    "addr:full":"24760 310th Ave NW Fisher MN 56762",
    "addr:housenumber":"24760",
    "addr:postcode":"56762",
    "addr:street":"310Th Ave Nw",
    "iso:country":"US",
    "sg:address":"24760 310th Ave NW",
    "sg:city":"Fisher",
    "sg:phone":"+1 218 281 1867",
    "sg:postcode":"56762",
    "sg:province":"MN",
    "sg:tags":[
        "farm",
        "grain",
        "beet",
        "cash"
    ],
    "wof:name":"Roger Beiswenger",
    "wof:placetype":"venue"
},
  "geometry": {"coordinates":[-96.718068,48.233149],"type":"Point"}
}