{
  "type": "Feature",
  "properties": {
    "addr:full":"1889 Perimeter Rd Saint Paul MN 55113",
    "addr:housenumber":"1889",
    "addr:postcode":"55113",
    "addr:street":"Perimeter Rd",
    "iso:country":"US",
    "sg:address":"1889 Perimeter Rd",
    "sg:city":"Saint Paul",
    "sg:classifiers":[
        {
            "category":"Restaurant",
            "type":"Food & Drink"
        }
    ],
    "sg:menulink":"http://www.allmenus.com/mn/roseville/208776-taco-bell/menu/",
    "sg:phone":"+1 651 636 3991",
    "sg:postcode":"55113",
    "sg:province":"MN",
    "sg:tags":[
        "mexican"
    ],
    "wof:name":"Taco Bell",
    "wof:placetype":"venue"
},
  "geometry": {"coordinates":[-93.17955600000001,45.012354],"type":"Point"}
}