{
  "type": "Feature",
  "properties": {
    "iso:country":"US",
    "sg:address":"1200 Mendelssohn Ave N",
    "sg:city":"Golden Valley",
    "sg:classifiers":[
        {
            "category":"Insurance",
            "subcategory":"Insurance Agent",
            "type":"Services"
        }
    ],
    "sg:phone":"+1 763 546 6334",
    "sg:postcode":"55427",
    "sg:province":"MN",
    "wof:name":"Action Insurance Brokers",
    "wof:placetype":"venue"
},
  "geometry": {"coordinates":[-93.400139,44.992981],"type":"Point"}
}