{
  "type": "Feature",
  "properties": {
    "addr:full":"1124 15th Ave NE East Grand Forks MN 56721",
    "addr:housenumber":"1124",
    "addr:postcode":"56721",
    "addr:street":"15Th Ave Ne",
    "iso:country":"US",
    "sg:address":"1124 15th Ave NE",
    "sg:city":"East Grand Forks",
    "sg:classifiers":[
        {
            "category":"Manufacturing",
            "subcategory":"Tools & Machinery",
            "type":"Manufacturing & Wholesale Goods"
        }
    ],
    "sg:phone":"+1 218 773 4010",
    "sg:postcode":"56721",
    "sg:province":"MN",
    "sg:tags":[
        "shop",
        "job"
    ],
    "wof:name":"Northern Valley Machine Inc",
    "wof:placetype":"venue"
},
  "geometry": {"coordinates":[-96.992301,47.936269],"type":"Point"}
}