{
  "type": "Feature",
  "properties": {
    "addr:full":"3642 Scheuneman Rd Saint Paul MN 55110",
    "addr:housenumber":"3642",
    "addr:postcode":"55110",
    "addr:street":"Scheuneman Rd",
    "iso:country":"US",
    "sg:address":"3642 Scheuneman Rd",
    "sg:city":"Saint Paul",
    "sg:classifiers":[
        {
            "category":"Building & Trades",
            "subcategory":"Construction",
            "type":"Services"
        },
        {
            "category":"Home & Garden",
            "subcategory":"Furniture",
            "type":"Retail Goods"
        }
    ],
    "sg:phone":"+1 651 653 0477",
    "sg:postcode":"55110",
    "sg:province":"MN",
    "sg:tags":[
        "cabinet",
        "custom"
    ],
    "wof:name":"Arnco Industries Inc",
    "wof:placetype":"venue"
},
  "geometry": {"coordinates":[-93.033153,45.054021],"type":"Point"}
}