{
  "type": "Feature",
  "properties": {
    "addr:full":"113 10th Ave W Grand Marais MN 55604",
    "addr:housenumber":"113",
    "addr:postcode":"55604",
    "addr:street":"10Th Ave W",
    "iso:country":"US",
    "sg:address":"113 10th Ave W",
    "sg:city":"Grand Marais",
    "sg:classifiers":[
        {
            "category":"Professional",
            "subcategory":"Business Services",
            "type":"Services"
        }
    ],
    "sg:phone":"+1 218 387 9700",
    "sg:postcode":"55604",
    "sg:province":"MN",
    "sg:tags":[
        "manufacture",
        "product",
        "proprietary",
        "market"
    ],
    "wof:name":"North Shore Design Build",
    "wof:placetype":"venue"
},
  "geometry": {"coordinates":[-90.34701800000001,47.75151],"type":"Point"}
}