{
  "type": "Feature",
  "properties": {
    "addr:full":"9822 Ottumwa Ave N Stillwater MN 55082",
    "addr:housenumber":"9822",
    "addr:postcode":"55082",
    "addr:street":"Ottumwa Ave N",
    "iso:country":"US",
    "sg:address":"9822 Ottumwa Ave N",
    "sg:city":"Stillwater",
    "sg:classifiers":[
        {
            "category":"Real Estate",
            "subcategory":"Real Estate Agent",
            "type":"Services"
        }
    ],
    "sg:phone":"+1 651 210 2441",
    "sg:postcode":"55082",
    "sg:province":"MN",
    "wof:name":"American Family Realty",
    "wof:placetype":"venue"
},
  "geometry": {"coordinates":[-92.805684,45.090604],"type":"Point"}
}