{
  "type": "Feature",
  "properties": {
    "addr:full":"12805 37th Ave N Minneapolis MN 55441",
    "addr:housenumber":"12805",
    "addr:postcode":"55441",
    "addr:street":"37Th Ave N",
    "iso:country":"US",
    "sg:address":"12805 37th Ave N",
    "sg:city":"Minneapolis",
    "sg:classifiers":[
        {
            "category":"Shopping",
            "subcategory":"Clothing, Apparel, & Fashions",
            "type":"Retail Goods"
        }
    ],
    "sg:phone":"+1 763 557 9941",
    "sg:postcode":"55441",
    "sg:province":"MN",
    "sg:tags":[
        "professional"
    ],
    "wof:name":"Herff Jones",
    "wof:placetype":"venue"
},
  "geometry": {"coordinates":[-93.44255699999999,45.022596],"type":"Point"}
}