{
  "type": "Feature",
  "properties": {
    "addr:full":"15038 102nd St Becker MN 55308",
    "addr:housenumber":"15038",
    "addr:postcode":"55308",
    "addr:street":"102Nd St",
    "iso:country":"US",
    "sg:address":"15038 102nd St",
    "sg:city":"Becker",
    "sg:classifiers":[
        {
            "category":"Professional",
            "subcategory":"Computer Services",
            "type":"Services"
        }
    ],
    "sg:phone":"+1 763 261 5498",
    "sg:postcode":"55308",
    "sg:province":"MN",
    "sg:tags":[
        "related"
    ],
    "wof:name":"B & N Entr",
    "wof:placetype":"venue"
},
  "geometry": {"coordinates":[-93.84961800000001,45.422708],"type":"Point"}
}