{
  "type": "Feature",
  "properties": {
    "iso:country":"US",
    "sg:address":"14194 Tradewinds Rd",
    "sg:city":"Audubon",
    "sg:phone":"+1 218 233 3492",
    "sg:postcode":"56511",
    "sg:province":"MN",
    "sg:tags":[
        "farm",
        "beet",
        "grain",
        "cash",
        "soybean"
    ],
    "wof:name":"Tom Grover",
    "wof:placetype":"venue"
},
  "geometry": {"coordinates":[-96.036804,46.776659],"type":"Point"}
}