{
  "type": "Feature",
  "properties": {
    "iso:country":"US",
    "sg:address":"1120 E 80th St",
    "sg:city":"Minneapolis",
    "sg:classifiers":[
        {
            "category":"Real Estate",
            "subcategory":"Real Estate Agent",
            "type":"Services"
        }
    ],
    "sg:phone":"+1 952 858 8580",
    "sg:postcode":"55420",
    "sg:province":"MN",
    "sg:tags":[
        "appraiser"
    ],
    "wof:name":"GJS Appraising",
    "wof:placetype":"venue"
},
  "geometry": {"coordinates":[-93.261838,44.857706],"type":"Point"}
}