{
  "type": "Feature",
  "properties": {
    "iso:country":"US",
    "sg:address":"11900 Wayzata Blvd #209",
    "sg:city":"Hopkins",
    "sg:classifiers":[
        {
            "category":"Social Services",
            "type":"Services"
        },
        {
            "category":"Professional",
            "type":"Services"
        },
        {
            "category":"Professional",
            "subcategory":"Lawyer & Legal Services",
            "type":"Services"
        },
        {
            "category":"Health Services",
            "subcategory":"Health Practitioner",
            "type":"Services"
        }
    ],
    "sg:phone":"+1 952 746 7894",
    "sg:postcode":"55305",
    "sg:province":"MN",
    "sg:tags":[
        "psychotherapist",
        "assistance",
        "mediation",
        "worker",
        "divorce"
    ],
    "sg:website":"http://www.SusanBGarfieldLICSW.com",
    "wof:name":"Susan B Garfield Licsw",
    "wof:placetype":"venue"
},
  "geometry": {"coordinates":[-93.42928999999999,44.971331],"type":"Point"}
}