{
  "type": "Feature",
  "properties": {
    "iso:country":"US",
    "sg:address":"882 Winterberry Ct",
    "sg:city":"Saint Paul",
    "sg:classifiers":[
        {
            "category":"Building & Trades",
            "subcategory":"Construction",
            "type":"Services"
        }
    ],
    "sg:phone":"+1 651 731 4923",
    "sg:postcode":"55125",
    "sg:province":"MN",
    "sg:tags":[
        "heavy"
    ],
    "wof:name":"Sport Court",
    "wof:placetype":"venue"
},
  "geometry": {"coordinates":[-92.93106299999999,44.937106],"type":"Point"}
}