{
  "type": "Feature",
  "properties": {
    "iso:country":"US",
    "sg:address":"3384 Norwest Ct",
    "sg:city":"Eagan",
    "sg:classifiers":[
        {
            "category":"Travel",
            "subcategory":"Hotels & Motels",
            "type":"Entertainment"
        }
    ],
    "sg:phone":"+1 651 681 9991",
    "sg:postcode":"55121",
    "sg:province":"MN",
    "sg:tags":[
        "operations"
    ],
    "wof:name":"Extended Stay America",
    "wof:placetype":"venue"
},
  "geometry": {"coordinates":[-93.16727299999999,44.835257],"type":"Point"}
}