{
  "type": "Feature",
  "properties": {
    "addr:full":"1784 Peltier Lake Dr Hugo MN 55038",
    "addr:housenumber":"1784",
    "addr:postcode":"55038",
    "addr:street":"Peltier Lake Dr",
    "iso:country":"US",
    "sg:address":"1784 Peltier Lake Dr",
    "sg:city":"Hugo",
    "sg:classifiers":[
        {
            "category":"Professional",
            "subcategory":"Secretarial Services",
            "type":"Services"
        }
    ],
    "sg:phone":"+1 651 762 9355",
    "sg:postcode":"55038",
    "sg:province":"MN",
    "sg:tags":[
        "reporting"
    ],
    "wof:name":"Minneapolis Writing Servi",
    "wof:placetype":"venue"
},
  "geometry": {"coordinates":[-93.051394,45.170737],"type":"Point"}
}