{
  "type": "Feature",
  "properties": {
    "addr:full":"1315 Lancer Dr La Crescent MN 55947",
    "addr:housenumber":"1315",
    "addr:postcode":"55947",
    "addr:street":"Lancer Dr",
    "iso:country":"US",
    "sg:address":"1315 Lancer Dr",
    "sg:city":"La Crescent",
    "sg:classifiers":[
        {
            "category":"Real Estate",
            "subcategory":"Real Estate Operator",
            "type":"Services"
        }
    ],
    "sg:phone":"+1 507 895 4040",
    "sg:postcode":"55947",
    "sg:province":"MN",
    "sg:tags":[
        "apartment"
    ],
    "wof:name":"Lancer Apartments",
    "wof:placetype":"venue"
},
  "geometry": {"coordinates":[-91.31364499999999,43.814889],"type":"Point"}
}