{
  "type": "Feature",
  "properties": {
    "iso:country":"US",
    "sg:address":"9905 13th Ave N",
    "sg:city":"Minneapolis",
    "sg:classifiers":[
        {
            "category":"Autos & Motor Vehicles",
            "subcategory":"Auto Supplies",
            "type":"Retail Goods"
        },
        {
            "category":"Sports & Exercise",
            "subcategory":"Race Track",
            "type":"Entertainment"
        }
    ],
    "sg:phone":"+1 763 545 3800",
    "sg:postcode":"55441",
    "sg:province":"MN",
    "sg:tags":[
        "automobile",
        "equipment",
        "part",
        "car",
        "performance",
        "racing"
    ],
    "wof:name":"Modern Automotive Performance",
    "wof:placetype":"venue"
},
  "geometry": {"coordinates":[-93.404318,44.993297],"type":"Point"}
}