{
  "type": "Feature",
  "properties": {
    "iso:country":"US",
    "sg:address":"4701 US Hwy 61",
    "sg:city":"White Bear Lake",
    "sg:classifiers":[
        {
            "category":"Government",
            "subcategory":"Office",
            "type":"Public Place"
        }
    ],
    "sg:phone":"+1 651 429 8562",
    "sg:postcode":"55110",
    "sg:province":"MN",
    "sg:tags":[
        "village"
    ],
    "sg:website":"www.whitebearlake.org",
    "wof:name":"White Bear Lake Comm Dev Dir",
    "wof:placetype":"venue"
},
  "geometry": {"coordinates":[-93.01291999999999,45.082021],"type":"Point"}
}