{
  "type": "Feature",
  "properties": {
    "iso:country":"US",
    "sg:address":"1524 Woodlane Dr",
    "sg:city":"Saint Paul",
    "sg:classifiers":[
        {
            "category":"Shopping",
            "subcategory":"Books",
            "type":"Retail Goods"
        }
    ],
    "sg:phone":"+1 651 730 0661",
    "sg:postcode":"55125",
    "sg:province":"MN",
    "sg:tags":[
        "used",
        "merchandise"
    ],
    "wof:name":"Book Corner The",
    "wof:placetype":"venue"
},
  "geometry": {"coordinates":[-92.96443600000001,44.928944],"type":"Point"}
}