{
  "type": "Feature",
  "properties": {
    "iso:country":"US",
    "sg:address":"27689 474th St",
    "sg:city":"Laporte",
    "sg:classifiers":[
        {
            "category":"Organizations",
            "subcategory":"Religious Organization",
            "type":"Services"
        }
    ],
    "sg:phone":"+1 218 224 3266",
    "sg:postcode":"56461",
    "sg:province":"MN",
    "wof:name":"Trinity Lutheran Church",
    "wof:placetype":"venue"
},
  "geometry": {"coordinates":[-94.78230600000001,47.344873],"type":"Point"}
}