{
  "type": "Feature",
  "properties": {
    "iso:country":"US",
    "sg:address":"26715 Xerxes Trl",
    "sg:city":"Elko",
    "sg:classifiers":[
        {
            "category":"Building & Trades",
            "subcategory":"Construction",
            "type":"Services"
        }
    ],
    "sg:phone":"+1 952 461 3257",
    "sg:postcode":"55020",
    "sg:province":"MN",
    "sg:tags":[
        "concrete",
        "masonry",
        "contractor"
    ],
    "wof:name":"Frederickson Concrete & Masnry",
    "wof:placetype":"venue"
},
  "geometry": {"coordinates":[-93.32037800000001,44.562576],"type":"Point"}
}