{
  "type": "Feature",
  "properties": {
    "iso:country":"US",
    "sg:address":"510 N Chestnut St",
    "sg:city":"Chaska",
    "sg:classifiers":[
        {
            "category":"Social Services",
            "type":"Services"
        }
    ],
    "sg:phone":"+1 952 448 5425",
    "sg:postcode":"55318",
    "sg:province":"MN",
    "sg:tags":[
        "counseling"
    ],
    "wof:name":"Sexual Violence Ctr",
    "wof:placetype":"venue"
},
  "geometry": {"coordinates":[-93.601449,44.78845],"type":"Point"}
}