{
  "type": "Feature",
  "properties": {
    "addr:full":"1115 30th Ave N Minneapolis MN 55411",
    "addr:housenumber":"1115",
    "addr:postcode":"55411",
    "addr:street":"30Th Ave N",
    "iso:country":"US",
    "sg:address":"1115 30th Ave N",
    "sg:city":"Minneapolis",
    "sg:classifiers":[
        {
            "category":"Place Of Worship",
            "subcategory":"Church",
            "type":"Public Place"
        },
        {
            "category":"Place Of Worship",
            "type":"Public Place"
        }
    ],
    "sg:phone":"+1 612 521 2670",
    "sg:postcode":"55411",
    "sg:province":"MN",
    "sg:tags":[
        "churches-baptist-general",
        "churches-baptist"
    ],
    "wof:name":"New Baptist Church",
    "wof:placetype":"venue"
},
  "geometry": {"coordinates":[-93.293244,45.011312],"type":"Point"}
}