{
  "type": "Feature",
  "properties": {
    "iso:country":"US",
    "sg:address":"529 E Washington St",
    "sg:city":"Ely",
    "sg:classifiers":[
        {
            "category":"Professional",
            "subcategory":"Business Services",
            "type":"Services"
        }
    ],
    "sg:phone":"+1 218 365 3570",
    "sg:postcode":"55731",
    "sg:province":"MN",
    "wof:name":"Reedy Auction Service",
    "wof:placetype":"venue"
},
  "geometry": {"coordinates":[-91.858288,47.905786],"type":"Point"}
}