{
  "type": "Feature",
  "properties": {
    "addr:full":"214 NW 1st Ave Grand Rapids MN 55744",
    "addr:housenumber":"214",
    "addr:postcode":"55744",
    "addr:street":"Nw 1St Ave",
    "iso:country":"US",
    "sg:address":"214 NW 1st Ave",
    "sg:city":"Grand Rapids",
    "sg:classifiers":[
        {
            "category":"Insurance",
            "subcategory":"Insurance Agent",
            "type":"Services"
        }
    ],
    "sg:phone":"+1 218 326 0304",
    "sg:postcode":"55744",
    "sg:province":"MN",
    "wof:name":"Niemala Financial Svc & Ins",
    "wof:placetype":"venue"
},
  "geometry": {"coordinates":[-93.529804,47.234758],"type":"Point"}
}