{
  "type": "Feature",
  "properties": {
    "iso:country":"US",
    "sg:address":"3224 Co Rd 8",
    "sg:city":"Brainerd",
    "sg:classifiers":[
        {
            "category":"Building & Trades",
            "subcategory":"Construction",
            "type":"Services"
        }
    ],
    "sg:phone":"+1 218 764 2681",
    "sg:postcode":"56401",
    "sg:province":"MN",
    "sg:tags":[
        "excavating",
        "contractor"
    ],
    "wof:name":"Ground Breakers",
    "wof:placetype":"venue"
},
  "geometry": {"coordinates":[-93.912237,46.200089],"type":"Point"}
}