{
  "type": "Feature",
  "properties": {
    "addr:full":"66272 430th Ave Mazeppa MN 55956",
    "addr:housenumber":"66272",
    "addr:postcode":"55956",
    "addr:street":"430Th Ave",
    "iso:country":"US",
    "sg:address":"66272 430th Ave",
    "sg:city":"Mazeppa",
    "sg:classifiers":[
        {
            "category":"Travel",
            "subcategory":"Hotels & Motels",
            "type":"Entertainment"
        },
        {
            "category":"Travel",
            "subcategory":"Resort",
            "type":"Entertainment"
        }
    ],
    "sg:phone":"+1 507 843 5321",
    "sg:postcode":"55956",
    "sg:province":"MN",
    "wof:name":"Arendt's Holstein Resort Inc.",
    "wof:placetype":"venue"
},
  "geometry": {"coordinates":[-92.531532,44.339947],"type":"Point"}
}