{
  "type": "Feature",
  "properties": {
    "addr:full":"115 Elm St E Annandale MN 55302",
    "addr:housenumber":"115",
    "addr:postcode":"55302",
    "addr:street":"Elm St E",
    "iso:country":"US",
    "sg:address":"115 Elm St E",
    "sg:city":"Annandale",
    "sg:classifiers":[
        {
            "category":"Autos & Motor Vehicles",
            "subcategory":"Fuel & Gas Station",
            "type":"Retail Goods"
        }
    ],
    "sg:phone":"+1 320 274 5657",
    "sg:postcode":"55302",
    "sg:province":"MN",
    "sg:tags":[
        "store"
    ],
    "wof:name":"Holiday Stationstores 234",
    "wof:placetype":"venue"
},
  "geometry": {"coordinates":[-94.122963,45.261142],"type":"Point"}
}