{
  "type": "Feature",
  "properties": {
    "iso:country":"US",
    "sg:address":"601 W 46th St",
    "sg:city":"Minneapolis",
    "sg:classifiers":[
        {
            "category":"Professional",
            "type":"Services"
        }
    ],
    "sg:phone":"+1 612 824 3000",
    "sg:postcode":"55419",
    "sg:province":"MN",
    "sg:tags":[
        "establishment"
    ],
    "wof:name":"Bergadon & Co",
    "wof:placetype":"venue"
},
  "geometry": {"coordinates":[-93.288315,44.919567],"type":"Point"}
}