{
  "type": "Feature",
  "properties": {
    "iso:country":"US",
    "sg:address":"413 N Norman St",
    "sg:city":"Ivanhoe",
    "sg:classifiers":[
        {
            "category":"Wholesale",
            "subcategory":"Hardware",
            "type":"Manufacturing & Wholesale Goods"
        },
        {
            "category":"Home & Garden",
            "subcategory":"Garden Supply",
            "type":"Retail Goods"
        },
        {
            "category":"Retail",
            "subcategory":"Repair Shop",
            "type":"Services"
        }
    ],
    "sg:phone":"+1 507 694 1241",
    "sg:postcode":"56142",
    "sg:province":"MN",
    "sg:tags":[
        "renting",
        "lawn",
        "outdoor",
        "power",
        "landscaping",
        "equipment-sales",
        "equipment",
        "saw"
    ],
    "sg:website":"http://www.stihlusa.com/",
    "wof:name":"Lipinski Small Engine",
    "wof:placetype":"venue"
},
  "geometry": {"coordinates":[-96.24726800000001,44.463417],"type":"Point"}
}