{
  "type": "Feature",
  "properties": {
    "addr:full":"2111 E. Franklin Ave Minneapolis MN 55404",
    "addr:housenumber":"2111",
    "addr:postcode":"55404",
    "addr:street":"E. Franklin Ave",
    "iso:country":"US",
    "sg:address":"2111 E. Franklin Ave",
    "sg:city":"Minneapolis",
    "sg:classifiers":[
        {
            "category":"Restaurant",
            "type":"Food & Drink"
        }
    ],
    "sg:phone":"+1 612 353 3389",
    "sg:postcode":"55404",
    "sg:province":"MN",
    "sg:tags":[
        "sushi",
        "bar",
        "japanese"
    ],
    "sg:website":"www.koyisushitoo.com/",
    "wof:name":"Koyi Sushi Too",
    "wof:placetype":"venue"
},
  "geometry": {"coordinates":[-93.24234199999999,44.962731],"type":"Point"}
}