{
  "type": "Feature",
  "properties": {
    "iso:country":"US",
    "sg:address":"47 Lake St S",
    "sg:city":"Big Lake",
    "sg:classifiers":[
        {
            "category":"Bars & Pubs",
            "type":"Food & Drink"
        }
    ],
    "sg:phone":"+1 763 263 8800",
    "sg:postcode":"55309",
    "sg:province":"MN",
    "wof:name":"Scooters Bar & Grille",
    "wof:placetype":"venue"
},
  "geometry": {"coordinates":[-93.74597900000001,45.331743],"type":"Point"}
}