{
  "type": "Feature",
  "properties": {
    "addr:full":"700 2nd Ave NW Rochester MN 55901",
    "addr:housenumber":"700",
    "addr:postcode":"55901",
    "addr:street":"2Nd Ave Nw",
    "iso:country":"US",
    "sg:address":"700 2nd Ave NW",
    "sg:city":"Rochester",
    "sg:classifiers":[
        {
            "category":"Community Center",
            "subcategory":"Senior",
            "type":"Public Place"
        },
        {
            "category":"Building & Trades",
            "subcategory":"Landscaping Services",
            "type":"Services"
        },
        {
            "category":"Social Services",
            "subcategory":"Adult Care",
            "type":"Services"
        }
    ],
    "sg:phone":"+1 507 288 4883",
    "sg:postcode":"55901",
    "sg:province":"MN",
    "sg:tags":[
        "counseling",
        "aged",
        "homes-institutional",
        "citizen"
    ],
    "wof:name":"Arbor Terrace",
    "wof:placetype":"venue"
},
  "geometry": {"coordinates":[-92.465942,44.030418],"type":"Point"}
}