{
  "type": "Feature",
  "properties": {
    "addr:full":"15150 Finn N Feather Blvd SE Bemidji MN 56601",
    "addr:postcode":"15150;56601",
    "addr:street":"Finn N Feather Blvd Se",
    "iso:country":"US",
    "sg:address":"15150 Finn N Feather Blvd SE",
    "sg:city":"Bemidji",
    "sg:classifiers":[
        {
            "category":"Travel",
            "subcategory":"Hotels & Motels",
            "type":"Entertainment"
        }
    ],
    "sg:phone":"+1 218 335 6598",
    "sg:postcode":"56601",
    "sg:province":"MN",
    "sg:tags":[
        "resort"
    ],
    "wof:name":"Finn N Feather Resort",
    "wof:placetype":"venue"
},
  "geometry": {"coordinates":[-94.661103,47.441299],"type":"Point"}
}