{
  "type": "Feature",
  "properties": {
    "iso:country":"US",
    "sg:address":"2590 Jackson St",
    "sg:city":"St Paul",
    "sg:classifiers":[
        {
            "category":"Building & Trades",
            "subcategory":"Construction",
            "type":"Services"
        }
    ],
    "sg:phone":"+1 651 484 6418",
    "sg:postcode":"55117",
    "sg:province":"MN",
    "sg:tags":[
        "painter",
        "special",
        "contractor"
    ],
    "wof:name":"Feickert Decorating Inc",
    "wof:placetype":"venue"
},
  "geometry": {"coordinates":[-93.096649,45.019543],"type":"Point"}
}