{
  "type": "Feature",
  "properties": {
    "iso:country":"US",
    "sg:address":"202 10th St S",
    "sg:city":"Moorhead",
    "sg:classifiers":[
        {
            "category":"Education",
            "subcategory":"School",
            "type":"Public Place"
        }
    ],
    "sg:phone":"+1 218 233 0553",
    "sg:postcode":"56560",
    "sg:province":"MN",
    "wof:name":"St Joseph School",
    "wof:placetype":"venue"
},
  "geometry": {"coordinates":[-96.764752,46.871691],"type":"Point"}
}