{
  "type": "Feature",
  "properties": {
    "iso:country":"US",
    "sg:address":"3118 162nd Ln NW",
    "sg:city":"Anoka",
    "sg:classifiers":[
        {
            "category":"Freight",
            "type":"Transportation"
        }
    ],
    "sg:phone":"+1 763 427 3110",
    "sg:postcode":"55304",
    "sg:province":"MN",
    "sg:tags":[
        "hauling",
        "trucking"
    ],
    "wof:name":"Ham Lake Haulers",
    "wof:placetype":"venue"
},
  "geometry": {"coordinates":[-93.34495699999999,45.265085],"type":"Point"}
}