{
  "type": "Feature",
  "properties": {
    "iso:country":"US",
    "sg:address":"1635 140th St E",
    "sg:city":"Dundas",
    "sg:classifiers":[
        {
            "category":"Freight",
            "type":"Transportation"
        }
    ],
    "sg:phone":"+1 507 334 0627",
    "sg:postcode":"55019",
    "sg:province":"MN",
    "sg:tags":[
        "operator",
        "local",
        "trucking"
    ],
    "wof:name":"Thomas Farm",
    "wof:placetype":"venue"
},
  "geometry": {"coordinates":[-93.26923499999999,44.385141],"type":"Point"}
}