{
  "type": "Feature",
  "properties": {
    "addr:full":"9752 Hemlock Rd NW Rice MN 56367",
    "addr:housenumber":"9752",
    "addr:postcode":"56367",
    "addr:street":"Hemlock Rd Nw",
    "iso:country":"US",
    "sg:address":"9752 Hemlock Rd NW",
    "sg:city":"Rice",
    "sg:classifiers":[
        {
            "category":"Food & Beverages",
            "subcategory":"Meat & Fish",
            "type":"Retail Goods"
        }
    ],
    "sg:phone":"+1 320 393 3570",
    "sg:postcode":"56367",
    "sg:province":"MN",
    "wof:name":"Cloverdale Meats & Fax Line",
    "wof:placetype":"venue"
},
  "geometry": {"coordinates":[-94.178014,45.708719],"type":"Point"}
}