{
  "type": "Feature",
  "properties": {
    "addr:full":"2985 Water Tower Pl Chanhassen MN 55317",
    "addr:housenumber":"2985",
    "addr:postcode":"55317",
    "addr:street":"Water Tower Pl",
    "iso:country":"US",
    "sg:address":"2985 Water Tower Pl",
    "sg:city":"Chanhassen",
    "sg:classifiers":[
        {
            "category":"Shopping",
            "subcategory":"Bicycles & Sporting Goods",
            "type":"Retail Goods"
        },
        {
            "category":"Sports & Exercise",
            "subcategory":"Swimming Pool",
            "type":"Entertainment"
        }
    ],
    "sg:phone":"+1 952 368 6070",
    "sg:postcode":"55317",
    "sg:province":"MN",
    "sg:website":"www.premierpools.com",
    "wof:name":"Premier Pool & Spa",
    "wof:placetype":"venue"
},
  "geometry": {"coordinates":[-93.59636500000001,44.859346],"type":"Point"}
}