{
  "type": "Feature",
  "properties": {
    "iso:country":"US",
    "sg:address":"109 W James St",
    "sg:city":"Paynesville",
    "sg:classifiers":[
        {
            "category":"Professional",
            "subcategory":"Computer Services",
            "type":"Services"
        }
    ],
    "sg:phone":"+1 320 243 7515",
    "sg:postcode":"56362",
    "sg:province":"MN",
    "sg:tags":[
        "scanning"
    ],
    "sg:website":"www.colormax.com",
    "wof:name":"Color Max",
    "wof:placetype":"venue"
},
  "geometry": {"coordinates":[-94.71437899999999,45.381819],"type":"Point"}
}