{
  "type": "Feature",
  "properties": {
    "addr:full":"111 S Shannon Dr Shakopee MN 55379",
    "addr:housenumber":"111",
    "addr:postcode":"55379",
    "addr:street":"S Shannon Dr",
    "iso:country":"US",
    "sg:address":"111 S Shannon Dr",
    "sg:city":"Shakopee",
    "sg:classifiers":[
        {
            "category":"Professional",
            "subcategory":"Business Services",
            "type":"Services"
        }
    ],
    "sg:phone":"+1 952 445 1628",
    "sg:postcode":"55379",
    "sg:province":"MN",
    "wof:name":"Benner Dubois Partnership",
    "wof:placetype":"venue"
},
  "geometry": {"coordinates":[-93.52147100000001,44.765704],"type":"Point"}
}