{
  "type": "Feature",
  "properties": {
    "iso:country":"US",
    "sg:address":"6716 190th Ln NW",
    "sg:city":"Anoka",
    "sg:classifiers":[
        {
            "category":"Building & Trades",
            "subcategory":"Cleaning & Sanitation",
            "type":"Services"
        }
    ],
    "sg:phone":"+1 763 753 9890",
    "sg:postcode":"55303",
    "sg:province":"MN",
    "sg:tags":[
        "maintenance"
    ],
    "wof:name":"Helping Hand Cleaning",
    "wof:placetype":"venue"
},
  "geometry": {"coordinates":[-93.439295,45.31617],"type":"Point"}
}