{
  "type": "Feature",
  "properties": {
    "addr:full":"420 Delaware St SE Minneapolis MN 55455",
    "addr:housenumber":"420",
    "addr:postcode":"55455",
    "addr:street":"Delaware St Se",
    "iso:country":"US",
    "sg:address":"420 Delaware St SE",
    "sg:city":"Minneapolis",
    "sg:classifiers":[
        {
            "category":"Education",
            "subcategory":"University",
            "type":"Public Place"
        }
    ],
    "sg:phone":"+1 612 624 1164",
    "sg:postcode":"55455",
    "sg:province":"MN",
    "sg:tags":[
        "college"
    ],
    "wof:name":"International Adoption Clinic-University of Mnnsta",
    "wof:placetype":"venue"
},
  "geometry": {"coordinates":[-93.234596,44.972401],"type":"Point"}
}