{
  "type": "Feature",
  "properties": {
    "iso:country":"US",
    "sg:address":"1103 Southbend Ave",
    "sg:city":"Mankato",
    "sg:classifiers":[
        {
            "category":"Retail",
            "subcategory":"Auto Repair",
            "type":"Services"
        }
    ],
    "sg:phone":"+1 507 388 4599",
    "sg:postcode":"56001",
    "sg:province":"MN",
    "sg:tags":[
        "mustang",
        "dealership",
        "truck",
        "general"
    ],
    "wof:name":"Minnesota Truck & Tractor",
    "wof:placetype":"venue"
},
  "geometry": {"coordinates":[-94.05382400000001,44.151728],"type":"Point"}
}