{
  "type": "Feature",
  "properties": {
    "iso:country":"US",
    "sg:address":"1900 8th St N",
    "sg:city":"St Cloud",
    "sg:classifiers":[
        {
            "category":"Retail",
            "subcategory":"Funeral Services",
            "type":"Services"
        }
    ],
    "sg:phone":"+1 320 252 2522",
    "sg:postcode":"56303",
    "sg:province":"MN",
    "sg:tags":[
        "director"
    ],
    "wof:name":"Williams Funeral Home",
    "wof:placetype":"venue"
},
  "geometry": {"coordinates":[-94.18104,45.565329],"type":"Point"}
}