{
  "type": "Feature",
  "properties": {
    "addr:full":"5205 Central Ave NE Fridley MN 55421",
    "addr:housenumber":"5205",
    "addr:postcode":"55421",
    "addr:street":"Central Ave Ne",
    "iso:country":"US",
    "sg:address":"5205 Central Ave NE",
    "sg:city":"Fridley",
    "sg:classifiers":[
        {
            "category":"Banks & Credit Unions",
            "subcategory":"Bank",
            "type":"Services"
        }
    ],
    "sg:phone":"+1 612 823 2265",
    "sg:postcode":"55421",
    "sg:province":"MN",
    "wof:name":"TCF Bank",
    "wof:placetype":"venue"
},
  "geometry": {"coordinates":[-93.247664,45.064342],"type":"Point"}
}