{
  "type": "Feature",
  "properties": {
    "addr:full":"1700 Broadway Ave N Rochester MN 55906",
    "addr:housenumber":"1700",
    "addr:postcode":"55906",
    "addr:street":"Broadway Ave N",
    "iso:country":"US",
    "sg:address":"1700 Broadway Ave N",
    "sg:city":"Rochester",
    "sg:classifiers":[
        {
            "category":"Social Services",
            "type":"Services"
        },
        {
            "category":"Personal",
            "type":"Services"
        }
    ],
    "sg:phone":"+1 507 285 9337",
    "sg:postcode":"55906",
    "sg:province":"MN",
    "sg:tags":[
        "family",
        "professional",
        "counselors-licensed",
        "individual",
        "marriage",
        "child",
        "counseling",
        "counselor"
    ],
    "wof:name":"Brink Gary Lmft",
    "wof:placetype":"venue"
},
  "geometry": {"coordinates":[-92.46064,44.041359],"type":"Point"}
}