{
  "type": "Feature",
  "properties": {
    "iso:country":"US",
    "sg:address":"8621 Columbine Rd",
    "sg:city":"Eden Prairie",
    "sg:classifiers":[
        {
            "category":"Real Estate",
            "subcategory":"Real Estate Operator",
            "type":"Services"
        }
    ],
    "sg:phone":"+1 952 914 0446",
    "sg:postcode":"55344",
    "sg:province":"MN",
    "wof:name":"Columbine Townhomes",
    "wof:placetype":"venue"
},
  "geometry": {"coordinates":[-93.440397,44.848266],"type":"Point"}
}