{
  "type": "Feature",
  "properties": {
    "addr:full":"7870 University Ave NE Fridley MN 55432",
    "addr:housenumber":"7870",
    "addr:postcode":"55432",
    "addr:street":"University Ave Ne",
    "iso:country":"US",
    "sg:address":"7870 University Ave NE",
    "sg:city":"Fridley",
    "sg:classifiers":[
        {
            "category":"Banks & Credit Unions",
            "subcategory":"Bank",
            "type":"Services"
        }
    ],
    "sg:phone":"+1 763 574 7500",
    "sg:postcode":"55432",
    "sg:province":"MN",
    "sg:tags":[
        "loan",
        "real estate"
    ],
    "wof:name":"Pro Action Mortgage",
    "wof:placetype":"venue"
},
  "geometry": {"coordinates":[-93.26364,45.110541],"type":"Point"}
}