{
  "type": "Feature",
  "properties": {
    "addr:full":"116 Broadway Ave S New Richland MN 56072",
    "addr:housenumber":"116",
    "addr:postcode":"56072",
    "addr:street":"Broadway Ave S New",
    "iso:country":"US",
    "sg:address":"116 Broadway Ave S",
    "sg:city":"New Richland",
    "sg:classifiers":[
        {
            "category":"Shopping",
            "subcategory":"Used Merchandise",
            "type":"Retail Goods"
        }
    ],
    "sg:phone":"+1 507 463 3443",
    "sg:postcode":"56072",
    "sg:province":"MN",
    "sg:tags":[
        "shop",
        "consignment"
    ],
    "wof:name":"Lady Bug Thrift Shop",
    "wof:placetype":"venue"
},
  "geometry": {"coordinates":[-93.49393000000001,43.893696],"type":"Point"}
}