{
  "type": "Feature",
  "properties": {
    "iso:country":"US",
    "sg:address":"7782 Goedderz Rd",
    "sg:city":"Baxter",
    "sg:classifiers":[
        {
            "category":"Retail",
            "subcategory":"Auto Repair",
            "type":"Services"
        }
    ],
    "sg:phone":"+1 218 824 4222",
    "sg:postcode":"56425",
    "sg:province":"MN",
    "sg:tags":[
        "body",
        "painting",
        "repairing",
        "automobile"
    ],
    "wof:name":"Abc Collision Repair & Detail",
    "wof:placetype":"venue"
},
  "geometry": {"coordinates":[-94.241438,46.345755],"type":"Point"}
}