{
  "type": "Feature",
  "properties": {
    "addr:full":"4389 Pleasant St SE Prior Lake MN 55372",
    "addr:housenumber":"4389",
    "addr:postcode":"55372",
    "addr:street":"Pleasant St Se",
    "iso:country":"US",
    "sg:address":"4389 Pleasant St SE",
    "sg:city":"Prior Lake",
    "sg:classifiers":[
        {
            "category":"Building & Trades",
            "subcategory":"Landscaping Services",
            "type":"Services"
        }
    ],
    "sg:phone":"+1 952 440 6104",
    "sg:postcode":"55372",
    "sg:province":"MN",
    "sg:tags":[
        "tree"
    ],
    "wof:name":"Thomas Tree Svc",
    "wof:placetype":"venue"
},
  "geometry": {"coordinates":[-93.430736,44.712632],"type":"Point"}
}