{
  "type": "Feature",
  "properties": {
    "addr:full":"401 Elder Cir NW St Michael MN 55376",
    "addr:housenumber":"401",
    "addr:postcode":"55376",
    "addr:street":"Elder Cir Nw St",
    "iso:country":"US",
    "sg:address":"401 Elder Cir NW",
    "sg:city":"St Michael",
    "sg:classifiers":[
        {
            "category":"Building & Trades",
            "subcategory":"Construction",
            "type":"Services"
        }
    ],
    "sg:phone":"+1 763 497 8146",
    "sg:postcode":"55376",
    "sg:province":"MN",
    "sg:tags":[
        "masonry",
        "contractor"
    ],
    "wof:name":"Newman Brick & Stone Masonry",
    "wof:placetype":"venue"
},
  "geometry": {"coordinates":[-93.67426399999999,45.216924],"type":"Point"}
}