{
  "type": "Feature",
  "properties": {
    "addr:full":"30875 320th St NW Crookston MN 56713",
    "addr:housenumber":"30875",
    "addr:postcode":"56713",
    "addr:street":"320Th St Nw",
    "iso:country":"US",
    "sg:address":"30875 320th St NW",
    "sg:city":"Crookston",
    "sg:phone":"+1 218 281 6708",
    "sg:postcode":"56713",
    "sg:province":"MN",
    "sg:tags":[
        "farm",
        "beet"
    ],
    "wof:name":"David Sylvester",
    "wof:placetype":"venue"
},
  "geometry": {"coordinates":[-96.7159,48.340384],"type":"Point"}
}