{
  "type": "Feature",
  "properties": {
    "addr:full":"2403 S Broadway St New Ulm MN 56073",
    "addr:housenumber":"2403",
    "addr:postcode":"56073",
    "addr:street":"S Broadway St",
    "iso:country":"US",
    "sg:address":"2403 S Broadway St",
    "sg:city":"New Ulm",
    "sg:classifiers":[
        {
            "category":"Autos & Motor Vehicles",
            "subcategory":"Automobile Sales",
            "type":"Retail Goods"
        }
    ],
    "sg:phone":"+1 507 354 3410",
    "sg:postcode":"56073",
    "sg:province":"MN",
    "sg:tags":[
        "car",
        "dealer"
    ],
    "sg:website":"www.madaymotors.com",
    "wof:name":"Maday Motors Jeep Eagle",
    "wof:placetype":"venue"
},
  "geometry": {"coordinates":[-94.436471,44.287617],"type":"Point"}
}