{
  "type": "Feature",
  "properties": {
    "addr:full":"219 Jefferson St N Wadena MN 56482",
    "addr:housenumber":"219",
    "addr:postcode":"56482",
    "addr:street":"Jefferson St N",
    "iso:country":"US",
    "sg:address":"219 Jefferson St N",
    "sg:city":"Wadena",
    "sg:classifiers":[
        {
            "category":"Insurance",
            "subcategory":"Insurance Agent",
            "type":"Services"
        }
    ],
    "sg:phone":"+1 218 631 4545",
    "sg:postcode":"56482",
    "sg:province":"MN",
    "wof:name":"Farm Bureau Insurance",
    "wof:placetype":"venue"
},
  "geometry": {"coordinates":[-95.134787,46.443987],"type":"Point"}
}