{
  "type": "Feature",
  "properties": {
    "iso:country":"US",
    "sg:address":"19650 Territorial Rd",
    "sg:city":"Osseo",
    "sg:classifiers":[
        {
            "category":"Home & Garden",
            "subcategory":"Garden Supply",
            "type":"Retail Goods"
        }
    ],
    "sg:phone":"+1 763 428 4933",
    "sg:postcode":"55311",
    "sg:province":"MN",
    "sg:tags":[
        "supp",
        "landscape"
    ],
    "wof:name":"Dundee Nursery & Ldscpg Co",
    "wof:placetype":"venue"
},
  "geometry": {"coordinates":[-93.526049,45.166506],"type":"Point"}
}