{
  "type": "Feature",
  "properties": {
    "iso:country":"US",
    "sg:address":"3 Civic Center Plz",
    "sg:city":"Mankato",
    "sg:classifiers":[
        {
            "category":"Professional",
            "subcategory":"Lawyer & Legal Services",
            "type":"Services"
        }
    ],
    "sg:phone":"+1 507 345 4505",
    "sg:postcode":"56001",
    "sg:province":"MN",
    "sg:tags":[
        "attorney"
    ],
    "sg:website":"http://www.frentzandfrentz.com",
    "wof:name":"Frentz & Frentz Law Offices",
    "wof:placetype":"venue"
},
  "geometry": {"coordinates":[-94.003969,44.165288],"type":"Point"}
}