{
  "type": "Feature",
  "properties": {
    "iso:country":"US",
    "sg:address":"399 Central Ave E",
    "sg:city":"St Michael",
    "sg:classifiers":[
        {
            "category":"Health Services",
            "subcategory":"Doctor",
            "type":"Services"
        }
    ],
    "sg:phone":"+1 763 497 2040",
    "sg:postcode":"55376",
    "sg:province":"MN",
    "sg:tags":[
        "dentist"
    ],
    "wof:name":"Dental Center",
    "wof:placetype":"venue"
},
  "geometry": {"coordinates":[-93.656341,45.209968],"type":"Point"}
}