{
  "type": "Feature",
  "properties": {
    "addr:full":"1420 29th Ave N St Cloud MN 56303",
    "addr:housenumber":"1420",
    "addr:postcode":"56303",
    "addr:street":"29Th Ave N",
    "iso:country":"US",
    "sg:address":"1420 29th Ave N",
    "sg:city":"St Cloud",
    "sg:classifiers":[
        {
            "category":"Organizations",
            "subcategory":"Religious Organization",
            "type":"Services"
        }
    ],
    "sg:phone":"+1 320 252 4355",
    "sg:postcode":"56303",
    "sg:province":"MN",
    "sg:tags":[
        "church"
    ],
    "wof:name":"Church Of Jesus Christ Of Lds",
    "wof:placetype":"venue"
},
  "geometry": {"coordinates":[-94.193,45.57636],"type":"Point"}
}