{
  "type": "Feature",
  "properties": {
    "iso:country":"US",
    "sg:address":"3308 W 44th St",
    "sg:city":"Minneapolis",
    "sg:classifiers":[
        {
            "category":"Real Estate",
            "subcategory":"Real Estate Agent",
            "type":"Services"
        }
    ],
    "sg:phone":"+1 612 929 9200",
    "sg:postcode":"55410",
    "sg:province":"MN",
    "wof:name":"Teamkendall Inc",
    "wof:placetype":"venue"
},
  "geometry": {"coordinates":[-93.322649,44.923406],"type":"Point"}
}