{
  "type": "Feature",
  "properties": {
    "iso:country":"US",
    "sg:address":"101 W Nokomis St",
    "sg:city":"Osakis",
    "sg:classifiers":[
        {
            "category":"Retail",
            "subcategory":"Funeral Services",
            "type":"Services"
        }
    ],
    "sg:phone":"+1 320 859 2118",
    "sg:postcode":"56360",
    "sg:province":"MN",
    "sg:tags":[
        "director"
    ],
    "wof:name":"Hetland Funeral Home",
    "wof:placetype":"venue"
},
  "geometry": {"coordinates":[-95.15573500000001,45.867141],"type":"Point"}
}