{
  "type": "Feature",
  "properties": {
    "addr:full":"8318 State Hwy 23 St Cloud MN 56301",
    "addr:housenumber":"8318",
    "addr:postcode":"56301",
    "addr:street":"State Hwy 23",
    "iso:country":"US",
    "sg:address":"8318 State Hwy 23",
    "sg:city":"St Cloud",
    "sg:classifiers":[
        {
            "category":"Shopping",
            "subcategory":"Used Merchandise",
            "type":"Retail Goods"
        }
    ],
    "sg:phone":"+1 320 253 6573",
    "sg:postcode":"56301",
    "sg:province":"MN",
    "sg:tags":[
        "antique"
    ],
    "wof:name":"Depot Antique Mall",
    "wof:placetype":"venue"
},
  "geometry": {"coordinates":[-94.28962199999999,45.511889],"type":"Point"}
}