{
  "type": "Feature",
  "properties": {
    "iso:country":"US",
    "sg:address":"815 2nd St E",
    "sg:city":"Northfield",
    "sg:classifiers":[
        {
            "category":"Professional",
            "subcategory":"Management & Consulting",
            "type":"Services"
        }
    ],
    "sg:phone":"+1 507 663 8963",
    "sg:postcode":"55057",
    "sg:province":"MN",
    "wof:name":"Horizon",
    "wof:placetype":"venue"
},
  "geometry": {"coordinates":[-93.14926800000001,44.458515],"type":"Point"}
}