{
  "type": "Feature",
  "properties": {
    "addr:full":"12132 120th St Villard MN 56385",
    "addr:housenumber":"12132",
    "addr:postcode":"56385",
    "addr:street":"120Th St Villard",
    "iso:country":"US",
    "sg:address":"12132 120th St",
    "sg:city":"Villard",
    "sg:phone":"+1 320 554 7971",
    "sg:postcode":"56385",
    "sg:province":"MN",
    "sg:tags":[
        "farm",
        "field",
        "corn",
        "crop"
    ],
    "wof:name":"Peter Ruegemer",
    "wof:placetype":"venue"
},
  "geometry": {"coordinates":[-95.199062,45.73005],"type":"Point"}
}