{
  "type": "Feature",
  "properties": {
    "addr:full":"9803 35th St NE Saint Michael MN 55376",
    "addr:housenumber":"9803",
    "addr:postcode":"55376",
    "addr:street":"35Th St Ne Saint Michael",
    "iso:country":"US",
    "sg:address":"9803 35th St NE",
    "sg:city":"Saint Michael",
    "sg:classifiers":[
        {
            "category":"Shopping",
            "subcategory":"Shoes",
            "type":"Retail Goods"
        }
    ],
    "sg:phone":"+1 763 497 3189",
    "sg:postcode":"55376",
    "sg:province":"MN",
    "wof:name":"Serene Feet",
    "wof:placetype":"venue"
},
  "geometry": {"coordinates":[-93.690707,45.202667],"type":"Point"}
}