{
  "type": "Feature",
  "properties": {
    "addr:full":"23360 Academy Ave Excelsior MN 55331",
    "addr:housenumber":"23360",
    "addr:postcode":"55331",
    "addr:street":"Academy Ave",
    "iso:country":"US",
    "sg:address":"23360 Academy Ave",
    "sg:city":"Excelsior",
    "sg:classifiers":[
        {
            "category":"Professional",
            "type":"Services"
        }
    ],
    "sg:phone":"+1 952 401 3431",
    "sg:postcode":"55331",
    "sg:province":"MN",
    "sg:tags":[
        "establishment"
    ],
    "wof:name":"Treasures Old & New",
    "wof:placetype":"venue"
},
  "geometry": {"coordinates":[-93.576307,44.897058],"type":"Point"}
}