{
  "type": "Feature",
  "properties": {
    "addr:full":"9855 Hamilton Rd Eden Prairie MN 55344",
    "addr:housenumber":"9855",
    "addr:postcode":"55344",
    "addr:street":"Hamilton Rd",
    "iso:country":"US",
    "sg:address":"9855 Hamilton Rd",
    "sg:city":"Eden Prairie",
    "sg:classifiers":[
        {
            "category":"Wholesale",
            "subcategory":"Office Equipment",
            "type":"Manufacturing & Wholesale Goods"
        }
    ],
    "sg:phone":"+1 952 941 6230",
    "sg:postcode":"55344",
    "sg:province":"MN",
    "sg:tags":[
        "industrial",
        "supply"
    ],
    "sg:website":"www.csystems.com",
    "wof:name":"Carlson Systems LLC",
    "wof:placetype":"venue"
},
  "geometry": {"coordinates":[-93.40165399999999,44.880854],"type":"Point"}
}