{
  "type": "Feature",
  "properties": {
    "iso:country":"US",
    "sg:address":"4285 Ithaca Ln N",
    "sg:city":"Minneapolis",
    "sg:classifiers":[
        {
            "category":"Professional",
            "subcategory":"Accounting & Tax Preparation",
            "type":"Services"
        }
    ],
    "sg:phone":"+1 763 557 0222",
    "sg:postcode":"55446",
    "sg:province":"MN",
    "sg:tags":[
        "return"
    ],
    "wof:name":"Yerys Income Tax",
    "wof:placetype":"venue"
},
  "geometry": {"coordinates":[-93.464569,45.03276],"type":"Point"}
}