{
  "type": "Feature",
  "properties": {
    "addr:full":"318 2nd St Grand Marais MN 55604",
    "addr:housenumber":"318",
    "addr:postcode":"55604",
    "addr:street":"2Nd St",
    "iso:country":"US",
    "sg:address":"318 2nd St",
    "sg:city":"Grand Marais",
    "sg:classifiers":[
        {
            "category":"Building & Trades",
            "subcategory":"Construction",
            "type":"Services"
        }
    ],
    "sg:phone":"+1 218 387 9872",
    "sg:postcode":"55604",
    "sg:province":"MN",
    "sg:tags":[
        "installation",
        "carpet"
    ],
    "wof:name":"John R Kunshier",
    "wof:placetype":"venue"
},
  "geometry": {"coordinates":[-90.338514,47.751779],"type":"Point"}
}