{
  "type": "Feature",
  "properties": {
    "iso:country":"US",
    "sg:address":"243 Broadway St W",
    "sg:city":"Monticello",
    "sg:classifiers":[
        {
            "category":"Real Estate",
            "subcategory":"Real Estate Operator",
            "type":"Services"
        }
    ],
    "sg:phone":"+1 651 644 9600",
    "sg:postcode":"55362",
    "sg:province":"MN",
    "sg:tags":[
        "apartment"
    ],
    "wof:name":"Broadway Square",
    "wof:placetype":"venue"
},
  "geometry": {"coordinates":[-93.796527,45.306529],"type":"Point"}
}