{
  "type": "Feature",
  "properties": {
    "addr:full":"1645 White Bear Ave N Saint Paul MN 55106",
    "addr:housenumber":"1645",
    "addr:postcode":"55106",
    "addr:street":"White Bear Ave N",
    "iso:country":"US",
    "sg:address":"1645 White Bear Ave N",
    "sg:city":"Saint Paul",
    "sg:classifiers":[
        {
            "category":"Retail",
            "subcategory":"Laundry & Dry Cleaning",
            "type":"Services"
        }
    ],
    "sg:phone":"+1 651 776 3485",
    "sg:postcode":"55106",
    "sg:province":"MN",
    "sg:tags":[
        "drycleaning",
        "plant"
    ],
    "wof:name":"Grand Cleaners",
    "wof:placetype":"venue"
},
  "geometry": {"coordinates":[-93.025299,44.99027],"type":"Point"}
}