{
  "type": "Feature",
  "properties": {
    "iso:country":"US",
    "sg:address":"1675 81st St E",
    "sg:city":"Hugo",
    "sg:classifiers":[
        {
            "category":"Personal",
            "type":"Services"
        }
    ],
    "sg:phone":"+1 651 429 4490",
    "sg:postcode":"55038",
    "sg:province":"MN",
    "wof:name":"Trev Co",
    "wof:placetype":"venue"
},
  "geometry": {"coordinates":[-93.057813,45.200306],"type":"Point"}
}