{
  "type": "Feature",
  "properties": {
    "iso:country":"US",
    "sg:address":"15903 Gooseberry Way",
    "sg:city":"Saint Paul",
    "sg:classifiers":[
        {
            "category":"Professional",
            "subcategory":"Employment Agencies",
            "type":"Services"
        }
    ],
    "sg:phone":"+1 952 432 0679",
    "sg:postcode":"55124",
    "sg:province":"MN",
    "sg:tags":[
        "help",
        "supply"
    ],
    "wof:name":"MTA Enterprises",
    "wof:placetype":"venue"
},
  "geometry": {"coordinates":[-93.218806,44.718675],"type":"Point"}
}