{
  "type": "Feature",
  "properties": {
    "iso:country":"US",
    "sg:address":"625 3rd Ave NW",
    "sg:city":"Faribault",
    "sg:classifiers":[
        {
            "category":"Professional",
            "subcategory":"Advertising",
            "type":"Services"
        }
    ],
    "sg:phone":"+1 507 330 3469",
    "sg:postcode":"55021",
    "sg:province":"MN",
    "sg:tags":[
        "counselor"
    ],
    "wof:name":"Brand Savvy Advertising",
    "wof:placetype":"venue"
},
  "geometry": {"coordinates":[-93.273062,44.297808],"type":"Point"}
}