{
  "type": "Feature",
  "properties": {
    "addr:full":"201 W Park Rd Hopkins MN 55343",
    "addr:housenumber":"201",
    "addr:postcode":"55343",
    "addr:street":"W Park Rd",
    "iso:country":"US",
    "sg:address":"201 W Park Rd",
    "sg:city":"Hopkins",
    "sg:classifiers":[
        {
            "category":"Professional",
            "subcategory":"Computer Services",
            "type":"Services"
        }
    ],
    "sg:phone":"+1 952 933 6868",
    "sg:postcode":"55343",
    "sg:province":"MN",
    "sg:tags":[
        "graphic"
    ],
    "sg:website":"http://www.customdatabase.com",
    "wof:name":"Custom Database Solutions",
    "wof:placetype":"venue"
},
  "geometry": {"coordinates":[-93.427299,44.928108],"type":"Point"}
}