{
  "type": "Feature",
  "properties": {
    "addr:full":"3621 Velvet St Sandstone MN 55072",
    "addr:housenumber":"3621",
    "addr:postcode":"55072",
    "addr:street":"Velvet St",
    "iso:country":"US",
    "sg:address":"3621 Velvet St",
    "sg:city":"Sandstone",
    "sg:classifiers":[
        {
            "category":"Health Services",
            "subcategory":"Clinic",
            "type":"Services"
        }
    ],
    "sg:phone":"+1 320 245 2850",
    "sg:postcode":"55072",
    "sg:province":"MN",
    "wof:name":"Minnesota Rural Health Assoc",
    "wof:placetype":"venue"
},
  "geometry": {"coordinates":[-93.075514,46.117333],"type":"Point"}
}