{
  "type": "Feature",
  "properties": {
    "addr:full":"7700 Hudson Rd Woodbury MN 55125",
    "addr:housenumber":"7700",
    "addr:postcode":"55125",
    "addr:street":"Hudson Rd",
    "iso:country":"US",
    "sg:address":"7700 Hudson Rd",
    "sg:city":"Woodbury",
    "sg:classifiers":[
        {
            "category":"Shopping",
            "subcategory":"Bicycles & Sporting Goods",
            "type":"Retail Goods"
        }
    ],
    "sg:phone":"+1 651 739 2399",
    "sg:postcode":"55125",
    "sg:province":"MN",
    "sg:tags":[
        "equipment",
        "exercise"
    ],
    "wof:name":"Exercise Equipment Outlet",
    "wof:placetype":"venue"
},
  "geometry": {"coordinates":[-92.951593,44.94747],"type":"Point"}
}