{
  "type": "Feature",
  "properties": {
    "iso:country":"US",
    "sg:address":"6507 114th Ave N",
    "sg:city":"Champlin",
    "sg:classifiers":[
        {
            "category":"Arts & Performance",
            "subcategory":"Theater",
            "type":"Entertainment"
        }
    ],
    "sg:phone":"+1 763 323 9882",
    "sg:postcode":"55316",
    "sg:province":"MN",
    "sg:tags":[
        "jockey",
        "disc",
        "group"
    ],
    "wof:name":"Crystal Pyramid Production",
    "wof:placetype":"venue"
},
  "geometry": {"coordinates":[-93.363851,45.161252],"type":"Point"}
}