{
  "type": "Feature",
  "properties": {
    "addr:full":"615 E 3rd St Graceville MN 56240",
    "addr:housenumber":"615",
    "addr:postcode":"56240",
    "addr:street":"E 3Rd St",
    "iso:country":"US",
    "sg:address":"615 E 3rd St",
    "sg:city":"Graceville",
    "sg:classifiers":[
        {
            "category":"Personal",
            "subcategory":"Beauty Salon",
            "type":"Services"
        }
    ],
    "sg:phone":"+1 320 748 7937",
    "sg:postcode":"56240",
    "sg:province":"MN",
    "wof:name":"J&R Headquarters",
    "wof:placetype":"venue"
},
  "geometry": {"coordinates":[-96.43477300000001,45.568058],"type":"Point"}
}