{
  "type": "Feature",
  "properties": {
    "iso:country":"US",
    "sg:address":"4436 Zenith Ave N",
    "sg:city":"Minneapolis",
    "sg:classifiers":[
        {
            "category":"Retail",
            "subcategory":"Repair Shop",
            "type":"Services"
        }
    ],
    "sg:phone":"+1 763 535 6612",
    "sg:postcode":"55422",
    "sg:province":"MN",
    "sg:tags":[
        "welding"
    ],
    "wof:name":"Fuller Welding Co",
    "wof:placetype":"venue"
},
  "geometry": {"coordinates":[-93.32124899999999,45.034359],"type":"Point"}
}