{
  "type": "Feature",
  "properties": {
    "iso:country":"US",
    "sg:address":"10432 Purdey Rd",
    "sg:city":"Eden Prairie",
    "sg:classifiers":[
        {
            "category":"Building & Trades",
            "subcategory":"Construction",
            "type":"Services"
        }
    ],
    "sg:phone":"+1 952 829 7600",
    "sg:postcode":"55347",
    "sg:province":"MN",
    "sg:tags":[
        "contractor"
    ],
    "wof:name":"Sather Company Inc",
    "wof:placetype":"venue"
},
  "geometry": {"coordinates":[-93.410352,44.812781],"type":"Point"}
}