{
  "type": "Feature",
  "properties": {
    "addr:full":"307 12th St S Buffalo MN 55313",
    "addr:housenumber":"307",
    "addr:postcode":"55313",
    "addr:street":"12Th St S",
    "iso:country":"US",
    "sg:address":"307 12th St S",
    "sg:city":"Buffalo",
    "sg:classifiers":[
        {
            "category":"Personal",
            "type":"Services"
        }
    ],
    "sg:phone":"+1 763 684 4115",
    "sg:postcode":"55313",
    "sg:province":"MN",
    "sg:tags":[
        "therapist",
        "massage"
    ],
    "wof:name":"Zachman Massage & Body Works",
    "wof:placetype":"venue"
},
  "geometry": {"coordinates":[-93.874653,45.156541],"type":"Point"}
}