{
  "type": "Feature",
  "properties": {
    "addr:full":"651 E Old Shakopee Rd Minneapolis MN 55420",
    "addr:housenumber":"651",
    "addr:postcode":"55420",
    "addr:street":"E Old Shakopee Rd",
    "iso:country":"US",
    "sg:address":"651 E Old Shakopee Rd",
    "sg:city":"Minneapolis",
    "sg:classifiers":[
        {
            "category":"Home & Garden",
            "subcategory":"Home Furnishings",
            "type":"Retail Goods"
        }
    ],
    "sg:phone":"+1 952 884 6972",
    "sg:postcode":"55420",
    "sg:province":"MN",
    "sg:tags":[
        "bakery"
    ],
    "wof:name":"Top Tier",
    "wof:placetype":"venue"
},
  "geometry": {"coordinates":[-93.26662899999999,44.826251],"type":"Point"}
}