{
  "type": "Feature",
  "properties": {
    "iso:country":"US",
    "sg:address":"1453 Creekside Dr",
    "sg:city":"Waconia",
    "sg:classifiers":[
        {
            "category":"Building & Trades",
            "subcategory":"Equipment Rental",
            "type":"Services"
        }
    ],
    "sg:phone":"+1 952 442 7450",
    "sg:postcode":"55387",
    "sg:province":"MN",
    "wof:name":"Audio Logic Pro Sound Company",
    "wof:placetype":"venue"
},
  "geometry": {"coordinates":[-93.8073,44.837324],"type":"Point"}
}