{
  "type": "Feature",
  "properties": {
    "iso:country":"US",
    "sg:address":"3621 Plymouth Rd",
    "sg:city":"Hopkins",
    "sg:classifiers":[
        {
            "category":"Professional",
            "subcategory":"Employment Agencies",
            "type":"Services"
        }
    ],
    "sg:phone":"+1 952 933 5285",
    "sg:postcode":"55305",
    "sg:province":"MN",
    "sg:tags":[
        "medical",
        "help"
    ],
    "wof:name":"Nurse Connection Inc",
    "wof:placetype":"venue"
},
  "geometry": {"coordinates":[-93.441654,44.937158],"type":"Point"}
}