{
  "type": "Feature",
  "properties": {
    "addr:full":"2950 E Pioneer Rd Duluth MN 55804",
    "addr:housenumber":"2950",
    "addr:postcode":"55804",
    "addr:street":"E Pioneer Rd",
    "iso:country":"US",
    "sg:address":"2950 E Pioneer Rd",
    "sg:city":"Duluth",
    "sg:classifiers":[
        {
            "category":"Building & Trades",
            "subcategory":"Construction",
            "type":"Services"
        }
    ],
    "sg:phone":"+1 218 525 0509",
    "sg:postcode":"55804",
    "sg:province":"MN",
    "sg:tags":[
        "house"
    ],
    "wof:name":"Don Mitchell Construction Inc",
    "wof:placetype":"venue"
},
  "geometry": {"coordinates":[-91.98998400000001,46.966865],"type":"Point"}
}