{
  "type": "Feature",
  "properties": {
    "addr:full":"50 Riverview Dr Winona MN 55987",
    "addr:housenumber":"50",
    "addr:postcode":"55987",
    "addr:street":"Riverview Dr",
    "iso:country":"US",
    "sg:address":"50 Riverview Dr",
    "sg:city":"Winona",
    "sg:classifiers":[
        {
            "category":"Food & Beverages",
            "subcategory":"Groceries & Convenience Stores",
            "type":"Retail Goods"
        }
    ],
    "sg:phone":"+1 507 452 7622",
    "sg:postcode":"55987",
    "sg:province":"MN",
    "wof:name":"Sinclair Retail",
    "wof:placetype":"venue"
},
  "geometry": {"coordinates":[-91.642698,44.055198],"type":"Point"}
}