{
  "type": "Feature",
  "properties": {
    "iso:country":"US",
    "sg:address":"26362 370th Ave",
    "sg:city":"Hillman",
    "sg:classifiers":[
        {
            "category":"Health Services",
            "subcategory":"Doctor",
            "type":"Services"
        }
    ],
    "sg:phone":"+1 320 277 3682",
    "sg:postcode":"56338",
    "sg:province":"MN",
    "sg:tags":[
        "clinic"
    ],
    "wof:name":"Mille Lacs Family Clinics",
    "wof:placetype":"venue"
},
  "geometry": {"coordinates":[-93.89313,46.156101],"type":"Point"}
}