{
  "type": "Feature",
  "properties": {
    "addr:full":"1636 Hilo Ave N Saint Paul MN 55128",
    "addr:housenumber":"1636",
    "addr:postcode":"55128",
    "addr:street":"Hilo Ave N",
    "iso:country":"US",
    "sg:address":"1636 Hilo Ave N",
    "sg:city":"Saint Paul",
    "sg:classifiers":[
        {
            "category":"Professional",
            "subcategory":"Art Services",
            "type":"Services"
        }
    ],
    "sg:phone":"+1 651 739 1636",
    "sg:postcode":"55128",
    "sg:province":"MN",
    "sg:tags":[
        "commercial",
        "design"
    ],
    "wof:name":"Van Tassel Design",
    "wof:placetype":"venue"
},
  "geometry": {"coordinates":[-92.949941,44.973185],"type":"Point"}
}