{
  "type": "Feature",
  "properties": {
    "addr:full":"1208 Southview Ln Albert Lea MN 56007",
    "addr:housenumber":"1208",
    "addr:postcode":"56007",
    "addr:street":"Southview Ln",
    "iso:country":"US",
    "sg:address":"1208 Southview Ln",
    "sg:city":"Albert Lea",
    "sg:classifiers":[
        {
            "category":"Social Services",
            "subcategory":"Child Care",
            "type":"Services"
        }
    ],
    "sg:phone":"+1 507 377 3263",
    "sg:postcode":"56007",
    "sg:province":"MN",
    "sg:tags":[
        "day",
        "merchandise"
    ],
    "wof:name":"Judy Mummert",
    "wof:placetype":"venue"
},
  "geometry": {"coordinates":[-93.38364900000001,43.637717],"type":"Point"}
}