{
  "type": "Feature",
  "properties": {
    "iso:country":"US",
    "sg:address":"198 Eastern Ave",
    "sg:city":"Vining",
    "sg:classifiers":[
        {
            "category":"Farming",
            "subcategory":"Dairy Farm",
            "type":"Manufacturing & Wholesale Goods"
        }
    ],
    "sg:phone":"+1 218 267 5321",
    "sg:postcode":"56588",
    "sg:province":"MN",
    "sg:tags":[
        "field",
        "corn",
        "crop"
    ],
    "wof:name":"Harold Thoems",
    "wof:placetype":"venue"
},
  "geometry": {"coordinates":[-95.510059,46.12535],"type":"Point"}
}