{
  "type": "Feature",
  "properties": {
    "addr:full":"6990 Alpine Trl Eden Prairie MN 55346",
    "addr:housenumber":"6990",
    "addr:postcode":"55346",
    "addr:street":"Alpine Trl",
    "iso:country":"US",
    "sg:address":"6990 Alpine Trl",
    "sg:city":"Eden Prairie",
    "sg:classifiers":[
        {
            "category":"Education",
            "subcategory":"School",
            "type":"Public Place"
        }
    ],
    "sg:phone":"+1 952 937 8428",
    "sg:postcode":"55346",
    "sg:province":"MN",
    "sg:tags":[
        "consulting",
        "business"
    ],
    "wof:name":"Walkabout School",
    "wof:placetype":"venue"
},
  "geometry": {"coordinates":[-93.484803,44.875962],"type":"Point"}
}