{
  "type": "Feature",
  "properties": {
    "iso:country":"US",
    "sg:address":"2213 Copperfield Dr",
    "sg:city":"Saint Paul",
    "sg:classifiers":[
        {
            "category":"Banks & Credit Unions",
            "subcategory":"Financial Services",
            "type":"Services"
        }
    ],
    "sg:phone":"+1 651 452 7453",
    "sg:postcode":"55120",
    "sg:province":"MN",
    "sg:tags":[
        "investor"
    ],
    "wof:name":"Investment Club Copperfield",
    "wof:placetype":"venue"
},
  "geometry": {"coordinates":[-93.110699,44.874207],"type":"Point"}
}