{
  "type": "Feature",
  "properties": {
    "addr:full":"21260 594th Ave Mankato MN 56001",
    "addr:housenumber":"21260",
    "addr:postcode":"56001",
    "addr:street":"594Th Ave",
    "iso:country":"US",
    "sg:address":"21260 594th Ave",
    "sg:city":"Mankato",
    "sg:classifiers":[
        {
            "category":"Social Services",
            "subcategory":"Child Care",
            "type":"Services"
        }
    ],
    "sg:phone":"+1 507 345 3828",
    "sg:postcode":"56001",
    "sg:province":"MN",
    "sg:tags":[
        "day"
    ],
    "wof:name":"Julie Bohnert",
    "wof:placetype":"venue"
},
  "geometry": {"coordinates":[-93.90895,44.155181],"type":"Point"}
}