{
  "type": "Feature",
  "properties": {
    "iso:country":"US",
    "sg:address":"4049 Minnehaha Ave",
    "sg:city":"Minneapolis",
    "sg:classifiers":[
        {
            "category":"Retail",
            "subcategory":"Laundry & Dry Cleaning",
            "type":"Services"
        }
    ],
    "sg:phone":"+1 612 724 1410",
    "sg:postcode":"55406",
    "sg:province":"MN",
    "wof:name":"Sew What",
    "wof:placetype":"venue"
},
  "geometry": {"coordinates":[-93.219976,44.928913],"type":"Point"}
}