{
  "type": "Feature",
  "properties": {
    "iso:country":"US",
    "sg:address":"700 Selby Ave",
    "sg:city":"St Paul",
    "sg:classifiers":[
        {
            "category":"Building & Trades",
            "subcategory":"Cleaning & Sanitation",
            "type":"Services"
        }
    ],
    "sg:phone":"+1 651 291 1270",
    "sg:postcode":"55104",
    "sg:province":"MN",
    "sg:tags":[
        "janitor"
    ],
    "wof:name":"Ham Cleaning Svc",
    "wof:placetype":"venue"
},
  "geometry": {"coordinates":[-93.130746,44.946529],"type":"Point"}
}