{
  "type": "Feature",
  "properties": {
    "addr:full":"919 Washington Ave Detroit Lakes MN 56501",
    "addr:housenumber":"919",
    "addr:postcode":"56501",
    "addr:street":"Washington Ave",
    "iso:country":"US",
    "sg:address":"919 Washington Ave",
    "sg:city":"Detroit Lakes",
    "sg:classifiers":[
        {
            "category":"Manufacturing",
            "subcategory":"Wood Products",
            "type":"Manufacturing & Wholesale Goods"
        }
    ],
    "sg:phone":"+1 218 847 1136",
    "sg:postcode":"56501",
    "sg:province":"MN",
    "sg:tags":[
        "mfg"
    ],
    "wof:name":"Trump Framing",
    "wof:placetype":"venue"
},
  "geometry": {"coordinates":[-95.845252,46.817003],"type":"Point"}
}