{
  "type": "Feature",
  "properties": {
    "addr:full":"1515 Saint Francis Ave Ste 100 Shakopee MN 55379",
    "addr:housenumber":"1515",
    "addr:postcode":"55379",
    "addr:street":"Saint Francis Ave Ste 100",
    "iso:country":"US",
    "sg:address":"1515 Saint Francis Ave Ste 100",
    "sg:city":"Shakopee",
    "sg:classifiers":[
        {
            "category":"Health Services",
            "subcategory":"Doctor",
            "type":"Services"
        },
        {
            "category":"Health Services",
            "subcategory":"Hospital",
            "type":"Services"
        }
    ],
    "sg:phone":"+1 952 403 3535",
    "sg:postcode":"55379",
    "sg:province":"MN",
    "sg:tags":[
        "medicine",
        "podiatrist",
        "practice",
        "internal",
        "family"
    ],
    "wof:name":"Lundgren George MD",
    "wof:placetype":"venue"
},
  "geometry": {"coordinates":[-93.502403,44.7701],"type":"Point"}
}