{
  "type": "Feature",
  "properties": {
    "iso:country":"US",
    "sg:address":"5700 Smetana Dr",
    "sg:city":"Hopkins",
    "sg:classifiers":[
        {
            "category":"Real Estate",
            "subcategory":"Real Estate Agent",
            "type":"Services"
        }
    ],
    "sg:phone":"+1 952 938 3418",
    "sg:postcode":"55343",
    "sg:province":"MN",
    "wof:name":"Hoyt Properties",
    "wof:placetype":"venue"
},
  "geometry": {"coordinates":[-93.404122,44.901323],"type":"Point"}
}