{
  "type": "Feature",
  "properties": {
    "addr:full":"620 E Howard St Hibbing MN 55746",
    "addr:housenumber":"620",
    "addr:postcode":"55746",
    "addr:street":"E Howard St",
    "iso:country":"US",
    "sg:address":"620 E Howard St",
    "sg:city":"Hibbing",
    "sg:classifiers":[
        {
            "category":"Local Transit",
            "type":"Transportation"
        }
    ],
    "sg:phone":"+1 218 262 6141",
    "sg:postcode":"55746",
    "sg:province":"MN",
    "sg:tags":[
        "bus",
        "line"
    ],
    "wof:name":"Tac Tran Inc",
    "wof:placetype":"venue"
},
  "geometry": {"coordinates":[-92.934926,47.427451],"type":"Point"}
}