{
  "type": "Feature",
  "properties": {
    "addr:full":"514 4th St N Browns Valley MN 56219",
    "addr:housenumber":"514",
    "addr:postcode":"56219",
    "addr:street":"4Th St N Browns",
    "iso:country":"US",
    "sg:address":"514 4th St N",
    "sg:city":"Browns Valley",
    "sg:classifiers":[
        {
            "category":"Retail",
            "subcategory":"Laundry & Dry Cleaning",
            "type":"Services"
        }
    ],
    "sg:phone":"+1 320 695 2163",
    "sg:postcode":"56219",
    "sg:province":"MN",
    "sg:tags":[
        "cleaners",
        "rug",
        "carpet"
    ],
    "wof:name":"K & D Carpet Cleaning",
    "wof:placetype":"venue"
},
  "geometry": {"coordinates":[-96.833815,45.600033],"type":"Point"}
}