{
  "type": "Feature",
  "properties": {
    "addr:full":"27285 Natchez Ave Elko MN 55020",
    "addr:housenumber":"27285",
    "addr:postcode":"55020",
    "addr:street":"Natchez Ave",
    "iso:country":"US",
    "sg:address":"27285 Natchez Ave",
    "sg:city":"Elko",
    "sg:classifiers":[
        {
            "category":"Manufacturing",
            "subcategory":"Metals",
            "type":"Manufacturing & Wholesale Goods"
        },
        {
            "category":"Building & Trades",
            "subcategory":"Construction",
            "type":"Services"
        }
    ],
    "sg:phone":"+1 952 461 8100",
    "sg:postcode":"55020",
    "sg:province":"MN",
    "sg:tags":[
        "hardware",
        "mantel",
        "mfg"
    ],
    "wof:name":"Custom Marble & Mantel",
    "wof:placetype":"venue"
},
  "geometry": {"coordinates":[-93.339187,44.552048],"type":"Point"}
}