{
  "type": "Feature",
  "properties": {
    "addr:full":"1305 4th St SE Austin MN 55912",
    "addr:housenumber":"1305",
    "addr:postcode":"55912",
    "addr:street":"4Th St Se",
    "iso:country":"US",
    "sg:address":"1305 4th St SE",
    "sg:city":"Austin",
    "sg:classifiers":[
        {
            "category":"Home & Garden",
            "subcategory":"Building Materials",
            "type":"Retail Goods"
        }
    ],
    "sg:phone":"+1 507 437 8264",
    "sg:postcode":"55912",
    "sg:province":"MN",
    "sg:tags":[
        "plate",
        "b",
        "door",
        "garage",
        "automotive",
        "glass",
        "window"
    ],
    "wof:name":"Viking Glass & Lock Service",
    "wof:placetype":"venue"
},
  "geometry": {"coordinates":[-92.96961,43.655843],"type":"Point"}
}