{
  "type": "Feature",
  "properties": {
    "iso:country":"US",
    "sg:address":"8200 Hill Trl N",
    "sg:city":"Lake Elmo",
    "sg:classifiers":[
        {
            "category":"Professional",
            "subcategory":"Employment Agencies",
            "type":"Services"
        }
    ],
    "sg:phone":"+1 651 777 4444",
    "sg:postcode":"55042",
    "sg:province":"MN",
    "wof:name":"Efficientjobmarketcom",
    "wof:placetype":"venue"
},
  "geometry": {"coordinates":[-92.941192,45.019145],"type":"Point"}
}