{
  "type": "Feature",
  "properties": {
    "iso:country":"US",
    "sg:address":"2208 Tower Ct",
    "sg:city":"Saint Paul",
    "sg:classifiers":[
        {
            "category":"Professional",
            "subcategory":"Business Services",
            "type":"Services"
        }
    ],
    "sg:phone":"+1 651 247 7713",
    "sg:postcode":"55125",
    "sg:province":"MN",
    "wof:name":"Gathje Enterprises LLC",
    "wof:placetype":"venue"
},
  "geometry": {"coordinates":[-92.94666100000001,44.916709],"type":"Point"}
}