{
  "type": "Feature",
  "properties": {
    "addr:full":"709 S Cherokee Ave St Paul MN 55107",
    "addr:housenumber":"709",
    "addr:postcode":"55107",
    "addr:street":"S Cherokee Ave",
    "iso:country":"US",
    "sg:address":"709 S Cherokee Ave",
    "sg:city":"St Paul",
    "sg:classifiers":[
        {
            "category":"Building & Trades",
            "subcategory":"Construction",
            "type":"Services"
        }
    ],
    "sg:phone":"+1 651 224 3442",
    "sg:postcode":"55107",
    "sg:province":"MN",
    "sg:tags":[
        "general",
        "contractor"
    ],
    "wof:name":"New Life Contracting Inc",
    "wof:placetype":"venue"
},
  "geometry": {"coordinates":[-93.104648,44.923611],"type":"Point"}
}