{
  "type": "Feature",
  "properties": {
    "iso:country":"US",
    "sg:address":"350 Main St N",
    "sg:city":"Stillwater",
    "sg:classifiers":[
        {
            "category":"Building & Trades",
            "subcategory":"Construction",
            "type":"Services"
        }
    ],
    "sg:phone":"+1 651 439 7690",
    "sg:postcode":"55082",
    "sg:province":"MN",
    "sg:tags":[
        "contractor"
    ],
    "wof:name":"WEIS Builders",
    "wof:placetype":"venue"
},
  "geometry": {"coordinates":[-92.80718,45.058992],"type":"Point"}
}