{
  "type": "Feature",
  "properties": {
    "iso:country":"US",
    "sg:address":"208 N Main St",
    "sg:city":"Granada",
    "sg:classifiers":[
        {
            "category":"Retail",
            "subcategory":"Auto Repair",
            "type":"Services"
        }
    ],
    "sg:phone":"+1 507 447 2400",
    "sg:postcode":"56039",
    "sg:province":"MN",
    "sg:tags":[
        "towing",
        "wrecker"
    ],
    "wof:name":"Granada Repair & Tow Service",
    "wof:placetype":"venue"
},
  "geometry": {"coordinates":[-94.34806399999999,43.69755],"type":"Point"}
}