{
  "type": "Feature",
  "properties": {
    "addr:full":"1922 Hemlock Ave Owatonna MN 55060",
    "addr:housenumber":"1922",
    "addr:postcode":"55060",
    "addr:street":"Hemlock Ave",
    "iso:country":"US",
    "sg:address":"1922 Hemlock Ave",
    "sg:city":"Owatonna",
    "sg:classifiers":[
        {
            "category":"Professional",
            "subcategory":"Business Services",
            "type":"Services"
        }
    ],
    "sg:phone":"+1 507 444 0218",
    "sg:postcode":"55060",
    "sg:province":"MN",
    "wof:name":"Growth Sales Inc",
    "wof:placetype":"venue"
},
  "geometry": {"coordinates":[-93.20662400000001,44.103652],"type":"Point"}
}