{
  "type": "Feature",
  "properties": {
    "iso:country":"US",
    "sg:address":"1315 S Broadway St",
    "sg:city":"New Ulm",
    "sg:classifiers":[
        {
            "category":"Wholesale",
            "subcategory":"Farm Supplies",
            "type":"Manufacturing & Wholesale Goods"
        }
    ],
    "sg:phone":"+1 507 359 2988",
    "sg:postcode":"56073",
    "sg:province":"MN",
    "wof:name":"Running Supply Inc",
    "wof:placetype":"venue"
},
  "geometry": {"coordinates":[-94.448109,44.299753],"type":"Point"}
}