{
  "type": "Feature",
  "properties": {
    "addr:full":"27589 Highway 65 NE Isanti MN 55040",
    "addr:housenumber":"27589",
    "addr:postcode":"55040",
    "addr:street":"Highway 65 Ne",
    "iso:country":"US",
    "sg:address":"27589 Highway 65 NE",
    "sg:city":"Isanti",
    "sg:classifiers":[
        {
            "category":"Building & Trades",
            "subcategory":"Construction",
            "type":"Services"
        }
    ],
    "sg:phone":"+1 763 434 8887",
    "sg:postcode":"55040",
    "sg:province":"MN",
    "sg:tags":[
        "repair",
        "air conditioning"
    ],
    "sg:website":"http://www.tradewindswholesale.com",
    "wof:name":"Tradewinds Wholesale",
    "wof:placetype":"venue"
},
  "geometry": {"coordinates":[-93.235049,45.469353],"type":"Point"}
}