{
  "type": "Feature",
  "properties": {
    "iso:country":"US",
    "sg:address":"23 Red River Ave N",
    "sg:city":"Cold Spring",
    "sg:classifiers":[
        {
            "category":"Personal",
            "subcategory":"Beauty Salon",
            "type":"Services"
        }
    ],
    "sg:phone":"+1 320 685 4452",
    "sg:postcode":"56320",
    "sg:province":"MN",
    "wof:name":"Styles Plus",
    "wof:placetype":"venue"
},
  "geometry": {"coordinates":[-94.429034,45.456647],"type":"Point"}
}