{
  "type": "Feature",
  "properties": {
    "addr:full":"8701 Wyoming Ave N Minneapolis MN 55445",
    "addr:housenumber":"8701",
    "addr:postcode":"55445",
    "addr:street":"Wyoming Ave N",
    "iso:country":"US",
    "sg:address":"8701 Wyoming Ave N",
    "sg:city":"Minneapolis",
    "sg:classifiers":[
        {
            "category":"Manufacturing",
            "subcategory":"Soap",
            "type":"Manufacturing & Wholesale Goods"
        }
    ],
    "sg:phone":"+1 763 424 4597",
    "sg:postcode":"55445",
    "sg:province":"MN",
    "sg:tags":[
        "detergents-wholesale",
        "manufacturer"
    ],
    "sg:website":"http://www.gilbychemical.com",
    "wof:name":"Gilby Products Inc.",
    "wof:placetype":"venue"
},
  "geometry": {"coordinates":[-93.384426,45.112247],"type":"Point"}
}