{
  "type": "Feature",
  "properties": {
    "addr:full":"910 Main St Red Wing MN 55066",
    "addr:housenumber":"910",
    "addr:postcode":"55066",
    "addr:street":"Main St",
    "iso:country":"US",
    "sg:address":"910 Main St",
    "sg:city":"Red Wing",
    "sg:classifiers":[
        {
            "category":"Insurance",
            "subcategory":"Insurance Agent",
            "type":"Services"
        }
    ],
    "sg:phone":"+1 651 388 7128",
    "sg:postcode":"55066",
    "sg:province":"MN",
    "wof:name":"Blue Cross & Blue Shield",
    "wof:placetype":"venue"
},
  "geometry": {"coordinates":[-92.540757,44.563603],"type":"Point"}
}