{
  "type": "Feature",
  "properties": {
    "addr:full":"704 S Washington Ave Spring Valley MN 55975",
    "addr:housenumber":"704",
    "addr:postcode":"55975",
    "addr:street":"S Washington Ave",
    "iso:country":"US",
    "sg:address":"704 S Washington Ave",
    "sg:city":"Spring Valley",
    "sg:classifiers":[
        {
            "category":"Health Services",
            "subcategory":"Chiropractor",
            "type":"Services"
        }
    ],
    "sg:phone":"+1 507 346 2748",
    "sg:postcode":"55975",
    "sg:province":"MN",
    "wof:name":"Spring Valley Chiropractic Ctr",
    "wof:placetype":"venue"
},
  "geometry": {"coordinates":[-92.39231599999999,43.681729],"type":"Point"}
}