{
  "type": "Feature",
  "properties": {
    "addr:full":"66672 200th St Alden MN 56009",
    "addr:housenumber":"66672",
    "addr:postcode":"56009",
    "addr:street":"200Th St",
    "iso:country":"US",
    "sg:address":"66672 200th St",
    "sg:city":"Alden",
    "sg:phone":"+1 507 265 3496",
    "sg:postcode":"56009",
    "sg:province":"MN",
    "sg:tags":[
        "farm",
        "corn"
    ],
    "wof:name":"Sandsmark Gary Farmer",
    "wof:placetype":"venue"
},
  "geometry": {"coordinates":[-93.53353,43.644074],"type":"Point"}
}