{
  "type": "Feature",
  "properties": {
    "addr:full":"601 6th St S Minneapolis MN 55415",
    "addr:housenumber":"601",
    "addr:postcode":"55415",
    "addr:street":"6Th St S",
    "iso:country":"US",
    "sg:address":"601 6th St S",
    "sg:city":"Minneapolis",
    "sg:classifiers":[
        {
            "category":"Parking",
            "type":"Transportation"
        }
    ],
    "sg:phone":"+1 612 338 2101",
    "sg:postcode":"55415",
    "sg:province":"MN",
    "sg:tags":[
        "garage"
    ],
    "wof:name":"Standard Parking",
    "wof:placetype":"venue"
},
  "geometry": {"coordinates":[-93.261864,44.97382],"type":"Point"}
}