{
  "type": "Feature",
  "properties": {
    "addr:full":"120 1st Ave E Shakopee MN 55379",
    "addr:housenumber":"120",
    "addr:postcode":"55379",
    "addr:street":"1St Ave E",
    "iso:country":"US",
    "sg:address":"120 1st Ave E",
    "sg:city":"Shakopee",
    "sg:classifiers":[
        {
            "category":"Insurance",
            "subcategory":"Insurance Agent",
            "type":"Services"
        }
    ],
    "sg:phone":"+1 952 445 9156",
    "sg:postcode":"55379",
    "sg:province":"MN",
    "wof:name":"Jerry Kucera Insurance",
    "wof:placetype":"venue"
},
  "geometry": {"coordinates":[-93.525885,44.799392],"type":"Point"}
}