{
  "type": "Feature",
  "properties": {
    "addr:full":"6171 Villa Ln NW Walker MN 56484",
    "addr:housenumber":"6171",
    "addr:postcode":"56484",
    "addr:street":"Villa Ln Nw",
    "iso:country":"US",
    "sg:address":"6171 Villa Ln NW",
    "sg:city":"Walker",
    "sg:classifiers":[
        {
            "category":"Home & Garden",
            "subcategory":"Furniture",
            "type":"Retail Goods"
        }
    ],
    "sg:phone":"+1 218 547 3111",
    "sg:postcode":"56484",
    "sg:province":"MN",
    "sg:tags":[
        "business",
        "merchandise"
    ],
    "wof:name":"Lines of Distinction Inc",
    "wof:placetype":"venue"
},
  "geometry": {"coordinates":[-94.610151,47.122251],"type":"Point"}
}