{
  "type": "Feature",
  "properties": {
    "addr:full":"1010 Washington Ave S Minneapolis MN 55415",
    "addr:housenumber":"1010",
    "addr:postcode":"55415",
    "addr:street":"Washington Ave S",
    "iso:country":"US",
    "sg:address":"1010 Washington Ave S",
    "sg:city":"Minneapolis",
    "sg:classifiers":[
        {
            "category":"Food & Beverages",
            "subcategory":"Liquor & Beverages",
            "type":"Retail Goods"
        }
    ],
    "sg:phone":"+1 612 339 4040",
    "sg:postcode":"55415",
    "sg:province":"MN",
    "sg:website":"www.liquordepot.com",
    "wof:name":"Liquor Depot",
    "wof:placetype":"venue"
},
  "geometry": {"coordinates":[-93.253203,44.975504],"type":"Point"}
}