{
  "type": "Feature",
  "properties": {
    "addr:full":"3628 Garden Blvd Saint Paul MN 55128",
    "addr:housenumber":"3628",
    "addr:postcode":"55128",
    "addr:street":"Garden Blvd",
    "iso:country":"US",
    "sg:address":"3628 Garden Blvd",
    "sg:city":"Saint Paul",
    "sg:classifiers":[
        {
            "category":"Health Services",
            "subcategory":"Medical Lab",
            "type":"Services"
        }
    ],
    "sg:phone":"+1 651 777 6017",
    "sg:postcode":"55128",
    "sg:province":"MN",
    "sg:tags":[
        "laboratory",
        "dental"
    ],
    "wof:name":"Lawrence Dental Ceramics Inc",
    "wof:placetype":"venue"
},
  "geometry": {"coordinates":[-92.972522,45.000076],"type":"Point"}
}