{
  "type": "Feature",
  "properties": {
    "addr:full":"2002 W Superior St Duluth MN 55806",
    "addr:housenumber":"2002",
    "addr:postcode":"55806",
    "addr:street":"W Superior St",
    "iso:country":"US",
    "sg:address":"2002 W Superior St",
    "sg:city":"Duluth",
    "sg:classifiers":[
        {
            "category":"Insurance",
            "subcategory":"Insurance Agent",
            "type":"Services"
        }
    ],
    "sg:phone":"+1 218 722 2972",
    "sg:postcode":"55806",
    "sg:province":"MN",
    "wof:name":"American National Insurance Co",
    "wof:placetype":"venue"
},
  "geometry": {"coordinates":[-92.124191,46.766916],"type":"Point"}
}