{
  "type": "Feature",
  "properties": {
    "addr:full":"4021 Vernon Ave S Minneapolis MN 55416",
    "addr:housenumber":"4021",
    "addr:postcode":"55416",
    "addr:street":"Vernon Ave S",
    "iso:country":"US",
    "sg:address":"4021 Vernon Ave S",
    "sg:city":"Minneapolis",
    "sg:classifiers":[
        {
            "category":"Insurance",
            "subcategory":"Insurance Agent",
            "type":"Services"
        }
    ],
    "sg:phone":"+1 952 920 4195",
    "sg:postcode":"55416",
    "sg:province":"MN",
    "wof:name":"Allstate",
    "wof:placetype":"venue"
},
  "geometry": {"coordinates":[-93.349428,44.928465],"type":"Point"}
}