{
  "type": "Feature",
  "properties": {
    "addr:full":"1617 SE Broadway Ave Albert Lea MN 56007",
    "addr:housenumber":"1617",
    "addr:postcode":"56007",
    "addr:street":"Se Broadway Ave",
    "iso:country":"US",
    "sg:address":"1617 SE Broadway Ave",
    "sg:city":"Albert Lea",
    "sg:classifiers":[
        {
            "category":"Retail",
            "subcategory":"Laundry & Dry Cleaning",
            "type":"Services"
        }
    ],
    "sg:phone":"+1 507 373 6279",
    "sg:postcode":"56007",
    "sg:province":"MN",
    "sg:tags":[
        "cleaners"
    ],
    "wof:name":"Mary's Dry Cleaning",
    "wof:placetype":"venue"
},
  "geometry": {"coordinates":[-93.361176,43.632],"type":"Point"}
}