{
  "type": "Feature",
  "properties": {
    "addr:full":"111 Winsted Ave W Winsted MN 55395",
    "addr:housenumber":"111",
    "addr:postcode":"55395",
    "addr:street":"Winsted Ave W",
    "iso:country":"US",
    "sg:address":"111 Winsted Ave W",
    "sg:city":"Winsted",
    "sg:classifiers":[
        {
            "category":"Organizations",
            "subcategory":"Religious Organization",
            "type":"Services"
        }
    ],
    "sg:phone":"+1 320 485 4421",
    "sg:postcode":"55395",
    "sg:province":"MN",
    "sg:tags":[
        "church"
    ],
    "wof:name":"Holy Trinity Catholic Church",
    "wof:placetype":"venue"
},
  "geometry": {"coordinates":[-94.048102,44.965162],"type":"Point"}
}