{
  "type": "Feature",
  "properties": {
    "iso:country":"US",
    "sg:address":"4149 Lyndale Ave N",
    "sg:city":"Minneapolis",
    "sg:classifiers":[
        {
            "category":"Banks & Credit Unions",
            "subcategory":"Bank",
            "type":"Services"
        }
    ],
    "sg:phone":"+1 612 287 8480",
    "sg:postcode":"55412",
    "sg:province":"MN",
    "sg:tags":[
        "broker",
        "mortgage"
    ],
    "wof:name":"Universal Mortgage Advisors",
    "wof:placetype":"venue"
},
  "geometry": {"coordinates":[-93.28818200000001,45.031377],"type":"Point"}
}