{
  "type": "Feature",
  "properties": {
    "iso:country":"US",
    "sg:address":"2024 Clinton Dr N",
    "sg:city":"Winona",
    "sg:phone":"+1 507 454 6910",
    "sg:postcode":"55987",
    "sg:province":"MN",
    "sg:tags":[
        "farm",
        "wheat"
    ],
    "wof:name":"Robert Bambenek",
    "wof:placetype":"venue"
},
  "geometry": {"coordinates":[-91.597683,44.001382],"type":"Point"}
}