{
  "type": "Feature",
  "properties": {
    "addr:full":"52 Front St E Hitterdal MN 56552",
    "addr:housenumber":"52",
    "addr:postcode":"56552",
    "addr:street":"Front St E Hitterdal",
    "iso:country":"US",
    "sg:address":"52 Front St E",
    "sg:city":"Hitterdal",
    "sg:classifiers":[
        {
            "category":"Professional",
            "subcategory":"Business Services",
            "type":"Services"
        },
        {
            "category":"Government",
            "subcategory":"Post Office",
            "type":"Public Place"
        }
    ],
    "sg:phone":"+1 800 275 8777",
    "sg:postcode":"56552",
    "sg:province":"MN",
    "sg:tags":[
        "mail",
        "shipping"
    ],
    "sg:website":"http://www.usps.com",
    "wof:name":"USPS - United States Post Office - Hitterdal Main Office",
    "wof:placetype":"venue"
},
  "geometry": {"coordinates":[-96.257154,46.977303],"type":"Point"}
}