{
  "type": "Feature",
  "properties": {
    "addr:full":"301 Main St Karlstad MN 56732",
    "addr:housenumber":"301",
    "addr:postcode":"56732",
    "addr:street":"Main St",
    "iso:country":"US",
    "sg:address":"301 Main St",
    "sg:city":"Karlstad",
    "sg:classifiers":[
        {
            "category":"Home & Garden",
            "subcategory":"Hardware",
            "type":"Retail Goods"
        }
    ],
    "sg:phone":"+1 218 436 2500",
    "sg:postcode":"56732",
    "sg:province":"MN",
    "wof:name":"Hardware Hank",
    "wof:placetype":"venue"
},
  "geometry": {"coordinates":[-96.519887,48.576468],"type":"Point"}
}