{
  "type": "Feature",
  "properties": {
    "iso:country":"US",
    "sg:address":"14140 Mn Highway 13 S",
    "sg:city":"Savage",
    "sg:classifiers":[
        {
            "category":"Restaurant",
            "type":"Food & Drink"
        }
    ],
    "sg:menulink":"http://www.allmenus.com/mn/savage/56699-leeann-chin/menu/",
    "sg:phone":"+1 952 226 4300",
    "sg:postcode":"55378",
    "sg:province":"MN",
    "sg:tags":[
        "asian",
        "chinese"
    ],
    "wof:name":"Leeann Chin",
    "wof:placetype":"venue"
},
  "geometry": {"coordinates":[-93.379822,44.747461],"type":"Point"}
}