{
  "type": "Feature",
  "properties": {
    "iso:country":"US",
    "sg:address":"90 Plato Blvd W",
    "sg:city":"Saint Paul",
    "sg:classifiers":[
        {
            "category":"Government",
            "subcategory":"Office",
            "type":"Public Place"
        }
    ],
    "sg:phone":"+1 651 296 2627",
    "sg:postcode":"55107",
    "sg:province":"MN",
    "sg:tags":[
        "food",
        "inspection"
    ],
    "wof:name":"Food Inspection Service",
    "wof:placetype":"venue"
},
  "geometry": {"coordinates":[-93.09113499999999,44.936887],"type":"Point"}
}