{
  "type": "Feature",
  "properties": {
    "iso:country":"US",
    "sg:address":"23 N Main St",
    "sg:city":"Sherburn",
    "sg:phone":"+1 507 764 6721",
    "sg:postcode":"56171",
    "sg:province":"MN",
    "wof:name":"Cup & Saucer & Sweet Shoppe",
    "wof:placetype":"venue"
},
  "geometry": {"coordinates":[-94.727334,43.652623],"type":"Point"}
}