{
  "type": "Feature",
  "properties": {
    "iso:country":"US",
    "sg:address":"118 W 6th St Suite A",
    "sg:city":"Monticello",
    "sg:classifiers":[
        {
            "category":"Utilities",
            "subcategory":"Telephone",
            "type":"Services"
        },
        {
            "category":"Professional",
            "subcategory":"Computer Services",
            "type":"Services"
        }
    ],
    "sg:phone":"+1 763 314 0100",
    "sg:postcode":"55362",
    "sg:province":"MN",
    "sg:tags":[
        "communication",
        "isp",
        "provider",
        "internet"
    ],
    "wof:name":"FiberNet Monticello",
    "wof:placetype":"venue"
},
  "geometry": {"coordinates":[-93.797389,45.301732],"type":"Point"}
}