{
  "type": "Feature",
  "properties": {
    "addr:full":"31378 County 24 Blvd Cannon Falls MN 55009",
    "addr:housenumber":"31378",
    "addr:postcode":"55009",
    "addr:street":"County 24 Blvd",
    "iso:country":"US",
    "sg:address":"31378 County 24 Blvd",
    "sg:city":"Cannon Falls",
    "sg:classifiers":[
        {
            "category":"Health Services",
            "subcategory":"Doctor",
            "type":"Services"
        }
    ],
    "sg:phone":"+1 507 263 3965",
    "sg:postcode":"55009",
    "sg:province":"MN",
    "sg:tags":[
        "dentist"
    ],
    "wof:name":"Mark J Juetten DDS",
    "wof:placetype":"venue"
},
  "geometry": {"coordinates":[-92.91001799999999,44.492397],"type":"Point"}
}