{
  "type": "Feature",
  "properties": {
    "iso:country":"US",
    "sg:address":"909 Minnesota Ave",
    "sg:city":"Owatonna",
    "sg:classifiers":[
        {
            "category":"Building & Trades",
            "subcategory":"Equipment Rental",
            "type":"Services"
        }
    ],
    "sg:phone":"+1 507 451 9466",
    "sg:postcode":"55060",
    "sg:province":"MN",
    "sg:tags":[
        "leasing"
    ],
    "wof:name":"D & Rt Enterprises LLC",
    "wof:placetype":"venue"
},
  "geometry": {"coordinates":[-93.206874,44.076252],"type":"Point"}
}