{
  "type": "Feature",
  "properties": {
    "addr:full":"716 E Hawthorne St Albert Lea MN 56007",
    "addr:housenumber":"716",
    "addr:postcode":"56007",
    "addr:street":"E Hawthorne",
    "iso:country":"US",
    "sg:address":"716 E Hawthorne St",
    "sg:city":"Albert Lea",
    "sg:phone":"+1 507 373 7485",
    "sg:postcode":"56007",
    "sg:province":"MN",
    "sg:tags":[
        "farm",
        "soybean"
    ],
    "wof:name":"Niest Farm",
    "wof:placetype":"venue"
},
  "geometry": {"coordinates":[-93.360829,43.65852],"type":"Point"}
}