{
  "type": "Feature",
  "properties": {
    "addr:full":"15250 Wayzata Blvd Wayzata MN 55391",
    "addr:housenumber":"15250",
    "addr:postcode":"55391",
    "addr:street":"Wayzata Blvd",
    "iso:country":"US",
    "sg:address":"15250 Wayzata Blvd",
    "sg:city":"Wayzata",
    "sg:classifiers":[
        {
            "category":"Professional",
            "subcategory":"Lawyer & Legal Services",
            "type":"Services"
        }
    ],
    "sg:phone":"+1 952 473 3031",
    "sg:postcode":"55391",
    "sg:province":"MN",
    "sg:tags":[
        "attorney"
    ],
    "wof:name":"Julian J Hook",
    "wof:placetype":"venue"
},
  "geometry": {"coordinates":[-93.47475300000001,44.971396],"type":"Point"}
}