{
  "type": "Feature",
  "properties": {
    "iso:country":"US",
    "sg:address":"10217 Hilltop Ct N",
    "sg:city":"Champlin",
    "sg:classifiers":[
        {
            "category":"Recreation",
            "type":"Entertainment"
        }
    ],
    "sg:phone":"+1 763 323 1104",
    "sg:postcode":"55316",
    "sg:province":"MN",
    "sg:tags":[
        "club",
        "membership"
    ],
    "wof:name":"Champlin Garden Club",
    "wof:placetype":"venue"
},
  "geometry": {"coordinates":[-93.410659,45.164112],"type":"Point"}
}