{
  "type": "Feature",
  "properties": {
    "addr:full":"109 Hwy 55 W Buffalo MN 55313",
    "addr:housenumber":"109",
    "addr:postcode":"55313",
    "addr:street":"Hwy 55 W",
    "iso:country":"US",
    "sg:address":"109 Hwy 55 W",
    "sg:city":"Buffalo",
    "sg:classifiers":[
        {
            "category":"Building & Trades",
            "subcategory":"Construction",
            "type":"Services"
        }
    ],
    "sg:phone":"+1 763 682 2662",
    "sg:postcode":"55313",
    "sg:province":"MN",
    "sg:tags":[
        "roofing",
        "contractor"
    ],
    "wof:name":"F A Tenney Co",
    "wof:placetype":"venue"
},
  "geometry": {"coordinates":[-93.885221,45.188385],"type":"Point"}
}