{
  "type": "Feature",
  "properties": {
    "iso:country":"US",
    "sg:address":"12513 Mystic Ln",
    "sg:city":"Burnsville",
    "sg:classifiers":[
        {
            "category":"Personal",
            "type":"Services"
        }
    ],
    "sg:phone":"+1 952 890 9779",
    "sg:postcode":"55337",
    "sg:province":"MN",
    "wof:name":"Rhoades & Johnson Co LLC",
    "wof:placetype":"venue"
},
  "geometry": {"coordinates":[-93.243718,44.7766],"type":"Point"}
}