{
  "type": "Feature",
  "properties": {
    "addr:full":"109 2nd Ave NE Roseau MN 56751",
    "addr:housenumber":"109",
    "addr:postcode":"56751",
    "addr:street":"2Nd Ave Ne",
    "iso:country":"US",
    "sg:address":"109 2nd Ave NE",
    "sg:city":"Roseau",
    "sg:classifiers":[
        {
            "category":"Insurance",
            "subcategory":"Life Insurance",
            "type":"Services"
        }
    ],
    "sg:phone":"+1 218 463 1451",
    "sg:postcode":"56751",
    "sg:province":"MN",
    "sg:tags":[
        "carrier"
    ],
    "wof:name":"Farm Bureau Financial Services",
    "wof:placetype":"venue"
},
  "geometry": {"coordinates":[-95.761635,48.846308],"type":"Point"}
}