{
  "type": "Feature",
  "properties": {
    "iso:country":"US",
    "sg:address":"8935 Co Rd 5 NW",
    "sg:city":"Garfield",
    "sg:classifiers":[
        {
            "category":"Professional",
            "type":"Services"
        }
    ],
    "sg:phone":"+1 651 777 4520",
    "sg:postcode":"56332",
    "sg:province":"MN",
    "sg:tags":[
        "establishment"
    ],
    "wof:name":"Michelle Campbell Cfp",
    "wof:placetype":"venue"
},
  "geometry": {"coordinates":[-95.51097,46.049921],"type":"Point"}
}