{
  "type": "Feature",
  "properties": {
    "addr:full":"102 Lincoln Ave S Battle Lake MN 56515",
    "addr:housenumber":"102",
    "addr:postcode":"56515",
    "addr:street":"Lincoln Ave S Battle",
    "iso:country":"US",
    "sg:address":"102 Lincoln Ave S",
    "sg:city":"Battle Lake",
    "sg:classifiers":[
        {
            "category":"Retail",
            "subcategory":"Funeral Services",
            "type":"Services"
        }
    ],
    "sg:phone":"+1 218 864 5278",
    "sg:postcode":"56515",
    "sg:province":"MN",
    "sg:tags":[
        "director"
    ],
    "wof:name":"Glende-Nilson",
    "wof:placetype":"venue"
},
  "geometry": {"coordinates":[-95.71558,46.281687],"type":"Point"}
}