{
  "type": "Feature",
  "properties": {
    "iso:country":"US",
    "sg:address":"3705 Colfax Ave N",
    "sg:city":"Minneapolis",
    "sg:classifiers":[
        {
            "category":"Building & Trades",
            "subcategory":"Cleaning & Sanitation",
            "type":"Services"
        }
    ],
    "sg:phone":"+1 612 871 3083",
    "sg:postcode":"55412",
    "sg:province":"MN",
    "sg:tags":[
        "janitor",
        "maintenance"
    ],
    "wof:name":"Big Jays Cleaning Svcs Co",
    "wof:placetype":"venue"
},
  "geometry": {"coordinates":[-93.29190699999999,45.023885],"type":"Point"}
}