{
  "type": "Feature",
  "properties": {
    "iso:country":"US",
    "sg:address":"504 Main St E",
    "sg:city":"Pipestone",
    "sg:classifiers":[
        {
            "category":"Banks & Credit Unions",
            "subcategory":"Bank",
            "type":"Services"
        }
    ],
    "sg:phone":"+1 507 562 0300",
    "sg:postcode":"56164",
    "sg:province":"MN",
    "sg:tags":[
        "broker",
        "mortgage"
    ],
    "wof:name":"Morgan Lending Solutions LLC",
    "wof:placetype":"venue"
},
  "geometry": {"coordinates":[-96.31181100000001,44.000461],"type":"Point"}
}