{
  "type": "Feature",
  "properties": {
    "iso:country":"US",
    "sg:address":"10949 91st Ave N",
    "sg:city":"Osseo",
    "sg:classifiers":[
        {
            "category":"Food & Beverages",
            "subcategory":"Groceries & Convenience Stores",
            "type":"Retail Goods"
        }
    ],
    "sg:phone":"+1 763 315 5002",
    "sg:postcode":"55369",
    "sg:province":"MN",
    "sg:tags":[
        "product"
    ],
    "wof:name":"Con Agra Foods",
    "wof:placetype":"venue"
},
  "geometry": {"coordinates":[-93.420214,45.119891],"type":"Point"}
}