{
  "type": "Feature",
  "properties": {
    "iso:country":"US",
    "sg:address":"294 Grove Ln E",
    "sg:city":"Wayzata",
    "sg:classifiers":[
        {
            "category":"Utilities",
            "type":"Services"
        }
    ],
    "sg:phone":"+1 952 943 8900",
    "sg:postcode":"55391",
    "sg:province":"MN",
    "sg:tags":[
        "energy"
    ],
    "wof:name":"Lgi Energy Solutions Inc",
    "wof:placetype":"venue"
},
  "geometry": {"coordinates":[-93.518778,44.969841],"type":"Point"}
}