{
  "type": "Feature",
  "properties": {
    "iso:country":"US",
    "sg:address":"44713 220th St",
    "sg:city":"Delavan",
    "sg:phone":"+1 507 854 3457",
    "sg:postcode":"56023",
    "sg:province":"MN",
    "sg:tags":[
        "farm",
        "corn",
        "soybean"
    ],
    "wof:name":"William Whitney",
    "wof:placetype":"venue"
},
  "geometry": {"coordinates":[-93.974452,43.804095],"type":"Point"}
}