{
  "type": "Feature",
  "properties": {
    "addr:full":"6840 Shingle Creek Pkwy Brooklyn Center MN 55430",
    "addr:housenumber":"6840",
    "addr:postcode":"55430",
    "addr:street":"Shingle Creek Pkwy",
    "iso:country":"US",
    "sg:address":"6840 Shingle Creek Pkwy",
    "sg:city":"Brooklyn Center",
    "sg:classifiers":[
        {
            "category":"Professional",
            "subcategory":"Advertising",
            "type":"Services"
        }
    ],
    "sg:phone":"+1 763 549 0148",
    "sg:postcode":"55430",
    "sg:province":"MN",
    "sg:tags":[
        "distribution"
    ],
    "wof:name":"ADX Distribution Co",
    "wof:placetype":"venue"
},
  "geometry": {"coordinates":[-93.310535,45.078002],"type":"Point"}
}