{
  "type": "Feature",
  "properties": {
    "iso:country":"US",
    "sg:address":"110 River St",
    "sg:city":"Hastings",
    "sg:classifiers":[
        {
            "category":"Real Estate",
            "subcategory":"Real Estate Operator",
            "type":"Services"
        }
    ],
    "sg:phone":"+1 651 438 9808",
    "sg:postcode":"55033",
    "sg:province":"MN",
    "sg:tags":[
        "property",
        "lessor"
    ],
    "wof:name":"Golden Key Property Management",
    "wof:placetype":"venue"
},
  "geometry": {"coordinates":[-92.865154,44.744401],"type":"Point"}
}