{
  "type": "Feature",
  "properties": {
    "iso:country":"US",
    "sg:address":"93648 480th Ave",
    "sg:city":"Windom",
    "sg:classifiers":[
        {
            "category":"Personal",
            "subcategory":"Beauty Salon",
            "type":"Services"
        }
    ],
    "sg:phone":"+1 507 831 2854",
    "sg:postcode":"56101",
    "sg:province":"MN",
    "sg:tags":[
        "shop"
    ],
    "wof:name":"Hen House Salon",
    "wof:placetype":"venue"
},
  "geometry": {"coordinates":[-95.11582900000001,43.845555],"type":"Point"}
}