{
  "type": "Feature",
  "properties": {
    "addr:full":"1230 Town Centre Dr Saint Paul MN 55123",
    "addr:housenumber":"1230",
    "addr:postcode":"55123",
    "addr:street":"Town Centre Dr",
    "iso:country":"US",
    "sg:address":"1230 Town Centre Dr",
    "sg:city":"Saint Paul",
    "sg:classifiers":[
        {
            "category":"Restaurant",
            "type":"Food & Drink"
        }
    ],
    "sg:phone":"+1 651 365 8600",
    "sg:postcode":"55123",
    "sg:province":"MN",
    "sg:tags":[
        "eating"
    ],
    "wof:name":"Red Robin Eagan 630 Inact",
    "wof:placetype":"venue"
},
  "geometry": {"coordinates":[-93.15633200000001,44.831849],"type":"Point"}
}