{
  "type": "Feature",
  "properties": {
    "iso:country":"US",
    "sg:address":"104 Thompson Ave S",
    "sg:city":"Rushmore",
    "sg:classifiers":[
        {
            "category":"Retail",
            "subcategory":"Repair Shop",
            "type":"Services"
        }
    ],
    "sg:phone":"+1 507 478 4916",
    "sg:postcode":"56168",
    "sg:province":"MN",
    "sg:tags":[
        "tractor"
    ],
    "wof:name":"Harlan's Auto Repair",
    "wof:placetype":"venue"
},
  "geometry": {"coordinates":[-95.801005,43.618414],"type":"Point"}
}