{
  "type": "Feature",
  "properties": {
    "iso:country":"US",
    "sg:address":"1893 W Taylor Ave",
    "sg:city":"St Paul",
    "sg:classifiers":[
        {
            "category":"Building & Trades",
            "subcategory":"Construction",
            "type":"Services"
        }
    ],
    "sg:phone":"+1 651 647 5778",
    "sg:postcode":"55104",
    "sg:province":"MN",
    "sg:tags":[
        "restoration",
        "cleaning",
        "patio",
        "deck"
    ],
    "wof:name":"JET Svc Co",
    "wof:placetype":"venue"
},
  "geometry": {"coordinates":[-93.18046200000001,44.968226],"type":"Point"}
}