{
  "type": "Feature",
  "properties": {
    "addr:full":"34055 Co Rd 4 Olivia MN 56277",
    "addr:housenumber":"34055;4",
    "addr:postcode":"56277",
    "addr:street":"Co Rd",
    "iso:country":"US",
    "sg:address":"34055 Co Rd 4",
    "sg:city":"Olivia",
    "sg:phone":"+1 320 523 2413",
    "sg:postcode":"56277",
    "sg:province":"MN",
    "sg:tags":[
        "farm",
        "corn",
        "grain",
        "cash"
    ],
    "wof:name":"Jack Einerson",
    "wof:placetype":"venue"
},
  "geometry": {"coordinates":[-94.994332,44.672404],"type":"Point"}
}