{
  "type": "Feature",
  "properties": {
    "addr:full":"26365 Golden Ave Wyoming MN 55092",
    "addr:housenumber":"26365",
    "addr:postcode":"55092",
    "addr:street":"Golden Ave",
    "iso:country":"US",
    "sg:address":"26365 Golden Ave",
    "sg:city":"Wyoming",
    "sg:classifiers":[
        {
            "category":"Professional",
            "subcategory":"Business Services",
            "type":"Services"
        }
    ],
    "sg:phone":"+1 651 462 3268",
    "sg:postcode":"55092",
    "sg:province":"MN",
    "sg:tags":[
        "interpreter",
        "translation"
    ],
    "wof:name":"Minnesota Language Connection",
    "wof:placetype":"venue"
},
  "geometry": {"coordinates":[-92.97980099999999,45.329216],"type":"Point"}
}