{
  "type": "Feature",
  "properties": {
    "addr:full":"215 2nd St Two Harbors MN 55616",
    "addr:housenumber":"215",
    "addr:postcode":"55616",
    "addr:street":"2Nd St;Harbors",
    "iso:country":"US",
    "sg:address":"215 2nd St",
    "sg:city":"Two Harbors",
    "sg:classifiers":[
        {
            "category":"Retail",
            "subcategory":"Repair Shop",
            "type":"Services"
        }
    ],
    "sg:phone":"+1 218 834 0743",
    "sg:postcode":"55616",
    "sg:province":"MN",
    "sg:tags":[
        "related"
    ],
    "wof:name":"Leroy's Repair",
    "wof:placetype":"venue"
},
  "geometry": {"coordinates":[-91.66318200000001,47.020906],"type":"Point"}
}