{
  "type": "Feature",
  "properties": {
    "addr:full":"332 Sextant Ave E Saint Paul MN 55117",
    "addr:housenumber":"332",
    "addr:postcode":"55117",
    "addr:street":"Sextant Ave E",
    "iso:country":"US",
    "sg:address":"332 Sextant Ave E",
    "sg:city":"Saint Paul",
    "sg:classifiers":[
        {
            "category":"Social Services",
            "subcategory":"Adult Care",
            "type":"Services"
        }
    ],
    "sg:phone":"+1 651 483 3093",
    "sg:postcode":"55117",
    "sg:province":"MN",
    "sg:tags":[
        "disabled",
        "for"
    ],
    "wof:name":"Nekton-Inc Sextant",
    "wof:placetype":"venue"
},
  "geometry": {"coordinates":[-93.087507,45.014237],"type":"Point"}
}