{
  "type": "Feature",
  "properties": {
    "addr:full":"16922 89th Ave N Osseo MN 55311",
    "addr:housenumber":"16922",
    "addr:postcode":"55311",
    "addr:street":"89Th Ave N",
    "iso:country":"US",
    "sg:address":"16922 89th Ave N",
    "sg:city":"Osseo",
    "sg:classifiers":[
        {
            "category":"Professional",
            "subcategory":"Testing Lab",
            "type":"Services"
        }
    ],
    "sg:phone":"+1 952 742 3764",
    "sg:postcode":"55311",
    "sg:province":"MN",
    "sg:tags":[
        "laboratory"
    ],
    "wof:name":"Krishnamurthy Ganesan",
    "wof:placetype":"venue"
},
  "geometry": {"coordinates":[-93.49434100000001,45.11653],"type":"Point"}
}