{
  "type": "Feature",
  "properties": {
    "addr:full":"847 Millard St St Charles MN 55972",
    "addr:housenumber":"847",
    "addr:postcode":"55972",
    "addr:street":"Millard St",
    "iso:country":"US",
    "sg:address":"847 Millard St",
    "sg:city":"St Charles",
    "sg:classifiers":[
        {
            "category":"Wholesale",
            "subcategory":"Durable Goods & Equipment",
            "type":"Manufacturing & Wholesale Goods"
        },
        {
            "category":"Manufacturing",
            "subcategory":"Lumber",
            "type":"Manufacturing & Wholesale Goods"
        }
    ],
    "sg:phone":"+1 507 932 4085",
    "sg:postcode":"55972",
    "sg:province":"MN",
    "sg:tags":[
        "forestry",
        "fire",
        "extinguisher"
    ],
    "wof:name":"Firehouse Apparatus & Equip",
    "wof:placetype":"venue"
},
  "geometry": {"coordinates":[-92.057309,43.969146],"type":"Point"}
}