{
  "type": "Feature",
  "properties": {
    "iso:country":"US",
    "sg:address":"350 W Burnsville Pkwy",
    "sg:city":"Burnsville",
    "sg:classifiers":[
        {
            "category":"Insurance",
            "subcategory":"Title Insurance",
            "type":"Services"
        }
    ],
    "sg:phone":"+1 952 894 7291",
    "sg:postcode":"55337",
    "sg:province":"MN",
    "sg:tags":[
        "provides"
    ],
    "wof:name":"Rels Title Services LLC",
    "wof:placetype":"venue"
},
  "geometry": {"coordinates":[-93.282844,44.770488],"type":"Point"}
}