{
  "type": "Feature",
  "properties": {
    "iso:country":"US",
    "sg:address":"2006 1st Ave",
    "sg:city":"Anoka",
    "sg:classifiers":[
        {
            "category":"Shopping",
            "subcategory":"Computers & Home Electronics",
            "type":"Retail Goods"
        }
    ],
    "sg:phone":"+1 763 427 9100",
    "sg:postcode":"55303",
    "sg:province":"MN",
    "sg:tags":[
        "software"
    ],
    "wof:name":"22nd Century Software Systems",
    "wof:placetype":"venue"
},
  "geometry": {"coordinates":[-93.38995199999999,45.198619],"type":"Point"}
}