{
  "type": "Feature",
  "properties": {
    "iso:country":"US",
    "sg:address":"5115 Excelsior Blvd",
    "sg:city":"Minneapolis",
    "sg:classifiers":[
        {
            "category":"Professional",
            "subcategory":"Management & Consulting",
            "type":"Services"
        },
        {
            "category":"Professional",
            "subcategory":"Computer Services",
            "type":"Services"
        }
    ],
    "sg:phone":"+1 952 926 1400",
    "sg:postcode":"55416",
    "sg:province":"MN",
    "sg:tags":[
        "consultant",
        "designer",
        "business"
    ],
    "wof:name":"Timber Creek Consulting Group",
    "wof:placetype":"venue"
},
  "geometry": {"coordinates":[-93.345,44.931871],"type":"Point"}
}