{
  "type": "Feature",
  "properties": {
    "addr:full":"38434 N Eagle Lake Rd Battle Lake MN 56515",
    "addr:housenumber":"38434",
    "addr:postcode":"56515",
    "addr:street":"N Eagle Lake Rd",
    "iso:country":"US",
    "sg:address":"38434 N Eagle Lake Rd",
    "sg:city":"Battle Lake",
    "sg:classifiers":[
        {
            "category":"Bars & Pubs",
            "type":"Food & Drink"
        }
    ],
    "sg:phone":"+1 651 646 0298",
    "sg:postcode":"56515",
    "sg:province":"MN",
    "sg:tags":[
        "tavern"
    ],
    "wof:name":"Herges Bar",
    "wof:placetype":"venue"
},
  "geometry": {"coordinates":[-95.69542800000001,46.178228],"type":"Point"}
}