{
  "type": "Feature",
  "properties": {
    "addr:full":"1235 Highway 25 N Buffalo MN 55313",
    "addr:housenumber":"1235",
    "addr:postcode":"55313",
    "addr:street":"Highway 25 N",
    "iso:country":"US",
    "sg:address":"1235 Highway 25 N",
    "sg:city":"Buffalo",
    "sg:classifiers":[
        {
            "category":"Personal",
            "subcategory":"Massage",
            "type":"Services"
        },
        {
            "category":"Personal",
            "subcategory":"Beauty Salon",
            "type":"Services"
        },
        {
            "category":"Personal",
            "subcategory":"Day Spa",
            "type":"Services"
        },
        {
            "category":"Personal",
            "subcategory":"Nail Salon",
            "type":"Services"
        }
    ],
    "sg:phone":"+1 763 684 1918",
    "sg:postcode":"55313",
    "sg:province":"MN",
    "sg:tags":[
        "therapist"
    ],
    "wof:name":"Exhileration Salon & Spa",
    "wof:placetype":"venue"
},
  "geometry": {"coordinates":[-93.87608299999999,45.188206],"type":"Point"}
}