{
  "type": "Feature",
  "properties": {
    "addr:full":"5056 43rd Ave N Moorhead MN 56560",
    "addr:housenumber":"5056",
    "addr:postcode":"56560",
    "addr:street":"43Rd Ave N",
    "iso:country":"US",
    "sg:address":"5056 43rd Ave N",
    "sg:city":"Moorhead",
    "sg:classifiers":[
        {
            "category":"Professional",
            "type":"Services"
        }
    ],
    "sg:phone":"+1 218 233 0250",
    "sg:postcode":"56560",
    "sg:province":"MN",
    "wof:name":"Harmen Tande",
    "wof:placetype":"venue"
},
  "geometry": {"coordinates":[-96.67358299999999,46.919967],"type":"Point"}
}