{
  "type": "Feature",
  "properties": {
    "addr:full":"500 S Saratoga St Marshall MN 56258",
    "addr:housenumber":"500",
    "addr:postcode":"56258",
    "addr:street":"S Saratoga St",
    "iso:country":"US",
    "sg:address":"500 S Saratoga St",
    "sg:city":"Marshall",
    "sg:classifiers":[
        {
            "category":"Organizations",
            "subcategory":"Religious Organization",
            "type":"Services"
        }
    ],
    "sg:phone":"+1 507 532 3414",
    "sg:postcode":"56258",
    "sg:province":"MN",
    "wof:name":"Calvary Baptist Church",
    "wof:placetype":"venue"
},
  "geometry": {"coordinates":[-95.78616,44.4396],"type":"Point"}
}