{
  "type": "Feature",
  "properties": {
    "addr:full":"204 Poplar Ave W Badger MN 56714",
    "addr:housenumber":"204",
    "addr:postcode":"56714",
    "addr:street":"Poplar Ave W Badger",
    "iso:country":"US",
    "sg:address":"204 Poplar Ave W",
    "sg:city":"Badger",
    "sg:classifiers":[
        {
            "category":"Shopping",
            "subcategory":"Bicycles & Sporting Goods",
            "type":"Retail Goods"
        }
    ],
    "sg:phone":"+1 218 528 3266",
    "sg:postcode":"56714",
    "sg:province":"MN",
    "wof:name":"Erickson Gun Shop",
    "wof:placetype":"venue"
},
  "geometry": {"coordinates":[-96.01963600000001,48.779178],"type":"Point"}
}