{
  "type": "Feature",
  "properties": {
    "iso:country":"US",
    "sg:address":"678 Compton Ct",
    "sg:city":"Eagan",
    "sg:classifiers":[
        {
            "category":"Utilities",
            "subcategory":"Telephone",
            "type":"Services"
        }
    ],
    "sg:phone":"+1 651 688 9900",
    "sg:postcode":"55123",
    "sg:province":"MN",
    "sg:tags":[
        "telecommunication"
    ],
    "wof:name":"Technology Management Corp",
    "wof:placetype":"venue"
},
  "geometry": {"coordinates":[-93.11379599999999,44.816334],"type":"Point"}
}