{
  "type": "Feature",
  "properties": {
    "iso:country":"US",
    "sg:address":"2600 Eagan Woods Dr",
    "sg:city":"Eagan",
    "sg:classifiers":[
        {
            "category":"Professional",
            "subcategory":"Lawyer & Legal Services",
            "type":"Services"
        }
    ],
    "sg:phone":"+1 651 365 5024",
    "sg:postcode":"55121",
    "sg:province":"MN",
    "sg:tags":[
        "attorney"
    ],
    "wof:name":"Maguire & Lemmon PC",
    "wof:placetype":"venue"
},
  "geometry": {"coordinates":[-93.168756,44.859497],"type":"Point"}
}