{
  "type": "Feature",
  "properties": {
    "addr:full":"4985 Miller Trunk Hwy Hermantown MN 55811",
    "addr:housenumber":"4985",
    "addr:postcode":"55811",
    "addr:street":"Miller Trunk Hwy",
    "iso:country":"US",
    "sg:address":"4985 Miller Trunk Hwy",
    "sg:city":"Hermantown",
    "sg:classifiers":[
        {
            "category":"Utilities",
            "subcategory":"Fuel Oil & Lpg",
            "type":"Services"
        },
        {
            "category":"Building & Trades",
            "subcategory":"Construction",
            "type":"Services"
        }
    ],
    "sg:phone":"+1 218 729 8241",
    "sg:postcode":"55811",
    "sg:province":"MN",
    "sg:tags":[
        "specialty",
        "kerosene",
        "system",
        "contractor",
        "heating",
        "oils-fuel",
        "air conditioning"
    ],
    "sg:website":"http://www.curtisoil.com",
    "wof:name":"Curtis Oil-Propane",
    "wof:placetype":"venue"
},
  "geometry": {"coordinates":[-92.20665,46.834412],"type":"Point"}
}