{
  "type": "Feature",
  "properties": {
    "iso:country":"US",
    "sg:address":"620 Water St S",
    "sg:city":"Northfield",
    "sg:classifiers":[
        {
            "category":"Restaurant",
            "type":"Food & Drink"
        }
    ],
    "sg:phone":"+1 507 663 1056",
    "sg:postcode":"55057",
    "sg:province":"MN",
    "sg:tags":[
        "mexican"
    ],
    "wof:name":"Diamond Days",
    "wof:placetype":"venue"
},
  "geometry": {"coordinates":[-93.16181,44.453749],"type":"Point"}
}