{
  "type": "Feature",
  "properties": {
    "addr:full":"204 E Sheridan St Ely MN 55731",
    "addr:housenumber":"204",
    "addr:postcode":"55731",
    "addr:street":"E Sheridan St",
    "iso:country":"US",
    "sg:address":"204 E Sheridan St",
    "sg:city":"Ely",
    "sg:classifiers":[
        {
            "category":"Shopping",
            "subcategory":"Clothing, Apparel, & Fashions",
            "type":"Retail Goods"
        }
    ],
    "sg:phone":"+1 218 365 4043",
    "sg:postcode":"55731",
    "sg:province":"MN",
    "sg:tags":[
        "ready",
        "to",
        "wear"
    ],
    "wof:name":"Andrea J's Women's Apparel",
    "wof:placetype":"venue"
},
  "geometry": {"coordinates":[-91.863882,47.90311],"type":"Point"}
}