{
  "type": "Feature",
  "properties": {
    "addr:full":"503 W Main St Osakis MN 56360",
    "addr:housenumber":"503",
    "addr:postcode":"56360",
    "addr:street":"W Main St",
    "iso:country":"US",
    "sg:address":"503 W Main St",
    "sg:city":"Osakis",
    "sg:classifiers":[
        {
            "category":"Building & Trades",
            "subcategory":"Construction",
            "type":"Services"
        }
    ],
    "sg:phone":"+1 320 859 2611",
    "sg:postcode":"56360",
    "sg:province":"MN",
    "sg:tags":[
        "contractor"
    ],
    "wof:name":"Priority Canopy Co",
    "wof:placetype":"venue"
},
  "geometry": {"coordinates":[-95.159397,45.868663],"type":"Point"}
}