{
  "type": "Feature",
  "properties": {
    "addr:full":"4304 16th Ave S Minneapolis MN 55407",
    "addr:housenumber":"4304",
    "addr:postcode":"55407",
    "addr:street":"16Th Ave S",
    "iso:country":"US",
    "sg:address":"4304 16th Ave S",
    "sg:city":"Minneapolis",
    "sg:classifiers":[
        {
            "category":"Shopping",
            "subcategory":"Books",
            "type":"Retail Goods"
        }
    ],
    "sg:phone":"+1 612 729 3633",
    "sg:postcode":"55407",
    "sg:province":"MN",
    "wof:name":"Abba Homeschool Resources",
    "wof:placetype":"venue"
},
  "geometry": {"coordinates":[-93.251181,44.923397],"type":"Point"}
}