{
  "type": "Feature",
  "properties": {
    "iso:country":"US",
    "sg:address":"104 S Washington St",
    "sg:city":"Lake City",
    "sg:classifiers":[
        {
            "category":"Professional",
            "subcategory":"Lawyer & Legal Services",
            "type":"Services"
        }
    ],
    "sg:phone":"+1 651 345 3305",
    "sg:postcode":"55041",
    "sg:province":"MN",
    "wof:name":"Schreiber & Jarstad",
    "wof:placetype":"venue"
},
  "geometry": {"coordinates":[-92.266217,44.449837],"type":"Point"}
}