{
  "type": "Feature",
  "properties": {
    "addr:full":"6193 Dell Ln S Saint Paul MN 55125",
    "addr:housenumber":"6193",
    "addr:postcode":"55125",
    "addr:street":"Dell Ln S",
    "iso:country":"US",
    "sg:address":"6193 Dell Ln S",
    "sg:city":"Saint Paul",
    "sg:classifiers":[
        {
            "category":"Organizations",
            "subcategory":"Non-profit Organization",
            "type":"Services"
        }
    ],
    "sg:phone":"+1 651 578 0033",
    "sg:postcode":"55125",
    "sg:province":"MN",
    "sg:tags":[
        "association",
        "social"
    ],
    "wof:name":"Christian Care Services",
    "wof:placetype":"venue"
},
  "geometry": {"coordinates":[-92.979861,44.945678],"type":"Point"}
}