{
  "type": "Feature",
  "properties": {
    "addr:full":"1212 Balsam Rd NW Bemidji MN 56601",
    "addr:housenumber":"1212",
    "addr:postcode":"56601",
    "addr:street":"Balsam Rd Nw",
    "iso:country":"US",
    "sg:address":"1212 Balsam Rd NW",
    "sg:city":"Bemidji",
    "sg:classifiers":[
        {
            "category":"Retail",
            "subcategory":"Repair Shop",
            "type":"Services"
        }
    ],
    "sg:phone":"+1 218 751 2969",
    "sg:postcode":"56601",
    "sg:province":"MN",
    "wof:name":"Vic S Septic Service",
    "wof:placetype":"venue"
},
  "geometry": {"coordinates":[-94.899106,47.526675],"type":"Point"}
}