{
  "type": "Feature",
  "properties": {
    "addr:full":"457 Dempsey Ave NW Buffalo MN 55313",
    "addr:housenumber":"457",
    "addr:postcode":"55313",
    "addr:street":"Dempsey Ave Nw",
    "iso:country":"US",
    "sg:address":"457 Dempsey Ave NW",
    "sg:city":"Buffalo",
    "sg:classifiers":[
        {
            "category":"Farming",
            "subcategory":"Livestock Farm",
            "type":"Manufacturing & Wholesale Goods"
        }
    ],
    "sg:phone":"+1 763 682 1539",
    "sg:postcode":"55313",
    "sg:province":"MN",
    "sg:tags":[
        "beef",
        "feedlot",
        "cattle"
    ],
    "wof:name":"Marquette Dairy",
    "wof:placetype":"venue"
},
  "geometry": {"coordinates":[-93.95128099999999,45.155369],"type":"Point"}
}