{
  "type": "Feature",
  "properties": {
    "addr:full":"202 E Howard St Hibbing MN 55746",
    "addr:housenumber":"202",
    "addr:postcode":"55746",
    "addr:street":"E Howard St",
    "iso:country":"US",
    "sg:address":"202 E Howard St",
    "sg:city":"Hibbing",
    "sg:classifiers":[
        {
            "category":"Banks & Credit Unions",
            "subcategory":"Bank",
            "type":"Services"
        }
    ],
    "sg:phone":"+1 218 262 0755",
    "sg:postcode":"55746",
    "sg:province":"MN",
    "sg:tags":[
        "mortgage"
    ],
    "wof:name":"Arrowhead Mortgage Inc",
    "wof:placetype":"venue"
},
  "geometry": {"coordinates":[-92.94053700000001,47.42738],"type":"Point"}
}