{
  "type": "Feature",
  "properties": {
    "addr:full":"106 E Washington Ave Fergus Falls MN 56537",
    "addr:housenumber":"106",
    "addr:postcode":"56537",
    "addr:street":"E Washington Ave",
    "iso:country":"US",
    "sg:address":"106 E Washington Ave",
    "sg:city":"Fergus Falls",
    "sg:classifiers":[
        {
            "category":"Health Services",
            "subcategory":"Doctor",
            "type":"Services"
        }
    ],
    "sg:phone":"+1 218 739 2297",
    "sg:postcode":"56537",
    "sg:province":"MN",
    "wof:name":"Greenagel Tom L DDS",
    "wof:placetype":"venue"
},
  "geometry": {"coordinates":[-96.072485,46.281361],"type":"Point"}
}