{
  "type": "Feature",
  "properties": {
    "iso:country":"US",
    "sg:address":"886 W Jefferson Ave",
    "sg:city":"St Paul",
    "sg:classifiers":[
        {
            "category":"Real Estate",
            "subcategory":"Real Estate Agent",
            "type":"Services"
        }
    ],
    "sg:phone":"+1 651 221 0590",
    "sg:postcode":"55102",
    "sg:province":"MN",
    "sg:tags":[
        "management"
    ],
    "wof:name":"Mc Grath Properties",
    "wof:placetype":"venue"
},
  "geometry": {"coordinates":[-93.138139,44.930443],"type":"Point"}
}