{
  "type": "Feature",
  "properties": {
    "addr:full":"5522 Hwy 67 Granite Falls MN 56241",
    "addr:housenumber":"5522",
    "addr:postcode":"56241",
    "addr:street":"Hwy 67",
    "iso:country":"US",
    "sg:address":"5522 Hwy 67",
    "sg:city":"Granite Falls",
    "sg:classifiers":[
        {
            "category":"Restaurant",
            "type":"Food & Drink"
        }
    ],
    "sg:phone":"+1 320 564 4141",
    "sg:postcode":"56241",
    "sg:province":"MN",
    "wof:name":"Mulligan's",
    "wof:placetype":"venue"
},
  "geometry": {"coordinates":[-95.53388699999999,44.79705],"type":"Point"}
}