{
  "type": "Feature",
  "properties": {
    "iso:country":"US",
    "sg:address":"147 W 4th St",
    "sg:city":"Red Wing",
    "sg:classifiers":[
        {
            "category":"Health Services",
            "subcategory":"Doctor",
            "type":"Services"
        }
    ],
    "sg:phone":"+1 651 385 3260",
    "sg:postcode":"55066",
    "sg:province":"MN",
    "sg:tags":[
        "physician",
        "surgeon"
    ],
    "wof:name":"Fairview Red Wing Medical Ctr",
    "wof:placetype":"venue"
},
  "geometry": {"coordinates":[-92.530277,44.566426],"type":"Point"}
}