{
  "type": "Feature",
  "properties": {
    "addr:full":"508 Main Ave N Thief River Fls MN 56701",
    "addr:housenumber":"508",
    "addr:postcode":"56701",
    "addr:street":"Main Ave N Thief River Fls",
    "iso:country":"US",
    "sg:address":"508 Main Ave N",
    "sg:city":"Thief River Fls",
    "sg:classifiers":[
        {
            "category":"Shopping",
            "subcategory":"Florist",
            "type":"Retail Goods"
        }
    ],
    "sg:phone":"+1 218 681 1940",
    "sg:postcode":"56701",
    "sg:province":"MN",
    "wof:name":"Hall's Floral Inc",
    "wof:placetype":"venue"
},
  "geometry": {"coordinates":[-96.181444,48.122156],"type":"Point"}
}