{
  "type": "Feature",
  "properties": {
    "addr:full":"2411 Pilot Knob Rd Eagan MN 55120",
    "addr:housenumber":"2411",
    "addr:postcode":"55120",
    "addr:street":"Pilot Knob Rd",
    "iso:country":"US",
    "sg:address":"2411 Pilot Knob Rd",
    "sg:city":"Eagan",
    "sg:classifiers":[
        {
            "category":"Manufacturing",
            "subcategory":"Metals",
            "type":"Manufacturing & Wholesale Goods"
        }
    ],
    "sg:phone":"+1 651 454 7777",
    "sg:postcode":"55120",
    "sg:province":"MN",
    "sg:tags":[
        "coating"
    ],
    "sg:website":"www.valmont.com",
    "wof:name":"Valmont Applied Coating Tech",
    "wof:placetype":"venue"
},
  "geometry": {"coordinates":[-93.167248,44.867041],"type":"Point"}
}