{
  "type": "Feature",
  "properties": {
    "iso:country":"US",
    "sg:address":"5000 Queen Ave S",
    "sg:city":"Minneapolis",
    "sg:classifiers":[
        {
            "category":"Professional",
            "subcategory":"Business Services",
            "type":"Services"
        }
    ],
    "sg:phone":"+1 612 296 0824",
    "sg:postcode":"55410",
    "sg:province":"MN",
    "sg:tags":[
        "translator",
        "interpreter"
    ],
    "wof:name":"Crissann Inc",
    "wof:placetype":"venue"
},
  "geometry": {"coordinates":[-93.30994,44.910571],"type":"Point"}
}