{
  "type": "Feature",
  "properties": {
    "iso:country":"US",
    "sg:address":"7166 4th St N",
    "sg:city":"St Paul",
    "sg:classifiers":[
        {
            "category":"Professional",
            "subcategory":"Management & Consulting",
            "type":"Services"
        },
        {
            "category":"Professional",
            "subcategory":"Advertising",
            "type":"Services"
        }
    ],
    "sg:phone":"+1 651 702 1297",
    "sg:postcode":"55128",
    "sg:province":"MN",
    "sg:tags":[
        "marketing",
        "mailing",
        "shipping",
        "communications"
    ],
    "sg:website":"www.regalservices.com",
    "wof:name":"Regal Services Group Inc",
    "wof:placetype":"venue"
},
  "geometry": {"coordinates":[-92.95943,44.953234],"type":"Point"}
}