{
  "type": "Feature",
  "properties": {
    "addr:full":"410 Hillock Ct Isanti MN 55040",
    "addr:housenumber":"410",
    "addr:postcode":"55040",
    "addr:street":"Hillock Ct",
    "iso:country":"US",
    "sg:address":"410 Hillock Ct",
    "sg:city":"Isanti",
    "sg:classifiers":[
        {
            "category":"Building & Trades",
            "subcategory":"Cleaning & Sanitation",
            "type":"Services"
        }
    ],
    "sg:phone":"+1 763 444 7808",
    "sg:postcode":"55040",
    "sg:province":"MN",
    "sg:tags":[
        "butler",
        "maid"
    ],
    "wof:name":"Enchanted Maid Svc",
    "wof:placetype":"venue"
},
  "geometry": {"coordinates":[-93.25619399999999,45.493832],"type":"Point"}
}