{
  "type": "Feature",
  "properties": {
    "addr:full":"216 Central Ave Nashwauk MN 55769",
    "addr:housenumber":"216",
    "addr:postcode":"55769",
    "addr:street":"Central Ave",
    "iso:country":"US",
    "sg:address":"216 Central Ave",
    "sg:city":"Nashwauk",
    "sg:classifiers":[
        {
            "category":"Professional",
            "type":"Services"
        }
    ],
    "sg:phone":"+1 218 885 1079",
    "sg:postcode":"55769",
    "sg:province":"MN",
    "wof:name":"Angels Wired",
    "wof:placetype":"venue"
},
  "geometry": {"coordinates":[-93.166016,47.38042],"type":"Point"}
}