{
  "type": "Feature",
  "properties": {
    "iso:country":"US",
    "sg:address":"3286 Richmond Alcove",
    "sg:city":"Saint Paul",
    "sg:classifiers":[
        {
            "category":"Professional",
            "type":"Services"
        }
    ],
    "sg:phone":"+1 651 730 6522",
    "sg:postcode":"55129",
    "sg:province":"MN",
    "wof:name":"A Simpler Time Inc",
    "wof:placetype":"venue"
},
  "geometry": {"coordinates":[-92.900656,44.901191],"type":"Point"}
}