{
  "type": "Feature",
  "properties": {
    "iso:country":"US",
    "sg:address":"5302 Grand Ave S",
    "sg:city":"Minneapolis",
    "sg:classifiers":[
        {
            "category":"Education",
            "subcategory":"Special Training",
            "type":"Public Place"
        }
    ],
    "sg:phone":"+1 612 827 1837",
    "sg:postcode":"55419",
    "sg:province":"MN",
    "wof:name":"Bruce Frank Scholarship F",
    "wof:placetype":"venue"
},
  "geometry": {"coordinates":[-93.28452900000001,44.904972],"type":"Point"}
}