{
  "type": "Feature",
  "properties": {
    "iso:country":"US",
    "sg:address":"2408 Central Ave NE",
    "sg:city":"Minneapolis",
    "sg:classifiers":[
        {
            "category":"Organizations",
            "subcategory":"Labor Organization",
            "type":"Services"
        }
    ],
    "sg:phone":"+1 612 781 9858",
    "sg:postcode":"55418",
    "sg:province":"MN",
    "sg:website":"http://www.nalc.org",
    "wof:name":"National Association of Letter Carriers",
    "wof:placetype":"venue"
},
  "geometry": {"coordinates":[-93.247371,45.012217],"type":"Point"}
}