{
  "type": "Feature",
  "properties": {
    "addr:full":"21660 S Diamond Lake Rd Rogers MN 55374",
    "addr:housenumber":"21660",
    "addr:postcode":"55374",
    "addr:street":"S Diamond Lake Rd",
    "iso:country":"US",
    "sg:address":"21660 S Diamond Lake Rd",
    "sg:city":"Rogers",
    "sg:classifiers":[
        {
            "category":"Banks & Credit Unions",
            "subcategory":"Bank",
            "type":"Services"
        }
    ],
    "sg:phone":"+1 763 428 2111",
    "sg:postcode":"55374",
    "sg:province":"MN",
    "sg:tags":[
        "state",
        "commercial"
    ],
    "wof:name":"21st Century Bank North",
    "wof:placetype":"venue"
},
  "geometry": {"coordinates":[-93.557045,45.199648],"type":"Point"}
}