{
  "type": "Feature",
  "properties": {
    "iso:country":"US",
    "sg:address":"2286 Carter Ave",
    "sg:city":"Saint Paul",
    "sg:classifiers":[
        {
            "category":"Professional",
            "subcategory":"Accounting & Tax Preparation",
            "type":"Services"
        }
    ],
    "sg:phone":"+1 651 646 0583",
    "sg:postcode":"55108",
    "sg:province":"MN",
    "wof:name":"Home Energy Audits LLC",
    "wof:placetype":"venue"
},
  "geometry": {"coordinates":[-93.19509499999999,44.981278],"type":"Point"}
}