{
  "type": "Feature",
  "properties": {
    "addr:full":"430 Oak Ave S Maple Lake MN 55358",
    "addr:housenumber":"430",
    "addr:postcode":"55358",
    "addr:street":"Oak Ave S Maple Lake",
    "iso:country":"US",
    "sg:address":"430 Oak Ave S",
    "sg:city":"Maple Lake",
    "sg:classifiers":[
        {
            "category":"Restaurant",
            "type":"Food & Drink"
        }
    ],
    "sg:phone":"+1 320 236 7245",
    "sg:postcode":"55358",
    "sg:province":"MN",
    "wof:name":"Twin Rails Bar & Grill",
    "wof:placetype":"venue"
},
  "geometry": {"coordinates":[-94.001953,45.224634],"type":"Point"}
}