{
  "type": "Feature",
  "properties": {
    "addr:full":"2500 Morrison St Saint Paul MN 55117",
    "addr:housenumber":"2500",
    "addr:postcode":"55117",
    "addr:street":"Morrison St",
    "iso:country":"US",
    "sg:address":"2500 Morrison St",
    "sg:city":"Saint Paul",
    "sg:classifiers":[
        {
            "category":"Building & Trades",
            "subcategory":"Construction",
            "type":"Services"
        }
    ],
    "sg:phone":"+1 651 484 5003",
    "sg:postcode":"55117",
    "sg:province":"MN",
    "sg:tags":[
        "house"
    ],
    "wof:name":"Kipps Custom Remodeling Inc",
    "wof:placetype":"venue"
},
  "geometry": {"coordinates":[-93.086476,45.016055],"type":"Point"}
}