{
  "type": "Feature",
  "properties": {
    "iso:country":"US",
    "sg:address":"500 S 13th St",
    "sg:city":"Olivia",
    "sg:classifiers":[
        {
            "category":"Real Estate",
            "subcategory":"Real Estate Operator",
            "type":"Services"
        }
    ],
    "sg:phone":"+1 320 523 2101",
    "sg:postcode":"56277",
    "sg:province":"MN",
    "sg:tags":[
        "apartment"
    ],
    "wof:name":"Westcourt Apartments",
    "wof:placetype":"venue"
},
  "geometry": {"coordinates":[-94.995431,44.772301],"type":"Point"}
}