{
  "type": "Feature",
  "properties": {
    "iso:country":"US",
    "sg:address":"582 4th St N",
    "sg:city":"Bayport",
    "sg:classifiers":[
        {
            "category":"Real Estate",
            "subcategory":"Real Estate Operator",
            "type":"Services"
        }
    ],
    "sg:phone":"+1 651 439 3106",
    "sg:postcode":"55003",
    "sg:province":"MN",
    "sg:tags":[
        "building",
        "nonresidential"
    ],
    "wof:name":"White Pine Community Mtg Rm",
    "wof:placetype":"venue"
},
  "geometry": {"coordinates":[-92.781086,45.021253],"type":"Point"}
}