{
  "type": "Feature",
  "properties": {
    "iso:country":"US",
    "sg:address":"32196 740th Ave",
    "sg:city":"Olivia",
    "sg:phone":"+1 320 523 1976",
    "sg:postcode":"56277",
    "sg:province":"MN",
    "sg:tags":[
        "beef",
        "farm",
        "corn",
        "cash",
        "grain",
        "cattle",
        "feedlot"
    ],
    "wof:name":"Harvey Mathiowetz",
    "wof:placetype":"venue"
},
  "geometry": {"coordinates":[-95.02981200000001,44.657958],"type":"Point"}
}