{
  "type": "Feature",
  "properties": {
    "addr:full":"3600 Phillips Pkwy Minneapolis MN 55426",
    "addr:housenumber":"3600",
    "addr:postcode":"55426",
    "addr:street":"Phillips Pkwy",
    "iso:country":"US",
    "sg:address":"3600 Phillips Pkwy",
    "sg:city":"Minneapolis",
    "sg:classifiers":[
        {
            "category":"Real Estate",
            "subcategory":"Real Estate Operator",
            "type":"Services"
        }
    ],
    "sg:phone":"+1 952 933 6538",
    "sg:postcode":"55426",
    "sg:province":"MN",
    "sg:tags":[
        "building",
        "apartment"
    ],
    "wof:name":"Menorah West Apartments",
    "wof:placetype":"venue"
},
  "geometry": {"coordinates":[-93.39447,44.937205],"type":"Point"}
}