{
  "type": "Feature",
  "properties": {
    "iso:country":"US",
    "sg:address":"503 Parkway Ave S Ofc Ofc",
    "sg:city":"Lanesboro",
    "sg:classifiers":[
        {
            "category":"Real Estate",
            "subcategory":"Real Estate Operator",
            "type":"Services"
        }
    ],
    "sg:phone":"+1 507 467 2551",
    "sg:postcode":"55949",
    "sg:province":"MN",
    "sg:tags":[
        "apartment"
    ],
    "wof:name":"Sylvan Manor Apts.",
    "wof:placetype":"venue"
},
  "geometry": {"coordinates":[-91.97683000000001,43.71651],"type":"Point"}
}