{
  "type": "Feature",
  "properties": {
    "addr:full":"88502 490th Ave Windom MN 56101",
    "addr:housenumber":"88502",
    "addr:postcode":"56101",
    "addr:street":"490Th Ave",
    "iso:country":"US",
    "sg:address":"88502 490th Ave",
    "sg:city":"Windom",
    "sg:classifiers":[
        {
            "category":"Farming",
            "subcategory":"Livestock Farm",
            "type":"Manufacturing & Wholesale Goods"
        }
    ],
    "sg:phone":"+1 507 831 2714",
    "sg:postcode":"56101",
    "sg:province":"MN",
    "sg:tags":[
        "hog",
        "beef",
        "liv",
        "cattle",
        "or",
        "feedlot"
    ],
    "wof:name":"Lake Field",
    "wof:placetype":"venue"
},
  "geometry": {"coordinates":[-95.095291,43.770398],"type":"Point"}
}