{
  "type": "Feature",
  "properties": {
    "addr:full":"609 W Main St Madelia MN 56062",
    "addr:housenumber":"609",
    "addr:postcode":"56062",
    "addr:street":"W Main St",
    "iso:country":"US",
    "sg:address":"609 W Main St",
    "sg:city":"Madelia",
    "sg:classifiers":[
        {
            "category":"Farming",
            "subcategory":"Nursery",
            "type":"Manufacturing & Wholesale Goods"
        }
    ],
    "sg:phone":"+1 507 642 8719",
    "sg:postcode":"56062",
    "sg:province":"MN",
    "sg:tags":[
        "ornamental",
        "greenhouse"
    ],
    "wof:name":"Shellee's Greenhouse",
    "wof:placetype":"venue"
},
  "geometry": {"coordinates":[-94.425224,44.050857],"type":"Point"}
}