{
  "type": "Feature",
  "properties": {
    "iso:country":"US",
    "sg:address":"7907 Powers Blvd",
    "sg:city":"Chanhassen",
    "sg:classifiers":[
        {
            "category":"Health Services",
            "subcategory":"Doctor",
            "type":"Services"
        },
        {
            "category":"Health Services",
            "subcategory":"Optometrist",
            "type":"Services"
        },
        {
            "category":"Health Services",
            "subcategory":"Health Practitioner",
            "type":"Services"
        }
    ],
    "sg:phone":"+1 952 906 7826",
    "sg:postcode":"55317",
    "sg:province":"MN",
    "sg:tags":[
        "physician",
        "laser",
        "surgeons",
        "ophthalmology",
        "surgery",
        "surgeon"
    ],
    "wof:name":"Barer, Charles F, Md - Edina Eye Physicians & Surgeon",
    "wof:placetype":"venue"
},
  "geometry": {"coordinates":[-93.54803200000001,44.860557],"type":"Point"}
}