{
  "type": "Feature",
  "properties": {
    "addr:full":"411 Broadway Ave N Rochester MN 55906",
    "addr:housenumber":"411",
    "addr:postcode":"55906",
    "addr:street":"Broadway Ave N",
    "iso:country":"US",
    "sg:address":"411 Broadway Ave N",
    "sg:city":"Rochester",
    "sg:classifiers":[
        {
            "category":"Professional",
            "subcategory":"Management & Consulting",
            "type":"Services"
        },
        {
            "category":"Professional",
            "subcategory":"Advertising",
            "type":"Services"
        },
        {
            "category":"Professional",
            "subcategory":"Computer Services",
            "type":"Services"
        }
    ],
    "sg:phone":"+1 507 281 3490",
    "sg:postcode":"55906",
    "sg:province":"MN",
    "sg:tags":[
        "marketing",
        "software",
        "agency",
        "consultant"
    ],
    "wof:name":"Mlt Group",
    "wof:placetype":"venue"
},
  "geometry": {"coordinates":[-92.46296599999999,44.027274],"type":"Point"}
}