{
  "type": "Feature",
  "properties": {
    "iso:country":"US",
    "sg:address":"38594 870th Ave",
    "sg:city":"Bird Island",
    "sg:phone":"+1 320 365 4361",
    "sg:postcode":"55310",
    "sg:province":"MN",
    "sg:tags":[
        "farm",
        "corn",
        "soybean"
    ],
    "wof:name":"Gass John",
    "wof:placetype":"venue"
},
  "geometry": {"coordinates":[-94.897587,44.847747],"type":"Point"}
}