{
  "type": "Feature",
  "properties": {
    "iso:country":"US",
    "sg:address":"8830 47th Ave N",
    "sg:city":"Minneapolis",
    "sg:classifiers":[
        {
            "category":"Insurance",
            "subcategory":"Insurance Agent",
            "type":"Services"
        }
    ],
    "sg:phone":"+1 763 535 3656",
    "sg:postcode":"55428",
    "sg:province":"MN",
    "wof:name":"Jamey Grosser Grosser Ins",
    "wof:placetype":"venue"
},
  "geometry": {"coordinates":[-93.391761,45.039814],"type":"Point"}
}