{
  "type": "Feature",
  "properties": {
    "iso:country":"US",
    "sg:address":"21079 Olinda Trl N",
    "sg:city":"Scandia",
    "sg:classifiers":[
        {
            "category":"Restaurant",
            "type":"Food & Drink"
        }
    ],
    "sg:phone":"+1 651 433 4054",
    "sg:postcode":"55073",
    "sg:province":"MN",
    "sg:tags":[
        "eating"
    ],
    "wof:name":"Scandia Cafe",
    "wof:placetype":"venue"
},
  "geometry": {"coordinates":[-92.80563100000001,45.254409],"type":"Point"}
}