{
  "type": "Feature",
  "properties": {
    "addr:full":"5840 73rd Ave N Brooklyn Park MN 55429",
    "addr:housenumber":"5840",
    "addr:postcode":"55429",
    "addr:street":"73Rd Ave N",
    "iso:country":"US",
    "sg:address":"5840 73rd Ave N",
    "sg:city":"Brooklyn Park",
    "sg:classifiers":[
        {
            "category":"Real Estate",
            "subcategory":"Real Estate Operator",
            "type":"Services"
        }
    ],
    "sg:phone":"+1 763 566 1577",
    "sg:postcode":"55429",
    "sg:province":"MN",
    "sg:tags":[
        "building",
        "apartment"
    ],
    "wof:name":"Ridgebrook Apartments",
    "wof:placetype":"venue"
},
  "geometry": {"coordinates":[-93.35501600000001,45.08733],"type":"Point"}
}