{
  "type": "Feature",
  "properties": {
    "iso:country":"US",
    "sg:address":"214 3rd St NW",
    "sg:city":"Bemidji",
    "sg:classifiers":[
        {
            "category":"Coffee & Tea",
            "type":"Food & Drink"
        },
        {
            "category":"Restaurant",
            "type":"Food & Drink"
        }
    ],
    "sg:phone":"+1 218 444 2899",
    "sg:postcode":"56601",
    "sg:province":"MN",
    "sg:tags":[
        "shop",
        "espresso"
    ],
    "wof:name":"Cabin Coffeehouse & Cafe",
    "wof:placetype":"venue"
},
  "geometry": {"coordinates":[-94.881401,47.470528],"type":"Point"}
}