{
  "type": "Feature",
  "properties": {
    "iso:country":"US",
    "sg:address":"601 Carlson Pkwy S",
    "sg:city":"Hopkins",
    "sg:classifiers":[
        {
            "category":"Manufacturing",
            "subcategory":"Glass & Minerals",
            "type":"Manufacturing & Wholesale Goods"
        }
    ],
    "sg:phone":"+1 952 449 4950",
    "sg:postcode":"55305",
    "sg:province":"MN",
    "sg:tags":[
        "mfg",
        "granite",
        "product",
        "cut",
        "drafting"
    ],
    "wof:name":"Cold Spring Granite Company",
    "wof:placetype":"venue"
},
  "geometry": {"coordinates":[-93.469363,44.974638],"type":"Point"}
}