{
  "type": "Feature",
  "properties": {
    "iso:country":"US",
    "sg:address":"1011 Washington Ave S Ste 200",
    "sg:city":"Minneapolis",
    "sg:classifiers":[
        {
            "category":"Education",
            "subcategory":"Special Training",
            "type":"Public Place"
        }
    ],
    "sg:phone":"+1 612 215 2575",
    "sg:postcode":"55415",
    "sg:province":"MN",
    "sg:tags":[
        "adult"
    ],
    "wof:name":"Loft Literary Center",
    "wof:placetype":"venue"
},
  "geometry": {"coordinates":[-93.25442,44.975848],"type":"Point"}
}