{
  "type": "Feature",
  "properties": {
    "iso:country":"US",
    "sg:address":"8352 150th St",
    "sg:city":"Kimball",
    "sg:classifiers":[
        {
            "category":"Home & Garden",
            "subcategory":"Garden Supply",
            "type":"Retail Goods"
        }
    ],
    "sg:phone":"+1 320 398 7126",
    "sg:postcode":"55353",
    "sg:province":"MN",
    "wof:name":"Peonies By Tom Garden Center",
    "wof:placetype":"venue"
},
  "geometry": {"coordinates":[-94.286292,45.341552],"type":"Point"}
}