{
  "type": "Feature",
  "properties": {
    "addr:full":"109 S 5th St Marshall MN 56258",
    "addr:housenumber":"109",
    "addr:postcode":"56258",
    "addr:street":"S 5Th St",
    "iso:country":"US",
    "sg:address":"109 S 5th St",
    "sg:city":"Marshall",
    "sg:classifiers":[
        {
            "category":"Health Services",
            "subcategory":"Podiatrist",
            "type":"Services"
        }
    ],
    "sg:phone":"+1 507 532 0077",
    "sg:postcode":"56258",
    "sg:province":"MN",
    "wof:name":"Halverson Dirk S DPM",
    "wof:placetype":"venue"
},
  "geometry": {"coordinates":[-95.79239800000001,44.449273],"type":"Point"}
}