{
  "type": "Feature",
  "properties": {
    "addr:full":"4012 2nd St NW Rochester MN 55901",
    "addr:housenumber":"4012",
    "addr:postcode":"55901",
    "addr:street":"2Nd St Nw",
    "iso:country":"US",
    "sg:address":"4012 2nd St NW",
    "sg:city":"Rochester",
    "sg:classifiers":[
        {
            "category":"Building & Trades",
            "subcategory":"Construction",
            "type":"Services"
        }
    ],
    "sg:phone":"+1 507 282 6573",
    "sg:postcode":"55901",
    "sg:province":"MN",
    "sg:tags":[
        "contractor"
    ],
    "wof:name":"Dale Curtin Drywall",
    "wof:placetype":"venue"
},
  "geometry": {"coordinates":[-92.52806,44.02477],"type":"Point"}
}