{
  "type": "Feature",
  "properties": {
    "addr:full":"11225 51st Ave N Minneapolis MN 55442",
    "addr:housenumber":"11225",
    "addr:postcode":"55442",
    "addr:street":"51St Ave N",
    "iso:country":"US",
    "sg:address":"11225 51st Ave N",
    "sg:city":"Minneapolis",
    "sg:classifiers":[
        {
            "category":"Building & Trades",
            "subcategory":"Construction",
            "type":"Services"
        }
    ],
    "sg:phone":"+1 763 383 1740",
    "sg:postcode":"55442",
    "sg:province":"MN",
    "sg:tags":[
        "sporting",
        "hanging",
        "contractor"
    ],
    "wof:name":"McM Sports Inc",
    "wof:placetype":"venue"
},
  "geometry": {"coordinates":[-93.42344199999999,45.047607],"type":"Point"}
}