{
  "type": "Feature",
  "properties": {
    "addr:full":"16112 State 34 Park Rapids MN 56470",
    "addr:housenumber":"16112;34",
    "addr:postcode":"56470",
    "addr:street":"State",
    "iso:country":"US",
    "sg:address":"16112 State 34",
    "sg:city":"Park Rapids",
    "sg:classifiers":[
        {
            "category":"Farming",
            "subcategory":"Nursery",
            "type":"Manufacturing & Wholesale Goods"
        }
    ],
    "sg:phone":"+1 218 732 8033",
    "sg:postcode":"56470",
    "sg:province":"MN",
    "sg:tags":[
        "greenhouse"
    ],
    "wof:name":"Hafner Green House",
    "wof:placetype":"venue"
},
  "geometry": {"coordinates":[-95.030434,46.921977],"type":"Point"}
}