{
  "type": "Feature",
  "properties": {
    "addr:full":"4815 Lakeview Dr Minneapolis MN 55424",
    "addr:housenumber":"4815",
    "addr:postcode":"55424",
    "addr:street":"Lakeview Dr",
    "iso:country":"US",
    "sg:address":"4815 Lakeview Dr",
    "sg:city":"Minneapolis",
    "sg:classifiers":[
        {
            "category":"Professional",
            "subcategory":"Management & Consulting",
            "type":"Services"
        },
        {
            "category":"Professional",
            "subcategory":"Engineering",
            "type":"Services"
        }
    ],
    "sg:phone":"+1 952 922 6625",
    "sg:postcode":"55424",
    "sg:province":"MN",
    "sg:tags":[
        "consultant",
        "engineer"
    ],
    "sg:website":"http://www.bmcbenefits.com",
    "wof:name":"Benefit Management Consultant Inc",
    "wof:placetype":"venue"
},
  "geometry": {"coordinates":[-93.346992,44.902328],"type":"Point"}
}