{
  "type": "Feature",
  "properties": {
    "iso:country":"US",
    "sg:address":"7450 France Ave S",
    "sg:city":"Minneapolis",
    "sg:classifiers":[
        {
            "category":"Real Estate",
            "subcategory":"Real Estate Agent",
            "type":"Services"
        }
    ],
    "sg:phone":"+1 952 884 8404",
    "sg:postcode":"55435",
    "sg:province":"MN",
    "sg:tags":[
        "broker",
        "associate"
    ],
    "wof:name":"Re/Max",
    "wof:placetype":"venue"
},
  "geometry": {"coordinates":[-93.32901200000001,44.870438],"type":"Point"}
}