{
  "type": "Feature",
  "properties": {
    "addr:full":"1418 S Oak Ave Owatonna MN 55060",
    "addr:housenumber":"1418",
    "addr:postcode":"55060",
    "addr:street":"S Oak Ave",
    "iso:country":"US",
    "sg:address":"1418 S Oak Ave",
    "sg:city":"Owatonna",
    "sg:classifiers":[
        {
            "category":"Freight",
            "type":"Transportation"
        }
    ],
    "sg:phone":"+1 507 451 4000",
    "sg:postcode":"55060",
    "sg:province":"MN",
    "wof:name":"Jefferson Lines",
    "wof:placetype":"venue"
},
  "geometry": {"coordinates":[-93.22676300000001,44.069544],"type":"Point"}
}