{
  "type": "Feature",
  "properties": {
    "iso:country":"US",
    "sg:address":"7700 110th St S",
    "sg:city":"Cottage Grove",
    "sg:classifiers":[
        {
            "category":"Building & Trades",
            "subcategory":"Landscaping Services",
            "type":"Services"
        }
    ],
    "sg:phone":"+1 651 459 5007",
    "sg:postcode":"55016",
    "sg:province":"MN",
    "sg:tags":[
        "tree"
    ],
    "wof:name":"Blue Chip Tree Co",
    "wof:placetype":"venue"
},
  "geometry": {"coordinates":[-92.949573,44.79018],"type":"Point"}
}