{
  "type": "Feature",
  "properties": {
    "addr:full":"9747 Union Lake Trl Lonsdale MN 55046",
    "addr:housenumber":"9747",
    "addr:postcode":"55046",
    "addr:street":"Union Lake Trl",
    "iso:country":"US",
    "sg:address":"9747 Union Lake Trl",
    "sg:city":"Lonsdale",
    "sg:classifiers":[
        {
            "category":"Professional",
            "type":"Services"
        }
    ],
    "sg:phone":"+1 507 744 2797",
    "sg:postcode":"55046",
    "sg:province":"MN",
    "sg:tags":[
        "establishment"
    ],
    "wof:name":"Trcka & Tricka",
    "wof:placetype":"venue"
},
  "geometry": {"coordinates":[-93.456717,44.460867],"type":"Point"}
}