{
  "type": "Feature",
  "properties": {
    "addr:full":"1500 Jackson St NE Minneapolis MN 55413",
    "addr:housenumber":"1500",
    "addr:postcode":"55413",
    "addr:street":"Jackson St Ne",
    "iso:country":"US",
    "sg:address":"1500 Jackson St NE",
    "sg:city":"Minneapolis",
    "sg:classifiers":[
        {
            "category":"Real Estate",
            "subcategory":"Architect",
            "type":"Services"
        }
    ],
    "sg:phone":"+1 612 706 5600",
    "sg:postcode":"55413",
    "sg:province":"MN",
    "sg:website":"www.livegreenlivesmart.org",
    "wof:name":"Locus Architecture",
    "wof:placetype":"venue"
},
  "geometry": {"coordinates":[-93.249802,45.003502],"type":"Point"}
}