{
  "type": "Feature",
  "properties": {
    "addr:full":"3025 Harbor Ln N Ste 101 Minneapolis MN 55447",
    "addr:housenumber":"3025",
    "addr:postcode":"55447",
    "addr:street":"Harbor Ln N Ste 101",
    "iso:country":"US",
    "sg:address":"3025 Harbor Ln N Ste 101",
    "sg:city":"Minneapolis",
    "sg:classifiers":[
        {
            "category":"Professional",
            "subcategory":"Business Services",
            "type":"Services"
        }
    ],
    "sg:phone":"+1 952 935 5790",
    "sg:postcode":"55447",
    "sg:province":"MN",
    "sg:tags":[
        "testing"
    ],
    "wof:name":"Touchstone Testing Service",
    "wof:placetype":"venue"
},
  "geometry": {"coordinates":[-93.4628,45.01416],"type":"Point"}
}