{
  "type": "Feature",
  "properties": {
    "addr:full":"3381 Gorham Ave Minneapolis MN 55426",
    "addr:housenumber":"3381",
    "addr:postcode":"55426",
    "addr:street":"Gorham Ave",
    "iso:country":"US",
    "sg:address":"3381 Gorham Ave",
    "sg:city":"Minneapolis",
    "sg:classifiers":[
        {
            "category":"Education",
            "subcategory":"Special Training",
            "type":"Public Place"
        }
    ],
    "sg:phone":"+1 952 927 4115",
    "sg:postcode":"55426",
    "sg:province":"MN",
    "sg:tags":[
        "university",
        "college",
        "school",
        "interest"
    ],
    "wof:name":"American College of Metaphysic",
    "wof:placetype":"venue"
},
  "geometry": {"coordinates":[-93.36592,44.939507],"type":"Point"}
}