{
  "type": "Feature",
  "properties": {
    "iso:country":"US",
    "sg:address":"797 Selby Ave",
    "sg:city":"Saint Paul",
    "sg:classifiers":[
        {
            "category":"Professional",
            "subcategory":"Computer Services",
            "type":"Services"
        }
    ],
    "sg:phone":"+1 651 222 8049",
    "sg:postcode":"55104",
    "sg:province":"MN",
    "sg:tags":[
        "programing",
        "custom"
    ],
    "wof:name":"Garrett Angstman Enterpri",
    "wof:placetype":"venue"
},
  "geometry": {"coordinates":[-93.134326,44.946683],"type":"Point"}
}