{
  "type": "Feature",
  "properties": {
    "addr:full":"15083 Flagstaff Ave Saint Paul MN 55124",
    "addr:housenumber":"15083",
    "addr:postcode":"55124",
    "addr:street":"Flagstaff Ave",
    "iso:country":"US",
    "sg:address":"15083 Flagstaff Ave",
    "sg:city":"Saint Paul",
    "sg:classifiers":[
        {
            "category":"Personal",
            "subcategory":"Beauty Salon",
            "type":"Services"
        }
    ],
    "sg:phone":"+1 952 997 7567",
    "sg:postcode":"55124",
    "sg:province":"MN",
    "sg:tags":[
        "shop"
    ],
    "wof:name":"K C Cuts",
    "wof:placetype":"venue"
},
  "geometry": {"coordinates":[-93.197478,44.723116],"type":"Point"}
}