{
  "type": "Feature",
  "properties": {
    "iso:country":"US",
    "sg:address":"129 Main St S",
    "sg:city":"Chatfield",
    "sg:classifiers":[
        {
            "category":"Restaurant",
            "type":"Food & Drink"
        }
    ],
    "sg:phone":"+1 507 867 3939",
    "sg:postcode":"55923",
    "sg:province":"MN",
    "wof:name":"Blues",
    "wof:placetype":"venue"
},
  "geometry": {"coordinates":[-92.189646,43.84606],"type":"Point"}
}