{
  "type": "Feature",
  "properties": {
    "iso:country":"US",
    "sg:address":"4700 Nathan Ln N",
    "sg:city":"Minneapolis",
    "sg:classifiers":[
        {
            "category":"Professional",
            "subcategory":"Research",
            "type":"Services"
        }
    ],
    "sg:phone":"+1 763 744 5000",
    "sg:postcode":"55442",
    "sg:province":"MN",
    "sg:tags":[
        "development",
        "electronics"
    ],
    "sg:website":"http://www.mrcwdc.com",
    "wof:name":"Alliant Techsystems Inc.",
    "wof:placetype":"venue"
},
  "geometry": {"coordinates":[-93.405315,45.038879],"type":"Point"}
}