{
  "type": "Feature",
  "properties": {
    "addr:full":"3705 Enterprise Dr SW Rochester MN 55902",
    "addr:housenumber":"3705",
    "addr:postcode":"55902",
    "addr:street":"Enterprise Dr Sw",
    "iso:country":"US",
    "sg:address":"3705 Enterprise Dr SW",
    "sg:city":"Rochester",
    "sg:classifiers":[
        {
            "category":"Building & Trades",
            "subcategory":"Construction",
            "type":"Services"
        }
    ],
    "sg:phone":"+1 507 287 8788",
    "sg:postcode":"55902",
    "sg:province":"MN",
    "sg:tags":[
        "brick",
        "floor",
        "laying",
        "merchandise",
        "contractor"
    ],
    "wof:name":"Degeus Tile & Granite",
    "wof:placetype":"venue"
},
  "geometry": {"coordinates":[-92.466621,43.96855],"type":"Point"}
}