{
  "type": "Feature",
  "properties": {
    "addr:full":"7066 Ninebark Dr NW Walker MN 56484",
    "addr:housenumber":"7066",
    "addr:postcode":"56484",
    "addr:street":"Ninebark Dr Nw",
    "iso:country":"US",
    "sg:address":"7066 Ninebark Dr NW",
    "sg:city":"Walker",
    "sg:classifiers":[
        {
            "category":"Travel",
            "subcategory":"Hotels & Motels",
            "type":"Entertainment"
        }
    ],
    "sg:phone":"+1 218 547 1626",
    "sg:postcode":"56484",
    "sg:province":"MN",
    "sg:tags":[
        "resort",
        "operation"
    ],
    "wof:name":"Ivanhoe Resort Inc",
    "wof:placetype":"venue"
},
  "geometry": {"coordinates":[-94.555978,47.063878],"type":"Point"}
}