{
  "type": "Feature",
  "properties": {
    "addr:full":"139 W Lake St Minneapolis MN 55408",
    "addr:housenumber":"139",
    "addr:postcode":"55408",
    "addr:street":"W Lake St",
    "iso:country":"US",
    "sg:address":"139 W Lake St",
    "sg:city":"Minneapolis",
    "sg:classifiers":[
        {
            "category":"Personal",
            "subcategory":"Beauty Salon",
            "type":"Services"
        }
    ],
    "sg:phone":"+1 612 827 3851",
    "sg:postcode":"55408",
    "sg:province":"MN",
    "sg:tags":[
        "shop"
    ],
    "wof:name":"Beaux Le Tress Designers",
    "wof:placetype":"venue"
},
  "geometry": {"coordinates":[-93.281203,44.948282],"type":"Point"}
}