{
  "type": "Feature",
  "properties": {
    "addr:full":"310 Wollan St Starbuck MN 56381",
    "addr:housenumber":"310",
    "addr:postcode":"56381",
    "addr:street":"Wollan St",
    "iso:country":"US",
    "sg:address":"310 Wollan St",
    "sg:city":"Starbuck",
    "sg:classifiers":[
        {
            "category":"Autos & Motor Vehicles",
            "subcategory":"Auto Supplies",
            "type":"Retail Goods"
        }
    ],
    "sg:phone":"+1 320 239 2234",
    "sg:postcode":"56381",
    "sg:province":"MN",
    "sg:tags":[
        "automobile",
        "part"
    ],
    "wof:name":"Starbuck Bumper To Bumper",
    "wof:placetype":"venue"
},
  "geometry": {"coordinates":[-95.532608,45.611004],"type":"Point"}
}