{
  "type": "Feature",
  "properties": {
    "addr:full":"3000 N 2nd St Ste C Minneapolis MN 55411",
    "addr:housenumber":"3000",
    "addr:postcode":"55411",
    "addr:street":"N 2Nd St Ste C",
    "iso:country":"US",
    "sg:address":"3000 N 2nd St Ste C",
    "sg:city":"Minneapolis",
    "sg:classifiers":[
        {
            "category":"Professional",
            "subcategory":"Printing & Photocopies",
            "type":"Services"
        }
    ],
    "sg:phone":"+1 612 312 1700",
    "sg:postcode":"55411",
    "sg:province":"MN",
    "sg:tags":[
        "lithographer"
    ],
    "sg:website":"http://www.advancedprocesstechnologies.com",
    "wof:name":"Digital Access",
    "wof:placetype":"venue"
},
  "geometry": {"coordinates":[-93.280449,45.0107],"type":"Point"}
}