{
  "type": "Feature",
  "properties": {
    "addr:full":"115 Minneapolis Ave Duluth MN 55803",
    "addr:housenumber":"115",
    "addr:postcode":"55803",
    "addr:street":"Minneapolis Ave",
    "iso:country":"US",
    "sg:address":"115 Minneapolis Ave",
    "sg:city":"Duluth",
    "sg:classifiers":[
        {
            "category":"Building & Trades",
            "subcategory":"Construction",
            "type":"Services"
        }
    ],
    "sg:phone":"+1 218 724 8473",
    "sg:postcode":"55803",
    "sg:province":"MN",
    "sg:tags":[
        "cabinet",
        "maker",
        "contractor"
    ],
    "wof:name":"Solberg Construction",
    "wof:placetype":"venue"
},
  "geometry": {"coordinates":[-92.076244,46.840064],"type":"Point"}
}