{
  "type": "Feature",
  "properties": {
    "iso:country":"US",
    "sg:address":"50 Sherburne Ave",
    "sg:city":"Saint Paul",
    "sg:classifiers":[
        {
            "category":"Government",
            "subcategory":"Office",
            "type":"Public Place"
        }
    ],
    "sg:phone":"+1 651 296 3776",
    "sg:postcode":"55103",
    "sg:province":"MN",
    "sg:tags":[
        "administrative",
        "program",
        "economic",
        "general"
    ],
    "wof:name":"Contracts and Technical Svcs",
    "wof:placetype":"venue"
},
  "geometry": {"coordinates":[-93.101647,44.956767],"type":"Point"}
}