{
  "type": "Feature",
  "properties": {
    "addr:full":"510 Norwood St Brainerd MN 56401",
    "addr:housenumber":"510",
    "addr:postcode":"56401",
    "addr:street":"Norwood St",
    "iso:country":"US",
    "sg:address":"510 Norwood St",
    "sg:city":"Brainerd",
    "sg:classifiers":[
        {
            "category":"Government",
            "subcategory":"Court House",
            "type":"Public Place"
        }
    ],
    "sg:phone":"+1 218 828 2311",
    "sg:postcode":"56401",
    "sg:province":"MN",
    "sg:tags":[
        "legal"
    ],
    "wof:name":"Mallie Law Office",
    "wof:placetype":"venue"
},
  "geometry": {"coordinates":[-94.20207499999999,46.353622],"type":"Point"}
}