{
  "type": "Feature",
  "properties": {
    "addr:full":"34020 Timbercrest Rd Redwood Falls MN 56283",
    "addr:postcode":"34020;56283",
    "addr:street":"Timbercrest Rd",
    "iso:country":"US",
    "sg:address":"34020 Timbercrest Rd",
    "sg:city":"Redwood Falls",
    "sg:classifiers":[
        {
            "category":"Organizations",
            "subcategory":"Religious Organization",
            "type":"Services"
        }
    ],
    "sg:phone":"+1 507 644 2121",
    "sg:postcode":"56283",
    "sg:province":"MN",
    "sg:tags":[
        "church"
    ],
    "wof:name":"Jehovah's Witnesses Kingdom",
    "wof:placetype":"venue"
},
  "geometry": {"coordinates":[-95.052262,44.542043],"type":"Point"}
}