{
  "type": "Feature",
  "properties": {
    "addr:full":"16380 Co Rd 4 Spring Grove MN 55974",
    "addr:housenumber":"16380",
    "addr:postcode":"55974",
    "addr:street":"Co Rd 4",
    "iso:country":"US",
    "sg:address":"16380 Co Rd 4",
    "sg:city":"Spring Grove",
    "sg:classifiers":[
        {
            "category":"Building & Trades",
            "subcategory":"Electrical",
            "type":"Services"
        }
    ],
    "sg:phone":"+1 507 498 5888",
    "sg:postcode":"55974",
    "sg:province":"MN",
    "sg:tags":[
        "electrical",
        "contractor"
    ],
    "wof:name":"Viking Electric",
    "wof:placetype":"venue"
},
  "geometry": {"coordinates":[-91.661012,43.610625],"type":"Point"}
}