{
  "type": "Feature",
  "properties": {
    "iso:country":"US",
    "sg:address":"315 1st St",
    "sg:city":"Lyle",
    "sg:classifiers":[
        {
            "category":"Arts & Performance",
            "subcategory":"Art Gallery",
            "type":"Entertainment"
        },
        {
            "category":"Farming",
            "subcategory":"Fish & Marine Products",
            "type":"Manufacturing & Wholesale Goods"
        },
        {
            "category":"Retail",
            "subcategory":"Repair Shop",
            "type":"Services"
        },
        {
            "category":"Shopping",
            "subcategory":"Crafts & Fabrics",
            "type":"Retail Goods"
        }
    ],
    "sg:phone":"+1 507 325 9900",
    "sg:postcode":"55953",
    "sg:province":"MN",
    "sg:tags":[
        "picture",
        "galleries",
        "consultant",
        "frame",
        "instruction",
        "restoration",
        "framing"
    ],
    "wof:name":"Fastframe",
    "wof:placetype":"venue"
},
  "geometry": {"coordinates":[-92.944552,43.503638],"type":"Point"}
}