{
  "type": "Feature",
  "properties": {
    "iso:country":"US",
    "sg:address":"7250 York Ave S",
    "sg:city":"Minneapolis",
    "sg:classifiers":[
        {
            "category":"Personal",
            "subcategory":"Beauty Salon",
            "type":"Services"
        }
    ],
    "sg:phone":"+1 612 825 0189",
    "sg:postcode":"55435",
    "sg:province":"MN",
    "wof:name":"All About Hair",
    "wof:placetype":"venue"
},
  "geometry": {"coordinates":[-93.32143499999999,44.871627],"type":"Point"}
}