{
  "type": "Feature",
  "properties": {
    "addr:full":"5640 Bryant Ave S Minneapolis MN 55419",
    "addr:housenumber":"5640",
    "addr:postcode":"55419",
    "addr:street":"Bryant Ave S",
    "iso:country":"US",
    "sg:address":"5640 Bryant Ave S",
    "sg:city":"Minneapolis",
    "sg:classifiers":[
        {
            "category":"Retail",
            "subcategory":"Animal Services",
            "type":"Services"
        }
    ],
    "sg:phone":"+1 612 822 7389",
    "sg:postcode":"55419",
    "sg:province":"MN",
    "sg:tags":[
        "pet",
        "exercising",
        "sitting"
    ],
    "wof:name":"Tails Of Two Cities",
    "wof:placetype":"venue"
},
  "geometry": {"coordinates":[-93.29084,44.900319],"type":"Point"}
}