{
  "type": "Feature",
  "properties": {
    "iso:country":"US",
    "sg:address":"3467 Gunston Ln",
    "sg:city":"Saint Paul",
    "sg:classifiers":[
        {
            "category":"Real Estate",
            "subcategory":"Real Estate Operator",
            "type":"Services"
        }
    ],
    "sg:phone":"+1 651 735 4434",
    "sg:postcode":"55129",
    "sg:province":"MN",
    "sg:tags":[
        "building",
        "nonresidential"
    ],
    "wof:name":"Frosch Vacation Properties LLC",
    "wof:placetype":"venue"
},
  "geometry": {"coordinates":[-92.894648,44.899181],"type":"Point"}
}