{
  "type": "Feature",
  "properties": {
    "iso:country":"US",
    "sg:address":"115 Main St",
    "sg:city":"Elrosa",
    "sg:classifiers":[
        {
            "category":"Restaurant",
            "type":"Food & Drink"
        }
    ],
    "sg:phone":"+1 320 697 0010",
    "sg:postcode":"56325",
    "sg:province":"MN",
    "wof:name":"Main Street Bar & Grill",
    "wof:placetype":"venue"
},
  "geometry": {"coordinates":[-94.948414,45.563737],"type":"Point"}
}