{
  "type": "Feature",
  "properties": {
    "addr:full":"310 Railway St N Dundas MN 55019",
    "addr:housenumber":"310",
    "addr:postcode":"55019",
    "addr:street":"Railway St N",
    "iso:country":"US",
    "sg:address":"310 Railway St N",
    "sg:city":"Dundas",
    "sg:classifiers":[
        {
            "category":"Retail",
            "subcategory":"Auto Repair",
            "type":"Services"
        }
    ],
    "sg:phone":"+1 507 650 0517",
    "sg:postcode":"55019",
    "sg:province":"MN",
    "sg:tags":[
        "body",
        "automobile",
        "painting"
    ],
    "wof:name":"Shop",
    "wof:placetype":"venue"
},
  "geometry": {"coordinates":[-93.205935,44.431783],"type":"Point"}
}