{
  "type": "Feature",
  "properties": {
    "iso:country":"US",
    "sg:address":"3220 124th Ave NW",
    "sg:city":"Minneapolis",
    "sg:classifiers":[
        {
            "category":"Restaurant",
            "type":"Food & Drink"
        }
    ],
    "sg:phone":"+1 763 422 6742",
    "sg:postcode":"55433",
    "sg:province":"MN",
    "sg:website":"www.kfc.com",
    "wof:name":"Kentucky Fried Chicken",
    "wof:placetype":"venue"
},
  "geometry": {"coordinates":[-93.345901,45.196201],"type":"Point"}
}