{
  "type": "Feature",
  "properties": {
    "iso:country":"US",
    "sg:address":"12889 Crooked Lake Blvd NW",
    "sg:city":"Coon Rapids",
    "sg:classifiers":[
        {
            "category":"Retail",
            "subcategory":"Repair Shop",
            "type":"Services"
        }
    ],
    "sg:phone":"+1 763 757 7620",
    "sg:postcode":"55448",
    "sg:province":"MN",
    "sg:tags":[
        "taxidermist"
    ],
    "wof:name":"North Country Taxidermy",
    "wof:placetype":"venue"
},
  "geometry": {"coordinates":[-93.33922099999999,45.204676],"type":"Point"}
}