{
  "type": "Feature",
  "properties": {
    "iso:country":"US",
    "sg:address":"11000 Hwy 10 NW",
    "sg:city":"Rice",
    "sg:classifiers":[
        {
            "category":"Freight",
            "type":"Transportation"
        }
    ],
    "sg:phone":"+1 320 393 4835",
    "sg:postcode":"56367",
    "sg:province":"MN",
    "sg:tags":[
        "operator",
        "trucking"
    ],
    "wof:name":"R W Stanton Jr Trucking",
    "wof:placetype":"venue"
},
  "geometry": {"coordinates":[-94.189842,45.720179],"type":"Point"}
}