{
  "type": "Feature",
  "properties": {
    "addr:full":"18077 Murphy Lake Blvd Prior Lake MN 55372",
    "addr:housenumber":"18077",
    "addr:postcode":"55372",
    "addr:street":"Murphy Lake Blvd",
    "iso:country":"US",
    "sg:address":"18077 Murphy Lake Blvd",
    "sg:city":"Prior Lake",
    "sg:classifiers":[
        {
            "category":"Home & Garden",
            "subcategory":"Building Materials",
            "type":"Retail Goods"
        }
    ],
    "sg:phone":"+1 952 447 3667",
    "sg:postcode":"55372",
    "sg:province":"MN",
    "wof:name":"Midwest Building Product Sales",
    "wof:placetype":"venue"
},
  "geometry": {"coordinates":[-93.367216,44.688341],"type":"Point"}
}