{
  "type": "Feature",
  "properties": {
    "iso:country":"US",
    "sg:address":"431 Lark Ave",
    "sg:city":"Saint Paul",
    "sg:classifiers":[
        {
            "category":"Building & Trades",
            "subcategory":"Construction",
            "type":"Services"
        }
    ],
    "sg:phone":"+1 651 772 6854",
    "sg:postcode":"55117",
    "sg:province":"MN",
    "sg:tags":[
        "home",
        "general",
        "remodeling",
        "contractor"
    ],
    "wof:name":"Asplund Squires Construction",
    "wof:placetype":"venue"
},
  "geometry": {"coordinates":[-93.083923,45.009139],"type":"Point"}
}