{
  "type": "Feature",
  "properties": {
    "addr:full":"4230 40th St SW Rochester MN 55902",
    "addr:housenumber":"4230",
    "addr:postcode":"55902",
    "addr:street":"40Th St Sw",
    "iso:country":"US",
    "sg:address":"4230 40th St SW",
    "sg:city":"Rochester",
    "sg:classifiers":[
        {
            "category":"Farming",
            "subcategory":"Farm",
            "type":"Manufacturing & Wholesale Goods"
        }
    ],
    "sg:phone":"+1 507 282 5937",
    "sg:postcode":"55902",
    "sg:province":"MN",
    "sg:tags":[
        "crop",
        "general"
    ],
    "wof:name":"James Dee Farm",
    "wof:placetype":"venue"
},
  "geometry": {"coordinates":[-92.525961,43.963936],"type":"Point"}
}