{
  "type": "Feature",
  "properties": {
    "addr:full":"923 4th St W Wabasha MN 55981",
    "addr:housenumber":"923",
    "addr:postcode":"55981",
    "addr:street":"4Th St W",
    "iso:country":"US",
    "sg:address":"923 4th St W",
    "sg:city":"Wabasha",
    "sg:classifiers":[
        {
            "category":"Retail",
            "subcategory":"Portrait Studio",
            "type":"Services"
        }
    ],
    "sg:phone":"+1 651 565 3426",
    "sg:postcode":"55981",
    "sg:province":"MN",
    "sg:tags":[
        "photo"
    ],
    "wof:name":"Rosendale Phil Photography",
    "wof:placetype":"venue"
},
  "geometry": {"coordinates":[-92.044546,44.385462],"type":"Point"}
}