{
  "type": "Feature",
  "properties": {
    "addr:full":"1390 University Ave W St Paul MN 55104",
    "addr:housenumber":"1390",
    "addr:postcode":"55104",
    "addr:street":"University Ave W",
    "iso:country":"US",
    "sg:address":"1390 University Ave W",
    "sg:city":"St Paul",
    "sg:classifiers":[
        {
            "category":"Shopping",
            "subcategory":"Books",
            "type":"Retail Goods"
        }
    ],
    "sg:phone":"+1 651 641 0026",
    "sg:postcode":"55104",
    "sg:province":"MN",
    "sg:tags":[
        "dealer"
    ],
    "sg:website":"www.bordersstores.com",
    "wof:name":"Borders Books & Music",
    "wof:placetype":"venue"
},
  "geometry": {"coordinates":[-93.15781699999999,44.955627],"type":"Point"}
}