{
  "type": "Feature",
  "properties": {
    "addr:full":"1295 Promenade Pl St Paul MN 55121",
    "addr:housenumber":"1295",
    "addr:postcode":"55121",
    "addr:street":"Promenade Pl",
    "iso:country":"US",
    "sg:address":"1295 Promenade Pl",
    "sg:city":"St Paul",
    "sg:classifiers":[
        {
            "category":"Retail",
            "subcategory":"Veterinary Services",
            "type":"Services"
        }
    ],
    "sg:phone":"+1 651 688 3001",
    "sg:postcode":"55121",
    "sg:province":"MN",
    "sg:tags":[
        "veterinarian"
    ],
    "wof:name":"Banfield The Pet Hospital",
    "wof:placetype":"venue"
},
  "geometry": {"coordinates":[-93.153105,44.835777],"type":"Point"}
}