{
  "type": "Feature",
  "properties": {
    "iso:country":"US",
    "sg:address":"20487 470th Ave NW",
    "sg:city":"Oslo",
    "sg:classifiers":[
        {
            "category":"Home & Garden",
            "subcategory":"Hardware",
            "type":"Retail Goods"
        }
    ],
    "sg:phone":"+1 218 965 4660",
    "sg:postcode":"56744",
    "sg:province":"MN",
    "sg:tags":[
        "measuring",
        "device"
    ],
    "wof:name":"Beamco, Inc.",
    "wof:placetype":"venue"
},
  "geometry": {"coordinates":[-97.063807,48.175057],"type":"Point"}
}