{
  "type": "Feature",
  "properties": {
    "addr:full":"14311 Co Rd 17 Lamberton MN 56152",
    "addr:housenumber":"14311;17",
    "addr:postcode":"56152",
    "addr:street":"Co Rd",
    "iso:country":"US",
    "sg:address":"14311 Co Rd 17",
    "sg:city":"Lamberton",
    "sg:phone":"+1 507 648 3335",
    "sg:postcode":"56152",
    "sg:province":"MN",
    "sg:tags":[
        "farm",
        "corn",
        "soybean"
    ],
    "wof:name":"Stuart Steffen",
    "wof:placetype":"venue"
},
  "geometry": {"coordinates":[-95.19852899999999,44.259638],"type":"Point"}
}