{
  "type": "Feature",
  "properties": {
    "addr:full":"1207 Jean Marie St Cloquet MN 55720",
    "addr:housenumber":"1207",
    "addr:postcode":"55720",
    "addr:street":"Jean Marie St",
    "iso:country":"US",
    "sg:address":"1207 Jean Marie St",
    "sg:city":"Cloquet",
    "sg:classifiers":[
        {
            "category":"Professional",
            "subcategory":"Business Services",
            "type":"Services"
        }
    ],
    "sg:phone":"+1 218 879 6025",
    "sg:postcode":"55720",
    "sg:province":"MN",
    "wof:name":"H & R Block",
    "wof:placetype":"venue"
},
  "geometry": {"coordinates":[-92.447388,46.735056],"type":"Point"}
}