{
  "type": "Feature",
  "properties": {
    "addr:full":"27384 US Hwy 61 Red Wing MN 55066",
    "addr:housenumber":"27384",
    "addr:postcode":"55066",
    "addr:street":"Us Hwy 61",
    "iso:country":"US",
    "sg:address":"27384 US Hwy 61",
    "sg:city":"Red Wing",
    "sg:classifiers":[
        {
            "category":"Building & Trades",
            "subcategory":"Construction",
            "type":"Services"
        }
    ],
    "sg:phone":"+1 651 388 3513",
    "sg:postcode":"55066",
    "sg:province":"MN",
    "sg:tags":[
        "acoustical",
        "material"
    ],
    "wof:name":"USG Interiors Inc",
    "wof:placetype":"venue"
},
  "geometry": {"coordinates":[-92.48596499999999,44.557679],"type":"Point"}
}