{
  "type": "Feature",
  "properties": {
    "addr:full":"1275 Rolling Oaks Ln NW Hutchinson MN 55350",
    "addr:housenumber":"1275",
    "addr:postcode":"55350",
    "addr:street":"Rolling Oaks Ln Nw",
    "iso:country":"US",
    "sg:address":"1275 Rolling Oaks Ln NW",
    "sg:city":"Hutchinson",
    "sg:classifiers":[
        {
            "category":"Building & Trades",
            "subcategory":"Construction",
            "type":"Services"
        }
    ],
    "sg:phone":"+1 320 296 1053",
    "sg:postcode":"55350",
    "sg:province":"MN",
    "sg:tags":[
        "carpentry",
        "contractor"
    ],
    "wof:name":"My Trimmings",
    "wof:placetype":"venue"
},
  "geometry": {"coordinates":[-94.396227,44.895127],"type":"Point"}
}