{
  "type": "Feature",
  "properties": {
    "iso:country":"US",
    "sg:address":"385 E River Rd",
    "sg:city":"Minneapolis",
    "sg:classifiers":[
        {
            "category":"Education",
            "subcategory":"College",
            "type":"Public Place"
        }
    ],
    "sg:phone":"+1 612 626 7007",
    "sg:postcode":"55455",
    "sg:province":"MN",
    "sg:tags":[
        "health",
        "center"
    ],
    "wof:name":"Center For Mgntic Rsonance RES",
    "wof:placetype":"venue"
},
  "geometry": {"coordinates":[-93.230915,44.970533],"type":"Point"}
}