{
  "type": "Feature",
  "properties": {
    "iso:country":"US",
    "sg:address":"1595 Selby Ave",
    "sg:city":"St Paul",
    "sg:classifiers":[
        {
            "category":"Professional",
            "subcategory":"Research",
            "type":"Services"
        }
    ],
    "sg:phone":"+1 651 641 0882",
    "sg:postcode":"55104",
    "sg:province":"MN",
    "sg:tags":[
        "nonphysical",
        "commercial",
        "market",
        "analysis"
    ],
    "sg:website":"www.eworksinc.com",
    "wof:name":"Entertainment Works",
    "wof:placetype":"venue"
},
  "geometry": {"coordinates":[-93.16865900000001,44.946635],"type":"Point"}
}