{
  "type": "Feature",
  "properties": {
    "addr:full":"8009 34th Ave S Ste 1250 Minneapolis MN 55425",
    "addr:housenumber":"8009",
    "addr:postcode":"55425",
    "addr:street":"34Th Ave S Ste 1250",
    "iso:country":"US",
    "sg:address":"8009 34th Ave S Ste 1250",
    "sg:city":"Minneapolis",
    "sg:classifiers":[
        {
            "category":"Organizations",
            "subcategory":"Labor Organization",
            "type":"Services"
        }
    ],
    "sg:phone":"+1 952 854 0093",
    "sg:postcode":"55425",
    "sg:province":"MN",
    "sg:website":"http://www.apwu.org",
    "wof:name":"American Postal Workers Union",
    "wof:placetype":"venue"
},
  "geometry": {"coordinates":[-93.222977,44.858481],"type":"Point"}
}