{
  "type": "Feature",
  "properties": {
    "iso:country":"US",
    "sg:address":"4325 Wild Rice Dr NE",
    "sg:city":"Wyoming",
    "sg:classifiers":[
        {
            "category":"Home & Garden",
            "subcategory":"Furniture",
            "type":"Retail Goods"
        }
    ],
    "sg:phone":"+1 763 434 0189",
    "sg:postcode":"55092",
    "sg:province":"MN",
    "sg:tags":[
        "cabinet"
    ],
    "wof:name":"S C Cabinets",
    "wof:placetype":"venue"
},
  "geometry": {"coordinates":[-93.16259599999999,45.337545],"type":"Point"}
}