{
  "type": "Feature",
  "properties": {
    "addr:full":"5650 147th St E Northfield MN 55057",
    "addr:housenumber":"5650",
    "addr:postcode":"55057",
    "addr:street":"147Th St E",
    "iso:country":"US",
    "sg:address":"5650 147th St E",
    "sg:city":"Northfield",
    "sg:classifiers":[
        {
            "category":"Retail",
            "subcategory":"Repair Shop",
            "type":"Services"
        }
    ],
    "sg:phone":"+1 507 645 7140",
    "sg:postcode":"55057",
    "sg:province":"MN",
    "wof:name":"G Mas Cleaning",
    "wof:placetype":"venue"
},
  "geometry": {"coordinates":[-93.19637299999999,44.374068],"type":"Point"}
}