{
  "type": "Feature",
  "properties": {
    "iso:country":"US",
    "sg:address":"754 6th Ave NW",
    "sg:city":"Saint Paul",
    "sg:classifiers":[
        {
            "category":"Building & Trades",
            "subcategory":"Electrical",
            "type":"Services"
        }
    ],
    "sg:phone":"+1 651 638 3503",
    "sg:postcode":"55112",
    "sg:province":"MN",
    "sg:tags":[
        "electrical",
        "contractor"
    ],
    "wof:name":"Hedkey Electric LLC",
    "wof:placetype":"venue"
},
  "geometry": {"coordinates":[-93.19438599999999,45.0618],"type":"Point"}
}