{
  "type": "Feature",
  "properties": {
    "addr:full":"222 Main Ave S Park Rapids MN 56470",
    "addr:housenumber":"222",
    "addr:postcode":"56470",
    "addr:street":"Main Ave S Park",
    "iso:country":"US",
    "sg:address":"222 Main Ave S",
    "sg:city":"Park Rapids",
    "sg:classifiers":[
        {
            "category":"Shopping",
            "type":"Retail Goods"
        }
    ],
    "sg:phone":"+1 218 732 9324",
    "sg:postcode":"56470",
    "sg:province":"MN",
    "sg:tags":[
        "cards",
        "sport",
        "baseball",
        "memorabilia"
    ],
    "wof:name":"Baseballnut Card Shop",
    "wof:placetype":"venue"
},
  "geometry": {"coordinates":[-95.059934,46.920833],"type":"Point"}
}