{
  "type": "Feature",
  "properties": {
    "iso:country":"US",
    "sg:address":"3499 Lexington Ave N",
    "sg:city":"St Paul",
    "sg:classifiers":[
        {
            "category":"Wholesale",
            "subcategory":"Groceries",
            "type":"Manufacturing & Wholesale Goods"
        }
    ],
    "sg:phone":"+1 651 482 8542",
    "sg:postcode":"55126",
    "sg:province":"MN",
    "sg:tags":[
        "extract",
        "flavoring"
    ],
    "wof:name":"Mc Cormick Flavor Div",
    "wof:placetype":"venue"
},
  "geometry": {"coordinates":[-93.14713999999999,45.049822],"type":"Point"}
}