{
  "type": "Feature",
  "properties": {
    "addr:full":"11927 Portland Ave Burnsville MN 55337",
    "addr:housenumber":"11927",
    "addr:postcode":"55337",
    "addr:street":"Portland Ave",
    "iso:country":"US",
    "sg:address":"11927 Portland Ave",
    "sg:city":"Burnsville",
    "sg:classifiers":[
        {
            "category":"Manufacturing",
            "subcategory":"Retail Goods",
            "type":"Manufacturing & Wholesale Goods"
        }
    ],
    "sg:phone":"+1 952 890 3431",
    "sg:postcode":"55337",
    "sg:province":"MN",
    "sg:tags":[
        "glass",
        "product",
        "mfg"
    ],
    "wof:name":"Imagine Design Inc",
    "wof:placetype":"venue"
},
  "geometry": {"coordinates":[-93.26818900000001,44.784585],"type":"Point"}
}