{
  "type": "Feature",
  "properties": {
    "addr:full":"2100 3rd Ave Anoka MN 55303",
    "addr:housenumber":"2100",
    "addr:postcode":"55303",
    "addr:street":"3Rd Ave",
    "iso:country":"US",
    "sg:address":"2100 3rd Ave",
    "sg:city":"Anoka",
    "sg:classifiers":[
        {
            "category":"Government",
            "subcategory":"Office",
            "type":"Public Place"
        }
    ],
    "sg:phone":"+1 763 323 5400",
    "sg:postcode":"55303",
    "sg:province":"MN",
    "sg:tags":[
        "county",
        "taxation"
    ],
    "wof:name":"Anoka County Assessor",
    "wof:placetype":"venue"
},
  "geometry": {"coordinates":[-93.38721099999999,45.199334],"type":"Point"}
}