{
  "type": "Feature",
  "properties": {
    "iso:country":"US",
    "sg:address":"13930 Yukon St NW",
    "sg:city":"Andover",
    "sg:classifiers":[
        {
            "category":"Building & Trades",
            "subcategory":"Cleaning & Sanitation",
            "type":"Services"
        }
    ],
    "sg:phone":"+1 763 767 2351",
    "sg:postcode":"55304",
    "sg:province":"MN",
    "sg:tags":[
        "house"
    ],
    "wof:name":"Kayleen's Personal Touch Clng",
    "wof:placetype":"venue"
},
  "geometry": {"coordinates":[-93.330232,45.226037],"type":"Point"}
}