{
  "type": "Feature",
  "properties": {
    "iso:country":"US",
    "sg:address":"512 Shoreview Park Rd",
    "sg:city":"Shoreview",
    "sg:classifiers":[
        {
            "category":"Manufacturing",
            "subcategory":"Printing",
            "type":"Manufacturing & Wholesale Goods"
        }
    ],
    "sg:phone":"+1 651 482 1720",
    "sg:postcode":"55126",
    "sg:province":"MN",
    "sg:tags":[
        "commercial"
    ],
    "wof:name":"Printing Resources Inc",
    "wof:placetype":"venue"
},
  "geometry": {"coordinates":[-93.122832,45.052523],"type":"Point"}
}