{
  "type": "Feature",
  "properties": {
    "addr:full":"1200 N Park St Fairmont MN 56031",
    "addr:housenumber":"1200",
    "addr:postcode":"56031",
    "addr:street":"N Park St",
    "iso:country":"US",
    "sg:address":"1200 N Park St",
    "sg:city":"Fairmont",
    "sg:classifiers":[
        {
            "category":"Education",
            "subcategory":"School",
            "type":"Public Place"
        }
    ],
    "sg:phone":"+1 507 235 6151",
    "sg:postcode":"56031",
    "sg:province":"MN",
    "sg:website":"www.fairmont.k12.mn.us",
    "wof:name":"Southern Plains Area Learning",
    "wof:placetype":"venue"
},
  "geometry": {"coordinates":[-94.461001,43.665414],"type":"Point"}
}