{
  "type": "Feature",
  "properties": {
    "addr:full":"2105 1st Ave S Minneapolis MN 55404",
    "addr:housenumber":"2105",
    "addr:postcode":"55404",
    "addr:street":"1St Ave S",
    "iso:country":"US",
    "sg:address":"2105 1st Ave S",
    "sg:city":"Minneapolis",
    "sg:classifiers":[
        {
            "category":"Organizations",
            "subcategory":"Non-profit Organization",
            "type":"Services"
        }
    ],
    "sg:phone":"+1 612 870 3461",
    "sg:postcode":"55404",
    "sg:province":"MN",
    "sg:tags":[
        "service/non-profit",
        "community"
    ],
    "sg:website":"www.windustry.org",
    "wof:name":"Windustry",
    "wof:placetype":"venue"
},
  "geometry": {"coordinates":[-93.27631100000001,44.961734],"type":"Point"}
}