{
  "type": "Feature",
  "properties": {
    "iso:country":"US",
    "sg:address":"1128 Maryland Ave E",
    "sg:city":"St Paul",
    "sg:classifiers":[
        {
            "category":"Professional",
            "subcategory":"Computer Services",
            "type":"Services"
        }
    ],
    "sg:phone":"+1 651 842 6955",
    "sg:postcode":"55106",
    "sg:province":"MN",
    "sg:tags":[
        "consultant",
        "designer"
    ],
    "wof:name":"CAT Computers Inc",
    "wof:placetype":"venue"
},
  "geometry": {"coordinates":[-93.050978,44.977467],"type":"Point"}
}