{
  "type": "Feature",
  "properties": {
    "iso:country":"US",
    "sg:address":"118 S Main St",
    "sg:city":"Drayton",
    "sg:classifiers":[
        {
            "category":"Insurance",
            "subcategory":"Insurance Agent",
            "type":"Services"
        }
    ],
    "sg:phone":"+1 701 454 3437",
    "sg:postcode":"58225",
    "sg:province":"MN",
    "wof:name":"Northland Insurance Inc",
    "wof:placetype":"venue"
},
  "geometry": {"coordinates":[-97.177751,48.561495],"type":"Point"}
}