{
  "type": "Feature",
  "properties": {
    "iso:country":"US",
    "sg:address":"4201 Cedar Ave S",
    "sg:city":"Minneapolis",
    "sg:classifiers":[
        {
            "category":"Real Estate",
            "subcategory":"Architect",
            "type":"Services"
        }
    ],
    "sg:phone":"+1 612 904 1332",
    "sg:postcode":"55407",
    "sg:province":"MN",
    "sg:tags":[
        "architectural"
    ],
    "wof:name":"Hagen Christenson & McIlw",
    "wof:placetype":"venue"
},
  "geometry": {"coordinates":[-93.247322,44.925148],"type":"Point"}
}