{
  "type": "Feature",
  "properties": {
    "iso:country":"US",
    "sg:address":"1535 4th St NE",
    "sg:city":"Minneapolis",
    "sg:classifiers":[
        {
            "category":"Building & Trades",
            "subcategory":"Construction",
            "type":"Services"
        }
    ],
    "sg:phone":"+1 612 789 9392",
    "sg:postcode":"55413",
    "sg:province":"MN",
    "sg:tags":[
        "handyman"
    ],
    "wof:name":"Metro Home Maintenance",
    "wof:placetype":"venue"
},
  "geometry": {"coordinates":[-93.261483,45.00381],"type":"Point"}
}