{
  "type": "Feature",
  "properties": {
    "addr:full":"99 Lake Dr E Chanhassen MN 55317",
    "addr:housenumber":"99",
    "addr:postcode":"55317",
    "addr:street":"Lake Dr E",
    "iso:country":"US",
    "sg:address":"99 Lake Dr E",
    "sg:city":"Chanhassen",
    "sg:classifiers":[
        {
            "category":"Professional",
            "subcategory":"Business Services",
            "type":"Services"
        }
    ],
    "sg:phone":"+1 952 949 2866",
    "sg:postcode":"55317",
    "sg:province":"MN",
    "sg:tags":[
        "furniture"
    ],
    "wof:name":"Financial Interiors",
    "wof:placetype":"venue"
},
  "geometry": {"coordinates":[-93.523004,44.860432],"type":"Point"}
}