{
  "type": "Feature",
  "properties": {
    "iso:country":"US",
    "sg:address":"7716 64th Ave N",
    "sg:city":"Minneapolis",
    "sg:classifiers":[
        {
            "category":"Organizations",
            "subcategory":"Religious Organization",
            "type":"Services"
        }
    ],
    "sg:phone":"+1 763 531 2175",
    "sg:postcode":"55428",
    "sg:province":"MN",
    "wof:name":"Red Rock Camp Fellowship",
    "wof:placetype":"venue"
},
  "geometry": {"coordinates":[-93.378635,45.07151],"type":"Point"}
}