{
  "type": "Feature",
  "properties": {
    "addr:full":"2121 W 52nd St Minneapolis MN 55419",
    "addr:housenumber":"2121",
    "addr:postcode":"55419",
    "addr:street":"W 52Nd St",
    "iso:country":"US",
    "sg:address":"2121 W 52nd St",
    "sg:city":"Minneapolis",
    "sg:classifiers":[
        {
            "category":"Professional",
            "type":"Services"
        }
    ],
    "sg:phone":"+1 612 929 7378",
    "sg:postcode":"55419",
    "sg:province":"MN",
    "wof:name":"Thomas J Laqua Ltd",
    "wof:placetype":"venue"
},
  "geometry": {"coordinates":[-93.307211,44.90866],"type":"Point"}
}