{
  "type": "Feature",
  "properties": {
    "addr:full":"410 W Eagle Lake Dr Osseo MN 55369",
    "addr:housenumber":"410",
    "addr:postcode":"55369",
    "addr:street":"W Eagle Lake Dr",
    "iso:country":"US",
    "sg:address":"410 W Eagle Lake Dr",
    "sg:city":"Osseo",
    "sg:classifiers":[
        {
            "category":"Banks & Credit Unions",
            "subcategory":"Investment Brokerage",
            "type":"Services"
        }
    ],
    "sg:phone":"+1 763 420 0062",
    "sg:postcode":"55369",
    "sg:province":"MN",
    "sg:tags":[
        "advisory",
        "financial"
    ],
    "wof:name":"AKA Financial",
    "wof:placetype":"venue"
},
  "geometry": {"coordinates":[-93.424611,45.078313],"type":"Point"}
}