{
  "type": "Feature",
  "properties": {
    "iso:country":"US",
    "sg:address":"357 4th St",
    "sg:city":"Audubon",
    "sg:classifiers":[
        {
            "category":"Professional",
            "subcategory":"Employment Agencies",
            "type":"Services"
        }
    ],
    "sg:phone":"+1 218 439 6363",
    "sg:postcode":"56511",
    "sg:province":"MN",
    "sg:tags":[
        "leasing"
    ],
    "sg:website":"www.tlccompanies.com",
    "wof:name":"TLC Co",
    "wof:placetype":"venue"
},
  "geometry": {"coordinates":[-95.98180600000001,46.86171],"type":"Point"}
}