{
  "type": "Feature",
  "properties": {
    "addr:full":"4974 Interlachen Dr NE Alexandria MN 56308",
    "addr:housenumber":"4974",
    "addr:postcode":"56308",
    "addr:street":"Interlachen Dr Ne",
    "iso:country":"US",
    "sg:address":"4974 Interlachen Dr NE",
    "sg:city":"Alexandria",
    "sg:classifiers":[
        {
            "category":"Travel",
            "subcategory":"Hotels & Motels",
            "type":"Entertainment"
        }
    ],
    "sg:phone":"+1 320 846 7400",
    "sg:postcode":"56308",
    "sg:province":"MN",
    "sg:tags":[
        "breakfast",
        "accommodation",
        "bed"
    ],
    "wof:name":"Carrington House B & B",
    "wof:placetype":"venue"
},
  "geometry": {"coordinates":[-95.356126,45.945962],"type":"Point"}
}