{
  "type": "Feature",
  "properties": {
    "iso:country":"US",
    "sg:address":"15001 450th St",
    "sg:city":"Bowlus",
    "sg:classifiers":[
        {
            "category":"Farming",
            "subcategory":"Farm",
            "type":"Manufacturing & Wholesale Goods"
        }
    ],
    "sg:phone":"+1 320 746 2873",
    "sg:postcode":"56314",
    "sg:province":"MN",
    "sg:tags":[
        "crop",
        "general"
    ],
    "wof:name":"Tom Stodolka Farm",
    "wof:placetype":"venue"
},
  "geometry": {"coordinates":[-94.429801,45.775242],"type":"Point"}
}