{
  "type": "Feature",
  "properties": {
    "addr:full":"19411 Whitetail Ln Belle Plaine MN 56011",
    "addr:housenumber":"19411",
    "addr:postcode":"56011",
    "addr:street":"Whitetail Ln Belle Plaine",
    "iso:country":"US",
    "sg:address":"19411 Whitetail Ln",
    "sg:city":"Belle Plaine",
    "sg:classifiers":[
        {
            "category":"Professional",
            "subcategory":"Management & Consulting",
            "type":"Services"
        }
    ],
    "sg:phone":"+1 952 873 6005",
    "sg:postcode":"56011",
    "sg:province":"MN",
    "wof:name":"Dobbleman & Assoc Inc",
    "wof:placetype":"venue"
},
  "geometry": {"coordinates":[-93.778638,44.652769],"type":"Point"}
}