{
  "type": "Feature",
  "properties": {
    "addr:full":"710 13th St N Breckenridge MN 56520",
    "addr:housenumber":"710",
    "addr:postcode":"56520",
    "addr:street":"13Th St N",
    "iso:country":"US",
    "sg:address":"710 13th St N",
    "sg:city":"Breckenridge",
    "sg:classifiers":[
        {
            "category":"Education",
            "subcategory":"School",
            "type":"Public Place"
        }
    ],
    "sg:phone":"+1 218 643 2694",
    "sg:postcode":"56520",
    "sg:province":"MN",
    "sg:tags":[
        "high"
    ],
    "sg:website":"http://www.breckenridgemn.net",
    "wof:name":"Breckenridge Senior High School",
    "wof:placetype":"venue"
},
  "geometry": {"coordinates":[-96.57653999999999,46.270712],"type":"Point"}
}