{
  "type": "Feature",
  "properties": {
    "iso:country":"US",
    "sg:address":"1650 College Way",
    "sg:city":"Fergus Falls",
    "sg:classifiers":[
        {
            "category":"Building & Trades",
            "subcategory":"Cleaning & Sanitation",
            "type":"Services"
        }
    ],
    "sg:phone":"+1 218 739 2127",
    "sg:postcode":"56537",
    "sg:province":"MN",
    "wof:name":"Service Master Co",
    "wof:placetype":"venue"
},
  "geometry": {"coordinates":[-96.10061899999999,46.287712],"type":"Point"}
}