{
  "type": "Feature",
  "properties": {
    "iso:country":"US",
    "sg:address":"12 S 6th St Ste 1137",
    "sg:city":"Minneapolis",
    "sg:classifiers":[
        {
            "category":"Professional",
            "subcategory":"Management & Consulting",
            "type":"Services"
        }
    ],
    "sg:phone":"+1 612 343 8188",
    "sg:postcode":"55402",
    "sg:province":"MN",
    "sg:tags":[
        "consultant"
    ],
    "wof:name":"Llsresources",
    "wof:placetype":"venue"
},
  "geometry": {"coordinates":[-93.27338899999999,44.978655],"type":"Point"}
}