{
  "type": "Feature",
  "properties": {
    "addr:full":"402 E Howard St Hibbing MN 55746",
    "addr:housenumber":"402",
    "addr:postcode":"55746",
    "addr:street":"E Howard St",
    "iso:country":"US",
    "sg:address":"402 E Howard St",
    "sg:city":"Hibbing",
    "sg:classifiers":[
        {
            "category":"Professional",
            "subcategory":"Lawyer & Legal Services",
            "type":"Services"
        }
    ],
    "sg:phone":"+1 218 262 0064",
    "sg:postcode":"55746",
    "sg:province":"MN",
    "sg:tags":[
        "attorney"
    ],
    "wof:name":"James Perunovich Law Offices",
    "wof:placetype":"venue"
},
  "geometry": {"coordinates":[-92.937871,47.427401],"type":"Point"}
}