{
  "type": "Feature",
  "properties": {
    "addr:full":"Lowry At Irving Ave Minneapolis MN 55401",
    "addr:postcode":"55401",
    "addr:street":"Ave",
    "iso:country":"US",
    "sg:address":"Lowry At Irving Ave",
    "sg:city":"Minneapolis",
    "sg:classifiers":[
        {
            "category":"Retail",
            "subcategory":"Funeral Services",
            "type":"Services"
        }
    ],
    "sg:phone":"+1 612 529 9691",
    "sg:postcode":"55401",
    "sg:province":"MN",
    "sg:tags":[
        "cemetery"
    ],
    "sg:website":"www.washburn-mcreavy.com",
    "wof:name":"Washburn-McReavy Funeral Chapels & Cremation Srvcs",
    "wof:placetype":"venue"
},
  "geometry": {"coordinates":[-93.299362,45.013176],"type":"Point"}
}