{
  "type": "Feature",
  "properties": {
    "addr:full":"2850 Metro Dr Minneapolis MN 55425",
    "addr:postcode":"2850;55425",
    "addr:street":"Metro Dr",
    "iso:country":"US",
    "sg:address":"2850 Metro Dr",
    "sg:city":"Minneapolis",
    "sg:classifiers":[
        {
            "category":"Professional",
            "subcategory":"Lawyer & Legal Services",
            "type":"Services"
        }
    ],
    "sg:phone":"+1 952 851 7875",
    "sg:postcode":"55425",
    "sg:province":"MN",
    "wof:name":"Xylan",
    "wof:placetype":"venue"
},
  "geometry": {"coordinates":[-93.229148,44.860199],"type":"Point"}
}