{
  "type": "Feature",
  "properties": {
    "addr:full":"31310 E Round Lake Rd Ponsford MN 56575",
    "addr:housenumber":"31310",
    "addr:postcode":"56575",
    "addr:street":"E Round Lake Rd",
    "iso:country":"US",
    "sg:address":"31310 E Round Lake Rd",
    "sg:city":"Ponsford",
    "sg:classifiers":[
        {
            "category":"Professional",
            "type":"Services"
        }
    ],
    "sg:phone":"+1 218 573 3800",
    "sg:postcode":"56575",
    "sg:province":"MN",
    "sg:tags":[
        "establishment"
    ],
    "wof:name":"Kemp & Kemp",
    "wof:placetype":"venue"
},
  "geometry": {"coordinates":[-95.533517,47.02492],"type":"Point"}
}