{
  "type": "Feature",
  "properties": {
    "addr:full":"408 13th Ave NW Little Falls MN 56345",
    "addr:housenumber":"408",
    "addr:postcode":"56345",
    "addr:street":"13Th Ave Nw",
    "iso:country":"US",
    "sg:address":"408 13th Ave NW",
    "sg:city":"Little Falls",
    "sg:classifiers":[
        {
            "category":"Real Estate",
            "subcategory":"Real Estate Operator",
            "type":"Services"
        }
    ],
    "sg:phone":"+1 320 632 9231",
    "sg:postcode":"56345",
    "sg:province":"MN",
    "sg:tags":[
        "commercial"
    ],
    "wof:name":"Eckblad Gold & Solem Partnr",
    "wof:placetype":"venue"
},
  "geometry": {"coordinates":[-94.37790099999999,45.990286],"type":"Point"}
}