{
  "type": "Feature",
  "properties": {
    "addr:full":"1360 190th St E Jordan MN 55352",
    "addr:housenumber":"1360",
    "addr:postcode":"55352",
    "addr:street":"190Th St E",
    "iso:country":"US",
    "sg:address":"1360 190th St E",
    "sg:city":"Jordan",
    "sg:classifiers":[
        {
            "category":"Farming",
            "subcategory":"Livestock Farm",
            "type":"Manufacturing & Wholesale Goods"
        }
    ],
    "sg:phone":"+1 952 492 2465",
    "sg:postcode":"55352",
    "sg:province":"MN",
    "sg:tags":[
        "equine"
    ],
    "wof:name":"Baggenstoss Milford",
    "wof:placetype":"venue"
},
  "geometry": {"coordinates":[-93.492814,44.674455],"type":"Point"}
}