{
  "type": "Feature",
  "properties": {
    "iso:country":"US",
    "sg:address":"4376 41st St W",
    "sg:city":"Webster",
    "sg:classifiers":[
        {
            "category":"Organizations",
            "subcategory":"Religious Organization",
            "type":"Services"
        }
    ],
    "sg:phone":"+1 952 652 2844",
    "sg:postcode":"55088",
    "sg:province":"MN",
    "sg:tags":[
        "church"
    ],
    "wof:name":"St John's Lutheran Church",
    "wof:placetype":"venue"
},
  "geometry": {"coordinates":[-93.348298,44.528607],"type":"Point"}
}