{
  "type": "Feature",
  "properties": {
    "addr:full":"1215 E 22nd St Minneapolis MN 55404",
    "addr:housenumber":"1215",
    "addr:postcode":"55404",
    "addr:street":"E 22Nd St",
    "iso:country":"US",
    "sg:address":"1215 E 22nd St",
    "sg:city":"Minneapolis",
    "sg:classifiers":[
        {
            "category":"Recreation",
            "type":"Entertainment"
        }
    ],
    "sg:phone":"+1 612 870 1332",
    "sg:postcode":"55404",
    "sg:province":"MN",
    "wof:name":"Fanfare Attractions",
    "wof:placetype":"venue"
},
  "geometry": {"coordinates":[-93.256274,44.96084],"type":"Point"}
}