{
  "type": "Feature",
  "properties": {
    "iso:country":"US",
    "sg:address":"5747 W Broadway Ave",
    "sg:city":"Minneapolis",
    "sg:classifiers":[
        {
            "category":"Professional",
            "subcategory":"Management & Consulting",
            "type":"Services"
        }
    ],
    "sg:phone":"+1 763 535 7925",
    "sg:postcode":"55428",
    "sg:province":"MN",
    "wof:name":"Denti Care",
    "wof:placetype":"venue"
},
  "geometry": {"coordinates":[-93.368516,45.057279],"type":"Point"}
}