{
  "type": "Feature",
  "properties": {
    "addr:full":"1100 7th St W St Paul MN 55102",
    "addr:housenumber":"1100",
    "addr:postcode":"55102",
    "addr:street":"7Th St W",
    "iso:country":"US",
    "sg:address":"1100 7th St W",
    "sg:city":"St Paul",
    "sg:classifiers":[
        {
            "category":"Professional",
            "type":"Services"
        },
        {
            "category":"Shopping",
            "subcategory":"Computers & Home Electronics",
            "type":"Retail Goods"
        }
    ],
    "sg:phone":"+1 651 256 8787",
    "sg:postcode":"55102",
    "sg:province":"MN",
    "sg:tags":[
        "software"
    ],
    "wof:name":"Connextivity",
    "wof:placetype":"venue"
},
  "geometry": {"coordinates":[-93.129802,44.925765],"type":"Point"}
}