{
  "type": "Feature",
  "properties": {
    "iso:country":"US",
    "sg:address":"55 Mounds Ave NW",
    "sg:city":"New Brighton",
    "sg:classifiers":[
        {
            "category":"Manufacturing",
            "subcategory":"Tools & Machinery",
            "type":"Manufacturing & Wholesale Goods"
        }
    ],
    "sg:phone":"+1 651 633 4566",
    "sg:postcode":"55112",
    "sg:province":"MN",
    "sg:tags":[
        "shop",
        "machine",
        "industrial",
        "accessory",
        "mfg"
    ],
    "sg:website":"www.cheetahprecision.com",
    "wof:name":"Cheetah Precision Inc",
    "wof:placetype":"venue"
},
  "geometry": {"coordinates":[-93.187607,45.083038],"type":"Point"}
}