{
  "type": "Feature",
  "properties": {
    "addr:full":"305 Dayton Ave Saint Paul MN 55102",
    "addr:housenumber":"305",
    "addr:postcode":"55102",
    "addr:street":"Dayton Ave",
    "iso:country":"US",
    "sg:address":"305 Dayton Ave",
    "sg:city":"Saint Paul",
    "sg:classifiers":[
        {
            "category":"Professional",
            "subcategory":"Computer Services",
            "type":"Services"
        }
    ],
    "sg:phone":"+1 952 841 6320",
    "sg:postcode":"55102",
    "sg:province":"MN",
    "sg:tags":[
        "datum"
    ],
    "wof:name":"Crash Networks",
    "wof:placetype":"venue"
},
  "geometry": {"coordinates":[-93.110786,44.947446],"type":"Point"}
}