{
  "type": "Feature",
  "properties": {
    "iso:country":"US",
    "sg:address":"1711 Co Rd B W",
    "sg:city":"Roseville",
    "sg:classifiers":[
        {
            "category":"Professional",
            "type":"Services"
        }
    ],
    "sg:phone":"+1 651 639 8434",
    "sg:postcode":"55113",
    "sg:province":"MN",
    "sg:tags":[
        "establishment"
    ],
    "wof:name":"Welsh Companies",
    "wof:placetype":"venue"
},
  "geometry": {"coordinates":[-93.17232,45.006231],"type":"Point"}
}