{
  "type": "Feature",
  "properties": {
    "addr:full":"5580 Co Rd 6 SW Howard Lake MN 55349",
    "addr:housenumber":"5580",
    "addr:postcode":"55349",
    "addr:street":"Co Rd 6 Sw",
    "iso:country":"US",
    "sg:address":"5580 Co Rd 6 SW",
    "sg:city":"Howard Lake",
    "sg:classifiers":[
        {
            "category":"Building & Trades",
            "subcategory":"Construction",
            "type":"Services"
        }
    ],
    "sg:phone":"+1 320 543 3576",
    "sg:postcode":"55349",
    "sg:province":"MN",
    "sg:tags":[
        "house"
    ],
    "wof:name":"Werner Builders Inc",
    "wof:placetype":"venue"
},
  "geometry": {"coordinates":[-94.07834699999999,45.070953],"type":"Point"}
}