{
  "type": "Feature",
  "properties": {
    "iso:country":"US",
    "sg:address":"5580 109th Ave NE",
    "sg:city":"Spicer",
    "sg:classifiers":[
        {
            "category":"Professional",
            "subcategory":"Management & Consulting",
            "type":"Services"
        }
    ],
    "sg:phone":"+1 320 796 3020",
    "sg:postcode":"56288",
    "sg:province":"MN",
    "sg:tags":[
        "fuel"
    ],
    "wof:name":"North Star Management",
    "wof:placetype":"venue"
},
  "geometry": {"coordinates":[-94.966872,45.229311],"type":"Point"}
}