{
  "type": "Feature",
  "properties": {
    "iso:country":"US",
    "sg:address":"28359 Co Rd 37",
    "sg:city":"Freeport",
    "sg:classifiers":[
        {
            "category":"Farming",
            "subcategory":"Dairy Farm",
            "type":"Manufacturing & Wholesale Goods"
        }
    ],
    "sg:phone":"+1 320 836 2891",
    "sg:postcode":"56331",
    "sg:province":"MN",
    "wof:name":"J Michael",
    "wof:placetype":"venue"
},
  "geometry": {"coordinates":[-94.702546,45.759083],"type":"Point"}
}