{
  "type": "Feature",
  "properties": {
    "addr:full":"5270 W 84th St Minneapolis MN 55437",
    "addr:housenumber":"5270",
    "addr:postcode":"55437",
    "addr:street":"W 84Th St",
    "iso:country":"US",
    "sg:address":"5270 W 84th St",
    "sg:city":"Minneapolis",
    "sg:classifiers":[
        {
            "category":"Insurance",
            "subcategory":"Insurance Agent",
            "type":"Services"
        },
        {
            "category":"Insurance",
            "subcategory":"Hazard Insurance",
            "type":"Services"
        },
        {
            "category":"Insurance",
            "subcategory":"Title Insurance",
            "type":"Services"
        }
    ],
    "sg:phone":"+1 952 835 7500",
    "sg:postcode":"55437",
    "sg:province":"MN",
    "sg:tags":[
        "auto",
        "homeowner"
    ],
    "sg:website":"http://apps.amfam.com/agentlocator/JSTEID?sourceid=yp3",
    "wof:name":"American Family Insurance- Jerry Steidl Agency Inc",
    "wof:placetype":"venue"
},
  "geometry": {"coordinates":[-93.346934,44.851742],"type":"Point"}
}