{
  "type": "Feature",
  "properties": {
    "addr:full":"601 E Main St Luverne MN 56156",
    "addr:housenumber":"601",
    "addr:postcode":"56156",
    "addr:street":"E Main St",
    "iso:country":"US",
    "sg:address":"601 E Main St",
    "sg:city":"Luverne",
    "sg:classifiers":[
        {
            "category":"Restaurant",
            "type":"Food & Drink"
        },
        {
            "category":"Food & Beverages",
            "subcategory":"Groceries & Convenience Stores",
            "type":"Retail Goods"
        }
    ],
    "sg:menulink":"http://www.allmenus.com/mn/luverne/225568-caseys-general-store/menu/",
    "sg:phone":"+1 507 283 4304",
    "sg:postcode":"56156",
    "sg:province":"MN",
    "sg:tags":[
        "american",
        "pizza"
    ],
    "wof:name":"Casey's General Store",
    "wof:placetype":"venue"
},
  "geometry": {"coordinates":[-96.20296,43.654162],"type":"Point"}
}