{
  "type": "Feature",
  "properties": {
    "addr:full":"7920 Zane Ave N Minneapolis MN 55443",
    "addr:housenumber":"7920",
    "addr:postcode":"55443",
    "addr:street":"Zane Ave N",
    "iso:country":"US",
    "sg:address":"7920 Zane Ave N",
    "sg:city":"Minneapolis",
    "sg:classifiers":[
        {
            "category":"Real Estate",
            "subcategory":"Real Estate Operator",
            "type":"Services"
        }
    ],
    "sg:phone":"+1 763 561 9170",
    "sg:postcode":"55443",
    "sg:province":"MN",
    "sg:tags":[
        "building",
        "apartment"
    ],
    "wof:name":"Point of America Office",
    "wof:placetype":"venue"
},
  "geometry": {"coordinates":[-93.356398,45.099491],"type":"Point"}
}