{
  "type": "Feature",
  "properties": {
    "addr:full":"100 1st St Fulda MN 56131",
    "addr:housenumber":"100",
    "addr:postcode":"56131",
    "addr:street":"1St St",
    "iso:country":"US",
    "sg:address":"100 1st St",
    "sg:city":"Fulda",
    "sg:phone":"+1 507 468 2285",
    "sg:postcode":"56131",
    "sg:province":"MN",
    "sg:tags":[
        "farm",
        "corn",
        "soybean"
    ],
    "wof:name":"Wayne Paplow",
    "wof:placetype":"venue"
},
  "geometry": {"coordinates":[-95.46553,43.847881],"type":"Point"}
}