{
  "type": "Feature",
  "properties": {
    "addr:full":"10305 165th Ave NE Oak Park MN 56357",
    "addr:housenumber":"10305",
    "addr:postcode":"56357",
    "addr:street":"165Th Ave Ne;Park",
    "iso:country":"US",
    "sg:address":"10305 165th Ave NE",
    "sg:city":"Oak Park",
    "sg:classifiers":[
        {
            "category":"Freight",
            "type":"Transportation"
        }
    ],
    "sg:phone":"+1 320 267 4761",
    "sg:postcode":"56357",
    "sg:province":"MN",
    "sg:tags":[
        "operator",
        "local",
        "trucking"
    ],
    "wof:name":"Robert Loken Trucking",
    "wof:placetype":"venue"
},
  "geometry": {"coordinates":[-93.823624,45.71685],"type":"Point"}
}