{
  "type": "Feature",
  "properties": {
    "addr:full":"2212 Garfield Ave Minneapolis MN 55405",
    "addr:housenumber":"2212",
    "addr:postcode":"55405",
    "addr:street":"Garfield Ave",
    "iso:country":"US",
    "sg:address":"2212 Garfield Ave",
    "sg:city":"Minneapolis",
    "sg:classifiers":[
        {
            "category":"Real Estate",
            "subcategory":"Real Estate Agent",
            "type":"Services"
        }
    ],
    "sg:phone":"+1 612 874 8434",
    "sg:postcode":"55405",
    "sg:province":"MN",
    "wof:name":"Alex Properties Inc",
    "wof:placetype":"venue"
},
  "geometry": {"coordinates":[-93.286849,44.959227],"type":"Point"}
}