{
  "type": "Feature",
  "properties": {
    "addr:full":"14140 82nd St Mayer MN 55360",
    "addr:housenumber":"14140",
    "addr:postcode":"55360",
    "addr:street":"82Nd St Mayer",
    "iso:country":"US",
    "sg:address":"14140 82nd St",
    "sg:city":"Mayer",
    "sg:classifiers":[
        {
            "category":"Manufacturing",
            "subcategory":"Food",
            "type":"Manufacturing & Wholesale Goods"
        },
        {
            "category":"Farming",
            "subcategory":"Farm",
            "type":"Manufacturing & Wholesale Goods"
        }
    ],
    "sg:phone":"+1 952 657 2492",
    "sg:postcode":"55360",
    "sg:province":"MN",
    "sg:tags":[
        "corn",
        "product"
    ],
    "wof:name":"Milton Vollrath",
    "wof:placetype":"venue"
},
  "geometry": {"coordinates":[-93.883781,44.855492],"type":"Point"}
}