{
  "type": "Feature",
  "properties": {
    "addr:full":"1339 Co Rd D E St Paul MN 55109",
    "addr:housenumber":"1339",
    "addr:postcode":"55109",
    "addr:street":"Co Rd D E",
    "iso:country":"US",
    "sg:address":"1339 Co Rd D E",
    "sg:city":"St Paul",
    "sg:classifiers":[
        {
            "category":"Professional",
            "subcategory":"Lawyer & Legal Services",
            "type":"Services"
        }
    ],
    "sg:phone":"+1 651 486 7475",
    "sg:postcode":"55109",
    "sg:province":"MN",
    "sg:tags":[
        "attorney"
    ],
    "wof:name":"Buckley & Jensen",
    "wof:placetype":"venue"
},
  "geometry": {"coordinates":[-93.046499,45.035843],"type":"Point"}
}