{
  "type": "Feature",
  "properties": {
    "addr:full":"28300 230th Ave Badger MN 56714",
    "addr:housenumber":"28300",
    "addr:postcode":"56714",
    "addr:street":"230Th Ave",
    "iso:country":"US",
    "sg:address":"28300 230th Ave",
    "sg:city":"Badger",
    "sg:phone":"+1 218 528 3229",
    "sg:postcode":"56714",
    "sg:province":"MN",
    "sg:tags":[
        "farm",
        "wheat"
    ],
    "wof:name":"Anderson Alden",
    "wof:placetype":"venue"
},
  "geometry": {"coordinates":[-96.117115,48.81953],"type":"Point"}
}