{
  "type": "Feature",
  "properties": {
    "addr:full":"6301 W Old Shakopee Rd Minneapolis MN 55438",
    "addr:housenumber":"6301",
    "addr:postcode":"55438",
    "addr:street":"W Old Shakopee Rd",
    "iso:country":"US",
    "sg:address":"6301 W Old Shakopee Rd",
    "sg:city":"Minneapolis",
    "sg:classifiers":[
        {
            "category":"Shopping",
            "subcategory":"Department Store",
            "type":"Retail Goods"
        }
    ],
    "sg:phone":"+1 952 885 0001",
    "sg:postcode":"55438",
    "sg:province":"MN",
    "wof:name":"Wal-Mart",
    "wof:placetype":"venue"
},
  "geometry": {"coordinates":[-93.36554599999999,44.807949],"type":"Point"}
}