{
  "type": "Feature",
  "properties": {
    "addr:full":"100 Hillcrest Cir Monticello MN 55362",
    "addr:housenumber":"100",
    "addr:postcode":"55362",
    "addr:street":"Hillcrest Cir",
    "iso:country":"US",
    "sg:address":"100 Hillcrest Cir",
    "sg:city":"Monticello",
    "sg:classifiers":[
        {
            "category":"Building & Trades",
            "subcategory":"Construction",
            "type":"Services"
        }
    ],
    "sg:phone":"+1 763 295 5276",
    "sg:postcode":"55362",
    "sg:province":"MN",
    "sg:tags":[
        "house"
    ],
    "wof:name":"Frank Opay Cnstr & Handyman",
    "wof:placetype":"venue"
},
  "geometry": {"coordinates":[-93.830202,45.320322],"type":"Point"}
}