{
  "type": "Feature",
  "properties": {
    "iso:country":"US",
    "sg:address":"425 7th St NE",
    "sg:city":"Staples",
    "sg:classifiers":[
        {
            "category":"Bars & Pubs",
            "type":"Food & Drink"
        }
    ],
    "sg:menulink":"http://www.allmenus.com/mn/staples/244382-degidios-restaurant--bar/menu/",
    "sg:phone":"+1 651 291 7105",
    "sg:postcode":"56479",
    "sg:province":"MN",
    "sg:tags":[
        "italian"
    ],
    "wof:name":"DeGidio's Restaurant & Bar",
    "wof:placetype":"venue"
},
  "geometry": {"coordinates":[-94.79055200000001,46.357958],"type":"Point"}
}