{
  "type": "Feature",
  "properties": {
    "addr:full":"1117 Orchard Pl Saint Paul MN 55118",
    "addr:housenumber":"1117",
    "addr:postcode":"55118",
    "addr:street":"Orchard Pl",
    "iso:country":"US",
    "sg:address":"1117 Orchard Pl",
    "sg:city":"Saint Paul",
    "sg:classifiers":[
        {
            "category":"Building & Trades",
            "subcategory":"Construction",
            "type":"Services"
        }
    ],
    "sg:phone":"+1 651 452 1859",
    "sg:postcode":"55118",
    "sg:province":"MN",
    "sg:tags":[
        "house"
    ],
    "wof:name":"Sdr Contracting Co Inc",
    "wof:placetype":"venue"
},
  "geometry": {"coordinates":[-93.149478,44.890378],"type":"Point"}
}