{
  "type": "Feature",
  "properties": {
    "addr:full":"1504 E 122nd St Burnsville MN 55337",
    "addr:housenumber":"1504",
    "addr:postcode":"55337",
    "addr:street":"E 122Nd St",
    "iso:country":"US",
    "sg:address":"1504 E 122nd St",
    "sg:city":"Burnsville",
    "sg:classifiers":[
        {
            "category":"Wholesale",
            "subcategory":"Electrical",
            "type":"Manufacturing & Wholesale Goods"
        }
    ],
    "sg:phone":"+1 952 890 1407",
    "sg:postcode":"55337",
    "sg:province":"MN",
    "sg:tags":[
        "repair",
        "parts",
        "electronic"
    ],
    "wof:name":"General Telecommunications",
    "wof:placetype":"venue"
},
  "geometry": {"coordinates":[-93.25498399999999,44.783088],"type":"Point"}
}