{
  "type": "Feature",
  "properties": {
    "addr:full":"2030 Dodd Rd Eagan MN 55120",
    "addr:housenumber":"2030",
    "addr:postcode":"55120",
    "addr:street":"Dodd Rd",
    "iso:country":"US",
    "sg:address":"2030 Dodd Rd",
    "sg:city":"Eagan",
    "sg:classifiers":[
        {
            "category":"Autos & Motor Vehicles",
            "subcategory":"Fuel & Gas Station",
            "type":"Retail Goods"
        }
    ],
    "sg:phone":"+1 651 454 5622",
    "sg:postcode":"55120",
    "sg:province":"MN",
    "sg:tags":[
        "oil"
    ],
    "wof:name":"Mendota Heights Amoco",
    "wof:placetype":"venue"
},
  "geometry": {"coordinates":[-93.126239,44.881875],"type":"Point"}
}