{
  "type": "Feature",
  "properties": {
    "iso:country":"US",
    "sg:address":"25039 E Clark Lake Rd",
    "sg:city":"Nisswa",
    "sg:classifiers":[
        {
            "category":"Health Services",
            "subcategory":"Health Practitioner",
            "type":"Services"
        }
    ],
    "sg:phone":"+1 218 963 2657",
    "sg:postcode":"56468",
    "sg:province":"MN",
    "sg:tags":[
        "psychologist"
    ],
    "wof:name":"Mary Kay Verkennes",
    "wof:placetype":"venue"
},
  "geometry": {"coordinates":[-94.26361799999999,46.517375],"type":"Point"}
}