{
  "type": "Feature",
  "properties": {
    "iso:country":"US",
    "sg:address":"7418 Cahill Rd",
    "sg:city":"Minneapolis",
    "sg:classifiers":[
        {
            "category":"Manufacturing",
            "subcategory":"Tools & Machinery",
            "type":"Manufacturing & Wholesale Goods"
        }
    ],
    "sg:phone":"+1 651 450 0008",
    "sg:postcode":"55439",
    "sg:province":"MN",
    "sg:tags":[
        "manufacture",
        "pediatric"
    ],
    "wof:name":"Denise Daniel Inc",
    "wof:placetype":"venue"
},
  "geometry": {"coordinates":[-93.363411,44.869194],"type":"Point"}
}