{
  "type": "Feature",
  "properties": {
    "iso:country":"US",
    "sg:address":"37676 State Hwy 28",
    "sg:city":"Sauk Centre",
    "sg:classifiers":[
        {
            "category":"Retail",
            "subcategory":"Laundry & Dry Cleaning",
            "type":"Services"
        }
    ],
    "sg:phone":"+1 320 352 2634",
    "sg:postcode":"56378",
    "sg:province":"MN",
    "sg:tags":[
        "cleaners",
        "rug",
        "carpet"
    ],
    "wof:name":"Primus Carpet Cleaning",
    "wof:placetype":"venue"
},
  "geometry": {"coordinates":[-94.89525999999999,45.76482],"type":"Point"}
}