{
  "type": "Feature",
  "properties": {
    "addr:full":"104 Rum River Dr S Princeton MN 55371",
    "addr:housenumber":"104",
    "addr:postcode":"55371",
    "addr:street":"Rum River Dr S",
    "iso:country":"US",
    "sg:address":"104 Rum River Dr S",
    "sg:city":"Princeton",
    "sg:classifiers":[
        {
            "category":"Insurance",
            "subcategory":"Insurance Agent",
            "type":"Services"
        }
    ],
    "sg:phone":"+1 763 389 3650",
    "sg:postcode":"55371",
    "sg:province":"MN",
    "sg:website":"www.princetonins.com",
    "wof:name":"Princeton Insurance",
    "wof:placetype":"venue"
},
  "geometry": {"coordinates":[-93.58005300000001,45.569673],"type":"Point"}
}