{
  "type": "Feature",
  "properties": {
    "iso:country":"US",
    "sg:address":"1140 Sinclair Lewis Ave",
    "sg:city":"Sauk Centre",
    "sg:classifiers":[
        {
            "category":"Banks & Credit Unions",
            "subcategory":"Bank",
            "type":"Services"
        }
    ],
    "sg:phone":"+1 320 351 8326",
    "sg:postcode":"56378",
    "sg:province":"MN",
    "sg:tags":[
        "loan",
        "real estate"
    ],
    "wof:name":"Team Access Mortgage",
    "wof:placetype":"venue"
},
  "geometry": {"coordinates":[-94.96364,45.737073],"type":"Point"}
}