{
  "type": "Feature",
  "properties": {
    "iso:country":"US",
    "sg:address":"5487 270th Ave",
    "sg:city":"Granite Falls",
    "sg:classifiers":[
        {
            "category":"Utilities",
            "subcategory":"Refuse",
            "type":"Services"
        }
    ],
    "sg:phone":"+1 320 564 4246",
    "sg:postcode":"56241",
    "sg:province":"MN",
    "sg:tags":[
        "system"
    ],
    "wof:name":"Minnesota Falls Dem Landfill",
    "wof:placetype":"venue"
},
  "geometry": {"coordinates":[-95.54938799999999,44.785852],"type":"Point"}
}