{
  "type": "Feature",
  "properties": {
    "addr:full":"611 N 6th Ave E Duluth MN 55805",
    "addr:housenumber":"611",
    "addr:postcode":"55805",
    "addr:street":"N 6Th Ave E",
    "iso:country":"US",
    "sg:address":"611 N 6th Ave E",
    "sg:city":"Duluth",
    "sg:classifiers":[
        {
            "category":"Retail",
            "subcategory":"Repair Shop",
            "type":"Services"
        }
    ],
    "sg:phone":"+1 218 727 2288",
    "sg:postcode":"55805",
    "sg:province":"MN",
    "wof:name":"Storey Taxidermy",
    "wof:placetype":"venue"
},
  "geometry": {"coordinates":[-92.09747400000001,46.796695],"type":"Point"}
}