{
  "type": "Feature",
  "properties": {
    "iso:country":"US",
    "sg:address":"632 E 2nd St",
    "sg:city":"Duluth",
    "sg:classifiers":[
        {
            "category":"Organizations",
            "subcategory":"Religious Organization",
            "type":"Services"
        }
    ],
    "sg:phone":"+1 218 722 5957",
    "sg:postcode":"55805",
    "sg:province":"MN",
    "sg:tags":[
        "place",
        "worship",
        "church"
    ],
    "wof:name":"Twelve Holy Apostles Greek Orthodox",
    "wof:placetype":"venue"
},
  "geometry": {"coordinates":[-92.092541,46.794297],"type":"Point"}
}