{
  "type": "Feature",
  "properties": {
    "addr:full":"3260 149th St W Rosemount MN 55068",
    "addr:housenumber":"3260",
    "addr:postcode":"55068",
    "addr:street":"149Th St W",
    "iso:country":"US",
    "sg:address":"3260 149th St W",
    "sg:city":"Rosemount",
    "sg:classifiers":[
        {
            "category":"Wholesale",
            "subcategory":"Durable Goods & Equipment",
            "type":"Manufacturing & Wholesale Goods"
        }
    ],
    "sg:phone":"+1 651 423 9255",
    "sg:postcode":"55068",
    "sg:province":"MN",
    "sg:tags":[
        "fire",
        "extinguisher"
    ],
    "wof:name":"First Response Inc",
    "wof:placetype":"venue"
},
  "geometry": {"coordinates":[-93.131297,44.733287],"type":"Point"}
}