{
  "type": "Feature",
  "properties": {
    "iso:country":"US",
    "sg:address":"2820 2nd St S",
    "sg:city":"St Cloud",
    "sg:classifiers":[
        {
            "category":"Personal",
            "subcategory":"Beauty Salon",
            "type":"Services"
        }
    ],
    "sg:phone":"+1 320 202 8574",
    "sg:postcode":"56301",
    "sg:province":"MN",
    "sg:tags":[
        "shop",
        "manicuring"
    ],
    "wof:name":"Q Nails",
    "wof:placetype":"venue"
},
  "geometry": {"coordinates":[-94.19137000000001,45.548454],"type":"Point"}
}