{
  "type": "Feature",
  "properties": {
    "iso:country":"US",
    "sg:address":"6831 Utica Cir",
    "sg:city":"Chanhassen",
    "sg:classifiers":[
        {
            "category":"Professional",
            "subcategory":"Computer Services",
            "type":"Services"
        }
    ],
    "sg:phone":"+1 952 401 0745",
    "sg:postcode":"55317",
    "sg:province":"MN",
    "sg:tags":[
        "programing",
        "custom"
    ],
    "wof:name":"Fiate Inc",
    "wof:placetype":"venue"
},
  "geometry": {"coordinates":[-93.550619,44.879949],"type":"Point"}
}