{
  "type": "Feature",
  "properties": {
    "iso:country":"US",
    "sg:address":"4424 Logan Ave N",
    "sg:city":"Minneapolis",
    "sg:classifiers":[
        {
            "category":"Arts & Performance",
            "subcategory":"Theater",
            "type":"Entertainment"
        }
    ],
    "sg:phone":"+1 612 756 0200",
    "sg:postcode":"55412",
    "sg:province":"MN",
    "sg:tags":[
        "group"
    ],
    "wof:name":"David Mann Solo Performance",
    "wof:placetype":"venue"
},
  "geometry": {"coordinates":[-93.30401999999999,45.036366],"type":"Point"}
}