{
  "type": "Feature",
  "properties": {
    "addr:full":"900 State Hwy 15 Hutchinson MN 55350",
    "addr:housenumber":"900",
    "addr:postcode":"55350",
    "addr:street":"State Hwy 15",
    "iso:country":"US",
    "sg:address":"900 State Hwy 15",
    "sg:city":"Hutchinson",
    "sg:classifiers":[
        {
            "category":"Health Services",
            "subcategory":"Clinic",
            "type":"Services"
        }
    ],
    "sg:phone":"+1 320 234 7515",
    "sg:postcode":"55350",
    "sg:province":"MN",
    "sg:tags":[
        "job",
        "specialty",
        "outpatient"
    ],
    "wof:name":"West Central Industries Inc",
    "wof:placetype":"venue"
},
  "geometry": {"coordinates":[-94.36839999999999,44.90526],"type":"Point"}
}