{
  "type": "Feature",
  "properties": {
    "iso:country":"US",
    "sg:address":"633 Prosper Dr",
    "sg:city":"Waite Park",
    "sg:classifiers":[
        {
            "category":"Wholesale",
            "subcategory":"Machinery & Supplies",
            "type":"Manufacturing & Wholesale Goods"
        }
    ],
    "sg:phone":"+1 320 252 3265",
    "sg:postcode":"56387",
    "sg:province":"MN",
    "sg:tags":[
        "baker"
    ],
    "sg:website":"www.dawnfood.com",
    "wof:name":"Dawn Food Products Svc Ctr",
    "wof:placetype":"venue"
},
  "geometry": {"coordinates":[-94.233873,45.541286],"type":"Point"}
}