{
  "type": "Feature",
  "properties": {
    "addr:full":"2200 Niagara Ln N Minneapolis MN 55447",
    "addr:housenumber":"2200",
    "addr:postcode":"55447",
    "addr:street":"Niagara Ln N",
    "iso:country":"US",
    "sg:address":"2200 Niagara Ln N",
    "sg:city":"Minneapolis",
    "sg:classifiers":[
        {
            "category":"Wholesale",
            "subcategory":"Office Equipment",
            "type":"Manufacturing & Wholesale Goods"
        },
        {
            "category":"Manufacturing",
            "subcategory":"Tools & Machinery",
            "type":"Manufacturing & Wholesale Goods"
        }
    ],
    "sg:phone":"+1 763 473 1032",
    "sg:postcode":"55447",
    "sg:province":"MN",
    "sg:tags":[
        "packaging",
        "machinery-wholesale",
        "manufacturer"
    ],
    "wof:name":"Packaging Systems Automation, Inc.",
    "wof:placetype":"venue"
},
  "geometry": {"coordinates":[-93.47169700000001,45.001531],"type":"Point"}
}