{
  "type": "Feature",
  "properties": {
    "iso:country":"US",
    "sg:address":"3400 Rosewood Ln N",
    "sg:city":"Minneapolis",
    "sg:classifiers":[
        {
            "category":"Professional",
            "subcategory":"Management & Consulting",
            "type":"Services"
        }
    ],
    "sg:phone":"+1 763 553 9016",
    "sg:postcode":"55441",
    "sg:province":"MN",
    "wof:name":"Yang Yuhong",
    "wof:placetype":"venue"
},
  "geometry": {"coordinates":[-93.44470099999999,45.021767],"type":"Point"}
}