{
  "type": "Feature",
  "properties": {
    "addr:full":"51 Birch Dr Esko MN 55733",
    "addr:housenumber":"51",
    "addr:postcode":"55733",
    "addr:street":"Birch Dr Esko",
    "iso:country":"US",
    "sg:address":"51 Birch Dr",
    "sg:city":"Esko",
    "sg:classifiers":[
        {
            "category":"Shopping",
            "subcategory":"Stationery & Office Supplies",
            "type":"Retail Goods"
        }
    ],
    "sg:phone":"+1 218 879 3916",
    "sg:postcode":"55733",
    "sg:province":"MN",
    "sg:tags":[
        "album",
        "scrapbook"
    ],
    "wof:name":"Creative Memories Consultant",
    "wof:placetype":"venue"
},
  "geometry": {"coordinates":[-92.353869,46.703967],"type":"Point"}
}