{
  "type": "Feature",
  "properties": {
    "iso:country":"US",
    "sg:address":"209 3rd Ave SE",
    "sg:city":"Aitkin",
    "sg:classifiers":[
        {
            "category":"Building & Trades",
            "subcategory":"Construction",
            "type":"Services"
        }
    ],
    "sg:phone":"+1 218 927 6908",
    "sg:postcode":"56431",
    "sg:province":"MN",
    "sg:tags":[
        "hanging",
        "contractor"
    ],
    "wof:name":"Ryan Tim Painting",
    "wof:placetype":"venue"
},
  "geometry": {"coordinates":[-93.702928,46.528095],"type":"Point"}
}