{
  "type": "Feature",
  "properties": {
    "addr:full":"778 Otto Ave St Paul MN 55102",
    "addr:housenumber":"778",
    "addr:postcode":"55102",
    "addr:street":"Otto Ave",
    "iso:country":"US",
    "sg:address":"778 Otto Ave",
    "sg:city":"St Paul",
    "sg:classifiers":[
        {
            "category":"Autos & Motor Vehicles",
            "subcategory":"Boat Sales",
            "type":"Retail Goods"
        }
    ],
    "sg:phone":"+1 651 228 4631",
    "sg:postcode":"55102",
    "sg:province":"MN",
    "sg:tags":[
        "equipment",
        "marine",
        "supply"
    ],
    "wof:name":"Marine Fueling",
    "wof:placetype":"venue"
},
  "geometry": {"coordinates":[-93.132924,44.919578],"type":"Point"}
}