{
  "type": "Feature",
  "properties": {
    "addr:full":"5200 85th Ave N Brooklyn Park MN 55443",
    "addr:housenumber":"5200",
    "addr:postcode":"55443",
    "addr:street":"85Th Ave N",
    "iso:country":"US",
    "sg:address":"5200 85th Ave N",
    "sg:city":"Brooklyn Park",
    "sg:classifiers":[
        {
            "category":"Government",
            "subcategory":"Office",
            "type":"Public Place"
        }
    ],
    "sg:phone":"+1 763 493 8070",
    "sg:postcode":"55443",
    "sg:province":"MN",
    "sg:tags":[
        "city",
        "program"
    ],
    "wof:name":"Brooklyn Park Environmental",
    "wof:placetype":"venue"
},
  "geometry": {"coordinates":[-93.34951599999999,45.108893],"type":"Point"}
}