{
  "type": "Feature",
  "properties": {
    "addr:full":"1702 Paul Bunyan Dr NW Bemidji MN 56601",
    "addr:housenumber":"1702",
    "addr:postcode":"56601",
    "addr:street":"Paul Bunyan Dr Nw",
    "iso:country":"US",
    "sg:address":"1702 Paul Bunyan Dr NW",
    "sg:city":"Bemidji",
    "sg:classifiers":[
        {
            "category":"Retail",
            "subcategory":"Car Wash",
            "type":"Services"
        }
    ],
    "sg:phone":"+1 218 444 9130",
    "sg:postcode":"56601",
    "sg:province":"MN",
    "sg:tags":[
        "carwash"
    ],
    "wof:name":"Fast Lane Car Wash",
    "wof:placetype":"venue"
},
  "geometry": {"coordinates":[-94.906693,47.494455],"type":"Point"}
}