{
  "type": "Feature",
  "properties": {
    "addr:full":"320 E Hennepin Avenue Minneapolis MN 55414",
    "addr:housenumber":"320",
    "addr:postcode":"55414",
    "addr:street":"E Hennepin Avenue",
    "iso:country":"US",
    "sg:address":"320 E Hennepin Avenue",
    "sg:city":"Minneapolis",
    "sg:classifiers":[
        {
            "category":"Shopping",
            "subcategory":"Clothing, Apparel, & Fashions",
            "type":"Retail Goods"
        }
    ],
    "sg:phone":"+1 612 333 3148",
    "sg:postcode":"55414",
    "sg:province":"MN",
    "sg:tags":[
        "clothing",
        "women's"
    ],
    "sg:website":"www.bellereveboutique.com/",
    "wof:name":"Belle Reve Boutique",
    "wof:placetype":"venue"
},
  "geometry": {"coordinates":[-93.255387,44.988345],"type":"Point"}
}