{
  "type": "Feature",
  "properties": {
    "addr:full":"1400 NW 2nd St Grand Rapids MN 55744",
    "addr:housenumber":"1400",
    "addr:postcode":"55744",
    "addr:street":"Nw 2Nd St",
    "iso:country":"US",
    "sg:address":"1400 NW 2nd St",
    "sg:city":"Grand Rapids",
    "sg:classifiers":[
        {
            "category":"Food & Beverages",
            "subcategory":"Liquor & Beverages",
            "type":"Retail Goods"
        }
    ],
    "sg:phone":"+1 218 327 4001",
    "sg:postcode":"55744",
    "sg:province":"MN",
    "sg:tags":[
        "alcoholic"
    ],
    "wof:name":"J & K Liquors Inc",
    "wof:placetype":"venue"
},
  "geometry": {"coordinates":[-93.55118,47.233889],"type":"Point"}
}