{
  "type": "Feature",
  "properties": {
    "addr:full":"44 St Croix Trl S Lakeland MN 55043",
    "addr:housenumber":"44",
    "addr:postcode":"55043",
    "addr:street":"St Croix Trl S Lakeland",
    "iso:country":"US",
    "sg:address":"44 St Croix Trl S",
    "sg:city":"Lakeland",
    "sg:classifiers":[
        {
            "category":"Autos & Motor Vehicles",
            "subcategory":"Boat Sales",
            "type":"Retail Goods"
        }
    ],
    "sg:phone":"+1 651 436 8902",
    "sg:postcode":"55043",
    "sg:province":"MN",
    "wof:name":"Professional Yacht Sales",
    "wof:placetype":"venue"
},
  "geometry": {"coordinates":[-92.770994,44.948302],"type":"Point"}
}