{
  "type": "Feature",
  "properties": {
    "addr:full":"30902 Tungsten St NW Princeton MN 55371",
    "addr:postcode":"30902;55371",
    "addr:street":"Tungsten St Nw",
    "iso:country":"US",
    "sg:address":"30902 Tungsten St NW",
    "sg:city":"Princeton",
    "sg:classifiers":[
        {
            "category":"Food & Beverages",
            "subcategory":"Fruits & Vegetables",
            "type":"Retail Goods"
        }
    ],
    "sg:phone":"+1 763 389 1218",
    "sg:postcode":"55371",
    "sg:province":"MN",
    "wof:name":"Rum Hallow Farm",
    "wof:placetype":"venue"
},
  "geometry": {"coordinates":[-93.425082,45.529739],"type":"Point"}
}