{
  "type": "Feature",
  "properties": {
    "addr:full":"220 Division St S Northfield MN 55057",
    "addr:housenumber":"220",
    "addr:postcode":"55057",
    "addr:street":"Division St S",
    "iso:country":"US",
    "sg:address":"220 Division St S",
    "sg:city":"Northfield",
    "sg:classifiers":[
        {
            "category":"Banks & Credit Unions",
            "subcategory":"Investment Brokerage",
            "type":"Services"
        }
    ],
    "sg:phone":"+1 507 663 0325",
    "sg:postcode":"55057",
    "sg:province":"MN",
    "sg:tags":[
        "stock",
        "bond"
    ],
    "wof:name":"Edward Jones Co",
    "wof:placetype":"venue"
},
  "geometry": {"coordinates":[-93.159064,44.458346],"type":"Point"}
}