{
  "type": "Feature",
  "properties": {
    "iso:country":"US",
    "sg:address":"6610 Clearwater Creek Dr",
    "sg:city":"Hugo",
    "sg:classifiers":[
        {
            "category":"Social Services",
            "type":"Services"
        }
    ],
    "sg:phone":"+1 651 426 0754",
    "sg:postcode":"55038",
    "sg:province":"MN",
    "sg:tags":[
        "outreach"
    ],
    "wof:name":"Restortion Mnstry Outreach Ctr",
    "wof:placetype":"venue"
},
  "geometry": {"coordinates":[-93.026914,45.148447],"type":"Point"}
}