{
  "type": "Feature",
  "properties": {
    "addr:full":"124 1st St SE Wadena MN 56482",
    "addr:housenumber":"124",
    "addr:postcode":"56482",
    "addr:street":"1St St Se",
    "iso:country":"US",
    "sg:address":"124 1st St SE",
    "sg:city":"Wadena",
    "sg:classifiers":[
        {
            "category":"Government",
            "subcategory":"Office",
            "type":"Public Place"
        }
    ],
    "sg:phone":"+1 218 631 7605",
    "sg:postcode":"56482",
    "sg:province":"MN",
    "sg:tags":[
        "county",
        "resource"
    ],
    "wof:name":"Wadena County Social Svc",
    "wof:placetype":"venue"
},
  "geometry": {"coordinates":[-95.135594,46.440389],"type":"Point"}
}