{
  "type": "Feature",
  "properties": {
    "iso:country":"US",
    "sg:address":"8751 State Hwy 7",
    "sg:city":"St Bonifacius",
    "sg:classifiers":[
        {
            "category":"Communications",
            "subcategory":"Film & Video Production",
            "type":"Services"
        }
    ],
    "sg:phone":"+1 952 446 8866",
    "sg:postcode":"55375",
    "sg:province":"MN",
    "sg:tags":[
        "audio"
    ],
    "wof:name":"Lake Country Studios LLC",
    "wof:placetype":"venue"
},
  "geometry": {"coordinates":[-93.744652,44.901706],"type":"Point"}
}