{
  "type": "Feature",
  "properties": {
    "addr:full":"1601 Hwy 12 E Willmar MN 56201",
    "addr:housenumber":"1601",
    "addr:postcode":"56201",
    "addr:street":"Hwy 12 E",
    "iso:country":"US",
    "sg:address":"1601 Hwy 12 E",
    "sg:city":"Willmar",
    "sg:classifiers":[
        {
            "category":"Professional",
            "subcategory":"Lawyer & Legal Services",
            "type":"Services"
        }
    ],
    "sg:phone":"+1 320 235 1876",
    "sg:postcode":"56201",
    "sg:province":"MN",
    "sg:tags":[
        "attorney"
    ],
    "wof:name":"Darval Wermerskirchen & Frank",
    "wof:placetype":"venue"
},
  "geometry": {"coordinates":[-95.021677,45.124159],"type":"Point"}
}