{
  "type": "Feature",
  "properties": {
    "addr:full":"20345 Doffing Ave Farmington MN 55024",
    "addr:postcode":"20345;55024",
    "addr:street":"Doffing Ave",
    "iso:country":"US",
    "sg:address":"20345 Doffing Ave",
    "sg:city":"Farmington",
    "sg:classifiers":[
        {
            "category":"Professional",
            "subcategory":"Computer Services",
            "type":"Services"
        }
    ],
    "sg:phone":"+1 651 460 6850",
    "sg:postcode":"55024",
    "sg:province":"MN",
    "sg:tags":[
        "design",
        "system"
    ],
    "wof:name":"Bre Cad/CAM & Engineering",
    "wof:placetype":"venue"
},
  "geometry": {"coordinates":[-93.01667399999999,44.656562],"type":"Point"}
}