{
  "type": "Feature",
  "properties": {
    "addr:full":"6351 170th St E Prior Lake MN 55372",
    "addr:housenumber":"6351",
    "addr:postcode":"55372",
    "addr:street":"170Th St E",
    "iso:country":"US",
    "sg:address":"6351 170th St E",
    "sg:city":"Prior Lake",
    "sg:classifiers":[
        {
            "category":"Professional",
            "type":"Services"
        }
    ],
    "sg:phone":"+1 952 440 7066",
    "sg:postcode":"55372",
    "sg:province":"MN",
    "wof:name":"Tidbits",
    "wof:placetype":"venue"
},
  "geometry": {"coordinates":[-93.39313799999999,44.703107],"type":"Point"}
}