{
  "type": "Feature",
  "properties": {
    "addr:full":"445 5th Ave NE Pine City MN 55063",
    "addr:housenumber":"445",
    "addr:postcode":"55063",
    "addr:street":"5Th Ave Ne",
    "iso:country":"US",
    "sg:address":"445 5th Ave NE",
    "sg:city":"Pine City",
    "sg:classifiers":[
        {
            "category":"Building & Trades",
            "subcategory":"Landscaping Services",
            "type":"Services"
        }
    ],
    "sg:phone":"+1 320 629 4990",
    "sg:postcode":"55063",
    "sg:province":"MN",
    "sg:tags":[
        "landscape",
        "contractor"
    ],
    "wof:name":"Jeff's Outdoor Svc Lawncare",
    "wof:placetype":"venue"
},
  "geometry": {"coordinates":[-92.965997,45.835557],"type":"Point"}
}