{
  "type": "Feature",
  "properties": {
    "addr:full":"5310 Shoreline Dr Mound MN 55364",
    "addr:housenumber":"5310",
    "addr:postcode":"55364",
    "addr:street":"Shoreline Dr Mound",
    "iso:country":"US",
    "sg:address":"5310 Shoreline Dr",
    "sg:city":"Mound",
    "sg:classifiers":[
        {
            "category":"Manufacturing",
            "subcategory":"Paper Products",
            "type":"Manufacturing & Wholesale Goods"
        }
    ],
    "sg:phone":"+1 763 478 2133",
    "sg:postcode":"55364",
    "sg:province":"MN",
    "sg:tags":[
        "box"
    ],
    "sg:website":"www.wgacarton.com",
    "wof:name":"Walter G Anderson Corp",
    "wof:placetype":"venue"
},
  "geometry": {"coordinates":[-93.655748,44.936745],"type":"Point"}
}