{
  "type": "Feature",
  "properties": {
    "addr:full":"624 NE 8th St Grand Rapids MN 55744",
    "addr:housenumber":"624",
    "addr:postcode":"55744",
    "addr:street":"Ne 8Th St",
    "iso:country":"US",
    "sg:address":"624 NE 8th St",
    "sg:city":"Grand Rapids",
    "sg:classifiers":[
        {
            "category":"Professional",
            "subcategory":"Business Services",
            "type":"Services"
        }
    ],
    "sg:phone":"+1 218 326 1559",
    "sg:postcode":"55744",
    "sg:province":"MN",
    "wof:name":"Helmer Enterprises Inc",
    "wof:placetype":"venue"
},
  "geometry": {"coordinates":[-93.517932,47.240245],"type":"Point"}
}