{
  "type": "Feature",
  "properties": {
    "addr:full":"7047 Kingfisher Ln NE Bemidji MN 56601",
    "addr:housenumber":"7047",
    "addr:postcode":"56601",
    "addr:street":"Kingfisher Ln Ne",
    "iso:country":"US",
    "sg:address":"7047 Kingfisher Ln NE",
    "sg:city":"Bemidji",
    "sg:classifiers":[
        {
            "category":"Building & Trades",
            "subcategory":"Construction",
            "type":"Services"
        }
    ],
    "sg:phone":"+1 218 751 2424",
    "sg:postcode":"56601",
    "sg:province":"MN",
    "sg:tags":[
        "house"
    ],
    "wof:name":"Rainbow Builders",
    "wof:placetype":"venue"
},
  "geometry": {"coordinates":[-94.776151,47.495149],"type":"Point"}
}