{
  "type": "Feature",
  "properties": {
    "addr:full":"6300 Shingle Creek Pkwy Minneapolis MN 55430",
    "addr:housenumber":"6300",
    "addr:postcode":"55430",
    "addr:street":"Shingle Creek Pkwy",
    "iso:country":"US",
    "sg:address":"6300 Shingle Creek Pkwy",
    "sg:city":"Minneapolis",
    "sg:classifiers":[
        {
            "category":"Professional",
            "subcategory":"Credit Reporting & Collection",
            "type":"Services"
        }
    ],
    "sg:phone":"+1 763 503 5200",
    "sg:postcode":"55430",
    "sg:province":"MN",
    "sg:tags":[
        "agency",
        "financial"
    ],
    "wof:name":"Financial Recovery Services",
    "wof:placetype":"venue"
},
  "geometry": {"coordinates":[-93.30734099999999,45.07062],"type":"Point"}
}