{
  "type": "Feature",
  "properties": {
    "addr:full":"3417 3rd St N St Cloud MN 56303",
    "addr:housenumber":"3417",
    "addr:postcode":"56303",
    "addr:street":"3Rd St N",
    "iso:country":"US",
    "sg:address":"3417 3rd St N",
    "sg:city":"St Cloud",
    "sg:classifiers":[
        {
            "category":"Communications",
            "subcategory":"Film & Video Production",
            "type":"Services"
        }
    ],
    "sg:phone":"+1 320 251 4050",
    "sg:postcode":"56303",
    "sg:province":"MN",
    "sg:tags":[
        "duplication",
        "tape"
    ],
    "wof:name":"Flicko's",
    "wof:placetype":"venue"
},
  "geometry": {"coordinates":[-94.200698,45.558671],"type":"Point"}
}