{
  "type": "Feature",
  "properties": {
    "iso:country":"US",
    "sg:address":"18475 Rum River Blvd",
    "sg:city":"Anoka",
    "sg:classifiers":[
        {
            "category":"Building & Trades",
            "subcategory":"Construction",
            "type":"Services"
        }
    ],
    "sg:phone":"+1 763 421 6417",
    "sg:postcode":"55303",
    "sg:province":"MN",
    "sg:tags":[
        "product",
        "asphalt"
    ],
    "sg:website":"www.czarsoftar.com",
    "wof:name":"Czars Of Tar",
    "wof:placetype":"venue"
},
  "geometry": {"coordinates":[-93.385181,45.306278],"type":"Point"}
}