{
  "type": "Feature",
  "properties": {
    "iso:country":"US",
    "sg:address":"1325 London Rd",
    "sg:city":"Duluth",
    "sg:classifiers":[
        {
            "category":"Freight",
            "type":"Transportation"
        }
    ],
    "sg:phone":"+1 218 724 0906",
    "sg:postcode":"55805",
    "sg:province":"MN",
    "sg:tags":[
        "operator",
        "trucking"
    ],
    "wof:name":"M R M Logistics",
    "wof:placetype":"venue"
},
  "geometry": {"coordinates":[-92.07946099999999,46.799167],"type":"Point"}
}