{
  "type": "Feature",
  "properties": {
    "addr:full":"1575 Charlton St Saint Paul MN 55118",
    "addr:housenumber":"1575",
    "addr:postcode":"55118",
    "addr:street":"Charlton St",
    "iso:country":"US",
    "sg:address":"1575 Charlton St",
    "sg:city":"Saint Paul",
    "sg:classifiers":[
        {
            "category":"Organizations",
            "subcategory":"Religious Organization",
            "type":"Services"
        }
    ],
    "sg:phone":"+1 651 457 6541",
    "sg:postcode":"55118",
    "sg:province":"MN",
    "wof:name":"St Stephen Lthrn Chrch Evnglst",
    "wof:placetype":"venue"
},
  "geometry": {"coordinates":[-93.096025,44.899152],"type":"Point"}
}