{
  "type": "Feature",
  "properties": {
    "addr:full":"5109 Grove St Minneapolis MN 55436",
    "addr:housenumber":"5109",
    "addr:postcode":"55436",
    "addr:street":"Grove St",
    "iso:country":"US",
    "sg:address":"5109 Grove St",
    "sg:city":"Minneapolis",
    "sg:classifiers":[
        {
            "category":"Manufacturing",
            "subcategory":"Printing",
            "type":"Manufacturing & Wholesale Goods"
        }
    ],
    "sg:phone":"+1 952 926 2825",
    "sg:postcode":"55436",
    "sg:province":"MN",
    "sg:tags":[
        "publishing"
    ],
    "wof:name":"Writedesign",
    "wof:placetype":"venue"
},
  "geometry": {"coordinates":[-93.35427,44.89875],"type":"Point"}
}