{
  "type": "Feature",
  "properties": {
    "addr:full":"780 Quixote Ave N Lakeland MN 55043",
    "addr:housenumber":"780",
    "addr:postcode":"55043",
    "addr:street":"Quixote Ave N",
    "iso:country":"US",
    "sg:address":"780 Quixote Ave N",
    "sg:city":"Lakeland",
    "sg:classifiers":[
        {
            "category":"Building & Trades",
            "subcategory":"Construction",
            "type":"Services"
        }
    ],
    "sg:phone":"+1 651 436 5732",
    "sg:postcode":"55043",
    "sg:province":"MN",
    "sg:tags":[
        "house"
    ],
    "wof:name":"James R Stanton Builders",
    "wof:placetype":"venue"
},
  "geometry": {"coordinates":[-92.765653,44.959177],"type":"Point"}
}