{
  "type": "Feature",
  "properties": {
    "iso:country":"US",
    "sg:address":"1175 Herbert St",
    "sg:city":"Saint Paul",
    "sg:classifiers":[
        {
            "category":"Professional",
            "type":"Services"
        }
    ],
    "sg:phone":"+1 651 772 6995",
    "sg:postcode":"55106",
    "sg:province":"MN",
    "wof:name":"Vang John Chong VA",
    "wof:placetype":"venue"
},
  "geometry": {"coordinates":[-93.03171500000001,44.977368],"type":"Point"}
}