{
  "type": "Feature",
  "properties": {
    "addr:full":"23301 Hwy 4 Paynesville MN 56362",
    "addr:housenumber":"23301",
    "addr:postcode":"56362",
    "addr:street":"Hwy 4",
    "iso:country":"US",
    "sg:address":"23301 Hwy 4",
    "sg:city":"Paynesville",
    "sg:classifiers":[
        {
            "category":"Retail",
            "subcategory":"Auto Repair",
            "type":"Services"
        }
    ],
    "sg:phone":"+1 320 243 4539",
    "sg:postcode":"56362",
    "sg:province":"MN",
    "sg:tags":[
        "general"
    ],
    "wof:name":"Robert L Pelzer Proprietor",
    "wof:placetype":"venue"
},
  "geometry": {"coordinates":[-94.79641700000001,45.46087],"type":"Point"}
}