{
  "type": "Feature",
  "properties": {
    "iso:country":"US",
    "sg:address":"7305 Dressage Rd",
    "sg:city":"Brainerd",
    "sg:classifiers":[
        {
            "category":"Recreation",
            "type":"Entertainment"
        }
    ],
    "sg:phone":"+1 218 764 2261",
    "sg:postcode":"56401",
    "sg:province":"MN",
    "wof:name":"Clare B Training Center Inc",
    "wof:placetype":"venue"
},
  "geometry": {"coordinates":[-94.00867,46.26161],"type":"Point"}
}