{
  "type": "Feature",
  "properties": {
    "addr:full":"8754 Lyndale Ave S Bloomington MN 55420",
    "addr:housenumber":"8754",
    "addr:postcode":"55420",
    "addr:street":"Lyndale Ave S",
    "iso:country":"US",
    "sg:address":"8754 Lyndale Ave S",
    "sg:city":"Bloomington",
    "sg:classifiers":[
        {
            "category":"Retail",
            "subcategory":"Laundry & Dry Cleaning",
            "type":"Services"
        }
    ],
    "sg:phone":"+1 952 884 4849",
    "sg:postcode":"55420",
    "sg:province":"MN",
    "sg:tags":[
        "cleaners"
    ],
    "wof:name":"Dry Cleaning Station",
    "wof:placetype":"venue"
},
  "geometry": {"coordinates":[-93.28864900000001,44.84375],"type":"Point"}
}