{
  "type": "Feature",
  "properties": {
    "addr:full":"1701 London Rd Duluth MN 55812",
    "addr:housenumber":"1701",
    "addr:postcode":"55812",
    "addr:street":"London Rd",
    "iso:country":"US",
    "sg:address":"1701 London Rd",
    "sg:city":"Duluth",
    "sg:classifiers":[
        {
            "category":"Home & Garden",
            "subcategory":"Building Materials",
            "type":"Retail Goods"
        }
    ],
    "sg:phone":"+1 218 728 4477",
    "sg:postcode":"55812",
    "sg:province":"MN",
    "sg:tags":[
        "paint"
    ],
    "wof:name":"St Germain's Paint Co",
    "wof:placetype":"venue"
},
  "geometry": {"coordinates":[-92.07337699999999,46.802312],"type":"Point"}
}