{
  "type": "Feature",
  "properties": {
    "iso:country":"US",
    "sg:address":"3199 Pilot Knob Rd",
    "sg:city":"Saint Paul",
    "sg:classifiers":[
        {
            "category":"Professional",
            "subcategory":"Management & Consulting",
            "type":"Services"
        }
    ],
    "sg:phone":"+1 651 687 2200",
    "sg:postcode":"55121",
    "sg:province":"MN",
    "sg:tags":[
        "manage",
        "computer",
        "facility"
    ],
    "wof:name":"Unisys Corporation",
    "wof:placetype":"venue"
},
  "geometry": {"coordinates":[-93.167233,44.84327],"type":"Point"}
}