{
  "type": "Feature",
  "properties": {
    "addr:full":"154 W Broadway St Monticello MN 55362",
    "addr:housenumber":"154",
    "addr:postcode":"55362",
    "addr:street":"W Broadway St",
    "iso:country":"US",
    "sg:address":"154 W Broadway St",
    "sg:city":"Monticello",
    "sg:classifiers":[
        {
            "category":"Professional",
            "type":"Services"
        },
        {
            "category":"Deli",
            "type":"Food & Drink"
        },
        {
            "category":"Restaurant",
            "type":"Food & Drink"
        },
        {
            "category":"Coffee & Tea",
            "type":"Food & Drink"
        }
    ],
    "sg:phone":"+1 763 295 3888",
    "sg:postcode":"55362",
    "sg:province":"MN",
    "sg:tags":[
        "delicatessen",
        "espresso",
        "caterer"
    ],
    "wof:name":"Cornerstone Cafe & Catering Co",
    "wof:placetype":"venue"
},
  "geometry": {"coordinates":[-93.79502599999999,45.305929],"type":"Point"}
}