{
  "type": "Feature",
  "properties": {
    "iso:country":"US",
    "sg:address":"1730 Diagonal Rd",
    "sg:city":"Worthington",
    "sg:classifiers":[
        {
            "category":"Organizations",
            "subcategory":"Religious Organization",
            "type":"Services"
        }
    ],
    "sg:phone":"+1 507 372 7976",
    "sg:postcode":"56187",
    "sg:province":"MN",
    "sg:tags":[
        "church"
    ],
    "wof:name":"Comunidad Cristiana",
    "wof:placetype":"venue"
},
  "geometry": {"coordinates":[-95.615405,43.632366],"type":"Point"}
}