{
  "type": "Feature",
  "properties": {
    "iso:country":"US",
    "sg:address":"4650 Egan Dr",
    "sg:city":"Savage",
    "sg:classifiers":[
        {
            "category":"Banks & Credit Unions",
            "subcategory":"Investment Brokerage",
            "type":"Services"
        }
    ],
    "sg:phone":"+1 952 894 9047",
    "sg:postcode":"55378",
    "sg:province":"MN",
    "sg:tags":[
        "security"
    ],
    "wof:name":"Sentre Securities Corp",
    "wof:placetype":"venue"
},
  "geometry": {"coordinates":[-93.33883899999999,44.746552],"type":"Point"}
}