{
  "type": "Feature",
  "properties": {
    "iso:country":"US",
    "sg:address":"6821 York Ave S",
    "sg:city":"Edina",
    "sg:classifiers":[
        {
            "category":"Education",
            "subcategory":"Special Training",
            "type":"Public Place"
        }
    ],
    "sg:phone":"+1 952 922 3000",
    "sg:postcode":"55435",
    "sg:province":"MN",
    "sg:tags":[
        "tutoring"
    ],
    "sg:website":"www.huntingtonlearning.com",
    "wof:name":"Huntington Learning Ctr",
    "wof:placetype":"venue"
},
  "geometry": {"coordinates":[-93.321169,44.878519],"type":"Point"}
}