{
  "type": "Feature",
  "properties": {
    "iso:country":"US",
    "sg:address":"21 Center Ave N",
    "sg:city":"Madelia",
    "sg:classifiers":[
        {
            "category":"Professional",
            "subcategory":"Business Services",
            "type":"Services"
        }
    ],
    "sg:phone":"+1 507 642 3911",
    "sg:postcode":"56062",
    "sg:province":"MN",
    "wof:name":"Enterprise North Inc",
    "wof:placetype":"venue"
},
  "geometry": {"coordinates":[-94.417012,44.051089],"type":"Point"}
}