{
  "type": "Feature",
  "properties": {
    "iso:country":"US",
    "sg:address":"13544 Haven Rd",
    "sg:city":"Little Falls",
    "sg:classifiers":[
        {
            "category":"Retail",
            "subcategory":"Auto Repair",
            "type":"Services"
        }
    ],
    "sg:phone":"+1 320 632 3292",
    "sg:postcode":"56345",
    "sg:province":"MN",
    "sg:tags":[
        "repairing",
        "automobile"
    ],
    "wof:name":"Benson Radiators & Fire Svc",
    "wof:placetype":"venue"
},
  "geometry": {"coordinates":[-94.362949,45.95648],"type":"Point"}
}