{
  "type": "Feature",
  "properties": {
    "addr:full":"392 E 240th St Jordan MN 55352",
    "addr:housenumber":"392",
    "addr:postcode":"55352",
    "addr:street":"E 240Th St",
    "iso:country":"US",
    "sg:address":"392 E 240th St",
    "sg:city":"Jordan",
    "sg:classifiers":[
        {
            "category":"Wholesale",
            "subcategory":"Machinery & Supplies",
            "type":"Manufacturing & Wholesale Goods"
        }
    ],
    "sg:phone":"+1 952 758 5298",
    "sg:postcode":"55352",
    "sg:province":"MN",
    "sg:tags":[
        "industrial",
        "equipment",
        "used",
        "machinery-new",
        "supplies-wholesale"
    ],
    "sg:website":"http://www.mjbmachinery.com",
    "wof:name":"Mjb Machinery Sales Inc.",
    "wof:placetype":"venue"
},
  "geometry": {"coordinates":[-93.515404,44.601798],"type":"Point"}
}