{
  "type": "Feature",
  "properties": {
    "addr:full":"2928 Piedmont Ave Duluth MN 55811",
    "addr:housenumber":"2928",
    "addr:postcode":"55811",
    "addr:street":"Piedmont Ave",
    "iso:country":"US",
    "sg:address":"2928 Piedmont Ave",
    "sg:city":"Duluth",
    "sg:classifiers":[
        {
            "category":"Professional",
            "subcategory":"Detective & Security Services",
            "type":"Services"
        }
    ],
    "sg:phone":"+1 218 590 8035",
    "sg:postcode":"55811",
    "sg:province":"MN",
    "sg:tags":[
        "fire",
        "alarm",
        "monitoring"
    ],
    "wof:name":"Wjm Fire Alarm Service LLC",
    "wof:placetype":"venue"
},
  "geometry": {"coordinates":[-92.16352000000001,46.784717],"type":"Point"}
}