{
  "type": "Feature",
  "properties": {
    "addr:full":"3418 131st St W Rosemount MN 55068",
    "addr:housenumber":"3418",
    "addr:postcode":"55068",
    "addr:street":"131St St W",
    "iso:country":"US",
    "sg:address":"3418 131st St W",
    "sg:city":"Rosemount",
    "sg:classifiers":[
        {
            "category":"Personal",
            "subcategory":"Beauty Salon",
            "type":"Services"
        }
    ],
    "sg:phone":"+1 651 423 3460",
    "sg:postcode":"55068",
    "sg:province":"MN",
    "sg:tags":[
        "shop"
    ],
    "wof:name":"Look Stylists",
    "wof:placetype":"venue"
},
  "geometry": {"coordinates":[-93.135869,44.758889],"type":"Point"}
}