{
  "type": "Feature",
  "properties": {
    "iso:country":"US",
    "sg:address":"6033 Sumter Pl N",
    "sg:city":"Minneapolis",
    "sg:classifiers":[
        {
            "category":"Communications",
            "subcategory":"Film & Video Production",
            "type":"Services"
        }
    ],
    "sg:phone":"+1 763 595 8223",
    "sg:postcode":"55428",
    "sg:province":"MN",
    "sg:tags":[
        "motion",
        "picture",
        "distribution"
    ],
    "wof:name":"Palm Productions LLC",
    "wof:placetype":"venue"
},
  "geometry": {"coordinates":[-93.379148,45.062904],"type":"Point"}
}