{
  "type": "Feature",
  "properties": {
    "addr:full":"15164 Lamb Ave Nerstrand MN 55053",
    "addr:housenumber":"15164",
    "addr:postcode":"55053",
    "addr:street":"Lamb Ave",
    "iso:country":"US",
    "sg:address":"15164 Lamb Ave",
    "sg:city":"Nerstrand",
    "sg:classifiers":[
        {
            "category":"Shopping",
            "subcategory":"Computers & Home Electronics",
            "type":"Retail Goods"
        },
        {
            "category":"Professional",
            "subcategory":"Computer Services",
            "type":"Services"
        }
    ],
    "sg:phone":"+1 507 664 9472",
    "sg:postcode":"55053",
    "sg:province":"MN",
    "sg:tags":[
        "repair",
        "recovery",
        "supply",
        "technical",
        "assistance",
        "system",
        "hardware",
        "network",
        "security-systems",
        "design",
        "equipment-service",
        "data",
        "support",
        "software"
    ],
    "wof:name":"Gigabyte Pro",
    "wof:placetype":"venue"
},
  "geometry": {"coordinates":[-93.060514,44.368088],"type":"Point"}
}