{
  "type": "Feature",
  "properties": {
    "addr:full":"330 E Broadway Minneapolis MN 55425",
    "addr:housenumber":"330",
    "addr:postcode":"55425",
    "addr:street":"E Broadway",
    "iso:country":"US",
    "sg:address":"330 E Broadway",
    "sg:city":"Minneapolis",
    "sg:classifiers":[
        {
            "category":"Shopping",
            "subcategory":"Clothing, Apparel, & Fashions",
            "type":"Retail Goods"
        }
    ],
    "sg:phone":"+1 952 858 9363",
    "sg:postcode":"55425",
    "sg:province":"MN",
    "sg:tags":[
        "accessory",
        "clothing",
        "women's"
    ],
    "wof:name":"Foxmoor",
    "wof:placetype":"venue"
},
  "geometry": {"coordinates":[-93.262716,44.998717],"type":"Point"}
}