{
  "type": "Feature",
  "properties": {
    "iso:country":"US",
    "sg:address":"620 Civic Heights Dr",
    "sg:city":"Circle Pines",
    "sg:classifiers":[
        {
            "category":"Health Services",
            "subcategory":"Chiropractor",
            "type":"Services"
        }
    ],
    "sg:phone":"+1 763 795 8300",
    "sg:postcode":"55014",
    "sg:province":"MN",
    "sg:website":"www.dlchiropractors.com",
    "wof:name":"Dockter Lutz Chiropractic",
    "wof:placetype":"venue"
},
  "geometry": {"coordinates":[-93.153541,45.145685],"type":"Point"}
}