{
  "type": "Feature",
  "properties": {
    "iso:country":"US",
    "sg:address":"61814 193rd St",
    "sg:city":"Litchfield",
    "sg:classifiers":[
        {
            "category":"Farming",
            "subcategory":"Farm",
            "type":"Manufacturing & Wholesale Goods"
        }
    ],
    "sg:phone":"+1 320 693 7606",
    "sg:postcode":"55355",
    "sg:province":"MN",
    "sg:tags":[
        "crop",
        "general"
    ],
    "wof:name":"Anderson Charle",
    "wof:placetype":"venue"
},
  "geometry": {"coordinates":[-94.528932,45.026205],"type":"Point"}
}