{
  "type": "Feature",
  "properties": {
    "addr:full":"510 E Franklin Ave Minneapolis MN 55404",
    "addr:housenumber":"510",
    "addr:postcode":"55404",
    "addr:street":"E Franklin Ave",
    "iso:country":"US",
    "sg:address":"510 E Franklin Ave",
    "sg:city":"Minneapolis",
    "sg:classifiers":[
        {
            "category":"Social Services",
            "type":"Services"
        }
    ],
    "sg:phone":"+1 612 870 7263",
    "sg:postcode":"55404",
    "sg:province":"MN",
    "wof:name":"Peace House",
    "wof:placetype":"venue"
},
  "geometry": {"coordinates":[-93.26774500000001,44.962767],"type":"Point"}
}