{
  "type": "Feature",
  "properties": {
    "iso:country":"US",
    "sg:address":"9250 Breckenridge Ln",
    "sg:city":"Eden Prairie",
    "sg:classifiers":[
        {
            "category":"Wholesale",
            "subcategory":"Toys & Hobbies",
            "type":"Manufacturing & Wholesale Goods"
        }
    ],
    "sg:phone":"+1 952 949 5931",
    "sg:postcode":"55347",
    "sg:province":"MN",
    "wof:name":"Paul Seyb & Associates Inc",
    "wof:placetype":"venue"
},
  "geometry": {"coordinates":[-93.50402,44.835907],"type":"Point"}
}