{
  "type": "Feature",
  "properties": {
    "addr:full":"3618 Rainbow Dr Minnetonka MN 55345",
    "addr:housenumber":"3618",
    "addr:postcode":"55345",
    "addr:street":"Rainbow Dr",
    "iso:country":"US",
    "sg:address":"3618 Rainbow Dr",
    "sg:city":"Minnetonka",
    "sg:classifiers":[
        {
            "category":"Real Estate",
            "subcategory":"Real Estate Operator",
            "type":"Services"
        }
    ],
    "sg:phone":"+1 952 476 6642",
    "sg:postcode":"55345",
    "sg:province":"MN",
    "sg:tags":[
        "building",
        "nonresidential"
    ],
    "wof:name":"Rfb Properties",
    "wof:placetype":"venue"
},
  "geometry": {"coordinates":[-93.497621,44.939552],"type":"Point"}
}