{
  "type": "Feature",
  "properties": {
    "addr:full":"7206 Co Rd 21 La Crescent MN 55947",
    "addr:housenumber":"7206",
    "addr:postcode":"55947",
    "addr:street":"Co Rd 21",
    "iso:country":"US",
    "sg:address":"7206 Co Rd 21",
    "sg:city":"La Crescent",
    "sg:classifiers":[
        {
            "category":"Farming",
            "subcategory":"Livestock Farm",
            "type":"Manufacturing & Wholesale Goods"
        }
    ],
    "sg:phone":"+1 507 894 4521",
    "sg:postcode":"55947",
    "sg:province":"MN",
    "sg:tags":[
        "feedlot",
        "corn",
        "soybean",
        "beef",
        "cattle"
    ],
    "wof:name":"Clair Welch",
    "wof:placetype":"venue"
},
  "geometry": {"coordinates":[-91.395949,43.770752],"type":"Point"}
}