{
  "type": "Feature",
  "properties": {
    "addr:full":"2215 Oliver Ave S Minneapolis MN 55405",
    "addr:housenumber":"2215",
    "addr:postcode":"55405",
    "addr:street":"Oliver Ave S",
    "iso:country":"US",
    "sg:address":"2215 Oliver Ave S",
    "sg:city":"Minneapolis",
    "sg:classifiers":[
        {
            "category":"Professional",
            "type":"Services"
        }
    ],
    "sg:phone":"+1 612 377 6483",
    "sg:postcode":"55405",
    "sg:province":"MN",
    "wof:name":"Mdestiny Inc",
    "wof:placetype":"venue"
},
  "geometry": {"coordinates":[-93.306336,44.959403],"type":"Point"}
}