{
  "type": "Feature",
  "properties": {
    "iso:country":"US",
    "sg:address":"19272 109th St",
    "sg:city":"Big Lake",
    "sg:classifiers":[
        {
            "category":"Professional",
            "subcategory":"Computer Services",
            "type":"Services"
        }
    ],
    "sg:phone":"+1 763 263 7657",
    "sg:postcode":"55309",
    "sg:province":"MN",
    "sg:tags":[
        "related"
    ],
    "wof:name":"Ness Computer Consulting",
    "wof:placetype":"venue"
},
  "geometry": {"coordinates":[-93.762389,45.411548],"type":"Point"}
}