{
  "type": "Feature",
  "properties": {
    "addr:full":"5528 Emerald Ave Mountain Iron MN 55768",
    "addr:housenumber":"5528",
    "addr:postcode":"55768",
    "addr:street":"Emerald Ave",
    "iso:country":"US",
    "sg:address":"5528 Emerald Ave",
    "sg:city":"Mountain Iron",
    "sg:classifiers":[
        {
            "category":"Education",
            "subcategory":"Library",
            "type":"Public Place"
        }
    ],
    "sg:phone":"+1 218 741 3840",
    "sg:postcode":"55768",
    "sg:province":"MN",
    "wof:name":"Als",
    "wof:placetype":"venue"
},
  "geometry": {"coordinates":[-92.593485,47.516836],"type":"Point"}
}