{
  "type": "Feature",
  "properties": {
    "iso:country":"US",
    "sg:address":"201 4th St NE",
    "sg:city":"Kasson",
    "sg:classifiers":[
        {
            "category":"Professional",
            "type":"Services"
        }
    ],
    "sg:phone":"+1 507 634 6641",
    "sg:postcode":"55944",
    "sg:province":"MN",
    "wof:name":"Cop Cat Designs",
    "wof:placetype":"venue"
},
  "geometry": {"coordinates":[-92.745707,44.033111],"type":"Point"}
}