{
  "type": "Feature",
  "properties": {
    "iso:country":"US",
    "sg:address":"1090 N Earl St",
    "sg:city":"St Paul",
    "sg:classifiers":[
        {
            "category":"Real Estate",
            "subcategory":"Real Estate Agent",
            "type":"Services"
        }
    ],
    "sg:phone":"+1 651 772 0026",
    "sg:postcode":"55106",
    "sg:province":"MN",
    "sg:website":"www.herizonone.com",
    "wof:name":"Herizon Realty",
    "wof:placetype":"venue"
},
  "geometry": {"coordinates":[-93.055722,44.974561],"type":"Point"}
}