{
  "type": "Feature",
  "properties": {
    "addr:full":"2900 Nicollet Ave Minneapolis MN 55408",
    "addr:housenumber":"2900",
    "addr:postcode":"55408",
    "addr:street":"Nicollet Ave",
    "iso:country":"US",
    "sg:address":"2900 Nicollet Ave",
    "sg:city":"Minneapolis",
    "sg:classifiers":[
        {
            "category":"Retail",
            "subcategory":"Car Wash",
            "type":"Services"
        }
    ],
    "sg:phone":"+1 612 870 1019",
    "sg:postcode":"55408",
    "sg:province":"MN",
    "wof:name":"Nicollet-Lake Self Serve Car Wash",
    "wof:placetype":"venue"
},
  "geometry": {"coordinates":[-93.278099,44.9506],"type":"Point"}
}