{
  "type": "Feature",
  "properties": {
    "iso:country":"US",
    "sg:address":"26 12th St S",
    "sg:city":"Sauk Centre",
    "sg:classifiers":[
        {
            "category":"Restaurant",
            "type":"Food & Drink"
        }
    ],
    "sg:phone":"+1 320 352 6505",
    "sg:postcode":"56378",
    "sg:province":"MN",
    "sg:tags":[
        "drinking",
        "eating",
        "caterer"
    ],
    "wof:name":"River's Edge Dining & Lounge",
    "wof:placetype":"venue"
},
  "geometry": {"coordinates":[-94.94193,45.72349],"type":"Point"}
}