{
  "type": "Feature",
  "properties": {
    "addr:full":"66060 140th Ave Claremont MN 55924",
    "addr:housenumber":"66060",
    "addr:postcode":"55924",
    "addr:street":"140Th Ave",
    "iso:country":"US",
    "sg:address":"66060 140th Ave",
    "sg:city":"Claremont",
    "sg:phone":"+1 507 528 2319",
    "sg:postcode":"55924",
    "sg:province":"MN",
    "sg:tags":[
        "farm",
        "corn",
        "soybean"
    ],
    "wof:name":"Bruce Schmoll",
    "wof:placetype":"venue"
},
  "geometry": {"coordinates":[-92.96526799999999,43.981206],"type":"Point"}
}