{
  "type": "Feature",
  "properties": {
    "iso:country":"US",
    "sg:address":"861 Edgewood Dr N",
    "sg:city":"Baxter",
    "sg:classifiers":[
        {
            "category":"Shopping",
            "type":"Retail Goods"
        }
    ],
    "sg:phone":"+1 218 828 9550",
    "sg:postcode":"56425",
    "sg:province":"MN",
    "sg:tags":[
        "equipment",
        "telephone",
        "supply"
    ],
    "wof:name":"Syvantis Technologies",
    "wof:placetype":"venue"
},
  "geometry": {"coordinates":[-94.24496600000001,46.363568],"type":"Point"}
}