{
  "type": "Feature",
  "properties": {
    "addr:full":"1001 S Broadway Ave Albert Lea MN 56007",
    "addr:housenumber":"1001",
    "addr:postcode":"56007",
    "addr:street":"S Broadway Ave",
    "iso:country":"US",
    "sg:address":"1001 S Broadway Ave",
    "sg:city":"Albert Lea",
    "sg:classifiers":[
        {
            "category":"Insurance",
            "subcategory":"Insurance Agent",
            "type":"Services"
        }
    ],
    "sg:phone":"+1 507 373 1964",
    "sg:postcode":"56007",
    "sg:province":"MN",
    "wof:name":"Cuna Mutual Life Insurance Co",
    "wof:placetype":"venue"
},
  "geometry": {"coordinates":[-93.36866999999999,43.640471],"type":"Point"}
}