{
  "type": "Feature",
  "properties": {
    "addr:full":"1603 6th Ave W Shakopee MN 55379",
    "addr:housenumber":"1603",
    "addr:postcode":"55379",
    "addr:street":"6Th Ave W",
    "iso:country":"US",
    "sg:address":"1603 6th Ave W",
    "sg:city":"Shakopee",
    "sg:classifiers":[
        {
            "category":"Building & Trades",
            "subcategory":"Construction",
            "type":"Services"
        }
    ],
    "sg:phone":"+1 952 445 6722",
    "sg:postcode":"55379",
    "sg:province":"MN",
    "sg:tags":[
        "contractor"
    ],
    "wof:name":"Leslie D Dengerud",
    "wof:placetype":"venue"
},
  "geometry": {"coordinates":[-93.54626500000001,44.79015],"type":"Point"}
}