{
  "type": "Feature",
  "properties": {
    "addr:full":"1450 Railroad Ave Albany MN 56307",
    "addr:housenumber":"1450",
    "addr:postcode":"56307",
    "addr:street":"Railroad Ave",
    "iso:country":"US",
    "sg:address":"1450 Railroad Ave",
    "sg:city":"Albany",
    "sg:classifiers":[
        {
            "category":"Sports & Exercise",
            "subcategory":"Bowling",
            "type":"Entertainment"
        }
    ],
    "sg:phone":"+1 320 845 4732",
    "sg:postcode":"56307",
    "sg:province":"MN",
    "sg:tags":[
        "center"
    ],
    "wof:name":"Albany Bowling Ctr & Pro Shop",
    "wof:placetype":"venue"
},
  "geometry": {"coordinates":[-94.588255,45.631258],"type":"Point"}
}