{
  "type": "Feature",
  "properties": {
    "addr:full":"90 N Fish Hatchery Rd St Paul MN 55106",
    "addr:housenumber":"90",
    "addr:postcode":"55106",
    "addr:street":"N Fish Hatchery Rd",
    "iso:country":"US",
    "sg:address":"90 N Fish Hatchery Rd",
    "sg:city":"St Paul",
    "sg:classifiers":[
        {
            "category":"Autos & Motor Vehicles",
            "subcategory":"Automobile Sales",
            "type":"Retail Goods"
        }
    ],
    "sg:phone":"+1 651 774 4744",
    "sg:postcode":"55106",
    "sg:province":"MN",
    "sg:tags":[
        "car",
        "dealer"
    ],
    "wof:name":"Mazda Motors Of America",
    "wof:placetype":"venue"
},
  "geometry": {"coordinates":[-93.047083,44.945297],"type":"Point"}
}