{
  "type": "Feature",
  "properties": {
    "iso:country":"US",
    "sg:address":"2909 W 6th St",
    "sg:city":"Duluth",
    "sg:classifiers":[
        {
            "category":"Building & Trades",
            "subcategory":"Plumbing",
            "type":"Services"
        }
    ],
    "sg:phone":"+1 218 722 3795",
    "sg:postcode":"55806",
    "sg:province":"MN",
    "sg:tags":[
        "plumbing",
        "heating",
        "contractor"
    ],
    "wof:name":"Isadore Jerry Plumbing & Htg",
    "wof:placetype":"venue"
},
  "geometry": {"coordinates":[-92.14251299999999,46.764719],"type":"Point"}
}