{
  "type": "Feature",
  "properties": {
    "addr:full":"4901 Chowen Ave S Minneapolis MN 55410",
    "addr:housenumber":"4901",
    "addr:postcode":"55410",
    "addr:street":"Chowen Ave S",
    "iso:country":"US",
    "sg:address":"4901 Chowen Ave S",
    "sg:city":"Minneapolis",
    "sg:classifiers":[
        {
            "category":"Education",
            "subcategory":"Preschool",
            "type":"Public Place"
        },
        {
            "category":"Education",
            "subcategory":"School",
            "type":"Public Place"
        }
    ],
    "sg:phone":"+1 612 926 8043",
    "sg:postcode":"55410",
    "sg:province":"MN",
    "sg:tags":[
        "elementary"
    ],
    "wof:name":"Lake Harriet United Methodist Church",
    "wof:placetype":"venue"
},
  "geometry": {"coordinates":[-93.325203,44.914299],"type":"Point"}
}