{
  "type": "Feature",
  "properties": {
    "iso:country":"US",
    "sg:address":"111 2nd St NE",
    "sg:city":"Roseau",
    "sg:classifiers":[
        {
            "category":"Cinema",
            "subcategory":"Movie Rental",
            "type":"Entertainment"
        }
    ],
    "sg:phone":"+1 218 463 1000",
    "sg:postcode":"56751",
    "sg:province":"MN",
    "sg:tags":[
        "leasing",
        "video",
        "disc",
        "tape"
    ],
    "wof:name":"Video Box & Tanning 3",
    "wof:placetype":"venue"
},
  "geometry": {"coordinates":[-95.76271199999999,48.847232],"type":"Point"}
}