{
  "type": "Feature",
  "properties": {
    "iso:country":"US",
    "sg:address":"435 University Ave W",
    "sg:city":"St Paul",
    "sg:classifiers":[
        {
            "category":"Shopping",
            "subcategory":"Jewelry",
            "type":"Retail Goods"
        }
    ],
    "sg:phone":"+1 651 293 9120",
    "sg:postcode":"55103",
    "sg:province":"MN",
    "sg:tags":[
        "repair",
        "jeweler"
    ],
    "wof:name":"Kim Dung Jewelry Store",
    "wof:placetype":"venue"
},
  "geometry": {"coordinates":[-93.117116,44.955834],"type":"Point"}
}