{
  "type": "Feature",
  "properties": {
    "addr:full":"26300 Freeport Ave Wyoming MN 55092",
    "addr:housenumber":"26300",
    "addr:postcode":"55092",
    "addr:street":"Freeport Ave",
    "iso:country":"US",
    "sg:address":"26300 Freeport Ave",
    "sg:city":"Wyoming",
    "sg:classifiers":[
        {
            "category":"Retail",
            "subcategory":"Repair Shop",
            "type":"Services"
        },
        {
            "category":"Professional",
            "subcategory":"Business Services",
            "type":"Services"
        }
    ],
    "sg:phone":"+1 651 462 2960",
    "sg:postcode":"55092",
    "sg:province":"MN",
    "sg:tags":[
        "upholsterer"
    ],
    "wof:name":"G L Hardy Design",
    "wof:placetype":"venue"
},
  "geometry": {"coordinates":[-92.986062,45.329645],"type":"Point"}
}