{
  "type": "Feature",
  "properties": {
    "iso:country":"US",
    "sg:address":"7608 S Bay Cir",
    "sg:city":"Minneapolis",
    "sg:classifiers":[
        {
            "category":"Professional",
            "subcategory":"Business Services",
            "type":"Services"
        }
    ],
    "sg:phone":"+1 952 898 9109",
    "sg:postcode":"55438",
    "sg:province":"MN",
    "wof:name":"South Bay Group",
    "wof:placetype":"venue"
},
  "geometry": {"coordinates":[-93.38317499999999,44.827776],"type":"Point"}
}