{
  "type": "Feature",
  "properties": {
    "addr:full":"971 E Frontage Rd Litchfield MN 55355",
    "addr:housenumber":"971",
    "addr:postcode":"55355",
    "addr:street":"E Frontage Rd",
    "iso:country":"US",
    "sg:address":"971 E Frontage Rd",
    "sg:city":"Litchfield",
    "sg:classifiers":[
        {
            "category":"Government",
            "subcategory":"Office",
            "type":"Public Place"
        }
    ],
    "sg:phone":"+1 320 593 4600",
    "sg:postcode":"55355",
    "sg:province":"MN",
    "sg:tags":[
        "conservation"
    ],
    "wof:name":"Litchfeld Wtlnds Acqsition Off",
    "wof:placetype":"venue"
},
  "geometry": {"coordinates":[-94.508004,45.122124],"type":"Point"}
}