{
  "type": "Feature",
  "properties": {
    "addr:full":"1109 Crosstown Blvd NE Anoka MN 55304",
    "addr:housenumber":"1109",
    "addr:postcode":"55304",
    "addr:street":"Crosstown Blvd Ne",
    "iso:country":"US",
    "sg:address":"1109 Crosstown Blvd NE",
    "sg:city":"Anoka",
    "sg:classifiers":[
        {
            "category":"Building & Trades",
            "subcategory":"Construction",
            "type":"Services"
        }
    ],
    "sg:phone":"+1 763 434 4365",
    "sg:postcode":"55304",
    "sg:province":"MN",
    "sg:tags":[
        "excavation",
        "contractor"
    ],
    "wof:name":"Gusse Bros Construction Inc",
    "wof:placetype":"venue"
},
  "geometry": {"coordinates":[-93.24263500000001,45.287907],"type":"Point"}
}