{
  "type": "Feature",
  "properties": {
    "addr:full":"31083 Co Rd 4 Badger MN 56714",
    "addr:housenumber":"31083;4",
    "addr:postcode":"56714",
    "addr:street":"Co Rd;Badger",
    "iso:country":"US",
    "sg:address":"31083 Co Rd 4",
    "sg:city":"Badger",
    "sg:phone":"+1 218 528 3700",
    "sg:postcode":"56714",
    "sg:province":"MN",
    "sg:tags":[
        "farm",
        "soybean"
    ],
    "wof:name":"Brian Gregerson",
    "wof:placetype":"venue"
},
  "geometry": {"coordinates":[-95.929473,48.686985],"type":"Point"}
}