{
  "type": "Feature",
  "properties": {
    "addr:full":"2028 3rd Ave N Minneapolis MN 55405",
    "addr:housenumber":"2028",
    "addr:postcode":"55405",
    "addr:street":"3Rd Ave N",
    "iso:country":"US",
    "sg:address":"2028 3rd Ave N",
    "sg:city":"Minneapolis",
    "sg:classifiers":[
        {
            "category":"Arts & Performance",
            "subcategory":"Art Gallery",
            "type":"Entertainment"
        }
    ],
    "sg:phone":"+1 612 377 5335",
    "sg:postcode":"55405",
    "sg:province":"MN",
    "sg:tags":[
        "consultant",
        "galleries"
    ],
    "wof:name":"Offbeat Gallery",
    "wof:placetype":"venue"
},
  "geometry": {"coordinates":[-93.306577,44.979778],"type":"Point"}
}