{
  "type": "Feature",
  "properties": {
    "addr:full":"3315 Co Rd 20 International Falls MN 56649",
    "addr:housenumber":"3315;20",
    "addr:postcode":"56649",
    "addr:street":"Co Rd",
    "iso:country":"US",
    "sg:address":"3315 Co Rd 20",
    "sg:city":"International Falls",
    "sg:classifiers":[
        {
            "category":"Professional",
            "subcategory":"Business Services",
            "type":"Services"
        }
    ],
    "sg:phone":"+1 218 286 5363",
    "sg:postcode":"56649",
    "sg:province":"MN",
    "wof:name":"Nagurski Studio",
    "wof:placetype":"venue"
},
  "geometry": {"coordinates":[-93.322785,48.612757],"type":"Point"}
}