{
  "type": "Feature",
  "properties": {
    "addr:full":"145 Lake Ave N Spicer MN 56288",
    "addr:housenumber":"145",
    "addr:postcode":"56288",
    "addr:street":"Lake Ave N Spicer",
    "iso:country":"US",
    "sg:address":"145 Lake Ave N",
    "sg:city":"Spicer",
    "sg:classifiers":[
        {
            "category":"Banks & Credit Unions",
            "subcategory":"Investment Brokerage",
            "type":"Services"
        }
    ],
    "sg:phone":"+1 320 796 6104",
    "sg:postcode":"56288",
    "sg:province":"MN",
    "sg:tags":[
        "commodity",
        "contract"
    ],
    "wof:name":"Van Ahn & Co Inc",
    "wof:placetype":"venue"
},
  "geometry": {"coordinates":[-94.938614,45.234177],"type":"Point"}
}