{
  "type": "Feature",
  "properties": {
    "iso:country":"US",
    "sg:address":"811 N Minnesota St",
    "sg:city":"New Ulm",
    "sg:classifiers":[
        {
            "category":"Building & Trades",
            "subcategory":"Construction",
            "type":"Services"
        }
    ],
    "sg:phone":"+1 507 354 1589",
    "sg:postcode":"56073",
    "sg:province":"MN",
    "sg:tags":[
        "carpentry",
        "contractor"
    ],
    "wof:name":"Haala Woodworking",
    "wof:placetype":"venue"
},
  "geometry": {"coordinates":[-94.467285,44.321996],"type":"Point"}
}