{
  "type": "Feature",
  "properties": {
    "addr:full":"19514 Pirz Lake Rd Paynesville MN 56362",
    "addr:housenumber":"19514",
    "addr:postcode":"56362",
    "addr:street":"Pirz Lake Rd",
    "iso:country":"US",
    "sg:address":"19514 Pirz Lake Rd",
    "sg:city":"Paynesville",
    "sg:classifiers":[
        {
            "category":"Building & Trades",
            "subcategory":"Construction",
            "type":"Services"
        }
    ],
    "sg:phone":"+1 320 243 4440",
    "sg:postcode":"56362",
    "sg:province":"MN",
    "sg:tags":[
        "hanging",
        "contractor"
    ],
    "wof:name":"Pats Painting & Decorating",
    "wof:placetype":"venue"
},
  "geometry": {"coordinates":[-94.599017,45.405284],"type":"Point"}
}