{
  "type": "Feature",
  "properties": {
    "addr:full":"1000 University Ave SE Ste 1 Minneapolis MN 55414",
    "addr:housenumber":"1000",
    "addr:postcode":"55414",
    "addr:street":"University Ave Se Ste 1",
    "iso:country":"US",
    "sg:address":"1000 University Ave SE Ste 1",
    "sg:city":"Minneapolis",
    "sg:classifiers":[
        {
            "category":"Autos & Motor Vehicles",
            "subcategory":"Auto Supplies",
            "type":"Retail Goods"
        }
    ],
    "sg:phone":"+1 612 331 2248",
    "sg:postcode":"55414",
    "sg:province":"MN",
    "sg:tags":[
        "tire"
    ],
    "wof:name":"Southeast Amoco",
    "wof:placetype":"venue"
},
  "geometry": {"coordinates":[-93.242171,44.981602],"type":"Point"}
}