{
  "type": "Feature",
  "properties": {
    "addr:full":"12781 890th Ave Maynard MN 56260",
    "addr:housenumber":"12781",
    "addr:postcode":"56260",
    "addr:street":"890Th Ave",
    "iso:country":"US",
    "sg:address":"12781 890th Ave",
    "sg:city":"Maynard",
    "sg:classifiers":[
        {
            "category":"Organizations",
            "subcategory":"Religious Organization",
            "type":"Services"
        }
    ],
    "sg:phone":"+1 320 367 2859",
    "sg:postcode":"56260",
    "sg:province":"MN",
    "sg:tags":[
        "church"
    ],
    "wof:name":"Wang Lutheran Church",
    "wof:placetype":"venue"
},
  "geometry": {"coordinates":[-95.427346,44.876264],"type":"Point"}
}