{
  "type": "Feature",
  "properties": {
    "addr:full":"21731 260th St New Ulm MN 56073",
    "addr:housenumber":"21731",
    "addr:postcode":"56073",
    "addr:street":"260Th St",
    "iso:country":"US",
    "sg:address":"21731 260th St",
    "sg:city":"New Ulm",
    "sg:phone":"+1 507 354 5933",
    "sg:postcode":"56073",
    "sg:province":"MN",
    "sg:tags":[
        "farm",
        "corn",
        "soybean"
    ],
    "wof:name":"Dennis Milbrett",
    "wof:placetype":"venue"
},
  "geometry": {"coordinates":[-94.60331499999999,44.340644],"type":"Point"}
}