{
  "type": "Feature",
  "properties": {
    "iso:country":"US",
    "sg:address":"2905 Regent Ave N",
    "sg:city":"Golden Valley",
    "sg:classifiers":[
        {
            "category":"Education",
            "subcategory":"Special Training",
            "type":"Public Place"
        }
    ],
    "sg:phone":"+1 763 529 2240",
    "sg:postcode":"55422",
    "sg:province":"MN",
    "sg:tags":[
        "instruction",
        "music"
    ],
    "wof:name":"Family Music Ctr",
    "wof:placetype":"venue"
},
  "geometry": {"coordinates":[-93.344455,45.011878],"type":"Point"}
}