{
  "type": "Feature",
  "properties": {
    "iso:country":"US",
    "sg:address":"1880 Radisson Rd NE",
    "sg:city":"Minneapolis",
    "sg:classifiers":[
        {
            "category":"Retail",
            "subcategory":"Auto Repair",
            "type":"Services"
        }
    ],
    "sg:phone":"+1 651 780 3440",
    "sg:postcode":"55449",
    "sg:province":"MN",
    "sg:tags":[
        "repairing",
        "automobile"
    ],
    "wof:name":"Sampson Brothers Well Co",
    "wof:placetype":"venue"
},
  "geometry": {"coordinates":[-93.223804,45.133506],"type":"Point"}
}