{
  "type": "Feature",
  "properties": {
    "addr:full":"3901 85th Ave N Minneapolis MN 55443",
    "addr:housenumber":"3901",
    "addr:postcode":"55443",
    "addr:street":"85Th Ave N",
    "iso:country":"US",
    "sg:address":"3901 85th Ave N",
    "sg:city":"Minneapolis",
    "sg:classifiers":[
        {
            "category":"Shopping",
            "subcategory":"Stationery & Office Supplies",
            "type":"Retail Goods"
        }
    ],
    "sg:phone":"+1 763 569 0984",
    "sg:postcode":"55443",
    "sg:province":"MN",
    "sg:tags":[
        "room",
        "shipping"
    ],
    "sg:website":"http://www.centralcontainer.com",
    "wof:name":"Central Container Corporation",
    "wof:placetype":"venue"
},
  "geometry": {"coordinates":[-93.330894,45.108804],"type":"Point"}
}