{
  "type": "Feature",
  "properties": {
    "addr:full":"14928 62nd Ave N Osseo MN 55311",
    "addr:housenumber":"14928",
    "addr:postcode":"55311",
    "addr:street":"62Nd Ave N",
    "iso:country":"US",
    "sg:address":"14928 62nd Ave N",
    "sg:city":"Osseo",
    "sg:classifiers":[
        {
            "category":"Banks & Credit Unions",
            "subcategory":"Bank",
            "type":"Services"
        }
    ],
    "sg:phone":"+1 763 559 5598",
    "sg:postcode":"55311",
    "sg:province":"MN",
    "sg:tags":[
        "broker",
        "mortgage"
    ],
    "wof:name":"Real Estate Mortgage Network",
    "wof:placetype":"venue"
},
  "geometry": {"coordinates":[-93.468971,45.066716],"type":"Point"}
}