{
  "type": "Feature",
  "properties": {
    "addr:full":"19176 Mill Dr Fergus Falls MN 56537",
    "addr:housenumber":"19176",
    "addr:postcode":"56537",
    "addr:street":"Mill Dr",
    "iso:country":"US",
    "sg:address":"19176 Mill Dr",
    "sg:city":"Fergus Falls",
    "sg:classifiers":[
        {
            "category":"Manufacturing",
            "subcategory":"Tools & Machinery",
            "type":"Manufacturing & Wholesale Goods"
        }
    ],
    "sg:phone":"+1 218 589 8671",
    "sg:postcode":"56537",
    "sg:province":"MN",
    "sg:tags":[
        "power",
        "mfg"
    ],
    "wof:name":"Kens Saw Shop",
    "wof:placetype":"venue"
},
  "geometry": {"coordinates":[-95.95625200000001,46.239184],"type":"Point"}
}