{
  "type": "Feature",
  "properties": {
    "iso:country":"US",
    "sg:address":"12673 Cable Ave",
    "sg:city":"Glencoe",
    "sg:phone":"+1 320 238 2477",
    "sg:postcode":"55336",
    "sg:province":"MN",
    "sg:tags":[
        "beef",
        "farm",
        "corn",
        "soybean",
        "cattle",
        "feedlot"
    ],
    "wof:name":"Ronald Engelmann",
    "wof:placetype":"venue"
},
  "geometry": {"coordinates":[-94.07115899999999,44.793211],"type":"Point"}
}