{
  "type": "Feature",
  "properties": {
    "iso:country":"US",
    "sg:address":"610 Washington Ave SE",
    "sg:city":"Minneapolis",
    "sg:classifiers":[
        {
            "category":"Fast Food",
            "type":"Food & Drink"
        },
        {
            "category":"Restaurant",
            "type":"Food & Drink"
        }
    ],
    "sg:phone":"+1 612 331 9041",
    "sg:postcode":"55414",
    "sg:province":"MN",
    "sg:tags":[
        "style",
        "chinese",
        "family",
        "asian",
        "pan",
        "take"
    ],
    "sg:website":"www.villagewok.com",
    "wof:name":"Village Wok",
    "wof:placetype":"venue"
},
  "geometry": {"coordinates":[-93.230003,44.973499],"type":"Point"}
}