{
  "type": "Feature",
  "properties": {
    "iso:country":"US",
    "sg:address":"2345 Rice St",
    "sg:city":"Saint Paul",
    "sg:classifiers":[
        {
            "category":"Wholesale",
            "subcategory":"Metals & Minerals",
            "type":"Manufacturing & Wholesale Goods"
        }
    ],
    "sg:phone":"+1 651 490 0122",
    "sg:postcode":"55113",
    "sg:province":"MN",
    "sg:tags":[
        "center"
    ],
    "wof:name":"Steel Sales Corp",
    "wof:placetype":"venue"
},
  "geometry": {"coordinates":[-93.106061,45.011354],"type":"Point"}
}