{
  "type": "Feature",
  "properties": {
    "iso:country":"US",
    "sg:address":"1111 2nd St S",
    "sg:city":"Waite Park",
    "sg:classifiers":[
        {
            "category":"Home & Garden",
            "subcategory":"Home Furnishings",
            "type":"Retail Goods"
        }
    ],
    "sg:phone":"+1 320 252 1440",
    "sg:postcode":"56387",
    "sg:province":"MN",
    "sg:tags":[
        "lighting",
        "fixture"
    ],
    "sg:website":"www.lightsonfirst.com",
    "wof:name":"Lights On First",
    "wof:placetype":"venue"
},
  "geometry": {"coordinates":[-94.23161,45.549619],"type":"Point"}
}