{
  "type": "Feature",
  "properties": {
    "iso:country":"US",
    "sg:address":"1900 E 86th St",
    "sg:city":"Minneapolis",
    "sg:classifiers":[
        {
            "category":"Professional",
            "type":"Services"
        }
    ],
    "sg:phone":"+1 952 853 9930",
    "sg:postcode":"55425",
    "sg:province":"MN",
    "wof:name":"Perfect Deal LLC",
    "wof:placetype":"venue"
},
  "geometry": {"coordinates":[-93.24350699999999,44.847956],"type":"Point"}
}