{
  "type": "Feature",
  "properties": {
    "iso:country":"US",
    "sg:address":"1394 Jackson St",
    "sg:city":"Saint Paul",
    "sg:classifiers":[
        {
            "category":"Professional",
            "type":"Services"
        }
    ],
    "sg:phone":"+1 651 488 1670",
    "sg:postcode":"55117",
    "sg:province":"MN",
    "wof:name":"Lee Lorpao",
    "wof:placetype":"venue"
},
  "geometry": {"coordinates":[-93.096339,44.982801],"type":"Point"}
}