{
  "type": "Feature",
  "properties": {
    "addr:full":"8100 34th Ave S Minneapolis MN 55425",
    "addr:housenumber":"8100",
    "addr:postcode":"55425",
    "addr:street":"34Th Ave S",
    "iso:country":"US",
    "sg:address":"8100 34th Ave S",
    "sg:city":"Minneapolis",
    "sg:classifiers":[
        {
            "category":"Insurance",
            "subcategory":"Health Insurance",
            "type":"Services"
        }
    ],
    "sg:phone":"+1 952 883 6000",
    "sg:postcode":"55425",
    "sg:province":"MN",
    "sg:tags":[
        "medical",
        "plan"
    ],
    "wof:name":"Healthpartners Res Foundation",
    "wof:placetype":"venue"
},
  "geometry": {"coordinates":[-93.223125,44.85667],"type":"Point"}
}