{
  "type": "Feature",
  "properties": {
    "addr:full":"6155 337th St Stacy MN 55079",
    "addr:housenumber":"6155",
    "addr:postcode":"55079",
    "addr:street":"337Th St",
    "iso:country":"US",
    "sg:address":"6155 337th St",
    "sg:city":"Stacy",
    "sg:classifiers":[
        {
            "category":"Building & Trades",
            "subcategory":"Construction",
            "type":"Services"
        }
    ],
    "sg:phone":"+1 651 462 8176",
    "sg:postcode":"55079",
    "sg:province":"MN",
    "sg:tags":[
        "new",
        "maintenance"
    ],
    "wof:name":"Total Home Plus",
    "wof:placetype":"venue"
},
  "geometry": {"coordinates":[-92.98195,45.436241],"type":"Point"}
}