{
  "type": "Feature",
  "properties": {
    "addr:full":"281 Central Ave E Saint Michael MN 55376",
    "addr:housenumber":"281",
    "addr:postcode":"55376",
    "addr:street":"Central Ave E Saint Michael",
    "iso:country":"US",
    "sg:address":"281 Central Ave E",
    "sg:city":"Saint Michael",
    "sg:classifiers":[
        {
            "category":"Restaurant",
            "type":"Food & Drink"
        },
        {
            "category":"Ice Cream",
            "type":"Food & Drink"
        }
    ],
    "sg:menulink":"http://www.allmenus.com/mn/st-michael/167928-dairy-queen/menu/",
    "sg:phone":"+1 763 497 5254",
    "sg:postcode":"55376",
    "sg:province":"MN",
    "sg:tags":[
        "burger",
        "american",
        "ice",
        "cream"
    ],
    "wof:name":"Dairy Queen",
    "wof:placetype":"venue"
},
  "geometry": {"coordinates":[-93.66050300000001,45.210085],"type":"Point"}
}