{
  "type": "Feature",
  "properties": {
    "iso:country":"US",
    "sg:address":"6440 Park Trail Rd",
    "sg:city":"Hamel",
    "sg:classifiers":[
        {
            "category":"Building & Trades",
            "subcategory":"Construction",
            "type":"Services"
        }
    ],
    "sg:phone":"+1 763 478 9493",
    "sg:postcode":"55340",
    "sg:province":"MN",
    "sg:tags":[
        "floor",
        "laying",
        "contractor"
    ],
    "wof:name":"Omatt",
    "wof:placetype":"venue"
},
  "geometry": {"coordinates":[-93.53834000000001,45.071036],"type":"Point"}
}