{
  "type": "Feature",
  "properties": {
    "addr:full":"3427 Central Ave NE Minneapolis MN 55418",
    "addr:housenumber":"3427",
    "addr:postcode":"55418",
    "addr:street":"Central Ave Ne",
    "iso:country":"US",
    "sg:address":"3427 Central Ave NE",
    "sg:city":"Minneapolis",
    "sg:classifiers":[
        {
            "category":"Social Services",
            "subcategory":"Job Training",
            "type":"Services"
        },
        {
            "category":"Health Services",
            "subcategory":"Clinic",
            "type":"Services"
        }
    ],
    "sg:phone":"+1 612 788 3333",
    "sg:postcode":"55418",
    "sg:province":"MN",
    "sg:tags":[
        "medical",
        "nursing",
        "homes-skilled",
        "facility"
    ],
    "wof:name":"Bywood East Health Care-Resident Line",
    "wof:placetype":"venue"
},
  "geometry": {"coordinates":[-93.247288,45.029661],"type":"Point"}
}