{
  "type": "Feature",
  "properties": {
    "iso:country":"US",
    "sg:address":"1105 Pioneer Rd",
    "sg:city":"Red Wing",
    "sg:classifiers":[
        {
            "category":"Building & Trades",
            "subcategory":"Construction",
            "type":"Services"
        }
    ],
    "sg:phone":"+1 651 388 8729",
    "sg:postcode":"55066",
    "sg:province":"MN",
    "sg:tags":[
        "residential"
    ],
    "wof:name":"Rigelman Fairbanks Constr",
    "wof:placetype":"venue"
},
  "geometry": {"coordinates":[-92.540178,44.542961],"type":"Point"}
}