{
  "type": "Feature",
  "properties": {
    "addr:full":"14324 Stewart Ln Hopkins MN 55345",
    "addr:housenumber":"14324",
    "addr:postcode":"55345",
    "addr:street":"Stewart Ln",
    "iso:country":"US",
    "sg:address":"14324 Stewart Ln",
    "sg:city":"Hopkins",
    "sg:classifiers":[
        {
            "category":"Building & Trades",
            "subcategory":"Construction",
            "type":"Services"
        }
    ],
    "sg:phone":"+1 952 908 0540",
    "sg:postcode":"55345",
    "sg:province":"MN",
    "sg:tags":[
        "general",
        "contractor"
    ],
    "wof:name":"Luloff Inc",
    "wof:placetype":"venue"
},
  "geometry": {"coordinates":[-93.46517799999999,44.903774],"type":"Point"}
}