{
  "type": "Feature",
  "properties": {
    "iso:country":"US",
    "sg:address":"107 Chestnut St E",
    "sg:city":"Stillwater",
    "sg:classifiers":[
        {
            "category":"Government",
            "subcategory":"Office",
            "type":"Public Place"
        }
    ],
    "sg:phone":"+1 651 297 4452",
    "sg:postcode":"55082",
    "sg:province":"MN",
    "sg:tags":[
        "state",
        "security"
    ],
    "wof:name":"National Guard Recruiting Ofc",
    "wof:placetype":"venue"
},
  "geometry": {"coordinates":[-92.807188,45.055434],"type":"Point"}
}