{
  "type": "Feature",
  "properties": {
    "addr:full":"38681 Branch Ave North Branch MN 55056",
    "addr:housenumber":"38681",
    "addr:postcode":"55056",
    "addr:street":"Branch Ave",
    "iso:country":"US",
    "sg:address":"38681 Branch Ave",
    "sg:city":"North Branch",
    "sg:classifiers":[
        {
            "category":"Restaurant",
            "type":"Food & Drink"
        }
    ],
    "sg:phone":"+1 651 237 0271",
    "sg:postcode":"55056",
    "sg:province":"MN",
    "wof:name":"Denny's",
    "wof:placetype":"venue"
},
  "geometry": {"coordinates":[-92.98168699999999,45.510301],"type":"Point"}
}