{
  "type": "Feature",
  "properties": {
    "iso:country":"US",
    "sg:address":"38681 Branch Ave",
    "sg:city":"North Branch",
    "sg:classifiers":[
        {
            "category":"Restaurant",
            "type":"Food & Drink"
        }
    ],
    "sg:phone":"+1 651 237 0271",
    "sg:postcode":"55056",
    "sg:province":"MN",
    "wof:name":"Denny's",
    "wof:placetype":"venue"
},
  "geometry": {"coordinates":[-92.98168699999999,45.510301],"type":"Point"}
}