{
  "type": "Feature",
  "properties": {
    "addr:full":"2175 Bronson Dr Saint Paul MN 55112",
    "addr:housenumber":"2175",
    "addr:postcode":"55112",
    "addr:street":"Bronson Dr",
    "iso:country":"US",
    "sg:address":"2175 Bronson Dr",
    "sg:city":"Saint Paul",
    "sg:classifiers":[
        {
            "category":"Building & Trades",
            "subcategory":"Landscaping Services",
            "type":"Services"
        }
    ],
    "sg:phone":"+1 763 784 8081",
    "sg:postcode":"55112",
    "sg:province":"MN",
    "wof:name":"Bacs Tree Stump Grinding",
    "wof:placetype":"venue"
},
  "geometry": {"coordinates":[-93.192775,45.104505],"type":"Point"}
}