{
  "type": "Feature",
  "properties": {
    "addr:full":"555 18th Ave SW Cambridge MN 55008",
    "addr:housenumber":"555",
    "addr:postcode":"55008",
    "addr:street":"18Th Ave Sw",
    "iso:country":"US",
    "sg:address":"555 18th Ave SW",
    "sg:city":"Cambridge",
    "sg:classifiers":[
        {
            "category":"Government",
            "subcategory":"Office",
            "type":"Public Place"
        }
    ],
    "sg:phone":"+1 763 689 1644",
    "sg:postcode":"55008",
    "sg:province":"MN",
    "sg:tags":[
        "county",
        "taxation"
    ],
    "wof:name":"Isanti County Auditor",
    "wof:placetype":"venue"
},
  "geometry": {"coordinates":[-93.23142799999999,45.557026],"type":"Point"}
}