{
  "type": "Feature",
  "properties": {
    "iso:country":"US",
    "sg:address":"4950 Penn Ave N",
    "sg:city":"Minneapolis",
    "sg:classifiers":[
        {
            "category":"Local Transit",
            "type":"Transportation"
        }
    ],
    "sg:phone":"+1 763 561 0407",
    "sg:postcode":"55430",
    "sg:province":"MN",
    "sg:tags":[
        "passenger"
    ],
    "wof:name":"All Day & Night Limosuine",
    "wof:placetype":"venue"
},
  "geometry": {"coordinates":[-93.309181,45.044972],"type":"Point"}
}