{
  "type": "Feature",
  "properties": {
    "iso:country":"US",
    "sg:address":"41330 100th St",
    "sg:city":"Waseca",
    "sg:phone":"+1 507 835 3851",
    "sg:postcode":"56093",
    "sg:province":"MN",
    "sg:tags":[
        "beef",
        "farm",
        "corn",
        "soybean",
        "cattle",
        "feedlot"
    ],
    "wof:name":"Thomas Slechta",
    "wof:placetype":"venue"
},
  "geometry": {"coordinates":[-93.56736600000001,44.149629],"type":"Point"}
}