{
  "type": "Feature",
  "properties": {
    "addr:full":"1546 Como Ave St Paul MN 55108",
    "addr:housenumber":"1546",
    "addr:postcode":"55108",
    "addr:street":"Como Ave",
    "iso:country":"US",
    "sg:address":"1546 Como Ave",
    "sg:city":"St Paul",
    "sg:classifiers":[
        {
            "category":"Food & Beverages",
            "subcategory":"Groceries & Convenience Stores",
            "type":"Retail Goods"
        }
    ],
    "sg:phone":"+1 651 646 6181",
    "sg:postcode":"55108",
    "sg:province":"MN",
    "sg:tags":[
        "grocer"
    ],
    "wof:name":"Shanghai Market",
    "wof:placetype":"venue"
},
  "geometry": {"coordinates":[-93.16707100000001,44.977306],"type":"Point"}
}