{
  "type": "Feature",
  "properties": {
    "addr:full":"1609 16th Ave NW Willmar MN 56201",
    "addr:housenumber":"1609",
    "addr:postcode":"56201",
    "addr:street":"16Th Ave Nw",
    "iso:country":"US",
    "sg:address":"1609 16th Ave NW",
    "sg:city":"Willmar",
    "sg:classifiers":[
        {
            "category":"Utilities",
            "subcategory":"Water",
            "type":"Services"
        }
    ],
    "sg:phone":"+1 320 235 0452",
    "sg:postcode":"56201",
    "sg:province":"MN",
    "sg:tags":[
        "pump",
        "well",
        "drilling",
        "contractor"
    ],
    "wof:name":"Marcus Water Well Company Inc",
    "wof:placetype":"venue"
},
  "geometry": {"coordinates":[-95.06672399999999,45.140146],"type":"Point"}
}