{
  "type": "Feature",
  "properties": {
    "iso:country":"US",
    "sg:address":"4332 Shady Oak Rd",
    "sg:city":"Hopkins",
    "sg:classifiers":[
        {
            "category":"Building & Trades",
            "subcategory":"Construction",
            "type":"Services"
        },
        {
            "category":"Home & Garden",
            "subcategory":"Furniture",
            "type":"Retail Goods"
        }
    ],
    "sg:phone":"+1 952 933 4933",
    "sg:postcode":"55343",
    "sg:province":"MN",
    "sg:tags":[
        "cabinet",
        "carpentry",
        "contractor"
    ],
    "wof:name":"B C Kitchens Inc",
    "wof:placetype":"venue"
},
  "geometry": {"coordinates":[-93.426918,44.924668],"type":"Point"}
}