{
  "type": "Feature",
  "properties": {
    "iso:country":"US",
    "sg:address":"18730 Vega Dr",
    "sg:city":"Anoka",
    "sg:classifiers":[
        {
            "category":"Professional",
            "type":"Services"
        }
    ],
    "sg:phone":"+1 763 213 0585",
    "sg:postcode":"55303",
    "sg:province":"MN",
    "wof:name":"Nate Moats",
    "wof:placetype":"venue"
},
  "geometry": {"coordinates":[-93.40785700000001,45.310781],"type":"Point"}
}