{
  "type": "Feature",
  "properties": {
    "iso:country":"US",
    "sg:address":"3957 Van Buren St NE",
    "sg:city":"Minneapolis",
    "sg:classifiers":[
        {
            "category":"Transit Center",
            "subcategory":"Freight",
            "type":"Transportation"
        },
        {
            "category":"Freight",
            "type":"Transportation"
        }
    ],
    "sg:phone":"+1 763 432 6425",
    "sg:postcode":"55421",
    "sg:province":"MN",
    "sg:tags":[
        "local",
        "trucking-motor",
        "trucking"
    ],
    "wof:name":"Bromaghin Trucking",
    "wof:placetype":"venue"
},
  "geometry": {"coordinates":[-93.24861199999999,45.040236],"type":"Point"}
}