{
  "type": "Feature",
  "properties": {
    "addr:full":"5100 Edina Industrial Blvd Minneapolis MN 55439",
    "addr:housenumber":"5100",
    "addr:postcode":"55439",
    "addr:street":"Edina Industrial Blvd",
    "iso:country":"US",
    "sg:address":"5100 Edina Industrial Blvd",
    "sg:city":"Minneapolis",
    "sg:classifiers":[
        {
            "category":"Professional",
            "subcategory":"Business Services",
            "type":"Services"
        }
    ],
    "sg:phone":"+1 952 746 2007",
    "sg:postcode":"55439",
    "sg:province":"MN",
    "wof:name":"Engler Skogmo Intr Design LLC",
    "wof:placetype":"venue"
},
  "geometry": {"coordinates":[-93.35278599999999,44.864219],"type":"Point"}
}