{
  "type": "Feature",
  "properties": {
    "iso:country":"US",
    "sg:address":"10 S Minnesota Ave",
    "sg:city":"Oronoco",
    "sg:classifiers":[
        {
            "category":"Government",
            "subcategory":"Post Office",
            "type":"Public Place"
        }
    ],
    "sg:phone":"+1 507 367 4932",
    "sg:postcode":"55960",
    "sg:province":"MN",
    "wof:name":"US Post Office",
    "wof:placetype":"venue"
},
  "geometry": {"coordinates":[-92.53468599999999,44.163578],"type":"Point"}
}