{
  "type": "Feature",
  "properties": {
    "addr:full":"221 Winona Street NE Chatfield MN 55923",
    "addr:housenumber":"221",
    "addr:postcode":"55923",
    "addr:street":"Winona Street Ne",
    "iso:country":"US",
    "sg:address":"221 Winona Street NE",
    "sg:city":"Chatfield",
    "sg:classifiers":[
        {
            "category":"Manufacturing",
            "subcategory":"Wood Products",
            "type":"Manufacturing & Wholesale Goods"
        },
        {
            "category":"Building & Trades",
            "subcategory":"Construction",
            "type":"Services"
        }
    ],
    "sg:phone":"+1 507 273 7728",
    "sg:postcode":"55923",
    "sg:province":"MN",
    "sg:tags":[
        "woodworking",
        "handyman",
        "carpenter"
    ],
    "wof:name":"Andrew Allen Construction LLC.",
    "wof:placetype":"venue"
},
  "geometry": {"coordinates":[-92.190842,43.85022],"type":"Point"}
}