{
  "type": "Feature",
  "properties": {
    "addr:full":"105 Forest Ave S Northfield MN 55019",
    "addr:housenumber":"105",
    "addr:postcode":"55019",
    "addr:street":"Forest Ave S",
    "iso:country":"US",
    "sg:address":"105 Forest Ave S",
    "sg:city":"Northfield",
    "sg:classifiers":[
        {
            "category":"Insurance",
            "subcategory":"Insurance Agent",
            "type":"Services"
        }
    ],
    "sg:phone":"+1 507 663 0066",
    "sg:postcode":"55019",
    "sg:province":"MN",
    "wof:name":"Country Insurance & Fincl Svcs",
    "wof:placetype":"venue"
},
  "geometry": {"coordinates":[-93.21024,44.429689],"type":"Point"}
}