{
  "type": "Feature",
  "properties": {
    "addr:full":"626 Main St N Cambridge MN 55008",
    "addr:housenumber":"626",
    "addr:postcode":"55008",
    "addr:street":"Main St N",
    "iso:country":"US",
    "sg:address":"626 Main St N",
    "sg:city":"Cambridge",
    "sg:classifiers":[
        {
            "category":"Education",
            "subcategory":"School",
            "type":"Public Place"
        }
    ],
    "sg:phone":"+1 763 552 8770",
    "sg:postcode":"55008",
    "sg:province":"MN",
    "wof:name":"Oakland Area Learning Ctr",
    "wof:placetype":"venue"
},
  "geometry": {"coordinates":[-93.21955199999999,45.579113],"type":"Point"}
}