{
  "type": "Feature",
  "properties": {
    "addr:full":"10745 Woodwatch Cir Eden Prairie MN 55347",
    "addr:housenumber":"10745",
    "addr:postcode":"55347",
    "addr:street":"Woodwatch Cir",
    "iso:country":"US",
    "sg:address":"10745 Woodwatch Cir",
    "sg:city":"Eden Prairie",
    "sg:classifiers":[
        {
            "category":"Professional",
            "type":"Services"
        }
    ],
    "sg:phone":"+1 952 942 0282",
    "sg:postcode":"55347",
    "sg:province":"MN",
    "wof:name":"Value Rite Real Estate Svcs",
    "wof:placetype":"venue"
},
  "geometry": {"coordinates":[-93.413839,44.84113],"type":"Point"}
}