{
  "type": "Feature",
  "properties": {
    "iso:country":"US",
    "sg:address":"2930 Douglas Dr N Apt 313",
    "sg:city":"Minneapolis",
    "sg:classifiers":[
        {
            "category":"Manufacturing",
            "subcategory":"Petroleum Products",
            "type":"Manufacturing & Wholesale Goods"
        }
    ],
    "sg:phone":"+1 763 545 4106",
    "sg:postcode":"55422",
    "sg:province":"MN",
    "sg:tags":[
        "contract"
    ],
    "wof:name":"Hmw Mfg. Rep.",
    "wof:placetype":"venue"
},
  "geometry": {"coordinates":[-93.36009799999999,45.010191],"type":"Point"}
}