{
  "type": "Feature",
  "properties": {
    "addr:full":"1000 Benton Dr N Sauk Rapids MN 56379",
    "addr:housenumber":"1000",
    "addr:postcode":"56379",
    "addr:street":"Benton Dr N",
    "iso:country":"US",
    "sg:address":"1000 Benton Dr N",
    "sg:city":"Sauk Rapids",
    "sg:classifiers":[
        {
            "category":"Sports & Exercise",
            "subcategory":"Gym",
            "type":"Entertainment"
        }
    ],
    "sg:phone":"+1 320 202 2988",
    "sg:postcode":"56379",
    "sg:province":"MN",
    "sg:tags":[
        "fitness",
        "physical",
        "facility"
    ],
    "wof:name":"Curves For Women",
    "wof:placetype":"venue"
},
  "geometry": {"coordinates":[-94.177654,45.596571],"type":"Point"}
}