{
  "type": "Feature",
  "properties": {
    "addr:full":"3360 220th St W Farmington MN 55024",
    "addr:housenumber":"3360",
    "addr:postcode":"55024",
    "addr:street":"220Th St W",
    "iso:country":"US",
    "sg:address":"3360 220th St W",
    "sg:city":"Farmington",
    "sg:classifiers":[
        {
            "category":"Retail",
            "subcategory":"Auto Repair",
            "type":"Services"
        }
    ],
    "sg:phone":"+1 651 463 2281",
    "sg:postcode":"55024",
    "sg:province":"MN",
    "sg:tags":[
        "general"
    ],
    "wof:name":"Starr Automotive",
    "wof:placetype":"venue"
},
  "geometry": {"coordinates":[-93.127439,44.630573],"type":"Point"}
}