{
  "type": "Feature",
  "properties": {
    "iso:country":"US",
    "sg:address":"550 Fairview Ave N",
    "sg:city":"St Paul",
    "sg:classifiers":[
        {
            "category":"Shopping",
            "subcategory":"Hobbies, Toys, & Games",
            "type":"Retail Goods"
        }
    ],
    "sg:phone":"+1 651 379 0805",
    "sg:postcode":"55104",
    "sg:province":"MN",
    "sg:tags":[
        "model",
        "supply"
    ],
    "wof:name":"On Time Hobby Crafts & Prdctn",
    "wof:placetype":"venue"
},
  "geometry": {"coordinates":[-93.17712299999999,44.95744],"type":"Point"}
}