{
  "type": "Feature",
  "properties": {
    "addr:full":"77 Farrell St Saint Paul MN 55119",
    "addr:housenumber":"77",
    "addr:postcode":"55119",
    "addr:street":"Farrell St",
    "iso:country":"US",
    "sg:address":"77 Farrell St",
    "sg:city":"Saint Paul",
    "sg:classifiers":[
        {
            "category":"Professional",
            "subcategory":"Management & Consulting",
            "type":"Services"
        }
    ],
    "sg:phone":"+1 651 739 7717",
    "sg:postcode":"55119",
    "sg:province":"MN",
    "wof:name":"International Idea Institute",
    "wof:placetype":"venue"
},
  "geometry": {"coordinates":[-92.987818,44.942098],"type":"Point"}
}