{
  "type": "Feature",
  "properties": {
    "addr:full":"3630 Baker Rd Hopkins MN 55305",
    "addr:housenumber":"3630",
    "addr:postcode":"55305",
    "addr:street":"Baker Rd",
    "iso:country":"US",
    "sg:address":"3630 Baker Rd",
    "sg:city":"Hopkins",
    "sg:classifiers":[
        {
            "category":"Professional",
            "type":"Services"
        }
    ],
    "sg:phone":"+1 952 930 3753",
    "sg:postcode":"55305",
    "sg:province":"MN",
    "wof:name":"Weather Trends",
    "wof:placetype":"venue"
},
  "geometry": {"coordinates":[-93.447355,44.936657],"type":"Point"}
}