{
  "type": "Feature",
  "properties": {
    "iso:country":"US",
    "sg:address":"4200 Bloomington Ave",
    "sg:city":"Minneapolis",
    "sg:classifiers":[
        {
            "category":"Autos & Motor Vehicles",
            "subcategory":"Fuel & Gas Station",
            "type":"Retail Goods"
        },
        {
            "category":"Personal",
            "type":"Services"
        },
        {
            "category":"Retail",
            "subcategory":"Auto Repair",
            "type":"Services"
        }
    ],
    "sg:phone":"+1 612 823 6864",
    "sg:postcode":"55407",
    "sg:province":"MN",
    "sg:tags":[
        "towing"
    ],
    "wof:name":"Lanhart Auto Repair",
    "wof:placetype":"venue"
},
  "geometry": {"coordinates":[-93.25250200000001,44.9268],"type":"Point"}
}