{
  "type": "Feature",
  "properties": {
    "addr:full":"645 Tonkawa Rd Long Lake MN 55356",
    "addr:housenumber":"645",
    "addr:postcode":"55356",
    "addr:street":"Tonkawa Rd",
    "iso:country":"US",
    "sg:address":"645 Tonkawa Rd",
    "sg:city":"Long Lake",
    "sg:classifiers":[
        {
            "category":"Organizations",
            "subcategory":"Religious Organization",
            "type":"Services"
        }
    ],
    "sg:phone":"+1 952 471 8216",
    "sg:postcode":"55356",
    "sg:province":"MN",
    "sg:tags":[
        "synagogue"
    ],
    "wof:name":"Temple Israel",
    "wof:placetype":"venue"
},
  "geometry": {"coordinates":[-93.624121,44.967143],"type":"Point"}
}