{
  "type": "Feature",
  "properties": {
    "iso:country":"US",
    "sg:address":"4886 US Hwy 61",
    "sg:city":"St Paul",
    "sg:classifiers":[
        {
            "category":"Professional",
            "subcategory":"Computer Services",
            "type":"Services"
        }
    ],
    "sg:phone":"+1 651 407 1704",
    "sg:postcode":"55110",
    "sg:province":"MN",
    "sg:tags":[
        "internet"
    ],
    "wof:name":"Blue Earth Internet",
    "wof:placetype":"venue"
},
  "geometry": {"coordinates":[-93.008511,45.086975],"type":"Point"}
}