{
  "type": "Feature",
  "properties": {
    "addr:full":"15254 Curtis Ave NW Monticello MN 55362",
    "addr:housenumber":"15254",
    "addr:postcode":"55362",
    "addr:street":"Curtis Ave Nw",
    "iso:country":"US",
    "sg:address":"15254 Curtis Ave NW",
    "sg:city":"Monticello",
    "sg:classifiers":[
        {
            "category":"Professional",
            "subcategory":"Lawyer & Legal Services",
            "type":"Services"
        }
    ],
    "sg:phone":"+1 763 878 0099",
    "sg:postcode":"55362",
    "sg:province":"MN",
    "wof:name":"Paul Grunzweig Legal",
    "wof:placetype":"venue"
},
  "geometry": {"coordinates":[-93.94762299999999,45.369654],"type":"Point"}
}