{
  "type": "Feature",
  "properties": {
    "addr:full":"111 W Elm Ave Waseca MN 56093",
    "addr:housenumber":"111",
    "addr:postcode":"56093",
    "addr:street":"W Elm Ave",
    "iso:country":"US",
    "sg:address":"111 W Elm Ave",
    "sg:city":"Waseca",
    "sg:classifiers":[
        {
            "category":"Shopping",
            "type":"Retail Goods"
        }
    ],
    "sg:phone":"+1 507 823 7036",
    "sg:postcode":"56093",
    "sg:province":"MN",
    "sg:tags":[
        "hearing",
        "equipment",
        "supply",
        "impaired"
    ],
    "wof:name":"American Hearing Care Clinic",
    "wof:placetype":"venue"
},
  "geometry": {"coordinates":[-93.507971,44.077508],"type":"Point"}
}