{
  "type": "Feature",
  "properties": {
    "addr:full":"3250 Louisiana Ave S Minneapolis MN 55426",
    "addr:housenumber":"3250",
    "addr:postcode":"55426",
    "addr:street":"Louisiana Ave S",
    "iso:country":"US",
    "sg:address":"3250 Louisiana Ave S",
    "sg:city":"Minneapolis",
    "sg:classifiers":[
        {
            "category":"Building & Trades",
            "subcategory":"Landscaping Services",
            "type":"Services"
        }
    ],
    "sg:phone":"+1 612 889 7425",
    "sg:postcode":"55426",
    "sg:province":"MN",
    "sg:tags":[
        "tree",
        "stump",
        "grinding",
        "removal"
    ],
    "wof:name":"Richard Geis Tree Service",
    "wof:placetype":"venue"
},
  "geometry": {"coordinates":[-93.37097799999999,44.944866],"type":"Point"}
}