{
  "type": "Feature",
  "properties": {
    "addr:full":"101 7th St Wilmont MN 56185",
    "addr:housenumber":"101",
    "addr:postcode":"56185",
    "addr:street":"7Th St",
    "iso:country":"US",
    "sg:address":"101 7th St",
    "sg:city":"Wilmont",
    "sg:classifiers":[
        {
            "category":"Building & Trades",
            "subcategory":"Construction",
            "type":"Services"
        }
    ],
    "sg:phone":"+1 507 926 5101",
    "sg:postcode":"56185",
    "sg:province":"MN",
    "sg:tags":[
        "house"
    ],
    "wof:name":"Brian Lenz",
    "wof:placetype":"venue"
},
  "geometry": {"coordinates":[-95.82724399999999,43.760999],"type":"Point"}
}