{
  "type": "Feature",
  "properties": {
    "iso:country":"US",
    "sg:address":"9526 Foley Blvd",
    "sg:city":"Minneapolis",
    "sg:classifiers":[
        {
            "category":"Retail",
            "subcategory":"Repair Shop",
            "type":"Services"
        },
        {
            "category":"Manufacturing",
            "subcategory":"Tools & Machinery",
            "type":"Manufacturing & Wholesale Goods"
        }
    ],
    "sg:phone":"+1 763 780 0828",
    "sg:postcode":"55433",
    "sg:province":"MN",
    "sg:tags":[
        "industrial",
        "related",
        "mfg"
    ],
    "wof:name":"Specialty Machines",
    "wof:placetype":"venue"
},
  "geometry": {"coordinates":[-93.285689,45.142958],"type":"Point"}
}