{
  "type": "Feature",
  "properties": {
    "addr:full":"207 N Jamison Dr Ada MN 56510",
    "addr:housenumber":"207",
    "addr:postcode":"56510",
    "addr:street":"N Jamison Dr",
    "iso:country":"US",
    "sg:address":"207 N Jamison Dr",
    "sg:city":"Ada",
    "sg:classifiers":[
        {
            "category":"Social Services",
            "subcategory":"Adult Care",
            "type":"Services"
        }
    ],
    "sg:phone":"+1 218 784 2219",
    "sg:postcode":"56510",
    "sg:province":"MN",
    "sg:tags":[
        "residential"
    ],
    "wof:name":"REM North Star",
    "wof:placetype":"venue"
},
  "geometry": {"coordinates":[-96.521946,47.297826],"type":"Point"}
}