{
  "type": "Feature",
  "properties": {
    "addr:full":"8424 Passfield Turn Maple Grove MN 55311",
    "addr:housenumber":"8424",
    "addr:postcode":"55311",
    "addr:street":"Passfield Turn",
    "iso:country":"US",
    "sg:address":"8424 Passfield Turn",
    "sg:city":"Maple Grove",
    "sg:classifiers":[
        {
            "category":"Professional",
            "subcategory":"Management & Consulting",
            "type":"Services"
        }
    ],
    "sg:phone":"+1 763 494 8666",
    "sg:postcode":"55311",
    "sg:province":"MN",
    "sg:tags":[
        "marketing",
        "consultant"
    ],
    "wof:name":"By Design Marketing Resources",
    "wof:placetype":"venue"
},
  "geometry": {"coordinates":[-93.47452199999999,45.108068],"type":"Point"}
}