{
  "type": "Feature",
  "properties": {
    "addr:full":"1 N Minnesota St New Ulm MN 56073",
    "addr:housenumber":"1",
    "addr:postcode":"56073",
    "addr:street":"N Minnesota St",
    "iso:country":"US",
    "sg:address":"1 N Minnesota St",
    "sg:city":"New Ulm",
    "sg:classifiers":[
        {
            "category":"Professional",
            "type":"Services"
        }
    ],
    "sg:phone":"+1 507 354 8614",
    "sg:postcode":"56073",
    "sg:province":"MN",
    "sg:tags":[
        "establishment"
    ],
    "wof:name":"Jansan Enterprises Inc",
    "wof:placetype":"venue"
},
  "geometry": {"coordinates":[-94.45993199999999,44.314296],"type":"Point"}
}