{
  "type": "Feature",
  "properties": {
    "iso:country":"US",
    "sg:address":"13358 Grove Dr",
    "sg:city":"Maple Grove",
    "sg:classifiers":[
        {
            "category":"Retail",
            "subcategory":"Auto Repair",
            "type":"Services"
        }
    ],
    "sg:phone":"+1 763 494 3700",
    "sg:postcode":"55369",
    "sg:province":"MN",
    "sg:tags":[
        "automobile",
        "lubrication"
    ],
    "wof:name":"Maple Grove Xpress Lube",
    "wof:placetype":"venue"
},
  "geometry": {"coordinates":[-93.450048,45.103442],"type":"Point"}
}