{
  "type": "Feature",
  "properties": {
    "addr:full":"821 East Ave Red Wing MN 55066",
    "addr:housenumber":"821",
    "addr:postcode":"55066",
    "addr:street":"East Ave",
    "iso:country":"US",
    "sg:address":"821 East Ave",
    "sg:city":"Red Wing",
    "sg:classifiers":[
        {
            "category":"Manufacturing",
            "subcategory":"Jewelry",
            "type":"Manufacturing & Wholesale Goods"
        }
    ],
    "sg:phone":"+1 651 388 8610",
    "sg:postcode":"55066",
    "sg:province":"MN",
    "sg:tags":[
        "costume",
        "mfg"
    ],
    "wof:name":"Beautiful Things By Laurel Lee",
    "wof:placetype":"venue"
},
  "geometry": {"coordinates":[-92.530756,44.559895],"type":"Point"}
}