{
  "type": "Feature",
  "properties": {
    "iso:country":"US",
    "sg:address":"119 Campbell St",
    "sg:city":"Parkers Prairie",
    "sg:classifiers":[
        {
            "category":"Retail",
            "subcategory":"Repair Shop",
            "type":"Services"
        }
    ],
    "sg:phone":"+1 218 338 6134",
    "sg:postcode":"56361",
    "sg:province":"MN",
    "wof:name":"Hollatz Radio & TV",
    "wof:placetype":"venue"
},
  "geometry": {"coordinates":[-95.324834,46.143903],"type":"Point"}
}