{
  "type": "Feature",
  "properties": {
    "iso:country":"US",
    "sg:address":"2321 Aldrich Ave S",
    "sg:city":"Minneapolis",
    "sg:classifiers":[
        {
            "category":"Building & Trades",
            "subcategory":"Construction",
            "type":"Services"
        }
    ],
    "sg:phone":"+1 612 623 0660",
    "sg:postcode":"55405",
    "sg:province":"MN",
    "sg:tags":[
        "stucco",
        "contractor"
    ],
    "wof:name":"Edward Donnelly Stucco Inc",
    "wof:placetype":"venue"
},
  "geometry": {"coordinates":[-93.289209,44.96021],"type":"Point"}
}