{
  "type": "Feature",
  "properties": {
    "iso:country":"US",
    "sg:address":"2916 140th Ave NE",
    "sg:city":"Anoka",
    "sg:classifiers":[
        {
            "category":"Building & Trades",
            "subcategory":"Electrical",
            "type":"Services"
        },
        {
            "category":"Wholesale",
            "subcategory":"Electrical",
            "type":"Manufacturing & Wholesale Goods"
        }
    ],
    "sg:phone":"+1 763 755 3039",
    "sg:postcode":"55304",
    "sg:province":"MN",
    "sg:tags":[
        "equipment",
        "alarm",
        "security",
        "burglar",
        "system"
    ],
    "wof:name":"Security Services Corp",
    "wof:placetype":"venue"
},
  "geometry": {"coordinates":[-93.195725,45.224199],"type":"Point"}
}