{
  "type": "Feature",
  "properties": {
    "iso:country":"US",
    "sg:address":"3418 Lake Ave",
    "sg:city":"New Prague",
    "sg:classifiers":[
        {
            "category":"Food & Beverages",
            "subcategory":"Specialty",
            "type":"Retail Goods"
        }
    ],
    "sg:phone":"+1 952 758 3892",
    "sg:postcode":"56071",
    "sg:province":"MN",
    "sg:tags":[
        "water",
        "bulk",
        "company"
    ],
    "wof:name":"Water Needs",
    "wof:placetype":"venue"
},
  "geometry": {"coordinates":[-93.50418000000001,44.538901],"type":"Point"}
}