{
  "type": "Feature",
  "properties": {
    "addr:full":"6631 Penn Ave S Minneapolis MN 55423",
    "addr:housenumber":"6631",
    "addr:postcode":"55423",
    "addr:street":"Penn Ave S",
    "iso:country":"US",
    "sg:address":"6631 Penn Ave S",
    "sg:city":"Minneapolis",
    "sg:classifiers":[
        {
            "category":"Personal",
            "subcategory":"Beauty Salon",
            "type":"Services"
        }
    ],
    "sg:phone":"+1 612 866 3686",
    "sg:postcode":"55423",
    "sg:province":"MN",
    "wof:name":"Ngoc Hair Salon",
    "wof:placetype":"venue"
},
  "geometry": {"coordinates":[-93.30856300000001,44.882919],"type":"Point"}
}