{
  "type": "Feature",
  "properties": {
    "iso:country":"US",
    "sg:address":"1378 N Albert St",
    "sg:city":"St Paul",
    "sg:classifiers":[
        {
            "category":"Manufacturing",
            "subcategory":"Printing",
            "type":"Manufacturing & Wholesale Goods"
        }
    ],
    "sg:phone":"+1 651 646 7429",
    "sg:postcode":"55108",
    "sg:province":"MN",
    "sg:tags":[
        "publisher",
        "music"
    ],
    "sg:website":"www.surrealtor.com",
    "wof:name":"Transit Gloria Media",
    "wof:placetype":"venue"
},
  "geometry": {"coordinates":[-93.159177,44.983377],"type":"Point"}
}