{
  "type": "Feature",
  "properties": {
    "iso:country":"US",
    "sg:address":"42043 60th St",
    "sg:city":"Blue Earth",
    "sg:classifiers":[
        {
            "category":"Shopping",
            "subcategory":"Gifts & Souvenirs",
            "type":"Retail Goods"
        }
    ],
    "sg:phone":"+1 507 526 3558",
    "sg:postcode":"56013",
    "sg:province":"MN",
    "wof:name":"Quiet Mouse",
    "wof:placetype":"venue"
},
  "geometry": {"coordinates":[-94.02369400000001,43.572376],"type":"Point"}
}