{
  "type": "Feature",
  "properties": {
    "iso:country":"US",
    "sg:address":"1619 Girard Ave N",
    "sg:city":"Minneapolis",
    "sg:classifiers":[
        {
            "category":"Organizations",
            "subcategory":"Religious Organization",
            "type":"Services"
        }
    ],
    "sg:phone":"+1 612 529 8215",
    "sg:postcode":"55411",
    "sg:province":"MN",
    "wof:name":"Visittion Mnstary N Mnneapolis",
    "wof:placetype":"venue"
},
  "geometry": {"coordinates":[-93.297257,44.996122],"type":"Point"}
}