{
  "type": "Feature",
  "properties": {
    "iso:country":"US",
    "sg:address":"61173 320th St",
    "sg:city":"Litchfield",
    "sg:phone":"+1 320 693 6684",
    "sg:postcode":"55355",
    "sg:province":"MN",
    "sg:tags":[
        "farm",
        "corn",
        "soybean"
    ],
    "wof:name":"Ralph Boyer",
    "wof:placetype":"venue"
},
  "geometry": {"coordinates":[-94.541788,45.210541],"type":"Point"}
}