{
  "type": "Feature",
  "properties": {
    "addr:full":"12701 Chowen Ave S Ste 104 Burnsville MN 55337",
    "addr:housenumber":"12701",
    "addr:postcode":"55337",
    "addr:street":"Chowen Ave S Ste 104",
    "iso:country":"US",
    "sg:address":"12701 Chowen Ave S Ste 104",
    "sg:city":"Burnsville",
    "sg:classifiers":[
        {
            "category":"Recreation",
            "subcategory":"Boat Charter",
            "type":"Entertainment"
        }
    ],
    "sg:phone":"+1 952 882 1443",
    "sg:postcode":"55337",
    "sg:province":"MN",
    "sg:tags":[
        "boating"
    ],
    "sg:website":"www.bottomsupmarinerepair.com",
    "wof:name":"Bottoms Up Marine Repair",
    "wof:placetype":"venue"
},
  "geometry": {"coordinates":[-93.32579800000001,44.775002],"type":"Point"}
}