{
  "type": "Feature",
  "properties": {
    "addr:full":"5112 William Ave Minneapolis MN 55436",
    "addr:housenumber":"5112",
    "addr:postcode":"55436",
    "addr:street":"William Ave",
    "iso:country":"US",
    "sg:address":"5112 William Ave",
    "sg:city":"Minneapolis",
    "sg:classifiers":[
        {
            "category":"Social Services",
            "subcategory":"Child Care",
            "type":"Services"
        }
    ],
    "sg:phone":"+1 952 922 7760",
    "sg:postcode":"55436",
    "sg:province":"MN",
    "sg:tags":[
        "daycare",
        "provider"
    ],
    "wof:name":"Geraldine Friesz",
    "wof:placetype":"venue"
},
  "geometry": {"coordinates":[-93.357692,44.909903],"type":"Point"}
}