{
  "type": "Feature",
  "properties": {
    "addr:full":"1530 Rowe Ave Worthington MN 56187",
    "addr:housenumber":"1530",
    "addr:postcode":"56187",
    "addr:street":"Rowe Ave",
    "iso:country":"US",
    "sg:address":"1530 Rowe Ave",
    "sg:city":"Worthington",
    "sg:classifiers":[
        {
            "category":"Health Services",
            "subcategory":"Health Practitioner",
            "type":"Services"
        }
    ],
    "sg:phone":"+1 507 372 2232",
    "sg:postcode":"56187",
    "sg:province":"MN",
    "sg:tags":[
        "therapist",
        "physical"
    ],
    "sg:website":"www.prairierehab.com",
    "wof:name":"Prairie Rhabilitation Svcs LLC",
    "wof:placetype":"venue"
},
  "geometry": {"coordinates":[-95.61193799999999,43.632137],"type":"Point"}
}