{
  "type": "Feature",
  "properties": {
    "addr:full":"38873 14th Ave North Branch MN 55056",
    "addr:housenumber":"38873",
    "addr:postcode":"55056",
    "addr:street":"14Th Ave",
    "iso:country":"US",
    "sg:address":"38873 14th Ave",
    "sg:city":"North Branch",
    "sg:classifiers":[
        {
            "category":"Shopping",
            "subcategory":"Florist",
            "type":"Retail Goods"
        }
    ],
    "sg:phone":"+1 651 674 8666",
    "sg:postcode":"55056",
    "sg:province":"MN",
    "wof:name":"Flower Shop",
    "wof:placetype":"venue"
},
  "geometry": {"coordinates":[-92.990878,45.511729],"type":"Point"}
}