{
  "type": "Feature",
  "properties": {
    "addr:full":"4915 W 35th St Ste 105 Minneapolis MN 55416",
    "addr:housenumber":"4915",
    "addr:postcode":"55416",
    "addr:street":"W 35Th St Ste 105",
    "iso:country":"US",
    "sg:address":"4915 W 35th St Ste 105",
    "sg:city":"Minneapolis",
    "sg:classifiers":[
        {
            "category":"Professional",
            "subcategory":"Employment Agencies",
            "type":"Services"
        },
        {
            "category":"Community Center",
            "subcategory":"Social",
            "type":"Public Place"
        }
    ],
    "sg:phone":"+1 952 935 6163",
    "sg:postcode":"55416",
    "sg:province":"MN",
    "sg:tags":[
        "jacking",
        "trenching",
        "contractor",
        "mud",
        "underground"
    ],
    "wof:name":"Red Pederson Utilities Inc",
    "wof:placetype":"venue"
},
  "geometry": {"coordinates":[-93.34157399999999,44.940811],"type":"Point"}
}