{
  "type": "Feature",
  "properties": {
    "iso:country":"US",
    "sg:address":"1506 12th St N",
    "sg:city":"Princeton",
    "sg:classifiers":[
        {
            "category":"Freight",
            "type":"Transportation"
        }
    ],
    "sg:phone":"+1 763 389 0539",
    "sg:postcode":"55371",
    "sg:province":"MN",
    "sg:tags":[
        "warehouse",
        "public"
    ],
    "wof:name":"Princeton Warehouse & Leasing",
    "wof:placetype":"venue"
},
  "geometry": {"coordinates":[-93.59795099999999,45.584896],"type":"Point"}
}