{
  "type": "Feature",
  "properties": {
    "addr:full":"104 2nd St Bluffton MN 56581",
    "addr:housenumber":"104",
    "addr:postcode":"56581",
    "addr:street":"2Nd St",
    "iso:country":"US",
    "sg:address":"104 2nd St",
    "sg:city":"Bluffton",
    "sg:classifiers":[
        {
            "category":"Government",
            "subcategory":"Post Office",
            "type":"Public Place"
        }
    ],
    "sg:phone":"+1 218 385 3365",
    "sg:postcode":"56581",
    "sg:province":"MN",
    "wof:name":"US Post Office",
    "wof:placetype":"venue"
},
  "geometry": {"coordinates":[-96.819147,47.456298],"type":"Point"}
}