{
  "type": "Feature",
  "properties": {
    "addr:full":"907 Hopkins Ctr Hopkins MN 55343",
    "addr:housenumber":"907",
    "addr:postcode":"55343",
    "addr:street":"Hopkins Ctr",
    "iso:country":"US",
    "sg:address":"907 Hopkins Ctr",
    "sg:city":"Hopkins",
    "sg:classifiers":[
        {
            "category":"Building & Trades",
            "subcategory":"Construction",
            "type":"Services"
        },
        {
            "category":"Home & Garden",
            "subcategory":"Carpets & Floor Coverings",
            "type":"Retail Goods"
        }
    ],
    "sg:phone":"+1 800 394 3064",
    "sg:postcode":"55343",
    "sg:province":"MN",
    "sg:tags":[
        "material",
        "tile-contractors",
        "rug",
        "flooring",
        "contractor"
    ],
    "sg:website":"http://www.filitrac.com/Click.aspx?tid=BDEDC5D5EF8BAE3541B5938870DA3DDECE60F60FEE115906&FiliAff=15016&sid=99202&utm_source=YellowPages&utm_medium=ppc&utm_campaign=national&utm_term=55343",
    "wof:name":"Hopkins Carpet One Floor & Home",
    "wof:placetype":"venue"
},
  "geometry": {"coordinates":[-93.41140300000001,44.925415],"type":"Point"}
}