{
  "type": "Feature",
  "properties": {
    "addr:full":"9609 Girard Ave S Bloomington MN 55431",
    "addr:housenumber":"9609",
    "addr:postcode":"55431",
    "addr:street":"Girard Ave S",
    "iso:country":"US",
    "sg:address":"9609 Girard Ave S",
    "sg:city":"Bloomington",
    "sg:classifiers":[
        {
            "category":"Manufacturing",
            "subcategory":"Metals",
            "type":"Manufacturing & Wholesale Goods"
        },
        {
            "category":"Wholesale",
            "subcategory":"Chemicals & Plastics",
            "type":"Manufacturing & Wholesale Goods"
        }
    ],
    "sg:phone":"+1 952 888 2847",
    "sg:postcode":"55431",
    "sg:province":"MN",
    "sg:tags":[
        "item",
        "food",
        "utensil",
        "cooking",
        "to",
        "health",
        "care"
    ],
    "sg:website":"www.kendrick-johnson.com",
    "wof:name":"Kendrick Johnson & Associates",
    "wof:placetype":"venue"
},
  "geometry": {"coordinates":[-93.297408,44.828265],"type":"Point"}
}