{
  "type": "Feature",
  "properties": {
    "addr:full":"13120 Pioneer Trl Eden Prairie MN 55347",
    "addr:housenumber":"13120",
    "addr:postcode":"55347",
    "addr:street":"Pioneer Trl",
    "iso:country":"US",
    "sg:address":"13120 Pioneer Trl",
    "sg:city":"Eden Prairie",
    "sg:classifiers":[
        {
            "category":"Manufacturing",
            "subcategory":"Tools & Machinery",
            "type":"Manufacturing & Wholesale Goods"
        }
    ],
    "sg:phone":"+1 952 941 0465",
    "sg:postcode":"55347",
    "sg:province":"MN",
    "sg:tags":[
        "machine",
        "shop"
    ],
    "wof:name":"General Machining Inc",
    "wof:placetype":"venue"
},
  "geometry": {"coordinates":[-93.44416699999999,44.827435],"type":"Point"}
}