{
  "type": "Feature",
  "properties": {
    "addr:full":"23688 Birch Rd Rogers MN 55374",
    "addr:housenumber":"23688",
    "addr:postcode":"55374",
    "addr:street":"Birch Rd",
    "iso:country":"US",
    "sg:address":"23688 Birch Rd",
    "sg:city":"Rogers",
    "sg:classifiers":[
        {
            "category":"Manufacturing",
            "subcategory":"Tools & Machinery",
            "type":"Manufacturing & Wholesale Goods"
        }
    ],
    "sg:phone":"+1 763 428 3779",
    "sg:postcode":"55374",
    "sg:province":"MN",
    "sg:tags":[
        "equipment",
        "system",
        "automation"
    ],
    "wof:name":"Hiwin Technologies",
    "wof:placetype":"venue"
},
  "geometry": {"coordinates":[-93.582733,45.199704],"type":"Point"}
}