{
  "type": "Feature",
  "properties": {
    "iso:country":"US",
    "sg:address":"3001 Island View Dr",
    "sg:city":"Mound",
    "sg:classifiers":[
        {
            "category":"Marine",
            "type":"Transportation"
        }
    ],
    "sg:phone":"+1 952 472 5061",
    "sg:postcode":"55364",
    "sg:province":"MN",
    "sg:tags":[
        "surveyor"
    ],
    "sg:website":"www.schmidtmarine.com",
    "wof:name":"Marine Specialties",
    "wof:placetype":"venue"
},
  "geometry": {"coordinates":[-93.636798,44.924753],"type":"Point"}
}