{
  "type": "Feature",
  "properties": {
    "iso:country":"US",
    "sg:address":"275 Penn Ave N",
    "sg:city":"Minneapolis",
    "sg:classifiers":[
        {
            "category":"Health Services",
            "subcategory":"Nursing And Care Facility",
            "type":"Services"
        }
    ],
    "sg:phone":"+1 612 377 4723",
    "sg:postcode":"55405",
    "sg:province":"MN",
    "sg:tags":[
        "residential",
        "skilled",
        "convalescent",
        "home"
    ],
    "wof:name":"Bryn Mawr Health Care Center",
    "wof:placetype":"venue"
},
  "geometry": {"coordinates":[-93.30840600000001,44.979059],"type":"Point"}
}