{
  "type": "Feature",
  "properties": {
    "iso:country":"US",
    "sg:address":"18 Main St N",
    "sg:city":"Winnebago",
    "sg:classifiers":[
        {
            "category":"Professional",
            "type":"Services"
        }
    ],
    "sg:phone":"+1 507 893 3113",
    "sg:postcode":"56098",
    "sg:province":"MN",
    "sg:tags":[
        "establishment"
    ],
    "wof:name":"Minnesota Natural Div",
    "wof:placetype":"venue"
},
  "geometry": {"coordinates":[-94.165696,43.768659],"type":"Point"}
}