{
  "type": "Feature",
  "properties": {
    "iso:country":"US",
    "sg:address":"8671 Quarry Ridge Ln",
    "sg:city":"Saint Paul",
    "sg:classifiers":[
        {
            "category":"Professional",
            "subcategory":"Accounting & Tax Preparation",
            "type":"Services"
        }
    ],
    "sg:phone":"+1 651 644 4490",
    "sg:postcode":"55125",
    "sg:province":"MN",
    "wof:name":"Gates Bookkeeping Title Works",
    "wof:placetype":"venue"
},
  "geometry": {"coordinates":[-92.93155,44.914491],"type":"Point"}
}