{
  "type": "Feature",
  "properties": {
    "addr:full":"26947 Nature Rd Royalton MN 56373",
    "addr:housenumber":"26947",
    "addr:postcode":"56373",
    "addr:street":"Nature Rd",
    "iso:country":"US",
    "sg:address":"26947 Nature Rd",
    "sg:city":"Royalton",
    "sg:classifiers":[
        {
            "category":"Restaurant",
            "type":"Food & Drink"
        }
    ],
    "sg:phone":"+1 320 393 2594",
    "sg:postcode":"56373",
    "sg:province":"MN",
    "sg:tags":[
        "eating"
    ],
    "wof:name":"Lanners Beef Farm",
    "wof:placetype":"venue"
},
  "geometry": {"coordinates":[-94.09266,45.832623],"type":"Point"}
}