{
  "type": "Feature",
  "properties": {
    "addr:full":"1624 Main Ave Moorhead MN 56560",
    "addr:housenumber":"1624",
    "addr:postcode":"56560",
    "addr:street":"Main Ave",
    "iso:country":"US",
    "sg:address":"1624 Main Ave",
    "sg:city":"Moorhead",
    "sg:classifiers":[
        {
            "category":"Manufacturing",
            "subcategory":"Printing",
            "type":"Manufacturing & Wholesale Goods"
        }
    ],
    "sg:phone":"+1 218 236 1115",
    "sg:postcode":"56560",
    "sg:province":"MN",
    "sg:tags":[
        "printer"
    ],
    "wof:name":"Copy KAT Printing",
    "wof:placetype":"venue"
},
  "geometry": {"coordinates":[-96.754189,46.873749],"type":"Point"}
}