{
  "type": "Feature",
  "properties": {
    "addr:full":"1125 S Frontage Rd Hastings MN 55033",
    "addr:housenumber":"1125",
    "addr:postcode":"55033",
    "addr:street":"S Frontage Rd",
    "iso:country":"US",
    "sg:address":"1125 S Frontage Rd",
    "sg:city":"Hastings",
    "sg:classifiers":[
        {
            "category":"Banks & Credit Unions",
            "subcategory":"Investment Brokerage",
            "type":"Services"
        }
    ],
    "sg:phone":"+1 651 437 7245",
    "sg:postcode":"55033",
    "sg:province":"MN",
    "sg:tags":[
        "consultant",
        "planning",
        "financial"
    ],
    "wof:name":"Hausman Tausignant Investment",
    "wof:placetype":"venue"
},
  "geometry": {"coordinates":[-92.87127099999999,44.738029],"type":"Point"}
}