{
  "type": "Feature",
  "properties": {
    "addr:full":"4920 173rd Ave NE #2 Andover MN 55304",
    "addr:housenumber":"4920",
    "addr:postcode":"55304",
    "addr:street":"173Rd Ave Ne # 2",
    "iso:country":"US",
    "sg:address":"4920 173rd Ave NE #2",
    "sg:city":"Andover",
    "sg:classifiers":[
        {
            "category":"Building & Trades",
            "subcategory":"Cleaning & Sanitation",
            "type":"Services"
        },
        {
            "category":"Building & Trades",
            "subcategory":"Construction",
            "type":"Services"
        },
        {
            "category":"Building & Trades",
            "subcategory":"Electrical",
            "type":"Services"
        }
    ],
    "sg:phone":"+1 763 515 7347",
    "sg:postcode":"55304",
    "sg:province":"MN",
    "sg:tags":[
        "system",
        "contractor",
        "furnaces-heating",
        "furnaces-repairing",
        "air conditioning"
    ],
    "sg:website":"http://www.jsmithhvac.com/",
    "wof:name":"Joel Smith Heating & Air Conditioning",
    "wof:placetype":"venue"
},
  "geometry": {"coordinates":[-93.143857,45.283259],"type":"Point"}
}