{
  "type": "Feature",
  "properties": {
    "addr:full":"8354 Walden Rd Brainerd MN 56401",
    "addr:housenumber":"8354",
    "addr:postcode":"56401",
    "addr:street":"Walden Rd",
    "iso:country":"US",
    "sg:address":"8354 Walden Rd",
    "sg:city":"Brainerd",
    "sg:classifiers":[
        {
            "category":"Building & Trades",
            "subcategory":"Plumbing",
            "type":"Services"
        }
    ],
    "sg:phone":"+1 218 855 0155",
    "sg:postcode":"56401",
    "sg:province":"MN",
    "sg:tags":[
        "contractor"
    ],
    "wof:name":"Lakes Area Plumbing",
    "wof:placetype":"venue"
},
  "geometry": {"coordinates":[-94.22529400000001,46.462264],"type":"Point"}
}