{
  "type": "Feature",
  "properties": {
    "iso:country":"US",
    "sg:address":"14 Red River Ave N",
    "sg:city":"Cold Spring",
    "sg:classifiers":[
        {
            "category":"Government",
            "subcategory":"Post Office",
            "type":"Public Place"
        }
    ],
    "sg:phone":"+1 320 685 8204",
    "sg:postcode":"56320",
    "sg:province":"MN",
    "wof:name":"US Post Office",
    "wof:placetype":"venue"
},
  "geometry": {"coordinates":[-94.428884,45.456755],"type":"Point"}
}