{
  "type": "Feature",
  "properties": {
    "addr:full":"5555 W 78th St Minneapolis MN 55439",
    "addr:housenumber":"5555",
    "addr:postcode":"55439",
    "addr:street":"W 78Th St",
    "iso:country":"US",
    "sg:address":"5555 W 78th St",
    "sg:city":"Minneapolis",
    "sg:classifiers":[
        {
            "category":"Parking",
            "type":"Transportation"
        },
        {
            "category":"Parking",
            "subcategory":"Garage",
            "type":"Transportation"
        }
    ],
    "sg:phone":"+1 952 826 7000",
    "sg:postcode":"55439",
    "sg:province":"MN",
    "sg:tags":[
        "attendant",
        "lot"
    ],
    "wof:name":"Metro Airports Comm Lindbergh",
    "wof:placetype":"venue"
},
  "geometry": {"coordinates":[-93.363907,44.863152],"type":"Point"}
}