{
  "type": "Feature",
  "properties": {
    "iso:country":"US",
    "sg:address":"814 Mainstreet",
    "sg:city":"Hopkins",
    "sg:classifiers":[
        {
            "category":"Bars & Pubs",
            "type":"Food & Drink"
        },
        {
            "category":"Restaurant",
            "type":"Food & Drink"
        }
    ],
    "sg:phone":"+1 952 938 2400",
    "sg:postcode":"55343",
    "sg:province":"MN",
    "sg:tags":[
        "brew",
        "grill"
    ],
    "wof:name":"Mainstreet Bar & Grill",
    "wof:placetype":"venue"
},
  "geometry": {"coordinates":[-93.41030600000001,44.92438],"type":"Point"}
}