{
  "type": "Feature",
  "properties": {
    "addr:full":"202 3rd Ave NW Pierz MN 56364",
    "addr:housenumber":"202",
    "addr:postcode":"56364",
    "addr:street":"3Rd Ave Nw",
    "iso:country":"US",
    "sg:address":"202 3rd Ave NW",
    "sg:city":"Pierz",
    "sg:classifiers":[
        {
            "category":"Wholesale",
            "subcategory":"Farm Supplies",
            "type":"Manufacturing & Wholesale Goods"
        }
    ],
    "sg:phone":"+1 320 468 6493",
    "sg:postcode":"56364",
    "sg:province":"MN",
    "sg:tags":[
        "feed",
        "grinding"
    ],
    "wof:name":"Pierz Farmers Mill Inc",
    "wof:placetype":"venue"
},
  "geometry": {"coordinates":[-94.106613,45.983282],"type":"Point"}
}