{
  "type": "Feature",
  "properties": {
    "iso:country":"US",
    "sg:address":"311 1st Ave NE",
    "sg:city":"Osseo",
    "sg:classifiers":[
        {
            "category":"Building & Trades",
            "subcategory":"Construction",
            "type":"Services"
        }
    ],
    "sg:phone":"+1 763 315 1076",
    "sg:postcode":"55369",
    "sg:province":"MN",
    "sg:tags":[
        "roofing",
        "industrial",
        "contractors-commercial",
        "contractor"
    ],
    "wof:name":"Anron Tool Inc",
    "wof:placetype":"venue"
},
  "geometry": {"coordinates":[-93.400617,45.119351],"type":"Point"}
}