{
  "type": "Feature",
  "properties": {
    "addr:full":"205 Manitoba St Spicer MN 56288",
    "addr:housenumber":"205",
    "addr:postcode":"56288",
    "addr:street":"Manitoba St",
    "iso:country":"US",
    "sg:address":"205 Manitoba St",
    "sg:city":"Spicer",
    "sg:classifiers":[
        {
            "category":"Personal",
            "subcategory":"Beauty Salon",
            "type":"Services"
        }
    ],
    "sg:phone":"+1 320 796 6843",
    "sg:postcode":"56288",
    "sg:province":"MN",
    "wof:name":"Styles Unlimited",
    "wof:placetype":"venue"
},
  "geometry": {"coordinates":[-94.94082899999999,45.235951],"type":"Point"}
}