{
  "type": "Feature",
  "properties": {
    "iso:country":"US",
    "sg:address":"4428 Dupont Ave S",
    "sg:city":"Minneapolis",
    "sg:classifiers":[
        {
            "category":"Building & Trades",
            "subcategory":"Construction",
            "type":"Services"
        }
    ],
    "sg:phone":"+1 612 824 4981",
    "sg:postcode":"55419",
    "sg:province":"MN",
    "sg:tags":[
        "marking",
        "maintenance",
        "parking"
    ],
    "wof:name":"College Parking Resurfacing",
    "wof:placetype":"venue"
},
  "geometry": {"coordinates":[-93.293476,44.921903],"type":"Point"}
}