{
  "type": "Feature",
  "properties": {
    "iso:country":"US",
    "sg:address":"46154 186th Avenue Ct",
    "sg:city":"Zumbrota",
    "sg:classifiers":[
        {
            "category":"Building & Trades",
            "subcategory":"Construction",
            "type":"Services"
        }
    ],
    "sg:phone":"+1 507 732 7759",
    "sg:postcode":"55992",
    "sg:province":"MN",
    "sg:tags":[
        "contractor"
    ],
    "wof:name":"Buck Construction",
    "wof:placetype":"venue"
},
  "geometry": {"coordinates":[-92.659192,44.279435],"type":"Point"}
}