{
  "type": "Feature",
  "properties": {
    "iso:country":"US",
    "sg:address":"1100 7th Ave",
    "sg:city":"Two Harbors",
    "sg:classifiers":[
        {
            "category":"Autos & Motor Vehicles",
            "subcategory":"Automobile Sales",
            "type":"Retail Goods"
        }
    ],
    "sg:phone":"+1 218 727 6658",
    "sg:postcode":"55616",
    "sg:province":"MN",
    "wof:name":"Sonjun Superstore",
    "wof:placetype":"venue"
},
  "geometry": {"coordinates":[-91.679982,47.025517],"type":"Point"}
}