{
  "type": "Feature",
  "properties": {
    "iso:country":"US",
    "sg:address":"5114 38th Ave S",
    "sg:city":"Minneapolis",
    "sg:classifiers":[
        {
            "category":"Shopping",
            "subcategory":"Pets & Pet Supplies",
            "type":"Retail Goods"
        },
        {
            "category":"Retail",
            "subcategory":"Veterinary Services",
            "type":"Services"
        }
    ],
    "sg:phone":"+1 612 724 4225",
    "sg:postcode":"55417",
    "sg:province":"MN",
    "sg:tags":[
        "specialty"
    ],
    "wof:name":"Kathys Kat Kare At Home Pet",
    "wof:placetype":"venue"
},
  "geometry": {"coordinates":[-93.217731,44.910546],"type":"Point"}
}