{
  "type": "Feature",
  "properties": {
    "iso:country":"US",
    "sg:address":"110 Cheshire Ln",
    "sg:city":"Hopkins",
    "sg:classifiers":[
        {
            "category":"Health Services",
            "subcategory":"Doctor",
            "type":"Services"
        }
    ],
    "sg:phone":"+1 952 475 3787",
    "sg:postcode":"55305",
    "sg:province":"MN",
    "sg:tags":[
        "medical"
    ],
    "wof:name":"Whiting Consultative Eyecare",
    "wof:placetype":"venue"
},
  "geometry": {"coordinates":[-93.459216,44.975618],"type":"Point"}
}