{
  "type": "Feature",
  "properties": {
    "iso:country":"US",
    "sg:address":"5259 Douglas Dr N",
    "sg:city":"Minneapolis",
    "sg:classifiers":[
        {
            "category":"Retail",
            "subcategory":"Auto Repair",
            "type":"Services"
        }
    ],
    "sg:phone":"+1 612 225 2650",
    "sg:postcode":"55429",
    "sg:province":"MN",
    "sg:tags":[
        "exhaust",
        "car",
        "system",
        "equipment",
        "brake",
        "automobile",
        "muffler",
        "performance",
        "sport",
        "racing"
    ],
    "sg:website":"http://www.tomtracker.com/redirect.cfm?bID=4837&hID=111353",
    "wof:name":"Meineke Car Care Center",
    "wof:placetype":"venue"
},
  "geometry": {"coordinates":[-93.360243,45.048693],"type":"Point"}
}