{
  "type": "Feature",
  "properties": {
    "iso:country":"US",
    "sg:address":"20 Jay Cooke Rd",
    "sg:city":"Esko",
    "sg:classifiers":[
        {
            "category":"Manufacturing",
            "subcategory":"Wood Products",
            "type":"Manufacturing & Wholesale Goods"
        }
    ],
    "sg:phone":"+1 218 879 7080",
    "sg:postcode":"55733",
    "sg:province":"MN",
    "sg:tags":[
        "pallet",
        "skid"
    ],
    "wof:name":"Savanna Pallets Inc",
    "wof:placetype":"venue"
},
  "geometry": {"coordinates":[-92.344449,46.705188],"type":"Point"}
}