{
  "type": "Feature",
  "properties": {
    "iso:country":"US",
    "sg:address":"44533 215th Ave",
    "sg:city":"Staples",
    "sg:classifiers":[
        {
            "category":"Farming",
            "subcategory":"Dairy Farm",
            "type":"Manufacturing & Wholesale Goods"
        }
    ],
    "sg:phone":"+1 218 924 2693",
    "sg:postcode":"56479",
    "sg:province":"MN",
    "wof:name":"Alfred Korfe",
    "wof:placetype":"venue"
},
  "geometry": {"coordinates":[-94.916274,46.271438],"type":"Point"}
}