{
  "type": "Feature",
  "properties": {
    "iso:country":"US",
    "sg:address":"1508 University Ave W",
    "sg:city":"St Paul",
    "sg:classifiers":[
        {
            "category":"Recreation",
            "type":"Entertainment"
        }
    ],
    "sg:phone":"+1 651 644 4665",
    "sg:postcode":"55104",
    "sg:province":"MN",
    "sg:tags":[
        "bingo",
        "game"
    ],
    "wof:name":"Midway Bingo Ctr",
    "wof:placetype":"venue"
},
  "geometry": {"coordinates":[-93.164897,44.955608],"type":"Point"}
}