{
  "type": "Feature",
  "properties": {
    "iso:country":"US",
    "sg:address":"905 Highland Ave",
    "sg:city":"Northfield",
    "sg:classifiers":[
        {
            "category":"Retail",
            "subcategory":"Repair Shop",
            "type":"Services"
        }
    ],
    "sg:phone":"+1 507 650 0379",
    "sg:postcode":"55057",
    "sg:province":"MN",
    "sg:tags":[
        "repairing",
        "piano",
        "refinishing"
    ],
    "wof:name":"Bill Van Loh Music Service",
    "wof:placetype":"venue"
},
  "geometry": {"coordinates":[-93.17505,44.465117],"type":"Point"}
}