{
  "type": "Feature",
  "properties": {
    "addr:full":"988 Seminole Ave Saint Paul MN 55118",
    "addr:housenumber":"988",
    "addr:postcode":"55118",
    "addr:street":"Seminole Ave",
    "iso:country":"US",
    "sg:address":"988 Seminole Ave",
    "sg:city":"Saint Paul",
    "sg:classifiers":[
        {
            "category":"Building & Trades",
            "subcategory":"Cleaning & Sanitation",
            "type":"Services"
        }
    ],
    "sg:phone":"+1 651 455 7481",
    "sg:postcode":"55118",
    "sg:province":"MN",
    "sg:tags":[
        "maintenance"
    ],
    "wof:name":"CJ Maintenance",
    "wof:placetype":"venue"
},
  "geometry": {"coordinates":[-93.099616,44.917371],"type":"Point"}
}