{
  "type": "Feature",
  "properties": {
    "addr:full":"149 Highview Rd Rockford MN 55373",
    "addr:housenumber":"149",
    "addr:postcode":"55373",
    "addr:street":"Highview Rd",
    "iso:country":"US",
    "sg:address":"149 Highview Rd",
    "sg:city":"Rockford",
    "sg:classifiers":[
        {
            "category":"Retail",
            "subcategory":"Repair Shop",
            "type":"Services"
        }
    ],
    "sg:phone":"+1 763 477 4148",
    "sg:postcode":"55373",
    "sg:province":"MN",
    "wof:name":"Elite Lock & Key",
    "wof:placetype":"venue"
},
  "geometry": {"coordinates":[-93.74558,45.082928],"type":"Point"}
}