{
  "type": "Feature",
  "properties": {
    "addr:full":"3112 6th Ave E Hibbing MN 55746",
    "addr:housenumber":"3112",
    "addr:postcode":"55746",
    "addr:street":"6Th Ave E Hibbing",
    "iso:country":"US",
    "sg:address":"3112 6th Ave E",
    "sg:city":"Hibbing",
    "sg:classifiers":[
        {
            "category":"Social Services",
            "type":"Services"
        }
    ],
    "sg:phone":"+1 218 262 5082",
    "sg:postcode":"55746",
    "sg:province":"MN",
    "sg:tags":[
        "organization",
        "welfare"
    ],
    "wof:name":"HRA Family Investment Ctr",
    "wof:placetype":"venue"
},
  "geometry": {"coordinates":[-92.934997,47.41409],"type":"Point"}
}