{
  "type": "Feature",
  "properties": {
    "iso:country":"US",
    "sg:address":"224 E Hennepin Ave",
    "sg:city":"Minneapolis",
    "sg:classifiers":[
        {
            "category":"Tea Room",
            "subcategory":"None",
            "type":"Food & Drink"
        },
        {
            "category":"Coffee & Tea",
            "type":"Food & Drink"
        },
        {
            "category":"Restaurant",
            "type":"Food & Drink"
        },
        {
            "category":"Food & Beverages",
            "subcategory":"Liquor & Beverages",
            "type":"Retail Goods"
        }
    ],
    "sg:phone":"+1 612 617 0292",
    "sg:postcode":"55414",
    "sg:province":"MN",
    "sg:tags":[
        "shop",
        "style",
        "family",
        "espresso",
        "lunch",
        "brunch",
        "breakfast"
    ],
    "wof:name":"Taraccino Coffee",
    "wof:placetype":"venue"
},
  "geometry": {"coordinates":[-93.257465,44.987608],"type":"Point"}
}