{
  "type": "Feature",
  "properties": {
    "iso:country":"US",
    "sg:address":"311 N Cedar Ave",
    "sg:city":"Owatonna",
    "sg:classifiers":[
        {
            "category":"Real Estate",
            "subcategory":"Real Estate Operator",
            "type":"Services"
        }
    ],
    "sg:phone":"+1 507 625 7207",
    "sg:postcode":"55060",
    "sg:province":"MN",
    "sg:tags":[
        "building",
        "apartment"
    ],
    "wof:name":"Greenbriar Apts",
    "wof:placetype":"venue"
},
  "geometry": {"coordinates":[-93.225909,44.08779],"type":"Point"}
}