{
  "type": "Feature",
  "properties": {
    "addr:full":"19891 230th Ave Greenbush MN 56726",
    "addr:housenumber":"19891",
    "addr:postcode":"56726",
    "addr:street":"230Th Ave",
    "iso:country":"US",
    "sg:address":"19891 230th Ave",
    "sg:city":"Greenbush",
    "sg:classifiers":[
        {
            "category":"Farming",
            "subcategory":"Livestock Farm",
            "type":"Manufacturing & Wholesale Goods"
        }
    ],
    "sg:phone":"+1 218 782 2325",
    "sg:postcode":"56726",
    "sg:province":"MN",
    "sg:tags":[
        "beef",
        "feedlot",
        "cattle"
    ],
    "wof:name":"Glen Hendrickson",
    "wof:placetype":"venue"
},
  "geometry": {"coordinates":[-96.103765,48.677361],"type":"Point"}
}