{
  "type": "Feature",
  "properties": {
    "addr:full":"907 Main St NW Elk River MN 55330",
    "addr:housenumber":"907",
    "addr:postcode":"55330",
    "addr:street":"Main St Nw",
    "iso:country":"US",
    "sg:address":"907 Main St NW",
    "sg:city":"Elk River",
    "sg:classifiers":[
        {
            "category":"Professional",
            "type":"Services"
        }
    ],
    "sg:phone":"+1 763 441 8363",
    "sg:postcode":"55330",
    "sg:province":"MN",
    "wof:name":"Minnesota Referral Network",
    "wof:placetype":"venue"
},
  "geometry": {"coordinates":[-93.55259100000001,45.312722],"type":"Point"}
}