{
  "type": "Feature",
  "properties": {
    "addr:full":"21600 Zodiac St NE Wyoming MN 55092",
    "addr:postcode":"21600;55092",
    "addr:street":"Zodiac St Ne",
    "iso:country":"US",
    "sg:address":"21600 Zodiac St NE",
    "sg:city":"Wyoming",
    "sg:classifiers":[
        {
            "category":"Travel",
            "subcategory":"Campground",
            "type":"Entertainment"
        }
    ],
    "sg:phone":"+1 651 462 5720",
    "sg:postcode":"55092",
    "sg:province":"MN",
    "sg:tags":[
        "camp"
    ],
    "wof:name":"Camp Ajawah",
    "wof:placetype":"venue"
},
  "geometry": {"coordinates":[-93.10264599999999,45.360188],"type":"Point"}
}