{
  "type": "Feature",
  "properties": {
    "iso:country":"US",
    "sg:address":"36 Snelling Ave S",
    "sg:city":"St Paul",
    "sg:classifiers":[
        {
            "category":"Social Services",
            "type":"Services"
        }
    ],
    "sg:phone":"+1 651 696 6882",
    "sg:postcode":"55105",
    "sg:province":"MN",
    "sg:tags":[
        "senior",
        "citizen"
    ],
    "sg:website":"www.elderberry.org",
    "wof:name":"Living At Home/Block Nurse Inc",
    "wof:placetype":"venue"
},
  "geometry": {"coordinates":[-93.166927,44.940803],"type":"Point"}
}