{
  "type": "Feature",
  "properties": {
    "iso:country":"US",
    "sg:address":"3638 181st Ave NW",
    "sg:city":"Anoka",
    "sg:classifiers":[
        {
            "category":"Professional",
            "subcategory":"Management & Consulting",
            "type":"Services"
        }
    ],
    "sg:phone":"+1 651 283 6969",
    "sg:postcode":"55304",
    "sg:province":"MN",
    "sg:tags":[
        "support",
        "facility"
    ],
    "wof:name":"Gigawhat",
    "wof:placetype":"venue"
},
  "geometry": {"coordinates":[-93.357955,45.298401],"type":"Point"}
}