{
  "type": "Feature",
  "properties": {
    "addr:full":"2070 Burnsville Ctr Burnsville MN 55306",
    "addr:postcode":"2070;55306",
    "iso:country":"US",
    "sg:address":"2070 Burnsville Ctr",
    "sg:city":"Burnsville",
    "sg:classifiers":[
        {
            "category":"Health Services",
            "subcategory":"Optometrist",
            "type":"Services"
        }
    ],
    "sg:phone":"+1 952 435 3686",
    "sg:postcode":"55306",
    "sg:province":"MN",
    "sg:website":"www.luxottica.com",
    "wof:name":"Luxottica Retail",
    "wof:placetype":"venue"
},
  "geometry": {"coordinates":[-93.29198599999999,44.745566],"type":"Point"}
}