{
  "type": "Feature",
  "properties": {
    "addr:full":"17883 255th Ave Sleepy Eye MN 56085",
    "addr:housenumber":"17883",
    "addr:postcode":"56085",
    "addr:street":"255Th Ave",
    "iso:country":"US",
    "sg:address":"17883 255th Ave",
    "sg:city":"Sleepy Eye",
    "sg:classifiers":[
        {
            "category":"Farming",
            "subcategory":"Dairy Farm",
            "type":"Manufacturing & Wholesale Goods"
        }
    ],
    "sg:phone":"+1 507 794 6603",
    "sg:postcode":"56085",
    "sg:province":"MN",
    "wof:name":"Charles Sellner",
    "wof:placetype":"venue"
},
  "geometry": {"coordinates":[-94.695036,44.210276],"type":"Point"}
}