{
  "type": "Feature",
  "properties": {
    "addr:full":"785 W Main St Caledonia MN 55921",
    "addr:housenumber":"785",
    "addr:postcode":"55921",
    "addr:street":"W Main St",
    "iso:country":"US",
    "sg:address":"785 W Main St",
    "sg:city":"Caledonia",
    "sg:classifiers":[
        {
            "category":"Utilities",
            "subcategory":"Natural Gas",
            "type":"Services"
        }
    ],
    "sg:phone":"+1 507 893 4856",
    "sg:postcode":"55921",
    "sg:province":"MN",
    "sg:tags":[
        "propane"
    ],
    "wof:name":"More's AG Center Inc",
    "wof:placetype":"venue"
},
  "geometry": {"coordinates":[-91.46673800000001,43.507851],"type":"Point"}
}