{
  "type": "Feature",
  "properties": {
    "iso:country":"US",
    "sg:address":"221 Central Ave",
    "sg:city":"Long Prairie",
    "sg:classifiers":[
        {
            "category":"Personal",
            "subcategory":"Beauty Salon",
            "type":"Services"
        }
    ],
    "sg:phone":"+1 320 732 2455",
    "sg:postcode":"56347",
    "sg:province":"MN",
    "sg:tags":[
        "shop"
    ],
    "wof:name":"D & J Stylists",
    "wof:placetype":"venue"
},
  "geometry": {"coordinates":[-94.862084,45.974068],"type":"Point"}
}