{
  "type": "Feature",
  "properties": {
    "iso:country":"US",
    "sg:address":"11220 Xeon St NW",
    "sg:city":"Minneapolis",
    "sg:classifiers":[
        {
            "category":"Transit Center",
            "subcategory":"Freight",
            "type":"Transportation"
        },
        {
            "category":"Freight",
            "type":"Transportation"
        }
    ],
    "sg:phone":"+1 763 767 3300",
    "sg:postcode":"55448",
    "sg:province":"MN",
    "sg:tags":[
        "trucking-motor",
        "trucking"
    ],
    "sg:website":"http://www.usfc.com",
    "wof:name":"Usfreightways",
    "wof:placetype":"venue"
},
  "geometry": {"coordinates":[-93.296927,45.173719],"type":"Point"}
}