{
  "type": "Feature",
  "properties": {
    "addr:full":"6501 Cambridge St Minneapolis MN 55426",
    "addr:housenumber":"6501",
    "addr:postcode":"55426",
    "addr:street":"Cambridge St",
    "iso:country":"US",
    "sg:address":"6501 Cambridge St",
    "sg:city":"Minneapolis",
    "sg:classifiers":[
        {
            "category":"Retail",
            "subcategory":"Car Wash",
            "type":"Services"
        }
    ],
    "sg:phone":"+1 952 938 2587",
    "sg:postcode":"55426",
    "sg:province":"MN",
    "wof:name":"Extreme Detail",
    "wof:placetype":"venue"
},
  "geometry": {"coordinates":[-93.362793,44.933226],"type":"Point"}
}