{
  "type": "Feature",
  "properties": {
    "iso:country":"US",
    "sg:address":"5575 Lower 182nd St W",
    "sg:city":"Farmington",
    "sg:classifiers":[
        {
            "category":"Communications",
            "type":"Services"
        }
    ],
    "sg:phone":"+1 651 460 4406",
    "sg:postcode":"55024",
    "sg:province":"MN",
    "sg:tags":[
        "communication"
    ],
    "wof:name":"J Rs Sky Way Communication",
    "wof:placetype":"venue"
},
  "geometry": {"coordinates":[-93.17764099999999,44.686405],"type":"Point"}
}