{
  "type": "Feature",
  "properties": {
    "iso:country":"US",
    "sg:address":"2011 1st Ave NE",
    "sg:city":"Austin",
    "sg:classifiers":[
        {
            "category":"Personal",
            "subcategory":"Beauty Salon",
            "type":"Services"
        }
    ],
    "sg:phone":"+1 507 437 4837",
    "sg:postcode":"55912",
    "sg:province":"MN",
    "sg:tags":[
        "shop"
    ],
    "wof:name":"Ruth Beauty Shop",
    "wof:placetype":"venue"
},
  "geometry": {"coordinates":[-92.93980500000001,43.667961],"type":"Point"}
}