{
  "type": "Feature",
  "properties": {
    "iso:country":"US",
    "sg:address":"3220 W Lake St",
    "sg:city":"Minneapolis",
    "sg:classifiers":[
        {
            "category":"Restaurant",
            "type":"Food & Drink"
        }
    ],
    "sg:phone":"+1 612 455 1250",
    "sg:postcode":"55416",
    "sg:province":"MN",
    "sg:tags":[
        "traditional",
        "american"
    ],
    "wof:name":"New Calhoun Grill",
    "wof:placetype":"venue"
},
  "geometry": {"coordinates":[-93.32128400000001,44.949357],"type":"Point"}
}