{
  "type": "Feature",
  "properties": {
    "addr:full":"920 2nd Ave S Minneapolis MN 55402",
    "addr:housenumber":"920",
    "addr:postcode":"55402",
    "addr:street":"2Nd Ave S",
    "iso:country":"US",
    "sg:address":"920 2nd Ave S",
    "sg:city":"Minneapolis",
    "sg:classifiers":[
        {
            "category":"Professional",
            "subcategory":"Accounting & Tax Preparation",
            "type":"Services"
        }
    ],
    "sg:phone":"+1 612 359 0678",
    "sg:postcode":"55402",
    "sg:province":"MN",
    "wof:name":"Melvin M Goldfein",
    "wof:placetype":"venue"
},
  "geometry": {"coordinates":[-93.27193699999999,44.973045],"type":"Point"}
}