{
  "type": "Feature",
  "properties": {
    "addr:full":"15041 Fillmore St NE Anoka MN 55304",
    "addr:housenumber":"15041",
    "addr:postcode":"55304",
    "addr:street":"Fillmore St Ne",
    "iso:country":"US",
    "sg:address":"15041 Fillmore St NE",
    "sg:city":"Anoka",
    "sg:classifiers":[
        {
            "category":"Education",
            "subcategory":"Special Training",
            "type":"Public Place"
        }
    ],
    "sg:phone":"+1 763 434 3809",
    "sg:postcode":"55304",
    "sg:province":"MN",
    "wof:name":"Toastmasters International",
    "wof:placetype":"venue"
},
  "geometry": {"coordinates":[-93.242574,45.243528],"type":"Point"}
}