{
  "type": "Feature",
  "properties": {
    "iso:country":"US",
    "sg:address":"990 Lone Oak Rd",
    "sg:city":"Eagan",
    "sg:classifiers":[
        {
            "category":"Freight",
            "type":"Transportation"
        },
        {
            "category":"Airline",
            "type":"Transportation"
        }
    ],
    "sg:phone":"+1 651 405 8257",
    "sg:postcode":"55121",
    "sg:province":"MN",
    "sg:tags":[
        "cargo",
        "air",
        "shipping",
        "transfer"
    ],
    "sg:website":"www.laf.lynden.com",
    "wof:name":"Lynden Air Freight Inc",
    "wof:placetype":"venue"
},
  "geometry": {"coordinates":[-93.13839400000001,44.847875],"type":"Point"}
}