{
  "type": "Feature",
  "properties": {
    "iso:country":"US",
    "sg:address":"206 Hwy 75 S",
    "sg:city":"Dumont",
    "sg:classifiers":[
        {
            "category":"Autos & Motor Vehicles",
            "subcategory":"Fuel & Gas Station",
            "type":"Retail Goods"
        }
    ],
    "sg:phone":"+1 320 563 8162",
    "sg:postcode":"56296",
    "sg:province":"MN",
    "sg:tags":[
        "oil"
    ],
    "wof:name":"Tri County Co-Op Assn",
    "wof:placetype":"venue"
},
  "geometry": {"coordinates":[-96.490279,45.802723],"type":"Point"}
}