{
  "type": "Feature",
  "properties": {
    "iso:country":"US",
    "sg:address":"796 120th St NE",
    "sg:city":"Monticello",
    "sg:classifiers":[
        {
            "category":"Professional",
            "subcategory":"Management & Consulting",
            "type":"Services"
        }
    ],
    "sg:phone":"+1 763 878 1513",
    "sg:postcode":"55362",
    "sg:province":"MN",
    "sg:tags":[
        "retail",
        "direct",
        "sales"
    ],
    "wof:name":"Beth Green",
    "wof:placetype":"venue"
},
  "geometry": {"coordinates":[-93.874652,45.325721],"type":"Point"}
}