{
  "type": "Feature",
  "properties": {
    "iso:country":"US",
    "sg:address":"108 Broadway E",
    "sg:city":"Little Falls",
    "sg:classifiers":[
        {
            "category":"Shopping",
            "subcategory":"Discount & Variety Stores",
            "type":"Retail Goods"
        }
    ],
    "sg:phone":"+1 320 632 3223",
    "sg:postcode":"56345",
    "sg:province":"MN",
    "wof:name":"Ron's Variety",
    "wof:placetype":"venue"
},
  "geometry": {"coordinates":[-94.36245,45.976349],"type":"Point"}
}