{
  "type": "Feature",
  "properties": {
    "iso:country":"US",
    "sg:address":"20229 Blue Lake Rd",
    "sg:city":"Emily",
    "sg:classifiers":[
        {
            "category":"Manufacturing",
            "subcategory":"Buildings",
            "type":"Manufacturing & Wholesale Goods"
        },
        {
            "category":"Building & Trades",
            "subcategory":"Construction",
            "type":"Services"
        }
    ],
    "sg:phone":"+1 218 763 3477",
    "sg:postcode":"56447",
    "sg:province":"MN",
    "sg:tags":[
        "home",
        "builder",
        "contractor"
    ],
    "wof:name":"Kenneth C Oftedahl",
    "wof:placetype":"venue"
},
  "geometry": {"coordinates":[-93.978673,46.778241],"type":"Point"}
}