{
  "type": "Feature",
  "properties": {
    "addr:full":"3004 Jamley Ave N Lake Elmo MN 55042",
    "addr:housenumber":"3004",
    "addr:postcode":"55042",
    "addr:street":"Jamley Ave N",
    "iso:country":"US",
    "sg:address":"3004 Jamley Ave N",
    "sg:city":"Lake Elmo",
    "sg:classifiers":[
        {
            "category":"Professional",
            "subcategory":"Business Services",
            "type":"Services"
        }
    ],
    "sg:phone":"+1 651 770 2245",
    "sg:postcode":"55042",
    "sg:province":"MN",
    "wof:name":"Accepted Bail Bonds",
    "wof:placetype":"venue"
},
  "geometry": {"coordinates":[-92.922854,44.992593],"type":"Point"}
}