{
  "type": "Feature",
  "properties": {
    "iso:country":"US",
    "sg:address":"8091 Bagley Ave",
    "sg:city":"Northfield",
    "sg:classifiers":[
        {
            "category":"Building & Trades",
            "subcategory":"Construction",
            "type":"Services"
        }
    ],
    "sg:phone":"+1 507 663 1294",
    "sg:postcode":"55057",
    "sg:province":"MN",
    "sg:tags":[
        "concrete",
        "contractor"
    ],
    "wof:name":"D & S Cement Co Inc",
    "wof:placetype":"venue"
},
  "geometry": {"coordinates":[-93.29621299999999,44.470483],"type":"Point"}
}