{
  "type": "Feature",
  "properties": {
    "addr:full":"46943 Jackson Rd Ottertail MN 56571",
    "addr:housenumber":"46943",
    "addr:postcode":"56571",
    "addr:street":"Jackson Rd",
    "iso:country":"US",
    "sg:address":"46943 Jackson Rd",
    "sg:city":"Ottertail",
    "sg:classifiers":[
        {
            "category":"Manufacturing",
            "subcategory":"Metals",
            "type":"Manufacturing & Wholesale Goods"
        }
    ],
    "sg:phone":"+1 218 367 2395",
    "sg:postcode":"56571",
    "sg:province":"MN",
    "sg:tags":[
        "screw",
        "nut",
        "bolt"
    ],
    "wof:name":"Bolt Norman",
    "wof:placetype":"venue"
},
  "geometry": {"coordinates":[-95.513852,46.474139],"type":"Point"}
}