{
  "type": "Feature",
  "properties": {
    "addr:full":"7656 Hampshire Ave N Minneapolis MN 55428",
    "addr:housenumber":"7656",
    "addr:postcode":"55428",
    "addr:street":"Hampshire Ave N",
    "iso:country":"US",
    "sg:address":"7656 Hampshire Ave N",
    "sg:city":"Minneapolis",
    "sg:classifiers":[
        {
            "category":"Social Services",
            "type":"Services"
        }
    ],
    "sg:phone":"+1 763 561 4131",
    "sg:postcode":"55428",
    "sg:province":"MN",
    "sg:tags":[
        "clinic",
        "specialty",
        "outpatient"
    ],
    "wof:name":"Gambrage Choice",
    "wof:placetype":"venue"
},
  "geometry": {"coordinates":[-93.366479,45.093432],"type":"Point"}
}