{
  "type": "Feature",
  "properties": {
    "addr:full":"1108 Vierling Dr E Shakopee MN 55379",
    "addr:housenumber":"1108",
    "addr:postcode":"55379",
    "addr:street":"Vierling Dr E",
    "iso:country":"US",
    "sg:address":"1108 Vierling Dr E",
    "sg:city":"Shakopee",
    "sg:classifiers":[
        {
            "category":"Banks & Credit Unions",
            "subcategory":"Bank",
            "type":"Services"
        }
    ],
    "sg:phone":"+1 952 445 3822",
    "sg:postcode":"55379",
    "sg:province":"MN",
    "sg:tags":[
        "depository",
        "banking"
    ],
    "wof:name":"Shapokee Money Exchange",
    "wof:placetype":"venue"
},
  "geometry": {"coordinates":[-93.511129,44.782299],"type":"Point"}
}