{
  "type": "Feature",
  "properties": {
    "addr:full":"222 4th St N Brownton MN 55312",
    "addr:housenumber":"222",
    "addr:postcode":"55312",
    "addr:street":"4Th St N",
    "iso:country":"US",
    "sg:address":"222 4th St N",
    "sg:city":"Brownton",
    "sg:classifiers":[
        {
            "category":"Building & Trades",
            "subcategory":"Construction",
            "type":"Services"
        }
    ],
    "sg:phone":"+1 320 587 7613",
    "sg:postcode":"55312",
    "sg:province":"MN",
    "sg:tags":[
        "painter"
    ],
    "wof:name":"Painters",
    "wof:placetype":"venue"
},
  "geometry": {"coordinates":[-94.353917,44.73526],"type":"Point"}
}