{
  "type": "Feature",
  "properties": {
    "addr:full":"14422 Ranch Rd Elk River MN 55330",
    "addr:housenumber":"14422",
    "addr:postcode":"55330",
    "addr:street":"Ranch Rd",
    "iso:country":"US",
    "sg:address":"14422 Ranch Rd",
    "sg:city":"Elk River",
    "sg:classifiers":[
        {
            "category":"Professional",
            "subcategory":"Management & Consulting",
            "type":"Services"
        }
    ],
    "sg:phone":"+1 763 234 7791",
    "sg:postcode":"55330",
    "sg:province":"MN",
    "sg:tags":[
        "paperless-processing",
        "electronic-forms",
        "rfid",
        "barcode",
        "data-collection",
        "iseries",
        "ibm",
        "as400",
        "information-technology",
        "roi"
    ],
    "sg:website":"http://www.bcs-mn.com",
    "wof:name":"BCSG, LLC",
    "wof:placetype":"venue"
},
  "geometry": {"coordinates":[-93.594515,45.352743],"type":"Point"}
}