{
  "type": "Feature",
  "properties": {
    "iso:country":"US",
    "sg:address":"75 Parkview Ln",
    "sg:city":"Esko",
    "sg:classifiers":[
        {
            "category":"Retail",
            "subcategory":"Repair Shop",
            "type":"Services"
        }
    ],
    "sg:phone":"+1 218 879 9632",
    "sg:postcode":"55733",
    "sg:province":"MN",
    "wof:name":"Art Dimensions",
    "wof:placetype":"venue"
},
  "geometry": {"coordinates":[-92.37985999999999,46.66578],"type":"Point"}
}