{
  "type": "Feature",
  "properties": {
    "iso:country":"US",
    "sg:address":"6959 Washington Ave S",
    "sg:city":"Minneapolis",
    "sg:classifiers":[
        {
            "category":"Manufacturing",
            "subcategory":"Wood Products",
            "type":"Manufacturing & Wholesale Goods"
        },
        {
            "category":"Retail",
            "subcategory":"Repair Shop",
            "type":"Services"
        },
        {
            "category":"Farming",
            "subcategory":"Fish & Marine Products",
            "type":"Manufacturing & Wholesale Goods"
        }
    ],
    "sg:phone":"+1 952 941 6649",
    "sg:postcode":"55439",
    "sg:province":"MN",
    "sg:tags":[
        "picture",
        "frames-wholesale",
        "frame",
        "restoration",
        "framing",
        "manufacturer"
    ],
    "sg:website":"http://www.metroframe.com",
    "wof:name":"Metropolitan Picture Framing",
    "wof:placetype":"venue"
},
  "geometry": {"coordinates":[-93.399117,44.876839],"type":"Point"}
}