{
  "type": "Feature",
  "properties": {
    "iso:country":"US",
    "sg:address":"3601 Minnesota Dr",
    "sg:city":"Edina",
    "sg:classifiers":[
        {
            "category":"Freight",
            "type":"Transportation"
        }
    ],
    "sg:phone":"+1 952 921 5826",
    "sg:postcode":"55435",
    "sg:province":"MN",
    "sg:tags":[
        "mover"
    ],
    "wof:name":"Ryder Move Management",
    "wof:placetype":"venue"
},
  "geometry": {"coordinates":[-93.324398,44.86223],"type":"Point"}
}