{
  "type": "Feature",
  "properties": {
    "addr:full":"12210 Pillsbury Forest Rd SW Pillager MN 56473",
    "addr:housenumber":"12210",
    "addr:postcode":"56473",
    "addr:street":"Pillsbury Forest Rd Sw",
    "iso:country":"US",
    "sg:address":"12210 Pillsbury Forest Rd SW",
    "sg:city":"Pillager",
    "sg:classifiers":[
        {
            "category":"Recreation",
            "type":"Entertainment"
        },
        {
            "category":"Retail",
            "subcategory":"Animal Services",
            "type":"Services"
        }
    ],
    "sg:phone":"+1 218 746 3990",
    "sg:postcode":"56473",
    "sg:province":"MN",
    "sg:tags":[
        "stable"
    ],
    "wof:name":"Outback Trail Rides",
    "wof:placetype":"venue"
},
  "geometry": {"coordinates":[-94.448166,46.380176],"type":"Point"}
}