{
  "type": "Feature",
  "properties": {
    "iso:country":"US",
    "sg:address":"905 Douglas Ave",
    "sg:city":"Minneapolis",
    "sg:classifiers":[
        {
            "category":"Organizations",
            "subcategory":"Community Association",
            "type":"Services"
        }
    ],
    "sg:phone":"+1 612 374 3013",
    "sg:postcode":"55403",
    "sg:province":"MN",
    "wof:name":"Douglas Ave Condominium Assn",
    "wof:placetype":"venue"
},
  "geometry": {"coordinates":[-93.291763,44.96647],"type":"Point"}
}