{
  "type": "Feature",
  "properties": {
    "iso:country":"US",
    "sg:address":"235 1st St W",
    "sg:city":"Milaca",
    "sg:classifiers":[
        {
            "category":"Manufacturing",
            "subcategory":"Tools & Machinery",
            "type":"Manufacturing & Wholesale Goods"
        }
    ],
    "sg:phone":"+1 320 983 6137",
    "sg:postcode":"56353",
    "sg:province":"MN",
    "sg:tags":[
        "industrial",
        "mfg"
    ],
    "wof:name":"Spectacle Lake Engineering",
    "wof:placetype":"venue"
},
  "geometry": {"coordinates":[-93.653476,45.754767],"type":"Point"}
}