{
  "type": "Feature",
  "properties": {
    "iso:country":"US",
    "sg:address":"3714 9th St NW",
    "sg:city":"Rochester",
    "sg:classifiers":[
        {
            "category":"Real Estate",
            "subcategory":"Real Estate Services",
            "type":"Services"
        },
        {
            "category":"Real Estate",
            "subcategory":"Real Estate Agent",
            "type":"Services"
        }
    ],
    "sg:phone":"+1 507 358 4715",
    "sg:postcode":"55901",
    "sg:province":"MN",
    "sg:tags":[
        "buyer",
        "broker"
    ],
    "wof:name":"Karissa Stubstad Realtor",
    "wof:placetype":"venue"
},
  "geometry": {"coordinates":[-92.521985,44.035282],"type":"Point"}
}