{
  "type": "Feature",
  "properties": {
    "iso:country":"US",
    "sg:address":"15292 Florist Cir",
    "sg:city":"St Paul",
    "sg:classifiers":[
        {
            "category":"Travel",
            "subcategory":"Hotels & Motels",
            "type":"Entertainment"
        }
    ],
    "sg:phone":"+1 952 997 6491",
    "sg:postcode":"55124",
    "sg:province":"MN",
    "sg:tags":[
        "resort"
    ],
    "wof:name":"Castle & Cook Resort",
    "wof:placetype":"venue"
},
  "geometry": {"coordinates":[-93.198933,44.727993],"type":"Point"}
}