{
  "type": "Feature",
  "properties": {
    "addr:full":"201 E Clover St Duluth MN 55812",
    "addr:housenumber":"201",
    "addr:postcode":"55812",
    "addr:street":"E Clover St",
    "iso:country":"US",
    "sg:address":"201 E Clover St",
    "sg:city":"Duluth",
    "sg:classifiers":[
        {
            "category":"Education",
            "subcategory":"School",
            "type":"Public Place"
        }
    ],
    "sg:phone":"+1 218 728 7463",
    "sg:postcode":"55812",
    "sg:province":"MN",
    "wof:name":"Woodland Community School",
    "wof:placetype":"venue"
},
  "geometry": {"coordinates":[-92.07426100000001,46.815846],"type":"Point"}
}