{
  "type": "Feature",
  "properties": {
    "addr:full":"6201 Butterworth Ln Hamel MN 55340",
    "addr:housenumber":"6201",
    "addr:postcode":"55340",
    "addr:street":"Butterworth Ln",
    "iso:country":"US",
    "sg:address":"6201 Butterworth Ln",
    "sg:city":"Hamel",
    "sg:classifiers":[
        {
            "category":"Real Estate",
            "subcategory":"Real Estate Agent",
            "type":"Services"
        }
    ],
    "sg:phone":"+1 763 478 6525",
    "sg:postcode":"55340",
    "sg:province":"MN",
    "sg:tags":[
        "appraiser"
    ],
    "wof:name":"Zimmerman Appraisal LLC",
    "wof:placetype":"venue"
},
  "geometry": {"coordinates":[-93.55635700000001,45.065708],"type":"Point"}
}