{
  "type": "Feature",
  "properties": {
    "iso:country":"US",
    "sg:address":"1220 Rossman Ave",
    "sg:city":"Detroit Lakes",
    "sg:classifiers":[
        {
            "category":"Government",
            "subcategory":"Office",
            "type":"Public Place"
        }
    ],
    "sg:phone":"+1 218 847 1589",
    "sg:postcode":"56501",
    "sg:province":"MN",
    "sg:tags":[
        "national",
        "security"
    ],
    "wof:name":"Minnesota Army Nat Gard Rcrter",
    "wof:placetype":"venue"
},
  "geometry": {"coordinates":[-95.853059,46.810923],"type":"Point"}
}