{
  "type": "Feature",
  "properties": {
    "addr:full":"641 Lake St E Wayzata MN 55391",
    "addr:housenumber":"641",
    "addr:postcode":"55391",
    "addr:street":"Lake St E",
    "iso:country":"US",
    "sg:address":"641 Lake St E",
    "sg:city":"Wayzata",
    "sg:classifiers":[
        {
            "category":"Professional",
            "subcategory":"Management & Consulting",
            "type":"Services"
        }
    ],
    "sg:phone":"+1 952 476 5480",
    "sg:postcode":"55391",
    "sg:province":"MN",
    "sg:tags":[
        "wire",
        "relation",
        "public",
        "cable-electric"
    ],
    "sg:website":"http://www.nortechsys.com",
    "wof:name":"Ita Group Inc",
    "wof:placetype":"venue"
},
  "geometry": {"coordinates":[-93.51279,44.96946],"type":"Point"}
}