{
  "type": "Feature",
  "properties": {
    "iso:country":"US",
    "sg:address":"1149 Cedarwood Dr",
    "sg:city":"Saint Paul",
    "sg:classifiers":[
        {
            "category":"Retail",
            "subcategory":"Repair Shop",
            "type":"Services"
        }
    ],
    "sg:phone":"+1 651 739 4959",
    "sg:postcode":"55125",
    "sg:province":"MN",
    "wof:name":"David W Overby",
    "wof:placetype":"venue"
},
  "geometry": {"coordinates":[-92.983611,44.931484],"type":"Point"}
}