{
  "type": "Feature",
  "properties": {
    "addr:full":"31325 Larkspur Ln Avon MN 56310",
    "addr:postcode":"31325;56310",
    "addr:street":"Larkspur Ln",
    "iso:country":"US",
    "sg:address":"31325 Larkspur Ln",
    "sg:city":"Avon",
    "sg:classifiers":[
        {
            "category":"Freight",
            "type":"Transportation"
        }
    ],
    "sg:phone":"+1 320 260 1026",
    "sg:postcode":"56310",
    "sg:province":"MN",
    "sg:tags":[
        "automobile",
        "trucking"
    ],
    "wof:name":"Dakota Auto Transport Inc",
    "wof:placetype":"venue"
},
  "geometry": {"coordinates":[-94.45256999999999,45.579291],"type":"Point"}
}