{
  "type": "Feature",
  "properties": {
    "addr:full":"1318 Monroe St NE Minneapolis MN 55413",
    "addr:housenumber":"1318",
    "addr:postcode":"55413",
    "addr:street":"Monroe St Ne",
    "iso:country":"US",
    "sg:address":"1318 Monroe St NE",
    "sg:city":"Minneapolis",
    "sg:classifiers":[
        {
            "category":"Professional",
            "subcategory":"Lawyer & Legal Services",
            "type":"Services"
        }
    ],
    "sg:phone":"+1 612 781 4426",
    "sg:postcode":"55413",
    "sg:province":"MN",
    "wof:name":"Pliam Law Group",
    "wof:placetype":"venue"
},
  "geometry": {"coordinates":[-93.252532,45.002871],"type":"Point"}
}