{
  "type": "Feature",
  "properties": {
    "iso:country":"US",
    "sg:address":"1900 8th Ave SW",
    "sg:city":"Austin",
    "sg:classifiers":[
        {
            "category":"Social Services",
            "subcategory":"Child Care",
            "type":"Services"
        }
    ],
    "sg:phone":"+1 507 437 8982",
    "sg:postcode":"55912",
    "sg:province":"MN",
    "sg:tags":[
        "day",
        "provider"
    ],
    "wof:name":"Anissa L Hultgren",
    "wof:placetype":"venue"
},
  "geometry": {"coordinates":[-92.99837599999999,43.659307],"type":"Point"}
}