{
  "type": "Feature",
  "properties": {
    "iso:country":"US",
    "sg:address":"2160 Hoffman Rd",
    "sg:city":"Mankato",
    "sg:classifiers":[
        {
            "category":"Food & Beverages",
            "subcategory":"Groceries & Convenience Stores",
            "type":"Retail Goods"
        }
    ],
    "sg:phone":"+1 507 625 5669",
    "sg:postcode":"56001",
    "sg:province":"MN",
    "wof:name":"Happy Dan's Convenience Stores",
    "wof:placetype":"venue"
},
  "geometry": {"coordinates":[-93.969016,44.156],"type":"Point"}
}