{
  "type": "Feature",
  "properties": {
    "addr:full":"3812 Hwy 21 Embarrass MN 55732",
    "addr:housenumber":"3812",
    "addr:postcode":"55732",
    "addr:street":"Hwy 21 Embarrass",
    "iso:country":"US",
    "sg:address":"3812 Hwy 21",
    "sg:city":"Embarrass",
    "sg:classifiers":[
        {
            "category":"Retail",
            "subcategory":"Portrait Studio",
            "type":"Services"
        }
    ],
    "sg:phone":"+1 218 984 3517",
    "sg:postcode":"55732",
    "sg:province":"MN",
    "sg:tags":[
        "photo"
    ],
    "wof:name":"Out of Ordinary Photography",
    "wof:placetype":"venue"
},
  "geometry": {"coordinates":[-92.095799,47.68754],"type":"Point"}
}