{
  "type": "Feature",
  "properties": {
    "iso:country":"US",
    "sg:address":"3777 35th St SE",
    "sg:city":"Delano",
    "sg:classifiers":[
        {
            "category":"Building & Trades",
            "subcategory":"Landscaping Services",
            "type":"Services"
        }
    ],
    "sg:phone":"+1 763 972 6014",
    "sg:postcode":"55328",
    "sg:province":"MN",
    "sg:tags":[
        "sanitary"
    ],
    "wof:name":"Thomas Ylitalo",
    "wof:placetype":"venue"
},
  "geometry": {"coordinates":[-93.80809000000001,45.099885],"type":"Point"}
}