{
  "type": "Feature",
  "properties": {
    "iso:country":"US",
    "sg:address":"551 Coon Rapids Blvd NW",
    "sg:city":"Coon Rapids",
    "sg:classifiers":[
        {
            "category":"Real Estate",
            "subcategory":"Real Estate Agent",
            "type":"Services"
        }
    ],
    "sg:phone":"+1 763 780 0463",
    "sg:postcode":"55433",
    "sg:province":"MN",
    "sg:tags":[
        "consultant"
    ],
    "sg:website":"www.residentialresearch.com",
    "wof:name":"Residential Research Svc",
    "wof:placetype":"venue"
},
  "geometry": {"coordinates":[-93.280985,45.144052],"type":"Point"}
}