{
  "type": "Feature",
  "properties": {
    "iso:country":"US",
    "sg:address":"8051 Hidden Cir",
    "sg:city":"Chanhassen",
    "sg:classifiers":[
        {
            "category":"Professional",
            "subcategory":"Computer Services",
            "type":"Services"
        }
    ],
    "sg:phone":"+1 952 906 1420",
    "sg:postcode":"55317",
    "sg:province":"MN",
    "sg:tags":[
        "related"
    ],
    "wof:name":"J Nicolai",
    "wof:placetype":"venue"
},
  "geometry": {"coordinates":[-93.52776299999999,44.857029],"type":"Point"}
}