{
  "type": "Feature",
  "properties": {
    "iso:country":"US",
    "sg:address":"1200 Moore Lake Dr E",
    "sg:city":"Minneapolis",
    "sg:classifiers":[
        {
            "category":"Personal",
            "type":"Services"
        },
        {
            "category":"Arena",
            "subcategory":"Sports Club",
            "type":"Entertainment"
        }
    ],
    "sg:phone":"+1 763 656 1500",
    "sg:postcode":"55432",
    "sg:province":"MN",
    "sg:tags":[
        "trainer",
        "consultant",
        "health",
        "fitness",
        "physical"
    ],
    "wof:name":"Life Time Fitness",
    "wof:placetype":"venue"
},
  "geometry": {"coordinates":[-93.240461,45.080786],"type":"Point"}
}