{
  "type": "Feature",
  "properties": {
    "iso:country":"US",
    "sg:address":"2548 Claremont Dr",
    "sg:city":"St Paul",
    "sg:classifiers":[
        {
            "category":"Manufacturing",
            "subcategory":"Metals",
            "type":"Manufacturing & Wholesale Goods"
        }
    ],
    "sg:phone":"+1 612 723 3022",
    "sg:postcode":"55120",
    "sg:province":"MN",
    "sg:tags":[
        "cable"
    ],
    "wof:name":"B W Cables",
    "wof:placetype":"venue"
},
  "geometry": {"coordinates":[-93.117413,44.865598],"type":"Point"}
}