{
  "type": "Feature",
  "properties": {
    "iso:country":"US",
    "sg:address":"24321 125th St NW",
    "sg:city":"Sunburg",
    "sg:phone":"+1 320 366 3871",
    "sg:postcode":"56289",
    "sg:province":"MN",
    "sg:tags":[
        "farm",
        "corn",
        "beef",
        "feedlot",
        "cattle"
    ],
    "wof:name":"Donald Berg",
    "wof:placetype":"venue"
},
  "geometry": {"coordinates":[-95.21414900000001,45.353095],"type":"Point"}
}