{
  "type": "Feature",
  "properties": {
    "addr:full":"1710 E Main St Albert Lea MN 56007",
    "addr:housenumber":"1710",
    "addr:postcode":"56007",
    "addr:street":"E Main St",
    "iso:country":"US",
    "sg:address":"1710 E Main St",
    "sg:city":"Albert Lea",
    "sg:classifiers":[
        {
            "category":"Wholesale",
            "subcategory":"Auto Parts",
            "type":"Manufacturing & Wholesale Goods"
        }
    ],
    "sg:phone":"+1 507 377 3322",
    "sg:postcode":"56007",
    "sg:province":"MN",
    "wof:name":"NAPA Auto Parts",
    "wof:placetype":"venue"
},
  "geometry": {"coordinates":[-93.34682100000001,43.652156],"type":"Point"}
}