{
  "type": "Feature",
  "properties": {
    "iso:country":"US",
    "sg:address":"26 6th Ave N",
    "sg:city":"Saint Cloud",
    "sg:classifiers":[
        {
            "category":"Utilities",
            "subcategory":"Telephone",
            "type":"Services"
        }
    ],
    "sg:phone":"+1 320 202 6700",
    "sg:postcode":"56303",
    "sg:province":"MN",
    "sg:tags":[
        "communications"
    ],
    "wof:name":"Customer Care Department",
    "wof:placetype":"venue"
},
  "geometry": {"coordinates":[-94.15987699999999,45.561385],"type":"Point"}
}