{
  "type": "Feature",
  "properties": {
    "iso:country":"US",
    "sg:address":"201 W Burnsville Pkwy",
    "sg:city":"Burnsville",
    "sg:classifiers":[
        {
            "category":"Real Estate",
            "subcategory":"Real Estate Agent",
            "type":"Services"
        }
    ],
    "sg:phone":"+1 952 641 3006",
    "sg:postcode":"55337",
    "sg:province":"MN",
    "wof:name":"Uptown Landing",
    "wof:placetype":"venue"
},
  "geometry": {"coordinates":[-93.280603,44.771526],"type":"Point"}
}