{
  "type": "Feature",
  "properties": {
    "addr:full":"3030 Sunset Rd Tower MN 55790",
    "addr:housenumber":"3030",
    "addr:postcode":"55790",
    "addr:street":"Sunset Rd",
    "iso:country":"US",
    "sg:address":"3030 Sunset Rd",
    "sg:city":"Tower",
    "sg:classifiers":[
        {
            "category":"Personal",
            "type":"Services"
        }
    ],
    "sg:phone":"+1 218 753 5314",
    "sg:postcode":"55790",
    "sg:province":"MN",
    "wof:name":"Lake Vermillion Seasonal Svcs",
    "wof:placetype":"venue"
},
  "geometry": {"coordinates":[-92.40442299999999,47.85529],"type":"Point"}
}