{
  "type": "Feature",
  "properties": {
    "addr:full":"33 SE 11th St Grand Rapids MN 55744",
    "addr:housenumber":"33",
    "addr:postcode":"55744",
    "addr:street":"Se 11Th St",
    "iso:country":"US",
    "sg:address":"33 SE 11th St",
    "sg:city":"Grand Rapids",
    "sg:classifiers":[
        {
            "category":"Wholesale",
            "subcategory":"Durable Goods & Equipment",
            "type":"Manufacturing & Wholesale Goods"
        }
    ],
    "sg:phone":"+1 218 327 8180",
    "sg:postcode":"55744",
    "sg:province":"MN",
    "wof:name":"Tan Incorporated",
    "wof:placetype":"venue"
},
  "geometry": {"coordinates":[-93.52828,47.220022],"type":"Point"}
}