{
  "type": "Feature",
  "properties": {
    "addr:full":"14075 96th Ave N Osseo MN 55369",
    "addr:housenumber":"14075",
    "addr:postcode":"55369",
    "addr:street":"96Th Ave N",
    "iso:country":"US",
    "sg:address":"14075 96th Ave N",
    "sg:city":"Osseo",
    "sg:classifiers":[
        {
            "category":"Real Estate",
            "subcategory":"Real Estate Agent",
            "type":"Services"
        }
    ],
    "sg:phone":"+1 763 420 9975",
    "sg:postcode":"55369",
    "sg:province":"MN",
    "wof:name":"US Appraisal Management",
    "wof:placetype":"venue"
},
  "geometry": {"coordinates":[-93.460354,45.129079],"type":"Point"}
}