{
  "type": "Feature",
  "properties": {
    "iso:country":"US",
    "sg:address":"4696 126th St N",
    "sg:city":"Saint Paul",
    "sg:classifiers":[
        {
            "category":"Shopping",
            "type":"Retail Goods"
        }
    ],
    "sg:phone":"+1 651 426 3890",
    "sg:postcode":"55110",
    "sg:province":"MN",
    "sg:tags":[
        "merchandise"
    ],
    "wof:name":"Recreational Water Systems",
    "wof:placetype":"venue"
},
  "geometry": {"coordinates":[-93.01220000000001,45.133325],"type":"Point"}
}