{
  "type": "Feature",
  "properties": {
    "iso:country":"US",
    "sg:address":"23123 600th St",
    "sg:city":"Mantorville",
    "sg:classifiers":[
        {
            "category":"Building & Trades",
            "subcategory":"Construction",
            "type":"Services"
        }
    ],
    "sg:phone":"+1 507 635 5359",
    "sg:postcode":"55955",
    "sg:province":"MN",
    "sg:tags":[
        "floor",
        "laying",
        "contractor"
    ],
    "wof:name":"Ideal Carpet & Flooring LLC",
    "wof:placetype":"venue"
},
  "geometry": {"coordinates":[-92.77609099999999,44.080203],"type":"Point"}
}