{
  "type": "Feature",
  "properties": {
    "iso:country":"US",
    "sg:address":"131 130th St S",
    "sg:city":"Glyndon",
    "sg:classifiers":[
        {
            "category":"Manufacturing",
            "subcategory":"Pet Food",
            "type":"Manufacturing & Wholesale Goods"
        }
    ],
    "sg:phone":"+1 218 498 0235",
    "sg:postcode":"56547",
    "sg:province":"MN",
    "sg:tags":[
        "animal",
        "mfg"
    ],
    "wof:name":"Crume Kennels",
    "wof:placetype":"venue"
},
  "geometry": {"coordinates":[-96.526605,46.875725],"type":"Point"}
}