{
  "type": "Feature",
  "properties": {
    "addr:full":"2213 Great Oaks Dr Burnsville MN 55337",
    "addr:housenumber":"2213",
    "addr:postcode":"55337",
    "addr:street":"Great Oaks Dr",
    "iso:country":"US",
    "sg:address":"2213 Great Oaks Dr",
    "sg:city":"Burnsville",
    "sg:classifiers":[
        {
            "category":"Building & Trades",
            "subcategory":"Construction",
            "type":"Services"
        }
    ],
    "sg:phone":"+1 952 997 2270",
    "sg:postcode":"55337",
    "sg:province":"MN",
    "sg:tags":[
        "house"
    ],
    "wof:name":"Donald L Johnson Homes",
    "wof:placetype":"venue"
},
  "geometry": {"coordinates":[-93.245538,44.762283],"type":"Point"}
}