{
  "type": "Feature",
  "properties": {
    "addr:full":"1266 Vierling Ct Shakopee MN 55379",
    "addr:housenumber":"1266",
    "addr:postcode":"55379",
    "addr:street":"Vierling Ct",
    "iso:country":"US",
    "sg:address":"1266 Vierling Ct",
    "sg:city":"Shakopee",
    "sg:classifiers":[
        {
            "category":"Autos & Motor Vehicles",
            "subcategory":"Auto Supplies",
            "type":"Retail Goods"
        }
    ],
    "sg:phone":"+1 952 403 6814",
    "sg:postcode":"55379",
    "sg:province":"MN",
    "sg:tags":[
        "automotive",
        "parts"
    ],
    "wof:name":"Checker Auto Parts 1886",
    "wof:placetype":"venue"
},
  "geometry": {"coordinates":[-93.517718,44.784657],"type":"Point"}
}