{
  "type": "Feature",
  "properties": {
    "iso:country":"US",
    "sg:address":"600 US Hwy 169",
    "sg:city":"Minneapolis",
    "sg:classifiers":[
        {
            "category":"Professional",
            "subcategory":"Computer Services",
            "type":"Services"
        },
        {
            "category":"Shopping",
            "subcategory":"Computers & Home Electronics",
            "type":"Retail Goods"
        }
    ],
    "sg:phone":"+1 952 544 7077",
    "sg:postcode":"55426",
    "sg:province":"MN",
    "sg:tags":[
        "oriented",
        "business",
        "software"
    ],
    "wof:name":"Epicor Software Corporation",
    "wof:placetype":"venue"
},
  "geometry": {"coordinates":[-93.40041100000001,44.975609],"type":"Point"}
}