{
  "type": "Feature",
  "properties": {
    "iso:country":"US",
    "sg:address":"8548 SW 138th St",
    "sg:city":"New Richland",
    "sg:classifiers":[
        {
            "category":"Building & Trades",
            "subcategory":"Electrical",
            "type":"Services"
        }
    ],
    "sg:phone":"+1 507 684 2221",
    "sg:postcode":"56072",
    "sg:province":"MN",
    "sg:tags":[
        "electric",
        "contractor"
    ],
    "wof:name":"M & M Electric Inc",
    "wof:placetype":"venue"
},
  "geometry": {"coordinates":[-93.36872700000001,43.891821],"type":"Point"}
}