{
  "type": "Feature",
  "properties": {
    "iso:country":"US",
    "sg:address":"3565 Searle Ct",
    "sg:city":"Vadnais Heights",
    "sg:classifiers":[
        {
            "category":"Building & Trades",
            "subcategory":"Construction",
            "type":"Services"
        }
    ],
    "sg:phone":"+1 651 483 9926",
    "sg:postcode":"55127",
    "sg:province":"MN",
    "sg:tags":[
        "concrete",
        "contractor"
    ],
    "wof:name":"James S Krey Masonry Contr",
    "wof:placetype":"venue"
},
  "geometry": {"coordinates":[-93.074358,45.049997],"type":"Point"}
}