{
  "type": "Feature",
  "properties": {
    "addr:full":"400 N Roy St St Paul MN 55104",
    "addr:housenumber":"400",
    "addr:postcode":"55104",
    "addr:street":"N Roy St",
    "iso:country":"US",
    "sg:address":"400 N Roy St",
    "sg:city":"St Paul",
    "sg:classifiers":[
        {
            "category":"Organizations",
            "subcategory":"Religious Organization",
            "type":"Services"
        }
    ],
    "sg:phone":"+1 651 689 1373",
    "sg:postcode":"55104",
    "sg:province":"MN",
    "sg:tags":[
        "church"
    ],
    "wof:name":"Spring Vale Baptist Church",
    "wof:placetype":"venue"
},
  "geometry": {"coordinates":[-93.16826399999999,44.952597],"type":"Point"}
}