{
  "type": "Feature",
  "properties": {
    "iso:country":"US",
    "sg:address":"6600 France Ave S Ste 640",
    "sg:city":"Minneapolis",
    "sg:classifiers":[
        {
            "category":"Insurance",
            "subcategory":"Title Insurance",
            "type":"Services"
        }
    ],
    "sg:phone":"+1 952 920 1001",
    "sg:postcode":"55435",
    "sg:province":"MN",
    "sg:tags":[
        "mortgage"
    ],
    "sg:website":"http://www.barrylaw.com",
    "wof:name":"Century Title Inc",
    "wof:placetype":"venue"
},
  "geometry": {"coordinates":[-93.329048,44.88282],"type":"Point"}
}