{
  "type": "Feature",
  "properties": {
    "iso:country":"US",
    "sg:address":"3837 43rd Ave S",
    "sg:city":"Minneapolis",
    "sg:classifiers":[
        {
            "category":"Professional",
            "type":"Services"
        }
    ],
    "sg:phone":"+1 612 729 5373",
    "sg:postcode":"55406",
    "sg:province":"MN",
    "wof:name":"Idlewilds",
    "wof:placetype":"venue"
},
  "geometry": {"coordinates":[-93.21140699999999,44.93313],"type":"Point"}
}