{
  "type": "Feature",
  "properties": {
    "iso:country":"US",
    "sg:address":"2103 8th St SW",
    "sg:city":"Austin",
    "sg:classifiers":[
        {
            "category":"Organizations",
            "subcategory":"Religious Organization",
            "type":"Services"
        }
    ],
    "sg:phone":"+1 507 437 6461",
    "sg:postcode":"55912",
    "sg:province":"MN",
    "sg:tags":[
        "church"
    ],
    "wof:name":"Beautiful Savior Lutheran Chr",
    "wof:placetype":"venue"
},
  "geometry": {"coordinates":[-92.984032,43.647131],"type":"Point"}
}