{
  "type": "Feature",
  "properties": {
    "addr:full":"5213 Saint Moritz Dr Minneapolis MN 55421",
    "addr:housenumber":"5213",
    "addr:postcode":"55421",
    "addr:street":"Saint Moritz Dr",
    "iso:country":"US",
    "sg:address":"5213 Saint Moritz Dr",
    "sg:city":"Minneapolis",
    "sg:classifiers":[
        {
            "category":"Arts & Performance",
            "subcategory":"Theater",
            "type":"Entertainment"
        }
    ],
    "sg:phone":"+1 763 789 2353",
    "sg:postcode":"55421",
    "sg:province":"MN",
    "sg:tags":[
        "theatrical",
        "manager",
        "producer"
    ],
    "sg:website":"http://www.actortrainingcast.com",
    "wof:name":"Cast Academy Of Acting & Showcase & Theatre",
    "wof:placetype":"venue"
},
  "geometry": {"coordinates":[-93.233839,45.062191],"type":"Point"}
}