{
  "type": "Feature",
  "properties": {
    "addr:full":"19157 210th St NW Crookston MN 56760",
    "addr:housenumber":"19157",
    "addr:postcode":"56760",
    "addr:street":"210Th St Nw",
    "iso:country":"US",
    "sg:address":"19157 210th St NW",
    "sg:city":"Crookston",
    "sg:classifiers":[
        {
            "category":"Farming",
            "subcategory":"Farm",
            "type":"Manufacturing & Wholesale Goods"
        }
    ],
    "sg:phone":"+1 218 647 8773",
    "sg:postcode":"56760",
    "sg:province":"MN",
    "sg:website":"www.blueoxfarms.com",
    "wof:name":"Blue Ox Farms",
    "wof:placetype":"venue"
},
  "geometry": {"coordinates":[-96.46055699999999,48.181548],"type":"Point"}
}