{
  "type": "Feature",
  "properties": {
    "iso:country":"US",
    "sg:address":"11688 40th St",
    "sg:city":"Bowlus",
    "sg:classifiers":[
        {
            "category":"Professional",
            "subcategory":"Computer Services",
            "type":"Services"
        }
    ],
    "sg:phone":"+1 320 584 0030",
    "sg:postcode":"56314",
    "sg:province":"MN",
    "sg:tags":[
        "related"
    ],
    "wof:name":"Two Rivers Creek Consulting",
    "wof:placetype":"venue"
},
  "geometry": {"coordinates":[-94.416267,45.819257],"type":"Point"}
}