{
  "type": "Feature",
  "properties": {
    "addr:full":"12180 Lindo Trl Lindstrom MN 55045",
    "addr:housenumber":"12180",
    "addr:postcode":"55045",
    "addr:street":"Lindo Trl",
    "iso:country":"US",
    "sg:address":"12180 Lindo Trl",
    "sg:city":"Lindstrom",
    "sg:classifiers":[
        {
            "category":"Wholesale",
            "subcategory":"Machinery & Supplies",
            "type":"Manufacturing & Wholesale Goods"
        }
    ],
    "sg:phone":"+1 651 257 8695",
    "sg:postcode":"55045",
    "sg:province":"MN",
    "sg:tags":[
        "compressor"
    ],
    "wof:name":"Robert Osterbauer",
    "wof:placetype":"venue"
},
  "geometry": {"coordinates":[-92.860298,45.448293],"type":"Point"}
}