{
  "type": "Feature",
  "properties": {
    "addr:full":"11060 Yucatan Rd Houston MN 55943",
    "addr:housenumber":"11060",
    "addr:postcode":"55943",
    "addr:street":"Yucatan Rd",
    "iso:country":"US",
    "sg:address":"11060 Yucatan Rd",
    "sg:city":"Houston",
    "sg:phone":"+1 507 896 3986",
    "sg:postcode":"55943",
    "sg:province":"MN",
    "sg:tags":[
        "beef",
        "farm",
        "corn",
        "cash",
        "crop",
        "field",
        "grain",
        "cattle"
    ],
    "wof:name":"Franklin Hahn",
    "wof:placetype":"venue"
},
  "geometry": {"coordinates":[-91.68086,43.686523],"type":"Point"}
}