{
  "type": "Feature",
  "properties": {
    "iso:country":"US",
    "sg:address":"3241 Hennepin Ave S",
    "sg:city":"Minneapolis",
    "sg:classifiers":[
        {
            "category":"Professional",
            "subcategory":"Business Services",
            "type":"Services"
        },
        {
            "category":"Professional",
            "subcategory":"Art Services",
            "type":"Services"
        }
    ],
    "sg:phone":"+1 612 861 3535",
    "sg:postcode":"55408",
    "sg:province":"MN",
    "sg:tags":[
        "graphic",
        "designer"
    ],
    "sg:website":"www.cooleydesignco.com",
    "wof:name":"Cool Ey Design",
    "wof:placetype":"venue"
},
  "geometry": {"coordinates":[-93.298258,44.943626],"type":"Point"}
}