{
  "type": "Feature",
  "properties": {
    "addr:full":"6401 Lombardy Ln Minneapolis MN 55428",
    "addr:housenumber":"6401",
    "addr:postcode":"55428",
    "addr:street":"Lombardy Ln",
    "iso:country":"US",
    "sg:address":"6401 Lombardy Ln",
    "sg:city":"Minneapolis",
    "sg:classifiers":[
        {
            "category":"Social Services",
            "subcategory":"Child Care",
            "type":"Services"
        }
    ],
    "sg:phone":"+1 763 537 1545",
    "sg:postcode":"55428",
    "sg:province":"MN",
    "sg:tags":[
        "daycare",
        "provider"
    ],
    "wof:name":"Patricia Deutscher",
    "wof:placetype":"venue"
},
  "geometry": {"coordinates":[-93.360906,45.062893],"type":"Point"}
}