{
  "type": "Feature",
  "properties": {
    "iso:country":"US",
    "sg:address":"320 3rd Ave NW",
    "sg:city":"Hutchinson",
    "sg:classifiers":[
        {
            "category":"Wholesale",
            "subcategory":"Machinery & Supplies",
            "type":"Manufacturing & Wholesale Goods"
        }
    ],
    "sg:phone":"+1 612 332 6137",
    "sg:postcode":"55350",
    "sg:province":"MN",
    "sg:tags":[
        "box"
    ],
    "sg:website":"www.stearnswood.com",
    "wof:name":"Stearnswood Inc",
    "wof:placetype":"venue"
},
  "geometry": {"coordinates":[-94.37778,44.89596],"type":"Point"}
}