{
  "type": "Feature",
  "properties": {
    "addr:full":"617 E Main St Ste 5 Anoka MN 55303",
    "addr:housenumber":"617",
    "addr:postcode":"55303",
    "addr:street":"E Main St Ste 5",
    "iso:country":"US",
    "sg:address":"617 E Main St Ste 5",
    "sg:city":"Anoka",
    "sg:classifiers":[
        {
            "category":"Real Estate",
            "subcategory":"Real Estate Operator",
            "type":"Services"
        }
    ],
    "sg:phone":"+1 763 427 5100",
    "sg:postcode":"55303",
    "sg:province":"MN",
    "sg:tags":[
        "apartment"
    ],
    "wof:name":"Dellwood Rental & Const Co",
    "wof:placetype":"venue"
},
  "geometry": {"coordinates":[-93.38069900000001,45.1978],"type":"Point"}
}