{
  "type": "Feature",
  "properties": {
    "addr:full":"810 22nd Ave E Alexandria MN 56308",
    "addr:housenumber":"810",
    "addr:postcode":"56308",
    "addr:street":"22Nd Ave E",
    "iso:country":"US",
    "sg:address":"810 22nd Ave E",
    "sg:city":"Alexandria",
    "sg:classifiers":[
        {
            "category":"Manufacturing",
            "subcategory":"Building Materials",
            "type":"Manufacturing & Wholesale Goods"
        }
    ],
    "sg:phone":"+1 320 762 4172",
    "sg:postcode":"56308",
    "sg:province":"MN",
    "sg:tags":[
        "mfg",
        "wood",
        "kitchen",
        "cabinet"
    ],
    "wof:name":"Cabinets By Carter Inc",
    "wof:placetype":"venue"
},
  "geometry": {"coordinates":[-95.36958199999999,45.864601],"type":"Point"}
}