{
  "type": "Feature",
  "properties": {
    "addr:full":"1201 Pike Lake Dr Saint Paul MN 55112",
    "addr:housenumber":"1201",
    "addr:postcode":"55112",
    "addr:street":"Pike Lake Dr",
    "iso:country":"US",
    "sg:address":"1201 Pike Lake Dr",
    "sg:city":"Saint Paul",
    "sg:classifiers":[
        {
            "category":"Manufacturing",
            "subcategory":"Signs",
            "type":"Manufacturing & Wholesale Goods"
        }
    ],
    "sg:phone":"+1 651 486 8946",
    "sg:postcode":"55112",
    "sg:province":"MN",
    "sg:tags":[
        "specialty",
        "mfg"
    ],
    "wof:name":"Sign-A-Rama",
    "wof:placetype":"venue"
},
  "geometry": {"coordinates":[-93.21151999999999,45.069759],"type":"Point"}
}