{
  "type": "Feature",
  "properties": {
    "iso:country":"US",
    "sg:address":"19747 Morningstar Rd",
    "sg:city":"Avon",
    "sg:classifiers":[
        {
            "category":"Retail",
            "subcategory":"Animal Services",
            "type":"Services"
        }
    ],
    "sg:phone":"+1 320 845 7797",
    "sg:postcode":"56310",
    "sg:province":"MN",
    "wof:name":"Morningstar Grooming",
    "wof:placetype":"venue"
},
  "geometry": {"coordinates":[-94.507087,45.577179],"type":"Point"}
}