{
  "type": "Feature",
  "properties": {
    "iso:country":"US",
    "sg:address":"6981 Washington Ave S",
    "sg:city":"Minneapolis",
    "sg:classifiers":[
        {
            "category":"Utilities",
            "subcategory":"Telephone",
            "type":"Services"
        },
        {
            "category":"Manufacturing",
            "subcategory":"Electronics",
            "type":"Manufacturing & Wholesale Goods"
        },
        {
            "category":"Communications",
            "type":"Services"
        }
    ],
    "sg:phone":"+1 952 946 7999",
    "sg:postcode":"55439",
    "sg:province":"MN",
    "sg:tags":[
        "equipment",
        "telecommunications-equipment",
        "system",
        "data",
        "supply"
    ],
    "sg:website":"http://www.voicedata.com",
    "wof:name":"Voice & Data Networks, Inc.",
    "wof:placetype":"venue"
},
  "geometry": {"coordinates":[-93.399019,44.876603],"type":"Point"}
}