{
  "type": "Feature",
  "properties": {
    "addr:full":"13785 Co Rd 6 Lamberton MN 56152",
    "addr:housenumber":"13785",
    "addr:postcode":"56152",
    "addr:street":"Co Rd 6 Lamberton",
    "iso:country":"US",
    "sg:address":"13785 Co Rd 6",
    "sg:city":"Lamberton",
    "sg:classifiers":[
        {
            "category":"Farming",
            "subcategory":"Livestock Farm",
            "type":"Manufacturing & Wholesale Goods"
        }
    ],
    "sg:phone":"+1 507 752 7056",
    "sg:postcode":"56152",
    "sg:province":"MN",
    "sg:tags":[
        "beef",
        "feedlot",
        "cattle"
    ],
    "wof:name":"Donald Dietz Farm",
    "wof:placetype":"venue"
},
  "geometry": {"coordinates":[-95.2692,44.253592],"type":"Point"}
}