{
  "type": "Feature",
  "properties": {
    "iso:country":"US",
    "sg:address":"2440 White Bear Ave N",
    "sg:city":"Saint Paul",
    "sg:classifiers":[
        {
            "category":"Restaurant",
            "type":"Food & Drink"
        }
    ],
    "sg:menulink":"http://www.allmenus.com/mn/maplewood/190785-burger-king/menu/",
    "sg:phone":"+1 651 779 6621",
    "sg:postcode":"55109",
    "sg:province":"MN",
    "sg:tags":[
        "burger",
        "american"
    ],
    "wof:name":"Burger King",
    "wof:placetype":"venue"
},
  "geometry": {"coordinates":[-93.019291,45.015104],"type":"Point"}
}