{
  "type": "Feature",
  "properties": {
    "iso:country":"US",
    "sg:address":"1805 Quarry Rd",
    "sg:city":"St Cloud",
    "sg:classifiers":[
        {
            "category":"Organizations",
            "subcategory":"Religious Organization",
            "type":"Services"
        }
    ],
    "sg:phone":"+1 320 202 0540",
    "sg:postcode":"56301",
    "sg:province":"MN",
    "sg:tags":[
        "church"
    ],
    "sg:website":"www.jubileewc.org",
    "wof:name":"Jubilee Worship Center",
    "wof:placetype":"venue"
},
  "geometry": {"coordinates":[-94.198395,45.539579],"type":"Point"}
}