{
  "type": "Feature",
  "properties": {
    "iso:country":"US",
    "sg:address":"19125 Sherman Shores Rd",
    "sg:city":"Audubon",
    "sg:classifiers":[
        {
            "category":"Professional",
            "subcategory":"Detective & Security Services",
            "type":"Services"
        }
    ],
    "sg:phone":"+1 701 297 7300",
    "sg:postcode":"56511",
    "sg:province":"MN",
    "sg:tags":[
        "guard"
    ],
    "wof:name":"Richard A Fisher",
    "wof:placetype":"venue"
},
  "geometry": {"coordinates":[-96.005112,46.805859],"type":"Point"}
}