{
  "type": "Feature",
  "properties": {
    "iso:country":"US",
    "sg:address":"4020 W 39th St",
    "sg:city":"Minneapolis",
    "sg:classifiers":[
        {
            "category":"Professional",
            "subcategory":"Management & Consulting",
            "type":"Services"
        }
    ],
    "sg:phone":"+1 952 926 5055",
    "sg:postcode":"55416",
    "sg:province":"MN",
    "sg:tags":[
        "business"
    ],
    "wof:name":"Dennis A Ahlburg & Assoc",
    "wof:placetype":"venue"
},
  "geometry": {"coordinates":[-93.33142599999999,44.93245],"type":"Point"}
}