{
  "type": "Feature",
  "properties": {
    "addr:full":"5242 W 6th St Winona MN 55987",
    "addr:housenumber":"5242",
    "addr:postcode":"55987",
    "addr:street":"W 6Th St",
    "iso:country":"US",
    "sg:address":"5242 W 6th St",
    "sg:city":"Winona",
    "sg:classifiers":[
        {
            "category":"Restaurant",
            "type":"Food & Drink"
        }
    ],
    "sg:phone":"+1 507 454 5911",
    "sg:postcode":"55987",
    "sg:province":"MN",
    "sg:tags":[
        "pizza"
    ],
    "wof:name":"Rocco's Pub & Pizza",
    "wof:placetype":"venue"
},
  "geometry": {"coordinates":[-91.70659000000001,44.068269],"type":"Point"}
}