{
  "type": "Feature",
  "properties": {
    "iso:country":"US",
    "sg:address":"1657 W Edmund Ave",
    "sg:city":"Saint Paul",
    "sg:classifiers":[
        {
            "category":"Cinema",
            "subcategory":"Movie Theater",
            "type":"Entertainment"
        }
    ],
    "sg:phone":"+1 651 645 6099",
    "sg:postcode":"55104",
    "sg:province":"MN",
    "sg:tags":[
        "motion",
        "picture",
        "production"
    ],
    "wof:name":"Dv Cinema Inc",
    "wof:placetype":"venue"
},
  "geometry": {"coordinates":[-93.17161900000001,44.958438],"type":"Point"}
}