{
  "type": "Feature",
  "properties": {
    "addr:full":"35742 610th Ave Bluffton MN 56518",
    "addr:housenumber":"35742",
    "addr:postcode":"56518",
    "addr:street":"610Th Ave",
    "iso:country":"US",
    "sg:address":"35742 610th Ave",
    "sg:city":"Bluffton",
    "sg:classifiers":[
        {
            "category":"Farming",
            "subcategory":"Dairy Farm",
            "type":"Manufacturing & Wholesale Goods"
        }
    ],
    "sg:phone":"+1 218 631 3771",
    "sg:postcode":"56518",
    "sg:province":"MN",
    "sg:tags":[
        "business"
    ],
    "wof:name":"Mark Rohr",
    "wof:placetype":"venue"
},
  "geometry": {"coordinates":[-95.217915,46.48257],"type":"Point"}
}