{
  "type": "Feature",
  "properties": {
    "addr:full":"11620 Louisiana Ave N Champlin MN 55316",
    "addr:housenumber":"11620",
    "addr:postcode":"55316",
    "addr:street":"Louisiana Ave N",
    "iso:country":"US",
    "sg:address":"11620 Louisiana Ave N",
    "sg:city":"Champlin",
    "sg:classifiers":[
        {
            "category":"Professional",
            "subcategory":"Computer Services",
            "type":"Services"
        }
    ],
    "sg:phone":"+1 763 712 1180",
    "sg:postcode":"55316",
    "sg:province":"MN",
    "sg:tags":[
        "related"
    ],
    "wof:name":"Tru Network Solutions Inc",
    "wof:placetype":"venue"
},
  "geometry": {"coordinates":[-93.370735,45.165422],"type":"Point"}
}