{
  "type": "Feature",
  "properties": {
    "iso:country":"US",
    "sg:address":"710 N Prior Ave",
    "sg:city":"St Paul",
    "sg:classifiers":[
        {
            "category":"Professional",
            "subcategory":"Detective & Security Services",
            "type":"Services"
        }
    ],
    "sg:phone":"+1 612 964 4596",
    "sg:postcode":"55104",
    "sg:province":"MN",
    "sg:tags":[
        "guard",
        "patrol"
    ],
    "wof:name":"PTC Security",
    "wof:placetype":"venue"
},
  "geometry": {"coordinates":[-93.18222400000001,44.961252],"type":"Point"}
}