{
  "type": "Feature",
  "properties": {
    "addr:full":"108 3rd St SE Medford MN 55049",
    "addr:housenumber":"108",
    "addr:postcode":"55049",
    "addr:street":"3Rd St Se",
    "iso:country":"US",
    "sg:address":"108 3rd St SE",
    "sg:city":"Medford",
    "sg:classifiers":[
        {
            "category":"Autos & Motor Vehicles",
            "subcategory":"Automobile Sales",
            "type":"Retail Goods"
        }
    ],
    "sg:phone":"+1 507 451 5494",
    "sg:postcode":"55049",
    "sg:province":"MN",
    "wof:name":"TCS Trailer Sales",
    "wof:placetype":"venue"
},
  "geometry": {"coordinates":[-93.243004,44.173136],"type":"Point"}
}