{
  "type": "Feature",
  "properties": {
    "iso:country":"US",
    "sg:address":"201 E Lake St",
    "sg:city":"Minneapolis",
    "sg:classifiers":[
        {
            "category":"Bars & Pubs",
            "type":"Food & Drink"
        }
    ],
    "sg:phone":"+1 612 823 6016",
    "sg:postcode":"55408",
    "sg:province":"MN",
    "wof:name":"Roundup Beer Hall",
    "wof:placetype":"venue"
},
  "geometry": {"coordinates":[-93.272858,44.948353],"type":"Point"}
}