{
  "type": "Feature",
  "properties": {
    "addr:full":"5708 Brookdale Dr N Brooklyn Park MN 55443",
    "addr:housenumber":"5708",
    "addr:postcode":"55443",
    "addr:street":"Brookdale Dr N",
    "iso:country":"US",
    "sg:address":"5708 Brookdale Dr N",
    "sg:city":"Brooklyn Park",
    "sg:classifiers":[
        {
            "category":"Food & Beverages",
            "subcategory":"Groceries & Convenience Stores",
            "type":"Retail Goods"
        }
    ],
    "sg:phone":"+1 763 560 2263",
    "sg:postcode":"55443",
    "sg:province":"MN",
    "sg:tags":[
        "grocer"
    ],
    "wof:name":"African Food Market",
    "wof:placetype":"venue"
},
  "geometry": {"coordinates":[-93.35638299999999,45.09545],"type":"Point"}
}