{
  "type": "Feature",
  "properties": {
    "addr:full":"330 W 2nd St Winona MN 55987",
    "addr:housenumber":"330",
    "addr:postcode":"55987",
    "addr:street":"W 2Nd St",
    "iso:country":"US",
    "sg:address":"330 W 2nd St",
    "sg:city":"Winona",
    "sg:classifiers":[
        {
            "category":"Shopping",
            "subcategory":"Department Store",
            "type":"Retail Goods"
        }
    ],
    "sg:phone":"+1 507 457 0222",
    "sg:postcode":"55987",
    "sg:province":"MN",
    "wof:name":"Sears Roebuck & Co",
    "wof:placetype":"venue"
},
  "geometry": {"coordinates":[-91.64272,44.055227],"type":"Point"}
}