{
  "type": "Feature",
  "properties": {
    "addr:full":"1753 US Hwy 61 Lake City MN 55041",
    "addr:housenumber":"1753",
    "addr:postcode":"55041",
    "addr:street":"Us Hwy 61",
    "iso:country":"US",
    "sg:address":"1753 US Hwy 61",
    "sg:city":"Lake City",
    "sg:classifiers":[
        {
            "category":"Wholesale",
            "subcategory":"Fruits & Vegetables",
            "type":"Manufacturing & Wholesale Goods"
        }
    ],
    "sg:phone":"+1 651 345 2305",
    "sg:postcode":"55041",
    "sg:province":"MN",
    "sg:tags":[
        "shipper"
    ],
    "sg:website":"www.pepinheights.com",
    "wof:name":"Pepin Heights Orchard Inc",
    "wof:placetype":"venue"
},
  "geometry": {"coordinates":[-92.285586,44.46255],"type":"Point"}
}