{
  "type": "Feature",
  "properties": {
    "addr:full":"170 7th Pl E Saint Paul MN 55101",
    "addr:housenumber":"170",
    "addr:postcode":"55101",
    "addr:street":"7Th Pl E",
    "iso:country":"US",
    "sg:address":"170 7th Pl E",
    "sg:city":"Saint Paul",
    "sg:classifiers":[
        {
            "category":"Professional",
            "subcategory":"Accounting & Tax Preparation",
            "type":"Services"
        }
    ],
    "sg:phone":"+1 651 265 2022",
    "sg:postcode":"55101",
    "sg:province":"MN",
    "wof:name":"Jerry M Faletti",
    "wof:placetype":"venue"
},
  "geometry": {"coordinates":[-93.08984599999999,44.950133],"type":"Point"}
}