{
  "type": "Feature",
  "properties": {
    "addr:full":"25526 Pillsbury Ave Lakeville MN 55044",
    "addr:postcode":"25526;55044",
    "addr:street":"Pillsbury Ave",
    "iso:country":"US",
    "sg:address":"25526 Pillsbury Ave",
    "sg:city":"Lakeville",
    "sg:classifiers":[
        {
            "category":"Farming",
            "subcategory":"Orchard",
            "type":"Manufacturing & Wholesale Goods"
        }
    ],
    "sg:phone":"+1 952 469 1851",
    "sg:postcode":"55044",
    "sg:province":"MN",
    "sg:tags":[
        "fruit",
        "tree"
    ],
    "wof:name":"Mackinnons Apple Creek Orchard",
    "wof:placetype":"venue"
},
  "geometry": {"coordinates":[-93.288073,44.584996],"type":"Point"}
}