{
  "type": "Feature",
  "properties": {
    "iso:country":"US",
    "sg:address":"78 Maple Ln",
    "sg:city":"Saint Paul",
    "sg:classifiers":[
        {
            "category":"Professional",
            "subcategory":"Secretarial Services",
            "type":"Services"
        }
    ],
    "sg:phone":"+1 651 484 2760",
    "sg:postcode":"55117",
    "sg:province":"MN",
    "sg:tags":[
        "reporting"
    ],
    "wof:name":"Tab Secretarial Services",
    "wof:placetype":"venue"
},
  "geometry": {"coordinates":[-93.098612,45.028303],"type":"Point"}
}