{
  "type": "Feature",
  "properties": {
    "iso:country":"US",
    "sg:address":"111 NE 10th Ave",
    "sg:city":"Grand Rapids",
    "sg:classifiers":[
        {
            "category":"Professional",
            "subcategory":"Accounting & Tax Preparation",
            "type":"Services"
        }
    ],
    "sg:phone":"+1 218 326 1763",
    "sg:postcode":"55744",
    "sg:province":"MN",
    "sg:tags":[
        "bookkeeping",
        "general"
    ],
    "wof:name":"SDS Accounting Svc Inc",
    "wof:placetype":"venue"
},
  "geometry": {"coordinates":[-93.513074,47.233732],"type":"Point"}
}