{
  "type": "Feature",
  "properties": {
    "addr:full":"750 W 78th St Richfield MN 55423",
    "addr:housenumber":"750",
    "addr:postcode":"55423",
    "addr:street":"W 78Th St",
    "iso:country":"US",
    "sg:address":"750 W 78th St",
    "sg:city":"Richfield",
    "sg:classifiers":[
        {
            "category":"Home & Garden",
            "subcategory":"Furniture",
            "type":"Retail Goods"
        }
    ],
    "sg:phone":"+1 612 861 1791",
    "sg:postcode":"55423",
    "sg:province":"MN",
    "sg:tags":[
        "mattress"
    ],
    "wof:name":"Mattress Giant",
    "wof:placetype":"venue"
},
  "geometry": {"coordinates":[-93.28882299999999,44.862752],"type":"Point"}
}