{
  "type": "Feature",
  "properties": {
    "iso:country":"US",
    "sg:address":"6540 Waldvogel Rd NE",
    "sg:city":"Nelson",
    "sg:phone":"+1 320 852 7931",
    "sg:postcode":"56355",
    "sg:province":"MN",
    "sg:tags":[
        "farm",
        "corn",
        "grain",
        "cash",
        "soybean"
    ],
    "wof:name":"Jerry Waldvogel",
    "wof:placetype":"venue"
},
  "geometry": {"coordinates":[-95.193507,45.960296],"type":"Point"}
}