{
  "type": "Feature",
  "properties": {
    "iso:country":"US",
    "sg:address":"1199 102nd St SE",
    "sg:city":"Delano",
    "sg:classifiers":[
        {
            "category":"Building & Trades",
            "subcategory":"Construction",
            "type":"Services"
        }
    ],
    "sg:phone":"+1 952 955 2543",
    "sg:postcode":"55328",
    "sg:province":"MN",
    "sg:tags":[
        "water",
        "repair",
        "well",
        "drilling"
    ],
    "wof:name":"Motzko Well Drilling",
    "wof:placetype":"venue"
},
  "geometry": {"coordinates":[-93.86565299999999,45.003465],"type":"Point"}
}