{
  "type": "Feature",
  "properties": {
    "iso:country":"US",
    "sg:address":"310 50th Ave W",
    "sg:city":"Alexandria",
    "sg:classifiers":[
        {
            "category":"Shopping",
            "subcategory":"Department Store",
            "type":"Retail Goods"
        }
    ],
    "sg:phone":"+1 320 763 4277",
    "sg:postcode":"56308",
    "sg:province":"MN",
    "sg:tags":[
        "battery",
        "supply"
    ],
    "sg:website":"http://www.fleetfarm.com",
    "wof:name":"Mills Fleet Farm",
    "wof:placetype":"venue"
},
  "geometry": {"coordinates":[-95.37994,45.845658],"type":"Point"}
}