{
  "type": "Feature",
  "properties": {
    "iso:country":"US",
    "sg:address":"7389 Bush Lake Rd",
    "sg:city":"Edina",
    "sg:classifiers":[
        {
            "category":"Manufacturing",
            "subcategory":"Retail Goods",
            "type":"Manufacturing & Wholesale Goods"
        }
    ],
    "sg:phone":"+1 952 831 5897",
    "sg:postcode":"55439",
    "sg:province":"MN",
    "sg:tags":[
        "manufacturer"
    ],
    "wof:name":"Wilson Wolf Mfg",
    "wof:placetype":"venue"
},
  "geometry": {"coordinates":[-93.35966500000001,44.868726],"type":"Point"}
}