{
  "type": "Feature",
  "properties": {
    "addr:full":"14475 Cameo Ave W Rosemount MN 55068",
    "addr:housenumber":"14475",
    "addr:postcode":"55068",
    "addr:street":"Cameo Ave W",
    "iso:country":"US",
    "sg:address":"14475 Cameo Ave W",
    "sg:city":"Rosemount",
    "sg:classifiers":[
        {
            "category":"Professional",
            "type":"Services"
        }
    ],
    "sg:phone":"+1 651 423 2594",
    "sg:postcode":"55068",
    "sg:province":"MN",
    "sg:tags":[
        "establishment"
    ],
    "wof:name":"Plaisted Companies Inc",
    "wof:placetype":"venue"
},
  "geometry": {"coordinates":[-93.128207,44.739441],"type":"Point"}
}