{
  "type": "Feature",
  "properties": {
    "addr:full":"62621 200th Ave Dodge Center MN 55927",
    "addr:housenumber":"62621",
    "addr:postcode":"55927",
    "addr:street":"200Th Ave",
    "iso:country":"US",
    "sg:address":"62621 200th Ave",
    "sg:city":"Dodge Center",
    "sg:classifiers":[
        {
            "category":"Insurance",
            "subcategory":"Insurance Agent",
            "type":"Services"
        }
    ],
    "sg:phone":"+1 507 374 2461",
    "sg:postcode":"55927",
    "sg:province":"MN",
    "wof:name":"Kerry Koestler Insurance",
    "wof:placetype":"venue"
},
  "geometry": {"coordinates":[-92.83900800000001,44.04434],"type":"Point"}
}