{
  "type": "Feature",
  "properties": {
    "addr:full":"2074 Emerald Ln Eagan MN 55122",
    "addr:housenumber":"2074",
    "addr:postcode":"55122",
    "addr:street":"Emerald Ln",
    "iso:country":"US",
    "sg:address":"2074 Emerald Ln",
    "sg:city":"Eagan",
    "sg:classifiers":[
        {
            "category":"Wholesale",
            "subcategory":"Machinery & Supplies",
            "type":"Manufacturing & Wholesale Goods"
        }
    ],
    "sg:phone":"+1 651 454 2828",
    "sg:postcode":"55122",
    "sg:province":"MN",
    "sg:tags":[
        "instrument",
        "surveying"
    ],
    "wof:name":"Grey Survey Repair",
    "wof:placetype":"venue"
},
  "geometry": {"coordinates":[-93.21266799999999,44.807969],"type":"Point"}
}