{
  "type": "Feature",
  "properties": {
    "addr:full":"129 W Bridge St Owatonna MN 55060",
    "addr:housenumber":"129",
    "addr:postcode":"55060",
    "addr:street":"W Bridge St",
    "iso:country":"US",
    "sg:address":"129 W Bridge St",
    "sg:city":"Owatonna",
    "sg:classifiers":[
        {
            "category":"Retail",
            "subcategory":"Portrait Studio",
            "type":"Services"
        }
    ],
    "sg:phone":"+1 507 446 8335",
    "sg:postcode":"55060",
    "sg:province":"MN",
    "sg:tags":[
        "photographer"
    ],
    "wof:name":"Shot In The Dark Studio",
    "wof:placetype":"venue"
},
  "geometry": {"coordinates":[-93.23031899999999,44.084288],"type":"Point"}
}