{
  "type": "Feature",
  "properties": {
    "iso:country":"US",
    "sg:address":"7400 Metro Blvd",
    "sg:city":"Edina",
    "sg:classifiers":[
        {
            "category":"Wholesale",
            "subcategory":"Machinery & Supplies",
            "type":"Manufacturing & Wholesale Goods"
        }
    ],
    "sg:phone":"+1 952 831 3831",
    "sg:postcode":"55439",
    "sg:province":"MN",
    "sg:tags":[
        "tubing",
        "industrial",
        "hose",
        "plastic"
    ],
    "wof:name":"Gates Rubber Company",
    "wof:placetype":"venue"
},
  "geometry": {"coordinates":[-93.351145,44.868979],"type":"Point"}
}