{
  "type": "Feature",
  "properties": {
    "addr:full":"66 Thompson Ave E Saint Paul MN 55118",
    "addr:housenumber":"66",
    "addr:postcode":"55118",
    "addr:street":"Thompson Ave E",
    "iso:country":"US",
    "sg:address":"66 Thompson Ave E",
    "sg:city":"Saint Paul",
    "sg:classifiers":[
        {
            "category":"Professional",
            "subcategory":"Business Services",
            "type":"Services"
        }
    ],
    "sg:phone":"+1 651 457 0555",
    "sg:postcode":"55118",
    "sg:province":"MN",
    "sg:tags":[
        "appraiser"
    ],
    "wof:name":"Mort Geller Jewelers Appraiser",
    "wof:placetype":"venue"
},
  "geometry": {"coordinates":[-93.08426,44.900387],"type":"Point"}
}