{
  "type": "Feature",
  "properties": {
    "addr:full":"4005 28th St SE Rochester MN 55904",
    "addr:housenumber":"4005",
    "addr:postcode":"55904",
    "addr:street":"28Th St Se",
    "iso:country":"US",
    "sg:address":"4005 28th St SE",
    "sg:city":"Rochester",
    "sg:classifiers":[
        {
            "category":"Building & Trades",
            "subcategory":"Construction",
            "type":"Services"
        }
    ],
    "sg:phone":"+1 507 292 1000",
    "sg:postcode":"55904",
    "sg:province":"MN",
    "sg:tags":[
        "roofing",
        "industrial",
        "contractors-commercial",
        "contractor"
    ],
    "wof:name":"Chapman Roofing",
    "wof:placetype":"venue"
},
  "geometry": {"coordinates":[-92.398737,43.981829],"type":"Point"}
}