{
  "type": "Feature",
  "properties": {
    "iso:country":"US",
    "sg:address":"226 6th St S",
    "sg:city":"Minneapolis",
    "sg:classifiers":[
        {
            "category":"Professional",
            "subcategory":"Lawyer & Legal Services",
            "type":"Services"
        }
    ],
    "sg:phone":"+1 612 455 3836",
    "sg:postcode":"55401",
    "sg:province":"MN",
    "wof:name":"Ojanen Karuna Atty",
    "wof:placetype":"venue"
},
  "geometry": {"coordinates":[-93.268249,44.976699],"type":"Point"}
}