{
  "type": "Feature",
  "properties": {
    "iso:country":"US",
    "sg:address":"510 N Chestnut St Ste 200",
    "sg:city":"Chaska",
    "sg:classifiers":[
        {
            "category":"Real Estate",
            "subcategory":"Real Estate Services",
            "type":"Services"
        }
    ],
    "sg:phone":"+1 952 448 4630",
    "sg:postcode":"55318",
    "sg:province":"MN",
    "sg:tags":[
        "management",
        "property"
    ],
    "wof:name":"Wilson Development Service",
    "wof:placetype":"venue"
},
  "geometry": {"coordinates":[-93.60169999999999,44.788799],"type":"Point"}
}