{
  "type": "Feature",
  "properties": {
    "addr:full":"847 Sibley Memorial Hwy Saint Paul MN 55118",
    "addr:housenumber":"847",
    "addr:postcode":"55118",
    "addr:street":"Sibley Memorial Hwy",
    "iso:country":"US",
    "sg:address":"847 Sibley Memorial Hwy",
    "sg:city":"Saint Paul",
    "sg:classifiers":[
        {
            "category":"Personal",
            "subcategory":"Barber",
            "type":"Services"
        }
    ],
    "sg:phone":"+1 651 457 4959",
    "sg:postcode":"55118",
    "sg:province":"MN",
    "sg:tags":[
        "shop"
    ],
    "wof:name":"Diamond Jims Barber Shop",
    "wof:placetype":"venue"
},
  "geometry": {"coordinates":[-93.129139,44.907364],"type":"Point"}
}