{
  "type": "Feature",
  "properties": {
    "addr:full":"11062 102nd Ave Milaca MN 56353",
    "addr:housenumber":"11062",
    "addr:postcode":"56353",
    "addr:street":"102Nd Ave",
    "iso:country":"US",
    "sg:address":"11062 102nd Ave",
    "sg:city":"Milaca",
    "sg:phone":"+1 320 369 4248",
    "sg:postcode":"56353",
    "sg:province":"MN",
    "sg:tags":[
        "farm",
        "corn"
    ],
    "wof:name":"Pollema Farm",
    "wof:placetype":"venue"
},
  "geometry": {"coordinates":[-93.621077,45.706188],"type":"Point"}
}