{
  "type": "Feature",
  "properties": {
    "iso:country":"US",
    "sg:address":"17821 Highway 7",
    "sg:city":"Minnetonka",
    "sg:classifiers":[
        {
            "category":"Health Services",
            "subcategory":"Optometrist",
            "type":"Services"
        }
    ],
    "sg:phone":"+1 952 993 3150",
    "sg:postcode":"55345",
    "sg:province":"MN",
    "sg:tags":[
        "ophthalmologist"
    ],
    "wof:name":"Brownfield James A MD",
    "wof:placetype":"venue"
},
  "geometry": {"coordinates":[-93.504097,44.908798],"type":"Point"}
}