{
  "type": "Feature",
  "properties": {
    "addr:full":"8544 Highway 37 Iron MN 55751",
    "addr:housenumber":"8544",
    "addr:postcode":"55751",
    "addr:street":"Highway 37",
    "iso:country":"US",
    "sg:address":"8544 Highway 37",
    "sg:city":"Iron",
    "sg:classifiers":[
        {
            "category":"Transit Center",
            "subcategory":"Freight",
            "type":"Transportation"
        },
        {
            "category":"Freight",
            "type":"Transportation"
        }
    ],
    "sg:phone":"+1 218 744 2710",
    "sg:postcode":"55751",
    "sg:province":"MN",
    "sg:tags":[
        "local",
        "trucking-motor",
        "trucking"
    ],
    "wof:name":"Centennial Inc",
    "wof:placetype":"venue"
},
  "geometry": {"coordinates":[-92.580383,47.398665],"type":"Point"}
}