{
  "type": "Feature",
  "properties": {
    "iso:country":"US",
    "sg:address":"1008 Lakeview Dr",
    "sg:city":"Burnsville",
    "sg:classifiers":[
        {
            "category":"Professional",
            "subcategory":"Management & Consulting",
            "type":"Services"
        }
    ],
    "sg:phone":"+1 952 890 6580",
    "sg:postcode":"55337",
    "sg:province":"MN",
    "sg:tags":[
        "business"
    ],
    "wof:name":"Construction Cost Consulting",
    "wof:placetype":"venue"
},
  "geometry": {"coordinates":[-93.257304,44.760715],"type":"Point"}
}