{
  "type": "Feature",
  "properties": {
    "iso:country":"US",
    "sg:address":"8056 Reid Rd",
    "sg:city":"Britt",
    "sg:classifiers":[
        {
            "category":"Retail",
            "subcategory":"Auto Repair",
            "type":"Services"
        },
        {
            "category":"Wholesale",
            "subcategory":"Auto Parts",
            "type":"Manufacturing & Wholesale Goods"
        }
    ],
    "sg:phone":"+1 218 749 5186",
    "sg:postcode":"55710",
    "sg:province":"MN",
    "sg:tags":[
        "body",
        "general"
    ],
    "wof:name":"Anderson Auto Perfections Inc",
    "wof:placetype":"venue"
},
  "geometry": {"coordinates":[-92.54638300000001,47.633122],"type":"Point"}
}