{
  "type": "Feature",
  "properties": {
    "iso:country":"US",
    "sg:address":"100 E 1st St",
    "sg:city":"Chaska",
    "sg:classifiers":[
        {
            "category":"Shopping",
            "subcategory":"Computers & Home Electronics",
            "type":"Retail Goods"
        }
    ],
    "sg:phone":"+1 952 448 7370",
    "sg:postcode":"55318",
    "sg:province":"MN",
    "sg:tags":[
        "equipment",
        "dealer"
    ],
    "wof:name":"Computer Plus",
    "wof:placetype":"venue"
},
  "geometry": {"coordinates":[-93.599937,44.784261],"type":"Point"}
}