{
  "type": "Feature",
  "properties": {
    "iso:country":"US",
    "sg:address":"2001 Monks Ave",
    "sg:city":"Mankato",
    "sg:classifiers":[
        {
            "category":"Real Estate",
            "subcategory":"Real Estate Operator",
            "type":"Services"
        }
    ],
    "sg:phone":"+1 507 625 2001",
    "sg:postcode":"56001",
    "sg:province":"MN",
    "sg:tags":[
        "mobile",
        "home",
        "site"
    ],
    "wof:name":"University Mobile Home Park",
    "wof:placetype":"venue"
},
  "geometry": {"coordinates":[-93.98915700000001,44.14048],"type":"Point"}
}