{
  "type": "Feature",
  "properties": {
    "iso:country":"US",
    "sg:address":"21342 330th St",
    "sg:city":"Albany",
    "sg:classifiers":[
        {
            "category":"Farming",
            "subcategory":"Livestock Farm",
            "type":"Manufacturing & Wholesale Goods"
        }
    ],
    "sg:phone":"+1 320 845 2279",
    "sg:postcode":"56307",
    "sg:province":"MN",
    "sg:tags":[
        "beef",
        "feedlot",
        "cattle"
    ],
    "wof:name":"Dan Dobmeier",
    "wof:placetype":"venue"
},
  "geometry": {"coordinates":[-94.544383,45.600227],"type":"Point"}
}