{
  "type": "Feature",
  "properties": {
    "addr:full":"302 1st St SE Little Falls MN 56345",
    "addr:housenumber":"302",
    "addr:postcode":"56345",
    "addr:street":"1St St Se",
    "iso:country":"US",
    "sg:address":"302 1st St SE",
    "sg:city":"Little Falls",
    "sg:classifiers":[
        {
            "category":"Shopping",
            "subcategory":"Gifts & Souvenirs",
            "type":"Retail Goods"
        }
    ],
    "sg:phone":"+1 320 632 0484",
    "sg:postcode":"56345",
    "sg:province":"MN",
    "wof:name":"Ambiance At 53",
    "wof:placetype":"venue"
},
  "geometry": {"coordinates":[-94.36317099999999,45.97431],"type":"Point"}
}