{
  "type": "Feature",
  "properties": {
    "addr:full":"39853 140th St Brewster MN 56119",
    "addr:housenumber":"39853",
    "addr:postcode":"56119",
    "addr:street":"140Th St",
    "iso:country":"US",
    "sg:address":"39853 140th St",
    "sg:city":"Brewster",
    "sg:classifiers":[
        {
            "category":"Farming",
            "subcategory":"Farm",
            "type":"Manufacturing & Wholesale Goods"
        }
    ],
    "sg:phone":"+1 507 468 2293",
    "sg:postcode":"56119",
    "sg:province":"MN",
    "sg:tags":[
        "crop",
        "general"
    ],
    "wof:name":"James Haberman",
    "wof:placetype":"venue"
},
  "geometry": {"coordinates":[-95.455697,43.78976],"type":"Point"}
}