{
  "type": "Feature",
  "properties": {
    "iso:country":"US",
    "sg:address":"19567 State Hwy 114",
    "sg:city":"Starbuck",
    "sg:classifiers":[
        {
            "category":"Retail",
            "subcategory":"Auto Repair",
            "type":"Services"
        }
    ],
    "sg:phone":"+1 320 239 4303",
    "sg:postcode":"56381",
    "sg:province":"MN",
    "sg:tags":[
        "repairing",
        "automobile"
    ],
    "wof:name":"Mac's Auto Svc",
    "wof:placetype":"venue"
},
  "geometry": {"coordinates":[-95.53116900000001,45.619518],"type":"Point"}
}