{
  "type": "Feature",
  "properties": {
    "iso:country":"US",
    "sg:address":"2135 Birmingham St",
    "sg:city":"Maplewood",
    "sg:classifiers":[
        {
            "category":"Education",
            "subcategory":"School",
            "type":"Public Place"
        }
    ],
    "sg:phone":"+1 651 748 7000",
    "sg:postcode":"55109",
    "sg:province":"MN",
    "sg:website":"www.isd622.org",
    "wof:name":"Weaver Elementary School",
    "wof:placetype":"venue"
},
  "geometry": {"coordinates":[-93.040841,45.005988],"type":"Point"}
}