{
  "type": "Feature",
  "properties": {
    "addr:full":"122 E McKinley St Owatonna MN 55060",
    "addr:housenumber":"122",
    "addr:postcode":"55060",
    "addr:street":"E Mckinley St",
    "iso:country":"US",
    "sg:address":"122 E McKinley St",
    "sg:city":"Owatonna",
    "sg:classifiers":[
        {
            "category":"Social Services",
            "subcategory":"Child Care",
            "type":"Services"
        }
    ],
    "sg:phone":"+1 507 444 7900",
    "sg:postcode":"55060",
    "sg:province":"MN",
    "sg:tags":[
        "day"
    ],
    "wof:name":"Owatonna Community Education",
    "wof:placetype":"venue"
},
  "geometry": {"coordinates":[-93.225634,44.072986],"type":"Point"}
}