{
  "type": "Feature",
  "properties": {
    "addr:full":"10408 Quinn St NW Minneapolis MN 55433",
    "addr:housenumber":"10408",
    "addr:postcode":"55433",
    "addr:street":"Quinn St Nw",
    "iso:country":"US",
    "sg:address":"10408 Quinn St NW",
    "sg:city":"Minneapolis",
    "sg:classifiers":[
        {
            "category":"Building & Trades",
            "subcategory":"Locksmith",
            "type":"Services"
        }
    ],
    "sg:phone":"+1 763 354 1879",
    "sg:postcode":"55433",
    "sg:province":"MN",
    "sg:tags":[
        "key"
    ],
    "wof:name":"Locksmith Service",
    "wof:placetype":"venue"
},
  "geometry": {"coordinates":[-93.324102,45.158842],"type":"Point"}
}