{
  "type": "Feature",
  "properties": {
    "addr:full":"9321 Xylon Cir S Minneapolis MN 55438",
    "addr:housenumber":"9321",
    "addr:postcode":"55438",
    "addr:street":"Xylon Cir S",
    "iso:country":"US",
    "sg:address":"9321 Xylon Cir S",
    "sg:city":"Minneapolis",
    "sg:classifiers":[
        {
            "category":"Shopping",
            "subcategory":"Crafts & Fabrics",
            "type":"Retail Goods"
        }
    ],
    "sg:phone":"+1 952 941 0093",
    "sg:postcode":"55438",
    "sg:province":"MN",
    "sg:tags":[
        "florists'",
        "supply",
        "florist",
        "supplies-wholesale",
        "manufacturer"
    ],
    "wof:name":"Van Hoef Sales",
    "wof:placetype":"venue"
},
  "geometry": {"coordinates":[-93.389066,44.834392],"type":"Point"}
}