{
  "type": "Feature",
  "properties": {
    "iso:country":"US",
    "sg:address":"1285 Flamewood Dr NE",
    "sg:city":"Sauk Rapids",
    "sg:classifiers":[
        {
            "category":"Professional",
            "subcategory":"Business Services",
            "type":"Services"
        }
    ],
    "sg:phone":"+1 320 251 0060",
    "sg:postcode":"56379",
    "sg:province":"MN",
    "wof:name":"Tgs Express Inc",
    "wof:placetype":"venue"
},
  "geometry": {"coordinates":[-94.078543,45.58537],"type":"Point"}
}