{
  "type": "Feature",
  "properties": {
    "addr:full":"610 Golfview Ct Mantorville MN 55955",
    "addr:housenumber":"610",
    "addr:postcode":"55955",
    "addr:street":"Golfview Ct",
    "iso:country":"US",
    "sg:address":"610 Golfview Ct",
    "sg:city":"Mantorville",
    "sg:classifiers":[
        {
            "category":"Shopping",
            "subcategory":"Party Supplies",
            "type":"Retail Goods"
        },
        {
            "category":"Building & Trades",
            "subcategory":"Equipment Rental",
            "type":"Services"
        }
    ],
    "sg:phone":"+1 507 273 9996",
    "sg:postcode":"55955",
    "sg:province":"MN",
    "sg:tags":[
        "yard",
        "favors",
        "tents-rental",
        "decoration",
        "store"
    ],
    "sg:website":"http://www.picnictablerental.com",
    "wof:name":"Picnic Table Rental",
    "wof:placetype":"venue"
},
  "geometry": {"coordinates":[-92.73860500000001,44.060368],"type":"Point"}
}