{
  "type": "Feature",
  "properties": {
    "iso:country":"US",
    "sg:address":"68261 400th St",
    "sg:city":"Franklin",
    "sg:classifiers":[
        {
            "category":"Freight",
            "type":"Transportation"
        }
    ],
    "sg:phone":"+1 507 557 3191",
    "sg:postcode":"55333",
    "sg:province":"MN",
    "sg:tags":[
        "operator",
        "local",
        "trucking"
    ],
    "wof:name":"McCorquodale Trucking Inc",
    "wof:placetype":"venue"
},
  "geometry": {"coordinates":[-94.873549,44.571431],"type":"Point"}
}