{
  "type": "Feature",
  "properties": {
    "addr:full":"2520 Pilot Knob Rd. Suite 100 Mendota Heights MN 55120",
    "addr:housenumber":"2520",
    "addr:postcode":"55120",
    "addr:street":"Pilot Knob Rd. Suite 100",
    "iso:country":"US",
    "sg:address":"2520 Pilot Knob Rd. Suite 100",
    "sg:city":"Mendota Heights",
    "sg:classifiers":[
        {
            "category":"Professional",
            "subcategory":"Research",
            "type":"Services"
        }
    ],
    "sg:phone":"+1 651 730 1008",
    "sg:postcode":"55120",
    "sg:province":"MN",
    "sg:website":"http://www.travantipharma.com",
    "wof:name":"Travanti Pharma",
    "wof:placetype":"venue"
},
  "geometry": {"coordinates":[-93.166972,44.864311],"type":"Point"}
}