{
  "type": "Feature",
  "properties": {
    "addr:full":"14201 Burngarten Dr Burnsville MN 55306",
    "addr:housenumber":"14201",
    "addr:postcode":"55306",
    "addr:street":"Burngarten Dr",
    "iso:country":"US",
    "sg:address":"14201 Burngarten Dr",
    "sg:city":"Burnsville",
    "sg:classifiers":[
        {
            "category":"Restaurant",
            "type":"Food & Drink"
        }
    ],
    "sg:phone":"+1 952 698 1888",
    "sg:postcode":"55306",
    "sg:province":"MN",
    "sg:tags":[
        "traditional",
        "american"
    ],
    "sg:website":"www.portercreek.com",
    "wof:name":"Porter Creek Hardwood Grill",
    "wof:placetype":"venue"
},
  "geometry": {"coordinates":[-93.296334,44.745714],"type":"Point"}
}