{
  "type": "Feature",
  "properties": {
    "addr:full":"770 Bayfield St St Paul MN 55107",
    "addr:housenumber":"770",
    "addr:postcode":"55107",
    "addr:street":"Bayfield St",
    "iso:country":"US",
    "sg:address":"770 Bayfield St",
    "sg:city":"St Paul",
    "sg:classifiers":[
        {
            "category":"Government",
            "subcategory":"Office",
            "type":"Public Place"
        }
    ],
    "sg:phone":"+1 651 291 0462",
    "sg:postcode":"55107",
    "sg:province":"MN",
    "sg:tags":[
        "federal",
        "security"
    ],
    "wof:name":"US Civil Air Patrol",
    "wof:placetype":"venue"
},
  "geometry": {"coordinates":[-93.06665099999999,44.942213],"type":"Point"}
}