{
  "type": "Feature",
  "properties": {
    "addr:full":"37055 195th St Springfield MN 56087",
    "addr:housenumber":"37055",
    "addr:postcode":"56087",
    "addr:street":"195Th St",
    "iso:country":"US",
    "sg:address":"37055 195th St",
    "sg:city":"Springfield",
    "sg:classifiers":[
        {
            "category":"Shopping",
            "subcategory":"Books",
            "type":"Retail Goods"
        }
    ],
    "sg:phone":"+1 507 723 5615",
    "sg:postcode":"56087",
    "sg:province":"MN",
    "sg:tags":[
        "bible"
    ],
    "wof:name":"Gideons International",
    "wof:placetype":"venue"
},
  "geometry": {"coordinates":[-94.906505,44.246207],"type":"Point"}
}