{
  "type": "Feature",
  "properties": {
    "addr:full":"914 S 8th St Minneapolis MN 55404",
    "addr:housenumber":"914",
    "addr:postcode":"55404",
    "addr:street":"S 8Th St",
    "iso:country":"US",
    "sg:address":"914 S 8th St",
    "sg:city":"Minneapolis",
    "sg:classifiers":[
        {
            "category":"Health Services",
            "subcategory":"Doctor",
            "type":"Services"
        }
    ],
    "sg:phone":"+1 612 347 5950",
    "sg:postcode":"55404",
    "sg:province":"MN",
    "sg:tags":[
        "physician",
        "surgeon"
    ],
    "wof:name":"Swan Suzanne K MD",
    "wof:placetype":"venue"
},
  "geometry": {"coordinates":[-93.260238,44.970495],"type":"Point"}
}