{
  "type": "Feature",
  "properties": {
    "iso:country":"US",
    "sg:address":"10078 Bluff Rd",
    "sg:city":"Eden Prairie",
    "sg:classifiers":[
        {
            "category":"Autos & Motor Vehicles",
            "subcategory":"Fuel & Gas Station",
            "type":"Retail Goods"
        }
    ],
    "sg:phone":"+1 952 946 8882",
    "sg:postcode":"55347",
    "sg:province":"MN",
    "sg:tags":[
        "station",
        "gasoline"
    ],
    "wof:name":"Arco",
    "wof:placetype":"venue"
},
  "geometry": {"coordinates":[-93.40455799999999,44.813495],"type":"Point"}
}