{
  "type": "Feature",
  "properties": {
    "iso:country":"US",
    "sg:address":"329 S Owasso Blvd",
    "sg:city":"Saint Paul",
    "sg:classifiers":[
        {
            "category":"Professional",
            "type":"Services"
        }
    ],
    "sg:phone":"+1 651 490 5253",
    "sg:postcode":"55113",
    "sg:province":"MN",
    "wof:name":"Midwest Atm Inc",
    "wof:placetype":"venue"
},
  "geometry": {"coordinates":[-93.11611600000001,45.034402],"type":"Point"}
}