{
  "type": "Feature",
  "properties": {
    "iso:country":"US",
    "sg:address":"2011 8th St SE",
    "sg:city":"East Grand Forks",
    "sg:classifiers":[
        {
            "category":"Freight",
            "type":"Transportation"
        }
    ],
    "sg:phone":"+1 218 773 1273",
    "sg:postcode":"56721",
    "sg:province":"MN",
    "sg:tags":[
        "hauling",
        "trucking"
    ],
    "wof:name":"Corbett Trucking",
    "wof:placetype":"venue"
},
  "geometry": {"coordinates":[-96.992347,47.910963],"type":"Point"}
}