{
  "type": "Feature",
  "properties": {
    "addr:full":"2239 Carter Ave Saint Paul MN 55108",
    "addr:housenumber":"2239",
    "addr:postcode":"55108",
    "addr:street":"Carter Ave",
    "iso:country":"US",
    "sg:address":"2239 Carter Ave",
    "sg:city":"Saint Paul",
    "sg:classifiers":[
        {
            "category":"Professional",
            "subcategory":"Lawyer & Legal Services",
            "type":"Services"
        }
    ],
    "sg:phone":"+1 651 644 1739",
    "sg:postcode":"55108",
    "sg:province":"MN",
    "wof:name":"Labine Mark Attorney At Law",
    "wof:placetype":"venue"
},
  "geometry": {"coordinates":[-93.194199,44.981201],"type":"Point"}
}