{
  "type": "Feature",
  "properties": {
    "addr:full":"1815 Wisconsin Ave Benson MN 56215",
    "addr:housenumber":"1815",
    "addr:postcode":"56215",
    "addr:street":"Wisconsin Ave",
    "iso:country":"US",
    "sg:address":"1815 Wisconsin Ave",
    "sg:city":"Benson",
    "sg:classifiers":[
        {
            "category":"Health Services",
            "subcategory":"Doctor",
            "type":"Services"
        }
    ],
    "sg:phone":"+1 320 589 7600",
    "sg:postcode":"56215",
    "sg:province":"MN",
    "sg:tags":[
        "physician",
        "surgeon"
    ],
    "wof:name":"Michael J Holte MD",
    "wof:placetype":"venue"
},
  "geometry": {"coordinates":[-95.60951900000001,45.314733],"type":"Point"}
}