{
  "type": "Feature",
  "properties": {
    "addr:full":"11142 Co Rd 94 SW Holmes City MN 56341",
    "addr:housenumber":"11142",
    "addr:postcode":"56341",
    "addr:street":"Co Rd 94 Sw",
    "iso:country":"US",
    "sg:address":"11142 Co Rd 94 SW",
    "sg:city":"Holmes City",
    "sg:classifiers":[
        {
            "category":"Food & Beverages",
            "subcategory":"Groceries & Convenience Stores",
            "type":"Retail Goods"
        }
    ],
    "sg:phone":"+1 320 886 5511",
    "sg:postcode":"56341",
    "sg:province":"MN",
    "sg:tags":[
        "grocer"
    ],
    "wof:name":"Blade's Store",
    "wof:placetype":"venue"
},
  "geometry": {"coordinates":[-95.546964,45.834801],"type":"Point"}
}