{
  "type": "Feature",
  "properties": {
    "addr:full":"1421 Bemidji Ave N Bemidji MN 56601",
    "addr:housenumber":"1421",
    "addr:postcode":"56601",
    "addr:street":"Bemidji Ave N",
    "iso:country":"US",
    "sg:address":"1421 Bemidji Ave N",
    "sg:city":"Bemidji",
    "sg:classifiers":[
        {
            "category":"Insurance",
            "subcategory":"Insurance Agent",
            "type":"Services"
        }
    ],
    "sg:phone":"+1 218 444 8320",
    "sg:postcode":"56601",
    "sg:province":"MN",
    "wof:name":"Country Insurance & Fincl Svcs",
    "wof:placetype":"venue"
},
  "geometry": {"coordinates":[-94.87968600000001,47.482676],"type":"Point"}
}