{
  "type": "Feature",
  "properties": {
    "addr:full":"962 University Ave W St Paul MN 55104",
    "addr:housenumber":"962",
    "addr:postcode":"55104",
    "addr:street":"University Ave W",
    "iso:country":"US",
    "sg:address":"962 University Ave W",
    "sg:city":"St Paul",
    "sg:classifiers":[
        {
            "category":"Social Services",
            "type":"Services"
        }
    ],
    "sg:phone":"+1 651 642 1379",
    "sg:postcode":"55104",
    "sg:province":"MN",
    "sg:tags":[
        "organization",
        "welfare"
    ],
    "wof:name":"Minnesota Chinese Svc Ctr",
    "wof:placetype":"venue"
},
  "geometry": {"coordinates":[-93.140287,44.955649],"type":"Point"}
}