{
  "type": "Feature",
  "properties": {
    "addr:full":"425 Main St W Cannon Falls MN 55009",
    "addr:housenumber":"425",
    "addr:postcode":"55009",
    "addr:street":"Main St W",
    "iso:country":"US",
    "sg:address":"425 Main St W",
    "sg:city":"Cannon Falls",
    "sg:classifiers":[
        {
            "category":"Food & Beverages",
            "subcategory":"Groceries & Convenience Stores",
            "type":"Retail Goods"
        }
    ],
    "sg:phone":"+1 507 263 3643",
    "sg:postcode":"55009",
    "sg:province":"MN",
    "sg:tags":[
        "grocer"
    ],
    "wof:name":"Econofoods",
    "wof:placetype":"venue"
},
  "geometry": {"coordinates":[-92.905969,44.506816],"type":"Point"}
}