{
  "type": "Feature",
  "properties": {
    "iso:country":"US",
    "sg:address":"2000 W 90th St",
    "sg:city":"Minneapolis",
    "sg:classifiers":[
        {
            "category":"Manufacturing",
            "subcategory":"Printing",
            "type":"Manufacturing & Wholesale Goods"
        }
    ],
    "sg:phone":"+1 952 881 2780",
    "sg:postcode":"55431",
    "sg:province":"MN",
    "sg:tags":[
        "manufacturer",
        "greeting",
        "cards-wholesale",
        "card",
        "mfg"
    ],
    "wof:name":"D R L Art",
    "wof:placetype":"venue"
},
  "geometry": {"coordinates":[-93.304802,44.84079],"type":"Point"}
}