{
  "type": "Feature",
  "properties": {
    "iso:country":"US",
    "sg:address":"223 N 1st St",
    "sg:city":"Wykoff",
    "sg:classifiers":[
        {
            "category":"Government",
            "subcategory":"Office",
            "type":"Public Place"
        }
    ],
    "sg:phone":"+1 507 352 4686",
    "sg:postcode":"55945",
    "sg:province":"MN",
    "sg:tags":[
        "village"
    ],
    "wof:name":"Township Hall",
    "wof:placetype":"venue"
},
  "geometry": {"coordinates":[-91.999257,44.310287],"type":"Point"}
}