{
  "type": "Feature",
  "properties": {
    "addr:full":"2400 Avon Dr Mound MN 55364",
    "addr:housenumber":"2400",
    "addr:postcode":"55364",
    "addr:street":"Avon Dr Mound",
    "iso:country":"US",
    "sg:address":"2400 Avon Dr",
    "sg:city":"Mound",
    "sg:classifiers":[
        {
            "category":"Utilities",
            "subcategory":"Telephone",
            "type":"Services"
        }
    ],
    "sg:phone":"+1 952 474 5499",
    "sg:postcode":"55364",
    "sg:province":"MN",
    "sg:tags":[
        "telecommunication"
    ],
    "wof:name":"Popp Industries Inc",
    "wof:placetype":"venue"
},
  "geometry": {"coordinates":[-93.651651,44.932993],"type":"Point"}
}