{
  "type": "Feature",
  "properties": {
    "addr:full":"57759 Fort Rd New Ulm MN 56073",
    "addr:housenumber":"57759",
    "addr:postcode":"56073",
    "addr:street":"Fort Rd",
    "iso:country":"US",
    "sg:address":"57759 Fort Rd",
    "sg:city":"New Ulm",
    "sg:classifiers":[
        {
            "category":"Retail",
            "subcategory":"Repair Shop",
            "type":"Services"
        },
        {
            "category":"Retail",
            "subcategory":"Auto Repair",
            "type":"Services"
        }
    ],
    "sg:phone":"+1 507 359 5126",
    "sg:postcode":"56073",
    "sg:province":"MN",
    "sg:tags":[
        "repairing",
        "automobile"
    ],
    "wof:name":"Andy's Repair",
    "wof:placetype":"venue"
},
  "geometry": {"coordinates":[-94.42400000000001,44.365527],"type":"Point"}
}