{
  "type": "Feature",
  "properties": {
    "addr:full":"25 Seymour Ave SE Minneapolis MN 55414",
    "addr:housenumber":"25",
    "addr:postcode":"55414",
    "addr:street":"Seymour Ave Se",
    "iso:country":"US",
    "sg:address":"25 Seymour Ave SE",
    "sg:city":"Minneapolis",
    "sg:classifiers":[
        {
            "category":"Education",
            "subcategory":"Music School",
            "type":"Public Place"
        },
        {
            "category":"Education",
            "subcategory":"School",
            "type":"Public Place"
        }
    ],
    "sg:phone":"+1 612 331 1283",
    "sg:postcode":"55414",
    "sg:province":"MN",
    "wof:name":"Accordion Productions",
    "wof:placetype":"venue"
},
  "geometry": {"coordinates":[-93.213138,44.968102],"type":"Point"}
}