{
  "type": "Feature",
  "properties": {
    "iso:country":"US",
    "sg:address":"600 Stinson Blvd",
    "sg:city":"Minneapolis",
    "sg:classifiers":[
        {
            "category":"Shopping",
            "subcategory":"Department Store",
            "type":"Retail Goods"
        }
    ],
    "sg:phone":"+1 612 379 0549",
    "sg:postcode":"55413",
    "sg:province":"MN",
    "wof:name":"Coborn's Incorporated",
    "wof:placetype":"venue"
},
  "geometry": {"coordinates":[-93.227104,44.99513],"type":"Point"}
}