{
  "type": "Feature",
  "properties": {
    "addr:full":"20251 State Hwy 34 Pelican Rapids MN 56572",
    "addr:housenumber":"20251",
    "addr:postcode":"56572",
    "addr:street":"State Hwy 34",
    "iso:country":"US",
    "sg:address":"20251 State Hwy 34",
    "sg:city":"Pelican Rapids",
    "sg:classifiers":[
        {
            "category":"Farming",
            "subcategory":"Farm",
            "type":"Manufacturing & Wholesale Goods"
        }
    ],
    "sg:phone":"+1 218 863 4475",
    "sg:postcode":"56572",
    "sg:province":"MN",
    "sg:tags":[
        "crop",
        "general"
    ],
    "wof:name":"Barn-D Farm",
    "wof:placetype":"venue"
},
  "geometry": {"coordinates":[-96.07276899999999,46.656696],"type":"Point"}
}