{
  "type": "Feature",
  "properties": {
    "addr:full":"10449 Utah Rd Minneapolis MN 55438",
    "addr:housenumber":"10449",
    "addr:postcode":"55438",
    "addr:street":"Utah Rd",
    "iso:country":"US",
    "sg:address":"10449 Utah Rd",
    "sg:city":"Minneapolis",
    "sg:classifiers":[
        {
            "category":"Professional",
            "subcategory":"Business Services",
            "type":"Services"
        }
    ],
    "sg:phone":"+1 952 941 0207",
    "sg:postcode":"55438",
    "sg:province":"MN",
    "wof:name":"Sonata Sales & Marketing",
    "wof:placetype":"venue"
},
  "geometry": {"coordinates":[-93.384845,44.81227],"type":"Point"}
}