{
  "type": "Feature",
  "properties": {
    "iso:country":"US",
    "sg:address":"225 6th St S",
    "sg:city":"Minneapolis",
    "sg:classifiers":[
        {
            "category":"Professional",
            "subcategory":"Lawyer & Legal Services",
            "type":"Services"
        }
    ],
    "sg:phone":"+1 612 373 8509",
    "sg:postcode":"55415",
    "sg:province":"MN",
    "wof:name":"William K Ecklund",
    "wof:placetype":"venue"
},
  "geometry": {"coordinates":[-93.267608,44.976188],"type":"Point"}
}