{
  "type": "Feature",
  "properties": {
    "iso:country":"US",
    "sg:address":"500 E Depue Ave",
    "sg:city":"Olivia",
    "sg:classifiers":[
        {
            "category":"Government",
            "subcategory":"Office",
            "type":"Public Place"
        }
    ],
    "sg:phone":"+1 320 523 3645",
    "sg:postcode":"56277",
    "sg:province":"MN",
    "sg:tags":[
        "county",
        "taxation"
    ],
    "wof:name":"Renville County Assessor",
    "wof:placetype":"venue"
},
  "geometry": {"coordinates":[-94.98331899999999,44.775496],"type":"Point"}
}