{
  "type": "Feature",
  "properties": {
    "addr:full":"1117 Aldrich Ave N Minneapolis MN 55411",
    "addr:housenumber":"1117",
    "addr:postcode":"55411",
    "addr:street":"Aldrich Ave N",
    "iso:country":"US",
    "sg:address":"1117 Aldrich Ave N",
    "sg:city":"Minneapolis",
    "sg:classifiers":[
        {
            "category":"Wholesale",
            "subcategory":"Scrap",
            "type":"Manufacturing & Wholesale Goods"
        },
        {
            "category":"Wholesale",
            "subcategory":"Electrical",
            "type":"Manufacturing & Wholesale Goods"
        }
    ],
    "sg:phone":"+1 612 521 8555",
    "sg:postcode":"55411",
    "sg:province":"MN",
    "sg:tags":[
        "distributor",
        "wire",
        "cable",
        "cable-electric"
    ],
    "sg:website":"http://www.sterlingwireandcable.com",
    "wof:name":"Sterling Wire & Cable",
    "wof:placetype":"venue"
},
  "geometry": {"coordinates":[-93.2895,44.990749],"type":"Point"}
}