{
  "type": "Feature",
  "properties": {
    "addr:full":"15470 Co Rd 35 W Cokato MN 55321",
    "addr:housenumber":"15470;35",
    "addr:postcode":"55321",
    "addr:street":"Co Rd;W",
    "iso:country":"US",
    "sg:address":"15470 Co Rd 35 W",
    "sg:city":"Cokato",
    "sg:classifiers":[
        {
            "category":"Building & Trades",
            "subcategory":"Construction",
            "type":"Services"
        }
    ],
    "sg:phone":"+1 320 286 6638",
    "sg:postcode":"55321",
    "sg:province":"MN",
    "sg:tags":[
        "contractor"
    ],
    "wof:name":"Pete Halonen Drywall",
    "wof:placetype":"venue"
},
  "geometry": {"coordinates":[-94.205129,45.15258],"type":"Point"}
}