{
  "type": "Feature",
  "properties": {
    "addr:full":"469 State Hwy 30 Pipestone MN 56164",
    "addr:housenumber":"469",
    "addr:postcode":"56164",
    "addr:street":"State Hwy 30",
    "iso:country":"US",
    "sg:address":"469 State Hwy 30",
    "sg:city":"Pipestone",
    "sg:phone":"+1 507 825 2089",
    "sg:postcode":"56164",
    "sg:province":"MN",
    "sg:tags":[
        "beef",
        "farm",
        "corn",
        "soybean",
        "cattle",
        "feedlot"
    ],
    "wof:name":"Ronald Hellie",
    "wof:placetype":"venue"
},
  "geometry": {"coordinates":[-96.38168400000001,43.994511],"type":"Point"}
}