{
  "type": "Feature",
  "properties": {
    "addr:full":"6750 France Ave S Edina MN 55435",
    "addr:housenumber":"6750",
    "addr:postcode":"55435",
    "addr:street":"France Ave S",
    "iso:country":"US",
    "sg:address":"6750 France Ave S",
    "sg:city":"Edina",
    "sg:classifiers":[
        {
            "category":"Real Estate",
            "subcategory":"Real Estate Agent",
            "type":"Services"
        }
    ],
    "sg:phone":"+1 952 926 6600",
    "sg:postcode":"55435",
    "sg:province":"MN",
    "sg:tags":[
        "management"
    ],
    "wof:name":"Southdale Office Ctr",
    "wof:placetype":"venue"
},
  "geometry": {"coordinates":[-93.329015,44.88269],"type":"Point"}
}