{
  "type": "Feature",
  "properties": {
    "addr:full":"1410 Grace Ave SW Willmar MN 56201",
    "addr:housenumber":"1410",
    "addr:postcode":"56201",
    "addr:street":"Grace Ave Sw",
    "iso:country":"US",
    "sg:address":"1410 Grace Ave SW",
    "sg:city":"Willmar",
    "sg:classifiers":[
        {
            "category":"Manufacturing",
            "subcategory":"Metals",
            "type":"Manufacturing & Wholesale Goods"
        }
    ],
    "sg:phone":"+1 320 235 8767",
    "sg:postcode":"56201",
    "sg:province":"MN",
    "sg:tags":[
        "mfg"
    ],
    "wof:name":"Door Specialties",
    "wof:placetype":"venue"
},
  "geometry": {"coordinates":[-95.060864,45.112703],"type":"Point"}
}