{
  "type": "Feature",
  "properties": {
    "addr:full":"110 4th St E Northfield MN 55057",
    "addr:housenumber":"110",
    "addr:postcode":"55057",
    "addr:street":"4Th St E",
    "iso:country":"US",
    "sg:address":"110 4th St E",
    "sg:city":"Northfield",
    "sg:classifiers":[
        {
            "category":"Restaurant",
            "type":"Food & Drink"
        }
    ],
    "sg:menulink":"http://www.allmenus.com/mn/northfield/58456-dominos-pizza/menu/",
    "sg:phone":"+1 507 663 1221",
    "sg:postcode":"55057",
    "sg:province":"MN",
    "sg:tags":[
        "american",
        "wing",
        "pizza"
    ],
    "wof:name":"Domino's Pizza",
    "wof:placetype":"venue"
},
  "geometry": {"coordinates":[-93.159986,44.456248],"type":"Point"}
}