{
  "type": "Feature",
  "properties": {
    "addr:full":"51595 Basswood Rd W Stanchfield MN 55080",
    "addr:housenumber":"51595",
    "addr:postcode":"55080",
    "addr:street":"Basswood Rd W Stanchfield",
    "iso:country":"US",
    "sg:address":"51595 Basswood Rd W",
    "sg:city":"Stanchfield",
    "sg:phone":"+1 320 396 3855",
    "sg:postcode":"55080",
    "sg:province":"MN",
    "sg:tags":[
        "farm",
        "soybean"
    ],
    "wof:name":"Dan Loerzel",
    "wof:placetype":"venue"
},
  "geometry": {"coordinates":[-93.134953,45.698514],"type":"Point"}
}