{
  "type": "Feature",
  "properties": {
    "iso:country":"US",
    "sg:address":"2801 Westwood Rd",
    "sg:city":"Wayzata",
    "sg:classifiers":[
        {
            "category":"Organizations",
            "subcategory":"Religious Organization",
            "type":"Services"
        }
    ],
    "sg:phone":"+1 952 471 8429",
    "sg:postcode":"55391",
    "sg:province":"MN",
    "sg:tags":[
        "church"
    ],
    "wof:name":"St Martin's By The Lake Church",
    "wof:placetype":"venue"
},
  "geometry": {"coordinates":[-93.595985,44.940692],"type":"Point"}
}