{
  "type": "Feature",
  "properties": {
    "addr:full":"11527 Palmer Cir Bloomington MN 55437",
    "addr:housenumber":"11527",
    "addr:postcode":"55437",
    "addr:street":"Palmer Cir",
    "iso:country":"US",
    "sg:address":"11527 Palmer Cir",
    "sg:city":"Bloomington",
    "sg:classifiers":[
        {
            "category":"Banks & Credit Unions",
            "subcategory":"Bank",
            "type":"Services"
        }
    ],
    "sg:phone":"+1 952 884 7088",
    "sg:postcode":"55437",
    "sg:province":"MN",
    "sg:tags":[
        "mortgage",
        "loan",
        "broker",
        "real estate"
    ],
    "wof:name":"Dometri Mortgage Corporation",
    "wof:placetype":"venue"
},
  "geometry": {"coordinates":[-93.341751,44.795415],"type":"Point"}
}