{
  "type": "Feature",
  "properties": {
    "addr:full":"3737 Baker Rd Hopkins MN 55305",
    "addr:housenumber":"3737",
    "addr:postcode":"55305",
    "addr:street":"Baker Rd",
    "iso:country":"US",
    "sg:address":"3737 Baker Rd",
    "sg:city":"Hopkins",
    "sg:classifiers":[
        {
            "category":"Retail",
            "subcategory":"Repair Shop",
            "type":"Services"
        }
    ],
    "sg:phone":"+1 952 935 9241",
    "sg:postcode":"55305",
    "sg:province":"MN",
    "sg:tags":[
        "typewriter"
    ],
    "wof:name":"Gittins Typewriter Co Inc",
    "wof:placetype":"venue"
},
  "geometry": {"coordinates":[-93.44687,44.934941],"type":"Point"}
}