{
  "type": "Feature",
  "properties": {
    "addr:full":"925 E Hennepin Ave Minneapolis MN 55414",
    "addr:housenumber":"925",
    "addr:postcode":"55414",
    "addr:street":"E Hennepin Ave",
    "iso:country":"US",
    "sg:address":"925 E Hennepin Ave",
    "sg:city":"Minneapolis",
    "sg:phone":"+1 612 379 1226",
    "sg:postcode":"55414",
    "sg:province":"MN",
    "sg:tags":[
        "equipment",
        "commercial",
        "repair"
    ],
    "wof:name":"Twin City Restaurant Equipment",
    "wof:placetype":"venue"
},
  "geometry": {"coordinates":[-93.23970799999999,44.991495],"type":"Point"}
}