{
  "type": "Feature",
  "properties": {
    "addr:full":"2959 Queen Ave Slayton MN 56172",
    "addr:housenumber":"2959",
    "addr:postcode":"56172",
    "addr:street":"Queen Ave",
    "iso:country":"US",
    "sg:address":"2959 Queen Ave",
    "sg:city":"Slayton",
    "sg:classifiers":[
        {
            "category":"Social Services",
            "type":"Services"
        }
    ],
    "sg:phone":"+1 507 836 8636",
    "sg:postcode":"56172",
    "sg:province":"MN",
    "sg:tags":[
        "counselor"
    ],
    "wof:name":"Shetek Behavior Solutions",
    "wof:placetype":"venue"
},
  "geometry": {"coordinates":[-95.747725,43.982994],"type":"Point"}
}