{
  "type": "Feature",
  "properties": {
    "addr:full":"217 E Walnut St Mankato MN 56001",
    "addr:housenumber":"217",
    "addr:postcode":"56001",
    "addr:street":"E Walnut St",
    "iso:country":"US",
    "sg:address":"217 E Walnut St",
    "sg:city":"Mankato",
    "sg:classifiers":[
        {
            "category":"Insurance",
            "subcategory":"Insurance Agent",
            "type":"Services"
        }
    ],
    "sg:phone":"+1 507 345 8700",
    "sg:postcode":"56001",
    "sg:province":"MN",
    "wof:name":"New York Life Insurance Co",
    "wof:placetype":"venue"
},
  "geometry": {"coordinates":[-94.002272,44.165709],"type":"Point"}
}