{
  "type": "Feature",
  "properties": {
    "iso:country":"US",
    "sg:address":"901 Colbert Ave SW",
    "sg:city":"Buffalo",
    "sg:classifiers":[
        {
            "category":"Professional",
            "subcategory":"Management & Consulting",
            "type":"Services"
        }
    ],
    "sg:phone":"+1 763 684 0331",
    "sg:postcode":"55313",
    "sg:province":"MN",
    "sg:tags":[
        "business"
    ],
    "wof:name":"Q1 Consulting Services LLC",
    "wof:placetype":"venue"
},
  "geometry": {"coordinates":[-93.9363,45.139034],"type":"Point"}
}