{
  "type": "Feature",
  "properties": {
    "addr:full":"1136 Grand Ave St Paul MN 55105",
    "addr:housenumber":"1136",
    "addr:postcode":"55105",
    "addr:street":"Grand Ave",
    "iso:country":"US",
    "sg:address":"1136 Grand Ave",
    "sg:city":"St Paul",
    "sg:classifiers":[
        {
            "category":"Shopping",
            "subcategory":"Used Merchandise",
            "type":"Retail Goods"
        }
    ],
    "sg:phone":"+1 651 222 2819",
    "sg:postcode":"55105",
    "sg:province":"MN",
    "sg:tags":[
        "clothing"
    ],
    "wof:name":"My Sisters' Closet",
    "wof:placetype":"venue"
},
  "geometry": {"coordinates":[-93.148033,44.939925],"type":"Point"}
}