{
  "type": "Feature",
  "properties": {
    "addr:full":"615 Southview Blvd South St Paul MN 55075",
    "addr:housenumber":"615",
    "addr:postcode":"55075",
    "addr:street":"Southview Blvd",
    "iso:country":"US",
    "sg:address":"615 Southview Blvd",
    "sg:city":"South St Paul",
    "sg:classifiers":[
        {
            "category":"Building & Trades",
            "subcategory":"Plumbing",
            "type":"Services"
        }
    ],
    "sg:phone":"+1 651 455 6323",
    "sg:postcode":"55075",
    "sg:province":"MN",
    "sg:tags":[
        "heating",
        "contractor"
    ],
    "wof:name":"Heights Mechanical Co",
    "wof:placetype":"venue"
},
  "geometry": {"coordinates":[-93.042243,44.888815],"type":"Point"}
}