{
  "type": "Feature",
  "properties": {
    "iso:country":"US",
    "sg:address":"9277 W 125th St",
    "sg:city":"Savage",
    "sg:classifiers":[
        {
            "category":"Transit Center",
            "subcategory":"Freight",
            "type":"Transportation"
        },
        {
            "category":"Freight",
            "type":"Transportation"
        }
    ],
    "sg:phone":"+1 952 496 9438",
    "sg:postcode":"55378",
    "sg:province":"MN",
    "sg:tags":[
        "local",
        "trucking-motor",
        "trucking"
    ],
    "wof:name":"Go Truckline",
    "wof:placetype":"venue"
},
  "geometry": {"coordinates":[-93.39586300000001,44.777087],"type":"Point"}
}