{
  "type": "Feature",
  "properties": {
    "iso:country":"US",
    "sg:address":"783 US Hwy 75",
    "sg:city":"Pipestone",
    "sg:classifiers":[
        {
            "category":"Farming",
            "subcategory":"Livestock Farm",
            "type":"Manufacturing & Wholesale Goods"
        }
    ],
    "sg:phone":"+1 507 825 4522",
    "sg:postcode":"56164",
    "sg:province":"MN",
    "sg:tags":[
        "beef",
        "feedlot",
        "cattle"
    ],
    "wof:name":"Lyle Siebenahler",
    "wof:placetype":"venue"
},
  "geometry": {"coordinates":[-96.307452,44.008391],"type":"Point"}
}