{
  "type": "Feature",
  "properties": {
    "addr:full":"5750 Madison St NE Fridley MN 55432",
    "addr:housenumber":"5750",
    "addr:postcode":"55432",
    "addr:street":"Madison St Ne",
    "iso:country":"US",
    "sg:address":"5750 Madison St NE",
    "sg:city":"Fridley",
    "sg:classifiers":[
        {
            "category":"Building & Trades",
            "subcategory":"Electrical",
            "type":"Services"
        }
    ],
    "sg:phone":"+1 763 574 9015",
    "sg:postcode":"55432",
    "sg:province":"MN",
    "sg:tags":[
        "electric",
        "contractor"
    ],
    "wof:name":"Wire-Rite Electric Co",
    "wof:placetype":"venue"
},
  "geometry": {"coordinates":[-93.254795,45.071713],"type":"Point"}
}