{
  "type": "Feature",
  "properties": {
    "addr:full":"1200 18th St E Hastings MN 55033",
    "addr:housenumber":"1200",
    "addr:postcode":"55033",
    "addr:street":"18Th St E",
    "iso:country":"US",
    "sg:address":"1200 18th St E",
    "sg:city":"Hastings",
    "sg:classifiers":[
        {
            "category":"Government",
            "subcategory":"Office",
            "type":"Public Place"
        }
    ],
    "sg:phone":"+1 651 438 8504",
    "sg:postcode":"55033",
    "sg:province":"MN",
    "sg:tags":[
        "veteran"
    ],
    "wof:name":"Hastings Veterans Home",
    "wof:placetype":"venue"
},
  "geometry": {"coordinates":[-92.839658,44.727361],"type":"Point"}
}