{
  "type": "Feature",
  "properties": {
    "addr:full":"1896 Adams St Mankato MN 56001",
    "addr:housenumber":"1896",
    "addr:postcode":"56001",
    "addr:street":"Adams St",
    "iso:country":"US",
    "sg:address":"1896 Adams St",
    "sg:city":"Mankato",
    "sg:classifiers":[
        {
            "category":"Autos & Motor Vehicles",
            "subcategory":"Auto Supplies",
            "type":"Retail Goods"
        }
    ],
    "sg:phone":"+1 507 389 4428",
    "sg:postcode":"56001",
    "sg:province":"MN",
    "sg:tags":[
        "repair",
        "general"
    ],
    "wof:name":"Sears Auto Center",
    "wof:placetype":"venue"
},
  "geometry": {"coordinates":[-93.949782,44.170503],"type":"Point"}
}