{
  "type": "Feature",
  "properties": {
    "iso:country":"US",
    "sg:address":"105 South St",
    "sg:city":"Sanborn",
    "sg:classifiers":[
        {
            "category":"Organizations",
            "subcategory":"Religious Organization",
            "type":"Services"
        }
    ],
    "sg:phone":"+1 507 648 3601",
    "sg:postcode":"56083",
    "sg:province":"MN",
    "sg:tags":[
        "church"
    ],
    "wof:name":"Zion Evangelical Lutheran Chr",
    "wof:placetype":"venue"
},
  "geometry": {"coordinates":[-95.13153699999999,44.209953],"type":"Point"}
}