{
  "type": "Feature",
  "properties": {
    "iso:country":"US",
    "sg:address":"172 139th Ave NW",
    "sg:city":"Andover",
    "sg:classifiers":[
        {
            "category":"Building & Trades",
            "subcategory":"Construction",
            "type":"Services"
        }
    ],
    "sg:phone":"+1 763 785 9605",
    "sg:postcode":"55304",
    "sg:province":"MN",
    "sg:tags":[
        "concrete",
        "cutting",
        "breaking",
        "sawing",
        "contractor"
    ],
    "wof:name":"Quality Cutting & Coring Inc",
    "wof:placetype":"venue"
},
  "geometry": {"coordinates":[-93.27045699999999,45.223984],"type":"Point"}
}