{
  "type": "Feature",
  "properties": {
    "addr:full":"37556 Co Rd 16 Clements MN 56224",
    "addr:housenumber":"37556;16",
    "addr:postcode":"56224",
    "addr:street":"Co Rd",
    "iso:country":"US",
    "sg:address":"37556 Co Rd 16",
    "sg:city":"Clements",
    "sg:classifiers":[
        {
            "category":"Wholesale",
            "subcategory":"Machinery & Supplies",
            "type":"Manufacturing & Wholesale Goods"
        }
    ],
    "sg:phone":"+1 507 692 2291",
    "sg:postcode":"56224",
    "sg:province":"MN",
    "sg:tags":[
        "building",
        "equipment",
        "livestock"
    ],
    "wof:name":"Walters Building Specialties",
    "wof:placetype":"venue"
},
  "geometry": {"coordinates":[-95.035747,44.383736],"type":"Point"}
}