{
  "type": "Feature",
  "properties": {
    "addr:full":"1521 Como Ave SE Minneapolis MN 55414",
    "addr:housenumber":"1521",
    "addr:postcode":"55414",
    "addr:street":"Como Ave Se",
    "iso:country":"US",
    "sg:address":"1521 Como Ave SE",
    "sg:city":"Minneapolis",
    "sg:classifiers":[
        {
            "category":"Banks & Credit Unions",
            "subcategory":"Investment Brokerage",
            "type":"Services"
        }
    ],
    "sg:phone":"+1 612 436 4346",
    "sg:postcode":"55414",
    "sg:province":"MN",
    "sg:tags":[
        "advisory",
        "financial"
    ],
    "wof:name":"Ned Financial Svc",
    "wof:placetype":"venue"
},
  "geometry": {"coordinates":[-93.23049,44.98791],"type":"Point"}
}