{
  "type": "Feature",
  "properties": {
    "iso:country":"US",
    "sg:address":"9601 Newton Ave S Ste B",
    "sg:city":"Minneapolis",
    "sg:classifiers":[
        {
            "category":"Building & Trades",
            "subcategory":"Construction",
            "type":"Services"
        }
    ],
    "sg:phone":"+1 952 835 7700",
    "sg:postcode":"55431",
    "sg:province":"MN",
    "sg:tags":[
        "supply",
        "radiators-heating",
        "sales"
    ],
    "wof:name":"Robert James Sales Inc",
    "wof:placetype":"venue"
},
  "geometry": {"coordinates":[-93.306,44.829929],"type":"Point"}
}