{
  "type": "Feature",
  "properties": {
    "addr:full":"7878 Market Blvd Chanhassen MN 55317",
    "addr:housenumber":"7878",
    "addr:postcode":"55317",
    "addr:street":"Market Blvd",
    "iso:country":"US",
    "sg:address":"7878 Market Blvd",
    "sg:city":"Chanhassen",
    "sg:classifiers":[
        {
            "category":"Shopping",
            "subcategory":"Tobacco",
            "type":"Retail Goods"
        }
    ],
    "sg:phone":"+1 952 906 3000",
    "sg:postcode":"55317",
    "sg:province":"MN",
    "sg:tags":[
        "product"
    ],
    "wof:name":"Chanhassen Tobacco",
    "wof:placetype":"venue"
},
  "geometry": {"coordinates":[-93.538062,44.860372],"type":"Point"}
}