{
  "type": "Feature",
  "properties": {
    "iso:country":"US",
    "sg:address":"2550 University Ave W",
    "sg:city":"Saint Paul",
    "sg:classifiers":[
        {
            "category":"Professional",
            "subcategory":"Management & Consulting",
            "type":"Services"
        }
    ],
    "sg:phone":"+1 651 645 4699",
    "sg:postcode":"55114",
    "sg:province":"MN",
    "sg:tags":[
        "planning",
        "financial",
        "asset"
    ],
    "wof:name":"Farley Planning Group Inc",
    "wof:placetype":"venue"
},
  "geometry": {"coordinates":[-93.20182699999999,44.965624],"type":"Point"}
}