{
  "type": "Feature",
  "properties": {
    "addr:full":"133 US Hwy 71 N Sauk Centre MN 56378",
    "addr:housenumber":"133",
    "addr:postcode":"56378",
    "addr:street":"Us Hwy 71 N",
    "iso:country":"US",
    "sg:address":"133 US Hwy 71 N",
    "sg:city":"Sauk Centre",
    "sg:classifiers":[
        {
            "category":"Retail",
            "subcategory":"Auto Repair",
            "type":"Services"
        }
    ],
    "sg:phone":"+1 320 352 6992",
    "sg:postcode":"56378",
    "sg:province":"MN",
    "sg:tags":[
        "repairing",
        "automobile"
    ],
    "wof:name":"Kavy's Auto & Truck Garage",
    "wof:placetype":"venue"
},
  "geometry": {"coordinates":[-94.952134,45.742142],"type":"Point"}
}