{
  "type": "Feature",
  "properties": {
    "iso:country":"US",
    "sg:address":"9149 N Shore Trl N",
    "sg:city":"Forest Lake",
    "sg:classifiers":[
        {
            "category":"Building & Trades",
            "subcategory":"Landscaping Services",
            "type":"Services"
        }
    ],
    "sg:phone":"+1 651 464 5999",
    "sg:postcode":"55025",
    "sg:province":"MN",
    "wof:name":"Jnt Landscaping",
    "wof:placetype":"venue"
},
  "geometry": {"coordinates":[-92.944254,45.275359],"type":"Point"}
}