{
  "type": "Feature",
  "properties": {
    "addr:full":"1535 Mississippi St NE Minneapolis MN 55432",
    "addr:housenumber":"1535",
    "addr:postcode":"55432",
    "addr:street":"Mississippi St Ne",
    "iso:country":"US",
    "sg:address":"1535 Mississippi St NE",
    "sg:city":"Minneapolis",
    "sg:classifiers":[
        {
            "category":"Shopping",
            "subcategory":"Hobbies, Toys, & Games",
            "type":"Retail Goods"
        },
        {
            "category":"Shopping",
            "subcategory":"Crafts & Fabrics",
            "type":"Retail Goods"
        }
    ],
    "sg:phone":"+1 763 571 9614",
    "sg:postcode":"55432",
    "sg:province":"MN",
    "sg:tags":[
        "shop",
        "model",
        "hobby",
        "supply"
    ],
    "wof:name":"Mississippi Woods And Crafts",
    "wof:placetype":"venue"
},
  "geometry": {"coordinates":[-93.231696,45.08596],"type":"Point"}
}