{
  "type": "Feature",
  "properties": {
    "addr:full":"1901 26th Ave NW Saint Paul MN 55112",
    "addr:housenumber":"1901",
    "addr:postcode":"55112",
    "addr:street":"26Th Ave Nw",
    "iso:country":"US",
    "sg:address":"1901 26th Ave NW",
    "sg:city":"Saint Paul",
    "sg:classifiers":[
        {
            "category":"Professional",
            "type":"Services"
        }
    ],
    "sg:phone":"+1 651 636 6259",
    "sg:postcode":"55112",
    "sg:province":"MN",
    "wof:name":"Solemn Resolutions LLC",
    "wof:placetype":"venue"
},
  "geometry": {"coordinates":[-93.22011000000001,45.078821],"type":"Point"}
}