{
  "type": "Feature",
  "properties": {
    "iso:country":"US",
    "sg:address":"121 Spring St",
    "sg:city":"Duluth",
    "sg:classifiers":[
        {
            "category":"Recreation",
            "subcategory":"Marina",
            "type":"Entertainment"
        }
    ],
    "sg:phone":"+1 218 628 3578",
    "sg:postcode":"55808",
    "sg:province":"MN",
    "sg:tags":[
        "boat",
        "motor"
    ],
    "sg:website":"www.spiritlakemarina.com",
    "wof:name":"Spirit Lake Marine Inc",
    "wof:placetype":"venue"
},
  "geometry": {"coordinates":[-92.206487,46.708038],"type":"Point"}
}