{
  "type": "Feature",
  "properties": {
    "iso:country":"US",
    "sg:address":"2597 190th Ave",
    "sg:city":"Marshall",
    "sg:phone":"+1 507 865 4580",
    "sg:postcode":"56258",
    "sg:province":"MN",
    "sg:tags":[
        "farm",
        "corn",
        "wheat",
        "soybean"
    ],
    "wof:name":"Runholt Family Farm Partnr",
    "wof:placetype":"venue"
},
  "geometry": {"coordinates":[-95.917704,44.424628],"type":"Point"}
}