{
  "type": "Feature",
  "properties": {
    "addr:full":"325 1st Ave SE Glenwood MN 56334",
    "addr:housenumber":"325",
    "addr:postcode":"56334",
    "addr:street":"1St Ave Se",
    "iso:country":"US",
    "sg:address":"325 1st Ave SE",
    "sg:city":"Glenwood",
    "sg:classifiers":[
        {
            "category":"Organizations",
            "subcategory":"Non-profit Organization",
            "type":"Services"
        }
    ],
    "sg:phone":"+1 320 634 3240",
    "sg:postcode":"56334",
    "sg:province":"MN",
    "wof:name":"Dove International",
    "wof:placetype":"venue"
},
  "geometry": {"coordinates":[-95.38499400000001,45.649408],"type":"Point"}
}