{
  "type": "Feature",
  "properties": {
    "addr:full":"728 E 1st St Litchfield MN 55355",
    "addr:housenumber":"728",
    "addr:postcode":"55355",
    "addr:street":"E 1St St",
    "iso:country":"US",
    "sg:address":"728 E 1st St",
    "sg:city":"Litchfield",
    "sg:classifiers":[
        {
            "category":"Retail",
            "subcategory":"Laundry & Dry Cleaning",
            "type":"Services"
        }
    ],
    "sg:phone":"+1 320 593 1294",
    "sg:postcode":"55355",
    "sg:province":"MN",
    "wof:name":"Eagle Carpet & Floor Cleaners",
    "wof:placetype":"venue"
},
  "geometry": {"coordinates":[-94.51477300000001,45.126224],"type":"Point"}
}