{
  "type": "Feature",
  "properties": {
    "addr:full":"8941 48th Ave N Minneapolis MN 55428",
    "addr:housenumber":"8941",
    "addr:postcode":"55428",
    "addr:street":"48Th Ave N",
    "iso:country":"US",
    "sg:address":"8941 48th Ave N",
    "sg:city":"Minneapolis",
    "sg:classifiers":[
        {
            "category":"Professional",
            "subcategory":"Credit Reporting & Collection",
            "type":"Services"
        }
    ],
    "sg:phone":"+1 763 533 4501",
    "sg:postcode":"55428",
    "sg:province":"MN",
    "sg:tags":[
        "debt",
        "adjuster"
    ],
    "sg:website":"http://www.accountmanager.com",
    "wof:name":"Account Manager",
    "wof:placetype":"venue"
},
  "geometry": {"coordinates":[-93.39346399999999,45.04168],"type":"Point"}
}