{
  "type": "Feature",
  "properties": {
    "addr:full":"7953 State Hwy 55 Rockford MN 55373",
    "addr:housenumber":"7953",
    "addr:postcode":"55373",
    "addr:street":"State Hwy 55",
    "iso:country":"US",
    "sg:address":"7953 State Hwy 55",
    "sg:city":"Rockford",
    "sg:classifiers":[
        {
            "category":"Organizations",
            "subcategory":"Religious Organization",
            "type":"Services"
        }
    ],
    "sg:phone":"+1 763 477 9126",
    "sg:postcode":"55373",
    "sg:province":"MN",
    "sg:website":"www.riverwoodcovenant.org",
    "wof:name":"Riverwood Covenant Church",
    "wof:placetype":"venue"
},
  "geometry": {"coordinates":[-93.711191,45.0797],"type":"Point"}
}