{
  "type": "Feature",
  "properties": {
    "addr:full":"505 3rd Ave SE Pine City MN 55063",
    "addr:housenumber":"505",
    "addr:postcode":"55063",
    "addr:street":"3Rd Ave Se",
    "iso:country":"US",
    "sg:address":"505 3rd Ave SE",
    "sg:city":"Pine City",
    "sg:classifiers":[
        {
            "category":"Insurance",
            "subcategory":"Insurance Agent",
            "type":"Services"
        }
    ],
    "sg:phone":"+1 320 629 2927",
    "sg:postcode":"55063",
    "sg:province":"MN",
    "wof:name":"American Family Insurance Agt",
    "wof:placetype":"venue"
},
  "geometry": {"coordinates":[-92.97042500000001,45.826664],"type":"Point"}
}