{
  "type": "Feature",
  "properties": {
    "addr:full":"1214 10th Ave N Saint James MN 56081",
    "addr:housenumber":"1214",
    "addr:postcode":"56081",
    "addr:street":"10Th Ave N",
    "iso:country":"US",
    "sg:address":"1214 10th Ave N",
    "sg:city":"Saint James",
    "sg:classifiers":[
        {
            "category":"Social Services",
            "type":"Services"
        }
    ],
    "sg:phone":"+1 507 375 3380",
    "sg:postcode":"56081",
    "sg:province":"MN",
    "wof:name":"National Assoc Retired Persons",
    "wof:placetype":"venue"
},
  "geometry": {"coordinates":[-94.62245799999999,43.989988],"type":"Point"}
}