{
  "type": "Feature",
  "properties": {
    "iso:country":"US",
    "sg:address":"505 Cedardale Dr SE",
    "sg:city":"Owatonna",
    "sg:classifiers":[
        {
            "category":"Social Services",
            "subcategory":"Child Care",
            "type":"Services"
        }
    ],
    "sg:phone":"+1 507 446 8762",
    "sg:postcode":"55060",
    "sg:province":"MN",
    "sg:tags":[
        "nursery",
        "day"
    ],
    "wof:name":"Trenda Inc",
    "wof:placetype":"venue"
},
  "geometry": {"coordinates":[-93.218031,44.060599],"type":"Point"}
}