{
  "type": "Feature",
  "properties": {
    "addr:full":"58120 238th St Mankato MN 56001",
    "addr:housenumber":"58120",
    "addr:postcode":"56001",
    "addr:street":"238Th St",
    "iso:country":"US",
    "sg:address":"58120 238th St",
    "sg:city":"Mankato",
    "sg:classifiers":[
        {
            "category":"Retail",
            "subcategory":"Portrait Studio",
            "type":"Services"
        }
    ],
    "sg:phone":"+1 507 388 6446",
    "sg:postcode":"56001",
    "sg:province":"MN",
    "sg:tags":[
        "photographer"
    ],
    "sg:website":"www.gl-photo.com",
    "wof:name":"G L Photo",
    "wof:placetype":"venue"
},
  "geometry": {"coordinates":[-93.95787300000001,44.225171],"type":"Point"}
}