{
  "type": "Feature",
  "properties": {
    "addr:full":"16711 Duluth Ave SE Prior Lake MN 55372",
    "addr:housenumber":"16711",
    "addr:postcode":"55372",
    "addr:street":"Duluth Ave Se",
    "iso:country":"US",
    "sg:address":"16711 Duluth Ave SE",
    "sg:city":"Prior Lake",
    "sg:classifiers":[
        {
            "category":"Restaurant",
            "type":"Food & Drink"
        }
    ],
    "sg:menulink":"http://www.allmenus.com/mn/prior-lake/151209-subway/menu/",
    "sg:phone":"+1 952 440 7827",
    "sg:postcode":"55372",
    "sg:province":"MN",
    "sg:tags":[
        "american",
        "sandwich"
    ],
    "wof:name":"Subway",
    "wof:placetype":"venue"
},
  "geometry": {"coordinates":[-93.43059100000001,44.707239],"type":"Point"}
}