{
  "type": "Feature",
  "properties": {
    "iso:country":"US",
    "sg:address":"8101 Scandia Trl N",
    "sg:city":"Forest Lake",
    "sg:classifiers":[
        {
            "category":"Manufacturing",
            "subcategory":"Metals",
            "type":"Manufacturing & Wholesale Goods"
        }
    ],
    "sg:phone":"+1 651 464 0202",
    "sg:postcode":"55025",
    "sg:province":"MN",
    "sg:tags":[
        "coating"
    ],
    "wof:name":"Polyurea Midwest",
    "wof:placetype":"venue"
},
  "geometry": {"coordinates":[-92.940405,45.262047],"type":"Point"}
}