{
  "type": "Feature",
  "properties": {
    "iso:country":"US",
    "sg:address":"208 W 98th St",
    "sg:city":"Bloomington",
    "sg:classifiers":[
        {
            "category":"Shopping",
            "subcategory":"Bicycles & Sporting Goods",
            "type":"Retail Goods"
        }
    ],
    "sg:phone":"+1 952 884 1990",
    "sg:postcode":"55420",
    "sg:province":"MN",
    "sg:tags":[
        "skating",
        "equipment",
        "supply"
    ],
    "sg:website":"www.pierceskateandski.com",
    "wof:name":"Pierce Skate & Ski",
    "wof:placetype":"venue"
},
  "geometry": {"coordinates":[-93.283378,44.82636],"type":"Point"}
}