{
  "type": "Feature",
  "properties": {
    "addr:full":"7980 Ranchers Rd NE Fridley MN 55432",
    "addr:postcode":"7980;55432",
    "addr:street":"Ranchers Rd Ne",
    "iso:country":"US",
    "sg:address":"7980 Ranchers Rd NE",
    "sg:city":"Fridley",
    "sg:classifiers":[
        {
            "category":"Manufacturing",
            "subcategory":"Tools & Machinery",
            "type":"Manufacturing & Wholesale Goods"
        }
    ],
    "sg:phone":"+1 763 785 2056",
    "sg:postcode":"55432",
    "sg:province":"MN",
    "sg:tags":[
        "machine",
        "shop"
    ],
    "sg:website":"www.c-machine.com",
    "wof:name":"C Machine Co",
    "wof:placetype":"venue"
},
  "geometry": {"coordinates":[-93.266184,45.113012],"type":"Point"}
}