{
  "type": "Feature",
  "properties": {
    "addr:full":"380 E Wheelock Pkwy Saint Paul MN 55101",
    "addr:housenumber":"380",
    "addr:postcode":"55101",
    "addr:street":"E Wheelock Pkwy",
    "iso:country":"US",
    "sg:address":"380 E Wheelock Pkwy",
    "sg:city":"Saint Paul",
    "sg:classifiers":[
        {
            "category":"Retail",
            "subcategory":"Repair Shop",
            "type":"Services"
        }
    ],
    "sg:phone":"+1 651 776 9093",
    "sg:postcode":"55101",
    "sg:province":"MN",
    "wof:name":"Black Stone Cleaning Inc",
    "wof:placetype":"venue"
},
  "geometry": {"coordinates":[-93.08365999999999,44.990117],"type":"Point"}
}