{
  "type": "Feature",
  "properties": {
    "iso:country":"US",
    "sg:address":"1583 4th Ave SW",
    "sg:city":"New Prague",
    "sg:classifiers":[
        {
            "category":"Building & Trades",
            "subcategory":"Construction",
            "type":"Services"
        }
    ],
    "sg:phone":"+1 952 758 3552",
    "sg:postcode":"56071",
    "sg:province":"MN",
    "sg:tags":[
        "concrete",
        "contractor"
    ],
    "wof:name":"Cavanaugh Concrete Co",
    "wof:placetype":"venue"
},
  "geometry": {"coordinates":[-93.585403,44.528608],"type":"Point"}
}