{
  "type": "Feature",
  "properties": {
    "iso:country":"US",
    "sg:address":"14400 Nicollet Ct",
    "sg:city":"Burnsville",
    "sg:classifiers":[
        {
            "category":"Travel",
            "subcategory":"Hotels & Motels",
            "type":"Entertainment"
        }
    ],
    "sg:phone":"+1 952 435 6366",
    "sg:postcode":"55306",
    "sg:province":"MN",
    "wof:name":"Hampton Inn",
    "wof:placetype":"venue"
},
  "geometry": {"coordinates":[-93.28119700000001,44.743698],"type":"Point"}
}