{
  "type": "Feature",
  "properties": {
    "addr:full":"213 Minnesota Ave N Aitkin MN 56431",
    "addr:housenumber":"213",
    "addr:postcode":"56431",
    "addr:street":"Minnesota Ave N",
    "iso:country":"US",
    "sg:address":"213 Minnesota Ave N",
    "sg:city":"Aitkin",
    "sg:classifiers":[
        {
            "category":"Manufacturing",
            "subcategory":"Printing",
            "type":"Manufacturing & Wholesale Goods"
        }
    ],
    "sg:phone":"+1 218 927 3761",
    "sg:postcode":"56431",
    "sg:province":"MN",
    "sg:tags":[
        "newspaper"
    ],
    "sg:website":"www.aitkinage.com",
    "wof:name":"Aitkin Independent Age",
    "wof:placetype":"venue"
},
  "geometry": {"coordinates":[-93.706699,46.534299],"type":"Point"}
}