{
  "type": "Feature",
  "properties": {
    "iso:country":"US",
    "sg:address":"1835 S 7th St",
    "sg:city":"Brainerd",
    "sg:classifiers":[
        {
            "category":"Professional",
            "subcategory":"Advertising",
            "type":"Services"
        }
    ],
    "sg:phone":"+1 218 829 1156",
    "sg:postcode":"56401",
    "sg:province":"MN",
    "sg:tags":[
        "counselor"
    ],
    "wof:name":"Callender Carney Advertising",
    "wof:placetype":"venue"
},
  "geometry": {"coordinates":[-94.199797,46.337493],"type":"Point"}
}