{
  "type": "Feature",
  "properties": {
    "iso:country":"US",
    "sg:address":"1810 Birch St",
    "sg:city":"Saint Paul",
    "sg:classifiers":[
        {
            "category":"Building & Trades",
            "subcategory":"Construction",
            "type":"Services"
        }
    ],
    "sg:phone":"+1 651 261 8648",
    "sg:postcode":"55110",
    "sg:province":"MN",
    "sg:tags":[
        "residential"
    ],
    "wof:name":"Macallan Construction Inc",
    "wof:placetype":"venue"
},
  "geometry": {"coordinates":[-93.02161,45.061053],"type":"Point"}
}