{
  "type": "Feature",
  "properties": {
    "addr:full":"14 Central Ave N Kensington MN 56343",
    "addr:housenumber":"14",
    "addr:postcode":"56343",
    "addr:street":"Central Ave N",
    "iso:country":"US",
    "sg:address":"14 Central Ave N",
    "sg:city":"Kensington",
    "sg:classifiers":[
        {
            "category":"Professional",
            "subcategory":"Printing & Photocopies",
            "type":"Services"
        }
    ],
    "sg:phone":"+1 320 965 2297",
    "sg:postcode":"56343",
    "sg:province":"MN",
    "sg:tags":[
        "lithographer"
    ],
    "wof:name":"Digital Print Solutions",
    "wof:placetype":"venue"
},
  "geometry": {"coordinates":[-95.694835,45.778989],"type":"Point"}
}