{
  "type": "Feature",
  "properties": {
    "iso:country":"US",
    "sg:address":"14260 23rd Ave N",
    "sg:city":"Minneapolis",
    "sg:classifiers":[
        {
            "category":"Banks & Credit Unions",
            "subcategory":"Bank",
            "type":"Services"
        }
    ],
    "sg:phone":"+1 763 557 8014",
    "sg:postcode":"55447",
    "sg:province":"MN",
    "sg:tags":[
        "loan",
        "real estate"
    ],
    "wof:name":"Lexis Mortgage & Loan Corp",
    "wof:placetype":"venue"
},
  "geometry": {"coordinates":[-93.46047900000001,45.003994],"type":"Point"}
}