{
  "type": "Feature",
  "properties": {
    "iso:country":"US",
    "sg:address":"20965 S Diamond Lake Rd",
    "sg:city":"Rogers",
    "sg:classifiers":[
        {
            "category":"Fast Food",
            "type":"Food & Drink"
        },
        {
            "category":"Restaurant",
            "type":"Food & Drink"
        },
        {
            "category":"Food & Beverages",
            "subcategory":"Groceries & Convenience Stores",
            "type":"Retail Goods"
        }
    ],
    "sg:phone":"+1 763 428 6455",
    "sg:postcode":"55374",
    "sg:province":"MN",
    "sg:tags":[
        "shop",
        "american",
        "sandwich",
        "take"
    ],
    "sg:website":"http://www.quiznos.com",
    "wof:name":"Quiznos Classic Subs",
    "wof:placetype":"venue"
},
  "geometry": {"coordinates":[-93.543615,45.199432],"type":"Point"}
}