{
  "type": "Feature",
  "properties": {
    "iso:country":"US",
    "sg:address":"203 Pine St",
    "sg:city":"Onamia",
    "sg:classifiers":[
        {
            "category":"Building & Trades",
            "subcategory":"Electrical",
            "type":"Services"
        }
    ],
    "sg:phone":"+1 320 532 1004",
    "sg:postcode":"56359",
    "sg:province":"MN",
    "sg:tags":[
        "electric",
        "contractor"
    ],
    "wof:name":"Rum River Electric Inc",
    "wof:placetype":"venue"
},
  "geometry": {"coordinates":[-93.667745,46.072643],"type":"Point"}
}