{
  "type": "Feature",
  "properties": {
    "iso:country":"US",
    "sg:address":"2283 Heath Ave N",
    "sg:city":"St Paul",
    "sg:classifiers":[
        {
            "category":"Restaurant",
            "type":"Food & Drink"
        }
    ],
    "sg:phone":"+1 612 866 4411",
    "sg:postcode":"55128",
    "sg:province":"MN",
    "wof:name":"Hennessy's On Nicollet Inc",
    "wof:placetype":"venue"
},
  "geometry": {"coordinates":[-92.953597,44.981591],"type":"Point"}
}