{
  "type": "Feature",
  "properties": {
    "addr:full":"1786 Minnehaha Ave E Saint Paul MN 55119",
    "addr:housenumber":"1786",
    "addr:postcode":"55119",
    "addr:street":"Minnehaha Ave E",
    "iso:country":"US",
    "sg:address":"1786 Minnehaha Ave E",
    "sg:city":"Saint Paul",
    "sg:classifiers":[
        {
            "category":"Restaurant",
            "type":"Food & Drink"
        }
    ],
    "sg:menulink":"http://www.allmenus.com/mn/st-paul/94035-the-little-oven/menu/",
    "sg:phone":"+1 651 735 4944",
    "sg:postcode":"55119",
    "sg:province":"MN",
    "sg:tags":[
        "italian"
    ],
    "wof:name":"The Little Oven",
    "wof:placetype":"venue"
},
  "geometry": {"coordinates":[-93.025006,44.962886],"type":"Point"}
}