{
  "type": "Feature",
  "properties": {
    "iso:country":"US",
    "sg:address":"1316 M St NE",
    "sg:city":"Brainerd",
    "sg:classifiers":[
        {
            "category":"Social Services",
            "subcategory":"Child Care",
            "type":"Services"
        }
    ],
    "sg:phone":"+1 218 828 7811",
    "sg:postcode":"56401",
    "sg:province":"MN",
    "sg:tags":[
        "day"
    ],
    "wof:name":"Circle of Friends",
    "wof:placetype":"venue"
},
  "geometry": {"coordinates":[-94.17156799999999,46.372128],"type":"Point"}
}