{
  "type": "Feature",
  "properties": {
    "iso:country":"US",
    "sg:address":"277 W Irvine Ave",
    "sg:city":"Saint Paul",
    "sg:classifiers":[
        {
            "category":"Professional",
            "subcategory":"Management & Consulting",
            "type":"Services"
        }
    ],
    "sg:phone":"+1 651 291 0192",
    "sg:postcode":"55102",
    "sg:province":"MN",
    "wof:name":"Buzz Product Development",
    "wof:placetype":"venue"
},
  "geometry": {"coordinates":[-93.11301899999999,44.942819],"type":"Point"}
}