{
  "type": "Feature",
  "properties": {
    "iso:country":"US",
    "sg:address":"1819 N Broadway",
    "sg:city":"Rochester",
    "sg:classifiers":[
        {
            "category":"Building & Trades",
            "subcategory":"Construction",
            "type":"Services"
        }
    ],
    "sg:phone":"+1 507 289 4169",
    "sg:postcode":"55906",
    "sg:province":"MN",
    "sg:tags":[
        "tile",
        "dealer"
    ],
    "wof:name":"T-M Construction Svc",
    "wof:placetype":"venue"
},
  "geometry": {"coordinates":[-92.460221,44.042886],"type":"Point"}
}