{
  "type": "Feature",
  "properties": {
    "addr:full":"301 Central Ave Ste 1 Nashwauk MN 55769",
    "addr:housenumber":"301",
    "addr:postcode":"55769",
    "addr:street":"Central Ave Ste 1 Nashwauk",
    "iso:country":"US",
    "sg:address":"301 Central Ave Ste 1",
    "sg:city":"Nashwauk",
    "sg:classifiers":[
        {
            "category":"Government",
            "subcategory":"City Hall",
            "type":"Public Place"
        },
        {
            "category":"Government",
            "subcategory":"Office",
            "type":"Public Place"
        }
    ],
    "sg:phone":"+1 218 885 1210",
    "sg:postcode":"55769",
    "sg:province":"MN",
    "sg:tags":[
        "town",
        "township",
        "planner",
        "government-city",
        "village"
    ],
    "wof:name":"City Hall",
    "wof:placetype":"venue"
},
  "geometry": {"coordinates":[-93.16589399999999,47.380421],"type":"Point"}
}