{
  "type": "Feature",
  "properties": {
    "addr:full":"26310 Co Rd 15 Redwood Falls MN 56283",
    "addr:housenumber":"26310;15",
    "addr:postcode":"56283",
    "addr:street":"Co Rd",
    "iso:country":"US",
    "sg:address":"26310 Co Rd 15",
    "sg:city":"Redwood Falls",
    "sg:phone":"+1 507 641 2336",
    "sg:postcode":"56283",
    "sg:province":"MN",
    "sg:tags":[
        "farm",
        "grain",
        "cash"
    ],
    "wof:name":"Mike Gaffney",
    "wof:placetype":"venue"
},
  "geometry": {"coordinates":[-95.155992,44.622943],"type":"Point"}
}