{
  "type": "Feature",
  "properties": {
    "addr:full":"204 Front St E Brandon MN 56315",
    "addr:housenumber":"204",
    "addr:postcode":"56315",
    "addr:street":"Front St E",
    "iso:country":"US",
    "sg:address":"204 Front St E",
    "sg:city":"Brandon",
    "sg:classifiers":[
        {
            "category":"Wholesale",
            "subcategory":"Farm Supplies",
            "type":"Manufacturing & Wholesale Goods"
        }
    ],
    "sg:phone":"+1 320 524 2286",
    "sg:postcode":"56315",
    "sg:province":"MN",
    "sg:tags":[
        "fertilizer"
    ],
    "sg:website":"www.proagfarmers.com",
    "wof:name":"Pro Ag Farmer Cooperative",
    "wof:placetype":"venue"
},
  "geometry": {"coordinates":[-95.597819,45.963625],"type":"Point"}
}