{
  "type": "Feature",
  "properties": {
    "iso:country":"US",
    "sg:address":"2 W Pine St",
    "sg:city":"Circle Pines",
    "sg:classifiers":[
        {
            "category":"Social Services",
            "subcategory":"Child Care",
            "type":"Services"
        }
    ],
    "sg:phone":"+1 763 786 2868",
    "sg:postcode":"55014",
    "sg:province":"MN",
    "wof:name":"Especially For Children",
    "wof:placetype":"venue"
},
  "geometry": {"coordinates":[-93.13650199999999,45.211044],"type":"Point"}
}