{
  "type": "Feature",
  "properties": {
    "addr:full":"6231 Long Lake Rd Makinen MN 55763",
    "addr:housenumber":"6231",
    "addr:postcode":"55763",
    "addr:street":"Long Lake Rd",
    "iso:country":"US",
    "sg:address":"6231 Long Lake Rd",
    "sg:city":"Makinen",
    "sg:classifiers":[
        {
            "category":"Transit Center",
            "subcategory":"Freight",
            "type":"Transportation"
        },
        {
            "category":"Freight",
            "type":"Transportation"
        }
    ],
    "sg:phone":"+1 218 744 2692",
    "sg:postcode":"55763",
    "sg:province":"MN",
    "sg:tags":[
        "local",
        "trucking-motor",
        "trucking"
    ],
    "wof:name":"Brandon Crep Trucking",
    "wof:placetype":"venue"
},
  "geometry": {"coordinates":[-92.345336,47.313364],"type":"Point"}
}