{
  "type": "Feature",
  "properties": {
    "addr:full":"2111 Knapp St St Paul MN 55108",
    "addr:housenumber":"2111",
    "addr:postcode":"55108",
    "addr:street":"Knapp St",
    "iso:country":"US",
    "sg:address":"2111 Knapp St",
    "sg:city":"St Paul",
    "sg:classifiers":[
        {
            "category":"Professional",
            "subcategory":"Management & Consulting",
            "type":"Services"
        }
    ],
    "sg:phone":"+1 651 645 6058",
    "sg:postcode":"55108",
    "sg:province":"MN",
    "sg:tags":[
        "consultant",
        "business"
    ],
    "wof:name":"Ted Bowman Trainer Educator",
    "wof:placetype":"venue"
},
  "geometry": {"coordinates":[-93.18973,44.979743],"type":"Point"}
}