{
  "type": "Feature",
  "properties": {
    "iso:country":"US",
    "sg:address":"4218 Valley Industrial Blvd S",
    "sg:city":"Shakopee",
    "sg:classifiers":[
        {
            "category":"Food & Beverages",
            "subcategory":"Groceries & Convenience Stores",
            "type":"Retail Goods"
        }
    ],
    "sg:phone":"+1 952 445 1350",
    "sg:postcode":"55379",
    "sg:province":"MN",
    "wof:name":"Trudeau Foods",
    "wof:placetype":"venue"
},
  "geometry": {"coordinates":[-93.46669900000001,44.793946],"type":"Point"}
}