{
  "type": "Feature",
  "properties": {
    "addr:full":"813 Myrtle St W Stillwater MN 55082",
    "addr:housenumber":"813",
    "addr:postcode":"55082",
    "addr:street":"Myrtle St W",
    "iso:country":"US",
    "sg:address":"813 Myrtle St W",
    "sg:city":"Stillwater",
    "sg:classifiers":[
        {
            "category":"Organizations",
            "subcategory":"Religious Organization",
            "type":"Services"
        }
    ],
    "sg:phone":"+1 651 439 1880",
    "sg:postcode":"55082",
    "sg:province":"MN",
    "sg:tags":[
        "place",
        "worship",
        "church"
    ],
    "sg:website":"http://www.umc.org",
    "wof:name":"First United Methodist Church",
    "wof:placetype":"venue"
},
  "geometry": {"coordinates":[-92.81807999999999,45.054852],"type":"Point"}
}