{
  "type": "Feature",
  "properties": {
    "addr:full":"913 Pershing Blvd Worthington MN 56187",
    "addr:housenumber":"913",
    "addr:postcode":"56187",
    "addr:street":"Pershing Blvd",
    "iso:country":"US",
    "sg:address":"913 Pershing Blvd",
    "sg:city":"Worthington",
    "sg:classifiers":[
        {
            "category":"Social Services",
            "subcategory":"Child Care",
            "type":"Services"
        }
    ],
    "sg:phone":"+1 507 376 3936",
    "sg:postcode":"56187",
    "sg:province":"MN",
    "sg:tags":[
        "daycare",
        "provider"
    ],
    "wof:name":"Paulette Yates",
    "wof:placetype":"venue"
},
  "geometry": {"coordinates":[-95.622922,43.624222],"type":"Point"}
}