{
  "type": "Feature",
  "properties": {
    "iso:country":"US",
    "sg:address":"122 1st St SE",
    "sg:city":"Fairfax",
    "sg:classifiers":[
        {
            "category":"Banks & Credit Unions",
            "subcategory":"Investment Brokerage",
            "type":"Services"
        },
        {
            "category":"Insurance",
            "subcategory":"Hazard Insurance",
            "type":"Services"
        }
    ],
    "sg:phone":"+1 507 426 7715",
    "sg:postcode":"55332",
    "sg:province":"MN",
    "sg:tags":[
        "agent",
        "resume"
    ],
    "wof:name":"Swanson Howard Insurance Agcy",
    "wof:placetype":"venue"
},
  "geometry": {"coordinates":[-94.71934299999999,44.527674],"type":"Point"}
}