{
  "type": "Feature",
  "properties": {
    "iso:country":"US",
    "sg:address":"2170 Co Rd D E",
    "sg:city":"Maplewood",
    "sg:classifiers":[
        {
            "category":"Recreation",
            "type":"Entertainment"
        }
    ],
    "sg:phone":"+1 651 748 8645",
    "sg:postcode":"55109",
    "sg:province":"MN",
    "sg:tags":[
        "historical"
    ],
    "wof:name":"Maplewood Area Historical Soc",
    "wof:placetype":"venue"
},
  "geometry": {"coordinates":[-93.012355,45.035707],"type":"Point"}
}