{
  "type": "Feature",
  "properties": {
    "iso:country":"US",
    "sg:address":"27327 400th Ave NE",
    "sg:city":"Grygla",
    "sg:classifiers":[
        {
            "category":"Freight",
            "type":"Transportation"
        }
    ],
    "sg:phone":"+1 218 294 6300",
    "sg:postcode":"56727",
    "sg:province":"MN",
    "sg:tags":[
        "dry",
        "bulk",
        "truck",
        "operator",
        "trucking"
    ],
    "wof:name":"Stanley Farm Trucking",
    "wof:placetype":"venue"
},
  "geometry": {"coordinates":[-95.615148,48.277417],"type":"Point"}
}