{
  "type": "Feature",
  "properties": {
    "addr:full":"716 N Prior Ave St Paul MN 55104",
    "addr:housenumber":"716",
    "addr:postcode":"55104",
    "addr:street":"N Prior Ave",
    "iso:country":"US",
    "sg:address":"716 N Prior Ave",
    "sg:city":"St Paul",
    "sg:classifiers":[
        {
            "category":"Home & Garden",
            "subcategory":"Furniture",
            "type":"Retail Goods"
        },
        {
            "category":"Wholesale",
            "subcategory":"Furniture",
            "type":"Manufacturing & Wholesale Goods"
        }
    ],
    "sg:phone":"+1 651 641 7575",
    "sg:postcode":"55104",
    "sg:province":"MN",
    "sg:website":"www.homeelegance.com",
    "wof:name":"Top Line Furniture Warehouse",
    "wof:placetype":"venue"
},
  "geometry": {"coordinates":[-93.18222299999999,44.960984],"type":"Point"}
}