{
  "type": "Feature",
  "properties": {
    "iso:country":"US",
    "sg:address":"2945 Lincoln Dr",
    "sg:city":"Roseville",
    "sg:classifiers":[
        {
            "category":"Health Services",
            "subcategory":"Nursing And Care Facility",
            "type":"Services"
        }
    ],
    "sg:phone":"+1 651 628 3000",
    "sg:postcode":"55113",
    "sg:province":"MN",
    "sg:tags":[
        "home",
        "retirement",
        "community"
    ],
    "sg:website":"www.preshomes.com",
    "wof:name":"Eagle Crest Retirement Cmnty",
    "wof:placetype":"venue"
},
  "geometry": {"coordinates":[-93.16841599999999,45.030515],"type":"Point"}
}