{
  "type": "Feature",
  "properties": {
    "iso:country":"US",
    "sg:address":"9269 Camelot Cir",
    "sg:city":"Minneapolis",
    "sg:classifiers":[
        {
            "category":"Professional",
            "type":"Services"
        }
    ],
    "sg:phone":"+1 952 896 0054",
    "sg:postcode":"55437",
    "sg:province":"MN",
    "wof:name":"Kinetica Inc",
    "wof:placetype":"venue"
},
  "geometry": {"coordinates":[-93.356483,44.836318],"type":"Point"}
}