{
  "type": "Feature",
  "properties": {
    "addr:full":"13940 30th Ave NE Atwater MN 56209",
    "addr:housenumber":"13940",
    "addr:postcode":"56209",
    "addr:street":"30Th Ave Ne",
    "iso:country":"US",
    "sg:address":"13940 30th Ave NE",
    "sg:city":"Atwater",
    "sg:classifiers":[
        {
            "category":"Building & Trades",
            "subcategory":"Construction",
            "type":"Services"
        },
        {
            "category":"Building & Trades",
            "subcategory":"Electrical",
            "type":"Services"
        }
    ],
    "sg:phone":"+1 320 212 5146",
    "sg:postcode":"56209",
    "sg:province":"MN",
    "sg:tags":[
        "industrial",
        "electrician",
        "electric",
        "altering",
        "contractor",
        "contractors-commercial",
        "remodeling"
    ],
    "wof:name":"Gary's Electric, Inc",
    "wof:placetype":"venue"
},
  "geometry": {"coordinates":[-94.840659,45.153218],"type":"Point"}
}