{
  "type": "Feature",
  "properties": {
    "iso:country":"US",
    "sg:address":"309 Brighton Ave S",
    "sg:city":"Buffalo",
    "sg:classifiers":[
        {
            "category":"Insurance",
            "subcategory":"Insurance Agent",
            "type":"Services"
        }
    ],
    "sg:phone":"+1 763 684 1280",
    "sg:postcode":"55313",
    "sg:province":"MN",
    "wof:name":"Has San Lake Mutual Insurance",
    "wof:placetype":"venue"
},
  "geometry": {"coordinates":[-93.85554999999999,45.165851],"type":"Point"}
}