{
  "type": "Feature",
  "properties": {
    "addr:full":"12806 Highway 9 N Felton MN 56536",
    "addr:housenumber":"12806",
    "addr:postcode":"56536",
    "addr:street":"Highway 9 N",
    "iso:country":"US",
    "sg:address":"12806 Highway 9 N",
    "sg:city":"Felton",
    "sg:classifiers":[
        {
            "category":"Farming",
            "subcategory":"Livestock Farm",
            "type":"Manufacturing & Wholesale Goods"
        }
    ],
    "sg:phone":"+1 218 494 3314",
    "sg:postcode":"56536",
    "sg:province":"MN",
    "sg:tags":[
        "feeding"
    ],
    "wof:name":"Robert Wright",
    "wof:placetype":"venue"
},
  "geometry": {"coordinates":[-96.49984000000001,47.031883],"type":"Point"}
}