{
  "type": "Feature",
  "properties": {
    "addr:full":"617 1st Ave N Minneapolis MN 55401",
    "addr:housenumber":"617",
    "addr:postcode":"55401",
    "addr:street":"1St Ave N",
    "iso:country":"US",
    "sg:address":"617 1st Ave N",
    "sg:city":"Minneapolis",
    "sg:classifiers":[
        {
            "category":"Communications",
            "subcategory":"Radio Station",
            "type":"Services"
        }
    ],
    "sg:phone":"+1 612 746 3948",
    "sg:postcode":"55401",
    "sg:province":"MN",
    "sg:tags":[
        "company",
        "broadcasting"
    ],
    "wof:name":"Clear Channel",
    "wof:placetype":"venue"
},
  "geometry": {"coordinates":[-93.275774,44.978906],"type":"Point"}
}