{
  "type": "Feature",
  "properties": {
    "iso:country":"US",
    "sg:address":"577 190th Ave",
    "sg:city":"Avoca",
    "sg:classifiers":[
        {
            "category":"Farming",
            "subcategory":"Livestock Farm",
            "type":"Manufacturing & Wholesale Goods"
        }
    ],
    "sg:phone":"+1 507 335 7787",
    "sg:postcode":"56114",
    "sg:province":"MN",
    "sg:tags":[
        "hog",
        "corn",
        "or",
        "feedlot"
    ],
    "wof:name":"Glen Kramer",
    "wof:placetype":"venue"
},
  "geometry": {"coordinates":[-95.68302,43.921099],"type":"Point"}
}