{
  "type": "Feature",
  "properties": {
    "iso:country":"US",
    "sg:address":"5629 Pleasant Ave",
    "sg:city":"Minneapolis",
    "sg:classifiers":[
        {
            "category":"Professional",
            "subcategory":"Business Services",
            "type":"Services"
        }
    ],
    "sg:phone":"+1 612 203 4662",
    "sg:postcode":"55419",
    "sg:province":"MN",
    "sg:tags":[
        "consultant",
        "coach"
    ],
    "wof:name":"Strategic Consulting And Coaching",
    "wof:placetype":"venue"
},
  "geometry": {"coordinates":[-93.283188,44.900952],"type":"Point"}
}