{
  "type": "Feature",
  "properties": {
    "addr:full":"43 Main St SE Minneapolis MN 55414",
    "addr:housenumber":"43",
    "addr:postcode":"55414",
    "addr:street":"Main St Se",
    "iso:country":"US",
    "sg:address":"43 Main St SE",
    "sg:city":"Minneapolis",
    "sg:classifiers":[
        {
            "category":"Museum",
            "type":"Entertainment"
        }
    ],
    "sg:phone":"+1 612 379 4046",
    "sg:postcode":"55414",
    "sg:province":"MN",
    "sg:tags":[
        "gallery"
    ],
    "wof:name":"Phrenology Co",
    "wof:placetype":"venue"
},
  "geometry": {"coordinates":[-93.257549,44.985567],"type":"Point"}
}