{
  "type": "Feature",
  "properties": {
    "addr:full":"1481 Champion Dr Saint Paul MN 55112",
    "addr:housenumber":"1481",
    "addr:postcode":"55112",
    "addr:street":"Champion Dr",
    "iso:country":"US",
    "sg:address":"1481 Champion Dr",
    "sg:city":"Saint Paul",
    "sg:classifiers":[
        {
            "category":"Arts & Performance",
            "subcategory":"Theater",
            "type":"Entertainment"
        }
    ],
    "sg:phone":"+1 651 636 2310",
    "sg:postcode":"55112",
    "sg:province":"MN",
    "sg:tags":[
        "group"
    ],
    "wof:name":"Antics Balloons",
    "wof:placetype":"venue"
},
  "geometry": {"coordinates":[-93.206008,45.044672],"type":"Point"}
}