{
  "type": "Feature",
  "properties": {
    "iso:country":"US",
    "sg:address":"511 Amos Way NW",
    "sg:city":"Bemidji",
    "sg:classifiers":[
        {
            "category":"Health Services",
            "subcategory":"Clinic",
            "type":"Services"
        }
    ],
    "sg:phone":"+1 218 759 9867",
    "sg:postcode":"56601",
    "sg:province":"MN",
    "sg:tags":[
        "home",
        "care"
    ],
    "wof:name":"Northwest Respiratory Sys LLC",
    "wof:placetype":"venue"
},
  "geometry": {"coordinates":[-94.877917,47.513532],"type":"Point"}
}