{
  "type": "Feature",
  "properties": {
    "addr:full":"790 Cleveland Ave S Ste 214 Saint Paul MN 55116",
    "addr:housenumber":"790",
    "addr:postcode":"55116",
    "addr:street":"Cleveland Ave S Ste 214",
    "iso:country":"US",
    "sg:address":"790 Cleveland Ave S Ste 214",
    "sg:city":"Saint Paul",
    "sg:classifiers":[
        {
            "category":"Professional",
            "subcategory":"Lawyer & Legal Services",
            "type":"Services"
        }
    ],
    "sg:phone":"+1 651 699 0601",
    "sg:postcode":"55116",
    "sg:province":"MN",
    "sg:tags":[
        "personal",
        "injury"
    ],
    "wof:name":"Bartsh Shawn M Atty",
    "wof:placetype":"venue"
},
  "geometry": {"coordinates":[-93.18740099999999,44.917999],"type":"Point"}
}