{
  "type": "Feature",
  "properties": {
    "iso:country":"US",
    "sg:address":"2 Park Ave SW",
    "sg:city":"Remer",
    "sg:classifiers":[
        {
            "category":"Shopping",
            "subcategory":"Bicycles & Sporting Goods",
            "type":"Retail Goods"
        }
    ],
    "sg:phone":"+1 218 566 2338",
    "sg:postcode":"56672",
    "sg:province":"MN",
    "wof:name":"Remer Trading Post",
    "wof:placetype":"venue"
},
  "geometry": {"coordinates":[-93.923328,47.054213],"type":"Point"}
}