{
  "type": "Feature",
  "properties": {
    "iso:country":"US",
    "sg:address":"535 Main St",
    "sg:city":"New Munich",
    "sg:classifiers":[
        {
            "category":"Home & Garden",
            "subcategory":"Building Materials",
            "type":"Retail Goods"
        }
    ],
    "sg:phone":"+1 320 837 5288",
    "sg:postcode":"56356",
    "sg:province":"MN",
    "sg:tags":[
        "mixed",
        "concrete"
    ],
    "sg:website":"www.wormslumber.com",
    "wof:name":"Worms Lumber & Ready Mix Inc",
    "wof:placetype":"venue"
},
  "geometry": {"coordinates":[-94.754019,45.629291],"type":"Point"}
}