{
  "type": "Feature",
  "properties": {
    "iso:country":"US",
    "sg:address":"10207 260th St S",
    "sg:city":"Hawley",
    "sg:classifiers":[
        {
            "category":"Personal",
            "subcategory":"Beauty Salon",
            "type":"Services"
        }
    ],
    "sg:phone":"+1 218 483 1489",
    "sg:postcode":"56549",
    "sg:province":"MN",
    "sg:tags":[
        "shop"
    ],
    "wof:name":"Great Outlooks Hair & Tanning",
    "wof:placetype":"venue"
},
  "geometry": {"coordinates":[-96.257169,46.743718],"type":"Point"}
}