{
  "type": "Feature",
  "properties": {
    "addr:full":"7117 10th St N St Paul MN 55128",
    "addr:housenumber":"7117",
    "addr:postcode":"55128",
    "addr:street":"10Th St N",
    "iso:country":"US",
    "sg:address":"7117 10th St N",
    "sg:city":"St Paul",
    "sg:classifiers":[
        {
            "category":"Real Estate",
            "subcategory":"Real Estate Agent",
            "type":"Services"
        }
    ],
    "sg:phone":"+1 651 738 7777",
    "sg:postcode":"55128",
    "sg:province":"MN",
    "sg:tags":[
        "management"
    ],
    "wof:name":"Envision Properties Inc",
    "wof:placetype":"venue"
},
  "geometry": {"coordinates":[-92.959857,44.963242],"type":"Point"}
}