{
  "type": "Feature",
  "properties": {
    "addr:full":"205 Main St Frost MN 56033",
    "addr:housenumber":"205",
    "addr:postcode":"56033",
    "addr:street":"Main St",
    "iso:country":"US",
    "sg:address":"205 Main St",
    "sg:city":"Frost",
    "sg:classifiers":[
        {
            "category":"Banks & Credit Unions",
            "subcategory":"Bank",
            "type":"Services"
        },
        {
            "category":"Banks & Credit Unions",
            "subcategory":"Financial Services",
            "type":"Services"
        }
    ],
    "sg:phone":"+1 507 878 3203",
    "sg:postcode":"56033",
    "sg:province":"MN",
    "sg:tags":[
        "commercial",
        "loan",
        "saving"
    ],
    "sg:website":"http://www.froststatebank.com",
    "wof:name":"Frost State Bank",
    "wof:placetype":"venue"
},
  "geometry": {"coordinates":[-93.923897,43.584731],"type":"Point"}
}