{
  "type": "Feature",
  "properties": {
    "addr:full":"3926 Sibley Memorial Hwy Saint Paul MN 55122",
    "addr:housenumber":"3926",
    "addr:postcode":"55122",
    "addr:street":"Sibley Memorial Hwy",
    "iso:country":"US",
    "sg:address":"3926 Sibley Memorial Hwy",
    "sg:city":"Saint Paul",
    "sg:classifiers":[
        {
            "category":"Personal",
            "type":"Services"
        }
    ],
    "sg:phone":"+1 651 452 6191",
    "sg:postcode":"55122",
    "sg:province":"MN",
    "sg:tags":[
        "sewing",
        "alteration"
    ],
    "wof:name":"Cedarvale Tailors",
    "wof:placetype":"venue"
},
  "geometry": {"coordinates":[-93.213303,44.817699],"type":"Point"}
}