{
  "type": "Feature",
  "properties": {
    "addr:full":"400 Central Ave E St Michael MN 55376",
    "addr:housenumber":"400",
    "addr:postcode":"55376",
    "addr:street":"Central Ave E St",
    "iso:country":"US",
    "sg:address":"400 Central Ave E",
    "sg:city":"St Michael",
    "sg:classifiers":[
        {
            "category":"Restaurant",
            "type":"Food & Drink"
        }
    ],
    "sg:phone":"+1 763 497 9100",
    "sg:postcode":"55376",
    "sg:province":"MN",
    "sg:tags":[
        "eating"
    ],
    "wof:name":"China Inn",
    "wof:placetype":"venue"
},
  "geometry": {"coordinates":[-93.65636600000001,45.210119],"type":"Point"}
}