{
  "type": "Feature",
  "properties": {
    "iso:country":"US",
    "sg:address":"21 Maus Dr",
    "sg:city":"Kimball",
    "sg:classifiers":[
        {
            "category":"Autos & Motor Vehicles",
            "subcategory":"Automobile Sales",
            "type":"Retail Goods"
        }
    ],
    "sg:phone":"+1 320 398 3210",
    "sg:postcode":"55353",
    "sg:province":"MN",
    "sg:tags":[
        "car",
        "dealer"
    ],
    "wof:name":"A M Maus & Son",
    "wof:placetype":"venue"
},
  "geometry": {"coordinates":[-94.298,45.319109],"type":"Point"}
}