{
  "type": "Feature",
  "properties": {
    "addr:full":"153 26th Ave SE Minneapolis MN 55414",
    "addr:housenumber":"153",
    "addr:postcode":"55414",
    "addr:street":"26Th Ave Se",
    "iso:country":"US",
    "sg:address":"153 26th Ave SE",
    "sg:city":"Minneapolis",
    "sg:classifiers":[
        {
            "category":"Arts & Performance",
            "subcategory":"Theater",
            "type":"Entertainment"
        }
    ],
    "sg:phone":"+1 651 681 8277",
    "sg:postcode":"55414",
    "sg:province":"MN",
    "sg:tags":[
        "music"
    ],
    "wof:name":"Magical Transformations",
    "wof:placetype":"venue"
},
  "geometry": {"coordinates":[-93.22112199999999,44.971389],"type":"Point"}
}