{
  "type": "Feature",
  "properties": {
    "addr:full":"2311 Hwy 52 N Rochester MN 55901",
    "addr:housenumber":"2311",
    "addr:postcode":"55901",
    "addr:street":"Hwy 52 N",
    "iso:country":"US",
    "sg:address":"2311 Hwy 52 N",
    "sg:city":"Rochester",
    "sg:classifiers":[
        {
            "category":"Insurance",
            "subcategory":"Insurance Agent",
            "type":"Services"
        }
    ],
    "sg:phone":"+1 507 285 9927",
    "sg:postcode":"55901",
    "sg:province":"MN",
    "wof:name":"Jon De Kok Agency",
    "wof:placetype":"venue"
},
  "geometry": {"coordinates":[-92.493846,44.053384],"type":"Point"}
}