{
  "type": "Feature",
  "properties": {
    "addr:full":"110 S Grove Ave Owatonna MN 55060",
    "addr:housenumber":"110",
    "addr:postcode":"55060",
    "addr:street":"S Grove Ave",
    "iso:country":"US",
    "sg:address":"110 S Grove Ave",
    "sg:city":"Owatonna",
    "sg:classifiers":[
        {
            "category":"Real Estate",
            "subcategory":"Real Estate Operator",
            "type":"Services"
        }
    ],
    "sg:phone":"+1 507 444 9014",
    "sg:postcode":"55060",
    "sg:province":"MN",
    "sg:tags":[
        "apartment"
    ],
    "wof:name":"B-GROVE LLC",
    "wof:placetype":"venue"
},
  "geometry": {"coordinates":[-93.221039,44.08467],"type":"Point"}
}