{
  "type": "Feature",
  "properties": {
    "addr:full":"9017 Irving Ave N Minneapolis MN 55444",
    "addr:housenumber":"9017",
    "addr:postcode":"55444",
    "addr:street":"Irving Ave N",
    "iso:country":"US",
    "sg:address":"9017 Irving Ave N",
    "sg:city":"Minneapolis",
    "sg:classifiers":[
        {
            "category":"Building & Trades",
            "subcategory":"Cleaning & Sanitation",
            "type":"Services"
        }
    ],
    "sg:phone":"+1 763 424 8331",
    "sg:postcode":"55444",
    "sg:province":"MN",
    "sg:tags":[
        "janitorial"
    ],
    "wof:name":"Pride of Minnesota Inc",
    "wof:placetype":"venue"
},
  "geometry": {"coordinates":[-93.30309200000001,45.120224],"type":"Point"}
}