{
  "type": "Feature",
  "properties": {
    "iso:country":"US",
    "sg:address":"1111 3rd Ave S",
    "sg:city":"Minneapolis",
    "sg:classifiers":[
        {
            "category":"Government",
            "subcategory":"Office",
            "type":"Public Place"
        }
    ],
    "sg:phone":"+1 612 341 7130",
    "sg:postcode":"55404",
    "sg:province":"MN",
    "sg:tags":[
        "job",
        "disability",
        "training",
        "for",
        "people"
    ],
    "wof:name":"Vocational Rehabilitation",
    "wof:placetype":"venue"
},
  "geometry": {"coordinates":[-93.272046,44.970359],"type":"Point"}
}