{
  "type": "Feature",
  "properties": {
    "iso:country":"US",
    "sg:address":"2147 University Ave W",
    "sg:city":"St Paul",
    "sg:classifiers":[
        {
            "category":"Health Services",
            "subcategory":"Health Practitioner",
            "type":"Services"
        }
    ],
    "sg:phone":"+1 651 644 4832",
    "sg:postcode":"55104",
    "sg:province":"MN",
    "sg:tags":[
        "nurse",
        "registry"
    ],
    "wof:name":"Quest Nursing Svc Inc",
    "wof:placetype":"venue"
},
  "geometry": {"coordinates":[-93.188914,44.96044],"type":"Point"}
}