{
  "type": "Feature",
  "properties": {
    "addr:full":"26696 Harvest Ave Wabasso MN 56293",
    "addr:housenumber":"26696",
    "addr:postcode":"56293",
    "addr:street":"Harvest Ave",
    "iso:country":"US",
    "sg:address":"26696 Harvest Ave",
    "sg:city":"Wabasso",
    "sg:classifiers":[
        {
            "category":"Farming",
            "subcategory":"Dairy Farm",
            "type":"Manufacturing & Wholesale Goods"
        }
    ],
    "sg:phone":"+1 507 342 5474",
    "sg:postcode":"56293",
    "sg:province":"MN",
    "wof:name":"B Plaetz",
    "wof:placetype":"venue"
},
  "geometry": {"coordinates":[-95.310548,44.437585],"type":"Point"}
}