{
  "type": "Feature",
  "properties": {
    "addr:full":"1441 Iglehart Ave Saint Paul MN 55104",
    "addr:housenumber":"1441",
    "addr:postcode":"55104",
    "addr:street":"Iglehart Ave",
    "iso:country":"US",
    "sg:address":"1441 Iglehart Ave",
    "sg:city":"Saint Paul",
    "sg:classifiers":[
        {
            "category":"Manufacturing",
            "subcategory":"Motor Vehicles & Parts",
            "type":"Manufacturing & Wholesale Goods"
        }
    ],
    "sg:phone":"+1 651 644 2323",
    "sg:postcode":"55104",
    "sg:province":"MN",
    "sg:tags":[
        "truck",
        "accessory"
    ],
    "wof:name":"Off-Road-Only",
    "wof:placetype":"venue"
},
  "geometry": {"coordinates":[-93.16157699999999,44.949457],"type":"Point"}
}