{
  "type": "Feature",
  "properties": {
    "addr:full":"9822 74th Street Cir Cottage Grove MN 55016",
    "addr:housenumber":"9822",
    "addr:postcode":"55016",
    "addr:street":"74Th Street Cir",
    "iso:country":"US",
    "sg:address":"9822 74th Street Cir",
    "sg:city":"Cottage Grove",
    "sg:classifiers":[
        {
            "category":"Personal",
            "subcategory":"Hair Removal",
            "type":"Services"
        }
    ],
    "sg:phone":"+1 651 459 1006",
    "sg:postcode":"55016",
    "sg:province":"MN",
    "wof:name":"D J Tax Service",
    "wof:placetype":"venue"
},
  "geometry": {"coordinates":[-92.9068,44.842851],"type":"Point"}
}