{
  "type": "Feature",
  "properties": {
    "addr:full":"24105 Co Hwy 48 Osage MN 56570",
    "addr:housenumber":"24105",
    "addr:postcode":"56570",
    "addr:street":"Co Hwy 48",
    "iso:country":"US",
    "sg:address":"24105 Co Hwy 48",
    "sg:city":"Osage",
    "sg:classifiers":[
        {
            "category":"Building & Trades",
            "subcategory":"Construction",
            "type":"Services"
        }
    ],
    "sg:phone":"+1 218 573 3567",
    "sg:postcode":"56570",
    "sg:province":"MN",
    "sg:tags":[
        "builder",
        "operative"
    ],
    "wof:name":"AA Enterprises MN Inc",
    "wof:placetype":"venue"
},
  "geometry": {"coordinates":[-95.247501,46.923301],"type":"Point"}
}