{
  "type": "Feature",
  "properties": {
    "addr:full":"1128 North Hwy Jackson MN 56143",
    "addr:housenumber":"1128",
    "addr:postcode":"56143",
    "addr:street":"North Hwy",
    "iso:country":"US",
    "sg:address":"1128 North Hwy",
    "sg:city":"Jackson",
    "sg:classifiers":[
        {
            "category":"Professional",
            "subcategory":"Management & Consulting",
            "type":"Services"
        }
    ],
    "sg:phone":"+1 507 847 5302",
    "sg:postcode":"56143",
    "sg:province":"MN",
    "sg:tags":[
        "consultant"
    ],
    "wof:name":"E & V Consultants",
    "wof:placetype":"venue"
},
  "geometry": {"coordinates":[-94.99764500000001,43.623771],"type":"Point"}
}