{
  "type": "Feature",
  "properties": {
    "iso:country":"US",
    "sg:address":"10901 Baltimore St NE",
    "sg:city":"Minneapolis",
    "sg:classifiers":[
        {
            "category":"Food & Beverages",
            "subcategory":"Liquor & Beverages",
            "type":"Retail Goods"
        }
    ],
    "sg:phone":"+1 763 786 4992",
    "sg:postcode":"55449",
    "sg:province":"MN",
    "sg:tags":[
        "store"
    ],
    "wof:name":"Grape Expectations",
    "wof:placetype":"venue"
},
  "geometry": {"coordinates":[-93.233238,45.168259],"type":"Point"}
}