{
  "type": "Feature",
  "properties": {
    "iso:country":"US",
    "sg:address":"300 Bemidji Ave N",
    "sg:city":"Bemidji",
    "sg:classifiers":[
        {
            "category":"Organizations",
            "subcategory":"Non-profit Organization",
            "type":"Services"
        }
    ],
    "sg:phone":"+1 218 759 0164",
    "sg:postcode":"56601",
    "sg:province":"MN",
    "wof:name":"Bemidji Visitor & Convention",
    "wof:placetype":"venue"
},
  "geometry": {"coordinates":[-94.87955599999999,47.471596],"type":"Point"}
}