{
  "type": "Feature",
  "properties": {
    "iso:country":"US",
    "sg:address":"111 N Washington St",
    "sg:city":"New Ulm",
    "sg:classifiers":[
        {
            "category":"Shopping",
            "subcategory":"Used Merchandise",
            "type":"Retail Goods"
        }
    ],
    "sg:phone":"+1 507 359 7606",
    "sg:postcode":"56073",
    "sg:province":"MN",
    "wof:name":"Schladweiler John",
    "wof:placetype":"venue"
},
  "geometry": {"coordinates":[-94.46501000000001,44.313076],"type":"Point"}
}