{
  "type": "Feature",
  "properties": {
    "addr:full":"37918 State Hwy 87 Frazee MN 56544",
    "addr:housenumber":"37918",
    "addr:postcode":"56544",
    "addr:street":"State Hwy 87",
    "iso:country":"US",
    "sg:address":"37918 State Hwy 87",
    "sg:city":"Frazee",
    "sg:classifiers":[
        {
            "category":"Building & Trades",
            "subcategory":"Electrical",
            "type":"Services"
        }
    ],
    "sg:phone":"+1 218 334 2382",
    "sg:postcode":"56544",
    "sg:province":"MN",
    "sg:tags":[
        "electric",
        "contractor"
    ],
    "wof:name":"Frazee Electric Inc",
    "wof:placetype":"venue"
},
  "geometry": {"coordinates":[-95.61320499999999,46.746008],"type":"Point"}
}