{
  "type": "Feature",
  "properties": {
    "addr:full":"337 E River Dr Park Rapids MN 56470",
    "addr:housenumber":"337",
    "addr:postcode":"56470",
    "addr:street":"E River Dr",
    "iso:country":"US",
    "sg:address":"337 E River Dr",
    "sg:city":"Park Rapids",
    "sg:classifiers":[
        {
            "category":"Shopping",
            "subcategory":"Bicycles & Sporting Goods",
            "type":"Retail Goods"
        }
    ],
    "sg:phone":"+1 218 732 5227",
    "sg:postcode":"56470",
    "sg:province":"MN",
    "wof:name":"Fullers Sporting Goods",
    "wof:placetype":"venue"
},
  "geometry": {"coordinates":[-95.05474,46.9336],"type":"Point"}
}