{
  "type": "Feature",
  "properties": {
    "iso:country":"US",
    "sg:address":"820 Decatur Ave N",
    "sg:city":"Golden Valley",
    "sg:classifiers":[
        {
            "category":"Restaurant",
            "type":"Food & Drink"
        }
    ],
    "sg:phone":"+1 763 544 0818",
    "sg:postcode":"55427",
    "sg:province":"MN",
    "sg:tags":[
        "management"
    ],
    "wof:name":"Brinda Heilicher Inc",
    "wof:placetype":"venue"
},
  "geometry": {"coordinates":[-93.392786,44.987724],"type":"Point"}
}