{
  "type": "Feature",
  "properties": {
    "addr:full":"20603 Co Rd 50 Hamel MN 55340",
    "addr:housenumber":"20603;50",
    "addr:postcode":"55340",
    "addr:street":"Co Rd;Hamel",
    "iso:country":"US",
    "sg:address":"20603 Co Rd 50",
    "sg:city":"Hamel",
    "sg:classifiers":[
        {
            "category":"Recreation",
            "type":"Entertainment"
        }
    ],
    "sg:phone":"+1 763 420 7200",
    "sg:postcode":"55340",
    "sg:province":"MN",
    "sg:tags":[
        "stable"
    ],
    "wof:name":"Featherbrook Farms",
    "wof:placetype":"venue"
},
  "geometry": {"coordinates":[-93.560655,45.094846],"type":"Point"}
}