{
  "type": "Feature",
  "properties": {
    "iso:country":"US",
    "sg:address":"1136 190th Ave",
    "sg:city":"Woodstock",
    "sg:classifiers":[
        {
            "category":"Building & Trades",
            "subcategory":"Construction",
            "type":"Services"
        }
    ],
    "sg:phone":"+1 507 777 4112",
    "sg:postcode":"56186",
    "sg:province":"MN",
    "sg:tags":[
        "contractor"
    ],
    "wof:name":"S & K Construction",
    "wof:placetype":"venue"
},
  "geometry": {"coordinates":[-96.08444799999999,44.01539],"type":"Point"}
}