{
  "type": "Feature",
  "properties": {
    "iso:country":"US",
    "sg:address":"38155 Branch Ave",
    "sg:city":"North Branch",
    "sg:classifiers":[
        {
            "category":"Restaurant",
            "type":"Food & Drink"
        }
    ],
    "sg:phone":"+1 651 277 0044",
    "sg:postcode":"55056",
    "sg:province":"MN",
    "sg:tags":[
        "eating",
        "caterer"
    ],
    "wof:name":"Ramaley Catering",
    "wof:placetype":"venue"
},
  "geometry": {"coordinates":[-92.984599,45.501538],"type":"Point"}
}