{
  "type": "Feature",
  "properties": {
    "iso:country":"US",
    "sg:address":"706 2nd Ave S",
    "sg:city":"Minneapolis",
    "sg:classifiers":[
        {
            "category":"Government",
            "subcategory":"Office",
            "type":"Public Place"
        }
    ],
    "sg:phone":"+1 612 332 6897",
    "sg:postcode":"55402",
    "sg:province":"MN",
    "sg:tags":[
        "international",
        "affairs"
    ],
    "wof:name":"Swedish Consulate General",
    "wof:placetype":"venue"
},
  "geometry": {"coordinates":[-93.270368,44.974845],"type":"Point"}
}