{
  "type": "Feature",
  "properties": {
    "addr:full":"3201 N 3rd St Minneapolis MN 55412",
    "addr:housenumber":"3201",
    "addr:postcode":"55412",
    "addr:street":"N 3Rd St",
    "iso:country":"US",
    "sg:address":"3201 N 3rd St",
    "sg:city":"Minneapolis",
    "sg:classifiers":[
        {
            "category":"Banks & Credit Unions",
            "subcategory":"Financial Services",
            "type":"Services"
        }
    ],
    "sg:phone":"+1 612 521 9602",
    "sg:postcode":"55412",
    "sg:province":"MN",
    "sg:tags":[
        "broker",
        "mortgage"
    ],
    "wof:name":"Century Investment Group",
    "wof:placetype":"venue"
},
  "geometry": {"coordinates":[-93.283401,45.0131],"type":"Point"}
}