{
  "type": "Feature",
  "properties": {
    "addr:full":"2672 Horseshoe Ln Saint Paul MN 55125",
    "addr:housenumber":"2672",
    "addr:postcode":"55125",
    "addr:street":"Horseshoe Ln",
    "iso:country":"US",
    "sg:address":"2672 Horseshoe Ln",
    "sg:city":"Saint Paul",
    "sg:classifiers":[
        {
            "category":"Retail",
            "subcategory":"Repair Shop",
            "type":"Services"
        }
    ],
    "sg:phone":"+1 651 730 8625",
    "sg:postcode":"55125",
    "sg:province":"MN",
    "wof:name":"Muffler Doctor",
    "wof:placetype":"venue"
},
  "geometry": {"coordinates":[-92.938074,44.90957],"type":"Point"}
}