{
  "type": "Feature",
  "properties": {
    "addr:full":"5701 Shingle Creek Pkwy Minneapolis MN 55430",
    "addr:housenumber":"5701",
    "addr:postcode":"55430",
    "addr:street":"Shingle Creek Pkwy",
    "iso:country":"US",
    "sg:address":"5701 Shingle Creek Pkwy",
    "sg:city":"Minneapolis",
    "sg:classifiers":[
        {
            "category":"Banks & Credit Unions",
            "subcategory":"Bank",
            "type":"Services"
        }
    ],
    "sg:phone":"+1 763 566 2929",
    "sg:postcode":"55430",
    "sg:province":"MN",
    "sg:tags":[
        "loan",
        "real estate"
    ],
    "wof:name":"Acme Mortgage Corp",
    "wof:placetype":"venue"
},
  "geometry": {"coordinates":[-93.31008799999999,45.064575],"type":"Point"}
}