{
  "type": "Feature",
  "properties": {
    "addr:full":"123 W Main St Belle Plaine MN 56011",
    "addr:housenumber":"123",
    "addr:postcode":"56011",
    "addr:street":"W Main St;Plaine",
    "iso:country":"US",
    "sg:address":"123 W Main St",
    "sg:city":"Belle Plaine",
    "sg:classifiers":[
        {
            "category":"Professional",
            "subcategory":"Art Services",
            "type":"Services"
        }
    ],
    "sg:phone":"+1 952 873 2339",
    "sg:postcode":"56011",
    "sg:province":"MN",
    "sg:tags":[
        "photographer"
    ],
    "wof:name":"Front Porch Photography",
    "wof:placetype":"venue"
},
  "geometry": {"coordinates":[-93.76942200000001,44.622922],"type":"Point"}
}