{
  "type": "Feature",
  "properties": {
    "addr:full":"2375 University Ave W Ste 160 St Paul MN 55114",
    "addr:housenumber":"2375",
    "addr:postcode":"55114",
    "addr:street":"University Ave W Ste 160",
    "iso:country":"US",
    "sg:address":"2375 University Ave W Ste 160",
    "sg:city":"St Paul",
    "sg:classifiers":[
        {
            "category":"Personal",
            "subcategory":"Massage",
            "type":"Services"
        }
    ],
    "sg:phone":"+1 612 325 3357",
    "sg:postcode":"55114",
    "sg:province":"MN",
    "sg:website":"www.massagegeek.com",
    "wof:name":"Massage Geek",
    "wof:placetype":"venue"
},
  "geometry": {"coordinates":[-93.197008,44.963944],"type":"Point"}
}