{
  "type": "Feature",
  "properties": {
    "addr:full":"Hwy 55 & Vicksburg L Minneapolis MN 55401",
    "addr:postcode":"55401",
    "addr:street":"Hwy 55 &",
    "iso:country":"US",
    "sg:address":"Hwy 55 & Vicksburg L",
    "sg:city":"Minneapolis",
    "sg:classifiers":[
        {
            "category":"Retail",
            "subcategory":"Storage",
            "type":"Services"
        }
    ],
    "sg:phone":"+1 763 551 0006",
    "sg:postcode":"55401",
    "sg:province":"MN",
    "sg:tags":[
        "self"
    ],
    "wof:name":"Plymouth Minnesota Mini Storage",
    "wof:placetype":"venue"
},
  "geometry": {"coordinates":[-93.269997,44.984501],"type":"Point"}
}