{
  "type": "Feature",
  "properties": {
    "addr:full":"5995 Opus Pkwy Hopkins MN 55343",
    "addr:housenumber":"5995",
    "addr:postcode":"55343",
    "addr:street":"Opus Pkwy",
    "iso:country":"US",
    "sg:address":"5995 Opus Pkwy",
    "sg:city":"Hopkins",
    "sg:classifiers":[
        {
            "category":"Shopping",
            "subcategory":"Gifts & Souvenirs",
            "type":"Retail Goods"
        }
    ],
    "sg:phone":"+1 952 912 5681",
    "sg:postcode":"55343",
    "sg:province":"MN",
    "wof:name":"Gene Kay",
    "wof:placetype":"venue"
},
  "geometry": {"coordinates":[-93.407678,44.897791],"type":"Point"}
}