{
  "type": "Feature",
  "properties": {
    "addr:full":"2105 E Lake Geneva Rd NE Alexandria MN 56308",
    "addr:housenumber":"2105",
    "addr:postcode":"56308",
    "addr:street":"E Lake Geneva Rd Ne",
    "iso:country":"US",
    "sg:address":"2105 E Lake Geneva Rd NE",
    "sg:city":"Alexandria",
    "sg:classifiers":[
        {
            "category":"Personal",
            "subcategory":"Beauty Salon",
            "type":"Services"
        }
    ],
    "sg:phone":"+1 320 762 2615",
    "sg:postcode":"56308",
    "sg:province":"MN",
    "sg:tags":[
        "shop"
    ],
    "wof:name":"Julies Tips & Toes",
    "wof:placetype":"venue"
},
  "geometry": {"coordinates":[-95.323128,45.90898],"type":"Point"}
}