{
  "type": "Feature",
  "properties": {
    "addr:full":"835 38th St NW Rochester MN 55901",
    "addr:housenumber":"835",
    "addr:postcode":"55901",
    "addr:street":"38Th St Nw",
    "iso:country":"US",
    "sg:address":"835 38th St NW",
    "sg:city":"Rochester",
    "sg:classifiers":[
        {
            "category":"Building & Trades",
            "subcategory":"Cleaning & Sanitation",
            "type":"Services"
        }
    ],
    "sg:phone":"+1 507 216 5088",
    "sg:postcode":"55901",
    "sg:province":"MN",
    "sg:tags":[
        "cleaner",
        "janitor",
        "supply"
    ],
    "sg:website":"http://www.arnolds-supply.com",
    "wof:name":"Arnold's Supply & Kleenit Co",
    "wof:placetype":"venue"
},
  "geometry": {"coordinates":[-92.474653,44.062299],"type":"Point"}
}