{
  "type": "Feature",
  "properties": {
    "addr:full":"959 Paris Ave N Stillwater MN 55082",
    "addr:housenumber":"959",
    "addr:postcode":"55082",
    "addr:street":"Paris Ave N",
    "iso:country":"US",
    "sg:address":"959 Paris Ave N",
    "sg:city":"Stillwater",
    "sg:classifiers":[
        {
            "category":"Organizations",
            "subcategory":"Religious Organization",
            "type":"Services"
        }
    ],
    "sg:phone":"+1 651 436 4450",
    "sg:postcode":"55082",
    "sg:province":"MN",
    "sg:tags":[
        "church"
    ],
    "wof:name":"Jehovah's Witnesses",
    "wof:placetype":"venue"
},
  "geometry": {"coordinates":[-92.800082,44.962905],"type":"Point"}
}