{
  "type": "Feature",
  "properties": {
    "addr:full":"504 9th St NE Dilworth MN 56529",
    "addr:housenumber":"504",
    "addr:postcode":"56529",
    "addr:street":"9Th St Ne",
    "iso:country":"US",
    "sg:address":"504 9th St NE",
    "sg:city":"Dilworth",
    "sg:classifiers":[
        {
            "category":"Professional",
            "subcategory":"Business Services",
            "type":"Services"
        }
    ],
    "sg:phone":"+1 218 287 1518",
    "sg:postcode":"56529",
    "sg:province":"MN",
    "sg:tags":[
        "consultant",
        "coach"
    ],
    "sg:website":"http://www.thepartnerchannel.com",
    "wof:name":"Carter Research & Consulting",
    "wof:placetype":"venue"
},
  "geometry": {"coordinates":[-96.69133600000001,46.8817],"type":"Point"}
}