{
  "type": "Feature",
  "properties": {
    "addr:full":"100 10th St N Breckenridge MN 56520",
    "addr:housenumber":"100",
    "addr:postcode":"56520",
    "addr:street":"10Th St N",
    "iso:country":"US",
    "sg:address":"100 10th St N",
    "sg:city":"Breckenridge",
    "sg:classifiers":[
        {
            "category":"Wholesale",
            "subcategory":"Groceries",
            "type":"Manufacturing & Wholesale Goods"
        },
        {
            "category":"Farming",
            "subcategory":"Farm & Veterinary Services",
            "type":"Manufacturing & Wholesale Goods"
        }
    ],
    "sg:phone":"+1 218 643 1797",
    "sg:postcode":"56520",
    "sg:province":"MN",
    "sg:tags":[
        "grain",
        "seed",
        "organic",
        "cleaning"
    ],
    "wof:name":"Richland Organics Inc",
    "wof:placetype":"venue"
},
  "geometry": {"coordinates":[-96.58074999999999,46.2634],"type":"Point"}
}