{
  "type": "Feature",
  "properties": {
    "addr:full":"13120 5 Mile Rd SE Brainerd MN 56401",
    "addr:housenumber":"13120",
    "addr:postcode":"56401",
    "addr:street":"5 Mile Rd Se",
    "iso:country":"US",
    "sg:address":"13120 5 Mile Rd SE",
    "sg:city":"Brainerd",
    "sg:classifiers":[
        {
            "category":"Professional",
            "subcategory":"Computer Services",
            "type":"Services"
        }
    ],
    "sg:phone":"+1 218 825 8166",
    "sg:postcode":"56401",
    "sg:province":"MN",
    "sg:tags":[
        "datum"
    ],
    "wof:name":"Lilydale",
    "wof:placetype":"venue"
},
  "geometry": {"coordinates":[-94.01810999999999,46.355679],"type":"Point"}
}