{
  "type": "Feature",
  "properties": {
    "addr:full":"1347 Ashland Ave Saint Paul MN 55104",
    "addr:housenumber":"1347",
    "addr:postcode":"55104",
    "addr:street":"Ashland Ave",
    "iso:country":"US",
    "sg:address":"1347 Ashland Ave",
    "sg:city":"Saint Paul",
    "sg:classifiers":[
        {
            "category":"Shopping",
            "subcategory":"Shoes",
            "type":"Retail Goods"
        }
    ],
    "sg:phone":"+1 651 647 1159",
    "sg:postcode":"55104",
    "sg:province":"MN",
    "wof:name":"Athletes First Functionally",
    "wof:placetype":"venue"
},
  "geometry": {"coordinates":[-93.159195,44.944026],"type":"Point"}
}