{
  "type": "Feature",
  "properties": {
    "addr:full":"1502 Hwy 33 S Cloquet MN 55720",
    "addr:housenumber":"1502",
    "addr:postcode":"55720",
    "addr:street":"Hwy 33 S",
    "iso:country":"US",
    "sg:address":"1502 Hwy 33 S",
    "sg:city":"Cloquet",
    "sg:classifiers":[
        {
            "category":"Banks & Credit Unions",
            "subcategory":"Bank",
            "type":"Services"
        }
    ],
    "sg:phone":"+1 218 879 4521",
    "sg:postcode":"55720",
    "sg:province":"MN",
    "sg:tags":[
        "mortgage"
    ],
    "wof:name":"Wells Fargo",
    "wof:placetype":"venue"
},
  "geometry": {"coordinates":[-92.456909,46.689517],"type":"Point"}
}