{
  "type": "Feature",
  "properties": {
    "addr:full":"465 Kouwe St NW Hutchinson MN 55350",
    "addr:housenumber":"465",
    "addr:postcode":"55350",
    "addr:street":"Kouwe St Nw",
    "iso:country":"US",
    "sg:address":"465 Kouwe St NW",
    "sg:city":"Hutchinson",
    "sg:classifiers":[
        {
            "category":"Shopping",
            "type":"Retail Goods"
        }
    ],
    "sg:phone":"+1 320 587 9605",
    "sg:postcode":"55350",
    "sg:province":"MN",
    "sg:tags":[
        "merchandise"
    ],
    "wof:name":"Minnesotavikingsstore Com",
    "wof:placetype":"venue"
},
  "geometry": {"coordinates":[-94.379167,44.898081],"type":"Point"}
}