{
  "type": "Feature",
  "properties": {
    "addr:full":"122 Hamel Rd Hamel MN 55340",
    "addr:housenumber":"122",
    "addr:postcode":"55340",
    "addr:street":"Hamel Rd",
    "iso:country":"US",
    "sg:address":"122 Hamel Rd",
    "sg:city":"Hamel",
    "sg:classifiers":[
        {
            "category":"Retail",
            "subcategory":"Portrait Studio",
            "type":"Services"
        }
    ],
    "sg:phone":"+1 763 478 9851",
    "sg:postcode":"55340",
    "sg:province":"MN",
    "sg:tags":[
        "photographer"
    ],
    "wof:name":"Michelle's Studio",
    "wof:placetype":"venue"
},
  "geometry": {"coordinates":[-93.522453,45.040287],"type":"Point"}
}