{
  "type": "Feature",
  "properties": {
    "addr:full":"6514 Fredenberg Lake Rd Duluth MN 55803",
    "addr:postcode":"6514;55803",
    "addr:street":"Lake Rd",
    "iso:country":"US",
    "sg:address":"6514 Fredenberg Lake Rd",
    "sg:city":"Duluth",
    "sg:classifiers":[
        {
            "category":"Wholesale",
            "subcategory":"Groceries",
            "type":"Manufacturing & Wholesale Goods"
        }
    ],
    "sg:phone":"+1 218 721 4659",
    "sg:postcode":"55803",
    "sg:province":"MN",
    "wof:name":"Tea With ME LLC",
    "wof:placetype":"venue"
},
  "geometry": {"coordinates":[-92.196409,46.982561],"type":"Point"}
}