{
  "type": "Feature",
  "properties": {
    "addr:full":"601 Paul Bunyan Dr SE Bemidji MN 56601",
    "addr:housenumber":"601",
    "addr:postcode":"56601",
    "addr:street":"Paul Bunyan Dr Se",
    "iso:country":"US",
    "sg:address":"601 Paul Bunyan Dr SE",
    "sg:city":"Bemidji",
    "sg:classifiers":[
        {
            "category":"Wholesale",
            "subcategory":"Vending Machines",
            "type":"Manufacturing & Wholesale Goods"
        }
    ],
    "sg:phone":"+1 218 444 9570",
    "sg:postcode":"56601",
    "sg:province":"MN",
    "wof:name":"Five Star Vending",
    "wof:placetype":"venue"
},
  "geometry": {"coordinates":[-94.86009799999999,47.45367],"type":"Point"}
}