{
  "type": "Feature",
  "properties": {
    "iso:country":"US",
    "sg:address":"106 Donovan Dr",
    "sg:city":"Alexandria",
    "sg:classifiers":[
        {
            "category":"Manufacturing",
            "subcategory":"Rubber & Plastics",
            "type":"Manufacturing & Wholesale Goods"
        }
    ],
    "sg:phone":"+1 320 763 6684",
    "sg:postcode":"56308",
    "sg:province":"MN",
    "sg:tags":[
        "product",
        "mfg"
    ],
    "wof:name":"Juno Inc",
    "wof:placetype":"venue"
},
  "geometry": {"coordinates":[-95.35385599999999,45.888867],"type":"Point"}
}