{
  "type": "Feature",
  "properties": {
    "addr:full":"3529 Edward St NE Minneapolis MN 55418",
    "addr:housenumber":"3529",
    "addr:postcode":"55418",
    "addr:street":"Edward St Ne",
    "iso:country":"US",
    "sg:address":"3529 Edward St NE",
    "sg:city":"Minneapolis",
    "sg:classifiers":[
        {
            "category":"Autos & Motor Vehicles",
            "subcategory":"Fuel & Gas Station",
            "type":"Retail Goods"
        }
    ],
    "sg:phone":"+1 612 781 2883",
    "sg:postcode":"55418",
    "sg:province":"MN",
    "sg:tags":[
        "station",
        "gasoline"
    ],
    "wof:name":"Aztec 66 LLC",
    "wof:placetype":"venue"
},
  "geometry": {"coordinates":[-93.22363300000001,45.032891],"type":"Point"}
}