{
  "type": "Feature",
  "properties": {
    "iso:country":"US",
    "sg:address":"2233 University Ave W",
    "sg:city":"St Paul",
    "sg:classifiers":[
        {
            "category":"Professional",
            "subcategory":"Management & Consulting",
            "type":"Services"
        }
    ],
    "sg:phone":"+1 612 874 0535",
    "sg:postcode":"55104",
    "sg:province":"MN",
    "sg:tags":[
        "consultant",
        "business"
    ],
    "sg:website":"www.effective.org",
    "wof:name":"Center For Policy Planning",
    "wof:placetype":"venue"
},
  "geometry": {"coordinates":[-93.192123,44.961715],"type":"Point"}
}