{
  "type": "Feature",
  "properties": {
    "addr:full":"1304 W Fairview Ave Olivia MN 56277",
    "addr:housenumber":"1304",
    "addr:postcode":"56277",
    "addr:street":"W Fairview Ave",
    "iso:country":"US",
    "sg:address":"1304 W Fairview Ave",
    "sg:city":"Olivia",
    "sg:classifiers":[
        {
            "category":"Professional",
            "subcategory":"Management & Consulting",
            "type":"Services"
        }
    ],
    "sg:phone":"+1 320 523 2319",
    "sg:postcode":"56277",
    "sg:province":"MN",
    "sg:tags":[
        "consultant"
    ],
    "wof:name":"Thomas Sheep Shearing",
    "wof:placetype":"venue"
},
  "geometry": {"coordinates":[-95.000782,44.77444],"type":"Point"}
}