{
  "type": "Feature",
  "properties": {
    "addr:full":"128 2nd St N Breckenridge MN 56520",
    "addr:housenumber":"128",
    "addr:postcode":"56520",
    "addr:street":"2Nd St N",
    "iso:country":"US",
    "sg:address":"128 2nd St N",
    "sg:city":"Breckenridge",
    "sg:classifiers":[
        {
            "category":"Shopping",
            "subcategory":"Computers & Home Electronics",
            "type":"Retail Goods"
        }
    ],
    "sg:phone":"+1 218 643 1544",
    "sg:postcode":"56520",
    "sg:province":"MN",
    "wof:name":"Mobile Efx",
    "wof:placetype":"venue"
},
  "geometry": {"coordinates":[-96.592142,46.26426],"type":"Point"}
}