{
  "type": "Feature",
  "properties": {
    "iso:country":"US",
    "sg:address":"3520 W Mineral Pond Blvd",
    "sg:city":"Anoka",
    "sg:classifiers":[
        {
            "category":"Retail",
            "subcategory":"Repair Shop",
            "type":"Services"
        }
    ],
    "sg:phone":"+1 763 427 2304",
    "sg:postcode":"55303",
    "sg:province":"MN",
    "wof:name":"Diamond Cleaning Co",
    "wof:placetype":"venue"
},
  "geometry": {"coordinates":[-93.399073,45.218631],"type":"Point"}
}