{
  "type": "Feature",
  "properties": {
    "addr:full":"20112 265th Ave Belle Plaine MN 56011",
    "addr:housenumber":"20112",
    "addr:postcode":"56011",
    "addr:street":"265Th Ave Belle Plaine",
    "iso:country":"US",
    "sg:address":"20112 265th Ave",
    "sg:city":"Belle Plaine",
    "sg:classifiers":[
        {
            "category":"Retail",
            "subcategory":"Auto Repair",
            "type":"Services"
        }
    ],
    "sg:phone":"+1 952 873 4869",
    "sg:postcode":"56011",
    "sg:province":"MN",
    "sg:tags":[
        "automotive"
    ],
    "wof:name":"Skelley Towing",
    "wof:placetype":"venue"
},
  "geometry": {"coordinates":[-93.79896100000001,44.663344],"type":"Point"}
}