{
  "type": "Feature",
  "properties": {
    "addr:full":"909 Main St NE Minneapolis MN 55413",
    "addr:housenumber":"909",
    "addr:postcode":"55413",
    "addr:street":"Main St Ne",
    "iso:country":"US",
    "sg:address":"909 Main St NE",
    "sg:city":"Minneapolis",
    "sg:classifiers":[
        {
            "category":"Professional",
            "subcategory":"Management & Consulting",
            "type":"Services"
        }
    ],
    "sg:phone":"+1 612 378 7985",
    "sg:postcode":"55413",
    "sg:province":"MN",
    "sg:tags":[
        "consultant"
    ],
    "wof:name":"Northeast Housing Resource Ctr",
    "wof:placetype":"venue"
},
  "geometry": {"coordinates":[-93.265849,44.996749],"type":"Point"}
}