{
  "type": "Feature",
  "properties": {
    "iso:country":"US",
    "sg:address":"55010 Sunrise Ln",
    "sg:city":"Mankato",
    "sg:classifiers":[
        {
            "category":"Insurance",
            "subcategory":"Insurance Agent",
            "type":"Services"
        }
    ],
    "sg:phone":"+1 507 388 3053",
    "sg:postcode":"56001",
    "sg:province":"MN",
    "wof:name":"Lynn's Building & Remodeling",
    "wof:placetype":"venue"
},
  "geometry": {"coordinates":[-94.077898,44.147663],"type":"Point"}
}