{
  "type": "Feature",
  "properties": {
    "addr:full":"60 Garden Dr Silver Bay MN 55614",
    "addr:housenumber":"60",
    "addr:postcode":"55614",
    "addr:street":"Garden Dr",
    "iso:country":"US",
    "sg:address":"60 Garden Dr",
    "sg:city":"Silver Bay",
    "sg:classifiers":[
        {
            "category":"Manufacturing",
            "subcategory":"Lumber",
            "type":"Manufacturing & Wholesale Goods"
        }
    ],
    "sg:phone":"+1 218 226 3576",
    "sg:postcode":"55614",
    "sg:province":"MN",
    "sg:tags":[
        "logging"
    ],
    "wof:name":"Clement Logging",
    "wof:placetype":"venue"
},
  "geometry": {"coordinates":[-91.284435,47.292928],"type":"Point"}
}