{
  "type": "Feature",
  "properties": {
    "addr:full":"1214 Liberty Ct Sartell MN 56377",
    "addr:housenumber":"1214",
    "addr:postcode":"56377",
    "addr:street":"Liberty Ct",
    "iso:country":"US",
    "sg:address":"1214 Liberty Ct",
    "sg:city":"Sartell",
    "sg:classifiers":[
        {
            "category":"Building & Trades",
            "subcategory":"Electrical",
            "type":"Services"
        }
    ],
    "sg:phone":"+1 320 656 9333",
    "sg:postcode":"56377",
    "sg:province":"MN",
    "sg:tags":[
        "install",
        "cable"
    ],
    "wof:name":"Jeff Gooding Cable Service",
    "wof:placetype":"venue"
},
  "geometry": {"coordinates":[-94.20747900000001,45.599818],"type":"Point"}
}