{
  "type": "Feature",
  "properties": {
    "addr:full":"15011 Minnetonka Industrial Rd Minnetonka MN 55345",
    "addr:housenumber":"15011",
    "addr:postcode":"55345",
    "addr:street":"Minnetonka Industrial Rd",
    "iso:country":"US",
    "sg:address":"15011 Minnetonka Industrial Rd",
    "sg:city":"Minnetonka",
    "sg:classifiers":[
        {
            "category":"Manufacturing",
            "subcategory":"Building Materials",
            "type":"Manufacturing & Wholesale Goods"
        }
    ],
    "sg:phone":"+1 952 936 0133",
    "sg:postcode":"55345",
    "sg:province":"MN",
    "sg:tags":[
        "cabinet"
    ],
    "wof:name":"Westwood Cabinets",
    "wof:placetype":"venue"
},
  "geometry": {"coordinates":[-93.47081900000001,44.935624],"type":"Point"}
}