{
  "type": "Feature",
  "properties": {
    "iso:country":"US",
    "sg:address":"1021 International Dr",
    "sg:city":"Fergus Falls",
    "sg:classifiers":[
        {
            "category":"Manufacturing",
            "subcategory":"Rubber & Plastics",
            "type":"Manufacturing & Wholesale Goods"
        }
    ],
    "sg:phone":"+1 218 998 3800",
    "sg:postcode":"56537",
    "sg:province":"MN",
    "wof:name":"Excel Plastics LLC",
    "wof:placetype":"venue"
},
  "geometry": {"coordinates":[-96.09374699999999,46.304347],"type":"Point"}
}