{
  "type": "Feature",
  "properties": {
    "iso:country":"US",
    "sg:address":"400 Airport Rd",
    "sg:city":"Albert Lea",
    "sg:classifiers":[
        {
            "category":"Education",
            "subcategory":"Special Training",
            "type":"Public Place"
        }
    ],
    "sg:phone":"+1 507 373 9265",
    "sg:postcode":"56007",
    "sg:province":"MN",
    "sg:tags":[
        "aircraft",
        "school"
    ],
    "sg:website":"www.minnesotaaviation.com",
    "wof:name":"M N Aviation",
    "wof:placetype":"venue"
},
  "geometry": {"coordinates":[-93.361491,43.680763],"type":"Point"}
}