{
  "type": "Feature",
  "properties": {
    "addr:full":"901 Humboldt Ave N Minneapolis MN 55411",
    "addr:housenumber":"901",
    "addr:postcode":"55411",
    "addr:street":"Humboldt Ave N",
    "iso:country":"US",
    "sg:address":"901 Humboldt Ave N",
    "sg:city":"Minneapolis",
    "sg:classifiers":[
        {
            "category":"Place Of Worship",
            "subcategory":"Church",
            "type":"Public Place"
        },
        {
            "category":"Place Of Worship",
            "type":"Public Place"
        }
    ],
    "sg:phone":"+1 612 374 3935",
    "sg:postcode":"55411",
    "sg:province":"MN",
    "sg:tags":[
        "covenant",
        "churches-evangelical",
        "churches-covenant"
    ],
    "sg:website":"http://www.thecovenant.net",
    "wof:name":"Community Covenant Church",
    "wof:placetype":"venue"
},
  "geometry": {"coordinates":[-93.298176,44.987237],"type":"Point"}
}