{
  "type": "Feature",
  "properties": {
    "iso:country":"US",
    "sg:address":"4532 Wilson St",
    "sg:city":"Minnetonka",
    "sg:classifiers":[
        {
            "category":"Personal",
            "subcategory":"Beauty Salon",
            "type":"Services"
        }
    ],
    "sg:phone":"+1 952 933 4516",
    "sg:postcode":"55345",
    "sg:province":"MN",
    "sg:tags":[
        "shop"
    ],
    "sg:website":"www.hairtech.us",
    "wof:name":"Hair Tech",
    "wof:placetype":"venue"
},
  "geometry": {"coordinates":[-93.480844,44.920211],"type":"Point"}
}