{
  "type": "Feature",
  "properties": {
    "addr:full":"5025 Fremont Ave N Minneapolis MN 55430",
    "addr:housenumber":"5025",
    "addr:postcode":"55430",
    "addr:street":"Fremont Ave N",
    "iso:country":"US",
    "sg:address":"5025 Fremont Ave N",
    "sg:city":"Minneapolis",
    "sg:classifiers":[
        {
            "category":"Wholesale",
            "subcategory":"Non-durable Goods",
            "type":"Manufacturing & Wholesale Goods"
        }
    ],
    "sg:phone":"+1 612 287 0573",
    "sg:postcode":"55430",
    "sg:province":"MN",
    "wof:name":"Latinamerican Trading Co",
    "wof:placetype":"venue"
},
  "geometry": {"coordinates":[-93.29669699999999,45.047083],"type":"Point"}
}