{
  "type": "Feature",
  "properties": {
    "addr:full":"21697 US Hwy 71 Park Rapids MN 56470",
    "addr:housenumber":"21697",
    "addr:postcode":"56470",
    "addr:street":"Us Hwy 71",
    "iso:country":"US",
    "sg:address":"21697 US Hwy 71",
    "sg:city":"Park Rapids",
    "sg:classifiers":[
        {
            "category":"Home & Garden",
            "subcategory":"Furniture",
            "type":"Retail Goods"
        }
    ],
    "sg:phone":"+1 218 732 3860",
    "sg:postcode":"56470",
    "sg:province":"MN",
    "wof:name":"Utke's Country Pine Furnishing",
    "wof:placetype":"venue"
},
  "geometry": {"coordinates":[-95.10096900000001,46.9784],"type":"Point"}
}