{
  "type": "Feature",
  "properties": {
    "addr:full":"1314 Newhall Dr Faribault MN 55021",
    "addr:housenumber":"1314",
    "addr:postcode":"55021",
    "addr:street":"Newhall Dr",
    "iso:country":"US",
    "sg:address":"1314 Newhall Dr",
    "sg:city":"Faribault",
    "sg:classifiers":[
        {
            "category":"Restaurant",
            "type":"Food & Drink"
        }
    ],
    "sg:phone":"+1 507 334 7777",
    "sg:postcode":"55021",
    "sg:province":"MN",
    "sg:tags":[
        "eating"
    ],
    "wof:name":"Quiznos Subs",
    "wof:placetype":"venue"
},
  "geometry": {"coordinates":[-93.252928,44.300897],"type":"Point"}
}