{
  "type": "Feature",
  "properties": {
    "addr:full":"8050 Ranchers Rd NE Minneapolis MN 55432",
    "addr:postcode":"8050;55432",
    "addr:street":"Ranchers Rd Ne",
    "iso:country":"US",
    "sg:address":"8050 Ranchers Rd NE",
    "sg:city":"Minneapolis",
    "sg:classifiers":[
        {
            "category":"Manufacturing",
            "subcategory":"Metals",
            "type":"Manufacturing & Wholesale Goods"
        }
    ],
    "sg:phone":"+1 763 780 2700",
    "sg:postcode":"55432",
    "sg:province":"MN",
    "sg:tags":[
        "machine",
        "screw",
        "product"
    ],
    "sg:website":"http://www.micro-matics.com",
    "wof:name":"Micro-Matics",
    "wof:placetype":"venue"
},
  "geometry": {"coordinates":[-93.26608299999999,45.113928],"type":"Point"}
}