{
  "type": "Feature",
  "properties": {
    "addr:full":"210 E 3rd St Albert Lea MN 56007",
    "addr:housenumber":"210",
    "addr:postcode":"56007",
    "addr:street":"E 3Rd St",
    "iso:country":"US",
    "sg:address":"210 E 3rd St",
    "sg:city":"Albert Lea",
    "sg:classifiers":[
        {
            "category":"Insurance",
            "subcategory":"Hazard Insurance",
            "type":"Services"
        }
    ],
    "sg:phone":"+1 507 377 2302",
    "sg:postcode":"56007",
    "sg:province":"MN",
    "sg:tags":[
        "bond"
    ],
    "wof:name":"Absolute Bail Bonds",
    "wof:placetype":"venue"
},
  "geometry": {"coordinates":[-93.367249,43.641664],"type":"Point"}
}