{
  "type": "Feature",
  "properties": {
    "iso:country":"US",
    "sg:address":"6882 Howard Ln",
    "sg:city":"Eden Prairie",
    "sg:classifiers":[
        {
            "category":"Professional",
            "type":"Services"
        }
    ],
    "sg:phone":"+1 952 937 5166",
    "sg:postcode":"55346",
    "sg:province":"MN",
    "wof:name":"Daciis LLC",
    "wof:placetype":"venue"
},
  "geometry": {"coordinates":[-93.463059,44.876854],"type":"Point"}
}