{
  "type": "Feature",
  "properties": {
    "iso:country":"US",
    "sg:address":"1418 Maras St",
    "sg:city":"Shakopee",
    "sg:classifiers":[
        {
            "category":"Retail",
            "subcategory":"Auto Repair",
            "type":"Services"
        }
    ],
    "sg:phone":"+1 952 403 0456",
    "sg:postcode":"55379",
    "sg:province":"MN",
    "sg:tags":[
        "general"
    ],
    "wof:name":"Shakopee Transm & Auto Svc",
    "wof:placetype":"venue"
},
  "geometry": {"coordinates":[-93.402027,44.777785],"type":"Point"}
}