{
  "type": "Feature",
  "properties": {
    "addr:full":"67800 205th St Darwin MN 55324",
    "addr:housenumber":"67800",
    "addr:postcode":"55324",
    "addr:street":"205Th St",
    "iso:country":"US",
    "sg:address":"67800 205th St",
    "sg:city":"Darwin",
    "sg:classifiers":[
        {
            "category":"Farming",
            "subcategory":"Dairy Farm",
            "type":"Manufacturing & Wholesale Goods"
        }
    ],
    "sg:phone":"+1 320 275 2661",
    "sg:postcode":"55324",
    "sg:province":"MN",
    "sg:tags":[
        "field",
        "corn",
        "soybean",
        "crop"
    ],
    "wof:name":"Ahlgren Brothers Inc",
    "wof:placetype":"venue"
},
  "geometry": {"coordinates":[-94.406829,45.044756],"type":"Point"}
}