{
  "type": "Feature",
  "properties": {
    "iso:country":"US",
    "sg:address":"412 Southhaven Dr",
    "sg:city":"Mankato",
    "sg:classifiers":[
        {
            "category":"Professional",
            "type":"Services"
        }
    ],
    "sg:phone":"+1 507 388 5296",
    "sg:postcode":"56001",
    "sg:province":"MN",
    "wof:name":"Enemy Mind Studios",
    "wof:placetype":"venue"
},
  "geometry": {"coordinates":[-93.95999999999999,44.140228],"type":"Point"}
}