{
  "type": "Feature",
  "properties": {
    "iso:country":"US",
    "sg:address":"6000 Bass Lake Rd Ste 109",
    "sg:city":"Minneapolis",
    "sg:phone":"+1 763 533 4404",
    "sg:postcode":"55429",
    "sg:province":"MN",
    "wof:name":"Gdm Financial",
    "wof:placetype":"venue"
},
  "geometry": {"coordinates":[-93.356514,45.054626],"type":"Point"}
}