{
  "type": "Feature",
  "properties": {
    "addr:full":"7615 Smetana Ln Eden Prairie MN 55344",
    "addr:housenumber":"7615",
    "addr:postcode":"55344",
    "addr:street":"Smetana Ln",
    "iso:country":"US",
    "sg:address":"7615 Smetana Ln",
    "sg:city":"Eden Prairie",
    "sg:classifiers":[
        {
            "category":"Wholesale",
            "subcategory":"Construction Materials",
            "type":"Manufacturing & Wholesale Goods"
        }
    ],
    "sg:phone":"+1 952 941 6512",
    "sg:postcode":"55344",
    "sg:province":"MN",
    "sg:tags":[
        "lumber"
    ],
    "wof:name":"Viking Forest Products LLC",
    "wof:placetype":"venue"
},
  "geometry": {"coordinates":[-93.411863,44.865086],"type":"Point"}
}