{
  "type": "Feature",
  "properties": {
    "iso:country":"US",
    "sg:address":"221 Main St S",
    "sg:city":"Hutchinson",
    "sg:classifiers":[
        {
            "category":"Wholesale",
            "subcategory":"Meat",
            "type":"Manufacturing & Wholesale Goods"
        }
    ],
    "sg:phone":"+1 320 587 2622",
    "sg:postcode":"55350",
    "sg:province":"MN",
    "sg:tags":[
        "product"
    ],
    "wof:name":"Lang's Meat Market & Bakery",
    "wof:placetype":"venue"
},
  "geometry": {"coordinates":[-94.36918300000001,44.889745],"type":"Point"}
}