{
  "type": "Feature",
  "properties": {
    "iso:country":"US",
    "sg:address":"1639 West End Blvd",
    "sg:city":"St. Louis Park",
    "sg:classifiers":[
        {
            "category":"Shopping",
            "subcategory":"Clothing, Apparel, & Fashions",
            "type":"Retail Goods"
        },
        {
            "category":"Sports & Exercise",
            "subcategory":"Bicycle Rental",
            "type":"Entertainment"
        },
        {
            "category":"Sports & Exercise",
            "subcategory":"Gym",
            "type":"Entertainment"
        }
    ],
    "sg:phone":"+1 763 545 9069",
    "sg:postcode":"55416",
    "sg:province":"MN",
    "sg:tags":[
        "clothing",
        "yoga",
        "wear",
        "women's"
    ],
    "sg:website":"www.lululemon.com",
    "wof:name":"lululemon athletica",
    "wof:placetype":"venue"
},
  "geometry": {"coordinates":[-93.347779,44.967427],"type":"Point"}
}