{
  "type": "Feature",
  "properties": {
    "addr:full":"10639 110th Ave Milaca MN 56353",
    "addr:housenumber":"10639",
    "addr:postcode":"56353",
    "addr:street":"110Th Ave",
    "iso:country":"US",
    "sg:address":"10639 110th Ave",
    "sg:city":"Milaca",
    "sg:classifiers":[
        {
            "category":"Manufacturing",
            "subcategory":"Tools & Machinery",
            "type":"Manufacturing & Wholesale Goods"
        }
    ],
    "sg:phone":"+1 320 369 4343",
    "sg:postcode":"56353",
    "sg:province":"MN",
    "wof:name":"Helm's Cycle Sales & Svc",
    "wof:placetype":"venue"
},
  "geometry": {"coordinates":[-93.63647899999999,45.700559],"type":"Point"}
}