{
  "type": "Feature",
  "properties": {
    "addr:full":"125 4th St NW Faribault MN 55021",
    "addr:housenumber":"125",
    "addr:postcode":"55021",
    "addr:street":"4Th St Nw",
    "iso:country":"US",
    "sg:address":"125 4th St NW",
    "sg:city":"Faribault",
    "sg:classifiers":[
        {
            "category":"Shopping",
            "subcategory":"Clothing, Apparel, & Fashions",
            "type":"Retail Goods"
        }
    ],
    "sg:phone":"+1 507 334 1684",
    "sg:postcode":"55021",
    "sg:province":"MN",
    "sg:tags":[
        "alteration"
    ],
    "wof:name":"Clothing Renovators",
    "wof:placetype":"venue"
},
  "geometry": {"coordinates":[-93.270205,44.294672],"type":"Point"}
}