{
  "type": "Feature",
  "properties": {
    "addr:full":"55 Center St E Harmony MN 55939",
    "addr:housenumber":"55",
    "addr:postcode":"55939",
    "addr:street":"Center St E",
    "iso:country":"US",
    "sg:address":"55 Center St E",
    "sg:city":"Harmony",
    "sg:classifiers":[
        {
            "category":"Food & Beverages",
            "subcategory":"Groceries & Convenience Stores",
            "type":"Retail Goods"
        }
    ],
    "sg:phone":"+1 507 886 2225",
    "sg:postcode":"55939",
    "sg:province":"MN",
    "sg:tags":[
        "grocer"
    ],
    "wof:name":"Harmony Foods",
    "wof:placetype":"venue"
},
  "geometry": {"coordinates":[-92.009331,43.554274],"type":"Point"}
}