{
  "type": "Feature",
  "properties": {
    "addr:full":"79702 250th St Graceville MN 56284",
    "addr:housenumber":"79702",
    "addr:postcode":"56284",
    "addr:street":"250Th St",
    "iso:country":"US",
    "sg:address":"79702 250th St",
    "sg:city":"Graceville",
    "sg:classifiers":[
        {
            "category":"Real Estate",
            "subcategory":"Real Estate Operator",
            "type":"Services"
        }
    ],
    "sg:phone":"+1 320 748 7417",
    "sg:postcode":"56284",
    "sg:province":"MN",
    "sg:tags":[
        "property",
        "lessor"
    ],
    "wof:name":"Mark Heck",
    "wof:placetype":"venue"
},
  "geometry": {"coordinates":[-95.17807999999999,44.744897],"type":"Point"}
}