{
  "type": "Feature",
  "properties": {
    "addr:full":"35708 Co Hwy 21 Ogema MN 56569",
    "addr:housenumber":"35708",
    "addr:postcode":"56569",
    "addr:street":"Co Hwy 21",
    "iso:country":"US",
    "sg:address":"35708 Co Hwy 21",
    "sg:city":"Ogema",
    "sg:classifiers":[
        {
            "category":"Health Services",
            "subcategory":"Hospital",
            "type":"Services"
        }
    ],
    "sg:phone":"+1 218 983 3870",
    "sg:postcode":"56569",
    "sg:province":"MN",
    "sg:tags":[
        "mental"
    ],
    "wof:name":"White Earth Mental Health",
    "wof:placetype":"venue"
},
  "geometry": {"coordinates":[-95.84831800000001,47.08428],"type":"Point"}
}