{
  "type": "Feature",
  "properties": {
    "iso:country":"US",
    "sg:address":"4750 London Rd",
    "sg:city":"Duluth",
    "sg:classifiers":[
        {
            "category":"Professional",
            "type":"Services"
        }
    ],
    "sg:phone":"+1 218 525 1255",
    "sg:postcode":"55804",
    "sg:province":"MN",
    "wof:name":"Sharon & Joel Labovitz Fo",
    "wof:placetype":"venue"
},
  "geometry": {"coordinates":[-92.02773999999999,46.827916],"type":"Point"}
}