{
  "type": "Feature",
  "properties": {
    "iso:country":"US",
    "sg:address":"3067 Co Rd 15 NW",
    "sg:city":"Brandon",
    "sg:classifiers":[
        {
            "category":"Shopping",
            "type":"Retail Goods"
        }
    ],
    "sg:phone":"+1 320 834 4680",
    "sg:postcode":"56315",
    "sg:province":"MN",
    "sg:tags":[
        "wedding",
        "supply"
    ],
    "wof:name":"One Sweet Wrap",
    "wof:placetype":"venue"
},
  "geometry": {"coordinates":[-95.64464700000001,45.924602],"type":"Point"}
}