{
  "type": "Feature",
  "properties": {
    "iso:country":"US",
    "sg:address":"8950 Eden Prairie Rd",
    "sg:city":"Eden Prairie",
    "sg:classifiers":[
        {
            "category":"Social Services",
            "type":"Services"
        }
    ],
    "sg:phone":"+1 952 934 3370",
    "sg:postcode":"55347",
    "sg:province":"MN",
    "sg:tags":[
        "senior",
        "citizen"
    ],
    "wof:name":"Senior Outreach-South",
    "wof:placetype":"venue"
},
  "geometry": {"coordinates":[-93.480628,44.838388],"type":"Point"}
}