{
  "type": "Feature",
  "properties": {
    "iso:country":"US",
    "sg:address":"401 Gilbertson St W",
    "sg:city":"Battle Lake",
    "sg:classifiers":[
        {
            "category":"Organizations",
            "subcategory":"Religious Organization",
            "type":"Services"
        }
    ],
    "sg:phone":"+1 218 864 5539",
    "sg:postcode":"56515",
    "sg:province":"MN",
    "sg:tags":[
        "church"
    ],
    "sg:website":"www.battlelakelions.org",
    "wof:name":"Battle Lake Alliance Church",
    "wof:placetype":"venue"
},
  "geometry": {"coordinates":[-95.717642,46.279749],"type":"Point"}
}