{
  "type": "Feature",
  "properties": {
    "addr:full":"323 6th St NE Staples MN 56479",
    "addr:housenumber":"323",
    "addr:postcode":"56479",
    "addr:street":"6Th St Ne",
    "iso:country":"US",
    "sg:address":"323 6th St NE",
    "sg:city":"Staples",
    "sg:classifiers":[
        {
            "category":"Health Services",
            "subcategory":"Chiropractor",
            "type":"Services"
        }
    ],
    "sg:phone":"+1 218 894 1737",
    "sg:postcode":"56479",
    "sg:province":"MN",
    "wof:name":"Staples Chiropractic Office",
    "wof:placetype":"venue"
},
  "geometry": {"coordinates":[-94.79206000000001,46.357411],"type":"Point"}
}