{
  "type": "Feature",
  "properties": {
    "iso:country":"US",
    "sg:address":"1265 US Hwy 10 W",
    "sg:city":"Detroit Lakes",
    "sg:classifiers":[
        {
            "category":"Restaurant",
            "type":"Food & Drink"
        }
    ],
    "sg:phone":"+1 218 844 5688",
    "sg:postcode":"56501",
    "sg:province":"MN",
    "wof:name":"Subway Sandwiches & Salads",
    "wof:placetype":"venue"
},
  "geometry": {"coordinates":[-95.862225,46.826057],"type":"Point"}
}