{
  "type": "Feature",
  "properties": {
    "iso:country":"US",
    "sg:address":"5101 Olson Memorial Hwy Ste 5000",
    "sg:city":"Minneapolis",
    "sg:classifiers":[
        {
            "category":"Insurance",
            "subcategory":"Hazard Insurance",
            "type":"Services"
        }
    ],
    "sg:phone":"+1 763 545 1927",
    "sg:postcode":"55422",
    "sg:province":"MN",
    "sg:website":"http://statefarm.mqgroup.com/url.asp?usr=237023",
    "wof:name":"State Farm Insurance Agent-David A Maggitt",
    "wof:placetype":"venue"
},
  "geometry": {"coordinates":[-93.342247,44.983971],"type":"Point"}
}