{
  "type": "Feature",
  "properties": {
    "addr:full":"1741 Radisson Rd NE Minneapolis MN 55449",
    "addr:postcode":"1741;55449",
    "addr:street":"Radisson Rd Ne",
    "iso:country":"US",
    "sg:address":"1741 Radisson Rd NE",
    "sg:city":"Minneapolis",
    "sg:classifiers":[
        {
            "category":"Manufacturing",
            "subcategory":"Glass & Minerals",
            "type":"Manufacturing & Wholesale Goods"
        }
    ],
    "sg:phone":"+1 763 783 8114",
    "sg:postcode":"55449",
    "sg:province":"MN",
    "sg:tags":[
        "mfg"
    ],
    "wof:name":"Penne Franks Simon",
    "wof:placetype":"venue"
},
  "geometry": {"coordinates":[-93.225472,45.132922],"type":"Point"}
}