{
  "type": "Feature",
  "properties": {
    "addr:full":"600 River Ave S Sauk Rapids MN 56379",
    "addr:housenumber":"600",
    "addr:postcode":"56379",
    "addr:street":"River Ave S Sauk",
    "iso:country":"US",
    "sg:address":"600 River Ave S",
    "sg:city":"Sauk Rapids",
    "sg:classifiers":[
        {
            "category":"Social Services",
            "subcategory":"Child Care",
            "type":"Services"
        }
    ],
    "sg:phone":"+1 320 230 1855",
    "sg:postcode":"56379",
    "sg:province":"MN",
    "sg:tags":[
        "day"
    ],
    "wof:name":"Hopscotch Daycare",
    "wof:placetype":"venue"
},
  "geometry": {"coordinates":[-94.163989,45.582691],"type":"Point"}
}