{
  "type": "Feature",
  "properties": {
    "iso:country":"US",
    "sg:address":"1065 Willow View Dr",
    "sg:city":"Long Lake",
    "sg:classifiers":[
        {
            "category":"Autos & Motor Vehicles",
            "subcategory":"Automobile Sales",
            "type":"Retail Goods"
        }
    ],
    "sg:phone":"+1 763 377 7756",
    "sg:postcode":"55356",
    "sg:province":"MN",
    "wof:name":"Volvo Trucks North America",
    "wof:placetype":"venue"
},
  "geometry": {"coordinates":[-93.587096,44.995408],"type":"Point"}
}