{
  "type": "Feature",
  "properties": {
    "iso:country":"US",
    "sg:address":"447 7th Ave S",
    "sg:city":"South Saint Paul",
    "sg:classifiers":[
        {
            "category":"Professional",
            "subcategory":"Art Services",
            "type":"Services"
        }
    ],
    "sg:phone":"+1 651 602 0121",
    "sg:postcode":"55075",
    "sg:province":"MN",
    "sg:tags":[
        "commercial",
        "design"
    ],
    "wof:name":"Hockeyworks",
    "wof:placetype":"venue"
},
  "geometry": {"coordinates":[-93.042299,44.884355],"type":"Point"}
}