{
  "type": "Feature",
  "properties": {
    "addr:full":"2806 15th Ave NW Rochester MN 55901",
    "addr:housenumber":"2806",
    "addr:postcode":"55901",
    "addr:street":"15Th Ave Nw",
    "iso:country":"US",
    "sg:address":"2806 15th Ave NW",
    "sg:city":"Rochester",
    "sg:classifiers":[
        {
            "category":"Building & Trades",
            "subcategory":"Construction",
            "type":"Services"
        }
    ],
    "sg:phone":"+1 507 288 3411",
    "sg:postcode":"55901",
    "sg:province":"MN",
    "sg:tags":[
        "altering",
        "bathroom",
        "remodeling",
        "contractor"
    ],
    "wof:name":"Bruce Hanson Construction",
    "wof:placetype":"venue"
},
  "geometry": {"coordinates":[-92.486259,44.052865],"type":"Point"}
}