{
  "type": "Feature",
  "properties": {
    "iso:country":"US",
    "sg:address":"16256 Temple Dr S",
    "sg:city":"Minnetonka",
    "sg:classifiers":[
        {
            "category":"Professional",
            "subcategory":"Computer Services",
            "type":"Services"
        }
    ],
    "sg:phone":"+1 952 935 8074",
    "sg:postcode":"55345",
    "sg:province":"MN",
    "sg:tags":[
        "prepackaged",
        "cd-rom",
        "software"
    ],
    "wof:name":"Remserv Inc",
    "wof:placetype":"venue"
},
  "geometry": {"coordinates":[-93.486043,44.914047],"type":"Point"}
}