{
  "type": "Feature",
  "properties": {
    "iso:country":"US",
    "sg:address":"5325 Lyndale Ave S",
    "sg:city":"Minneapolis",
    "sg:classifiers":[
        {
            "category":"Restaurant",
            "type":"Food & Drink"
        }
    ],
    "sg:phone":"+1 612 827 7376",
    "sg:postcode":"55419",
    "sg:province":"MN",
    "sg:tags":[
        "italian"
    ],
    "sg:website":"http://www.primamn.com",
    "wof:name":"Prima Pasta/Salads/Panini",
    "wof:placetype":"venue"
},
  "geometry": {"coordinates":[-93.28822,44.906173],"type":"Point"}
}