{
  "type": "Feature",
  "properties": {
    "iso:country":"US",
    "sg:address":"19981 Dogwood St NW",
    "sg:city":"Cedar",
    "sg:classifiers":[
        {
            "category":"Building & Trades",
            "subcategory":"Plumbing",
            "type":"Services"
        }
    ],
    "sg:phone":"+1 763 413 0728",
    "sg:postcode":"55011",
    "sg:province":"MN",
    "sg:tags":[
        "design",
        "install",
        "septic",
        "system"
    ],
    "wof:name":"D & T & Son Trucking & Excvtg",
    "wof:placetype":"venue"
},
  "geometry": {"coordinates":[-93.27167,45.332191],"type":"Point"}
}