{
  "type": "Feature",
  "properties": {
    "addr:full":"2117 W River Rd Ste 1 Minneapolis MN 55411",
    "addr:housenumber":"2117",
    "addr:postcode":"55411",
    "addr:street":"W River Rd Ste 1",
    "iso:country":"US",
    "sg:address":"2117 W River Rd Ste 1",
    "sg:city":"Minneapolis",
    "sg:classifiers":[
        {
            "category":"Community Center",
            "type":"Public Place"
        },
        {
            "category":"Government",
            "subcategory":"Office",
            "type":"Public Place"
        }
    ],
    "sg:phone":"+1 612 230 6550",
    "sg:postcode":"55411",
    "sg:province":"MN",
    "sg:tags":[
        "recreation",
        "government-city",
        "township",
        "village"
    ],
    "sg:website":"http://www.ci.minneapolis.mn.us",
    "wof:name":"Minneapolis Park Police",
    "wof:placetype":"venue"
},
  "geometry": {"coordinates":[-93.27695300000001,45.000357],"type":"Point"}
}