{
  "type": "Feature",
  "properties": {
    "addr:full":"1620 17th St NW Faribault MN 55021",
    "addr:housenumber":"1620",
    "addr:postcode":"55021",
    "addr:street":"17Th St Nw",
    "iso:country":"US",
    "sg:address":"1620 17th St NW",
    "sg:city":"Faribault",
    "sg:classifiers":[
        {
            "category":"Health Services",
            "subcategory":"Health Practitioner",
            "type":"Services"
        }
    ],
    "sg:phone":"+1 507 332 2204",
    "sg:postcode":"55021",
    "sg:province":"MN",
    "sg:tags":[
        "therapy",
        "physical"
    ],
    "wof:name":"Therapyworks PA",
    "wof:placetype":"venue"
},
  "geometry": {"coordinates":[-93.29154200000001,44.309012],"type":"Point"}
}