{
  "type": "Feature",
  "properties": {
    "iso:country":"US",
    "sg:address":"900 3rd St",
    "sg:city":"Saint Paul Park",
    "sg:classifiers":[
        {
            "category":"Organizations",
            "subcategory":"Religious Organization",
            "type":"Services"
        }
    ],
    "sg:phone":"+1 651 768 0737",
    "sg:postcode":"55071",
    "sg:province":"MN",
    "wof:name":"Celebrtion Praise Cmnty Church",
    "wof:placetype":"venue"
},
  "geometry": {"coordinates":[-92.99789,44.840416],"type":"Point"}
}