{
  "type": "Feature",
  "properties": {
    "addr:full":"9231 Cain Rd Hamel MN 55340",
    "addr:housenumber":"9231",
    "addr:postcode":"55340",
    "addr:street":"Cain Rd",
    "iso:country":"US",
    "sg:address":"9231 Cain Rd",
    "sg:city":"Hamel",
    "sg:classifiers":[
        {
            "category":"Farming",
            "subcategory":"Dairy Farm",
            "type":"Manufacturing & Wholesale Goods"
        }
    ],
    "sg:phone":"+1 763 420 3188",
    "sg:postcode":"55340",
    "sg:province":"MN",
    "wof:name":"Heinz Dairy Farms",
    "wof:placetype":"venue"
},
  "geometry": {"coordinates":[-93.564086,45.121752],"type":"Point"}
}