{
  "type": "Feature",
  "properties": {
    "iso:country":"US",
    "sg:address":"300 N 1st St",
    "sg:city":"Marshall",
    "sg:classifiers":[
        {
            "category":"Professional",
            "subcategory":"Computer Services",
            "type":"Services"
        }
    ],
    "sg:phone":"+1 507 532 9641",
    "sg:postcode":"56258",
    "sg:province":"MN",
    "sg:tags":[
        "website",
        "design"
    ],
    "sg:website":"www.starpoint.net",
    "wof:name":"Net Point",
    "wof:placetype":"venue"
},
  "geometry": {"coordinates":[-95.78469,44.44826],"type":"Point"}
}