{
  "type": "Feature",
  "properties": {
    "addr:full":"3927 120th Ave Bowlus MN 56314",
    "addr:housenumber":"3927",
    "addr:postcode":"56314",
    "addr:street":"120Th Ave",
    "iso:country":"US",
    "sg:address":"3927 120th Ave",
    "sg:city":"Bowlus",
    "sg:classifiers":[
        {
            "category":"Freight",
            "type":"Transportation"
        }
    ],
    "sg:phone":"+1 320 584 8216",
    "sg:postcode":"56314",
    "sg:province":"MN",
    "sg:tags":[
        "trucking"
    ],
    "wof:name":"Duane's Trucking Co",
    "wof:placetype":"venue"
},
  "geometry": {"coordinates":[-94.409761,45.811786],"type":"Point"}
}