{
  "type": "Feature",
  "properties": {
    "iso:country":"US",
    "sg:address":"14210 Northdale Blvd",
    "sg:city":"Rogers",
    "sg:classifiers":[
        {
            "category":"Wholesale",
            "subcategory":"Construction Materials",
            "type":"Manufacturing & Wholesale Goods"
        }
    ],
    "sg:phone":"+1 763 428 4540",
    "sg:postcode":"55374",
    "sg:province":"MN",
    "sg:tags":[
        "f"
    ],
    "wof:name":"Bury Companies Inc",
    "wof:placetype":"venue"
},
  "geometry": {"coordinates":[-93.55572600000001,45.212347],"type":"Point"}
}