{
  "type": "Feature",
  "properties": {
    "iso:country":"US",
    "sg:address":"1723 Grant St NW",
    "sg:city":"Faribault",
    "sg:classifiers":[
        {
            "category":"Autos & Motor Vehicles",
            "subcategory":"Auto Supplies",
            "type":"Retail Goods"
        },
        {
            "category":"Retail",
            "subcategory":"Auto Repair",
            "type":"Services"
        }
    ],
    "sg:phone":"+1 507 334 2061",
    "sg:postcode":"55021",
    "sg:province":"MN",
    "sg:tags":[
        "tire"
    ],
    "wof:name":"Faribault Tire and Auto Svc",
    "wof:placetype":"venue"
},
  "geometry": {"coordinates":[-93.29315800000001,44.294614],"type":"Point"}
}