{
  "type": "Feature",
  "properties": {
    "addr:full":"8931 Palm Rd Britt MN 55710",
    "addr:housenumber":"8931",
    "addr:postcode":"55710",
    "addr:street":"Palm Rd",
    "iso:country":"US",
    "sg:address":"8931 Palm Rd",
    "sg:city":"Britt",
    "sg:classifiers":[
        {
            "category":"Travel",
            "subcategory":"Hotels & Motels",
            "type":"Entertainment"
        }
    ],
    "sg:phone":"+1 218 749 6692",
    "sg:postcode":"55710",
    "sg:province":"MN",
    "sg:tags":[
        "resort",
        "operation"
    ],
    "wof:name":"Shady Bay Resort Inc",
    "wof:placetype":"venue"
},
  "geometry": {"coordinates":[-92.626446,47.642271],"type":"Point"}
}