{
  "type": "Feature",
  "properties": {
    "addr:full":"321 Kingsway Dr Mankato MN 56003",
    "addr:housenumber":"321",
    "addr:postcode":"56003",
    "addr:street":"Kingsway Dr",
    "iso:country":"US",
    "sg:address":"321 Kingsway Dr",
    "sg:city":"Mankato",
    "sg:classifiers":[
        {
            "category":"Building & Trades",
            "subcategory":"Construction",
            "type":"Services"
        }
    ],
    "sg:phone":"+1 507 345 2190",
    "sg:postcode":"56003",
    "sg:province":"MN",
    "sg:tags":[
        "roofing",
        "contractor"
    ],
    "wof:name":"Payless Roofing",
    "wof:placetype":"venue"
},
  "geometry": {"coordinates":[-94.042326,44.18528],"type":"Point"}
}