{
  "type": "Feature",
  "properties": {
    "iso:country":"US",
    "sg:address":"2111 Indiana Ave N",
    "sg:city":"Minneapolis",
    "sg:classifiers":[
        {
            "category":"Banks & Credit Unions",
            "subcategory":"Bank",
            "type":"Services"
        }
    ],
    "sg:phone":"+1 763 588 8563",
    "sg:postcode":"55422",
    "sg:province":"MN",
    "sg:tags":[
        "mortgage"
    ],
    "wof:name":"Wellstreet Mortgage",
    "wof:placetype":"venue"
},
  "geometry": {"coordinates":[-93.332137,45.002548],"type":"Point"}
}