{
  "type": "Feature",
  "properties": {
    "iso:country":"US",
    "sg:address":"9087 Broderick Blvd",
    "sg:city":"Inver Grove Heights",
    "sg:classifiers":[
        {
            "category":"Food & Beverages",
            "subcategory":"Groceries & Convenience Stores",
            "type":"Retail Goods"
        }
    ],
    "sg:phone":"+1 651 451 1760",
    "sg:postcode":"55076",
    "sg:province":"MN",
    "wof:name":"Holiday Stationstores Inc",
    "wof:placetype":"venue"
},
  "geometry": {"coordinates":[-93.043488,44.817308],"type":"Point"}
}