{
  "type": "Feature",
  "properties": {
    "iso:country":"US",
    "sg:address":"211 Central Ave",
    "sg:city":"Nashwauk",
    "sg:classifiers":[
        {
            "category":"Health Services",
            "subcategory":"Doctor",
            "type":"Services"
        }
    ],
    "sg:phone":"+1 218 885 1449",
    "sg:postcode":"55769",
    "sg:province":"MN",
    "sg:tags":[
        "physician",
        "surgeon"
    ],
    "wof:name":"Grand Rapids Clinic-Nashwauk",
    "wof:placetype":"venue"
},
  "geometry": {"coordinates":[-93.165965,47.380572],"type":"Point"}
}