{
  "type": "Feature",
  "properties": {
    "addr:full":"2800 N Rustic Pl Little Canada MN 55117",
    "addr:housenumber":"2800",
    "addr:postcode":"55117",
    "addr:street":"N Rustic Pl",
    "iso:country":"US",
    "sg:address":"2800 N Rustic Pl",
    "sg:city":"Little Canada",
    "sg:classifiers":[
        {
            "category":"Real Estate",
            "subcategory":"Real Estate Operator",
            "type":"Services"
        }
    ],
    "sg:phone":"+1 651 483 8509",
    "sg:postcode":"55117",
    "sg:province":"MN",
    "sg:tags":[
        "apartment"
    ],
    "wof:name":"Lakeside Apartments",
    "wof:placetype":"venue"
},
  "geometry": {"coordinates":[-93.103511,45.024645],"type":"Point"}
}