{
  "type": "Feature",
  "properties": {
    "addr:full":"3529 Longfellow Ave S Minneapolis MN 55407",
    "addr:housenumber":"3529",
    "addr:postcode":"55407",
    "addr:street":"Longfellow Ave S",
    "iso:country":"US",
    "sg:address":"3529 Longfellow Ave S",
    "sg:city":"Minneapolis",
    "sg:classifiers":[
        {
            "category":"Recreation",
            "type":"Entertainment"
        }
    ],
    "sg:phone":"+1 612 721 4184",
    "sg:postcode":"55407",
    "sg:province":"MN",
    "wof:name":"Daddy Wings",
    "wof:placetype":"venue"
},
  "geometry": {"coordinates":[-93.24599000000001,44.938252],"type":"Point"}
}