{
  "type": "Feature",
  "properties": {
    "iso:country":"US",
    "sg:address":"4781 Miller Trunk Hwy",
    "sg:city":"Duluth",
    "sg:classifiers":[
        {
            "category":"Autos & Motor Vehicles",
            "subcategory":"Automobile Sales",
            "type":"Retail Goods"
        }
    ],
    "sg:phone":"+1 218 733 0100",
    "sg:postcode":"55811",
    "sg:province":"MN",
    "wof:name":"Kolar Superstore",
    "wof:placetype":"venue"
},
  "geometry": {"coordinates":[-92.18412499999999,46.820541],"type":"Point"}
}