{
  "type": "Feature",
  "properties": {
    "addr:full":"1779 Carnelian Ln Saint Paul MN 55122",
    "addr:housenumber":"1779",
    "addr:postcode":"55122",
    "addr:street":"Carnelian Ln",
    "iso:country":"US",
    "sg:address":"1779 Carnelian Ln",
    "sg:city":"Saint Paul",
    "sg:classifiers":[
        {
            "category":"Professional",
            "type":"Services"
        }
    ],
    "sg:phone":"+1 651 454 7127",
    "sg:postcode":"55122",
    "sg:province":"MN",
    "wof:name":"Townhome/Condominium Appr",
    "wof:placetype":"venue"
},
  "geometry": {"coordinates":[-93.19344100000001,44.809205],"type":"Point"}
}