{
  "type": "Feature",
  "properties": {
    "addr:full":"15 4th St NE Minneapolis MN 55413",
    "addr:housenumber":"15",
    "addr:postcode":"55413",
    "addr:street":"4Th St Ne",
    "iso:country":"US",
    "sg:address":"15 4th St NE",
    "sg:city":"Minneapolis",
    "sg:classifiers":[
        {
            "category":"Bars & Pubs",
            "type":"Food & Drink"
        }
    ],
    "sg:phone":"+1 612 378 5115",
    "sg:postcode":"55413",
    "sg:province":"MN",
    "sg:tags":[
        "dance",
        "club",
        "night"
    ],
    "wof:name":"Ground Zero Niteclub",
    "wof:placetype":"venue"
},
  "geometry": {"coordinates":[-93.25513100000001,44.988996],"type":"Point"}
}