{
  "type": "Feature",
  "properties": {
    "addr:full":"125 W Kent Rd Duluth MN 55812",
    "addr:housenumber":"125",
    "addr:postcode":"55812",
    "addr:street":"W Kent Rd",
    "iso:country":"US",
    "sg:address":"125 W Kent Rd",
    "sg:city":"Duluth",
    "sg:classifiers":[
        {
            "category":"Real Estate",
            "subcategory":"Real Estate Agent",
            "type":"Services"
        }
    ],
    "sg:phone":"+1 218 724 3394",
    "sg:postcode":"55812",
    "sg:province":"MN",
    "wof:name":"Han Shire Investments Inc",
    "wof:placetype":"venue"
},
  "geometry": {"coordinates":[-92.081923,46.813982],"type":"Point"}
}