{
  "type": "Feature",
  "properties": {
    "addr:full":"1004 Sunset Dr Fergus Falls MN 56537",
    "addr:housenumber":"1004",
    "addr:postcode":"56537",
    "addr:street":"Sunset Dr",
    "iso:country":"US",
    "sg:address":"1004 Sunset Dr",
    "sg:city":"Fergus Falls",
    "sg:classifiers":[
        {
            "category":"Building & Trades",
            "subcategory":"Construction",
            "type":"Services"
        }
    ],
    "sg:phone":"+1 218 736 3100",
    "sg:postcode":"56537",
    "sg:province":"MN",
    "sg:tags":[
        "excavation",
        "contractor"
    ],
    "wof:name":"Earl Strande Excavating",
    "wof:placetype":"venue"
},
  "geometry": {"coordinates":[-96.05398,46.292313],"type":"Point"}
}