{
  "type": "Feature",
  "properties": {
    "iso:country":"US",
    "sg:address":"3020 W 66th St",
    "sg:city":"Minneapolis",
    "sg:classifiers":[
        {
            "category":"Autos & Motor Vehicles",
            "subcategory":"Auto Supplies",
            "type":"Retail Goods"
        },
        {
            "category":"Retail",
            "subcategory":"Auto Repair",
            "type":"Services"
        }
    ],
    "sg:phone":"+1 612 225 9574",
    "sg:postcode":"55423",
    "sg:province":"MN",
    "sg:tags":[
        "tire"
    ],
    "sg:website":"http://www.tiresplus.com",
    "wof:name":"Tires Plus Total Car Care",
    "wof:placetype":"venue"
},
  "geometry": {"coordinates":[-93.317593,44.883592],"type":"Point"}
}