{
  "type": "Feature",
  "properties": {
    "iso:country":"US",
    "sg:address":"505 N 2nd St",
    "sg:city":"Princeton",
    "sg:classifiers":[
        {
            "category":"Organizations",
            "subcategory":"Community Association",
            "type":"Services"
        }
    ],
    "sg:phone":"+1 763 389 9959",
    "sg:postcode":"55371",
    "sg:province":"MN",
    "sg:tags":[
        "military"
    ],
    "wof:name":"Princeton VFW Club",
    "wof:placetype":"venue"
},
  "geometry": {"coordinates":[-93.580842,45.571024],"type":"Point"}
}