{
  "type": "Feature",
  "properties": {
    "iso:country":"US",
    "sg:address":"1413 Hwy 33 S",
    "sg:city":"Cloquet",
    "sg:classifiers":[
        {
            "category":"Travel",
            "subcategory":"Hotels & Motels",
            "type":"Entertainment"
        }
    ],
    "sg:phone":"+1 218 879 4638",
    "sg:postcode":"55720",
    "sg:province":"MN",
    "wof:name":"Driftwood Apartments",
    "wof:placetype":"venue"
},
  "geometry": {"coordinates":[-92.456975,46.69791],"type":"Point"}
}