{
  "type": "Feature",
  "properties": {
    "iso:country":"US",
    "sg:address":"6130 72nd Ln N",
    "sg:city":"Minneapolis",
    "sg:classifiers":[
        {
            "category":"Building & Trades",
            "subcategory":"Construction",
            "type":"Services"
        }
    ],
    "sg:phone":"+1 763 560 7214",
    "sg:postcode":"55429",
    "sg:province":"MN",
    "sg:tags":[
        "hanging",
        "contractor"
    ],
    "wof:name":"Faiks Quality Painting",
    "wof:placetype":"venue"
},
  "geometry": {"coordinates":[-93.360313,45.086765],"type":"Point"}
}