{
  "type": "Feature",
  "properties": {
    "iso:country":"US",
    "sg:address":"195 State Hwy 5",
    "sg:city":"Saint Paul",
    "sg:classifiers":[
        {
            "category":"Professional",
            "type":"Services"
        }
    ],
    "sg:phone":"+1 651 292 1646",
    "sg:postcode":"55101",
    "sg:province":"MN",
    "wof:name":"B & B Office Services",
    "wof:placetype":"venue"
},
  "geometry": {"coordinates":[-93.090322,44.950789],"type":"Point"}
}