{
  "type": "Feature",
  "properties": {
    "addr:full":"336 Main Ave Chandler MN 56122",
    "addr:housenumber":"336",
    "addr:postcode":"56122",
    "addr:street":"Main Ave",
    "iso:country":"US",
    "sg:address":"336 Main Ave",
    "sg:city":"Chandler",
    "sg:classifiers":[
        {
            "category":"Food & Beverages",
            "subcategory":"Groceries & Convenience Stores",
            "type":"Retail Goods"
        }
    ],
    "sg:phone":"+1 507 677 2254",
    "sg:postcode":"56122",
    "sg:province":"MN",
    "sg:tags":[
        "grocer"
    ],
    "wof:name":"Chandler Grocery",
    "wof:placetype":"venue"
},
  "geometry": {"coordinates":[-95.947287,43.928931],"type":"Point"}
}