{
  "type": "Feature",
  "properties": {
    "addr:full":"1567 Selby Ave Saint Paul MN 55104",
    "addr:housenumber":"1567",
    "addr:postcode":"55104",
    "addr:street":"Selby Ave",
    "iso:country":"US",
    "sg:address":"1567 Selby Ave",
    "sg:city":"Saint Paul",
    "sg:classifiers":[
        {
            "category":"Health Services",
            "subcategory":"Chiropractor",
            "type":"Services"
        }
    ],
    "sg:phone":"+1 651 644 3900",
    "sg:postcode":"55104",
    "sg:province":"MN",
    "wof:name":"Skon Chiropractic Clinic",
    "wof:placetype":"venue"
},
  "geometry": {"coordinates":[-93.165569,44.946654],"type":"Point"}
}