{
  "type": "Feature",
  "properties": {
    "iso:country":"US",
    "sg:address":"13504 Morgan Ave S",
    "sg:city":"Burnsville",
    "sg:classifiers":[
        {
            "category":"Banks & Credit Unions",
            "subcategory":"Financial Services",
            "type":"Services"
        }
    ],
    "sg:phone":"+1 952 882 8305",
    "sg:postcode":"55337",
    "sg:province":"MN",
    "sg:tags":[
        "company",
        "holding"
    ],
    "wof:name":"Alednac Ltd",
    "wof:placetype":"venue"
},
  "geometry": {"coordinates":[-93.305261,44.760481],"type":"Point"}
}