{
  "type": "Feature",
  "properties": {
    "addr:full":"1320 Toledo Ave N Minneapolis MN 55422",
    "addr:housenumber":"1320",
    "addr:postcode":"55422",
    "addr:street":"Toledo Ave N",
    "iso:country":"US",
    "sg:address":"1320 Toledo Ave N",
    "sg:city":"Minneapolis",
    "sg:classifiers":[
        {
            "category":"Professional",
            "subcategory":"Management & Consulting",
            "type":"Services"
        },
        {
            "category":"Banks & Credit Unions",
            "subcategory":"Financial Services",
            "type":"Services"
        }
    ],
    "sg:phone":"+1 763 521 2244",
    "sg:postcode":"55422",
    "sg:province":"MN",
    "sg:tags":[
        "consultant",
        "financing",
        "planning"
    ],
    "wof:name":"Lazarov & Associates",
    "wof:placetype":"venue"
},
  "geometry": {"coordinates":[-93.345879,44.992402],"type":"Point"}
}