{
  "type": "Feature",
  "properties": {
    "addr:full":"504 Hwy 25 S Monticello MN 55362",
    "addr:housenumber":"504",
    "addr:postcode":"55362",
    "addr:street":"Hwy 25 S",
    "iso:country":"US",
    "sg:address":"504 Hwy 25 S",
    "sg:city":"Monticello",
    "sg:classifiers":[
        {
            "category":"Health Services",
            "subcategory":"Doctor",
            "type":"Services"
        }
    ],
    "sg:phone":"+1 763 295 4060",
    "sg:postcode":"55362",
    "sg:province":"MN",
    "sg:tags":[
        "medical"
    ],
    "wof:name":"Buffalo Clinic PA",
    "wof:placetype":"venue"
},
  "geometry": {"coordinates":[-93.796689,45.302006],"type":"Point"}
}