{
  "type": "Feature",
  "properties": {
    "addr:full":"305 2nd St NW Stewartville MN 55976",
    "addr:housenumber":"305",
    "addr:postcode":"55976",
    "addr:street":"2Nd St Nw",
    "iso:country":"US",
    "sg:address":"305 2nd St NW",
    "sg:city":"Stewartville",
    "sg:classifiers":[
        {
            "category":"Professional",
            "subcategory":"Employment Agencies",
            "type":"Services"
        }
    ],
    "sg:phone":"+1 507 533 4530",
    "sg:postcode":"55976",
    "sg:province":"MN",
    "sg:tags":[
        "help",
        "supply"
    ],
    "wof:name":"Quality Office Services",
    "wof:placetype":"venue"
},
  "geometry": {"coordinates":[-92.492287,43.856214],"type":"Point"}
}