{
  "type": "Feature",
  "properties": {
    "addr:full":"1211 Old Hwy 8 New Brighton MN 55112",
    "addr:housenumber":"1211",
    "addr:postcode":"55112",
    "addr:street":"Old Hwy 8",
    "iso:country":"US",
    "sg:address":"1211 Old Hwy 8",
    "sg:city":"New Brighton",
    "sg:classifiers":[
        {
            "category":"Building & Trades",
            "subcategory":"Plumbing",
            "type":"Services"
        }
    ],
    "sg:phone":"+1 651 633 0125",
    "sg:postcode":"55112",
    "sg:province":"MN",
    "sg:tags":[
        "heating",
        "contractor"
    ],
    "wof:name":"Care Air Conditioining & Htg",
    "wof:placetype":"venue"
},
  "geometry": {"coordinates":[-93.191875,45.071464],"type":"Point"}
}