{
  "type": "Feature",
  "properties": {
    "addr:full":"3938 W 49th St Minneapolis MN 55424",
    "addr:housenumber":"3938",
    "addr:postcode":"55424",
    "addr:street":"W 49Th St",
    "iso:country":"US",
    "sg:address":"3938 W 49th St",
    "sg:city":"Minneapolis",
    "sg:classifiers":[
        {
            "category":"Organizations",
            "subcategory":"Religious Organization",
            "type":"Services"
        }
    ],
    "sg:phone":"+1 952 926 3069",
    "sg:postcode":"55424",
    "sg:province":"MN",
    "wof:name":"DCS Investments Inc",
    "wof:placetype":"venue"
},
  "geometry": {"coordinates":[-93.332137,44.914405],"type":"Point"}
}