{
  "type": "Feature",
  "properties": {
    "addr:full":"7201 156th Ave NW Pennock MN 56279",
    "addr:housenumber":"7201",
    "addr:postcode":"56279",
    "addr:street":"156Th Ave Nw",
    "iso:country":"US",
    "sg:address":"7201 156th Ave NW",
    "sg:city":"Pennock",
    "sg:classifiers":[
        {
            "category":"Retail",
            "subcategory":"Auto Repair",
            "type":"Services"
        }
    ],
    "sg:phone":"+1 320 599 4223",
    "sg:postcode":"56279",
    "sg:province":"MN",
    "sg:tags":[
        "body"
    ],
    "wof:name":"J & M Painting",
    "wof:placetype":"venue"
},
  "geometry": {"coordinates":[-95.13533200000001,45.272534],"type":"Point"}
}