{
  "type": "Feature",
  "properties": {
    "addr:full":"1809 N Minnesota St New Ulm MN 56073",
    "addr:housenumber":"1809",
    "addr:postcode":"56073",
    "addr:street":"N Minnesota St",
    "iso:country":"US",
    "sg:address":"1809 N Minnesota St",
    "sg:city":"New Ulm",
    "sg:classifiers":[
        {
            "category":"Building & Trades",
            "subcategory":"Plumbing",
            "type":"Services"
        }
    ],
    "sg:phone":"+1 507 354 6178",
    "sg:postcode":"56073",
    "sg:province":"MN",
    "sg:tags":[
        "contractor"
    ],
    "wof:name":"Schultz Plumbing & Heating",
    "wof:placetype":"venue"
},
  "geometry": {"coordinates":[-94.475852,44.330885],"type":"Point"}
}