{
  "type": "Feature",
  "properties": {
    "iso:country":"US",
    "sg:address":"320 2nd St NW",
    "sg:city":"Wadena",
    "sg:classifiers":[
        {
            "category":"Building & Trades",
            "subcategory":"Construction",
            "type":"Services"
        }
    ],
    "sg:phone":"+1 218 631 1178",
    "sg:postcode":"56482",
    "sg:province":"MN",
    "sg:tags":[
        "dirt",
        "moving",
        "contractor"
    ],
    "wof:name":"Eugene Cottrell",
    "wof:placetype":"venue"
},
  "geometry": {"coordinates":[-95.136692,46.445784],"type":"Point"}
}