{
  "type": "Feature",
  "properties": {
    "addr:full":"3000 County Road 42 W Burnsville MN 55337",
    "addr:housenumber":"3000",
    "addr:postcode":"55337",
    "addr:street":"County Road 42 W",
    "iso:country":"US",
    "sg:address":"3000 County Road 42 W",
    "sg:city":"Burnsville",
    "sg:classifiers":[
        {
            "category":"Health Services",
            "subcategory":"Chiropractor",
            "type":"Services"
        }
    ],
    "sg:phone":"+1 952 224 5448",
    "sg:postcode":"55337",
    "sg:province":"MN",
    "wof:name":"Savage Chiropractic & Natural Care Center",
    "wof:placetype":"venue"
},
  "geometry": {"coordinates":[-93.317313,44.746477],"type":"Point"}
}