{
  "type": "Feature",
  "properties": {
    "iso:country":"US",
    "sg:address":"1555 Queens Dr",
    "sg:city":"Saint Paul",
    "sg:classifiers":[
        {
            "category":"Shopping",
            "subcategory":"Computers & Home Electronics",
            "type":"Retail Goods"
        }
    ],
    "sg:phone":"+1 651 731 1090",
    "sg:postcode":"55125",
    "sg:province":"MN",
    "sg:tags":[
        "supply",
        "electronic",
        "household",
        "appliance",
        "equipment",
        "consumer"
    ],
    "wof:name":"Best Buy",
    "wof:placetype":"venue"
},
  "geometry": {"coordinates":[-92.957801,44.926601],"type":"Point"}
}