{
  "type": "Feature",
  "properties": {
    "addr:full":"15344 Blackhawk Rd Audubon MN 56511",
    "addr:housenumber":"15344",
    "addr:postcode":"56511",
    "addr:street":"Blackhawk Rd",
    "iso:country":"US",
    "sg:address":"15344 Blackhawk Rd",
    "sg:city":"Audubon",
    "sg:classifiers":[
        {
            "category":"Professional",
            "type":"Services"
        }
    ],
    "sg:phone":"+1 218 439 6165",
    "sg:postcode":"56511",
    "sg:province":"MN",
    "wof:name":"Scott & Lisa Rietsema",
    "wof:placetype":"venue"
},
  "geometry": {"coordinates":[-96.02303499999999,46.796787],"type":"Point"}
}