{
  "type": "Feature",
  "properties": {
    "addr:full":"204 Skyline Dr Wabasha MN 55981",
    "addr:housenumber":"204",
    "addr:postcode":"55981",
    "addr:street":"Skyline Dr",
    "iso:country":"US",
    "sg:address":"204 Skyline Dr",
    "sg:city":"Wabasha",
    "sg:classifiers":[
        {
            "category":"Shopping",
            "type":"Retail Goods"
        }
    ],
    "sg:phone":"+1 651 565 2340",
    "sg:postcode":"55981",
    "sg:province":"MN",
    "sg:tags":[
        "merchandise"
    ],
    "wof:name":"Pembroke Gallery & Design",
    "wof:placetype":"venue"
},
  "geometry": {"coordinates":[-92.03744399999999,44.353028],"type":"Point"}
}