{
  "type": "Feature",
  "properties": {
    "iso:country":"US",
    "sg:address":"340 S Lake Ave",
    "sg:city":"Duluth",
    "sg:classifiers":[
        {
            "category":"Restaurant",
            "type":"Food & Drink"
        }
    ],
    "sg:menulink":"http://www.allmenus.com/mn/duluth/88104-green-mill/menu/",
    "sg:phone":"+1 218 727 7000",
    "sg:postcode":"55802",
    "sg:province":"MN",
    "sg:tags":[
        "american",
        "pizza"
    ],
    "wof:name":"Green Mill",
    "wof:placetype":"venue"
},
  "geometry": {"coordinates":[-92.095659,46.783112],"type":"Point"}
}