{
  "type": "Feature",
  "properties": {
    "addr:full":"6810 Hemlock Ln N Maple Grove MN 55369",
    "addr:housenumber":"6810",
    "addr:postcode":"55369",
    "addr:street":"Hemlock Ln N",
    "iso:country":"US",
    "sg:address":"6810 Hemlock Ln N",
    "sg:city":"Maple Grove",
    "sg:classifiers":[
        {
            "category":"Health Services",
            "subcategory":"Doctor",
            "type":"Services"
        }
    ],
    "sg:phone":"+1 763 425 9888",
    "sg:postcode":"55369",
    "sg:province":"MN",
    "sg:tags":[
        "dentist"
    ],
    "sg:website":"www.accorde.com",
    "wof:name":"Accorde Orthodontists PA",
    "wof:placetype":"venue"
},
  "geometry": {"coordinates":[-93.43110900000001,45.078581],"type":"Point"}
}