{
  "type": "Feature",
  "properties": {
    "addr:full":"62 N 1st St Vining MN 56588",
    "addr:housenumber":"62",
    "addr:postcode":"56588",
    "addr:street":"N 1St St",
    "iso:country":"US",
    "sg:address":"62 N 1st St",
    "sg:city":"Vining",
    "sg:classifiers":[
        {
            "category":"Manufacturing",
            "subcategory":"Tools & Machinery",
            "type":"Manufacturing & Wholesale Goods"
        }
    ],
    "sg:phone":"+1 218 267 5050",
    "sg:postcode":"56588",
    "sg:province":"MN",
    "sg:tags":[
        "industrial",
        "mfg"
    ],
    "wof:name":"Urbank Machine & Company Inc",
    "wof:placetype":"venue"
},
  "geometry": {"coordinates":[-95.510476,46.124527],"type":"Point"}
}