{
  "type": "Feature",
  "properties": {
    "addr:full":"213 N Sibley Ave Litchfield MN 55355",
    "addr:housenumber":"213",
    "addr:postcode":"55355",
    "addr:street":"N Sibley Ave",
    "iso:country":"US",
    "sg:address":"213 N Sibley Ave",
    "sg:city":"Litchfield",
    "sg:classifiers":[
        {
            "category":"Personal",
            "subcategory":"Barber",
            "type":"Services"
        }
    ],
    "sg:phone":"+1 320 693 2421",
    "sg:postcode":"55355",
    "sg:province":"MN",
    "sg:tags":[
        "shop"
    ],
    "wof:name":"Larry's Barber & Style",
    "wof:placetype":"venue"
},
  "geometry": {"coordinates":[-94.528195,45.128473],"type":"Point"}
}