{
  "type": "Feature",
  "properties": {
    "addr:full":"6817 Wayzata Blvd Minneapolis MN 55426",
    "addr:housenumber":"6817",
    "addr:postcode":"55426",
    "addr:street":"Wayzata Blvd",
    "iso:country":"US",
    "sg:address":"6817 Wayzata Blvd",
    "sg:city":"Minneapolis",
    "sg:classifiers":[
        {
            "category":"Shopping",
            "subcategory":"Stationery & Office Supplies",
            "type":"Retail Goods"
        },
        {
            "category":"Professional",
            "subcategory":"Computer Services",
            "type":"Services"
        }
    ],
    "sg:phone":"+1 952 544 5400",
    "sg:postcode":"55426",
    "sg:province":"MN",
    "sg:tags":[
        "repair",
        "equipment"
    ],
    "sg:website":"www.cttechnologies.com",
    "wof:name":"Ct Technologies",
    "wof:placetype":"venue"
},
  "geometry": {"coordinates":[-93.366203,44.970901],"type":"Point"}
}