{
  "type": "Feature",
  "properties": {
    "iso:country":"US",
    "sg:address":"21909 594th Ave",
    "sg:city":"Mankato",
    "sg:classifiers":[
        {
            "category":"Retail",
            "subcategory":"Repair Shop",
            "type":"Services"
        }
    ],
    "sg:phone":"+1 507 344 0858",
    "sg:postcode":"56001",
    "sg:province":"MN",
    "wof:name":"Leos Custom Cycle",
    "wof:placetype":"venue"
},
  "geometry": {"coordinates":[-93.908895,44.181251],"type":"Point"}
}