{
  "type": "Feature",
  "properties": {
    "addr:full":"87455 340th Ave Heron Lake MN 56137",
    "addr:housenumber":"87455",
    "addr:postcode":"56137",
    "addr:street":"340Th Ave",
    "iso:country":"US",
    "sg:address":"87455 340th Ave",
    "sg:city":"Heron Lake",
    "sg:classifiers":[
        {
            "category":"Real Estate",
            "subcategory":"Real Estate Operator",
            "type":"Services"
        }
    ],
    "sg:phone":"+1 507 793 2446",
    "sg:postcode":"56137",
    "sg:province":"MN",
    "sg:tags":[
        "property",
        "lessor"
    ],
    "wof:name":"Donald Pelzel",
    "wof:placetype":"venue"
},
  "geometry": {"coordinates":[-95.39561,43.750359],"type":"Point"}
}