{
  "type": "Feature",
  "properties": {
    "iso:country":"US",
    "sg:address":"70305 270th Ave",
    "sg:city":"Kasson",
    "sg:classifiers":[
        {
            "category":"Farming",
            "subcategory":"Livestock Farm",
            "type":"Manufacturing & Wholesale Goods"
        },
        {
            "category":"Farming",
            "subcategory":"Farm",
            "type":"Manufacturing & Wholesale Goods"
        }
    ],
    "sg:phone":"+1 507 365 8007",
    "sg:postcode":"55944",
    "sg:province":"MN",
    "sg:tags":[
        "ranch"
    ],
    "wof:name":"Joel Senjem",
    "wof:placetype":"venue"
},
  "geometry": {"coordinates":[-92.698097,44.025434],"type":"Point"}
}