{
  "type": "Feature",
  "properties": {
    "iso:country":"US",
    "sg:address":"2510 Bridge Ave",
    "sg:city":"Albert Lea",
    "sg:classifiers":[
        {
            "category":"Shopping",
            "subcategory":"Clothing, Apparel, & Fashions",
            "type":"Retail Goods"
        }
    ],
    "sg:phone":"+1 507 373 8926",
    "sg:postcode":"56007",
    "sg:province":"MN",
    "sg:tags":[
        "accessory"
    ],
    "wof:name":"Claires",
    "wof:placetype":"venue"
},
  "geometry": {"coordinates":[-93.358829,43.681892],"type":"Point"}
}