{
  "type": "Feature",
  "properties": {
    "iso:country":"US",
    "sg:address":"200 7th St NE",
    "sg:city":"Little Falls",
    "sg:classifiers":[
        {
            "category":"Freight",
            "type":"Transportation"
        }
    ],
    "sg:phone":"+1 320 632 2349",
    "sg:postcode":"56345",
    "sg:province":"MN",
    "sg:tags":[
        "operator",
        "trucking"
    ],
    "wof:name":"OBrien & Associates",
    "wof:placetype":"venue"
},
  "geometry": {"coordinates":[-94.35279199999999,45.977309],"type":"Point"}
}