{
  "type": "Feature",
  "properties": {
    "addr:full":"1723 11th St E Glencoe MN 55336",
    "addr:housenumber":"1723",
    "addr:postcode":"55336",
    "addr:street":"11Th St E",
    "iso:country":"US",
    "sg:address":"1723 11th St E",
    "sg:city":"Glencoe",
    "sg:classifiers":[
        {
            "category":"Building & Trades",
            "subcategory":"Construction",
            "type":"Services"
        }
    ],
    "sg:phone":"+1 320 864 4223",
    "sg:postcode":"55336",
    "sg:province":"MN",
    "sg:tags":[
        "house",
        "contractor"
    ],
    "wof:name":"Ndi Builders",
    "wof:placetype":"venue"
},
  "geometry": {"coordinates":[-94.139394,44.770162],"type":"Point"}
}