{
  "type": "Feature",
  "properties": {
    "iso:country":"US",
    "sg:address":"10384 Cherokee St",
    "sg:city":"Wadena",
    "sg:classifiers":[
        {
            "category":"Professional",
            "subcategory":"Detective & Security Services",
            "type":"Services"
        }
    ],
    "sg:phone":"+1 218 631 2520",
    "sg:postcode":"56482",
    "sg:province":"MN",
    "sg:tags":[
        "car"
    ],
    "wof:name":"Lone Star Agency",
    "wof:placetype":"venue"
},
  "geometry": {"coordinates":[-95.14832199999999,46.413415],"type":"Point"}
}