{
  "type": "Feature",
  "properties": {
    "iso:country":"US",
    "sg:address":"4131 Grand Ave",
    "sg:city":"Duluth",
    "sg:classifiers":[
        {
            "category":"Restaurant",
            "type":"Food & Drink"
        }
    ],
    "sg:phone":"+1 218 628 3977",
    "sg:postcode":"55807",
    "sg:province":"MN",
    "sg:tags":[
        "eating"
    ],
    "wof:name":"Wong's Express",
    "wof:placetype":"venue"
},
  "geometry": {"coordinates":[-92.152715,46.750598],"type":"Point"}
}