{
  "type": "Feature",
  "properties": {
    "addr:full":"2163 W Berkeley Ave Saint Paul MN 55105",
    "addr:housenumber":"2163",
    "addr:postcode":"55105",
    "addr:street":"W Berkeley Ave",
    "iso:country":"US",
    "sg:address":"2163 W Berkeley Ave",
    "sg:city":"Saint Paul",
    "sg:classifiers":[
        {
            "category":"Professional",
            "type":"Services"
        }
    ],
    "sg:phone":"+1 651 690 0466",
    "sg:postcode":"55105",
    "sg:province":"MN",
    "wof:name":"Mike Westermeyer",
    "wof:placetype":"venue"
},
  "geometry": {"coordinates":[-93.191175,44.93348],"type":"Point"}
}