{
  "type": "Feature",
  "properties": {
    "iso:country":"US",
    "sg:address":"214 6th Ave",
    "sg:city":"Internatl Falls",
    "sg:classifiers":[
        {
            "category":"Museum",
            "type":"Entertainment"
        }
    ],
    "sg:phone":"+1 218 283 4316",
    "sg:postcode":"56649",
    "sg:province":"MN",
    "wof:name":"Koochiching Cnty Hist Museum",
    "wof:placetype":"venue"
},
  "geometry": {"coordinates":[-93.408278,48.602877],"type":"Point"}
}