{
  "type": "Feature",
  "properties": {
    "addr:full":"2931 E Lake St Minneapolis MN 55406",
    "addr:housenumber":"2931",
    "addr:postcode":"55406",
    "addr:street":"E Lake St",
    "iso:country":"US",
    "sg:address":"2931 E Lake St",
    "sg:city":"Minneapolis",
    "sg:classifiers":[
        {
            "category":"Personal",
            "subcategory":"Tattoo Parlor",
            "type":"Services"
        }
    ],
    "sg:phone":"+1 612 722 5053",
    "sg:postcode":"55406",
    "sg:province":"MN",
    "sg:tags":[
        "tattooing"
    ],
    "wof:name":"555 Studios",
    "wof:placetype":"venue"
},
  "geometry": {"coordinates":[-93.22877800000001,44.948297],"type":"Point"}
}