{
  "type": "Feature",
  "properties": {
    "iso:country":"US",
    "sg:address":"22004 208th St",
    "sg:city":"Richmond",
    "sg:classifiers":[
        {
            "category":"Building & Trades",
            "subcategory":"Landscaping Services",
            "type":"Services"
        }
    ],
    "sg:phone":"+1 320 597 4158",
    "sg:postcode":"56368",
    "sg:province":"MN",
    "sg:tags":[
        "lawn",
        "landscape",
        "maintenance",
        "contractor"
    ],
    "wof:name":"Turf Pro's",
    "wof:placetype":"venue"
},
  "geometry": {"coordinates":[-94.534811,45.443617],"type":"Point"}
}