{
  "type": "Feature",
  "properties": {
    "addr:full":"901 Mainstreet Hopkins MN 55343",
    "addr:housenumber":"901",
    "addr:postcode":"55343",
    "addr:street":"Mainstreet",
    "iso:country":"US",
    "sg:address":"901 Mainstreet",
    "sg:city":"Hopkins",
    "sg:classifiers":[
        {
            "category":"Professional",
            "subcategory":"Accounting & Tax Preparation",
            "type":"Services"
        }
    ],
    "sg:phone":"+1 952 935 7290",
    "sg:postcode":"55343",
    "sg:province":"MN",
    "wof:name":"B & W",
    "wof:placetype":"venue"
},
  "geometry": {"coordinates":[-93.412689,44.924377],"type":"Point"}
}