{
  "type": "Feature",
  "properties": {
    "addr:full":"3470 129th Ave NW Minneapolis MN 55448",
    "addr:housenumber":"3470",
    "addr:postcode":"55448",
    "addr:street":"129Th Ave Nw",
    "iso:country":"US",
    "sg:address":"3470 129th Ave NW",
    "sg:city":"Minneapolis",
    "sg:classifiers":[
        {
            "category":"Restaurant",
            "type":"Food & Drink"
        }
    ],
    "sg:phone":"+1 763 576 9267",
    "sg:postcode":"55448",
    "sg:province":"MN",
    "wof:name":"Applebee's Neighborhood Grill & Bar",
    "wof:placetype":"venue"
},
  "geometry": {"coordinates":[-93.353798,45.205898],"type":"Point"}
}