{
  "type": "Feature",
  "properties": {
    "addr:full":"219 Manila St Willmar MN 56201",
    "addr:housenumber":"219",
    "addr:postcode":"56201",
    "addr:street":"Manila St",
    "iso:country":"US",
    "sg:address":"219 Manila St",
    "sg:city":"Willmar",
    "sg:classifiers":[
        {
            "category":"Social Services",
            "type":"Services"
        }
    ],
    "sg:phone":"+1 320 231 3986",
    "sg:postcode":"56201",
    "sg:province":"MN",
    "wof:name":"Pilot Parents",
    "wof:placetype":"venue"
},
  "geometry": {"coordinates":[-95.040263,45.126859],"type":"Point"}
}