{
  "type": "Feature",
  "properties": {
    "addr:full":"310 S Broadway Crookston MN 56716",
    "addr:housenumber":"310",
    "addr:postcode":"56716",
    "addr:street":"S Broadway",
    "iso:country":"US",
    "sg:address":"310 S Broadway",
    "sg:city":"Crookston",
    "sg:classifiers":[
        {
            "category":"Professional",
            "subcategory":"Lawyer & Legal Services",
            "type":"Services"
        }
    ],
    "sg:phone":"+1 218 281 1200",
    "sg:postcode":"56716",
    "sg:province":"MN",
    "sg:tags":[
        "attorney"
    ],
    "wof:name":"Fischer Law Office",
    "wof:placetype":"venue"
},
  "geometry": {"coordinates":[-96.608304,47.771988],"type":"Point"}
}