{
  "type": "Feature",
  "properties": {
    "addr:full":"304 E River Rd Brainerd MN 56401",
    "addr:housenumber":"304",
    "addr:postcode":"56401",
    "addr:street":"E River Rd",
    "iso:country":"US",
    "sg:address":"304 E River Rd",
    "sg:city":"Brainerd",
    "sg:classifiers":[
        {
            "category":"Professional",
            "subcategory":"Advertising",
            "type":"Services"
        }
    ],
    "sg:phone":"+1 218 829 0232",
    "sg:postcode":"56401",
    "sg:province":"MN",
    "wof:name":"Charter Media Svc & Production",
    "wof:placetype":"venue"
},
  "geometry": {"coordinates":[-94.208134,46.355726],"type":"Point"}
}