{
  "type": "Feature",
  "properties": {
    "addr:full":"17934 Weaver Lake Dr Osseo MN 55311",
    "addr:housenumber":"17934",
    "addr:postcode":"55311",
    "addr:street":"Weaver Lake Dr",
    "iso:country":"US",
    "sg:address":"17934 Weaver Lake Dr",
    "sg:city":"Osseo",
    "sg:classifiers":[
        {
            "category":"Manufacturing",
            "subcategory":"Building Materials",
            "type":"Manufacturing & Wholesale Goods"
        },
        {
            "category":"Building & Trades",
            "subcategory":"Construction",
            "type":"Services"
        }
    ],
    "sg:phone":"+1 763 416 5060",
    "sg:postcode":"55311",
    "sg:province":"MN",
    "sg:tags":[
        "mfg",
        "wood",
        "cabinet",
        "kitchen",
        "woodworker"
    ],
    "wof:name":"Mc Laughlin Woodcraft",
    "wof:placetype":"venue"
},
  "geometry": {"coordinates":[-93.50703,45.111975],"type":"Point"}
}