{
  "type": "Feature",
  "properties": {
    "iso:country":"US",
    "sg:address":"650 3rd Ave SE",
    "sg:city":"Minneapolis",
    "sg:classifiers":[
        {
            "category":"Real Estate",
            "subcategory":"Real Estate Agent",
            "type":"Services"
        }
    ],
    "sg:phone":"+1 612 253 0650",
    "sg:postcode":"55414",
    "sg:province":"MN",
    "sg:tags":[
        "appraiser",
        "business"
    ],
    "wof:name":"Mardell Partners Inc",
    "wof:placetype":"venue"
},
  "geometry": {"coordinates":[-93.248876,44.989498],"type":"Point"}
}