{
  "type": "Feature",
  "properties": {
    "addr:full":"7150 Humphrey Dr Minneapolis MN 55450",
    "addr:housenumber":"7150",
    "addr:postcode":"55450",
    "addr:street":"Humphrey Dr",
    "iso:country":"US",
    "sg:address":"7150 Humphrey Dr",
    "sg:city":"Minneapolis",
    "sg:classifiers":[
        {
            "category":"Retail",
            "subcategory":"Auto Rental",
            "type":"Services"
        }
    ],
    "sg:phone":"+1 612 727 1055",
    "sg:postcode":"55450",
    "sg:province":"MN",
    "sg:tags":[
        "car",
        "truck"
    ],
    "sg:website":"http://www.budget.com/budgetWeb/html/rentals/minneapolis-rental.html?mid=local-yp",
    "wof:name":"Budget Rent-A-Car - Minneapolis-St Paul Intl Apo 2",
    "wof:placetype":"venue"
},
  "geometry": {"coordinates":[-93.22791100000001,44.873543],"type":"Point"}
}