{
  "type": "Feature",
  "properties": {
    "addr:full":"223 Water St Excelsior MN 55331",
    "addr:housenumber":"223",
    "addr:postcode":"55331",
    "addr:street":"Water St",
    "iso:country":"US",
    "sg:address":"223 Water St",
    "sg:city":"Excelsior",
    "sg:classifiers":[
        {
            "category":"Shopping",
            "subcategory":"Clothing, Apparel, & Fashions",
            "type":"Retail Goods"
        }
    ],
    "sg:phone":"+1 952 474 4519",
    "sg:postcode":"55331",
    "sg:province":"MN",
    "sg:tags":[
        "accessory",
        "clothing",
        "women's"
    ],
    "wof:name":"Meridian Ltd A Bennett",
    "wof:placetype":"venue"
},
  "geometry": {"coordinates":[-93.566805,44.902654],"type":"Point"}
}