{
  "type": "Feature",
  "properties": {
    "iso:country":"US",
    "sg:address":"21835 Vista Rd",
    "sg:city":"Hutchinson",
    "sg:classifiers":[
        {
            "category":"Retail",
            "subcategory":"Repair Shop",
            "type":"Services"
        }
    ],
    "sg:phone":"+1 320 587 7754",
    "sg:postcode":"55350",
    "sg:province":"MN",
    "sg:tags":[
        "machine"
    ],
    "wof:name":"Vista Machine Tool Inc",
    "wof:placetype":"venue"
},
  "geometry": {"coordinates":[-94.405275,44.935741],"type":"Point"}
}