{
  "type": "Feature",
  "properties": {
    "iso:country":"US",
    "sg:address":"3900 Vinewood Ln N",
    "sg:city":"Minneapolis",
    "sg:classifiers":[
        {
            "category":"Restaurant",
            "type":"Food & Drink"
        }
    ],
    "sg:menulink":"http://www.allmenus.com/mn/plymouth/84065-dominos-pizza/menu/",
    "sg:phone":"+1 763 557 9999",
    "sg:postcode":"55441",
    "sg:province":"MN",
    "sg:tags":[
        "american",
        "wing",
        "pizza"
    ],
    "wof:name":"Domino's Pizza",
    "wof:placetype":"venue"
},
  "geometry": {"coordinates":[-93.447458,45.027328],"type":"Point"}
}