{
  "type": "Feature",
  "properties": {
    "iso:country":"US",
    "sg:address":"12601 Hudson Rd S",
    "sg:city":"Afton",
    "sg:classifiers":[
        {
            "category":"Freight",
            "type":"Transportation"
        }
    ],
    "sg:phone":"+1 651 436 8461",
    "sg:postcode":"55001",
    "sg:province":"MN",
    "sg:tags":[
        "over",
        "trucking"
    ],
    "wof:name":"Heights Service Inc",
    "wof:placetype":"venue"
},
  "geometry": {"coordinates":[-92.852142,44.946045],"type":"Point"}
}