{
  "type": "Feature",
  "properties": {
    "addr:full":"405 W Lake St Minneapolis MN 55408",
    "addr:housenumber":"405",
    "addr:postcode":"55408",
    "addr:street":"W Lake St",
    "iso:country":"US",
    "sg:address":"405 W Lake St",
    "sg:city":"Minneapolis",
    "sg:classifiers":[
        {
            "category":"Social Services",
            "type":"Services"
        }
    ],
    "sg:phone":"+1 612 824 2612",
    "sg:postcode":"55408",
    "sg:province":"MN",
    "sg:tags":[
        "youth",
        "organization",
        "center"
    ],
    "wof:name":"Twin Cities Underground",
    "wof:placetype":"venue"
},
  "geometry": {"coordinates":[-93.285517,44.948286],"type":"Point"}
}