{
  "type": "Feature",
  "properties": {
    "iso:country":"US",
    "sg:address":"1545 92nd Ln NE",
    "sg:city":"Minneapolis",
    "sg:classifiers":[
        {
            "category":"Building & Trades",
            "subcategory":"Construction",
            "type":"Services"
        }
    ],
    "sg:phone":"+1 763 792 3878",
    "sg:postcode":"55449",
    "sg:province":"MN",
    "sg:tags":[
        "insulation",
        "contractor"
    ],
    "sg:website":"http://www.acousticassociates.com",
    "wof:name":"Acoustic Associates Panel Shop",
    "wof:placetype":"venue"
},
  "geometry": {"coordinates":[-93.231165,45.138252],"type":"Point"}
}