{
  "type": "Feature",
  "properties": {
    "addr:full":"3848 W Broadway Ave Minneapolis MN 55422",
    "addr:housenumber":"3848",
    "addr:postcode":"55422",
    "addr:street":"W Broadway Ave",
    "iso:country":"US",
    "sg:address":"3848 W Broadway Ave",
    "sg:city":"Minneapolis",
    "sg:classifiers":[
        {
            "category":"Real Estate",
            "subcategory":"Real Estate Operator",
            "type":"Services"
        }
    ],
    "sg:phone":"+1 763 533 2600",
    "sg:postcode":"55422",
    "sg:province":"MN",
    "sg:tags":[
        "apartment"
    ],
    "wof:name":"Robin Wood Apartments",
    "wof:placetype":"venue"
},
  "geometry": {"coordinates":[-93.332015,45.02535],"type":"Point"}
}