{
  "type": "Feature",
  "properties": {
    "addr:full":"591 Summit Ave Saint Paul MN 55102",
    "addr:housenumber":"591",
    "addr:postcode":"55102",
    "addr:street":"Summit Ave",
    "iso:country":"US",
    "sg:address":"591 Summit Ave",
    "sg:city":"Saint Paul",
    "sg:classifiers":[
        {
            "category":"Professional",
            "subcategory":"Business Services",
            "type":"Services"
        }
    ],
    "sg:phone":"+1 651 290 2023",
    "sg:postcode":"55102",
    "sg:province":"MN",
    "wof:name":"Custom Accents",
    "wof:placetype":"venue"
},
  "geometry": {"coordinates":[-93.123801,44.941423],"type":"Point"}
}