{
  "type": "Feature",
  "properties": {
    "iso:country":"US",
    "sg:address":"1720 Big Lake Rd",
    "sg:city":"Cloquet",
    "sg:classifiers":[
        {
            "category":"Government",
            "subcategory":"Office",
            "type":"Public Place"
        }
    ],
    "sg:phone":"+1 218 878 8002",
    "sg:postcode":"55720",
    "sg:province":"MN",
    "sg:tags":[
        "combined"
    ],
    "wof:name":"Fond Dulac Preservation",
    "wof:placetype":"venue"
},
  "geometry": {"coordinates":[-92.536222,46.714547],"type":"Point"}
}