{
  "type": "Feature",
  "properties": {
    "iso:country":"US",
    "sg:address":"1231 Oxford St",
    "sg:city":"Worthington",
    "sg:classifiers":[
        {
            "category":"Travel",
            "subcategory":"Hotels & Motels",
            "type":"Entertainment"
        }
    ],
    "sg:phone":"+1 507 376 6136",
    "sg:postcode":"56187",
    "sg:province":"MN",
    "sg:tags":[
        "operation",
        "lodging"
    ],
    "sg:website":"http://www.budgetinn.com",
    "wof:name":"Budget Inn",
    "wof:placetype":"venue"
},
  "geometry": {"coordinates":[-95.59688300000001,43.631192],"type":"Point"}
}