{
  "type": "Feature",
  "properties": {
    "iso:country":"US",
    "sg:address":"23980 Yellowstone Trl",
    "sg:city":"Excelsior",
    "sg:classifiers":[
        {
            "category":"Wholesale",
            "subcategory":"Durable Goods & Equipment",
            "type":"Manufacturing & Wholesale Goods"
        }
    ],
    "sg:phone":"+1 952 470 5463",
    "sg:postcode":"55331",
    "sg:province":"MN",
    "sg:tags":[
        "representative",
        "manufacturer"
    ],
    "wof:name":"Osofast",
    "wof:placetype":"venue"
},
  "geometry": {"coordinates":[-93.585459,44.894951],"type":"Point"}
}