{
  "type": "Feature",
  "properties": {
    "addr:full":"1605 1st St S Willmar MN 56201",
    "addr:housenumber":"1605",
    "addr:postcode":"56201",
    "addr:street":"1St St S",
    "iso:country":"US",
    "sg:address":"1605 1st St S",
    "sg:city":"Willmar",
    "sg:classifiers":[
        {
            "category":"Sports & Exercise",
            "subcategory":"Gym",
            "type":"Entertainment"
        }
    ],
    "sg:phone":"+1 320 222 6984",
    "sg:postcode":"56201",
    "sg:province":"MN",
    "sg:tags":[
        "club",
        "health",
        "studio",
        "gymnasium"
    ],
    "wof:name":"Anytime Fitness",
    "wof:placetype":"venue"
},
  "geometry": {"coordinates":[-95.04261,45.106862],"type":"Point"}
}