{
  "type": "Feature",
  "properties": {
    "addr:full":"1601 Hwy 25 N Buffalo MN 55313",
    "addr:housenumber":"1601",
    "addr:postcode":"55313",
    "addr:street":"Hwy 25 N",
    "iso:country":"US",
    "sg:address":"1601 Hwy 25 N",
    "sg:city":"Buffalo",
    "sg:classifiers":[
        {
            "category":"Organizations",
            "subcategory":"Religious Organization",
            "type":"Services"
        }
    ],
    "sg:phone":"+1 763 682 1470",
    "sg:postcode":"55313",
    "sg:province":"MN",
    "sg:tags":[
        "church"
    ],
    "sg:website":"www.buffalocovenant.org",
    "wof:name":"Buffalo Convenant Church",
    "wof:placetype":"venue"
},
  "geometry": {"coordinates":[-93.874548,45.193083],"type":"Point"}
}