{
  "type": "Feature",
  "properties": {
    "iso:country":"US",
    "sg:address":"6226 Garfield Ave",
    "sg:city":"Minneapolis",
    "sg:classifiers":[
        {
            "category":"Structure",
            "subcategory":"Office Building",
            "type":"Public Place"
        }
    ],
    "sg:phone":"+1 612 869 8026",
    "sg:postcode":"55423",
    "sg:province":"MN",
    "sg:tags":[
        "park"
    ],
    "wof:name":"Sjw Properties",
    "wof:placetype":"venue"
},
  "geometry": {"coordinates":[-93.287002,44.889664],"type":"Point"}
}