{
  "type": "Feature",
  "properties": {
    "addr:full":"511 W Stevens Ave Rushford MN 55971",
    "addr:housenumber":"511",
    "addr:postcode":"55971",
    "addr:street":"W Stevens Ave",
    "iso:country":"US",
    "sg:address":"511 W Stevens Ave",
    "sg:city":"Rushford",
    "sg:classifiers":[
        {
            "category":"Social Services",
            "subcategory":"Child Care",
            "type":"Services"
        }
    ],
    "sg:phone":"+1 507 864 7635",
    "sg:postcode":"55971",
    "sg:province":"MN",
    "sg:tags":[
        "day",
        "provider"
    ],
    "wof:name":"Craig Vogen",
    "wof:placetype":"venue"
},
  "geometry": {"coordinates":[-91.761685,43.807793],"type":"Point"}
}