{
  "type": "Feature",
  "properties": {
    "iso:country":"US",
    "sg:address":"2599 Mississippi St",
    "sg:city":"New Brighton",
    "sg:classifiers":[
        {
            "category":"Freight",
            "type":"Transportation"
        }
    ],
    "sg:phone":"+1 651 633 1313",
    "sg:postcode":"55112",
    "sg:province":"MN",
    "sg:tags":[
        "trucking"
    ],
    "wof:name":"Timmer's Express",
    "wof:placetype":"venue"
},
  "geometry": {"coordinates":[-93.22017099999999,45.08601],"type":"Point"}
}