{
  "type": "Feature",
  "properties": {
    "addr:full":"626 S Kniss Ave Luverne MN 56156",
    "addr:housenumber":"626",
    "addr:postcode":"56156",
    "addr:street":"S Kniss Ave",
    "iso:country":"US",
    "sg:address":"626 S Kniss Ave",
    "sg:city":"Luverne",
    "sg:classifiers":[
        {
            "category":"Personal",
            "subcategory":"Beauty Salon",
            "type":"Services"
        }
    ],
    "sg:phone":"+1 507 283 4343",
    "sg:postcode":"56156",
    "sg:province":"MN",
    "wof:name":"Shear Reflections",
    "wof:placetype":"venue"
},
  "geometry": {"coordinates":[-96.21315300000001,43.647719],"type":"Point"}
}