{
  "type": "Feature",
  "properties": {
    "addr:full":"25485 Highview Ave Farmington MN 55024",
    "addr:postcode":"25485;55024",
    "addr:street":"Highview Ave",
    "iso:country":"US",
    "sg:address":"25485 Highview Ave",
    "sg:city":"Farmington",
    "sg:classifiers":[
        {
            "category":"Professional",
            "type":"Services"
        }
    ],
    "sg:phone":"+1 952 469 5620",
    "sg:postcode":"55024",
    "sg:province":"MN",
    "sg:tags":[
        "establishment"
    ],
    "wof:name":"Stay Well",
    "wof:placetype":"venue"
},
  "geometry": {"coordinates":[-93.23821599999999,44.580698],"type":"Point"}
}