{
  "type": "Feature",
  "properties": {
    "iso:country":"US",
    "sg:address":"1543 210th St",
    "sg:city":"Truman",
    "sg:phone":"+1 507 776 2487",
    "sg:postcode":"56088",
    "sg:province":"MN",
    "sg:tags":[
        "farm",
        "corn",
        "soybean"
    ],
    "wof:name":"Mark Ufer",
    "wof:placetype":"venue"
},
  "geometry": {"coordinates":[-94.56406200000001,43.789829],"type":"Point"}
}