{
  "type": "Feature",
  "properties": {
    "addr:full":"1601 W Main St Albert Lea MN 56007",
    "addr:housenumber":"1601",
    "addr:postcode":"56007",
    "addr:street":"W Main St",
    "iso:country":"US",
    "sg:address":"1601 W Main St",
    "sg:city":"Albert Lea",
    "sg:classifiers":[
        {
            "category":"Shopping",
            "subcategory":"Computers & Home Electronics",
            "type":"Retail Goods"
        }
    ],
    "sg:phone":"+1 507 377 9775",
    "sg:postcode":"56007",
    "sg:province":"MN",
    "sg:tags":[
        "equipment",
        "satellite",
        "system"
    ],
    "wof:name":"Wayne's TV Svc",
    "wof:placetype":"venue"
},
  "geometry": {"coordinates":[-93.388947,43.646315],"type":"Point"}
}