{
  "type": "Feature",
  "properties": {
    "iso:country":"US",
    "sg:address":"36666 State Hwy 65",
    "sg:city":"Mcgregor",
    "sg:classifiers":[
        {
            "category":"Recreation",
            "type":"Entertainment"
        }
    ],
    "sg:phone":"+1 218 768 3311",
    "sg:postcode":"55760",
    "sg:province":"MN",
    "sg:tags":[
        "center"
    ],
    "wof:name":"East Lake Community Ctr",
    "wof:placetype":"venue"
},
  "geometry": {"coordinates":[-93.283604,46.542426],"type":"Point"}
}