{
  "type": "Feature",
  "properties": {
    "iso:country":"US",
    "sg:address":"105 Meadow Ln N",
    "sg:city":"Minneapolis",
    "sg:classifiers":[
        {
            "category":"Professional",
            "type":"Services"
        }
    ],
    "sg:phone":"+1 763 377 1797",
    "sg:postcode":"55422",
    "sg:province":"MN",
    "wof:name":"Hurry Pulver",
    "wof:placetype":"venue"
},
  "geometry": {"coordinates":[-93.331327,44.979249],"type":"Point"}
}