{
  "type": "Feature",
  "properties": {
    "iso:country":"US",
    "sg:address":"488 Robert St S",
    "sg:city":"Saint Paul",
    "sg:classifiers":[
        {
            "category":"Manufacturing",
            "subcategory":"Apparel",
            "type":"Manufacturing & Wholesale Goods"
        }
    ],
    "sg:phone":"+1 651 224 7591",
    "sg:postcode":"55107",
    "sg:province":"MN",
    "sg:tags":[
        "manufacture",
        "athletic",
        "contract",
        "uniform"
    ],
    "wof:name":"Angel",
    "wof:placetype":"venue"
},
  "geometry": {"coordinates":[-93.080761,44.930485],"type":"Point"}
}