{
  "type": "Feature",
  "properties": {
    "iso:country":"US",
    "sg:address":"1965 Donegal Dr",
    "sg:city":"Saint Paul",
    "sg:classifiers":[
        {
            "category":"Real Estate",
            "subcategory":"Developer",
            "type":"Services"
        }
    ],
    "sg:phone":"+1 651 702 0158",
    "sg:postcode":"55125",
    "sg:province":"MN",
    "wof:name":"Reliance Development",
    "wof:placetype":"venue"
},
  "geometry": {"coordinates":[-92.93418699999999,44.925234],"type":"Point"}
}