{
  "type": "Feature",
  "properties": {
    "addr:full":"30736 725th Ave Dassel MN 55325",
    "addr:housenumber":"30736",
    "addr:postcode":"55325",
    "addr:street":"725Th Ave",
    "iso:country":"US",
    "sg:address":"30736 725th Ave",
    "sg:city":"Dassel",
    "sg:classifiers":[
        {
            "category":"Building & Trades",
            "subcategory":"Construction",
            "type":"Services"
        }
    ],
    "sg:phone":"+1 320 212 9065",
    "sg:postcode":"55325",
    "sg:province":"MN",
    "sg:tags":[
        "window",
        "replacement"
    ],
    "wof:name":"Obeco",
    "wof:placetype":"venue"
},
  "geometry": {"coordinates":[-94.30668900000001,45.189112],"type":"Point"}
}