{
  "type": "Feature",
  "properties": {
    "iso:country":"US",
    "sg:address":"551 Coon Rapids Blvd NW # 100",
    "sg:city":"Minneapolis",
    "sg:classifiers":[
        {
            "category":"Professional",
            "subcategory":"Management & Consulting",
            "type":"Services"
        },
        {
            "category":"Banks & Credit Unions",
            "subcategory":"Financial Services",
            "type":"Services"
        }
    ],
    "sg:phone":"+1 763 421 5300",
    "sg:postcode":"55433",
    "sg:province":"MN",
    "sg:tags":[
        "consultant",
        "financing",
        "planning"
    ],
    "wof:name":"Next Financial Group",
    "wof:placetype":"venue"
},
  "geometry": {"coordinates":[-93.280764,45.144033],"type":"Point"}
}