{
  "type": "Feature",
  "properties": {
    "addr:full":"251 1st Ave S Windom MN 56101",
    "addr:housenumber":"251",
    "addr:postcode":"56101",
    "addr:street":"1St Ave S Windom",
    "iso:country":"US",
    "sg:address":"251 1st Ave S",
    "sg:city":"Windom",
    "sg:classifiers":[
        {
            "category":"Autos & Motor Vehicles",
            "subcategory":"Auto Supplies",
            "type":"Retail Goods"
        },
        {
            "category":"Retail",
            "subcategory":"Auto Repair",
            "type":"Services"
        }
    ],
    "sg:phone":"+1 507 831 4585",
    "sg:postcode":"56101",
    "sg:province":"MN",
    "sg:tags":[
        "automobile",
        "part"
    ],
    "wof:name":"Country Pride Services Co-Op",
    "wof:placetype":"venue"
},
  "geometry": {"coordinates":[-95.115617,43.856084],"type":"Point"}
}