{
  "type": "Feature",
  "properties": {
    "iso:country":"US",
    "sg:address":"8 E 4th St",
    "sg:city":"Saint Paul",
    "sg:classifiers":[
        {
            "category":"Professional",
            "subcategory":"Lawyer & Legal Services",
            "type":"Services"
        }
    ],
    "sg:phone":"+1 651 490 0222",
    "sg:postcode":"55101",
    "sg:province":"MN",
    "wof:name":"Terry Duggins Office",
    "wof:placetype":"venue"
},
  "geometry": {"coordinates":[-93.09254799999999,44.945318],"type":"Point"}
}