{
  "type": "Feature",
  "properties": {
    "addr:full":"2055 Lilac Dr N Minneapolis MN 55422",
    "addr:housenumber":"2055",
    "addr:postcode":"55422",
    "addr:street":"Lilac Dr N",
    "iso:country":"US",
    "sg:address":"2055 Lilac Dr N",
    "sg:city":"Minneapolis",
    "sg:classifiers":[
        {
            "category":"Government",
            "subcategory":"Office",
            "type":"Public Place"
        }
    ],
    "sg:phone":"+1 763 797 3000",
    "sg:postcode":"55422",
    "sg:province":"MN",
    "sg:tags":[
        "dept",
        "transportation"
    ],
    "wof:name":"Metro District-Golden Valley",
    "wof:placetype":"venue"
},
  "geometry": {"coordinates":[-93.349924,44.999921],"type":"Point"}
}