{
  "type": "Feature",
  "properties": {
    "addr:full":"1515 Saint Francis Ave Shakopee MN 55379",
    "addr:housenumber":"1515",
    "addr:postcode":"55379",
    "addr:street":"Saint Francis Ave",
    "iso:country":"US",
    "sg:address":"1515 Saint Francis Ave",
    "sg:city":"Shakopee",
    "sg:classifiers":[
        {
            "category":"Health Services",
            "subcategory":"Doctor",
            "type":"Services"
        }
    ],
    "sg:phone":"+1 952 445 6700",
    "sg:postcode":"55379",
    "sg:province":"MN",
    "sg:tags":[
        "medical"
    ],
    "wof:name":"Metropltan Pdtric Spcalists PA",
    "wof:placetype":"venue"
},
  "geometry": {"coordinates":[-93.50204100000001,44.770156],"type":"Point"}
}