{
  "type": "Feature",
  "properties": {
    "addr:full":"79 Navaho Ave Mankato MN 56001",
    "addr:housenumber":"79",
    "addr:postcode":"56001",
    "addr:street":"Navaho Ave",
    "iso:country":"US",
    "sg:address":"79 Navaho Ave",
    "sg:city":"Mankato",
    "sg:classifiers":[
        {
            "category":"Banks & Credit Unions",
            "subcategory":"Bank",
            "type":"Services"
        }
    ],
    "sg:phone":"+1 507 388 8600",
    "sg:postcode":"56001",
    "sg:province":"MN",
    "sg:tags":[
        "loan",
        "real estate"
    ],
    "wof:name":"Northland Mortgage-Rochester",
    "wof:placetype":"venue"
},
  "geometry": {"coordinates":[-93.96310699999999,44.168536],"type":"Point"}
}