{
  "type": "Feature",
  "properties": {
    "iso:country":"US",
    "sg:address":"4280 Centerville Rd",
    "sg:city":"St Paul",
    "sg:classifiers":[
        {
            "category":"Professional",
            "subcategory":"Research",
            "type":"Services"
        }
    ],
    "sg:phone":"+1 651 426 6466",
    "sg:postcode":"55127",
    "sg:province":"MN",
    "sg:tags":[
        "development",
        "laboratory"
    ],
    "sg:website":"www.bioe.com",
    "wof:name":"Bio Ergonomics Inc",
    "wof:placetype":"venue"
},
  "geometry": {"coordinates":[-93.056079,45.066749],"type":"Point"}
}