{
  "type": "Feature",
  "properties": {
    "addr:full":"955 1st St E Bemidji MN 56601",
    "addr:housenumber":"955",
    "addr:postcode":"56601",
    "addr:street":"1St St",
    "iso:country":"US",
    "sg:address":"955 1st St E",
    "sg:city":"Bemidji",
    "sg:classifiers":[
        {
            "category":"Manufacturing",
            "subcategory":"Building Materials",
            "type":"Manufacturing & Wholesale Goods"
        }
    ],
    "sg:phone":"+1 218 751 6962",
    "sg:postcode":"56601",
    "sg:province":"MN",
    "sg:tags":[
        "door"
    ],
    "sg:website":"www.northcentraldoor.com",
    "wof:name":"North Central Door Co Corp",
    "wof:placetype":"venue"
},
  "geometry": {"coordinates":[-94.854123,47.460913],"type":"Point"}
}