{
  "type": "Feature",
  "properties": {
    "iso:country":"US",
    "sg:address":"620 11th Ave",
    "sg:city":"Two Harbors",
    "sg:classifiers":[
        {
            "category":"Building & Trades",
            "subcategory":"Construction",
            "type":"Services"
        }
    ],
    "sg:phone":"+1 218 834 9568",
    "sg:postcode":"55616",
    "sg:province":"MN",
    "sg:tags":[
        "contractor"
    ],
    "wof:name":"Northern Divide Fence",
    "wof:placetype":"venue"
},
  "geometry": {"coordinates":[-91.67255400000001,47.029634],"type":"Point"}
}