{
  "type": "Feature",
  "properties": {
    "iso:country":"US",
    "sg:address":"25766 Lake Rd",
    "sg:city":"St Cloud",
    "sg:classifiers":[
        {
            "category":"Building & Trades",
            "subcategory":"Plumbing",
            "type":"Services"
        }
    ],
    "sg:phone":"+1 320 252 8961",
    "sg:postcode":"56301",
    "sg:province":"MN",
    "sg:tags":[
        "plumbing",
        "contractor"
    ],
    "wof:name":"Anderson Plumbing Inc",
    "wof:placetype":"venue"
},
  "geometry": {"coordinates":[-94.27994700000001,45.500554],"type":"Point"}
}