{
  "type": "Feature",
  "properties": {
    "iso:country":"US",
    "sg:address":"5756 Maple Grove Rd",
    "sg:city":"Hermantown",
    "sg:classifiers":[
        {
            "category":"Building & Trades",
            "subcategory":"Landscaping Services",
            "type":"Services"
        }
    ],
    "sg:phone":"+1 218 729 5063",
    "sg:postcode":"55810",
    "sg:province":"MN",
    "sg:tags":[
        "landscape",
        "contractor"
    ],
    "wof:name":"Quality Plus Landscaping",
    "wof:placetype":"venue"
},
  "geometry": {"coordinates":[-92.285177,46.807317],"type":"Point"}
}