{
  "type": "Feature",
  "properties": {
    "iso:country":"US",
    "sg:address":"17881 Wedgewood Dr",
    "sg:city":"Zumbrota",
    "sg:classifiers":[
        {
            "category":"Health Services",
            "subcategory":"Clinic",
            "type":"Services"
        }
    ],
    "sg:phone":"+1 507 732 4002",
    "sg:postcode":"55992",
    "sg:province":"MN",
    "wof:name":"Nelson Dairy Consultants",
    "wof:placetype":"venue"
},
  "geometry": {"coordinates":[-92.67336899999999,44.276722],"type":"Point"}
}