{
  "type": "Feature",
  "properties": {
    "iso:country":"US",
    "sg:address":"305 Co Hwy 12",
    "sg:city":"Medford",
    "sg:classifiers":[
        {
            "category":"Home & Garden",
            "subcategory":"Home Furnishings",
            "type":"Retail Goods"
        }
    ],
    "sg:phone":"+1 507 455 4117",
    "sg:postcode":"55049",
    "sg:province":"MN",
    "sg:tags":[
        "kitchen",
        "accessory"
    ],
    "wof:name":"Kitchen Collection",
    "wof:placetype":"venue"
},
  "geometry": {"coordinates":[-93.244415,44.175115],"type":"Point"}
}