{
  "type": "Feature",
  "properties": {
    "addr:full":"29497 Co Rd 35 Worthington MN 56187",
    "addr:housenumber":"29497;35",
    "addr:postcode":"56187",
    "addr:street":"Co Rd",
    "iso:country":"US",
    "sg:address":"29497 Co Rd 35",
    "sg:city":"Worthington",
    "sg:classifiers":[
        {
            "category":"Building & Trades",
            "subcategory":"Construction",
            "type":"Services"
        }
    ],
    "sg:phone":"+1 507 376 3284",
    "sg:postcode":"56187",
    "sg:province":"MN",
    "sg:tags":[
        "contractor",
        "general"
    ],
    "wof:name":"Worthington Seamless Gutters",
    "wof:placetype":"venue"
},
  "geometry": {"coordinates":[-95.66584400000001,43.630841],"type":"Point"}
}