{
  "type": "Feature",
  "properties": {
    "addr:full":"2902 191st St Currie MN 56123",
    "addr:housenumber":"2902",
    "addr:postcode":"56123",
    "addr:street":"191St St",
    "iso:country":"US",
    "sg:address":"2902 191st St",
    "sg:city":"Currie",
    "sg:phone":"+1 507 859 2756",
    "sg:postcode":"56123",
    "sg:province":"MN",
    "sg:tags":[
        "farm",
        "corn",
        "soybean"
    ],
    "wof:name":"Donald Hahn",
    "wof:placetype":"venue"
},
  "geometry": {"coordinates":[-95.477553,44.123421],"type":"Point"}
}