{
  "type": "Feature",
  "properties": {
    "addr:full":"33695 Co St Aid Hwy 10 Albany MN 56307",
    "addr:housenumber":"33695",
    "addr:postcode":"56307",
    "addr:street":"Co St Aid Hwy 10",
    "iso:country":"US",
    "sg:address":"33695 Co St Aid Hwy 10",
    "sg:city":"Albany",
    "sg:classifiers":[
        {
            "category":"Manufacturing",
            "subcategory":"Signs",
            "type":"Manufacturing & Wholesale Goods"
        }
    ],
    "sg:phone":"+1 320 845 7445",
    "sg:postcode":"56307",
    "sg:province":"MN",
    "sg:tags":[
        "specialty",
        "mfg"
    ],
    "wof:name":"Guy Neon",
    "wof:placetype":"venue"
},
  "geometry": {"coordinates":[-94.60212199999999,45.610343],"type":"Point"}
}