{
  "type": "Feature",
  "properties": {
    "iso:country":"US",
    "sg:address":"211 S Otter Ave",
    "sg:city":"Parkers Prairie",
    "sg:classifiers":[
        {
            "category":"Retail",
            "subcategory":"Auto Repair",
            "type":"Services"
        }
    ],
    "sg:phone":"+1 218 338 4391",
    "sg:postcode":"56361",
    "sg:province":"MN",
    "sg:tags":[
        "repairing",
        "automobile"
    ],
    "wof:name":"Dick's Standard Svc",
    "wof:placetype":"venue"
},
  "geometry": {"coordinates":[-95.329123,46.152174],"type":"Point"}
}