{
  "type": "Feature",
  "properties": {
    "addr:full":"11942 15th Ave SW Raymond MN 56282",
    "addr:housenumber":"11942",
    "addr:postcode":"56282",
    "addr:street":"15Th Ave Sw",
    "iso:country":"US",
    "sg:address":"11942 15th Ave SW",
    "sg:city":"Raymond",
    "sg:classifiers":[
        {
            "category":"Farming",
            "subcategory":"Farm",
            "type":"Manufacturing & Wholesale Goods"
        }
    ],
    "sg:phone":"+1 320 599 4174",
    "sg:postcode":"56282",
    "sg:province":"MN",
    "sg:tags":[
        "crop",
        "general"
    ],
    "wof:name":"Duane Hultgren Farms",
    "wof:placetype":"venue"
},
  "geometry": {"coordinates":[-95.20596399999999,45.109604],"type":"Point"}
}