{
  "type": "Feature",
  "properties": {
    "addr:full":"8501 Evergreen Blvd NW Minneapolis MN 55433",
    "addr:housenumber":"8501",
    "addr:postcode":"55433",
    "addr:street":"Evergreen Blvd Nw",
    "iso:country":"US",
    "sg:address":"8501 Evergreen Blvd NW",
    "sg:city":"Minneapolis",
    "sg:classifiers":[
        {
            "category":"Structure",
            "subcategory":"Factory",
            "type":"Public Place"
        },
        {
            "category":"Utilities",
            "subcategory":"Natural Gas",
            "type":"Services"
        }
    ],
    "sg:phone":"+1 763 717 0707",
    "sg:postcode":"55433",
    "sg:province":"MN",
    "sg:tags":[
        "measuring",
        "pollution",
        "equipment",
        "air"
    ],
    "sg:website":"http://www.aircure.com",
    "wof:name":"Air Cure Inc (Del)",
    "wof:placetype":"venue"
},
  "geometry": {"coordinates":[-93.274567,45.124489],"type":"Point"}
}