{
  "type": "Feature",
  "properties": {
    "addr:full":"1790 W Broadway St Winona MN 55987",
    "addr:housenumber":"1790",
    "addr:postcode":"55987",
    "addr:street":"W Broadway St",
    "iso:country":"US",
    "sg:address":"1790 W Broadway St",
    "sg:city":"Winona",
    "sg:classifiers":[
        {
            "category":"Health Services",
            "subcategory":"Clinic",
            "type":"Services"
        }
    ],
    "sg:phone":"+1 507 452 5490",
    "sg:postcode":"55987",
    "sg:province":"MN",
    "sg:tags":[
        "home"
    ],
    "wof:name":"SEMCIL/United Home",
    "wof:placetype":"venue"
},
  "geometry": {"coordinates":[-91.685778,44.055855],"type":"Point"}
}