{
  "type": "Feature",
  "properties": {
    "addr:full":"520 N 8th St Lake City MN 55041",
    "addr:housenumber":"520",
    "addr:postcode":"55041",
    "addr:street":"N 8Th St",
    "iso:country":"US",
    "sg:address":"520 N 8th St",
    "sg:city":"Lake City",
    "sg:classifiers":[
        {
            "category":"Manufacturing",
            "subcategory":"Metals",
            "type":"Manufacturing & Wholesale Goods"
        }
    ],
    "sg:phone":"+1 651 345 8097",
    "sg:postcode":"55041",
    "sg:province":"MN",
    "sg:tags":[
        "foundry"
    ],
    "wof:name":"Federal Mogul Machine Inspect",
    "wof:placetype":"venue"
},
  "geometry": {"coordinates":[-92.276355,44.446087],"type":"Point"}
}