{
  "type": "Feature",
  "properties": {
    "iso:country":"US",
    "sg:address":"1850 Adams St",
    "sg:city":"Mankato",
    "sg:classifiers":[
        {
            "category":"Ice Cream",
            "type":"Food & Drink"
        }
    ],
    "sg:menulink":"http://www.allmenus.com/mn/mankato/168313-dairy-queen/menu/",
    "sg:phone":"+1 507 388 1375",
    "sg:postcode":"56001",
    "sg:province":"MN",
    "sg:tags":[
        "burger",
        "american"
    ],
    "wof:name":"Dairy Queen",
    "wof:placetype":"venue"
},
  "geometry": {"coordinates":[-93.95236800000001,44.170497],"type":"Point"}
}