{
  "type": "Feature",
  "properties": {
    "iso:country":"US",
    "sg:address":"3315 Overlook Dr",
    "sg:city":"Minneapolis",
    "sg:classifiers":[
        {
            "category":"Building & Trades",
            "subcategory":"Locksmith",
            "type":"Services"
        }
    ],
    "sg:phone":"+1 952 807 0364",
    "sg:postcode":"55431",
    "sg:province":"MN",
    "sg:tags":[
        "key"
    ],
    "wof:name":"Any Place 24 Locksmith",
    "wof:placetype":"venue"
},
  "geometry": {"coordinates":[-93.322356,44.79844],"type":"Point"}
}