{
  "type": "Feature",
  "properties": {
    "addr:full":"3527 Co Rd 97 Internatl Falls MN 56649",
    "addr:housenumber":"3527;97",
    "addr:postcode":"56649",
    "addr:street":"Co Rd;Falls",
    "iso:country":"US",
    "sg:address":"3527 Co Rd 97",
    "sg:city":"Internatl Falls",
    "sg:classifiers":[
        {
            "category":"Building & Trades",
            "subcategory":"Electrical",
            "type":"Services"
        }
    ],
    "sg:phone":"+1 218 377 4494",
    "sg:postcode":"56649",
    "sg:province":"MN",
    "sg:tags":[
        "electric",
        "contractor"
    ],
    "wof:name":"Blais Electric LLC",
    "wof:placetype":"venue"
},
  "geometry": {"coordinates":[-93.37451900000001,48.503949],"type":"Point"}
}