{
  "type": "Feature",
  "properties": {
    "iso:country":"US",
    "sg:address":"40811 Ladoux Rd",
    "sg:city":"Ponsford",
    "sg:classifiers":[
        {
            "category":"Professional",
            "type":"Services"
        }
    ],
    "sg:phone":"+1 218 573 3637",
    "sg:postcode":"56575",
    "sg:province":"MN",
    "sg:tags":[
        "establishment"
    ],
    "wof:name":"Metzer & Metzer",
    "wof:placetype":"venue"
},
  "geometry": {"coordinates":[-95.53008800000001,47.018887],"type":"Point"}
}