{
  "type": "Feature",
  "properties": {
    "addr:full":"821 W 43rd St Minneapolis MN 55409",
    "addr:housenumber":"821",
    "addr:postcode":"55409",
    "addr:street":"W 43Rd St",
    "iso:country":"US",
    "sg:address":"821 W 43rd St",
    "sg:city":"Minneapolis",
    "sg:classifiers":[
        {
            "category":"Real Estate",
            "subcategory":"Real Estate Operator",
            "type":"Services"
        }
    ],
    "sg:phone":"+1 612 269 6895",
    "sg:postcode":"55409",
    "sg:province":"MN",
    "sg:tags":[
        "building",
        "nonresidential"
    ],
    "wof:name":"Mauriel Overby Enterprises LLC",
    "wof:placetype":"venue"
},
  "geometry": {"coordinates":[-93.29065,44.924924],"type":"Point"}
}