{
  "type": "Feature",
  "properties": {
    "iso:country":"US",
    "sg:address":"1015 4th Ave NE",
    "sg:city":"Austin",
    "sg:classifiers":[
        {
            "category":"Home & Garden",
            "subcategory":"Furniture",
            "type":"Retail Goods"
        }
    ],
    "sg:phone":"+1 507 437 2842",
    "sg:postcode":"55912",
    "sg:province":"MN",
    "sg:tags":[
        "cabinet"
    ],
    "wof:name":"Ed Uhlis Cabinet Shop",
    "wof:placetype":"venue"
},
  "geometry": {"coordinates":[-92.962986,43.669974],"type":"Point"}
}