{
  "type": "Feature",
  "properties": {
    "iso:country":"US",
    "sg:address":"250 Marquette Ave",
    "sg:city":"Minneapolis",
    "sg:classifiers":[
        {
            "category":"Professional",
            "subcategory":"Lawyer & Legal Services",
            "type":"Services"
        }
    ],
    "sg:phone":"+1 612 746 0360",
    "sg:postcode":"55401",
    "sg:province":"MN",
    "sg:website":"www.igbanugolaw.com",
    "wof:name":"Igbanugo Herbert A Atty",
    "wof:placetype":"venue"
},
  "geometry": {"coordinates":[-93.26715799999999,44.98093],"type":"Point"}
}