{
  "type": "Feature",
  "properties": {
    "iso:country":"US",
    "sg:address":"4340 Lyndale Ave N",
    "sg:city":"Minneapolis",
    "sg:classifiers":[
        {
            "category":"Manufacturing",
            "subcategory":"Motor Vehicles & Parts",
            "type":"Manufacturing & Wholesale Goods"
        }
    ],
    "sg:phone":"+1 612 529 8446",
    "sg:postcode":"55412",
    "sg:province":"MN",
    "sg:tags":[
        "repair",
        "motorcycle",
        "mfg"
    ],
    "wof:name":"McC",
    "wof:placetype":"venue"
},
  "geometry": {"coordinates":[-93.288183,45.034339],"type":"Point"}
}