{
  "type": "Feature",
  "properties": {
    "iso:country":"US",
    "sg:address":"11945 Central Ave NE",
    "sg:city":"Blaine",
    "sg:classifiers":[
        {
            "category":"Health Services",
            "subcategory":"Doctor",
            "type":"Services"
        }
    ],
    "sg:phone":"+1 763 767 9119",
    "sg:postcode":"55434",
    "sg:province":"MN",
    "sg:tags":[
        "dentist"
    ],
    "wof:name":"St Croix Endodontics",
    "wof:placetype":"venue"
},
  "geometry": {"coordinates":[-93.23493000000001,45.181011],"type":"Point"}
}