{
  "type": "Feature",
  "properties": {
    "iso:country":"US",
    "sg:address":"8867 Flesher Cir",
    "sg:city":"Eden Prairie",
    "sg:classifiers":[
        {
            "category":"Home & Garden",
            "subcategory":"Home Furnishings",
            "type":"Retail Goods"
        }
    ],
    "sg:phone":"+1 952 934 1217",
    "sg:postcode":"55347",
    "sg:province":"MN",
    "wof:name":"Jeannie Hussey Design",
    "wof:placetype":"venue"
},
  "geometry": {"coordinates":[-93.456153,44.843567],"type":"Point"}
}