{
  "type": "Feature",
  "properties": {
    "addr:full":"692 Riviera Dr Saint Paul MN 55112",
    "addr:housenumber":"692",
    "addr:postcode":"55112",
    "addr:street":"Riviera Dr",
    "iso:country":"US",
    "sg:address":"692 Riviera Dr",
    "sg:city":"Saint Paul",
    "sg:classifiers":[
        {
            "category":"Social Services",
            "type":"Services"
        }
    ],
    "sg:phone":"+1 651 633 6744",
    "sg:postcode":"55112",
    "sg:province":"MN",
    "wof:name":"Noer Michael",
    "wof:placetype":"venue"
},
  "geometry": {"coordinates":[-93.20415800000001,45.039374],"type":"Point"}
}