{
  "type": "Feature",
  "properties": {
    "iso:country":"US",
    "sg:address":"1276 Keston St",
    "sg:city":"Saint Paul",
    "sg:classifiers":[
        {
            "category":"Education",
            "subcategory":"Special Training",
            "type":"Public Place"
        }
    ],
    "sg:phone":"+1 651 340 4356",
    "sg:postcode":"55108",
    "sg:province":"MN",
    "sg:tags":[
        "educational"
    ],
    "wof:name":"Low Russanne",
    "wof:placetype":"venue"
},
  "geometry": {"coordinates":[-93.19758299999999,44.979475],"type":"Point"}
}