{
  "type": "Feature",
  "properties": {
    "iso:country":"US",
    "sg:address":"9301 Wedgwood Ln N",
    "sg:city":"Maple Grove",
    "sg:classifiers":[
        {
            "category":"Building & Trades",
            "subcategory":"Locksmith",
            "type":"Services"
        }
    ],
    "sg:phone":"+1 952 562 0056",
    "sg:postcode":"55369",
    "sg:province":"MN",
    "sg:tags":[
        "key"
    ],
    "wof:name":"A A 24 Hour A A A Locksmith",
    "wof:placetype":"venue"
},
  "geometry": {"coordinates":[-93.45027399999999,45.123527],"type":"Point"}
}