{
  "type": "Feature",
  "properties": {
    "addr:full":"3087 Brookshire Ln Saint Paul MN 55112",
    "addr:housenumber":"3087",
    "addr:postcode":"55112",
    "addr:street":"Brookshire Ln",
    "iso:country":"US",
    "sg:address":"3087 Brookshire Ln",
    "sg:city":"Saint Paul",
    "sg:classifiers":[
        {
            "category":"Building & Trades",
            "subcategory":"Construction",
            "type":"Services"
        }
    ],
    "sg:phone":"+1 651 636 4190",
    "sg:postcode":"55112",
    "sg:province":"MN",
    "sg:tags":[
        "home",
        "general",
        "family",
        "contractor"
    ],
    "wof:name":"Lee-Jay Brick & Stone Inc",
    "wof:placetype":"venue"
},
  "geometry": {"coordinates":[-93.22421199999999,45.071469],"type":"Point"}
}