{
  "type": "Feature",
  "properties": {
    "addr:full":"812 Minnesota Ave Detroit Lakes MN 56501",
    "addr:housenumber":"812",
    "addr:postcode":"56501",
    "addr:street":"Minnesota Ave",
    "iso:country":"US",
    "sg:address":"812 Minnesota Ave",
    "sg:city":"Detroit Lakes",
    "sg:classifiers":[
        {
            "category":"Wholesale",
            "subcategory":"Computers",
            "type":"Manufacturing & Wholesale Goods"
        }
    ],
    "sg:phone":"+1 218 847 7220",
    "sg:postcode":"56501",
    "sg:province":"MN",
    "sg:tags":[
        "programing",
        "custom"
    ],
    "wof:name":"Data Tex West",
    "wof:placetype":"venue"
},
  "geometry": {"coordinates":[-95.84846400000001,46.818493],"type":"Point"}
}