{
  "type": "Feature",
  "properties": {
    "iso:country":"US",
    "sg:address":"101 Industrial Blvd",
    "sg:city":"Hinckley",
    "sg:classifiers":[
        {
            "category":"Autos & Motor Vehicles",
            "subcategory":"Auto Supplies",
            "type":"Retail Goods"
        }
    ],
    "sg:phone":"+1 320 384 6242",
    "sg:postcode":"55037",
    "sg:province":"MN",
    "wof:name":"NAPA Auto & Truck Parts",
    "wof:placetype":"venue"
},
  "geometry": {"coordinates":[-92.9268,46.01723],"type":"Point"}
}