{
  "type": "Feature",
  "properties": {
    "iso:country":"US",
    "sg:address":"3300 Co Rd 10",
    "sg:city":"Minneapolis",
    "sg:classifiers":[
        {
            "category":"Professional",
            "subcategory":"Employment Agencies",
            "type":"Services"
        }
    ],
    "sg:phone":"+1 763 560 6015",
    "sg:postcode":"55429",
    "sg:province":"MN",
    "sg:tags":[
        "help",
        "contractor"
    ],
    "sg:website":"www.crtechnical.com",
    "wof:name":"Crow River Technical",
    "wof:placetype":"venue"
},
  "geometry": {"coordinates":[-93.324246,45.060319],"type":"Point"}
}