{
  "type": "Feature",
  "properties": {
    "addr:full":"7794 Main St Maple Grove MN 55369",
    "addr:housenumber":"7794",
    "addr:postcode":"55369",
    "addr:street":"Main St",
    "iso:country":"US",
    "sg:address":"7794 Main St",
    "sg:city":"Maple Grove",
    "sg:classifiers":[
        {
            "category":"Personal",
            "subcategory":"Beauty Salon",
            "type":"Services"
        }
    ],
    "sg:phone":"+1 763 420 9000",
    "sg:postcode":"55369",
    "sg:province":"MN",
    "sg:tags":[
        "manicuring"
    ],
    "wof:name":"Nails & Spa",
    "wof:placetype":"venue"
},
  "geometry": {"coordinates":[-93.44158400000001,45.097007],"type":"Point"}
}