{
  "type": "Feature",
  "properties": {
    "addr:full":"1405 S 7th St St Peter MN 56082",
    "addr:housenumber":"1405",
    "addr:postcode":"56082",
    "addr:street":"S 7Th St",
    "iso:country":"US",
    "sg:address":"1405 S 7th St",
    "sg:city":"St Peter",
    "sg:classifiers":[
        {
            "category":"Education",
            "subcategory":"School",
            "type":"Public Place"
        }
    ],
    "sg:phone":"+1 507 934 2754",
    "sg:postcode":"56082",
    "sg:province":"MN",
    "wof:name":"St Peter Public Schools S Elem",
    "wof:placetype":"venue"
},
  "geometry": {"coordinates":[-93.971802,44.31678],"type":"Point"}
}