{
  "type": "Feature",
  "properties": {
    "addr:full":"129 S Grant St Houston MN 55943",
    "addr:housenumber":"129",
    "addr:postcode":"55943",
    "addr:street":"S Grant St",
    "iso:country":"US",
    "sg:address":"129 S Grant St",
    "sg:city":"Houston",
    "sg:classifiers":[
        {
            "category":"Restaurant",
            "type":"Food & Drink"
        }
    ],
    "sg:phone":"+1 507 896 1000",
    "sg:postcode":"55943",
    "sg:province":"MN",
    "wof:name":"Through The Grapevine",
    "wof:placetype":"venue"
},
  "geometry": {"coordinates":[-91.568963,43.76294],"type":"Point"}
}