{
  "type": "Feature",
  "properties": {
    "addr:full":"40825 Verdin St NW Braham MN 55006",
    "addr:postcode":"40825;55006",
    "addr:street":"Verdin St Nw",
    "iso:country":"US",
    "sg:address":"40825 Verdin St NW",
    "sg:city":"Braham",
    "sg:classifiers":[
        {
            "category":"Restaurant",
            "type":"Food & Drink"
        }
    ],
    "sg:phone":"+1 320 396 4487",
    "sg:postcode":"55006",
    "sg:province":"MN",
    "sg:tags":[
        "style",
        "family",
        "lunch",
        "american",
        "brunch",
        "breakfast"
    ],
    "sg:website":"http://www.dennys.com",
    "wof:name":"Denny's",
    "wof:placetype":"venue"
},
  "geometry": {"coordinates":[-93.32749200000001,45.705114],"type":"Point"}
}