{
  "type": "Feature",
  "properties": {
    "addr:full":"5885 Oxford St Saint Paul MN 55126",
    "addr:housenumber":"5885",
    "addr:postcode":"55126",
    "addr:street":"Oxford St",
    "iso:country":"US",
    "sg:address":"5885 Oxford St",
    "sg:city":"Saint Paul",
    "sg:classifiers":[
        {
            "category":"Professional",
            "type":"Services"
        }
    ],
    "sg:phone":"+1 651 483 6099",
    "sg:postcode":"55126",
    "sg:province":"MN",
    "wof:name":"Consulting Toxicology Ser",
    "wof:placetype":"venue"
},
  "geometry": {"coordinates":[-93.144926,45.118561],"type":"Point"}
}