{
  "type": "Feature",
  "properties": {
    "iso:country":"US",
    "sg:address":"1158 Highway 7 E",
    "sg:city":"Hutchinson",
    "sg:classifiers":[
        {
            "category":"Manufacturing",
            "subcategory":"Tools & Machinery",
            "type":"Manufacturing & Wholesale Goods"
        },
        {
            "category":"Retail",
            "subcategory":"Repair Shop",
            "type":"Services"
        },
        {
            "category":"Retail",
            "subcategory":"Auto Repair",
            "type":"Services"
        }
    ],
    "sg:phone":"+1 320 234 6015",
    "sg:postcode":"55350",
    "sg:province":"MN",
    "sg:tags":[
        "machine",
        "automobile",
        "machinery-rebuild"
    ],
    "sg:website":"http://www.nordiccomp.com",
    "wof:name":"Nordic Components",
    "wof:placetype":"venue"
},
  "geometry": {"coordinates":[-94.394656,44.893407],"type":"Point"}
}