{
  "type": "Feature",
  "properties": {
    "addr:full":"2286 Valley View Ave Saint Paul MN 55119",
    "addr:housenumber":"2286",
    "addr:postcode":"55119",
    "addr:street":"Valley View Ave",
    "iso:country":"US",
    "sg:address":"2286 Valley View Ave",
    "sg:city":"Saint Paul",
    "sg:classifiers":[
        {
            "category":"Social Services",
            "subcategory":"Child Care",
            "type":"Services"
        }
    ],
    "sg:phone":"+1 651 739 8710",
    "sg:postcode":"55119",
    "sg:province":"MN",
    "sg:tags":[
        "day"
    ],
    "wof:name":"Vicki C Walseth",
    "wof:placetype":"venue"
},
  "geometry": {"coordinates":[-93.002515,44.913569],"type":"Point"}
}