{
  "type": "Feature",
  "properties": {
    "addr:full":"16575 Roosevelt Rd SE Cass Lake MN 56633",
    "addr:housenumber":"16575",
    "addr:postcode":"56633",
    "addr:street":"Roosevelt Rd Se",
    "iso:country":"US",
    "sg:address":"16575 Roosevelt Rd SE",
    "sg:city":"Cass Lake",
    "sg:classifiers":[
        {
            "category":"Freight",
            "type":"Transportation"
        }
    ],
    "sg:phone":"+1 218 335 7628",
    "sg:postcode":"56633",
    "sg:province":"MN",
    "sg:tags":[
        "trucking"
    ],
    "wof:name":"Armstrong Trucking",
    "wof:placetype":"venue"
},
  "geometry": {"coordinates":[-94.649157,47.419061],"type":"Point"}
}