{
  "type": "Feature",
  "properties": {
    "iso:country":"US",
    "sg:address":"2042 W 98th St",
    "sg:city":"Bloomington",
    "sg:classifiers":[
        {
            "category":"Professional",
            "subcategory":"Management & Consulting",
            "type":"Services"
        }
    ],
    "sg:phone":"+1 952 888 3812",
    "sg:postcode":"55431",
    "sg:province":"MN",
    "sg:tags":[
        "consultant"
    ],
    "wof:name":"LRF Consulting",
    "wof:placetype":"venue"
},
  "geometry": {"coordinates":[-93.302451,44.826389],"type":"Point"}
}