{
  "type": "Feature",
  "properties": {
    "addr:full":"4810 Co Rd 11 NW Alexandria MN 56308",
    "addr:housenumber":"4810;11",
    "addr:postcode":"56308",
    "addr:street":"Co Rd",
    "iso:country":"US",
    "sg:address":"4810 Co Rd 11 NW",
    "sg:city":"Alexandria",
    "sg:classifiers":[
        {
            "category":"Building & Trades",
            "subcategory":"Construction",
            "type":"Services"
        }
    ],
    "sg:phone":"+1 320 846 4200",
    "sg:postcode":"56308",
    "sg:province":"MN",
    "sg:tags":[
        "excavating",
        "contractor"
    ],
    "wof:name":"Rapp Construction",
    "wof:placetype":"venue"
},
  "geometry": {"coordinates":[-95.376925,45.940701],"type":"Point"}
}