{
  "type": "Feature",
  "properties": {
    "addr:full":"1406 E 40th St Hibbing MN 55746",
    "addr:housenumber":"1406",
    "addr:postcode":"55746",
    "addr:street":"E 40Th St",
    "iso:country":"US",
    "sg:address":"1406 E 40th St",
    "sg:city":"Hibbing",
    "sg:classifiers":[
        {
            "category":"Health Services",
            "subcategory":"Chiropractor",
            "type":"Services"
        }
    ],
    "sg:phone":"+1 218 262 1880",
    "sg:postcode":"55746",
    "sg:province":"MN",
    "wof:name":"Quirk Chiropractic Clinic",
    "wof:placetype":"venue"
},
  "geometry": {"coordinates":[-92.924325,47.40083],"type":"Point"}
}