{
  "type": "Feature",
  "properties": {
    "addr:full":"1701 Century Cir Saint Paul MN 55125",
    "addr:housenumber":"1701",
    "addr:postcode":"55125",
    "addr:street":"Century Cir",
    "iso:country":"US",
    "sg:address":"1701 Century Cir",
    "sg:city":"Saint Paul",
    "sg:classifiers":[
        {
            "category":"Professional",
            "type":"Services"
        }
    ],
    "sg:phone":"+1 651 739 8373",
    "sg:postcode":"55125",
    "sg:province":"MN",
    "wof:name":"PC Concepts",
    "wof:placetype":"venue"
},
  "geometry": {"coordinates":[-92.98159099999999,44.924907],"type":"Point"}
}