{
  "type": "Feature",
  "properties": {
    "iso:country":"US",
    "sg:address":"310 Haarfager Ave S",
    "sg:city":"Canby",
    "sg:classifiers":[
        {
            "category":"Social Services",
            "subcategory":"Adult Care",
            "type":"Services"
        }
    ],
    "sg:phone":"+1 507 223 5269",
    "sg:postcode":"56220",
    "sg:province":"MN",
    "sg:tags":[
        "home",
        "residential"
    ],
    "wof:name":"Serenity House",
    "wof:placetype":"venue"
},
  "geometry": {"coordinates":[-96.280383,44.707656],"type":"Point"}
}