{
  "type": "Feature",
  "properties": {
    "addr:full":"7263 Washington Ave S Minneapolis MN 55439",
    "addr:housenumber":"7263",
    "addr:postcode":"55439",
    "addr:street":"Washington Ave S",
    "iso:country":"US",
    "sg:address":"7263 Washington Ave S",
    "sg:city":"Minneapolis",
    "sg:classifiers":[
        {
            "category":"Building & Trades",
            "subcategory":"Cleaning & Sanitation",
            "type":"Services"
        }
    ],
    "sg:phone":"+1 952 912 1055",
    "sg:postcode":"55439",
    "sg:province":"MN",
    "sg:tags":[
        "janitorial"
    ],
    "sg:website":"http://www.tcmtinc.com",
    "wof:name":"Twin City Maintenance Team Inc",
    "wof:placetype":"venue"
},
  "geometry": {"coordinates":[-93.398724,44.872866],"type":"Point"}
}