{
  "type": "Feature",
  "properties": {
    "iso:country":"US",
    "sg:address":"727 14th St NW",
    "sg:city":"Rochester",
    "sg:classifiers":[
        {
            "category":"Wholesale",
            "subcategory":"Home Furnishings",
            "type":"Manufacturing & Wholesale Goods"
        }
    ],
    "sg:phone":"+1 507 289 5890",
    "sg:postcode":"55901",
    "sg:province":"MN",
    "sg:tags":[
        "merchandise"
    ],
    "wof:name":"Fifield Frame Shop",
    "wof:placetype":"venue"
},
  "geometry": {"coordinates":[-92.473399,44.036214],"type":"Point"}
}