{
  "type": "Feature",
  "properties": {
    "addr:full":"200 33rd Ave S Saint Cloud MN 56301",
    "addr:housenumber":"200",
    "addr:postcode":"56301",
    "addr:street":"33Rd Ave S",
    "iso:country":"US",
    "sg:address":"200 33rd Ave S",
    "sg:city":"Saint Cloud",
    "sg:classifiers":[
        {
            "category":"Banks & Credit Unions",
            "subcategory":"Bank",
            "type":"Services"
        }
    ],
    "sg:phone":"+1 320 251 4402",
    "sg:postcode":"56301",
    "sg:province":"MN",
    "sg:tags":[
        "national",
        "commercial"
    ],
    "wof:name":"St Cloud National Bnk & Tr Co",
    "wof:placetype":"venue"
},
  "geometry": {"coordinates":[-94.19820900000001,45.549659],"type":"Point"}
}