{
  "type": "Feature",
  "properties": {
    "addr:full":"4855 12th St Winona MN 55987",
    "addr:housenumber":"4855",
    "addr:postcode":"55987",
    "addr:street":"12Th St",
    "iso:country":"US",
    "sg:address":"4855 12th St",
    "sg:city":"Winona",
    "sg:classifiers":[
        {
            "category":"Insurance",
            "subcategory":"Hazard Insurance",
            "type":"Services"
        }
    ],
    "sg:phone":"+1 507 454 1997",
    "sg:postcode":"55987",
    "sg:province":"MN",
    "sg:tags":[
        "commercial",
        "business"
    ],
    "wof:name":"Jim Bell",
    "wof:placetype":"venue"
},
  "geometry": {"coordinates":[-91.71284,44.059687],"type":"Point"}
}