{
  "type": "Feature",
  "properties": {
    "iso:country":"US",
    "sg:address":"41385 US Hwy 71",
    "sg:city":"Windom",
    "sg:classifiers":[
        {
            "category":"Education",
            "subcategory":"School",
            "type":"Public Place"
        }
    ],
    "sg:phone":"+1 507 831 6901",
    "sg:postcode":"56101",
    "sg:province":"MN",
    "sg:tags":[
        "district"
    ],
    "wof:name":"WINDOM SCHOOL DISTRICT 177",
    "wof:placetype":"venue"
},
  "geometry": {"coordinates":[-95.120403,43.88634],"type":"Point"}
}