{
  "type": "Feature",
  "properties": {
    "addr:full":"7901 Flying Cloud Dr Eden Prairie MN 55344",
    "addr:housenumber":"7901",
    "addr:postcode":"55344",
    "addr:street":"Flying Cloud Dr",
    "iso:country":"US",
    "sg:address":"7901 Flying Cloud Dr",
    "sg:city":"Eden Prairie",
    "sg:classifiers":[
        {
            "category":"Insurance",
            "subcategory":"Insurance Agent",
            "type":"Services"
        }
    ],
    "sg:phone":"+1 952 881 3232",
    "sg:postcode":"55344",
    "sg:province":"MN",
    "sg:tags":[
        "a",
        "as",
        "company",
        "holding",
        "operates"
    ],
    "wof:name":"Access Insurance Agency LLC",
    "wof:placetype":"venue"
},
  "geometry": {"coordinates":[-93.42574399999999,44.859812],"type":"Point"}
}