{
  "type": "Feature",
  "properties": {
    "addr:full":"6626 W Highway 61 Tofte MN 55615",
    "addr:housenumber":"6626",
    "addr:postcode":"55615",
    "addr:street":"W Highway 61",
    "iso:country":"US",
    "sg:address":"6626 W Highway 61",
    "sg:city":"Tofte",
    "sg:classifiers":[
        {
            "category":"Travel",
            "subcategory":"Hotels & Motels",
            "type":"Entertainment"
        }
    ],
    "sg:phone":"+1 218 663 7223",
    "sg:postcode":"55615",
    "sg:province":"MN",
    "sg:tags":[
        "lodging"
    ],
    "sg:website":"http://www.chateauleveaux.com",
    "wof:name":"Chateau Leveaux-Lake Superior",
    "wof:placetype":"venue"
},
  "geometry": {"coordinates":[-90.821781,47.581322],"type":"Point"}
}