{
  "type": "Feature",
  "properties": {
    "addr:full":"1307 Science Ave NW New Prague MN 56071",
    "addr:housenumber":"1307",
    "addr:postcode":"56071",
    "addr:street":"Science Ave Nw",
    "iso:country":"US",
    "sg:address":"1307 Science Ave NW",
    "sg:city":"New Prague",
    "sg:classifiers":[
        {
            "category":"Shopping",
            "subcategory":"Hobbies, Toys, & Games",
            "type":"Retail Goods"
        }
    ],
    "sg:phone":"+1 952 758 5322",
    "sg:postcode":"56071",
    "sg:province":"MN",
    "sg:tags":[
        "craft",
        "supply"
    ],
    "wof:name":"Arts & Scraps",
    "wof:placetype":"venue"
},
  "geometry": {"coordinates":[-93.581519,44.558835],"type":"Point"}
}