{
  "type": "Feature",
  "properties": {
    "iso:country":"US",
    "sg:address":"7919 State Hwy 29 N",
    "sg:city":"Carlos",
    "sg:classifiers":[
        {
            "category":"Bars & Pubs",
            "type":"Food & Drink"
        }
    ],
    "sg:phone":"+1 320 852 9829",
    "sg:postcode":"56319",
    "sg:province":"MN",
    "sg:tags":[
        "club",
        "night"
    ],
    "wof:name":"Looker's",
    "wof:placetype":"venue"
},
  "geometry": {"coordinates":[-95.312628,45.970994],"type":"Point"}
}