{
  "type": "Feature",
  "properties": {
    "addr:full":"1606 S Broadway St New Ulm MN 56073",
    "addr:housenumber":"1606",
    "addr:postcode":"56073",
    "addr:street":"S Broadway St",
    "iso:country":"US",
    "sg:address":"1606 S Broadway St",
    "sg:city":"New Ulm",
    "sg:classifiers":[
        {
            "category":"Personal",
            "subcategory":"Beauty Salon",
            "type":"Services"
        }
    ],
    "sg:phone":"+1 507 354 8766",
    "sg:postcode":"56073",
    "sg:province":"MN",
    "sg:tags":[
        "shop"
    ],
    "wof:name":"Cutting Edge",
    "wof:placetype":"venue"
},
  "geometry": {"coordinates":[-94.44552299999999,44.296833],"type":"Point"}
}