{
  "type": "Feature",
  "properties": {
    "iso:country":"US",
    "sg:address":"3251 Fernbrook Ln N",
    "sg:city":"Minneapolis",
    "sg:classifiers":[
        {
            "category":"Professional",
            "subcategory":"Management & Consulting",
            "type":"Services"
        },
        {
            "category":"Professional",
            "subcategory":"Advertising",
            "type":"Services"
        }
    ],
    "sg:phone":"+1 763 476 1333",
    "sg:postcode":"55447",
    "sg:province":"MN",
    "sg:tags":[
        "counselor"
    ],
    "wof:name":"Distinction Marketing",
    "wof:placetype":"venue"
},
  "geometry": {"coordinates":[-93.46150900000001,45.015705],"type":"Point"}
}