{
  "type": "Feature",
  "properties": {
    "addr:full":"5325 Spring Ln Minnetonka MN 55345",
    "addr:housenumber":"5325",
    "addr:postcode":"55345",
    "addr:street":"Spring Ln",
    "iso:country":"US",
    "sg:address":"5325 Spring Ln",
    "sg:city":"Minnetonka",
    "sg:classifiers":[
        {
            "category":"Recreation",
            "type":"Entertainment"
        }
    ],
    "sg:phone":"+1 952 474 1114",
    "sg:postcode":"55345",
    "sg:province":"MN",
    "wof:name":"Sunboat Crses of Lk Minnetonka",
    "wof:placetype":"venue"
},
  "geometry": {"coordinates":[-93.502667,44.906665],"type":"Point"}
}