{
  "type": "Feature",
  "properties": {
    "iso:country":"US",
    "sg:address":"342 2nd St NW",
    "sg:city":"Ortonville",
    "sg:classifiers":[
        {
            "category":"Manufacturing",
            "subcategory":"Tools & Machinery",
            "type":"Manufacturing & Wholesale Goods"
        }
    ],
    "sg:phone":"+1 320 839 3411",
    "sg:postcode":"56278",
    "sg:province":"MN",
    "sg:tags":[
        "farm",
        "mfg"
    ],
    "wof:name":"Upper Minn River Watershed Dst",
    "wof:placetype":"venue"
},
  "geometry": {"coordinates":[-96.44687500000001,45.306525],"type":"Point"}
}