{
  "type": "Feature",
  "properties": {
    "iso:country":"US",
    "sg:address":"420 Hwy 10 S",
    "sg:city":"Saint Cloud",
    "sg:classifiers":[
        {
            "category":"Travel",
            "subcategory":"Hotels & Motels",
            "type":"Entertainment"
        }
    ],
    "sg:phone":"+1 320 253 0500",
    "sg:postcode":"56304",
    "sg:province":"MN",
    "sg:tags":[
        "operation"
    ],
    "wof:name":"Days Inn",
    "wof:placetype":"venue"
},
  "geometry": {"coordinates":[-94.137308,45.564556],"type":"Point"}
}