{
  "type": "Feature",
  "properties": {
    "iso:country":"US",
    "sg:address":"1684 Cliff Rd E",
    "sg:city":"Burnsville",
    "sg:classifiers":[
        {
            "category":"Professional",
            "subcategory":"Management & Consulting",
            "type":"Services"
        }
    ],
    "sg:phone":"+1 952 252 6000",
    "sg:postcode":"55337",
    "sg:province":"MN",
    "wof:name":"Resource Services Alliance",
    "wof:placetype":"venue"
},
  "geometry": {"coordinates":[-93.249523,44.790547],"type":"Point"}
}