{
  "type": "Feature",
  "properties": {
    "iso:country":"US",
    "sg:address":"805 Great Oaks Ln",
    "sg:city":"Saint Paul",
    "sg:classifiers":[
        {
            "category":"Building & Trades",
            "subcategory":"Construction",
            "type":"Services"
        }
    ],
    "sg:phone":"+1 651 405 3962",
    "sg:postcode":"55123",
    "sg:province":"MN",
    "sg:tags":[
        "home",
        "commercial",
        "family"
    ],
    "wof:name":"George C Maurer Construction",
    "wof:placetype":"venue"
},
  "geometry": {"coordinates":[-93.125591,44.827421],"type":"Point"}
}