{
  "type": "Feature",
  "properties": {
    "iso:country":"US",
    "sg:address":"926 County Highway 10",
    "sg:city":"Minneapolis",
    "sg:classifiers":[
        {
            "category":"Autos & Motor Vehicles",
            "subcategory":"Automobile Sales",
            "type":"Retail Goods"
        }
    ],
    "sg:phone":"+1 763 277 7777",
    "sg:postcode":"55432",
    "sg:province":"MN",
    "sg:tags":[
        "dealers-used",
        "car",
        "used",
        "cars-wholesale",
        "new"
    ],
    "wof:name":"Quality Auto Sales & Finance",
    "wof:placetype":"venue"
},
  "geometry": {"coordinates":[-93.24769999999999,45.123616],"type":"Point"}
}