{
  "type": "Feature",
  "properties": {
    "iso:country":"US",
    "sg:address":"6117 Blue Circle Dr",
    "sg:city":"Minnetonka",
    "sg:classifiers":[
        {
            "category":"Shopping",
            "subcategory":"Computers & Home Electronics",
            "type":"Retail Goods"
        }
    ],
    "sg:phone":"+1 952 380 0203",
    "sg:postcode":"55343",
    "sg:province":"MN",
    "sg:tags":[
        "software"
    ],
    "wof:name":"Logictran",
    "wof:placetype":"venue"
},
  "geometry": {"coordinates":[-93.406837,44.89194],"type":"Point"}
}