{
  "type": "Feature",
  "properties": {
    "addr:full":"14450 W Burnsville Pkwy Burnsville MN 55306",
    "addr:housenumber":"14450",
    "addr:postcode":"55306",
    "addr:street":"W Burnsville Pkwy",
    "iso:country":"US",
    "sg:address":"14450 W Burnsville Pkwy",
    "sg:city":"Burnsville",
    "sg:classifiers":[
        {
            "category":"Building & Trades",
            "subcategory":"Construction",
            "type":"Services"
        }
    ],
    "sg:phone":"+1 952 746 3000",
    "sg:postcode":"55306",
    "sg:province":"MN",
    "sg:tags":[
        "home",
        "builder"
    ],
    "wof:name":"A T Homes Rcs",
    "wof:placetype":"venue"
},
  "geometry": {"coordinates":[-93.32354599999999,44.740306],"type":"Point"}
}