{
  "type": "Feature",
  "properties": {
    "addr:full":"111 Carleton Ave Morgan MN 56266",
    "addr:housenumber":"111",
    "addr:postcode":"56266",
    "addr:street":"Carleton Ave",
    "iso:country":"US",
    "sg:address":"111 Carleton Ave",
    "sg:city":"Morgan",
    "sg:classifiers":[
        {
            "category":"Freight",
            "type":"Transportation"
        }
    ],
    "sg:phone":"+1 507 641 2068",
    "sg:postcode":"56266",
    "sg:province":"MN",
    "sg:tags":[
        "interstate",
        "local",
        "trucking"
    ],
    "wof:name":"Jemmings Trucking",
    "wof:placetype":"venue"
},
  "geometry": {"coordinates":[-94.930266,44.416847],"type":"Point"}
}