{
  "type": "Feature",
  "properties": {
    "iso:country":"US",
    "sg:address":"1630 Gilmore Valley Rd",
    "sg:city":"Winona",
    "sg:classifiers":[
        {
            "category":"Building & Trades",
            "subcategory":"Construction",
            "type":"Services"
        }
    ],
    "sg:phone":"+1 507 454 5853",
    "sg:postcode":"55987",
    "sg:province":"MN",
    "sg:tags":[
        "house"
    ],
    "wof:name":"Wittenberg Home Builders",
    "wof:placetype":"venue"
},
  "geometry": {"coordinates":[-91.705955,44.029126],"type":"Point"}
}