{
  "type": "Feature",
  "properties": {
    "addr:full":"13199 Dahle Ave Dundas MN 55019",
    "addr:housenumber":"13199",
    "addr:postcode":"55019",
    "addr:street":"Dahle Ave",
    "iso:country":"US",
    "sg:address":"13199 Dahle Ave",
    "sg:city":"Dundas",
    "sg:classifiers":[
        {
            "category":"Building & Trades",
            "subcategory":"Construction",
            "type":"Services"
        }
    ],
    "sg:phone":"+1 507 645 6170",
    "sg:postcode":"55019",
    "sg:province":"MN",
    "sg:tags":[
        "hanging",
        "contractor"
    ],
    "wof:name":"Wells Painting Drywall",
    "wof:placetype":"venue"
},
  "geometry": {"coordinates":[-93.221126,44.395372],"type":"Point"}
}