{
  "type": "Feature",
  "properties": {
    "iso:country":"US",
    "sg:address":"2704 Brunswick Ave S",
    "sg:city":"Minneapolis",
    "sg:classifiers":[
        {
            "category":"Building & Trades",
            "subcategory":"Construction",
            "type":"Services"
        },
        {
            "category":"Home & Garden",
            "subcategory":"Furniture",
            "type":"Retail Goods"
        }
    ],
    "sg:phone":"+1 952 929 2497",
    "sg:postcode":"55416",
    "sg:province":"MN",
    "sg:tags":[
        "maker",
        "cabinet"
    ],
    "wof:name":"Cabinetry By Richard Inc",
    "wof:placetype":"venue"
},
  "geometry": {"coordinates":[-93.358307,44.954922],"type":"Point"}
}