{
  "type": "Feature",
  "properties": {
    "addr:full":"1130 S Field Ave Rush City MN 55069",
    "addr:housenumber":"1130",
    "addr:postcode":"55069",
    "addr:street":"S Field Ave",
    "iso:country":"US",
    "sg:address":"1130 S Field Ave",
    "sg:city":"Rush City",
    "sg:classifiers":[
        {
            "category":"Manufacturing",
            "subcategory":"Retail Goods",
            "type":"Manufacturing & Wholesale Goods"
        }
    ],
    "sg:phone":"+1 320 358 0282",
    "sg:postcode":"55069",
    "sg:province":"MN",
    "sg:tags":[
        "assembly",
        "fabricating"
    ],
    "wof:name":"United Fabrication & Supply",
    "wof:placetype":"venue"
},
  "geometry": {"coordinates":[-92.967438,45.677632],"type":"Point"}
}