{
  "type": "Feature",
  "properties": {
    "addr:full":"1309 W Birch Ave Olivia MN 56277",
    "addr:housenumber":"1309",
    "addr:postcode":"56277",
    "addr:street":"W Birch Ave",
    "iso:country":"US",
    "sg:address":"1309 W Birch Ave",
    "sg:city":"Olivia",
    "sg:classifiers":[
        {
            "category":"Social Services",
            "subcategory":"Child Care",
            "type":"Services"
        }
    ],
    "sg:phone":"+1 320 523 2526",
    "sg:postcode":"56277",
    "sg:province":"MN",
    "sg:tags":[
        "daycare",
        "provider"
    ],
    "wof:name":"Debra Mahoney",
    "wof:placetype":"venue"
},
  "geometry": {"coordinates":[-94.995769,44.76853],"type":"Point"}
}