{
  "type": "Feature",
  "properties": {
    "addr:full":"1717 University Ave SE Minneapolis MN 55414",
    "addr:housenumber":"1717",
    "addr:postcode":"55414",
    "addr:street":"University Ave Se",
    "iso:country":"US",
    "sg:address":"1717 University Ave SE",
    "sg:city":"Minneapolis",
    "sg:classifiers":[
        {
            "category":"Arts & Performance",
            "subcategory":"Music",
            "type":"Entertainment"
        }
    ],
    "sg:phone":"+1 612 481 0601",
    "sg:postcode":"55414",
    "sg:province":"MN",
    "sg:tags":[
        "jockey",
        "disc"
    ],
    "wof:name":"MUSE Entertainment",
    "wof:placetype":"venue"
},
  "geometry": {"coordinates":[-93.232162,44.977779],"type":"Point"}
}