{
  "type": "Feature",
  "properties": {
    "iso:country":"US",
    "sg:address":"3019 Westwood Rd",
    "sg:city":"Wayzata",
    "sg:classifiers":[
        {
            "category":"Professional",
            "type":"Services"
        }
    ],
    "sg:phone":"+1 952 931 9108",
    "sg:postcode":"55391",
    "sg:province":"MN",
    "wof:name":"Dallas Johnson Marketing Serv",
    "wof:placetype":"venue"
},
  "geometry": {"coordinates":[-93.600527,44.940573],"type":"Point"}
}