{
  "type": "Feature",
  "properties": {
    "addr:full":"2118 E 33rd St Minneapolis MN 55407",
    "addr:housenumber":"2118",
    "addr:postcode":"55407",
    "addr:street":"E 33Rd St",
    "iso:country":"US",
    "sg:address":"2118 E 33rd St",
    "sg:city":"Minneapolis",
    "sg:classifiers":[
        {
            "category":"Social Services",
            "subcategory":"Child Care",
            "type":"Services"
        }
    ],
    "sg:phone":"+1 612 724 1105",
    "sg:postcode":"55407",
    "sg:province":"MN",
    "sg:tags":[
        "daycare",
        "provider"
    ],
    "wof:name":"Amy Schmitz",
    "wof:placetype":"venue"
},
  "geometry": {"coordinates":[-93.240821,44.943016],"type":"Point"}
}