{
  "type": "Feature",
  "properties": {
    "addr:full":"5836 Lincoln Dr Edina MN 55436",
    "addr:housenumber":"5836",
    "addr:postcode":"55436",
    "addr:street":"Lincoln Dr",
    "iso:country":"US",
    "sg:address":"5836 Lincoln Dr",
    "sg:city":"Edina",
    "sg:classifiers":[
        {
            "category":"Retail",
            "subcategory":"Laundry & Dry Cleaning",
            "type":"Services"
        }
    ],
    "sg:phone":"+1 952 938 1252",
    "sg:postcode":"55436",
    "sg:province":"MN",
    "sg:tags":[
        "cleaners"
    ],
    "wof:name":"Pilgrim Cleaners & Launderers",
    "wof:placetype":"venue"
},
  "geometry": {"coordinates":[-93.40072499999999,44.896327],"type":"Point"}
}