{
  "type": "Feature",
  "properties": {
    "addr:full":"1620 Park Place Blvd Minneapolis MN 55416",
    "addr:housenumber":"1620",
    "addr:postcode":"55416",
    "addr:street":"Park Place Blvd",
    "iso:country":"US",
    "sg:address":"1620 Park Place Blvd",
    "sg:city":"Minneapolis",
    "sg:classifiers":[
        {
            "category":"Restaurant",
            "type":"Food & Drink"
        },
        {
            "category":"Ice Cream",
            "type":"Food & Drink"
        }
    ],
    "sg:menulink":"http://www.allmenus.com/mn/st-louis-park/167927-dairy-queen/menu/",
    "sg:phone":"+1 952 545 6544",
    "sg:postcode":"55416",
    "sg:province":"MN",
    "sg:tags":[
        "burger",
        "american",
        "ice",
        "cream"
    ],
    "wof:name":"Dairy Queen",
    "wof:placetype":"venue"
},
  "geometry": {"coordinates":[-93.350069,44.966935],"type":"Point"}
}