{
  "type": "Feature",
  "properties": {
    "iso:country":"US",
    "sg:address":"281 4th St",
    "sg:city":"Echo",
    "sg:classifiers":[
        {
            "category":"Government",
            "subcategory":"Post Office",
            "type":"Public Place"
        }
    ],
    "sg:phone":"+1 507 925 4368",
    "sg:postcode":"56237",
    "sg:province":"MN",
    "wof:name":"US Post Office",
    "wof:placetype":"venue"
},
  "geometry": {"coordinates":[-95.417295,44.61747],"type":"Point"}
}