{
  "type": "Feature",
  "properties": {
    "iso:country":"US",
    "sg:address":"4323 Hwy 52 N",
    "sg:city":"Rochester",
    "sg:classifiers":[
        {
            "category":"Travel",
            "subcategory":"Hotels & Motels",
            "type":"Entertainment"
        }
    ],
    "sg:phone":"+1 507 285 3335",
    "sg:postcode":"55901",
    "sg:province":"MN",
    "wof:name":"Country Inn & Suites",
    "wof:placetype":"venue"
},
  "geometry": {"coordinates":[-92.50309799999999,44.070534],"type":"Point"}
}