{
  "type": "Feature",
  "properties": {
    "iso:country":"US",
    "sg:address":"33776 Loon Dr",
    "sg:city":"Ogema",
    "sg:classifiers":[
        {
            "category":"Professional",
            "type":"Services"
        }
    ],
    "sg:phone":"+1 218 983 4247",
    "sg:postcode":"56569",
    "sg:province":"MN",
    "sg:tags":[
        "establishment"
    ],
    "wof:name":"Reitan & Reitan",
    "wof:placetype":"venue"
},
  "geometry": {"coordinates":[-95.68929199999999,47.059454],"type":"Point"}
}