{
  "type": "Feature",
  "properties": {
    "addr:full":"1413 4th St SE Minneapolis MN 55414",
    "addr:housenumber":"1413",
    "addr:postcode":"55414",
    "addr:street":"4Th St Se",
    "iso:country":"US",
    "sg:address":"1413 4th St SE",
    "sg:city":"Minneapolis",
    "sg:classifiers":[
        {
            "category":"Fast Food",
            "type":"Food & Drink"
        }
    ],
    "sg:phone":"+1 612 355 5500",
    "sg:postcode":"55414",
    "sg:province":"MN",
    "sg:tags":[
        "burger"
    ],
    "sg:website":"www.fiveguys.com",
    "wof:name":"Five Guys Burgers and Fries",
    "wof:placetype":"venue"
},
  "geometry": {"coordinates":[-93.234748,44.980617],"type":"Point"}
}