{
  "type": "Feature",
  "properties": {
    "iso:country":"US",
    "sg:address":"17770 Highway 7",
    "sg:city":"Minnetonka",
    "sg:classifiers":[
        {
            "category":"Health Services",
            "subcategory":"Chiropractor",
            "type":"Services"
        }
    ],
    "sg:phone":"+1 952 474 7402",
    "sg:postcode":"55345",
    "sg:province":"MN",
    "wof:name":"Back In Action Chiropractic",
    "wof:placetype":"venue"
},
  "geometry": {"coordinates":[-93.50610399999999,44.912899],"type":"Point"}
}