{
  "type": "Feature",
  "properties": {
    "addr:full":"401 83rd Ave NE Minneapolis MN 55432",
    "addr:housenumber":"401",
    "addr:postcode":"55432",
    "addr:street":"83Rd Ave Ne",
    "iso:country":"US",
    "sg:address":"401 83rd Ave NE",
    "sg:city":"Minneapolis",
    "sg:classifiers":[
        {
            "category":"Professional",
            "subcategory":"Computer Services",
            "type":"Services"
        }
    ],
    "sg:phone":"+1 763 784 3799",
    "sg:postcode":"55432",
    "sg:province":"MN",
    "sg:tags":[
        "programing",
        "custom"
    ],
    "wof:name":"D Rootham Computer Consul",
    "wof:placetype":"venue"
},
  "geometry": {"coordinates":[-93.25988,45.119118],"type":"Point"}
}