{
  "type": "Feature",
  "properties": {
    "iso:country":"US",
    "sg:address":"1147 2nd Ave",
    "sg:city":"Mountain Lake",
    "sg:classifiers":[
        {
            "category":"Bars & Pubs",
            "type":"Food & Drink"
        }
    ],
    "sg:phone":"+1 507 427 2450",
    "sg:postcode":"56159",
    "sg:province":"MN",
    "wof:name":"Bar",
    "wof:placetype":"venue"
},
  "geometry": {"coordinates":[-94.92707900000001,43.938722],"type":"Point"}
}