{
  "type": "Feature",
  "properties": {
    "iso:country":"US",
    "sg:address":"2699 Blue Ridge Dr",
    "sg:city":"Saint Paul",
    "sg:classifiers":[
        {
            "category":"Social Services",
            "subcategory":"Child Care",
            "type":"Services"
        }
    ],
    "sg:phone":"+1 651 730 9086",
    "sg:postcode":"55125",
    "sg:province":"MN",
    "sg:tags":[
        "daycare",
        "provider"
    ],
    "wof:name":"Heidi Lewis",
    "wof:placetype":"venue"
},
  "geometry": {"coordinates":[-92.92608300000001,44.909305],"type":"Point"}
}