{
  "type": "Feature",
  "properties": {
    "addr:full":"8571 Derby Ct Eden Prairie MN 55347",
    "addr:housenumber":"8571",
    "addr:postcode":"55347",
    "addr:street":"Derby Ct",
    "iso:country":"US",
    "sg:address":"8571 Derby Ct",
    "sg:city":"Eden Prairie",
    "sg:classifiers":[
        {
            "category":"Shopping",
            "subcategory":"Computers & Home Electronics",
            "type":"Retail Goods"
        }
    ],
    "sg:phone":"+1 952 949 9074",
    "sg:postcode":"55347",
    "sg:province":"MN",
    "wof:name":"D A Heck Software Service",
    "wof:placetype":"venue"
},
  "geometry": {"coordinates":[-93.494698,44.848261],"type":"Point"}
}