{
  "type": "Feature",
  "properties": {
    "addr:full":"410 Central Ave E Medford MN 55049",
    "addr:housenumber":"410",
    "addr:postcode":"55049",
    "addr:street":"Central Ave E",
    "iso:country":"US",
    "sg:address":"410 Central Ave E",
    "sg:city":"Medford",
    "sg:classifiers":[
        {
            "category":"Food & Beverages",
            "subcategory":"Groceries & Convenience Stores",
            "type":"Retail Goods"
        }
    ],
    "sg:phone":"+1 507 451 7721",
    "sg:postcode":"55049",
    "sg:province":"MN",
    "wof:name":"Jeff Ettinger",
    "wof:placetype":"venue"
},
  "geometry": {"coordinates":[-93.242963,44.173216],"type":"Point"}
}