{
  "type": "Feature",
  "properties": {
    "addr:full":"2601 E Hennepin Ave Minneapolis MN 55413",
    "addr:housenumber":"2601",
    "addr:postcode":"55413",
    "addr:street":"E Hennepin Ave",
    "iso:country":"US",
    "sg:address":"2601 E Hennepin Ave",
    "sg:city":"Minneapolis",
    "sg:classifiers":[
        {
            "category":"Food & Beverages",
            "subcategory":"Fruits & Vegetables",
            "type":"Retail Goods"
        }
    ],
    "sg:phone":"+1 612 676 0944",
    "sg:postcode":"55413",
    "sg:province":"MN",
    "sg:tags":[
        "produce"
    ],
    "wof:name":"Cut Fruit Express",
    "wof:placetype":"venue"
},
  "geometry": {"coordinates":[-93.215149,44.991581],"type":"Point"}
}