{
  "type": "Feature",
  "properties": {
    "iso:country":"US",
    "sg:address":"104 Park St",
    "sg:city":"Ada",
    "sg:classifiers":[
        {
            "category":"Government",
            "subcategory":"Office",
            "type":"Public Place"
        }
    ],
    "sg:phone":"+1 218 784 2102",
    "sg:postcode":"56535",
    "sg:province":"MN",
    "wof:name":"Norman County Recycling Ctr",
    "wof:placetype":"venue"
},
  "geometry": {"coordinates":[-96.018255,47.671734],"type":"Point"}
}