{
  "type": "Feature",
  "properties": {
    "iso:country":"US",
    "sg:address":"276 Snelling Ave",
    "sg:city":"Saint Paul",
    "sg:classifiers":[
        {
            "category":"Insurance",
            "subcategory":"Insurance Agent",
            "type":"Services"
        }
    ],
    "sg:phone":"+1 651 646 0635",
    "sg:postcode":"55104",
    "sg:province":"MN",
    "wof:name":"AFLAC",
    "wof:placetype":"venue"
},
  "geometry": {"coordinates":[-93.166916,44.95019],"type":"Point"}
}