{
  "type": "Feature",
  "properties": {
    "addr:full":"1418 Rocky Ln Saint Paul MN 55122",
    "addr:housenumber":"1418",
    "addr:postcode":"55122",
    "addr:street":"Rocky Ln",
    "iso:country":"US",
    "sg:address":"1418 Rocky Ln",
    "sg:city":"Saint Paul",
    "sg:classifiers":[
        {
            "category":"Travel",
            "subcategory":"Travel Agent",
            "type":"Entertainment"
        }
    ],
    "sg:phone":"+1 651 688 7320",
    "sg:postcode":"55122",
    "sg:province":"MN",
    "sg:tags":[
        "operator",
        "tour"
    ],
    "wof:name":"Friends of 261",
    "wof:placetype":"venue"
},
  "geometry": {"coordinates":[-93.170922,44.814119],"type":"Point"}
}