{
  "type": "Feature",
  "properties": {
    "iso:country":"US",
    "sg:address":"1011 Moore Lake Dr W",
    "sg:city":"Fridley",
    "sg:classifiers":[
        {
            "category":"Health Services",
            "subcategory":"Health Practitioner",
            "type":"Services"
        },
        {
            "category":"Health Services",
            "subcategory":"Doctor",
            "type":"Services"
        }
    ],
    "sg:phone":"+1 763 586 6045",
    "sg:postcode":"55432",
    "sg:province":"MN",
    "sg:tags":[
        "acupuncture",
        "medical"
    ],
    "wof:name":"Total Health Acupuncture Clnc",
    "wof:placetype":"venue"
},
  "geometry": {"coordinates":[-93.24548900000001,45.080839],"type":"Point"}
}