{
  "type": "Feature",
  "properties": {
    "addr:full":"12530 Ulysses St NE Blaine MN 55434",
    "addr:housenumber":"12530",
    "addr:postcode":"55434",
    "addr:street":"Ulysses St Ne",
    "iso:country":"US",
    "sg:address":"12530 Ulysses St NE",
    "sg:city":"Blaine",
    "sg:classifiers":[
        {
            "category":"Food & Beverages",
            "subcategory":"Groceries & Convenience Stores",
            "type":"Retail Goods"
        }
    ],
    "sg:phone":"+1 763 757 1969",
    "sg:postcode":"55434",
    "sg:province":"MN",
    "wof:name":"Oasis",
    "wof:placetype":"venue"
},
  "geometry": {"coordinates":[-93.237713,45.197741],"type":"Point"}
}