{
  "type": "Feature",
  "properties": {
    "iso:country":"US",
    "sg:address":"9919 Lyndale Ave S",
    "sg:city":"Minneapolis",
    "sg:classifiers":[
        {
            "category":"Banks & Credit Unions",
            "subcategory":"Investment Brokerage",
            "type":"Services"
        }
    ],
    "sg:phone":"+1 952 881 3124",
    "sg:postcode":"55420",
    "sg:province":"MN",
    "sg:tags":[
        "security"
    ],
    "wof:name":"Edward Jones 08229",
    "wof:placetype":"venue"
},
  "geometry": {"coordinates":[-93.288512,44.825197],"type":"Point"}
}