{
  "type": "Feature",
  "properties": {
    "iso:country":"US",
    "sg:address":"3776 Connelly Ave",
    "sg:city":"Saint Paul",
    "sg:classifiers":[
        {
            "category":"Real Estate",
            "subcategory":"Real Estate Operator",
            "type":"Services"
        }
    ],
    "sg:phone":"+1 651 631 1724",
    "sg:postcode":"55112",
    "sg:province":"MN",
    "sg:tags":[
        "building",
        "nonresidential"
    ],
    "wof:name":"Pot of Gold Inc",
    "wof:placetype":"venue"
},
  "geometry": {"coordinates":[-93.155289,45.050205],"type":"Point"}
}