{
  "type": "Feature",
  "properties": {
    "iso:country":"US",
    "sg:address":"8929 Aztec Dr",
    "sg:city":"Eden Prairie",
    "sg:classifiers":[
        {
            "category":"Banks & Credit Unions",
            "subcategory":"Bank",
            "type":"Services"
        }
    ],
    "sg:phone":"+1 952 947 4010",
    "sg:postcode":"55347",
    "sg:province":"MN",
    "sg:tags":[
        "loan",
        "broker",
        "real estate"
    ],
    "wof:name":"First Mortgage Financial Corp",
    "wof:placetype":"venue"
},
  "geometry": {"coordinates":[-93.43810000000001,44.842268],"type":"Point"}
}