{
  "type": "Feature",
  "properties": {
    "iso:country":"US",
    "sg:address":"502 Monroe St SE",
    "sg:city":"Hutchinson",
    "sg:classifiers":[
        {
            "category":"Building & Trades",
            "subcategory":"Construction",
            "type":"Services"
        }
    ],
    "sg:phone":"+1 320 587 3514",
    "sg:postcode":"55350",
    "sg:province":"MN",
    "sg:tags":[
        "house"
    ],
    "wof:name":"Morris Builders",
    "wof:placetype":"venue"
},
  "geometry": {"coordinates":[-94.363651,44.886555],"type":"Point"}
}