{
  "type": "Feature",
  "properties": {
    "addr:full":"5299 Old Long Lake Rd NW Bemidji MN 56601",
    "addr:housenumber":"5299",
    "addr:postcode":"56601",
    "addr:street":"Old Long Lake Rd Nw",
    "iso:country":"US",
    "sg:address":"5299 Old Long Lake Rd NW",
    "sg:city":"Bemidji",
    "sg:classifiers":[
        {
            "category":"Professional",
            "subcategory":"Business Services",
            "type":"Services"
        }
    ],
    "sg:phone":"+1 218 243 2901",
    "sg:postcode":"56601",
    "sg:province":"MN",
    "wof:name":"Wss Enterprises LLC",
    "wof:placetype":"venue"
},
  "geometry": {"coordinates":[-94.984495,47.664306],"type":"Point"}
}