{
  "type": "Feature",
  "properties": {
    "iso:country":"US",
    "sg:address":"5051 Eden Ave",
    "sg:city":"Minneapolis",
    "sg:classifiers":[
        {
            "category":"Education",
            "subcategory":"School",
            "type":"Public Place"
        }
    ],
    "sg:phone":"+1 952 929 5463",
    "sg:postcode":"55436",
    "sg:province":"MN",
    "sg:tags":[
        "elementary",
        "religious"
    ],
    "wof:name":"Our Lady of Grace School",
    "wof:placetype":"venue"
},
  "geometry": {"coordinates":[-93.352261,44.909469],"type":"Point"}
}