{
  "type": "Feature",
  "properties": {
    "addr:full":"202 Grant St Jackson MN 56143",
    "addr:housenumber":"202",
    "addr:postcode":"56143",
    "addr:street":"Grant St",
    "iso:country":"US",
    "sg:address":"202 Grant St",
    "sg:city":"Jackson",
    "sg:classifiers":[
        {
            "category":"Banks & Credit Unions",
            "subcategory":"Bank",
            "type":"Services"
        }
    ],
    "sg:phone":"+1 507 847 4700",
    "sg:postcode":"56143",
    "sg:province":"MN",
    "sg:website":"www.unitedprairiebank.com",
    "wof:name":"United Prairie Bank-Jackson",
    "wof:placetype":"venue"
},
  "geometry": {"coordinates":[-94.98768699999999,43.622316],"type":"Point"}
}