{
  "type": "Feature",
  "properties": {
    "addr:full":"109 W Center St Lake City MN 55041",
    "addr:housenumber":"109",
    "addr:postcode":"55041",
    "addr:street":"W Center St",
    "iso:country":"US",
    "sg:address":"109 W Center St",
    "sg:city":"Lake City",
    "sg:classifiers":[
        {
            "category":"Shopping",
            "subcategory":"Jewelry",
            "type":"Retail Goods"
        },
        {
            "category":"Shopping",
            "subcategory":"Gifts & Souvenirs",
            "type":"Retail Goods"
        }
    ],
    "sg:phone":"+1 651 345 3825",
    "sg:postcode":"55041",
    "sg:province":"MN",
    "sg:tags":[
        "stone",
        "metal",
        "precious",
        "jeweler"
    ],
    "wof:name":"Swan Limited Jewelers",
    "wof:placetype":"venue"
},
  "geometry": {"coordinates":[-92.265624,44.448619],"type":"Point"}
}