{
  "type": "Feature",
  "properties": {
    "addr:full":"1571 W Laurel Ave Saint Paul MN 55104",
    "addr:housenumber":"1571",
    "addr:postcode":"55104",
    "addr:street":"W Laurel Ave",
    "iso:country":"US",
    "sg:address":"1571 W Laurel Ave",
    "sg:city":"Saint Paul",
    "sg:classifiers":[
        {
            "category":"Professional",
            "type":"Services"
        }
    ],
    "sg:phone":"+1 651 603 8728",
    "sg:postcode":"55104",
    "sg:province":"MN",
    "wof:name":"It4u",
    "wof:placetype":"venue"
},
  "geometry": {"coordinates":[-93.165424,44.945077],"type":"Point"}
}