{
  "type": "Feature",
  "properties": {
    "addr:full":"2577 Vermilion Trl Makinen MN 55763",
    "addr:housenumber":"2577",
    "addr:postcode":"55763",
    "addr:street":"Vermilion Trl",
    "iso:country":"US",
    "sg:address":"2577 Vermilion Trl",
    "sg:city":"Makinen",
    "sg:classifiers":[
        {
            "category":"Government",
            "subcategory":"Fire Station",
            "type":"Public Place"
        }
    ],
    "sg:phone":"+1 218 638 2141",
    "sg:postcode":"55763",
    "sg:province":"MN",
    "sg:tags":[
        "department"
    ],
    "wof:name":"Colvin Fire Hall",
    "wof:placetype":"venue"
},
  "geometry": {"coordinates":[-92.220837,47.306505],"type":"Point"}
}