{
  "type": "Feature",
  "properties": {
    "addr:full":"12760 Lake Blvd Lindstrom MN 55045",
    "addr:housenumber":"12760",
    "addr:postcode":"55045",
    "addr:street":"Lake Blvd",
    "iso:country":"US",
    "sg:address":"12760 Lake Blvd",
    "sg:city":"Lindstrom",
    "sg:classifiers":[
        {
            "category":"Shopping",
            "subcategory":"Clothing, Apparel, & Fashions",
            "type":"Retail Goods"
        }
    ],
    "sg:phone":"+1 651 213 0621",
    "sg:postcode":"55045",
    "sg:province":"MN",
    "sg:tags":[
        "shop",
        "bridal"
    ],
    "wof:name":"Bridal Creations",
    "wof:placetype":"venue"
},
  "geometry": {"coordinates":[-92.848567,45.389846],"type":"Point"}
}