{
  "type": "Feature",
  "properties": {
    "iso:country":"US",
    "sg:address":"3228 6th Ave NE",
    "sg:city":"Rochester",
    "sg:classifiers":[
        {
            "category":"Building & Trades",
            "subcategory":"Construction",
            "type":"Services"
        }
    ],
    "sg:phone":"+1 507 289 7471",
    "sg:postcode":"55906",
    "sg:province":"MN",
    "sg:tags":[
        "house"
    ],
    "wof:name":"Homes By Daniel Mogen",
    "wof:placetype":"venue"
},
  "geometry": {"coordinates":[-92.450991,44.057308],"type":"Point"}
}