{
  "type": "Feature",
  "properties": {
    "iso:country":"US",
    "sg:address":"911 Washington Ave",
    "sg:city":"Detroit Lakes",
    "sg:classifiers":[
        {
            "category":"Personal",
            "subcategory":"Beauty Salon",
            "type":"Services"
        }
    ],
    "sg:phone":"+1 218 847 5070",
    "sg:postcode":"56501",
    "sg:province":"MN",
    "wof:name":"Hair & Co",
    "wof:placetype":"venue"
},
  "geometry": {"coordinates":[-95.845248,46.817115],"type":"Point"}
}