{
  "type": "Feature",
  "properties": {
    "addr:full":"2550 Horizon Dr Burnsville MN 55337",
    "addr:housenumber":"2550",
    "addr:postcode":"55337",
    "addr:street":"Horizon Dr",
    "iso:country":"US",
    "sg:address":"2550 Horizon Dr",
    "sg:city":"Burnsville",
    "sg:classifiers":[
        {
            "category":"Health Services",
            "subcategory":"Health Practitioner",
            "type":"Services"
        },
        {
            "category":"Health Services",
            "subcategory":"Chiropractor",
            "type":"Services"
        }
    ],
    "sg:phone":"+1 952 846 4149",
    "sg:postcode":"55337",
    "sg:province":"MN",
    "sg:tags":[
        "acupuncture"
    ],
    "wof:name":"Pro Active Chiropractic",
    "wof:placetype":"venue"
},
  "geometry": {"coordinates":[-93.24009700000001,44.7924],"type":"Point"}
}