{
  "type": "Feature",
  "properties": {
    "addr:full":"3829 Gowan Ave NW Maple Lake MN 55358",
    "addr:housenumber":"3829",
    "addr:postcode":"55358",
    "addr:street":"Gowan Ave Nw",
    "iso:country":"US",
    "sg:address":"3829 Gowan Ave NW",
    "sg:city":"Maple Lake",
    "sg:phone":"+1 320 963 5452",
    "sg:postcode":"55358",
    "sg:province":"MN",
    "sg:tags":[
        "farm",
        "corn",
        "soybean"
    ],
    "wof:name":"Greg Haglin",
    "wof:placetype":"venue"
},
  "geometry": {"coordinates":[-94.012888,45.205226],"type":"Point"}
}