{
  "type": "Feature",
  "properties": {
    "iso:country":"US",
    "sg:address":"101 N 2nd St",
    "sg:city":"Mankato",
    "sg:classifiers":[
        {
            "category":"Professional",
            "subcategory":"Management & Consulting",
            "type":"Services"
        }
    ],
    "sg:phone":"+1 507 388 7138",
    "sg:postcode":"56001",
    "sg:province":"MN",
    "sg:tags":[
        "consultant"
    ],
    "wof:name":"Paul Holzhueter Consulting",
    "wof:placetype":"venue"
},
  "geometry": {"coordinates":[-94.000941,44.167396],"type":"Point"}
}