{
  "type": "Feature",
  "properties": {
    "addr:full":"3435 W Broadway Ave Minneapolis MN 55422",
    "addr:housenumber":"3435",
    "addr:postcode":"55422",
    "addr:street":"W Broadway Ave",
    "iso:country":"US",
    "sg:address":"3435 W Broadway Ave",
    "sg:city":"Minneapolis",
    "sg:classifiers":[
        {
            "category":"Health Services",
            "subcategory":"Clinic",
            "type":"Services"
        }
    ],
    "sg:phone":"+1 763 520 1152",
    "sg:postcode":"55422",
    "sg:province":"MN",
    "sg:tags":[
        "welfare"
    ],
    "wof:name":"North Memorial Health Care",
    "wof:placetype":"venue"
},
  "geometry": {"coordinates":[-93.32214999999999,45.016272],"type":"Point"}
}