{
  "type": "Feature",
  "properties": {
    "addr:full":"1165 115th Ave NE Foley MN 56329",
    "addr:housenumber":"1165",
    "addr:postcode":"56329",
    "addr:street":"115Th Ave Ne",
    "iso:country":"US",
    "sg:address":"1165 115th Ave NE",
    "sg:city":"Foley",
    "sg:classifiers":[
        {
            "category":"Freight",
            "type":"Transportation"
        }
    ],
    "sg:phone":"+1 320 968 6321",
    "sg:postcode":"56329",
    "sg:province":"MN",
    "sg:tags":[
        "operator",
        "local",
        "trucking"
    ],
    "wof:name":"Plante Trucking",
    "wof:placetype":"venue"
},
  "geometry": {"coordinates":[-93.924177,45.584984],"type":"Point"}
}