{
  "type": "Feature",
  "properties": {
    "iso:country":"US",
    "sg:address":"2100 Silver Lake Rd NW",
    "sg:city":"St Paul",
    "sg:classifiers":[
        {
            "category":"Social Services",
            "subcategory":"Adult Care",
            "type":"Services"
        },
        {
            "category":"Health Services",
            "subcategory":"Nursing And Care Facility",
            "type":"Services"
        }
    ],
    "sg:phone":"+1 651 604 2900",
    "sg:postcode":"55112",
    "sg:province":"MN",
    "sg:tags":[
        "home",
        "retirement",
        "community",
        "residential"
    ],
    "sg:website":"www.meadowoodshores.com",
    "wof:name":"Meadowood Shores",
    "wof:placetype":"venue"
},
  "geometry": {"coordinates":[-93.218987,45.085119],"type":"Point"}
}