{
  "type": "Feature",
  "properties": {
    "iso:country":"US",
    "sg:address":"801 W Washington St",
    "sg:city":"Brainerd",
    "sg:classifiers":[
        {
            "category":"Food & Beverages",
            "subcategory":"Groceries & Convenience Stores",
            "type":"Retail Goods"
        }
    ],
    "sg:phone":"+1 218 829 0249",
    "sg:postcode":"56401",
    "sg:province":"MN",
    "wof:name":"Freedom Valu Store 59",
    "wof:placetype":"venue"
},
  "geometry": {"coordinates":[-94.22172999999999,46.35592],"type":"Point"}
}