{
  "type": "Feature",
  "properties": {
    "addr:full":"108 2nd St NE Aitkin MN 56431",
    "addr:housenumber":"108",
    "addr:postcode":"56431",
    "addr:street":"2Nd St Ne",
    "iso:country":"US",
    "sg:address":"108 2nd St NE",
    "sg:city":"Aitkin",
    "sg:classifiers":[
        {
            "category":"Real Estate",
            "subcategory":"Real Estate Operator",
            "type":"Services"
        }
    ],
    "sg:phone":"+1 218 927 2169",
    "sg:postcode":"56431",
    "sg:province":"MN",
    "sg:tags":[
        "body",
        "repairing",
        "building",
        "nonresidential",
        "automobile",
        "painting"
    ],
    "sg:website":"http://aitkinmotorco.com",
    "wof:name":"Aitkin Motor Co",
    "wof:placetype":"venue"
},
  "geometry": {"coordinates":[-93.704376,46.53339],"type":"Point"}
}