{
  "type": "Feature",
  "properties": {
    "iso:country":"US",
    "sg:address":"1530 Natchez Ave S",
    "sg:city":"Minneapolis",
    "sg:classifiers":[
        {
            "category":"Professional",
            "subcategory":"Advertising",
            "type":"Services"
        }
    ],
    "sg:phone":"+1 763 377 1000",
    "sg:postcode":"55416",
    "sg:province":"MN",
    "sg:tags":[
        "agency"
    ],
    "wof:name":"Legend Mktg Communications",
    "wof:placetype":"venue"
},
  "geometry": {"coordinates":[-93.339077,44.968302],"type":"Point"}
}