{
  "type": "Feature",
  "properties": {
    "addr:full":"2575 Fairview Ave N Ste 250 Saint Paul MN 55113",
    "addr:housenumber":"2575",
    "addr:postcode":"55113",
    "addr:street":"Fairview Ave N Ste 250",
    "iso:country":"US",
    "sg:address":"2575 Fairview Ave N Ste 250",
    "sg:city":"Saint Paul",
    "sg:classifiers":[
        {
            "category":"Real Estate",
            "subcategory":"Real Estate Services",
            "type":"Services"
        }
    ],
    "sg:phone":"+1 651 633 6312",
    "sg:postcode":"55113",
    "sg:province":"MN",
    "sg:tags":[
        "management",
        "property"
    ],
    "wof:name":"Commers Enterprises",
    "wof:placetype":"venue"
},
  "geometry": {"coordinates":[-93.1772,45.018398],"type":"Point"}
}