{
  "type": "Feature",
  "properties": {
    "addr:full":"3566 W Tischer Rd Duluth MN 55803",
    "addr:housenumber":"3566",
    "addr:postcode":"55803",
    "addr:street":"W Tischer Rd",
    "iso:country":"US",
    "sg:address":"3566 W Tischer Rd",
    "sg:city":"Duluth",
    "sg:classifiers":[
        {
            "category":"Home & Garden",
            "subcategory":"Home Furnishings",
            "type":"Retail Goods"
        }
    ],
    "sg:phone":"+1 218 728 6950",
    "sg:postcode":"55803",
    "sg:province":"MN",
    "sg:tags":[
        "quilting"
    ],
    "wof:name":"Pine Needle Quilting",
    "wof:placetype":"venue"
},
  "geometry": {"coordinates":[-92.050995,46.880059],"type":"Point"}
}