{
  "type": "Feature",
  "properties": {
    "iso:country":"US",
    "sg:address":"8525 Edinbrook Xing",
    "sg:city":"Minneapolis",
    "sg:classifiers":[
        {
            "category":"Utilities",
            "subcategory":"Telephone",
            "type":"Services"
        }
    ],
    "sg:phone":"+1 763 424 2668",
    "sg:postcode":"55443",
    "sg:province":"MN",
    "sg:tags":[
        "telecommunication"
    ],
    "wof:name":"Twin City Telecom",
    "wof:placetype":"venue"
},
  "geometry": {"coordinates":[-93.32430100000001,45.108935],"type":"Point"}
}