{
  "type": "Feature",
  "properties": {
    "iso:country":"US",
    "sg:address":"1404 7th St NW",
    "sg:city":"Faribault",
    "sg:classifiers":[
        {
            "category":"Wholesale",
            "subcategory":"Drugs",
            "type":"Manufacturing & Wholesale Goods"
        }
    ],
    "sg:phone":"+1 507 334 4929",
    "sg:postcode":"55021",
    "sg:province":"MN",
    "sg:tags":[
        "equipment"
    ],
    "wof:name":"Lextron Animal Health",
    "wof:placetype":"venue"
},
  "geometry": {"coordinates":[-93.29000499999999,44.297881],"type":"Point"}
}