{
  "type": "Feature",
  "properties": {
    "iso:country":"US",
    "sg:address":"17557 300th St",
    "sg:city":"Clarissa",
    "sg:classifiers":[
        {
            "category":"Organizations",
            "subcategory":"Membership Organization",
            "type":"Services"
        }
    ],
    "sg:phone":"+1 218 756 2416",
    "sg:postcode":"56440",
    "sg:province":"MN",
    "wof:name":"Mid Minnesota Draft Horse Assn",
    "wof:placetype":"venue"
},
  "geometry": {"coordinates":[-94.994578,46.063065],"type":"Point"}
}