{
  "type": "Feature",
  "properties": {
    "addr:full":"620 8th St NE Milaca MN 56353",
    "addr:housenumber":"620",
    "addr:postcode":"56353",
    "addr:street":"8Th St Ne",
    "iso:country":"US",
    "sg:address":"620 8th St NE",
    "sg:city":"Milaca",
    "sg:classifiers":[
        {
            "category":"Government",
            "subcategory":"Office",
            "type":"Public Place"
        },
        {
            "category":"Shopping",
            "subcategory":"Computers & Home Electronics",
            "type":"Retail Goods"
        }
    ],
    "sg:phone":"+1 320 983 2368",
    "sg:postcode":"56353",
    "sg:province":"MN",
    "sg:tags":[
        "state",
        "program",
        "health"
    ],
    "wof:name":"Health Care E Mail",
    "wof:placetype":"venue"
},
  "geometry": {"coordinates":[-93.645326,45.761886],"type":"Point"}
}