{
  "type": "Feature",
  "properties": {
    "iso:country":"US",
    "sg:address":"7101 10th St N",
    "sg:city":"Saint Paul",
    "sg:classifiers":[
        {
            "category":"Farming",
            "subcategory":"Nursery",
            "type":"Manufacturing & Wholesale Goods"
        }
    ],
    "sg:phone":"+1 651 730 7616",
    "sg:postcode":"55128",
    "sg:province":"MN",
    "sg:tags":[
        "ornamental"
    ],
    "wof:name":"Flowers & Friends",
    "wof:placetype":"venue"
},
  "geometry": {"coordinates":[-92.96432299999999,44.963274],"type":"Point"}
}