{
  "type": "Feature",
  "properties": {
    "addr:full":"3650 Aquila Ave S Minneapolis MN 55426",
    "addr:postcode":"3650;55426",
    "addr:street":"Aquila Ave S",
    "iso:country":"US",
    "sg:address":"3650 Aquila Ave S",
    "sg:city":"Minneapolis",
    "sg:classifiers":[
        {
            "category":"Restaurant",
            "type":"Food & Drink"
        }
    ],
    "sg:phone":"+1 952 936 0440",
    "sg:postcode":"55426",
    "sg:province":"MN",
    "sg:tags":[
        "a",
        "king",
        "fast",
        "operates",
        "burger",
        "as"
    ],
    "wof:name":"Burger King",
    "wof:placetype":"venue"
},
  "geometry": {"coordinates":[-93.386399,44.936001],"type":"Point"}
}