{
  "type": "Feature",
  "properties": {
    "addr:full":"311 6th St Jackson MN 56143",
    "addr:housenumber":"311",
    "addr:postcode":"56143",
    "addr:street":"6Th St",
    "iso:country":"US",
    "sg:address":"311 6th St",
    "sg:city":"Jackson",
    "sg:classifiers":[
        {
            "category":"Freight",
            "type":"Transportation"
        }
    ],
    "sg:phone":"+1 507 847 2526",
    "sg:postcode":"56143",
    "sg:province":"MN",
    "sg:tags":[
        "special"
    ],
    "wof:name":"Willets Storage & Gravel Co",
    "wof:placetype":"venue"
},
  "geometry": {"coordinates":[-94.991494,43.621514],"type":"Point"}
}