{
  "type": "Feature",
  "properties": {
    "iso:country":"US",
    "sg:address":"908 S State St",
    "sg:city":"New Ulm",
    "sg:classifiers":[
        {
            "category":"Social Services",
            "subcategory":"Child Care",
            "type":"Services"
        }
    ],
    "sg:phone":"+1 507 354 7444",
    "sg:postcode":"56073",
    "sg:province":"MN",
    "sg:tags":[
        "daycare",
        "provider"
    ],
    "wof:name":"Ann Scharfencamp",
    "wof:placetype":"venue"
},
  "geometry": {"coordinates":[-94.453396,44.302946],"type":"Point"}
}