{
  "type": "Feature",
  "properties": {
    "iso:country":"US",
    "sg:address":"2317 Cottage Dr",
    "sg:city":"Stillwater",
    "sg:classifiers":[
        {
            "category":"Building & Trades",
            "subcategory":"Cleaning & Sanitation",
            "type":"Services"
        }
    ],
    "sg:phone":"+1 651 439 8388",
    "sg:postcode":"55082",
    "sg:province":"MN",
    "sg:tags":[
        "maintenance"
    ],
    "wof:name":"Woodhouse Inc",
    "wof:placetype":"venue"
},
  "geometry": {"coordinates":[-92.83593399999999,45.0455],"type":"Point"}
}