{
  "type": "Feature",
  "properties": {
    "addr:full":"105 7th St E Glencoe MN 55336",
    "addr:housenumber":"105",
    "addr:postcode":"55336",
    "addr:street":"7Th St E",
    "iso:country":"US",
    "sg:address":"105 7th St E",
    "sg:city":"Glencoe",
    "sg:classifiers":[
        {
            "category":"Personal",
            "type":"Services"
        }
    ],
    "sg:phone":"+1 320 864 4382",
    "sg:postcode":"55336",
    "sg:province":"MN",
    "sg:tags":[
        "leather"
    ],
    "wof:name":"Best Tanning",
    "wof:placetype":"venue"
},
  "geometry": {"coordinates":[-94.16095900000001,44.766147],"type":"Point"}
}