{
  "type": "Feature",
  "properties": {
    "iso:country":"US",
    "sg:address":"14332 21st Ave N",
    "sg:city":"Minneapolis",
    "sg:classifiers":[
        {
            "category":"Wholesale",
            "subcategory":"Hardware",
            "type":"Manufacturing & Wholesale Goods"
        },
        {
            "category":"Wholesale",
            "subcategory":"Metals & Minerals",
            "type":"Manufacturing & Wholesale Goods"
        }
    ],
    "sg:phone":"+1 763 476 5831",
    "sg:postcode":"55447",
    "sg:province":"MN",
    "sg:tags":[
        "pipe",
        "plumbing",
        "well",
        "representative",
        "supply"
    ],
    "sg:website":"www.bmarep.com",
    "wof:name":"Bennerotte Marketing Agency",
    "wof:placetype":"venue"
},
  "geometry": {"coordinates":[-93.470034,45.000915],"type":"Point"}
}