{
  "type": "Feature",
  "properties": {
    "addr:full":"301 Royalston Ave Minneapolis MN 55405",
    "addr:housenumber":"301",
    "addr:postcode":"55405",
    "addr:street":"Royalston Ave",
    "iso:country":"US",
    "sg:address":"301 Royalston Ave",
    "sg:city":"Minneapolis",
    "sg:classifiers":[
        {
            "category":"Restaurant",
            "type":"Food & Drink"
        },
        {
            "category":"Shopping",
            "subcategory":"Pets & Pet Supplies",
            "type":"Retail Goods"
        }
    ],
    "sg:phone":"+1 612 339 7720",
    "sg:postcode":"55405",
    "sg:province":"MN",
    "sg:tags":[
        "supplies-leasing",
        "seafood",
        "aquarium",
        "maintenance"
    ],
    "wof:name":"Fish Guys Inc the",
    "wof:placetype":"venue"
},
  "geometry": {"coordinates":[-93.283096,44.980099],"type":"Point"}
}