{
  "type": "Feature",
  "properties": {
    "iso:country":"US",
    "sg:address":"3124 Birch Pl",
    "sg:city":"Hopkins",
    "sg:classifiers":[
        {
            "category":"Wholesale",
            "subcategory":"Machinery & Supplies",
            "type":"Manufacturing & Wholesale Goods"
        }
    ],
    "sg:phone":"+1 952 931 7170",
    "sg:postcode":"55305",
    "sg:province":"MN",
    "sg:tags":[
        "equipment",
        "material",
        "handling"
    ],
    "wof:name":"S & K Pallet Jack Repair & Sls",
    "wof:placetype":"venue"
},
  "geometry": {"coordinates":[-93.409659,44.945552],"type":"Point"}
}