{
  "type": "Feature",
  "properties": {
    "addr:full":"12450 Gettysburg Ave N Champlin MN 55316",
    "addr:housenumber":"12450",
    "addr:postcode":"55316",
    "addr:street":"Gettysburg Ave N",
    "iso:country":"US",
    "sg:address":"12450 Gettysburg Ave N",
    "sg:city":"Champlin",
    "sg:classifiers":[
        {
            "category":"Freight",
            "type":"Transportation"
        }
    ],
    "sg:phone":"+1 763 323 9017",
    "sg:postcode":"55316",
    "sg:province":"MN",
    "wof:name":"Senior Transportation",
    "wof:placetype":"venue"
},
  "geometry": {"coordinates":[-93.396828,45.178882],"type":"Point"}
}