{
  "type": "Feature",
  "properties": {
    "iso:country":"US",
    "sg:address":"2920 220th St E",
    "sg:city":"Prior Lake",
    "sg:classifiers":[
        {
            "category":"Retail",
            "subcategory":"Repair Shop",
            "type":"Services"
        }
    ],
    "sg:phone":"+1 952 447 7600",
    "sg:postcode":"55372",
    "sg:province":"MN",
    "wof:name":"Lock Stock & Barrel Gun Shop",
    "wof:placetype":"venue"
},
  "geometry": {"coordinates":[-93.466488,44.630666],"type":"Point"}
}