{
  "type": "Feature",
  "properties": {
    "addr:full":"50 S 6th St Ste 1320 Minneapolis MN 55402",
    "addr:housenumber":"50",
    "addr:postcode":"55402",
    "addr:street":"S 6Th St Ste 1320",
    "iso:country":"US",
    "sg:address":"50 S 6th St Ste 1320",
    "sg:city":"Minneapolis",
    "sg:classifiers":[
        {
            "category":"Parking",
            "type":"Transportation"
        }
    ],
    "sg:phone":"+1 612 371 0938",
    "sg:postcode":"55402",
    "sg:province":"MN",
    "sg:website":"www.standardparking.com",
    "wof:name":"Standard Parking",
    "wof:placetype":"venue"
},
  "geometry": {"coordinates":[-93.271373,44.977845],"type":"Point"}
}