{
  "type": "Feature",
  "properties": {
    "addr:full":"4150 2nd St S St Cloud MN 56301",
    "addr:housenumber":"4150",
    "addr:postcode":"56301",
    "addr:street":"2Nd St S",
    "iso:country":"US",
    "sg:address":"4150 2nd St S",
    "sg:city":"St Cloud",
    "sg:classifiers":[
        {
            "category":"Banks & Credit Unions",
            "subcategory":"Investment Brokerage",
            "type":"Services"
        }
    ],
    "sg:phone":"+1 320 656 3317",
    "sg:postcode":"56301",
    "sg:province":"MN",
    "sg:tags":[
        "consultant",
        "planning",
        "financial"
    ],
    "wof:name":"Bremer Investments",
    "wof:placetype":"venue"
},
  "geometry": {"coordinates":[-94.20837299999999,45.549684],"type":"Point"}
}