{
  "type": "Feature",
  "properties": {
    "iso:country":"US",
    "sg:address":"24644 Co Rd 24",
    "sg:city":"Glenwood",
    "sg:classifiers":[
        {
            "category":"Retail",
            "subcategory":"Repair Shop",
            "type":"Services"
        }
    ],
    "sg:phone":"+1 320 634 3337",
    "sg:postcode":"56334",
    "sg:province":"MN",
    "wof:name":"Olsons Gunsmithing",
    "wof:placetype":"venue"
},
  "geometry": {"coordinates":[-95.442662,45.657375],"type":"Point"}
}