{
  "type": "Feature",
  "properties": {
    "iso:country":"US",
    "sg:address":"218 Oak Grove St",
    "sg:city":"Minneapolis",
    "sg:classifiers":[
        {
            "category":"Real Estate",
            "subcategory":"Real Estate Operator",
            "type":"Services"
        }
    ],
    "sg:phone":"+1 612 872 0184",
    "sg:postcode":"55403",
    "sg:province":"MN",
    "sg:tags":[
        "building",
        "apartment"
    ],
    "wof:name":"William Rahn",
    "wof:placetype":"venue"
},
  "geometry": {"coordinates":[-93.284868,44.967405],"type":"Point"}
}