{
  "type": "Feature",
  "properties": {
    "addr:full":"1624 171st St Holland MN 56139",
    "addr:housenumber":"1624",
    "addr:postcode":"56139",
    "addr:street":"171St St",
    "iso:country":"US",
    "sg:address":"1624 171st St",
    "sg:city":"Holland",
    "sg:phone":"+1 507 347 3236",
    "sg:postcode":"56139",
    "sg:province":"MN",
    "sg:tags":[
        "farm",
        "corn",
        "soybean"
    ],
    "wof:name":"Pater Arvin Farm",
    "wof:placetype":"venue"
},
  "geometry": {"coordinates":[-96.13929899999999,44.09542],"type":"Point"}
}