{
  "type": "Feature",
  "properties": {
    "addr:full":"34079 Laketown Rd Sturgeon Lake MN 55783",
    "addr:postcode":"34079;55783",
    "addr:street":"Laketown Rd",
    "iso:country":"US",
    "sg:address":"34079 Laketown Rd",
    "sg:city":"Sturgeon Lake",
    "sg:classifiers":[
        {
            "category":"Personal",
            "subcategory":"Beauty Salon",
            "type":"Services"
        }
    ],
    "sg:phone":"+1 218 372 3123",
    "sg:postcode":"55783",
    "sg:province":"MN",
    "wof:name":"Hair Affair & Tanning Ctr",
    "wof:placetype":"venue"
},
  "geometry": {"coordinates":[-92.792231,46.375034],"type":"Point"}
}