{
  "type": "Feature",
  "properties": {
    "addr:full":"1636 State Hwy 65 Mora MN 55051",
    "addr:housenumber":"1636",
    "addr:postcode":"55051",
    "addr:street":"State Hwy 65",
    "iso:country":"US",
    "sg:address":"1636 State Hwy 65",
    "sg:city":"Mora",
    "sg:classifiers":[
        {
            "category":"Banks & Credit Unions",
            "subcategory":"Bank",
            "type":"Services"
        }
    ],
    "sg:phone":"+1 320 679 6833",
    "sg:postcode":"55051",
    "sg:province":"MN",
    "sg:tags":[
        "loan",
        "real estate"
    ],
    "sg:website":"www.connectmortgageinc.com",
    "wof:name":"Connect Mortgage",
    "wof:placetype":"venue"
},
  "geometry": {"coordinates":[-93.29671999999999,45.822832],"type":"Point"}
}