{
  "type": "Feature",
  "properties": {
    "iso:country":"US",
    "sg:address":"2200 1st St N",
    "sg:city":"Saint Paul",
    "sg:classifiers":[
        {
            "category":"Professional",
            "subcategory":"Lawyer & Legal Services",
            "type":"Services"
        }
    ],
    "sg:phone":"+1 651 223 6518",
    "sg:postcode":"55109",
    "sg:province":"MN",
    "wof:name":"Marco Lori",
    "wof:placetype":"venue"
},
  "geometry": {"coordinates":[-92.997348,45.008362],"type":"Point"}
}