{
  "type": "Feature",
  "properties": {
    "iso:country":"US",
    "sg:address":"201 Lake St NW",
    "sg:city":"Warroad",
    "sg:classifiers":[
        {
            "category":"Professional",
            "type":"Services"
        },
        {
            "category":"Shopping",
            "subcategory":"Clothing, Apparel, & Fashions",
            "type":"Retail Goods"
        }
    ],
    "sg:phone":"+1 218 386 2206",
    "sg:postcode":"56763",
    "sg:province":"MN",
    "wof:name":"Zone One",
    "wof:placetype":"venue"
},
  "geometry": {"coordinates":[-95.32329900000001,48.90671],"type":"Point"}
}