{
  "type": "Feature",
  "properties": {
    "addr:full":"19491 529th Ln Mcgregor MN 55760",
    "addr:housenumber":"19491",
    "addr:postcode":"55760",
    "addr:street":"529Th Ln",
    "iso:country":"US",
    "sg:address":"19491 529th Ln",
    "sg:city":"Mcgregor",
    "sg:classifiers":[
        {
            "category":"Building & Trades",
            "subcategory":"Construction",
            "type":"Services"
        }
    ],
    "sg:phone":"+1 218 426 5005",
    "sg:postcode":"55760",
    "sg:province":"MN",
    "sg:tags":[
        "masonry",
        "contractor"
    ],
    "wof:name":"A 1 Masonry & Snowplowing",
    "wof:placetype":"venue"
},
  "geometry": {"coordinates":[-93.273983,46.781959],"type":"Point"}
}