{
  "type": "Feature",
  "properties": {
    "iso:country":"US",
    "sg:address":"30070 125th Ave",
    "sg:city":"St Joseph",
    "sg:classifiers":[
        {
            "category":"Building & Trades",
            "subcategory":"Construction",
            "type":"Services"
        }
    ],
    "sg:phone":"+1 320 363 7626",
    "sg:postcode":"56374",
    "sg:province":"MN",
    "sg:tags":[
        "personal",
        "house",
        "handyman"
    ],
    "wof:name":"Ace Handyman Repair Svc",
    "wof:placetype":"venue"
},
  "geometry": {"coordinates":[-94.364992,45.561321],"type":"Point"}
}