{
  "type": "Feature",
  "properties": {
    "iso:country":"US",
    "sg:address":"600 W 78th St",
    "sg:city":"Chanhassen",
    "sg:classifiers":[
        {
            "category":"Real Estate",
            "subcategory":"Real Estate Agent",
            "type":"Services"
        }
    ],
    "sg:phone":"+1 952 974 7877",
    "sg:postcode":"55317",
    "sg:province":"MN",
    "sg:tags":[
        "consultant"
    ],
    "wof:name":"Coffman Development Svc",
    "wof:placetype":"venue"
},
  "geometry": {"coordinates":[-93.53492199999999,44.862253],"type":"Point"}
}