{
  "type": "Feature",
  "properties": {
    "iso:country":"US",
    "sg:address":"25355 US Hwy 169",
    "sg:city":"Zimmerman",
    "sg:classifiers":[
        {
            "category":"Manufacturing",
            "subcategory":"Watercraft",
            "type":"Manufacturing & Wholesale Goods"
        }
    ],
    "sg:phone":"+1 763 856 2231",
    "sg:postcode":"55398",
    "sg:province":"MN",
    "sg:tags":[
        "boat"
    ],
    "wof:name":"Bell Canoe Works Inc",
    "wof:placetype":"venue"
},
  "geometry": {"coordinates":[-93.57258299999999,45.427482],"type":"Point"}
}