{
  "type": "Feature",
  "properties": {
    "addr:full":"702 8th Ave SW Pipestone MN 56164",
    "addr:housenumber":"702",
    "addr:postcode":"56164",
    "addr:street":"8Th Ave Sw",
    "iso:country":"US",
    "sg:address":"702 8th Ave SW",
    "sg:city":"Pipestone",
    "sg:classifiers":[
        {
            "category":"Professional",
            "subcategory":"Management & Consulting",
            "type":"Services"
        },
        {
            "category":"Manufacturing",
            "subcategory":"Food",
            "type":"Manufacturing & Wholesale Goods"
        },
        {
            "category":"Wholesale",
            "subcategory":"Fruits & Vegetables",
            "type":"Manufacturing & Wholesale Goods"
        },
        {
            "category":"Farming",
            "subcategory":"Farm",
            "type":"Manufacturing & Wholesale Goods"
        }
    ],
    "sg:phone":"+1 507 825 3922",
    "sg:postcode":"56164",
    "sg:province":"MN",
    "sg:tags":[
        "product",
        "bean",
        "corn"
    ],
    "wof:name":"Earl Carlson",
    "wof:placetype":"venue"
},
  "geometry": {"coordinates":[-96.327721,43.994268],"type":"Point"}
}