{
  "type": "Feature",
  "properties": {
    "iso:country":"US",
    "sg:address":"19727 Eastwood Dr",
    "sg:city":"Osakis",
    "sg:classifiers":[
        {
            "category":"Travel",
            "subcategory":"Hotels & Motels",
            "type":"Entertainment"
        }
    ],
    "sg:phone":"+1 320 859 4535",
    "sg:postcode":"56360",
    "sg:province":"MN",
    "sg:tags":[
        "resort"
    ],
    "wof:name":"Sun-Fish Resort",
    "wof:placetype":"venue"
},
  "geometry": {"coordinates":[-95.090355,45.915743],"type":"Point"}
}