{
  "type": "Feature",
  "properties": {
    "iso:country":"US",
    "sg:address":"6355 Lake Sarah Heights Dr",
    "sg:city":"Rockford",
    "sg:classifiers":[
        {
            "category":"Professional",
            "subcategory":"Management & Consulting",
            "type":"Services"
        }
    ],
    "sg:phone":"+1 763 477 6596",
    "sg:postcode":"55373",
    "sg:province":"MN",
    "sg:tags":[
        "consultant",
        "business"
    ],
    "wof:name":"Ability and Beyond",
    "wof:placetype":"venue"
},
  "geometry": {"coordinates":[-93.671485,45.06908],"type":"Point"}
}