{
  "type": "Feature",
  "properties": {
    "iso:country":"US",
    "sg:address":"19316 489th Ave",
    "sg:city":"Lake Crystal",
    "sg:phone":"+1 507 726 6123",
    "sg:postcode":"56055",
    "sg:province":"MN",
    "sg:tags":[
        "farm",
        "corn"
    ],
    "wof:name":"Laingen",
    "wof:placetype":"venue"
},
  "geometry": {"coordinates":[-94.309044,44.102717],"type":"Point"}
}