{
  "type": "Feature",
  "properties": {
    "addr:full":"401 E 4th St Saint Paul MN 55101",
    "addr:housenumber":"401",
    "addr:postcode":"55101",
    "addr:street":"E 4Th St",
    "iso:country":"US",
    "sg:address":"401 E 4th St",
    "sg:city":"Saint Paul",
    "sg:classifiers":[
        {
            "category":"Shopping",
            "subcategory":"Stationery & Office Supplies",
            "type":"Retail Goods"
        }
    ],
    "sg:phone":"+1 651 225 0969",
    "sg:postcode":"55101",
    "sg:province":"MN",
    "wof:name":"One Source Supply",
    "wof:placetype":"venue"
},
  "geometry": {"coordinates":[-93.078245,44.952892],"type":"Point"}
}