{
  "type": "Feature",
  "properties": {
    "iso:country":"US",
    "sg:address":"26 Water St",
    "sg:city":"Excelsior",
    "sg:phone":"+1 952 474 3716",
    "sg:postcode":"55331",
    "sg:province":"MN",
    "sg:website":"http://www.five-star-cinemas.com",
    "wof:name":"Excelsior Dock Cinema 3",
    "wof:placetype":"venue"
},
  "geometry": {"coordinates":[-93.565321,44.90417],"type":"Point"}
}