{
  "type": "Feature",
  "properties": {
    "iso:country":"US",
    "sg:address":"6200 S Linwood Dr NE",
    "sg:city":"Wyoming",
    "sg:classifiers":[
        {
            "category":"Professional",
            "subcategory":"Advertising",
            "type":"Services"
        }
    ],
    "sg:phone":"+1 651 462 4513",
    "sg:postcode":"55092",
    "sg:province":"MN",
    "sg:tags":[
        "agency"
    ],
    "wof:name":"Creative Freedom Inc",
    "wof:placetype":"venue"
},
  "geometry": {"coordinates":[-93.120698,45.347519],"type":"Point"}
}