{
  "type": "Feature",
  "properties": {
    "addr:full":"10283 280th St E Cannon Falls MN 55009",
    "addr:housenumber":"10283",
    "addr:postcode":"55009",
    "addr:street":"280Th St E",
    "iso:country":"US",
    "sg:address":"10283 280th St E",
    "sg:city":"Cannon Falls",
    "sg:classifiers":[
        {
            "category":"Real Estate",
            "subcategory":"Real Estate Operator",
            "type":"Services"
        }
    ],
    "sg:phone":"+1 507 263 0173",
    "sg:postcode":"55009",
    "sg:province":"MN",
    "sg:tags":[
        "property",
        "lessor"
    ],
    "wof:name":"Cannon Valley Pine Creek Farms",
    "wof:placetype":"venue"
},
  "geometry": {"coordinates":[-92.831917,44.543227],"type":"Point"}
}