{
  "type": "Feature",
  "properties": {
    "addr:full":"2851 Snelling Ave N Saint Paul MN 55113",
    "addr:housenumber":"2851",
    "addr:postcode":"55113",
    "addr:street":"Snelling Ave N",
    "iso:country":"US",
    "sg:address":"2851 Snelling Ave N",
    "sg:city":"Saint Paul",
    "sg:classifiers":[
        {
            "category":"Restaurant",
            "type":"Food & Drink"
        }
    ],
    "sg:phone":"+1 651 633 4422",
    "sg:postcode":"55113",
    "sg:province":"MN",
    "wof:name":"Countryside Restaurant",
    "wof:placetype":"venue"
},
  "geometry": {"coordinates":[-93.167297,45.026501],"type":"Point"}
}