{
  "type": "Feature",
  "properties": {
    "addr:full":"3337 Kyle Ave N Minneapolis MN 55422",
    "addr:housenumber":"3337",
    "addr:postcode":"55422",
    "addr:street":"Kyle Ave N",
    "iso:country":"US",
    "sg:address":"3337 Kyle Ave N",
    "sg:city":"Minneapolis",
    "sg:classifiers":[
        {
            "category":"Wholesale",
            "subcategory":"Electrical",
            "type":"Manufacturing & Wholesale Goods"
        }
    ],
    "sg:phone":"+1 763 287 8004",
    "sg:postcode":"55422",
    "sg:province":"MN",
    "sg:tags":[
        "equipment",
        "electric",
        "equipment-testing"
    ],
    "wof:name":"William M Ruva Co",
    "wof:placetype":"venue"
},
  "geometry": {"coordinates":[-93.334953,45.016218],"type":"Point"}
}