{
  "type": "Feature",
  "properties": {
    "iso:country":"US",
    "sg:address":"7760 France Ave S # 1100",
    "sg:city":"Minneapolis",
    "sg:classifiers":[
        {
            "category":"Structure",
            "subcategory":"Warehouse",
            "type":"Public Place"
        },
        {
            "category":"Retail",
            "subcategory":"Storage",
            "type":"Services"
        }
    ],
    "sg:phone":"+1 952 886 7319",
    "sg:postcode":"55435",
    "sg:province":"MN",
    "sg:tags":[
        "self",
        "warehouses-public-commercial"
    ],
    "wof:name":"Gopher Storage South",
    "wof:placetype":"venue"
},
  "geometry": {"coordinates":[-93.32891100000001,44.861321],"type":"Point"}
}