{
  "type": "Feature",
  "properties": {
    "iso:country":"US",
    "sg:address":"11830 Runnel Cir",
    "sg:city":"Eden Prairie",
    "sg:classifiers":[
        {
            "category":"Professional",
            "subcategory":"Business Services",
            "type":"Services"
        }
    ],
    "sg:phone":"+1 612 669 7171",
    "sg:postcode":"55347",
    "sg:province":"MN",
    "sg:website":"www.midwestskier.com",
    "wof:name":"Midwest Skier",
    "wof:placetype":"venue"
},
  "geometry": {"coordinates":[-93.426483,44.825305],"type":"Point"}
}