{
  "type": "Feature",
  "properties": {
    "iso:country":"US",
    "sg:address":"3424 Utah Ave N",
    "sg:city":"Minneapolis",
    "sg:classifiers":[
        {
            "category":"Building & Trades",
            "subcategory":"Construction",
            "type":"Services"
        }
    ],
    "sg:phone":"+1 763 545 9542",
    "sg:postcode":"55427",
    "sg:province":"MN",
    "sg:tags":[
        "drywall",
        "contractor"
    ],
    "wof:name":"Tj Drywall",
    "wof:placetype":"venue"
},
  "geometry": {"coordinates":[-93.381828,45.018921],"type":"Point"}
}