{
  "type": "Feature",
  "properties": {
    "addr:full":"29465 Rendova St NE Isanti MN 55040",
    "addr:postcode":"29465;55040",
    "addr:street":"Rendova St Ne",
    "iso:country":"US",
    "sg:address":"29465 Rendova St NE",
    "sg:city":"Isanti",
    "sg:phone":"+1 763 444 0420",
    "sg:postcode":"55040",
    "sg:province":"MN",
    "wof:name":"Bmw Stables",
    "wof:placetype":"venue"
},
  "geometry": {"coordinates":[-93.17868,45.501749],"type":"Point"}
}