{
  "type": "Feature",
  "properties": {
    "iso:country":"US",
    "sg:address":"6405 France Ave S",
    "sg:city":"Edina",
    "sg:classifiers":[
        {
            "category":"Health Services",
            "subcategory":"Doctor",
            "type":"Services"
        }
    ],
    "sg:phone":"+1 952 925 4161",
    "sg:postcode":"55435",
    "sg:province":"MN",
    "sg:tags":[
        "physician",
        "surgeon"
    ],
    "wof:name":"Mn Opthalmic Plastic Srgy Spec",
    "wof:placetype":"venue"
},
  "geometry": {"coordinates":[-93.328874,44.885744],"type":"Point"}
}