{
  "type": "Feature",
  "properties": {
    "addr:full":"582 Tyler Rd S Red Wing MN 55066",
    "addr:housenumber":"582",
    "addr:postcode":"55066",
    "addr:street":"Tyler Rd S",
    "iso:country":"US",
    "sg:address":"582 Tyler Rd S",
    "sg:city":"Red Wing",
    "sg:classifiers":[
        {
            "category":"Home & Garden",
            "subcategory":"Building Materials",
            "type":"Retail Goods"
        }
    ],
    "sg:phone":"+1 651 388 4757",
    "sg:postcode":"55066",
    "sg:province":"MN",
    "wof:name":"Lumber One Avon",
    "wof:placetype":"venue"
},
  "geometry": {"coordinates":[-92.58544500000001,44.565616],"type":"Point"}
}