{
  "type": "Feature",
  "properties": {
    "iso:country":"US",
    "sg:address":"1020 Minnesota St E",
    "sg:city":"Cannon Falls",
    "sg:classifiers":[
        {
            "category":"Education",
            "subcategory":"School",
            "type":"Public Place"
        }
    ],
    "sg:phone":"+1 507 263 4226",
    "sg:postcode":"55009",
    "sg:province":"MN",
    "sg:website":"www.cannonfallsschools.com",
    "wof:name":"Cannon Falls Elementary School",
    "wof:placetype":"venue"
},
  "geometry": {"coordinates":[-92.888413,44.511304],"type":"Point"}
}