{
  "type": "Feature",
  "properties": {
    "addr:full":"5507 120th St NW Maple Lake MN 55358",
    "addr:housenumber":"5507",
    "addr:postcode":"55358",
    "addr:street":"120Th St Nw",
    "iso:country":"US",
    "sg:address":"5507 120th St NW",
    "sg:city":"Maple Lake",
    "sg:classifiers":[
        {
            "category":"Building & Trades",
            "subcategory":"Construction",
            "type":"Services"
        }
    ],
    "sg:phone":"+1 320 963 3327",
    "sg:postcode":"55358",
    "sg:province":"MN",
    "sg:tags":[
        "hanging",
        "contractor"
    ],
    "wof:name":"Smith Bros Pntg & Wallcovering",
    "wof:placetype":"venue"
},
  "geometry": {"coordinates":[-94.00446100000001,45.325588],"type":"Point"}
}