{
  "type": "Feature",
  "properties": {
    "addr:full":"45842 Co Hwy 54 Ottertail MN 56571",
    "addr:housenumber":"45842",
    "addr:postcode":"56571",
    "addr:street":"Co Hwy 54",
    "iso:country":"US",
    "sg:address":"45842 Co Hwy 54",
    "sg:city":"Ottertail",
    "sg:classifiers":[
        {
            "category":"Retail",
            "subcategory":"Repair Shop",
            "type":"Services"
        }
    ],
    "sg:phone":"+1 218 367 2205",
    "sg:postcode":"56571",
    "sg:province":"MN",
    "sg:tags":[
        "welding"
    ],
    "wof:name":"Cliffs Repair",
    "wof:placetype":"venue"
},
  "geometry": {"coordinates":[-95.537423,46.462675],"type":"Point"}
}