{
  "type": "Feature",
  "properties": {
    "iso:country":"US",
    "sg:address":"2435 Brinkhaus St",
    "sg:city":"Chaska",
    "sg:classifiers":[
        {
            "category":"Wholesale",
            "subcategory":"Hardware",
            "type":"Manufacturing & Wholesale Goods"
        },
        {
            "category":"Wholesale",
            "subcategory":"Durable Goods & Equipment",
            "type":"Manufacturing & Wholesale Goods"
        }
    ],
    "sg:phone":"+1 952 448 6230",
    "sg:postcode":"55318",
    "sg:province":"MN",
    "sg:tags":[
        "representative",
        "manufacturer"
    ],
    "wof:name":"Win 3 Inc",
    "wof:placetype":"venue"
},
  "geometry": {"coordinates":[-93.62815999999999,44.820808],"type":"Point"}
}