{
  "type": "Feature",
  "properties": {
    "addr:full":"3401 Douglas Dr N Minneapolis MN 55422",
    "addr:housenumber":"3401",
    "addr:postcode":"55422",
    "addr:street":"Douglas Dr N",
    "iso:country":"US",
    "sg:address":"3401 Douglas Dr N",
    "sg:city":"Minneapolis",
    "sg:classifiers":[
        {
            "category":"Autos & Motor Vehicles",
            "subcategory":"Auto Supplies",
            "type":"Retail Goods"
        },
        {
            "category":"Retail",
            "subcategory":"Auto Repair",
            "type":"Services"
        }
    ],
    "sg:phone":"+1 763 535 2786",
    "sg:postcode":"55422",
    "sg:province":"MN",
    "sg:tags":[
        "tire"
    ],
    "wof:name":"Big Block Automotive",
    "wof:placetype":"venue"
},
  "geometry": {"coordinates":[-93.360224,45.018228],"type":"Point"}
}