{
  "type": "Feature",
  "properties": {
    "iso:country":"US",
    "sg:address":"4328 Zenith Ave N",
    "sg:city":"Minneapolis",
    "sg:classifiers":[
        {
            "category":"Building & Trades",
            "subcategory":"Construction",
            "type":"Services"
        },
        {
            "category":"Health Services",
            "subcategory":"Doctor",
            "type":"Services"
        }
    ],
    "sg:phone":"+1 763 504 9294",
    "sg:postcode":"55422",
    "sg:province":"MN",
    "sg:tags":[
        "dentist",
        "nonresidential"
    ],
    "wof:name":"DDM Construction Inc",
    "wof:placetype":"venue"
},
  "geometry": {"coordinates":[-93.32128,45.036043],"type":"Point"}
}