{
  "type": "Feature",
  "properties": {
    "iso:country":"US",
    "sg:address":"812 15th St N",
    "sg:city":"Moorhead",
    "sg:classifiers":[
        {
            "category":"Retail",
            "subcategory":"Repair Shop",
            "type":"Services"
        }
    ],
    "sg:phone":"+1 218 299 6411",
    "sg:postcode":"56560",
    "sg:province":"MN",
    "wof:name":"J&J Septic Service",
    "wof:placetype":"venue"
},
  "geometry": {"coordinates":[-96.755713,46.885412],"type":"Point"}
}