{
  "type": "Feature",
  "properties": {
    "addr:full":"702 3rd Ave SE Barnesville MN 56514",
    "addr:housenumber":"702",
    "addr:postcode":"56514",
    "addr:street":"3Rd Ave Se",
    "iso:country":"US",
    "sg:address":"702 3rd Ave SE",
    "sg:city":"Barnesville",
    "sg:classifiers":[
        {
            "category":"Wholesale",
            "subcategory":"Non-durable Goods",
            "type":"Manufacturing & Wholesale Goods"
        }
    ],
    "sg:phone":"+1 218 354 2146",
    "sg:postcode":"56514",
    "sg:province":"MN",
    "wof:name":"Sylvester Richard",
    "wof:placetype":"venue"
},
  "geometry": {"coordinates":[-96.411777,46.651248],"type":"Point"}
}