{
  "type": "Feature",
  "properties": {
    "iso:country":"US",
    "sg:address":"11013 President Dr NE",
    "sg:city":"Minneapolis",
    "sg:classifiers":[
        {
            "category":"Organizations",
            "subcategory":"Religious Organization",
            "type":"Services"
        }
    ],
    "sg:phone":"+1 763 757 4404",
    "sg:postcode":"55434",
    "sg:province":"MN",
    "sg:website":"http://www.jerichoministry.com",
    "wof:name":"Jericho Ministry",
    "wof:placetype":"venue"
},
  "geometry": {"coordinates":[-93.25961,45.170324],"type":"Point"}
}