{
  "type": "Feature",
  "properties": {
    "addr:full":"47434 Skyline Dr Bemidji MN 56601",
    "addr:housenumber":"47434",
    "addr:postcode":"56601",
    "addr:street":"Skyline Dr",
    "iso:country":"US",
    "sg:address":"47434 Skyline Dr",
    "sg:city":"Bemidji",
    "sg:classifiers":[
        {
            "category":"Retail",
            "subcategory":"Laundry & Dry Cleaning",
            "type":"Services"
        },
        {
            "category":"Building & Trades",
            "subcategory":"Cleaning & Sanitation",
            "type":"Services"
        }
    ],
    "sg:phone":"+1 218 751 0403",
    "sg:postcode":"56601",
    "sg:province":"MN",
    "sg:tags":[
        "cleaner",
        "upholstery",
        "rug",
        "carpet"
    ],
    "wof:name":"Chem-Dry",
    "wof:placetype":"venue"
},
  "geometry": {"coordinates":[-94.878607,47.34372],"type":"Point"}
}