{
  "type": "Feature",
  "properties": {
    "addr:full":"9480 71st St S Cottage Grove MN 55016",
    "addr:housenumber":"9480",
    "addr:postcode":"55016",
    "addr:street":"71St St S",
    "iso:country":"US",
    "sg:address":"9480 71st St S",
    "sg:city":"Cottage Grove",
    "sg:classifiers":[
        {
            "category":"Building & Trades",
            "subcategory":"Cleaning & Sanitation",
            "type":"Services"
        }
    ],
    "sg:phone":"+1 651 768 0455",
    "sg:postcode":"55016",
    "sg:province":"MN",
    "sg:tags":[
        "maintenance"
    ],
    "wof:name":"Absolute Best Cleaning LLC",
    "wof:placetype":"venue"
},
  "geometry": {"coordinates":[-92.91521899999999,44.846304],"type":"Point"}
}