{
  "type": "Feature",
  "properties": {
    "iso:country":"US",
    "sg:address":"9495 Deegan Ave NE",
    "sg:city":"Monticello",
    "sg:classifiers":[
        {
            "category":"Fast Food",
            "type":"Food & Drink"
        },
        {
            "category":"Restaurant",
            "type":"Food & Drink"
        }
    ],
    "sg:phone":"+1 763 295 6913",
    "sg:postcode":"55362",
    "sg:province":"MN",
    "sg:tags":[
        "mexican",
        "take"
    ],
    "sg:website":"http://www.tacojohns.com",
    "wof:name":"Taco John's",
    "wof:placetype":"venue"
},
  "geometry": {"coordinates":[-93.806476,45.288294],"type":"Point"}
}