{
  "type": "Feature",
  "properties": {
    "iso:country":"US",
    "sg:address":"10550 County Road 81",
    "sg:city":"Osseo",
    "sg:classifiers":[
        {
            "category":"Professional",
            "subcategory":"Computer Services",
            "type":"Services"
        }
    ],
    "sg:phone":"+1 763 315 1112",
    "sg:postcode":"55369",
    "sg:province":"MN",
    "sg:tags":[
        "repair"
    ],
    "wof:name":"Olympic Communications",
    "wof:placetype":"venue"
},
  "geometry": {"coordinates":[-93.4235,45.122898],"type":"Point"}
}