{
  "type": "Feature",
  "properties": {
    "addr:full":"1500 94th Ln NE Minneapolis MN 55449",
    "addr:housenumber":"1500",
    "addr:postcode":"55449",
    "addr:street":"94Th Ln Ne",
    "iso:country":"US",
    "sg:address":"1500 94th Ln NE",
    "sg:city":"Minneapolis",
    "sg:classifiers":[
        {
            "category":"Wholesale",
            "subcategory":"Hardware",
            "type":"Manufacturing & Wholesale Goods"
        }
    ],
    "sg:phone":"+1 952 887 3900",
    "sg:postcode":"55449",
    "sg:province":"MN",
    "sg:tags":[
        "dust",
        "collecting",
        "system"
    ],
    "wof:name":"Torit Products Donaldson Co",
    "wof:placetype":"venue"
},
  "geometry": {"coordinates":[-93.230412,45.141675],"type":"Point"}
}