{
  "type": "Feature",
  "properties": {
    "addr:full":"7180 Hwy 14 SE Rochester MN 55904",
    "addr:housenumber":"7180",
    "addr:postcode":"55904",
    "addr:street":"Hwy 14 Se",
    "iso:country":"US",
    "sg:address":"7180 Hwy 14 SE",
    "sg:city":"Rochester",
    "sg:classifiers":[
        {
            "category":"Autos & Motor Vehicles",
            "subcategory":"Motorcycle Sales",
            "type":"Retail Goods"
        }
    ],
    "sg:phone":"+1 507 288 9050",
    "sg:postcode":"55904",
    "sg:province":"MN",
    "sg:tags":[
        "scooter"
    ],
    "sg:website":"www.rochhd.com",
    "wof:name":"Rochester Harley-Davidson Inc",
    "wof:placetype":"venue"
},
  "geometry": {"coordinates":[-92.335239,44.002774],"type":"Point"}
}