{
  "type": "Feature",
  "properties": {
    "addr:full":"753 56th St Chandler MN 56122",
    "addr:housenumber":"753",
    "addr:postcode":"56122",
    "addr:street":"56Th St",
    "iso:country":"US",
    "sg:address":"753 56th St",
    "sg:city":"Chandler",
    "sg:classifiers":[
        {
            "category":"Freight",
            "type":"Transportation"
        }
    ],
    "sg:phone":"+1 507 677 2327",
    "sg:postcode":"56122",
    "sg:province":"MN",
    "sg:tags":[
        "building",
        "heavy",
        "rigging",
        "house",
        "contractor",
        "equipment",
        "moving",
        "mover"
    ],
    "wof:name":"Van Dyke Brothers Inc",
    "wof:placetype":"venue"
},
  "geometry": {"coordinates":[-95.91342899999999,43.928349],"type":"Point"}
}