{
  "type": "Feature",
  "properties": {
    "iso:country":"US",
    "sg:address":"2015 Jefferson Rd",
    "sg:city":"Northfield",
    "sg:classifiers":[
        {
            "category":"Building & Trades",
            "subcategory":"Construction",
            "type":"Services"
        }
    ],
    "sg:phone":"+1 507 645 4118",
    "sg:postcode":"55057",
    "sg:province":"MN",
    "sg:tags":[
        "home",
        "family",
        "contractor"
    ],
    "wof:name":"Jasnoch Construction Inc",
    "wof:placetype":"venue"
},
  "geometry": {"coordinates":[-93.18138500000001,44.438495],"type":"Point"}
}