{
  "type": "Feature",
  "properties": {
    "iso:country":"US",
    "sg:address":"6750 France Ave S",
    "sg:city":"Minneapolis",
    "sg:classifiers":[
        {
            "category":"Shopping",
            "subcategory":"Beauty & Cosmetics",
            "type":"Retail Goods"
        }
    ],
    "sg:phone":"+1 952 929 0600",
    "sg:postcode":"55435",
    "sg:province":"MN",
    "sg:tags":[
        "hair",
        "supply"
    ],
    "wof:name":"Sir Winston Hair Institute",
    "wof:placetype":"venue"
},
  "geometry": {"coordinates":[-93.329015,44.88269],"type":"Point"}
}