{
  "type": "Feature",
  "properties": {
    "iso:country":"US",
    "sg:address":"7209 W Shore Dr",
    "sg:city":"Minneapolis",
    "sg:classifiers":[
        {
            "category":"Structure",
            "subcategory":"Office Building",
            "type":"Public Place"
        }
    ],
    "sg:phone":"+1 612 760 8300",
    "sg:postcode":"55435",
    "sg:province":"MN",
    "sg:tags":[
        "park"
    ],
    "wof:name":"Mjl Properties Ii",
    "wof:placetype":"venue"
},
  "geometry": {"coordinates":[-93.343568,44.872784],"type":"Point"}
}