{
  "type": "Feature",
  "properties": {
    "iso:country":"US",
    "sg:address":"15 1st Ave S",
    "sg:city":"Buffalo",
    "sg:classifiers":[
        {
            "category":"Shopping",
            "subcategory":"Hobbies, Toys, & Games",
            "type":"Retail Goods"
        }
    ],
    "sg:phone":"+1 763 682 4959",
    "sg:postcode":"55313",
    "sg:province":"MN",
    "sg:tags":[
        "craft"
    ],
    "wof:name":"Scrap N' Chat",
    "wof:placetype":"venue"
},
  "geometry": {"coordinates":[-93.87488399999999,45.171891],"type":"Point"}
}