{
  "type": "Feature",
  "properties": {
    "iso:country":"US",
    "sg:address":"19685 State Hwy 7",
    "sg:city":"Excelsior",
    "sg:classifiers":[
        {
            "category":"Health Services",
            "subcategory":"Doctor",
            "type":"Services"
        }
    ],
    "sg:phone":"+1 952 473 4211",
    "sg:postcode":"55331",
    "sg:province":"MN",
    "sg:tags":[
        "medical"
    ],
    "wof:name":"Leonard F Parsons MD",
    "wof:placetype":"venue"
},
  "geometry": {"coordinates":[-93.528899,44.909096],"type":"Point"}
}