{
  "type": "Feature",
  "properties": {
    "iso:country":"US",
    "sg:address":"3153 Daisy Beach Rd",
    "sg:city":"Tower",
    "sg:classifiers":[
        {
            "category":"Professional",
            "subcategory":"Engineering",
            "type":"Services"
        }
    ],
    "sg:phone":"+1 218 753 1271",
    "sg:postcode":"55790",
    "sg:province":"MN",
    "sg:tags":[
        "engineer"
    ],
    "wof:name":"Simone Engineering Fcx",
    "wof:placetype":"venue"
},
  "geometry": {"coordinates":[-92.416935,47.859331],"type":"Point"}
}