{
  "type": "Feature",
  "properties": {
    "addr:full":"3631 Perry Ave N Minneapolis MN 55422",
    "addr:housenumber":"3631",
    "addr:postcode":"55422",
    "addr:street":"Perry Ave N",
    "iso:country":"US",
    "sg:address":"3631 Perry Ave N",
    "sg:city":"Minneapolis",
    "sg:classifiers":[
        {
            "category":"Communications",
            "subcategory":"Film & Video Production",
            "type":"Services"
        }
    ],
    "sg:phone":"+1 763 529 4609",
    "sg:postcode":"55422",
    "sg:province":"MN",
    "sg:tags":[
        "motion"
    ],
    "wof:name":"Lapinski Productions",
    "wof:placetype":"venue"
},
  "geometry": {"coordinates":[-93.34154700000001,45.021756],"type":"Point"}
}