{
  "type": "Feature",
  "properties": {
    "addr:full":"101 Lincoln Ave Milan MN 56262",
    "addr:housenumber":"101",
    "addr:postcode":"56262",
    "addr:street":"Lincoln Ave",
    "iso:country":"US",
    "sg:address":"101 Lincoln Ave",
    "sg:city":"Milan",
    "sg:classifiers":[
        {
            "category":"Organizations",
            "subcategory":"Community Association",
            "type":"Services"
        }
    ],
    "sg:phone":"+1 320 734 4600",
    "sg:postcode":"56262",
    "sg:province":"MN",
    "wof:name":"American Legion Club Post 359",
    "wof:placetype":"venue"
},
  "geometry": {"coordinates":[-95.910608,45.110988],"type":"Point"}
}