{
  "type": "Feature",
  "properties": {
    "iso:country":"US",
    "sg:address":"3111 Stone Ridge Ct",
    "sg:city":"Saint Paul",
    "sg:classifiers":[
        {
            "category":"Food & Beverages",
            "subcategory":"Groceries & Convenience Stores",
            "type":"Retail Goods"
        }
    ],
    "sg:phone":"+1 651 765 0647",
    "sg:postcode":"55109",
    "sg:province":"MN",
    "wof:name":"Finer Things LLC",
    "wof:placetype":"venue"
},
  "geometry": {"coordinates":[-93.06183299999999,45.03525],"type":"Point"}
}