{
  "type": "Feature",
  "properties": {
    "addr:full":"1183 73 1/2 Ave NE Minneapolis MN 55432",
    "addr:housenumber":"1183;1 / 2",
    "addr:postcode":"55432",
    "addr:street":"73;Ave Ne",
    "iso:country":"US",
    "sg:address":"1183 73 1/2 Ave NE",
    "sg:city":"Minneapolis",
    "sg:classifiers":[
        {
            "category":"Manufacturing",
            "subcategory":"Metals",
            "type":"Manufacturing & Wholesale Goods"
        }
    ],
    "sg:phone":"+1 763 781 0000",
    "sg:postcode":"55432",
    "sg:province":"MN",
    "sg:tags":[
        "metal-wholesale",
        "manufacturer"
    ],
    "wof:name":"Shiny Metals Inc",
    "wof:placetype":"venue"
},
  "geometry": {"coordinates":[-93.24139599999999,45.101135],"type":"Point"}
}