{
  "type": "Feature",
  "properties": {
    "addr:full":"4124 Roseway Rd Minneapolis MN 55409",
    "addr:housenumber":"4124",
    "addr:postcode":"55409",
    "addr:street":"Roseway Rd",
    "iso:country":"US",
    "sg:address":"4124 Roseway Rd",
    "sg:city":"Minneapolis",
    "sg:classifiers":[
        {
            "category":"Park",
            "type":"Public Place"
        }
    ],
    "sg:postcode":"55409",
    "sg:province":"MN",
    "sg:website":"www.minneapolisparks.org/default...",
    "wof:name":"Lyndale Park Rose Garden",
    "wof:placetype":"venue"
},
  "geometry": {"coordinates":[-93.293447,44.929489],"type":"Point"}
}