{
  "type": "Feature",
  "properties": {
    "addr:full":"3429 Co Rd 15 SW Willmar MN 56201",
    "addr:housenumber":"3429",
    "addr:postcode":"56201",
    "addr:street":"Co Rd 15 Sw",
    "iso:country":"US",
    "sg:address":"3429 Co Rd 15 SW",
    "sg:city":"Willmar",
    "sg:classifiers":[
        {
            "category":"Manufacturing",
            "subcategory":"Furniture",
            "type":"Manufacturing & Wholesale Goods"
        }
    ],
    "sg:phone":"+1 320 235 3406",
    "sg:postcode":"56201",
    "sg:province":"MN",
    "sg:tags":[
        "installs",
        "laminated",
        "mfg"
    ],
    "wof:name":"Countertops Plus",
    "wof:placetype":"venue"
},
  "geometry": {"coordinates":[-95.088173,45.101277],"type":"Point"}
}