{
  "type": "Feature",
  "properties": {
    "iso:country":"US",
    "sg:address":"1315 Hwy 25 N",
    "sg:city":"Buffalo",
    "sg:classifiers":[
        {
            "category":"Professional",
            "subcategory":"Accounting & Tax Preparation",
            "type":"Services"
        }
    ],
    "sg:phone":"+1 763 684 0072",
    "sg:postcode":"55313",
    "sg:province":"MN",
    "sg:tags":[
        "return",
        "filing"
    ],
    "wof:name":"H & R Block Tax Svc",
    "wof:placetype":"venue"
},
  "geometry": {"coordinates":[-93.875933,45.189429],"type":"Point"}
}