{
  "type": "Feature",
  "properties": {
    "addr:full":"24460 State Hwy 83 Waldorf MN 56091",
    "addr:housenumber":"24460",
    "addr:postcode":"56091",
    "addr:street":"State Hwy 83",
    "iso:country":"US",
    "sg:address":"24460 State Hwy 83",
    "sg:city":"Waldorf",
    "sg:phone":"+1 507 239 2377",
    "sg:postcode":"56091",
    "sg:province":"MN",
    "sg:tags":[
        "farm",
        "corn",
        "soybean"
    ],
    "wof:name":"Eldean Proehl",
    "wof:placetype":"venue"
},
  "geometry": {"coordinates":[-93.69751599999999,43.905969],"type":"Point"}
}