{
  "type": "Feature",
  "properties": {
    "addr:full":"3525 Vicksburg Ln N Ste 400 Minneapolis MN 55447",
    "addr:housenumber":"3525",
    "addr:postcode":"55447",
    "addr:street":"Vicksburg Ln N Ste 400",
    "iso:country":"US",
    "sg:address":"3525 Vicksburg Ln N Ste 400",
    "sg:city":"Minneapolis",
    "sg:classifiers":[
        {
            "category":"Wholesale",
            "subcategory":"Jewelry",
            "type":"Manufacturing & Wholesale Goods"
        },
        {
            "category":"Shopping",
            "subcategory":"Jewelry",
            "type":"Retail Goods"
        },
        {
            "category":"Manufacturing",
            "subcategory":"Jewelry",
            "type":"Manufacturing & Wholesale Goods"
        },
        {
            "category":"Retail",
            "subcategory":"Repair Shop",
            "type":"Services"
        }
    ],
    "sg:phone":"+1 763 537 3144",
    "sg:postcode":"55447",
    "sg:province":"MN",
    "sg:tags":[
        "repairing",
        "designer",
        "supply",
        "watch",
        "jeweler",
        "finding"
    ],
    "sg:website":"http://www.TesaJewellers.com",
    "wof:name":"Tesa Jewellers",
    "wof:placetype":"venue"
},
  "geometry": {"coordinates":[-93.48188500000001,45.020916],"type":"Point"}
}