{
  "type": "Feature",
  "properties": {
    "addr:full":"970 Cutoff Rd Grand Marais MN 55604",
    "addr:housenumber":"970",
    "addr:postcode":"55604",
    "addr:street":"Cutoff Rd",
    "iso:country":"US",
    "sg:address":"970 Cutoff Rd",
    "sg:city":"Grand Marais",
    "sg:classifiers":[
        {
            "category":"Professional",
            "type":"Services"
        }
    ],
    "sg:phone":"+1 218 387 1333",
    "sg:postcode":"55604",
    "sg:province":"MN",
    "wof:name":"Johnson Rifle Co",
    "wof:placetype":"venue"
},
  "geometry": {"coordinates":[-90.326446,47.784323],"type":"Point"}
}