{
  "type": "Feature",
  "properties": {
    "iso:country":"US",
    "sg:address":"7651 Central Ave NE",
    "sg:city":"Minneapolis",
    "sg:classifiers":[
        {
            "category":"Retail",
            "subcategory":"Repair Shop",
            "type":"Services"
        }
    ],
    "sg:phone":"+1 763 862 8175",
    "sg:postcode":"55432",
    "sg:province":"MN",
    "wof:name":"Crown Drain Cleaning",
    "wof:placetype":"venue"
},
  "geometry": {"coordinates":[-93.23804,45.106642],"type":"Point"}
}