{
  "type": "Feature",
  "properties": {
    "iso:country":"US",
    "sg:address":"21911 Co Hwy 37",
    "sg:city":"Detroit Lakes",
    "sg:classifiers":[
        {
            "category":"Professional",
            "type":"Services"
        }
    ],
    "sg:phone":"+1 218 844 5209",
    "sg:postcode":"56501",
    "sg:province":"MN",
    "wof:name":"Wells Brothers Inc",
    "wof:placetype":"venue"
},
  "geometry": {"coordinates":[-95.526312,46.889074],"type":"Point"}
}