{
  "type": "Feature",
  "properties": {
    "addr:full":"1758 Ireland Ave SW Howard Lake MN 55349",
    "addr:housenumber":"1758",
    "addr:postcode":"55349",
    "addr:street":"Ireland Ave Sw Howard Lake",
    "iso:country":"US",
    "sg:address":"1758 Ireland Ave SW",
    "sg:city":"Howard Lake",
    "sg:classifiers":[
        {
            "category":"Farming",
            "subcategory":"Farm",
            "type":"Manufacturing & Wholesale Goods"
        }
    ],
    "sg:phone":"+1 320 543 2643",
    "sg:postcode":"55349",
    "sg:province":"MN",
    "sg:tags":[
        "real",
        "property",
        "crop",
        "lessor",
        "general"
    ],
    "wof:name":"Gary Gruenhagen",
    "wof:placetype":"venue"
},
  "geometry": {"coordinates":[-94.06316200000001,45.126783],"type":"Point"}
}