{
  "type": "Feature",
  "properties": {
    "addr:full":"108 Stratford St W Avon MN 56310",
    "addr:housenumber":"108",
    "addr:postcode":"56310",
    "addr:street":"Stratford St W",
    "iso:country":"US",
    "sg:address":"108 Stratford St W",
    "sg:city":"Avon",
    "sg:classifiers":[
        {
            "category":"Health Services",
            "subcategory":"Doctor",
            "type":"Services"
        }
    ],
    "sg:phone":"+1 320 356 7602",
    "sg:postcode":"56310",
    "sg:province":"MN",
    "sg:tags":[
        "medical"
    ],
    "wof:name":"Avon Medical Clinic",
    "wof:placetype":"venue"
},
  "geometry": {"coordinates":[-94.451554,45.609174],"type":"Point"}
}