{
  "type": "Feature",
  "properties": {
    "addr:full":"38965 206th St Green Isle MN 55338",
    "addr:housenumber":"38965",
    "addr:postcode":"55338",
    "addr:street":"206Th St;Isle",
    "iso:country":"US",
    "sg:address":"38965 206th St",
    "sg:city":"Green Isle",
    "sg:classifiers":[
        {
            "category":"Retail",
            "subcategory":"Auto Repair",
            "type":"Services"
        }
    ],
    "sg:phone":"+1 507 326 3521",
    "sg:postcode":"55338",
    "sg:province":"MN",
    "sg:tags":[
        "automotive",
        "general"
    ],
    "wof:name":"Fries Repair",
    "wof:placetype":"venue"
},
  "geometry": {"coordinates":[-94.054576,44.651319],"type":"Point"}
}