{
  "type": "Feature",
  "properties": {
    "addr:full":"4710 Buck Lake Rd Watertown MN 55388",
    "addr:housenumber":"4710",
    "addr:postcode":"55388",
    "addr:street":"Buck Lake Rd",
    "iso:country":"US",
    "sg:address":"4710 Buck Lake Rd",
    "sg:city":"Watertown",
    "sg:classifiers":[
        {
            "category":"Food & Beverages",
            "subcategory":"Groceries & Convenience Stores",
            "type":"Retail Goods"
        }
    ],
    "sg:phone":"+1 952 446 1639",
    "sg:postcode":"55388",
    "sg:province":"MN",
    "wof:name":"Watkins Products",
    "wof:placetype":"venue"
},
  "geometry": {"coordinates":[-93.77806200000001,44.913557],"type":"Point"}
}