{
  "type": "Feature",
  "properties": {
    "addr:full":"300 6th St SE Minneapolis MN 55414",
    "addr:housenumber":"300",
    "addr:postcode":"55414",
    "addr:street":"6Th St Se",
    "iso:country":"US",
    "sg:address":"300 6th St SE",
    "sg:city":"Minneapolis",
    "sg:classifiers":[
        {
            "category":"Government",
            "subcategory":"Office",
            "type":"Public Place"
        }
    ],
    "sg:phone":"+1 612 348 3170",
    "sg:postcode":"55414",
    "sg:province":"MN",
    "sg:tags":[
        "general"
    ],
    "wof:name":"District Court Records Center",
    "wof:placetype":"venue"
},
  "geometry": {"coordinates":[-93.248306,44.988087],"type":"Point"}
}