{
  "type": "Feature",
  "properties": {
    "iso:country":"US",
    "sg:address":"2735 79th Ct E",
    "sg:city":"Inver Grove Heights",
    "sg:classifiers":[
        {
            "category":"Organizations",
            "subcategory":"Religious Organization",
            "type":"Services"
        }
    ],
    "sg:phone":"+1 651 455 3761",
    "sg:postcode":"55076",
    "sg:province":"MN",
    "wof:name":"Spirit Healing Power",
    "wof:placetype":"venue"
},
  "geometry": {"coordinates":[-93.05130800000001,44.836199],"type":"Point"}
}