{
  "type": "Feature",
  "properties": {
    "iso:country":"US",
    "sg:address":"423 2nd Ave NE",
    "sg:city":"Staples",
    "sg:classifiers":[
        {
            "category":"Bars & Pubs",
            "type":"Food & Drink"
        }
    ],
    "sg:phone":"+1 218 894 9979",
    "sg:postcode":"56479",
    "sg:province":"MN",
    "sg:tags":[
        "drinking"
    ],
    "wof:name":"Lefty's Bar",
    "wof:placetype":"venue"
},
  "geometry": {"coordinates":[-94.794617,46.355724],"type":"Point"}
}