{
  "type": "Feature",
  "properties": {
    "addr:full":"105 N Mill St Fertile MN 56540",
    "addr:housenumber":"105",
    "addr:postcode":"56540",
    "addr:street":"N Mill St",
    "iso:country":"US",
    "sg:address":"105 N Mill St",
    "sg:city":"Fertile",
    "sg:classifiers":[
        {
            "category":"Professional",
            "subcategory":"Lawyer & Legal Services",
            "type":"Services"
        }
    ],
    "sg:phone":"+1 218 945 6913",
    "sg:postcode":"56540",
    "sg:province":"MN",
    "sg:tags":[
        "attorney"
    ],
    "wof:name":"Raymond J German LTD",
    "wof:placetype":"venue"
},
  "geometry": {"coordinates":[-96.28062,47.535062],"type":"Point"}
}