{
  "type": "Feature",
  "properties": {
    "iso:country":"US",
    "sg:address":"20315 Iberia Ave",
    "sg:city":"Lakeville",
    "sg:classifiers":[
        {
            "category":"Retail",
            "subcategory":"Auto Repair",
            "type":"Services"
        }
    ],
    "sg:phone":"+1 952 469 3266",
    "sg:postcode":"55044",
    "sg:province":"MN",
    "sg:tags":[
        "general"
    ],
    "wof:name":"Hometown Auto Service",
    "wof:placetype":"venue"
},
  "geometry": {"coordinates":[-93.24789199999999,44.655552],"type":"Point"}
}