{
  "type": "Feature",
  "properties": {
    "iso:country":"US",
    "sg:address":"1211 W Pierce Butler Rte",
    "sg:city":"St Paul",
    "sg:classifiers":[
        {
            "category":"Health Services",
            "subcategory":"Chiropractor",
            "type":"Services"
        }
    ],
    "sg:phone":"+1 651 645 8838",
    "sg:postcode":"55104",
    "sg:province":"MN",
    "wof:name":"Envision Chiropractic Pa",
    "wof:placetype":"venue"
},
  "geometry": {"coordinates":[-93.150828,44.966986],"type":"Point"}
}