{
  "type": "Feature",
  "properties": {
    "iso:country":"US",
    "sg:address":"3301 NW 21st Ave",
    "sg:city":"Owatonna",
    "sg:classifiers":[
        {
            "category":"Wholesale",
            "subcategory":"Farm Supplies",
            "type":"Manufacturing & Wholesale Goods"
        }
    ],
    "sg:phone":"+1 507 451 6706",
    "sg:postcode":"55060",
    "sg:province":"MN",
    "wof:name":"Central Co-Op",
    "wof:placetype":"venue"
},
  "geometry": {"coordinates":[-93.239932,44.120873],"type":"Point"}
}