{
  "type": "Feature",
  "properties": {
    "addr:full":"9100 10th Ave N Ste 200 Minneapolis MN 55427",
    "addr:housenumber":"9100",
    "addr:postcode":"55427",
    "addr:street":"10Th Ave N Ste 200",
    "iso:country":"US",
    "sg:address":"9100 10th Ave N Ste 200",
    "sg:city":"Minneapolis",
    "sg:classifiers":[
        {
            "category":"Home & Garden",
            "subcategory":"Building Materials",
            "type":"Retail Goods"
        }
    ],
    "sg:phone":"+1 763 417 0040",
    "sg:postcode":"55427",
    "sg:province":"MN",
    "sg:tags":[
        "marble-natural"
    ],
    "wof:name":"Granite Specialists",
    "wof:placetype":"venue"
},
  "geometry": {"coordinates":[-93.393869,44.989021],"type":"Point"}
}