{
  "type": "Feature",
  "properties": {
    "addr:full":"26 7th Ave N St Cloud MN 56303",
    "addr:housenumber":"26",
    "addr:postcode":"56303",
    "addr:street":"7Th Ave N",
    "iso:country":"US",
    "sg:address":"26 7th Ave N",
    "sg:city":"St Cloud",
    "sg:classifiers":[
        {
            "category":"Insurance",
            "subcategory":"Insurance Agent",
            "type":"Services"
        }
    ],
    "sg:phone":"+1 320 654 0408",
    "sg:postcode":"56303",
    "sg:province":"MN",
    "sg:tags":[
        "adjuster"
    ],
    "wof:name":"Cardinal Adjusting Svc Inc",
    "wof:placetype":"venue"
},
  "geometry": {"coordinates":[-94.160713,45.560514],"type":"Point"}
}