{
  "type": "Feature",
  "properties": {
    "addr:full":"5491 Dunaiski Rd Duluth MN 55811",
    "addr:housenumber":"5491",
    "addr:postcode":"55811",
    "addr:street":"Dunaiski Rd",
    "iso:country":"US",
    "sg:address":"5491 Dunaiski Rd",
    "sg:city":"Duluth",
    "sg:classifiers":[
        {
            "category":"Freight",
            "type":"Transportation"
        }
    ],
    "sg:phone":"+1 218 729 9228",
    "sg:postcode":"55811",
    "sg:province":"MN",
    "sg:tags":[
        "operator",
        "local",
        "trucking"
    ],
    "wof:name":"Olson Stanley L",
    "wof:placetype":"venue"
},
  "geometry": {"coordinates":[-92.258669,46.860086],"type":"Point"}
}