{
  "type": "Feature",
  "properties": {
    "addr:full":"20602 120th St Hutchinson MN 55350",
    "addr:housenumber":"20602",
    "addr:postcode":"55350",
    "addr:street":"120Th St",
    "iso:country":"US",
    "sg:address":"20602 120th St",
    "sg:city":"Hutchinson",
    "sg:phone":"+1 320 587 9103",
    "sg:postcode":"55350",
    "sg:province":"MN",
    "sg:tags":[
        "farm",
        "corn",
        "soybean"
    ],
    "wof:name":"Lee Henke",
    "wof:placetype":"venue"
},
  "geometry": {"coordinates":[-94.408698,44.790495],"type":"Point"}
}