{
  "type": "Feature",
  "properties": {
    "addr:full":"307 Iowa Ave S Eitzen MN 55931",
    "addr:housenumber":"307",
    "addr:postcode":"55931",
    "addr:street":"Iowa Ave S Eitzen",
    "iso:country":"US",
    "sg:address":"307 Iowa Ave S",
    "sg:city":"Eitzen",
    "sg:classifiers":[
        {
            "category":"Organizations",
            "subcategory":"Religious Organization",
            "type":"Services"
        }
    ],
    "sg:phone":"+1 507 495 3158",
    "sg:postcode":"55931",
    "sg:province":"MN",
    "sg:tags":[
        "churches-lutheran",
        "church"
    ],
    "wof:name":"Zion Lutheran Church",
    "wof:placetype":"venue"
},
  "geometry": {"coordinates":[-91.464038,43.505218],"type":"Point"}
}