{
  "type": "Feature",
  "properties": {
    "addr:full":"1301 18th Ave NW Austin MN 55912",
    "addr:housenumber":"1301",
    "addr:postcode":"55912",
    "addr:street":"18Th Ave Nw",
    "iso:country":"US",
    "sg:address":"1301 18th Ave NW",
    "sg:city":"Austin",
    "sg:classifiers":[
        {
            "category":"Personal",
            "subcategory":"Beauty Salon",
            "type":"Services"
        }
    ],
    "sg:phone":"+1 507 433 6464",
    "sg:postcode":"55912",
    "sg:province":"MN",
    "wof:name":"Regis Salons",
    "wof:placetype":"venue"
},
  "geometry": {"coordinates":[-92.990126,43.684726],"type":"Point"}
}