{
  "type": "Feature",
  "properties": {
    "addr:full":"70 E 4th St Winona MN 55987",
    "addr:housenumber":"70",
    "addr:postcode":"55987",
    "addr:street":"E 4Th St",
    "iso:country":"US",
    "sg:address":"70 E 4th St",
    "sg:city":"Winona",
    "sg:classifiers":[
        {
            "category":"Health Services",
            "subcategory":"Dentist",
            "type":"Services"
        }
    ],
    "sg:phone":"+1 507 454 2020",
    "sg:postcode":"55987",
    "sg:province":"MN",
    "wof:name":"Morgan Paul DDS",
    "wof:placetype":"venue"
},
  "geometry": {"coordinates":[-91.636072,44.051137],"type":"Point"}
}