{
  "type": "Feature",
  "properties": {
    "addr:full":"15629 Patterson Rd Brainerd MN 56401",
    "addr:housenumber":"15629",
    "addr:postcode":"56401",
    "addr:street":"Patterson Rd",
    "iso:country":"US",
    "sg:address":"15629 Patterson Rd",
    "sg:city":"Brainerd",
    "sg:classifiers":[
        {
            "category":"Banks & Credit Unions",
            "subcategory":"Financial Services",
            "type":"Services"
        }
    ],
    "sg:phone":"+1 218 828 1493",
    "sg:postcode":"56401",
    "sg:province":"MN",
    "sg:tags":[
        "trust",
        "investment",
        "real estate"
    ],
    "wof:name":"Tru North Homes Inc",
    "wof:placetype":"venue"
},
  "geometry": {"coordinates":[-94.295728,46.380832],"type":"Point"}
}