{
  "type": "Feature",
  "properties": {
    "addr:full":"49480 Azara Ave W Stanchfield MN 55080",
    "addr:postcode":"49480;55080",
    "addr:street":"Azara Ave W Stanchfield",
    "iso:country":"US",
    "sg:address":"49480 Azara Ave W",
    "sg:city":"Stanchfield",
    "sg:classifiers":[
        {
            "category":"Farming",
            "subcategory":"Livestock Farm",
            "type":"Manufacturing & Wholesale Goods"
        }
    ],
    "sg:phone":"+1 320 396 2003",
    "sg:postcode":"55080",
    "sg:province":"MN",
    "sg:tags":[
        "beef",
        "feedlot",
        "cattle"
    ],
    "wof:name":"Lonnie Eklund",
    "wof:placetype":"venue"
},
  "geometry": {"coordinates":[-93.119663,45.664528],"type":"Point"}
}