{
  "type": "Feature",
  "properties": {
    "addr:full":"308 Walnut St SW Sleepy Eye MN 56085",
    "addr:housenumber":"308",
    "addr:postcode":"56085",
    "addr:street":"Walnut St Sw Sleepy",
    "iso:country":"US",
    "sg:address":"308 Walnut St SW",
    "sg:city":"Sleepy Eye",
    "sg:classifiers":[
        {
            "category":"Freight",
            "type":"Transportation"
        }
    ],
    "sg:phone":"+1 507 794 6842",
    "sg:postcode":"56085",
    "sg:province":"MN",
    "sg:tags":[
        "operator",
        "local",
        "trucking"
    ],
    "wof:name":"Schroepfer Trucking",
    "wof:placetype":"venue"
},
  "geometry": {"coordinates":[-94.727225,44.296293],"type":"Point"}
}