{
  "type": "Feature",
  "properties": {
    "addr:full":"3603 Sunwood Trl St Paul MN 55123",
    "addr:housenumber":"3603",
    "addr:postcode":"55123",
    "addr:street":"Sunwood Trl",
    "iso:country":"US",
    "sg:address":"3603 Sunwood Trl",
    "sg:city":"St Paul",
    "sg:classifiers":[
        {
            "category":"Professional",
            "type":"Services"
        }
    ],
    "sg:phone":"+1 651 686 5227",
    "sg:postcode":"55123",
    "sg:province":"MN",
    "sg:tags":[
        "establishment"
    ],
    "wof:name":"Professional Project Partners",
    "wof:placetype":"venue"
},
  "geometry": {"coordinates":[-93.134013,44.82544],"type":"Point"}
}