{
  "type": "Feature",
  "properties": {
    "iso:country":"US",
    "sg:address":"1028 N Riverfront Dr",
    "sg:city":"Mankato",
    "sg:classifiers":[
        {
            "category":"Organizations",
            "subcategory":"Non-profit Organization",
            "type":"Services"
        }
    ],
    "sg:phone":"+1 507 345 3568",
    "sg:postcode":"56001",
    "sg:province":"MN",
    "wof:name":"Elks Lodge",
    "wof:placetype":"venue"
},
  "geometry": {"coordinates":[-93.99393999999999,44.176592],"type":"Point"}
}