{
  "type": "Feature",
  "properties": {
    "iso:country":"US",
    "sg:address":"4201 Parklawn Ave",
    "sg:city":"Minneapolis",
    "sg:classifiers":[
        {
            "category":"Retail",
            "subcategory":"Auto Repair",
            "type":"Services"
        }
    ],
    "sg:phone":"+1 612 579 3368",
    "sg:postcode":"55435",
    "sg:province":"MN",
    "sg:tags":[
        "body"
    ],
    "wof:name":"Paintless Dent Repair",
    "wof:placetype":"venue"
},
  "geometry": {"coordinates":[-93.335971,44.866634],"type":"Point"}
}