{
  "type": "Feature",
  "properties": {
    "addr:full":"1826 Northwestern Ave S Stillwater MN 55082",
    "addr:housenumber":"1826",
    "addr:postcode":"55082",
    "addr:street":"Northwestern Ave S",
    "iso:country":"US",
    "sg:address":"1826 Northwestern Ave S",
    "sg:city":"Stillwater",
    "sg:classifiers":[
        {
            "category":"Sports & Exercise",
            "subcategory":"Gym",
            "type":"Entertainment"
        }
    ],
    "sg:phone":"+1 651 439 7611",
    "sg:postcode":"55082",
    "sg:province":"MN",
    "sg:tags":[
        "gymnasium"
    ],
    "sg:website":"http://www.rivervalleyathleticclub.com",
    "wof:name":"River Valley Athletic Club",
    "wof:placetype":"venue"
},
  "geometry": {"coordinates":[-92.828159,45.039515],"type":"Point"}
}