{
  "type": "Feature",
  "properties": {
    "addr:full":"6256 Hill Rd Tower MN 55790",
    "addr:housenumber":"6256",
    "addr:postcode":"55790",
    "addr:street":"Hill Rd",
    "iso:country":"US",
    "sg:address":"6256 Hill Rd",
    "sg:city":"Tower",
    "sg:classifiers":[
        {
            "category":"Retail",
            "subcategory":"Repair Shop",
            "type":"Services"
        }
    ],
    "sg:phone":"+1 218 741 7467",
    "sg:postcode":"55790",
    "sg:province":"MN",
    "sg:tags":[
        "welding"
    ],
    "wof:name":"Anspaugh Portable Welding",
    "wof:placetype":"venue"
},
  "geometry": {"coordinates":[-92.346594,47.736587],"type":"Point"}
}