{
  "type": "Feature",
  "properties": {
    "addr:full":"8096 67th St NW Maple Lake MN 55358",
    "addr:housenumber":"8096",
    "addr:postcode":"55358",
    "addr:street":"67Th St Nw",
    "iso:country":"US",
    "sg:address":"8096 67th St NW",
    "sg:city":"Maple Lake",
    "sg:phone":"+1 320 963 3897",
    "sg:postcode":"55358",
    "sg:province":"MN",
    "sg:tags":[
        "farming",
        "crop"
    ],
    "wof:name":"Kapseg Inc",
    "wof:placetype":"venue"
},
  "geometry": {"coordinates":[-94.056997,45.250938],"type":"Point"}
}