{
  "type": "Feature",
  "properties": {
    "iso:country":"US",
    "sg:address":"1300 Nicollet Ave",
    "sg:city":"Minneapolis",
    "sg:classifiers":[
        {
            "category":"Communications",
            "type":"Services"
        }
    ],
    "sg:phone":"+1 612 752 5500",
    "sg:postcode":"55403",
    "sg:province":"MN",
    "sg:tags":[
        "web",
        "design"
    ],
    "wof:name":"Imaginet",
    "wof:placetype":"venue"
},
  "geometry": {"coordinates":[-93.277199,44.9711],"type":"Point"}
}