{
  "type": "Feature",
  "properties": {
    "addr:full":"80773 2nd Ave Glenville MN 56036",
    "addr:housenumber":"80773",
    "addr:postcode":"56036",
    "addr:street":"2Nd Ave",
    "iso:country":"US",
    "sg:address":"80773 2nd Ave",
    "sg:city":"Glenville",
    "sg:classifiers":[
        {
            "category":"Retail",
            "subcategory":"Auto Repair",
            "type":"Services"
        }
    ],
    "sg:phone":"+1 507 448 3607",
    "sg:postcode":"56036",
    "sg:province":"MN",
    "wof:name":"Denny's Repair",
    "wof:placetype":"venue"
},
  "geometry": {"coordinates":[-93.253395,43.512886],"type":"Point"}
}