{
  "type": "Feature",
  "properties": {
    "iso:country":"US",
    "sg:address":"10040 Nord Rd",
    "sg:city":"Minneapolis",
    "sg:classifiers":[
        {
            "category":"Banks & Credit Unions",
            "subcategory":"Investment Brokerage",
            "type":"Services"
        }
    ],
    "sg:phone":"+1 952 831 8682",
    "sg:postcode":"55437",
    "sg:province":"MN",
    "sg:tags":[
        "advisory"
    ],
    "wof:name":"Walter Broughton",
    "wof:placetype":"venue"
},
  "geometry": {"coordinates":[-93.344848,44.821657],"type":"Point"}
}