{
  "type": "Feature",
  "properties": {
    "addr:full":"956 Mankato Ave Winona MN 55987",
    "addr:housenumber":"956",
    "addr:postcode":"55987",
    "addr:street":"Mankato Ave",
    "iso:country":"US",
    "sg:address":"956 Mankato Ave",
    "sg:city":"Winona",
    "sg:classifiers":[
        {
            "category":"Travel",
            "subcategory":"Hotels & Motels",
            "type":"Entertainment"
        }
    ],
    "sg:phone":"+1 507 454 4390",
    "sg:postcode":"55987",
    "sg:province":"MN",
    "sg:tags":[
        "lounge",
        "cocktail"
    ],
    "sg:website":"www.choicehotels.com",
    "wof:name":"Quality Inn",
    "wof:placetype":"venue"
},
  "geometry": {"coordinates":[-91.622472,44.031269],"type":"Point"}
}