{
  "type": "Feature",
  "properties": {
    "iso:country":"US",
    "sg:address":"3576 Sibley Memorial Hwy",
    "sg:city":"Eagan",
    "sg:classifiers":[
        {
            "category":"Professional",
            "type":"Services"
        }
    ],
    "sg:phone":"+1 651 452 5908",
    "sg:postcode":"55121",
    "sg:province":"MN",
    "sg:tags":[
        "establishment"
    ],
    "wof:name":"Nwb",
    "wof:placetype":"venue"
},
  "geometry": {"coordinates":[-93.19770200000001,44.827936],"type":"Point"}
}