{
  "type": "Feature",
  "properties": {
    "addr:full":"528 Hennepin Ave Minneapolis MN 55403",
    "addr:housenumber":"528",
    "addr:postcode":"55403",
    "addr:street":"Hennepin Ave",
    "iso:country":"US",
    "sg:address":"528 Hennepin Ave",
    "sg:city":"Minneapolis",
    "sg:classifiers":[
        {
            "category":"Arts & Performance",
            "subcategory":"Theater",
            "type":"Entertainment"
        }
    ],
    "sg:phone":"+1 612 339 4944",
    "sg:postcode":"55403",
    "sg:province":"MN",
    "sg:tags":[
        "theatre"
    ],
    "sg:website":"www.illusiontheater.org",
    "wof:name":"Illusion Theater & School Inc",
    "wof:placetype":"venue"
},
  "geometry": {"coordinates":[-93.273247,44.979089],"type":"Point"}
}