{
  "type": "Feature",
  "properties": {
    "iso:country":"US",
    "sg:address":"1207 Vermillion St",
    "sg:city":"Hastings",
    "sg:classifiers":[
        {
            "category":"Shopping",
            "subcategory":"Books",
            "type":"Retail Goods"
        }
    ],
    "sg:phone":"+1 651 480 2232",
    "sg:postcode":"55033",
    "sg:province":"MN",
    "wof:name":"MVP Sports Cards & Comics",
    "wof:placetype":"venue"
},
  "geometry": {"coordinates":[-92.852324,44.732343],"type":"Point"}
}