{
  "type": "Feature",
  "properties": {
    "addr:full":"1725 Meadowview Rd Saint Paul MN 55121",
    "addr:housenumber":"1725",
    "addr:postcode":"55121",
    "addr:street":"Meadowview Rd",
    "iso:country":"US",
    "sg:address":"1725 Meadowview Rd",
    "sg:city":"Saint Paul",
    "sg:classifiers":[
        {
            "category":"Utilities",
            "subcategory":"Refuse",
            "type":"Services"
        }
    ],
    "sg:phone":"+1 651 457 7497",
    "sg:postcode":"55121",
    "sg:province":"MN",
    "sg:tags":[
        "a",
        "as",
        "trash",
        "pickup",
        "operates"
    ],
    "wof:name":"Nitti Sanitation Inc",
    "wof:placetype":"venue"
},
  "geometry": {"coordinates":[-93.189224,44.844352],"type":"Point"}
}