{
  "type": "Feature",
  "properties": {
    "addr:full":"16862 Iredale Path Lakeville MN 55044",
    "addr:housenumber":"16862",
    "addr:postcode":"55044",
    "addr:street":"Iredale Path",
    "iso:country":"US",
    "sg:address":"16862 Iredale Path",
    "sg:city":"Lakeville",
    "sg:classifiers":[
        {
            "category":"Professional",
            "subcategory":"Management & Consulting",
            "type":"Services"
        }
    ],
    "sg:phone":"+1 952 435 0866",
    "sg:postcode":"55044",
    "sg:province":"MN",
    "wof:name":"Keeler & Assoc",
    "wof:placetype":"venue"
},
  "geometry": {"coordinates":[-93.259353,44.705162],"type":"Point"}
}