{
  "type": "Feature",
  "properties": {
    "iso:country":"US",
    "sg:address":"6540 Lucia Ln NE",
    "sg:city":"Minneapolis",
    "sg:classifiers":[
        {
            "category":"Building & Trades",
            "subcategory":"Electrical",
            "type":"Services"
        }
    ],
    "sg:phone":"+1 763 232 1719",
    "sg:postcode":"55432",
    "sg:province":"MN",
    "sg:tags":[
        "electrical",
        "contractor"
    ],
    "wof:name":"Red Horse Inc",
    "wof:placetype":"venue"
},
  "geometry": {"coordinates":[-93.241955,45.089543],"type":"Point"}
}