{
  "type": "Feature",
  "properties": {
    "iso:country":"US",
    "sg:address":"26884 153rd St",
    "sg:city":"Pierz",
    "sg:classifiers":[
        {
            "category":"Building & Trades",
            "subcategory":"Landscaping Services",
            "type":"Services"
        }
    ],
    "sg:phone":"+1 320 468 2399",
    "sg:postcode":"56364",
    "sg:province":"MN",
    "sg:tags":[
        "tree"
    ],
    "wof:name":"4 Seasons Tree Care Inc",
    "wof:placetype":"venue"
},
  "geometry": {"coordinates":[-94.095821,45.983341],"type":"Point"}
}