{
  "type": "Feature",
  "properties": {
    "addr:full":"1706 Lor Ray Dr North Mankato MN 56003",
    "addr:housenumber":"1706",
    "addr:postcode":"56003",
    "addr:street":"Lor Ray Dr North",
    "iso:country":"US",
    "sg:address":"1706 Lor Ray Dr",
    "sg:city":"North Mankato",
    "sg:classifiers":[
        {
            "category":"Health Services",
            "subcategory":"Chiropractor",
            "type":"Services"
        }
    ],
    "sg:phone":"+1 507 385 1015",
    "sg:postcode":"56003",
    "sg:province":"MN",
    "wof:name":"Schugel Family Chiropractic",
    "wof:placetype":"venue"
},
  "geometry": {"coordinates":[-94.033339,44.177603],"type":"Point"}
}