{
  "type": "Feature",
  "properties": {
    "iso:country":"US",
    "sg:address":"14949 113th St",
    "sg:city":"Little Falls",
    "sg:classifiers":[
        {
            "category":"Retail",
            "subcategory":"Auto Repair",
            "type":"Services"
        }
    ],
    "sg:phone":"+1 320 632 0944",
    "sg:postcode":"56345",
    "sg:province":"MN",
    "sg:tags":[
        "general"
    ],
    "wof:name":"Brains Auto Repair",
    "wof:placetype":"venue"
},
  "geometry": {"coordinates":[-94.347093,45.925794],"type":"Point"}
}