{
  "type": "Feature",
  "properties": {
    "addr:full":"16115 Main Ave SE Prior Lake MN 55372",
    "addr:housenumber":"16115",
    "addr:postcode":"55372",
    "addr:street":"Main Ave Se",
    "iso:country":"US",
    "sg:address":"16115 Main Ave SE",
    "sg:city":"Prior Lake",
    "sg:classifiers":[
        {
            "category":"Retail",
            "subcategory":"Auto Repair",
            "type":"Services"
        }
    ],
    "sg:phone":"+1 952 447 4275",
    "sg:postcode":"55372",
    "sg:province":"MN",
    "sg:tags":[
        "repairing",
        "automobile"
    ],
    "wof:name":"Prior Lake Motors",
    "wof:placetype":"venue"
},
  "geometry": {"coordinates":[-93.420714,44.717287],"type":"Point"}
}