{
  "type": "Feature",
  "properties": {
    "addr:full":"4250 113th Ave NE Spicer MN 56288",
    "addr:housenumber":"4250",
    "addr:postcode":"56288",
    "addr:street":"113Th Ave Ne",
    "iso:country":"US",
    "sg:address":"4250 113th Ave NE",
    "sg:city":"Spicer",
    "sg:classifiers":[
        {
            "category":"Autos & Motor Vehicles",
            "subcategory":"Automobile Sales",
            "type":"Retail Goods"
        }
    ],
    "sg:phone":"+1 320 796 5940",
    "sg:postcode":"56288",
    "sg:province":"MN",
    "sg:tags":[
        "new",
        "car"
    ],
    "wof:name":"Dean Fernelius",
    "wof:placetype":"venue"
},
  "geometry": {"coordinates":[-94.98366300000001,45.233159],"type":"Point"}
}