{
  "type": "Feature",
  "properties": {
    "addr:full":"112 E Hennepin Ave Minneapolis MN 55414",
    "addr:housenumber":"112",
    "addr:postcode":"55414",
    "addr:street":"E Hennepin Ave",
    "iso:country":"US",
    "sg:address":"112 E Hennepin Ave",
    "sg:city":"Minneapolis",
    "sg:classifiers":[
        {
            "category":"Professional",
            "type":"Services"
        }
    ],
    "sg:phone":"+1 612 377 6464",
    "sg:postcode":"55414",
    "sg:province":"MN",
    "wof:name":"River Jakes Inc",
    "wof:placetype":"venue"
},
  "geometry": {"coordinates":[-93.25778800000001,44.987409],"type":"Point"}
}