{
  "type": "Feature",
  "properties": {
    "addr:full":"4307 22nd Ave NW Rochester MN 55901",
    "addr:housenumber":"4307",
    "addr:postcode":"55901",
    "addr:street":"22Nd Ave Nw",
    "iso:country":"US",
    "sg:address":"4307 22nd Ave NW",
    "sg:city":"Rochester",
    "sg:classifiers":[
        {
            "category":"Personal",
            "subcategory":"Hair Removal",
            "type":"Services"
        }
    ],
    "sg:phone":"+1 507 536 4626",
    "sg:postcode":"55901",
    "sg:province":"MN",
    "wof:name":"Debt Freedom Clinic",
    "wof:placetype":"venue"
},
  "geometry": {"coordinates":[-92.49731300000001,44.068635],"type":"Point"}
}