{
  "type": "Feature",
  "properties": {
    "iso:country":"US",
    "sg:address":"4324 31st Ave S",
    "sg:city":"Minneapolis",
    "sg:classifiers":[
        {
            "category":"Communications",
            "subcategory":"Film & Video Production",
            "type":"Services"
        }
    ],
    "sg:phone":"+1 612 721 6801",
    "sg:postcode":"55406",
    "sg:province":"MN",
    "sg:tags":[
        "motion"
    ],
    "wof:name":"Breathe In Sing Out Prductions",
    "wof:placetype":"venue"
},
  "geometry": {"coordinates":[-93.227124,44.923704],"type":"Point"}
}