{
  "type": "Feature",
  "properties": {
    "iso:country":"US",
    "sg:address":"2130 S Broadway",
    "sg:city":"Rochester",
    "sg:classifiers":[
        {
            "category":"Shopping",
            "subcategory":"Hobbies, Toys, & Games",
            "type":"Retail Goods"
        }
    ],
    "sg:phone":"+1 507 281 2031",
    "sg:postcode":"55904",
    "sg:province":"MN",
    "wof:name":"Very Impressive Ppr Scrapbooks",
    "wof:placetype":"venue"
},
  "geometry": {"coordinates":[-92.462265,43.99002],"type":"Point"}
}