{
  "type": "Feature",
  "properties": {
    "iso:country":"US",
    "sg:address":"1454 W Co Rd C",
    "sg:city":"Roseville",
    "sg:classifiers":[
        {
            "category":"Manufacturing",
            "subcategory":"Printing",
            "type":"Manufacturing & Wholesale Goods"
        }
    ],
    "sg:phone":"+1 651 697 1100",
    "sg:postcode":"55113",
    "sg:province":"MN",
    "sg:tags":[
        "commercial",
        "printer",
        "design"
    ],
    "sg:website":"www.resolutiongraphics.com",
    "wof:name":"Resolution Graphics Inc",
    "wof:placetype":"venue"
},
  "geometry": {"coordinates":[-93.159093,45.020678],"type":"Point"}
}