{
  "type": "Feature",
  "properties": {
    "addr:full":"1865 20th St NW Appleton MN 56208",
    "addr:housenumber":"1865",
    "addr:postcode":"56208",
    "addr:street":"20Th St Nw",
    "iso:country":"US",
    "sg:address":"1865 20th St NW",
    "sg:city":"Appleton",
    "sg:classifiers":[
        {
            "category":"Professional",
            "subcategory":"Management & Consulting",
            "type":"Services"
        }
    ],
    "sg:phone":"+1 320 394 2257",
    "sg:postcode":"56208",
    "sg:province":"MN",
    "sg:tags":[
        "farm"
    ],
    "wof:name":"Ronald Rudnick",
    "wof:placetype":"venue"
},
  "geometry": {"coordinates":[-95.965658,45.323985],"type":"Point"}
}