{
  "type": "Feature",
  "properties": {
    "addr:full":"12617 Wayzata Blvd Hopkins MN 55305",
    "addr:housenumber":"12617",
    "addr:postcode":"55305",
    "addr:street":"Wayzata Blvd",
    "iso:country":"US",
    "sg:address":"12617 Wayzata Blvd",
    "sg:city":"Hopkins",
    "sg:classifiers":[
        {
            "category":"Shopping",
            "subcategory":"Clothing, Apparel, & Fashions",
            "type":"Retail Goods"
        }
    ],
    "sg:phone":"+1 952 544 0630",
    "sg:postcode":"55305",
    "sg:province":"MN",
    "sg:tags":[
        "apparel",
        "accessory",
        "women's"
    ],
    "sg:website":"http://www.anntaylor.com",
    "wof:name":"Ann Taylor",
    "wof:placetype":"venue"
},
  "geometry": {"coordinates":[-93.43907,44.970495],"type":"Point"}
}