{
  "type": "Feature",
  "properties": {
    "addr:full":"5613 Railroad Blvd Wyoming MN 55092",
    "addr:housenumber":"5613",
    "addr:postcode":"55092",
    "addr:street":"Railroad Blvd",
    "iso:country":"US",
    "sg:address":"5613 Railroad Blvd",
    "sg:city":"Wyoming",
    "sg:classifiers":[
        {
            "category":"Government",
            "subcategory":"Office",
            "type":"Public Place"
        }
    ],
    "sg:phone":"+1 651 462 3688",
    "sg:postcode":"55092",
    "sg:province":"MN",
    "sg:tags":[
        "village"
    ],
    "wof:name":"Wyoming City Office",
    "wof:placetype":"venue"
},
  "geometry": {"coordinates":[-92.99337,45.338549],"type":"Point"}
}