{
  "type": "Feature",
  "properties": {
    "addr:full":"3325 Flag Ave S Minneapolis MN 55426",
    "addr:housenumber":"3325",
    "addr:postcode":"55426",
    "addr:street":"Flag Ave S",
    "iso:country":"US",
    "sg:address":"3325 Flag Ave S",
    "sg:city":"Minneapolis",
    "sg:classifiers":[
        {
            "category":"Wholesale",
            "subcategory":"Groceries",
            "type":"Manufacturing & Wholesale Goods"
        }
    ],
    "sg:phone":"+1 952 938 3234",
    "sg:postcode":"55426",
    "sg:province":"MN",
    "sg:tags":[
        "coffee",
        "tea-wholesale",
        "manufacturer"
    ],
    "sg:website":"http://www.borderfoods.com",
    "wof:name":"Tea On Rocks",
    "wof:placetype":"venue"
},
  "geometry": {"coordinates":[-93.396428,44.94369],"type":"Point"}
}