{
  "type": "Feature",
  "properties": {
    "addr:full":"292 W Broadway Ave Bloomington MN 55411",
    "addr:housenumber":"292",
    "addr:postcode":"55411",
    "addr:street":"W Broadway Ave",
    "iso:country":"US",
    "sg:address":"292 W Broadway Ave",
    "sg:city":"Bloomington",
    "sg:classifiers":[
        {
            "category":"Home & Garden",
            "subcategory":"Furniture",
            "type":"Retail Goods"
        }
    ],
    "sg:phone":"+1 952 858 9531",
    "sg:postcode":"55411",
    "sg:province":"MN",
    "sg:tags":[
        "mattress"
    ],
    "sg:website":"www.sleepair.com",
    "wof:name":"Select Comfort Corp",
    "wof:placetype":"venue"
},
  "geometry": {"coordinates":[-93.283233,44.999211],"type":"Point"}
}