{
  "type": "Feature",
  "properties": {
    "addr:full":"505 1st Ave NE Minneapolis MN 55413",
    "addr:housenumber":"505",
    "addr:postcode":"55413",
    "addr:street":"1St Ave Ne",
    "iso:country":"US",
    "sg:address":"505 1st Ave NE",
    "sg:city":"Minneapolis",
    "sg:classifiers":[
        {
            "category":"Wholesale",
            "subcategory":"Durable Goods & Equipment",
            "type":"Manufacturing & Wholesale Goods"
        },
        {
            "category":"Shopping",
            "subcategory":"Computers & Home Electronics",
            "type":"Retail Goods"
        }
    ],
    "sg:phone":"+1 612 331 4046",
    "sg:postcode":"55413",
    "sg:province":"MN",
    "sg:tags":[
        "audio"
    ],
    "wof:name":"Infocomm Information Resources",
    "wof:placetype":"venue"
},
  "geometry": {"coordinates":[-93.25288,44.990522],"type":"Point"}
}