{
  "type": "Feature",
  "properties": {
    "iso:country":"US",
    "sg:address":"2116 Marquis Rd",
    "sg:city":"Minneapolis",
    "sg:classifiers":[
        {
            "category":"Professional",
            "subcategory":"Research",
            "type":"Services"
        }
    ],
    "sg:phone":"+1 763 545 0912",
    "sg:postcode":"55427",
    "sg:province":"MN",
    "sg:tags":[
        "nonphysical",
        "commercial"
    ],
    "wof:name":"Merila Tchncal Wrting Cnslting",
    "wof:placetype":"venue"
},
  "geometry": {"coordinates":[-93.396399,45.00324],"type":"Point"}
}