{
  "type": "Feature",
  "properties": {
    "iso:country":"US",
    "sg:address":"6335 Bachman Cir",
    "sg:city":"Inver Grove Heights",
    "sg:classifiers":[
        {
            "category":"Building & Trades",
            "subcategory":"Landscaping Services",
            "type":"Services"
        }
    ],
    "sg:phone":"+1 651 457 6605",
    "sg:postcode":"55077",
    "sg:province":"MN",
    "sg:tags":[
        "landscape"
    ],
    "wof:name":"Saintmartin Ldscpg & Lawn Svc",
    "wof:placetype":"venue"
},
  "geometry": {"coordinates":[-93.069036,44.857181],"type":"Point"}
}