{
  "type": "Feature",
  "properties": {
    "addr:full":"50595 197th Ave Verndale MN 56481",
    "addr:housenumber":"50595",
    "addr:postcode":"56481",
    "addr:street":"197Th Ave",
    "iso:country":"US",
    "sg:address":"50595 197th Ave",
    "sg:city":"Verndale",
    "sg:classifiers":[
        {
            "category":"Professional",
            "type":"Services"
        }
    ],
    "sg:phone":"+1 218 445 5953",
    "sg:postcode":"56481",
    "sg:province":"MN",
    "wof:name":"Northland Graveside Svc",
    "wof:placetype":"venue"
},
  "geometry": {"coordinates":[-94.951615,46.366497],"type":"Point"}
}