{
  "type": "Feature",
  "properties": {
    "iso:country":"US",
    "sg:address":"219 Main St",
    "sg:city":"Karlstad",
    "sg:classifiers":[
        {
            "category":"Shopping",
            "subcategory":"Florist",
            "type":"Retail Goods"
        }
    ],
    "sg:phone":"+1 218 436 3131",
    "sg:postcode":"56732",
    "sg:province":"MN",
    "wof:name":"Mainstreet Floral & Gifts",
    "wof:placetype":"venue"
},
  "geometry": {"coordinates":[-96.52066600000001,48.577211],"type":"Point"}
}