{
  "type": "Feature",
  "properties": {
    "iso:country":"US",
    "sg:address":"1428 Skyline Rd",
    "sg:city":"Saint Paul",
    "sg:classifiers":[
        {
            "category":"Social Services",
            "subcategory":"Child Care",
            "type":"Services"
        }
    ],
    "sg:phone":"+1 651 454 8989",
    "sg:postcode":"55121",
    "sg:province":"MN",
    "sg:tags":[
        "day"
    ],
    "wof:name":"Little Britches Chilcare",
    "wof:placetype":"venue"
},
  "geometry": {"coordinates":[-93.168375,44.851517],"type":"Point"}
}