{
  "type": "Feature",
  "properties": {
    "iso:country":"US",
    "sg:address":"7212 72nd Ln N Apt 213",
    "sg:city":"Minneapolis",
    "sg:classifiers":[
        {
            "category":"Building & Trades",
            "subcategory":"Construction",
            "type":"Services"
        }
    ],
    "sg:phone":"+1 763 560 5868",
    "sg:postcode":"55428",
    "sg:province":"MN",
    "sg:tags":[
        "contractor",
        "mason"
    ],
    "wof:name":"Lee W Sathel",
    "wof:placetype":"venue"
},
  "geometry": {"coordinates":[-93.37332499999999,45.084836],"type":"Point"}
}