{
  "type": "Feature",
  "properties": {
    "addr:full":"590 W 79 Chanhassen MN 55317",
    "addr:housenumber":"590",
    "addr:postcode":"55317",
    "addr:street":"W 79",
    "iso:country":"US",
    "sg:address":"590 W 79",
    "sg:city":"Chanhassen",
    "sg:classifiers":[
        {
            "category":"Restaurant",
            "type":"Food & Drink"
        }
    ],
    "sg:phone":"+1 952 949 9190",
    "sg:postcode":"55317",
    "sg:province":"MN",
    "sg:website":"applebees.com",
    "wof:name":"Applebee's Neighborhood Grill & Bar",
    "wof:placetype":"venue"
},
  "geometry": {"coordinates":[-93.53504100000001,44.859343],"type":"Point"}
}