{
  "type": "Feature",
  "properties": {
    "iso:country":"US",
    "sg:address":"1148 Whitewater Ave",
    "sg:city":"St Charles",
    "sg:classifiers":[
        {
            "category":"Sports & Exercise",
            "subcategory":"Bowling",
            "type":"Entertainment"
        }
    ],
    "sg:phone":"+1 507 932 3490",
    "sg:postcode":"55972",
    "sg:province":"MN",
    "sg:tags":[
        "center"
    ],
    "wof:name":"Unity Legion Lanes",
    "wof:placetype":"venue"
},
  "geometry": {"coordinates":[-92.064964,43.967363],"type":"Point"}
}