{
  "type": "Feature",
  "properties": {
    "addr:full":"8256 Commonwealth Dr Eden Prairie MN 55344",
    "addr:housenumber":"8256",
    "addr:postcode":"55344",
    "addr:street":"Commonwealth Dr",
    "iso:country":"US",
    "sg:address":"8256 Commonwealth Dr",
    "sg:city":"Eden Prairie",
    "sg:classifiers":[
        {
            "category":"Shopping",
            "subcategory":"Computers & Home Electronics",
            "type":"Retail Goods"
        }
    ],
    "sg:phone":"+1 952 944 2070",
    "sg:postcode":"55344",
    "sg:province":"MN",
    "sg:tags":[
        "software"
    ],
    "wof:name":"Gamestop",
    "wof:placetype":"venue"
},
  "geometry": {"coordinates":[-93.433747,44.853916],"type":"Point"}
}