{
  "type": "Feature",
  "properties": {
    "iso:country":"US",
    "sg:address":"13433 Meeker Mc Leod Ave",
    "sg:city":"Hutchinson",
    "sg:classifiers":[
        {
            "category":"Farming",
            "subcategory":"Farm",
            "type":"Manufacturing & Wholesale Goods"
        }
    ],
    "sg:phone":"+1 320 587 4574",
    "sg:postcode":"55350",
    "sg:province":"MN",
    "sg:tags":[
        "crop",
        "general"
    ],
    "wof:name":"Willard Wendorff",
    "wof:placetype":"venue"
},
  "geometry": {"coordinates":[-94.502268,44.938508],"type":"Point"}
}