{
  "type": "Feature",
  "properties": {
    "iso:country":"US",
    "sg:address":"412 S Central Ave",
    "sg:city":"Hills",
    "sg:classifiers":[
        {
            "category":"Organizations",
            "subcategory":"Religious Organization",
            "type":"Services"
        }
    ],
    "sg:phone":"+1 507 962 3254",
    "sg:postcode":"56138",
    "sg:province":"MN",
    "sg:tags":[
        "church"
    ],
    "wof:name":"United Reform Church",
    "wof:placetype":"venue"
},
  "geometry": {"coordinates":[-96.357642,43.52576],"type":"Point"}
}