{
  "type": "Feature",
  "properties": {
    "addr:full":"41 N Broadway Pelican Rapids MN 56572",
    "addr:housenumber":"41",
    "addr:postcode":"56572",
    "addr:street":"N Broadway",
    "iso:country":"US",
    "sg:address":"41 N Broadway",
    "sg:city":"Pelican Rapids",
    "sg:classifiers":[
        {
            "category":"Restaurant",
            "type":"Food & Drink"
        }
    ],
    "sg:menulink":"http://www.allmenus.com/mn/pelican-rapids/243974-jimmys-pizza/menu/",
    "sg:phone":"+1 218 863 7777",
    "sg:postcode":"56572",
    "sg:province":"MN",
    "sg:tags":[
        "american",
        "pizza"
    ],
    "wof:name":"Jimmy's Pizza",
    "wof:placetype":"venue"
},
  "geometry": {"coordinates":[-96.083423,46.570211],"type":"Point"}
}