{
  "type": "Feature",
  "properties": {
    "addr:full":"3675 Ihduhapi Trl Loretto MN 55357",
    "addr:housenumber":"3675",
    "addr:postcode":"55357",
    "addr:street":"Ihduhapi Trl",
    "iso:country":"US",
    "sg:address":"3675 Ihduhapi Trl",
    "sg:city":"Loretto",
    "sg:classifiers":[
        {
            "category":"Organizations",
            "subcategory":"Non-profit Organization",
            "type":"Services"
        }
    ],
    "sg:phone":"+1 763 479 3555",
    "sg:postcode":"55357",
    "sg:province":"MN",
    "sg:website":"www.vinlandcenter.org",
    "wof:name":"Vinland National Ctr",
    "wof:placetype":"venue"
},
  "geometry": {"coordinates":[-93.65098,45.048367],"type":"Point"}
}