{
  "type": "Feature",
  "properties": {
    "addr:full":"8148 Everest Ln N Maple Grove MN 55311",
    "addr:housenumber":"8148",
    "addr:postcode":"55311",
    "addr:street":"Everest Ln N",
    "iso:country":"US",
    "sg:address":"8148 Everest Ln N",
    "sg:city":"Maple Grove",
    "sg:classifiers":[
        {
            "category":"Building & Trades",
            "subcategory":"Plumbing",
            "type":"Services"
        }
    ],
    "sg:phone":"+1 763 494 5356",
    "sg:postcode":"55311",
    "sg:province":"MN",
    "sg:tags":[
        "plumbing",
        "contractor"
    ],
    "wof:name":"Lee Mechanical Inc",
    "wof:placetype":"venue"
},
  "geometry": {"coordinates":[-93.495465,45.101632],"type":"Point"}
}