{
  "type": "Feature",
  "properties": {
    "addr:full":"916 8th St Farmington MN 55024",
    "addr:housenumber":"916",
    "addr:postcode":"55024",
    "addr:street":"8Th St",
    "iso:country":"US",
    "sg:address":"916 8th St",
    "sg:city":"Farmington",
    "sg:classifiers":[
        {
            "category":"Health Services",
            "subcategory":"Doctor",
            "type":"Services"
        }
    ],
    "sg:phone":"+1 651 463 2300",
    "sg:postcode":"55024",
    "sg:province":"MN",
    "sg:tags":[
        "dentist"
    ],
    "wof:name":"Dental Health Ctr",
    "wof:placetype":"venue"
},
  "geometry": {"coordinates":[-93.137387,44.63284],"type":"Point"}
}