{
  "type": "Feature",
  "properties": {
    "addr:full":"1779 75th Ave Lake Wilson MN 56151",
    "addr:housenumber":"1779",
    "addr:postcode":"56151",
    "addr:street":"75Th Ave",
    "iso:country":"US",
    "sg:address":"1779 75th Ave",
    "sg:city":"Lake Wilson",
    "sg:classifiers":[
        {
            "category":"Farming",
            "subcategory":"Livestock Farm",
            "type":"Manufacturing & Wholesale Goods"
        }
    ],
    "sg:phone":"+1 507 734 3022",
    "sg:postcode":"56151",
    "sg:province":"MN",
    "sg:tags":[
        "corn",
        "beef",
        "feedlot",
        "cattle"
    ],
    "wof:name":"Miller Les & Curt Farm Inc",
    "wof:placetype":"venue"
},
  "geometry": {"coordinates":[-95.91374999999999,44.105969],"type":"Point"}
}