{
  "type": "Feature",
  "properties": {
    "addr:full":"444 Lafayette Rd St Paul MN 55155",
    "addr:housenumber":"444",
    "addr:postcode":"55155",
    "addr:street":"Lafayette Rd",
    "iso:country":"US",
    "sg:address":"444 Lafayette Rd",
    "sg:city":"St Paul",
    "sg:classifiers":[
        {
            "category":"Government",
            "subcategory":"Office",
            "type":"Public Place"
        }
    ],
    "sg:phone":"+1 651 297 7305",
    "sg:postcode":"55155",
    "sg:province":"MN",
    "sg:tags":[
        "state",
        "resource"
    ],
    "wof:name":"Hearing Impaired Council",
    "wof:placetype":"venue"
},
  "geometry": {"coordinates":[-93.084447,44.954651],"type":"Point"}
}