{
  "type": "Feature",
  "properties": {
    "addr:full":"105 E Lyon Ave Lake City MN 55041",
    "addr:housenumber":"105",
    "addr:postcode":"55041",
    "addr:street":"E Lyon Ave",
    "iso:country":"US",
    "sg:address":"105 E Lyon Ave",
    "sg:city":"Lake City",
    "sg:classifiers":[
        {
            "category":"Banks & Credit Unions",
            "subcategory":"Bank",
            "type":"Services"
        }
    ],
    "sg:phone":"+1 651 345 3311",
    "sg:postcode":"55041",
    "sg:province":"MN",
    "sg:website":"www.greatbanking.net",
    "wof:name":"American Bank Lake City",
    "wof:placetype":"venue"
},
  "geometry": {"coordinates":[-92.266164,44.449854],"type":"Point"}
}