{
  "type": "Feature",
  "properties": {
    "addr:full":"26789 300th St Badger MN 56714",
    "addr:housenumber":"26789",
    "addr:postcode":"56714",
    "addr:street":"300Th St",
    "iso:country":"US",
    "sg:address":"26789 300th St",
    "sg:city":"Badger",
    "sg:classifiers":[
        {
            "category":"Farming",
            "subcategory":"Livestock Farm",
            "type":"Manufacturing & Wholesale Goods"
        }
    ],
    "sg:phone":"+1 218 528 4341",
    "sg:postcode":"56714",
    "sg:province":"MN",
    "sg:tags":[
        "animal",
        "general"
    ],
    "wof:name":"Northen Digital SEC Systems",
    "wof:placetype":"venue"
},
  "geometry": {"coordinates":[-96.03458500000001,48.833438],"type":"Point"}
}