{
  "type": "Feature",
  "properties": {
    "addr:full":"1960 Wyndham Hill Dr Hastings MN 55033",
    "addr:housenumber":"1960",
    "addr:postcode":"55033",
    "addr:street":"Wyndham Hill Dr",
    "iso:country":"US",
    "sg:address":"1960 Wyndham Hill Dr",
    "sg:city":"Hastings",
    "sg:classifiers":[
        {
            "category":"Wholesale",
            "subcategory":"Machinery & Supplies",
            "type":"Manufacturing & Wholesale Goods"
        }
    ],
    "sg:phone":"+1 320 629 3766",
    "sg:postcode":"55033",
    "sg:province":"MN",
    "sg:tags":[
        "equipment",
        "establishment",
        "repair"
    ],
    "wof:name":"Natures Way Taxidermy",
    "wof:placetype":"venue"
},
  "geometry": {"coordinates":[-92.890097,44.727994],"type":"Point"}
}