{
  "type": "Feature",
  "properties": {
    "addr:full":"18712 580th Ave Wells MN 56097",
    "addr:housenumber":"18712",
    "addr:postcode":"56097",
    "addr:street":"580Th Ave",
    "iso:country":"US",
    "sg:address":"18712 580th Ave",
    "sg:city":"Wells",
    "sg:classifiers":[
        {
            "category":"Farming",
            "subcategory":"Livestock Farm",
            "type":"Manufacturing & Wholesale Goods"
        }
    ],
    "sg:phone":"+1 507 553 3889",
    "sg:postcode":"56097",
    "sg:province":"MN",
    "sg:tags":[
        "hog",
        "feedlot"
    ],
    "wof:name":"Staloch Bros",
    "wof:placetype":"venue"
},
  "geometry": {"coordinates":[-93.70831200000001,43.757815],"type":"Point"}
}