{
  "type": "Feature",
  "properties": {
    "iso:country":"US",
    "sg:address":"1652 Greenview Dr SW",
    "sg:city":"Rochester",
    "sg:classifiers":[
        {
            "category":"Insurance",
            "subcategory":"Insurance Agent",
            "type":"Services"
        }
    ],
    "sg:phone":"+1 507 281 9947",
    "sg:postcode":"55902",
    "sg:province":"MN",
    "wof:name":"Alan Lichty",
    "wof:placetype":"venue"
},
  "geometry": {"coordinates":[-92.486639,44.003196],"type":"Point"}
}