{
  "type": "Feature",
  "properties": {
    "addr:full":"140 Arrowhead Ln Moose Lake MN 55767",
    "addr:housenumber":"140",
    "addr:postcode":"55767",
    "addr:street":"Arrowhead Ln",
    "iso:country":"US",
    "sg:address":"140 Arrowhead Ln",
    "sg:city":"Moose Lake",
    "sg:classifiers":[
        {
            "category":"Real Estate",
            "subcategory":"Real Estate Agent",
            "type":"Services"
        }
    ],
    "sg:phone":"+1 218 485 0544",
    "sg:postcode":"55767",
    "sg:province":"MN",
    "sg:tags":[
        "consultant"
    ],
    "wof:name":"Re/Max Moose Lake",
    "wof:placetype":"venue"
},
  "geometry": {"coordinates":[-92.76538600000001,46.450964],"type":"Point"}
}