{
  "type": "Feature",
  "properties": {
    "addr:full":"487 Mendota Rd W Saint Paul MN 55118",
    "addr:housenumber":"487",
    "addr:postcode":"55118",
    "addr:street":"Mendota Rd W",
    "iso:country":"US",
    "sg:address":"487 Mendota Rd W",
    "sg:city":"Saint Paul",
    "sg:classifiers":[
        {
            "category":"Shopping",
            "subcategory":"Bicycles & Sporting Goods",
            "type":"Retail Goods"
        }
    ],
    "sg:phone":"+1 651 646 7389",
    "sg:postcode":"55118",
    "sg:province":"MN",
    "wof:name":"Daryl D Bremer",
    "wof:placetype":"venue"
},
  "geometry": {"coordinates":[-93.10024,44.884173],"type":"Point"}
}