{
  "type": "Feature",
  "properties": {
    "addr:full":"16301 Valley Rd Eden Prairie MN 55347",
    "addr:housenumber":"16301",
    "addr:postcode":"55347",
    "addr:street":"Valley Rd",
    "iso:country":"US",
    "sg:address":"16301 Valley Rd",
    "sg:city":"Eden Prairie",
    "sg:classifiers":[
        {
            "category":"Building & Trades",
            "subcategory":"Construction",
            "type":"Services"
        }
    ],
    "sg:phone":"+1 952 949 0525",
    "sg:postcode":"55347",
    "sg:province":"MN",
    "sg:tags":[
        "skylight"
    ],
    "wof:name":"Daylight Designs",
    "wof:placetype":"venue"
},
  "geometry": {"coordinates":[-93.485378,44.834342],"type":"Point"}
}