{
  "type": "Feature",
  "properties": {
    "addr:full":"736 E Lake St Minneapolis MN 55407",
    "addr:housenumber":"736",
    "addr:postcode":"55407",
    "addr:street":"E Lake St",
    "iso:country":"US",
    "sg:address":"736 E Lake St",
    "sg:city":"Minneapolis",
    "sg:classifiers":[
        {
            "category":"Shopping",
            "subcategory":"Clothing, Apparel, & Fashions",
            "type":"Retail Goods"
        }
    ],
    "sg:phone":"+1 612 822 6276",
    "sg:postcode":"55407",
    "sg:province":"MN",
    "sg:tags":[
        "sportswear",
        "family"
    ],
    "wof:name":"Michaels Hip Hop Shop",
    "wof:placetype":"venue"
},
  "geometry": {"coordinates":[-93.26365,44.948363],"type":"Point"}
}