{
  "type": "Feature",
  "properties": {
    "iso:country":"US",
    "sg:address":"10640 South Ave",
    "sg:city":"Chisago City",
    "sg:classifiers":[
        {
            "category":"Food & Beverages",
            "subcategory":"Liquor & Beverages",
            "type":"Retail Goods"
        }
    ],
    "sg:phone":"+1 651 257 2385",
    "sg:postcode":"55013",
    "sg:province":"MN",
    "wof:name":"Chisago Warehouse Liquors",
    "wof:placetype":"venue"
},
  "geometry": {"coordinates":[-92.891189,45.373347],"type":"Point"}
}