{
  "type": "Feature",
  "properties": {
    "addr:full":"35763 State Hwy 65 Nashwauk MN 55769",
    "addr:housenumber":"35763",
    "addr:postcode":"55769",
    "addr:street":"State Hwy 65",
    "iso:country":"US",
    "sg:address":"35763 State Hwy 65",
    "sg:city":"Nashwauk",
    "sg:classifiers":[
        {
            "category":"Retail",
            "subcategory":"Repair Shop",
            "type":"Services"
        }
    ],
    "sg:phone":"+1 218 885 2225",
    "sg:postcode":"55769",
    "sg:province":"MN",
    "wof:name":"Nashwauk Truck & Trailer Repr",
    "wof:placetype":"venue"
},
  "geometry": {"coordinates":[-93.168601,47.394821],"type":"Point"}
}