{
  "type": "Feature",
  "properties": {
    "iso:country":"US",
    "sg:address":"6230 10th St N",
    "sg:city":"St Paul",
    "sg:classifiers":[
        {
            "category":"Professional",
            "subcategory":"Advertising",
            "type":"Services"
        }
    ],
    "sg:phone":"+1 651 209 6677",
    "sg:postcode":"55128",
    "sg:province":"MN",
    "sg:website":"www.offsiterealty.com",
    "wof:name":"OFFSITEREALTY.COM",
    "wof:placetype":"venue"
},
  "geometry": {"coordinates":[-92.980396,44.963298],"type":"Point"}
}