{
  "type": "Feature",
  "properties": {
    "addr:full":"7601 Penn Avenue South Richfield MN 55423",
    "addr:housenumber":"7601",
    "addr:postcode":"55423",
    "addr:street":"Penn Avenue South",
    "iso:country":"US",
    "sg:address":"7601 Penn Avenue South",
    "sg:city":"Richfield",
    "sg:classifiers":[
        {
            "category":"Professional",
            "subcategory":"Computer Services",
            "type":"Services"
        }
    ],
    "sg:phone":"+1 888 237 8289",
    "sg:postcode":"55423",
    "sg:province":"MN",
    "sg:website":"http://www.bestbuy.com/",
    "wof:name":"Best Buy",
    "wof:placetype":"venue"
},
  "geometry": {"coordinates":[-93.308678,44.863662],"type":"Point"}
}