{
  "type": "Feature",
  "properties": {
    "addr:full":"14917 Garrett Ave Saint Paul MN 55124",
    "addr:housenumber":"14917",
    "addr:postcode":"55124",
    "addr:street":"Garrett Ave",
    "iso:country":"US",
    "sg:address":"14917 Garrett Ave",
    "sg:city":"Saint Paul",
    "sg:classifiers":[
        {
            "category":"Sports & Exercise",
            "subcategory":"Bowling",
            "type":"Entertainment"
        }
    ],
    "sg:phone":"+1 952 432 1515",
    "sg:postcode":"55124",
    "sg:province":"MN",
    "wof:name":"Appleplace Bowling Center",
    "wof:placetype":"venue"
},
  "geometry": {"coordinates":[-93.210886,44.734575],"type":"Point"}
}