{
  "type": "Feature",
  "properties": {
    "addr:full":"208 Ehrich St Minnesota Lake MN 56068",
    "addr:housenumber":"208",
    "addr:postcode":"56068",
    "addr:street":"Ehrich St",
    "iso:country":"US",
    "sg:address":"208 Ehrich St",
    "sg:city":"Minnesota Lake",
    "sg:phone":"+1 507 462 3459",
    "sg:postcode":"56068",
    "sg:province":"MN",
    "sg:tags":[
        "farm",
        "corn",
        "cash",
        "crop",
        "field",
        "grain",
        "soybean"
    ],
    "wof:name":"David Proehl",
    "wof:placetype":"venue"
},
  "geometry": {"coordinates":[-93.835892,43.838442],"type":"Point"}
}