{
  "type": "Feature",
  "properties": {
    "iso:country":"US",
    "sg:address":"14715 534th Ave",
    "sg:city":"Vernon Center",
    "sg:classifiers":[
        {
            "category":"Farming",
            "subcategory":"Livestock Farm",
            "type":"Manufacturing & Wholesale Goods"
        }
    ],
    "sg:phone":"+1 507 549 3381",
    "sg:postcode":"56090",
    "sg:province":"MN",
    "sg:tags":[
        "hog",
        "or",
        "feedlot"
    ],
    "wof:name":"Roeloff Farms Inc",
    "wof:placetype":"venue"
},
  "geometry": {"coordinates":[-94.13852,43.979441],"type":"Point"}
}