{
  "type": "Feature",
  "properties": {
    "addr:full":"2180 Marshall Ave Saint Paul MN 55104",
    "addr:housenumber":"2180",
    "addr:postcode":"55104",
    "addr:street":"Marshall Ave",
    "iso:country":"US",
    "sg:address":"2180 Marshall Ave",
    "sg:city":"Saint Paul",
    "sg:classifiers":[
        {
            "category":"Personal",
            "subcategory":"Tanning Parlor",
            "type":"Services"
        }
    ],
    "sg:phone":"+1 651 644 3241",
    "sg:postcode":"55104",
    "sg:province":"MN",
    "wof:name":"Tangerine Dreams",
    "wof:placetype":"venue"
},
  "geometry": {"coordinates":[-93.192497,44.948502],"type":"Point"}
}