{
  "type": "Feature",
  "properties": {
    "iso:country":"US",
    "sg:address":"2074 110th Ave",
    "sg:city":"Holland",
    "sg:phone":"+1 507 347 3328",
    "sg:postcode":"56139",
    "sg:province":"MN",
    "sg:tags":[
        "farm",
        "animal",
        "general"
    ],
    "wof:name":"Jason Borman",
    "wof:placetype":"venue"
},
  "geometry": {"coordinates":[-96.24532000000001,44.152956],"type":"Point"}
}