{
  "type": "Feature",
  "properties": {
    "iso:country":"US",
    "sg:address":"1856 E Madison Ave",
    "sg:city":"Mankato",
    "sg:classifiers":[
        {
            "category":"Ice Cream",
            "type":"Food & Drink"
        }
    ],
    "sg:menulink":"http://www.allmenus.com/mn/mankato/182844-culvers/menu/",
    "sg:phone":"+1 507 344 1554",
    "sg:postcode":"56001",
    "sg:province":"MN",
    "sg:tags":[
        "burger",
        "american"
    ],
    "wof:name":"Culver's",
    "wof:placetype":"venue"
},
  "geometry": {"coordinates":[-93.952461,44.166918],"type":"Point"}
}