{
  "type": "Feature",
  "properties": {
    "addr:full":"50111 Co Hwy 17 Vergas MN 56587",
    "addr:housenumber":"50111",
    "addr:postcode":"56587",
    "addr:street":"Co Hwy 17",
    "iso:country":"US",
    "sg:address":"50111 Co Hwy 17",
    "sg:city":"Vergas",
    "sg:classifiers":[
        {
            "category":"Shopping",
            "subcategory":"Books",
            "type":"Retail Goods"
        }
    ],
    "sg:phone":"+1 218 342 2793",
    "sg:postcode":"56587",
    "sg:province":"MN",
    "wof:name":"Driftwood Books & News",
    "wof:placetype":"venue"
},
  "geometry": {"coordinates":[-95.840084,46.690357],"type":"Point"}
}