{
  "type": "Feature",
  "properties": {
    "addr:full":"5650 41st Ave NW Willmar MN 56201",
    "addr:housenumber":"5650",
    "addr:postcode":"56201",
    "addr:street":"41St Ave Nw",
    "iso:country":"US",
    "sg:address":"5650 41st Ave NW",
    "sg:city":"Willmar",
    "sg:phone":"+1 320 235 8465",
    "sg:postcode":"56201",
    "sg:province":"MN",
    "sg:tags":[
        "farm",
        "field",
        "crop"
    ],
    "wof:name":"Arndt John",
    "wof:placetype":"venue"
},
  "geometry": {"coordinates":[-95.12181099999999,45.164267],"type":"Point"}
}