{
  "type": "Feature",
  "properties": {
    "iso:country":"US",
    "sg:address":"407 11th St S",
    "sg:city":"Virginia",
    "sg:classifiers":[
        {
            "category":"Building & Trades",
            "subcategory":"Construction",
            "type":"Services"
        }
    ],
    "sg:phone":"+1 218 749 0825",
    "sg:postcode":"55792",
    "sg:province":"MN",
    "sg:tags":[
        "house"
    ],
    "wof:name":"Range Renovations",
    "wof:placetype":"venue"
},
  "geometry": {"coordinates":[-92.537368,47.513172],"type":"Point"}
}