{
  "type": "Feature",
  "properties": {
    "iso:country":"US",
    "sg:address":"1331 Larpenteur Ave W",
    "sg:city":"Roseville",
    "sg:classifiers":[
        {
            "category":"Retail",
            "subcategory":"Auto Repair",
            "type":"Services"
        },
        {
            "category":"Autos & Motor Vehicles",
            "subcategory":"Auto Supplies",
            "type":"Retail Goods"
        }
    ],
    "sg:phone":"+1 651 642 1523",
    "sg:postcode":"55113",
    "sg:province":"MN",
    "sg:tags":[
        "repairing",
        "automobile",
        "tire",
        "performs"
    ],
    "sg:website":"www.tiresplus.com",
    "wof:name":"Team Tires Plus",
    "wof:placetype":"venue"
},
  "geometry": {"coordinates":[-93.15588,44.991928],"type":"Point"}
}