{
  "type": "Feature",
  "properties": {
    "iso:country":"US",
    "sg:address":"3572 Blue Jay Way",
    "sg:city":"Eagan",
    "sg:classifiers":[
        {
            "category":"Banks & Credit Unions",
            "subcategory":"Investment Brokerage",
            "type":"Services"
        }
    ],
    "sg:phone":"+1 651 688 7112",
    "sg:postcode":"55123",
    "sg:province":"MN",
    "sg:tags":[
        "consultant",
        "planning",
        "financial"
    ],
    "wof:name":"Business & Estate Advantages",
    "wof:placetype":"venue"
},
  "geometry": {"coordinates":[-93.142797,44.827062],"type":"Point"}
}