{
  "type": "Feature",
  "properties": {
    "addr:full":"4601 Excelsior Blvd Minneapolis MN 55416",
    "addr:housenumber":"4601",
    "addr:postcode":"55416",
    "addr:street":"Excelsior Blvd",
    "iso:country":"US",
    "sg:address":"4601 Excelsior Blvd",
    "sg:city":"Minneapolis",
    "sg:classifiers":[
        {
            "category":"Banks & Credit Unions",
            "subcategory":"Financial Services",
            "type":"Services"
        }
    ],
    "sg:phone":"+1 952 926 8880",
    "sg:postcode":"55416",
    "sg:province":"MN",
    "sg:tags":[
        "broker",
        "mortgage"
    ],
    "wof:name":"Capital Corporate Financing Inc",
    "wof:placetype":"venue"
},
  "geometry": {"coordinates":[-93.338402,44.9338],"type":"Point"}
}