{
  "type": "Feature",
  "properties": {
    "addr:full":"945 Ash St Clearwater MN 55320",
    "addr:housenumber":"945",
    "addr:postcode":"55320",
    "addr:street":"Ash St",
    "iso:country":"US",
    "sg:address":"945 Ash St",
    "sg:city":"Clearwater",
    "sg:classifiers":[
        {
            "category":"Restaurant",
            "type":"Food & Drink"
        }
    ],
    "sg:phone":"+1 320 558 9227",
    "sg:postcode":"55320",
    "sg:province":"MN",
    "wof:name":"Burger King",
    "wof:placetype":"venue"
},
  "geometry": {"coordinates":[-94.056011,45.413167],"type":"Point"}
}