{
  "type": "Feature",
  "properties": {
    "addr:full":"363 210th Ave Fulda MN 56131",
    "addr:housenumber":"363",
    "addr:postcode":"56131",
    "addr:street":"210Th Ave",
    "iso:country":"US",
    "sg:address":"363 210th Ave",
    "sg:city":"Fulda",
    "sg:phone":"+1 507 425 2946",
    "sg:postcode":"56131",
    "sg:province":"MN",
    "sg:tags":[
        "farm",
        "corn",
        "soybean"
    ],
    "wof:name":"Stan Kramer Inc",
    "wof:placetype":"venue"
},
  "geometry": {"coordinates":[-95.64291900000001,43.893399],"type":"Point"}
}