{
  "type": "Feature",
  "properties": {
    "iso:country":"US",
    "sg:address":"920 E 28th St Ste 300",
    "sg:city":"Minneapolis",
    "sg:classifiers":[
        {
            "category":"Health Services",
            "subcategory":"Doctor",
            "type":"Services"
        }
    ],
    "sg:phone":"+1 612 863 8150",
    "sg:postcode":"55407",
    "sg:province":"MN",
    "sg:tags":[
        "physician",
        "cardiology",
        "thoracic",
        "surgeons",
        "surgeon",
        "surgery",
        "cardiovascular"
    ],
    "wof:name":"Vascular Specialists Of Minnes",
    "wof:placetype":"venue"
},
  "geometry": {"coordinates":[-93.261105,44.95195],"type":"Point"}
}