{
  "type": "Feature",
  "properties": {
    "addr:full":"35854 Co Hwy 72 Battle Lake MN 56515",
    "addr:housenumber":"35854",
    "addr:postcode":"56515",
    "addr:street":"Co Hwy 72",
    "iso:country":"US",
    "sg:address":"35854 Co Hwy 72",
    "sg:city":"Battle Lake",
    "sg:classifiers":[
        {
            "category":"Retail",
            "subcategory":"Auto Repair",
            "type":"Services"
        }
    ],
    "sg:phone":"+1 218 864 8284",
    "sg:postcode":"56515",
    "sg:province":"MN",
    "sg:tags":[
        "body"
    ],
    "wof:name":"Garzas Body & Paint Shop",
    "wof:placetype":"venue"
},
  "geometry": {"coordinates":[-95.74318100000001,46.366097],"type":"Point"}
}