{
  "type": "Feature",
  "properties": {
    "iso:country":"US",
    "sg:address":"2060 Centre Pointe Blvd",
    "sg:city":"Saint Paul",
    "sg:classifiers":[
        {
            "category":"Utilities",
            "subcategory":"Telephone",
            "type":"Services"
        }
    ],
    "sg:phone":"+1 651 675 2100",
    "sg:postcode":"55120",
    "sg:province":"MN",
    "sg:tags":[
        "communications"
    ],
    "wof:name":"Expnets",
    "wof:placetype":"venue"
},
  "geometry": {"coordinates":[-93.152108,44.882375],"type":"Point"}
}