{
  "type": "Feature",
  "properties": {
    "addr:full":"14026 Taconite St NE Anoka MN 55304",
    "addr:housenumber":"14026",
    "addr:postcode":"55304",
    "addr:street":"Taconite St Ne",
    "iso:country":"US",
    "sg:address":"14026 Taconite St NE",
    "sg:city":"Anoka",
    "sg:classifiers":[
        {
            "category":"Shopping",
            "subcategory":"Used Merchandise",
            "type":"Retail Goods"
        }
    ],
    "sg:phone":"+1 763 757 6020",
    "sg:postcode":"55304",
    "sg:province":"MN",
    "wof:name":"Wings & Things Antiques",
    "wof:placetype":"venue"
},
  "geometry": {"coordinates":[-93.209558,45.225342],"type":"Point"}
}