{
  "type": "Feature",
  "properties": {
    "iso:country":"US",
    "sg:address":"1699 Robert St S",
    "sg:city":"Saint Paul",
    "sg:classifiers":[
        {
            "category":"Restaurant",
            "type":"Food & Drink"
        }
    ],
    "sg:menulink":"http://www.allmenus.com/mn/west-st-paul/238517-timber-lodge-steakhouse/menu/",
    "sg:phone":"+1 651 455 5229",
    "sg:postcode":"55118",
    "sg:province":"MN",
    "sg:tags":[
        "american",
        "steakhouse"
    ],
    "wof:name":"Timber Lodge Steakhouse",
    "wof:placetype":"venue"
},
  "geometry": {"coordinates":[-93.08121199999999,44.894768],"type":"Point"}
}