{
  "type": "Feature",
  "properties": {
    "iso:country":"US",
    "sg:address":"1540 State Hwy 43",
    "sg:city":"Rushford",
    "sg:classifiers":[
        {
            "category":"Home & Garden",
            "subcategory":"Building Materials",
            "type":"Retail Goods"
        }
    ],
    "sg:phone":"+1 507 864 2744",
    "sg:postcode":"55971",
    "sg:province":"MN",
    "sg:tags":[
        "lumber"
    ],
    "wof:name":"Jim's Building Ctr",
    "wof:placetype":"venue"
},
  "geometry": {"coordinates":[-91.765117,43.789983],"type":"Point"}
}