{
  "type": "Feature",
  "properties": {
    "iso:country":"US",
    "sg:address":"1009 N Kilburn St",
    "sg:city":"Saint Paul",
    "sg:classifiers":[
        {
            "category":"Professional",
            "subcategory":"Management & Consulting",
            "type":"Services"
        }
    ],
    "sg:phone":"+1 651 487 6995",
    "sg:postcode":"55103",
    "sg:province":"MN",
    "sg:tags":[
        "computer",
        "custom"
    ],
    "wof:name":"Versatrans Solutions Inc",
    "wof:placetype":"venue"
},
  "geometry": {"coordinates":[-93.14052700000001,44.972217],"type":"Point"}
}