{
  "type": "Feature",
  "properties": {
    "iso:country":"US",
    "sg:address":"177 Midwest Trl N",
    "sg:city":"Lake Elmo",
    "sg:classifiers":[
        {
            "category":"Professional",
            "subcategory":"Engineering",
            "type":"Services"
        }
    ],
    "sg:phone":"+1 651 436 1401",
    "sg:postcode":"55042",
    "sg:province":"MN",
    "wof:name":"Edquist John",
    "wof:placetype":"venue"
},
  "geometry": {"coordinates":[-92.85042799999999,44.950909],"type":"Point"}
}