{
  "type": "Feature",
  "properties": {
    "addr:full":"12764 State Hwy 26 Brownsville MN 55919",
    "addr:housenumber":"12764",
    "addr:postcode":"55919",
    "addr:street":"State Hwy 26",
    "iso:country":"US",
    "sg:address":"12764 State Hwy 26",
    "sg:city":"Brownsville",
    "sg:classifiers":[
        {
            "category":"Professional",
            "subcategory":"Business Services",
            "type":"Services"
        }
    ],
    "sg:phone":"+1 507 482 7777",
    "sg:postcode":"55919",
    "sg:province":"MN",
    "sg:tags":[
        "broker",
        "merchandise"
    ],
    "wof:name":"Tri State Auto Brokerage",
    "wof:placetype":"venue"
},
  "geometry": {"coordinates":[-91.275694,43.660625],"type":"Point"}
}