{
  "type": "Feature",
  "properties": {
    "addr:full":"140 Main St S Winnebago MN 56098",
    "addr:housenumber":"140",
    "addr:postcode":"56098",
    "addr:street":"Main St S",
    "iso:country":"US",
    "sg:address":"140 Main St S",
    "sg:city":"Winnebago",
    "sg:classifiers":[
        {
            "category":"Organizations",
            "subcategory":"Community Association",
            "type":"Services"
        }
    ],
    "sg:phone":"+1 507 893 3217",
    "sg:postcode":"56098",
    "sg:province":"MN",
    "sg:tags":[
        "chamber",
        "commerce"
    ],
    "wof:name":"Winnebago Chamber Of Commerce",
    "wof:placetype":"venue"
},
  "geometry": {"coordinates":[-94.16573,43.764801],"type":"Point"}
}