{
  "type": "Feature",
  "properties": {
    "addr:full":"2780 Snelling Ave N St Paul MN 55113",
    "addr:housenumber":"2780",
    "addr:postcode":"55113",
    "addr:street":"Snelling Ave N",
    "iso:country":"US",
    "sg:address":"2780 Snelling Ave N",
    "sg:city":"St Paul",
    "sg:classifiers":[
        {
            "category":"Professional",
            "subcategory":"Lawyer & Legal Services",
            "type":"Services"
        },
        {
            "category":"Autos & Motor Vehicles",
            "subcategory":"Auto Supplies",
            "type":"Retail Goods"
        }
    ],
    "sg:phone":"+1 651 636 4040",
    "sg:postcode":"55113",
    "sg:province":"MN",
    "sg:tags":[
        "attorney"
    ],
    "wof:name":"Patrick E Florin",
    "wof:placetype":"venue"
},
  "geometry": {"coordinates":[-93.166999,45.021509],"type":"Point"}
}