{
  "type": "Feature",
  "properties": {
    "addr:full":"300 6th St S Minneapolis MN 55415",
    "addr:housenumber":"300",
    "addr:postcode":"55415",
    "addr:street":"6Th St S",
    "iso:country":"US",
    "sg:address":"300 6th St S",
    "sg:city":"Minneapolis",
    "sg:classifiers":[
        {
            "category":"Government",
            "subcategory":"Court House",
            "type":"Public Place"
        }
    ],
    "sg:phone":"+1 612 348 4003",
    "sg:postcode":"55415",
    "sg:province":"MN",
    "sg:tags":[
        "county",
        "counsel"
    ],
    "wof:name":"Hennepin Cnty Victm Witnss Unt",
    "wof:placetype":"venue"
},
  "geometry": {"coordinates":[-93.26597,44.975541],"type":"Point"}
}