{
  "type": "Feature",
  "properties": {
    "addr:full":"12 Bridge Sq Anoka MN 55303",
    "addr:housenumber":"12",
    "addr:postcode":"55303",
    "addr:street":"Bridge Sq",
    "iso:country":"US",
    "sg:address":"12 Bridge Sq",
    "sg:city":"Anoka",
    "sg:classifiers":[
        {
            "category":"Health Services",
            "subcategory":"Optometrist",
            "type":"Services"
        },
        {
            "category":"Shopping",
            "subcategory":"Optician",
            "type":"Retail Goods"
        }
    ],
    "sg:phone":"+1 763 421 4334",
    "sg:postcode":"55303",
    "sg:province":"MN",
    "sg:tags":[
        "eyewear"
    ],
    "sg:website":"www.bridgesquareoptical.com",
    "wof:name":"Bridge Square Optical",
    "wof:placetype":"venue"
},
  "geometry": {"coordinates":[-93.391403,45.197399],"type":"Point"}
}