{
  "type": "Feature",
  "properties": {
    "addr:full":"3200 W 70th St Minneapolis MN 55435",
    "addr:housenumber":"3200",
    "addr:postcode":"55435",
    "addr:street":"W 70Th St",
    "iso:country":"US",
    "sg:address":"3200 W 70th St",
    "sg:city":"Minneapolis",
    "sg:classifiers":[
        {
            "category":"Shopping",
            "subcategory":"Music",
            "type":"Retail Goods"
        }
    ],
    "sg:phone":"+1 952 920 5080",
    "sg:postcode":"55435",
    "sg:province":"MN",
    "sg:tags":[
        "repair"
    ],
    "wof:name":"Paul A Schmitt Music Company",
    "wof:placetype":"venue"
},
  "geometry": {"coordinates":[-93.320634,44.876426],"type":"Point"}
}