{
  "type": "Feature",
  "properties": {
    "addr:full":"2025 Nicollet Ave Minneapolis MN 55404",
    "addr:housenumber":"2025",
    "addr:postcode":"55404",
    "addr:street":"Nicollet Ave",
    "iso:country":"US",
    "sg:address":"2025 Nicollet Ave",
    "sg:city":"Minneapolis",
    "sg:classifiers":[
        {
            "category":"Personal",
            "type":"Services"
        },
        {
            "category":"Professional",
            "subcategory":"Management & Consulting",
            "type":"Services"
        }
    ],
    "sg:phone":"+1 612 813 0501",
    "sg:postcode":"55404",
    "sg:province":"MN",
    "sg:tags":[
        "credit",
        "debt",
        "counseling"
    ],
    "wof:name":"African Credit Education",
    "wof:placetype":"venue"
},
  "geometry": {"coordinates":[-93.27775099999999,44.961119],"type":"Point"}
}