{
  "type": "Feature",
  "properties": {
    "iso:country":"US",
    "sg:address":"24835 Gates Ave",
    "sg:city":"Faribault",
    "sg:classifiers":[
        {
            "category":"Autos & Motor Vehicles",
            "subcategory":"Auto Supplies",
            "type":"Retail Goods"
        },
        {
            "category":"Retail",
            "subcategory":"Auto Repair",
            "type":"Services"
        }
    ],
    "sg:phone":"+1 507 332 6936",
    "sg:postcode":"55021",
    "sg:province":"MN",
    "sg:tags":[
        "automotive",
        "tune",
        "tire"
    ],
    "sg:website":"http://www.napaautocare.com/",
    "wof:name":"Richland Repair",
    "wof:placetype":"venue"
},
  "geometry": {"coordinates":[-93.13166,44.269316],"type":"Point"}
}