{
  "type": "Feature",
  "properties": {
    "addr:full":"5001 Xerxes Ave Minneapolis MN 55410",
    "addr:housenumber":"5001",
    "addr:postcode":"55410",
    "addr:street":"Xerxes Ave",
    "iso:country":"US",
    "sg:address":"5001 Xerxes Ave",
    "sg:city":"Minneapolis",
    "sg:classifiers":[
        {
            "category":"Autos & Motor Vehicles",
            "subcategory":"Auto Supplies",
            "type":"Retail Goods"
        }
    ],
    "sg:phone":"+1 612 927 7981",
    "sg:postcode":"55410",
    "sg:province":"MN",
    "sg:tags":[
        "automotive",
        "repair"
    ],
    "wof:name":"All JS Tire Center Inc",
    "wof:placetype":"venue"
},
  "geometry": {"coordinates":[-93.318848,44.910641],"type":"Point"}
}