{
  "type": "Feature",
  "properties": {
    "iso:country":"US",
    "sg:address":"5124 Tifton Dr",
    "sg:city":"Minneapolis",
    "sg:classifiers":[
        {
            "category":"Real Estate",
            "subcategory":"Real Estate Agent",
            "type":"Services"
        }
    ],
    "sg:phone":"+1 952 844 0567",
    "sg:postcode":"55439",
    "sg:province":"MN",
    "wof:name":"Andrea Wersell Real Estate",
    "wof:placetype":"venue"
},
  "geometry": {"coordinates":[-93.356416,44.878023],"type":"Point"}
}