{
  "type": "Feature",
  "properties": {
    "addr:full":"13116 Crooked Lake Blvd NW Minneapolis MN 55448",
    "addr:housenumber":"13116",
    "addr:postcode":"55448",
    "addr:street":"Crooked Lake Blvd Nw",
    "iso:country":"US",
    "sg:address":"13116 Crooked Lake Blvd NW",
    "sg:city":"Minneapolis",
    "sg:classifiers":[
        {
            "category":"Building & Trades",
            "subcategory":"Plumbing",
            "type":"Services"
        },
        {
            "category":"Building & Trades",
            "subcategory":"Cleaning & Sanitation",
            "type":"Services"
        }
    ],
    "sg:phone":"+1 763 789 4240",
    "sg:postcode":"55448",
    "sg:province":"MN",
    "sg:tags":[
        "cleaner",
        "repairer",
        "sewer",
        "plumbing-drain"
    ],
    "wof:name":"J W Dinius Northeast Sewer Cleaning",
    "wof:placetype":"venue"
},
  "geometry": {"coordinates":[-93.337334,45.208865],"type":"Point"}
}