{
  "type": "Feature",
  "properties": {
    "addr:full":"10537 Utah Rd Minneapolis MN 55438",
    "addr:housenumber":"10537",
    "addr:postcode":"55438",
    "addr:street":"Utah Rd",
    "iso:country":"US",
    "sg:address":"10537 Utah Rd",
    "sg:city":"Minneapolis",
    "sg:classifiers":[
        {
            "category":"Building & Trades",
            "subcategory":"Construction",
            "type":"Services"
        }
    ],
    "sg:phone":"+1 952 944 5710",
    "sg:postcode":"55438",
    "sg:province":"MN",
    "sg:tags":[
        "residential"
    ],
    "wof:name":"Charles Gangelhoff",
    "wof:placetype":"venue"
},
  "geometry": {"coordinates":[-93.384792,44.813842],"type":"Point"}
}