{
  "type": "Feature",
  "properties": {
    "iso:country":"US",
    "sg:address":"10 S 5th St",
    "sg:city":"Minneapolis",
    "sg:classifiers":[
        {
            "category":"Professional",
            "subcategory":"Lawyer & Legal Services",
            "type":"Services"
        }
    ],
    "sg:phone":"+1 612 375 1555",
    "sg:postcode":"55402",
    "sg:province":"MN",
    "sg:website":"www.spencelawfirm.com",
    "wof:name":"Spence Mick Atty",
    "wof:placetype":"venue"
},
  "geometry": {"coordinates":[-93.27220199999999,44.9795],"type":"Point"}
}