{
  "type": "Feature",
  "properties": {
    "iso:country":"US",
    "sg:address":"19258 Turner Ave",
    "sg:city":"Hutchinson",
    "sg:classifiers":[
        {
            "category":"Freight",
            "type":"Transportation"
        }
    ],
    "sg:phone":"+1 320 587 4002",
    "sg:postcode":"55350",
    "sg:province":"MN",
    "sg:tags":[
        "operator",
        "gene",
        "local",
        "trucking"
    ],
    "wof:name":"Daniels G R Warehouse",
    "wof:placetype":"venue"
},
  "geometry": {"coordinates":[-94.416129,44.894086],"type":"Point"}
}