{
  "type": "Feature",
  "properties": {
    "addr:full":"925 4th St E Tracy MN 56175",
    "addr:housenumber":"925",
    "addr:postcode":"56175",
    "addr:street":"4Th St",
    "iso:country":"US",
    "sg:address":"925 4th St E",
    "sg:city":"Tracy",
    "sg:classifiers":[
        {
            "category":"Retail",
            "subcategory":"Repair Shop",
            "type":"Services"
        }
    ],
    "sg:phone":"+1 507 629 3008",
    "sg:postcode":"56175",
    "sg:province":"MN",
    "wof:name":"Lavoys Repair",
    "wof:placetype":"venue"
},
  "geometry": {"coordinates":[-95.60814499999999,44.239248],"type":"Point"}
}