{
  "type": "Feature",
  "properties": {
    "iso:country":"US",
    "sg:address":"4139 Roosevelt Rd",
    "sg:city":"St Cloud",
    "sg:classifiers":[
        {
            "category":"Wholesale",
            "subcategory":"Groceries",
            "type":"Manufacturing & Wholesale Goods"
        }
    ],
    "sg:phone":"+1 320 259 0726",
    "sg:postcode":"56301",
    "sg:province":"MN",
    "sg:tags":[
        "pizza"
    ],
    "wof:name":"Kraft Pizza",
    "wof:placetype":"venue"
},
  "geometry": {"coordinates":[-94.15217199999999,45.500325],"type":"Point"}
}