{
  "type": "Feature",
  "properties": {
    "iso:country":"US",
    "sg:address":"7194 115th St N",
    "sg:city":"St Paul",
    "sg:classifiers":[
        {
            "category":"Health Services",
            "subcategory":"Clinic",
            "type":"Services"
        }
    ],
    "sg:phone":"+1 651 209 1180",
    "sg:postcode":"55082",
    "sg:province":"MN",
    "wof:name":"Corad Health Care",
    "wof:placetype":"venue"
},
  "geometry": {"coordinates":[-92.951869,45.117151],"type":"Point"}
}