{
  "type": "Feature",
  "properties": {
    "iso:country":"US",
    "sg:address":"206 N Hill Ave",
    "sg:city":"Ogilvie",
    "sg:classifiers":[
        {
            "category":"Health Services",
            "subcategory":"Doctor",
            "type":"Services"
        }
    ],
    "sg:phone":"+1 320 272 4450",
    "sg:postcode":"56358",
    "sg:province":"MN",
    "sg:tags":[
        "dentist"
    ],
    "wof:name":"Brenda Junnila DDS Inc",
    "wof:placetype":"venue"
},
  "geometry": {"coordinates":[-93.425974,45.830419],"type":"Point"}
}