{
  "type": "Feature",
  "properties": {
    "iso:country":"US",
    "sg:address":"2508 Hennepin Ave S",
    "sg:city":"Minneapolis",
    "sg:classifiers":[
        {
            "category":"Restaurant",
            "type":"Food & Drink"
        }
    ],
    "sg:phone":"+1 952 933 9989",
    "sg:postcode":"55405",
    "sg:province":"MN",
    "sg:tags":[
        "shop",
        "coffee"
    ],
    "wof:name":"European Coffee House",
    "wof:placetype":"venue"
},
  "geometry": {"coordinates":[-93.295613,44.957296],"type":"Point"}
}