{
  "type": "Feature",
  "properties": {
    "iso:country":"US",
    "sg:address":"445 Lake St E",
    "sg:city":"Wayzata",
    "sg:classifiers":[
        {
            "category":"Health Services",
            "subcategory":"Doctor",
            "type":"Services"
        }
    ],
    "sg:phone":"+1 763 420 6834",
    "sg:postcode":"55391",
    "sg:province":"MN",
    "wof:name":"William J Kottemann DDS PA",
    "wof:placetype":"venue"
},
  "geometry": {"coordinates":[-93.51545900000001,44.970119],"type":"Point"}
}