{
  "type": "Feature",
  "properties": {
    "addr:full":"146 Wilderness Way Good Thunder MN 56037",
    "addr:housenumber":"146",
    "addr:postcode":"56037",
    "addr:street":"Wilderness Way",
    "iso:country":"US",
    "sg:address":"146 Wilderness Way",
    "sg:city":"Good Thunder",
    "sg:classifiers":[
        {
            "category":"Building & Trades",
            "subcategory":"Landscaping Services",
            "type":"Services"
        }
    ],
    "sg:phone":"+1 507 278 3414",
    "sg:postcode":"56037",
    "sg:province":"MN",
    "wof:name":"Lice Tree Nursery",
    "wof:placetype":"venue"
},
  "geometry": {"coordinates":[-93.985479,44.059289],"type":"Point"}
}