{
  "type": "Feature",
  "properties": {
    "iso:country":"US",
    "sg:address":"5115 Burning Tree Rd",
    "sg:city":"Duluth",
    "sg:classifiers":[
        {
            "category":"Health Services",
            "subcategory":"Clinic",
            "type":"Services"
        }
    ],
    "sg:phone":"+1 218 723 8080",
    "sg:postcode":"55811",
    "sg:province":"MN",
    "sg:tags":[
        "banks",
        "blood",
        "center"
    ],
    "wof:name":"Memorial Blood Ctr",
    "wof:placetype":"venue"
},
  "geometry": {"coordinates":[-92.16923199999999,46.80872],"type":"Point"}
}