{
  "type": "Feature",
  "properties": {
    "iso:country":"US",
    "sg:address":"141 Skyline Dr",
    "sg:city":"Granite Falls",
    "sg:classifiers":[
        {
            "category":"Organizations",
            "subcategory":"Membership Organization",
            "type":"Services"
        }
    ],
    "sg:phone":"+1 320 564 2419",
    "sg:postcode":"56241",
    "sg:province":"MN",
    "wof:name":"Pioneer Power Inc Hanley Falls",
    "wof:placetype":"venue"
},
  "geometry": {"coordinates":[-95.523241,44.811107],"type":"Point"}
}