{
  "type": "Feature",
  "properties": {
    "iso:country":"US",
    "sg:address":"10936 Foley Blvd NW",
    "sg:city":"Minneapolis",
    "sg:classifiers":[
        {
            "category":"Organizations",
            "subcategory":"Religious Organization",
            "type":"Services"
        }
    ],
    "sg:phone":"+1 763 755 3748",
    "sg:postcode":"55448",
    "sg:province":"MN",
    "sg:tags":[
        "child",
        "day",
        "care"
    ],
    "wof:name":"Christ Child Pre-School",
    "wof:placetype":"venue"
},
  "geometry": {"coordinates":[-93.27666600000001,45.168232],"type":"Point"}
}