{
  "type": "Feature",
  "properties": {
    "iso:country":"US",
    "sg:address":"430 S Saratoga St",
    "sg:city":"St Paul",
    "sg:classifiers":[
        {
            "category":"Professional",
            "subcategory":"Management & Consulting",
            "type":"Services"
        }
    ],
    "sg:phone":"+1 651 690 9517",
    "sg:postcode":"55105",
    "sg:province":"MN",
    "sg:tags":[
        "consultant",
        "business"
    ],
    "wof:name":"Karl Research & Consulting",
    "wof:placetype":"venue"
},
  "geometry": {"coordinates":[-93.164399,44.927227],"type":"Point"}
}