{
  "type": "Feature",
  "properties": {
    "addr:full":"507 2nd Ave NE Buffalo MN 55313",
    "addr:housenumber":"507",
    "addr:postcode":"55313",
    "addr:street":"2Nd Ave Ne",
    "iso:country":"US",
    "sg:address":"507 2nd Ave NE",
    "sg:city":"Buffalo",
    "sg:classifiers":[
        {
            "category":"Retail",
            "subcategory":"Repair Shop",
            "type":"Services"
        }
    ],
    "sg:phone":"+1 763 682 5858",
    "sg:postcode":"55313",
    "sg:province":"MN",
    "sg:tags":[
        "gun",
        "gunsmith"
    ],
    "wof:name":"Bison Arms Company",
    "wof:placetype":"venue"
},
  "geometry": {"coordinates":[-93.873226,45.178222],"type":"Point"}
}