{
  "type": "Feature",
  "properties": {
    "addr:full":"701 Soo Ln Buffalo MN 55313",
    "addr:housenumber":"701",
    "addr:postcode":"55313",
    "addr:street":"Soo Ln",
    "iso:country":"US",
    "sg:address":"701 Soo Ln",
    "sg:city":"Buffalo",
    "sg:classifiers":[
        {
            "category":"Restaurant",
            "type":"Food & Drink"
        },
        {
            "category":"Local Transit",
            "type":"Transportation"
        }
    ],
    "sg:menulink":"http://www.allmenus.com/mn/buffalo/151364-subway/menu/",
    "sg:phone":"+1 763 682 1819",
    "sg:postcode":"55313",
    "sg:province":"MN",
    "sg:tags":[
        "american",
        "sandwich"
    ],
    "wof:name":"Subway",
    "wof:placetype":"venue"
},
  "geometry": {"coordinates":[-93.87227300000001,45.178454],"type":"Point"}
}