{
  "type": "Feature",
  "properties": {
    "addr:full":"4700 Welcome Ave N Minneapolis MN 55429",
    "addr:housenumber":"4700",
    "addr:postcode":"55429",
    "addr:street":"Welcome Ave N",
    "iso:country":"US",
    "sg:address":"4700 Welcome Ave N",
    "sg:city":"Minneapolis",
    "sg:classifiers":[
        {
            "category":"Building & Trades",
            "subcategory":"Construction",
            "type":"Services"
        }
    ],
    "sg:phone":"+1 763 535 7833",
    "sg:postcode":"55429",
    "sg:province":"MN",
    "sg:tags":[
        "excavation",
        "contractor"
    ],
    "wof:name":"E S Plumbing & Heating",
    "wof:placetype":"venue"
},
  "geometry": {"coordinates":[-93.35142399999999,45.041827],"type":"Point"}
}