{
  "type": "Feature",
  "properties": {
    "addr:full":"313 Main St S Sauk Centre MN 56378",
    "addr:housenumber":"313",
    "addr:postcode":"56378",
    "addr:street":"Main St S Sauk Centre",
    "iso:country":"US",
    "sg:address":"313 Main St S",
    "sg:city":"Sauk Centre",
    "sg:classifiers":[
        {
            "category":"Professional",
            "type":"Services"
        }
    ],
    "sg:phone":"+1 320 351 8141",
    "sg:postcode":"56378",
    "sg:province":"MN",
    "sg:tags":[
        "establishment"
    ],
    "wof:name":"Extras",
    "wof:placetype":"venue"
},
  "geometry": {"coordinates":[-94.95187199999999,45.736957],"type":"Point"}
}