{
  "type": "Feature",
  "properties": {
    "addr:full":"1137 Cedar View Dr Minneapolis MN 55405",
    "addr:housenumber":"1137",
    "addr:postcode":"55405",
    "addr:street":"Cedar View Dr",
    "iso:country":"US",
    "sg:address":"1137 Cedar View Dr",
    "sg:city":"Minneapolis",
    "sg:phone":"+1 612 871 9169",
    "sg:postcode":"55405",
    "sg:province":"MN",
    "wof:name":"Loring Car Wash",
    "wof:placetype":"venue"
},
  "geometry": {"coordinates":[-93.31695499999999,44.967486],"type":"Point"}
}