{
  "type": "Feature",
  "properties": {
    "iso:country":"US",
    "sg:address":"2160 Xylon Ave N",
    "sg:city":"Minneapolis",
    "sg:classifiers":[
        {
            "category":"Professional",
            "subcategory":"Management & Consulting",
            "type":"Services"
        }
    ],
    "sg:phone":"+1 952 545 0544",
    "sg:postcode":"55427",
    "sg:province":"MN",
    "sg:tags":[
        "sport"
    ],
    "wof:name":"Sutton Co Inc",
    "wof:placetype":"venue"
},
  "geometry": {"coordinates":[-93.38598399999999,45.001749],"type":"Point"}
}