{
  "type": "Feature",
  "properties": {
    "iso:country":"US",
    "sg:address":"228 Central Ave N",
    "sg:city":"Faribault",
    "sg:classifiers":[
        {
            "category":"Home & Garden",
            "subcategory":"Building Materials",
            "type":"Retail Goods"
        }
    ],
    "sg:phone":"+1 507 332 4010",
    "sg:postcode":"55021",
    "sg:province":"MN",
    "wof:name":"Picture Perfect Windows",
    "wof:placetype":"venue"
},
  "geometry": {"coordinates":[-93.268432,44.29331],"type":"Point"}
}