{
  "type": "Feature",
  "properties": {
    "addr:full":"940 Co Rd 6 SW Stewartville MN 55976",
    "addr:housenumber":"940",
    "addr:postcode":"55976",
    "addr:street":"Co Rd 6 Sw",
    "iso:country":"US",
    "sg:address":"940 Co Rd 6 SW",
    "sg:city":"Stewartville",
    "sg:classifiers":[
        {
            "category":"Social Services",
            "subcategory":"Child Care",
            "type":"Services"
        }
    ],
    "sg:phone":"+1 507 533 6993",
    "sg:postcode":"55976",
    "sg:province":"MN",
    "sg:tags":[
        "day",
        "provider"
    ],
    "wof:name":"Country Kids Daycare",
    "wof:placetype":"venue"
},
  "geometry": {"coordinates":[-92.514185,43.848245],"type":"Point"}
}