{
  "type": "Feature",
  "properties": {
    "addr:full":"310 4th St NE Staples MN 56479",
    "addr:housenumber":"310",
    "addr:postcode":"56479",
    "addr:street":"4Th St Ne",
    "iso:country":"US",
    "sg:address":"310 4th St NE",
    "sg:city":"Staples",
    "sg:classifiers":[
        {
            "category":"Organizations",
            "subcategory":"Religious Organization",
            "type":"Services"
        }
    ],
    "sg:phone":"+1 218 894 2296",
    "sg:postcode":"56479",
    "sg:province":"MN",
    "sg:tags":[
        "church"
    ],
    "wof:name":"Sacred Heart Catholic Church",
    "wof:placetype":"venue"
},
  "geometry": {"coordinates":[-94.79476699999999,46.357595],"type":"Point"}
}