{
  "type": "Feature",
  "properties": {
    "iso:country":"US",
    "sg:address":"310 4th St NE",
    "sg:city":"Staples",
    "sg:classifiers":[
        {
            "category":"Organizations",
            "subcategory":"Religious Organization",
            "type":"Services"
        }
    ],
    "sg:phone":"+1 218 894 2296",
    "sg:postcode":"56479",
    "sg:province":"MN",
    "sg:tags":[
        "church"
    ],
    "wof:name":"Sacred Heart Catholic Church",
    "wof:placetype":"venue"
},
  "geometry": {"coordinates":[-94.79476699999999,46.357595],"type":"Point"}
}