{
  "type": "Feature",
  "properties": {
    "addr:full":"8432 Surrakka Rd Cloquet MN 55720",
    "addr:housenumber":"8432",
    "addr:postcode":"55720",
    "addr:street":"Surrakka Rd",
    "iso:country":"US",
    "sg:address":"8432 Surrakka Rd",
    "sg:city":"Cloquet",
    "sg:classifiers":[
        {
            "category":"Building & Trades",
            "subcategory":"Construction",
            "type":"Services"
        }
    ],
    "sg:phone":"+1 218 879 1608",
    "sg:postcode":"55720",
    "sg:province":"MN",
    "sg:tags":[
        "house"
    ],
    "wof:name":"Cloquet Constructors",
    "wof:placetype":"venue"
},
  "geometry": {"coordinates":[-92.557907,46.809454],"type":"Point"}
}