{
  "type": "Feature",
  "properties": {
    "addr:full":"5711 Xerxes Ave N Minneapolis MN 55430",
    "addr:housenumber":"5711",
    "addr:postcode":"55430",
    "addr:street":"Xerxes Ave N",
    "iso:country":"US",
    "sg:address":"5711 Xerxes Ave N",
    "sg:city":"Minneapolis",
    "sg:classifiers":[
        {
            "category":"Restaurant",
            "type":"Food & Drink"
        }
    ],
    "sg:menulink":"http://www.allmenus.com/mn/brooklyn-center/229769-leeann-chin/menu/",
    "sg:phone":"+1 763 561 9020",
    "sg:postcode":"55430",
    "sg:province":"MN",
    "sg:tags":[
        "american",
        "asian",
        "chinese"
    ],
    "wof:name":"Leeann Chin",
    "wof:placetype":"venue"
},
  "geometry": {"coordinates":[-93.321843,45.056979],"type":"Point"}
}