{
  "type": "Feature",
  "properties": {
    "iso:country":"US",
    "sg:address":"1130 Hennepin Ave N",
    "sg:city":"Glencoe",
    "sg:classifiers":[
        {
            "category":"Shopping",
            "type":"Retail Goods"
        }
    ],
    "sg:phone":"+1 320 864 5262",
    "sg:postcode":"55336",
    "sg:province":"MN",
    "sg:tags":[
        "supply",
        "hearing",
        "equipment",
        "health",
        "impaired",
        "merchandise"
    ],
    "wof:name":"Hearing Care Specialists Inc",
    "wof:placetype":"venue"
},
  "geometry": {"coordinates":[-94.151669,44.770737],"type":"Point"}
}