{
  "type": "Feature",
  "properties": {
    "iso:country":"US",
    "sg:address":"1430 Maryland Ave E",
    "sg:city":"St Paul",
    "sg:classifiers":[
        {
            "category":"Professional",
            "subcategory":"Testing Lab",
            "type":"Services"
        },
        {
            "category":"Government",
            "subcategory":"Office",
            "type":"Public Place"
        },
        {
            "category":"Government",
            "subcategory":"Police Station",
            "type":"Public Place"
        }
    ],
    "sg:phone":"+1 651 642 0660",
    "sg:postcode":"55106",
    "sg:province":"MN",
    "sg:tags":[
        "laboratory",
        "state",
        "executive"
    ],
    "wof:name":"Bureau Criminal Apprehension",
    "wof:placetype":"venue"
},
  "geometry": {"coordinates":[-93.03868199999999,44.977453],"type":"Point"}
}