{
  "type": "Feature",
  "properties": {
    "iso:country":"US",
    "sg:address":"9665 265th St",
    "sg:city":"Elko",
    "sg:classifiers":[
        {
            "category":"Sports & Exercise",
            "subcategory":"Race Track",
            "type":"Entertainment"
        }
    ],
    "sg:phone":"+1 952 461 3300",
    "sg:postcode":"55020",
    "sg:province":"MN",
    "sg:tags":[
        "operation",
        "racing",
        "or"
    ],
    "wof:name":"Brothers Jorgenson Racing Inc",
    "wof:placetype":"venue"
},
  "geometry": {"coordinates":[-93.32783000000001,44.565599],"type":"Point"}
}