{
  "type": "Feature",
  "properties": {
    "iso:country":"US",
    "sg:address":"13033 Ridgedale Dr",
    "sg:city":"Hopkins",
    "sg:classifiers":[
        {
            "category":"Wholesale",
            "subcategory":"Stationery",
            "type":"Manufacturing & Wholesale Goods"
        }
    ],
    "sg:phone":"+1 952 886 7337",
    "sg:postcode":"55305",
    "sg:province":"MN",
    "sg:tags":[
        "paper"
    ],
    "wof:name":"Mayflower Properties",
    "wof:placetype":"venue"
},
  "geometry": {"coordinates":[-93.45102300000001,44.970592],"type":"Point"}
}