{
  "type": "Feature",
  "properties": {
    "iso:country":"US",
    "sg:address":"861 85th St",
    "sg:city":"Sherburn",
    "sg:classifiers":[
        {
            "category":"Farming",
            "subcategory":"Farm",
            "type":"Manufacturing & Wholesale Goods"
        }
    ],
    "sg:phone":"+1 507 764 4440",
    "sg:postcode":"56171",
    "sg:province":"MN",
    "sg:tags":[
        "crop",
        "general"
    ],
    "wof:name":"Ryan Kahler",
    "wof:placetype":"venue"
},
  "geometry": {"coordinates":[-94.711687,43.609638],"type":"Point"}
}