{
  "type": "Feature",
  "properties": {
    "addr:full":"17547 Bijou Cir Lake Park MN 56554",
    "addr:postcode":"17547;56554",
    "addr:street":"Bijou Cir;Park",
    "iso:country":"US",
    "sg:address":"17547 Bijou Cir",
    "sg:city":"Lake Park",
    "sg:classifiers":[
        {
            "category":"Building & Trades",
            "subcategory":"Construction",
            "type":"Services"
        }
    ],
    "sg:phone":"+1 218 238 6604",
    "sg:postcode":"56554",
    "sg:province":"MN",
    "sg:tags":[
        "a",
        "as",
        "general",
        "operates",
        "contractor"
    ],
    "wof:name":"Gms New Creation Construction",
    "wof:placetype":"venue"
},
  "geometry": {"coordinates":[-96.151275,46.823664],"type":"Point"}
}