{
  "type": "Feature",
  "properties": {
    "iso:country":"US",
    "sg:address":"200 E Travelers Trl Ste 105",
    "sg:city":"Burnsville",
    "sg:classifiers":[
        {
            "category":"Health Services",
            "subcategory":"Health Practitioner",
            "type":"Services"
        },
        {
            "category":"Health Services",
            "subcategory":"Chiropractor",
            "type":"Services"
        }
    ],
    "sg:phone":"+1 952 707 0110",
    "sg:postcode":"55337",
    "sg:province":"MN",
    "sg:tags":[
        "acupuncture"
    ],
    "sg:website":"www.southviewchiro.com",
    "wof:name":"Southview Chiropractic",
    "wof:placetype":"venue"
},
  "geometry": {"coordinates":[-93.27548899999999,44.775352],"type":"Point"}
}