{
  "type": "Feature",
  "properties": {
    "iso:country":"US",
    "sg:address":"304 Washington Ave N",
    "sg:city":"Minneapolis",
    "sg:classifiers":[
        {
            "category":"Food & Beverages",
            "subcategory":"Specialty",
            "type":"Retail Goods"
        }
    ],
    "sg:phone":"+1 612 340 0078",
    "sg:postcode":"55401",
    "sg:province":"MN",
    "sg:tags":[
        "tea",
        "coffee"
    ],
    "sg:website":"www.marysburgbooks.com",
    "wof:name":"Marysburg Books Coffee",
    "wof:placetype":"venue"
},
  "geometry": {"coordinates":[-93.273803,44.985326],"type":"Point"}
}