{
  "type": "Feature",
  "properties": {
    "iso:country":"US",
    "sg:address":"120 State St W",
    "sg:city":"Cannon Falls",
    "sg:classifiers":[
        {
            "category":"Social Services",
            "type":"Services"
        }
    ],
    "sg:phone":"+1 507 263 2136",
    "sg:postcode":"55009",
    "sg:province":"MN",
    "wof:name":"Shepherds Center of Cannon Vly",
    "wof:placetype":"venue"
},
  "geometry": {"coordinates":[-92.90152999999999,44.510088],"type":"Point"}
}