{
  "type": "Feature",
  "properties": {
    "addr:full":"1223 S Broadway St New Ulm MN 56073",
    "addr:housenumber":"1223",
    "addr:postcode":"56073",
    "addr:street":"S Broadway St",
    "iso:country":"US",
    "sg:address":"1223 S Broadway St",
    "sg:city":"New Ulm",
    "sg:classifiers":[
        {
            "category":"Personal",
            "subcategory":"Beauty Salon",
            "type":"Services"
        }
    ],
    "sg:phone":"+1 507 359 7300",
    "sg:postcode":"56073",
    "sg:province":"MN",
    "sg:tags":[
        "shop"
    ],
    "wof:name":"Salon Masters",
    "wof:placetype":"venue"
},
  "geometry": {"coordinates":[-94.448927,44.300662],"type":"Point"}
}