{
  "type": "Feature",
  "properties": {
    "iso:country":"US",
    "sg:address":"7600 Parklawn Ave",
    "sg:city":"Edina",
    "sg:classifiers":[
        {
            "category":"Insurance",
            "subcategory":"Insurance Agent",
            "type":"Services"
        }
    ],
    "sg:phone":"+1 952 831 3836",
    "sg:postcode":"55435",
    "sg:province":"MN",
    "wof:name":"MSI Insurance",
    "wof:placetype":"venue"
},
  "geometry": {"coordinates":[-93.335984,44.865373],"type":"Point"}
}