{
  "type": "Feature",
  "properties": {
    "addr:full":"6025 Penn Ave S Minneapolis MN 55419",
    "addr:housenumber":"6025",
    "addr:postcode":"55419",
    "addr:street":"Penn Ave S",
    "iso:country":"US",
    "sg:address":"6025 Penn Ave S",
    "sg:city":"Minneapolis",
    "sg:classifiers":[
        {
            "category":"Shopping",
            "type":"Retail Goods"
        }
    ],
    "sg:phone":"+1 612 861 2883",
    "sg:postcode":"55419",
    "sg:province":"MN",
    "sg:tags":[
        "merchandise"
    ],
    "wof:name":"Aussie Pet Mobile Minneapolis",
    "wof:placetype":"venue"
},
  "geometry": {"coordinates":[-93.308588,44.892993],"type":"Point"}
}