{
  "type": "Feature",
  "properties": {
    "iso:country":"US",
    "sg:address":"1515 Sinclair Lewis Ave",
    "sg:city":"Sauk Centre",
    "sg:classifiers":[
        {
            "category":"Shopping",
            "subcategory":"Bicycles & Sporting Goods",
            "type":"Retail Goods"
        }
    ],
    "sg:phone":"+1 320 352 2155",
    "sg:postcode":"56378",
    "sg:province":"MN",
    "wof:name":"Fletcher Bait & Tackle",
    "wof:placetype":"venue"
},
  "geometry": {"coordinates":[-94.96793099999999,45.736886],"type":"Point"}
}