{
  "type": "Feature",
  "properties": {
    "iso:country":"US",
    "sg:address":"888 Cooper Ln",
    "sg:city":"Saint Paul",
    "sg:classifiers":[
        {
            "category":"Building & Trades",
            "subcategory":"Plumbing",
            "type":"Services"
        }
    ],
    "sg:phone":"+1 952 432 0908",
    "sg:postcode":"55124",
    "sg:province":"MN",
    "sg:tags":[
        "contractor"
    ],
    "wof:name":"Witt and Associates Inc",
    "wof:placetype":"venue"
},
  "geometry": {"coordinates":[-93.233608,44.7254],"type":"Point"}
}