{
  "type": "Feature",
  "properties": {
    "iso:country":"US",
    "sg:address":"7705 Western Ave",
    "sg:city":"Meadowlands",
    "sg:classifiers":[
        {
            "category":"Utilities",
            "subcategory":"Telephone",
            "type":"Services"
        }
    ],
    "sg:phone":"+1 218 260 4111",
    "sg:postcode":"55765",
    "sg:province":"MN",
    "sg:tags":[
        "telecommunication"
    ],
    "wof:name":"Robison Computer Services Inc",
    "wof:placetype":"venue"
},
  "geometry": {"coordinates":[-92.733923,47.070689],"type":"Point"}
}