{
  "type": "Feature",
  "properties": {
    "iso:country":"US",
    "sg:address":"23601 Natchez Ave",
    "sg:city":"Stacy",
    "sg:classifiers":[
        {
            "category":"Building & Trades",
            "subcategory":"Construction",
            "type":"Services"
        }
    ],
    "sg:phone":"+1 651 462 1104",
    "sg:postcode":"55044",
    "sg:province":"MN",
    "sg:tags":[
        "carpentry",
        "contractor"
    ],
    "wof:name":"Jbs Carpentry",
    "wof:placetype":"venue"
},
  "geometry": {"coordinates":[-93.338618,44.601932],"type":"Point"}
}