{
  "type": "Feature",
  "properties": {
    "addr:full":"525 4th St NW Faribault MN 55021",
    "addr:housenumber":"525",
    "addr:postcode":"55021",
    "addr:street":"4Th St Nw",
    "iso:country":"US",
    "sg:address":"525 4th St NW",
    "sg:city":"Faribault",
    "sg:classifiers":[
        {
            "category":"Restaurant",
            "type":"Food & Drink"
        }
    ],
    "sg:menulink":"http://www.allmenus.com/mn/faribault/193942-mcdonalds/menu/",
    "sg:postcode":"55021",
    "sg:province":"MN",
    "sg:tags":[
        "burger",
        "american"
    ],
    "wof:name":"McDonald's",
    "wof:placetype":"venue"
},
  "geometry": {"coordinates":[-93.27661500000001,44.294685],"type":"Point"}
}