{
  "type": "Feature",
  "properties": {
    "addr:full":"336 E Broadway Minneapolis MN 55425",
    "addr:housenumber":"336",
    "addr:postcode":"55425",
    "addr:street":"E Broadway",
    "iso:country":"US",
    "sg:address":"336 E Broadway",
    "sg:city":"Minneapolis",
    "sg:phone":"+1 952 854 1498",
    "sg:postcode":"55425",
    "sg:province":"MN",
    "sg:website":"http://www.dollartree.com/",
    "wof:name":"Dollar Tree",
    "wof:placetype":"venue"
},
  "geometry": {"coordinates":[-93.24044499999999,44.854399],"type":"Point"}
}