{
  "type": "Feature",
  "properties": {
    "addr:full":"191 S River Ridge Cir Burnsville MN 55337",
    "addr:housenumber":"191",
    "addr:postcode":"55337",
    "addr:street":"S River Ridge Cir",
    "iso:country":"US",
    "sg:address":"191 S River Ridge Cir",
    "sg:city":"Burnsville",
    "sg:classifiers":[
        {
            "category":"Shopping",
            "subcategory":"Antiques",
            "type":"Retail Goods"
        }
    ],
    "sg:phone":"+1 952 894 7200",
    "sg:postcode":"55337",
    "sg:province":"MN",
    "wof:name":"Antiques Minnesota",
    "wof:placetype":"venue"
},
  "geometry": {"coordinates":[-93.282898,44.777199],"type":"Point"}
}