{
  "type": "Feature",
  "properties": {
    "iso:country":"US",
    "sg:address":"2748 Hennepin Ave",
    "sg:city":"Minneapolis",
    "sg:classifiers":[
        {
            "category":"Real Estate",
            "subcategory":"Architect",
            "type":"Services"
        }
    ],
    "sg:phone":"+1 612 870 7507",
    "sg:postcode":"55408",
    "sg:province":"MN",
    "sg:tags":[
        "architects'",
        "specification",
        "construction",
        "builders'",
        "architectural"
    ],
    "sg:website":"http://www.domainarch.com",
    "wof:name":"Domain Architecture & Design",
    "wof:placetype":"venue"
},
  "geometry": {"coordinates":[-93.298401,44.952202],"type":"Point"}
}