{
  "type": "Feature",
  "properties": {
    "iso:country":"US",
    "sg:address":"7300 France Ave S Ste 323",
    "sg:city":"Minneapolis",
    "sg:classifiers":[
        {
            "category":"Professional",
            "type":"Services"
        }
    ],
    "sg:phone":"+1 952 837 1852",
    "sg:postcode":"55435",
    "sg:province":"MN",
    "sg:tags":[
        "motion",
        "technician",
        "picture"
    ],
    "sg:website":"http://www.matrixv.com",
    "wof:name":"Matrix Video Inc",
    "wof:placetype":"venue"
},
  "geometry": {"coordinates":[-93.32901,44.871109],"type":"Point"}
}