{
  "type": "Feature",
  "properties": {
    "addr:full":"7974 Hwy 135 N Embarrass MN 55732",
    "addr:housenumber":"7974",
    "addr:postcode":"55732",
    "addr:street":"Hwy 135 N",
    "iso:country":"US",
    "sg:address":"7974 Hwy 135 N",
    "sg:city":"Embarrass",
    "sg:classifiers":[
        {
            "category":"Social Services",
            "subcategory":"Child Care",
            "type":"Services"
        }
    ],
    "sg:phone":"+1 218 984 2829",
    "sg:postcode":"55732",
    "sg:province":"MN",
    "sg:tags":[
        "daycare",
        "provider"
    ],
    "wof:name":"Hildebrandt Viona",
    "wof:placetype":"venue"
},
  "geometry": {"coordinates":[-92.289491,47.699316],"type":"Point"}
}