{
  "type": "Feature",
  "properties": {
    "iso:country":"US",
    "sg:address":"615 Lake St S",
    "sg:city":"Long Prairie",
    "sg:classifiers":[
        {
            "category":"Organizations",
            "subcategory":"Professional Association",
            "type":"Services"
        }
    ],
    "sg:phone":"+1 320 732 6914",
    "sg:postcode":"56347",
    "sg:province":"MN",
    "sg:tags":[
        "business"
    ],
    "wof:name":"Firemens Relief Associations",
    "wof:placetype":"venue"
},
  "geometry": {"coordinates":[-94.865622,45.965279],"type":"Point"}
}