{
  "type": "Feature",
  "properties": {
    "addr:full":"2721 E 42nd St Minneapolis MN 55406",
    "addr:housenumber":"2721",
    "addr:postcode":"55406",
    "addr:street":"E 42Nd St",
    "iso:country":"US",
    "sg:address":"2721 E 42nd St",
    "sg:city":"Minneapolis",
    "sg:classifiers":[
        {
            "category":"Organizations",
            "subcategory":"Labor Organization",
            "type":"Services"
        }
    ],
    "sg:phone":"+1 612 721 1833",
    "sg:postcode":"55406",
    "sg:province":"MN",
    "wof:name":"Abatement Workers Local 205",
    "wof:placetype":"venue"
},
  "geometry": {"coordinates":[-93.232304,44.926803],"type":"Point"}
}