{
  "type": "Feature",
  "properties": {
    "addr:full":"48115 510th St Perham MN 56573",
    "addr:housenumber":"48115",
    "addr:postcode":"56573",
    "addr:street":"510Th St",
    "iso:country":"US",
    "sg:address":"48115 510th St",
    "sg:city":"Perham",
    "sg:classifiers":[
        {
            "category":"Farming",
            "subcategory":"Dairy Farm",
            "type":"Manufacturing & Wholesale Goods"
        },
        {
            "category":"Farming",
            "subcategory":"Farm",
            "type":"Manufacturing & Wholesale Goods"
        }
    ],
    "sg:phone":"+1 218 346 4972",
    "sg:postcode":"56573",
    "sg:province":"MN",
    "sg:website":"http://www.larrymanningrealty.com",
    "wof:name":"Manning Farms",
    "wof:placetype":"venue"
},
  "geometry": {"coordinates":[-95.483369,46.701431],"type":"Point"}
}