{
  "type": "Feature",
  "properties": {
    "addr:full":"710 E Wabasha St Winona MN 55987",
    "addr:housenumber":"710",
    "addr:postcode":"55987",
    "addr:street":"E Wabasha St",
    "iso:country":"US",
    "sg:address":"710 E Wabasha St",
    "sg:city":"Winona",
    "sg:classifiers":[
        {
            "category":"Social Services",
            "subcategory":"Child Care",
            "type":"Services"
        }
    ],
    "sg:phone":"+1 507 452 7848",
    "sg:postcode":"55987",
    "sg:province":"MN",
    "sg:tags":[
        "nursery",
        "day"
    ],
    "wof:name":"Stacy Rossin",
    "wof:placetype":"venue"
},
  "geometry": {"coordinates":[-91.621191,44.043612],"type":"Point"}
}