{
  "type": "Feature",
  "properties": {
    "addr:full":"805 5th St NW Kasson MN 55944",
    "addr:housenumber":"805",
    "addr:postcode":"55944",
    "addr:street":"5Th St Nw",
    "iso:country":"US",
    "sg:address":"805 5th St NW",
    "sg:city":"Kasson",
    "sg:classifiers":[
        {
            "category":"Wholesale",
            "subcategory":"Non-durable Goods",
            "type":"Manufacturing & Wholesale Goods"
        }
    ],
    "sg:phone":"+1 507 634 4775",
    "sg:postcode":"55944",
    "sg:province":"MN",
    "wof:name":"Pat Dibble Baskets & ACC",
    "wof:placetype":"venue"
},
  "geometry": {"coordinates":[-92.759533,44.03416],"type":"Point"}
}