{
  "type": "Feature",
  "properties": {
    "iso:country":"US",
    "sg:address":"17998 221st Ave",
    "sg:city":"Big Lake",
    "sg:classifiers":[
        {
            "category":"Freight",
            "type":"Transportation"
        }
    ],
    "sg:phone":"+1 763 263 6125",
    "sg:postcode":"55309",
    "sg:province":"MN",
    "sg:tags":[
        "operator",
        "local",
        "trucking"
    ],
    "wof:name":"Vances Trucking Service Inc",
    "wof:placetype":"venue"
},
  "geometry": {"coordinates":[-93.718801,45.371332],"type":"Point"}
}