{
  "type": "Feature",
  "properties": {
    "iso:country":"US",
    "sg:address":"105 Main St E",
    "sg:city":"Hinckley",
    "sg:classifiers":[
        {
            "category":"Insurance",
            "subcategory":"Hazard Insurance",
            "type":"Services"
        },
        {
            "category":"Insurance",
            "subcategory":"Insurance Agent",
            "type":"Services"
        },
        {
            "category":"Insurance",
            "subcategory":"Life Insurance",
            "type":"Services"
        },
        {
            "category":"Insurance",
            "subcategory":"Title Insurance",
            "type":"Services"
        }
    ],
    "sg:phone":"+1 320 384 6334",
    "sg:postcode":"55037",
    "sg:province":"MN",
    "sg:tags":[
        "auto",
        "commercial",
        "business",
        "homeowner"
    ],
    "sg:website":"http://www.farmersagent.com/dkroschel/",
    "wof:name":"Deborah Kroschel - Farmers Insurance",
    "wof:placetype":"venue"
},
  "geometry": {"coordinates":[-92.942791,46.015735],"type":"Point"}
}