{
  "type": "Feature",
  "properties": {
    "addr:full":"9701 Avocet St NW Coon Rapids MN 55433",
    "addr:housenumber":"9701",
    "addr:postcode":"55433",
    "addr:street":"Avocet St Nw",
    "iso:country":"US",
    "sg:address":"9701 Avocet St NW",
    "sg:city":"Coon Rapids",
    "sg:classifiers":[
        {
            "category":"Professional",
            "subcategory":"Business Services",
            "type":"Services"
        }
    ],
    "sg:phone":"+1 763 754 3975",
    "sg:postcode":"55433",
    "sg:province":"MN",
    "sg:tags":[
        "information",
        "referral"
    ],
    "wof:name":"DSM Information Svc Inc",
    "wof:placetype":"venue"
},
  "geometry": {"coordinates":[-93.301191,45.148936],"type":"Point"}
}