{
  "type": "Feature",
  "properties": {
    "iso:country":"US",
    "sg:address":"2525 E Franklin Ave",
    "sg:city":"Minneapolis",
    "sg:classifiers":[
        {
            "category":"Professional",
            "subcategory":"Accounting & Tax Preparation",
            "type":"Services"
        }
    ],
    "sg:phone":"+1 612 746 4200",
    "sg:postcode":"55406",
    "sg:province":"MN",
    "sg:tags":[
        "accountant"
    ],
    "wof:name":"Mohamed A Egeh CPA",
    "wof:placetype":"venue"
},
  "geometry": {"coordinates":[-93.2229,44.938599],"type":"Point"}
}