{
  "type": "Feature",
  "properties": {
    "iso:country":"US",
    "sg:address":"18 Main St S",
    "sg:city":"Hutchinson",
    "sg:classifiers":[
        {
            "category":"Insurance",
            "subcategory":"Insurance Agent",
            "type":"Services"
        }
    ],
    "sg:phone":"+1 320 587 2071",
    "sg:postcode":"55350",
    "sg:province":"MN",
    "wof:name":"Albers Insurance",
    "wof:placetype":"venue"
},
  "geometry": {"coordinates":[-94.369379,44.892066],"type":"Point"}
}