{
  "type": "Feature",
  "properties": {
    "iso:country":"US",
    "sg:address":"708 Grant Ave",
    "sg:city":"Mankato",
    "sg:classifiers":[
        {
            "category":"Professional",
            "subcategory":"Engineering",
            "type":"Services"
        }
    ],
    "sg:phone":"+1 507 345 6971",
    "sg:postcode":"56003",
    "sg:province":"MN",
    "wof:name":"D E F Associates",
    "wof:placetype":"venue"
},
  "geometry": {"coordinates":[-94.01883100000001,44.172814],"type":"Point"}
}