{
  "type": "Feature",
  "properties": {
    "addr:full":"119 Main St W New Prague MN 56071",
    "addr:housenumber":"119",
    "addr:postcode":"56071",
    "addr:street":"Main St W",
    "iso:country":"US",
    "sg:address":"119 Main St W",
    "sg:city":"New Prague",
    "sg:classifiers":[
        {
            "category":"Shopping",
            "subcategory":"Jewelry",
            "type":"Retail Goods"
        }
    ],
    "sg:phone":"+1 952 758 2422",
    "sg:postcode":"56071",
    "sg:province":"MN",
    "sg:tags":[
        "merchandise",
        "jeweler"
    ],
    "wof:name":"Marquardt Jewelers Inc",
    "wof:placetype":"venue"
},
  "geometry": {"coordinates":[-93.577596,44.543653],"type":"Point"}
}