{
  "type": "Feature",
  "properties": {
    "addr:full":"307 N State St Waseca MN 56093",
    "addr:housenumber":"307",
    "addr:postcode":"56093",
    "addr:street":"N State St",
    "iso:country":"US",
    "sg:address":"307 N State St",
    "sg:city":"Waseca",
    "sg:classifiers":[
        {
            "category":"Government",
            "subcategory":"Office",
            "type":"Public Place"
        }
    ],
    "sg:phone":"+1 507 835 0610",
    "sg:postcode":"56093",
    "sg:province":"MN",
    "sg:tags":[
        "executive"
    ],
    "wof:name":"County Auditor Office",
    "wof:placetype":"venue"
},
  "geometry": {"coordinates":[-93.507321,44.080319],"type":"Point"}
}