{
  "type": "Feature",
  "properties": {
    "iso:country":"US",
    "sg:address":"4635 Nicols Rd Ste 200",
    "sg:city":"Saint Paul",
    "sg:classifiers":[
        {
            "category":"Health Services",
            "subcategory":"Clinic",
            "type":"Services"
        }
    ],
    "sg:phone":"+1 651 454 0684",
    "sg:postcode":"55122",
    "sg:province":"MN",
    "sg:tags":[
        "counseling",
        "mental"
    ],
    "wof:name":"South Suburban Psychological & Counseling Svcs",
    "wof:placetype":"venue"
},
  "geometry": {"coordinates":[-93.218002,44.7887],"type":"Point"}
}