{
  "type": "Feature",
  "properties": {
    "iso:country":"US",
    "sg:address":"4500 Lyndale Ave S",
    "sg:city":"Minneapolis",
    "sg:classifiers":[
        {
            "category":"Organizations",
            "subcategory":"Religious Organization",
            "type":"Services"
        }
    ],
    "sg:phone":"+1 612 822 3139",
    "sg:postcode":"55419",
    "sg:province":"MN",
    "sg:tags":[
        "church"
    ],
    "wof:name":"Visitation Church",
    "wof:placetype":"venue"
},
  "geometry": {"coordinates":[-93.288315,44.919567],"type":"Point"}
}