{
  "type": "Feature",
  "properties": {
    "addr:full":"8587 Edinburgh Centre Dr N Minneapolis MN 55443",
    "addr:housenumber":"8587",
    "addr:postcode":"55443",
    "addr:street":"Edinburgh Centre Dr N",
    "iso:country":"US",
    "sg:address":"8587 Edinburgh Centre Dr N",
    "sg:city":"Minneapolis",
    "sg:classifiers":[
        {
            "category":"Restaurant",
            "type":"Food & Drink"
        }
    ],
    "sg:phone":"+1 763 315 8852",
    "sg:postcode":"55443",
    "sg:province":"MN",
    "wof:name":"Thanh Nhung Restaurant",
    "wof:placetype":"venue"
},
  "geometry": {"coordinates":[-93.303513,45.11134],"type":"Point"}
}