{
  "type": "Feature",
  "properties": {
    "addr:full":"2392 Leibel St White Bear Lake MN 55110",
    "addr:housenumber":"2392",
    "addr:postcode":"55110",
    "addr:street":"Leibel St",
    "iso:country":"US",
    "sg:address":"2392 Leibel St",
    "sg:city":"White Bear Lake",
    "sg:classifiers":[
        {
            "category":"Building & Trades",
            "subcategory":"Cleaning & Sanitation",
            "type":"Services"
        }
    ],
    "sg:phone":"+1 651 426 2959",
    "sg:postcode":"55110",
    "sg:province":"MN",
    "sg:tags":[
        "house"
    ],
    "wof:name":"Touch Of Class Cleaning",
    "wof:placetype":"venue"
},
  "geometry": {"coordinates":[-92.997709,45.12182],"type":"Point"}
}