{
  "type": "Feature",
  "properties": {
    "addr:full":"5020 Miller Trunk Hwy Hermantown MN 55811",
    "addr:housenumber":"5020",
    "addr:postcode":"55811",
    "addr:street":"Miller Trunk Hwy",
    "iso:country":"US",
    "sg:address":"5020 Miller Trunk Hwy",
    "sg:city":"Hermantown",
    "sg:classifiers":[
        {
            "category":"Retail",
            "subcategory":"Car Wash",
            "type":"Services"
        }
    ],
    "sg:phone":"+1 218 729 1678",
    "sg:postcode":"55811",
    "sg:province":"MN",
    "sg:tags":[
        "polishing",
        "washing"
    ],
    "wof:name":"Miller Trunk Auto Cleaning",
    "wof:placetype":"venue"
},
  "geometry": {"coordinates":[-92.20626,46.834501],"type":"Point"}
}