{
  "type": "Feature",
  "properties": {
    "iso:country":"US",
    "sg:address":"1141 6th St NW",
    "sg:city":"Rochester",
    "sg:classifiers":[
        {
            "category":"Restaurant",
            "type":"Food & Drink"
        }
    ],
    "sg:phone":"+1 507 282 2697",
    "sg:postcode":"55901",
    "sg:province":"MN",
    "sg:tags":[
        "eating"
    ],
    "wof:name":"Sol Baja Tortilla Grill",
    "wof:placetype":"venue"
},
  "geometry": {"coordinates":[-92.479276,44.029151],"type":"Point"}
}