{
  "type": "Feature",
  "properties": {
    "addr:full":"219 Ave B NE Chatfield MN 55923",
    "addr:housenumber":"219",
    "addr:postcode":"55923",
    "addr:street":"Ave B Ne",
    "iso:country":"US",
    "sg:address":"219 Ave B NE",
    "sg:city":"Chatfield",
    "sg:classifiers":[
        {
            "category":"Education",
            "subcategory":"Library",
            "type":"Public Place"
        }
    ],
    "sg:phone":"+1 507 867 3462",
    "sg:postcode":"55923",
    "sg:province":"MN",
    "wof:name":"Friends of Chatfield Pub Lib",
    "wof:placetype":"venue"
},
  "geometry": {"coordinates":[-92.186333,43.851139],"type":"Point"}
}