{
  "type": "Feature",
  "properties": {
    "addr:full":"450 Eastvold Ave Ortonville MN 56278",
    "addr:housenumber":"450",
    "addr:postcode":"56278",
    "addr:street":"Eastvold Ave",
    "iso:country":"US",
    "sg:address":"450 Eastvold Ave",
    "sg:city":"Ortonville",
    "sg:classifiers":[
        {
            "category":"Health Services",
            "subcategory":"Hospital",
            "type":"Services"
        }
    ],
    "sg:phone":"+1 320 839 2502",
    "sg:postcode":"56278",
    "sg:province":"MN",
    "sg:website":"www.ortonvilleareahealth.org",
    "wof:name":"Ortonville Hospital",
    "wof:placetype":"venue"
},
  "geometry": {"coordinates":[-96.44666599999999,45.314779],"type":"Point"}
}