{
  "type": "Feature",
  "properties": {
    "addr:full":"500 Cindy Ln Owatonna MN 55060",
    "addr:housenumber":"500",
    "addr:postcode":"55060",
    "addr:street":"Cindy Ln",
    "iso:country":"US",
    "sg:address":"500 Cindy Ln",
    "sg:city":"Owatonna",
    "sg:classifiers":[
        {
            "category":"Professional",
            "type":"Services"
        }
    ],
    "sg:phone":"+1 507 455 1257",
    "sg:postcode":"55060",
    "sg:province":"MN",
    "wof:name":"Robert A Glusica Inc",
    "wof:placetype":"venue"
},
  "geometry": {"coordinates":[-93.24450299999999,44.078219],"type":"Point"}
}