{
  "type": "Feature",
  "properties": {
    "addr:full":"7629 Egan Dr Savage MN 55378",
    "addr:housenumber":"7629",
    "addr:postcode":"55378",
    "addr:street":"Egan Dr",
    "iso:country":"US",
    "sg:address":"7629 Egan Dr",
    "sg:city":"Savage",
    "sg:classifiers":[
        {
            "category":"Health Services",
            "subcategory":"Dentist",
            "type":"Services"
        }
    ],
    "sg:phone":"+1 952 440 5100",
    "sg:postcode":"55378",
    "sg:province":"MN",
    "sg:tags":[
        "dentists-pediatric",
        "pediatric",
        "dentistry"
    ],
    "sg:website":"www.childrensdentalc.com",
    "wof:name":"Children's Dental Care",
    "wof:placetype":"venue"
},
  "geometry": {"coordinates":[-93.37706300000001,44.746115],"type":"Point"}
}