{
  "type": "Feature",
  "properties": {
    "addr:full":"1704 5th Ave NW Austin MN 55912",
    "addr:housenumber":"1704",
    "addr:postcode":"55912",
    "addr:street":"5Th Ave Nw",
    "iso:country":"US",
    "sg:address":"1704 5th Ave NW",
    "sg:city":"Austin",
    "sg:classifiers":[
        {
            "category":"Professional",
            "subcategory":"Engineering",
            "type":"Services"
        }
    ],
    "sg:phone":"+1 507 433 2510",
    "sg:postcode":"55912",
    "sg:province":"MN",
    "wof:name":"Broadcast Technical Solutions",
    "wof:placetype":"venue"
},
  "geometry": {"coordinates":[-92.998316,43.671264],"type":"Point"}
}