{
  "type": "Feature",
  "properties": {
    "addr:full":"116 Park St N St Clair MN 56080",
    "addr:housenumber":"116",
    "addr:postcode":"56080",
    "addr:street":"Park St N",
    "iso:country":"US",
    "sg:address":"116 Park St N",
    "sg:city":"St Clair",
    "sg:classifiers":[
        {
            "category":"Government",
            "subcategory":"Post Office",
            "type":"Public Place"
        }
    ],
    "sg:phone":"+1 507 245 3000",
    "sg:postcode":"56080",
    "sg:province":"MN",
    "wof:name":"US Post Office",
    "wof:placetype":"venue"
},
  "geometry": {"coordinates":[-93.85519499999999,44.082225],"type":"Point"}
}