{
  "type": "Feature",
  "properties": {
    "iso:country":"US",
    "sg:address":"115 Garfield St S",
    "sg:city":"Cambridge",
    "sg:classifiers":[
        {
            "category":"Shopping",
            "subcategory":"Pharmacy",
            "type":"Retail Goods"
        }
    ],
    "sg:phone":"+1 763 552 3100",
    "sg:postcode":"55008",
    "sg:province":"MN",
    "wof:name":"Walgreens",
    "wof:placetype":"venue"
},
  "geometry": {"coordinates":[-93.213995,45.571586],"type":"Point"}
}