{
  "type": "Feature",
  "properties": {
    "iso:country":"US",
    "sg:address":"2600 Kenzie Ter",
    "sg:city":"Minneapolis",
    "sg:classifiers":[
        {
            "category":"Building & Trades",
            "subcategory":"Construction",
            "type":"Services"
        }
    ],
    "sg:phone":"+1 612 852 8781",
    "sg:postcode":"55418",
    "sg:province":"MN",
    "sg:tags":[
        "wallcoverings-installation",
        "wallpaper",
        "painting",
        "contractor"
    ],
    "wof:name":"Kevin Beam Custom Painting, Inc.",
    "wof:placetype":"venue"
},
  "geometry": {"coordinates":[-93.223687,45.014272],"type":"Point"}
}