{
  "type": "Feature",
  "properties": {
    "addr:full":"720 Mahtomedi Ave Mahtomedi MN 55115",
    "addr:housenumber":"720",
    "addr:postcode":"55115",
    "addr:street":"Mahtomedi Ave",
    "iso:country":"US",
    "sg:address":"720 Mahtomedi Ave",
    "sg:city":"Mahtomedi",
    "sg:classifiers":[
        {
            "category":"Recreation",
            "type":"Entertainment"
        },
        {
            "category":"Sports & Exercise",
            "subcategory":"Gym",
            "type":"Entertainment"
        }
    ],
    "sg:phone":"+1 651 426 7545",
    "sg:postcode":"55115",
    "sg:province":"MN",
    "sg:tags":[
        "c",
        "gymnastic",
        "facility",
        "instruction",
        "membership",
        "fitness",
        "physical"
    ],
    "wof:name":"Krueger's Family Fitness Ctr",
    "wof:placetype":"venue"
},
  "geometry": {"coordinates":[-92.957623,45.064692],"type":"Point"}
}