{
  "type": "Feature",
  "properties": {
    "iso:country":"US",
    "sg:address":"2960 Snelling Ave N",
    "sg:city":"Saint Paul",
    "sg:classifiers":[
        {
            "category":"Insurance",
            "subcategory":"Insurance Agent",
            "type":"Services"
        }
    ],
    "sg:phone":"+1 651 638 0755",
    "sg:postcode":"55113",
    "sg:province":"MN",
    "wof:name":"Cheryl Steinman",
    "wof:placetype":"venue"
},
  "geometry": {"coordinates":[-93.167106,45.029276],"type":"Point"}
}