{
  "type": "Feature",
  "properties": {
    "iso:country":"US",
    "sg:address":"961 Grand Ave",
    "sg:city":"St Paul",
    "sg:classifiers":[
        {
            "category":"Shopping",
            "subcategory":"Tobacco",
            "type":"Retail Goods"
        }
    ],
    "sg:phone":"+1 651 222 8700",
    "sg:postcode":"55105",
    "sg:province":"MN",
    "sg:tags":[
        "cigarette",
        "product",
        "cigar",
        "dealer"
    ],
    "sg:website":"www.stogiesongrand.com",
    "wof:name":"Stogies On Grand",
    "wof:placetype":"venue"
},
  "geometry": {"coordinates":[-93.14027,44.940037],"type":"Point"}
}