{
  "type": "Feature",
  "properties": {
    "iso:country":"US",
    "sg:address":"6311 Wayzata Blvd",
    "sg:city":"Minneapolis",
    "sg:classifiers":[
        {
            "category":"Health Services",
            "subcategory":"Clinic",
            "type":"Services"
        }
    ],
    "sg:phone":"+1 952 500 9012",
    "sg:postcode":"55416",
    "sg:province":"MN",
    "sg:tags":[
        "welfare"
    ],
    "wof:name":"Grains For Health",
    "wof:placetype":"venue"
},
  "geometry": {"coordinates":[-93.35942,44.970344],"type":"Point"}
}