{
  "type": "Feature",
  "properties": {
    "iso:country":"US",
    "sg:address":"2560 Kyle Ave N",
    "sg:city":"Golden Valley",
    "sg:classifiers":[
        {
            "category":"Manufacturing",
            "subcategory":"Tools & Machinery",
            "type":"Manufacturing & Wholesale Goods"
        }
    ],
    "sg:phone":"+1 763 588 4450",
    "sg:postcode":"55422",
    "sg:province":"MN",
    "sg:tags":[
        "equipment",
        "laboratory",
        "supply"
    ],
    "wof:name":"Thermal Devices",
    "wof:placetype":"venue"
},
  "geometry": {"coordinates":[-93.33429099999999,45.004712],"type":"Point"}
}