{
  "type": "Feature",
  "properties": {
    "addr:full":"714 Co Rd 3 NW Byron MN 55920",
    "addr:housenumber":"714",
    "addr:postcode":"55920",
    "addr:street":"Co Rd 3 Nw",
    "iso:country":"US",
    "sg:address":"714 Co Rd 3 NW",
    "sg:city":"Byron",
    "sg:classifiers":[
        {
            "category":"Home & Garden",
            "subcategory":"Building Materials",
            "type":"Retail Goods"
        }
    ],
    "sg:phone":"+1 507 775 6066",
    "sg:postcode":"55920",
    "sg:province":"MN",
    "sg:tags":[
        "general",
        "improvement"
    ],
    "wof:name":"Home Improvement Professionals",
    "wof:placetype":"venue"
},
  "geometry": {"coordinates":[-92.60813,44.029053],"type":"Point"}
}