{
  "type": "Feature",
  "properties": {
    "addr:full":"409 Territorial St W Watertown MN 55388",
    "addr:housenumber":"409",
    "addr:postcode":"55388",
    "addr:street":"Territorial St W",
    "iso:country":"US",
    "sg:address":"409 Territorial St W",
    "sg:city":"Watertown",
    "sg:classifiers":[
        {
            "category":"Travel",
            "subcategory":"Travel Agent",
            "type":"Entertainment"
        }
    ],
    "sg:phone":"+1 952 446 1789",
    "sg:postcode":"55388",
    "sg:province":"MN",
    "sg:tags":[
        "cruise"
    ],
    "wof:name":"Arrow Travel",
    "wof:placetype":"venue"
},
  "geometry": {"coordinates":[-93.85108200000001,44.965467],"type":"Point"}
}