{
  "type": "Feature",
  "properties": {
    "addr:full":"32557 Clay Bank Rd Erhard MN 56534",
    "addr:housenumber":"32557",
    "addr:postcode":"56534",
    "addr:street":"Clay Bank Rd",
    "iso:country":"US",
    "sg:address":"32557 Clay Bank Rd",
    "sg:city":"Erhard",
    "sg:classifiers":[
        {
            "category":"Farming",
            "subcategory":"Farm",
            "type":"Manufacturing & Wholesale Goods"
        }
    ],
    "sg:phone":"+1 218 736 5035",
    "sg:postcode":"56534",
    "sg:province":"MN",
    "sg:tags":[
        "crop",
        "general"
    ],
    "wof:name":"Cliff Moen",
    "wof:placetype":"venue"
},
  "geometry": {"coordinates":[-96.04262900000001,46.430876],"type":"Point"}
}