{
  "type": "Feature",
  "properties": {
    "addr:full":"8453 Shadow Creek Dr Osseo MN 55311",
    "addr:housenumber":"8453",
    "addr:postcode":"55311",
    "addr:street":"Shadow Creek Dr",
    "iso:country":"US",
    "sg:address":"8453 Shadow Creek Dr",
    "sg:city":"Osseo",
    "sg:classifiers":[
        {
            "category":"Manufacturing",
            "subcategory":"Metals",
            "type":"Manufacturing & Wholesale Goods"
        }
    ],
    "sg:phone":"+1 763 416 4741",
    "sg:postcode":"55311",
    "sg:province":"MN",
    "sg:tags":[
        "steel",
        "distributor",
        "mill",
        "warehouse"
    ],
    "wof:name":"Colleen Steele Independen",
    "wof:placetype":"venue"
},
  "geometry": {"coordinates":[-93.47743699999999,45.108301],"type":"Point"}
}