{
  "type": "Feature",
  "properties": {
    "iso:country":"US",
    "sg:address":"6891 Redwing Ln",
    "sg:city":"Chanhassen",
    "sg:classifiers":[
        {
            "category":"Social Services",
            "subcategory":"Child Care",
            "type":"Services"
        }
    ],
    "sg:phone":"+1 952 474 3159",
    "sg:postcode":"55317",
    "sg:province":"MN",
    "sg:tags":[
        "day"
    ],
    "wof:name":"Jane E Whal",
    "wof:placetype":"venue"
},
  "geometry": {"coordinates":[-93.546333,44.879362],"type":"Point"}
}