{
  "type": "Feature",
  "properties": {
    "iso:country":"US",
    "sg:address":"470 Highway 7 E",
    "sg:city":"Hutchinson",
    "sg:classifiers":[
        {
            "category":"Personal",
            "subcategory":"Massage",
            "type":"Services"
        },
        {
            "category":"Health Services",
            "subcategory":"Clinic",
            "type":"Services"
        },
        {
            "category":"Health Services",
            "subcategory":"Health Practitioner",
            "type":"Services"
        }
    ],
    "sg:phone":"+1 320 587 5554",
    "sg:postcode":"55350",
    "sg:province":"MN",
    "sg:tags":[
        "therapist",
        "therapy",
        "physical"
    ],
    "wof:name":"Golden Touch Therapeutic Massage",
    "wof:placetype":"venue"
},
  "geometry": {"coordinates":[-94.35327100000001,44.895488],"type":"Point"}
}