{
  "type": "Feature",
  "properties": {
    "iso:country":"US",
    "sg:address":"559 E Centennial 84 Dr",
    "sg:city":"New York Mills",
    "sg:classifiers":[
        {
            "category":"Retail",
            "subcategory":"Auto Repair",
            "type":"Services"
        }
    ],
    "sg:phone":"+1 218 385 2730",
    "sg:postcode":"56567",
    "sg:province":"MN",
    "sg:tags":[
        "repairing",
        "automobile"
    ],
    "wof:name":"Niemela Repair",
    "wof:placetype":"venue"
},
  "geometry": {"coordinates":[-95.35915300000001,46.511129],"type":"Point"}
}