{
  "type": "Feature",
  "properties": {
    "addr:full":"1258 Ohio St Saint Paul MN 55118",
    "addr:housenumber":"1258",
    "addr:postcode":"55118",
    "addr:street":"Ohio St",
    "iso:country":"US",
    "sg:address":"1258 Ohio St",
    "sg:city":"Saint Paul",
    "sg:classifiers":[
        {
            "category":"Recreation",
            "type":"Entertainment"
        }
    ],
    "sg:phone":"+1 651 457 2266",
    "sg:postcode":"55118",
    "sg:province":"MN",
    "wof:name":"Wallin Jack Piano Studies",
    "wof:placetype":"venue"
},
  "geometry": {"coordinates":[-93.09721,44.907345],"type":"Point"}
}