{
  "type": "Feature",
  "properties": {
    "iso:country":"US",
    "sg:address":"11888 Marigold St NW",
    "sg:city":"Minneapolis",
    "sg:classifiers":[
        {
            "category":"Professional",
            "subcategory":"Engineering",
            "type":"Services"
        }
    ],
    "sg:phone":"+1 763 427 8625",
    "sg:postcode":"55433",
    "sg:province":"MN",
    "wof:name":"Engineering Solutions",
    "wof:placetype":"venue"
},
  "geometry": {"coordinates":[-93.34874600000001,45.183675],"type":"Point"}
}