{
  "type": "Feature",
  "properties": {
    "iso:country":"US",
    "sg:address":"150 Eaton St",
    "sg:city":"St Paul",
    "sg:classifiers":[
        {
            "category":"Wholesale",
            "subcategory":"Furniture",
            "type":"Manufacturing & Wholesale Goods"
        }
    ],
    "sg:phone":"+1 651 221 1009",
    "sg:postcode":"55107",
    "sg:province":"MN",
    "wof:name":"Kehoe Office Furnishings Inc",
    "wof:placetype":"venue"
},
  "geometry": {"coordinates":[-93.07751500000001,44.935374],"type":"Point"}
}