{
  "type": "Feature",
  "properties": {
    "iso:country":"US",
    "sg:address":"6566 France Ave S",
    "sg:city":"Minneapolis",
    "sg:classifiers":[
        {
            "category":"Education",
            "subcategory":"Special Training",
            "type":"Public Place"
        }
    ],
    "sg:phone":"+1 952 935 9644",
    "sg:postcode":"55435",
    "sg:province":"MN",
    "wof:name":"Murray Music",
    "wof:placetype":"venue"
},
  "geometry": {"coordinates":[-93.32894899999999,44.885708],"type":"Point"}
}