{
  "type": "Feature",
  "properties": {
    "iso:country":"US",
    "sg:address":"1220 13th St N",
    "sg:city":"Saint Cloud",
    "sg:classifiers":[
        {
            "category":"Professional",
            "subcategory":"Business Services",
            "type":"Services"
        }
    ],
    "sg:phone":"+1 320 255 9879",
    "sg:postcode":"56303",
    "sg:province":"MN",
    "sg:tags":[
        "arbitration",
        "mediation"
    ],
    "wof:name":"Lalor Arbitration & Mediation",
    "wof:placetype":"venue"
},
  "geometry": {"coordinates":[-94.17947100000001,45.572956],"type":"Point"}
}