{
  "type": "Feature",
  "properties": {
    "iso:country":"US",
    "sg:address":"11918 Co Rd 3 NW",
    "sg:city":"Pine Island",
    "sg:classifiers":[
        {
            "category":"Farming",
            "subcategory":"Dairy Farm",
            "type":"Manufacturing & Wholesale Goods"
        }
    ],
    "sg:phone":"+1 507 356 4187",
    "sg:postcode":"55963",
    "sg:province":"MN",
    "wof:name":"Donald Weis",
    "wof:placetype":"venue"
},
  "geometry": {"coordinates":[-92.640525,44.17325],"type":"Point"}
}