{
  "type": "Feature",
  "properties": {
    "addr:full":"299 Johnson Ave SW Waseca MN 56093",
    "addr:housenumber":"299",
    "addr:postcode":"56093",
    "addr:street":"Johnson Ave Sw",
    "iso:country":"US",
    "sg:address":"299 Johnson Ave SW",
    "sg:city":"Waseca",
    "sg:classifiers":[
        {
            "category":"Manufacturing",
            "subcategory":"Metals",
            "type":"Manufacturing & Wholesale Goods"
        }
    ],
    "sg:phone":"+1 507 833 6678",
    "sg:postcode":"56093",
    "sg:province":"MN",
    "sg:tags":[
        "copper"
    ],
    "wof:name":"Lodan International",
    "wof:placetype":"venue"
},
  "geometry": {"coordinates":[-93.51065699999999,44.069573],"type":"Point"}
}