{
  "type": "Feature",
  "properties": {
    "iso:country":"US",
    "sg:address":"7175 Washington Ave S",
    "sg:city":"Minneapolis",
    "sg:classifiers":[
        {
            "category":"Shopping",
            "type":"Retail Goods"
        }
    ],
    "sg:phone":"+1 952 942 6227",
    "sg:postcode":"55439",
    "sg:province":"MN",
    "sg:tags":[
        "repair",
        "merchandise"
    ],
    "wof:name":"Gallery Service",
    "wof:placetype":"venue"
},
  "geometry": {"coordinates":[-93.398799,44.876061],"type":"Point"}
}