{
  "type": "Feature",
  "properties": {
    "addr:full":"400 4th St S Minneapolis MN 55415",
    "addr:housenumber":"400",
    "addr:postcode":"55415",
    "addr:street":"4Th St S",
    "iso:country":"US",
    "sg:address":"400 4th St S",
    "sg:city":"Minneapolis",
    "sg:classifiers":[
        {
            "category":"Government",
            "subcategory":"Police Station",
            "type":"Public Place"
        }
    ],
    "sg:phone":"+1 612 673 5500",
    "sg:postcode":"55415",
    "sg:province":"MN",
    "sg:tags":[
        "department"
    ],
    "wof:name":"Minneapolis Civilian Police",
    "wof:placetype":"venue"
},
  "geometry": {"coordinates":[-93.26297700000001,44.976879],"type":"Point"}
}