{
  "type": "Feature",
  "properties": {
    "addr:full":"115 Marion St Dilworth MN 56529",
    "addr:housenumber":"115",
    "addr:postcode":"56529",
    "addr:street":"Marion St",
    "iso:country":"US",
    "sg:address":"115 Marion St",
    "sg:city":"Dilworth",
    "sg:classifiers":[
        {
            "category":"Home & Garden",
            "subcategory":"Furniture",
            "type":"Retail Goods"
        }
    ],
    "sg:phone":"+1 218 287 2090",
    "sg:postcode":"56529",
    "sg:province":"MN",
    "wof:name":"Maurys Woodware",
    "wof:placetype":"venue"
},
  "geometry": {"coordinates":[-96.69385699999999,46.871192],"type":"Point"}
}