{
  "type": "Feature",
  "properties": {
    "iso:country":"US",
    "sg:address":"521 W 53rd St",
    "sg:city":"Minneapolis",
    "sg:classifiers":[
        {
            "category":"Real Estate",
            "subcategory":"Real Estate Agent",
            "type":"Services"
        }
    ],
    "sg:phone":"+1 612 827 5609",
    "sg:postcode":"55419",
    "sg:province":"MN",
    "wof:name":"T & E Real Estate LLC",
    "wof:placetype":"venue"
},
  "geometry": {"coordinates":[-93.28682999999999,44.906443],"type":"Point"}
}