{
  "type": "Feature",
  "properties": {
    "iso:country":"US",
    "sg:address":"217 Broadway W",
    "sg:city":"Little Falls",
    "sg:classifiers":[
        {
            "category":"Insurance",
            "subcategory":"Insurance Agent",
            "type":"Services"
        }
    ],
    "sg:phone":"+1 320 632 3642",
    "sg:postcode":"56345",
    "sg:province":"MN",
    "wof:name":"Greater Minnesota Insurance",
    "wof:placetype":"venue"
},
  "geometry": {"coordinates":[-94.372838,45.977078],"type":"Point"}
}