{
  "type": "Feature",
  "properties": {
    "addr:full":"6711 Plz Curve NE Minneapolis MN 55432",
    "addr:housenumber":"6711",
    "addr:postcode":"55432",
    "addr:street":"Plz Curve Ne",
    "iso:country":"US",
    "sg:address":"6711 Plz Curve NE",
    "sg:city":"Minneapolis",
    "sg:classifiers":[
        {
            "category":"Social Services",
            "subcategory":"Child Care",
            "type":"Services"
        }
    ],
    "sg:phone":"+1 763 571 5041",
    "sg:postcode":"55432",
    "sg:province":"MN",
    "sg:tags":[
        "daycare",
        "provider"
    ],
    "wof:name":"Korczak Kornela",
    "wof:placetype":"venue"
},
  "geometry": {"coordinates":[-93.26396200000001,45.089435],"type":"Point"}
}