{
  "type": "Feature",
  "properties": {
    "addr:full":"625 W Central Entrance Duluth MN 55811",
    "addr:housenumber":"625",
    "addr:postcode":"55811",
    "addr:street":"W Central Entrance",
    "iso:country":"US",
    "sg:address":"625 W Central Entrance",
    "sg:city":"Duluth",
    "sg:classifiers":[
        {
            "category":"Retail",
            "subcategory":"Portrait Studio",
            "type":"Services"
        }
    ],
    "sg:phone":"+1 218 722 7696",
    "sg:postcode":"55811",
    "sg:province":"MN",
    "sg:tags":[
        "photographer"
    ],
    "wof:name":"True Colors Digital Photo",
    "wof:placetype":"venue"
},
  "geometry": {"coordinates":[-92.144688,46.801011],"type":"Point"}
}