{
  "type": "Feature",
  "properties": {
    "iso:country":"US",
    "sg:address":"2250 Pilot Knob Rd",
    "sg:city":"Eagan",
    "sg:classifiers":[
        {
            "category":"Professional",
            "subcategory":"Management & Consulting",
            "type":"Services"
        }
    ],
    "sg:phone":"+1 651 405 4000",
    "sg:postcode":"55120",
    "sg:province":"MN",
    "sg:tags":[
        "marketing",
        "program"
    ],
    "sg:website":"www.pnms.com",
    "wof:name":"Prime Net Marketing Svc",
    "wof:placetype":"venue"
},
  "geometry": {"coordinates":[-93.167145,44.874931],"type":"Point"}
}