{
  "type": "Feature",
  "properties": {
    "iso:country":"US",
    "sg:address":"40519 State Hwy 6",
    "sg:city":"Emily",
    "sg:classifiers":[
        {
            "category":"Wholesale",
            "subcategory":"Construction Materials",
            "type":"Manufacturing & Wholesale Goods"
        }
    ],
    "sg:phone":"+1 218 763 3048",
    "sg:postcode":"56447",
    "sg:province":"MN",
    "sg:tags":[
        "sand",
        "gravel"
    ],
    "wof:name":"Emily Sand & Gravel",
    "wof:placetype":"venue"
},
  "geometry": {"coordinates":[-93.961353,46.736639],"type":"Point"}
}