{
  "type": "Feature",
  "properties": {
    "addr:full":"1900 University Ave NE Minneapolis MN 55418",
    "addr:housenumber":"1900",
    "addr:postcode":"55418",
    "addr:street":"University Ave Ne",
    "iso:country":"US",
    "sg:address":"1900 University Ave NE",
    "sg:city":"Minneapolis",
    "sg:classifiers":[
        {
            "category":"Education",
            "subcategory":"University",
            "type":"Public Place"
        },
        {
            "category":"Food & Beverages",
            "subcategory":"Meat & Fish",
            "type":"Retail Goods"
        }
    ],
    "sg:phone":"+1 612 788 1133",
    "sg:postcode":"55418",
    "sg:province":"MN",
    "sg:tags":[
        "shop",
        "college"
    ],
    "wof:name":"University Halal Meat Market",
    "wof:placetype":"venue"
},
  "geometry": {"coordinates":[-93.26326400000001,45.00745],"type":"Point"}
}