{
  "type": "Feature",
  "properties": {
    "iso:country":"US",
    "sg:address":"23040 Stratford Pl",
    "sg:city":"Excelsior",
    "sg:classifiers":[
        {
            "category":"Shopping",
            "subcategory":"Beauty & Cosmetics",
            "type":"Retail Goods"
        }
    ],
    "sg:phone":"+1 952 470 7992",
    "sg:postcode":"55331",
    "sg:province":"MN",
    "sg:tags":[
        "merchandise"
    ],
    "wof:name":"Beauti Control Cosmetics",
    "wof:placetype":"venue"
},
  "geometry": {"coordinates":[-93.56039199999999,44.892408],"type":"Point"}
}