{
  "type": "Feature",
  "properties": {
    "iso:country":"US",
    "sg:address":"9525 230th St W",
    "sg:city":"Morristown",
    "sg:classifiers":[
        {
            "category":"Organizations",
            "subcategory":"Community Association",
            "type":"Services"
        }
    ],
    "sg:phone":"+1 507 685 4578",
    "sg:postcode":"55052",
    "sg:province":"MN",
    "sg:tags":[
        "club"
    ],
    "wof:name":"Morristown Gun Club",
    "wof:placetype":"venue"
},
  "geometry": {"coordinates":[-93.46388399999999,44.254288],"type":"Point"}
}