{
  "type": "Feature",
  "properties": {
    "iso:country":"US",
    "sg:address":"310 E 38th St",
    "sg:city":"Minneapolis",
    "sg:classifiers":[
        {
            "category":"Organizations",
            "subcategory":"Professional Association",
            "type":"Services"
        }
    ],
    "sg:phone":"+1 612 822 8020",
    "sg:postcode":"55409",
    "sg:province":"MN",
    "wof:name":"Welfare Rights Committee",
    "wof:placetype":"venue"
},
  "geometry": {"coordinates":[-93.27175099999999,44.934218],"type":"Point"}
}