{
  "type": "Feature",
  "properties": {
    "addr:full":"3428 Lakeridge Pl NW Ste A Rochester MN 55901",
    "addr:housenumber":"3428",
    "addr:postcode":"55901",
    "addr:street":"Lakeridge Pl Nw Ste A",
    "iso:country":"US",
    "sg:address":"3428 Lakeridge Pl NW Ste A",
    "sg:city":"Rochester",
    "sg:classifiers":[
        {
            "category":"Manufacturing",
            "subcategory":"Buildings",
            "type":"Manufacturing & Wholesale Goods"
        },
        {
            "category":"Building & Trades",
            "subcategory":"Construction",
            "type":"Services"
        }
    ],
    "sg:phone":"+1 507 529 1161",
    "sg:postcode":"55901",
    "sg:province":"MN",
    "sg:tags":[
        "industrial",
        "system",
        "specialty",
        "builder",
        "heating",
        "contractor",
        "contractors-commercial",
        "home",
        "air conditioning"
    ],
    "sg:website":"http://www.bigelowhomes.net",
    "wof:name":"Bigelow Enterprises",
    "wof:placetype":"venue"
},
  "geometry": {"coordinates":[-92.514912,44.031658],"type":"Point"}
}