{
  "type": "Feature",
  "properties": {
    "addr:full":"1000 N Front St New Ulm MN 56073",
    "addr:housenumber":"1000",
    "addr:postcode":"56073",
    "addr:street":"N Front St",
    "iso:country":"US",
    "sg:address":"1000 N Front St",
    "sg:city":"New Ulm",
    "sg:classifiers":[
        {
            "category":"Building & Trades",
            "subcategory":"Construction",
            "type":"Services"
        }
    ],
    "sg:phone":"+1 507 354 4171",
    "sg:postcode":"56073",
    "sg:province":"MN",
    "sg:tags":[
        "general",
        "contractor"
    ],
    "wof:name":"M R Paving & Excavating Inc",
    "wof:placetype":"venue"
},
  "geometry": {"coordinates":[-94.46255499999999,44.325558],"type":"Point"}
}