{
  "type": "Feature",
  "properties": {
    "addr:full":"10655 Beard Ave S Minneapolis MN 55431",
    "addr:housenumber":"10655",
    "addr:postcode":"55431",
    "addr:street":"Beard Ave S",
    "iso:country":"US",
    "sg:address":"10655 Beard Ave S",
    "sg:city":"Minneapolis",
    "sg:classifiers":[
        {
            "category":"Communications",
            "subcategory":"Film & Video Production",
            "type":"Services"
        },
        {
            "category":"Shopping",
            "subcategory":"Music",
            "type":"Retail Goods"
        },
        {
            "category":"Banks & Credit Unions",
            "subcategory":"Investment Brokerage",
            "type":"Services"
        }
    ],
    "sg:phone":"+1 651 247 1860",
    "sg:postcode":"55431",
    "sg:province":"MN",
    "sg:tags":[
        "sale",
        "dvds-rental",
        "record",
        "tapes-wholesale",
        "tape",
        "cd's",
        "store",
        "manufacturer"
    ],
    "wof:name":"Sk Audio",
    "wof:placetype":"venue"
},
  "geometry": {"coordinates":[-93.32440699999999,44.811147],"type":"Point"}
}