{
  "type": "Feature",
  "properties": {
    "addr:full":"1111 13th Ave SE Detroit Lakes MN 56501",
    "addr:housenumber":"1111",
    "addr:postcode":"56501",
    "addr:street":"13Th Ave Se",
    "iso:country":"US",
    "sg:address":"1111 13th Ave SE",
    "sg:city":"Detroit Lakes",
    "sg:classifiers":[
        {
            "category":"Manufacturing",
            "subcategory":"Metals",
            "type":"Manufacturing & Wholesale Goods"
        }
    ],
    "sg:phone":"+1 218 847 4446",
    "sg:postcode":"56501",
    "sg:province":"MN",
    "sg:tags":[
        "stamping"
    ],
    "sg:website":"www.holmescenter.org",
    "wof:name":"BTD Mfg Inc",
    "wof:placetype":"venue"
},
  "geometry": {"coordinates":[-95.827005,46.814802],"type":"Point"}
}