{
  "type": "Feature",
  "properties": {
    "addr:full":"145 1st Ave SE Hutchinson MN 55350",
    "addr:housenumber":"145",
    "addr:postcode":"55350",
    "addr:street":"1St Ave Se",
    "iso:country":"US",
    "sg:address":"145 1st Ave SE",
    "sg:city":"Hutchinson",
    "sg:classifiers":[
        {
            "category":"Personal",
            "subcategory":"Beauty Salon",
            "type":"Services"
        },
        {
            "category":"Personal",
            "subcategory":"Barber",
            "type":"Services"
        }
    ],
    "sg:phone":"+1 320 587 8335",
    "sg:postcode":"55350",
    "sg:province":"MN",
    "wof:name":"First Avenue Barber And Beauty Salon",
    "wof:placetype":"venue"
},
  "geometry": {"coordinates":[-94.367211,44.891129],"type":"Point"}
}