{
  "type": "Feature",
  "properties": {
    "iso:country":"US",
    "sg:address":"1414 W 24th St",
    "sg:city":"Minneapolis",
    "sg:classifiers":[
        {
            "category":"Professional",
            "subcategory":"Management & Consulting",
            "type":"Services"
        }
    ],
    "sg:phone":"+1 612 377 6226",
    "sg:postcode":"55405",
    "sg:province":"MN",
    "sg:tags":[
        "development",
        "product"
    ],
    "wof:name":"Human Dimensions Inc",
    "wof:placetype":"venue"
},
  "geometry": {"coordinates":[-93.298067,44.959207],"type":"Point"}
}