{
  "type": "Feature",
  "properties": {
    "iso:country":"US",
    "sg:address":"6420 Camden Ave N",
    "sg:city":"Brooklyn Center",
    "sg:classifiers":[
        {
            "category":"Building & Trades",
            "subcategory":"Construction",
            "type":"Services"
        }
    ],
    "sg:phone":"+1 763 569 0284",
    "sg:postcode":"55430",
    "sg:province":"MN",
    "sg:tags":[
        "company"
    ],
    "wof:name":"Centre's Construction",
    "wof:placetype":"venue"
},
  "geometry": {"coordinates":[-93.289118,45.071638],"type":"Point"}
}