{
  "type": "Feature",
  "properties": {
    "addr:full":"34372 Co Rd 143 Ogema MN 56569",
    "addr:housenumber":"34372",
    "addr:postcode":"56569",
    "addr:street":"Co Rd 143",
    "iso:country":"US",
    "sg:address":"34372 Co Rd 143",
    "sg:city":"Ogema",
    "sg:classifiers":[
        {
            "category":"Professional",
            "type":"Services"
        },
        {
            "category":"Building & Trades",
            "subcategory":"Construction",
            "type":"Services"
        }
    ],
    "sg:phone":"+1 218 983 3247",
    "sg:postcode":"56569",
    "sg:province":"MN",
    "sg:tags":[
        "establishment",
        "contractor"
    ],
    "wof:name":"Davidsons Drywall",
    "wof:placetype":"venue"
},
  "geometry": {"coordinates":[-95.66059300000001,47.034897],"type":"Point"}
}