{
  "type": "Feature",
  "properties": {
    "addr:full":"2337 Palmer Dr New Brighton MN 55112",
    "addr:housenumber":"2337",
    "addr:postcode":"55112",
    "addr:street":"Palmer Dr",
    "iso:country":"US",
    "sg:address":"2337 Palmer Dr",
    "sg:city":"New Brighton",
    "sg:classifiers":[
        {
            "category":"Recreation",
            "type":"Entertainment"
        }
    ],
    "sg:phone":"+1 651 631 2379",
    "sg:postcode":"55112",
    "sg:province":"MN",
    "sg:tags":[
        "martial",
        "arts",
        "instruction"
    ],
    "wof:name":"Peak Performance",
    "wof:placetype":"venue"
},
  "geometry": {"coordinates":[-93.216132,45.067583],"type":"Point"}
}