{
  "type": "Feature",
  "properties": {
    "addr:full":"122 9th Ave N Waite Park MN 56387",
    "addr:housenumber":"122",
    "addr:postcode":"56387",
    "addr:street":"9Th Ave N",
    "iso:country":"US",
    "sg:address":"122 9th Ave N",
    "sg:city":"Waite Park",
    "sg:classifiers":[
        {
            "category":"Building & Trades",
            "subcategory":"Cleaning & Sanitation",
            "type":"Services"
        }
    ],
    "sg:phone":"+1 320 253 6455",
    "sg:postcode":"56387",
    "sg:province":"MN",
    "sg:tags":[
        "maintenance"
    ],
    "wof:name":"Sorensons Chimney Service",
    "wof:placetype":"venue"
},
  "geometry": {"coordinates":[-94.227914,45.556759],"type":"Point"}
}