{
  "type": "Feature",
  "properties": {
    "addr:full":"1301 Cliff Rd E Burnsville MN 55337",
    "addr:housenumber":"1301",
    "addr:postcode":"55337",
    "addr:street":"Cliff Rd E",
    "iso:country":"US",
    "sg:address":"1301 Cliff Rd E",
    "sg:city":"Burnsville",
    "sg:classifiers":[
        {
            "category":"Home & Garden",
            "subcategory":"Furniture",
            "type":"Retail Goods"
        }
    ],
    "sg:phone":"+1 952 808 5118",
    "sg:postcode":"55337",
    "sg:province":"MN",
    "sg:tags":[
        "store"
    ],
    "wof:name":"Furnituredealer.Net",
    "wof:placetype":"venue"
},
  "geometry": {"coordinates":[-93.256871,44.790213],"type":"Point"}
}