{
  "type": "Feature",
  "properties": {
    "addr:full":"12847 Idlewild Dr NE Bemidji MN 56601",
    "addr:housenumber":"12847",
    "addr:postcode":"56601",
    "addr:street":"Idlewild Dr Ne",
    "iso:country":"US",
    "sg:address":"12847 Idlewild Dr NE",
    "sg:city":"Bemidji",
    "sg:classifiers":[
        {
            "category":"Professional",
            "subcategory":"Lawyer & Legal Services",
            "type":"Services"
        }
    ],
    "sg:phone":"+1 218 243 3178",
    "sg:postcode":"56601",
    "sg:province":"MN",
    "sg:tags":[
        "attorney"
    ],
    "wof:name":"Mc Rae Law Office",
    "wof:placetype":"venue"
},
  "geometry": {"coordinates":[-94.865835,47.591926],"type":"Point"}
}