{
  "type": "Feature",
  "properties": {
    "iso:country":"US",
    "sg:address":"13621 Lake Dr NE",
    "sg:city":"Forest Lake",
    "sg:classifiers":[
        {
            "category":"Wholesale",
            "subcategory":"Machinery & Supplies",
            "type":"Manufacturing & Wholesale Goods"
        },
        {
            "category":"Home & Garden",
            "subcategory":"Garden Supply",
            "type":"Retail Goods"
        }
    ],
    "sg:phone":"+1 651 982 6895",
    "sg:postcode":"55025",
    "sg:province":"MN",
    "sg:tags":[
        "sprinkler",
        "library"
    ],
    "wof:name":"John Deere Landscapes",
    "wof:placetype":"venue"
},
  "geometry": {"coordinates":[-93.093239,45.217078],"type":"Point"}
}