{
  "type": "Feature",
  "properties": {
    "addr:full":"2999 Co Rd 42 W Burnsville MN 55306",
    "addr:housenumber":"2999;42",
    "addr:postcode":"55306",
    "addr:street":"Co Rd;W",
    "iso:country":"US",
    "sg:address":"2999 Co Rd 42 W",
    "sg:city":"Burnsville",
    "sg:classifiers":[
        {
            "category":"Building & Trades",
            "subcategory":"Construction",
            "type":"Services"
        }
    ],
    "sg:phone":"+1 952 469 3900",
    "sg:postcode":"55306",
    "sg:province":"MN",
    "sg:tags":[
        "repairing",
        "remodeling",
        "contractor"
    ],
    "sg:website":"www.robertsresidentialremodeling.com",
    "wof:name":"Roberts Residential Remodeling",
    "wof:placetype":"venue"
},
  "geometry": {"coordinates":[-93.314516,44.746221],"type":"Point"}
}