{
  "type": "Feature",
  "properties": {
    "addr:full":"9822 Sundown Rd NW Solway MN 56678",
    "addr:housenumber":"9822",
    "addr:postcode":"56678",
    "addr:street":"Sundown Rd Nw",
    "iso:country":"US",
    "sg:address":"9822 Sundown Rd NW",
    "sg:city":"Solway",
    "sg:phone":"+1 218 467 3310",
    "sg:postcode":"56678",
    "sg:province":"MN",
    "sg:tags":[
        "farm",
        "field",
        "crop"
    ],
    "wof:name":"Duane Winge",
    "wof:placetype":"venue"
},
  "geometry": {"coordinates":[-95.163184,47.563539],"type":"Point"}
}