{
  "type": "Feature",
  "properties": {
    "addr:full":"31500 291st Ave Browerville MN 56438",
    "addr:housenumber":"31500",
    "addr:postcode":"56438",
    "addr:street":"291St Ave",
    "iso:country":"US",
    "sg:address":"31500 291st Ave",
    "sg:city":"Browerville",
    "sg:classifiers":[
        {
            "category":"Travel",
            "subcategory":"Campground",
            "type":"Entertainment"
        }
    ],
    "sg:phone":"+1 320 594 2750",
    "sg:postcode":"56438",
    "sg:province":"MN",
    "sg:tags":[
        "organization",
        "camp",
        "religious"
    ],
    "sg:website":"www.littleelkranch.com",
    "wof:name":"Little Elk Youth Ranch Inc",
    "wof:placetype":"venue"
},
  "geometry": {"coordinates":[-94.762209,46.080851],"type":"Point"}
}