{
  "type": "Feature",
  "properties": {
    "iso:country":"US",
    "sg:address":"1545 Northway Dr",
    "sg:city":"St Cloud",
    "sg:classifiers":[
        {
            "category":"Health Services",
            "subcategory":"Doctor",
            "type":"Services"
        }
    ],
    "sg:phone":"+1 320 252 1300",
    "sg:postcode":"56303",
    "sg:province":"MN",
    "sg:tags":[
        "dentist"
    ],
    "wof:name":"Gregory C Pappenfus DDS",
    "wof:placetype":"venue"
},
  "geometry": {"coordinates":[-94.182256,45.578955],"type":"Point"}
}