{
  "type": "Feature",
  "properties": {
    "addr:full":"1297 Granite St Granite Falls MN 56241",
    "addr:housenumber":"1297",
    "addr:postcode":"56241",
    "addr:street":"Granite St",
    "iso:country":"US",
    "sg:address":"1297 Granite St",
    "sg:city":"Granite Falls",
    "sg:phone":"+1 320 564 2525",
    "sg:postcode":"56241",
    "sg:province":"MN",
    "sg:tags":[
        "oil"
    ],
    "wof:name":"Tri County Co-Op Oil Co",
    "wof:placetype":"venue"
},
  "geometry": {"coordinates":[-95.54566199999999,44.805957],"type":"Point"}
}