{
  "type": "Feature",
  "properties": {
    "addr:full":"422 Santa Fe Cir Chanhassen MN 55317",
    "addr:housenumber":"422",
    "addr:postcode":"55317",
    "addr:street":"Santa Fe Cir",
    "iso:country":"US",
    "sg:address":"422 Santa Fe Cir",
    "sg:city":"Chanhassen",
    "sg:classifiers":[
        {
            "category":"Organizations",
            "subcategory":"Religious Organization",
            "type":"Services"
        }
    ],
    "sg:phone":"+1 952 934 4444",
    "sg:postcode":"55317",
    "sg:province":"MN",
    "wof:name":"Renewal Fellowship",
    "wof:placetype":"venue"
},
  "geometry": {"coordinates":[-93.533024,44.866312],"type":"Point"}
}