{
  "type": "Feature",
  "properties": {
    "addr:full":"5825 Vega Ave New Germany MN 55367",
    "addr:housenumber":"5825",
    "addr:postcode":"55367",
    "addr:street":"Vega Ave",
    "iso:country":"US",
    "sg:address":"5825 Vega Ave",
    "sg:city":"New Germany",
    "sg:classifiers":[
        {
            "category":"Professional",
            "type":"Services"
        }
    ],
    "sg:phone":"+1 952 353 2143",
    "sg:postcode":"55367",
    "sg:province":"MN",
    "wof:name":"Alvin Stewder",
    "wof:placetype":"venue"
},
  "geometry": {"coordinates":[-93.9508,44.898472],"type":"Point"}
}