{
  "type": "Feature",
  "properties": {
    "iso:country":"US",
    "sg:address":"20729 State Hwy 55",
    "sg:city":"Glenwood",
    "sg:classifiers":[
        {
            "category":"Real Estate",
            "subcategory":"Developer",
            "type":"Services"
        },
        {
            "category":"Real Estate",
            "subcategory":"Real Estate Operator",
            "type":"Services"
        }
    ],
    "sg:phone":"+1 320 634 4690",
    "sg:postcode":"56334",
    "sg:province":"MN",
    "sg:tags":[
        "mobile",
        "home",
        "site"
    ],
    "wof:name":"Pine Hill Park",
    "wof:placetype":"venue"
},
  "geometry": {"coordinates":[-95.36103199999999,45.639044],"type":"Point"}
}