{
  "type": "Feature",
  "properties": {
    "addr:full":"1655 Annapolis Ln N Minneapolis MN 55441",
    "addr:housenumber":"1655",
    "addr:postcode":"55441",
    "addr:street":"Annapolis Ln N",
    "iso:country":"US",
    "sg:address":"1655 Annapolis Ln N",
    "sg:city":"Minneapolis",
    "sg:classifiers":[
        {
            "category":"Autos & Motor Vehicles",
            "subcategory":"Auto Supplies",
            "type":"Retail Goods"
        }
    ],
    "sg:phone":"+1 763 559 5412",
    "sg:postcode":"55441",
    "sg:province":"MN",
    "sg:tags":[
        "wheel"
    ],
    "sg:website":"http://www.discounttire.com/dtcs/home.do?utm_source=YellowPages&utm_medium=iyp&utm_campaign=YellowPagesIYPOrg",
    "wof:name":"Discount Tire",
    "wof:placetype":"venue"
},
  "geometry": {"coordinates":[-93.45387100000001,44.998369],"type":"Point"}
}