{
  "type": "Feature",
  "properties": {
    "iso:country":"US",
    "sg:address":"1401 S 12th Ave",
    "sg:city":"Virginia",
    "sg:classifiers":[
        {
            "category":"Shopping",
            "subcategory":"Department Store",
            "type":"Retail Goods"
        }
    ],
    "sg:phone":"+1 218 741 9228",
    "sg:postcode":"55792",
    "sg:province":"MN",
    "wof:name":"Thunderbird Mall",
    "wof:placetype":"venue"
},
  "geometry": {"coordinates":[-92.551918,47.512421],"type":"Point"}
}