{
  "type": "Feature",
  "properties": {
    "addr:full":"46483 Terry Rd Talmoon MN 56637",
    "addr:housenumber":"46483",
    "addr:postcode":"56637",
    "addr:street":"Terry Rd",
    "iso:country":"US",
    "sg:address":"46483 Terry Rd",
    "sg:city":"Talmoon",
    "sg:classifiers":[
        {
            "category":"Autos & Motor Vehicles",
            "subcategory":"Automobile Sales",
            "type":"Retail Goods"
        }
    ],
    "sg:phone":"+1 218 832 3457",
    "sg:postcode":"56637",
    "sg:province":"MN",
    "sg:tags":[
        "equipment",
        "aircraft",
        "parts",
        "supply"
    ],
    "wof:name":"North Star Aero",
    "wof:placetype":"venue"
},
  "geometry": {"coordinates":[-93.820639,47.600293],"type":"Point"}
}