{
  "type": "Feature",
  "properties": {
    "addr:full":"1552 80th Ave Sherburn MN 56171",
    "addr:housenumber":"1552",
    "addr:postcode":"56171",
    "addr:street":"80Th Ave",
    "iso:country":"US",
    "sg:address":"1552 80th Ave",
    "sg:city":"Sherburn",
    "sg:classifiers":[
        {
            "category":"Farming",
            "subcategory":"Livestock Farm",
            "type":"Manufacturing & Wholesale Goods"
        }
    ],
    "sg:phone":"+1 507 639 3592",
    "sg:postcode":"56171",
    "sg:province":"MN",
    "sg:tags":[
        "feedlot",
        "corn",
        "soybean",
        "beef",
        "cattle"
    ],
    "wof:name":"Paul Matajka",
    "wof:placetype":"venue"
},
  "geometry": {"coordinates":[-94.714563,43.709903],"type":"Point"}
}