{
  "type": "Feature",
  "properties": {
    "addr:full":"6597 Laketowne Pl Albertville MN 55301",
    "addr:housenumber":"6597",
    "addr:postcode":"55301",
    "addr:street":"Laketowne Pl",
    "iso:country":"US",
    "sg:address":"6597 Laketowne Pl",
    "sg:city":"Albertville",
    "sg:classifiers":[
        {
            "category":"Real Estate",
            "subcategory":"Real Estate Services",
            "type":"Services"
        },
        {
            "category":"Real Estate",
            "subcategory":"Real Estate Agent",
            "type":"Services"
        }
    ],
    "sg:phone":"+1 763 420 3082",
    "sg:postcode":"55301",
    "sg:province":"MN",
    "sg:tags":[
        "management"
    ],
    "wof:name":"Alshouse Properties",
    "wof:placetype":"venue"
},
  "geometry": {"coordinates":[-93.66256,45.246902],"type":"Point"}
}