{
  "type": "Feature",
  "properties": {
    "addr:full":"1311 580th St Echo MN 56237",
    "addr:housenumber":"1311",
    "addr:postcode":"56237",
    "addr:street":"580Th St",
    "iso:country":"US",
    "sg:address":"1311 580th St",
    "sg:city":"Echo",
    "sg:phone":"+1 507 925 4391",
    "sg:postcode":"56237",
    "sg:province":"MN",
    "sg:tags":[
        "farm",
        "soybean"
    ],
    "wof:name":"Brad Werner",
    "wof:placetype":"venue"
},
  "geometry": {"coordinates":[-95.482963,44.587185],"type":"Point"}
}