{
  "type": "Feature",
  "properties": {
    "iso:country":"US",
    "sg:address":"709 6th St SE",
    "sg:city":"Rochester",
    "sg:classifiers":[
        {
            "category":"Social Services",
            "subcategory":"Child Care",
            "type":"Services"
        }
    ],
    "sg:phone":"+1 507 288 8707",
    "sg:postcode":"55904",
    "sg:province":"MN",
    "sg:tags":[
        "day"
    ],
    "wof:name":"Danice J Mulholland",
    "wof:placetype":"venue"
},
  "geometry": {"coordinates":[-92.452564,44.017035],"type":"Point"}
}