{
  "type": "Feature",
  "properties": {
    "addr:full":"7501 Chicago Ave S Minneapolis MN 55423",
    "addr:housenumber":"7501",
    "addr:postcode":"55423",
    "addr:street":"Chicago Ave S",
    "iso:country":"US",
    "sg:address":"7501 Chicago Ave S",
    "sg:city":"Minneapolis",
    "sg:classifiers":[
        {
            "category":"Retail",
            "subcategory":"Laundry & Dry Cleaning",
            "type":"Services"
        }
    ],
    "sg:phone":"+1 612 866 2079",
    "sg:postcode":"55423",
    "sg:province":"MN",
    "sg:tags":[
        "cleaners",
        "rug",
        "carpet"
    ],
    "wof:name":"Victoria Cleaners",
    "wof:placetype":"venue"
},
  "geometry": {"coordinates":[-93.263048,44.865519],"type":"Point"}
}