{
  "type": "Feature",
  "properties": {
    "iso:country":"US",
    "sg:address":"40007 Hupp St NE",
    "sg:city":"Stanchfield",
    "sg:classifiers":[
        {
            "category":"Building & Trades",
            "subcategory":"Construction",
            "type":"Services"
        }
    ],
    "sg:phone":"+1 612 298 1950",
    "sg:postcode":"55080",
    "sg:province":"MN",
    "sg:tags":[
        "painter"
    ],
    "wof:name":"Srk Painting & Texture",
    "wof:placetype":"venue"
},
  "geometry": {"coordinates":[-93.15683799999999,45.691394],"type":"Point"}
}