{
  "type": "Feature",
  "properties": {
    "addr:full":"18652 Co Hwy 25 Detroit Lakes MN 56501",
    "addr:housenumber":"18652",
    "addr:postcode":"56501",
    "addr:street":"Co Hwy 25",
    "iso:country":"US",
    "sg:address":"18652 Co Hwy 25",
    "sg:city":"Detroit Lakes",
    "sg:classifiers":[
        {
            "category":"Retail",
            "subcategory":"Auto Repair",
            "type":"Services"
        }
    ],
    "sg:phone":"+1 218 844 5613",
    "sg:postcode":"56501",
    "sg:province":"MN",
    "sg:tags":[
        "repairing",
        "automobile"
    ],
    "wof:name":"Extreme Edge",
    "wof:placetype":"venue"
},
  "geometry": {"coordinates":[-95.795422,46.840683],"type":"Point"}
}