{
  "type": "Feature",
  "properties": {
    "iso:country":"US",
    "sg:address":"207 S Oak St",
    "sg:city":"Hendricks",
    "sg:phone":"+1 507 275 3513",
    "sg:postcode":"56136",
    "sg:province":"MN",
    "sg:tags":[
        "farm",
        "corn",
        "soybean"
    ],
    "wof:name":"Ron Johnson",
    "wof:placetype":"venue"
},
  "geometry": {"coordinates":[-96.421368,44.506034],"type":"Point"}
}