{
  "type": "Feature",
  "properties": {
    "addr:full":"45 Main St E Richmond MN 56368",
    "addr:housenumber":"45",
    "addr:postcode":"56368",
    "addr:street":"Main St E",
    "iso:country":"US",
    "sg:address":"45 Main St E",
    "sg:city":"Richmond",
    "sg:classifiers":[
        {
            "category":"Professional",
            "subcategory":"Lawyer & Legal Services",
            "type":"Services"
        }
    ],
    "sg:phone":"+1 320 597 3539",
    "sg:postcode":"56368",
    "sg:province":"MN",
    "sg:tags":[
        "attorney"
    ],
    "wof:name":"Reichert Wenner Koch",
    "wof:placetype":"venue"
},
  "geometry": {"coordinates":[-94.518068,45.453944],"type":"Point"}
}