{
  "type": "Feature",
  "properties": {
    "addr:full":"1601 Adams St Mankato MN 56001",
    "addr:housenumber":"1601",
    "addr:postcode":"56001",
    "addr:street":"Adams St",
    "iso:country":"US",
    "sg:address":"1601 Adams St",
    "sg:city":"Mankato",
    "sg:classifiers":[
        {
            "category":"Banks & Credit Unions",
            "subcategory":"Bank",
            "type":"Services"
        }
    ],
    "sg:phone":"+1 507 386 7100",
    "sg:postcode":"56001",
    "sg:province":"MN",
    "sg:tags":[
        "federal",
        "savings",
        "institution"
    ],
    "sg:website":"www.wellsfederal.com",
    "wof:name":"Wells Federal Bank",
    "wof:placetype":"venue"
},
  "geometry": {"coordinates":[-93.96171699999999,44.169705],"type":"Point"}
}