{
  "type": "Feature",
  "properties": {
    "iso:country":"US",
    "sg:address":"19831 Town and Country Estate Ln",
    "sg:city":"Detroit Lakes",
    "sg:classifiers":[
        {
            "category":"Building & Trades",
            "subcategory":"Construction",
            "type":"Services"
        }
    ],
    "sg:phone":"+1 218 847 3659",
    "sg:postcode":"56501",
    "sg:province":"MN",
    "sg:tags":[
        "equipment",
        "installation"
    ],
    "wof:name":"Fegely Installations Inc",
    "wof:placetype":"venue"
},
  "geometry": {"coordinates":[-95.87287000000001,46.862401],"type":"Point"}
}