{
  "type": "Feature",
  "properties": {
    "iso:country":"US",
    "sg:address":"36562 707th Ave",
    "sg:city":"Kimball",
    "sg:phone":"+1 320 398 8882",
    "sg:postcode":"55353",
    "sg:province":"MN",
    "sg:tags":[
        "farm",
        "corn",
        "soybean"
    ],
    "wof:name":"Van Nurdne Graig",
    "wof:placetype":"venue"
},
  "geometry": {"coordinates":[-94.34333100000001,45.279687],"type":"Point"}
}