{
  "type": "Feature",
  "properties": {
    "addr:full":"5173 W 140th St Savage MN 55378",
    "addr:housenumber":"5173",
    "addr:postcode":"55378",
    "addr:street":"W 140Th St",
    "iso:country":"US",
    "sg:address":"5173 W 140th St",
    "sg:city":"Savage",
    "sg:classifiers":[
        {
            "category":"Shopping",
            "subcategory":"Clothing, Apparel, & Fashions",
            "type":"Retail Goods"
        }
    ],
    "sg:phone":"+1 952 707 6933",
    "sg:postcode":"55378",
    "sg:province":"MN",
    "sg:tags":[
        "garment"
    ],
    "wof:name":"Cartoon & Sports Apparel",
    "wof:placetype":"venue"
},
  "geometry": {"coordinates":[-93.36851799999999,44.749972],"type":"Point"}
}