{
  "type": "Feature",
  "properties": {
    "addr:full":"22021 Terrace Rd NE Cedar MN 55011",
    "addr:housenumber":"22021",
    "addr:postcode":"55011",
    "addr:street":"Terrace Rd Ne Cedar",
    "iso:country":"US",
    "sg:address":"22021 Terrace Rd NE",
    "sg:city":"Cedar",
    "sg:classifiers":[
        {
            "category":"Freight",
            "type":"Transportation"
        }
    ],
    "sg:phone":"+1 763 434 7427",
    "sg:postcode":"55011",
    "sg:province":"MN",
    "sg:tags":[
        "operator",
        "local",
        "trucking"
    ],
    "wof:name":"John Brletich Trucking",
    "wof:placetype":"venue"
},
  "geometry": {"coordinates":[-93.25955,45.369269],"type":"Point"}
}