{
  "type": "Feature",
  "properties": {
    "addr:full":"10608 Vincent Ave S Minneapolis MN 55431",
    "addr:housenumber":"10608",
    "addr:postcode":"55431",
    "addr:street":"Vincent Ave S",
    "iso:country":"US",
    "sg:address":"10608 Vincent Ave S",
    "sg:city":"Minneapolis",
    "sg:classifiers":[
        {
            "category":"Home & Garden",
            "subcategory":"Hardware",
            "type":"Retail Goods"
        }
    ],
    "sg:phone":"+1 612 251 8599",
    "sg:postcode":"55431",
    "sg:province":"MN",
    "wof:name":"Xtreme Value Electronics",
    "wof:placetype":"venue"
},
  "geometry": {"coordinates":[-93.316868,44.808474],"type":"Point"}
}