{
  "type": "Feature",
  "properties": {
    "addr:full":"1180 Yankee Doodle Rd Eagan MN 55121",
    "addr:housenumber":"1180",
    "addr:postcode":"55121",
    "addr:street":"Yankee Doodle Rd",
    "iso:country":"US",
    "sg:address":"1180 Yankee Doodle Rd",
    "sg:city":"Eagan",
    "sg:classifiers":[
        {
            "category":"Retail",
            "subcategory":"Auto Repair",
            "type":"Services"
        }
    ],
    "sg:phone":"+1 651 454 5510",
    "sg:postcode":"55121",
    "sg:province":"MN",
    "sg:tags":[
        "automobile",
        "lubrication"
    ],
    "wof:name":"Valvoline Instant Oil Change",
    "wof:placetype":"venue"
},
  "geometry": {"coordinates":[-93.155051,44.833462],"type":"Point"}
}