{
  "type": "Feature",
  "properties": {
    "addr:full":"1625 Murphy Pkwy Saint Paul MN 55122",
    "addr:housenumber":"1625",
    "addr:postcode":"55122",
    "addr:street":"Murphy Pkwy",
    "iso:country":"US",
    "sg:address":"1625 Murphy Pkwy",
    "sg:city":"Saint Paul",
    "sg:classifiers":[
        {
            "category":"Professional",
            "type":"Services"
        }
    ],
    "sg:phone":"+1 651 688 7204",
    "sg:postcode":"55122",
    "sg:province":"MN",
    "wof:name":"Arshad Ahsan",
    "wof:placetype":"venue"
},
  "geometry": {"coordinates":[-93.18304000000001,44.812472],"type":"Point"}
}