{
  "type": "Feature",
  "properties": {
    "iso:country":"US",
    "sg:address":"908 Ridgecrest Dr",
    "sg:city":"Carver",
    "sg:classifiers":[
        {
            "category":"Professional",
            "subcategory":"Art Services",
            "type":"Services"
        }
    ],
    "sg:phone":"+1 612 968 1474",
    "sg:postcode":"55315",
    "sg:province":"MN",
    "sg:tags":[
        "interior",
        "designer",
        "decorator"
    ],
    "wof:name":"Bill Schmieg Decorating",
    "wof:placetype":"venue"
},
  "geometry": {"coordinates":[-93.645005,44.7472],"type":"Point"}
}