{
  "type": "Feature",
  "properties": {
    "addr:full":"264 Franklin St Winona MN 55987",
    "addr:housenumber":"264",
    "addr:postcode":"55987",
    "addr:street":"Franklin St",
    "iso:country":"US",
    "sg:address":"264 Franklin St",
    "sg:city":"Winona",
    "sg:classifiers":[
        {
            "category":"Real Estate",
            "subcategory":"Real Estate Operator",
            "type":"Services"
        }
    ],
    "sg:phone":"+1 507 452 4041",
    "sg:postcode":"55987",
    "sg:province":"MN",
    "sg:tags":[
        "building",
        "apartment"
    ],
    "wof:name":"Parkview Apts",
    "wof:placetype":"venue"
},
  "geometry": {"coordinates":[-91.632232,44.04894],"type":"Point"}
}