{
  "type": "Feature",
  "properties": {
    "iso:country":"US",
    "sg:address":"1501 London Rd",
    "sg:city":"Duluth",
    "sg:classifiers":[
        {
            "category":"Shopping",
            "subcategory":"Bicycles & Sporting Goods",
            "type":"Retail Goods"
        },
        {
            "category":"Autos & Motor Vehicles",
            "subcategory":"Boat Sales",
            "type":"Retail Goods"
        },
        {
            "category":"Recreation",
            "subcategory":"Fishing",
            "type":"Entertainment"
        }
    ],
    "sg:phone":"+1 218 724 8833",
    "sg:postcode":"55812",
    "sg:province":"MN",
    "sg:tags":[
        "tackle",
        "equipment",
        "supply"
    ],
    "sg:website":"http://www.marinegeneral.com",
    "wof:name":"Marine General",
    "wof:placetype":"venue"
},
  "geometry": {"coordinates":[-92.077904,46.800011],"type":"Point"}
}