{
  "type": "Feature",
  "properties": {
    "iso:country":"US",
    "sg:address":"135 Good Counsel Dr",
    "sg:city":"Mankato",
    "sg:classifiers":[
        {
            "category":"Education",
            "subcategory":"School",
            "type":"Public Place"
        }
    ],
    "sg:phone":"+1 507 388 2997",
    "sg:postcode":"56001",
    "sg:province":"MN",
    "wof:name":"Notre Dame Elementary School",
    "wof:placetype":"venue"
},
  "geometry": {"coordinates":[-93.98304899999999,44.186151],"type":"Point"}
}