{
  "type": "Feature",
  "properties": {
    "addr:full":"10400 Goldenrod St NW Coon Rapids MN 55448",
    "addr:housenumber":"10400",
    "addr:postcode":"55448",
    "addr:street":"Goldenrod St Nw",
    "iso:country":"US",
    "sg:address":"10400 Goldenrod St NW",
    "sg:city":"Coon Rapids",
    "sg:classifiers":[
        {
            "category":"Professional",
            "subcategory":"Management & Consulting",
            "type":"Services"
        }
    ],
    "sg:phone":"+1 763 757 0653",
    "sg:postcode":"55448",
    "sg:province":"MN",
    "sg:tags":[
        "consultant",
        "business"
    ],
    "wof:name":"L A Nedge",
    "wof:placetype":"venue"
},
  "geometry": {"coordinates":[-93.275341,45.158896],"type":"Point"}
}