{
  "type": "Feature",
  "properties": {
    "addr:full":"2101 County Road 42 W Burnsville MN 55306",
    "addr:housenumber":"2101",
    "addr:postcode":"55306",
    "addr:street":"County Road 42 W",
    "iso:country":"US",
    "sg:address":"2101 County Road 42 W",
    "sg:city":"Burnsville",
    "sg:classifiers":[
        {
            "category":"Restaurant",
            "type":"Food & Drink"
        }
    ],
    "sg:phone":"+1 952 435 6888",
    "sg:postcode":"55306",
    "sg:province":"MN",
    "sg:website":"www.wendys.com",
    "wof:name":"Wendy's",
    "wof:placetype":"venue"
},
  "geometry": {"coordinates":[-93.304802,44.7463],"type":"Point"}
}