{
  "type": "Feature",
  "properties": {
    "addr:full":"8830 Douglas Dr N Minneapolis MN 55445",
    "addr:housenumber":"8830",
    "addr:postcode":"55445",
    "addr:street":"Douglas Dr N",
    "iso:country":"US",
    "sg:address":"8830 Douglas Dr N",
    "sg:city":"Minneapolis",
    "sg:classifiers":[
        {
            "category":"Professional",
            "subcategory":"Management & Consulting",
            "type":"Services"
        }
    ],
    "sg:phone":"+1 763 424 8070",
    "sg:postcode":"55445",
    "sg:province":"MN",
    "wof:name":"Mark Pollmann",
    "wof:placetype":"venue"
},
  "geometry": {"coordinates":[-93.36225399999999,45.114256],"type":"Point"}
}