{
  "type": "Feature",
  "properties": {
    "addr:full":"340 Railroad St Hamburg MN 55339",
    "addr:housenumber":"340",
    "addr:postcode":"55339",
    "addr:street":"Railroad St",
    "iso:country":"US",
    "sg:address":"340 Railroad St",
    "sg:city":"Hamburg",
    "sg:classifiers":[
        {
            "category":"Manufacturing",
            "subcategory":"Rubber & Plastics",
            "type":"Manufacturing & Wholesale Goods"
        }
    ],
    "sg:phone":"+1 952 467 4030",
    "sg:postcode":"55339",
    "sg:province":"MN",
    "wof:name":"Molded Foam Products",
    "wof:placetype":"venue"
},
  "geometry": {"coordinates":[-93.96707499999999,44.733036],"type":"Point"}
}