{
  "type": "Feature",
  "properties": {
    "iso:country":"US",
    "sg:address":"4630 370th Ave",
    "sg:city":"Elmore",
    "sg:classifiers":[
        {
            "category":"Professional",
            "subcategory":"Business Services",
            "type":"Services"
        }
    ],
    "sg:phone":"+1 507 943 3485",
    "sg:postcode":"56027",
    "sg:province":"MN",
    "sg:tags":[
        "auctioneer"
    ],
    "wof:name":"Marlin Krupp Auctioneer",
    "wof:placetype":"venue"
},
  "geometry": {"coordinates":[-94.127922,43.560196],"type":"Point"}
}