{
  "type": "Feature",
  "properties": {
    "addr:full":"11440 Crooked Lake Blvd NW Minneapolis MN 55433",
    "addr:housenumber":"11440",
    "addr:postcode":"55433",
    "addr:street":"Crooked Lake Blvd Nw",
    "iso:country":"US",
    "sg:address":"11440 Crooked Lake Blvd NW",
    "sg:city":"Minneapolis",
    "sg:classifiers":[
        {
            "category":"Education",
            "subcategory":"Library",
            "type":"Public Place"
        }
    ],
    "sg:phone":"+1 763 576 5972",
    "sg:postcode":"55433",
    "sg:province":"MN",
    "wof:name":"Libraries",
    "wof:placetype":"venue"
},
  "geometry": {"coordinates":[-93.337898,45.1786],"type":"Point"}
}