{
  "type": "Feature",
  "properties": {
    "addr:full":"5225 W 92nd St Bloomington MN 55437",
    "addr:housenumber":"5225",
    "addr:postcode":"55437",
    "addr:street":"W 92Nd St",
    "iso:country":"US",
    "sg:address":"5225 W 92nd St",
    "sg:city":"Bloomington",
    "sg:classifiers":[
        {
            "category":"Real Estate",
            "subcategory":"Real Estate Agent",
            "type":"Services"
        }
    ],
    "sg:phone":"+1 952 830 0707",
    "sg:postcode":"55437",
    "sg:province":"MN",
    "sg:tags":[
        "finding",
        "apartment",
        "rental"
    ],
    "wof:name":"Apartment Hunters",
    "wof:placetype":"venue"
},
  "geometry": {"coordinates":[-93.34858,44.837667],"type":"Point"}
}