{
  "type": "Feature",
  "properties": {
    "addr:full":"33525 Jefferson St NE Cambridge MN 55008",
    "addr:housenumber":"33525",
    "addr:postcode":"55008",
    "addr:street":"Jefferson St Ne",
    "iso:country":"US",
    "sg:address":"33525 Jefferson St NE",
    "sg:city":"Cambridge",
    "sg:classifiers":[
        {
            "category":"Education",
            "subcategory":"School",
            "type":"Public Place"
        }
    ],
    "sg:phone":"+1 763 689 4305",
    "sg:postcode":"55008",
    "sg:province":"MN",
    "sg:tags":[
        "organization",
        "religious"
    ],
    "wof:name":"Calvary Baptist Academy",
    "wof:placetype":"venue"
},
  "geometry": {"coordinates":[-93.254533,45.576278],"type":"Point"}
}