{
  "type": "Feature",
  "properties": {
    "iso:country":"US",
    "sg:address":"8401 73rd Ave N",
    "sg:city":"Minneapolis",
    "sg:classifiers":[
        {
            "category":"Wholesale",
            "subcategory":"Home Furnishings",
            "type":"Manufacturing & Wholesale Goods"
        }
    ],
    "sg:phone":"+1 763 971 0555",
    "sg:postcode":"55428",
    "sg:province":"MN",
    "sg:tags":[
        "utensil",
        "tool",
        "kitchen"
    ],
    "wof:name":"Thyme In The Kitchen Inc",
    "wof:placetype":"venue"
},
  "geometry": {"coordinates":[-93.389664,45.087371],"type":"Point"}
}