{
  "type": "Feature",
  "properties": {
    "addr:full":"23310 Main St Hampton MN 55031",
    "addr:housenumber":"23310",
    "addr:postcode":"55031",
    "addr:street":"Main St",
    "iso:country":"US",
    "sg:address":"23310 Main St",
    "sg:city":"Hampton",
    "sg:classifiers":[
        {
            "category":"Personal",
            "subcategory":"Beauty Salon",
            "type":"Services"
        }
    ],
    "sg:phone":"+1 651 438 7424",
    "sg:postcode":"55031",
    "sg:province":"MN",
    "wof:name":"Main Street Salon",
    "wof:placetype":"venue"
},
  "geometry": {"coordinates":[-92.99808899999999,44.610691],"type":"Point"}
}