{
  "type": "Feature",
  "properties": {
    "addr:full":"122 3rd St N Atwater MN 56209",
    "addr:housenumber":"122",
    "addr:postcode":"56209",
    "addr:street":"3Rd St N",
    "iso:country":"US",
    "sg:address":"122 3rd St N",
    "sg:city":"Atwater",
    "sg:classifiers":[
        {
            "category":"Sports & Exercise",
            "subcategory":"Bowling",
            "type":"Entertainment"
        }
    ],
    "sg:phone":"+1 320 974 8554",
    "sg:postcode":"56209",
    "sg:province":"MN",
    "sg:tags":[
        "center"
    ],
    "wof:name":"Mc Pete's II Sports Bar & Lns",
    "wof:placetype":"venue"
},
  "geometry": {"coordinates":[-94.781006,45.13817],"type":"Point"}
}