{
  "type": "Feature",
  "properties": {
    "iso:country":"US",
    "sg:address":"10995 Club West Pkwy Ste 400",
    "sg:city":"Minneapolis",
    "sg:classifiers":[
        {
            "category":"Insurance",
            "subcategory":"Insurance Agent",
            "type":"Services"
        }
    ],
    "sg:phone":"+1 763 717 0500",
    "sg:postcode":"55449",
    "sg:province":"MN",
    "sg:tags":[
        "auto"
    ],
    "sg:website":"http://clickserve.dartsearch.net/link/click?lid=43000000300033379",
    "wof:name":"Allstate Insurance Company - Chris Reinke",
    "wof:placetype":"venue"
},
  "geometry": {"coordinates":[-93.22987999999999,45.168493],"type":"Point"}
}