{
  "type": "Feature",
  "properties": {
    "iso:country":"US",
    "sg:address":"1506 Maple Grove Rd",
    "sg:city":"Duluth",
    "sg:classifiers":[
        {
            "category":"Professional",
            "subcategory":"Management & Consulting",
            "type":"Services"
        }
    ],
    "sg:phone":"+1 218 727 1249",
    "sg:postcode":"55811",
    "sg:province":"MN",
    "sg:tags":[
        "retail",
        "direct",
        "sales"
    ],
    "wof:name":"Shaklee Distributor",
    "wof:placetype":"venue"
},
  "geometry": {"coordinates":[-92.160965,46.807502],"type":"Point"}
}