{
  "type": "Feature",
  "properties": {
    "addr:full":"10130 Palm St NW Minneapolis MN 55433",
    "addr:housenumber":"10130",
    "addr:postcode":"55433",
    "addr:street":"Palm St Nw",
    "iso:country":"US",
    "sg:address":"10130 Palm St NW",
    "sg:city":"Minneapolis",
    "sg:classifiers":[
        {
            "category":"Utilities",
            "subcategory":"Refuse",
            "type":"Services"
        }
    ],
    "sg:phone":"+1 763 754 6655",
    "sg:postcode":"55433",
    "sg:province":"MN",
    "sg:tags":[
        "rubbish",
        "container",
        "collection",
        "garbage",
        "removal"
    ],
    "wof:name":"A-1 A Beyer's Hauling Inc",
    "wof:placetype":"venue"
},
  "geometry": {"coordinates":[-93.28719700000001,45.153877],"type":"Point"}
}