{
  "type": "Feature",
  "properties": {
    "iso:country":"US",
    "sg:address":"101 14th St NE",
    "sg:city":"Buffalo",
    "sg:classifiers":[
        {
            "category":"Health Services",
            "subcategory":"Health Practitioner",
            "type":"Services"
        }
    ],
    "sg:phone":"+1 763 684 3880",
    "sg:postcode":"55313",
    "sg:province":"MN",
    "sg:tags":[
        "therapist",
        "physical"
    ],
    "wof:name":"Buffalo Hospital Sister Kenny",
    "wof:placetype":"venue"
},
  "geometry": {"coordinates":[-93.871979,45.18622],"type":"Point"}
}