{
  "type": "Feature",
  "properties": {
    "iso:country":"US",
    "sg:address":"919 W Armstrong Ave",
    "sg:city":"St Paul",
    "sg:classifiers":[
        {
            "category":"Social Services",
            "type":"Services"
        }
    ],
    "sg:phone":"+1 651 292 1965",
    "sg:postcode":"55102",
    "sg:province":"MN",
    "sg:tags":[
        "organization",
        "religious",
        "welfare"
    ],
    "sg:website":"www.sarahfamilyministries.org",
    "wof:name":"Sarah Family Ministries",
    "wof:placetype":"venue"
},
  "geometry": {"coordinates":[-93.13641800000001,44.925022],"type":"Point"}
}