{
  "type": "Feature",
  "properties": {
    "addr:full":"7306 Rogers Point Trl NW Walker MN 56484",
    "addr:housenumber":"7306",
    "addr:postcode":"56484",
    "addr:street":"Rogers Point Trl Nw",
    "iso:country":"US",
    "sg:address":"7306 Rogers Point Trl NW",
    "sg:city":"Walker",
    "sg:classifiers":[
        {
            "category":"Building & Trades",
            "subcategory":"Construction",
            "type":"Services"
        }
    ],
    "sg:phone":"+1 218 547 4140",
    "sg:postcode":"56484",
    "sg:province":"MN",
    "sg:tags":[
        "industrial"
    ],
    "wof:name":"Leech Lake Builders Inc",
    "wof:placetype":"venue"
},
  "geometry": {"coordinates":[-94.406803,47.07062],"type":"Point"}
}