{
  "type": "Feature",
  "properties": {
    "addr:full":"4125 Clinton Ave S Minneapolis MN 55409",
    "addr:housenumber":"4125",
    "addr:postcode":"55409",
    "addr:street":"Clinton Ave S",
    "iso:country":"US",
    "sg:address":"4125 Clinton Ave S",
    "sg:city":"Minneapolis",
    "sg:classifiers":[
        {
            "category":"Social Services",
            "subcategory":"Child Care",
            "type":"Services"
        }
    ],
    "sg:phone":"+1 612 824 2316",
    "sg:postcode":"55409",
    "sg:province":"MN",
    "sg:tags":[
        "daycare",
        "provider"
    ],
    "wof:name":"Diane Sterling",
    "wof:placetype":"venue"
},
  "geometry": {"coordinates":[-93.27136400000001,44.927889],"type":"Point"}
}