{
  "type": "Feature",
  "properties": {
    "iso:country":"US",
    "sg:address":"1403 E College Dr",
    "sg:city":"Marshall",
    "sg:classifiers":[
        {
            "category":"Banks & Credit Unions",
            "subcategory":"Bank",
            "type":"Services"
        }
    ],
    "sg:phone":"+1 507 532 9151",
    "sg:postcode":"56258",
    "sg:province":"MN",
    "wof:name":"United Southwest Bank",
    "wof:placetype":"venue"
},
  "geometry": {"coordinates":[-95.764306,44.45053],"type":"Point"}
}