{
  "type": "Feature",
  "properties": {
    "iso:country":"US",
    "sg:address":"12465 Heather Ave N",
    "sg:city":"Hugo",
    "sg:classifiers":[
        {
            "category":"Personal",
            "type":"Services"
        }
    ],
    "sg:phone":"+1 651 653 0064",
    "sg:postcode":"55038",
    "sg:province":"MN",
    "wof:name":"Wausau Financial Systems Inc",
    "wof:placetype":"venue"
},
  "geometry": {"coordinates":[-92.95729,45.130367],"type":"Point"}
}