{
  "type": "Feature",
  "properties": {
    "iso:country":"US",
    "sg:address":"400 2nd St S",
    "sg:city":"St Cloud",
    "sg:classifiers":[
        {
            "category":"Recreation",
            "type":"Entertainment"
        }
    ],
    "sg:phone":"+1 320 529 6580",
    "sg:postcode":"56301",
    "sg:province":"MN",
    "sg:tags":[
        "pool",
        "swimming"
    ],
    "wof:name":"St Cloud Municipal Pool",
    "wof:placetype":"venue"
},
  "geometry": {"coordinates":[-94.15652,45.55927],"type":"Point"}
}