{
  "type": "Feature",
  "properties": {
    "iso:country":"US",
    "sg:address":"1280 Hwy 14 W",
    "sg:city":"Rochester",
    "sg:classifiers":[
        {
            "category":"Restaurant",
            "type":"Food & Drink"
        }
    ],
    "sg:phone":"+1 507 288 4944",
    "sg:postcode":"55902",
    "sg:province":"MN",
    "wof:name":"Romano's Macaroni Grill",
    "wof:placetype":"venue"
},
  "geometry": {"coordinates":[-92.481253,44.006955],"type":"Point"}
}