{
  "type": "Feature",
  "properties": {
    "iso:country":"US",
    "sg:address":"403 S. Cedar Lake Road",
    "sg:city":"Minneapolis",
    "sg:classifiers":[
        {
            "category":"Shopping",
            "subcategory":"Beauty & Cosmetics",
            "type":"Retail Goods"
        },
        {
            "category":"Home & Garden",
            "subcategory":"Home Furnishings",
            "type":"Retail Goods"
        },
        {
            "category":"Shopping",
            "subcategory":"Antiques",
            "type":"Retail Goods"
        }
    ],
    "sg:phone":"+1 612 377 8000",
    "sg:postcode":"55405",
    "sg:province":"MN",
    "sg:tags":[
        "decor",
        "supply"
    ],
    "sg:website":"cockadoodledoostore.com/",
    "wof:name":"Cockadoodledoo",
    "wof:placetype":"venue"
},
  "geometry": {"coordinates":[-93.30836499999999,44.973706],"type":"Point"}
}