{
  "type": "Feature",
  "properties": {
    "addr:full":"38360 N Eagle Lake Rd Battle Lake MN 56515",
    "addr:housenumber":"38360",
    "addr:postcode":"56515",
    "addr:street":"N Eagle Lake Rd",
    "iso:country":"US",
    "sg:address":"38360 N Eagle Lake Rd",
    "sg:city":"Battle Lake",
    "sg:classifiers":[
        {
            "category":"Travel",
            "subcategory":"Campground",
            "type":"Entertainment"
        }
    ],
    "sg:phone":"+1 218 864 5303",
    "sg:postcode":"56515",
    "sg:province":"MN",
    "sg:tags":[
        "recreation",
        "sport",
        "camp"
    ],
    "wof:name":"Faith Haven Camp Inc",
    "wof:placetype":"venue"
},
  "geometry": {"coordinates":[-95.694428,46.178977],"type":"Point"}
}