{
  "type": "Feature",
  "properties": {
    "iso:country":"US",
    "sg:address":"6156 McQuade Rd",
    "sg:city":"Duluth",
    "sg:classifiers":[
        {
            "category":"Manufacturing",
            "subcategory":"Apparel",
            "type":"Manufacturing & Wholesale Goods"
        }
    ],
    "sg:phone":"+1 218 525 2518",
    "sg:postcode":"55804",
    "sg:province":"MN",
    "sg:tags":[
        "product",
        "mfg"
    ],
    "wof:name":"Canvas Works",
    "wof:placetype":"venue"
},
  "geometry": {"coordinates":[-91.921003,46.956827],"type":"Point"}
}