{
  "type": "Feature",
  "properties": {
    "addr:full":"2084 State Hwy 15 Truman MN 56088",
    "addr:housenumber":"2084",
    "addr:postcode":"56088",
    "addr:street":"State Hwy 15 Truman",
    "iso:country":"US",
    "sg:address":"2084 State Hwy 15",
    "sg:city":"Truman",
    "sg:classifiers":[
        {
            "category":"Farming",
            "subcategory":"Livestock Farm",
            "type":"Manufacturing & Wholesale Goods"
        }
    ],
    "sg:phone":"+1 507 776 2137",
    "sg:postcode":"56088",
    "sg:province":"MN",
    "sg:tags":[
        "hog",
        "or",
        "feedlot"
    ],
    "wof:name":"Vogts Hog Finishing",
    "wof:placetype":"venue"
},
  "geometry": {"coordinates":[-94.42793899999999,43.778572],"type":"Point"}
}