{
  "type": "Feature",
  "properties": {
    "addr:full":"409 Paul Ave S Cologne MN 55322",
    "addr:housenumber":"409",
    "addr:postcode":"55322",
    "addr:street":"Paul Ave S Cologne",
    "iso:country":"US",
    "sg:address":"409 Paul Ave S",
    "sg:city":"Cologne",
    "sg:classifiers":[
        {
            "category":"Food & Beverages",
            "subcategory":"Groceries & Convenience Stores",
            "type":"Retail Goods"
        }
    ],
    "sg:phone":"+1 952 466 5657",
    "sg:postcode":"55322",
    "sg:province":"MN",
    "wof:name":"Cenex Convenience Store",
    "wof:placetype":"venue"
},
  "geometry": {"coordinates":[-93.781426,44.767485],"type":"Point"}
}