{
  "type": "Feature",
  "properties": {
    "addr:full":"825 Nicollet Mall Ste 190 Minneapolis MN 55402",
    "addr:housenumber":"825",
    "addr:postcode":"55402",
    "addr:street":"Nicollet Mall Ste 190",
    "iso:country":"US",
    "sg:address":"825 Nicollet Mall Ste 190",
    "sg:city":"Minneapolis",
    "sg:classifiers":[
        {
            "category":"Personal",
            "subcategory":"Barber",
            "type":"Services"
        }
    ],
    "sg:phone":"+1 612 332 4334",
    "sg:postcode":"55402",
    "sg:province":"MN",
    "wof:name":"Arcade Barbers",
    "wof:placetype":"venue"
},
  "geometry": {"coordinates":[-93.273225,44.975672],"type":"Point"}
}