{
  "type": "Feature",
  "properties": {
    "addr:full":"105 S Cedar St Onamia MN 56359",
    "addr:housenumber":"105",
    "addr:postcode":"56359",
    "addr:street":"S Cedar St",
    "iso:country":"US",
    "sg:address":"105 S Cedar St",
    "sg:city":"Onamia",
    "sg:classifiers":[
        {
            "category":"Shopping",
            "subcategory":"Gifts & Souvenirs",
            "type":"Retail Goods"
        }
    ],
    "sg:phone":"+1 320 532 3162",
    "sg:postcode":"56359",
    "sg:province":"MN",
    "sg:tags":[
        "announcement",
        "invitation"
    ],
    "wof:name":"Business Industries Inc",
    "wof:placetype":"venue"
},
  "geometry": {"coordinates":[-93.665503,46.068219],"type":"Point"}
}