{
  "type": "Feature",
  "properties": {
    "addr:full":"461 3rd St N Dassel MN 55325",
    "addr:housenumber":"461",
    "addr:postcode":"55325",
    "addr:street":"3Rd St N",
    "iso:country":"US",
    "sg:address":"461 3rd St N",
    "sg:city":"Dassel",
    "sg:classifiers":[
        {
            "category":"Building & Trades",
            "subcategory":"Electrical",
            "type":"Services"
        }
    ],
    "sg:phone":"+1 320 275 2764",
    "sg:postcode":"55325",
    "sg:province":"MN",
    "sg:tags":[
        "electric",
        "contractor"
    ],
    "wof:name":"Bonniwell Electric Inc",
    "wof:placetype":"venue"
},
  "geometry": {"coordinates":[-94.30983000000001,45.081745],"type":"Point"}
}