{
  "type": "Feature",
  "properties": {
    "addr:full":"3534 Douglas Dr N Minneapolis MN 55422",
    "addr:housenumber":"3534",
    "addr:postcode":"55422",
    "addr:street":"Douglas Dr N",
    "iso:country":"US",
    "sg:address":"3534 Douglas Dr N",
    "sg:city":"Minneapolis",
    "sg:classifiers":[
        {
            "category":"Shopping",
            "subcategory":"Clothing, Apparel, & Fashions",
            "type":"Retail Goods"
        }
    ],
    "sg:phone":"+1 763 592 0154",
    "sg:postcode":"55422",
    "sg:province":"MN",
    "sg:tags":[
        "tailor"
    ],
    "wof:name":"Fishinco Tailoring & Alteratn",
    "wof:placetype":"venue"
},
  "geometry": {"coordinates":[-93.35998499999999,45.021475],"type":"Point"}
}