{
  "type": "Feature",
  "properties": {
    "addr:full":"306 Main Ave S Park Rapids MN 56470",
    "addr:housenumber":"306",
    "addr:postcode":"56470",
    "addr:street":"Main Ave S Park",
    "iso:country":"US",
    "sg:address":"306 Main Ave S",
    "sg:city":"Park Rapids",
    "sg:classifiers":[
        {
            "category":"Shopping",
            "subcategory":"Gifts & Souvenirs",
            "type":"Retail Goods"
        }
    ],
    "sg:phone":"+1 218 732 8988",
    "sg:postcode":"56470",
    "sg:province":"MN",
    "sg:tags":[
        "shop"
    ],
    "sg:website":"www.clowsnest.com",
    "wof:name":"Clow's Nest",
    "wof:placetype":"venue"
},
  "geometry": {"coordinates":[-95.059915,46.919975],"type":"Point"}
}