{
  "type": "Feature",
  "properties": {
    "addr:full":"16138 US Hwy 169 Milaca MN 56353",
    "addr:housenumber":"16138",
    "addr:postcode":"56353",
    "addr:street":"Us Hwy 169",
    "iso:country":"US",
    "sg:address":"16138 US Hwy 169",
    "sg:city":"Milaca",
    "sg:classifiers":[
        {
            "category":"Autos & Motor Vehicles",
            "subcategory":"Automobile Sales",
            "type":"Retail Goods"
        }
    ],
    "sg:phone":"+1 320 983 3444",
    "sg:postcode":"56353",
    "sg:province":"MN",
    "sg:tags":[
        "car",
        "dealer"
    ],
    "sg:website":"www.nlaci.com",
    "wof:name":"Northland Auto Ctr Inc",
    "wof:placetype":"venue"
},
  "geometry": {"coordinates":[-93.649038,45.780182],"type":"Point"}
}