{
  "type": "Feature",
  "properties": {
    "iso:country":"US",
    "sg:address":"524 NW 3rd Ave",
    "sg:city":"Grand Rapids",
    "sg:classifiers":[
        {
            "category":"Home & Garden",
            "subcategory":"Household Appliances",
            "type":"Retail Goods"
        }
    ],
    "sg:phone":"+1 218 326 6607",
    "sg:postcode":"55744",
    "sg:province":"MN",
    "sg:tags":[
        "cleaners",
        "vacuum"
    ],
    "wof:name":"Kirby Repair Shop Co",
    "wof:placetype":"venue"
},
  "geometry": {"coordinates":[-93.53288499999999,47.237214],"type":"Point"}
}