{
  "type": "Feature",
  "properties": {
    "iso:country":"US",
    "sg:address":"209 Saint Anthony St N",
    "sg:city":"Preston",
    "sg:classifiers":[
        {
            "category":"Food & Beverages",
            "subcategory":"Liquor & Beverages",
            "type":"Retail Goods"
        }
    ],
    "sg:phone":"+1 507 765 2565",
    "sg:postcode":"55965",
    "sg:province":"MN",
    "wof:name":"Preston Liquor Store",
    "wof:placetype":"venue"
},
  "geometry": {"coordinates":[-92.081974,43.671515],"type":"Point"}
}