{
  "type": "Feature",
  "properties": {
    "iso:country":"US",
    "sg:address":"16609 77th Pl N",
    "sg:city":"Osseo",
    "sg:classifiers":[
        {
            "category":"Real Estate",
            "subcategory":"Real Estate Services",
            "type":"Services"
        },
        {
            "category":"Real Estate",
            "subcategory":"Real Estate Agent",
            "type":"Services"
        }
    ],
    "sg:phone":"+1 763 420 8945",
    "sg:postcode":"55311",
    "sg:province":"MN",
    "sg:tags":[
        "buyer",
        "broker"
    ],
    "wof:name":"Leann Sargent Ltd",
    "wof:placetype":"venue"
},
  "geometry": {"coordinates":[-93.490923,45.095689],"type":"Point"}
}