{
  "type": "Feature",
  "properties": {
    "addr:full":"1021 1st St NW St Paul MN 55112",
    "addr:housenumber":"1021",
    "addr:postcode":"55112",
    "addr:street":"1St St Nw",
    "iso:country":"US",
    "sg:address":"1021 1st St NW",
    "sg:city":"St Paul",
    "sg:classifiers":[
        {
            "category":"Freight",
            "type":"Transportation"
        }
    ],
    "sg:phone":"+1 651 636 0366",
    "sg:postcode":"55112",
    "sg:province":"MN",
    "sg:tags":[
        "trucking"
    ],
    "wof:name":"Roadrunner Trucking Inc",
    "wof:placetype":"venue"
},
  "geometry": {"coordinates":[-93.2016,45.050975],"type":"Point"}
}