{
  "type": "Feature",
  "properties": {
    "iso:country":"US",
    "sg:address":"1218 E 1st St",
    "sg:city":"Duluth",
    "sg:classifiers":[
        {
            "category":"Personal",
            "subcategory":"Beauty Salon",
            "type":"Services"
        }
    ],
    "sg:phone":"+1 218 728 9018",
    "sg:postcode":"55805",
    "sg:province":"MN",
    "wof:name":"Illusions Hair Design",
    "wof:placetype":"venue"
},
  "geometry": {"coordinates":[-92.083191,46.799786],"type":"Point"}
}