{
  "type": "Feature",
  "properties": {
    "iso:country":"US",
    "sg:address":"6933 210th St W",
    "sg:city":"Faribault",
    "sg:classifiers":[
        {
            "category":"Building & Trades",
            "subcategory":"Construction",
            "type":"Services"
        }
    ],
    "sg:phone":"+1 507 334 5789",
    "sg:postcode":"55021",
    "sg:province":"MN",
    "sg:tags":[
        "contractor",
        "mechanical"
    ],
    "wof:name":"Als Mechanical",
    "wof:placetype":"venue"
},
  "geometry": {"coordinates":[-93.40197000000001,44.283321],"type":"Point"}
}