{
  "type": "Feature",
  "properties": {
    "addr:full":"20121 Co Rd 10 Hamel MN 55340",
    "addr:housenumber":"20121;10",
    "addr:postcode":"55340",
    "addr:street":"Co Rd;Hamel",
    "iso:country":"US",
    "sg:address":"20121 Co Rd 10",
    "sg:city":"Hamel",
    "sg:classifiers":[
        {
            "category":"Organizations",
            "subcategory":"Community Association",
            "type":"Services"
        }
    ],
    "sg:phone":"+1 763 420 2555",
    "sg:postcode":"55340",
    "sg:province":"MN",
    "wof:name":"Lyons Club",
    "wof:placetype":"venue"
},
  "geometry": {"coordinates":[-93.548289,45.095097],"type":"Point"}
}