{
  "type": "Feature",
  "properties": {
    "addr:full":"4101 W Division St St Cloud MN 56301",
    "addr:housenumber":"4101",
    "addr:postcode":"56301",
    "addr:street":"W Division St",
    "iso:country":"US",
    "sg:address":"4101 W Division St",
    "sg:city":"St Cloud",
    "sg:classifiers":[
        {
            "category":"Shopping",
            "subcategory":"Clothing, Apparel, & Fashions",
            "type":"Retail Goods"
        }
    ],
    "sg:phone":"+1 320 251 0237",
    "sg:postcode":"56301",
    "sg:province":"MN",
    "sg:tags":[
        "furnishing"
    ],
    "wof:name":"Express Mens",
    "wof:placetype":"venue"
},
  "geometry": {"coordinates":[-94.21331499999999,45.553492],"type":"Point"}
}