{
  "type": "Feature",
  "properties": {
    "addr:full":"4211 Oregon Ave N Minneapolis MN 55428",
    "addr:housenumber":"4211",
    "addr:postcode":"55428",
    "addr:street":"Oregon Ave N",
    "iso:country":"US",
    "sg:address":"4211 Oregon Ave N",
    "sg:city":"Minneapolis",
    "sg:classifiers":[
        {
            "category":"Building & Trades",
            "subcategory":"Construction",
            "type":"Services"
        }
    ],
    "sg:phone":"+1 763 520 2490",
    "sg:postcode":"55428",
    "sg:province":"MN",
    "sg:tags":[
        "house",
        "improvement",
        "home"
    ],
    "wof:name":"K's Home Improvements",
    "wof:placetype":"venue"
},
  "geometry": {"coordinates":[-93.374106,45.038436],"type":"Point"}
}