{
  "type": "Feature",
  "properties": {
    "iso:country":"US",
    "sg:address":"381 Fry St",
    "sg:city":"St Paul",
    "sg:classifiers":[
        {
            "category":"Professional",
            "subcategory":"Computer Services",
            "type":"Services"
        }
    ],
    "sg:phone":"+1 651 291 5125",
    "sg:postcode":"55104",
    "sg:province":"MN",
    "sg:tags":[
        "website",
        "design"
    ],
    "wof:name":"Edigita Corp",
    "wof:placetype":"venue"
},
  "geometry": {"coordinates":[-93.16965,44.953252],"type":"Point"}
}