{
  "type": "Feature",
  "properties": {
    "iso:country":"US",
    "sg:address":"29338 Endress Way",
    "sg:city":"Cannon Falls",
    "sg:classifiers":[
        {
            "category":"Manufacturing",
            "subcategory":"Printing",
            "type":"Manufacturing & Wholesale Goods"
        }
    ],
    "sg:phone":"+1 507 263 2107",
    "sg:postcode":"55009",
    "sg:province":"MN",
    "sg:tags":[
        "book"
    ],
    "wof:name":"Jonathan Press",
    "wof:placetype":"venue"
},
  "geometry": {"coordinates":[-92.993489,44.523492],"type":"Point"}
}