{
  "type": "Feature",
  "properties": {
    "iso:country":"US",
    "sg:address":"116 Holmes St S",
    "sg:city":"Shakopee",
    "sg:classifiers":[
        {
            "category":"Personal",
            "subcategory":"Beauty Salon",
            "type":"Services"
        }
    ],
    "sg:phone":"+1 952 233 2557",
    "sg:postcode":"55379",
    "sg:province":"MN",
    "sg:tags":[
        "shop"
    ],
    "wof:name":"Annas Beauty Salon",
    "wof:placetype":"venue"
},
  "geometry": {"coordinates":[-93.527136,44.798616],"type":"Point"}
}