{
  "type": "Feature",
  "properties": {
    "iso:country":"US",
    "sg:address":"3746 Sunset Dr",
    "sg:city":"Spring Park",
    "sg:classifiers":[
        {
            "category":"Restaurant",
            "type":"Food & Drink"
        }
    ],
    "sg:phone":"+1 952 471 8513",
    "sg:postcode":"55384",
    "sg:province":"MN",
    "sg:tags":[
        "personal",
        "eating"
    ],
    "wof:name":"Lord Fletchers of The Lake",
    "wof:placetype":"venue"
},
  "geometry": {"coordinates":[-93.61745000000001,44.941569],"type":"Point"}
}