{
  "type": "Feature",
  "properties": {
    "addr:full":"3992 Pennsylvania Ave Eagan MN 55123",
    "addr:housenumber":"3992",
    "addr:postcode":"55123",
    "addr:street":"Pennsylvania Ave",
    "iso:country":"US",
    "sg:address":"3992 Pennsylvania Ave",
    "sg:city":"Eagan",
    "sg:classifiers":[
        {
            "category":"Building & Trades",
            "subcategory":"Plumbing",
            "type":"Services"
        }
    ],
    "sg:phone":"+1 651 686 6696",
    "sg:postcode":"55123",
    "sg:province":"MN",
    "sg:tags":[
        "plumbing",
        "contractor"
    ],
    "wof:name":"Bruckmueller Plumbing Inc",
    "wof:placetype":"venue"
},
  "geometry": {"coordinates":[-93.128922,44.810932],"type":"Point"}
}