{
  "type": "Feature",
  "properties": {
    "addr:full":"231 Ellsworth St SE Sleepy Eye MN 56085",
    "addr:housenumber":"231",
    "addr:postcode":"56085",
    "addr:street":"Ellsworth St Se;Eye",
    "iso:country":"US",
    "sg:address":"231 Ellsworth St SE",
    "sg:city":"Sleepy Eye",
    "sg:classifiers":[
        {
            "category":"Health Services",
            "subcategory":"Doctor",
            "type":"Services"
        }
    ],
    "sg:phone":"+1 507 794 2180",
    "sg:postcode":"56085",
    "sg:province":"MN",
    "sg:tags":[
        "physician",
        "surgeon"
    ],
    "wof:name":"Curtis Greg Dr Dnst",
    "wof:placetype":"venue"
},
  "geometry": {"coordinates":[-94.71917999999999,44.286273],"type":"Point"}
}