{
  "type": "Feature",
  "properties": {
    "iso:country":"US",
    "sg:address":"3257 Watkins Spur Rd",
    "sg:city":"Cloquet",
    "sg:classifiers":[
        {
            "category":"Professional",
            "subcategory":"Business Services",
            "type":"Services"
        }
    ],
    "sg:phone":"+1 218 879 6166",
    "sg:postcode":"55720",
    "sg:province":"MN",
    "wof:name":"Tri County Home Inspection",
    "wof:placetype":"venue"
},
  "geometry": {"coordinates":[-92.636019,46.704273],"type":"Point"}
}