{
  "type": "Feature",
  "properties": {
    "addr:full":"3257 Watkins Spur Rd Cloquet MN 55720",
    "addr:housenumber":"3257",
    "addr:postcode":"55720",
    "addr:street":"Watkins Spur Rd",
    "iso:country":"US",
    "sg:address":"3257 Watkins Spur Rd",
    "sg:city":"Cloquet",
    "sg:classifiers":[
        {
            "category":"Professional",
            "subcategory":"Business Services",
            "type":"Services"
        }
    ],
    "sg:phone":"+1 218 879 6166",
    "sg:postcode":"55720",
    "sg:province":"MN",
    "wof:name":"Tri County Home Inspection",
    "wof:placetype":"venue"
},
  "geometry": {"coordinates":[-92.636019,46.704273],"type":"Point"}
}