{
  "type": "Feature",
  "properties": {
    "iso:country":"US",
    "sg:address":"75417 255th St",
    "sg:city":"Clarks Grove",
    "sg:classifiers":[
        {
            "category":"Manufacturing",
            "subcategory":"Glass & Minerals",
            "type":"Manufacturing & Wholesale Goods"
        }
    ],
    "sg:phone":"+1 507 826 3281",
    "sg:postcode":"56016",
    "sg:province":"MN",
    "sg:tags":[
        "ready"
    ],
    "wof:name":"Clark's Grove Ready Mix",
    "wof:placetype":"venue"
},
  "geometry": {"coordinates":[-93.359865,43.723883],"type":"Point"}
}