{
  "type": "Feature",
  "properties": {
    "iso:country":"US",
    "sg:address":"14460 Shore Ln NE",
    "sg:city":"Prior Lake",
    "sg:classifiers":[
        {
            "category":"Manufacturing",
            "subcategory":"Metals",
            "type":"Manufacturing & Wholesale Goods"
        }
    ],
    "sg:phone":"+1 952 496 1492",
    "sg:postcode":"55372",
    "sg:province":"MN",
    "sg:tags":[
        "tool",
        "mfg"
    ],
    "wof:name":"All Star Engraving",
    "wof:placetype":"venue"
},
  "geometry": {"coordinates":[-93.409691,44.741488],"type":"Point"}
}