{
  "type": "Feature",
  "properties": {
    "iso:country":"US",
    "sg:address":"2875 130th St W",
    "sg:city":"Faribault",
    "sg:classifiers":[
        {
            "category":"Fast Food",
            "type":"Food & Drink"
        },
        {
            "category":"Restaurant",
            "type":"Food & Drink"
        },
        {
            "category":"Food & Beverages",
            "subcategory":"Groceries & Convenience Stores",
            "type":"Retail Goods"
        }
    ],
    "sg:phone":"+1 507 663 1509",
    "sg:postcode":"55021",
    "sg:province":"MN",
    "sg:tags":[
        "shop",
        "american",
        "sandwich",
        "take"
    ],
    "wof:name":"Subway",
    "wof:placetype":"venue"
},
  "geometry": {"coordinates":[-93.32016400000001,44.399611],"type":"Point"}
}