{
  "type": "Feature",
  "properties": {
    "addr:full":"601 Railway St SW Lonsdale MN 55046",
    "addr:housenumber":"601",
    "addr:postcode":"55046",
    "addr:street":"Railway St Sw",
    "iso:country":"US",
    "sg:address":"601 Railway St SW",
    "sg:city":"Lonsdale",
    "sg:classifiers":[
        {
            "category":"Building & Trades",
            "subcategory":"Landscaping Services",
            "type":"Services"
        }
    ],
    "sg:phone":"+1 507 744 2267",
    "sg:postcode":"55046",
    "sg:province":"MN",
    "sg:tags":[
        "lawn",
        "maintenance"
    ],
    "wof:name":"Grass Master Lawn Service",
    "wof:placetype":"venue"
},
  "geometry": {"coordinates":[-93.438008,44.47791],"type":"Point"}
}