{
  "type": "Feature",
  "properties": {
    "iso:country":"US",
    "sg:address":"2950 Metro Dr",
    "sg:city":"Bloomington",
    "sg:classifiers":[
        {
            "category":"Health Services",
            "subcategory":"Clinic",
            "type":"Services"
        }
    ],
    "sg:phone":"+1 952 854 2285",
    "sg:postcode":"55425",
    "sg:province":"MN",
    "sg:tags":[
        "home"
    ],
    "wof:name":"Universal Pediatric Svc Inc",
    "wof:placetype":"venue"
},
  "geometry": {"coordinates":[-93.22751599999999,44.858715],"type":"Point"}
}