{
  "type": "Feature",
  "properties": {
    "iso:country":"US",
    "sg:address":"16165 Huron Path",
    "sg:city":"Lakeville",
    "sg:classifiers":[
        {
            "category":"Government",
            "subcategory":"Office",
            "type":"Public Place"
        }
    ],
    "sg:phone":"+1 952 953 4549",
    "sg:postcode":"55044",
    "sg:province":"MN",
    "wof:name":"USDA National Appeals Div",
    "wof:placetype":"venue"
},
  "geometry": {"coordinates":[-93.244029,44.714718],"type":"Point"}
}