{
  "type": "Feature",
  "properties": {
    "iso:country":"US",
    "sg:address":"29764 Mohican Cir",
    "sg:city":"Pequot Lakes",
    "sg:classifiers":[
        {
            "category":"Building & Trades",
            "subcategory":"Cleaning & Sanitation",
            "type":"Services"
        },
        {
            "category":"Building & Trades",
            "subcategory":"Plumbing",
            "type":"Services"
        }
    ],
    "sg:phone":"+1 218 562 4082",
    "sg:postcode":"56472",
    "sg:province":"MN",
    "sg:tags":[
        "ventilating",
        "system",
        "contractor"
    ],
    "wof:name":"Northern Skies Air Duct Cleani",
    "wof:placetype":"venue"
},
  "geometry": {"coordinates":[-94.23150200000001,46.585382],"type":"Point"}
}