{
  "type": "Feature",
  "properties": {
    "addr:full":"1215 NW 4th St Grand Rapids MN 55744",
    "addr:housenumber":"1215",
    "addr:postcode":"55744",
    "addr:street":"Nw 4Th St",
    "iso:country":"US",
    "sg:address":"1215 NW 4th St",
    "sg:city":"Grand Rapids",
    "sg:classifiers":[
        {
            "category":"Travel",
            "subcategory":"Hotels & Motels",
            "type":"Entertainment"
        }
    ],
    "sg:phone":"+1 218 326 6609",
    "sg:postcode":"55744",
    "sg:province":"MN",
    "sg:tags":[
        "operation"
    ],
    "wof:name":"Forest Lake Motel Inc",
    "wof:placetype":"venue"
},
  "geometry": {"coordinates":[-93.546699,47.236073],"type":"Point"}
}