{
  "type": "Feature",
  "properties": {
    "addr:full":"5516 11th Ave S Minneapolis MN 55417",
    "addr:housenumber":"5516",
    "addr:postcode":"55417",
    "addr:street":"11Th Ave S",
    "iso:country":"US",
    "sg:address":"5516 11th Ave S",
    "sg:city":"Minneapolis",
    "sg:classifiers":[
        {
            "category":"Real Estate",
            "subcategory":"Real Estate Services",
            "type":"Services"
        }
    ],
    "sg:phone":"+1 612 821 9174",
    "sg:postcode":"55417",
    "sg:province":"MN",
    "sg:tags":[
        "commercial"
    ],
    "wof:name":"Mountain West Services Inc",
    "wof:placetype":"venue"
},
  "geometry": {"coordinates":[-93.258888,44.903122],"type":"Point"}
}