{
  "type": "Feature",
  "properties": {
    "iso:country":"US",
    "sg:address":"20497 Pintail Ct",
    "sg:city":"Rogers",
    "sg:classifiers":[
        {
            "category":"Building & Trades",
            "subcategory":"Construction",
            "type":"Services"
        }
    ],
    "sg:phone":"+1 763 238 0596",
    "sg:postcode":"55374",
    "sg:province":"MN",
    "sg:tags":[
        "contractor",
        "painting",
        "hanging"
    ],
    "wof:name":"Stewys Painting Inc",
    "wof:placetype":"venue"
},
  "geometry": {"coordinates":[-93.539722,45.208752],"type":"Point"}
}