{
  "type": "Feature",
  "properties": {
    "iso:country":"US",
    "sg:address":"503 Belvidere St E",
    "sg:city":"Saint Paul",
    "sg:classifiers":[
        {
            "category":"Professional",
            "type":"Services"
        }
    ],
    "sg:phone":"+1 651 222 3267",
    "sg:postcode":"55107",
    "sg:province":"MN",
    "wof:name":"Silvia Espinoza",
    "wof:placetype":"venue"
},
  "geometry": {"coordinates":[-93.063864,44.922192],"type":"Point"}
}