{
  "type": "Feature",
  "properties": {
    "iso:country":"US",
    "sg:address":"3935 Minnehaha Ave",
    "sg:city":"Minneapolis",
    "sg:classifiers":[
        {
            "category":"Freight",
            "type":"Transportation"
        }
    ],
    "sg:phone":"+1 612 721 1585",
    "sg:postcode":"55406",
    "sg:province":"MN",
    "wof:name":"Michaelsen Transportation",
    "wof:placetype":"venue"
},
  "geometry": {"coordinates":[-93.221548,44.931212],"type":"Point"}
}