{
  "type": "Feature",
  "properties": {
    "iso:country":"US",
    "sg:address":"4737 S County Rd 101",
    "sg:city":"Minnetonka",
    "sg:classifiers":[
        {
            "category":"Building & Trades",
            "subcategory":"Plumbing",
            "type":"Services"
        }
    ],
    "sg:phone":"+1 952 888 7341",
    "sg:postcode":"55345",
    "sg:province":"MN",
    "sg:website":"minnetonkamn.rotorooter.com/",
    "wof:name":"Roto-Rooter Plumbing & Drain Services",
    "wof:placetype":"venue"
},
  "geometry": {"coordinates":[-93.50300900000001,44.916334],"type":"Point"}
}