{
  "type": "Feature",
  "properties": {
    "iso:country":"US",
    "sg:address":"501 S State St",
    "sg:city":"Waseca",
    "sg:classifiers":[
        {
            "category":"Utilities",
            "subcategory":"Fuel Oil & Lpg",
            "type":"Services"
        }
    ],
    "sg:phone":"+1 507 835 2610",
    "sg:postcode":"56093",
    "sg:province":"MN",
    "wof:name":"Kritzer Oil Co",
    "wof:placetype":"venue"
},
  "geometry": {"coordinates":[-93.50770799999999,44.075098],"type":"Point"}
}