{
  "type": "Feature",
  "properties": {
    "addr:full":"1712 Randolph Ave Saint Paul MN 55105",
    "addr:housenumber":"1712",
    "addr:postcode":"55105",
    "addr:street":"Randolph Ave",
    "iso:country":"US",
    "sg:address":"1712 Randolph Ave",
    "sg:city":"Saint Paul",
    "sg:classifiers":[
        {
            "category":"Education",
            "subcategory":"School",
            "type":"Public Place"
        }
    ],
    "sg:phone":"+1 651 698 2451",
    "sg:postcode":"55105",
    "sg:province":"MN",
    "sg:tags":[
        "high",
        "middle",
        "elementary"
    ],
    "wof:name":"St Paul Academy and Summit School",
    "wof:placetype":"venue"
},
  "geometry": {"coordinates":[-93.172096,44.926998],"type":"Point"}
}