{
  "type": "Feature",
  "properties": {
    "iso:country":"US",
    "sg:address":"11820 Lockridge Ave S",
    "sg:city":"Hastings",
    "sg:classifiers":[
        {
            "category":"Manufacturing",
            "subcategory":"Tools & Machinery",
            "type":"Manufacturing & Wholesale Goods"
        }
    ],
    "sg:phone":"+1 651 480 3309",
    "sg:postcode":"55033",
    "sg:province":"MN",
    "sg:tags":[
        "equipment",
        "mfg"
    ],
    "wof:name":"Wissota Supply Co",
    "wof:placetype":"venue"
},
  "geometry": {"coordinates":[-92.875258,44.776428],"type":"Point"}
}