{
  "type": "Feature",
  "properties": {
    "iso:country":"US",
    "sg:address":"7308 Aspen Ln N",
    "sg:city":"Minneapolis",
    "sg:classifiers":[
        {
            "category":"Insurance",
            "subcategory":"Insurance Agent",
            "type":"Services"
        }
    ],
    "sg:phone":"+1 763 391 7760",
    "sg:postcode":"55428",
    "sg:province":"MN",
    "wof:name":"Primerica",
    "wof:placetype":"venue"
},
  "geometry": {"coordinates":[-93.388784,45.090684],"type":"Point"}
}