{
  "type": "Feature",
  "properties": {
    "addr:full":"214 Main St N Winthrop MN 55396",
    "addr:housenumber":"214",
    "addr:postcode":"55396",
    "addr:street":"Main St N",
    "iso:country":"US",
    "sg:address":"214 Main St N",
    "sg:city":"Winthrop",
    "sg:classifiers":[
        {
            "category":"Retail",
            "subcategory":"Laundry & Dry Cleaning",
            "type":"Services"
        }
    ],
    "sg:phone":"+1 507 647 5431",
    "sg:postcode":"55396",
    "sg:province":"MN",
    "wof:name":"Winthrop Laundromat",
    "wof:placetype":"venue"
},
  "geometry": {"coordinates":[-94.364484,44.541934],"type":"Point"}
}