{
  "type": "Feature",
  "properties": {
    "iso:country":"US",
    "sg:address":"1180 Cushing Cir",
    "sg:city":"Saint Paul",
    "sg:classifiers":[
        {
            "category":"Real Estate",
            "subcategory":"Real Estate Operator",
            "type":"Services"
        }
    ],
    "sg:phone":"+1 651 644 1089",
    "sg:postcode":"55108",
    "sg:province":"MN",
    "sg:tags":[
        "building",
        "apartment"
    ],
    "wof:name":"Burlington Apts",
    "wof:placetype":"venue"
},
  "geometry": {"coordinates":[-93.15119199999999,44.970946],"type":"Point"}
}