{
  "type": "Feature",
  "properties": {
    "iso:country":"US",
    "sg:address":"8047 Somerset Rd",
    "sg:city":"Saint Paul",
    "sg:classifiers":[
        {
            "category":"Professional",
            "subcategory":"Business Services",
            "type":"Services"
        }
    ],
    "sg:phone":"+1 651 731 8750",
    "sg:postcode":"55125",
    "sg:province":"MN",
    "wof:name":"Quality Hm Insptn & Consulting",
    "wof:placetype":"venue"
},
  "geometry": {"coordinates":[-92.942813,44.930811],"type":"Point"}
}