{
  "type": "Feature",
  "properties": {
    "addr:full":"28 S Highway 9 Morris MN 56267",
    "addr:housenumber":"28",
    "addr:postcode":"56267",
    "addr:street":"S Highway 9",
    "iso:country":"US",
    "sg:address":"28 S Highway 9",
    "sg:city":"Morris",
    "sg:classifiers":[
        {
            "category":"Restaurant",
            "type":"Food & Drink"
        }
    ],
    "sg:menulink":"http://www.allmenus.com/mn/morris/80140-pizza-hut/menu/",
    "sg:phone":"+1 320 589 4084",
    "sg:postcode":"56267",
    "sg:province":"MN",
    "sg:tags":[
        "american",
        "pizza"
    ],
    "wof:name":"Pizza Hut",
    "wof:placetype":"venue"
},
  "geometry": {"coordinates":[-95.910689,45.582844],"type":"Point"}
}