{
  "type": "Feature",
  "properties": {
    "addr:full":"2711 Broadway St NE Minneapolis MN 55413",
    "addr:housenumber":"2711",
    "addr:postcode":"55413",
    "addr:street":"Broadway St Ne",
    "iso:country":"US",
    "sg:address":"2711 Broadway St NE",
    "sg:city":"Minneapolis",
    "sg:classifiers":[
        {
            "category":"Autos & Motor Vehicles",
            "subcategory":"Automobile Sales",
            "type":"Retail Goods"
        },
        {
            "category":"Manufacturing",
            "subcategory":"Tools & Machinery",
            "type":"Manufacturing & Wholesale Goods"
        },
        {
            "category":"Transit Center",
            "subcategory":"Freight",
            "type":"Transportation"
        }
    ],
    "sg:phone":"+1 612 331 8524",
    "sg:postcode":"55413",
    "sg:province":"MN",
    "sg:tags":[
        "handling",
        "equipment-wholesale",
        "material",
        "trucks-industrial",
        "truck",
        "forklift",
        "manufacturer"
    ],
    "wof:name":"Midwest Forklift Inc",
    "wof:placetype":"venue"
},
  "geometry": {"coordinates":[-93.222782,44.998745],"type":"Point"}
}