{
  "type": "Feature",
  "properties": {
    "iso:country":"US",
    "sg:address":"11887 Jenkins St NE",
    "sg:city":"Minneapolis",
    "sg:classifiers":[
        {
            "category":"Professional",
            "subcategory":"Detective & Security Services",
            "type":"Services"
        }
    ],
    "sg:phone":"+1 763 767 0311",
    "sg:postcode":"55449",
    "sg:province":"MN",
    "sg:tags":[
        "information",
        "bureau"
    ],
    "wof:name":"Law Enforcement Training Services",
    "wof:placetype":"venue"
},
  "geometry": {"coordinates":[-93.22215300000001,45.186061],"type":"Point"}
}