{
  "type": "Feature",
  "properties": {
    "addr:full":"3810 W Broadway Ave Minneapolis MN 55422",
    "addr:housenumber":"3810",
    "addr:postcode":"55422",
    "addr:street":"W Broadway Ave",
    "iso:country":"US",
    "sg:address":"3810 W Broadway Ave",
    "sg:city":"Minneapolis",
    "sg:classifiers":[
        {
            "category":"Retail",
            "subcategory":"Car Wash",
            "type":"Services"
        }
    ],
    "sg:phone":"+1 763 521 4229",
    "sg:postcode":"55422",
    "sg:province":"MN",
    "sg:tags":[
        "automobile",
        "detail",
        "clean"
    ],
    "wof:name":"Gerald's Detailing",
    "wof:placetype":"venue"
},
  "geometry": {"coordinates":[-93.33132999999999,45.02446],"type":"Point"}
}