{
  "type": "Feature",
  "properties": {
    "iso:country":"US",
    "sg:address":"612 N Mill St",
    "sg:city":"Fertile",
    "sg:classifiers":[
        {
            "category":"Retail",
            "subcategory":"Auto Repair",
            "type":"Services"
        }
    ],
    "sg:phone":"+1 218 945 6536",
    "sg:postcode":"56540",
    "sg:province":"MN",
    "sg:tags":[
        "body",
        "automobile",
        "buses-distributors",
        "painting",
        "manufacturer"
    ],
    "wof:name":"Hall's Auto Body",
    "wof:placetype":"venue"
},
  "geometry": {"coordinates":[-96.28034100000001,47.54136],"type":"Point"}
}