{
  "type": "Feature",
  "properties": {
    "addr:full":"619 Beltrami Ave NW Bemidji MN 56601",
    "addr:housenumber":"619",
    "addr:postcode":"56601",
    "addr:street":"Beltrami Ave Nw",
    "iso:country":"US",
    "sg:address":"619 Beltrami Ave NW",
    "sg:city":"Bemidji",
    "sg:classifiers":[
        {
            "category":"Government",
            "subcategory":"Office",
            "type":"Public Place"
        }
    ],
    "sg:phone":"+1 218 333 4174",
    "sg:postcode":"56601",
    "sg:province":"MN",
    "sg:tags":[
        "county",
        "taxation"
    ],
    "sg:website":"www.co.beltrami.mn.us",
    "wof:name":"Beltrami County Treasurer",
    "wof:placetype":"venue"
},
  "geometry": {"coordinates":[-94.881288,47.474508],"type":"Point"}
}