{
  "type": "Feature",
  "properties": {
    "iso:country":"US",
    "sg:address":"5140 W 102nd St",
    "sg:city":"Minneapolis",
    "sg:classifiers":[
        {
            "category":"Professional",
            "type":"Services"
        }
    ],
    "sg:phone":"+1 952 835 5857",
    "sg:postcode":"55437",
    "sg:province":"MN",
    "wof:name":"Healthy Life of Minneapolis",
    "wof:placetype":"venue"
},
  "geometry": {"coordinates":[-93.347566,44.819217],"type":"Point"}
}