{
  "type": "Feature",
  "properties": {
    "iso:country":"US",
    "sg:address":"2306 5th St SW",
    "sg:city":"Rochester",
    "sg:classifiers":[
        {
            "category":"Building & Trades",
            "subcategory":"Construction",
            "type":"Services"
        }
    ],
    "sg:phone":"+1 507 288 8711",
    "sg:postcode":"55902",
    "sg:province":"MN",
    "sg:tags":[
        "handyman"
    ],
    "wof:name":"W C H Repair",
    "wof:placetype":"venue"
},
  "geometry": {"coordinates":[-92.498938,44.017991],"type":"Point"}
}