{
  "type": "Feature",
  "properties": {
    "addr:full":"401 4th Ave SW New Prague MN 56071",
    "addr:housenumber":"401",
    "addr:postcode":"56071",
    "addr:street":"4Th Ave Sw",
    "iso:country":"US",
    "sg:address":"401 4th Ave SW",
    "sg:city":"New Prague",
    "sg:classifiers":[
        {
            "category":"Manufacturing",
            "subcategory":"Chemicals & Compounds",
            "type":"Manufacturing & Wholesale Goods"
        },
        {
            "category":"Manufacturing",
            "subcategory":"Tools & Machinery",
            "type":"Manufacturing & Wholesale Goods"
        }
    ],
    "sg:phone":"+1 952 758 9760",
    "sg:postcode":"56071",
    "sg:province":"MN",
    "sg:tags":[
        "physician",
        "substance",
        "mfg",
        "cyclic",
        "diagnostic",
        "surgeon"
    ],
    "wof:name":"Lide Laboratories Inc",
    "wof:placetype":"venue"
},
  "geometry": {"coordinates":[-93.584007,44.540387],"type":"Point"}
}