{
  "type": "Feature",
  "properties": {
    "iso:country":"US",
    "sg:address":"16518 420th Ave",
    "sg:city":"Waseca",
    "sg:classifiers":[
        {
            "category":"Farming",
            "subcategory":"Livestock Farm",
            "type":"Manufacturing & Wholesale Goods"
        }
    ],
    "sg:phone":"+1 507 685 2403",
    "sg:postcode":"56093",
    "sg:province":"MN",
    "sg:tags":[
        "beef",
        "feedlot",
        "cattle"
    ],
    "wof:name":"Clarence Weiski",
    "wof:placetype":"venue"
},
  "geometry": {"coordinates":[-93.436942,44.167046],"type":"Point"}
}