{
  "type": "Feature",
  "properties": {
    "iso:country":"US",
    "sg:address":"2834 170th St W",
    "sg:city":"Farmington",
    "sg:phone":"+1 651 423 5621",
    "sg:postcode":"55024",
    "sg:province":"MN",
    "sg:tags":[
        "farm",
        "soybean"
    ],
    "wof:name":"William Brett Berg",
    "wof:placetype":"venue"
},
  "geometry": {"coordinates":[-93.121011,44.702892],"type":"Point"}
}