{
  "type": "Feature",
  "properties": {
    "iso:country":"US",
    "sg:address":"7259 Divinity Ln",
    "sg:city":"Eden Prairie",
    "sg:classifiers":[
        {
            "category":"Farming",
            "subcategory":"Farm",
            "type":"Manufacturing & Wholesale Goods"
        }
    ],
    "sg:phone":"+1 952 934 4590",
    "sg:postcode":"55346",
    "sg:province":"MN",
    "sg:tags":[
        "crop",
        "general"
    ],
    "wof:name":"Godward Wild Rice Farms Inc",
    "wof:placetype":"venue"
},
  "geometry": {"coordinates":[-93.44844399999999,44.872327],"type":"Point"}
}