{
  "type": "Feature",
  "properties": {
    "iso:country":"US",
    "sg:address":"1314 E Franklin Ave",
    "sg:city":"Minneapolis",
    "sg:classifiers":[
        {
            "category":"Education",
            "subcategory":"Library",
            "type":"Public Place"
        }
    ],
    "sg:phone":"+1 612 630 6800",
    "sg:postcode":"55404",
    "sg:province":"MN",
    "sg:website":"www.mplib.org",
    "wof:name":"Minneapolis Public Library",
    "wof:placetype":"venue"
},
  "geometry": {"coordinates":[-93.254997,44.962601],"type":"Point"}
}