{
  "type": "Feature",
  "properties": {
    "addr:full":"17003 255th Ave Sleepy Eye MN 56085",
    "addr:housenumber":"17003",
    "addr:postcode":"56085",
    "addr:street":"255Th Ave",
    "iso:country":"US",
    "sg:address":"17003 255th Ave",
    "sg:city":"Sleepy Eye",
    "sg:phone":"+1 507 794 6930",
    "sg:postcode":"56085",
    "sg:province":"MN",
    "sg:tags":[
        "farm",
        "corn",
        "beef",
        "feedlot",
        "cattle"
    ],
    "wof:name":"Gary Hillesheim",
    "wof:placetype":"venue"
},
  "geometry": {"coordinates":[-94.69542300000001,44.224785],"type":"Point"}
}