{
  "type": "Feature",
  "properties": {
    "addr:full":"125 Forest Ave E Mora MN 55051",
    "addr:housenumber":"125",
    "addr:postcode":"55051",
    "addr:street":"Forest Ave E Mora",
    "iso:country":"US",
    "sg:address":"125 Forest Ave E",
    "sg:city":"Mora",
    "sg:classifiers":[
        {
            "category":"Insurance",
            "subcategory":"Insurance Agent",
            "type":"Services"
        }
    ],
    "sg:phone":"+1 320 679 3376",
    "sg:postcode":"55051",
    "sg:province":"MN",
    "wof:name":"Roman Miller Agency",
    "wof:placetype":"venue"
},
  "geometry": {"coordinates":[-93.295799,45.875493],"type":"Point"}
}