{
  "type": "Feature",
  "properties": {
    "addr:full":"1926 Chicago Ave S Minneapolis MN 55404",
    "addr:housenumber":"1926",
    "addr:postcode":"55404",
    "addr:street":"Chicago Ave S",
    "iso:country":"US",
    "sg:address":"1926 Chicago Ave S",
    "sg:city":"Minneapolis",
    "sg:classifiers":[
        {
            "category":"Banks & Credit Unions",
            "subcategory":"Bank",
            "type":"Services"
        }
    ],
    "sg:phone":"+1 612 871 8232",
    "sg:postcode":"55404",
    "sg:province":"MN",
    "sg:tags":[
        "cashing",
        "check"
    ],
    "wof:name":"Tawakal Money Express",
    "wof:placetype":"venue"
},
  "geometry": {"coordinates":[-93.262623,44.963035],"type":"Point"}
}