{
  "type": "Feature",
  "properties": {
    "iso:country":"US",
    "sg:address":"637 109th Ave NW",
    "sg:city":"Minneapolis",
    "sg:classifiers":[
        {
            "category":"Building & Trades",
            "subcategory":"Construction",
            "type":"Services"
        }
    ],
    "sg:phone":"+1 763 755 4382",
    "sg:postcode":"55448",
    "sg:province":"MN",
    "sg:tags":[
        "residential",
        "contractor"
    ],
    "wof:name":"Edward Rejman Home Improvement",
    "wof:placetype":"venue"
},
  "geometry": {"coordinates":[-93.285263,45.167926],"type":"Point"}
}