{
  "type": "Feature",
  "properties": {
    "iso:country":"US",
    "sg:address":"5737 Egan Dr",
    "sg:city":"Savage",
    "sg:classifiers":[
        {
            "category":"Restaurant",
            "type":"Food & Drink"
        }
    ],
    "sg:phone":"+1 952 440 1999",
    "sg:postcode":"55378",
    "sg:province":"MN",
    "wof:name":"Chanticlear Pizza",
    "wof:placetype":"venue"
},
  "geometry": {"coordinates":[-93.352548,44.746585],"type":"Point"}
}