{
  "type": "Feature",
  "properties": {
    "addr:full":"101 1st Ave SW Glenwood MN 56334",
    "addr:housenumber":"101",
    "addr:postcode":"56334",
    "addr:street":"1St Ave Sw",
    "iso:country":"US",
    "sg:address":"101 1st Ave SW",
    "sg:city":"Glenwood",
    "sg:classifiers":[
        {
            "category":"Health Services",
            "subcategory":"Doctor",
            "type":"Services"
        }
    ],
    "sg:phone":"+1 320 634 4543",
    "sg:postcode":"56334",
    "sg:province":"MN",
    "sg:tags":[
        "dentist"
    ],
    "wof:name":"G E Maher LTD",
    "wof:placetype":"venue"
},
  "geometry": {"coordinates":[-95.390241,45.64925],"type":"Point"}
}