{
  "type": "Feature",
  "properties": {
    "iso:country":"US",
    "sg:address":"5709 Clinton Ave",
    "sg:city":"Minneapolis",
    "sg:classifiers":[
        {
            "category":"Building & Trades",
            "subcategory":"Construction",
            "type":"Services"
        }
    ],
    "sg:phone":"+1 612 869 5194",
    "sg:postcode":"55419",
    "sg:province":"MN",
    "sg:tags":[
        "industrial",
        "altering",
        "contractor",
        "contractors-commercial",
        "remodeling"
    ],
    "wof:name":"S A Knutson Development Co",
    "wof:placetype":"venue"
},
  "geometry": {"coordinates":[-93.272487,44.899165],"type":"Point"}
}