{
  "type": "Feature",
  "properties": {
    "addr:full":"7 Colwyn Way Lake Crystal MN 56055",
    "addr:housenumber":"7",
    "addr:postcode":"56055",
    "addr:street":"Colwyn Way",
    "iso:country":"US",
    "sg:address":"7 Colwyn Way",
    "sg:city":"Lake Crystal",
    "sg:classifiers":[
        {
            "category":"Shopping",
            "subcategory":"Catalog Store",
            "type":"Retail Goods"
        }
    ],
    "sg:phone":"+1 507 726 6833",
    "sg:postcode":"56055",
    "sg:province":"MN",
    "sg:tags":[
        "mail",
        "order"
    ],
    "wof:name":"Choice Incentives",
    "wof:placetype":"venue"
},
  "geometry": {"coordinates":[-94.22302500000001,44.09781],"type":"Point"}
}