{
  "type": "Feature",
  "properties": {
    "addr:full":"140 Snelling Ave St Paul MN 55104",
    "addr:housenumber":"140",
    "addr:postcode":"55104",
    "addr:street":"Snelling Ave",
    "iso:country":"US",
    "sg:address":"140 Snelling Ave",
    "sg:city":"St Paul",
    "sg:classifiers":[
        {
            "category":"Food & Beverages",
            "subcategory":"Liquor & Beverages",
            "type":"Retail Goods"
        }
    ],
    "sg:phone":"+1 651 645 5555",
    "sg:postcode":"55104",
    "sg:province":"MN",
    "wof:name":"Park Liquor Store",
    "wof:placetype":"venue"
},
  "geometry": {"coordinates":[-93.16692500000001,44.945147],"type":"Point"}
}