{
  "type": "Feature",
  "properties": {
    "addr:full":"48845 860th St Lakefield MN 56150",
    "addr:housenumber":"48845",
    "addr:postcode":"56150",
    "addr:street":"860Th St",
    "iso:country":"US",
    "sg:address":"48845 860th St",
    "sg:city":"Lakefield",
    "sg:classifiers":[
        {
            "category":"Building & Trades",
            "subcategory":"Construction",
            "type":"Services"
        }
    ],
    "sg:phone":"+1 507 662 6448",
    "sg:postcode":"56150",
    "sg:province":"MN",
    "sg:tags":[
        "welder"
    ],
    "wof:name":"Thoreson Repair",
    "wof:placetype":"venue"
},
  "geometry": {"coordinates":[-95.100128,43.732081],"type":"Point"}
}