{
  "type": "Feature",
  "properties": {
    "addr:full":"261 Chester St Saint Paul MN 55107",
    "addr:housenumber":"261",
    "addr:postcode":"55107",
    "addr:street":"Chester St",
    "iso:country":"US",
    "sg:address":"261 Chester St",
    "sg:city":"Saint Paul",
    "sg:classifiers":[
        {
            "category":"Airline",
            "type":"Transportation"
        }
    ],
    "sg:phone":"+1 800 463 3339",
    "sg:postcode":"55107",
    "sg:province":"MN",
    "sg:tags":[
        "courier",
        "air"
    ],
    "wof:name":"Fedex",
    "wof:placetype":"venue"
},
  "geometry": {"coordinates":[-93.072102,44.939258],"type":"Point"}
}