{
  "type": "Feature",
  "properties": {
    "iso:country":"US",
    "sg:address":"2580 Meehan Dr",
    "sg:city":"Saint Paul",
    "sg:classifiers":[
        {
            "category":"Building & Trades",
            "subcategory":"Construction",
            "type":"Services"
        }
    ],
    "sg:phone":"+1 651 653 6604",
    "sg:postcode":"55110",
    "sg:province":"MN",
    "sg:tags":[
        "water",
        "well",
        "drilling"
    ],
    "wof:name":"Black Rock Well Drilling",
    "wof:placetype":"venue"
},
  "geometry": {"coordinates":[-92.997029,45.109167],"type":"Point"}
}