{
  "type": "Feature",
  "properties": {
    "iso:country":"US",
    "sg:address":"1304 Jefferson St S",
    "sg:city":"Wadena",
    "sg:classifiers":[
        {
            "category":"Autos & Motor Vehicles",
            "subcategory":"Automobile Sales",
            "type":"Retail Goods"
        }
    ],
    "sg:phone":"+1 218 631 3966",
    "sg:postcode":"56482",
    "sg:province":"MN",
    "sg:tags":[
        "car",
        "dealer"
    ],
    "wof:name":"Four Boys Motor Sports",
    "wof:placetype":"venue"
},
  "geometry": {"coordinates":[-95.14164100000001,46.430493],"type":"Point"}
}