{
  "type": "Feature",
  "properties": {
    "iso:country":"US",
    "sg:address":"11 1st St NW",
    "sg:city":"Fairfax",
    "sg:classifiers":[
        {
            "category":"Retail",
            "subcategory":"Veterinary Services",
            "type":"Services"
        }
    ],
    "sg:phone":"+1 507 426 7258",
    "sg:postcode":"55332",
    "sg:province":"MN",
    "sg:tags":[
        "veterinarian"
    ],
    "wof:name":"Fairfax Veterinary Clinic",
    "wof:placetype":"venue"
},
  "geometry": {"coordinates":[-94.722202,44.530515],"type":"Point"}
}