{
  "type": "Feature",
  "properties": {
    "iso:country":"US",
    "sg:address":"14981 Hwy 115",
    "sg:city":"Little Falls",
    "sg:classifiers":[
        {
            "category":"Wholesale",
            "subcategory":"Vending Machines",
            "type":"Manufacturing & Wholesale Goods"
        }
    ],
    "sg:phone":"+1 320 632 6996",
    "sg:postcode":"56345",
    "sg:province":"MN",
    "wof:name":"Canteen Corp",
    "wof:placetype":"venue"
},
  "geometry": {"coordinates":[-94.356616,46.075343],"type":"Point"}
}