{
  "type": "Feature",
  "properties": {
    "addr:full":"306 10th St S Breckenridge MN 56520",
    "addr:housenumber":"306",
    "addr:postcode":"56520",
    "addr:street":"10Th St S",
    "iso:country":"US",
    "sg:address":"306 10th St S",
    "sg:city":"Breckenridge",
    "sg:classifiers":[
        {
            "category":"Social Services",
            "subcategory":"Child Care",
            "type":"Services"
        }
    ],
    "sg:phone":"+1 218 643 2919",
    "sg:postcode":"56520",
    "sg:province":"MN",
    "sg:tags":[
        "daycare",
        "provider"
    ],
    "wof:name":"Pattys Playhouse",
    "wof:placetype":"venue"
},
  "geometry": {"coordinates":[-96.580685,46.260966],"type":"Point"}
}