{
  "type": "Feature",
  "properties": {
    "iso:country":"US",
    "sg:address":"18310 Erkium St NW",
    "sg:city":"Anoka",
    "sg:classifiers":[
        {
            "category":"Professional",
            "subcategory":"Advertising",
            "type":"Services"
        }
    ],
    "sg:phone":"+1 763 509 0036",
    "sg:postcode":"55303",
    "sg:province":"MN",
    "wof:name":"Mooers & Assoc LTD",
    "wof:placetype":"venue"
},
  "geometry": {"coordinates":[-93.405322,45.302233],"type":"Point"}
}