{
  "type": "Feature",
  "properties": {
    "addr:full":"29895 Sportsman Dr Chisago City MN 55013",
    "addr:postcode":"29895;55013",
    "addr:street":"Sportsman Dr",
    "iso:country":"US",
    "sg:address":"29895 Sportsman Dr",
    "sg:city":"Chisago City",
    "sg:classifiers":[
        {
            "category":"Health Services",
            "subcategory":"Nursing And Care Facility",
            "type":"Services"
        }
    ],
    "sg:phone":"+1 651 257 4394",
    "sg:postcode":"55013",
    "sg:province":"MN",
    "sg:tags":[
        "home",
        "retirement",
        "community"
    ],
    "wof:name":"Homestead Cooperative",
    "wof:placetype":"venue"
},
  "geometry": {"coordinates":[-92.884156,45.379549],"type":"Point"}
}