{
  "type": "Feature",
  "properties": {
    "iso:country":"US",
    "sg:address":"11563 57th St NE",
    "sg:city":"Albertville",
    "sg:classifiers":[
        {
            "category":"Retail",
            "subcategory":"Car Wash",
            "type":"Services"
        }
    ],
    "sg:phone":"+1 763 497 4990",
    "sg:postcode":"55301",
    "sg:province":"MN",
    "sg:tags":[
        "carwash"
    ],
    "wof:name":"Eulls Auto Brite",
    "wof:placetype":"venue"
},
  "geometry": {"coordinates":[-93.65366,45.234598],"type":"Point"}
}