{
  "type": "Feature",
  "properties": {
    "iso:country":"US",
    "sg:address":"18020 Echo Dr",
    "sg:city":"Farmington",
    "sg:classifiers":[
        {
            "category":"Building & Trades",
            "subcategory":"Plumbing",
            "type":"Services"
        }
    ],
    "sg:phone":"+1 651 263 2057",
    "sg:postcode":"55024",
    "sg:province":"MN",
    "sg:tags":[
        "plumber",
        "industrial",
        "contractors-commercial"
    ],
    "wof:name":"Paul's Plumbing",
    "wof:placetype":"venue"
},
  "geometry": {"coordinates":[-93.168576,44.688251],"type":"Point"}
}