{
  "type": "Feature",
  "properties": {
    "addr:full":"115 W Lincoln Ave Fergus Falls MN 56537",
    "addr:housenumber":"115",
    "addr:postcode":"56537",
    "addr:street":"W Lincoln Ave",
    "iso:country":"US",
    "sg:address":"115 W Lincoln Ave",
    "sg:city":"Fergus Falls",
    "sg:classifiers":[
        {
            "category":"Organizations",
            "subcategory":"Non-profit Organization",
            "type":"Services"
        }
    ],
    "sg:phone":"+1 218 736 6842",
    "sg:postcode":"56537",
    "sg:province":"MN",
    "wof:name":"FERGUS Falls Snr Ctzn Program",
    "wof:placetype":"venue"
},
  "geometry": {"coordinates":[-96.074378,46.283424],"type":"Point"}
}