{
  "type": "Feature",
  "properties": {
    "iso:country":"US",
    "sg:address":"735 Melody Ln",
    "sg:city":"Fergus Falls",
    "sg:classifiers":[
        {
            "category":"Arts & Performance",
            "subcategory":"Theater",
            "type":"Entertainment"
        }
    ],
    "sg:phone":"+1 218 739 9314",
    "sg:postcode":"56537",
    "sg:province":"MN",
    "sg:tags":[
        "live",
        "music"
    ],
    "wof:name":"Steve's Audio Plus",
    "wof:placetype":"venue"
},
  "geometry": {"coordinates":[-96.094099,46.276387],"type":"Point"}
}