{
  "type": "Feature",
  "properties": {
    "iso:country":"US",
    "sg:address":"1016 Summit Ave",
    "sg:city":"Detroit Lakes",
    "sg:classifiers":[
        {
            "category":"Real Estate",
            "subcategory":"Architect",
            "type":"Services"
        }
    ],
    "sg:phone":"+1 218 847 1851",
    "sg:postcode":"56501",
    "sg:province":"MN",
    "wof:name":"Duffney Architecture",
    "wof:placetype":"venue"
},
  "geometry": {"coordinates":[-95.849827,46.815654],"type":"Point"}
}