{
  "type": "Feature",
  "properties": {
    "addr:full":"5120 Trenton Ln N Minneapolis MN 55442",
    "addr:housenumber":"5120",
    "addr:postcode":"55442",
    "addr:street":"Trenton Ln N",
    "iso:country":"US",
    "sg:address":"5120 Trenton Ln N",
    "sg:city":"Minneapolis",
    "sg:classifiers":[
        {
            "category":"Manufacturing",
            "subcategory":"Metals",
            "type":"Manufacturing & Wholesale Goods"
        },
        {
            "category":"Manufacturing",
            "subcategory":"Building Materials",
            "type":"Manufacturing & Wholesale Goods"
        }
    ],
    "sg:phone":"+1 763 559 3647",
    "sg:postcode":"55442",
    "sg:province":"MN",
    "sg:tags":[
        "fabricator",
        "work",
        "sheet"
    ],
    "wof:name":"Erector Metals Inc",
    "wof:placetype":"venue"
},
  "geometry": {"coordinates":[-93.412949,45.046631],"type":"Point"}
}