{
  "type": "Feature",
  "properties": {
    "iso:country":"US",
    "sg:address":"4769 State Highway 114 SW",
    "sg:city":"Alexandria",
    "sg:classifiers":[
        {
            "category":"Travel",
            "subcategory":"Hotels & Motels",
            "type":"Entertainment"
        }
    ],
    "sg:phone":"+1 320 886 9439",
    "sg:postcode":"56308",
    "sg:province":"MN",
    "wof:name":"State Line Motel",
    "wof:placetype":"venue"
},
  "geometry": {"coordinates":[-95.490348,45.843299],"type":"Point"}
}