{
  "type": "Feature",
  "properties": {
    "iso:country":"US",
    "sg:address":"33692 6th St NE",
    "sg:city":"Cambridge",
    "sg:classifiers":[
        {
            "category":"Insurance",
            "subcategory":"Insurance Agent",
            "type":"Services"
        }
    ],
    "sg:phone":"+1 763 689 6867",
    "sg:postcode":"55008",
    "sg:province":"MN",
    "wof:name":"C&M Capital Enterprise",
    "wof:placetype":"venue"
},
  "geometry": {"coordinates":[-93.259551,45.580256],"type":"Point"}
}