{
  "type": "Feature",
  "properties": {
    "iso:country":"US",
    "sg:address":"201 Elm Ave N",
    "sg:city":"Thief River Falls",
    "sg:classifiers":[
        {
            "category":"Shopping",
            "subcategory":"Computers & Home Electronics",
            "type":"Retail Goods"
        }
    ],
    "sg:phone":"+1 218 681 1776",
    "sg:postcode":"56701",
    "sg:province":"MN",
    "wof:name":"Extreme Computer Systems",
    "wof:placetype":"venue"
},
  "geometry": {"coordinates":[-96.15713,48.11777],"type":"Point"}
}