{
  "type": "Feature",
  "properties": {
    "addr:full":"111 4th St SE Kasson MN 55944",
    "addr:housenumber":"111",
    "addr:postcode":"55944",
    "addr:street":"4Th St Se",
    "iso:country":"US",
    "sg:address":"111 4th St SE",
    "sg:city":"Kasson",
    "sg:classifiers":[
        {
            "category":"Autos & Motor Vehicles",
            "subcategory":"Auto Supplies",
            "type":"Retail Goods"
        }
    ],
    "sg:phone":"+1 507 477 3636",
    "sg:postcode":"55944",
    "sg:province":"MN",
    "sg:tags":[
        "automobile",
        "part",
        "used",
        "mfg"
    ],
    "wof:name":"Kasson Parts Depot",
    "wof:placetype":"venue"
},
  "geometry": {"coordinates":[-92.747277,44.025835],"type":"Point"}
}