{
  "type": "Feature",
  "properties": {
    "iso:country":"US",
    "sg:address":"319 Vine Ave",
    "sg:city":"Albert Lea",
    "sg:classifiers":[
        {
            "category":"Social Services",
            "type":"Services"
        }
    ],
    "sg:phone":"+1 507 373 8757",
    "sg:postcode":"56007",
    "sg:province":"MN",
    "wof:name":"Imprints International",
    "wof:placetype":"venue"
},
  "geometry": {"coordinates":[-93.37879100000001,43.651404],"type":"Point"}
}