{
  "type": "Feature",
  "properties": {
    "iso:country":"US",
    "sg:address":"211 Sherman St",
    "sg:city":"Jackson",
    "sg:classifiers":[
        {
            "category":"Home & Garden",
            "subcategory":"Hardware",
            "type":"Retail Goods"
        }
    ],
    "sg:phone":"+1 507 847 2180",
    "sg:postcode":"56143",
    "sg:province":"MN",
    "sg:tags":[
        "farm",
        "equipment",
        "parts"
    ],
    "wof:name":"True Value Hardware",
    "wof:placetype":"venue"
},
  "geometry": {"coordinates":[-94.988541,43.621517],"type":"Point"}
}