{
  "type": "Feature",
  "properties": {
    "addr:full":"1120 Bryant St Alexandria MN 56308",
    "addr:housenumber":"1120",
    "addr:postcode":"56308",
    "addr:street":"Bryant St",
    "iso:country":"US",
    "sg:address":"1120 Bryant St",
    "sg:city":"Alexandria",
    "sg:classifiers":[
        {
            "category":"Farming",
            "subcategory":"Livestock Farm",
            "type":"Manufacturing & Wholesale Goods"
        }
    ],
    "sg:phone":"+1 320 763 7834",
    "sg:postcode":"56308",
    "sg:province":"MN",
    "wof:name":"Soderholm Livestock",
    "wof:placetype":"venue"
},
  "geometry": {"coordinates":[-95.385262,45.879911],"type":"Point"}
}