{
  "type": "Feature",
  "properties": {
    "addr:full":"528 Dale St SW Hutchinson MN 55350",
    "addr:housenumber":"528",
    "addr:postcode":"55350",
    "addr:street":"Dale St Sw",
    "iso:country":"US",
    "sg:address":"528 Dale St SW",
    "sg:city":"Hutchinson",
    "sg:classifiers":[
        {
            "category":"Manufacturing",
            "subcategory":"Furniture",
            "type":"Manufacturing & Wholesale Goods"
        }
    ],
    "sg:phone":"+1 320 587 2112",
    "sg:postcode":"55350",
    "sg:province":"MN",
    "sg:tags":[
        "product",
        "wood",
        "fixture",
        "store",
        "mfg"
    ],
    "sg:website":"http://www.gf.com",
    "wof:name":"Goebel Fixture Co.",
    "wof:placetype":"venue"
},
  "geometry": {"coordinates":[-94.382503,44.886225],"type":"Point"}
}