{
  "type": "Feature",
  "properties": {
    "iso:country":"US",
    "sg:address":"1656 41st St",
    "sg:city":"Edgerton",
    "sg:classifiers":[
        {
            "category":"Farming",
            "subcategory":"Livestock Farm",
            "type":"Manufacturing & Wholesale Goods"
        }
    ],
    "sg:phone":"+1 507 442 7233",
    "sg:postcode":"56128",
    "sg:province":"MN",
    "sg:tags":[
        "hog",
        "or",
        "feedlot"
    ],
    "wof:name":"Darwin Schelhaas",
    "wof:placetype":"venue"
},
  "geometry": {"coordinates":[-96.13372,43.906587],"type":"Point"}
}