{
  "type": "Feature",
  "properties": {
    "iso:country":"US",
    "sg:address":"201 S 3rd St",
    "sg:city":"St Peter",
    "sg:classifiers":[
        {
            "category":"Retail",
            "subcategory":"Veterinary Services",
            "type":"Services"
        },
        {
            "category":"Shopping",
            "subcategory":"Pharmacy",
            "type":"Retail Goods"
        }
    ],
    "sg:phone":"+1 507 931 8707",
    "sg:postcode":"56082",
    "sg:province":"MN",
    "sg:tags":[
        "veterinarian"
    ],
    "wof:name":"Vet Rx",
    "wof:placetype":"venue"
},
  "geometry": {"coordinates":[-93.95786,44.325579],"type":"Point"}
}