{
  "type": "Feature",
  "properties": {
    "addr:full":"225 W Broadway Hallock MN 56728",
    "addr:housenumber":"225",
    "addr:postcode":"56728",
    "addr:street":"W Broadway",
    "iso:country":"US",
    "sg:address":"225 W Broadway",
    "sg:city":"Hallock",
    "sg:classifiers":[
        {
            "category":"Restaurant",
            "type":"Food & Drink"
        }
    ],
    "sg:phone":"+1 218 843 3740",
    "sg:postcode":"56728",
    "sg:province":"MN",
    "sg:tags":[
        "grill",
        "bar"
    ],
    "wof:name":"Caribou Grill",
    "wof:placetype":"venue"
},
  "geometry": {"coordinates":[-96.95037000000001,48.77541],"type":"Point"}
}