{
  "type": "Feature",
  "properties": {
    "addr:full":"855 River Ave S Sauk Rapids MN 56379",
    "addr:housenumber":"855",
    "addr:postcode":"56379",
    "addr:street":"River Ave S Sauk",
    "iso:country":"US",
    "sg:address":"855 River Ave S",
    "sg:city":"Sauk Rapids",
    "sg:classifiers":[
        {
            "category":"Real Estate",
            "subcategory":"Real Estate Operator",
            "type":"Services"
        }
    ],
    "sg:phone":"+1 320 253 2155",
    "sg:postcode":"56379",
    "sg:province":"MN",
    "sg:tags":[
        "building",
        "apartment"
    ],
    "wof:name":"Larson Properties",
    "wof:placetype":"venue"
},
  "geometry": {"coordinates":[-94.163567,45.581287],"type":"Point"}
}