{
  "type": "Feature",
  "properties": {
    "addr:full":"18986 Pueblo Ave Jordan MN 55352",
    "addr:housenumber":"18986",
    "addr:postcode":"55352",
    "addr:street":"Pueblo Ave",
    "iso:country":"US",
    "sg:address":"18986 Pueblo Ave",
    "sg:city":"Jordan",
    "sg:classifiers":[
        {
            "category":"Building & Trades",
            "subcategory":"Construction",
            "type":"Services"
        }
    ],
    "sg:phone":"+1 952 492 6543",
    "sg:postcode":"55352",
    "sg:province":"MN",
    "sg:tags":[
        "contractor"
    ],
    "wof:name":"Ahlbrecht Masonry Inc",
    "wof:placetype":"venue"
},
  "geometry": {"coordinates":[-93.572255,44.674975],"type":"Point"}
}