{
  "type": "Feature",
  "properties": {
    "iso:country":"US",
    "sg:address":"3530 Lexington Ave N",
    "sg:city":"Saint Paul",
    "sg:classifiers":[
        {
            "category":"Health Services",
            "subcategory":"Nursing And Care Facility",
            "type":"Services"
        }
    ],
    "sg:phone":"+1 651 766 4300",
    "sg:postcode":"55126",
    "sg:province":"MN",
    "sg:tags":[
        "skilled"
    ],
    "wof:name":"Ecumen Home Care  Inc",
    "wof:placetype":"venue"
},
  "geometry": {"coordinates":[-93.146984,45.048767],"type":"Point"}
}