{
  "type": "Feature",
  "properties": {
    "iso:country":"US",
    "sg:address":"206 Lake St",
    "sg:city":"Alexandria",
    "sg:classifiers":[
        {
            "category":"Manufacturing",
            "subcategory":"Tools & Machinery",
            "type":"Manufacturing & Wholesale Goods"
        }
    ],
    "sg:phone":"+1 320 763 9660",
    "sg:postcode":"56308",
    "sg:province":"MN",
    "sg:tags":[
        "automotive",
        "electrical",
        "equipment"
    ],
    "wof:name":"Rocket Auto Electric",
    "wof:placetype":"venue"
},
  "geometry": {"coordinates":[-95.370103,45.890431],"type":"Point"}
}