{
  "type": "Feature",
  "properties": {
    "addr:full":"1600 W Lake St Minneapolis MN 55408",
    "addr:housenumber":"1600",
    "addr:postcode":"55408",
    "addr:street":"W Lake St",
    "iso:country":"US",
    "sg:address":"1600 W Lake St",
    "sg:city":"Minneapolis",
    "sg:classifiers":[
        {
            "category":"Restaurant",
            "type":"Food & Drink"
        }
    ],
    "sg:phone":"+1 612 827 5710",
    "sg:postcode":"55408",
    "sg:province":"MN",
    "sg:tags":[
        "new",
        "american",
        "french"
    ],
    "sg:website":"www.barbette.com",
    "wof:name":"Barbette",
    "wof:placetype":"venue"
},
  "geometry": {"coordinates":[-93.302111,44.948373],"type":"Point"}
}