{
  "type": "Feature",
  "properties": {
    "addr:full":"419 Water St E Cannon Falls MN 55009",
    "addr:housenumber":"419",
    "addr:postcode":"55009",
    "addr:street":"Water St E",
    "iso:country":"US",
    "sg:address":"419 Water St E",
    "sg:city":"Cannon Falls",
    "sg:classifiers":[
        {
            "category":"Home & Garden",
            "subcategory":"Furniture",
            "type":"Retail Goods"
        }
    ],
    "sg:phone":"+1 507 263 4722",
    "sg:postcode":"55009",
    "sg:province":"MN",
    "wof:name":"Tinkerwood",
    "wof:placetype":"venue"
},
  "geometry": {"coordinates":[-92.895804,44.512092],"type":"Point"}
}