{
  "type": "Feature",
  "properties": {
    "addr:full":"3400 Park Ave Minneapolis MN 55407",
    "addr:housenumber":"3400",
    "addr:postcode":"55407",
    "addr:street":"Park Ave",
    "iso:country":"US",
    "sg:address":"3400 Park Ave",
    "sg:city":"Minneapolis",
    "sg:classifiers":[
        {
            "category":"Place Of Worship",
            "subcategory":"Church",
            "type":"Public Place"
        },
        {
            "category":"Place Of Worship",
            "type":"Public Place"
        }
    ],
    "sg:phone":"+1 612 825 6863",
    "sg:postcode":"55407",
    "sg:province":"MN",
    "sg:tags":[
        "churches-methodist"
    ],
    "wof:name":"Park Avenue Methodist Church Inc",
    "wof:placetype":"venue"
},
  "geometry": {"coordinates":[-93.265137,44.94138],"type":"Point"}
}