{
  "type": "Feature",
  "properties": {
    "iso:country":"US",
    "sg:address":"102 Main St E",
    "sg:city":"Dalton",
    "sg:classifiers":[
        {
            "category":"Professional",
            "subcategory":"Business Services",
            "type":"Services"
        }
    ],
    "sg:phone":"+1 218 589 7107",
    "sg:postcode":"56324",
    "sg:province":"MN",
    "sg:tags":[
        "telemarketing"
    ],
    "wof:name":"Synergy Advantage Group",
    "wof:placetype":"venue"
},
  "geometry": {"coordinates":[-95.91471300000001,46.17373],"type":"Point"}
}