{
  "type": "Feature",
  "properties": {
    "addr:full":"6148 Olson Memorial Hwy Minneapolis MN 55422",
    "addr:housenumber":"6148",
    "addr:postcode":"55422",
    "addr:street":"Olson Memorial Hwy",
    "iso:country":"US",
    "sg:address":"6148 Olson Memorial Hwy",
    "sg:city":"Minneapolis",
    "sg:classifiers":[
        {
            "category":"Building & Trades",
            "subcategory":"Construction",
            "type":"Services"
        }
    ],
    "sg:phone":"+1 763 450 2208",
    "sg:postcode":"55422",
    "sg:province":"MN",
    "sg:tags":[
        "roofing",
        "consultant",
        "contractor"
    ],
    "wof:name":"New Line Roofing",
    "wof:placetype":"venue"
},
  "geometry": {"coordinates":[-93.360574,44.984205],"type":"Point"}
}