{
  "type": "Feature",
  "properties": {
    "iso:country":"US",
    "sg:address":"125 Main St E",
    "sg:city":"Cannon Falls",
    "sg:classifiers":[
        {
            "category":"Restaurant",
            "type":"Food & Drink"
        }
    ],
    "sg:phone":"+1 320 384 0388",
    "sg:postcode":"55009",
    "sg:province":"MN",
    "wof:name":"Classic Pizza",
    "wof:placetype":"venue"
},
  "geometry": {"coordinates":[-92.901077,44.506812],"type":"Point"}
}