{
  "type": "Feature",
  "properties": {
    "iso:country":"US",
    "sg:address":"202 W Broadway Ave",
    "sg:city":"Minneapolis",
    "sg:classifiers":[
        {
            "category":"Shopping",
            "subcategory":"Clothing, Apparel, & Fashions",
            "type":"Retail Goods"
        }
    ],
    "sg:phone":"+1 952 854 4980",
    "sg:postcode":"55411",
    "sg:province":"MN",
    "sg:tags":[
        "sporting",
        "shoes"
    ],
    "wof:name":"Champs Sports",
    "wof:placetype":"venue"
},
  "geometry": {"coordinates":[-93.281711,44.999201],"type":"Point"}
}