{
  "type": "Feature",
  "properties": {
    "addr:full":"204 Poplar Ave N Canby MN 56220",
    "addr:housenumber":"204",
    "addr:postcode":"56220",
    "addr:street":"Poplar Ave N",
    "iso:country":"US",
    "sg:address":"204 Poplar Ave N",
    "sg:city":"Canby",
    "sg:classifiers":[
        {
            "category":"Professional",
            "type":"Services"
        }
    ],
    "sg:phone":"+1 507 223 7937",
    "sg:postcode":"56220",
    "sg:province":"MN",
    "wof:name":"Minnesota State Wide Asso",
    "wof:placetype":"venue"
},
  "geometry": {"coordinates":[-96.279477,44.713387],"type":"Point"}
}