{
  "type": "Feature",
  "properties": {
    "addr:full":"5948 185th St Milaca MN 56353",
    "addr:housenumber":"5948",
    "addr:postcode":"56353",
    "addr:street":"185Th St",
    "iso:country":"US",
    "sg:address":"5948 185th St",
    "sg:city":"Milaca",
    "sg:classifiers":[
        {
            "category":"Social Services",
            "subcategory":"Child Care",
            "type":"Services"
        }
    ],
    "sg:phone":"+1 320 556 3390",
    "sg:postcode":"56353",
    "sg:province":"MN",
    "sg:tags":[
        "day",
        "provider"
    ],
    "wof:name":"Carole A Rowland",
    "wof:placetype":"venue"
},
  "geometry": {"coordinates":[-93.535963,45.814679],"type":"Point"}
}