{
  "type": "Feature",
  "properties": {
    "iso:country":"US",
    "sg:address":"1821 University Ave W",
    "sg:city":"Saint Paul",
    "sg:classifiers":[
        {
            "category":"Wholesale",
            "subcategory":"Electrical",
            "type":"Manufacturing & Wholesale Goods"
        }
    ],
    "sg:phone":"+1 651 774 6322",
    "sg:postcode":"55104",
    "sg:province":"MN",
    "sg:tags":[
        "component",
        "representative"
    ],
    "wof:name":"Countryman Associates Company",
    "wof:placetype":"venue"
},
  "geometry": {"coordinates":[-93.17591899999999,44.955664],"type":"Point"}
}