{
  "type": "Feature",
  "properties": {
    "addr:full":"971 6th Ave N Sauk Rapids MN 56379",
    "addr:housenumber":"971",
    "addr:postcode":"56379",
    "addr:street":"6Th Ave N Sauk",
    "iso:country":"US",
    "sg:address":"971 6th Ave N",
    "sg:city":"Sauk Rapids",
    "sg:classifiers":[
        {
            "category":"Manufacturing",
            "subcategory":"Printing",
            "type":"Manufacturing & Wholesale Goods"
        }
    ],
    "sg:phone":"+1 320 259 5359",
    "sg:postcode":"56379",
    "sg:province":"MN",
    "sg:tags":[
        "book"
    ],
    "wof:name":"Global Publishing Co",
    "wof:placetype":"venue"
},
  "geometry": {"coordinates":[-94.17026,45.599832],"type":"Point"}
}