{
  "type": "Feature",
  "properties": {
    "iso:country":"US",
    "sg:address":"11231 NE River Rd",
    "sg:city":"Rice",
    "sg:classifiers":[
        {
            "category":"Retail",
            "subcategory":"Veterinary Services",
            "type":"Services"
        }
    ],
    "sg:phone":"+1 320 393 2633",
    "sg:postcode":"56367",
    "sg:province":"MN",
    "wof:name":"Carlton Graves",
    "wof:placetype":"venue"
},
  "geometry": {"coordinates":[-94.21319200000001,45.728184],"type":"Point"}
}