{
  "type": "Feature",
  "properties": {
    "iso:country":"US",
    "sg:address":"418 Grant Ave",
    "sg:city":"Eveleth",
    "sg:classifiers":[
        {
            "category":"Personal",
            "subcategory":"Beauty Salon",
            "type":"Services"
        }
    ],
    "sg:phone":"+1 218 744 0111",
    "sg:postcode":"55734",
    "sg:province":"MN",
    "wof:name":"Hair Force One",
    "wof:placetype":"venue"
},
  "geometry": {"coordinates":[-92.539947,47.464104],"type":"Point"}
}