{
  "type": "Feature",
  "properties": {
    "addr:full":"15768 232nd Ave NE Hawick MN 56273",
    "addr:housenumber":"15768",
    "addr:postcode":"56273",
    "addr:street":"232Nd Ave Ne",
    "iso:country":"US",
    "sg:address":"15768 232nd Ave NE",
    "sg:city":"Hawick",
    "sg:classifiers":[
        {
            "category":"Professional",
            "subcategory":"Business Services",
            "type":"Services"
        },
        {
            "category":"Government",
            "subcategory":"Office",
            "type":"Public Place"
        }
    ],
    "sg:phone":"+1 320 276 8526",
    "sg:postcode":"56273",
    "sg:province":"MN",
    "sg:tags":[
        "village"
    ],
    "wof:name":"Roseville Township Hall",
    "wof:placetype":"venue"
},
  "geometry": {"coordinates":[-94.828003,45.347916],"type":"Point"}
}