{
  "type": "Feature",
  "properties": {
    "iso:country":"US",
    "sg:address":"500 Lake St",
    "sg:city":"Excelsior",
    "sg:classifiers":[
        {
            "category":"Health Services",
            "subcategory":"Doctor",
            "type":"Services"
        }
    ],
    "sg:phone":"+1 952 401 7692",
    "sg:postcode":"55331",
    "sg:province":"MN",
    "sg:tags":[
        "physician",
        "surgeon"
    ],
    "wof:name":"Onyx Oncology",
    "wof:placetype":"venue"
},
  "geometry": {"coordinates":[-93.563446,44.903003],"type":"Point"}
}