{
  "type": "Feature",
  "properties": {
    "iso:country":"US",
    "sg:address":"2429 Nicollet Ave",
    "sg:city":"Minneapolis",
    "sg:classifiers":[
        {
            "category":"Real Estate",
            "subcategory":"Real Estate Agent",
            "type":"Services"
        }
    ],
    "sg:phone":"+1 612 870 1190",
    "sg:postcode":"55404",
    "sg:province":"MN",
    "wof:name":"Home Link Realty",
    "wof:placetype":"venue"
},
  "geometry": {"coordinates":[-93.27778499999999,44.957844],"type":"Point"}
}