{
  "type": "Feature",
  "properties": {
    "iso:country":"US",
    "sg:address":"18129 Valley View Rd",
    "sg:city":"Eden Prairie",
    "sg:classifiers":[
        {
            "category":"Professional",
            "type":"Services"
        }
    ],
    "sg:phone":"+1 952 949 3045",
    "sg:postcode":"55346",
    "sg:province":"MN",
    "wof:name":"Gianni Gambucci Company",
    "wof:placetype":"venue"
},
  "geometry": {"coordinates":[-93.50683600000001,44.873256],"type":"Point"}
}