{
  "type": "Feature",
  "properties": {
    "addr:full":"12516 Pinehurst Dr Burnsville MN 55337",
    "addr:housenumber":"12516",
    "addr:postcode":"55337",
    "addr:street":"Pinehurst Dr",
    "iso:country":"US",
    "sg:address":"12516 Pinehurst Dr",
    "sg:city":"Burnsville",
    "sg:classifiers":[
        {
            "category":"Professional",
            "subcategory":"Business Services",
            "type":"Services"
        }
    ],
    "sg:phone":"+1 952 894 6999",
    "sg:postcode":"55337",
    "sg:province":"MN",
    "wof:name":"Guyana Assoc of Minnesota",
    "wof:placetype":"venue"
},
  "geometry": {"coordinates":[-93.234966,44.775679],"type":"Point"}
}