{
  "type": "Feature",
  "properties": {
    "iso:country":"US",
    "sg:address":"21 Pine Dr",
    "sg:city":"Circle Pines",
    "sg:classifiers":[
        {
            "category":"Personal",
            "subcategory":"Beauty Salon",
            "type":"Services"
        }
    ],
    "sg:phone":"+1 763 780 1131",
    "sg:postcode":"55014",
    "sg:province":"MN",
    "sg:tags":[
        "shop"
    ],
    "wof:name":"Design Affair Studio",
    "wof:placetype":"venue"
},
  "geometry": {"coordinates":[-93.14982000000001,45.152367],"type":"Point"}
}