{
  "type": "Feature",
  "properties": {
    "addr:full":"1986 State Hwy 23 Mora MN 55051",
    "addr:housenumber":"1986",
    "addr:postcode":"55051",
    "addr:street":"State Hwy 23",
    "iso:country":"US",
    "sg:address":"1986 State Hwy 23",
    "sg:city":"Mora",
    "sg:phone":"+1 320 679 5295",
    "sg:postcode":"55051",
    "sg:province":"MN",
    "sg:tags":[
        "grain",
        "cash"
    ],
    "wof:name":"Ralph Lick",
    "wof:placetype":"venue"
},
  "geometry": {"coordinates":[-93.310412,45.853446],"type":"Point"}
}