{
  "type": "Feature",
  "properties": {
    "addr:full":"41704 293rd Ave Le Sueur MN 56058",
    "addr:housenumber":"41704",
    "addr:postcode":"56058",
    "addr:street":"293Rd Ave",
    "iso:country":"US",
    "sg:address":"41704 293rd Ave",
    "sg:city":"Le Sueur",
    "sg:classifiers":[
        {
            "category":"Farming",
            "subcategory":"Nursery",
            "type":"Manufacturing & Wholesale Goods"
        }
    ],
    "sg:phone":"+1 507 931 3557",
    "sg:postcode":"56058",
    "sg:province":"MN",
    "sg:tags":[
        "ornamental"
    ],
    "wof:name":"Country Petals Greenhouse",
    "wof:placetype":"venue"
},
  "geometry": {"coordinates":[-93.85134499999999,44.345693],"type":"Point"}
}