{
  "type": "Feature",
  "properties": {
    "iso:country":"US",
    "sg:address":"1800 Bowsens Ln",
    "sg:city":"Woodbury",
    "sg:classifiers":[
        {
            "category":"Organizations",
            "subcategory":"Membership Organization",
            "type":"Services"
        }
    ],
    "sg:phone":"+1 651 702 3603",
    "sg:postcode":"55125",
    "sg:province":"MN",
    "sg:tags":[
        "athletic"
    ],
    "wof:name":"Metro Officials Svc",
    "wof:placetype":"venue"
},
  "geometry": {"coordinates":[-92.911023,44.920843],"type":"Point"}
}