{
  "type": "Feature",
  "properties": {
    "addr:full":"1974 Lexington Ave N St Paul MN 55113",
    "addr:housenumber":"1974",
    "addr:postcode":"55113",
    "addr:street":"Lexington Ave N",
    "iso:country":"US",
    "sg:address":"1974 Lexington Ave N",
    "sg:city":"St Paul",
    "sg:classifiers":[
        {
            "category":"Personal",
            "type":"Services"
        }
    ],
    "sg:phone":"+1 651 488 3552",
    "sg:postcode":"55113",
    "sg:province":"MN",
    "sg:tags":[
        "consultant",
        "wedding"
    ],
    "wof:name":"Weddings Dunwell",
    "wof:placetype":"venue"
},
  "geometry": {"coordinates":[-93.14639,45.001017],"type":"Point"}
}