{
  "type": "Feature",
  "properties": {
    "iso:country":"US",
    "sg:address":"651 Hickory Pl",
    "sg:city":"Circle Pines",
    "sg:classifiers":[
        {
            "category":"Freight",
            "type":"Transportation"
        }
    ],
    "sg:phone":"+1 612 282 4993",
    "sg:postcode":"55014",
    "sg:province":"MN",
    "sg:tags":[
        "excavation",
        "trucking",
        "plowing",
        "snow"
    ],
    "wof:name":"Kodiak Trucking and Excvtg Inc",
    "wof:placetype":"venue"
},
  "geometry": {"coordinates":[-93.10923,45.141729],"type":"Point"}
}