{
  "type": "Feature",
  "properties": {
    "addr:full":"19600 Cardinal Dr Grand Rapids MN 55744",
    "addr:housenumber":"19600",
    "addr:postcode":"55744",
    "addr:street":"Cardinal Dr",
    "iso:country":"US",
    "sg:address":"19600 Cardinal Dr",
    "sg:city":"Grand Rapids",
    "sg:classifiers":[
        {
            "category":"Manufacturing",
            "subcategory":"Lumber",
            "type":"Manufacturing & Wholesale Goods"
        }
    ],
    "sg:phone":"+1 218 326 5965",
    "sg:postcode":"55744",
    "sg:province":"MN",
    "sg:tags":[
        "operation",
        "timber",
        "tract"
    ],
    "wof:name":"Wegner Carl",
    "wof:placetype":"venue"
},
  "geometry": {"coordinates":[-93.40094999999999,47.153437],"type":"Point"}
}