{
  "type": "Feature",
  "properties": {
    "iso:country":"US",
    "sg:address":"811 9th St NW",
    "sg:city":"Bemidji",
    "sg:classifiers":[
        {
            "category":"Manufacturing",
            "subcategory":"Wood Products",
            "type":"Manufacturing & Wholesale Goods"
        }
    ],
    "sg:phone":"+1 218 444 9017",
    "sg:postcode":"56601",
    "sg:province":"MN",
    "sg:tags":[
        "millwork-wholesale",
        "millwork",
        "manufacturer"
    ],
    "wof:name":"Woodshop Designs",
    "wof:placetype":"venue"
},
  "geometry": {"coordinates":[-94.89007700000001,47.476649],"type":"Point"}
}