{
  "type": "Feature",
  "properties": {
    "addr:full":"5393 Miller Trunk Hwy Duluth MN 55811",
    "addr:housenumber":"5393",
    "addr:postcode":"55811",
    "addr:street":"Miller Trunk Hwy",
    "iso:country":"US",
    "sg:address":"5393 Miller Trunk Hwy",
    "sg:city":"Duluth",
    "sg:classifiers":[
        {
            "category":"Wholesale",
            "subcategory":"Construction Materials",
            "type":"Manufacturing & Wholesale Goods"
        },
        {
            "category":"Wholesale",
            "subcategory":"Machinery & Supplies",
            "type":"Manufacturing & Wholesale Goods"
        }
    ],
    "sg:phone":"+1 218 729 8075",
    "sg:postcode":"55811",
    "sg:province":"MN",
    "sg:tags":[
        "dry wall",
        "contractor"
    ],
    "wof:name":"Tamarack Materials Inc",
    "wof:placetype":"venue"
},
  "geometry": {"coordinates":[-92.243165,46.837813],"type":"Point"}
}