{
  "type": "Feature",
  "properties": {
    "iso:country":"US",
    "sg:address":"116 1st Ave E",
    "sg:city":"Cambridge",
    "sg:classifiers":[
        {
            "category":"Insurance",
            "subcategory":"Insurance Agent",
            "type":"Services"
        }
    ],
    "sg:phone":"+1 763 689 3100",
    "sg:postcode":"55008",
    "sg:province":"MN",
    "sg:website":"http://www.peoplesstateagency.com",
    "wof:name":"Peoples State Agency",
    "wof:placetype":"venue"
},
  "geometry": {"coordinates":[-93.223367,45.572659],"type":"Point"}
}