{
  "type": "Feature",
  "properties": {
    "iso:country":"US",
    "sg:address":"563 University Ave W",
    "sg:city":"St Paul",
    "sg:classifiers":[
        {
            "category":"Shopping",
            "subcategory":"Clothing, Apparel, & Fashions",
            "type":"Retail Goods"
        }
    ],
    "sg:phone":"+1 651 291 9175",
    "sg:postcode":"55103",
    "sg:province":"MN",
    "sg:tags":[
        "tailor"
    ],
    "wof:name":"New Fashions Tailoring",
    "wof:placetype":"venue"
},
  "geometry": {"coordinates":[-93.126289,44.955793],"type":"Point"}
}