{
  "type": "Feature",
  "properties": {
    "iso:country":"US",
    "sg:address":"6453 80th Ave N",
    "sg:city":"Glyndon",
    "sg:classifiers":[
        {
            "category":"Building & Trades",
            "subcategory":"Construction",
            "type":"Services"
        }
    ],
    "sg:phone":"+1 218 233 3477",
    "sg:postcode":"56547",
    "sg:province":"MN",
    "sg:tags":[
        "roofing",
        "industrial",
        "contractors-commercial",
        "contractor"
    ],
    "wof:name":"Rc Roofing",
    "wof:placetype":"venue"
},
  "geometry": {"coordinates":[-96.661204,46.963169],"type":"Point"}
}