{
  "type": "Feature",
  "properties": {
    "iso:country":"US",
    "sg:address":"2871 W Highway 14",
    "sg:city":"Owatonna",
    "sg:classifiers":[
        {
            "category":"Professional",
            "subcategory":"Accounting & Tax Preparation",
            "type":"Services"
        }
    ],
    "sg:phone":"+1 507 451 1873",
    "sg:postcode":"55060",
    "sg:province":"MN",
    "sg:tags":[
        "bookkeeping"
    ],
    "wof:name":"Stockwell Accounting",
    "wof:placetype":"venue"
},
  "geometry": {"coordinates":[-93.26347199999999,44.09524],"type":"Point"}
}