{
  "type": "Feature",
  "properties": {
    "addr:full":"4455 US Hwy 212 Montevideo MN 56265",
    "addr:housenumber":"4455",
    "addr:postcode":"56265",
    "addr:street":"Us Hwy 212",
    "iso:country":"US",
    "sg:address":"4455 US Hwy 212",
    "sg:city":"Montevideo",
    "sg:classifiers":[
        {
            "category":"Retail",
            "subcategory":"Repair Shop",
            "type":"Services"
        }
    ],
    "sg:phone":"+1 320 269 2920",
    "sg:postcode":"56265",
    "sg:province":"MN",
    "sg:tags":[
        "plumbing",
        "drain",
        "cleaning",
        "sewer"
    ],
    "wof:name":"T A Lauritsen Septic & Drain",
    "wof:placetype":"venue"
},
  "geometry": {"coordinates":[-95.690713,44.910452],"type":"Point"}
}