{
  "type": "Feature",
  "properties": {
    "addr:full":"1970 15th St NE Sauk Rapids MN 56379",
    "addr:housenumber":"1970",
    "addr:postcode":"56379",
    "addr:street":"15Th St Ne",
    "iso:country":"US",
    "sg:address":"1970 15th St NE",
    "sg:city":"Sauk Rapids",
    "sg:classifiers":[
        {
            "category":"Organizations",
            "subcategory":"Religious Organization",
            "type":"Services"
        }
    ],
    "sg:phone":"+1 320 654 0623",
    "sg:postcode":"56379",
    "sg:province":"MN",
    "sg:tags":[
        "church"
    ],
    "wof:name":"Spirit Of Life Church Unitaria",
    "wof:placetype":"venue"
},
  "geometry": {"coordinates":[-94.12542999999999,45.588283],"type":"Point"}
}