{
  "type": "Feature",
  "properties": {
    "iso:country":"US",
    "sg:address":"7510 Market Place Dr",
    "sg:city":"Eden Prairie",
    "sg:classifiers":[
        {
            "category":"Building & Trades",
            "subcategory":"Cleaning & Sanitation",
            "type":"Services"
        }
    ],
    "sg:phone":"+1 952 944 4000",
    "sg:postcode":"55344",
    "sg:province":"MN",
    "sg:tags":[
        "janitor",
        "maintenance"
    ],
    "wof:name":"Multi Services Inc",
    "wof:placetype":"venue"
},
  "geometry": {"coordinates":[-93.425048,44.868469],"type":"Point"}
}