{
  "type": "Feature",
  "properties": {
    "iso:country":"US",
    "sg:address":"1015 Maryland Ave E",
    "sg:city":"Saint Paul",
    "sg:classifiers":[
        {
            "category":"Banks & Credit Unions",
            "subcategory":"Bank",
            "type":"Services"
        }
    ],
    "sg:phone":"+1 651 776 6195",
    "sg:postcode":"55106",
    "sg:province":"MN",
    "sg:tags":[
        "mortgage"
    ],
    "wof:name":"Omega Direct Services",
    "wof:placetype":"venue"
},
  "geometry": {"coordinates":[-93.056265,44.977607],"type":"Point"}
}