{
  "type": "Feature",
  "properties": {
    "addr:full":"2404 Oakland Ave Duluth MN 55812",
    "addr:housenumber":"2404",
    "addr:postcode":"55812",
    "addr:street":"Oakland Ave",
    "iso:country":"US",
    "sg:address":"2404 Oakland Ave",
    "sg:city":"Duluth",
    "sg:classifiers":[
        {
            "category":"Education",
            "subcategory":"College",
            "type":"Public Place"
        }
    ],
    "sg:phone":"+1 218 726 8178",
    "sg:postcode":"55812",
    "sg:province":"MN",
    "sg:tags":[
        "institutional",
        "research"
    ],
    "wof:name":"Housing Offce Univ Minnsta",
    "wof:placetype":"venue"
},
  "geometry": {"coordinates":[-92.08395299999999,46.821323],"type":"Point"}
}