{
  "type": "Feature",
  "properties": {
    "addr:full":"1201 7th Ave N Sauk Rapids MN 56379",
    "addr:housenumber":"1201",
    "addr:postcode":"56379",
    "addr:street":"7Th Ave N Sauk",
    "iso:country":"US",
    "sg:address":"1201 7th Ave N",
    "sg:city":"Sauk Rapids",
    "sg:classifiers":[
        {
            "category":"Insurance",
            "subcategory":"Insurance Agent",
            "type":"Services"
        }
    ],
    "sg:phone":"+1 320 259 9866",
    "sg:postcode":"56379",
    "sg:province":"MN",
    "wof:name":"Heartland Financial Strategies",
    "wof:placetype":"venue"
},
  "geometry": {"coordinates":[-94.167548,45.605819],"type":"Point"}
}