{
  "type": "Feature",
  "properties": {
    "addr:full":"13535 Johnson St NE Ham Lake MN 55304",
    "addr:housenumber":"13535",
    "addr:postcode":"55304",
    "addr:street":"Johnson St Ne",
    "iso:country":"US",
    "sg:address":"13535 Johnson St NE",
    "sg:city":"Ham Lake",
    "sg:classifiers":[
        {
            "category":"Building & Trades",
            "subcategory":"Construction",
            "type":"Services"
        }
    ],
    "sg:phone":"+1 763 757 6859",
    "sg:postcode":"55304",
    "sg:province":"MN",
    "sg:tags":[
        "underground",
        "wire",
        "laying",
        "cable"
    ],
    "wof:name":"T-Ray Construction",
    "wof:placetype":"venue"
},
  "geometry": {"coordinates":[-93.23666,45.215416],"type":"Point"}
}