{
  "type": "Feature",
  "properties": {
    "addr:full":"31307 144th St Princeton MN 55371",
    "addr:housenumber":"31307",
    "addr:postcode":"55371",
    "addr:street":"144Th St",
    "iso:country":"US",
    "sg:address":"31307 144th St",
    "sg:city":"Princeton",
    "sg:classifiers":[
        {
            "category":"Manufacturing",
            "subcategory":"Tools & Machinery",
            "type":"Manufacturing & Wholesale Goods"
        }
    ],
    "sg:phone":"+1 763 856 5020",
    "sg:postcode":"55371",
    "sg:province":"MN",
    "sg:tags":[
        "machine",
        "coolant",
        "recycling",
        "sales"
    ],
    "wof:name":"Innovative Solutions",
    "wof:placetype":"venue"
},
  "geometry": {"coordinates":[-93.634439,45.541751],"type":"Point"}
}