{
  "type": "Feature",
  "properties": {
    "addr:full":"1040 Getty St Sauk Centre MN 56378",
    "addr:housenumber":"1040",
    "addr:postcode":"56378",
    "addr:street":"Getty St",
    "iso:country":"US",
    "sg:address":"1040 Getty St",
    "sg:city":"Sauk Centre",
    "sg:classifiers":[
        {
            "category":"Wholesale",
            "subcategory":"Dairy",
            "type":"Manufacturing & Wholesale Goods"
        }
    ],
    "sg:phone":"+1 320 352 2328",
    "sg:postcode":"56378",
    "sg:province":"MN",
    "sg:tags":[
        "product",
        "eating"
    ],
    "wof:name":"Orths Quality Dairy",
    "wof:placetype":"venue"
},
  "geometry": {"coordinates":[-94.953835,45.727725],"type":"Point"}
}