{
  "type": "Feature",
  "properties": {
    "addr:full":"18500 Pilot Knob Rd Farmington MN 55024",
    "addr:housenumber":"18500",
    "addr:postcode":"55024",
    "addr:street":"Pilot Knob Rd",
    "iso:country":"US",
    "sg:address":"18500 Pilot Knob Rd",
    "sg:city":"Farmington",
    "sg:classifiers":[
        {
            "category":"Restaurant",
            "type":"Food & Drink"
        }
    ],
    "sg:phone":"+1 651 460 4400",
    "sg:postcode":"55024",
    "sg:province":"MN",
    "sg:tags":[
        "eating"
    ],
    "wof:name":"Teds Pizza",
    "wof:placetype":"venue"
},
  "geometry": {"coordinates":[-93.176841,44.677464],"type":"Point"}
}