{
  "type": "Feature",
  "properties": {
    "iso:country":"US",
    "sg:address":"110 Main St S",
    "sg:city":"Austin",
    "sg:classifiers":[
        {
            "category":"Professional",
            "subcategory":"Advertising",
            "type":"Services"
        }
    ],
    "sg:phone":"+1 507 434 3707",
    "sg:postcode":"55912",
    "sg:province":"MN",
    "sg:tags":[
        "guide"
    ],
    "wof:name":"Yellow Book",
    "wof:placetype":"venue"
},
  "geometry": {"coordinates":[-92.974929,43.666486],"type":"Point"}
}