{
  "type": "Feature",
  "properties": {
    "iso:country":"US",
    "sg:address":"3565 Hoffman Rd E",
    "sg:city":"St Paul",
    "sg:classifiers":[
        {
            "category":"Local Transit",
            "type":"Transportation"
        }
    ],
    "sg:phone":"+1 651 770 5668",
    "sg:postcode":"55110",
    "sg:province":"MN",
    "sg:tags":[
        "passenger",
        "limousine"
    ],
    "sg:website":"www.totallimo.com",
    "wof:name":"Total Luxury Limousine Service",
    "wof:placetype":"venue"
},
  "geometry": {"coordinates":[-93.03169,45.049663],"type":"Point"}
}