{
  "type": "Feature",
  "properties": {
    "iso:country":"US",
    "sg:address":"456 3rd Ave SE",
    "sg:city":"Perham",
    "sg:classifiers":[
        {
            "category":"Health Services",
            "subcategory":"Chiropractor",
            "type":"Services"
        }
    ],
    "sg:phone":"+1 218 346 2330",
    "sg:postcode":"56573",
    "sg:province":"MN",
    "wof:name":"Pankonin Vincent DC",
    "wof:placetype":"venue"
},
  "geometry": {"coordinates":[-95.573882,46.590103],"type":"Point"}
}