{
  "type": "Feature",
  "properties": {
    "iso:country":"US",
    "sg:address":"9621 10th Ave N",
    "sg:city":"Minneapolis",
    "sg:classifiers":[
        {
            "category":"Building & Trades",
            "subcategory":"Landscaping Services",
            "type":"Services"
        },
        {
            "category":"Professional",
            "subcategory":"Business Services",
            "type":"Services"
        }
    ],
    "sg:phone":"+1 763 545 9740",
    "sg:postcode":"55441",
    "sg:province":"MN",
    "sg:tags":[
        "product",
        "environmental",
        "ecological",
        "remediation",
        "services-site"
    ],
    "sg:website":"http://www.lindstromenvironmental.com",
    "wof:name":"Lindstrom Environmental, Inc.",
    "wof:placetype":"venue"
},
  "geometry": {"coordinates":[-93.402463,44.989386],"type":"Point"}
}