{
  "type": "Feature",
  "properties": {
    "addr:full":"2040 Ramlow Pl St Paul MN 55116",
    "addr:housenumber":"2040",
    "addr:postcode":"55116",
    "addr:street":"Ramlow Pl",
    "iso:country":"US",
    "sg:address":"2040 Ramlow Pl",
    "sg:city":"St Paul",
    "sg:classifiers":[
        {
            "category":"Professional",
            "subcategory":"Computer Services",
            "type":"Services"
        }
    ],
    "sg:phone":"+1 651 699 9642",
    "sg:postcode":"55116",
    "sg:province":"MN",
    "sg:tags":[
        "repair"
    ],
    "wof:name":"E I Computer Consulting",
    "wof:placetype":"venue"
},
  "geometry": {"coordinates":[-93.18593199999999,44.905178],"type":"Point"}
}