{
  "type": "Feature",
  "properties": {
    "addr:full":"3581 Ridgewood Rd Saint Paul MN 55112",
    "addr:housenumber":"3581",
    "addr:postcode":"55112",
    "addr:street":"Ridgewood Rd",
    "iso:country":"US",
    "sg:address":"3581 Ridgewood Rd",
    "sg:city":"Saint Paul",
    "sg:classifiers":[
        {
            "category":"Manufacturing",
            "subcategory":"Electronics",
            "type":"Manufacturing & Wholesale Goods"
        }
    ],
    "sg:phone":"+1 651 633 4061",
    "sg:postcode":"55112",
    "sg:province":"MN",
    "sg:tags":[
        "power",
        "mfg",
        "supply",
        "component",
        "char",
        "including",
        "electronic"
    ],
    "wof:name":"Systematics Inc",
    "wof:placetype":"venue"
},
  "geometry": {"coordinates":[-93.164957,45.050011],"type":"Point"}
}