{
  "type": "Feature",
  "properties": {
    "addr:full":"515 NE 2nd Ave Grand Rapids MN 55744",
    "addr:housenumber":"515",
    "addr:postcode":"55744",
    "addr:street":"Ne 2Nd Ave",
    "iso:country":"US",
    "sg:address":"515 NE 2nd Ave",
    "sg:city":"Grand Rapids",
    "sg:classifiers":[
        {
            "category":"Professional",
            "subcategory":"Lawyer & Legal Services",
            "type":"Services"
        }
    ],
    "sg:phone":"+1 218 327 2675",
    "sg:postcode":"55744",
    "sg:province":"MN",
    "wof:name":"Brian C Bengtson",
    "wof:placetype":"venue"
},
  "geometry": {"coordinates":[-93.525324,47.237851],"type":"Point"}
}