{
  "type": "Feature",
  "properties": {
    "addr:full":"14426 Townline Ave Shakopee MN 55379",
    "addr:housenumber":"14426",
    "addr:postcode":"55379",
    "addr:street":"Townline Ave",
    "iso:country":"US",
    "sg:address":"14426 Townline Ave",
    "sg:city":"Shakopee",
    "sg:classifiers":[
        {
            "category":"Building & Trades",
            "subcategory":"Construction",
            "type":"Services"
        }
    ],
    "sg:phone":"+1 952 233 3344",
    "sg:postcode":"55379",
    "sg:province":"MN",
    "sg:tags":[
        "repairing",
        "house",
        "contractor",
        "home",
        "improvement",
        "remodeling"
    ],
    "wof:name":"Creative Home Improvement Inc",
    "wof:placetype":"venue"
},
  "geometry": {"coordinates":[-93.525026,44.742788],"type":"Point"}
}