{
  "type": "Feature",
  "properties": {
    "addr:full":"11769 330th St Onamia MN 56359",
    "addr:housenumber":"11769",
    "addr:postcode":"56359",
    "addr:street":"330Th St",
    "iso:country":"US",
    "sg:address":"11769 330th St",
    "sg:city":"Onamia",
    "sg:classifiers":[
        {
            "category":"Farming",
            "subcategory":"Livestock Farm",
            "type":"Manufacturing & Wholesale Goods"
        }
    ],
    "sg:phone":"+1 320 532 3556",
    "sg:postcode":"56359",
    "sg:province":"MN",
    "sg:tags":[
        "beef",
        "feedlot",
        "cattle"
    ],
    "wof:name":"James Jones",
    "wof:placetype":"venue"
},
  "geometry": {"coordinates":[-93.66139699999999,46.025789],"type":"Point"}
}