{
  "type": "Feature",
  "properties": {
    "iso:country":"US",
    "sg:address":"14165 James Rd Ste 106",
    "sg:city":"Rogers",
    "sg:classifiers":[
        {
            "category":"Health Services",
            "subcategory":"Optometrist",
            "type":"Services"
        },
        {
            "category":"Shopping",
            "subcategory":"Optical Goods",
            "type":"Retail Goods"
        },
        {
            "category":"Shopping",
            "subcategory":"Optician",
            "type":"Retail Goods"
        }
    ],
    "sg:phone":"+1 763 428 3757",
    "sg:postcode":"55374",
    "sg:province":"MN",
    "sg:tags":[
        "lens",
        "eyeglass",
        "contact"
    ],
    "sg:website":"http://www.eyewestvisionclinic.com",
    "wof:name":"Eye West Vision Clinic",
    "wof:placetype":"venue"
},
  "geometry": {"coordinates":[-93.549888,45.214821],"type":"Point"}
}