{
  "type": "Feature",
  "properties": {
    "iso:country":"US",
    "sg:address":"417 11th St S",
    "sg:city":"St James",
    "sg:classifiers":[
        {
            "category":"Health Services",
            "subcategory":"Health Practitioner",
            "type":"Services"
        }
    ],
    "sg:phone":"+1 507 375 9114",
    "sg:postcode":"56081",
    "sg:province":"MN",
    "sg:tags":[
        "psychologist"
    ],
    "wof:name":"Tieffenbacher & Assoc",
    "wof:placetype":"venue"
},
  "geometry": {"coordinates":[-94.619439,43.981589],"type":"Point"}
}