{
  "type": "Feature",
  "properties": {
    "iso:country":"US",
    "sg:address":"2525 Williams Dr",
    "sg:city":"Burnsville",
    "sg:classifiers":[
        {
            "category":"Social Services",
            "subcategory":"Child Care",
            "type":"Services"
        },
        {
            "category":"Education",
            "subcategory":"Preschool",
            "type":"Public Place"
        },
        {
            "category":"Education",
            "subcategory":"School",
            "type":"Public Place"
        }
    ],
    "sg:phone":"+1 952 808 1233",
    "sg:postcode":"55337",
    "sg:province":"MN",
    "sg:tags":[
        "elementary",
        "day"
    ],
    "sg:website":"www.wonderkidz.net",
    "wof:name":"Wonder Kidz Montessorri & Child Care",
    "wof:placetype":"venue"
},
  "geometry": {"coordinates":[-93.313103,44.770401],"type":"Point"}
}