{
  "type": "Feature",
  "properties": {
    "addr:full":"11103 River Rd NE Hanover MN 55341",
    "addr:housenumber":"11103",
    "addr:postcode":"55341",
    "addr:street":"River Rd Ne",
    "iso:country":"US",
    "sg:address":"11103 River Rd NE",
    "sg:city":"Hanover",
    "sg:classifiers":[
        {
            "category":"Autos & Motor Vehicles",
            "subcategory":"Auto Supplies",
            "type":"Retail Goods"
        },
        {
            "category":"Retail",
            "subcategory":"Auto Repair",
            "type":"Services"
        }
    ],
    "sg:phone":"+1 763 498 6544",
    "sg:postcode":"55341",
    "sg:province":"MN",
    "sg:tags":[
        "wheel",
        "tire",
        "transmission",
        "automobile",
        "part",
        "brake",
        "transmissions-other"
    ],
    "sg:website":"http://www.hanovereuroparts.com",
    "wof:name":"Hanover European Auto Parts",
    "wof:placetype":"venue"
},
  "geometry": {"coordinates":[-93.662897,45.154595],"type":"Point"}
}