{
  "type": "Feature",
  "properties": {
    "addr:full":"14746 Harvest Rd Glencoe MN 55336",
    "addr:housenumber":"14746",
    "addr:postcode":"55336",
    "addr:street":"Harvest Rd",
    "iso:country":"US",
    "sg:address":"14746 Harvest Rd",
    "sg:city":"Glencoe",
    "sg:classifiers":[
        {
            "category":"Farming",
            "subcategory":"Dairy Farm",
            "type":"Manufacturing & Wholesale Goods"
        }
    ],
    "sg:phone":"+1 320 864 4498",
    "sg:postcode":"55336",
    "sg:province":"MN",
    "wof:name":"Duane Vinkemeier",
    "wof:placetype":"venue"
},
  "geometry": {"coordinates":[-94.206772,44.834059],"type":"Point"}
}