{
  "type": "Feature",
  "properties": {
    "iso:country":"US",
    "sg:address":"9321 E Bloomington Fwy",
    "sg:city":"Minneapolis",
    "sg:classifiers":[
        {
            "category":"Home & Garden",
            "subcategory":"Furniture",
            "type":"Retail Goods"
        }
    ],
    "sg:phone":"+1 952 881 3945",
    "sg:postcode":"55420",
    "sg:province":"MN",
    "wof:name":"Bucks Unpainted Furniture",
    "wof:placetype":"venue"
},
  "geometry": {"coordinates":[-93.295457,44.83573],"type":"Point"}
}