{
  "type": "Feature",
  "properties": {
    "addr:full":"90331 470th Ave Windom MN 56101",
    "addr:housenumber":"90331",
    "addr:postcode":"56101",
    "addr:street":"470Th Ave",
    "iso:country":"US",
    "sg:address":"90331 470th Ave",
    "sg:city":"Windom",
    "sg:classifiers":[
        {
            "category":"Personal",
            "subcategory":"Beauty Salon",
            "type":"Services"
        }
    ],
    "sg:phone":"+1 507 831 3100",
    "sg:postcode":"56101",
    "sg:province":"MN",
    "sg:tags":[
        "hair",
        "stylist"
    ],
    "wof:name":"His & Her Hair Nook",
    "wof:placetype":"venue"
},
  "geometry": {"coordinates":[-95.13472400000001,43.68503],"type":"Point"}
}