{
  "type": "Feature",
  "properties": {
    "addr:full":"410 1st Ave NE Rochester MN 55906",
    "addr:housenumber":"410",
    "addr:postcode":"55906",
    "addr:street":"1St Ave Ne",
    "iso:country":"US",
    "sg:address":"410 1st Ave NE",
    "sg:city":"Rochester",
    "sg:classifiers":[
        {
            "category":"Building & Trades",
            "subcategory":"Construction",
            "type":"Services"
        }
    ],
    "sg:phone":"+1 507 281 1349",
    "sg:postcode":"55906",
    "sg:province":"MN",
    "sg:tags":[
        "contractor",
        "carpentry",
        "material",
        "mfg"
    ],
    "wof:name":"Thompson Jim Ovrhd Gar Door Co",
    "wof:placetype":"venue"
},
  "geometry": {"coordinates":[-92.46151399999999,44.028016],"type":"Point"}
}