{
  "type": "Feature",
  "properties": {
    "iso:country":"US",
    "sg:address":"910 1st St S",
    "sg:city":"Hopkins",
    "sg:classifiers":[
        {
            "category":"Government",
            "subcategory":"Post Office",
            "type":"Public Place"
        }
    ],
    "sg:phone":"+1 952 935 8606",
    "sg:postcode":"55343",
    "sg:province":"MN",
    "sg:tags":[
        "postal",
        "us"
    ],
    "wof:name":"Hopkins Main Office",
    "wof:placetype":"venue"
},
  "geometry": {"coordinates":[-93.412745,44.922302],"type":"Point"}
}