{
  "type": "Feature",
  "properties": {
    "addr:full":"95 Sherburne Ave Saint Paul MN 55103",
    "addr:housenumber":"95",
    "addr:postcode":"55103",
    "addr:street":"Sherburne Ave",
    "iso:country":"US",
    "sg:address":"95 Sherburne Ave",
    "sg:city":"Saint Paul",
    "sg:classifiers":[
        {
            "category":"Banks & Credit Unions",
            "subcategory":"Bank",
            "type":"Services"
        }
    ],
    "sg:phone":"+1 651 291 3700",
    "sg:postcode":"55103",
    "sg:province":"MN",
    "sg:tags":[
        "state"
    ],
    "wof:name":"Affinity Plus Fdrl Crdt Union",
    "wof:placetype":"venue"
},
  "geometry": {"coordinates":[-93.10221799999999,44.95684],"type":"Point"}
}