{
  "type": "Feature",
  "properties": {
    "iso:country":"US",
    "sg:address":"2588 62nd St NW",
    "sg:city":"Maple Lake",
    "sg:classifiers":[
        {
            "category":"Building & Trades",
            "subcategory":"Construction",
            "type":"Services"
        }
    ],
    "sg:phone":"+1 320 963 3061",
    "sg:postcode":"55358",
    "sg:province":"MN",
    "sg:tags":[
        "dry wall",
        "contractor"
    ],
    "wof:name":"Don's Drywall",
    "wof:placetype":"venue"
},
  "geometry": {"coordinates":[-93.946032,45.240173],"type":"Point"}
}