{
  "type": "Feature",
  "properties": {
    "iso:country":"US",
    "sg:address":"1415 Saint Francis Ave",
    "sg:city":"Shakopee",
    "sg:classifiers":[
        {
            "category":"Health Services",
            "subcategory":"Doctor",
            "type":"Services"
        }
    ],
    "sg:phone":"+1 952 993 7750",
    "sg:postcode":"55379",
    "sg:province":"MN",
    "sg:tags":[
        "practice",
        "obstetrician",
        "family",
        "gynecologist"
    ],
    "wof:name":"Torkelson Susan J MD",
    "wof:placetype":"venue"
},
  "geometry": {"coordinates":[-93.504992,44.770071],"type":"Point"}
}