{
  "type": "Feature",
  "properties": {
    "addr:full":"620 1st St SE Richmond MN 56368",
    "addr:housenumber":"620",
    "addr:postcode":"56368",
    "addr:street":"1St St Se",
    "iso:country":"US",
    "sg:address":"620 1st St SE",
    "sg:city":"Richmond",
    "sg:classifiers":[
        {
            "category":"Building & Trades",
            "subcategory":"Plumbing",
            "type":"Services"
        }
    ],
    "sg:phone":"+1 320 597 2463",
    "sg:postcode":"56368",
    "sg:province":"MN",
    "sg:tags":[
        "plumber",
        "industrial",
        "contractors-commercial"
    ],
    "wof:name":"Hennen's Waterworks",
    "wof:placetype":"venue"
},
  "geometry": {"coordinates":[-94.50764599999999,45.453023],"type":"Point"}
}