{
  "type": "Feature",
  "properties": {
    "addr:full":"28688 Underwood Rd Grand Rapids MN 55744",
    "addr:housenumber":"28688",
    "addr:postcode":"55744",
    "addr:street":"Underwood Rd",
    "iso:country":"US",
    "sg:address":"28688 Underwood Rd",
    "sg:city":"Grand Rapids",
    "sg:classifiers":[
        {
            "category":"Manufacturing",
            "subcategory":"Lumber",
            "type":"Manufacturing & Wholesale Goods"
        }
    ],
    "sg:phone":"+1 218 326 4230",
    "sg:postcode":"55744",
    "sg:province":"MN",
    "sg:tags":[
        "logging",
        "eating"
    ],
    "wof:name":"M & R Chips Inc",
    "wof:placetype":"venue"
},
  "geometry": {"coordinates":[-93.454831,47.166955],"type":"Point"}
}