{
  "type": "Feature",
  "properties": {
    "iso:country":"US",
    "sg:address":"428 Washington Ave N",
    "sg:city":"Minneapolis",
    "sg:classifiers":[
        {
            "category":"Manufacturing",
            "subcategory":"Printing",
            "type":"Manufacturing & Wholesale Goods"
        }
    ],
    "sg:phone":"+1 612 343 5923",
    "sg:postcode":"55401",
    "sg:province":"MN",
    "sg:tags":[
        "publisher"
    ],
    "wof:name":"Free Spirit Publishing Inc",
    "wof:placetype":"venue"
},
  "geometry": {"coordinates":[-93.27460600000001,44.985852],"type":"Point"}
}