{
  "type": "Feature",
  "properties": {
    "iso:country":"US",
    "sg:address":"9795 Twain Dr SW",
    "sg:city":"Bemidji",
    "sg:classifiers":[
        {
            "category":"Retail",
            "subcategory":"Auto Repair",
            "type":"Services"
        }
    ],
    "sg:phone":"+1 218 751 1492",
    "sg:postcode":"56601",
    "sg:province":"MN",
    "sg:tags":[
        "automotive"
    ],
    "wof:name":"Stus Auto Electric & Repair",
    "wof:placetype":"venue"
},
  "geometry": {"coordinates":[-95.023629,47.451026],"type":"Point"}
}