{
  "type": "Feature",
  "properties": {
    "iso:country":"US",
    "sg:address":"103 W 3rd Ave",
    "sg:city":"Keewatin",
    "sg:classifiers":[
        {
            "category":"Banks & Credit Unions",
            "subcategory":"Bank",
            "type":"Services"
        }
    ],
    "sg:phone":"+1 218 778 6833",
    "sg:postcode":"55753",
    "sg:province":"MN",
    "wof:name":"Central Hanna Employees CU",
    "wof:placetype":"venue"
},
  "geometry": {"coordinates":[-93.076131,47.398785],"type":"Point"}
}