{
  "type": "Feature",
  "properties": {
    "addr:full":"1837 Eustis St Saint Paul MN 55113",
    "addr:housenumber":"1837",
    "addr:postcode":"55113",
    "addr:street":"Eustis St",
    "iso:country":"US",
    "sg:address":"1837 Eustis St",
    "sg:city":"Saint Paul",
    "sg:classifiers":[
        {
            "category":"Building & Trades",
            "subcategory":"Construction",
            "type":"Services"
        }
    ],
    "sg:phone":"+1 651 644 3713",
    "sg:postcode":"55113",
    "sg:province":"MN",
    "sg:tags":[
        "house"
    ],
    "wof:name":"Zbacnik Renovations",
    "wof:placetype":"venue"
},
  "geometry": {"coordinates":[-93.202586,44.995991],"type":"Point"}
}