{
  "type": "Feature",
  "properties": {
    "addr:full":"2239 130th Ave Russell MN 56169",
    "addr:housenumber":"2239",
    "addr:postcode":"56169",
    "addr:street":"130Th Ave",
    "iso:country":"US",
    "sg:address":"2239 130th Ave",
    "sg:city":"Russell",
    "sg:phone":"+1 507 823 4661",
    "sg:postcode":"56169",
    "sg:province":"MN",
    "sg:tags":[
        "farm",
        "corn",
        "soybean"
    ],
    "wof:name":"Dayle Swift",
    "wof:placetype":"venue"
},
  "geometry": {"coordinates":[-96.03829500000001,44.383224],"type":"Point"}
}