{
  "type": "Feature",
  "properties": {
    "addr:full":"20411 110th St N Borup MN 56519",
    "addr:housenumber":"20411",
    "addr:postcode":"56519",
    "addr:street":"110Th St N",
    "iso:country":"US",
    "sg:address":"20411 110th St N",
    "sg:city":"Borup",
    "sg:phone":"+1 218 494 3345",
    "sg:postcode":"56519",
    "sg:province":"MN",
    "sg:tags":[
        "farm",
        "grain",
        "cash"
    ],
    "wof:name":"Dale Smith",
    "wof:placetype":"venue"
},
  "geometry": {"coordinates":[-96.564117,47.145132],"type":"Point"}
}