{
  "type": "Feature",
  "properties": {
    "addr:full":"1600 2nd Ave NW Stewartville MN 55976",
    "addr:housenumber":"1600",
    "addr:postcode":"55976",
    "addr:street":"2Nd Ave Nw",
    "iso:country":"US",
    "sg:address":"1600 2nd Ave NW",
    "sg:city":"Stewartville",
    "sg:classifiers":[
        {
            "category":"Wholesale",
            "subcategory":"Non-durable Goods",
            "type":"Manufacturing & Wholesale Goods"
        }
    ],
    "sg:phone":"+1 507 533 4691",
    "sg:postcode":"55976",
    "sg:province":"MN",
    "wof:name":"Balloons of Joy",
    "wof:placetype":"venue"
},
  "geometry": {"coordinates":[-92.48992,43.86859],"type":"Point"}
}