{
  "type": "Feature",
  "properties": {
    "iso:country":"US",
    "sg:address":"11125 E Gull Lake Rd",
    "sg:city":"East Gull Lake",
    "sg:classifiers":[
        {
            "category":"Building & Trades",
            "subcategory":"Construction",
            "type":"Services"
        }
    ],
    "sg:phone":"+1 218 828 1153",
    "sg:postcode":"56401",
    "sg:province":"MN",
    "sg:tags":[
        "general",
        "contractor"
    ],
    "wof:name":"Brennan Construction",
    "wof:placetype":"venue"
},
  "geometry": {"coordinates":[-94.351089,46.402055],"type":"Point"}
}