{
  "type": "Feature",
  "properties": {
    "iso:country":"US",
    "sg:address":"1215 Roberts Rd SW",
    "sg:city":"Hutchinson",
    "sg:classifiers":[
        {
            "category":"Organizations",
            "subcategory":"Religious Organization",
            "type":"Services"
        }
    ],
    "sg:phone":"+1 320 587 2668",
    "sg:postcode":"55350",
    "sg:province":"MN",
    "sg:tags":[
        "church"
    ],
    "sg:website":"www.shalombaptist.org",
    "wof:name":"Shalom Baptist Church",
    "wof:placetype":"venue"
},
  "geometry": {"coordinates":[-94.395922,44.885281],"type":"Point"}
}