{
  "type": "Feature",
  "properties": {
    "addr:full":"644 Selby Ave St Paul MN 55104",
    "addr:housenumber":"644",
    "addr:postcode":"55104",
    "addr:street":"Selby Ave",
    "iso:country":"US",
    "sg:address":"644 Selby Ave",
    "sg:city":"St Paul",
    "sg:classifiers":[
        {
            "category":"Professional",
            "type":"Services"
        }
    ],
    "sg:phone":"+1 651 224 2034",
    "sg:postcode":"55104",
    "sg:province":"MN",
    "sg:tags":[
        "establishment"
    ],
    "wof:name":"Six-O-Six Drop In Ctr",
    "wof:placetype":"venue"
},
  "geometry": {"coordinates":[-93.128078,44.946527],"type":"Point"}
}