{
  "type": "Feature",
  "properties": {
    "iso:country":"US",
    "sg:address":"11625 Live Oak Dr",
    "sg:city":"Hopkins",
    "sg:classifiers":[
        {
            "category":"Building & Trades",
            "subcategory":"Construction",
            "type":"Services"
        }
    ],
    "sg:phone":"+1 952 542 3838",
    "sg:postcode":"55305",
    "sg:province":"MN",
    "sg:tags":[
        "general",
        "contractor"
    ],
    "wof:name":"Energy Builders",
    "wof:placetype":"venue"
},
  "geometry": {"coordinates":[-93.425996,44.96308],"type":"Point"}
}