{
  "type": "Feature",
  "properties": {
    "iso:country":"US",
    "sg:address":"2702 W Superior St",
    "sg:city":"Duluth",
    "sg:classifiers":[
        {
            "category":"Professional",
            "subcategory":"Business Services",
            "type":"Services"
        }
    ],
    "sg:phone":"+1 218 628 9995",
    "sg:postcode":"55806",
    "sg:province":"MN",
    "sg:tags":[
        "information",
        "bureau",
        "convention"
    ],
    "wof:name":"Duluth Airshow",
    "wof:placetype":"venue"
},
  "geometry": {"coordinates":[-92.132885,46.760239],"type":"Point"}
}