{
  "type": "Feature",
  "properties": {
    "addr:full":"1005 Pebble Lake Rd Fergus Falls MN 56537",
    "addr:housenumber":"1005",
    "addr:postcode":"56537",
    "addr:street":"Pebble Lake Rd",
    "iso:country":"US",
    "sg:address":"1005 Pebble Lake Rd",
    "sg:city":"Fergus Falls",
    "sg:classifiers":[
        {
            "category":"Professional",
            "subcategory":"Lawyer & Legal Services",
            "type":"Services"
        }
    ],
    "sg:phone":"+1 218 736 2076",
    "sg:postcode":"56537",
    "sg:province":"MN",
    "sg:tags":[
        "attorney"
    ],
    "wof:name":"Hatling Law Office",
    "wof:placetype":"venue"
},
  "geometry": {"coordinates":[-96.057562,46.273576],"type":"Point"}
}