{
  "type": "Feature",
  "properties": {
    "addr:full":"22018 Co Rd 71 Grand Rapids MN 55744",
    "addr:housenumber":"22018;71",
    "addr:postcode":"55744",
    "addr:street":"Co Rd",
    "iso:country":"US",
    "sg:address":"22018 Co Rd 71",
    "sg:city":"Grand Rapids",
    "sg:classifiers":[
        {
            "category":"Social Services",
            "subcategory":"Child Care",
            "type":"Services"
        }
    ],
    "sg:phone":"+1 218 245 3980",
    "sg:postcode":"55744",
    "sg:province":"MN",
    "sg:tags":[
        "day"
    ],
    "wof:name":"Country Fun Daycare",
    "wof:placetype":"venue"
},
  "geometry": {"coordinates":[-93.385105,47.196827],"type":"Point"}
}