{
  "type": "Feature",
  "properties": {
    "iso:country":"US",
    "sg:address":"6429 Kenwood Rd",
    "sg:city":"Saint Cloud",
    "sg:classifiers":[
        {
            "category":"Manufacturing",
            "subcategory":"Toys & Sporting Goods",
            "type":"Manufacturing & Wholesale Goods"
        }
    ],
    "sg:phone":"+1 320 252 5842",
    "sg:postcode":"56303",
    "sg:province":"MN",
    "sg:tags":[
        "mfg"
    ],
    "wof:name":"Little Country Inn",
    "wof:placetype":"venue"
},
  "geometry": {"coordinates":[-94.249397,45.579121],"type":"Point"}
}