{
  "type": "Feature",
  "properties": {
    "addr:full":"2309 Como Ave Saint Paul MN 55108",
    "addr:housenumber":"2309",
    "addr:postcode":"55108",
    "addr:street":"Como Ave",
    "iso:country":"US",
    "sg:address":"2309 Como Ave",
    "sg:city":"Saint Paul",
    "sg:classifiers":[
        {
            "category":"Arts & Performance",
            "subcategory":"Art Gallery",
            "type":"Entertainment"
        },
        {
            "category":"Shopping",
            "subcategory":"Jewelry",
            "type":"Retail Goods"
        }
    ],
    "sg:phone":"+1 651 486 8990",
    "sg:postcode":"55108",
    "sg:province":"MN",
    "wof:name":"Vine & Branches Gallery & Gathering Place",
    "wof:placetype":"venue"
},
  "geometry": {"coordinates":[-93.195611,44.982652],"type":"Point"}
}