{
  "type": "Feature",
  "properties": {
    "addr:full":"11555 K-Tel Dr Minnetonka MN 55343",
    "addr:housenumber":"11555",
    "addr:postcode":"55343",
    "addr:street":"K-Tel Dr",
    "iso:country":"US",
    "sg:address":"11555 K-Tel Dr",
    "sg:city":"Minnetonka",
    "sg:classifiers":[
        {
            "category":"Home & Garden",
            "subcategory":"Building Materials",
            "type":"Retail Goods"
        }
    ],
    "sg:phone":"+1 952 938 3585",
    "sg:postcode":"55343",
    "sg:province":"MN",
    "sg:tags":[
        "screen",
        "window"
    ],
    "sg:website":"www.alcosupply.com",
    "wof:name":"Alco Service & Supply Co",
    "wof:placetype":"venue"
},
  "geometry": {"coordinates":[-93.42692099999999,44.912923],"type":"Point"}
}