{
  "type": "Feature",
  "properties": {
    "iso:country":"US",
    "sg:address":"27490 Garden Ave",
    "sg:city":"Vesta",
    "sg:phone":"+1 507 984 5473",
    "sg:postcode":"56292",
    "sg:province":"MN",
    "sg:tags":[
        "farm",
        "corn"
    ],
    "wof:name":"Bruce Wotschke",
    "wof:placetype":"venue"
},
  "geometry": {"coordinates":[-95.35002299999999,44.450108],"type":"Point"}
}