{
  "type": "Feature",
  "properties": {
    "addr:full":"11200 Prairie Lakes Dr Eden Prairie MN 55344",
    "addr:housenumber":"11200",
    "addr:postcode":"55344",
    "addr:street":"Prairie Lakes Dr",
    "iso:country":"US",
    "sg:address":"11200 Prairie Lakes Dr",
    "sg:city":"Eden Prairie",
    "sg:classifiers":[
        {
            "category":"Retail",
            "subcategory":"Veterinary Services",
            "type":"Services"
        }
    ],
    "sg:phone":"+1 952 942 8199",
    "sg:postcode":"55344",
    "sg:province":"MN",
    "sg:tags":[
        "veterinarian"
    ],
    "sg:website":"www.banfield.net",
    "wof:name":"Banfield The Pet Hospital",
    "wof:placetype":"venue"
},
  "geometry": {"coordinates":[-93.418814,44.854061],"type":"Point"}
}