{
  "type": "Feature",
  "properties": {
    "addr:full":"1175 Reding Ave Red Wing MN 55066",
    "addr:housenumber":"1175",
    "addr:postcode":"55066",
    "addr:street":"Reding Ave",
    "iso:country":"US",
    "sg:address":"1175 Reding Ave",
    "sg:city":"Red Wing",
    "sg:classifiers":[
        {
            "category":"Manufacturing",
            "subcategory":"Printing",
            "type":"Manufacturing & Wholesale Goods"
        }
    ],
    "sg:phone":"+1 651 388 8972",
    "sg:postcode":"55066",
    "sg:province":"MN",
    "sg:tags":[
        "cards",
        "greeting"
    ],
    "wof:name":"Words 'N' Such",
    "wof:placetype":"venue"
},
  "geometry": {"coordinates":[-92.61382999999999,44.55555],"type":"Point"}
}