{
  "type": "Feature",
  "properties": {
    "addr:full":"11441 Rupp Dr Burnsville MN 55337",
    "addr:housenumber":"11441",
    "addr:postcode":"55337",
    "addr:street":"Rupp Dr",
    "iso:country":"US",
    "sg:address":"11441 Rupp Dr",
    "sg:city":"Burnsville",
    "sg:classifiers":[
        {
            "category":"Professional",
            "subcategory":"Engineering",
            "type":"Services"
        },
        {
            "category":"Wholesale",
            "subcategory":"Electrical",
            "type":"Manufacturing & Wholesale Goods"
        }
    ],
    "sg:phone":"+1 952 894 9228",
    "sg:postcode":"55337",
    "sg:province":"MN",
    "sg:tags":[
        "consulting",
        "assembler",
        "contract",
        "part",
        "electronic",
        "engineer"
    ],
    "sg:website":"http://www.analog-tech.com",
    "wof:name":"Analog Technologies, Corp.",
    "wof:placetype":"venue"
},
  "geometry": {"coordinates":[-93.255669,44.796071],"type":"Point"}
}