{
  "type": "Feature",
  "properties": {
    "addr:full":"3758 Nicollet Ave Minneapolis MN 55409",
    "addr:housenumber":"3758",
    "addr:postcode":"55409",
    "addr:street":"Nicollet Ave",
    "iso:country":"US",
    "sg:address":"3758 Nicollet Ave",
    "sg:city":"Minneapolis",
    "sg:classifiers":[
        {
            "category":"Restaurant",
            "type":"Food & Drink"
        }
    ],
    "sg:phone":"+1 612 821 0041",
    "sg:postcode":"55409",
    "sg:province":"MN",
    "wof:name":"Nardies Enterprise",
    "wof:placetype":"venue"
},
  "geometry": {"coordinates":[-93.277986,44.935165],"type":"Point"}
}