{
  "type": "Feature",
  "properties": {
    "iso:country":"US",
    "sg:address":"102 8th St",
    "sg:city":"Walker",
    "sg:classifiers":[
        {
            "category":"Retail",
            "subcategory":"Portrait Studio",
            "type":"Services"
        }
    ],
    "sg:phone":"+1 218 547 2922",
    "sg:postcode":"56484",
    "sg:province":"MN",
    "sg:tags":[
        "photo"
    ],
    "wof:name":"G M T Photo",
    "wof:placetype":"venue"
},
  "geometry": {"coordinates":[-94.587035,47.102478],"type":"Point"}
}