{
  "type": "Feature",
  "properties": {
    "iso:country":"US",
    "sg:address":"11300 Hampshire Ave S",
    "sg:city":"Bloomington",
    "sg:classifiers":[
        {
            "category":"Professional",
            "subcategory":"Business Services",
            "type":"Services"
        }
    ],
    "sg:phone":"+1 952 942 6880",
    "sg:postcode":"55438",
    "sg:province":"MN",
    "sg:tags":[
        "record",
        "document"
    ],
    "wof:name":"Iron Mountain Secure Shredding",
    "wof:placetype":"venue"
},
  "geometry": {"coordinates":[-93.36894100000001,44.80083],"type":"Point"}
}