{
  "type": "Feature",
  "properties": {
    "iso:country":"US",
    "sg:address":"507 N Nokomis St",
    "sg:city":"Alexandria",
    "sg:classifiers":[
        {
            "category":"Insurance",
            "subcategory":"Title Insurance",
            "type":"Services"
        }
    ],
    "sg:phone":"+1 320 762 5003",
    "sg:postcode":"56308",
    "sg:province":"MN",
    "wof:name":"Aspen Title Of Alexandria LLC",
    "wof:placetype":"venue"
},
  "geometry": {"coordinates":[-95.36663299999999,45.895716],"type":"Point"}
}