{
  "type": "Feature",
  "properties": {
    "addr:full":"2514 Maple Ave Slayton MN 56172",
    "addr:housenumber":"2514",
    "addr:postcode":"56172",
    "addr:street":"Maple Ave",
    "iso:country":"US",
    "sg:address":"2514 Maple Ave",
    "sg:city":"Slayton",
    "sg:classifiers":[
        {
            "category":"Banks & Credit Unions",
            "subcategory":"Investment Brokerage",
            "type":"Services"
        }
    ],
    "sg:phone":"+1 507 836 8531",
    "sg:postcode":"56172",
    "sg:province":"MN",
    "sg:tags":[
        "commodity"
    ],
    "wof:name":"Collins Commodity Svc",
    "wof:placetype":"venue"
},
  "geometry": {"coordinates":[-95.753485,43.988831],"type":"Point"}
}