{
  "type": "Feature",
  "properties": {
    "iso:country":"US",
    "sg:address":"2965 E Alger Grade",
    "sg:city":"Two Harbors",
    "sg:classifiers":[
        {
            "category":"Professional",
            "type":"Services"
        }
    ],
    "sg:phone":"+1 218 834 4471",
    "sg:postcode":"55616",
    "sg:province":"MN",
    "sg:tags":[
        "establishment"
    ],
    "wof:name":"Weber's",
    "wof:placetype":"venue"
},
  "geometry": {"coordinates":[-91.61827,47.146517],"type":"Point"}
}