{
  "type": "Feature",
  "properties": {
    "addr:full":"701 4th Ave S Ste 500 Minneapolis MN 55415",
    "addr:housenumber":"701",
    "addr:postcode":"55415",
    "addr:street":"4Th Ave S Ste 500",
    "iso:country":"US",
    "sg:address":"701 4th Ave S Ste 500",
    "sg:city":"Minneapolis",
    "sg:classifiers":[
        {
            "category":"Professional",
            "subcategory":"Lawyer & Legal Services",
            "type":"Services"
        }
    ],
    "sg:phone":"+1 612 337 9543",
    "sg:postcode":"55415",
    "sg:province":"MN",
    "sg:tags":[
        "information",
        "attorney",
        "referral"
    ],
    "wof:name":"Faris & Faris",
    "wof:placetype":"venue"
},
  "geometry": {"coordinates":[-93.266785,44.974606],"type":"Point"}
}