{
  "type": "Feature",
  "properties": {
    "addr:full":"15557 Quincy Rd NE Dover MN 55929",
    "addr:housenumber":"15557",
    "addr:postcode":"55929",
    "addr:street":"Quincy Rd Ne",
    "iso:country":"US",
    "sg:address":"15557 Quincy Rd NE",
    "sg:city":"Dover",
    "sg:classifiers":[
        {
            "category":"Building & Trades",
            "subcategory":"Landscaping Services",
            "type":"Services"
        }
    ],
    "sg:phone":"+1 507 932 3559",
    "sg:postcode":"55929",
    "sg:province":"MN",
    "sg:tags":[
        "lawn",
        "maintenance"
    ],
    "wof:name":"Lawn Leprechaun Lawn Care",
    "wof:placetype":"venue"
},
  "geometry": {"coordinates":[-92.168272,44.021383],"type":"Point"}
}