{
  "type": "Feature",
  "properties": {
    "addr:full":"4561 182nd St South Haven MN 55382",
    "addr:housenumber":"4561",
    "addr:postcode":"55382",
    "addr:street":"182Nd St;Haven",
    "iso:country":"US",
    "sg:address":"4561 182nd St",
    "sg:city":"South Haven",
    "sg:classifiers":[
        {
            "category":"Farming",
            "subcategory":"Dairy Farm",
            "type":"Manufacturing & Wholesale Goods"
        }
    ],
    "sg:phone":"+1 320 251 3425",
    "sg:postcode":"55382",
    "sg:province":"MN",
    "wof:name":"L Rose",
    "wof:placetype":"venue"
},
  "geometry": {"coordinates":[-94.20533500000001,45.388115],"type":"Point"}
}