{
  "type": "Feature",
  "properties": {
    "iso:country":"US",
    "sg:address":"775 Robert St S",
    "sg:city":"Saint Paul",
    "sg:classifiers":[
        {
            "category":"Building & Trades",
            "subcategory":"Plumbing",
            "type":"Services"
        }
    ],
    "sg:phone":"+1 651 224 7441",
    "sg:postcode":"55107",
    "sg:province":"MN",
    "sg:tags":[
        "plumbing",
        "heating",
        "contractor"
    ],
    "wof:name":"R & S Home Improvements",
    "wof:placetype":"venue"
},
  "geometry": {"coordinates":[-93.080782,44.922464],"type":"Point"}
}