{
  "type": "Feature",
  "properties": {
    "iso:country":"US",
    "sg:address":"5679 40th St SW",
    "sg:city":"Waverly",
    "sg:classifiers":[
        {
            "category":"Farming",
            "subcategory":"Dairy Farm",
            "type":"Manufacturing & Wholesale Goods"
        }
    ],
    "sg:phone":"+1 763 658 4376",
    "sg:postcode":"55390",
    "sg:province":"MN",
    "wof:name":"Dale Sawatzke",
    "wof:placetype":"venue"
},
  "geometry": {"coordinates":[-94.00660499999999,45.094364],"type":"Point"}
}