{
  "type": "Feature",
  "properties": {
    "iso:country":"US",
    "sg:address":"925 US Hwy 169",
    "sg:city":"Plymouth",
    "sg:classifiers":[
        {
            "category":"Wholesale",
            "subcategory":"Furniture",
            "type":"Manufacturing & Wholesale Goods"
        }
    ],
    "sg:phone":"+1 763 971 8737",
    "sg:postcode":"55441",
    "sg:province":"MN",
    "sg:website":"www.colmn.com",
    "wof:name":"Office Liquidators",
    "wof:placetype":"venue"
},
  "geometry": {"coordinates":[-93.400662,44.972671],"type":"Point"}
}