{
  "type": "Feature",
  "properties": {
    "iso:country":"US",
    "sg:address":"2626 E 82nd St",
    "sg:city":"Minneapolis",
    "sg:classifiers":[
        {
            "category":"Professional",
            "subcategory":"Business Services",
            "type":"Services"
        }
    ],
    "sg:phone":"+1 952 858 8319",
    "sg:postcode":"55425",
    "sg:province":"MN",
    "sg:tags":[
        "inventory",
        "computing"
    ],
    "wof:name":"R G I S Inventory Specialists",
    "wof:placetype":"venue"
},
  "geometry": {"coordinates":[-93.232935,44.855192],"type":"Point"}
}