{
  "type": "Feature",
  "properties": {
    "addr:full":"5132 Gorgas Ave Minneapolis MN 55424",
    "addr:housenumber":"5132",
    "addr:postcode":"55424",
    "addr:street":"Gorgas Ave",
    "iso:country":"US",
    "sg:address":"5132 Gorgas Ave",
    "sg:city":"Minneapolis",
    "sg:classifiers":[
        {
            "category":"Building & Trades",
            "subcategory":"Plumbing",
            "type":"Services"
        }
    ],
    "sg:phone":"+1 952 922 8487",
    "sg:postcode":"55424",
    "sg:province":"MN",
    "sg:tags":[
        "plumber",
        "industrial",
        "contractors-commercial"
    ],
    "wof:name":"His Plumbing Co, Inc",
    "wof:placetype":"venue"
},
  "geometry": {"coordinates":[-93.330298,44.910233],"type":"Point"}
}