{
  "type": "Feature",
  "properties": {
    "iso:country":"US",
    "sg:address":"2940 Pillsbury Ave S",
    "sg:city":"Minneapolis",
    "sg:classifiers":[
        {
            "category":"Banks & Credit Unions",
            "subcategory":"Bank",
            "type":"Services"
        }
    ],
    "sg:phone":"+1 612 825 8488",
    "sg:postcode":"55408",
    "sg:province":"MN",
    "sg:tags":[
        "money",
        "transfer"
    ],
    "wof:name":"Tawkal Money Express",
    "wof:placetype":"venue"
},
  "geometry": {"coordinates":[-93.281436,44.948649],"type":"Point"}
}