{
  "type": "Feature",
  "properties": {
    "iso:country":"US",
    "sg:address":"507 12th St NE",
    "sg:city":"New Prague",
    "sg:classifiers":[
        {
            "category":"Government",
            "subcategory":"Office",
            "type":"Public Place"
        }
    ],
    "sg:phone":"+1 952 758 3124",
    "sg:postcode":"56071",
    "sg:province":"MN",
    "sg:tags":[
        "village"
    ],
    "wof:name":"New Prague Street Commissioner",
    "wof:placetype":"venue"
},
  "geometry": {"coordinates":[-93.56753999999999,44.558147],"type":"Point"}
}