{
  "type": "Feature",
  "properties": {
    "addr:full":"400 Marquette Ave Minneapolis MN 55401",
    "addr:housenumber":"400",
    "addr:postcode":"55401",
    "addr:street":"Marquette Ave",
    "iso:country":"US",
    "sg:address":"400 Marquette Ave",
    "sg:city":"Minneapolis",
    "sg:classifiers":[
        {
            "category":"Parking",
            "type":"Transportation"
        }
    ],
    "sg:phone":"+1 612 376 7805",
    "sg:postcode":"55401",
    "sg:province":"MN",
    "wof:name":"Allied Parking Inc",
    "wof:placetype":"venue"
},
  "geometry": {"coordinates":[-93.26853800000001,44.979289],"type":"Point"}
}