{
  "type": "Feature",
  "properties": {
    "iso:country":"US",
    "sg:address":"2076 E Flanders Rd",
    "sg:city":"St Paul",
    "sg:classifiers":[
        {
            "category":"Retail",
            "subcategory":"Laundry & Dry Cleaning",
            "type":"Services"
        }
    ],
    "sg:phone":"+1 651 777 1100",
    "sg:postcode":"55109",
    "sg:province":"MN",
    "sg:tags":[
        "cleaners",
        "rug",
        "carpet"
    ],
    "wof:name":"Classic Care Carpet",
    "wof:placetype":"venue"
},
  "geometry": {"coordinates":[-93.01232400000001,45.015954],"type":"Point"}
}