{
  "type": "Feature",
  "properties": {
    "addr:full":"22503 Independence Ave Morristown MN 55052",
    "addr:housenumber":"22503",
    "addr:postcode":"55052",
    "addr:street":"Independence Ave",
    "iso:country":"US",
    "sg:address":"22503 Independence Ave",
    "sg:city":"Morristown",
    "sg:classifiers":[
        {
            "category":"Farming",
            "subcategory":"Farm & Veterinary Services",
            "type":"Manufacturing & Wholesale Goods"
        }
    ],
    "sg:phone":"+1 507 685 4260",
    "sg:postcode":"55052",
    "sg:province":"MN",
    "sg:tags":[
        "breeder",
        "livestock"
    ],
    "wof:name":"Johnson SLJ Valley Angus",
    "wof:placetype":"venue"
},
  "geometry": {"coordinates":[-93.443844,44.261382],"type":"Point"}
}