{
  "type": "Feature",
  "properties": {
    "addr:full":"8420 Excelsior Blvd Hopkins MN 55343",
    "addr:housenumber":"8420",
    "addr:postcode":"55343",
    "addr:street":"Excelsior Blvd",
    "iso:country":"US",
    "sg:address":"8420 Excelsior Blvd",
    "sg:city":"Hopkins",
    "sg:classifiers":[
        {
            "category":"Retail",
            "subcategory":"Laundry & Dry Cleaning",
            "type":"Services"
        }
    ],
    "sg:phone":"+1 952 935 4806",
    "sg:postcode":"55343",
    "sg:province":"MN",
    "sg:tags":[
        "cleaner",
        "commercial"
    ],
    "wof:name":"Blake Cleaners",
    "wof:placetype":"venue"
},
  "geometry": {"coordinates":[-93.386308,44.92572],"type":"Point"}
}