{
  "type": "Feature",
  "properties": {
    "addr:full":"805 Forest Ave W Mora MN 55051",
    "addr:housenumber":"805",
    "addr:postcode":"55051",
    "addr:street":"Forest Ave W Mora",
    "iso:country":"US",
    "sg:address":"805 Forest Ave W",
    "sg:city":"Mora",
    "sg:classifiers":[
        {
            "category":"Museum",
            "type":"Entertainment"
        }
    ],
    "sg:phone":"+1 320 679 1665",
    "sg:postcode":"55051",
    "sg:province":"MN",
    "wof:name":"Kanabec History Ctr",
    "wof:placetype":"venue"
},
  "geometry": {"coordinates":[-93.305553,45.875074],"type":"Point"}
}