{
  "type": "Feature",
  "properties": {
    "iso:country":"US",
    "sg:address":"401 2nd St NW",
    "sg:city":"Hinckley",
    "sg:classifiers":[
        {
            "category":"Retail",
            "subcategory":"Auto Repair",
            "type":"Services"
        }
    ],
    "sg:phone":"+1 320 384 6307",
    "sg:postcode":"55037",
    "sg:province":"MN",
    "sg:tags":[
        "automotive"
    ],
    "wof:name":"D C Auto Electric",
    "wof:placetype":"venue"
},
  "geometry": {"coordinates":[-92.95142,46.018356],"type":"Point"}
}