{
  "type": "Feature",
  "properties": {
    "iso:country":"US",
    "sg:address":"3101 84th Ln NE",
    "sg:city":"Minneapolis",
    "sg:classifiers":[
        {
            "category":"Building & Trades",
            "subcategory":"Construction",
            "type":"Services"
        }
    ],
    "sg:phone":"+1 763 783 3663",
    "sg:postcode":"55449",
    "sg:province":"MN",
    "sg:tags":[
        "water",
        "remodeling",
        "stucco",
        "infiltration"
    ],
    "wof:name":"Greg Zimmerman Stucco Inc",
    "wof:placetype":"venue"
},
  "geometry": {"coordinates":[-93.19530399999999,45.123434],"type":"Point"}
}