{
  "type": "Feature",
  "properties": {
    "iso:country":"US",
    "sg:address":"24938 Hazelwood Dr",
    "sg:city":"Nisswa",
    "sg:classifiers":[
        {
            "category":"Building & Trades",
            "subcategory":"Construction",
            "type":"Services"
        }
    ],
    "sg:phone":"+1 218 963 0203",
    "sg:postcode":"56468",
    "sg:province":"MN",
    "sg:tags":[
        "roofing",
        "industrial",
        "contractors-commercial",
        "contractor"
    ],
    "wof:name":"Hanson Roofing & Construction",
    "wof:placetype":"venue"
},
  "geometry": {"coordinates":[-94.288892,46.512454],"type":"Point"}
}