{
  "type": "Feature",
  "properties": {
    "iso:country":"US",
    "sg:address":"1340 Mendota Heights Rd",
    "sg:city":"Mendota Heights",
    "sg:classifiers":[
        {
            "category":"Wholesale",
            "subcategory":"Computers",
            "type":"Manufacturing & Wholesale Goods"
        },
        {
            "category":"Professional",
            "subcategory":"Computer Services",
            "type":"Services"
        }
    ],
    "sg:phone":"+1 651 605 9000",
    "sg:postcode":"55120",
    "sg:province":"MN",
    "sg:tags":[
        "design",
        "engineering",
        "electrical",
        "system"
    ],
    "wof:name":"Cray Inc",
    "wof:placetype":"venue"
},
  "geometry": {"coordinates":[-93.16656399999999,44.865461],"type":"Point"}
}