{
  "type": "Feature",
  "properties": {
    "iso:country":"US",
    "sg:address":"225 W 1st St",
    "sg:city":"Waconia",
    "sg:classifiers":[
        {
            "category":"Autos & Motor Vehicles",
            "subcategory":"Auto Supplies",
            "type":"Retail Goods"
        }
    ],
    "sg:phone":"+1 952 442 4434",
    "sg:postcode":"55387",
    "sg:province":"MN",
    "sg:tags":[
        "automobile",
        "parts"
    ],
    "wof:name":"Napa Parts Of Waconia",
    "wof:placetype":"venue"
},
  "geometry": {"coordinates":[-93.790401,44.849278],"type":"Point"}
}