{
  "type": "Feature",
  "properties": {
    "addr:full":"32246 Co Hwy 74 Underwood MN 56586",
    "addr:housenumber":"32246",
    "addr:postcode":"56586",
    "addr:street":"Co Hwy 74",
    "iso:country":"US",
    "sg:address":"32246 Co Hwy 74",
    "sg:city":"Underwood",
    "sg:phone":"+1 218 495 3454",
    "sg:postcode":"56586",
    "sg:province":"MN",
    "sg:tags":[
        "farm",
        "soybean"
    ],
    "wof:name":"George Iverson",
    "wof:placetype":"venue"
},
  "geometry": {"coordinates":[-95.816971,46.412237],"type":"Point"}
}