{
  "type": "Feature",
  "properties": {
    "addr:full":"855 Pleasantview Rd Chanhassen MN 55317",
    "addr:housenumber":"855",
    "addr:postcode":"55317",
    "addr:street":"Pleasantview Rd",
    "iso:country":"US",
    "sg:address":"855 Pleasantview Rd",
    "sg:city":"Chanhassen",
    "sg:classifiers":[
        {
            "category":"Recreation",
            "type":"Entertainment"
        }
    ],
    "sg:phone":"+1 952 474 7001",
    "sg:postcode":"55317",
    "sg:province":"MN",
    "sg:tags":[
        "charter",
        "boat"
    ],
    "sg:website":"www.customchartercruises.com",
    "wof:name":"Custom Charters-Lk Minnetonka",
    "wof:placetype":"venue"
},
  "geometry": {"coordinates":[-93.54274700000001,44.888071],"type":"Point"}
}