{
  "type": "Feature",
  "properties": {
    "addr:full":"20829 State Hwy 15 Hutchinson MN 55350",
    "addr:housenumber":"20829",
    "addr:postcode":"55350",
    "addr:street":"State Hwy 15",
    "iso:country":"US",
    "sg:address":"20829 State Hwy 15",
    "sg:city":"Hutchinson",
    "sg:classifiers":[
        {
            "category":"Building & Trades",
            "subcategory":"Construction",
            "type":"Services"
        }
    ],
    "sg:phone":"+1 320 587 5496",
    "sg:postcode":"55350",
    "sg:province":"MN",
    "sg:tags":[
        "well",
        "drilling"
    ],
    "wof:name":"Le Roy Barrick Well Drilling",
    "wof:placetype":"venue"
},
  "geometry": {"coordinates":[-94.36744,44.922026],"type":"Point"}
}