{
  "type": "Feature",
  "properties": {
    "iso:country":"US",
    "sg:address":"359 Hoover St NE",
    "sg:city":"Minneapolis",
    "sg:classifiers":[
        {
            "category":"Personal",
            "type":"Services"
        }
    ],
    "sg:phone":"+1 612 721 6645",
    "sg:postcode":"55413",
    "sg:province":"MN",
    "sg:tags":[
        "towing"
    ],
    "wof:name":"Cedar Towing & Garage Service",
    "wof:placetype":"venue"
},
  "geometry": {"coordinates":[-93.21779600000001,44.993099],"type":"Point"}
}