{
  "type": "Feature",
  "properties": {
    "iso:country":"US",
    "sg:address":"25679 State Hwy 91",
    "sg:city":"Adrian",
    "sg:phone":"+1 507 483 2286",
    "sg:postcode":"56110",
    "sg:province":"MN",
    "sg:tags":[
        "hog",
        "farm",
        "corn",
        "soybean",
        "or",
        "feedlot"
    ],
    "wof:name":"Jerald Roemeling",
    "wof:placetype":"venue"
},
  "geometry": {"coordinates":[-95.933387,43.623773],"type":"Point"}
}