{
  "type": "Feature",
  "properties": {
    "addr:full":"7870 Park Dr Chanhassen MN 55317",
    "addr:housenumber":"7870",
    "addr:postcode":"55317",
    "addr:street":"Park Dr",
    "iso:country":"US",
    "sg:address":"7870 Park Dr",
    "sg:city":"Chanhassen",
    "sg:classifiers":[
        {
            "category":"Manufacturing",
            "subcategory":"Electronics",
            "type":"Manufacturing & Wholesale Goods"
        }
    ],
    "sg:phone":"+1 952 474 6200",
    "sg:postcode":"55317",
    "sg:province":"MN",
    "sg:tags":[
        "industrial",
        "driver",
        "semiconductor",
        "controller",
        "device",
        "manufacturer"
    ],
    "sg:website":"http://www.scrcontroller.com",
    "wof:name":"Control Concepts Inc.",
    "wof:placetype":"venue"
},
  "geometry": {"coordinates":[-93.555423,44.860661],"type":"Point"}
}