{
  "type": "Feature",
  "properties": {
    "addr:full":"806 Center St Mankato MN 56003",
    "addr:housenumber":"806",
    "addr:postcode":"56003",
    "addr:street":"Center St",
    "iso:country":"US",
    "sg:address":"806 Center St",
    "sg:city":"Mankato",
    "sg:classifiers":[
        {
            "category":"Organizations",
            "subcategory":"Professional Association",
            "type":"Services"
        }
    ],
    "sg:phone":"+1 507 388 6529",
    "sg:postcode":"56003",
    "sg:province":"MN",
    "wof:name":"Zonta International",
    "wof:placetype":"venue"
},
  "geometry": {"coordinates":[-94.01357,44.176111],"type":"Point"}
}