{
  "type": "Feature",
  "properties": {
    "addr:full":"12034 110th St Leota MN 56153",
    "addr:housenumber":"12034",
    "addr:postcode":"56153",
    "addr:street":"110Th St",
    "iso:country":"US",
    "sg:address":"12034 110th St",
    "sg:city":"Leota",
    "sg:classifiers":[
        {
            "category":"Education",
            "subcategory":"School",
            "type":"Public Place"
        }
    ],
    "sg:phone":"+1 507 443 5501",
    "sg:postcode":"56153",
    "sg:province":"MN",
    "wof:name":"Leota Christian Elementary",
    "wof:placetype":"venue"
},
  "geometry": {"coordinates":[-96.007282,43.834039],"type":"Point"}
}