{
  "type": "Feature",
  "properties": {
    "addr:full":"41 Birch St E Trimont MN 56176",
    "addr:housenumber":"41",
    "addr:postcode":"56176",
    "addr:street":"Birch St E Trimont",
    "iso:country":"US",
    "sg:address":"41 Birch St E",
    "sg:city":"Trimont",
    "sg:classifiers":[
        {
            "category":"Farming",
            "subcategory":"Nursery",
            "type":"Manufacturing & Wholesale Goods"
        }
    ],
    "sg:phone":"+1 507 639 6341",
    "sg:postcode":"56176",
    "sg:province":"MN",
    "sg:tags":[
        "greenhouse"
    ],
    "wof:name":"Trimont Greenhouse & Floral",
    "wof:placetype":"venue"
},
  "geometry": {"coordinates":[-94.714037,43.759964],"type":"Point"}
}