{
  "type": "Feature",
  "properties": {
    "iso:country":"US",
    "sg:address":"2626 W Lake St",
    "sg:city":"Minneapolis",
    "sg:classifiers":[
        {
            "category":"Wholesale",
            "subcategory":"Vending Machines",
            "type":"Manufacturing & Wholesale Goods"
        }
    ],
    "sg:phone":"+1 612 928 9037",
    "sg:postcode":"55408",
    "sg:province":"MN",
    "sg:website":"www.weisman.com",
    "wof:name":"Weisman Enterprises Inc",
    "wof:placetype":"venue"
},
  "geometry": {"coordinates":[-93.30709299999999,44.949376],"type":"Point"}
}