{
  "type": "Feature",
  "properties": {
    "addr:full":"211 2nd St NW Rochester MN 55901",
    "addr:housenumber":"211",
    "addr:postcode":"55901",
    "addr:street":"2Nd St Nw",
    "iso:country":"US",
    "sg:address":"211 2nd St NW",
    "sg:city":"Rochester",
    "sg:classifiers":[
        {
            "category":"Health Services",
            "subcategory":"Doctor",
            "type":"Services"
        }
    ],
    "sg:phone":"+1 507 282 1774",
    "sg:postcode":"55901",
    "sg:province":"MN",
    "sg:tags":[
        "physician",
        "surgeon"
    ],
    "wof:name":"G R Diessner MD",
    "wof:placetype":"venue"
},
  "geometry": {"coordinates":[-92.467201,44.025414],"type":"Point"}
}