{
  "type": "Feature",
  "properties": {
    "addr:full":"580 Arrowhead Ln Moose Lake MN 55767",
    "addr:housenumber":"580",
    "addr:postcode":"55767",
    "addr:street":"Arrowhead Ln",
    "iso:country":"US",
    "sg:address":"580 Arrowhead Ln",
    "sg:city":"Moose Lake",
    "sg:classifiers":[
        {
            "category":"Wholesale",
            "subcategory":"Farm Supplies",
            "type":"Manufacturing & Wholesale Goods"
        }
    ],
    "sg:phone":"+1 218 485 4111",
    "sg:postcode":"55767",
    "sg:province":"MN",
    "sg:tags":[
        "feed"
    ],
    "wof:name":"Moose Lake Cooperative Assn",
    "wof:placetype":"venue"
},
  "geometry": {"coordinates":[-92.758822,46.456313],"type":"Point"}
}