{
  "type": "Feature",
  "properties": {
    "addr:full":"1505 Grand Ave Saint Paul MN 55105",
    "addr:housenumber":"1505",
    "addr:postcode":"55105",
    "addr:street":"Grand Ave",
    "iso:country":"US",
    "sg:address":"1505 Grand Ave",
    "sg:city":"Saint Paul",
    "sg:classifiers":[
        {
            "category":"Health Services",
            "subcategory":"Health Practitioner",
            "type":"Services"
        }
    ],
    "sg:phone":"+1 651 690 5530",
    "sg:postcode":"55105",
    "sg:province":"MN",
    "wof:name":"Stillwater Acupuncture",
    "wof:placetype":"venue"
},
  "geometry": {"coordinates":[-93.16307,44.940122],"type":"Point"}
}