{
  "type": "Feature",
  "properties": {
    "iso:country":"US",
    "sg:address":"619 E Main St",
    "sg:city":"Pipestone",
    "sg:classifiers":[
        {
            "category":"Autos & Motor Vehicles",
            "subcategory":"Auto Supplies",
            "type":"Retail Goods"
        },
        {
            "category":"Retail",
            "subcategory":"Auto Repair",
            "type":"Services"
        }
    ],
    "sg:phone":"+1 507 825 3396",
    "sg:postcode":"56164",
    "sg:province":"MN",
    "sg:tags":[
        "shop",
        "automobile",
        "accessory",
        "machine",
        "parts",
        "accessories-wholesale",
        "part",
        "manufacturer"
    ],
    "wof:name":"Sturdevant Auto Parts",
    "wof:placetype":"venue"
},
  "geometry": {"coordinates":[-96.310371,44.000526],"type":"Point"}
}