{
  "type": "Feature",
  "properties": {
    "addr:full":"995 Minnehaha Ave E Saint Paul MN 55106",
    "addr:housenumber":"995",
    "addr:postcode":"55106",
    "addr:street":"Minnehaha Ave E",
    "iso:country":"US",
    "sg:address":"995 Minnehaha Ave E",
    "sg:city":"Saint Paul",
    "sg:classifiers":[
        {
            "category":"Social Services",
            "subcategory":"Child Care",
            "type":"Services"
        }
    ],
    "sg:phone":"+1 651 771 3393",
    "sg:postcode":"55106",
    "sg:province":"MN",
    "sg:tags":[
        "daycare",
        "provider"
    ],
    "wof:name":"Sharon Huff",
    "wof:placetype":"venue"
},
  "geometry": {"coordinates":[-93.060151,44.963121],"type":"Point"}
}