{
  "type": "Feature",
  "properties": {
    "iso:country":"US",
    "sg:address":"3007 16th St NW",
    "sg:city":"St Paul",
    "sg:classifiers":[
        {
            "category":"Manufacturing",
            "subcategory":"Printing",
            "type":"Manufacturing & Wholesale Goods"
        }
    ],
    "sg:phone":"+1 651 633 6690",
    "sg:postcode":"55112",
    "sg:province":"MN",
    "sg:tags":[
        "book"
    ],
    "sg:website":"www.regnig.com",
    "wof:name":"Regnig Mountain Press",
    "wof:placetype":"venue"
},
  "geometry": {"coordinates":[-93.226009,45.075092],"type":"Point"}
}