{
  "type": "Feature",
  "properties": {
    "addr:full":"54852 200th St Mankato MN 56001",
    "addr:housenumber":"54852",
    "addr:postcode":"56001",
    "addr:street":"200Th St",
    "iso:country":"US",
    "sg:address":"54852 200th St",
    "sg:city":"Mankato",
    "sg:classifiers":[
        {
            "category":"Transit Center",
            "subcategory":"Freight",
            "type":"Transportation"
        },
        {
            "category":"Freight",
            "type":"Transportation"
        }
    ],
    "sg:phone":"+1 507 380 1919",
    "sg:postcode":"56001",
    "sg:province":"MN",
    "sg:tags":[
        "local",
        "trucking-motor",
        "trucking"
    ],
    "wof:name":"B E Trucking",
    "wof:placetype":"venue"
},
  "geometry": {"coordinates":[-94.082842,44.122981],"type":"Point"}
}