{
  "type": "Feature",
  "properties": {
    "addr:full":"32939 Overdale Rd Melrose MN 56352",
    "addr:housenumber":"32939",
    "addr:postcode":"56352",
    "addr:street":"Overdale Rd",
    "iso:country":"US",
    "sg:address":"32939 Overdale Rd",
    "sg:city":"Melrose",
    "sg:classifiers":[
        {
            "category":"Farming",
            "subcategory":"Dairy Farm",
            "type":"Manufacturing & Wholesale Goods"
        }
    ],
    "sg:phone":"+1 320 987 3147",
    "sg:postcode":"56352",
    "sg:province":"MN",
    "wof:name":"Dan Hopfer Farm",
    "wof:placetype":"venue"
},
  "geometry": {"coordinates":[-94.78824400000001,45.596984],"type":"Point"}
}