{
  "type": "Feature",
  "properties": {
    "iso:country":"US",
    "sg:address":"815 Pine St",
    "sg:city":"Crosby",
    "sg:classifiers":[
        {
            "category":"Wholesale",
            "subcategory":"Auto Parts",
            "type":"Manufacturing & Wholesale Goods"
        }
    ],
    "sg:phone":"+1 218 545 1881",
    "sg:postcode":"56441",
    "sg:province":"MN",
    "sg:tags":[
        "equipment",
        "truck"
    ],
    "wof:name":"Pat Noble",
    "wof:placetype":"venue"
},
  "geometry": {"coordinates":[-93.970387,46.475297],"type":"Point"}
}