{
  "type": "Feature",
  "properties": {
    "iso:country":"US",
    "sg:address":"3920 Cedar Shore Dr",
    "sg:city":"Minneapolis",
    "sg:classifiers":[
        {
            "category":"Professional",
            "subcategory":"Business Services",
            "type":"Services"
        }
    ],
    "sg:phone":"+1 952 922 0511",
    "sg:postcode":"55416",
    "sg:province":"MN",
    "wof:name":"Bb Granite Design",
    "wof:placetype":"venue"
},
  "geometry": {"coordinates":[-93.330089,44.956617],"type":"Point"}
}