{
  "type": "Feature",
  "properties": {
    "addr:full":"15213 Crystal Dr E Burnsville MN 55306",
    "addr:housenumber":"15213",
    "addr:postcode":"55306",
    "addr:street":"Crystal Dr E",
    "iso:country":"US",
    "sg:address":"15213 Crystal Dr E",
    "sg:city":"Burnsville",
    "sg:classifiers":[
        {
            "category":"Professional",
            "subcategory":"Accounting & Tax Preparation",
            "type":"Services"
        }
    ],
    "sg:phone":"+1 952 898 5044",
    "sg:postcode":"55306",
    "sg:province":"MN",
    "wof:name":"Associates Financial Group",
    "wof:placetype":"venue"
},
  "geometry": {"coordinates":[-93.265804,44.725866],"type":"Point"}
}