{
  "type": "Feature",
  "properties": {
    "iso:country":"US",
    "sg:address":"13137 Crooked Lake Blvd NW",
    "sg:city":"Coon Rapids",
    "sg:classifiers":[
        {
            "category":"Insurance",
            "subcategory":"Insurance Agent",
            "type":"Services"
        }
    ],
    "sg:phone":"+1 763 862 7791",
    "sg:postcode":"55448",
    "sg:province":"MN",
    "wof:name":"American Interstate Insurance",
    "wof:placetype":"venue"
},
  "geometry": {"coordinates":[-93.33721799999999,45.211178],"type":"Point"}
}