{
  "type": "Feature",
  "properties": {
    "addr:full":"2752 195th Ave Mora MN 55051",
    "addr:housenumber":"2752",
    "addr:postcode":"55051",
    "addr:street":"195Th Ave",
    "iso:country":"US",
    "sg:address":"2752 195th Ave",
    "sg:city":"Mora",
    "sg:classifiers":[
        {
            "category":"Shopping",
            "subcategory":"Musical Instruments",
            "type":"Retail Goods"
        }
    ],
    "sg:phone":"+1 320 679 4466",
    "sg:postcode":"55051",
    "sg:province":"MN",
    "wof:name":"Marks Music",
    "wof:placetype":"venue"
},
  "geometry": {"coordinates":[-93.14748899999999,45.868049],"type":"Point"}
}