{
  "type": "Feature",
  "properties": {
    "iso:country":"US",
    "sg:address":"873 Goodrich Ave",
    "sg:city":"Saint Paul",
    "sg:classifiers":[
        {
            "category":"Personal",
            "type":"Services"
        }
    ],
    "sg:phone":"+1 651 227 7145",
    "sg:postcode":"55105",
    "sg:province":"MN",
    "wof:name":"Christine Otteson",
    "wof:placetype":"venue"
},
  "geometry": {"coordinates":[-93.138577,44.937898],"type":"Point"}
}