{
  "type": "Feature",
  "properties": {
    "iso:country":"US",
    "sg:address":"3709 41st Ave S",
    "sg:city":"Minneapolis",
    "sg:classifiers":[
        {
            "category":"Building & Trades",
            "subcategory":"Cleaning & Sanitation",
            "type":"Services"
        }
    ],
    "sg:phone":"+1 612 747 5867",
    "sg:postcode":"55406",
    "sg:province":"MN",
    "sg:tags":[
        "maintenance"
    ],
    "wof:name":"Spruce Cleaning",
    "wof:placetype":"venue"
},
  "geometry": {"coordinates":[-93.213975,44.934383],"type":"Point"}
}