{
  "type": "Feature",
  "properties": {
    "addr:full":"5615 Manitou Rd Excelsior MN 55331",
    "addr:housenumber":"5615",
    "addr:postcode":"55331",
    "addr:street":"Manitou Rd",
    "iso:country":"US",
    "sg:address":"5615 Manitou Rd",
    "sg:city":"Excelsior",
    "sg:classifiers":[
        {
            "category":"Home & Garden",
            "subcategory":"Hardware",
            "type":"Retail Goods"
        }
    ],
    "sg:phone":"+1 952 474 6814",
    "sg:postcode":"55331",
    "sg:province":"MN",
    "wof:name":"Ace Hardware",
    "wof:placetype":"venue"
},
  "geometry": {"coordinates":[-93.589185,44.900792],"type":"Point"}
}