{
  "type": "Feature",
  "properties": {
    "addr:full":"700 10th St NW Saint Paul MN 55112",
    "addr:housenumber":"700",
    "addr:postcode":"55112",
    "addr:street":"10Th St Nw",
    "iso:country":"US",
    "sg:address":"700 10th St NW",
    "sg:city":"Saint Paul",
    "sg:classifiers":[
        {
            "category":"Retail",
            "subcategory":"Repair Shop",
            "type":"Services"
        }
    ],
    "sg:phone":"+1 651 633 6903",
    "sg:postcode":"55112",
    "sg:province":"MN",
    "wof:name":"A-Aarons Cleaning",
    "wof:placetype":"venue"
},
  "geometry": {"coordinates":[-93.1982,45.064634],"type":"Point"}
}