{
  "type": "Feature",
  "properties": {
    "iso:country":"US",
    "sg:address":"17638 Lyons St NE",
    "sg:city":"Forest Lake",
    "sg:classifiers":[
        {
            "category":"Building & Trades",
            "subcategory":"Construction",
            "type":"Services"
        }
    ],
    "sg:phone":"+1 651 464 2082",
    "sg:postcode":"55025",
    "sg:province":"MN",
    "sg:tags":[
        "excavating",
        "contractor"
    ],
    "wof:name":"Olson's Sewer Svc",
    "wof:placetype":"venue"
},
  "geometry": {"coordinates":[-93.019559,45.287439],"type":"Point"}
}