{
  "type": "Feature",
  "properties": {
    "iso:country":"US",
    "sg:address":"4125 22nd Ave NW",
    "sg:city":"Rochester",
    "sg:classifiers":[
        {
            "category":"Retail",
            "subcategory":"Auto Repair",
            "type":"Services"
        }
    ],
    "sg:phone":"+1 507 288 1604",
    "sg:postcode":"55901",
    "sg:province":"MN",
    "sg:tags":[
        "transmission",
        "automotive"
    ],
    "wof:name":"Kennedy Transmission Rochester",
    "wof:placetype":"venue"
},
  "geometry": {"coordinates":[-92.49754900000001,44.066588],"type":"Point"}
}