{
  "type": "Feature",
  "properties": {
    "addr:full":"522 E Howard St Hibbing MN 55746",
    "addr:housenumber":"522",
    "addr:postcode":"55746",
    "addr:street":"E Howard St",
    "iso:country":"US",
    "sg:address":"522 E Howard St",
    "sg:city":"Hibbing",
    "sg:classifiers":[
        {
            "category":"Utilities",
            "subcategory":"Telephone",
            "type":"Services"
        }
    ],
    "sg:phone":"+1 218 262 0001",
    "sg:postcode":"55746",
    "sg:province":"MN",
    "sg:tags":[
        "internet",
        "computer",
        "doe",
        "provider",
        "software"
    ],
    "wof:name":"Bridge The",
    "wof:placetype":"venue"
},
  "geometry": {"coordinates":[-92.936235,47.427419],"type":"Point"}
}