{
  "type": "Feature",
  "properties": {
    "iso:country":"US",
    "sg:address":"15913 Cascade Path",
    "sg:city":"Rosemount",
    "sg:classifiers":[
        {
            "category":"Professional",
            "type":"Services"
        }
    ],
    "sg:phone":"+1 651 423 2053",
    "sg:postcode":"55068",
    "sg:province":"MN",
    "wof:name":"Nowscapes Inc",
    "wof:placetype":"venue"
},
  "geometry": {"coordinates":[-93.142968,44.717737],"type":"Point"}
}