{
  "type": "Feature",
  "properties": {
    "addr:full":"5831 Cedar Lake Rd S Minneapolis MN 55416",
    "addr:housenumber":"5831",
    "addr:postcode":"55416",
    "addr:street":"Cedar Lake Rd",
    "iso:country":"US",
    "sg:address":"5831 Cedar Lake Rd S",
    "sg:city":"Minneapolis",
    "sg:classifiers":[
        {
            "category":"Insurance",
            "subcategory":"Insurance Agent",
            "type":"Services"
        }
    ],
    "sg:phone":"+1 952 525 2002",
    "sg:postcode":"55416",
    "sg:province":"MN",
    "sg:tags":[
        "business"
    ],
    "wof:name":"John Wally & Assoc",
    "wof:placetype":"venue"
},
  "geometry": {"coordinates":[-93.35534699999999,44.965602],"type":"Point"}
}