{
  "type": "Feature",
  "properties": {
    "iso:country":"US",
    "sg:address":"311 7th Ave SE",
    "sg:city":"Minneapolis",
    "sg:classifiers":[
        {
            "category":"Professional",
            "type":"Services"
        }
    ],
    "sg:phone":"+1 612 379 1009",
    "sg:postcode":"55414",
    "sg:province":"MN",
    "wof:name":"Yamada Studio",
    "wof:placetype":"venue"
},
  "geometry": {"coordinates":[-93.24561199999999,44.984291],"type":"Point"}
}