{
  "type": "Feature",
  "properties": {
    "addr:full":"10924 Chowen Ave S Minneapolis MN 55431",
    "addr:housenumber":"10924",
    "addr:postcode":"55431",
    "addr:street":"Chowen Ave S",
    "iso:country":"US",
    "sg:address":"10924 Chowen Ave S",
    "sg:city":"Minneapolis",
    "sg:classifiers":[
        {
            "category":"Building & Trades",
            "subcategory":"Construction",
            "type":"Services"
        }
    ],
    "sg:phone":"+1 952 888 9831",
    "sg:postcode":"55431",
    "sg:province":"MN",
    "sg:tags":[
        "house"
    ],
    "wof:name":"Niedfeldt Construction",
    "wof:placetype":"venue"
},
  "geometry": {"coordinates":[-93.325824,44.805215],"type":"Point"}
}