{
  "type": "Feature",
  "properties": {
    "addr:full":"1850 Adams St Ste 116 Mankato MN 56001",
    "addr:housenumber":"1850",
    "addr:postcode":"56001",
    "addr:street":"Adams St Ste 116",
    "iso:country":"US",
    "sg:address":"1850 Adams St Ste 116",
    "sg:city":"Mankato",
    "sg:classifiers":[
        {
            "category":"Shopping",
            "subcategory":"Hobbies, Toys, & Games",
            "type":"Retail Goods"
        }
    ],
    "sg:phone":"+1 507 344 1940",
    "sg:postcode":"56001",
    "sg:province":"MN",
    "sg:tags":[
        "video",
        "supply"
    ],
    "sg:website":"http://www.gamestop.com/",
    "wof:name":"Gamestop",
    "wof:placetype":"venue"
},
  "geometry": {"coordinates":[-93.952393,44.170471],"type":"Point"}
}