{
  "type": "Feature",
  "properties": {
    "addr:full":"1122 Scarborough Ln Saint Paul MN 55125",
    "addr:housenumber":"1122",
    "addr:postcode":"55125",
    "addr:street":"Scarborough Ln",
    "iso:country":"US",
    "sg:address":"1122 Scarborough Ln",
    "sg:city":"Saint Paul",
    "sg:classifiers":[
        {
            "category":"Professional",
            "subcategory":"Business Services",
            "type":"Services"
        }
    ],
    "sg:phone":"+1 651 731 2508",
    "sg:postcode":"55125",
    "sg:province":"MN",
    "wof:name":"Stan Eicher Agency Inc",
    "wof:placetype":"venue"
},
  "geometry": {"coordinates":[-92.917788,44.931406],"type":"Point"}
}