{
  "type": "Feature",
  "properties": {
    "iso:country":"US",
    "sg:address":"3844 Skunk Creek Rd",
    "sg:city":"Barnum",
    "sg:classifiers":[
        {
            "category":"Building & Trades",
            "subcategory":"Construction",
            "type":"Services"
        }
    ],
    "sg:phone":"+1 218 389 0002",
    "sg:postcode":"55707",
    "sg:province":"MN",
    "sg:tags":[
        "house"
    ],
    "wof:name":"Soukkala Cnstr & Remodel",
    "wof:placetype":"venue"
},
  "geometry": {"coordinates":[-92.548616,46.497715],"type":"Point"}
}