{
  "type": "Feature",
  "properties": {
    "addr:full":"407 8th St S Waite Park MN 56387",
    "addr:housenumber":"407",
    "addr:postcode":"56387",
    "addr:street":"8Th St S",
    "iso:country":"US",
    "sg:address":"407 8th St S",
    "sg:city":"Waite Park",
    "sg:classifiers":[
        {
            "category":"Social Services",
            "subcategory":"Child Care",
            "type":"Services"
        }
    ],
    "sg:phone":"+1 320 251 9189",
    "sg:postcode":"56387",
    "sg:province":"MN",
    "sg:tags":[
        "daycare",
        "provider"
    ],
    "wof:name":"Patricia Genette",
    "wof:placetype":"venue"
},
  "geometry": {"coordinates":[-94.221757,45.539477],"type":"Point"}
}