{
  "type": "Feature",
  "properties": {
    "iso:country":"US",
    "sg:address":"5229 Edina Industrial Blvd",
    "sg:city":"Edina",
    "sg:classifiers":[
        {
            "category":"Professional",
            "type":"Services"
        }
    ],
    "sg:phone":"+1 952 842 2560",
    "sg:postcode":"55439",
    "sg:province":"MN",
    "sg:tags":[
        "establishment"
    ],
    "wof:name":"Ilc Enercon Corp",
    "wof:placetype":"venue"
},
  "geometry": {"coordinates":[-93.359382,44.863148],"type":"Point"}
}