{
  "type": "Feature",
  "properties": {
    "addr:full":"80 37th Ave S St Cloud MN 56301",
    "addr:housenumber":"80",
    "addr:postcode":"56301",
    "addr:street":"37Th Ave S",
    "iso:country":"US",
    "sg:address":"80 37th Ave S",
    "sg:city":"St Cloud",
    "sg:classifiers":[
        {
            "category":"Professional",
            "subcategory":"Advertising",
            "type":"Services"
        }
    ],
    "sg:phone":"+1 320 259 0655",
    "sg:postcode":"56301",
    "sg:province":"MN",
    "sg:tags":[
        "guide"
    ],
    "wof:name":"Dex Media Inc",
    "wof:placetype":"venue"
},
  "geometry": {"coordinates":[-94.203261,45.551654],"type":"Point"}
}