{
  "type": "Feature",
  "properties": {
    "iso:country":"US",
    "sg:address":"3553 Widgeon Way",
    "sg:city":"St Paul",
    "sg:classifiers":[
        {
            "category":"Building & Trades",
            "subcategory":"Landscaping Services",
            "type":"Services"
        }
    ],
    "sg:phone":"+1 651 454 1459",
    "sg:postcode":"55123",
    "sg:province":"MN",
    "sg:tags":[
        "lawn",
        "maintenance",
        "grounds"
    ],
    "wof:name":"Graddy's Lawn Care",
    "wof:placetype":"venue"
},
  "geometry": {"coordinates":[-93.156216,44.827488],"type":"Point"}
}