{
  "type": "Feature",
  "properties": {
    "iso:country":"US",
    "sg:address":"7935 Stone Creek Dr Ste 150",
    "sg:city":"Chanhassen",
    "sg:classifiers":[
        {
            "category":"Health Services",
            "subcategory":"Dentist",
            "type":"Services"
        }
    ],
    "sg:phone":"+1 952 937 2839",
    "sg:postcode":"55317",
    "sg:province":"MN",
    "sg:website":"www.stonecreekdental.biz",
    "wof:name":"Stone Creek Dental",
    "wof:placetype":"venue"
},
  "geometry": {"coordinates":[-93.571692,44.861928],"type":"Point"}
}