{
  "type": "Feature",
  "properties": {
    "iso:country":"US",
    "sg:address":"7901 Pickfair Dr",
    "sg:city":"Minneapolis",
    "sg:classifiers":[
        {
            "category":"Professional",
            "subcategory":"Engineering",
            "type":"Services"
        }
    ],
    "sg:phone":"+1 952 941 4216",
    "sg:postcode":"55438",
    "sg:province":"MN",
    "wof:name":"Boruta Engineering Inc",
    "wof:placetype":"venue"
},
  "geometry": {"coordinates":[-93.38673199999999,44.844658],"type":"Point"}
}