{
  "type": "Feature",
  "properties": {
    "addr:full":"18178 Minnetonka Blvd Wayzata MN 55391",
    "addr:housenumber":"18178",
    "addr:postcode":"55391",
    "addr:street":"Minnetonka Blvd",
    "iso:country":"US",
    "sg:address":"18178 Minnetonka Blvd",
    "sg:city":"Wayzata",
    "sg:classifiers":[
        {
            "category":"Manufacturing",
            "subcategory":"Printing",
            "type":"Manufacturing & Wholesale Goods"
        }
    ],
    "sg:phone":"+1 763 473 0890",
    "sg:postcode":"55391",
    "sg:province":"MN",
    "sg:tags":[
        "newspaper"
    ],
    "wof:name":"Lakeshore Weekly News",
    "wof:placetype":"venue"
},
  "geometry": {"coordinates":[-93.511121,44.942227],"type":"Point"}
}