{
  "type": "Feature",
  "properties": {
    "iso:country":"US",
    "sg:address":"105 Peavey Rd Ste 140",
    "sg:city":"Chaska",
    "sg:classifiers":[
        {
            "category":"Organizations",
            "subcategory":"Religious Organization",
            "type":"Services"
        }
    ],
    "sg:phone":"+1 952 442 2112",
    "sg:postcode":"55318",
    "sg:province":"MN",
    "sg:website":"www.bethelfellowshipchurch.org",
    "wof:name":"Bethel Fellowship Church",
    "wof:placetype":"venue"
},
  "geometry": {"coordinates":[-93.595483,44.84496],"type":"Point"}
}