{
  "type": "Feature",
  "properties": {
    "addr:full":"658 Cedar St St Paul MN 55101",
    "addr:housenumber":"658",
    "addr:postcode":"55101",
    "addr:street":"Cedar St",
    "iso:country":"US",
    "sg:address":"658 Cedar St",
    "sg:city":"St Paul",
    "sg:classifiers":[
        {
            "category":"Government",
            "subcategory":"Office",
            "type":"Public Place"
        }
    ],
    "sg:phone":"+1 651 296 5148",
    "sg:postcode":"55101",
    "sg:province":"MN",
    "sg:tags":[
        "state",
        "inspection"
    ],
    "wof:name":"Campaign Finance & Public Dscl",
    "wof:placetype":"venue"
},
  "geometry": {"coordinates":[-93.100779,44.956319],"type":"Point"}
}