{
  "type": "Feature",
  "properties": {
    "addr:full":"9958 Cavell Ave S Minneapolis MN 55438",
    "addr:housenumber":"9958",
    "addr:postcode":"55438",
    "addr:street":"Cavell Ave S",
    "iso:country":"US",
    "sg:address":"9958 Cavell Ave S",
    "sg:city":"Minneapolis",
    "sg:classifiers":[
        {
            "category":"Professional",
            "subcategory":"Computer Services",
            "type":"Services"
        }
    ],
    "sg:phone":"+1 952 828 9788",
    "sg:postcode":"55438",
    "sg:province":"MN",
    "sg:tags":[
        "design",
        "system"
    ],
    "wof:name":"HP",
    "wof:placetype":"venue"
},
  "geometry": {"coordinates":[-93.395566,44.822415],"type":"Point"}
}