{
  "type": "Feature",
  "properties": {
    "addr:full":"4743 Judd Rd Gilbert MN 55741",
    "addr:housenumber":"4743",
    "addr:postcode":"55741",
    "addr:street":"Judd Rd",
    "iso:country":"US",
    "sg:address":"4743 Judd Rd",
    "sg:city":"Gilbert",
    "sg:classifiers":[
        {
            "category":"Building & Trades",
            "subcategory":"Construction",
            "type":"Services"
        }
    ],
    "sg:phone":"+1 218 865 7151",
    "sg:postcode":"55741",
    "sg:province":"MN",
    "sg:tags":[
        "contractor"
    ],
    "wof:name":"Glass & Door Inc",
    "wof:placetype":"venue"
},
  "geometry": {"coordinates":[-92.38196499999999,47.459125],"type":"Point"}
}