{
  "type": "Feature",
  "properties": {
    "iso:country":"US",
    "sg:address":"7580 Quattro Dr",
    "sg:city":"Chanhassen",
    "sg:classifiers":[
        {
            "category":"Professional",
            "subcategory":"Employment Agencies",
            "type":"Services"
        }
    ],
    "sg:phone":"+1 952 294 0334",
    "sg:postcode":"55317",
    "sg:province":"MN",
    "sg:website":"www.eexecutives.net",
    "wof:name":"E Executives",
    "wof:placetype":"venue"
},
  "geometry": {"coordinates":[-93.513397,44.865898],"type":"Point"}
}