{
  "type": "Feature",
  "properties": {
    "iso:country":"US",
    "sg:address":"3635 Black Oaks Ln N",
    "sg:city":"Minneapolis",
    "sg:classifiers":[
        {
            "category":"Banks & Credit Unions",
            "subcategory":"Financial Services",
            "type":"Services"
        }
    ],
    "sg:phone":"+1 763 557 1965",
    "sg:postcode":"55446",
    "sg:province":"MN",
    "sg:tags":[
        "personal",
        "trust",
        "investment"
    ],
    "wof:name":"Brundelie Family Ltd",
    "wof:placetype":"venue"
},
  "geometry": {"coordinates":[-93.48782799999999,45.023837],"type":"Point"}
}