{
  "type": "Feature",
  "properties": {
    "addr:full":"7059 38th St N Saint Paul MN 55128",
    "addr:housenumber":"7059",
    "addr:postcode":"55128",
    "addr:street":"38Th St N",
    "iso:country":"US",
    "sg:address":"7059 38th St N",
    "sg:city":"Saint Paul",
    "sg:classifiers":[
        {
            "category":"Professional",
            "subcategory":"Detective & Security Services",
            "type":"Services"
        }
    ],
    "sg:phone":"+1 651 773 9584",
    "sg:postcode":"55128",
    "sg:province":"MN",
    "sg:tags":[
        "eating",
        "system"
    ],
    "wof:name":"Tk Services Inc",
    "wof:placetype":"venue"
},
  "geometry": {"coordinates":[-92.963584,45.003269],"type":"Point"}
}