{
  "type": "Feature",
  "properties": {
    "addr:full":"3540 75th St E Inver Grove Heights MN 55076",
    "addr:housenumber":"3540",
    "addr:postcode":"55076",
    "addr:street":"75Th St E",
    "iso:country":"US",
    "sg:address":"3540 75th St E",
    "sg:city":"Inver Grove Heights",
    "sg:classifiers":[
        {
            "category":"Organizations",
            "subcategory":"Religious Organization",
            "type":"Services"
        }
    ],
    "sg:phone":"+1 651 457 2477",
    "sg:postcode":"55076",
    "sg:province":"MN",
    "wof:name":"Eastern MN Decns Assoc Inc",
    "wof:placetype":"venue"
},
  "geometry": {"coordinates":[-93.034164,44.840714],"type":"Point"}
}