{
  "type": "Feature",
  "properties": {
    "addr:full":"9837 Colorado Cir Minneapolis MN 55438",
    "addr:housenumber":"9837",
    "addr:postcode":"55438",
    "addr:street":"Colorado Cir",
    "iso:country":"US",
    "sg:address":"9837 Colorado Cir",
    "sg:city":"Minneapolis",
    "sg:classifiers":[
        {
            "category":"Building & Trades",
            "subcategory":"Construction",
            "type":"Services"
        }
    ],
    "sg:phone":"+1 612 916 4050",
    "sg:postcode":"55438",
    "sg:province":"MN",
    "sg:tags":[
        "house"
    ],
    "wof:name":"Jansen Construction Services",
    "wof:placetype":"venue"
},
  "geometry": {"coordinates":[-93.36003700000001,44.82635],"type":"Point"}
}