{
  "type": "Feature",
  "properties": {
    "addr:full":"812 Division St S Northfield MN 55057",
    "addr:housenumber":"812",
    "addr:postcode":"55057",
    "addr:street":"Division St S",
    "iso:country":"US",
    "sg:address":"812 Division St S",
    "sg:city":"Northfield",
    "sg:classifiers":[
        {
            "category":"Building & Trades",
            "subcategory":"Construction",
            "type":"Services"
        }
    ],
    "sg:phone":"+1 507 663 0766",
    "sg:postcode":"55057",
    "sg:province":"MN",
    "sg:tags":[
        "contractor",
        "painting",
        "hanging"
    ],
    "wof:name":"Doug Child Painting",
    "wof:placetype":"venue"
},
  "geometry": {"coordinates":[-93.160149,44.451357],"type":"Point"}
}