{
  "type": "Feature",
  "properties": {
    "addr:full":"307 5th Ave S Brownton MN 55312",
    "addr:housenumber":"307",
    "addr:postcode":"55312",
    "addr:street":"5Th Ave S Brownton",
    "iso:country":"US",
    "sg:address":"307 5th Ave S",
    "sg:city":"Brownton",
    "sg:classifiers":[
        {
            "category":"Personal",
            "subcategory":"Beauty Salon",
            "type":"Services"
        }
    ],
    "sg:phone":"+1 320 328 5728",
    "sg:postcode":"55312",
    "sg:province":"MN",
    "sg:tags":[
        "shop"
    ],
    "wof:name":"Barb's Beauty Shop",
    "wof:placetype":"venue"
},
  "geometry": {"coordinates":[-94.350705,44.730149],"type":"Point"}
}