{
  "type": "Feature",
  "properties": {
    "iso:country":"US",
    "sg:address":"5600 Norwich Ave N",
    "sg:city":"Stillwater",
    "sg:classifiers":[
        {
            "category":"Building & Trades",
            "subcategory":"Construction",
            "type":"Services"
        }
    ],
    "sg:phone":"+1 651 430 2481",
    "sg:postcode":"55082",
    "sg:province":"MN",
    "sg:tags":[
        "home",
        "builder"
    ],
    "wof:name":"Presbyterian Homes Boutwells",
    "wof:placetype":"venue"
},
  "geometry": {"coordinates":[-92.829054,45.02938],"type":"Point"}
}