{
  "type": "Feature",
  "properties": {
    "addr:full":"2121 Cliff Dr Saint Paul MN 55122",
    "addr:housenumber":"2121",
    "addr:postcode":"55122",
    "addr:street":"Cliff Dr",
    "iso:country":"US",
    "sg:address":"2121 Cliff Dr",
    "sg:city":"Saint Paul",
    "sg:classifiers":[
        {
            "category":"Health Services",
            "subcategory":"Chiropractor",
            "type":"Services"
        }
    ],
    "sg:phone":"+1 651 330 3896",
    "sg:postcode":"55122",
    "sg:province":"MN",
    "wof:name":"Cedar Cliff Chiropractic",
    "wof:placetype":"venue"
},
  "geometry": {"coordinates":[-93.215149,44.790817],"type":"Point"}
}