{
  "type": "Feature",
  "properties": {
    "iso:country":"US",
    "sg:address":"1306 Tiller Ln",
    "sg:city":"Saint Paul",
    "sg:classifiers":[
        {
            "category":"Professional",
            "subcategory":"Business Services",
            "type":"Services"
        }
    ],
    "sg:phone":"+1 651 636 6636",
    "sg:postcode":"55112",
    "sg:province":"MN",
    "wof:name":"SES & Associates LLC",
    "wof:placetype":"venue"
},
  "geometry": {"coordinates":[-93.15683799999999,45.042204],"type":"Point"}
}