{
  "type": "Feature",
  "properties": {
    "addr:full":"580 Humbolt Dr NW Big Lake MN 55309",
    "addr:housenumber":"580",
    "addr:postcode":"55309",
    "addr:street":"Humbolt Dr Nw",
    "iso:country":"US",
    "sg:address":"580 Humbolt Dr NW",
    "sg:city":"Big Lake",
    "sg:classifiers":[
        {
            "category":"Home & Garden",
            "subcategory":"Furniture",
            "type":"Retail Goods"
        },
        {
            "category":"Building & Trades",
            "subcategory":"Construction",
            "type":"Services"
        }
    ],
    "sg:phone":"+1 763 263 0890",
    "sg:postcode":"55309",
    "sg:province":"MN",
    "sg:tags":[
        "house",
        "contractor"
    ],
    "wof:name":"Al's Custom Built Sheds",
    "wof:placetype":"venue"
},
  "geometry": {"coordinates":[-93.736913,45.331935],"type":"Point"}
}