{
  "type": "Feature",
  "properties": {
    "iso:country":"US",
    "sg:address":"849 University Ave W",
    "sg:city":"St Paul",
    "sg:classifiers":[
        {
            "category":"Shopping",
            "subcategory":"Gifts & Souvenirs",
            "type":"Retail Goods"
        }
    ],
    "sg:phone":"+1 651 209 6080",
    "sg:postcode":"55104",
    "sg:province":"MN",
    "sg:tags":[
        "shop"
    ],
    "wof:name":"About Asia",
    "wof:placetype":"venue"
},
  "geometry": {"coordinates":[-93.13499899999999,44.955797],"type":"Point"}
}