{
  "type": "Feature",
  "properties": {
    "iso:country":"US",
    "sg:address":"1660 Highway 100 S Ste 500",
    "sg:city":"Minneapolis",
    "sg:classifiers":[
        {
            "category":"Professional",
            "subcategory":"Lawyer & Legal Services",
            "type":"Services"
        }
    ],
    "sg:phone":"+1 952 697 3660",
    "sg:postcode":"55416",
    "sg:province":"MN",
    "wof:name":"Letourneau Dennis R Atty",
    "wof:placetype":"venue"
},
  "geometry": {"coordinates":[-93.34320099999999,44.9678],"type":"Point"}
}