{
  "type": "Feature",
  "properties": {
    "iso:country":"US",
    "sg:address":"2100 Mustang Dr",
    "sg:city":"St Paul",
    "sg:classifiers":[
        {
            "category":"Professional",
            "subcategory":"Advertising",
            "type":"Services"
        },
        {
            "category":"Manufacturing",
            "subcategory":"Tools & Machinery",
            "type":"Manufacturing & Wholesale Goods"
        }
    ],
    "sg:phone":"+1 763 780 1400",
    "sg:postcode":"55112",
    "sg:province":"MN",
    "sg:tags":[
        "distribution",
        "industrial",
        "mfg"
    ],
    "sg:website":"www.midwayis.com",
    "wof:name":"Midway Industrial Supply Inc",
    "wof:placetype":"venue"
},
  "geometry": {"coordinates":[-93.188514,45.087708],"type":"Point"}
}