{
  "type": "Feature",
  "properties": {
    "iso:country":"US",
    "sg:address":"357 Dennison Ave",
    "sg:city":"St Paul",
    "sg:classifiers":[
        {
            "category":"Real Estate",
            "subcategory":"Real Estate Agent",
            "type":"Services"
        }
    ],
    "sg:phone":"+1 651 765 4800",
    "sg:postcode":"55126",
    "sg:province":"MN",
    "wof:name":"Karna Real Estate Inc",
    "wof:placetype":"venue"
},
  "geometry": {"coordinates":[-93.115627,45.069818],"type":"Point"}
}