{
  "type": "Feature",
  "properties": {
    "addr:full":"25 E King St Saint Paul MN 55107",
    "addr:housenumber":"25",
    "addr:postcode":"55107",
    "addr:street":"E King St",
    "iso:country":"US",
    "sg:address":"25 E King St",
    "sg:city":"Saint Paul",
    "sg:classifiers":[
        {
            "category":"Government",
            "subcategory":"Court House",
            "type":"Public Place"
        }
    ],
    "sg:phone":"+1 651 296 2474",
    "sg:postcode":"55107",
    "sg:province":"MN",
    "wof:name":"State Court Administrator",
    "wof:placetype":"venue"
},
  "geometry": {"coordinates":[-93.084475,44.928028],"type":"Point"}
}