{
  "type": "Feature",
  "properties": {
    "iso:country":"US",
    "sg:address":"4326 Trenton Ln NW",
    "sg:city":"Rochester",
    "sg:classifiers":[
        {
            "category":"Shopping",
            "subcategory":"Used Merchandise",
            "type":"Retail Goods"
        }
    ],
    "sg:phone":"+1 507 281 2129",
    "sg:postcode":"55901",
    "sg:province":"MN",
    "wof:name":"Sherrys From Past",
    "wof:placetype":"venue"
},
  "geometry": {"coordinates":[-92.514309,44.067611],"type":"Point"}
}