{
  "type": "Feature",
  "properties": {
    "addr:full":"1737 120th St Fairmont MN 56031",
    "addr:housenumber":"1737",
    "addr:postcode":"56031",
    "addr:street":"120Th St",
    "iso:country":"US",
    "sg:address":"1737 120th St",
    "sg:city":"Fairmont",
    "sg:phone":"+1 507 238 2721",
    "sg:postcode":"56031",
    "sg:province":"MN",
    "sg:tags":[
        "farm",
        "corn",
        "soybean"
    ],
    "wof:name":"Donald Bulfer",
    "wof:placetype":"venue"
},
  "geometry": {"coordinates":[-94.52652399999999,43.65941],"type":"Point"}
}