{
  "type": "Feature",
  "properties": {
    "iso:country":"US",
    "sg:address":"2066 250th St",
    "sg:city":"Truman",
    "sg:phone":"+1 507 776 3158",
    "sg:postcode":"56088",
    "sg:province":"MN",
    "sg:tags":[
        "farm",
        "corn"
    ],
    "wof:name":"David Bates",
    "wof:placetype":"venue"
},
  "geometry": {"coordinates":[-94.454477,43.847978],"type":"Point"}
}