{
  "type": "Feature",
  "properties": {
    "addr:full":"26570 Fallbrook Ave Wyoming MN 55092",
    "addr:housenumber":"26570",
    "addr:postcode":"55092",
    "addr:street":"Fallbrook Ave",
    "iso:country":"US",
    "sg:address":"26570 Fallbrook Ave",
    "sg:city":"Wyoming",
    "sg:classifiers":[
        {
            "category":"Manufacturing",
            "subcategory":"Metals",
            "type":"Manufacturing & Wholesale Goods"
        }
    ],
    "sg:phone":"+1 651 462 2466",
    "sg:postcode":"55092",
    "sg:province":"MN",
    "sg:tags":[
        "valve"
    ],
    "wof:name":"Sandy Manufacturing Co",
    "wof:placetype":"venue"
},
  "geometry": {"coordinates":[-93.00128100000001,45.336364],"type":"Point"}
}