{
  "type": "Feature",
  "properties": {
    "addr:full":"5203 E Superior St Duluth MN 55804",
    "addr:housenumber":"5203",
    "addr:postcode":"55804",
    "addr:street":"E Superior St",
    "iso:country":"US",
    "sg:address":"5203 E Superior St",
    "sg:city":"Duluth",
    "sg:classifiers":[
        {
            "category":"Real Estate",
            "subcategory":"Real Estate Services",
            "type":"Services"
        },
        {
            "category":"Real Estate",
            "subcategory":"Real Estate Agent",
            "type":"Services"
        }
    ],
    "sg:phone":"+1 218 525 6370",
    "sg:postcode":"55804",
    "sg:province":"MN",
    "sg:tags":[
        "buyer",
        "management",
        "broker"
    ],
    "wof:name":"Lewis & Clark",
    "wof:placetype":"venue"
},
  "geometry": {"coordinates":[-92.01983199999999,46.834342],"type":"Point"}
}