{
  "type": "Feature",
  "properties": {
    "iso:country":"US",
    "sg:address":"415 1st Ave NE",
    "sg:city":"Staples",
    "sg:classifiers":[
        {
            "category":"Retail",
            "subcategory":"Laundry & Dry Cleaning",
            "type":"Services"
        },
        {
            "category":"Shopping",
            "subcategory":"Clothing, Apparel, & Fashions",
            "type":"Retail Goods"
        }
    ],
    "sg:phone":"+1 218 894 1089",
    "sg:postcode":"56479",
    "sg:province":"MN",
    "sg:tags":[
        "drycleaning",
        "plant",
        "alteration"
    ],
    "wof:name":"Crystal Sew N Clean",
    "wof:placetype":"venue"
},
  "geometry": {"coordinates":[-94.79484600000001,46.354716],"type":"Point"}
}