{
  "type": "Feature",
  "properties": {
    "iso:country":"US",
    "sg:address":"713 W Franklin Ave",
    "sg:city":"Minneapolis",
    "sg:classifiers":[
        {
            "category":"Shopping",
            "subcategory":"Clothing, Apparel, & Fashions",
            "type":"Retail Goods"
        },
        {
            "category":"Manufacturing",
            "subcategory":"Leather Goods",
            "type":"Manufacturing & Wholesale Goods"
        }
    ],
    "sg:phone":"+1 612 871 2195",
    "sg:postcode":"55405",
    "sg:province":"MN",
    "sg:tags":[
        "accessory"
    ],
    "wof:name":"Pursecution",
    "wof:placetype":"venue"
},
  "geometry": {"coordinates":[-93.288082,44.962703],"type":"Point"}
}