{
  "type": "Feature",
  "properties": {
    "addr:full":"10010 Sundance Rd Rogers MN 55374",
    "addr:housenumber":"10010",
    "addr:postcode":"55374",
    "addr:street":"Sundance Rd",
    "iso:country":"US",
    "sg:address":"10010 Sundance Rd",
    "sg:city":"Rogers",
    "sg:classifiers":[
        {
            "category":"Retail",
            "subcategory":"Repair Shop",
            "type":"Services"
        }
    ],
    "sg:phone":"+1 763 498 0002",
    "sg:postcode":"55374",
    "sg:province":"MN",
    "sg:tags":[
        "refrigeration"
    ],
    "wof:name":"Eric Drongeson",
    "wof:placetype":"venue"
},
  "geometry": {"coordinates":[-93.615257,45.135864],"type":"Point"}
}