{
  "type": "Feature",
  "properties": {
    "iso:country":"US",
    "sg:address":"473 W Michigan St",
    "sg:city":"Saint Paul",
    "sg:classifiers":[
        {
            "category":"Manufacturing",
            "subcategory":"Furniture",
            "type":"Manufacturing & Wholesale Goods"
        }
    ],
    "sg:phone":"+1 651 228 9259",
    "sg:postcode":"55102",
    "sg:province":"MN",
    "sg:tags":[
        "patio",
        "mfg"
    ],
    "wof:name":"Ceda Comfort Inc",
    "wof:placetype":"venue"
},
  "geometry": {"coordinates":[-93.12108499999999,44.935016],"type":"Point"}
}