{
  "type": "Feature",
  "properties": {
    "addr:full":"19912 565th Ave Mankato MN 56001",
    "addr:housenumber":"19912",
    "addr:postcode":"56001",
    "addr:street":"565Th Ave",
    "iso:country":"US",
    "sg:address":"19912 565th Ave",
    "sg:city":"Mankato",
    "sg:classifiers":[
        {
            "category":"Recreation",
            "type":"Entertainment"
        }
    ],
    "sg:phone":"+1 507 388 5985",
    "sg:postcode":"56001",
    "sg:province":"MN",
    "wof:name":"Solyntjes Stables",
    "wof:placetype":"venue"
},
  "geometry": {"coordinates":[-94.018879,44.121547],"type":"Point"}
}