{
  "type": "Feature",
  "properties": {
    "addr:full":"122 1st St SE Akeley MN 56433",
    "addr:housenumber":"122",
    "addr:postcode":"56433",
    "addr:street":"1St St Se",
    "iso:country":"US",
    "sg:address":"122 1st St SE",
    "sg:city":"Akeley",
    "sg:classifiers":[
        {
            "category":"Arena",
            "subcategory":"Sports Club",
            "type":"Entertainment"
        }
    ],
    "sg:phone":"+1 218 675 5108",
    "sg:postcode":"56433",
    "sg:province":"MN",
    "sg:tags":[
        "health"
    ],
    "wof:name":"Body Rhythms",
    "wof:placetype":"venue"
},
  "geometry": {"coordinates":[-94.726631,47.002144],"type":"Point"}
}