{
  "type": "Feature",
  "properties": {
    "addr:full":"30 Plato Blvd W St Paul MN 55107",
    "addr:housenumber":"30",
    "addr:postcode":"55107",
    "addr:street":"Plato Blvd W",
    "iso:country":"US",
    "sg:address":"30 Plato Blvd W",
    "sg:city":"St Paul",
    "sg:classifiers":[
        {
            "category":"Professional",
            "subcategory":"Accounting & Tax Preparation",
            "type":"Services"
        }
    ],
    "sg:phone":"+1 651 227 6695",
    "sg:postcode":"55107",
    "sg:province":"MN",
    "sg:tags":[
        "accountant"
    ],
    "sg:website":"www.mucr.com",
    "wof:name":"Mahoney Ulbrich Christiansen",
    "wof:placetype":"venue"
},
  "geometry": {"coordinates":[-93.09280099999999,44.936122],"type":"Point"}
}