{
  "type": "Feature",
  "properties": {
    "addr:full":"6410 Pagenkopf Rd Maple Plain MN 55359",
    "addr:housenumber":"6410",
    "addr:postcode":"55359",
    "addr:street":"Pagenkopf Rd;Plain",
    "iso:country":"US",
    "sg:address":"6410 Pagenkopf Rd",
    "sg:city":"Maple Plain",
    "sg:classifiers":[
        {
            "category":"Home & Garden",
            "subcategory":"Furniture",
            "type":"Retail Goods"
        }
    ],
    "sg:phone":"+1 763 479 6147",
    "sg:postcode":"55359",
    "sg:province":"MN",
    "wof:name":"Sundean Services",
    "wof:placetype":"venue"
},
  "geometry": {"coordinates":[-93.690138,45.02229],"type":"Point"}
}