{
  "type": "Feature",
  "properties": {
    "addr:full":"1550 Fairview Rd N Baxter MN 56425",
    "addr:housenumber":"1550",
    "addr:postcode":"56425",
    "addr:street":"Fairview Rd N",
    "iso:country":"US",
    "sg:address":"1550 Fairview Rd N",
    "sg:city":"Baxter",
    "sg:classifiers":[
        {
            "category":"Banks & Credit Unions",
            "subcategory":"Bank",
            "type":"Services"
        }
    ],
    "sg:phone":"+1 218 825 4852",
    "sg:postcode":"56425",
    "sg:province":"MN",
    "sg:tags":[
        "national",
        "commercial"
    ],
    "wof:name":"Lakewood Bank NA",
    "wof:placetype":"venue"
},
  "geometry": {"coordinates":[-94.236985,46.353077],"type":"Point"}
}