{
  "type": "Feature",
  "properties": {
    "iso:country":"US",
    "sg:address":"494 Jackson St",
    "sg:city":"St Paul",
    "sg:classifiers":[
        {
            "category":"Shopping",
            "type":"Retail Goods"
        }
    ],
    "sg:phone":"+1 651 222 4431",
    "sg:postcode":"55101",
    "sg:province":"MN",
    "sg:tags":[
        "picture",
        "frame"
    ],
    "wof:name":"Twin City Picture Framing",
    "wof:placetype":"venue"
},
  "geometry": {"coordinates":[-93.09299799999999,44.95186],"type":"Point"}
}