{
  "type": "Feature",
  "properties": {
    "iso:country":"US",
    "sg:address":"1804 Broadway St",
    "sg:city":"Alexandria",
    "sg:classifiers":[
        {
            "category":"Social Services",
            "type":"Services"
        }
    ],
    "sg:phone":"+1 320 762 5124",
    "sg:postcode":"56308",
    "sg:province":"MN",
    "wof:name":"Lutheran Social Service",
    "wof:placetype":"venue"
},
  "geometry": {"coordinates":[-95.37791900000001,45.871738],"type":"Point"}
}