{
  "type": "Feature",
  "properties": {
    "addr:full":"26357 Forest Blvd N Wyoming MN 55092",
    "addr:housenumber":"26357",
    "addr:postcode":"55092",
    "addr:street":"Forest Blvd N",
    "iso:country":"US",
    "sg:address":"26357 Forest Blvd N",
    "sg:city":"Wyoming",
    "sg:classifiers":[
        {
            "category":"Social Services",
            "type":"Services"
        }
    ],
    "sg:phone":"+1 651 462 6644",
    "sg:postcode":"55092",
    "sg:province":"MN",
    "sg:tags":[
        "counselor",
        "marriage",
        "family"
    ],
    "wof:name":"Hope Counseling & Education",
    "wof:placetype":"venue"
},
  "geometry": {"coordinates":[-92.99706,45.330131],"type":"Point"}
}