{
  "type": "Feature",
  "properties": {
    "addr:full":"3445 Park Ave S Minneapolis MN 55407",
    "addr:housenumber":"3445",
    "addr:postcode":"55407",
    "addr:street":"Park Ave S",
    "iso:country":"US",
    "sg:address":"3445 Park Ave S",
    "sg:city":"Minneapolis",
    "sg:classifiers":[
        {
            "category":"Social Services",
            "subcategory":"Child Care",
            "type":"Services"
        }
    ],
    "sg:phone":"+1 612 825 6277",
    "sg:postcode":"55407",
    "sg:province":"MN",
    "sg:tags":[
        "daycare",
        "provider"
    ],
    "wof:name":"Carol Aguilar",
    "wof:placetype":"venue"
},
  "geometry": {"coordinates":[-93.265027,44.940376],"type":"Point"}
}