{
  "type": "Feature",
  "properties": {
    "addr:full":"816 Arizona St NW Lonsdale MN 55046",
    "addr:housenumber":"816",
    "addr:postcode":"55046",
    "addr:street":"Arizona St Nw",
    "iso:country":"US",
    "sg:address":"816 Arizona St NW",
    "sg:city":"Lonsdale",
    "sg:classifiers":[
        {
            "category":"Retail",
            "subcategory":"Auto Repair",
            "type":"Services"
        }
    ],
    "sg:phone":"+1 763 559 9516",
    "sg:postcode":"55046",
    "sg:province":"MN",
    "sg:tags":[
        "engine"
    ],
    "wof:name":"Diesel Injection Specialists",
    "wof:placetype":"venue"
},
  "geometry": {"coordinates":[-93.442819,44.479132],"type":"Point"}
}