{
  "type": "Feature",
  "properties": {
    "addr:full":"2049 W Lincoln Ave Saint Paul MN 55105",
    "addr:housenumber":"2049",
    "addr:postcode":"55105",
    "addr:street":"W Lincoln Ave",
    "iso:country":"US",
    "sg:address":"2049 W Lincoln Ave",
    "sg:city":"Saint Paul",
    "sg:classifiers":[
        {
            "category":"Professional",
            "subcategory":"Art Services",
            "type":"Services"
        }
    ],
    "sg:phone":"+1 651 699 3406",
    "sg:postcode":"55105",
    "sg:province":"MN",
    "sg:tags":[
        "commercial",
        "design"
    ],
    "wof:name":"Young Zeck Image Cmmunications",
    "wof:placetype":"venue"
},
  "geometry": {"coordinates":[-93.184084,44.939108],"type":"Point"}
}