{
  "type": "Feature",
  "properties": {
    "iso:country":"US",
    "sg:address":"1312 Dodd Rd",
    "sg:city":"Saint Paul",
    "sg:classifiers":[
        {
            "category":"Utilities",
            "subcategory":"Refuse",
            "type":"Services"
        }
    ],
    "sg:phone":"+1 651 457 2377",
    "sg:postcode":"55118",
    "sg:province":"MN",
    "sg:tags":[
        "system"
    ],
    "wof:name":"T C Refuse Recycling",
    "wof:placetype":"venue"
},
  "geometry": {"coordinates":[-93.11244499999999,44.907166],"type":"Point"}
}