{
  "type": "Feature",
  "properties": {
    "iso:country":"US",
    "sg:address":"9145 State Hwy 55",
    "sg:city":"Minneapolis",
    "sg:classifiers":[
        {
            "category":"Health Services",
            "subcategory":"Doctor",
            "type":"Services"
        }
    ],
    "sg:phone":"+1 763 595 8579",
    "sg:postcode":"55427",
    "sg:province":"MN",
    "sg:tags":[
        "medical"
    ],
    "wof:name":"Warren G Hasty",
    "wof:placetype":"venue"
},
  "geometry": {"coordinates":[-93.394946,44.983759],"type":"Point"}
}