{
  "type": "Feature",
  "properties": {
    "iso:country":"US",
    "sg:address":"312 NE 3rd Ave",
    "sg:city":"Grand Rapids",
    "sg:classifiers":[
        {
            "category":"Building & Trades",
            "subcategory":"Plumbing",
            "type":"Services"
        }
    ],
    "sg:phone":"+1 218 326 4249",
    "sg:postcode":"55744",
    "sg:province":"MN",
    "sg:tags":[
        "heating",
        "contractor"
    ],
    "wof:name":"HVAC Svc",
    "wof:placetype":"venue"
},
  "geometry": {"coordinates":[-93.523633,47.235795],"type":"Point"}
}