{
  "type": "Feature",
  "properties": {
    "iso:country":"US",
    "sg:address":"900 Johnson St",
    "sg:city":"Fairmont",
    "sg:classifiers":[
        {
            "category":"Professional",
            "subcategory":"Management & Consulting",
            "type":"Services"
        }
    ],
    "sg:phone":"+1 507 235 4128",
    "sg:postcode":"56031",
    "sg:province":"MN",
    "sg:tags":[
        "consultant",
        "educational"
    ],
    "wof:name":"Services For Challenging Youth",
    "wof:placetype":"venue"
},
  "geometry": {"coordinates":[-94.44824800000001,43.637627],"type":"Point"}
}