{
  "type": "Feature",
  "properties": {
    "addr:full":"6800 Cedar Lake Rd S Minneapolis MN 55426",
    "addr:housenumber":"6800",
    "addr:postcode":"55426",
    "addr:street":"Cedar Lake Rd",
    "iso:country":"US",
    "sg:address":"6800 Cedar Lake Rd S",
    "sg:city":"Minneapolis",
    "sg:classifiers":[
        {
            "category":"Education",
            "subcategory":"School",
            "type":"Public Place"
        }
    ],
    "sg:phone":"+1 952 593 1181",
    "sg:postcode":"55426",
    "sg:province":"MN",
    "wof:name":"Explore",
    "wof:placetype":"venue"
},
  "geometry": {"coordinates":[-93.36717899999999,44.961393],"type":"Point"}
}