{
  "type": "Feature",
  "properties": {
    "addr:full":"4706 US Hwy 61 White Bear Lake MN 55110",
    "addr:housenumber":"4706",
    "addr:postcode":"55110",
    "addr:street":"Us Hwy 61",
    "iso:country":"US",
    "sg:address":"4706 US Hwy 61",
    "sg:city":"White Bear Lake",
    "sg:classifiers":[
        {
            "category":"Home & Garden",
            "subcategory":"Furniture",
            "type":"Retail Goods"
        }
    ],
    "sg:phone":"+1 651 429 1212",
    "sg:postcode":"55110",
    "sg:province":"MN",
    "sg:tags":[
        "equipment",
        "kitchen",
        "cabinet"
    ],
    "wof:name":"Preferred Kitchens Inc",
    "wof:placetype":"venue"
},
  "geometry": {"coordinates":[-93.01297099999999,45.081822],"type":"Point"}
}