{
  "type": "Feature",
  "properties": {
    "addr:full":"6071 Blake Ridge Rd Edina MN 55436",
    "addr:housenumber":"6071",
    "addr:postcode":"55436",
    "addr:street":"Blake Ridge Rd",
    "iso:country":"US",
    "sg:address":"6071 Blake Ridge Rd",
    "sg:city":"Edina",
    "sg:classifiers":[
        {
            "category":"Professional",
            "type":"Services"
        }
    ],
    "sg:phone":"+1 952 926 5622",
    "sg:postcode":"55436",
    "sg:province":"MN",
    "sg:tags":[
        "establishment"
    ],
    "wof:name":"Blake Ridge Clubhouse",
    "wof:placetype":"venue"
},
  "geometry": {"coordinates":[-93.379429,44.898867],"type":"Point"}
}