{
  "type": "Feature",
  "properties": {
    "iso:country":"US",
    "sg:address":"53 Glenwood Ave",
    "sg:city":"Minneapolis",
    "sg:classifiers":[
        {
            "category":"Social Services",
            "type":"Services"
        },
        {
            "category":"Place Of Worship",
            "subcategory":"Church",
            "type":"Public Place"
        },
        {
            "category":"Place Of Worship",
            "type":"Public Place"
        },
        {
            "category":"Shopping",
            "subcategory":"Thrift Store",
            "type":"Retail Goods"
        }
    ],
    "sg:phone":"+1 612 659 0705",
    "sg:postcode":"55403",
    "sg:province":"MN",
    "sg:tags":[
        "shop",
        "churches-salvation",
        "army"
    ],
    "sg:website":"http://www.salvationarmyusa.org/",
    "wof:name":"Salvation Army",
    "wof:placetype":"venue"
},
  "geometry": {"coordinates":[-93.27887,44.978901],"type":"Point"}
}