{
  "type": "Feature",
  "properties": {
    "addr:full":"15550 Tamarac Cir NE Miltona MN 56354",
    "addr:housenumber":"15550",
    "addr:postcode":"56354",
    "addr:street":"Tamarac Cir Ne",
    "iso:country":"US",
    "sg:address":"15550 Tamarac Cir NE",
    "sg:city":"Miltona",
    "sg:classifiers":[
        {
            "category":"Organizations",
            "subcategory":"Community Association",
            "type":"Services"
        }
    ],
    "sg:phone":"+1 218 943 6911",
    "sg:postcode":"56354",
    "sg:province":"MN",
    "wof:name":"International Assoc of LI",
    "wof:placetype":"venue"
},
  "geometry": {"coordinates":[-95.345483,46.055829],"type":"Point"}
}