{
  "type": "Feature",
  "properties": {
    "iso:country":"US",
    "sg:address":"6430 Regency Ln",
    "sg:city":"Eden Prairie",
    "sg:classifiers":[
        {
            "category":"Banks & Credit Unions",
            "subcategory":"Investment Brokerage",
            "type":"Services"
        }
    ],
    "sg:phone":"+1 952 830 1012",
    "sg:postcode":"55344",
    "sg:province":"MN",
    "sg:tags":[
        "consultant",
        "planning",
        "financial"
    ],
    "wof:name":"Miller & Assoc",
    "wof:placetype":"venue"
},
  "geometry": {"coordinates":[-93.415853,44.883208],"type":"Point"}
}