{
  "type": "Feature",
  "properties": {
    "addr:full":"8135 Co Hwy 61 Willow River MN 55795",
    "addr:housenumber":"8135",
    "addr:postcode":"55795",
    "addr:street":"Co Hwy 61;River",
    "iso:country":"US",
    "sg:address":"8135 Co Hwy 61",
    "sg:city":"Willow River",
    "sg:classifiers":[
        {
            "category":"Restaurant",
            "type":"Food & Drink"
        }
    ],
    "sg:phone":"+1 218 372 3935",
    "sg:postcode":"55795",
    "sg:province":"MN",
    "wof:name":"Willow River Cafe",
    "wof:placetype":"venue"
},
  "geometry": {"coordinates":[-92.84039300000001,46.317031],"type":"Point"}
}