{
  "type": "Feature",
  "properties": {
    "addr:full":"7316 Aspen Ln N Minneapolis MN 55428",
    "addr:housenumber":"7316",
    "addr:postcode":"55428",
    "addr:street":"Aspen Ln N",
    "iso:country":"US",
    "sg:address":"7316 Aspen Ln N",
    "sg:city":"Minneapolis",
    "sg:classifiers":[
        {
            "category":"Shopping",
            "subcategory":"Hobbies, Toys, & Games",
            "type":"Retail Goods"
        }
    ],
    "sg:phone":"+1 763 315 8700",
    "sg:postcode":"55428",
    "sg:province":"MN",
    "sg:tags":[
        "model",
        "supply"
    ],
    "sg:website":"www.twincityhobby.com",
    "wof:name":"Twin City Hobby & Raceway",
    "wof:placetype":"venue"
},
  "geometry": {"coordinates":[-93.388778,45.090334],"type":"Point"}
}