{
  "type": "Feature",
  "properties": {
    "addr:full":"3124 Columbus Ave S Minneapolis MN 55407",
    "addr:housenumber":"3124",
    "addr:postcode":"55407",
    "addr:street":"Columbus Ave S",
    "iso:country":"US",
    "sg:address":"3124 Columbus Ave S",
    "sg:city":"Minneapolis",
    "sg:classifiers":[
        {
            "category":"Freight",
            "type":"Transportation"
        }
    ],
    "sg:phone":"+1 612 824 7172",
    "sg:postcode":"55407",
    "sg:province":"MN",
    "sg:tags":[
        "delivery"
    ],
    "wof:name":"Guy Otto Delivery",
    "wof:placetype":"venue"
},
  "geometry": {"coordinates":[-93.26398500000001,44.945203],"type":"Point"}
}