{
  "type": "Feature",
  "properties": {
    "iso:country":"US",
    "sg:address":"1430 Washington Ave S",
    "sg:city":"Minneapolis",
    "sg:classifiers":[
        {
            "category":"Organizations",
            "subcategory":"Non-profit Organization",
            "type":"Services"
        }
    ],
    "sg:phone":"+1 612 692 8440",
    "sg:postcode":"55454",
    "sg:province":"MN",
    "sg:tags":[
        "human"
    ],
    "sg:website":"www.isaw.org",
    "wof:name":"International Self Reliance",
    "wof:placetype":"venue"
},
  "geometry": {"coordinates":[-93.247726,44.973095],"type":"Point"}
}