{
  "type": "Feature",
  "properties": {
    "iso:country":"US",
    "sg:address":"12880 122nd St S",
    "sg:city":"Hastings",
    "sg:classifiers":[
        {
            "category":"Banks & Credit Unions",
            "subcategory":"Bank",
            "type":"Services"
        }
    ],
    "sg:phone":"+1 651 438 9870",
    "sg:postcode":"55033",
    "sg:province":"MN",
    "sg:tags":[
        "mortgage"
    ],
    "wof:name":"Swing Mortgage Corp",
    "wof:placetype":"venue"
},
  "geometry": {"coordinates":[-92.846577,44.771988],"type":"Point"}
}