{
  "type": "Feature",
  "properties": {
    "iso:country":"US",
    "sg:address":"1875 19th St NW",
    "sg:city":"Rochester",
    "sg:classifiers":[
        {
            "category":"Health Services",
            "subcategory":"Nursing And Care Facility",
            "type":"Services"
        }
    ],
    "sg:phone":"+1 507 282 9449",
    "sg:postcode":"55901",
    "sg:province":"MN",
    "sg:tags":[
        "home",
        "convalescent"
    ],
    "wof:name":"Maple Manor Nursing Home",
    "wof:placetype":"venue"
},
  "geometry": {"coordinates":[-92.49096900000001,44.04355],"type":"Point"}
}