{
  "type": "Feature",
  "properties": {
    "addr:full":"132 W Main St Perham MN 56573",
    "addr:housenumber":"132",
    "addr:postcode":"56573",
    "addr:street":"W Main St",
    "iso:country":"US",
    "sg:address":"132 W Main St",
    "sg:city":"Perham",
    "sg:classifiers":[
        {
            "category":"Shopping",
            "subcategory":"Shoes",
            "type":"Retail Goods"
        }
    ],
    "sg:phone":"+1 218 346 2605",
    "sg:postcode":"56573",
    "sg:province":"MN",
    "wof:name":"Rae's Shoes",
    "wof:placetype":"venue"
},
  "geometry": {"coordinates":[-95.573655,46.594732],"type":"Point"}
}