{
  "type": "Feature",
  "properties": {
    "addr:full":"5620 Quam Ave NE St Michael MN 55376",
    "addr:postcode":"5620;55376",
    "addr:street":"Quam Ave Ne St",
    "iso:country":"US",
    "sg:address":"5620 Quam Ave NE",
    "sg:city":"St Michael",
    "sg:classifiers":[
        {
            "category":"Wholesale",
            "subcategory":"Electrical",
            "type":"Manufacturing & Wholesale Goods"
        }
    ],
    "sg:phone":"+1 763 428 5500",
    "sg:postcode":"55376",
    "sg:province":"MN",
    "sg:tags":[
        "electric",
        "motor"
    ],
    "wof:name":"Fairlane Motors",
    "wof:placetype":"venue"
},
  "geometry": {"coordinates":[-93.55674399999999,45.236489],"type":"Point"}
}