{
  "type": "Feature",
  "properties": {
    "iso:country":"US",
    "sg:address":"512 Nicollet Ave",
    "sg:city":"Minneapolis",
    "sg:classifiers":[
        {
            "category":"Building & Trades",
            "subcategory":"Electrical",
            "type":"Services"
        }
    ],
    "sg:phone":"+1 612 330 5642",
    "sg:postcode":"55402",
    "sg:province":"MN",
    "sg:tags":[
        "transmission",
        "energy"
    ],
    "wof:name":"Translink Development Company",
    "wof:placetype":"venue"
},
  "geometry": {"coordinates":[-93.271434,44.978005],"type":"Point"}
}