{
  "type": "Feature",
  "properties": {
    "addr:full":"1880 Adams St Mankato MN 56001",
    "addr:housenumber":"1880",
    "addr:postcode":"56001",
    "addr:street":"Adams St",
    "iso:country":"US",
    "sg:address":"1880 Adams St",
    "sg:city":"Mankato",
    "sg:classifiers":[
        {
            "category":"Restaurant",
            "type":"Food & Drink"
        }
    ],
    "sg:phone":"+1 507 388 5559",
    "sg:postcode":"56001",
    "sg:province":"MN",
    "sg:tags":[
        "eating"
    ],
    "wof:name":"Ground Round",
    "wof:placetype":"venue"
},
  "geometry": {"coordinates":[-93.951398,44.170534],"type":"Point"}
}