{
  "type": "Feature",
  "properties": {
    "addr:full":"133 7th Ave N Hopkins MN 55343",
    "addr:housenumber":"133",
    "addr:postcode":"55343",
    "addr:street":"7Th Ave N",
    "iso:country":"US",
    "sg:address":"133 7th Ave N",
    "sg:city":"Hopkins",
    "sg:classifiers":[
        {
            "category":"Social Services",
            "subcategory":"Child Care",
            "type":"Services"
        }
    ],
    "sg:phone":"+1 952 935 7645",
    "sg:postcode":"55343",
    "sg:province":"MN",
    "sg:tags":[
        "day"
    ],
    "wof:name":"Colleen M Jensen",
    "wof:placetype":"venue"
},
  "geometry": {"coordinates":[-93.408644,44.926692],"type":"Point"}
}