{
  "type": "Feature",
  "properties": {
    "iso:country":"US",
    "sg:address":"33025 Jewel Ct",
    "sg:city":"Chisago City",
    "sg:classifiers":[
        {
            "category":"Insurance",
            "subcategory":"Insurance Agent",
            "type":"Services"
        }
    ],
    "sg:phone":"+1 651 257 7700",
    "sg:postcode":"55013",
    "sg:province":"MN",
    "wof:name":"Perrine Lange Agency Inc",
    "wof:placetype":"venue"
},
  "geometry": {"coordinates":[-92.916055,45.42997],"type":"Point"}
}