{
  "type": "Feature",
  "properties": {
    "addr:full":"200 Doctors Park Chaska MN 55318",
    "addr:housenumber":"200",
    "addr:postcode":"55318",
    "addr:street":"Doctors Park",
    "iso:country":"US",
    "sg:address":"200 Doctors Park",
    "sg:city":"Chaska",
    "sg:classifiers":[
        {
            "category":"Health Services",
            "subcategory":"Doctor",
            "type":"Services"
        }
    ],
    "sg:phone":"+1 952 448 2050",
    "sg:postcode":"55318",
    "sg:province":"MN",
    "sg:tags":[
        "practice",
        "family"
    ],
    "wof:name":"Schneider R J MD Crossroads Medical Centers PA",
    "wof:placetype":"venue"
},
  "geometry": {"coordinates":[-93.611397,44.8097],"type":"Point"}
}