{
  "type": "Feature",
  "properties": {
    "addr:full":"3150 Ranchview Ln N Minneapolis MN 55447",
    "addr:housenumber":"3150",
    "addr:postcode":"55447",
    "addr:street":"Ranchview Ln N",
    "iso:country":"US",
    "sg:address":"3150 Ranchview Ln N",
    "sg:city":"Minneapolis",
    "sg:classifiers":[
        {
            "category":"Wholesale",
            "subcategory":"Machinery & Supplies",
            "type":"Manufacturing & Wholesale Goods"
        }
    ],
    "sg:phone":"+1 763 551 0700",
    "sg:postcode":"55447",
    "sg:province":"MN",
    "sg:tags":[
        "janitor"
    ],
    "wof:name":"Janitorial Supplies Wholesale",
    "wof:placetype":"venue"
},
  "geometry": {"coordinates":[-93.476552,45.015593],"type":"Point"}
}