{
  "type": "Feature",
  "properties": {
    "addr:full":"593 Snelling Ave St Paul MN 55104",
    "addr:housenumber":"593",
    "addr:postcode":"55104",
    "addr:street":"Snelling Ave",
    "iso:country":"US",
    "sg:address":"593 Snelling Ave",
    "sg:city":"St Paul",
    "sg:classifiers":[
        {
            "category":"Manufacturing",
            "subcategory":"Signs",
            "type":"Manufacturing & Wholesale Goods"
        }
    ],
    "sg:phone":"+1 651 644 1991",
    "sg:postcode":"55104",
    "sg:province":"MN",
    "sg:tags":[
        "specialty",
        "mfg"
    ],
    "wof:name":"Snappy Signs",
    "wof:placetype":"venue"
},
  "geometry": {"coordinates":[-93.16709,44.95866],"type":"Point"}
}