{
  "type": "Feature",
  "properties": {
    "iso:country":"US",
    "sg:address":"3461 W Broadway Ave",
    "sg:city":"Minneapolis",
    "sg:classifiers":[
        {
            "category":"Cinema",
            "subcategory":"Movie Rental",
            "type":"Entertainment"
        }
    ],
    "sg:phone":"+1 763 521 9550",
    "sg:postcode":"55422",
    "sg:province":"MN",
    "sg:tags":[
        "game",
        "video"
    ],
    "sg:website":"www.blockbuster.com",
    "wof:name":"Blockbuster Video",
    "wof:placetype":"venue"
},
  "geometry": {"coordinates":[-93.324501,45.018299],"type":"Point"}
}