{
  "type": "Feature",
  "properties": {
    "iso:country":"US",
    "sg:address":"1425 Flag Ave S",
    "sg:city":"Minneapolis",
    "sg:classifiers":[
        {
            "category":"Professional",
            "type":"Services"
        }
    ],
    "sg:phone":"+1 952 545 0384",
    "sg:postcode":"55426",
    "sg:province":"MN",
    "sg:tags":[
        "establishment"
    ],
    "wof:name":"Schlosser & Schlosser",
    "wof:placetype":"venue"
},
  "geometry": {"coordinates":[-93.39701599999999,44.968525],"type":"Point"}
}