{
  "type": "Feature",
  "properties": {
    "addr:full":"323 Mindy Ln Montrose MN 55363",
    "addr:housenumber":"323",
    "addr:postcode":"55363",
    "addr:street":"Mindy Ln",
    "iso:country":"US",
    "sg:address":"323 Mindy Ln",
    "sg:city":"Montrose",
    "sg:classifiers":[
        {
            "category":"Social Services",
            "subcategory":"Child Care",
            "type":"Services"
        }
    ],
    "sg:phone":"+1 763 675 3616",
    "sg:postcode":"55363",
    "sg:province":"MN",
    "sg:tags":[
        "nursery",
        "day"
    ],
    "wof:name":"Ronda S Rainbow Childcare",
    "wof:placetype":"venue"
},
  "geometry": {"coordinates":[-93.91885600000001,45.071853],"type":"Point"}
}