{
  "type": "Feature",
  "properties": {
    "addr:full":"11725 54th Ave N Minneapolis MN 55442",
    "addr:housenumber":"11725",
    "addr:postcode":"55442",
    "addr:street":"54Th Ave N",
    "iso:country":"US",
    "sg:address":"11725 54th Ave N",
    "sg:city":"Minneapolis",
    "sg:classifiers":[
        {
            "category":"Building & Trades",
            "subcategory":"Construction",
            "type":"Services"
        }
    ],
    "sg:phone":"+1 763 557 1657",
    "sg:postcode":"55442",
    "sg:province":"MN",
    "sg:tags":[
        "home",
        "general",
        "family",
        "contractor"
    ],
    "wof:name":"Robert Fitch Construction",
    "wof:placetype":"venue"
},
  "geometry": {"coordinates":[-93.429512,45.050872],"type":"Point"}
}