{
  "type": "Feature",
  "properties": {
    "addr:full":"10180 Tyler St NE Minneapolis MN 55434",
    "addr:housenumber":"10180",
    "addr:postcode":"55434",
    "addr:street":"Tyler St Ne",
    "iso:country":"US",
    "sg:address":"10180 Tyler St NE",
    "sg:city":"Minneapolis",
    "sg:classifiers":[
        {
            "category":"Manufacturing",
            "subcategory":"Food",
            "type":"Manufacturing & Wholesale Goods"
        },
        {
            "category":"Farming",
            "subcategory":"Farm",
            "type":"Manufacturing & Wholesale Goods"
        }
    ],
    "sg:phone":"+1 763 785 2830",
    "sg:postcode":"55434",
    "sg:province":"MN",
    "sg:tags":[
        "corn",
        "product"
    ],
    "wof:name":"Schweim Farm",
    "wof:placetype":"venue"
},
  "geometry": {"coordinates":[-93.247676,45.154639],"type":"Point"}
}