{
  "type": "Feature",
  "properties": {
    "addr:full":"14710 32nd Ave N Minneapolis MN 55447",
    "addr:housenumber":"14710",
    "addr:postcode":"55447",
    "addr:street":"32Nd Ave N",
    "iso:country":"US",
    "sg:address":"14710 32nd Ave N",
    "sg:city":"Minneapolis",
    "sg:classifiers":[
        {
            "category":"Health Services",
            "subcategory":"Nursing And Care Facility",
            "type":"Services"
        }
    ],
    "sg:phone":"+1 651 688 8808",
    "sg:postcode":"55447",
    "sg:province":"MN",
    "sg:tags":[
        "intermediate"
    ],
    "wof:name":"Dakota Communities Inc",
    "wof:placetype":"venue"
},
  "geometry": {"coordinates":[-93.467426,45.016122],"type":"Point"}
}