{
  "type": "Feature",
  "properties": {
    "iso:country":"US",
    "sg:address":"1881 Furness St",
    "sg:city":"Saint Paul",
    "sg:classifiers":[
        {
            "category":"Professional",
            "subcategory":"Business Services",
            "type":"Services"
        }
    ],
    "sg:phone":"+1 651 747 8416",
    "sg:postcode":"55109",
    "sg:province":"MN",
    "wof:name":"Penta State Agency Inc",
    "wof:placetype":"venue"
},
  "geometry": {"coordinates":[-93.00943700000001,44.996642],"type":"Point"}
}