{
  "type": "Feature",
  "properties": {
    "addr:full":"180 Co Rd 26 Windom MN 56101",
    "addr:housenumber":"180;26",
    "addr:postcode":"56101",
    "addr:street":"Co Rd",
    "iso:country":"US",
    "sg:address":"180 Co Rd 26",
    "sg:city":"Windom",
    "sg:classifiers":[
        {
            "category":"Government",
            "subcategory":"Office",
            "type":"Public Place"
        }
    ],
    "sg:phone":"+1 507 831 1200",
    "sg:postcode":"56101",
    "sg:province":"MN",
    "sg:tags":[
        "state",
        "program"
    ],
    "sg:website":"www.state.mn.us",
    "wof:name":"Transportation Dept",
    "wof:placetype":"venue"
},
  "geometry": {"coordinates":[-95.101951,43.858843],"type":"Point"}
}