{
  "type": "Feature",
  "properties": {
    "iso:country":"US",
    "sg:address":"4301 Highway 7",
    "sg:city":"Minneapolis",
    "sg:classifiers":[
        {
            "category":"Sports & Exercise",
            "subcategory":"Gym",
            "type":"Entertainment"
        }
    ],
    "sg:phone":"+1 952 920 3060",
    "sg:postcode":"55416",
    "sg:province":"MN",
    "wof:name":"Fitness King",
    "wof:placetype":"venue"
},
  "geometry": {"coordinates":[-93.334,44.947201],"type":"Point"}
}