{
  "type": "Feature",
  "properties": {
    "addr:full":"19065 State Hwy 91 Adrian MN 56110",
    "addr:housenumber":"19065",
    "addr:postcode":"56110",
    "addr:street":"State Hwy 91",
    "iso:country":"US",
    "sg:address":"19065 State Hwy 91",
    "sg:city":"Adrian",
    "sg:phone":"+1 507 472 8405",
    "sg:postcode":"56110",
    "sg:province":"MN",
    "sg:tags":[
        "farm",
        "corn",
        "soybean"
    ],
    "wof:name":"Cyril Gengler",
    "wof:placetype":"venue"
},
  "geometry": {"coordinates":[-95.93291600000001,43.717013],"type":"Point"}
}