{
  "type": "Feature",
  "properties": {
    "addr:full":"1011 2nd St N Brownton MN 55312",
    "addr:housenumber":"1011",
    "addr:postcode":"55312",
    "addr:street":"2Nd St N",
    "iso:country":"US",
    "sg:address":"1011 2nd St N",
    "sg:city":"Brownton",
    "sg:phone":"+1 320 328 5544",
    "sg:postcode":"55312",
    "sg:province":"MN",
    "sg:tags":[
        "farm",
        "corn"
    ],
    "wof:name":"Leonard Pikal",
    "wof:placetype":"venue"
},
  "geometry": {"coordinates":[-94.343681,44.733153],"type":"Point"}
}