{
  "type": "Feature",
  "properties": {
    "addr:full":"304 2nd Ave NE Medford MN 55049",
    "addr:housenumber":"304",
    "addr:postcode":"55049",
    "addr:street":"2Nd Ave Ne",
    "iso:country":"US",
    "sg:address":"304 2nd Ave NE",
    "sg:city":"Medford",
    "sg:classifiers":[
        {
            "category":"Organizations",
            "subcategory":"Non-profit Organization",
            "type":"Services"
        }
    ],
    "sg:phone":"+1 507 451 3356",
    "sg:postcode":"55049",
    "sg:province":"MN",
    "sg:tags":[
        "human"
    ],
    "wof:name":"Our Homes South Inc",
    "wof:placetype":"venue"
},
  "geometry": {"coordinates":[-93.244418,44.174965],"type":"Point"}
}