{
  "type": "Feature",
  "properties": {
    "addr:full":"6810 Greenfield Rd Loretto MN 55357",
    "addr:housenumber":"6810",
    "addr:postcode":"55357",
    "addr:street":"Greenfield Rd",
    "iso:country":"US",
    "sg:address":"6810 Greenfield Rd",
    "sg:city":"Loretto",
    "sg:classifiers":[
        {
            "category":"Professional",
            "subcategory":"Management & Consulting",
            "type":"Services"
        }
    ],
    "sg:phone":"+1 763 477 5599",
    "sg:postcode":"55357",
    "sg:province":"MN",
    "sg:tags":[
        "consultant",
        "business"
    ],
    "sg:website":"www.wwiinncoaching.com",
    "wof:name":"William Mills & Assoc",
    "wof:placetype":"venue"
},
  "geometry": {"coordinates":[-93.686667,45.078606],"type":"Point"}
}