{
  "type": "Feature",
  "properties": {
    "iso:country":"US",
    "sg:address":"1145 Woodhill Dr",
    "sg:city":"Saint Paul",
    "sg:classifiers":[
        {
            "category":"Organizations",
            "subcategory":"Community Association",
            "type":"Services"
        }
    ],
    "sg:phone":"+1 651 483 5313",
    "sg:postcode":"55113",
    "sg:province":"MN",
    "wof:name":"Roseville VFW Post 7555",
    "wof:placetype":"venue"
},
  "geometry": {"coordinates":[-93.14708299999999,45.022825],"type":"Point"}
}