{
  "type": "Feature",
  "properties": {
    "iso:country":"US",
    "sg:address":"13035 297th Ave",
    "sg:city":"Princeton",
    "sg:classifiers":[
        {
            "category":"Retail",
            "subcategory":"Repair Shop",
            "type":"Services"
        }
    ],
    "sg:phone":"+1 763 631 3092",
    "sg:postcode":"55371",
    "sg:province":"MN",
    "wof:name":"Classic Clean Homes",
    "wof:placetype":"venue"
},
  "geometry": {"coordinates":[-93.593903,45.509203],"type":"Point"}
}