{
  "type": "Feature",
  "properties": {
    "iso:country":"US",
    "sg:address":"183 Birnamwood Dr",
    "sg:city":"Burnsville",
    "sg:classifiers":[
        {
            "category":"Social Services",
            "subcategory":"Job Training",
            "type":"Services"
        }
    ],
    "sg:phone":"+1 952 890 6988",
    "sg:postcode":"55337",
    "sg:province":"MN",
    "wof:name":"Professional Dynamics Inc",
    "wof:placetype":"venue"
},
  "geometry": {"coordinates":[-93.25531599999999,44.777805],"type":"Point"}
}