{
  "type": "Feature",
  "properties": {
    "addr:full":"11440 Marketplace Dr N Champlin MN 55316",
    "addr:housenumber":"11440",
    "addr:postcode":"55316",
    "addr:street":"Marketplace Dr N",
    "iso:country":"US",
    "sg:address":"11440 Marketplace Dr N",
    "sg:city":"Champlin",
    "sg:classifiers":[
        {
            "category":"Restaurant",
            "type":"Food & Drink"
        }
    ],
    "sg:phone":"+1 763 712 1869",
    "sg:postcode":"55316",
    "sg:province":"MN",
    "sg:tags":[
        "eating",
        "chinese"
    ],
    "sg:website":"www.enjoychinarestaurant.com/",
    "wof:name":"Enjoy China",
    "wof:placetype":"venue"
},
  "geometry": {"coordinates":[-93.390602,45.1605],"type":"Point"}
}