{
  "type": "Feature",
  "properties": {
    "iso:country":"US",
    "sg:address":"4010 Bloomington Ave S",
    "sg:city":"Minneapolis",
    "sg:classifiers":[
        {
            "category":"Shopping",
            "subcategory":"Pharmacy",
            "type":"Retail Goods"
        }
    ],
    "sg:phone":"+1 612 824 0754",
    "sg:postcode":"55407",
    "sg:province":"MN",
    "sg:tags":[
        "photofinishing",
        "laboratory"
    ],
    "wof:name":"Snyders Drug Store 30",
    "wof:placetype":"venue"
},
  "geometry": {"coordinates":[-93.25246300000001,44.928802],"type":"Point"}
}