{
  "type": "Feature",
  "properties": {
    "iso:country":"US",
    "sg:address":"13245 Co Rd 25",
    "sg:city":"New Ulm",
    "sg:classifiers":[
        {
            "category":"Manufacturing",
            "subcategory":"Signs",
            "type":"Manufacturing & Wholesale Goods"
        }
    ],
    "sg:phone":"+1 507 354 3150",
    "sg:postcode":"56073",
    "sg:province":"MN",
    "wof:name":"Pro-Sign Of New Ulm",
    "wof:placetype":"venue"
},
  "geometry": {"coordinates":[-94.434603,44.267621],"type":"Point"}
}