{
  "type": "Feature",
  "properties": {
    "addr:full":"6740 140th Ave S Sabin MN 56580",
    "addr:housenumber":"6740",
    "addr:postcode":"56580",
    "addr:street":"140Th Ave S Sabin",
    "iso:country":"US",
    "sg:address":"6740 140th Ave S",
    "sg:city":"Sabin",
    "sg:classifiers":[
        {
            "category":"Shopping",
            "type":"Retail Goods"
        }
    ],
    "sg:phone":"+1 218 789 7348",
    "sg:postcode":"56580",
    "sg:province":"MN",
    "sg:tags":[
        "merchandise"
    ],
    "wof:name":"High Impact Sign",
    "wof:placetype":"venue"
},
  "geometry": {"coordinates":[-96.671232,46.688654],"type":"Point"}
}