{
  "type": "Feature",
  "properties": {
    "addr:full":"131 Main St E Freeport MN 56331",
    "addr:housenumber":"131",
    "addr:postcode":"56331",
    "addr:street":"Main St E",
    "iso:country":"US",
    "sg:address":"131 Main St E",
    "sg:city":"Freeport",
    "sg:classifiers":[
        {
            "category":"Retail",
            "subcategory":"Auto Repair",
            "type":"Services"
        }
    ],
    "sg:phone":"+1 320 836 2985",
    "sg:postcode":"56331",
    "sg:province":"MN",
    "sg:tags":[
        "body",
        "repairing",
        "painting",
        "automobile"
    ],
    "wof:name":"Ivan's Auto Body",
    "wof:placetype":"venue"
},
  "geometry": {"coordinates":[-94.68956900000001,45.663285],"type":"Point"}
}