{
  "type": "Feature",
  "properties": {
    "addr:full":"17695 Co Rd 7 Verndale MN 56481",
    "addr:housenumber":"17695",
    "addr:postcode":"56481",
    "addr:street":"Co Rd 7 Verndale",
    "iso:country":"US",
    "sg:address":"17695 Co Rd 7",
    "sg:city":"Verndale",
    "sg:classifiers":[
        {
            "category":"Building & Trades",
            "subcategory":"Construction",
            "type":"Services"
        }
    ],
    "sg:phone":"+1 218 445 5063",
    "sg:postcode":"56481",
    "sg:province":"MN",
    "sg:tags":[
        "house"
    ],
    "wof:name":"Bigtimber Construction Inc",
    "wof:placetype":"venue"
},
  "geometry": {"coordinates":[-95.000868,46.499274],"type":"Point"}
}