{
  "type": "Feature",
  "properties": {
    "addr:full":"321 1st Ave N Minneapolis MN 55401",
    "addr:housenumber":"321",
    "addr:postcode":"55401",
    "addr:street":"1St Ave N",
    "iso:country":"US",
    "sg:address":"321 1st Ave N",
    "sg:city":"Minneapolis",
    "sg:classifiers":[
        {
            "category":"Wholesale",
            "subcategory":"Machinery & Supplies",
            "type":"Manufacturing & Wholesale Goods"
        }
    ],
    "sg:phone":"+1 612 332 1122",
    "sg:postcode":"55401",
    "sg:province":"MN",
    "sg:tags":[
        "equipment",
        "industrial"
    ],
    "wof:name":"Industrial Equities",
    "wof:placetype":"venue"
},
  "geometry": {"coordinates":[-93.272372,44.981368],"type":"Point"}
}