{
  "type": "Feature",
  "properties": {
    "addr:full":"10645 Co Rd 50 Cologne MN 55322",
    "addr:housenumber":"10645;50",
    "addr:postcode":"55322",
    "addr:street":"Co Rd",
    "iso:country":"US",
    "sg:address":"10645 Co Rd 50",
    "sg:city":"Cologne",
    "sg:classifiers":[
        {
            "category":"Building & Trades",
            "subcategory":"Electrical",
            "type":"Services"
        }
    ],
    "sg:phone":"+1 952 466 5937",
    "sg:postcode":"55322",
    "sg:province":"MN",
    "sg:tags":[
        "electrical",
        "contractor"
    ],
    "wof:name":"Dubbe Electric Inc",
    "wof:placetype":"venue"
},
  "geometry": {"coordinates":[-93.79464400000001,44.716974],"type":"Point"}
}