{
  "type": "Feature",
  "properties": {
    "iso:country":"US",
    "sg:address":"430 1st St N",
    "sg:city":"Minneapolis",
    "sg:classifiers":[
        {
            "category":"Professional",
            "subcategory":"Advertising",
            "type":"Services"
        }
    ],
    "sg:phone":"+1 612 321 0744",
    "sg:postcode":"55401",
    "sg:province":"MN",
    "sg:tags":[
        "agency"
    ],
    "wof:name":"Gruggen Buckley Inc",
    "wof:placetype":"venue"
},
  "geometry": {"coordinates":[-93.273224,44.988337],"type":"Point"}
}