{
  "type": "Feature",
  "properties": {
    "iso:country":"US",
    "sg:address":"637 Selby Ave",
    "sg:city":"St Paul",
    "sg:classifiers":[
        {
            "category":"Professional",
            "subcategory":"Management & Consulting",
            "type":"Services"
        }
    ],
    "sg:phone":"+1 651 224 7647",
    "sg:postcode":"55104",
    "sg:province":"MN",
    "sg:tags":[
        "marketing",
        "consultant"
    ],
    "wof:name":"Sensory Logic",
    "wof:placetype":"venue"
},
  "geometry": {"coordinates":[-93.128423,44.946677],"type":"Point"}
}