{
  "type": "Feature",
  "properties": {
    "addr:full":"41754 880th Ave Bird Island MN 55310",
    "addr:housenumber":"41754",
    "addr:postcode":"55310",
    "addr:street":"880Th Ave",
    "iso:country":"US",
    "sg:address":"41754 880th Ave",
    "sg:city":"Bird Island",
    "sg:classifiers":[
        {
            "category":"Farming",
            "subcategory":"Farm",
            "type":"Manufacturing & Wholesale Goods"
        }
    ],
    "sg:phone":"+1 320 365 4780",
    "sg:postcode":"55310",
    "sg:province":"MN",
    "sg:tags":[
        "crop",
        "general"
    ],
    "wof:name":"Ed Woelfel",
    "wof:placetype":"venue"
},
  "geometry": {"coordinates":[-94.83924500000001,44.862591],"type":"Point"}
}