{
  "type": "Feature",
  "properties": {
    "iso:country":"US",
    "sg:address":"16355 36th Ave N",
    "sg:city":"Minneapolis",
    "sg:classifiers":[
        {
            "category":"Professional",
            "subcategory":"Business Services",
            "type":"Services"
        }
    ],
    "sg:phone":"+1 763 544 7200",
    "sg:postcode":"55446",
    "sg:province":"MN",
    "sg:tags":[
        "program",
        "incentive"
    ],
    "sg:website":"www.motivaction.com",
    "wof:name":"Motivaction",
    "wof:placetype":"venue"
},
  "geometry": {"coordinates":[-93.488472,45.023052],"type":"Point"}
}