{
  "type": "Feature",
  "properties": {
    "addr:full":"220 Division St S Northfield MN 55057",
    "addr:housenumber":"220",
    "addr:postcode":"55057",
    "addr:street":"Division St S",
    "iso:country":"US",
    "sg:address":"220 Division St S",
    "sg:city":"Northfield",
    "sg:classifiers":[
        {
            "category":"Professional",
            "type":"Services"
        }
    ],
    "sg:phone":"+1 507 645 4223",
    "sg:postcode":"55057",
    "sg:province":"MN",
    "sg:tags":[
        "establishment"
    ],
    "wof:name":"J C Egbert & Assoc",
    "wof:placetype":"venue"
},
  "geometry": {"coordinates":[-93.159064,44.458346],"type":"Point"}
}