{
  "type": "Feature",
  "properties": {
    "iso:country":"US",
    "sg:address":"5422 Highway 71 NW",
    "sg:city":"Bemidji",
    "sg:classifiers":[
        {
            "category":"Wholesale",
            "subcategory":"Hardware",
            "type":"Manufacturing & Wholesale Goods"
        },
        {
            "category":"Home & Garden",
            "subcategory":"Building Materials",
            "type":"Retail Goods"
        },
        {
            "category":"Building & Trades",
            "subcategory":"Construction",
            "type":"Services"
        }
    ],
    "sg:phone":"+1 218 444 9112",
    "sg:postcode":"56601",
    "sg:province":"MN",
    "sg:tags":[
        "concrete-stamped",
        "decorative",
        "contractor",
        "concrete",
        "shape",
        "hardware-builders",
        "block"
    ],
    "wof:name":"Lakes Concrete Plus",
    "wof:placetype":"venue"
},
  "geometry": {"coordinates":[-94.875021,47.551576],"type":"Point"}
}