{
  "type": "Feature",
  "properties": {
    "iso:country":"US",
    "sg:address":"5224 Northbrook Blvd N",
    "sg:city":"Stillwater",
    "sg:classifiers":[
        {
            "category":"Manufacturing",
            "subcategory":"Signs",
            "type":"Manufacturing & Wholesale Goods"
        }
    ],
    "sg:phone":"+1 651 439 5126",
    "sg:postcode":"55082",
    "sg:province":"MN",
    "wof:name":"Bayside Neon",
    "wof:placetype":"venue"
},
  "geometry": {"coordinates":[-92.82274,45.025758],"type":"Point"}
}