{
  "type": "Feature",
  "properties": {
    "iso:country":"US",
    "sg:address":"1006 County Road 42 W",
    "sg:city":"Burnsville",
    "sg:classifiers":[
        {
            "category":"Restaurant",
            "type":"Food & Drink"
        }
    ],
    "sg:menulink":"http://www.allmenus.com/mn/burnsville/56776-cam-ranh-bay/menu/",
    "sg:phone":"+1 952 898 5366",
    "sg:postcode":"55337",
    "sg:province":"MN",
    "sg:tags":[
        "asian",
        "vietnamese"
    ],
    "wof:name":"Cam Ranh Bay",
    "wof:placetype":"venue"
},
  "geometry": {"coordinates":[-93.26105099999999,44.738106],"type":"Point"}
}