{
  "type": "Feature",
  "properties": {
    "addr:full":"1039 Ruggles St Saint Paul MN 55113",
    "addr:housenumber":"1039",
    "addr:postcode":"55113",
    "addr:street":"Ruggles St",
    "iso:country":"US",
    "sg:address":"1039 Ruggles St",
    "sg:city":"Saint Paul",
    "sg:classifiers":[
        {
            "category":"Social Services",
            "subcategory":"Child Care",
            "type":"Services"
        }
    ],
    "sg:phone":"+1 651 488 5857",
    "sg:postcode":"55113",
    "sg:province":"MN",
    "sg:tags":[
        "day"
    ],
    "wof:name":"Ic Layout Services Inc",
    "wof:placetype":"venue"
},
  "geometry": {"coordinates":[-93.146058,44.996596],"type":"Point"}
}