{
  "type": "Feature",
  "properties": {
    "iso:country":"US",
    "sg:address":"237 State St",
    "sg:city":"Tracy",
    "sg:classifiers":[
        {
            "category":"Social Services",
            "subcategory":"Child Care",
            "type":"Services"
        }
    ],
    "sg:phone":"+1 507 629 3240",
    "sg:postcode":"56175",
    "sg:province":"MN",
    "sg:tags":[
        "daycare",
        "provider"
    ],
    "wof:name":"Gwen Andree",
    "wof:placetype":"venue"
},
  "geometry": {"coordinates":[-95.61162299999999,44.232855],"type":"Point"}
}