{
  "type": "Feature",
  "properties": {
    "iso:country":"US",
    "sg:address":"4510 Wellington Ln N",
    "sg:city":"Minneapolis",
    "sg:classifiers":[
        {
            "category":"Real Estate",
            "subcategory":"Real Estate Agent",
            "type":"Services"
        }
    ],
    "sg:phone":"+1 763 559 6321",
    "sg:postcode":"55442",
    "sg:province":"MN",
    "wof:name":"Oppegard Appraisals",
    "wof:placetype":"venue"
},
  "geometry": {"coordinates":[-93.41692399999999,45.036997],"type":"Point"}
}