{
  "type": "Feature",
  "properties": {
    "addr:full":"190 1st Ave Round Lake MN 56167",
    "addr:housenumber":"190",
    "addr:postcode":"56167",
    "addr:street":"1St Ave",
    "iso:country":"US",
    "sg:address":"190 1st Ave",
    "sg:city":"Round Lake",
    "sg:classifiers":[
        {
            "category":"Building & Trades",
            "subcategory":"Construction",
            "type":"Services"
        }
    ],
    "sg:phone":"+1 507 945 0173",
    "sg:postcode":"56167",
    "sg:province":"MN",
    "sg:tags":[
        "contractor"
    ],
    "wof:name":"Walker Custom Siding",
    "wof:placetype":"venue"
},
  "geometry": {"coordinates":[-95.47089099999999,43.541484],"type":"Point"}
}