{
  "type": "Feature",
  "properties": {
    "iso:country":"US",
    "sg:address":"1015 157th St E",
    "sg:city":"Burnsville",
    "sg:classifiers":[
        {
            "category":"Building & Trades",
            "subcategory":"Construction",
            "type":"Services"
        }
    ],
    "sg:phone":"+1 952 435 5727",
    "sg:postcode":"55306",
    "sg:province":"MN",
    "sg:tags":[
        "resurfacing",
        "floor",
        "laying",
        "refinishing",
        "contractor"
    ],
    "wof:name":"Nokomis Hardwood Floors",
    "wof:placetype":"venue"
},
  "geometry": {"coordinates":[-93.26233499999999,44.717095],"type":"Point"}
}