{
  "type": "Feature",
  "properties": {
    "addr:full":"13911 Ridgedale Dr # 395 Hopkins MN 55305",
    "addr:housenumber":"13911",
    "addr:postcode":"55305",
    "addr:street":"Ridgedale Dr # 395",
    "iso:country":"US",
    "sg:address":"13911 Ridgedale Dr # 395",
    "sg:city":"Hopkins",
    "sg:classifiers":[
        {
            "category":"Health Services",
            "subcategory":"Dentist",
            "type":"Services"
        }
    ],
    "sg:phone":"+1 952 545 8603",
    "sg:postcode":"55305",
    "sg:province":"MN",
    "sg:tags":[
        "clinic",
        "dental"
    ],
    "sg:website":"http://www.parkdental.com",
    "wof:name":"Park Dental",
    "wof:placetype":"venue"
},
  "geometry": {"coordinates":[-93.457088,44.970445],"type":"Point"}
}