{
  "type": "Feature",
  "properties": {
    "addr:full":"14895 318th St Center City MN 55012",
    "addr:housenumber":"14895",
    "addr:postcode":"55012",
    "addr:street":"318Th St",
    "iso:country":"US",
    "sg:address":"14895 318th St",
    "sg:city":"Center City",
    "sg:classifiers":[
        {
            "category":"Building & Trades",
            "subcategory":"Construction",
            "type":"Services"
        }
    ],
    "sg:phone":"+1 651 257 4136",
    "sg:postcode":"55012",
    "sg:province":"MN",
    "sg:tags":[
        "painter"
    ],
    "wof:name":"Savro Painting & Finishing",
    "wof:placetype":"venue"
},
  "geometry": {"coordinates":[-92.80525799999999,45.408647],"type":"Point"}
}