{
  "type": "Feature",
  "properties": {
    "iso:country":"US",
    "sg:address":"7650 Peony Ln N",
    "sg:city":"Osseo",
    "sg:classifiers":[
        {
            "category":"Utilities",
            "subcategory":"Telephone",
            "type":"Services"
        }
    ],
    "sg:phone":"+1 763 242 9439",
    "sg:postcode":"55311",
    "sg:province":"MN",
    "sg:tags":[
        "web",
        "internet",
        "hosting",
        "provider"
    ],
    "wof:name":"Nslink Hosting Services",
    "wof:placetype":"venue"
},
  "geometry": {"coordinates":[-93.507389,45.094312],"type":"Point"}
}