{
  "type": "Feature",
  "properties": {
    "addr:full":"626 S Holcombe Ave Litchfield MN 55355",
    "addr:housenumber":"626",
    "addr:postcode":"55355",
    "addr:street":"S Holcombe Ave",
    "iso:country":"US",
    "sg:address":"626 S Holcombe Ave",
    "sg:city":"Litchfield",
    "sg:classifiers":[
        {
            "category":"Building & Trades",
            "subcategory":"Electrical",
            "type":"Services"
        }
    ],
    "sg:phone":"+1 320 693 8975",
    "sg:postcode":"55355",
    "sg:province":"MN",
    "sg:tags":[
        "electrical",
        "contractor"
    ],
    "wof:name":"Landers Electric Inc",
    "wof:placetype":"venue"
},
  "geometry": {"coordinates":[-94.525232,45.11986],"type":"Point"}
}