{
  "type": "Feature",
  "properties": {
    "iso:country":"US",
    "sg:address":"14250 Burnhaven Dr",
    "sg:city":"Burnsville",
    "sg:classifiers":[
        {
            "category":"Home & Garden",
            "subcategory":"Building Materials",
            "type":"Retail Goods"
        },
        {
            "category":"Home & Garden",
            "subcategory":"Home Furnishings",
            "type":"Retail Goods"
        },
        {
            "category":"Home & Garden",
            "subcategory":"Hardware",
            "type":"Retail Goods"
        },
        {
            "category":"Wholesale",
            "subcategory":"Home Furnishings",
            "type":"Manufacturing & Wholesale Goods"
        }
    ],
    "sg:phone":"+1 952 898 2754",
    "sg:postcode":"55306",
    "sg:province":"MN",
    "sg:tags":[
        "household",
        "fixture",
        "system",
        "equipment",
        "lighting",
        "fan"
    ],
    "sg:website":"www.fanmanlighting.com",
    "wof:name":"Fan Man Lighting",
    "wof:placetype":"venue"
},
  "geometry": {"coordinates":[-93.294945,44.743973],"type":"Point"}
}