{
  "type": "Feature",
  "properties": {
    "iso:country":"US",
    "sg:address":"1172 Cliff Rd E",
    "sg:city":"Burnsville",
    "sg:classifiers":[
        {
            "category":"Shopping",
            "subcategory":"Stationery & Office Supplies",
            "type":"Retail Goods"
        }
    ],
    "sg:phone":"+1 952 808 8747",
    "sg:postcode":"55337",
    "sg:province":"MN",
    "sg:tags":[
        "equipment"
    ],
    "wof:name":"Cary Computing Solutions",
    "wof:placetype":"venue"
},
  "geometry": {"coordinates":[-93.258904,44.790199],"type":"Point"}
}