{
  "type": "Feature",
  "properties": {
    "addr:full":"15513 Grove Cir N Maple Grove MN 55369",
    "addr:housenumber":"15513",
    "addr:postcode":"55369",
    "addr:street":"Grove Cir N",
    "iso:country":"US",
    "sg:address":"15513 Grove Cir N",
    "sg:city":"Maple Grove",
    "sg:classifiers":[
        {
            "category":"Building & Trades",
            "subcategory":"Construction",
            "type":"Services"
        }
    ],
    "sg:phone":"+1 763 420 7134",
    "sg:postcode":"55369",
    "sg:province":"MN",
    "sg:tags":[
        "contractor"
    ],
    "wof:name":"Ryan Companies",
    "wof:placetype":"venue"
},
  "geometry": {"coordinates":[-93.477051,45.134778],"type":"Point"}
}