{
  "type": "Feature",
  "properties": {
    "addr:full":"10572 France Ave S Minneapolis MN 55431",
    "addr:postcode":"10572;55431",
    "addr:street":"Ave S",
    "iso:country":"US",
    "sg:address":"10572 France Ave S",
    "sg:city":"Minneapolis",
    "sg:classifiers":[
        {
            "category":"Military Area",
            "type":"Public Place"
        }
    ],
    "sg:phone":"+1 952 881 6911",
    "sg:postcode":"55431",
    "sg:province":"MN",
    "sg:tags":[
        "force",
        "armed",
        "recruiting"
    ],
    "sg:website":"http://www.marines.com",
    "wof:name":"United States Marine Corps",
    "wof:placetype":"venue"
},
  "geometry": {"coordinates":[-93.329531,44.812232],"type":"Point"}
}