{
  "type": "Feature",
  "properties": {
    "iso:country":"US",
    "sg:address":"10808 Glen Wilding Ln",
    "sg:city":"Minneapolis",
    "sg:classifiers":[
        {
            "category":"Professional",
            "subcategory":"Lawyer & Legal Services",
            "type":"Services"
        }
    ],
    "sg:phone":"+1 952 884 6408",
    "sg:postcode":"55431",
    "sg:province":"MN",
    "wof:name":"McCormick Mary K McCormick International Atty",
    "wof:placetype":"venue"
},
  "geometry": {"coordinates":[-93.29949999999999,44.807899],"type":"Point"}
}