{
  "type": "Feature",
  "properties": {
    "addr:full":"2279 Marshall Ave St Paul MN 55104",
    "addr:housenumber":"2279",
    "addr:postcode":"55104",
    "addr:street":"Marshall Ave",
    "iso:country":"US",
    "sg:address":"2279 Marshall Ave",
    "sg:city":"St Paul",
    "sg:classifiers":[
        {
            "category":"Organizations",
            "subcategory":"Community Association",
            "type":"Services"
        }
    ],
    "sg:phone":"+1 651 646 7126",
    "sg:postcode":"55104",
    "sg:province":"MN",
    "sg:tags":[
        "club"
    ],
    "wof:name":"Town & Country Club",
    "wof:placetype":"venue"
},
  "geometry": {"coordinates":[-93.197783,44.948427],"type":"Point"}
}