{
  "type": "Feature",
  "properties": {
    "addr:full":"268 Dayton Ave Saint Paul MN 55102",
    "addr:housenumber":"268",
    "addr:postcode":"55102",
    "addr:street":"Dayton Ave",
    "iso:country":"US",
    "sg:address":"268 Dayton Ave",
    "sg:city":"Saint Paul",
    "sg:classifiers":[
        {
            "category":"Professional",
            "subcategory":"Business Services",
            "type":"Services"
        }
    ],
    "sg:phone":"+1 651 225 4338",
    "sg:postcode":"55102",
    "sg:province":"MN",
    "wof:name":"Music Inc",
    "wof:placetype":"venue"
},
  "geometry": {"coordinates":[-93.112391,44.947299],"type":"Point"}
}