{
  "type": "Feature",
  "properties": {
    "iso:country":"US",
    "sg:address":"8316 Pillsbury Ave S",
    "sg:city":"Minneapolis",
    "sg:classifiers":[
        {
            "category":"Autos & Motor Vehicles",
            "subcategory":"Automobile Sales",
            "type":"Retail Goods"
        }
    ],
    "sg:phone":"+1 612 386 6301",
    "sg:postcode":"55420",
    "sg:province":"MN",
    "sg:tags":[
        "new",
        "car"
    ],
    "wof:name":"K 2 Auto Group",
    "wof:placetype":"venue"
},
  "geometry": {"coordinates":[-93.282174,44.853238],"type":"Point"}
}