{
  "type": "Feature",
  "properties": {
    "addr:full":"1396 16th Ave NW Saint Paul MN 55112",
    "addr:housenumber":"1396",
    "addr:postcode":"55112",
    "addr:street":"16Th Ave Nw",
    "iso:country":"US",
    "sg:address":"1396 16th Ave NW",
    "sg:city":"Saint Paul",
    "sg:classifiers":[
        {
            "category":"Professional",
            "type":"Services"
        }
    ],
    "sg:phone":"+1 651 636 9415",
    "sg:postcode":"55112",
    "sg:province":"MN",
    "wof:name":"Monetary Resources",
    "wof:placetype":"venue"
},
  "geometry": {"coordinates":[-93.208536,45.070171],"type":"Point"}
}