{
  "type": "Feature",
  "properties": {
    "iso:country":"US",
    "sg:address":"5650 Starview Ln",
    "sg:city":"Prior Lake",
    "sg:classifiers":[
        {
            "category":"Building & Trades",
            "subcategory":"Construction",
            "type":"Services"
        }
    ],
    "sg:phone":"+1 952 447 7300",
    "sg:postcode":"55372",
    "sg:province":"MN",
    "sg:tags":[
        "installs",
        "modular",
        "retaining",
        "block",
        "wall"
    ],
    "wof:name":"Advanced Wall Structures",
    "wof:placetype":"venue"
},
  "geometry": {"coordinates":[-93.416641,44.662828],"type":"Point"}
}