{
  "type": "Feature",
  "properties": {
    "iso:country":"US",
    "sg:address":"10900 Hampshire Ave S",
    "sg:city":"Minneapolis",
    "sg:classifiers":[
        {
            "category":"Health Services",
            "subcategory":"Hospital",
            "type":"Services"
        },
        {
            "category":"Insurance",
            "subcategory":"Hazard Insurance",
            "type":"Services"
        },
        {
            "category":"Banks & Credit Unions",
            "subcategory":"Financial Services",
            "type":"Services"
        },
        {
            "category":"Insurance",
            "subcategory":"Health Insurance",
            "type":"Services"
        }
    ],
    "sg:phone":"+1 952 829 3500",
    "sg:postcode":"55438",
    "sg:province":"MN",
    "sg:tags":[
        "sharing",
        "hospitalization",
        "profit",
        "medical",
        "surgical",
        "benefit",
        "pension",
        "employee",
        "plan"
    ],
    "wof:name":"C B C A",
    "wof:placetype":"venue"
},
  "geometry": {"coordinates":[-93.368713,44.804836],"type":"Point"}
}