{
  "type": "Feature",
  "properties": {
    "iso:country":"US",
    "sg:address":"224 4th St NE",
    "sg:city":"Staples",
    "sg:classifiers":[
        {
            "category":"Manufacturing",
            "subcategory":"Printing",
            "type":"Manufacturing & Wholesale Goods"
        }
    ],
    "sg:phone":"+1 218 894 1112",
    "sg:postcode":"56479",
    "sg:province":"MN",
    "sg:tags":[
        "newspaper"
    ],
    "wof:name":"Staples World",
    "wof:placetype":"venue"
},
  "geometry": {"coordinates":[-94.79481199999999,46.356437],"type":"Point"}
}