{
  "type": "Feature",
  "properties": {
    "addr:full":"7082 Elder Ave NW Maple Lake MN 55358",
    "addr:housenumber":"7082",
    "addr:postcode":"55358",
    "addr:street":"Elder Ave Nw",
    "iso:country":"US",
    "sg:address":"7082 Elder Ave NW",
    "sg:city":"Maple Lake",
    "sg:classifiers":[
        {
            "category":"Farming",
            "subcategory":"Poultry Farm",
            "type":"Manufacturing & Wholesale Goods"
        }
    ],
    "sg:phone":"+1 320 963 3278",
    "sg:postcode":"55358",
    "sg:province":"MN",
    "sg:tags":[
        "egg"
    ],
    "wof:name":"Wright Wing Game Farm",
    "wof:placetype":"venue"
},
  "geometry": {"coordinates":[-93.973527,45.248673],"type":"Point"}
}