{
  "type": "Feature",
  "properties": {
    "addr:full":"13901 Aldrich Ave S Burnsville MN 55337",
    "addr:housenumber":"13901",
    "addr:postcode":"55337",
    "addr:street":"Aldrich Ave S",
    "iso:country":"US",
    "sg:address":"13901 Aldrich Ave S",
    "sg:city":"Burnsville",
    "sg:classifiers":[
        {
            "category":"Shopping",
            "subcategory":"Hobbies, Toys, & Games",
            "type":"Retail Goods"
        }
    ],
    "sg:phone":"+1 651 894 4119",
    "sg:postcode":"55337",
    "sg:province":"MN",
    "sg:tags":[
        "arts",
        "craft",
        "specialty"
    ],
    "wof:name":"Michaels 8608",
    "wof:placetype":"venue"
},
  "geometry": {"coordinates":[-93.288115,44.75111],"type":"Point"}
}