{
  "type": "Feature",
  "properties": {
    "addr:full":"15590 240th Ave New Richland MN 56072",
    "addr:housenumber":"15590",
    "addr:postcode":"56072",
    "addr:street":"240Th Ave",
    "iso:country":"US",
    "sg:address":"15590 240th Ave",
    "sg:city":"New Richland",
    "sg:classifiers":[
        {
            "category":"Sports & Exercise",
            "subcategory":"Golf",
            "type":"Entertainment"
        }
    ],
    "sg:phone":"+1 507 465 3516",
    "sg:postcode":"56072",
    "sg:province":"MN",
    "sg:tags":[
        "course"
    ],
    "wof:name":"Riverview Golf Course",
    "wof:placetype":"venue"
},
  "geometry": {"coordinates":[-93.454679,43.906083],"type":"Point"}
}