{
  "type": "Feature",
  "properties": {
    "iso:country":"US",
    "sg:address":"2701 Xylon Ave N",
    "sg:city":"Minneapolis",
    "sg:classifiers":[
        {
            "category":"Shopping",
            "subcategory":"Gifts & Souvenirs",
            "type":"Retail Goods"
        }
    ],
    "sg:phone":"+1 763 525 1998",
    "sg:postcode":"55427",
    "sg:province":"MN",
    "sg:tags":[
        "shop"
    ],
    "wof:name":"Heaven Sent Specialty Gifts",
    "wof:placetype":"venue"
},
  "geometry": {"coordinates":[-93.38531500000001,45.00868],"type":"Point"}
}