{
  "type": "Feature",
  "properties": {
    "iso:country":"US",
    "sg:address":"1730 New Brighton Blvd",
    "sg:city":"Minneapolis",
    "sg:classifiers":[
        {
            "category":"Health Services",
            "subcategory":"Medical Lab",
            "type":"Services"
        }
    ],
    "sg:phone":"+1 612 384 3968",
    "sg:postcode":"55413",
    "sg:province":"MN",
    "sg:tags":[
        "laboratory"
    ],
    "wof:name":"Personal Lab Services",
    "wof:placetype":"venue"
},
  "geometry": {"coordinates":[-93.228348,45.003528],"type":"Point"}
}