{
  "type": "Feature",
  "properties": {
    "iso:country":"US",
    "sg:address":"9114 Tyler St NE",
    "sg:city":"Minneapolis",
    "sg:classifiers":[
        {
            "category":"Utilities",
            "type":"Services"
        }
    ],
    "sg:phone":"+1 763 786 8803",
    "sg:postcode":"55434",
    "sg:province":"MN",
    "sg:tags":[
        "sanitary"
    ],
    "wof:name":"Breske Snow and Dirt Remo",
    "wof:placetype":"venue"
},
  "geometry": {"coordinates":[-93.247052,45.1367],"type":"Point"}
}