{
  "type": "Feature",
  "properties": {
    "addr:full":"6160 Summit Dr N Minneapolis MN 55430",
    "addr:housenumber":"6160",
    "addr:postcode":"55430",
    "addr:street":"Summit Dr N",
    "iso:country":"US",
    "sg:address":"6160 Summit Dr N",
    "sg:city":"Minneapolis",
    "sg:classifiers":[
        {
            "category":"Manufacturing",
            "subcategory":"Printing",
            "type":"Manufacturing & Wholesale Goods"
        }
    ],
    "sg:phone":"+1 763 595 0808",
    "sg:postcode":"55430",
    "sg:province":"MN",
    "sg:tags":[
        "publishing",
        "periodical"
    ],
    "wof:name":"Tpg Sports Inc",
    "wof:placetype":"venue"
},
  "geometry": {"coordinates":[-93.304329,45.064074],"type":"Point"}
}