{
  "type": "Feature",
  "properties": {
    "addr:full":"3055 State Hwy 200 Ada MN 56510",
    "addr:housenumber":"3055",
    "addr:postcode":"56510",
    "addr:street":"State Hwy 200",
    "iso:country":"US",
    "sg:address":"3055 State Hwy 200",
    "sg:city":"Ada",
    "sg:phone":"+1 218 784 4137",
    "sg:postcode":"56510",
    "sg:province":"MN",
    "sg:tags":[
        "farm",
        "field",
        "crop"
    ],
    "wof:name":"Peterson Marlen",
    "wof:placetype":"venue"
},
  "geometry": {"coordinates":[-96.40710900000001,47.296087],"type":"Point"}
}