{
  "type": "Feature",
  "properties": {
    "addr:full":"19910 Larkin Rd Hamel MN 55340",
    "addr:housenumber":"19910",
    "addr:postcode":"55340",
    "addr:street":"Larkin Rd",
    "iso:country":"US",
    "sg:address":"19910 Larkin Rd",
    "sg:city":"Hamel",
    "sg:classifiers":[
        {
            "category":"Building & Trades",
            "subcategory":"Landscaping Services",
            "type":"Services"
        },
        {
            "category":"Home & Garden",
            "subcategory":"Building Materials",
            "type":"Retail Goods"
        }
    ],
    "sg:phone":"+1 763 416 2183",
    "sg:postcode":"55340",
    "sg:province":"MN",
    "sg:tags":[
        "designer",
        "wall",
        "consultant",
        "contractor",
        "retaining",
        "landscape"
    ],
    "sg:website":"http://www.lawn-care-minnesota.com/index.html",
    "wof:name":"Permagreen Lawn and Landscape",
    "wof:placetype":"venue"
},
  "geometry": {"coordinates":[-93.543318,45.087657],"type":"Point"}
}