{
  "type": "Feature",
  "properties": {
    "iso:country":"US",
    "sg:address":"5636 E Lake Carlos Dr NE",
    "sg:city":"Alexandria",
    "sg:classifiers":[
        {
            "category":"Manufacturing",
            "subcategory":"Textiles",
            "type":"Manufacturing & Wholesale Goods"
        }
    ],
    "sg:phone":"+1 320 846 6042",
    "sg:postcode":"56308",
    "sg:province":"MN",
    "sg:tags":[
        "coated",
        "fabric",
        "mfg"
    ],
    "wof:name":"Minnesota Gopher State SE",
    "wof:placetype":"venue"
},
  "geometry": {"coordinates":[-95.352013,45.947924],"type":"Point"}
}