{
  "type": "Feature",
  "properties": {
    "addr:full":"2813 W 54th St Minneapolis MN 55410",
    "addr:housenumber":"2813",
    "addr:postcode":"55410",
    "addr:street":"W 54Th St",
    "iso:country":"US",
    "sg:address":"2813 W 54th St",
    "sg:city":"Minneapolis",
    "sg:classifiers":[
        {
            "category":"Personal",
            "type":"Services"
        }
    ],
    "sg:phone":"+1 612 285 2871",
    "sg:postcode":"55410",
    "sg:province":"MN",
    "sg:tags":[
        "image",
        "consultants-personal"
    ],
    "wof:name":"Make Up By Michelle",
    "wof:placetype":"venue"
},
  "geometry": {"coordinates":[-93.31462999999999,44.905178],"type":"Point"}
}