{
  "type": "Feature",
  "properties": {
    "addr:full":"10829 Greenbrier Rd Hopkins MN 55305",
    "addr:housenumber":"10829",
    "addr:postcode":"55305",
    "addr:street":"Greenbrier Rd",
    "iso:country":"US",
    "sg:address":"10829 Greenbrier Rd",
    "sg:city":"Hopkins",
    "sg:classifiers":[
        {
            "category":"Professional",
            "subcategory":"Advertising",
            "type":"Services"
        }
    ],
    "sg:phone":"+1 952 541 0196",
    "sg:postcode":"55305",
    "sg:province":"MN",
    "sg:tags":[
        "mail",
        "direct"
    ],
    "wof:name":"Carlco Bindery & Mailing Co",
    "wof:placetype":"venue"
},
  "geometry": {"coordinates":[-93.416433,44.950904],"type":"Point"}
}