{
  "type": "Feature",
  "properties": {
    "iso:country":"US",
    "sg:address":"19515 Chippendale Ave W",
    "sg:city":"Farmington",
    "sg:classifiers":[
        {
            "category":"Building & Trades",
            "subcategory":"Landscaping Services",
            "type":"Services"
        }
    ],
    "sg:phone":"+1 651 463 2271",
    "sg:postcode":"55024",
    "sg:province":"MN",
    "sg:tags":[
        "topsoil"
    ],
    "wof:name":"Independent Black Dirt Co Inc",
    "wof:placetype":"venue"
},
  "geometry": {"coordinates":[-93.136692,44.665958],"type":"Point"}
}