{
  "type": "Feature",
  "properties": {
    "addr:full":"245 Triangle Ln N Jordan MN 55352",
    "addr:housenumber":"245",
    "addr:postcode":"55352",
    "addr:street":"Triangle Ln N",
    "iso:country":"US",
    "sg:address":"245 Triangle Ln N",
    "sg:city":"Jordan",
    "sg:classifiers":[
        {
            "category":"Autos & Motor Vehicles",
            "subcategory":"Automobile Sales",
            "type":"Retail Goods"
        }
    ],
    "sg:phone":"+1 952 492 5551",
    "sg:postcode":"55352",
    "sg:province":"MN",
    "sg:tags":[
        "new",
        "car"
    ],
    "wof:name":"Buy Right Auto Sale",
    "wof:placetype":"venue"
},
  "geometry": {"coordinates":[-93.637697,44.670533],"type":"Point"}
}