{
  "type": "Feature",
  "properties": {
    "iso:country":"US",
    "sg:address":"220 W Elm St",
    "sg:city":"Norwood",
    "sg:classifiers":[
        {
            "category":"Personal",
            "subcategory":"Beauty Salon",
            "type":"Services"
        }
    ],
    "sg:phone":"+1 952 467 2255",
    "sg:postcode":"55368",
    "sg:province":"MN",
    "wof:name":"Chameleon Salon",
    "wof:placetype":"venue"
},
  "geometry": {"coordinates":[-93.926992,44.767997],"type":"Point"}
}