{
  "type": "Feature",
  "properties": {
    "iso:country":"US",
    "sg:address":"6616 Cody St",
    "sg:city":"Duluth",
    "sg:classifiers":[
        {
            "category":"Shopping",
            "subcategory":"Florist",
            "type":"Retail Goods"
        }
    ],
    "sg:phone":"+1 218 628 1091",
    "sg:postcode":"55807",
    "sg:province":"MN",
    "sg:website":"www.samsflorist.com",
    "wof:name":"Sams Florist & Greenhouses",
    "wof:placetype":"venue"
},
  "geometry": {"coordinates":[-92.18303400000001,46.740214],"type":"Point"}
}