{
  "type": "Feature",
  "properties": {
    "addr:full":"512 Lake Shore Dr Sauk Centre MN 56378",
    "addr:housenumber":"512",
    "addr:postcode":"56378",
    "addr:street":"Lake Shore Dr",
    "iso:country":"US",
    "sg:address":"512 Lake Shore Dr",
    "sg:city":"Sauk Centre",
    "sg:phone":"+1 320 352 2364",
    "sg:postcode":"56378",
    "sg:province":"MN",
    "sg:tags":[
        "farm",
        "corn"
    ],
    "wof:name":"David Sillerud",
    "wof:placetype":"venue"
},
  "geometry": {"coordinates":[-94.95688,45.747645],"type":"Point"}
}