{
  "type": "Feature",
  "properties": {
    "addr:full":"5476 Wyoming Trl Wyoming MN 55092",
    "addr:housenumber":"5476",
    "addr:postcode":"55092",
    "addr:street":"Wyoming Trl",
    "iso:country":"US",
    "sg:address":"5476 Wyoming Trl",
    "sg:city":"Wyoming",
    "sg:classifiers":[
        {
            "category":"Social Services",
            "subcategory":"Child Care",
            "type":"Services"
        }
    ],
    "sg:phone":"+1 651 462 4588",
    "sg:postcode":"55092",
    "sg:province":"MN",
    "sg:tags":[
        "daycare",
        "provider"
    ],
    "wof:name":"Caroline Henry",
    "wof:placetype":"venue"
},
  "geometry": {"coordinates":[-92.99576399999999,45.332999],"type":"Point"}
}