{
  "type": "Feature",
  "properties": {
    "addr:full":"1544 Sheldon St Saint Paul MN 55108",
    "addr:housenumber":"1544",
    "addr:postcode":"55108",
    "addr:street":"Sheldon St",
    "iso:country":"US",
    "sg:address":"1544 Sheldon St",
    "sg:city":"Saint Paul",
    "sg:classifiers":[
        {
            "category":"Health Services",
            "subcategory":"Health Practitioner",
            "type":"Services"
        }
    ],
    "sg:phone":"+1 651 646 3091",
    "sg:postcode":"55108",
    "sg:province":"MN",
    "wof:name":"Global Ansthsia Bus Assocaites",
    "wof:placetype":"venue"
},
  "geometry": {"coordinates":[-93.157842,44.987804],"type":"Point"}
}