{
  "type": "Feature",
  "properties": {
    "addr:full":"8 W 60th St Minneapolis MN 55419",
    "addr:housenumber":"8",
    "addr:postcode":"55419",
    "addr:street":"W 60Th St",
    "iso:country":"US",
    "sg:address":"8 W 60th St",
    "sg:city":"Minneapolis",
    "sg:classifiers":[
        {
            "category":"Education",
            "subcategory":"Special Training",
            "type":"Public Place"
        }
    ],
    "sg:phone":"+1 612 871 1340",
    "sg:postcode":"55419",
    "sg:province":"MN",
    "sg:tags":[
        "tutoring"
    ],
    "wof:name":"I AM Learning Ctr",
    "wof:placetype":"venue"
},
  "geometry": {"coordinates":[-93.279304,44.893828],"type":"Point"}
}