{
  "type": "Feature",
  "properties": {
    "iso:country":"US",
    "sg:address":"7975 210th St N",
    "sg:city":"Hawley",
    "sg:classifiers":[
        {
            "category":"Building & Trades",
            "subcategory":"Cleaning & Sanitation",
            "type":"Services"
        }
    ],
    "sg:phone":"+1 218 483 4161",
    "sg:postcode":"56549",
    "sg:province":"MN",
    "sg:tags":[
        "maintenance"
    ],
    "wof:name":"A & B Window Cleaning",
    "wof:placetype":"venue"
},
  "geometry": {"coordinates":[-96.364248,46.953913],"type":"Point"}
}