{
  "type": "Feature",
  "properties": {
    "iso:country":"US",
    "sg:address":"710 W 96th St",
    "sg:city":"Bloomington",
    "sg:classifiers":[
        {
            "category":"Building & Trades",
            "subcategory":"Landscaping Services",
            "type":"Services"
        }
    ],
    "sg:phone":"+1 952 881 1575",
    "sg:postcode":"55420",
    "sg:province":"MN",
    "sg:tags":[
        "lawn",
        "maintenance",
        "grounds"
    ],
    "wof:name":"True Cut",
    "wof:placetype":"venue"
},
  "geometry": {"coordinates":[-93.289787,44.829966],"type":"Point"}
}