{
  "type": "Feature",
  "properties": {
    "addr:full":"8040 40th St SW Montevideo MN 56265",
    "addr:housenumber":"8040",
    "addr:postcode":"56265",
    "addr:street":"40Th St Sw",
    "iso:country":"US",
    "sg:address":"8040 40th St SW",
    "sg:city":"Montevideo",
    "sg:classifiers":[
        {
            "category":"Autos & Motor Vehicles",
            "subcategory":"Auto Supplies",
            "type":"Retail Goods"
        },
        {
            "category":"Manufacturing",
            "subcategory":"Motor Vehicles & Parts",
            "type":"Manufacturing & Wholesale Goods"
        },
        {
            "category":"Retail",
            "subcategory":"Auto Repair",
            "type":"Services"
        }
    ],
    "sg:phone":"+1 320 269 8405",
    "sg:postcode":"56265",
    "sg:province":"MN",
    "sg:tags":[
        "body",
        "shop",
        "buses-distributors",
        "automobile",
        "removal",
        "buses-parts",
        "equipment",
        "parts",
        "accessories-wholesale",
        "dent",
        "painting",
        "repairing",
        "manufacturer"
    ],
    "wof:name":"Dyshaw Auto Body",
    "wof:placetype":"venue"
},
  "geometry": {"coordinates":[-95.756832,44.96394],"type":"Point"}
}