{
  "type": "Feature",
  "properties": {
    "addr:full":"950 5th St W Northfield MN 55057",
    "addr:housenumber":"950",
    "addr:postcode":"55057",
    "addr:street":"5Th St W",
    "iso:country":"US",
    "sg:address":"950 5th St W",
    "sg:city":"Northfield",
    "sg:classifiers":[
        {
            "category":"Professional",
            "subcategory":"Advertising",
            "type":"Services"
        }
    ],
    "sg:phone":"+1 507 663 8974",
    "sg:postcode":"55057",
    "sg:province":"MN",
    "sg:tags":[
        "mailing",
        "shipping"
    ],
    "wof:name":"CMI",
    "wof:placetype":"venue"
},
  "geometry": {"coordinates":[-93.173112,44.454817],"type":"Point"}
}