{
  "type": "Feature",
  "properties": {
    "addr:full":"1323 Barclay St Saint Paul MN 55106",
    "addr:housenumber":"1323",
    "addr:postcode":"55106",
    "addr:street":"Barclay St",
    "iso:country":"US",
    "sg:address":"1323 Barclay St",
    "sg:city":"Saint Paul",
    "sg:classifiers":[
        {
            "category":"Professional",
            "type":"Services"
        }
    ],
    "sg:phone":"+1 651 774 8973",
    "sg:postcode":"55106",
    "sg:province":"MN",
    "wof:name":"Kod Inc",
    "wof:placetype":"venue"
},
  "geometry": {"coordinates":[-93.03807399999999,44.9847],"type":"Point"}
}