{
  "type": "Feature",
  "properties": {
    "iso:country":"US",
    "sg:address":"4201 W Division St",
    "sg:city":"St Cloud",
    "sg:classifiers":[
        {
            "category":"Restaurant",
            "type":"Food & Drink"
        }
    ],
    "sg:phone":"+1 320 252 1791",
    "sg:postcode":"56301",
    "sg:province":"MN",
    "wof:name":"Zeppole's Pizza & Pasta",
    "wof:placetype":"venue"
},
  "geometry": {"coordinates":[-94.212526,45.553478],"type":"Point"}
}