{
  "type": "Feature",
  "properties": {
    "addr:full":"8675 Keenan Rd Iron MN 55751",
    "addr:housenumber":"8675",
    "addr:postcode":"55751",
    "addr:street":"Keenan Rd",
    "iso:country":"US",
    "sg:address":"8675 Keenan Rd",
    "sg:city":"Iron",
    "sg:classifiers":[
        {
            "category":"Building & Trades",
            "subcategory":"Construction",
            "type":"Services"
        }
    ],
    "sg:phone":"+1 218 744 4827",
    "sg:postcode":"55751",
    "sg:province":"MN",
    "sg:tags":[
        "house"
    ],
    "wof:name":"Northern Pole Builders",
    "wof:placetype":"venue"
},
  "geometry": {"coordinates":[-92.59151300000001,47.386691],"type":"Point"}
}