{
  "type": "Feature",
  "properties": {
    "iso:country":"US",
    "sg:address":"3710 153rd Ave NE",
    "sg:city":"Anoka",
    "sg:classifiers":[
        {
            "category":"Building & Trades",
            "subcategory":"Construction",
            "type":"Services"
        }
    ],
    "sg:phone":"+1 763 413 1169",
    "sg:postcode":"55304",
    "sg:province":"MN",
    "sg:tags":[
        "house"
    ],
    "wof:name":"Stoneridge Builder Inc",
    "wof:placetype":"venue"
},
  "geometry": {"coordinates":[-93.17477700000001,45.24777],"type":"Point"}
}