{
  "type": "Feature",
  "properties": {
    "addr:full":"10424 860th Ave Glenville MN 56036",
    "addr:housenumber":"10424",
    "addr:postcode":"56036",
    "addr:street":"860Th Ave",
    "iso:country":"US",
    "sg:address":"10424 860th Ave",
    "sg:city":"Glenville",
    "sg:classifiers":[
        {
            "category":"Farming",
            "subcategory":"Livestock Farm",
            "type":"Manufacturing & Wholesale Goods"
        }
    ],
    "sg:phone":"+1 507 325 2337",
    "sg:postcode":"56036",
    "sg:province":"MN",
    "sg:tags":[
        "hog",
        "or",
        "feedlot"
    ],
    "wof:name":"Phil Cooper",
    "wof:placetype":"venue"
},
  "geometry": {"coordinates":[-93.149182,43.50973],"type":"Point"}
}