{
  "type": "Feature",
  "properties": {
    "iso:country":"US",
    "sg:address":"11440 65th St NE",
    "sg:city":"Elgin",
    "sg:classifiers":[
        {
            "category":"Home & Garden",
            "subcategory":"Furniture",
            "type":"Retail Goods"
        }
    ],
    "sg:phone":"+1 507 876 9937",
    "sg:postcode":"55932",
    "sg:province":"MN",
    "sg:tags":[
        "top",
        "counter"
    ],
    "wof:name":"Red Barn Granite Co",
    "wof:placetype":"venue"
},
  "geometry": {"coordinates":[-92.25121900000001,44.093109],"type":"Point"}
}