{
  "type": "Feature",
  "properties": {
    "iso:country":"US",
    "sg:address":"10721 Cambridge Ct",
    "sg:city":"Burnsville",
    "sg:classifiers":[
        {
            "category":"Wholesale",
            "subcategory":"Machinery & Supplies",
            "type":"Manufacturing & Wholesale Goods"
        }
    ],
    "sg:phone":"+1 952 890 2419",
    "sg:postcode":"55337",
    "sg:province":"MN",
    "sg:tags":[
        "machine",
        "tool"
    ],
    "wof:name":"Kingsmen Machinery Company Inc",
    "wof:placetype":"venue"
},
  "geometry": {"coordinates":[-93.235145,44.80885],"type":"Point"}
}