{
  "type": "Feature",
  "properties": {
    "addr:full":"13911 Ridgedale Dr Hopkins MN 55305",
    "addr:housenumber":"13911",
    "addr:postcode":"55305",
    "addr:street":"Ridgedale Dr",
    "iso:country":"US",
    "sg:address":"13911 Ridgedale Dr",
    "sg:city":"Hopkins",
    "sg:classifiers":[
        {
            "category":"Real Estate",
            "subcategory":"Real Estate Services",
            "type":"Services"
        }
    ],
    "sg:phone":"+1 952 545 2285",
    "sg:postcode":"55305",
    "sg:province":"MN",
    "sg:tags":[
        "company",
        "title"
    ],
    "wof:name":"O P Title Svc",
    "wof:placetype":"venue"
},
  "geometry": {"coordinates":[-93.45894800000001,44.969347],"type":"Point"}
}