{
  "type": "Feature",
  "properties": {
    "addr:full":"128 E 70th St Minneapolis MN 55423",
    "addr:housenumber":"128",
    "addr:postcode":"55423",
    "addr:street":"E 70Th St",
    "iso:country":"US",
    "sg:address":"128 E 70th St",
    "sg:city":"Minneapolis",
    "sg:classifiers":[
        {
            "category":"Building & Trades",
            "subcategory":"Construction",
            "type":"Services"
        }
    ],
    "sg:phone":"+1 952 934 4099",
    "sg:postcode":"55423",
    "sg:province":"MN",
    "sg:tags":[
        "system",
        "contractor",
        "air conditioning"
    ],
    "wof:name":"Premier Heating And Air Conditioning Inc",
    "wof:placetype":"venue"
},
  "geometry": {"coordinates":[-93.27562,44.876308],"type":"Point"}
}