{
  "type": "Feature",
  "properties": {
    "iso:country":"US",
    "sg:address":"128 E 70th St",
    "sg:city":"Minneapolis",
    "sg:classifiers":[
        {
            "category":"Building & Trades",
            "subcategory":"Construction",
            "type":"Services"
        }
    ],
    "sg:phone":"+1 952 934 4099",
    "sg:postcode":"55423",
    "sg:province":"MN",
    "sg:tags":[
        "system",
        "contractor",
        "air conditioning"
    ],
    "wof:name":"Premier Heating And Air Conditioning Inc",
    "wof:placetype":"venue"
},
  "geometry": {"coordinates":[-93.27562,44.876308],"type":"Point"}
}