{
  "type": "Feature",
  "properties": {
    "addr:full":"310 1st St S Montrose MN 55363",
    "addr:housenumber":"310",
    "addr:postcode":"55363",
    "addr:street":"1St St S",
    "iso:country":"US",
    "sg:address":"310 1st St S",
    "sg:city":"Montrose",
    "sg:classifiers":[
        {
            "category":"Wholesale",
            "subcategory":"Durable Goods & Equipment",
            "type":"Manufacturing & Wholesale Goods"
        }
    ],
    "sg:phone":"+1 763 675 6704",
    "sg:postcode":"55363",
    "sg:province":"MN",
    "sg:tags":[
        "instrument",
        "musical"
    ],
    "wof:name":"Eden",
    "wof:placetype":"venue"
},
  "geometry": {"coordinates":[-93.91398599999999,45.068641],"type":"Point"}
}