{
  "type": "Feature",
  "properties": {
    "addr:full":"7 Robb Farm Rd Saint Paul MN 55127",
    "addr:housenumber":"7",
    "addr:postcode":"55127",
    "addr:street":"Robb Farm Rd",
    "iso:country":"US",
    "sg:address":"7 Robb Farm Rd",
    "sg:city":"Saint Paul",
    "sg:classifiers":[
        {
            "category":"Professional",
            "subcategory":"Management & Consulting",
            "type":"Services"
        }
    ],
    "sg:phone":"+1 651 482 8834",
    "sg:postcode":"55127",
    "sg:province":"MN",
    "sg:tags":[
        "firm"
    ],
    "wof:name":"Accelerated Practice Concepts",
    "wof:placetype":"venue"
},
  "geometry": {"coordinates":[-93.067196,45.084896],"type":"Point"}
}