{
  "type": "Feature",
  "properties": {
    "iso:country":"US",
    "sg:address":"5898 Omaha Ave N",
    "sg:city":"Stillwater",
    "sg:classifiers":[
        {
            "category":"Retail",
            "subcategory":"Repair Shop",
            "type":"Services"
        }
    ],
    "sg:phone":"+1 651 439 9032",
    "sg:postcode":"55082",
    "sg:province":"MN",
    "sg:tags":[
        "camera"
    ],
    "wof:name":"Allied Camera Repr Oak Pk Hts",
    "wof:placetype":"venue"
},
  "geometry": {"coordinates":[-92.812631,45.034758],"type":"Point"}
}