{
  "type": "Feature",
  "properties": {
    "iso:country":"US",
    "sg:address":"7848 Niagara Ln N",
    "sg:city":"Osseo",
    "sg:classifiers":[
        {
            "category":"Professional",
            "subcategory":"Business Services",
            "type":"Services"
        }
    ],
    "sg:phone":"+1 763 494 3903",
    "sg:postcode":"55311",
    "sg:province":"MN",
    "wof:name":"Fresh Air Plant",
    "wof:placetype":"venue"
},
  "geometry": {"coordinates":[-93.47304099999999,45.096559],"type":"Point"}
}