{
  "type": "Feature",
  "properties": {
    "addr:full":"4136 18th Ave NW Rochester MN 55901",
    "addr:housenumber":"4136",
    "addr:postcode":"55901",
    "addr:street":"18Th Ave Nw",
    "iso:country":"US",
    "sg:address":"4136 18th Ave NW",
    "sg:city":"Rochester",
    "sg:classifiers":[
        {
            "category":"Food & Beverages",
            "subcategory":"Groceries & Convenience Stores",
            "type":"Retail Goods"
        }
    ],
    "sg:phone":"+1 507 281 2410",
    "sg:postcode":"55901",
    "sg:province":"MN",
    "wof:name":"Asian Pacific Market",
    "wof:placetype":"venue"
},
  "geometry": {"coordinates":[-92.488951,44.065876],"type":"Point"}
}