{
  "type": "Feature",
  "properties": {
    "addr:full":"1307 Hwy 13 E Burnsville MN 55337",
    "addr:housenumber":"1307",
    "addr:postcode":"55337",
    "addr:street":"Hwy 13 E",
    "iso:country":"US",
    "sg:address":"1307 Hwy 13 E",
    "sg:city":"Burnsville",
    "sg:classifiers":[
        {
            "category":"Wholesale",
            "subcategory":"Toys & Hobbies",
            "type":"Manufacturing & Wholesale Goods"
        },
        {
            "category":"Shopping",
            "subcategory":"Hobbies, Toys, & Games",
            "type":"Retail Goods"
        }
    ],
    "sg:phone":"+1 952 895 9643",
    "sg:postcode":"55337",
    "sg:province":"MN",
    "sg:tags":[
        "model",
        "supply"
    ],
    "wof:name":"R/C Car Kings",
    "wof:placetype":"venue"
},
  "geometry": {"coordinates":[-93.253084,44.78467],"type":"Point"}
}