{
  "type": "Feature",
  "properties": {
    "addr:full":"25072 121st Ave Sebeka MN 56477",
    "addr:housenumber":"25072",
    "addr:postcode":"56477",
    "addr:street":"121St Ave",
    "iso:country":"US",
    "sg:address":"25072 121st Ave",
    "sg:city":"Sebeka",
    "sg:classifiers":[
        {
            "category":"Professional",
            "subcategory":"Advertising",
            "type":"Services"
        },
        {
            "category":"Manufacturing",
            "subcategory":"Motor Vehicles & Parts",
            "type":"Manufacturing & Wholesale Goods"
        }
    ],
    "sg:phone":"+1 218 837 5597",
    "sg:postcode":"56477",
    "sg:province":"MN",
    "sg:tags":[
        "distribution",
        "mfg"
    ],
    "wof:name":"Leaders Distributing Co",
    "wof:placetype":"venue"
},
  "geometry": {"coordinates":[-95.115031,46.596626],"type":"Point"}
}