{
  "type": "Feature",
  "properties": {
    "addr:full":"3451 James Ave N Minneapolis MN 55412",
    "addr:housenumber":"3451",
    "addr:postcode":"55412",
    "addr:street":"James Ave N",
    "iso:country":"US",
    "sg:address":"3451 James Ave N",
    "sg:city":"Minneapolis",
    "sg:classifiers":[
        {
            "category":"Professional",
            "type":"Services"
        }
    ],
    "sg:phone":"+1 612 529 7056",
    "sg:postcode":"55412",
    "sg:province":"MN",
    "wof:name":"Vern Erickson",
    "wof:placetype":"venue"
},
  "geometry": {"coordinates":[-93.300721,45.017681],"type":"Point"}
}