{
  "type": "Feature",
  "properties": {
    "addr:full":"3201 Snelling Ave Minneapolis MN 55406",
    "addr:housenumber":"3201",
    "addr:postcode":"55406",
    "addr:street":"Snelling Ave",
    "iso:country":"US",
    "sg:address":"3201 Snelling Ave",
    "sg:city":"Minneapolis",
    "sg:classifiers":[
        {
            "category":"Manufacturing",
            "subcategory":"Petroleum Products",
            "type":"Manufacturing & Wholesale Goods"
        }
    ],
    "sg:phone":"+1 612 724 9169",
    "sg:postcode":"55406",
    "sg:province":"MN",
    "sg:tags":[
        "contract"
    ],
    "wof:name":"Jento Mfg Co",
    "wof:placetype":"venue"
},
  "geometry": {"coordinates":[-93.233391,44.944759],"type":"Point"}
}