{
  "type": "Feature",
  "properties": {
    "iso:country":"US",
    "sg:address":"6401 W 106th St Ste 201",
    "sg:city":"Minneapolis",
    "sg:classifiers":[
        {
            "category":"Wholesale",
            "subcategory":"Non-durable Goods",
            "type":"Manufacturing & Wholesale Goods"
        },
        {
            "category":"Professional",
            "subcategory":"Business Services",
            "type":"Services"
        }
    ],
    "sg:phone":"+1 952 894 0110",
    "sg:postcode":"55438",
    "sg:province":"MN",
    "sg:tags":[
        "broker",
        "merchandise",
        "merchandise-wholesale"
    ],
    "sg:website":"http://www.fmmi.net",
    "wof:name":"Fmmi",
    "wof:placetype":"venue"
},
  "geometry": {"coordinates":[-93.36659299999999,44.811574],"type":"Point"}
}