{
  "type": "Feature",
  "properties": {
    "iso:country":"US",
    "sg:address":"5369 N Shore Dr",
    "sg:city":"Duluth",
    "sg:classifiers":[
        {
            "category":"Health Services",
            "subcategory":"Health Practitioner",
            "type":"Services"
        }
    ],
    "sg:phone":"+1 218 525 5794",
    "sg:postcode":"55804",
    "sg:province":"MN",
    "wof:name":"Back In Balance Therapies",
    "wof:placetype":"venue"
},
  "geometry": {"coordinates":[-91.890288,46.90172],"type":"Point"}
}