{
  "type": "Feature",
  "properties": {
    "addr:full":"8258 Co Rd 25 NW Evansville MN 56326",
    "addr:housenumber":"8258;25",
    "addr:postcode":"56326",
    "addr:street":"Co Rd",
    "iso:country":"US",
    "sg:address":"8258 Co Rd 25 NW",
    "sg:city":"Evansville",
    "sg:classifiers":[
        {
            "category":"Utilities",
            "subcategory":"Fuel Oil & Lpg",
            "type":"Services"
        }
    ],
    "sg:phone":"+1 218 948 2225",
    "sg:postcode":"56326",
    "sg:province":"MN",
    "sg:tags":[
        "dealer"
    ],
    "wof:name":"R & S Bulk Service",
    "wof:placetype":"venue"
},
  "geometry": {"coordinates":[-95.738411,45.977534],"type":"Point"}
}