{
  "type": "Feature",
  "properties": {
    "iso:country":"US",
    "sg:address":"9943 Harriet Ave S",
    "sg:city":"Minneapolis",
    "sg:classifiers":[
        {
            "category":"Building & Trades",
            "subcategory":"Construction",
            "type":"Services"
        }
    ],
    "sg:phone":"+1 952 888 6445",
    "sg:postcode":"55420",
    "sg:province":"MN",
    "sg:tags":[
        "concrete",
        "masonry",
        "contractor"
    ],
    "wof:name":"CJ Concrete & Masonry Inc",
    "wof:placetype":"venue"
},
  "geometry": {"coordinates":[-93.28532,44.824256],"type":"Point"}
}