{
  "type": "Feature",
  "properties": {
    "addr:full":"45214 Co Hwy 80 Perham MN 56573",
    "addr:housenumber":"45214",
    "addr:postcode":"56573",
    "addr:street":"Co Hwy 80",
    "iso:country":"US",
    "sg:address":"45214 Co Hwy 80",
    "sg:city":"Perham",
    "sg:classifiers":[
        {
            "category":"Building & Trades",
            "subcategory":"Construction",
            "type":"Services"
        }
    ],
    "sg:phone":"+1 218 346 9355",
    "sg:postcode":"56573",
    "sg:province":"MN",
    "sg:tags":[
        "well",
        "drilling"
    ],
    "wof:name":"Neyens Well Drilling",
    "wof:placetype":"venue"
},
  "geometry": {"coordinates":[-95.541723,46.576953],"type":"Point"}
}