{
  "type": "Feature",
  "properties": {
    "iso:country":"US",
    "sg:address":"404 W Lyon Ave",
    "sg:city":"Lake City",
    "sg:classifiers":[
        {
            "category":"Organizations",
            "subcategory":"Religious Organization",
            "type":"Services"
        }
    ],
    "sg:phone":"+1 651 345 5060",
    "sg:postcode":"55041",
    "sg:province":"MN",
    "wof:name":"Saint Marys Church",
    "wof:placetype":"venue"
},
  "geometry": {"coordinates":[-92.26958500000001,44.447188],"type":"Point"}
}