{
  "type": "Feature",
  "properties": {
    "addr:full":"8875 US Hwy 12 Delano MN 55328",
    "addr:housenumber":"8875",
    "addr:postcode":"55328",
    "addr:street":"Us Hwy 12",
    "iso:country":"US",
    "sg:address":"8875 US Hwy 12",
    "sg:city":"Delano",
    "sg:classifiers":[
        {
            "category":"Retail",
            "subcategory":"Animal Services",
            "type":"Services"
        }
    ],
    "sg:phone":"+1 763 972 2433",
    "sg:postcode":"55328",
    "sg:province":"MN",
    "wof:name":"Abbie Lake Kennels Boarding &",
    "wof:placetype":"venue"
},
  "geometry": {"coordinates":[-93.74899499999999,45.035749],"type":"Point"}
}