{
  "type": "Feature",
  "properties": {
    "iso:country":"US",
    "sg:address":"32018 Dahomey Ave",
    "sg:city":"Northfield",
    "sg:classifiers":[
        {
            "category":"Professional",
            "subcategory":"Business Services",
            "type":"Services"
        }
    ],
    "sg:phone":"+1 507 645 1311",
    "sg:postcode":"55057",
    "sg:province":"MN",
    "sg:tags":[
        "water",
        "treatment"
    ],
    "wof:name":"Hague Quality Water",
    "wof:placetype":"venue"
},
  "geometry": {"coordinates":[-93.145771,44.484481],"type":"Point"}
}