{
  "type": "Feature",
  "properties": {
    "addr:full":"4724 Adair Ct Minneapolis MN 55429",
    "addr:housenumber":"4724",
    "addr:postcode":"55429",
    "addr:street":"Adair Ct",
    "iso:country":"US",
    "sg:address":"4724 Adair Ct",
    "sg:city":"Minneapolis",
    "sg:classifiers":[
        {
            "category":"Professional",
            "subcategory":"Computer Services",
            "type":"Services"
        }
    ],
    "sg:phone":"+1 763 535 2461",
    "sg:postcode":"55429",
    "sg:province":"MN",
    "wof:name":"Lausen Brothers Enterprises",
    "wof:placetype":"venue"
},
  "geometry": {"coordinates":[-93.3573,45.040844],"type":"Point"}
}