{
  "type": "Feature",
  "properties": {
    "addr:full":"1822 Western Ave NW Faribault MN 55021",
    "addr:housenumber":"1822",
    "addr:postcode":"55021",
    "addr:street":"Western Ave Nw",
    "iso:country":"US",
    "sg:address":"1822 Western Ave NW",
    "sg:city":"Faribault",
    "sg:classifiers":[
        {
            "category":"Shopping",
            "subcategory":"Used Merchandise",
            "type":"Retail Goods"
        }
    ],
    "sg:phone":"+1 507 334 7480",
    "sg:postcode":"55021",
    "sg:province":"MN",
    "sg:tags":[
        "shop",
        "thrift"
    ],
    "wof:name":"Jan's Thrift Shop",
    "wof:placetype":"venue"
},
  "geometry": {"coordinates":[-93.303127,44.310359],"type":"Point"}
}