{
  "type": "Feature",
  "properties": {
    "addr:full":"19545 Highway 7 Excelsior MN 55331",
    "addr:housenumber":"19545",
    "addr:postcode":"55331",
    "addr:street":"Highway 7",
    "iso:country":"US",
    "sg:address":"19545 Highway 7",
    "sg:city":"Excelsior",
    "sg:classifiers":[
        {
            "category":"Retail",
            "subcategory":"Storage",
            "type":"Services"
        }
    ],
    "sg:phone":"+1 952 474 2123",
    "sg:postcode":"55331",
    "sg:province":"MN",
    "sg:tags":[
        "self"
    ],
    "wof:name":"Shurgard Storage",
    "wof:placetype":"venue"
},
  "geometry": {"coordinates":[-93.528198,44.909302],"type":"Point"}
}