{
  "type": "Feature",
  "properties": {
    "addr:full":"2250 Rice St Saint Paul MN 55113",
    "addr:housenumber":"2250",
    "addr:postcode":"55113",
    "addr:street":"Rice St",
    "iso:country":"US",
    "sg:address":"2250 Rice St",
    "sg:city":"Saint Paul",
    "sg:classifiers":[
        {
            "category":"Autos & Motor Vehicles",
            "subcategory":"Fuel & Gas Station",
            "type":"Retail Goods"
        }
    ],
    "sg:phone":"+1 651 483 6857",
    "sg:postcode":"55113",
    "sg:province":"MN",
    "sg:tags":[
        "grocery",
        "station",
        "gasoline"
    ],
    "wof:name":"Oasis Markets Inc",
    "wof:placetype":"venue"
},
  "geometry": {"coordinates":[-93.105981,45.009902],"type":"Point"}
}