{
  "type": "Feature",
  "properties": {
    "iso:country":"US",
    "sg:address":"1406 Yankee Doodle Rd",
    "sg:city":"Eagan",
    "sg:classifiers":[
        {
            "category":"Autos & Motor Vehicles",
            "subcategory":"Fuel & Gas Station",
            "type":"Retail Goods"
        }
    ],
    "sg:phone":"+1 651 452 9853",
    "sg:postcode":"55121",
    "sg:province":"MN",
    "sg:tags":[
        "oil"
    ],
    "sg:website":"www.superamerica.com",
    "wof:name":"Super America",
    "wof:placetype":"venue"
},
  "geometry": {"coordinates":[-93.167704,44.833367],"type":"Point"}
}