{
  "type": "Feature",
  "properties": {
    "addr:full":"6650 Vernon Ave S Apt 107 Minneapolis MN 55436",
    "addr:housenumber":"6650;107",
    "addr:postcode":"55436",
    "addr:street":"Vernon Ave S Apt",
    "iso:country":"US",
    "sg:address":"6650 Vernon Ave S Apt 107",
    "sg:city":"Minneapolis",
    "sg:classifiers":[
        {
            "category":"Real Estate",
            "subcategory":"Real Estate Services",
            "type":"Services"
        }
    ],
    "sg:phone":"+1 952 933 6025",
    "sg:postcode":"55436",
    "sg:province":"MN",
    "sg:tags":[
        "management",
        "condominium"
    ],
    "wof:name":"Fountain Woods Condominium Association",
    "wof:placetype":"venue"
},
  "geometry": {"coordinates":[-93.39370099999999,44.892544],"type":"Point"}
}