{
  "type": "Feature",
  "properties": {
    "iso:country":"US",
    "sg:address":"6155 Dawn Ave E",
    "sg:city":"Inver Grove Hts",
    "sg:classifiers":[
        {
            "category":"Professional",
            "type":"Services"
        },
        {
            "category":"Manufacturing",
            "subcategory":"Toys & Sporting Goods",
            "type":"Manufacturing & Wholesale Goods"
        }
    ],
    "sg:phone":"+1 651 554 3034",
    "sg:postcode":"55076",
    "sg:province":"MN",
    "sg:tags":[
        "mfg",
        "sand",
        "snow",
        "paint",
        "spray",
        "establishment"
    ],
    "wof:name":"Creative Toy Corporation",
    "wof:placetype":"venue"
},
  "geometry": {"coordinates":[-93.023906,44.859373],"type":"Point"}
}