{
  "type": "Feature",
  "properties": {
    "addr:full":"1651 Jefferson Pkwy Northfield MN 55057",
    "addr:housenumber":"1651",
    "addr:postcode":"55057",
    "addr:street":"Jefferson Pkwy",
    "iso:country":"US",
    "sg:address":"1651 Jefferson Pkwy",
    "sg:city":"Northfield",
    "sg:classifiers":[
        {
            "category":"Professional",
            "subcategory":"Business Services",
            "type":"Services"
        }
    ],
    "sg:phone":"+1 507 664 3500",
    "sg:postcode":"55057",
    "sg:province":"MN",
    "sg:tags":[
        "conference",
        "center"
    ],
    "wof:name":"Northfield Community Resource",
    "wof:placetype":"venue"
},
  "geometry": {"coordinates":[-93.159099,44.440503],"type":"Point"}
}