{
  "type": "Feature",
  "properties": {
    "iso:country":"US",
    "sg:address":"1355 170th Ave",
    "sg:city":"Wolverton",
    "sg:classifiers":[
        {
            "category":"Farming",
            "subcategory":"Dairy Farm",
            "type":"Manufacturing & Wholesale Goods"
        }
    ],
    "sg:phone":"+1 218 995 2301",
    "sg:postcode":"56550",
    "sg:province":"MN",
    "wof:name":"Ernst & Son",
    "wof:placetype":"venue"
},
  "geometry": {"coordinates":[-96.78522,47.251975],"type":"Point"}
}