{
  "type": "Feature",
  "properties": {
    "addr:full":"1355 170th Ave Wolverton MN 56550",
    "addr:housenumber":"1355",
    "addr:postcode":"56550",
    "addr:street":"170Th Ave",
    "iso:country":"US",
    "sg:address":"1355 170th Ave",
    "sg:city":"Wolverton",
    "sg:classifiers":[
        {
            "category":"Farming",
            "subcategory":"Dairy Farm",
            "type":"Manufacturing & Wholesale Goods"
        }
    ],
    "sg:phone":"+1 218 995 2301",
    "sg:postcode":"56550",
    "sg:province":"MN",
    "wof:name":"Ernst & Son",
    "wof:placetype":"venue"
},
  "geometry": {"coordinates":[-96.78522,47.251975],"type":"Point"}
}