{
  "type": "Feature",
  "properties": {
    "iso:country":"US",
    "sg:address":"617 6th St",
    "sg:city":"Farmington",
    "sg:classifiers":[
        {
            "category":"Retail",
            "subcategory":"Repair Shop",
            "type":"Services"
        }
    ],
    "sg:phone":"+1 651 463 2044",
    "sg:postcode":"55024",
    "sg:province":"MN",
    "sg:tags":[
        "automotive"
    ],
    "wof:name":"Pro Tune Inc",
    "wof:placetype":"venue"
},
  "geometry": {"coordinates":[-93.1401,44.635738],"type":"Point"}
}