{
  "type": "Feature",
  "properties": {
    "iso:country":"US",
    "sg:address":"2361 Oak Ln",
    "sg:city":"Saint Paul",
    "sg:classifiers":[
        {
            "category":"Retail",
            "subcategory":"Auto Repair",
            "type":"Services"
        }
    ],
    "sg:phone":"+1 651 770 0592",
    "sg:postcode":"55110",
    "sg:province":"MN",
    "sg:tags":[
        "general"
    ],
    "wof:name":"Equity Auto Care",
    "wof:placetype":"venue"
},
  "geometry": {"coordinates":[-93.001189,45.048359],"type":"Point"}
}