{
  "type": "Feature",
  "properties": {
    "addr:full":"157 Snelling Ave N Saint Paul MN 55104",
    "addr:housenumber":"157",
    "addr:postcode":"55104",
    "addr:street":"Snelling Ave N",
    "iso:country":"US",
    "sg:address":"157 Snelling Ave N",
    "sg:city":"Saint Paul",
    "sg:classifiers":[
        {
            "category":"Shopping",
            "subcategory":"Antiques",
            "type":"Retail Goods"
        },
        {
            "category":"Shopping",
            "subcategory":"Used Merchandise",
            "type":"Retail Goods"
        }
    ],
    "sg:phone":"+1 651 917 0470",
    "sg:postcode":"55104",
    "sg:province":"MN",
    "sg:tags":[
        "vintage",
        "consignment"
    ],
    "sg:website":"www.upsixvintage.com",
    "wof:name":"Up Six",
    "wof:placetype":"venue"
},
  "geometry": {"coordinates":[-93.16701399999999,44.946145],"type":"Point"}
}