{
  "type": "Feature",
  "properties": {
    "addr:full":"39500 Park Trl Center City MN 55012",
    "addr:housenumber":"39500",
    "addr:postcode":"55012",
    "addr:street":"Park Trl",
    "iso:country":"US",
    "sg:address":"39500 Park Trl",
    "sg:city":"Center City",
    "sg:classifiers":[
        {
            "category":"Farming",
            "subcategory":"Dairy Farm",
            "type":"Manufacturing & Wholesale Goods"
        }
    ],
    "sg:phone":"+1 651 583 2140",
    "sg:postcode":"55012",
    "sg:province":"MN",
    "wof:name":"Wild River Farms",
    "wof:placetype":"venue"
},
  "geometry": {"coordinates":[-92.754469,45.524114],"type":"Point"}
}