{
  "type": "Feature",
  "properties": {
    "iso:country":"US",
    "sg:address":"1600 11th Ave NE",
    "sg:city":"Willmar",
    "sg:classifiers":[
        {
            "category":"Personal",
            "subcategory":"Beauty Salon",
            "type":"Services"
        }
    ],
    "sg:phone":"+1 320 231 3223",
    "sg:postcode":"56201",
    "sg:province":"MN",
    "sg:tags":[
        "shop"
    ],
    "wof:name":"Inspa Studio",
    "wof:placetype":"venue"
},
  "geometry": {"coordinates":[-95.022086,45.136345],"type":"Point"}
}