{
  "type": "Feature",
  "properties": {
    "iso:country":"US",
    "sg:address":"214 N Mill St",
    "sg:city":"Fertile",
    "sg:classifiers":[
        {
            "category":"Manufacturing",
            "subcategory":"Printing",
            "type":"Manufacturing & Wholesale Goods"
        }
    ],
    "sg:phone":"+1 218 945 6120",
    "sg:postcode":"56540",
    "sg:province":"MN",
    "sg:tags":[
        "newspaper"
    ],
    "wof:name":"Fertile Journal",
    "wof:placetype":"venue"
},
  "geometry": {"coordinates":[-96.28041899999999,47.535999],"type":"Point"}
}