{
  "type": "Feature",
  "properties": {
    "addr:full":"1200 N Jefferson St New Ulm MN 56073",
    "addr:housenumber":"1200",
    "addr:postcode":"56073",
    "addr:street":"N Jefferson St",
    "iso:country":"US",
    "sg:address":"1200 N Jefferson St",
    "sg:city":"New Ulm",
    "sg:classifiers":[
        {
            "category":"Retail",
            "subcategory":"Auto Repair",
            "type":"Services"
        }
    ],
    "sg:phone":"+1 507 354 3516",
    "sg:postcode":"56073",
    "sg:province":"MN",
    "sg:tags":[
        "body",
        "automobile",
        "painting"
    ],
    "wof:name":"Traurig Body Shop",
    "wof:placetype":"venue"
},
  "geometry": {"coordinates":[-94.477964,44.322672],"type":"Point"}
}