{
  "type": "Feature",
  "properties": {
    "addr:full":"1373 130th Ave Ogilvie MN 56358",
    "addr:housenumber":"1373",
    "addr:postcode":"56358",
    "addr:street":"130Th Ave",
    "iso:country":"US",
    "sg:address":"1373 130th Ave",
    "sg:city":"Ogilvie",
    "sg:classifiers":[
        {
            "category":"Real Estate",
            "subcategory":"Real Estate Operator",
            "type":"Services"
        }
    ],
    "sg:phone":"+1 320 272 4847",
    "sg:postcode":"56358",
    "sg:province":"MN",
    "sg:tags":[
        "property",
        "lessor"
    ],
    "wof:name":"Conrad Swenson",
    "wof:placetype":"venue"
},
  "geometry": {"coordinates":[-93.43773,45.775925],"type":"Point"}
}