{
  "type": "Feature",
  "properties": {
    "iso:country":"US",
    "sg:address":"32240 County 1 Blvd",
    "sg:city":"Red Wing",
    "sg:classifiers":[
        {
            "category":"Farming",
            "subcategory":"Dairy Farm",
            "type":"Manufacturing & Wholesale Goods"
        }
    ],
    "sg:phone":"+1 651 258 4610",
    "sg:postcode":"55066",
    "sg:province":"MN",
    "sg:tags":[
        "field",
        "corn",
        "grain",
        "cash",
        "crop"
    ],
    "wof:name":"Don Gadient",
    "wof:placetype":"venue"
},
  "geometry": {"coordinates":[-92.63959699999999,44.481931],"type":"Point"}
}