{
  "type": "Feature",
  "properties": {
    "iso:country":"US",
    "sg:address":"1336 Energy Park Dr",
    "sg:city":"St Paul",
    "sg:classifiers":[
        {
            "category":"Manufacturing",
            "subcategory":"Printing",
            "type":"Manufacturing & Wholesale Goods"
        }
    ],
    "sg:phone":"+1 651 644 9136",
    "sg:postcode":"55108",
    "sg:province":"MN",
    "sg:tags":[
        "lithographic",
        "printer",
        "commercial",
        "publishing"
    ],
    "wof:name":"Litho Express Inc",
    "wof:placetype":"venue"
},
  "geometry": {"coordinates":[-93.15634900000001,44.970663],"type":"Point"}
}