{
  "type": "Feature",
  "properties": {
    "iso:country":"US",
    "sg:address":"30 S 7th St",
    "sg:city":"Minneapolis",
    "sg:classifiers":[
        {
            "category":"Professional",
            "type":"Services"
        },
        {
            "category":"Travel",
            "subcategory":"Hotels & Motels",
            "type":"Entertainment"
        }
    ],
    "sg:phone":"+1 612 349 4000",
    "sg:postcode":"55402",
    "sg:province":"MN",
    "sg:tags":[
        "caterer"
    ],
    "wof:name":"Marriott Hotels & Resorts",
    "wof:placetype":"venue"
},
  "geometry": {"coordinates":[-93.27480300000001,44.978001],"type":"Point"}
}