{
  "type": "Feature",
  "properties": {
    "addr:full":"1162 Randolph Ave St Paul MN 55105",
    "addr:housenumber":"1162",
    "addr:postcode":"55105",
    "addr:street":"Randolph Ave",
    "iso:country":"US",
    "sg:address":"1162 Randolph Ave",
    "sg:city":"St Paul",
    "sg:classifiers":[
        {
            "category":"Shopping",
            "subcategory":"Hobbies, Toys, & Games",
            "type":"Retail Goods"
        }
    ],
    "sg:phone":"+1 651 699 5878",
    "sg:postcode":"55105",
    "sg:province":"MN",
    "sg:tags":[
        "product",
        "ceramic"
    ],
    "wof:name":"Diane & Fran's Ceramic Crtns",
    "wof:placetype":"venue"
},
  "geometry": {"coordinates":[-93.14987600000001,44.926871],"type":"Point"}
}