{
  "type": "Feature",
  "properties": {
    "addr:full":"408 E 5th St Litchfield MN 55355",
    "addr:housenumber":"408",
    "addr:postcode":"55355",
    "addr:street":"E 5Th St",
    "iso:country":"US",
    "sg:address":"408 E 5th St",
    "sg:city":"Litchfield",
    "sg:classifiers":[
        {
            "category":"Professional",
            "type":"Services"
        }
    ],
    "sg:phone":"+1 320 693 2201",
    "sg:postcode":"55355",
    "sg:province":"MN",
    "wof:name":"Candlewood Corner",
    "wof:placetype":"venue"
},
  "geometry": {"coordinates":[-94.51940500000001,45.13108],"type":"Point"}
}