{
  "type": "Feature",
  "properties": {
    "iso:country":"US",
    "sg:address":"17787 Idalia Path",
    "sg:city":"Lakeville",
    "sg:classifiers":[
        {
            "category":"Professional",
            "type":"Services"
        }
    ],
    "sg:phone":"+1 952 435 2720",
    "sg:postcode":"55044",
    "sg:province":"MN",
    "sg:tags":[
        "establishment"
    ],
    "wof:name":"Ditolla & Ditolla",
    "wof:placetype":"venue"
},
  "geometry": {"coordinates":[-93.253987,44.689648],"type":"Point"}
}