{
  "type": "Feature",
  "properties": {
    "addr:full":"411 Union Terrace Ln N Minneapolis MN 55441",
    "addr:housenumber":"411",
    "addr:postcode":"55441",
    "addr:street":"Union Terrace Ln N",
    "iso:country":"US",
    "sg:address":"411 Union Terrace Ln N",
    "sg:city":"Minneapolis",
    "sg:classifiers":[
        {
            "category":"Professional",
            "subcategory":"Accounting & Tax Preparation",
            "type":"Services"
        }
    ],
    "sg:phone":"+1 612 349 2796",
    "sg:postcode":"55441",
    "sg:province":"MN",
    "wof:name":"Jack W Koffel",
    "wof:placetype":"venue"
},
  "geometry": {"coordinates":[-93.41464000000001,44.984362],"type":"Point"}
}