{
  "type": "Feature",
  "properties": {
    "addr:full":"146 3rd St SE Blooming Prairie MN 55917",
    "addr:housenumber":"146",
    "addr:postcode":"55917",
    "addr:street":"3Rd St Se",
    "iso:country":"US",
    "sg:address":"146 3rd St SE",
    "sg:city":"Blooming Prairie",
    "sg:classifiers":[
        {
            "category":"Government",
            "subcategory":"Office",
            "type":"Public Place"
        }
    ],
    "sg:phone":"+1 507 583 6683",
    "sg:postcode":"55917",
    "sg:province":"MN",
    "sg:tags":[
        "govt",
        "city"
    ],
    "wof:name":"Municipal Utilities Office",
    "wof:placetype":"venue"
},
  "geometry": {"coordinates":[-93.054316,43.863369],"type":"Point"}
}