{
  "type": "Feature",
  "properties": {
    "iso:country":"US",
    "sg:address":"1619 W Main St",
    "sg:city":"Albert Lea",
    "sg:classifiers":[
        {
            "category":"Banks & Credit Unions",
            "subcategory":"Bank",
            "type":"Services"
        }
    ],
    "sg:phone":"+1 507 373 9889",
    "sg:postcode":"56007",
    "sg:province":"MN",
    "wof:name":"Wells Federal Bank",
    "wof:placetype":"venue"
},
  "geometry": {"coordinates":[-93.389048,43.646344],"type":"Point"}
}