{
  "type": "Feature",
  "properties": {
    "addr:full":"48163 390th St New York Mills MN 56567",
    "addr:housenumber":"48163",
    "addr:postcode":"56567",
    "addr:street":"390Th St;York",
    "iso:country":"US",
    "sg:address":"48163 390th St",
    "sg:city":"New York Mills",
    "sg:classifiers":[
        {
            "category":"Farming",
            "subcategory":"Dairy Farm",
            "type":"Manufacturing & Wholesale Goods"
        }
    ],
    "sg:phone":"+1 218 346 3529",
    "sg:postcode":"56567",
    "sg:province":"MN",
    "wof:name":"Hill Top Farm",
    "wof:placetype":"venue"
},
  "geometry": {"coordinates":[-95.49417099999999,46.528067],"type":"Point"}
}