{
  "type": "Feature",
  "properties": {
    "addr:full":"1560 Skyline Trl Eagan MN 55121",
    "addr:housenumber":"1560",
    "addr:postcode":"55121",
    "addr:street":"Skyline Trl",
    "iso:country":"US",
    "sg:address":"1560 Skyline Trl",
    "sg:city":"Eagan",
    "sg:classifiers":[
        {
            "category":"Professional",
            "subcategory":"Management & Consulting",
            "type":"Services"
        }
    ],
    "sg:phone":"+1 651 454 1262",
    "sg:postcode":"55121",
    "sg:province":"MN",
    "sg:tags":[
        "conference",
        "consultant",
        "meeting"
    ],
    "wof:name":"Ilaug Conference Resources",
    "wof:placetype":"venue"
},
  "geometry": {"coordinates":[-93.177393,44.849567],"type":"Point"}
}