{
  "type": "Feature",
  "properties": {
    "addr:full":"995 Burns Ave Saint Paul MN 55106",
    "addr:housenumber":"995",
    "addr:postcode":"55106",
    "addr:street":"Burns Ave",
    "iso:country":"US",
    "sg:address":"995 Burns Ave",
    "sg:city":"Saint Paul",
    "sg:classifiers":[
        {
            "category":"Building & Trades",
            "subcategory":"Plumbing",
            "type":"Services"
        }
    ],
    "sg:phone":"+1 651 776 4585",
    "sg:postcode":"55106",
    "sg:province":"MN",
    "sg:tags":[
        "air",
        "heating",
        "conditioning",
        "contractor"
    ],
    "wof:name":"Forrest Heating Service Inc",
    "wof:placetype":"venue"
},
  "geometry": {"coordinates":[-93.056195,44.948769],"type":"Point"}
}