{
  "type": "Feature",
  "properties": {
    "addr:full":"700 8th St SW Pine Island MN 55963",
    "addr:housenumber":"700",
    "addr:postcode":"55963",
    "addr:street":"8Th St Sw",
    "iso:country":"US",
    "sg:address":"700 8th St SW",
    "sg:city":"Pine Island",
    "sg:classifiers":[
        {
            "category":"Retail",
            "subcategory":"Auto Repair",
            "type":"Services"
        }
    ],
    "sg:phone":"+1 507 356 2000",
    "sg:postcode":"55963",
    "sg:province":"MN",
    "sg:tags":[
        "general"
    ],
    "wof:name":"Countryside Transm & Auto Repr",
    "wof:placetype":"venue"
},
  "geometry": {"coordinates":[-92.65835,44.19547],"type":"Point"}
}