{
  "type": "Feature",
  "properties": {
    "addr:full":"9408 Lyndale Ave S Bloomington MN 55420",
    "addr:housenumber":"9408",
    "addr:postcode":"55420",
    "addr:street":"Lyndale Ave S",
    "iso:country":"US",
    "sg:address":"9408 Lyndale Ave S",
    "sg:city":"Bloomington",
    "sg:classifiers":[
        {
            "category":"Shopping",
            "subcategory":"Gifts & Souvenirs",
            "type":"Retail Goods"
        }
    ],
    "sg:phone":"+1 952 881 2783",
    "sg:postcode":"55420",
    "sg:province":"MN",
    "sg:tags":[
        "party",
        "product",
        "paper",
        "supply"
    ],
    "wof:name":"Party America",
    "wof:placetype":"venue"
},
  "geometry": {"coordinates":[-93.288704,44.83172],"type":"Point"}
}