{
  "type": "Feature",
  "properties": {
    "addr:full":"100 N Minnesota St New Ulm MN 56073",
    "addr:housenumber":"100",
    "addr:postcode":"56073",
    "addr:street":"N Minnesota St",
    "iso:country":"US",
    "sg:address":"100 N Minnesota St",
    "sg:city":"New Ulm",
    "sg:classifiers":[
        {
            "category":"Organizations",
            "subcategory":"Professional Association",
            "type":"Services"
        }
    ],
    "sg:phone":"+1 507 354 8821",
    "sg:postcode":"56073",
    "sg:province":"MN",
    "wof:name":"Community Concert Ass'n",
    "wof:placetype":"venue"
},
  "geometry": {"coordinates":[-94.460843,44.315277],"type":"Point"}
}