{
  "type": "Feature",
  "properties": {
    "addr:full":"75 Norman Ridge Dr Minneapolis MN 55437",
    "addr:housenumber":"75",
    "addr:postcode":"55437",
    "addr:street":"Norman Ridge Dr",
    "iso:country":"US",
    "sg:address":"75 Norman Ridge Dr",
    "sg:city":"Minneapolis",
    "sg:classifiers":[
        {
            "category":"Arts & Performance",
            "subcategory":"Dance",
            "type":"Entertainment"
        }
    ],
    "sg:phone":"+1 952 835 7596",
    "sg:postcode":"55437",
    "sg:province":"MN",
    "sg:tags":[
        "instruction",
        "dancing"
    ],
    "wof:name":"Steps Dance Center",
    "wof:placetype":"venue"
},
  "geometry": {"coordinates":[-93.35526,44.837294],"type":"Point"}
}