{
  "type": "Feature",
  "properties": {
    "addr:full":"14220 Grand Ave Burnsville MN 55337",
    "addr:housenumber":"14220",
    "addr:postcode":"55337",
    "addr:street":"Grand Ave",
    "iso:country":"US",
    "sg:address":"14220 Grand Ave",
    "sg:city":"Burnsville",
    "sg:classifiers":[
        {
            "category":"Food & Beverages",
            "subcategory":"Groceries & Convenience Stores",
            "type":"Retail Goods"
        }
    ],
    "sg:phone":"+1 952 435 3373",
    "sg:postcode":"55337",
    "sg:province":"MN",
    "wof:name":"BP",
    "wof:placetype":"venue"
},
  "geometry": {"coordinates":[-93.281496,44.746415],"type":"Point"}
}