{
  "type": "Feature",
  "properties": {
    "addr:full":"37308 Co Rd 8 Mountain Lake MN 56159",
    "addr:housenumber":"37308",
    "addr:postcode":"56159",
    "addr:street":"Co Rd 8",
    "iso:country":"US",
    "sg:address":"37308 Co Rd 8",
    "sg:city":"Mountain Lake",
    "sg:classifiers":[
        {
            "category":"Wholesale",
            "subcategory":"Farm Supplies",
            "type":"Manufacturing & Wholesale Goods"
        }
    ],
    "sg:phone":"+1 507 427 2421",
    "sg:postcode":"56159",
    "sg:province":"MN",
    "sg:tags":[
        "bean"
    ],
    "wof:name":"New Vision Co-Op",
    "wof:placetype":"venue"
},
  "geometry": {"coordinates":[-94.87920200000001,43.946679],"type":"Point"}
}