{
  "type": "Feature",
  "properties": {
    "iso:country":"US",
    "sg:address":"7722 Somerset Rd",
    "sg:city":"Saint Paul",
    "sg:classifiers":[
        {
            "category":"Professional",
            "subcategory":"Business Services",
            "type":"Services"
        }
    ],
    "sg:phone":"+1 651 738 1058",
    "sg:postcode":"55125",
    "sg:province":"MN",
    "wof:name":"Sprau Family Ltd Partnership",
    "wof:placetype":"venue"
},
  "geometry": {"coordinates":[-92.951296,44.931078],"type":"Point"}
}