{
  "type": "Feature",
  "properties": {
    "iso:country":"US",
    "sg:address":"525 W Broadway Ave",
    "sg:city":"Minneapolis",
    "sg:classifiers":[
        {
            "category":"Education",
            "subcategory":"Special Training",
            "type":"Public Place"
        }
    ],
    "sg:phone":"+1 612 529 0010",
    "sg:postcode":"55411",
    "sg:province":"MN",
    "sg:tags":[
        "educational"
    ],
    "wof:name":"Lighthouse Training Center",
    "wof:placetype":"venue"
},
  "geometry": {"coordinates":[-93.28594,44.999142],"type":"Point"}
}