{
  "type": "Feature",
  "properties": {
    "addr:full":"1660 Highway 100 S Minneapolis MN 55416",
    "addr:housenumber":"1660",
    "addr:postcode":"55416",
    "addr:street":"Highway 100 S",
    "iso:country":"US",
    "sg:address":"1660 Highway 100 S",
    "sg:city":"Minneapolis",
    "sg:classifiers":[
        {
            "category":"Real Estate",
            "subcategory":"Real Estate Operator",
            "type":"Services"
        }
    ],
    "sg:phone":"+1 612 332 5101",
    "sg:postcode":"55416",
    "sg:province":"MN",
    "sg:tags":[
        "apartment"
    ],
    "wof:name":"Riverwest Apartments",
    "wof:placetype":"venue"
},
  "geometry": {"coordinates":[-93.34320099999999,44.9678],"type":"Point"}
}