{
  "type": "Feature",
  "properties": {
    "iso:country":"US",
    "sg:address":"6701 Gowan Ave SW",
    "sg:city":"Howard Lake",
    "sg:classifiers":[
        {
            "category":"Building & Trades",
            "subcategory":"Construction",
            "type":"Services"
        }
    ],
    "sg:phone":"+1 320 543 2398",
    "sg:postcode":"55349",
    "sg:province":"MN",
    "sg:tags":[
        "hanging",
        "contractor"
    ],
    "wof:name":"Michael J Kittock",
    "wof:placetype":"venue"
},
  "geometry": {"coordinates":[-94.0124,45.055438],"type":"Point"}
}