{
  "type": "Feature",
  "properties": {
    "iso:country":"US",
    "sg:address":"14826 Co Rd 1",
    "sg:city":"Cosmos",
    "sg:classifiers":[
        {
            "category":"Farming",
            "subcategory":"Farm",
            "type":"Manufacturing & Wholesale Goods"
        }
    ],
    "sg:phone":"+1 320 693 2766",
    "sg:postcode":"55355",
    "sg:province":"MN",
    "sg:tags":[
        "crop",
        "general"
    ],
    "wof:name":"Richard Hoff",
    "wof:placetype":"venue"
},
  "geometry": {"coordinates":[-94.60463900000001,44.962335],"type":"Point"}
}