{
  "type": "Feature",
  "properties": {
    "addr:full":"1205 4th Ave NW East Grand Forks MN 56721",
    "addr:housenumber":"1205",
    "addr:postcode":"56721",
    "addr:street":"4Th Ave Nw",
    "iso:country":"US",
    "sg:address":"1205 4th Ave NW",
    "sg:city":"East Grand Forks",
    "sg:classifiers":[
        {
            "category":"Farming",
            "subcategory":"Farm",
            "type":"Manufacturing & Wholesale Goods"
        }
    ],
    "sg:phone":"+1 218 773 2614",
    "sg:postcode":"56721",
    "sg:province":"MN",
    "sg:tags":[
        "operator"
    ],
    "wof:name":"Ernest C Kangas",
    "wof:placetype":"venue"
},
  "geometry": {"coordinates":[-97.02411600000001,47.937521],"type":"Point"}
}