{
  "type": "Feature",
  "properties": {
    "iso:country":"US",
    "sg:address":"10060 Dogwood St NW C1",
    "sg:city":"Minneapolis",
    "sg:classifiers":[
        {
            "category":"Real Estate",
            "subcategory":"Real Estate Services",
            "type":"Services"
        },
        {
            "category":"Real Estate",
            "subcategory":"Real Estate Operator",
            "type":"Services"
        }
    ],
    "sg:phone":"+1 763 576 5155",
    "sg:postcode":"55448",
    "sg:province":"MN",
    "sg:tags":[
        "vacancy",
        "apartment",
        "rental",
        "finder",
        "listing"
    ],
    "wof:name":"North Star Ridge",
    "wof:placetype":"venue"
},
  "geometry": {"coordinates":[-93.271719,45.152684],"type":"Point"}
}