{
  "type": "Feature",
  "properties": {
    "iso:country":"US",
    "sg:address":"6510 Bayview Dr",
    "sg:city":"Excelsior",
    "sg:classifiers":[
        {
            "category":"Building & Trades",
            "subcategory":"Construction",
            "type":"Services"
        }
    ],
    "sg:phone":"+1 952 474 5198",
    "sg:postcode":"55331",
    "sg:province":"MN",
    "sg:tags":[
        "repairing",
        "house",
        "remodeling",
        "contractor"
    ],
    "wof:name":"Mach Home Builders",
    "wof:placetype":"venue"
},
  "geometry": {"coordinates":[-93.64520899999999,44.885761],"type":"Point"}
}