{
  "type": "Feature",
  "properties": {
    "iso:country":"US",
    "sg:address":"737 W Parkview Ave",
    "sg:city":"Saint Paul",
    "sg:classifiers":[
        {
            "category":"Professional",
            "subcategory":"Management & Consulting",
            "type":"Services"
        }
    ],
    "sg:phone":"+1 651 489 8072",
    "sg:postcode":"55117",
    "sg:province":"MN",
    "sg:tags":[
        "business"
    ],
    "wof:name":"Tree House Productions",
    "wof:placetype":"venue"
},
  "geometry": {"coordinates":[-93.129519,44.983756],"type":"Point"}
}