{
  "type": "Feature",
  "properties": {
    "addr:full":"455 Watkins St Mora MN 55051",
    "addr:housenumber":"455",
    "addr:postcode":"55051",
    "addr:street":"Watkins St",
    "iso:country":"US",
    "sg:address":"455 Watkins St",
    "sg:city":"Mora",
    "sg:classifiers":[
        {
            "category":"Manufacturing",
            "subcategory":"Apparel",
            "type":"Manufacturing & Wholesale Goods"
        }
    ],
    "sg:phone":"+1 320 679 1994",
    "sg:postcode":"55051",
    "sg:province":"MN",
    "sg:tags":[
        "outerwear",
        "mfg"
    ],
    "wof:name":"Judith Ann Originals",
    "wof:placetype":"venue"
},
  "geometry": {"coordinates":[-93.295773,45.872771],"type":"Point"}
}