{
  "type": "Feature",
  "properties": {
    "iso:country":"US",
    "sg:address":"4025 83rd Ave N",
    "sg:city":"Minneapolis",
    "sg:classifiers":[
        {
            "category":"Manufacturing",
            "subcategory":"Textiles",
            "type":"Manufacturing & Wholesale Goods"
        }
    ],
    "sg:phone":"+1 763 561 8115",
    "sg:postcode":"55443",
    "sg:province":"MN",
    "sg:tags":[
        "mill",
        "fabric",
        "cotton"
    ],
    "wof:name":"ZS Creations",
    "wof:placetype":"venue"
},
  "geometry": {"coordinates":[-93.33378,45.105202],"type":"Point"}
}