{
  "type": "Feature",
  "properties": {
    "addr:full":"18285 Minnetonka Blvd # D Wayzata MN 55391",
    "addr:housenumber":"18285",
    "addr:postcode":"55391",
    "addr:street":"Minnetonka Blvd # D",
    "iso:country":"US",
    "sg:address":"18285 Minnetonka Blvd # D",
    "sg:city":"Wayzata",
    "sg:classifiers":[
        {
            "category":"Shopping",
            "subcategory":"Hobbies, Toys, & Games",
            "type":"Retail Goods"
        }
    ],
    "sg:phone":"+1 952 473 1253",
    "sg:postcode":"55391",
    "sg:province":"MN",
    "sg:tags":[
        "supply"
    ],
    "wof:name":"Phoenix Games",
    "wof:placetype":"venue"
},
  "geometry": {"coordinates":[-93.512264,44.942147],"type":"Point"}
}