{
  "type": "Feature",
  "properties": {
    "addr:full":"1156 Anderson Ln Saint Paul MN 55127",
    "addr:housenumber":"1156",
    "addr:postcode":"55127",
    "addr:street":"Anderson Ln",
    "iso:country":"US",
    "sg:address":"1156 Anderson Ln",
    "sg:city":"Saint Paul",
    "sg:classifiers":[
        {
            "category":"Social Services",
            "subcategory":"Child Care",
            "type":"Services"
        }
    ],
    "sg:phone":"+1 651 429 3886",
    "sg:postcode":"55127",
    "sg:province":"MN",
    "sg:tags":[
        "day"
    ],
    "wof:name":"Sara Kubitschek",
    "wof:placetype":"venue"
},
  "geometry": {"coordinates":[-93.05275899999999,45.11041],"type":"Point"}
}