{
  "type": "Feature",
  "properties": {
    "addr:full":"2555 US Hwy 10 St Paul MN 55112",
    "addr:housenumber":"2555",
    "addr:postcode":"55112",
    "addr:street":"Us Hwy 10",
    "iso:country":"US",
    "sg:address":"2555 US Hwy 10",
    "sg:city":"St Paul",
    "sg:classifiers":[
        {
            "category":"Restaurant",
            "type":"Food & Drink"
        }
    ],
    "sg:phone":"+1 763 786 2216",
    "sg:postcode":"55112",
    "sg:province":"MN",
    "wof:name":"Best Steak House",
    "wof:placetype":"venue"
},
  "geometry": {"coordinates":[-93.21307,45.107742],"type":"Point"}
}