{
  "type": "Feature",
  "properties": {
    "iso:country":"US",
    "sg:address":"8160 Coller Way",
    "sg:city":"Saint Paul",
    "sg:classifiers":[
        {
            "category":"Manufacturing",
            "subcategory":"Tools & Machinery",
            "type":"Manufacturing & Wholesale Goods"
        }
    ],
    "sg:phone":"+1 651 264 9444",
    "sg:postcode":"55125",
    "sg:province":"MN",
    "sg:tags":[
        "electrical",
        "mfg"
    ],
    "wof:name":"Viking Tool & Fastener",
    "wof:placetype":"venue"
},
  "geometry": {"coordinates":[-92.937101,44.942064],"type":"Point"}
}