{
  "type": "Feature",
  "properties": {
    "addr:full":"16230 8th Ave N Minneapolis MN 55447",
    "addr:housenumber":"16230",
    "addr:postcode":"55447",
    "addr:street":"8Th Ave N",
    "iso:country":"US",
    "sg:address":"16230 8th Ave N",
    "sg:city":"Minneapolis",
    "sg:classifiers":[
        {
            "category":"Wholesale",
            "subcategory":"Stationery",
            "type":"Manufacturing & Wholesale Goods"
        }
    ],
    "sg:phone":"+1 763 473 1919",
    "sg:postcode":"55447",
    "sg:province":"MN",
    "sg:tags":[
        "paper"
    ],
    "wof:name":"James E Abell",
    "wof:placetype":"venue"
},
  "geometry": {"coordinates":[-93.485896,44.986335],"type":"Point"}
}