{
  "type": "Feature",
  "properties": {
    "addr:full":"12579 Driftwood Ln Saint Paul MN 55124",
    "addr:housenumber":"12579",
    "addr:postcode":"55124",
    "addr:street":"Driftwood Ln",
    "iso:country":"US",
    "sg:address":"12579 Driftwood Ln",
    "sg:city":"Saint Paul",
    "sg:classifiers":[
        {
            "category":"Shopping",
            "subcategory":"Pharmacy",
            "type":"Retail Goods"
        }
    ],
    "sg:phone":"+1 952 423 4395",
    "sg:postcode":"55124",
    "sg:province":"MN",
    "wof:name":"Willmott Drug",
    "wof:placetype":"venue"
},
  "geometry": {"coordinates":[-93.16432399999999,44.766789],"type":"Point"}
}