{
  "type": "Feature",
  "properties": {
    "iso:country":"US",
    "sg:address":"1949 Shawnee Rd",
    "sg:city":"Saint Paul",
    "sg:classifiers":[
        {
            "category":"Manufacturing",
            "subcategory":"Textiles",
            "type":"Manufacturing & Wholesale Goods"
        }
    ],
    "sg:phone":"+1 651 688 2006",
    "sg:postcode":"55122",
    "sg:province":"MN",
    "sg:tags":[
        "mill",
        "knit",
        "outerwear"
    ],
    "wof:name":"Knits Usa Inc",
    "wof:placetype":"venue"
},
  "geometry": {"coordinates":[-93.20258800000001,44.826113],"type":"Point"}
}