{
  "type": "Feature",
  "properties": {
    "addr:full":"2548 Big Horn Bay Rd NW Alexandria MN 56308",
    "addr:housenumber":"2548",
    "addr:postcode":"56308",
    "addr:street":"Big Horn Bay Rd Nw",
    "iso:country":"US",
    "sg:address":"2548 Big Horn Bay Rd NW",
    "sg:city":"Alexandria",
    "sg:classifiers":[
        {
            "category":"Travel",
            "subcategory":"Hotels & Motels",
            "type":"Entertainment"
        }
    ],
    "sg:phone":"+1 320 834 2514",
    "sg:postcode":"56308",
    "sg:province":"MN",
    "sg:tags":[
        "resort",
        "operation"
    ],
    "wof:name":"Big Horn Bay Ceramic's",
    "wof:placetype":"venue"
},
  "geometry": {"coordinates":[-95.41618,46.02022],"type":"Point"}
}