{
  "type": "Feature",
  "properties": {
    "iso:country":"US",
    "sg:address":"12633 Sable Dr",
    "sg:city":"Burnsville",
    "sg:classifiers":[
        {
            "category":"Shopping",
            "type":"Retail Goods"
        },
        {
            "category":"Manufacturing",
            "subcategory":"Paper Products",
            "type":"Manufacturing & Wholesale Goods"
        }
    ],
    "sg:phone":"+1 952 890 8479",
    "sg:postcode":"55337",
    "sg:province":"MN",
    "sg:tags":[
        "packaging",
        "materials-wholesale",
        "material",
        "manufacturer"
    ],
    "wof:name":"Flexsol Packaging",
    "wof:placetype":"venue"
},
  "geometry": {"coordinates":[-93.23137199999999,44.775086],"type":"Point"}
}