{
  "type": "Feature",
  "properties": {
    "iso:country":"US",
    "sg:address":"7704 W 160th Street Lakeville Crossing Shopping Center",
    "sg:city":"Lakeville",
    "sg:classifiers":[
        {
            "category":"Restaurant",
            "type":"Food & Drink"
        }
    ],
    "sg:phone":"+1 952 997 6646",
    "sg:postcode":"55044",
    "sg:province":"MN",
    "sg:tags":[
        "fusion",
        "sushi",
        "bar",
        "thai",
        "asian"
    ],
    "sg:website":"ronincafe.com",
    "wof:name":"Ronin Sushi Cafe",
    "wof:placetype":"venue"
},
  "geometry": {"coordinates":[-93.22216899999999,44.71736],"type":"Point"}
}