{
  "type": "Feature",
  "properties": {
    "addr:full":"1630 University Ave W St Paul MN 55104",
    "addr:housenumber":"1630",
    "addr:postcode":"55104",
    "addr:street":"University Ave W",
    "iso:country":"US",
    "sg:address":"1630 University Ave W",
    "sg:city":"St Paul",
    "sg:classifiers":[
        {
            "category":"Health Services",
            "subcategory":"Doctor",
            "type":"Services"
        }
    ],
    "sg:phone":"+1 651 645 5612",
    "sg:postcode":"55104",
    "sg:province":"MN",
    "sg:tags":[
        "dentist"
    ],
    "wof:name":"Midway Family Orthodontics",
    "wof:placetype":"venue"
},
  "geometry": {"coordinates":[-93.167995,44.955602],"type":"Point"}
}