{
  "type": "Feature",
  "properties": {
    "addr:full":"13604 80th Cir N Osseo MN 55369",
    "addr:housenumber":"13604",
    "addr:postcode":"55369",
    "addr:street":"80Th Cir N",
    "iso:country":"US",
    "sg:address":"13604 80th Cir N",
    "sg:city":"Osseo",
    "sg:classifiers":[
        {
            "category":"Recreation",
            "type":"Entertainment"
        }
    ],
    "sg:phone":"+1 763 420 8333",
    "sg:postcode":"55369",
    "sg:province":"MN",
    "wof:name":"USA Karate Inc",
    "wof:placetype":"venue"
},
  "geometry": {"coordinates":[-93.45352699999999,45.100591],"type":"Point"}
}