{
  "type": "Feature",
  "properties": {
    "iso:country":"US",
    "sg:address":"4309 Constance Blvd NE",
    "sg:city":"Anoka",
    "sg:classifiers":[
        {
            "category":"Manufacturing",
            "subcategory":"Retail Goods",
            "type":"Manufacturing & Wholesale Goods"
        }
    ],
    "sg:phone":"+1 763 434 6215",
    "sg:postcode":"55304",
    "sg:province":"MN",
    "sg:tags":[
        "candle",
        "product",
        "mfg"
    ],
    "wof:name":"White Oak Candles LLC",
    "wof:placetype":"venue"
},
  "geometry": {"coordinates":[-93.160518,45.265729],"type":"Point"}
}