{
  "type": "Feature",
  "properties": {
    "iso:country":"US",
    "sg:address":"127 E 2nd St",
    "sg:city":"Duluth",
    "sg:classifiers":[
        {
            "category":"Manufacturing",
            "subcategory":"Printing",
            "type":"Manufacturing & Wholesale Goods"
        }
    ],
    "sg:phone":"+1 218 727 1513",
    "sg:postcode":"55805",
    "sg:province":"MN",
    "sg:tags":[
        "print",
        "commercial",
        "lithographic",
        "typesetting"
    ],
    "sg:website":"www.serviceprinters.com",
    "wof:name":"Service Printers Of Duluth Inc",
    "wof:placetype":"venue"
},
  "geometry": {"coordinates":[-92.098259,46.790001],"type":"Point"}
}