{
  "type": "Feature",
  "properties": {
    "addr:full":"7525 Brooklyn Blvd Brooklyn Park MN 55443",
    "addr:housenumber":"7525",
    "addr:postcode":"55443",
    "addr:street":"Brooklyn Blvd",
    "iso:country":"US",
    "sg:address":"7525 Brooklyn Blvd",
    "sg:city":"Brooklyn Park",
    "sg:classifiers":[
        {
            "category":"Food & Beverages",
            "subcategory":"Groceries & Convenience Stores",
            "type":"Retail Goods"
        }
    ],
    "sg:phone":"+1 763 566 6624",
    "sg:postcode":"55443",
    "sg:province":"MN",
    "sg:website":"www.holidaystationstores.com",
    "wof:name":"Holiday Station Store",
    "wof:placetype":"venue"
},
  "geometry": {"coordinates":[-93.353745,45.092808],"type":"Point"}
}