{
  "type": "Feature",
  "properties": {
    "addr:full":"746 Selby Ave St Paul MN 55104",
    "addr:housenumber":"746",
    "addr:postcode":"55104",
    "addr:street":"Selby Ave",
    "iso:country":"US",
    "sg:address":"746 Selby Ave",
    "sg:city":"St Paul",
    "sg:classifiers":[
        {
            "category":"Wholesale",
            "subcategory":"Machinery & Supplies",
            "type":"Manufacturing & Wholesale Goods"
        }
    ],
    "sg:phone":"+1 651 222 1738",
    "sg:postcode":"55104",
    "sg:province":"MN",
    "sg:tags":[
        "equipment",
        "sewer",
        "cleaning"
    ],
    "sg:website":"www.mytana.com",
    "wof:name":"My-Tana Mfg Co",
    "wof:placetype":"venue"
},
  "geometry": {"coordinates":[-93.132983,44.946532],"type":"Point"}
}