{
  "type": "Feature",
  "properties": {
    "addr:full":"505 Wabasha St N St Paul MN 55102",
    "addr:housenumber":"505",
    "addr:postcode":"55102",
    "addr:street":"Wabasha St N",
    "iso:country":"US",
    "sg:address":"505 Wabasha St N",
    "sg:city":"St Paul",
    "sg:classifiers":[
        {
            "category":"Education",
            "subcategory":"Junior College",
            "type":"Public Place"
        },
        {
            "category":"Education",
            "subcategory":"School",
            "type":"Public Place"
        }
    ],
    "sg:phone":"+1 651 726 2100",
    "sg:postcode":"55102",
    "sg:province":"MN",
    "sg:tags":[
        "technical",
        "high",
        "institute"
    ],
    "sg:website":"www.mnbusinessacademy.org",
    "wof:name":"Minnesota Business Academy",
    "wof:placetype":"venue"
},
  "geometry": {"coordinates":[-93.09847000000001,44.94972],"type":"Point"}
}