{
  "type": "Feature",
  "properties": {
    "iso:country":"US",
    "sg:address":"5533 River Wood Dr",
    "sg:city":"Savage",
    "sg:classifiers":[
        {
            "category":"Building & Trades",
            "subcategory":"Construction",
            "type":"Services"
        }
    ],
    "sg:phone":"+1 952 926 3671",
    "sg:postcode":"55378",
    "sg:province":"MN",
    "sg:tags":[
        "repairing",
        "house",
        "remodeling",
        "contractor"
    ],
    "wof:name":"Builders Advantage",
    "wof:placetype":"venue"
},
  "geometry": {"coordinates":[-93.349458,44.735689],"type":"Point"}
}