{
  "type": "Feature",
  "properties": {
    "iso:country":"US",
    "sg:address":"302 N Plainview Ave",
    "sg:city":"Mankato",
    "sg:classifiers":[
        {
            "category":"Manufacturing",
            "subcategory":"Food",
            "type":"Manufacturing & Wholesale Goods"
        }
    ],
    "sg:phone":"+1 507 388 2288",
    "sg:postcode":"56001",
    "sg:province":"MN",
    "sg:tags":[
        "personal",
        "malt",
        "beverage",
        "mfg",
        "alcoholic"
    ],
    "wof:name":"Bandana Brewery",
    "wof:placetype":"venue"
},
  "geometry": {"coordinates":[-93.971155,44.163093],"type":"Point"}
}