{
  "type": "Feature",
  "properties": {
    "iso:country":"US",
    "sg:address":"3850 Dight Ave",
    "sg:city":"Minneapolis",
    "sg:classifiers":[
        {
            "category":"Freight",
            "type":"Transportation"
        }
    ],
    "sg:phone":"+1 612 724 1036",
    "sg:postcode":"55406",
    "sg:province":"MN",
    "sg:tags":[
        "delivery",
        "operator",
        "local",
        "courier",
        "trucking"
    ],
    "wof:name":"Ground Delivery Systems Inc",
    "wof:placetype":"venue"
},
  "geometry": {"coordinates":[-93.225998,44.933201],"type":"Point"}
}