{
  "type": "Feature",
  "properties": {
    "iso:country":"US",
    "sg:address":"5353 Gamble Dr Ste 125",
    "sg:city":"Minneapolis",
    "sg:classifiers":[
        {
            "category":"Professional",
            "subcategory":"Lawyer & Legal Services",
            "type":"Services"
        }
    ],
    "sg:phone":"+1 952 544 1577",
    "sg:postcode":"55416",
    "sg:province":"MN",
    "sg:tags":[
        "personal",
        "injury"
    ],
    "wof:name":"Zins David E Atty",
    "wof:placetype":"venue"
},
  "geometry": {"coordinates":[-93.34729799999999,44.965401],"type":"Point"}
}