{
  "type": "Feature",
  "properties": {
    "addr:full":"1521 39th Ave NE Minneapolis MN 55421",
    "addr:housenumber":"1521",
    "addr:postcode":"55421",
    "addr:street":"39Th Ave Ne",
    "iso:country":"US",
    "sg:address":"1521 39th Ave NE",
    "sg:city":"Minneapolis",
    "sg:classifiers":[
        {
            "category":"Professional",
            "subcategory":"Management & Consulting",
            "type":"Services"
        }
    ],
    "sg:phone":"+1 763 782 9190",
    "sg:postcode":"55421",
    "sg:province":"MN",
    "sg:tags":[
        "public",
        "relations"
    ],
    "wof:name":"Bex Promotions",
    "wof:placetype":"venue"
},
  "geometry": {"coordinates":[-93.23731100000001,45.038321],"type":"Point"}
}