{
  "type": "Feature",
  "properties": {
    "addr:full":"4049 Vernon Ave S Minneapolis MN 55416",
    "addr:housenumber":"4049",
    "addr:postcode":"55416",
    "addr:street":"Vernon Ave S",
    "iso:country":"US",
    "sg:address":"4049 Vernon Ave S",
    "sg:city":"Minneapolis",
    "sg:classifiers":[
        {
            "category":"Real Estate",
            "subcategory":"Real Estate Agent",
            "type":"Services"
        },
        {
            "category":"Real Estate",
            "subcategory":"Real Estate Services",
            "type":"Services"
        }
    ],
    "sg:phone":"+1 952 926 6390",
    "sg:postcode":"55416",
    "sg:province":"MN",
    "sg:tags":[
        "abstract",
        "company",
        "title"
    ],
    "wof:name":"Executive Closers Inc",
    "wof:placetype":"venue"
},
  "geometry": {"coordinates":[-93.349138,44.929823],"type":"Point"}
}