{
  "type": "Feature",
  "properties": {
    "addr:full":"329 State Hwy 15 Truman MN 56088",
    "addr:housenumber":"329",
    "addr:postcode":"56088",
    "addr:street":"State Hwy 15 Truman",
    "iso:country":"US",
    "sg:address":"329 State Hwy 15",
    "sg:city":"Truman",
    "sg:classifiers":[
        {
            "category":"Autos & Motor Vehicles",
            "subcategory":"Automobile Sales",
            "type":"Retail Goods"
        }
    ],
    "sg:phone":"+1 507 776 2131",
    "sg:postcode":"56088",
    "sg:province":"MN",
    "sg:tags":[
        "new",
        "used"
    ],
    "sg:website":"www.melcarlsonchev.com",
    "wof:name":"Mel Carlson Chevrolet Inc",
    "wof:placetype":"venue"
},
  "geometry": {"coordinates":[-94.428175,43.825217],"type":"Point"}
}