{
  "type": "Feature",
  "properties": {
    "addr:full":"322 Aspen Ave NE Menahga MN 56464",
    "addr:housenumber":"322",
    "addr:postcode":"56464",
    "addr:street":"Aspen Ave Ne",
    "iso:country":"US",
    "sg:address":"322 Aspen Ave NE",
    "sg:city":"Menahga",
    "sg:classifiers":[
        {
            "category":"Health Services",
            "subcategory":"Chiropractor",
            "type":"Services"
        }
    ],
    "sg:phone":"+1 218 564 4441",
    "sg:postcode":"56464",
    "sg:province":"MN",
    "sg:tags":[
        "chiropractic"
    ],
    "wof:name":"James Pinoniemi",
    "wof:placetype":"venue"
},
  "geometry": {"coordinates":[-95.100076,46.756972],"type":"Point"}
}