{
  "type": "Feature",
  "properties": {
    "iso:country":"US",
    "sg:address":"6237 University Ave NE",
    "sg:city":"Minneapolis",
    "sg:classifiers":[
        {
            "category":"Wholesale",
            "subcategory":"Machinery & Supplies",
            "type":"Manufacturing & Wholesale Goods"
        }
    ],
    "sg:phone":"+1 763 571 9212",
    "sg:postcode":"55432",
    "sg:province":"MN",
    "sg:tags":[
        "equipment",
        "establishment"
    ],
    "wof:name":"Xenetech U S A Inc",
    "wof:placetype":"venue"
},
  "geometry": {"coordinates":[-93.263355,45.081885],"type":"Point"}
}