{
  "type": "Feature",
  "properties": {
    "iso:country":"US",
    "sg:address":"4324 W 36th St",
    "sg:city":"St Louis Park",
    "sg:classifiers":[
        {
            "category":"Building & Trades",
            "subcategory":"Construction",
            "type":"Services"
        }
    ],
    "sg:phone":"+1 952 922 6530",
    "sg:postcode":"55416",
    "sg:province":"MN",
    "sg:tags":[
        "contractor"
    ],
    "wof:name":"Asher Cable Contracting Inc",
    "wof:placetype":"venue"
},
  "geometry": {"coordinates":[-93.332812,44.93851],"type":"Point"}
}