{
  "type": "Feature",
  "properties": {
    "addr:full":"618 Industrial Blvd NE Minneapolis MN 55413",
    "addr:housenumber":"618",
    "addr:postcode":"55413",
    "addr:street":"Industrial Blvd Ne",
    "iso:country":"US",
    "sg:address":"618 Industrial Blvd NE",
    "sg:city":"Minneapolis",
    "sg:classifiers":[
        {
            "category":"Wholesale",
            "subcategory":"Hardware",
            "type":"Manufacturing & Wholesale Goods"
        }
    ],
    "sg:phone":"+1 612 379 3137",
    "sg:postcode":"55413",
    "sg:province":"MN",
    "sg:tags":[
        "fastener"
    ],
    "wof:name":"Fastenal Co",
    "wof:placetype":"venue"
},
  "geometry": {"coordinates":[-93.21164400000001,45.000448],"type":"Point"}
}