{
  "type": "Feature",
  "properties": {
    "iso:country":"US",
    "sg:address":"5119 212th St W",
    "sg:city":"Farmington",
    "sg:classifiers":[
        {
            "category":"Manufacturing",
            "subcategory":"Rubber & Plastics",
            "type":"Manufacturing & Wholesale Goods"
        }
    ],
    "sg:phone":"+1 651 463 4800",
    "sg:postcode":"55024",
    "sg:province":"MN",
    "sg:website":"www.duoplastics.com",
    "wof:name":"Imperial Plastics Inc",
    "wof:placetype":"venue"
},
  "geometry": {"coordinates":[-93.16718400000001,44.641753],"type":"Point"}
}