{
  "type": "Feature",
  "properties": {
    "iso:country":"US",
    "sg:address":"215 W 4th St",
    "sg:city":"Duluth",
    "sg:classifiers":[
        {
            "category":"Government",
            "subcategory":"Office",
            "type":"Public Place"
        }
    ],
    "sg:phone":"+1 218 726 1370",
    "sg:postcode":"55806",
    "sg:province":"MN",
    "wof:name":"Duluth Indian Svc",
    "wof:placetype":"venue"
},
  "geometry": {"coordinates":[-92.106205,46.786934],"type":"Point"}
}