{
  "type": "Feature",
  "properties": {
    "addr:full":"10024 Dupont Ave S Minneapolis MN 55431",
    "addr:housenumber":"10024",
    "addr:postcode":"55431",
    "addr:street":"Dupont Ave S",
    "iso:country":"US",
    "sg:address":"10024 Dupont Ave S",
    "sg:city":"Minneapolis",
    "sg:classifiers":[
        {
            "category":"Manufacturing",
            "subcategory":"Printing",
            "type":"Manufacturing & Wholesale Goods"
        }
    ],
    "sg:phone":"+1 952 881 7549",
    "sg:postcode":"55431",
    "sg:province":"MN",
    "sg:tags":[
        "commercial",
        "design"
    ],
    "wof:name":"Tj Graphics Group",
    "wof:placetype":"venue"
},
  "geometry": {"coordinates":[-93.29373099999999,44.819494],"type":"Point"}
}