{
  "type": "Feature",
  "properties": {
    "addr:full":"23092 Havelka Ct N Forest Lake MN 55025",
    "addr:postcode":"23092;55025",
    "addr:street":"Havelka Ct N",
    "iso:country":"US",
    "sg:address":"23092 Havelka Ct N",
    "sg:city":"Forest Lake",
    "sg:classifiers":[
        {
            "category":"Professional",
            "subcategory":"Business Services",
            "type":"Services"
        }
    ],
    "sg:phone":"+1 651 982 6766",
    "sg:postcode":"55025",
    "sg:province":"MN",
    "wof:name":"Ceqinus Group Inc",
    "wof:placetype":"venue"
},
  "geometry": {"coordinates":[-93.010515,45.284226],"type":"Point"}
}