{
  "type": "Feature",
  "properties": {
    "addr:full":"13492 3rd St Becker MN 55308",
    "addr:housenumber":"13492",
    "addr:postcode":"55308",
    "addr:street":"3Rd St",
    "iso:country":"US",
    "sg:address":"13492 3rd St",
    "sg:city":"Becker",
    "sg:classifiers":[
        {
            "category":"Wholesale",
            "subcategory":"Durable Goods & Equipment",
            "type":"Manufacturing & Wholesale Goods"
        }
    ],
    "sg:phone":"+1 763 261 5759",
    "sg:postcode":"55308",
    "sg:province":"MN",
    "wof:name":"Stamps n More",
    "wof:placetype":"venue"
},
  "geometry": {"coordinates":[-93.879852,45.397092],"type":"Point"}
}