{
  "type": "Feature",
  "properties": {
    "iso:country":"US",
    "sg:address":"4112 308th Ln NW",
    "sg:city":"Cambridge",
    "sg:classifiers":[
        {
            "category":"Freight",
            "type":"Transportation"
        }
    ],
    "sg:phone":"+1 763 689 2134",
    "sg:postcode":"55008",
    "sg:province":"MN",
    "sg:tags":[
        "operator",
        "local",
        "trucking"
    ],
    "wof:name":"David Grundmeier Trucking",
    "wof:placetype":"venue"
},
  "geometry": {"coordinates":[-93.37119199999999,45.528743],"type":"Point"}
}