{
  "type": "Feature",
  "properties": {
    "iso:country":"US",
    "sg:address":"8849 Hastings St NE",
    "sg:city":"Minneapolis",
    "sg:classifiers":[
        {
            "category":"Social Services",
            "subcategory":"Child Care",
            "type":"Services"
        }
    ],
    "sg:phone":"+1 763 784 1535",
    "sg:postcode":"55449",
    "sg:province":"MN",
    "sg:tags":[
        "daycare"
    ],
    "wof:name":"Lois E Leavitt",
    "wof:placetype":"venue"
},
  "geometry": {"coordinates":[-93.22507299999999,45.131883],"type":"Point"}
}