{
  "type": "Feature",
  "properties": {
    "iso:country":"US",
    "sg:address":"9725 Garfield Ave S",
    "sg:city":"Minneapolis",
    "sg:classifiers":[
        {
            "category":"Education",
            "subcategory":"Vocational School",
            "type":"Public Place"
        },
        {
            "category":"Education",
            "subcategory":"School",
            "type":"Public Place"
        }
    ],
    "sg:phone":"+1 952 746 5215",
    "sg:postcode":"55420",
    "sg:province":"MN",
    "sg:tags":[
        "high",
        "middle",
        "cosmetology",
        "elementary"
    ],
    "wof:name":"Scotlewis Schools",
    "wof:placetype":"venue"
},
  "geometry": {"coordinates":[-93.286655,44.828206],"type":"Point"}
}