{
  "type": "Feature",
  "properties": {
    "addr:full":"428 W Franklin Ave Minneapolis MN 55405",
    "addr:housenumber":"428",
    "addr:postcode":"55405",
    "addr:street":"W Franklin Ave",
    "iso:country":"US",
    "sg:address":"428 W Franklin Ave",
    "sg:city":"Minneapolis",
    "sg:classifiers":[
        {
            "category":"Real Estate",
            "subcategory":"Real Estate Agent",
            "type":"Services"
        }
    ],
    "sg:phone":"+1 612 275 3742",
    "sg:postcode":"55405",
    "sg:province":"MN",
    "wof:name":"Travis Meldahl",
    "wof:placetype":"venue"
},
  "geometry": {"coordinates":[-93.28524899999999,44.962777],"type":"Point"}
}