{
  "type": "Feature",
  "properties": {
    "addr:full":"29439 263rd Ave Albany MN 56307",
    "addr:housenumber":"29439",
    "addr:postcode":"56307",
    "addr:street":"263Rd Ave",
    "iso:country":"US",
    "sg:address":"29439 263rd Ave",
    "sg:city":"Albany",
    "sg:classifiers":[
        {
            "category":"Freight",
            "type":"Transportation"
        }
    ],
    "sg:phone":"+1 320 845 4638",
    "sg:postcode":"56307",
    "sg:province":"MN",
    "sg:tags":[
        "operator",
        "local",
        "trucking"
    ],
    "wof:name":"Thelen Trucking",
    "wof:placetype":"venue"
},
  "geometry": {"coordinates":[-94.660284,45.548655],"type":"Point"}
}