{
  "type": "Feature",
  "properties": {
    "iso:country":"US",
    "sg:address":"4904 Miller Trunk Hwy",
    "sg:city":"Duluth",
    "sg:classifiers":[
        {
            "category":"Retail",
            "subcategory":"Auto Repair",
            "type":"Services"
        }
    ],
    "sg:phone":"+1 218 729 5252",
    "sg:postcode":"55811",
    "sg:province":"MN",
    "sg:tags":[
        "automotive"
    ],
    "wof:name":"Smokeys Towing & Auto Service",
    "wof:placetype":"venue"
},
  "geometry": {"coordinates":[-92.19608599999999,46.827928],"type":"Point"}
}