{
  "type": "Feature",
  "properties": {
    "addr:full":"2635 Nanticoke St Duluth MN 55811",
    "addr:housenumber":"2635",
    "addr:postcode":"55811",
    "addr:street":"Nanticoke St",
    "iso:country":"US",
    "sg:address":"2635 Nanticoke St",
    "sg:city":"Duluth",
    "sg:classifiers":[
        {
            "category":"Retail",
            "subcategory":"Auto Repair",
            "type":"Services"
        }
    ],
    "sg:phone":"+1 218 722 2198",
    "sg:postcode":"55811",
    "sg:province":"MN",
    "sg:tags":[
        "machine",
        "automobile",
        "shop",
        "automotive"
    ],
    "wof:name":"Blackwell's Custom Balancing",
    "wof:placetype":"venue"
},
  "geometry": {"coordinates":[-92.162498,46.782293],"type":"Point"}
}