{
  "type": "Feature",
  "properties": {
    "addr:full":"118 W Main St Luverne MN 56156",
    "addr:housenumber":"118",
    "addr:postcode":"56156",
    "addr:street":"W Main St",
    "iso:country":"US",
    "sg:address":"118 W Main St",
    "sg:city":"Luverne",
    "sg:classifiers":[
        {
            "category":"Personal",
            "subcategory":"Barber",
            "type":"Services"
        }
    ],
    "sg:phone":"+1 507 283 4535",
    "sg:postcode":"56156",
    "sg:province":"MN",
    "sg:tags":[
        "shop"
    ],
    "wof:name":"Chucks Barber Shop",
    "wof:placetype":"venue"
},
  "geometry": {"coordinates":[-96.210959,43.654368],"type":"Point"}
}