{
  "type": "Feature",
  "properties": {
    "addr:full":"1600 Chicago Ave Minneapolis MN 55404",
    "addr:housenumber":"1600",
    "addr:postcode":"55404",
    "addr:street":"Chicago Ave",
    "iso:country":"US",
    "sg:address":"1600 Chicago Ave",
    "sg:city":"Minneapolis",
    "sg:classifiers":[
        {
            "category":"Food & Beverages",
            "subcategory":"Groceries & Convenience Stores",
            "type":"Retail Goods"
        }
    ],
    "sg:phone":"+1 612 333 6478",
    "sg:postcode":"55404",
    "sg:province":"MN",
    "wof:name":"Elliot Park Grocery",
    "wof:placetype":"venue"
},
  "geometry": {"coordinates":[-93.26254299999999,44.967152],"type":"Point"}
}