{
  "type": "Feature",
  "properties": {
    "addr:full":"7648 Brooklyn Blvd Minneapolis MN 55443",
    "addr:housenumber":"7648",
    "addr:postcode":"55443",
    "addr:street":"Brooklyn Blvd",
    "iso:country":"US",
    "sg:address":"7648 Brooklyn Blvd",
    "sg:city":"Minneapolis",
    "sg:classifiers":[
        {
            "category":"Professional",
            "subcategory":"Employment Agencies",
            "type":"Services"
        }
    ],
    "sg:phone":"+1 763 561 9675",
    "sg:postcode":"55443",
    "sg:province":"MN",
    "sg:tags":[
        "leasing"
    ],
    "sg:website":"www.theworkconnection.com",
    "wof:name":"Work Connection Inc",
    "wof:placetype":"venue"
},
  "geometry": {"coordinates":[-93.35253899999999,45.092033],"type":"Point"}
}