{
  "type": "Feature",
  "properties": {
    "addr:full":"110 4th St NE Staples MN 56479",
    "addr:housenumber":"110",
    "addr:postcode":"56479",
    "addr:street":"4Th St Ne",
    "iso:country":"US",
    "sg:address":"110 4th St NE",
    "sg:city":"Staples",
    "sg:classifiers":[
        {
            "category":"Cinema",
            "subcategory":"Movie Rental",
            "type":"Entertainment"
        }
    ],
    "sg:phone":"+1 218 894 2216",
    "sg:postcode":"56479",
    "sg:province":"MN",
    "sg:tags":[
        "video",
        "tape"
    ],
    "wof:name":"Video Volumn",
    "wof:placetype":"venue"
},
  "geometry": {"coordinates":[-94.79486799999999,46.355551],"type":"Point"}
}