{
  "type": "Feature",
  "properties": {
    "iso:country":"US",
    "sg:address":"1025 30th Ave",
    "sg:city":"Sherburn",
    "sg:phone":"+1 507 764 5598",
    "sg:postcode":"56171",
    "sg:province":"MN",
    "sg:tags":[
        "farm",
        "corn",
        "soybean"
    ],
    "wof:name":"Ronald Schafer",
    "wof:placetype":"venue"
},
  "geometry": {"coordinates":[-94.81423599999999,43.637758],"type":"Point"}
}