{
  "type": "Feature",
  "properties": {
    "iso:country":"US",
    "sg:address":"13631 179th St",
    "sg:city":"Little Falls",
    "sg:classifiers":[
        {
            "category":"Building & Trades",
            "subcategory":"Construction",
            "type":"Services"
        }
    ],
    "sg:phone":"+1 320 632 0433",
    "sg:postcode":"56345",
    "sg:province":"MN",
    "sg:tags":[
        "house"
    ],
    "wof:name":"Little Elf Contracting Inc",
    "wof:placetype":"venue"
},
  "geometry": {"coordinates":[-94.37469,46.016738],"type":"Point"}
}