{
  "type": "Feature",
  "properties": {
    "addr:full":"632 Main St North Branch MN 55056",
    "addr:housenumber":"632",
    "addr:postcode":"55056",
    "addr:street":"Main St",
    "iso:country":"US",
    "sg:address":"632 Main St",
    "sg:city":"North Branch",
    "sg:classifiers":[
        {
            "category":"Sports & Exercise",
            "subcategory":"Gym",
            "type":"Entertainment"
        }
    ],
    "sg:phone":"+1 651 277 1013",
    "sg:postcode":"55056",
    "sg:province":"MN",
    "sg:tags":[
        "club",
        "health",
        "studio",
        "gymnasium"
    ],
    "wof:name":"Curves For Women",
    "wof:placetype":"venue"
},
  "geometry": {"coordinates":[-92.978381,45.511369],"type":"Point"}
}