{
  "type": "Feature",
  "properties": {
    "addr:full":"12905 US Hwy 71 Sanborn MN 56083",
    "addr:housenumber":"12905",
    "addr:postcode":"56083",
    "addr:street":"Us Hwy 71",
    "iso:country":"US",
    "sg:address":"12905 US Hwy 71",
    "sg:city":"Sanborn",
    "sg:classifiers":[
        {
            "category":"Wholesale",
            "subcategory":"Farm Supplies",
            "type":"Manufacturing & Wholesale Goods"
        }
    ],
    "sg:phone":"+1 507 648 3648",
    "sg:postcode":"56083",
    "sg:province":"MN",
    "sg:tags":[
        "feed",
        "livestock"
    ],
    "wof:name":"New Line Products Inc",
    "wof:placetype":"venue"
},
  "geometry": {"coordinates":[-95.12826200000001,44.237237],"type":"Point"}
}