{
  "type": "Feature",
  "properties": {
    "addr:full":"5650 Park Irene Dr NE Miltona MN 56354",
    "addr:housenumber":"5650",
    "addr:postcode":"56354",
    "addr:street":"Park Irene Dr Ne",
    "iso:country":"US",
    "sg:address":"5650 Park Irene Dr NE",
    "sg:city":"Miltona",
    "sg:classifiers":[
        {
            "category":"Wholesale",
            "subcategory":"Stationery",
            "type":"Manufacturing & Wholesale Goods"
        }
    ],
    "sg:phone":"+1 218 943 6223",
    "sg:postcode":"56354",
    "sg:province":"MN",
    "sg:tags":[
        "business",
        "form",
        "system"
    ],
    "wof:name":"North Central Business Forms",
    "wof:placetype":"venue"
},
  "geometry": {"coordinates":[-95.301115,46.058751],"type":"Point"}
}