{
  "type": "Feature",
  "properties": {
    "addr:full":"14313 Watersedge Trl NE Prior Lake MN 55372",
    "addr:housenumber":"14313",
    "addr:postcode":"55372",
    "addr:street":"Watersedge Trl Ne",
    "iso:country":"US",
    "sg:address":"14313 Watersedge Trl NE",
    "sg:city":"Prior Lake",
    "sg:classifiers":[
        {
            "category":"Building & Trades",
            "subcategory":"Landscaping Services",
            "type":"Services"
        }
    ],
    "sg:phone":"+1 952 445 5440",
    "sg:postcode":"55372",
    "sg:province":"MN",
    "sg:tags":[
        "lawn",
        "maintenance",
        "grounds"
    ],
    "wof:name":"All Climate Grounds Mntnc",
    "wof:placetype":"venue"
},
  "geometry": {"coordinates":[-93.388293,44.742667],"type":"Point"}
}