{
  "type": "Feature",
  "properties": {
    "iso:country":"US",
    "sg:address":"100 24th St NW",
    "sg:city":"Austin",
    "sg:classifiers":[
        {
            "category":"Professional",
            "subcategory":"Lawyer & Legal Services",
            "type":"Services"
        }
    ],
    "sg:phone":"+1 507 437 3159",
    "sg:postcode":"55912",
    "sg:province":"MN",
    "wof:name":"Scott Richardson Atty",
    "wof:placetype":"venue"
},
  "geometry": {"coordinates":[-93.008715,43.667904],"type":"Point"}
}