{
  "type": "Feature",
  "properties": {
    "iso:country":"US",
    "sg:address":"1046 5th St W",
    "sg:city":"Hastings",
    "sg:classifiers":[
        {
            "category":"Organizations",
            "subcategory":"Religious Organization",
            "type":"Services"
        }
    ],
    "sg:phone":"+1 651 480 2273",
    "sg:postcode":"55033",
    "sg:province":"MN",
    "wof:name":"Hope Lutheran Church",
    "wof:placetype":"venue"
},
  "geometry": {"coordinates":[-92.870102,44.741326],"type":"Point"}
}