{
  "type": "Feature",
  "properties": {
    "addr:full":"1861 Quentin Ave S Lakeland MN 55043",
    "addr:housenumber":"1861",
    "addr:postcode":"55043",
    "addr:street":"Quentin Ave S Lakeland",
    "iso:country":"US",
    "sg:address":"1861 Quentin Ave S",
    "sg:city":"Lakeland",
    "sg:classifiers":[
        {
            "category":"Building & Trades",
            "subcategory":"Construction",
            "type":"Services"
        }
    ],
    "sg:phone":"+1 651 439 7944",
    "sg:postcode":"55043",
    "sg:province":"MN",
    "sg:tags":[
        "contractor"
    ],
    "wof:name":"Obermeier Drywall",
    "wof:placetype":"venue"
},
  "geometry": {"coordinates":[-92.76955599999999,44.922333],"type":"Point"}
}