{
  "type": "Feature",
  "properties": {
    "addr:full":"1003 W Linden St Fergus Falls MN 56537",
    "addr:housenumber":"1003",
    "addr:postcode":"56537",
    "addr:street":"W Linden St",
    "iso:country":"US",
    "sg:address":"1003 W Linden St",
    "sg:city":"Fergus Falls",
    "sg:classifiers":[
        {
            "category":"Social Services",
            "type":"Services"
        }
    ],
    "sg:phone":"+1 218 736 5025",
    "sg:postcode":"56537",
    "sg:province":"MN",
    "wof:name":"Terrace S L S",
    "wof:placetype":"venue"
},
  "geometry": {"coordinates":[-96.09284,46.286541],"type":"Point"}
}