{
  "type": "Feature",
  "properties": {
    "addr:full":"7433 Chicago Ave Minneapolis MN 55423",
    "addr:housenumber":"7433",
    "addr:postcode":"55423",
    "addr:street":"Chicago Ave",
    "iso:country":"US",
    "sg:address":"7433 Chicago Ave",
    "sg:city":"Minneapolis",
    "sg:classifiers":[
        {
            "category":"Professional",
            "subcategory":"Art Services",
            "type":"Services"
        }
    ],
    "sg:phone":"+1 612 558 8104",
    "sg:postcode":"55423",
    "sg:province":"MN",
    "sg:tags":[
        "interior",
        "designer",
        "decorator"
    ],
    "wof:name":"Exclusive Interiors, Inc.",
    "wof:placetype":"venue"
},
  "geometry": {"coordinates":[-93.26301599999999,44.868514],"type":"Point"}
}