{
  "type": "Feature",
  "properties": {
    "addr:full":"6938 Lakeshore Dr NW Williams MN 56686",
    "addr:housenumber":"6938",
    "addr:postcode":"56686",
    "addr:street":"Lakeshore Dr Nw",
    "iso:country":"US",
    "sg:address":"6938 Lakeshore Dr NW",
    "sg:city":"Williams",
    "sg:classifiers":[
        {
            "category":"Education",
            "subcategory":"Vocational School",
            "type":"Public Place"
        }
    ],
    "sg:phone":"+1 218 783 5306",
    "sg:postcode":"56686",
    "sg:province":"MN",
    "wof:name":"Pass Perfect Assoc",
    "wof:placetype":"venue"
},
  "geometry": {"coordinates":[-94.942263,48.963237],"type":"Point"}
}