{
  "type": "Feature",
  "properties": {
    "iso:country":"US",
    "sg:address":"1270 105th Ave NW",
    "sg:city":"Minneapolis",
    "sg:classifiers":[
        {
            "category":"Building & Trades",
            "subcategory":"Construction",
            "type":"Services"
        }
    ],
    "sg:phone":"+1 763 286 3255",
    "sg:postcode":"55433",
    "sg:province":"MN",
    "sg:tags":[
        "site",
        "clean"
    ],
    "wof:name":"M & H Dust Busters",
    "wof:placetype":"venue"
},
  "geometry": {"coordinates":[-93.294661,45.160353],"type":"Point"}
}