{
  "type": "Feature",
  "properties": {
    "iso:country":"US",
    "sg:address":"2066 Palace Ave",
    "sg:city":"Saint Paul",
    "sg:classifiers":[
        {
            "category":"Social Services",
            "subcategory":"Child Care",
            "type":"Services"
        },
        {
            "category":"Education",
            "subcategory":"Preschool",
            "type":"Public Place"
        },
        {
            "category":"Education",
            "subcategory":"School",
            "type":"Public Place"
        }
    ],
    "sg:phone":"+1 651 690 0590",
    "sg:postcode":"55105",
    "sg:province":"MN",
    "sg:tags":[
        "elementary",
        "day"
    ],
    "wof:name":"Master Care",
    "wof:placetype":"venue"
},
  "geometry": {"coordinates":[-93.189201,44.929001],"type":"Point"}
}