{
  "type": "Feature",
  "properties": {
    "addr:full":"779 Smith Ave S Saint Paul MN 55107",
    "addr:housenumber":"779",
    "addr:postcode":"55107",
    "addr:street":"Smith Ave S",
    "iso:country":"US",
    "sg:address":"779 Smith Ave S",
    "sg:city":"Saint Paul",
    "sg:classifiers":[
        {
            "category":"Professional",
            "type":"Services"
        }
    ],
    "sg:phone":"+1 651 224 2444",
    "sg:postcode":"55107",
    "sg:province":"MN",
    "wof:name":"Moonmagick",
    "wof:placetype":"venue"
},
  "geometry": {"coordinates":[-93.101899,44.921706],"type":"Point"}
}