{
  "type": "Feature",
  "properties": {
    "addr:full":"1260 Wildwood Pl Chaska MN 55318",
    "addr:housenumber":"1260",
    "addr:postcode":"55318",
    "addr:street":"Wildwood Pl",
    "iso:country":"US",
    "sg:address":"1260 Wildwood Pl",
    "sg:city":"Chaska",
    "sg:classifiers":[
        {
            "category":"Building & Trades",
            "subcategory":"Construction",
            "type":"Services"
        }
    ],
    "sg:phone":"+1 952 448 4071",
    "sg:postcode":"55318",
    "sg:province":"MN",
    "sg:tags":[
        "contractor"
    ],
    "wof:name":"Roof Development Properties",
    "wof:placetype":"venue"
},
  "geometry": {"coordinates":[-93.577698,44.818003],"type":"Point"}
}