{
  "type": "Feature",
  "properties": {
    "addr:full":"301 2nd St E Hector MN 55342",
    "addr:housenumber":"301",
    "addr:postcode":"55342",
    "addr:street":"2Nd St E Hector",
    "iso:country":"US",
    "sg:address":"301 2nd St E",
    "sg:city":"Hector",
    "sg:classifiers":[
        {
            "category":"Real Estate",
            "subcategory":"Real Estate Operator",
            "type":"Services"
        }
    ],
    "sg:phone":"+1 320 848 2485",
    "sg:postcode":"55342",
    "sg:province":"MN",
    "sg:tags":[
        "apartment"
    ],
    "wof:name":"Sampson Family Lp",
    "wof:placetype":"venue"
},
  "geometry": {"coordinates":[-94.713593,44.742962],"type":"Point"}
}