{
  "type": "Feature",
  "properties": {
    "addr:full":"1921 S 16th Ave W Virginia MN 55792",
    "addr:housenumber":"1921",
    "addr:postcode":"55792",
    "addr:street":"S 16Th Ave W",
    "iso:country":"US",
    "sg:address":"1921 S 16th Ave W",
    "sg:city":"Virginia",
    "sg:classifiers":[
        {
            "category":"Wholesale",
            "subcategory":"Machinery & Supplies",
            "type":"Manufacturing & Wholesale Goods"
        }
    ],
    "sg:phone":"+1 218 749 4484",
    "sg:postcode":"55792",
    "sg:province":"MN",
    "sg:tags":[
        "engine"
    ],
    "sg:website":"www.istate.com",
    "wof:name":"Interstate Detroit Diesel Inc",
    "wof:placetype":"venue"
},
  "geometry": {"coordinates":[-92.559432,47.507576],"type":"Point"}
}