{
  "type": "Feature",
  "properties": {
    "iso:country":"US",
    "sg:address":"702 9th Ave S",
    "sg:city":"Sauk Rapids",
    "sg:classifiers":[
        {
            "category":"Manufacturing",
            "subcategory":"Wood Products",
            "type":"Manufacturing & Wholesale Goods"
        }
    ],
    "sg:phone":"+1 320 253 3761",
    "sg:postcode":"56379",
    "sg:province":"MN",
    "sg:tags":[
        "material",
        "mfg"
    ],
    "wof:name":"Pioneer Panel Systems Inc",
    "wof:placetype":"venue"
},
  "geometry": {"coordinates":[-94.15355700000001,45.582471],"type":"Point"}
}