{
  "type": "Feature",
  "properties": {
    "iso:country":"US",
    "sg:address":"20700 Quentin Ave",
    "sg:city":"Hastings",
    "sg:classifiers":[
        {
            "category":"Professional",
            "subcategory":"Management & Consulting",
            "type":"Services"
        }
    ],
    "sg:phone":"+1 651 438 2164",
    "sg:postcode":"55033",
    "sg:province":"MN",
    "sg:tags":[
        "business"
    ],
    "wof:name":"M A Thompson Consulting Inc",
    "wof:placetype":"venue"
},
  "geometry": {"coordinates":[-92.75037,44.64996],"type":"Point"}
}