{
  "type": "Feature",
  "properties": {
    "iso:country":"US",
    "sg:address":"7243 218th Street Way N",
    "sg:city":"Forest Lake",
    "sg:classifiers":[
        {
            "category":"Freight",
            "type":"Transportation"
        }
    ],
    "sg:phone":"+1 651 464 4121",
    "sg:postcode":"55025",
    "sg:province":"MN",
    "sg:tags":[
        "truck",
        "broker"
    ],
    "wof:name":"SNP Marketing Inc",
    "wof:placetype":"venue"
},
  "geometry": {"coordinates":[-92.958805,45.263879],"type":"Point"}
}