{
  "type": "Feature",
  "properties": {
    "addr:full":"1111 W 22nd St Minneapolis MN 55405",
    "addr:housenumber":"1111",
    "addr:postcode":"55405",
    "addr:street":"W 22Nd St",
    "iso:country":"US",
    "sg:address":"1111 W 22nd St",
    "sg:city":"Minneapolis",
    "sg:classifiers":[
        {
            "category":"Health Services",
            "subcategory":"Health Practitioner",
            "type":"Services"
        }
    ],
    "sg:phone":"+1 612 374 4770",
    "sg:postcode":"55405",
    "sg:province":"MN",
    "sg:tags":[
        "psychotherapist"
    ],
    "wof:name":"Brenda Huttee",
    "wof:placetype":"venue"
},
  "geometry": {"coordinates":[-93.292885,44.960843],"type":"Point"}
}