{
  "type": "Feature",
  "properties": {
    "addr:full":"7887 Fuller Rd Eden Prairie MN 55344",
    "addr:housenumber":"7887",
    "addr:postcode":"55344",
    "addr:street":"Fuller Rd",
    "iso:country":"US",
    "sg:address":"7887 Fuller Rd",
    "sg:city":"Eden Prairie",
    "sg:classifiers":[
        {
            "category":"Wholesale",
            "subcategory":"Groceries",
            "type":"Manufacturing & Wholesale Goods"
        }
    ],
    "sg:phone":"+1 952 994 2234",
    "sg:postcode":"55344",
    "sg:province":"MN",
    "sg:tags":[
        "coffee",
        "roasting"
    ],
    "wof:name":"Wicked Coffee Inc",
    "wof:placetype":"venue"
},
  "geometry": {"coordinates":[-93.479851,44.861652],"type":"Point"}
}