{
  "type": "Feature",
  "properties": {
    "iso:country":"US",
    "sg:address":"524 E Lake Cowdry Rd NW",
    "sg:city":"Alexandria",
    "sg:classifiers":[
        {
            "category":"Banks & Credit Unions",
            "subcategory":"Financial Services",
            "type":"Services"
        }
    ],
    "sg:phone":"+1 320 762 2531",
    "sg:postcode":"56308",
    "sg:province":"MN",
    "sg:tags":[
        "investor"
    ],
    "wof:name":"Investment Pros",
    "wof:placetype":"venue"
},
  "geometry": {"coordinates":[-95.414849,45.899244],"type":"Point"}
}