{
  "type": "Feature",
  "properties": {
    "addr:full":"245 Marie Ave E Saint Paul MN 55118",
    "addr:housenumber":"245",
    "addr:postcode":"55118",
    "addr:street":"Marie Ave E",
    "iso:country":"US",
    "sg:address":"245 Marie Ave E",
    "sg:city":"Saint Paul",
    "sg:classifiers":[
        {
            "category":"Manufacturing",
            "subcategory":"Chemicals & Compounds",
            "type":"Manufacturing & Wholesale Goods"
        }
    ],
    "sg:phone":"+1 651 455 1261",
    "sg:postcode":"55118",
    "sg:province":"MN",
    "sg:tags":[
        "mfg",
        "printing",
        "ink"
    ],
    "wof:name":"Flint Ink Corporation",
    "wof:placetype":"venue"
},
  "geometry": {"coordinates":[-93.073713,44.891028],"type":"Point"}
}