{
  "type": "Feature",
  "properties": {
    "addr:full":"70123 250th St Dassel MN 55325",
    "addr:housenumber":"70123",
    "addr:postcode":"55325",
    "addr:street":"250Th St",
    "iso:country":"US",
    "sg:address":"70123 250th St",
    "sg:city":"Dassel",
    "sg:classifiers":[
        {
            "category":"Manufacturing",
            "subcategory":"Buildings",
            "type":"Manufacturing & Wholesale Goods"
        },
        {
            "category":"Building & Trades",
            "subcategory":"Construction",
            "type":"Services"
        }
    ],
    "sg:phone":"+1 320 275 9184",
    "sg:postcode":"55325",
    "sg:province":"MN",
    "sg:tags":[
        "home",
        "builder",
        "contractor"
    ],
    "wof:name":"Ka Construction",
    "wof:placetype":"venue"
},
  "geometry": {"coordinates":[-94.35762699999999,45.109323],"type":"Point"}
}