{
  "type": "Feature",
  "properties": {
    "iso:country":"US",
    "sg:address":"603 4th Ave E",
    "sg:city":"Alexandria",
    "sg:classifiers":[
        {
            "category":"Organizations",
            "subcategory":"Religious Organization",
            "type":"Services"
        }
    ],
    "sg:phone":"+1 320 763 4623",
    "sg:postcode":"56308",
    "sg:province":"MN",
    "wof:name":"Parsonage Rev Chrstn Erickson",
    "wof:placetype":"venue"
},
  "geometry": {"coordinates":[-95.37003300000001,45.888302],"type":"Point"}
}