{
  "type": "Feature",
  "properties": {
    "addr:full":"5201 Bryant Ave N Minneapolis MN 55430",
    "addr:housenumber":"5201",
    "addr:postcode":"55430",
    "addr:street":"Bryant Ave N",
    "iso:country":"US",
    "sg:address":"5201 Bryant Ave N",
    "sg:city":"Minneapolis",
    "sg:classifiers":[
        {
            "category":"Health Services",
            "subcategory":"Doctor",
            "type":"Services"
        }
    ],
    "sg:phone":"+1 612 529 9484",
    "sg:postcode":"55430",
    "sg:province":"MN",
    "wof:name":"Heritage Dental Center",
    "wof:placetype":"venue"
},
  "geometry": {"coordinates":[-93.29150300000001,45.049324],"type":"Point"}
}