{
  "type": "Feature",
  "properties": {
    "iso:country":"US",
    "sg:address":"102 E Front St",
    "sg:city":"Fulda",
    "sg:phone":"+1 507 425 2541",
    "sg:postcode":"56131",
    "sg:province":"MN",
    "sg:tags":[
        "oil"
    ],
    "wof:name":"Nobles County Co-Op Oil Co",
    "wof:placetype":"venue"
},
  "geometry": {"coordinates":[-95.600178,43.869765],"type":"Point"}
}