{
  "type": "Feature",
  "properties": {
    "addr:full":"5355 28th St NW Maple Lake MN 55358",
    "addr:housenumber":"5355",
    "addr:postcode":"55358",
    "addr:street":"28Th St Nw",
    "iso:country":"US",
    "sg:address":"5355 28th St NW",
    "sg:city":"Maple Lake",
    "sg:classifiers":[
        {
            "category":"Farming",
            "subcategory":"Nursery",
            "type":"Manufacturing & Wholesale Goods"
        }
    ],
    "sg:phone":"+1 320 963 3682",
    "sg:postcode":"55358",
    "sg:province":"MN",
    "sg:tags":[
        "ornamental"
    ],
    "wof:name":"Clarence Carlson",
    "wof:placetype":"venue"
},
  "geometry": {"coordinates":[-93.999166,45.193439],"type":"Point"}
}