{
  "type": "Feature",
  "properties": {
    "addr:full":"3368 Bunker Lake Blvd NW Andover MN 55304",
    "addr:housenumber":"3368",
    "addr:postcode":"55304",
    "addr:street":"Bunker Lake Blvd Nw",
    "iso:country":"US",
    "sg:address":"3368 Bunker Lake Blvd NW",
    "sg:city":"Andover",
    "sg:classifiers":[
        {
            "category":"Health Services",
            "subcategory":"Chiropractor",
            "type":"Services"
        }
    ],
    "sg:phone":"+1 763 427 0820",
    "sg:postcode":"55304",
    "sg:province":"MN",
    "sg:website":"www.mndrx.com",
    "wof:name":"Spinal Decompression Clinics of Minnesota",
    "wof:placetype":"venue"
},
  "geometry": {"coordinates":[-93.351741,45.219329],"type":"Point"}
}