{
  "type": "Feature",
  "properties": {
    "iso:country":"US",
    "sg:address":"4530 Airpark Blvd",
    "sg:city":"Duluth",
    "sg:classifiers":[
        {
            "category":"Retail",
            "subcategory":"Laundry & Dry Cleaning",
            "type":"Services"
        }
    ],
    "sg:phone":"+1 218 722 4413",
    "sg:postcode":"55811",
    "sg:province":"MN",
    "sg:tags":[
        "linen",
        "supply"
    ],
    "wof:name":"Ameri Pride Linen & Apparel",
    "wof:placetype":"venue"
},
  "geometry": {"coordinates":[-92.168358,46.833098],"type":"Point"}
}