{
  "type": "Feature",
  "properties": {
    "iso:country":"US",
    "sg:address":"5830 409th St",
    "sg:city":"Rice",
    "sg:classifiers":[
        {
            "category":"Retail",
            "subcategory":"Auto Repair",
            "type":"Services"
        }
    ],
    "sg:phone":"+1 320 251 3902",
    "sg:postcode":"56367",
    "sg:province":"MN",
    "sg:tags":[
        "body",
        "automobile",
        "painting"
    ],
    "wof:name":"Mark's Auto Body",
    "wof:placetype":"venue"
},
  "geometry": {"coordinates":[-94.22911000000001,45.715465],"type":"Point"}
}