{
  "type": "Feature",
  "properties": {
    "addr:full":"917 Washington Ave SE Minneapolis MN 55414",
    "addr:housenumber":"917",
    "addr:postcode":"55414",
    "addr:street":"Washington Ave Se",
    "iso:country":"US",
    "sg:address":"917 Washington Ave SE",
    "sg:city":"Minneapolis",
    "sg:classifiers":[
        {
            "category":"Cinema",
            "subcategory":"Movie Rental",
            "type":"Entertainment"
        }
    ],
    "sg:phone":"+1 612 617 9633",
    "sg:postcode":"55414",
    "sg:province":"MN",
    "sg:tags":[
        "leasing",
        "video",
        "disc",
        "tape"
    ],
    "sg:website":"www.blockbuster.com",
    "wof:name":"Blockbuster Video",
    "wof:placetype":"venue"
},
  "geometry": {"coordinates":[-93.22416800000001,44.97362],"type":"Point"}
}