{
  "type": "Feature",
  "properties": {
    "addr:full":"923 10th St SW Rochester MN 55902",
    "addr:housenumber":"923",
    "addr:postcode":"55902",
    "addr:street":"10Th St Sw",
    "iso:country":"US",
    "sg:address":"923 10th St SW",
    "sg:city":"Rochester",
    "sg:classifiers":[
        {
            "category":"Professional",
            "subcategory":"Computer Services",
            "type":"Services"
        }
    ],
    "sg:phone":"+1 507 292 0566",
    "sg:postcode":"55902",
    "sg:province":"MN",
    "sg:tags":[
        "programing",
        "custom"
    ],
    "wof:name":"Walker Reading Technologies",
    "wof:placetype":"venue"
},
  "geometry": {"coordinates":[-92.476411,44.012108],"type":"Point"}
}