{
  "type": "Feature",
  "properties": {
    "iso:country":"US",
    "sg:address":"525 S Lake Ave Ste 405",
    "sg:city":"Duluth",
    "sg:classifiers":[
        {
            "category":"Travel",
            "subcategory":"Hotels & Motels",
            "type":"Entertainment"
        }
    ],
    "sg:phone":"+1 218 723 8433",
    "sg:postcode":"55802",
    "sg:province":"MN",
    "wof:name":"Rodeway Inn",
    "wof:placetype":"venue"
},
  "geometry": {"coordinates":[-92.09381,46.780329],"type":"Point"}
}