{
  "type": "Feature",
  "properties": {
    "addr:full":"5130 Camden Ave N Minneapolis MN 55430",
    "addr:housenumber":"5130",
    "addr:postcode":"55430",
    "addr:street":"Camden Ave N",
    "iso:country":"US",
    "sg:address":"5130 Camden Ave N",
    "sg:city":"Minneapolis",
    "sg:classifiers":[
        {
            "category":"Wholesale",
            "subcategory":"Photographic Equipment",
            "type":"Manufacturing & Wholesale Goods"
        }
    ],
    "sg:phone":"+1 612 522 5961",
    "sg:postcode":"55430",
    "sg:province":"MN",
    "sg:tags":[
        "equipment-repair"
    ],
    "sg:website":"http://www.flashrepair.com",
    "wof:name":"3w Electronics Of Minneapolis",
    "wof:placetype":"venue"
},
  "geometry": {"coordinates":[-93.288937,45.048063],"type":"Point"}
}