{
  "type": "Feature",
  "properties": {
    "addr:full":"4040 Salem Ave S Minneapolis MN 55416",
    "addr:housenumber":"4040",
    "addr:postcode":"55416",
    "addr:street":"Salem Ave S",
    "iso:country":"US",
    "sg:address":"4040 Salem Ave S",
    "sg:city":"Minneapolis",
    "sg:classifiers":[
        {
            "category":"Retail",
            "subcategory":"Repair Shop",
            "type":"Services"
        }
    ],
    "sg:phone":"+1 952 929 3487",
    "sg:postcode":"55416",
    "sg:province":"MN",
    "wof:name":"Marine Repair Service",
    "wof:placetype":"venue"
},
  "geometry": {"coordinates":[-93.344675,44.928332],"type":"Point"}
}