{
  "type": "Feature",
  "properties": {
    "iso:country":"US",
    "sg:address":"3173 Co Rd 20",
    "sg:city":"International Falls",
    "sg:classifiers":[
        {
            "category":"Home & Garden",
            "subcategory":"Garden Supply",
            "type":"Retail Goods"
        }
    ],
    "sg:phone":"+1 218 286 3551",
    "sg:postcode":"56649",
    "sg:province":"MN",
    "wof:name":"Sjoblom Landscape & Nursery",
    "wof:placetype":"venue"
},
  "geometry": {"coordinates":[-93.31338,48.612539],"type":"Point"}
}