{
  "type": "Feature",
  "properties": {
    "iso:country":"US",
    "sg:address":"2780 Snelling Ave N",
    "sg:city":"Roseville",
    "sg:classifiers":[
        {
            "category":"Health Services",
            "subcategory":"Chiropractor",
            "type":"Services"
        }
    ],
    "sg:phone":"+1 651 633 9667",
    "sg:postcode":"55113",
    "sg:province":"MN",
    "wof:name":"Nadig Chiropractic Clinic",
    "wof:placetype":"venue"
},
  "geometry": {"coordinates":[-93.166999,45.021509],"type":"Point"}
}