{
  "type": "Feature",
  "properties": {
    "addr:full":"43029 Engstrom Beach Rd Dent MN 56528",
    "addr:postcode":"43029;56528",
    "addr:street":"Engstrom Beach Rd",
    "iso:country":"US",
    "sg:address":"43029 Engstrom Beach Rd",
    "sg:city":"Dent",
    "sg:classifiers":[
        {
            "category":"Professional",
            "type":"Services"
        }
    ],
    "sg:phone":"+1 218 758 2259",
    "sg:postcode":"56528",
    "sg:province":"MN",
    "sg:tags":[
        "establishment"
    ],
    "wof:name":"Heuer Family",
    "wof:placetype":"venue"
},
  "geometry": {"coordinates":[-95.776298,46.583696],"type":"Point"}
}