{
  "type": "Feature",
  "properties": {
    "addr:full":"410 7th St SE Hinckley MN 55037",
    "addr:housenumber":"410",
    "addr:postcode":"55037",
    "addr:street":"7Th St Se",
    "iso:country":"US",
    "sg:address":"410 7th St SE",
    "sg:city":"Hinckley",
    "sg:classifiers":[
        {
            "category":"Real Estate",
            "subcategory":"Real Estate Operator",
            "type":"Services"
        }
    ],
    "sg:phone":"+1 320 384 6140",
    "sg:postcode":"55037",
    "sg:province":"MN",
    "sg:tags":[
        "apartment"
    ],
    "wof:name":"Willow Wind Apartments",
    "wof:placetype":"venue"
},
  "geometry": {"coordinates":[-92.938158,46.008545],"type":"Point"}
}