{
  "type": "Feature",
  "properties": {
    "addr:full":"302 Scott St Jeffers MN 56145",
    "addr:housenumber":"302",
    "addr:postcode":"56145",
    "addr:street":"Scott St",
    "iso:country":"US",
    "sg:address":"302 Scott St",
    "sg:city":"Jeffers",
    "sg:classifiers":[
        {
            "category":"Shopping",
            "subcategory":"Hobbies, Toys, & Games",
            "type":"Retail Goods"
        }
    ],
    "sg:phone":"+1 507 628 4288",
    "sg:postcode":"56145",
    "sg:province":"MN",
    "sg:tags":[
        "equipment",
        "ceramic",
        "supply"
    ],
    "wof:name":"M & L Ceramics",
    "wof:placetype":"venue"
},
  "geometry": {"coordinates":[-95.200078,44.057155],"type":"Point"}
}