{
  "type": "Feature",
  "properties": {
    "addr:full":"122 180th Ave Fairmont MN 56031",
    "addr:housenumber":"122",
    "addr:postcode":"56031",
    "addr:street":"180Th Ave",
    "iso:country":"US",
    "sg:address":"122 180th Ave",
    "sg:city":"Fairmont",
    "sg:classifiers":[
        {
            "category":"Professional",
            "subcategory":"Management & Consulting",
            "type":"Services"
        }
    ],
    "sg:phone":"+1 507 632 4686",
    "sg:postcode":"56031",
    "sg:province":"MN",
    "sg:tags":[
        "farm"
    ],
    "wof:name":"Curt Bremer",
    "wof:placetype":"venue"
},
  "geometry": {"coordinates":[-94.512334,43.503732],"type":"Point"}
}