{
  "type": "Feature",
  "properties": {
    "iso:country":"US",
    "sg:address":"23600 Delmar Ave",
    "sg:city":"Jordan",
    "sg:classifiers":[
        {
            "category":"Farming",
            "subcategory":"Dairy Farm",
            "type":"Manufacturing & Wholesale Goods"
        }
    ],
    "sg:phone":"+1 952 492 6925",
    "sg:postcode":"55352",
    "sg:province":"MN",
    "wof:name":"Mark Krautkremer",
    "wof:placetype":"venue"
},
  "geometry": {"coordinates":[-93.623555,44.612264],"type":"Point"}
}