{
  "type": "Feature",
  "properties": {
    "iso:country":"US",
    "sg:address":"11460 Martin St NW",
    "sg:city":"Minneapolis",
    "sg:classifiers":[
        {
            "category":"Personal",
            "subcategory":"Barber",
            "type":"Services"
        }
    ],
    "sg:phone":"+1 763 755 5095",
    "sg:postcode":"55433",
    "sg:province":"MN",
    "sg:tags":[
        "shop"
    ],
    "wof:name":"Village 10 Barber Stylists",
    "wof:placetype":"venue"
},
  "geometry": {"coordinates":[-93.31549800000001,45.178799],"type":"Point"}
}