{
  "type": "Feature",
  "properties": {
    "iso:country":"US",
    "sg:address":"54097 Grant St",
    "sg:city":"Osage",
    "sg:classifiers":[
        {
            "category":"Travel",
            "subcategory":"Hotels & Motels",
            "type":"Entertainment"
        }
    ],
    "sg:phone":"+1 218 573 3182",
    "sg:postcode":"56570",
    "sg:province":"MN",
    "sg:tags":[
        "resort"
    ],
    "wof:name":"R & D Resort & Campground",
    "wof:placetype":"venue"
},
  "geometry": {"coordinates":[-95.26707,46.94941],"type":"Point"}
}