{
  "type": "Feature",
  "properties": {
    "iso:country":"US",
    "sg:address":"1536 Woodlane Dr",
    "sg:city":"Saint Paul",
    "sg:classifiers":[
        {
            "category":"Shopping",
            "subcategory":"Florist",
            "type":"Retail Goods"
        }
    ],
    "sg:phone":"+1 651 738 1029",
    "sg:postcode":"55125",
    "sg:province":"MN",
    "wof:name":"Woodlane Flowers Inc",
    "wof:placetype":"venue"
},
  "geometry": {"coordinates":[-92.965875,44.92635],"type":"Point"}
}