{
  "type": "Feature",
  "properties": {
    "addr:full":"13850 1st St Becker MN 55308",
    "addr:housenumber":"13850",
    "addr:postcode":"55308",
    "addr:street":"1St St",
    "iso:country":"US",
    "sg:address":"13850 1st St",
    "sg:city":"Becker",
    "sg:classifiers":[
        {
            "category":"Restaurant",
            "type":"Food & Drink"
        }
    ],
    "sg:menulink":"http://www.allmenus.com/mn/becker/84093-dominos-pizza/menu/",
    "sg:phone":"+1 763 262 0300",
    "sg:postcode":"55308",
    "sg:province":"MN",
    "sg:tags":[
        "american",
        "wing",
        "pizza"
    ],
    "wof:name":"Domino's Pizza",
    "wof:placetype":"venue"
},
  "geometry": {"coordinates":[-93.873864,45.391182],"type":"Point"}
}