{
  "type": "Feature",
  "properties": {
    "addr:full":"2018 E Kenwood Dr Saint Paul MN 55117",
    "addr:housenumber":"2018",
    "addr:postcode":"55117",
    "addr:street":"E Kenwood Dr",
    "iso:country":"US",
    "sg:address":"2018 E Kenwood Dr",
    "sg:city":"Saint Paul",
    "sg:classifiers":[
        {
            "category":"Arts & Performance",
            "subcategory":"Theater",
            "type":"Entertainment"
        }
    ],
    "sg:phone":"+1 651 774 0200",
    "sg:postcode":"55117",
    "sg:province":"MN",
    "sg:tags":[
        "group"
    ],
    "wof:name":"Susan M Vass",
    "wof:placetype":"venue"
},
  "geometry": {"coordinates":[-93.06820500000001,45.002748],"type":"Point"}
}