{
  "type": "Feature",
  "properties": {
    "iso:country":"US",
    "sg:address":"8417 Onigum Rd NW",
    "sg:city":"Walker",
    "sg:classifiers":[
        {
            "category":"Professional",
            "type":"Services"
        }
    ],
    "sg:phone":"+1 218 547 4034",
    "sg:postcode":"56484",
    "sg:province":"MN",
    "sg:tags":[
        "establishment"
    ],
    "wof:name":"Wilhelm & Wilhelm",
    "wof:placetype":"venue"
},
  "geometry": {"coordinates":[-94.51958999999999,47.12347],"type":"Point"}
}