{
  "type": "Feature",
  "properties": {
    "iso:country":"US",
    "sg:address":"6860 Shingle Creek Pkwy",
    "sg:city":"Brooklyn Center",
    "sg:classifiers":[
        {
            "category":"Education",
            "subcategory":"Special Training",
            "type":"Public Place"
        }
    ],
    "sg:phone":"+1 763 566 1104",
    "sg:postcode":"55430",
    "sg:province":"MN",
    "sg:tags":[
        "center"
    ],
    "wof:name":"Serendipity Education Programs",
    "wof:placetype":"venue"
},
  "geometry": {"coordinates":[-93.31124800000001,45.077938],"type":"Point"}
}