{
  "type": "Feature",
  "properties": {
    "iso:country":"US",
    "sg:address":"17025 Commercial Park Dr NW",
    "sg:city":"Brainerd",
    "sg:classifiers":[
        {
            "category":"Professional",
            "subcategory":"Business Services",
            "type":"Services"
        }
    ],
    "sg:phone":"+1 218 829 1141",
    "sg:postcode":"56401",
    "sg:province":"MN",
    "sg:tags":[
        "drafting"
    ],
    "wof:name":"PFS Design",
    "wof:placetype":"venue"
},
  "geometry": {"coordinates":[-94.28351000000001,46.398509],"type":"Point"}
}