{
  "type": "Feature",
  "properties": {
    "iso:country":"US",
    "sg:address":"1306 Lori Ave",
    "sg:city":"Detroit Lakes",
    "sg:classifiers":[
        {
            "category":"Manufacturing",
            "subcategory":"Apparel",
            "type":"Manufacturing & Wholesale Goods"
        }
    ],
    "sg:phone":"+1 218 844 8374",
    "sg:postcode":"56501",
    "sg:province":"MN",
    "sg:tags":[
        "outerwear",
        "mfg"
    ],
    "wof:name":"Et Voila",
    "wof:placetype":"venue"
},
  "geometry": {"coordinates":[-95.826459,46.809005],"type":"Point"}
}