{
  "type": "Feature",
  "properties": {
    "addr:full":"105 E Ross Ave Erskine MN 56535",
    "addr:housenumber":"105",
    "addr:postcode":"56535",
    "addr:street":"E Ross Ave",
    "iso:country":"US",
    "sg:address":"105 E Ross Ave",
    "sg:city":"Erskine",
    "sg:classifiers":[
        {
            "category":"Government",
            "subcategory":"Office",
            "type":"Public Place"
        }
    ],
    "sg:phone":"+1 218 687 4646",
    "sg:postcode":"56535",
    "sg:province":"MN",
    "sg:tags":[
        "city"
    ],
    "wof:name":"Erskine City Clerk",
    "wof:placetype":"venue"
},
  "geometry": {"coordinates":[-96.00854200000001,47.667787],"type":"Point"}
}