{
  "type": "Feature",
  "properties": {
    "iso:country":"US",
    "sg:address":"3502 Riverview Cir",
    "sg:city":"Moorhead",
    "sg:classifiers":[
        {
            "category":"Building & Trades",
            "subcategory":"Construction",
            "type":"Services"
        }
    ],
    "sg:phone":"+1 218 236 7528",
    "sg:postcode":"56560",
    "sg:province":"MN",
    "sg:tags":[
        "house",
        "residential"
    ],
    "wof:name":"Dale Buchholz Construction",
    "wof:placetype":"venue"
},
  "geometry": {"coordinates":[-96.78305899999999,46.839034],"type":"Point"}
}