{
  "type": "Feature",
  "properties": {
    "addr:full":"3170 123rd Ave NW Minneapolis MN 55433",
    "addr:housenumber":"3170",
    "addr:postcode":"55433",
    "addr:street":"123Rd Ave Nw",
    "iso:country":"US",
    "sg:address":"3170 123rd Ave NW",
    "sg:city":"Minneapolis",
    "sg:classifiers":[
        {
            "category":"Wholesale",
            "subcategory":"Stationery",
            "type":"Manufacturing & Wholesale Goods"
        }
    ],
    "sg:phone":"+1 763 427 6371",
    "sg:postcode":"55433",
    "sg:province":"MN",
    "sg:tags":[
        "supply"
    ],
    "wof:name":"Fancy Pages Scrappin",
    "wof:placetype":"venue"
},
  "geometry": {"coordinates":[-93.344042,45.193733],"type":"Point"}
}