{
  "type": "Feature",
  "properties": {
    "iso:country":"US",
    "sg:address":"732 6th St",
    "sg:city":"Westbrook",
    "sg:classifiers":[
        {
            "category":"Personal",
            "type":"Services"
        }
    ],
    "sg:phone":"+1 507 274 5441",
    "sg:postcode":"56183",
    "sg:province":"MN",
    "sg:tags":[
        "therapist",
        "massage"
    ],
    "wof:name":"Martha Jensen CMT Thrptc",
    "wof:placetype":"venue"
},
  "geometry": {"coordinates":[-95.434844,44.042147],"type":"Point"}
}