{
  "type": "Feature",
  "properties": {
    "addr:full":"2555 West. 78th St. Chanhassen MN 55317",
    "addr:housenumber":"2555",
    "addr:postcode":"55317",
    "addr:street":"West. 78Th St.",
    "iso:country":"US",
    "sg:address":"2555 West. 78th St.",
    "sg:city":"Chanhassen",
    "sg:classifiers":[
        {
            "category":"Real Estate",
            "subcategory":"Real Estate Services",
            "type":"Services"
        },
        {
            "category":"Real Estate",
            "subcategory":"Developer",
            "type":"Services"
        },
        {
            "category":"Real Estate",
            "subcategory":"Real Estate Agent",
            "type":"Services"
        }
    ],
    "sg:phone":"+1 952 237 1958",
    "sg:postcode":"55317",
    "sg:province":"MN",
    "sg:tags":[
        "information",
        "investing",
        "consultant",
        "broker",
        "buyer",
        "referral"
    ],
    "sg:website":"http://marysmith.edinarealty.com",
    "wof:name":"Mary Smith _Agent_ Edina Realty",
    "wof:placetype":"venue"
},
  "geometry": {"coordinates":[-93.58673899999999,44.863889],"type":"Point"}
}