{
  "type": "Feature",
  "properties": {
    "iso:country":"US",
    "sg:address":"508 Water St SW",
    "sg:city":"Sleepy Eye",
    "sg:classifiers":[
        {
            "category":"Shopping",
            "type":"Retail Goods"
        }
    ],
    "sg:phone":"+1 507 380 1765",
    "sg:postcode":"56085",
    "sg:province":"MN",
    "sg:tags":[
        "tropical",
        "fish"
    ],
    "wof:name":"Bettas Direct",
    "wof:placetype":"venue"
},
  "geometry": {"coordinates":[-94.73013,44.29418],"type":"Point"}
}