{
  "type": "Feature",
  "properties": {
    "addr:full":"13561 36th St NW Annandale MN 55302",
    "addr:housenumber":"13561",
    "addr:postcode":"55302",
    "addr:street":"36Th St Nw",
    "iso:country":"US",
    "sg:address":"13561 36th St NW",
    "sg:city":"Annandale",
    "sg:classifiers":[
        {
            "category":"Banks & Credit Unions",
            "subcategory":"Financial Services",
            "type":"Services"
        }
    ],
    "sg:phone":"+1 320 274 2566",
    "sg:postcode":"55302",
    "sg:province":"MN",
    "sg:tags":[
        "investor"
    ],
    "wof:name":"Even Keel Investment Group",
    "wof:placetype":"venue"
},
  "geometry": {"coordinates":[-94.16814100000001,45.204204],"type":"Point"}
}