{
  "type": "Feature",
  "properties": {
    "addr:full":"1421 Swanhill Dr Albert Lea MN 56007",
    "addr:housenumber":"1421",
    "addr:postcode":"56007",
    "addr:street":"Swanhill Dr",
    "iso:country":"US",
    "sg:address":"1421 Swanhill Dr",
    "sg:city":"Albert Lea",
    "sg:classifiers":[
        {
            "category":"Building & Trades",
            "subcategory":"Landscaping Services",
            "type":"Services"
        }
    ],
    "sg:phone":"+1 507 377 1378",
    "sg:postcode":"56007",
    "sg:province":"MN",
    "wof:name":"Nancys Lawn Service",
    "wof:placetype":"venue"
},
  "geometry": {"coordinates":[-93.38916999999999,43.633342],"type":"Point"}
}