{
  "type": "Feature",
  "properties": {
    "addr:full":"11240 86th Ave N Osseo MN 55369",
    "addr:housenumber":"11240",
    "addr:postcode":"55369",
    "addr:street":"86Th Ave N",
    "iso:country":"US",
    "sg:address":"11240 86th Ave N",
    "sg:city":"Osseo",
    "sg:classifiers":[
        {
            "category":"Insurance",
            "subcategory":"Insurance Agent",
            "type":"Services"
        }
    ],
    "sg:phone":"+1 763 494 8553",
    "sg:postcode":"55369",
    "sg:province":"MN",
    "wof:name":"David S Parvey Agency",
    "wof:placetype":"venue"
},
  "geometry": {"coordinates":[-93.43443600000001,45.111814],"type":"Point"}
}