{
  "type": "Feature",
  "properties": {
    "iso:country":"US",
    "sg:address":"613 Michigan Ave",
    "sg:city":"Walker",
    "sg:classifiers":[
        {
            "category":"Shopping",
            "subcategory":"Gifts & Souvenirs",
            "type":"Retail Goods"
        }
    ],
    "sg:phone":"+1 218 547 1122",
    "sg:postcode":"56484",
    "sg:province":"MN",
    "sg:tags":[
        "shop"
    ],
    "wof:name":"Home Town Charm",
    "wof:placetype":"venue"
},
  "geometry": {"coordinates":[-94.585077,47.100697],"type":"Point"}
}