{
  "type": "Feature",
  "properties": {
    "addr:full":"105 4th Ave SE Milaca MN 56353",
    "addr:housenumber":"105",
    "addr:postcode":"56353",
    "addr:street":"4Th Ave Se",
    "iso:country":"US",
    "sg:address":"105 4th Ave SE",
    "sg:city":"Milaca",
    "sg:classifiers":[
        {
            "category":"Building & Trades",
            "subcategory":"Construction",
            "type":"Services"
        }
    ],
    "sg:phone":"+1 320 983 3551",
    "sg:postcode":"56353",
    "sg:province":"MN",
    "sg:tags":[
        "general",
        "contractor"
    ],
    "wof:name":"Lunn Construction Co",
    "wof:placetype":"venue"
},
  "geometry": {"coordinates":[-93.64709999999999,45.755577],"type":"Point"}
}