{
  "type": "Feature",
  "properties": {
    "addr:full":"8030 133rd St W Saint Paul MN 55124",
    "addr:housenumber":"8030",
    "addr:postcode":"55124",
    "addr:street":"133Rd St W",
    "iso:country":"US",
    "sg:address":"8030 133rd St W",
    "sg:city":"Saint Paul",
    "sg:classifiers":[
        {
            "category":"Professional",
            "subcategory":"Management & Consulting",
            "type":"Services"
        }
    ],
    "sg:phone":"+1 612 386 8570",
    "sg:postcode":"55124",
    "sg:province":"MN",
    "wof:name":"Rainmakers Group",
    "wof:placetype":"venue"
},
  "geometry": {"coordinates":[-93.228067,44.755969],"type":"Point"}
}