{
  "type": "Feature",
  "properties": {
    "iso:country":"US",
    "sg:address":"5809 Rhode Island Ave N",
    "sg:city":"Minneapolis",
    "sg:classifiers":[
        {
            "category":"Retail",
            "subcategory":"Animal Services",
            "type":"Services"
        }
    ],
    "sg:phone":"+1 763 535 9668",
    "sg:postcode":"55428",
    "sg:province":"MN",
    "sg:tags":[
        "pet",
        "exercising",
        "sitting"
    ],
    "wof:name":"Animal & Plant Helpers",
    "wof:placetype":"venue"
},
  "geometry": {"coordinates":[-93.37951200000001,45.059146],"type":"Point"}
}