{
  "type": "Feature",
  "properties": {
    "addr:full":"285 Brown Rd N Long Lake MN 55356",
    "addr:housenumber":"285",
    "addr:postcode":"55356",
    "addr:street":"Brown Rd N",
    "iso:country":"US",
    "sg:address":"285 Brown Rd N",
    "sg:city":"Long Lake",
    "sg:classifiers":[
        {
            "category":"Shopping",
            "subcategory":"Used Merchandise",
            "type":"Retail Goods"
        }
    ],
    "sg:phone":"+1 952 470 6151",
    "sg:postcode":"55356",
    "sg:province":"MN",
    "wof:name":"Back To The Future Furnitures",
    "wof:placetype":"venue"
},
  "geometry": {"coordinates":[-93.57387300000001,44.983403],"type":"Point"}
}