{
  "type": "Feature",
  "properties": {
    "addr:full":"6445 Lake Road Ter Saint Paul MN 55125",
    "addr:housenumber":"6445",
    "addr:postcode":"55125",
    "addr:street":"Lake Road Ter",
    "iso:country":"US",
    "sg:address":"6445 Lake Road Ter",
    "sg:city":"Saint Paul",
    "sg:classifiers":[
        {
            "category":"Restaurant",
            "type":"Food & Drink"
        }
    ],
    "sg:menulink":"http://www.allmenus.com/mn/woodbury/101256-cousins-subs/menu/",
    "sg:phone":"+1 651 702 0477",
    "sg:postcode":"55125",
    "sg:province":"MN",
    "sg:tags":[
        "wrap",
        "american",
        "sandwich"
    ],
    "wof:name":"Cousin's Subs",
    "wof:placetype":"venue"
},
  "geometry": {"coordinates":[-92.978075,44.913538],"type":"Point"}
}