{
  "type": "Feature",
  "properties": {
    "iso:country":"US",
    "sg:address":"20664 150th St",
    "sg:city":"Glenwood",
    "sg:phone":"+1 320 634 3262",
    "sg:postcode":"56334",
    "sg:province":"MN",
    "sg:tags":[
        "farm",
        "corn"
    ],
    "wof:name":"K & D Farms",
    "wof:placetype":"venue"
},
  "geometry": {"coordinates":[-95.35514499999999,45.686362],"type":"Point"}
}