{
  "type": "Feature",
  "properties": {
    "addr:full":"14900 Ymca Ln Lake Park MN 56554",
    "addr:housenumber":"14900",
    "addr:postcode":"56554",
    "addr:street":"Ymca Ln",
    "iso:country":"US",
    "sg:address":"14900 Ymca Ln",
    "sg:city":"Lake Park",
    "sg:classifiers":[
        {
            "category":"Professional",
            "type":"Services"
        }
    ],
    "sg:phone":"+1 218 532 3545",
    "sg:postcode":"56554",
    "sg:province":"MN",
    "wof:name":"Freeman V Wuollet",
    "wof:placetype":"venue"
},
  "geometry": {"coordinates":[-96.068082,46.790773],"type":"Point"}
}