{
  "type": "Feature",
  "properties": {
    "addr:full":"990 Elm St E Annandale MN 55302",
    "addr:housenumber":"990",
    "addr:postcode":"55302",
    "addr:street":"Elm St E",
    "iso:country":"US",
    "sg:address":"990 Elm St E",
    "sg:city":"Annandale",
    "sg:classifiers":[
        {
            "category":"Building & Trades",
            "subcategory":"Construction",
            "type":"Services"
        }
    ],
    "sg:phone":"+1 320 274 3411",
    "sg:postcode":"55302",
    "sg:province":"MN",
    "sg:tags":[
        "residential"
    ],
    "wof:name":"Boltz Builders",
    "wof:placetype":"venue"
},
  "geometry": {"coordinates":[-94.10709,45.255089],"type":"Point"}
}