{
  "type": "Feature",
  "properties": {
    "addr:full":"769 111th St Lake Wilson MN 56151",
    "addr:housenumber":"769",
    "addr:postcode":"56151",
    "addr:street":"111Th St",
    "iso:country":"US",
    "sg:address":"769 111th St",
    "sg:city":"Lake Wilson",
    "sg:phone":"+1 507 879 3233",
    "sg:postcode":"56151",
    "sg:province":"MN",
    "sg:tags":[
        "farm",
        "soybean"
    ],
    "wof:name":"Steven Beek",
    "wof:placetype":"venue"
},
  "geometry": {"coordinates":[-95.90958999999999,44.00786],"type":"Point"}
}