{
  "type": "Feature",
  "properties": {
    "addr:full":"303 West Ave Zumbrota MN 55992",
    "addr:housenumber":"303",
    "addr:postcode":"55992",
    "addr:street":"West Ave",
    "iso:country":"US",
    "sg:address":"303 West Ave",
    "sg:city":"Zumbrota",
    "sg:classifiers":[
        {
            "category":"Building & Trades",
            "subcategory":"Construction",
            "type":"Services"
        }
    ],
    "sg:phone":"+1 507 732 5312",
    "sg:postcode":"55992",
    "sg:province":"MN",
    "sg:tags":[
        "system",
        "contractor",
        "air conditioning"
    ],
    "wof:name":"Plum'r, The",
    "wof:placetype":"venue"
},
  "geometry": {"coordinates":[-92.670418,44.294103],"type":"Point"}
}