{
  "type": "Feature",
  "properties": {
    "addr:full":"55056 State Highway 34 Osage MN 56570",
    "addr:housenumber":"55056",
    "addr:postcode":"56570",
    "addr:street":"State Highway 34",
    "iso:country":"US",
    "sg:address":"55056 State Highway 34",
    "sg:city":"Osage",
    "sg:classifiers":[
        {
            "category":"Manufacturing",
            "subcategory":"Tools & Machinery",
            "type":"Manufacturing & Wholesale Goods"
        }
    ],
    "sg:phone":"+1 218 573 3405",
    "sg:postcode":"56570",
    "sg:province":"MN",
    "sg:tags":[
        "hand"
    ],
    "wof:name":"Jeanie Jac Inc",
    "wof:placetype":"venue"
},
  "geometry": {"coordinates":[-95.247393,46.920476],"type":"Point"}
}