{
  "type": "Feature",
  "properties": {
    "iso:country":"US",
    "sg:address":"704 Cleveland Ave S",
    "sg:city":"Saint Paul",
    "sg:classifiers":[
        {
            "category":"Restaurant",
            "type":"Food & Drink"
        }
    ],
    "sg:menulink":"http://www.allmenus.com/mn/st-paul/121011-neapolitan-punch-pizza/menu/",
    "sg:phone":"+1 651 696 1066",
    "sg:postcode":"55116",
    "sg:province":"MN",
    "sg:tags":[
        "american",
        "pizza"
    ],
    "wof:name":"Neapolitan Punch Pizza",
    "wof:placetype":"venue"
},
  "geometry": {"coordinates":[-93.187403,44.920306],"type":"Point"}
}