{
  "type": "Feature",
  "properties": {
    "addr:full":"7801 67th Ave N Minneapolis MN 55428",
    "addr:housenumber":"7801",
    "addr:postcode":"55428",
    "addr:street":"67Th Ave N",
    "iso:country":"US",
    "sg:address":"7801 67th Ave N",
    "sg:city":"Minneapolis",
    "sg:classifiers":[
        {
            "category":"Professional",
            "type":"Services"
        }
    ],
    "sg:phone":"+1 763 535 2209",
    "sg:postcode":"55428",
    "sg:province":"MN",
    "wof:name":"An Affair To Remember",
    "wof:placetype":"venue"
},
  "geometry": {"coordinates":[-93.378773,45.076758],"type":"Point"}
}