{
  "type": "Feature",
  "properties": {
    "iso:country":"US",
    "sg:address":"216 N Cedar Ave",
    "sg:city":"Owatonna",
    "sg:classifiers":[
        {
            "category":"Home & Garden",
            "subcategory":"Building Materials",
            "type":"Retail Goods"
        }
    ],
    "sg:phone":"+1 507 455 4089",
    "sg:postcode":"55060",
    "sg:province":"MN",
    "sg:tags":[
        "paint"
    ],
    "wof:name":"Borgman Paint Co",
    "wof:placetype":"venue"
},
  "geometry": {"coordinates":[-93.226061,44.08658],"type":"Point"}
}