{
  "type": "Feature",
  "properties": {
    "addr:full":"11230 276th Ave Zimmerman MN 55398",
    "addr:housenumber":"11230",
    "addr:postcode":"55398",
    "addr:street":"276Th Ave",
    "iso:country":"US",
    "sg:address":"11230 276th Ave",
    "sg:city":"Zimmerman",
    "sg:classifiers":[
        {
            "category":"Building & Trades",
            "subcategory":"Construction",
            "type":"Services"
        }
    ],
    "sg:phone":"+1 763 389 4688",
    "sg:postcode":"55398",
    "sg:province":"MN",
    "sg:tags":[
        "project"
    ],
    "wof:name":"Boardwalk Construction",
    "wof:placetype":"venue"
},
  "geometry": {"coordinates":[-93.552909,45.470427],"type":"Point"}
}