{
  "type": "Feature",
  "properties": {
    "addr:full":"31193 183rd St Pierz MN 56364",
    "addr:housenumber":"31193",
    "addr:postcode":"56364",
    "addr:street":"183Rd St",
    "iso:country":"US",
    "sg:address":"31193 183rd St",
    "sg:city":"Pierz",
    "sg:phone":"+1 320 468 6571",
    "sg:postcode":"56364",
    "sg:province":"MN",
    "sg:tags":[
        "farm",
        "field",
        "corn",
        "crop"
    ],
    "wof:name":"Gary Diederich",
    "wof:placetype":"venue"
},
  "geometry": {"coordinates":[-94.01053400000001,46.026561],"type":"Point"}
}