{
  "type": "Feature",
  "properties": {
    "addr:full":"108 Coffee St E Lanesboro MN 55949",
    "addr:housenumber":"108",
    "addr:postcode":"55949",
    "addr:street":"Coffee St E Lanesboro",
    "iso:country":"US",
    "sg:address":"108 Coffee St E",
    "sg:city":"Lanesboro",
    "sg:classifiers":[
        {
            "category":"Food & Beverages",
            "subcategory":"Bakery",
            "type":"Retail Goods"
        }
    ],
    "sg:phone":"+1 507 467 2323",
    "sg:postcode":"55949",
    "sg:province":"MN",
    "sg:tags":[
        "baker"
    ],
    "wof:name":"Village Foods",
    "wof:placetype":"venue"
},
  "geometry": {"coordinates":[-91.976949,43.722065],"type":"Point"}
}