{
  "type": "Feature",
  "properties": {
    "addr:full":"2655 Irving Ave S Minneapolis MN 55408",
    "addr:housenumber":"2655",
    "addr:postcode":"55408",
    "addr:street":"Irving Ave S",
    "iso:country":"US",
    "sg:address":"2655 Irving Ave S",
    "sg:city":"Minneapolis",
    "sg:classifiers":[
        {
            "category":"Real Estate",
            "subcategory":"Real Estate Agent",
            "type":"Services"
        }
    ],
    "sg:phone":"+1 612 377 6336",
    "sg:postcode":"55408",
    "sg:province":"MN",
    "wof:name":"Home Sweet Home Management Inc",
    "wof:placetype":"venue"
},
  "geometry": {"coordinates":[-93.300158,44.955146],"type":"Point"}
}