{
  "type": "Feature",
  "properties": {
    "iso:country":"US",
    "sg:address":"8106 Alpine Dr NW",
    "sg:city":"Anoka",
    "sg:classifiers":[
        {
            "category":"Manufacturing",
            "subcategory":"Tools & Machinery",
            "type":"Manufacturing & Wholesale Goods"
        },
        {
            "category":"Industrial Area",
            "type":"Public Place"
        }
    ],
    "sg:phone":"+1 763 427 9681",
    "sg:postcode":"55303",
    "sg:province":"MN",
    "sg:tags":[
        "repair",
        "equipment-repairing",
        "machinery-rebuild"
    ],
    "wof:name":"Vasseur's Engineering",
    "wof:placetype":"venue"
},
  "geometry": {"coordinates":[-93.471369,45.248533],"type":"Point"}
}