{
  "type": "Feature",
  "properties": {
    "addr:full":"20037 Jefferson St NE Cedar MN 55011",
    "addr:housenumber":"20037",
    "addr:postcode":"55011",
    "addr:street":"Jefferson St Ne Cedar",
    "iso:country":"US",
    "sg:address":"20037 Jefferson St NE",
    "sg:city":"Cedar",
    "sg:classifiers":[
        {
            "category":"Building & Trades",
            "subcategory":"Plumbing",
            "type":"Services"
        }
    ],
    "sg:phone":"+1 763 434 1323",
    "sg:postcode":"55011",
    "sg:province":"MN",
    "sg:tags":[
        "mechanical",
        "contractor"
    ],
    "wof:name":"Moon Beam Mechanical Inc",
    "wof:placetype":"venue"
},
  "geometry": {"coordinates":[-93.25739400000001,45.331819],"type":"Point"}
}