{
  "type": "Feature",
  "properties": {
    "iso:country":"US",
    "sg:address":"24 Division St E",
    "sg:city":"Buffalo",
    "sg:classifiers":[
        {
            "category":"Professional",
            "subcategory":"Accounting & Tax Preparation",
            "type":"Services"
        }
    ],
    "sg:phone":"+1 763 682 3355",
    "sg:postcode":"55313",
    "sg:province":"MN",
    "wof:name":"Tenney Corporation",
    "wof:placetype":"venue"
},
  "geometry": {"coordinates":[-93.875906,45.171973],"type":"Point"}
}