{
  "type": "Feature",
  "properties": {
    "iso:country":"US",
    "sg:address":"4741 Humboldt Ave S",
    "sg:city":"Minneapolis",
    "sg:classifiers":[
        {
            "category":"Professional",
            "subcategory":"Management & Consulting",
            "type":"Services"
        }
    ],
    "sg:phone":"+1 612 823 6068",
    "sg:postcode":"55419",
    "sg:province":"MN",
    "sg:tags":[
        "consultant",
        "educational"
    ],
    "wof:name":"Zvosec Consulting",
    "wof:placetype":"venue"
},
  "geometry": {"coordinates":[-93.298456,44.917332],"type":"Point"}
}