{
  "type": "Feature",
  "properties": {
    "addr:full":"32 10th Ave S Hopkins MN 55343",
    "addr:housenumber":"32",
    "addr:postcode":"55343",
    "addr:street":"10Th Ave S",
    "iso:country":"US",
    "sg:address":"32 10th Ave S",
    "sg:city":"Hopkins",
    "sg:classifiers":[
        {
            "category":"Professional",
            "subcategory":"Advertising",
            "type":"Services"
        }
    ],
    "sg:phone":"+1 952 933 0015",
    "sg:postcode":"55343",
    "sg:province":"MN",
    "sg:tags":[
        "agency"
    ],
    "wof:name":"American Media Services",
    "wof:placetype":"venue"
},
  "geometry": {"coordinates":[-93.412876,44.923009],"type":"Point"}
}