{
  "type": "Feature",
  "properties": {
    "iso:country":"US",
    "sg:address":"25202 Camp Ave",
    "sg:city":"Milroy",
    "sg:classifiers":[
        {
            "category":"Building & Trades",
            "subcategory":"Construction",
            "type":"Services"
        }
    ],
    "sg:phone":"+1 507 336 2493",
    "sg:postcode":"56263",
    "sg:province":"MN",
    "sg:tags":[
        "heavy"
    ],
    "wof:name":"Schlemmer Tiling",
    "wof:placetype":"venue"
},
  "geometry": {"coordinates":[-95.513322,44.426555],"type":"Point"}
}