{
  "type": "Feature",
  "properties": {
    "iso:country":"US",
    "sg:address":"248 N River St",
    "sg:city":"Delano",
    "sg:classifiers":[
        {
            "category":"Restaurant",
            "type":"Food & Drink"
        }
    ],
    "sg:phone":"+1 612 202 4777",
    "sg:postcode":"55328",
    "sg:province":"MN",
    "sg:tags":[
        "eating"
    ],
    "wof:name":"Little Johns English Pub Rest",
    "wof:placetype":"venue"
},
  "geometry": {"coordinates":[-93.789241,45.042567],"type":"Point"}
}