{
  "type": "Feature",
  "properties": {
    "iso:country":"US",
    "sg:address":"1230 Trapp Rd",
    "sg:city":"Eagan",
    "sg:classifiers":[
        {
            "category":"Freight",
            "type":"Transportation"
        }
    ],
    "sg:phone":"+1 651 405 4300",
    "sg:postcode":"55121",
    "sg:province":"MN",
    "sg:website":"www.airplusltd.com",
    "wof:name":"Stonepath Logistics",
    "wof:placetype":"venue"
},
  "geometry": {"coordinates":[-93.15644899999999,44.859191],"type":"Point"}
}