{
  "type": "Feature",
  "properties": {
    "addr:full":"209 S 12th St Montevideo MN 56265",
    "addr:housenumber":"209",
    "addr:postcode":"56265",
    "addr:street":"S 12Th St",
    "iso:country":"US",
    "sg:address":"209 S 12th St",
    "sg:city":"Montevideo",
    "sg:classifiers":[
        {
            "category":"Social Services",
            "subcategory":"Child Care",
            "type":"Services"
        }
    ],
    "sg:phone":"+1 320 269 8911",
    "sg:postcode":"56265",
    "sg:province":"MN",
    "sg:tags":[
        "daycare",
        "provider"
    ],
    "wof:name":"Debra Grussing",
    "wof:placetype":"venue"
},
  "geometry": {"coordinates":[-95.712157,44.944258],"type":"Point"}
}