{
  "type": "Feature",
  "properties": {
    "addr:full":"701 N Broadway St New Ulm MN 56073",
    "addr:housenumber":"701",
    "addr:postcode":"56073",
    "addr:street":"N Broadway St",
    "iso:country":"US",
    "sg:address":"701 N Broadway St",
    "sg:city":"New Ulm",
    "sg:classifiers":[
        {
            "category":"Autos & Motor Vehicles",
            "subcategory":"Fuel & Gas Station",
            "type":"Retail Goods"
        }
    ],
    "sg:phone":"+1 507 354 4814",
    "sg:postcode":"56073",
    "sg:province":"MN",
    "sg:tags":[
        "oil"
    ],
    "wof:name":"AAA Towing Svc/Amoco Bp",
    "wof:placetype":"venue"
},
  "geometry": {"coordinates":[-94.467812,44.320434],"type":"Point"}
}