{
  "type": "Feature",
  "properties": {
    "addr:full":"30980 County 7 Blvd Welch MN 55089",
    "addr:housenumber":"30980",
    "addr:postcode":"55089",
    "addr:street":"County 7 Blvd",
    "iso:country":"US",
    "sg:address":"30980 County 7 Blvd",
    "sg:city":"Welch",
    "sg:classifiers":[
        {
            "category":"Government",
            "subcategory":"Office",
            "type":"Public Place"
        }
    ],
    "sg:phone":"+1 651 258 4582",
    "sg:postcode":"55089",
    "sg:province":"MN",
    "sg:tags":[
        "village"
    ],
    "wof:name":"Vasa Township Garage",
    "wof:placetype":"venue"
},
  "geometry": {"coordinates":[-92.726901,44.497557],"type":"Point"}
}