{
  "type": "Feature",
  "properties": {
    "iso:country":"US",
    "sg:address":"1227 N Broadway St",
    "sg:city":"New Ulm",
    "sg:classifiers":[
        {
            "category":"Retail",
            "subcategory":"Auto Repair",
            "type":"Services"
        }
    ],
    "sg:phone":"+1 507 354 2712",
    "sg:postcode":"56073",
    "sg:province":"MN",
    "sg:tags":[
        "general"
    ],
    "wof:name":"Terrys Auto Service",
    "wof:placetype":"venue"
},
  "geometry": {"coordinates":[-94.472283,44.325054],"type":"Point"}
}