{
  "type": "Feature",
  "properties": {
    "iso:country":"US",
    "sg:address":"4955 Eagle Creek Blvd",
    "sg:city":"Shakopee",
    "sg:classifiers":[
        {
            "category":"Retail",
            "subcategory":"Repair Shop",
            "type":"Services"
        }
    ],
    "sg:phone":"+1 952 445 6814",
    "sg:postcode":"55379",
    "sg:province":"MN",
    "sg:tags":[
        "taxidermist"
    ],
    "wof:name":"Craig's Taxidermy",
    "wof:placetype":"venue"
},
  "geometry": {"coordinates":[-93.4798,44.782679],"type":"Point"}
}