{
  "type": "Feature",
  "properties": {
    "addr:full":"31 W College St Duluth MN 55811",
    "addr:housenumber":"31",
    "addr:postcode":"55811",
    "addr:street":"W College St",
    "iso:country":"US",
    "sg:address":"31 W College St",
    "sg:city":"Duluth",
    "sg:classifiers":[
        {
            "category":"Education",
            "subcategory":"School",
            "type":"Public Place"
        }
    ],
    "sg:phone":"+1 218 728 7411",
    "sg:postcode":"55811",
    "sg:province":"MN",
    "sg:tags":[
        "elementary"
    ],
    "wof:name":"Chester Park Elementary School",
    "wof:placetype":"venue"
},
  "geometry": {"coordinates":[-92.079773,46.814981],"type":"Point"}
}