{
  "type": "Feature",
  "properties": {
    "iso:country":"US",
    "sg:address":"656 4th St",
    "sg:city":"Audubon",
    "sg:classifiers":[
        {
            "category":"Manufacturing",
            "subcategory":"Wood Products",
            "type":"Manufacturing & Wholesale Goods"
        },
        {
            "category":"Home & Garden",
            "subcategory":"Building Materials",
            "type":"Retail Goods"
        }
    ],
    "sg:phone":"+1 218 439 3385",
    "sg:postcode":"56511",
    "sg:province":"MN",
    "sg:tags":[
        "millwork-wholesale",
        "millwork",
        "lumber-used",
        "manufacturer"
    ],
    "wof:name":"Country Wood Products Inc",
    "wof:placetype":"venue"
},
  "geometry": {"coordinates":[-95.981803,46.864988],"type":"Point"}
}