{
  "type": "Feature",
  "properties": {
    "addr:full":"4604 Drew Ave S Minneapolis MN 55410",
    "addr:housenumber":"4604",
    "addr:postcode":"55410",
    "addr:street":"Drew Ave S",
    "iso:country":"US",
    "sg:address":"4604 Drew Ave S",
    "sg:city":"Minneapolis",
    "sg:classifiers":[
        {
            "category":"Professional",
            "subcategory":"Management & Consulting",
            "type":"Services"
        }
    ],
    "sg:phone":"+1 612 920 3573",
    "sg:postcode":"55410",
    "sg:province":"MN",
    "wof:name":"Market Geography",
    "wof:placetype":"venue"
},
  "geometry": {"coordinates":[-93.32661400000001,44.918294],"type":"Point"}
}