{
  "type": "Feature",
  "properties": {
    "iso:country":"US",
    "sg:address":"5544 Shore Trl NE",
    "sg:city":"Prior Lake",
    "sg:classifiers":[
        {
            "category":"Building & Trades",
            "subcategory":"Construction",
            "type":"Services"
        }
    ],
    "sg:phone":"+1 952 884 8348",
    "sg:postcode":"55372",
    "sg:province":"MN",
    "sg:tags":[
        "house"
    ],
    "wof:name":"Lakeland Home Exterior",
    "wof:placetype":"venue"
},
  "geometry": {"coordinates":[-93.410247,44.73992],"type":"Point"}
}