{
  "type": "Feature",
  "properties": {
    "iso:country":"US",
    "sg:address":"607 Washington Ave S",
    "sg:city":"Minneapolis",
    "sg:classifiers":[
        {
            "category":"Restaurant",
            "type":"Food & Drink"
        }
    ],
    "sg:phone":"+1 612 338 6451",
    "sg:postcode":"55415",
    "sg:province":"MN",
    "sg:tags":[
        "thai"
    ],
    "wof:name":"Sawatdee Thai Restaurant",
    "wof:placetype":"venue"
},
  "geometry": {"coordinates":[-93.25990299999999,44.978199],"type":"Point"}
}