{
  "type": "Feature",
  "properties": {
    "addr:full":"501 Main St Cold Spring MN 56320",
    "addr:housenumber":"501",
    "addr:postcode":"56320",
    "addr:street":"Main St",
    "iso:country":"US",
    "sg:address":"501 Main St",
    "sg:city":"Cold Spring",
    "sg:classifiers":[
        {
            "category":"Education",
            "subcategory":"School",
            "type":"Public Place"
        }
    ],
    "sg:phone":"+1 320 685 3541",
    "sg:postcode":"56320",
    "sg:province":"MN",
    "sg:tags":[
        "organization",
        "religious"
    ],
    "sg:website":"www.stboniface.com",
    "wof:name":"St Boniface Parish",
    "wof:placetype":"venue"
},
  "geometry": {"coordinates":[-94.43052900000001,45.4558],"type":"Point"}
}