{
  "type": "Feature",
  "properties": {
    "addr:full":"1301 36th Ave W Alexandria MN 56308",
    "addr:housenumber":"1301",
    "addr:postcode":"56308",
    "addr:street":"36Th Ave W",
    "iso:country":"US",
    "sg:address":"1301 36th Ave W",
    "sg:city":"Alexandria",
    "sg:classifiers":[
        {
            "category":"Retail",
            "subcategory":"Auto Repair",
            "type":"Services"
        }
    ],
    "sg:phone":"+1 320 852 9950",
    "sg:postcode":"56308",
    "sg:province":"MN",
    "sg:tags":[
        "repairing",
        "automobile"
    ],
    "wof:name":"Chisum Repair Systems",
    "wof:placetype":"venue"
},
  "geometry": {"coordinates":[-95.39595300000001,45.85799],"type":"Point"}
}