{
  "type": "Feature",
  "properties": {
    "addr:full":"318 Current St NW Sleepy Eye MN 56085",
    "addr:housenumber":"318",
    "addr:postcode":"sleepy;56085",
    "addr:street":"Current St Nw",
    "iso:country":"US",
    "sg:address":"318 Current St NW",
    "sg:city":"Sleepy Eye",
    "sg:classifiers":[
        {
            "category":"Local Transit",
            "type":"Transportation"
        }
    ],
    "sg:phone":"+1 507 794 7941",
    "sg:postcode":"56085",
    "sg:province":"MN",
    "sg:tags":[
        "bus",
        "line"
    ],
    "wof:name":"Sleepy Eye Bus Lines Inc",
    "wof:placetype":"venue"
},
  "geometry": {"coordinates":[-94.727127,44.30106],"type":"Point"}
}