{
  "type": "Feature",
  "properties": {
    "iso:country":"US",
    "sg:address":"421 Main St W",
    "sg:city":"Cannon Falls",
    "sg:classifiers":[
        {
            "category":"Shopping",
            "subcategory":"Music",
            "type":"Retail Goods"
        }
    ],
    "sg:phone":"+1 507 263 2045",
    "sg:postcode":"55009",
    "sg:province":"MN",
    "wof:name":"Valu Plus Video",
    "wof:placetype":"venue"
},
  "geometry": {"coordinates":[-92.905931,44.506816],"type":"Point"}
}