{
  "type": "Feature",
  "properties": {
    "addr:full":"4300 Dodd Rd Saint Paul MN 55123",
    "addr:housenumber":"4300",
    "addr:postcode":"55123",
    "addr:street":"Dodd Rd",
    "iso:country":"US",
    "sg:address":"4300 Dodd Rd",
    "sg:city":"Saint Paul",
    "sg:classifiers":[
        {
            "category":"Education",
            "subcategory":"School",
            "type":"Public Place"
        }
    ],
    "sg:phone":"+1 651 683 6980",
    "sg:postcode":"55123",
    "sg:province":"MN",
    "sg:tags":[
        "elementary"
    ],
    "wof:name":"Pinewood Community Elementary",
    "wof:placetype":"venue"
},
  "geometry": {"coordinates":[-93.118281,44.800121],"type":"Point"}
}