{
  "type": "Feature",
  "properties": {
    "addr:full":"1373 Arcade St St Paul MN 55106",
    "addr:housenumber":"1373",
    "addr:postcode":"55106",
    "addr:street":"Arcade St",
    "iso:country":"US",
    "sg:address":"1373 Arcade St",
    "sg:city":"St Paul",
    "sg:classifiers":[
        {
            "category":"Shopping",
            "subcategory":"Computers & Home Electronics",
            "type":"Retail Goods"
        },
        {
            "category":"Professional",
            "subcategory":"Computer Services",
            "type":"Services"
        }
    ],
    "sg:phone":"+1 651 772 0913",
    "sg:postcode":"55106",
    "sg:province":"MN",
    "sg:tags":[
        "repair"
    ],
    "wof:name":"N Y Computer Center",
    "wof:placetype":"venue"
},
  "geometry": {"coordinates":[-93.066079,44.982176],"type":"Point"}
}