{
  "type": "Feature",
  "properties": {
    "iso:country":"US",
    "sg:address":"1729 Grand Ave",
    "sg:city":"Saint Paul",
    "sg:classifiers":[
        {
            "category":"Real Estate",
            "subcategory":"Real Estate Operator",
            "type":"Services"
        }
    ],
    "sg:phone":"+1 651 698 4777",
    "sg:postcode":"55105",
    "sg:province":"MN",
    "sg:tags":[
        "apartment"
    ],
    "wof:name":"Grand Place Apts",
    "wof:placetype":"venue"
},
  "geometry": {"coordinates":[-93.17338700000001,44.940197],"type":"Point"}
}