{
  "type": "Feature",
  "properties": {
    "addr:full":"219 N Kingston St Caledonia MN 55921",
    "addr:housenumber":"219",
    "addr:postcode":"55921",
    "addr:street":"N Kingston St",
    "iso:country":"US",
    "sg:address":"219 N Kingston St",
    "sg:city":"Caledonia",
    "sg:classifiers":[
        {
            "category":"Shopping",
            "subcategory":"Gifts & Souvenirs",
            "type":"Retail Goods"
        }
    ],
    "sg:phone":"+1 507 725 8581",
    "sg:postcode":"55921",
    "sg:province":"MN",
    "wof:name":"Farmhouse Eatery and Gifts",
    "wof:placetype":"venue"
},
  "geometry": {"coordinates":[-91.497052,43.636435],"type":"Point"}
}