{
  "type": "Feature",
  "properties": {
    "addr:full":"226 Alder Rd South Haven MN 55382",
    "addr:housenumber":"226",
    "addr:postcode":"55382",
    "addr:street":"Alder Rd",
    "iso:country":"US",
    "sg:address":"226 Alder Rd",
    "sg:city":"South Haven",
    "sg:classifiers":[
        {
            "category":"Professional",
            "subcategory":"Business Services",
            "type":"Services"
        }
    ],
    "sg:phone":"+1 320 274 2660",
    "sg:postcode":"55382",
    "sg:province":"MN",
    "wof:name":"Home Time Inspections",
    "wof:placetype":"venue"
},
  "geometry": {"coordinates":[-94.11345,45.334509],"type":"Point"}
}