{
  "type": "Feature",
  "properties": {
    "addr:full":"7101 York Ave S Edina MN 55435",
    "addr:housenumber":"7101",
    "addr:postcode":"55435",
    "addr:street":"York Ave S",
    "iso:country":"US",
    "sg:address":"7101 York Ave S",
    "sg:city":"Edina",
    "sg:classifiers":[
        {
            "category":"Professional",
            "subcategory":"Management & Consulting",
            "type":"Services"
        },
        {
            "category":"Professional",
            "subcategory":"Employment Agencies",
            "type":"Services"
        }
    ],
    "sg:phone":"+1 952 921 3377",
    "sg:postcode":"55435",
    "sg:province":"MN",
    "sg:tags":[
        "opportunity"
    ],
    "wof:name":"Regency Recruiters Inc",
    "wof:placetype":"venue"
},
  "geometry": {"coordinates":[-93.321155,44.875409],"type":"Point"}
}