{
  "type": "Feature",
  "properties": {
    "addr:full":"1505 Central Ave NE East Grand Forks MN 56721",
    "addr:housenumber":"1505",
    "addr:postcode":"56721",
    "addr:street":"Central Ave Ne",
    "iso:country":"US",
    "sg:address":"1505 Central Ave NE",
    "sg:city":"East Grand Forks",
    "sg:classifiers":[
        {
            "category":"Education",
            "subcategory":"School",
            "type":"Public Place"
        }
    ],
    "sg:phone":"+1 218 773 0315",
    "sg:postcode":"56721",
    "sg:province":"MN",
    "sg:tags":[
        "consulting",
        "business"
    ],
    "wof:name":"Area Special Education Coop",
    "wof:placetype":"venue"
},
  "geometry": {"coordinates":[-97.020021,47.941781],"type":"Point"}
}