{
  "type": "Feature",
  "properties": {
    "iso:country":"US",
    "sg:address":"6051 Co Rd 9 NE",
    "sg:city":"Carlos",
    "sg:classifiers":[
        {
            "category":"Farming",
            "subcategory":"Dairy Farm",
            "type":"Manufacturing & Wholesale Goods"
        }
    ],
    "sg:phone":"+1 320 852 7920",
    "sg:postcode":"56319",
    "sg:province":"MN",
    "wof:name":"J Bradley",
    "wof:placetype":"venue"
},
  "geometry": {"coordinates":[-95.29187899999999,45.947552],"type":"Point"}
}