{
  "type": "Feature",
  "properties": {
    "iso:country":"US",
    "sg:address":"3403 22nd St S",
    "sg:city":"St Cloud",
    "sg:classifiers":[
        {
            "category":"Real Estate",
            "subcategory":"Real Estate Operator",
            "type":"Services"
        }
    ],
    "sg:phone":"+1 320 202 8763",
    "sg:postcode":"56301",
    "sg:province":"MN",
    "sg:tags":[
        "apartment"
    ],
    "wof:name":"Stratford Square Apts",
    "wof:placetype":"venue"
},
  "geometry": {"coordinates":[-94.20075900000001,45.537782],"type":"Point"}
}