{
  "type": "Feature",
  "properties": {
    "addr:full":"5525 Prairie Grass Dr Sartell MN 56377",
    "addr:housenumber":"5525",
    "addr:postcode":"56377",
    "addr:street":"Prairie Grass Dr",
    "iso:country":"US",
    "sg:address":"5525 Prairie Grass Dr",
    "sg:city":"Sartell",
    "sg:classifiers":[
        {
            "category":"Professional",
            "subcategory":"Business Services",
            "type":"Services"
        }
    ],
    "sg:phone":"+1 320 259 0766",
    "sg:postcode":"56377",
    "sg:province":"MN",
    "wof:name":"Apollo Auction Co",
    "wof:placetype":"venue"
},
  "geometry": {"coordinates":[-94.224733,45.689342],"type":"Point"}
}