{
  "type": "Feature",
  "properties": {
    "addr:full":"219 Meadowlark Ln Melrose MN 56352",
    "addr:housenumber":"219",
    "addr:postcode":"56352",
    "addr:street":"Meadowlark Ln",
    "iso:country":"US",
    "sg:address":"219 Meadowlark Ln",
    "sg:city":"Melrose",
    "sg:classifiers":[
        {
            "category":"Retail",
            "subcategory":"Animal Services",
            "type":"Services"
        }
    ],
    "sg:phone":"+1 320 256 9663",
    "sg:postcode":"56352",
    "sg:province":"MN",
    "sg:tags":[
        "pet",
        "grooming",
        "washing"
    ],
    "wof:name":"Cuddly Critters Pet Salon",
    "wof:placetype":"venue"
},
  "geometry": {"coordinates":[-94.81751800000001,45.663208],"type":"Point"}
}