{
  "type": "Feature",
  "properties": {
    "iso:country":"US",
    "sg:address":"3040 E Beltline",
    "sg:city":"Hibbing",
    "sg:classifiers":[
        {
            "category":"Retail",
            "subcategory":"Auto Repair",
            "type":"Services"
        }
    ],
    "sg:phone":"+1 218 262 5533",
    "sg:postcode":"55746",
    "sg:province":"MN",
    "sg:tags":[
        "automotive",
        "general"
    ],
    "sg:website":"www.vioc.com",
    "wof:name":"Valvoline Instant Oil Change",
    "wof:placetype":"venue"
},
  "geometry": {"coordinates":[-92.923427,47.412992],"type":"Point"}
}