{
  "type": "Feature",
  "properties": {
    "iso:country":"US",
    "sg:address":"9755 Hamilton Rd",
    "sg:city":"Eden Prairie",
    "sg:classifiers":[
        {
            "category":"Insurance",
            "subcategory":"Insurance Agent",
            "type":"Services"
        }
    ],
    "sg:phone":"+1 952 746 4944",
    "sg:postcode":"55344",
    "sg:province":"MN",
    "wof:name":"American Family Insurance",
    "wof:placetype":"venue"
},
  "geometry": {"coordinates":[-93.40165399999999,44.880854],"type":"Point"}
}