{
  "type": "Feature",
  "properties": {
    "addr:full":"4724 Cedar Ave S Minneapolis MN 55407",
    "addr:housenumber":"4724",
    "addr:postcode":"55407",
    "addr:street":"Cedar Ave S",
    "iso:country":"US",
    "sg:address":"4724 Cedar Ave S",
    "sg:city":"Minneapolis",
    "sg:classifiers":[
        {
            "category":"Restaurant",
            "type":"Food & Drink"
        }
    ],
    "sg:phone":"+1 612 724 0063",
    "sg:postcode":"55407",
    "sg:province":"MN",
    "sg:tags":[
        "pizza"
    ],
    "sg:website":"http://www.carbonespizzeria.com",
    "wof:name":"Carbone's Pizzeria",
    "wof:placetype":"venue"
},
  "geometry": {"coordinates":[-93.24749799999999,44.916801],"type":"Point"}
}