{
  "type": "Feature",
  "properties": {
    "iso:country":"US",
    "sg:address":"7300 Metro Blvd",
    "sg:city":"Minneapolis",
    "sg:classifiers":[
        {
            "category":"Wholesale",
            "subcategory":"Electrical",
            "type":"Manufacturing & Wholesale Goods"
        }
    ],
    "sg:phone":"+1 952 893 1214",
    "sg:postcode":"55439",
    "sg:province":"MN",
    "sg:tags":[
        "electronic"
    ],
    "wof:name":"American Micro Systems",
    "wof:placetype":"venue"
},
  "geometry": {"coordinates":[-93.352823,44.868041],"type":"Point"}
}