{
  "type": "Feature",
  "properties": {
    "addr:full":"847 30th Ave N Saint Cloud MN 56303",
    "addr:housenumber":"847",
    "addr:postcode":"56303",
    "addr:street":"30Th Ave N",
    "iso:country":"US",
    "sg:address":"847 30th Ave N",
    "sg:city":"Saint Cloud",
    "sg:classifiers":[
        {
            "category":"Wholesale",
            "subcategory":"Farm Supplies",
            "type":"Manufacturing & Wholesale Goods"
        }
    ],
    "sg:phone":"+1 320 253 3265",
    "sg:postcode":"56303",
    "sg:province":"MN",
    "sg:tags":[
        "raw",
        "product",
        "material"
    ],
    "wof:name":"Nut Man",
    "wof:placetype":"venue"
},
  "geometry": {"coordinates":[-94.194338,45.56728],"type":"Point"}
}