{
  "type": "Feature",
  "properties": {
    "iso:country":"US",
    "sg:address":"847 30th Ave N",
    "sg:city":"Saint Cloud",
    "sg:classifiers":[
        {
            "category":"Wholesale",
            "subcategory":"Farm Supplies",
            "type":"Manufacturing & Wholesale Goods"
        }
    ],
    "sg:phone":"+1 320 253 3265",
    "sg:postcode":"56303",
    "sg:province":"MN",
    "sg:tags":[
        "raw",
        "product",
        "material"
    ],
    "wof:name":"Nut Man",
    "wof:placetype":"venue"
},
  "geometry": {"coordinates":[-94.194338,45.56728],"type":"Point"}
}