{
  "type": "Feature",
  "properties": {
    "addr:full":"44668 620th Ave Sebeka MN 56477",
    "addr:housenumber":"44668",
    "addr:postcode":"56477",
    "addr:street":"620Th Ave",
    "iso:country":"US",
    "sg:address":"44668 620th Ave",
    "sg:city":"Sebeka",
    "sg:classifiers":[
        {
            "category":"Manufacturing",
            "subcategory":"Tools & Machinery",
            "type":"Manufacturing & Wholesale Goods"
        }
    ],
    "sg:phone":"+1 218 837 5446",
    "sg:postcode":"56477",
    "sg:province":"MN",
    "sg:tags":[
        "metalworking",
        "industrial",
        "mfg"
    ],
    "wof:name":"Advan Tech",
    "wof:placetype":"venue"
},
  "geometry": {"coordinates":[-95.197137,46.613743],"type":"Point"}
}