{
  "type": "Feature",
  "properties": {
    "addr:full":"694 S Oakdale Ave St Paul MN 55107",
    "addr:housenumber":"694",
    "addr:postcode":"55107",
    "addr:street":"S Oakdale Ave",
    "iso:country":"US",
    "sg:address":"694 S Oakdale Ave",
    "sg:city":"St Paul",
    "sg:classifiers":[
        {
            "category":"Arts & Performance",
            "subcategory":"Theater",
            "type":"Entertainment"
        }
    ],
    "sg:phone":"+1 651 292 8352",
    "sg:postcode":"55107",
    "sg:province":"MN",
    "sg:tags":[
        "live",
        "music"
    ],
    "wof:name":"T Albert Lloyd & The Kingpins",
    "wof:placetype":"venue"
},
  "geometry": {"coordinates":[-93.07798099999999,44.925381],"type":"Point"}
}