{
  "type": "Feature",
  "properties": {
    "iso:country":"US",
    "sg:address":"3552 W River Pkwy NW",
    "sg:city":"Rochester",
    "sg:classifiers":[
        {
            "category":"Professional",
            "type":"Services"
        }
    ],
    "sg:phone":"+1 507 529 9300",
    "sg:postcode":"55901",
    "sg:province":"MN",
    "wof:name":"Appraiasal Co",
    "wof:placetype":"venue"
},
  "geometry": {"coordinates":[-92.472874,44.059872],"type":"Point"}
}