{
  "type": "Feature",
  "properties": {
    "addr:full":"3279 Town Rd International Falls MN 56649",
    "addr:housenumber":"3279",
    "addr:postcode":"56649",
    "addr:street":"Town Rd",
    "iso:country":"US",
    "sg:address":"3279 Town Rd",
    "sg:city":"International Falls",
    "sg:classifiers":[
        {
            "category":"Health Services",
            "subcategory":"Clinic",
            "type":"Services"
        }
    ],
    "sg:phone":"+1 218 377 4401",
    "sg:postcode":"56649",
    "sg:province":"MN",
    "wof:name":"River Oaks Home Health CA",
    "wof:placetype":"venue"
},
  "geometry": {"coordinates":[-93.45024600000001,48.560421],"type":"Point"}
}