{
  "type": "Feature",
  "properties": {
    "iso:country":"US",
    "sg:address":"30300 Bulick Ave",
    "sg:city":"Adrian",
    "sg:classifiers":[
        {
            "category":"Government",
            "subcategory":"Office",
            "type":"Public Place"
        }
    ],
    "sg:phone":"+1 507 967 2193",
    "sg:postcode":"56110",
    "sg:province":"MN",
    "wof:name":"Daniel Lee Boltjes",
    "wof:placetype":"venue"
},
  "geometry": {"coordinates":[-95.993088,43.644514],"type":"Point"}
}