{
  "type": "Feature",
  "properties": {
    "addr:full":"10820 150th St Cologne MN 55322",
    "addr:housenumber":"10820",
    "addr:postcode":"55322",
    "addr:street":"150Th St",
    "iso:country":"US",
    "sg:address":"10820 150th St",
    "sg:city":"Cologne",
    "sg:classifiers":[
        {
            "category":"Manufacturing",
            "subcategory":"Tools & Machinery",
            "type":"Manufacturing & Wholesale Goods"
        }
    ],
    "sg:phone":"+1 952 466 2437",
    "sg:postcode":"55322",
    "sg:province":"MN",
    "sg:tags":[
        "machine",
        "mfg"
    ],
    "wof:name":"J&J Tool Inc",
    "wof:placetype":"venue"
},
  "geometry": {"coordinates":[-93.80006299999999,44.731471],"type":"Point"}
}