{
  "type": "Feature",
  "properties": {
    "iso:country":"US",
    "sg:address":"327 E River Pkwy",
    "sg:city":"Champlin",
    "sg:classifiers":[
        {
            "category":"Professional",
            "type":"Services"
        }
    ],
    "sg:phone":"+1 763 427 4022",
    "sg:postcode":"55316",
    "sg:province":"MN",
    "wof:name":"Hlc of Anoka Inc",
    "wof:placetype":"venue"
},
  "geometry": {"coordinates":[-93.392135,45.187099],"type":"Point"}
}