{
  "type": "Feature",
  "properties": {
    "addr:full":"1200 1st Ave NE Little Falls MN 56345",
    "addr:housenumber":"1200",
    "addr:postcode":"56345",
    "addr:street":"1St Ave Ne",
    "iso:country":"US",
    "sg:address":"1200 1st Ave NE",
    "sg:city":"Little Falls",
    "sg:classifiers":[
        {
            "category":"Health Services",
            "subcategory":"Nursing And Care Facility",
            "type":"Services"
        }
    ],
    "sg:phone":"+1 320 632 9211",
    "sg:postcode":"56345",
    "sg:province":"MN",
    "sg:tags":[
        "home",
        "convalescent"
    ],
    "wof:name":"Lutheran Care Ctr",
    "wof:placetype":"venue"
},
  "geometry": {"coordinates":[-94.34365099999999,45.975729],"type":"Point"}
}