{
  "type": "Feature",
  "properties": {
    "addr:full":"901 Lake Elmo Ave N Lake Elmo MN 55042",
    "addr:housenumber":"901",
    "addr:postcode":"55042",
    "addr:street":"Lake Elmo Ave N",
    "iso:country":"US",
    "sg:address":"901 Lake Elmo Ave N",
    "sg:city":"Lake Elmo",
    "sg:classifiers":[
        {
            "category":"Real Estate",
            "subcategory":"Real Estate Agent",
            "type":"Services"
        }
    ],
    "sg:phone":"+1 651 436 2790",
    "sg:postcode":"55042",
    "sg:province":"MN",
    "sg:tags":[
        "property",
        "management"
    ],
    "wof:name":"Cimarron Park",
    "wof:placetype":"venue"
},
  "geometry": {"coordinates":[-92.883127,44.961908],"type":"Point"}
}