{
  "type": "Feature",
  "properties": {
    "addr:full":"1865 W Wayzata Blvd Long Lake MN 55356",
    "addr:housenumber":"1865",
    "addr:postcode":"55356",
    "addr:street":"W Wayzata Blvd",
    "iso:country":"US",
    "sg:address":"1865 W Wayzata Blvd",
    "sg:city":"Long Lake",
    "sg:classifiers":[
        {
            "category":"Restaurant",
            "type":"Food & Drink"
        }
    ],
    "sg:menulink":"http://www.allmenus.com/mn/long-lake/58411-dominos-pizza/menu/",
    "sg:phone":"+1 952 473 0400",
    "sg:postcode":"55356",
    "sg:province":"MN",
    "sg:tags":[
        "american",
        "wing",
        "pizza"
    ],
    "wof:name":"Domino's Pizza",
    "wof:placetype":"venue"
},
  "geometry": {"coordinates":[-93.572306,44.985539],"type":"Point"}
}