{
  "type": "Feature",
  "properties": {
    "iso:country":"US",
    "sg:address":"12452 State Hwy 16",
    "sg:city":"Houston",
    "sg:phone":"+1 507 896 2117",
    "sg:postcode":"55943",
    "sg:province":"MN",
    "sg:tags":[
        "farm",
        "corn",
        "crop",
        "field",
        "dairy",
        "soybean"
    ],
    "wof:name":"Brian Lee",
    "wof:placetype":"venue"
},
  "geometry": {"coordinates":[-91.50138800000001,43.773717],"type":"Point"}
}