{
  "type": "Feature",
  "properties": {
    "addr:full":"125 N Main St Blue Earth MN 56013",
    "addr:housenumber":"125",
    "addr:postcode":"56013",
    "addr:street":"N Main St",
    "iso:country":"US",
    "sg:address":"125 N Main St",
    "sg:city":"Blue Earth",
    "sg:classifiers":[
        {
            "category":"Government",
            "subcategory":"Court House",
            "type":"Public Place"
        }
    ],
    "sg:phone":"+1 507 526 4564",
    "sg:postcode":"56013",
    "sg:province":"MN",
    "sg:tags":[
        "county",
        "attorney"
    ],
    "wof:name":"County of Faribault",
    "wof:placetype":"venue"
},
  "geometry": {"coordinates":[-94.102558,43.639399],"type":"Point"}
}