{
  "type": "Feature",
  "properties": {
    "iso:country":"US",
    "sg:address":"301 Walnut Ave",
    "sg:city":"Carlton",
    "sg:classifiers":[
        {
            "category":"Government",
            "subcategory":"Court House",
            "type":"Public Place"
        }
    ],
    "sg:phone":"+1 218 384 9583",
    "sg:postcode":"55718",
    "sg:province":"MN",
    "sg:tags":[
        "county"
    ],
    "wof:name":"Carlton County Juvenile Court",
    "wof:placetype":"venue"
},
  "geometry": {"coordinates":[-92.42483900000001,46.664709],"type":"Point"}
}