{
  "type": "Feature",
  "properties": {
    "addr:full":"5239 University Ave NE Minneapolis MN 55421",
    "addr:housenumber":"5239",
    "addr:postcode":"55421",
    "addr:street":"University Ave Ne",
    "iso:country":"US",
    "sg:address":"5239 University Ave NE",
    "sg:city":"Minneapolis",
    "sg:classifiers":[
        {
            "category":"Retail",
            "subcategory":"Auto Repair",
            "type":"Services"
        }
    ],
    "sg:phone":"+1 763 572 2449",
    "sg:postcode":"55421",
    "sg:province":"MN",
    "sg:tags":[
        "automotive",
        "general"
    ],
    "wof:name":"Galaxy Auto Center",
    "wof:placetype":"venue"
},
  "geometry": {"coordinates":[-93.262838,45.063754],"type":"Point"}
}