{
  "type": "Feature",
  "properties": {
    "iso:country":"US",
    "sg:address":"235 4th Ave",
    "sg:city":"International Falls",
    "sg:classifiers":[
        {
            "category":"Professional",
            "subcategory":"Lawyer & Legal Services",
            "type":"Services"
        }
    ],
    "sg:phone":"+1 218 283 9481",
    "sg:postcode":"56649",
    "sg:province":"MN",
    "wof:name":"Boyle Law Office",
    "wof:placetype":"venue"
},
  "geometry": {"coordinates":[-93.405073,48.603085],"type":"Point"}
}