{
  "type": "Feature",
  "properties": {
    "iso:country":"US",
    "sg:address":"319 Main St",
    "sg:city":"Manchester",
    "sg:classifiers":[
        {
            "category":"Retail",
            "subcategory":"Repair Shop",
            "type":"Services"
        }
    ],
    "sg:phone":"+1 507 869 3779",
    "sg:postcode":"56007",
    "sg:province":"MN",
    "sg:tags":[
        "scooter",
        "motorcycle",
        "motor"
    ],
    "wof:name":"Pemberton Powersports",
    "wof:placetype":"venue"
},
  "geometry": {"coordinates":[-93.452307,43.725835],"type":"Point"}
}