{
  "type": "Feature",
  "properties": {
    "iso:country":"US",
    "sg:address":"46 Oak Ave N",
    "sg:city":"Annandale",
    "sg:classifiers":[
        {
            "category":"Shopping",
            "type":"Retail Goods"
        }
    ],
    "sg:phone":"+1 320 274 6224",
    "sg:postcode":"55302",
    "sg:province":"MN",
    "sg:tags":[
        "item",
        "boutique"
    ],
    "sg:website":"http://amboutique-mn.com",
    "wof:name":"Am Boutique",
    "wof:placetype":"venue"
},
  "geometry": {"coordinates":[-94.124433,45.263137],"type":"Point"}
}