{
  "type": "Feature",
  "properties": {
    "addr:full":"905 Park Ave Morris MN 56267",
    "addr:housenumber":"905",
    "addr:postcode":"56267",
    "addr:street":"Park Ave",
    "iso:country":"US",
    "sg:address":"905 Park Ave",
    "sg:city":"Morris",
    "sg:classifiers":[
        {
            "category":"Real Estate",
            "subcategory":"Real Estate Operator",
            "type":"Services"
        }
    ],
    "sg:phone":"+1 320 589 4259",
    "sg:postcode":"56267",
    "sg:province":"MN",
    "sg:tags":[
        "mobile",
        "home",
        "site"
    ],
    "wof:name":"Woodland Home",
    "wof:placetype":"venue"
},
  "geometry": {"coordinates":[-95.92362199999999,45.587666],"type":"Point"}
}