{
  "type": "Feature",
  "properties": {
    "addr:full":"100 Le Sueur Ave Eagle Lake MN 56024",
    "addr:housenumber":"100",
    "addr:postcode":"56024",
    "addr:street":"Le Sueur Ave",
    "iso:country":"US",
    "sg:address":"100 Le Sueur Ave",
    "sg:city":"Eagle Lake",
    "sg:classifiers":[
        {
            "category":"Government",
            "subcategory":"Post Office",
            "type":"Public Place"
        }
    ],
    "sg:phone":"+1 507 257 3200",
    "sg:postcode":"56024",
    "sg:province":"MN",
    "wof:name":"US Post Office",
    "wof:placetype":"venue"
},
  "geometry": {"coordinates":[-93.87966299999999,44.163055],"type":"Point"}
}