{
  "type": "Feature",
  "properties": {
    "iso:country":"US",
    "sg:address":"101 3rd St",
    "sg:city":"Tracy",
    "sg:classifiers":[
        {
            "category":"Restaurant",
            "type":"Food & Drink"
        }
    ],
    "sg:phone":"+1 507 629 9000",
    "sg:postcode":"56175",
    "sg:province":"MN",
    "wof:name":"Mace's Dining",
    "wof:placetype":"venue"
},
  "geometry": {"coordinates":[-95.61969999999999,44.23264],"type":"Point"}
}