{
  "type": "Feature",
  "properties": {
    "addr:full":"11536 Co Rd 14 Herman MN 56265",
    "addr:housenumber":"11536;14",
    "addr:postcode":"56265",
    "addr:street":"Co Rd;Herman",
    "iso:country":"US",
    "sg:address":"11536 Co Rd 14",
    "sg:city":"Herman",
    "sg:phone":"+1 320 246 3410",
    "sg:postcode":"56265",
    "sg:province":"MN",
    "sg:tags":[
        "farm"
    ],
    "wof:name":"Randy L Werk",
    "wof:placetype":"venue"
},
  "geometry": {"coordinates":[-95.826308,44.992899],"type":"Point"}
}