{
  "type": "Feature",
  "properties": {
    "iso:country":"US",
    "sg:address":"16860 Welcome Ave SE",
    "sg:city":"Prior Lake",
    "sg:classifiers":[
        {
            "category":"Retail",
            "subcategory":"Repair Shop",
            "type":"Services"
        }
    ],
    "sg:phone":"+1 952 447 2345",
    "sg:postcode":"55372",
    "sg:province":"MN",
    "sg:tags":[
        "welding"
    ],
    "wof:name":"G Benson Welding",
    "wof:placetype":"venue"
},
  "geometry": {"coordinates":[-93.401602,44.705729],"type":"Point"}
}