{
  "type": "Feature",
  "properties": {
    "iso:country":"US",
    "sg:address":"14429 Vintage St NW",
    "sg:city":"Andover",
    "sg:classifiers":[
        {
            "category":"Professional",
            "subcategory":"Lawyer & Legal Services",
            "type":"Services"
        }
    ],
    "sg:phone":"+1 763 427 4746",
    "sg:postcode":"55304",
    "sg:province":"MN",
    "sg:tags":[
        "plan"
    ],
    "wof:name":"Kreative Research & Marketing",
    "wof:placetype":"venue"
},
  "geometry": {"coordinates":[-93.359228,45.232606],"type":"Point"}
}