{
  "type": "Feature",
  "properties": {
    "iso:country":"US",
    "sg:address":"115 Main St W",
    "sg:city":"Nevis",
    "sg:classifiers":[
        {
            "category":"Food & Beverages",
            "subcategory":"Specialty",
            "type":"Retail Goods"
        }
    ],
    "sg:phone":"+1 218 652 3091",
    "sg:postcode":"56467",
    "sg:province":"MN",
    "sg:tags":[
        "product",
        "health",
        "diet"
    ],
    "wof:name":"Imani Natural Products",
    "wof:placetype":"venue"
},
  "geometry": {"coordinates":[-94.842478,46.964624],"type":"Point"}
}