{
  "type": "Feature",
  "properties": {
    "addr:full":"4220 3rd Ave W Hibbing MN 55746",
    "addr:housenumber":"4220",
    "addr:postcode":"55746",
    "addr:street":"3Rd Ave W Hibbing",
    "iso:country":"US",
    "sg:address":"4220 3rd Ave W",
    "sg:city":"Hibbing",
    "sg:classifiers":[
        {
            "category":"Organizations",
            "subcategory":"Religious Organization",
            "type":"Services"
        }
    ],
    "sg:phone":"+1 218 262 6685",
    "sg:postcode":"55746",
    "sg:province":"MN",
    "sg:tags":[
        "church"
    ],
    "sg:website":"www.hibbingalliance.org",
    "wof:name":"Hibbing Alliance Church",
    "wof:placetype":"venue"
},
  "geometry": {"coordinates":[-92.942419,47.399697],"type":"Point"}
}