{
  "type": "Feature",
  "properties": {
    "iso:country":"US",
    "sg:address":"140 Elton Hills Ln NW",
    "sg:city":"Rochester",
    "sg:classifiers":[
        {
            "category":"Banks & Credit Unions",
            "subcategory":"Bank",
            "type":"Services"
        }
    ],
    "sg:phone":"+1 507 281 3456",
    "sg:postcode":"55901",
    "sg:province":"MN",
    "sg:tags":[
        "mortgage",
        "real estate"
    ],
    "wof:name":"Burnett Home Loans Inc",
    "wof:placetype":"venue"
},
  "geometry": {"coordinates":[-92.463449,44.041295],"type":"Point"}
}