{
  "type": "Feature",
  "properties": {
    "addr:full":"505 Highway 169 N Minneapolis MN 55441",
    "addr:housenumber":"505",
    "addr:postcode":"55441",
    "addr:street":"Highway 169 N",
    "iso:country":"US",
    "sg:address":"505 Highway 169 N",
    "sg:city":"Minneapolis",
    "sg:classifiers":[
        {
            "category":"Professional",
            "subcategory":"Employment Agencies",
            "type":"Services"
        }
    ],
    "sg:phone":"+1 612 279 8236",
    "sg:postcode":"55441",
    "sg:province":"MN",
    "sg:tags":[
        "temporary",
        "contractor"
    ],
    "sg:website":"http://twincities.citysearch.com/profile/external/45674037/plymouth_mn/manpower.html?publisher=yellowpages&reference_id=1&placement=ypwebsitemip",
    "wof:name":"Manpower",
    "wof:placetype":"venue"
},
  "geometry": {"coordinates":[-93.40263,44.984471],"type":"Point"}
}