{
  "type": "Feature",
  "properties": {
    "iso:country":"US",
    "sg:address":"14450 S Robert Trl",
    "sg:city":"Rosemount",
    "sg:classifiers":[
        {
            "category":"Health Services",
            "subcategory":"Dentist",
            "type":"Services"
        }
    ],
    "sg:phone":"+1 651 423 1181",
    "sg:postcode":"55068",
    "sg:province":"MN",
    "sg:tags":[
        "implant",
        "dentistry",
        "dentists-pediatric",
        "dentists-implantology"
    ],
    "sg:website":"http://www.drmarknelson.net",
    "wof:name":"Nelson Mark J",
    "wof:placetype":"venue"
},
  "geometry": {"coordinates":[-93.126091,44.739523],"type":"Point"}
}