{
  "type": "Feature",
  "properties": {
    "addr:full":"18882 Stoner Memorial Dr NE Hines MN 56647",
    "addr:housenumber":"18882",
    "addr:postcode":"56647",
    "addr:street":"Stoner Memorial Dr Ne",
    "iso:country":"US",
    "sg:address":"18882 Stoner Memorial Dr NE",
    "sg:city":"Hines",
    "sg:classifiers":[
        {
            "category":"Travel",
            "subcategory":"Hotels & Motels",
            "type":"Entertainment"
        }
    ],
    "sg:phone":"+1 218 835 4552",
    "sg:postcode":"56647",
    "sg:province":"MN",
    "sg:tags":[
        "resort"
    ],
    "wof:name":"White Birch Resort",
    "wof:placetype":"venue"
},
  "geometry": {"coordinates":[-94.613321,47.746905],"type":"Point"}
}