{
  "type": "Feature",
  "properties": {
    "iso:country":"US",
    "sg:address":"11947 Kenyon St NE",
    "sg:city":"Minneapolis",
    "sg:classifiers":[
        {
            "category":"Health Services",
            "subcategory":"Clinic",
            "type":"Services"
        }
    ],
    "sg:phone":"+1 763 767 4753",
    "sg:postcode":"55449",
    "sg:province":"MN",
    "wof:name":"Health Serenity & Longevity",
    "wof:placetype":"venue"
},
  "geometry": {"coordinates":[-93.220809,45.187141],"type":"Point"}
}