{
  "type": "Feature",
  "properties": {
    "addr:full":"2327 Clearwater Rd Saint Cloud MN 56301",
    "addr:housenumber":"2327",
    "addr:postcode":"56301",
    "addr:street":"Clearwater Rd",
    "iso:country":"US",
    "sg:address":"2327 Clearwater Rd",
    "sg:city":"Saint Cloud",
    "sg:classifiers":[
        {
            "category":"Shopping",
            "subcategory":"Gifts & Souvenirs",
            "type":"Retail Goods"
        }
    ],
    "sg:phone":"+1 320 230 3696",
    "sg:postcode":"56301",
    "sg:province":"MN",
    "wof:name":"Granite City Gifts",
    "wof:placetype":"venue"
},
  "geometry": {"coordinates":[-94.161373,45.533664],"type":"Point"}
}