{
  "type": "Feature",
  "properties": {
    "iso:country":"US",
    "sg:address":"5392 Fish Lake Dam Rd",
    "sg:city":"Duluth",
    "sg:classifiers":[
        {
            "category":"Travel",
            "subcategory":"Hotels & Motels",
            "type":"Entertainment"
        }
    ],
    "sg:phone":"+1 218 721 3355",
    "sg:postcode":"55803",
    "sg:province":"MN",
    "sg:tags":[
        "resort"
    ],
    "sg:website":"www.hibanksresort.com",
    "wof:name":"Hi Banks Resort",
    "wof:placetype":"venue"
},
  "geometry": {"coordinates":[-92.23905499999999,46.964717],"type":"Point"}
}