{
  "type": "Feature",
  "properties": {
    "addr:full":"2550 University Ave W St Paul MN 55114",
    "addr:housenumber":"2550",
    "addr:postcode":"55114",
    "addr:street":"University Ave W",
    "iso:country":"US",
    "sg:address":"2550 University Ave W",
    "sg:city":"St Paul",
    "sg:classifiers":[
        {
            "category":"Professional",
            "type":"Services"
        }
    ],
    "sg:phone":"+1 651 644 2921",
    "sg:postcode":"55114",
    "sg:province":"MN",
    "sg:tags":[
        "establishment"
    ],
    "wof:name":"Himsa America",
    "wof:placetype":"venue"
},
  "geometry": {"coordinates":[-93.20182699999999,44.965624],"type":"Point"}
}