{
  "type": "Feature",
  "properties": {
    "iso:country":"US",
    "sg:address":"428 Stratford St W",
    "sg:city":"Avon",
    "sg:classifiers":[
        {
            "category":"Restaurant",
            "type":"Food & Drink"
        }
    ],
    "sg:phone":"+1 320 356 7372",
    "sg:postcode":"56310",
    "sg:province":"MN",
    "sg:website":"http://www.fishersclub.com",
    "wof:name":"Fisher Club",
    "wof:placetype":"venue"
},
  "geometry": {"coordinates":[-94.455409,45.611292],"type":"Point"}
}