{
  "type": "Feature",
  "properties": {
    "addr:full":"20628 170th Ave S Barnesville MN 56514",
    "addr:housenumber":"20628",
    "addr:postcode":"56514",
    "addr:street":"170Th Ave S Barnesville",
    "iso:country":"US",
    "sg:address":"20628 170th Ave S",
    "sg:city":"Barnesville",
    "sg:classifiers":[
        {
            "category":"Farming",
            "subcategory":"Livestock Farm",
            "type":"Manufacturing & Wholesale Goods"
        }
    ],
    "sg:phone":"+1 218 493 4667",
    "sg:postcode":"56514",
    "sg:province":"MN",
    "sg:tags":[
        "specialty",
        "animal"
    ],
    "wof:name":"Lowervalley Elk Ranch Lvr",
    "wof:placetype":"venue"
},
  "geometry": {"coordinates":[-96.36230999999999,46.645236],"type":"Point"}
}