{
  "type": "Feature",
  "properties": {
    "addr:full":"1883 Sioux Blvd St Paul MN 55112",
    "addr:housenumber":"1883",
    "addr:postcode":"55112",
    "addr:street":"Sioux Blvd",
    "iso:country":"US",
    "sg:address":"1883 Sioux Blvd",
    "sg:city":"St Paul",
    "sg:classifiers":[
        {
            "category":"Building & Trades",
            "subcategory":"Construction",
            "type":"Services"
        }
    ],
    "sg:phone":"+1 651 636 7645",
    "sg:postcode":"55112",
    "sg:province":"MN",
    "sg:tags":[
        "repairing",
        "remodeling",
        "contractor"
    ],
    "sg:website":"www.woodendreamsinc.com",
    "wof:name":"Wooden Dreams Inc",
    "wof:placetype":"venue"
},
  "geometry": {"coordinates":[-93.21031000000001,45.056367],"type":"Point"}
}