{
  "type": "Feature",
  "properties": {
    "addr:full":"8670 160th Ct NW Anoka MN 55303",
    "addr:housenumber":"8670",
    "addr:postcode":"55303",
    "addr:street":"160Th Ct Nw",
    "iso:country":"US",
    "sg:address":"8670 160th Ct NW",
    "sg:city":"Anoka",
    "sg:classifiers":[
        {
            "category":"Professional",
            "subcategory":"Management & Consulting",
            "type":"Services"
        }
    ],
    "sg:phone":"+1 763 241 3943",
    "sg:postcode":"55303",
    "sg:province":"MN",
    "sg:tags":[
        "organizing",
        "business",
        "services-household"
    ],
    "wof:name":"Top Shelf Management Inc",
    "wof:placetype":"venue"
},
  "geometry": {"coordinates":[-93.48766999999999,45.263024],"type":"Point"}
}