{
  "type": "Feature",
  "properties": {
    "iso:country":"US",
    "sg:address":"7250 France Ave S Ste 418",
    "sg:city":"Minneapolis",
    "sg:classifiers":[
        {
            "category":"Wholesale",
            "subcategory":"Medical Equipment & Supplies",
            "type":"Manufacturing & Wholesale Goods"
        },
        {
            "category":"Health Services",
            "subcategory":"Health Practitioner",
            "type":"Services"
        }
    ],
    "sg:phone":"+1 952 887 1688",
    "sg:postcode":"55435",
    "sg:province":"MN",
    "sg:tags":[
        "assistive",
        "device",
        "audiologists",
        "aid",
        "hearing"
    ],
    "sg:website":"http://www.avada.com",
    "wof:name":"Avada Audiology & Hearing Care",
    "wof:placetype":"venue"
},
  "geometry": {"coordinates":[-93.329014,44.871903],"type":"Point"}
}