{
  "type": "Feature",
  "properties": {
    "addr:full":"1105 4th St N Sartell MN 56377",
    "addr:housenumber":"1105",
    "addr:postcode":"56377",
    "addr:street":"4Th St N",
    "iso:country":"US",
    "sg:address":"1105 4th St N",
    "sg:city":"Sartell",
    "sg:classifiers":[
        {
            "category":"Shopping",
            "subcategory":"Catalog Store",
            "type":"Retail Goods"
        }
    ],
    "sg:phone":"+1 320 253 5362",
    "sg:postcode":"56377",
    "sg:province":"MN",
    "sg:tags":[
        "mail",
        "order",
        "online"
    ],
    "sg:website":"http://www.csnmarketingsolutions.com",
    "wof:name":"Csn Marketing Group",
    "wof:placetype":"venue"
},
  "geometry": {"coordinates":[-94.2283,45.624251],"type":"Point"}
}