{
  "type": "Feature",
  "properties": {
    "iso:country":"US",
    "sg:address":"251 Summit Ave",
    "sg:city":"St Paul",
    "sg:classifiers":[
        {
            "category":"Professional",
            "type":"Services"
        }
    ],
    "sg:phone":"+1 651 227 1473",
    "sg:postcode":"55102",
    "sg:province":"MN",
    "sg:tags":[
        "establishment"
    ],
    "wof:name":"251 Summit Condon Assoc",
    "wof:placetype":"venue"
},
  "geometry": {"coordinates":[-93.10940100000001,44.945639],"type":"Point"}
}