{
  "type": "Feature",
  "properties": {
    "addr:full":"1538 Spring Ave Worthington MN 56187",
    "addr:housenumber":"1538",
    "addr:postcode":"56187",
    "addr:street":"Spring Ave",
    "iso:country":"US",
    "sg:address":"1538 Spring Ave",
    "sg:city":"Worthington",
    "sg:classifiers":[
        {
            "category":"Education",
            "subcategory":"Special Training",
            "type":"Public Place"
        }
    ],
    "sg:phone":"+1 507 372 5432",
    "sg:postcode":"56187",
    "sg:province":"MN",
    "sg:tags":[
        "instruction",
        "driving"
    ],
    "wof:name":"Hollis Truck Driving Academy",
    "wof:placetype":"venue"
},
  "geometry": {"coordinates":[-95.578457,43.633578],"type":"Point"}
}