{
  "type": "Feature",
  "properties": {
    "addr:full":"533 N 3rd St La Crescent MN 55947",
    "addr:housenumber":"533",
    "addr:postcode":"55947",
    "addr:street":"N 3Rd St;Crescent",
    "iso:country":"US",
    "sg:address":"533 N 3rd St",
    "sg:city":"La Crescent",
    "sg:classifiers":[
        {
            "category":"Building & Trades",
            "subcategory":"Plumbing",
            "type":"Services"
        }
    ],
    "sg:phone":"+1 507 895 6181",
    "sg:postcode":"55947",
    "sg:province":"MN",
    "sg:tags":[
        "contractor"
    ],
    "wof:name":"Songer Plumbing & Excavating",
    "wof:placetype":"venue"
},
  "geometry": {"coordinates":[-91.309353,43.832079],"type":"Point"}
}