{
  "type": "Feature",
  "properties": {
    "addr:full":"15050 25th St NW Cokato MN 55321",
    "addr:housenumber":"15050",
    "addr:postcode":"55321",
    "addr:street":"25Th St Nw",
    "iso:country":"US",
    "sg:address":"15050 25th St NW",
    "sg:city":"Cokato",
    "sg:classifiers":[
        {
            "category":"Shopping",
            "type":"Retail Goods"
        }
    ],
    "sg:phone":"+1 320 286 6602",
    "sg:postcode":"55321",
    "sg:province":"MN",
    "sg:tags":[
        "merchandise"
    ],
    "wof:name":"Nato Shop",
    "wof:placetype":"venue"
},
  "geometry": {"coordinates":[-94.200791,45.189591],"type":"Point"}
}