{
  "type": "Feature",
  "properties": {
    "addr:full":"9391 Rosewood Ln N Osseo MN 55369",
    "addr:housenumber":"9391",
    "addr:postcode":"55369",
    "addr:street":"Rosewood Ln N",
    "iso:country":"US",
    "sg:address":"9391 Rosewood Ln N",
    "sg:city":"Osseo",
    "sg:classifiers":[
        {
            "category":"Wholesale",
            "subcategory":"Non-durable Goods",
            "type":"Manufacturing & Wholesale Goods"
        }
    ],
    "sg:phone":"+1 763 420 6915",
    "sg:postcode":"55369",
    "sg:province":"MN",
    "wof:name":"Johnson-Waters Marketing Inc",
    "wof:placetype":"venue"
},
  "geometry": {"coordinates":[-93.444191,45.124836],"type":"Point"}
}