{
  "type": "Feature",
  "properties": {
    "iso:country":"US",
    "sg:address":"12040 Riverwood Cir",
    "sg:city":"Burnsville",
    "sg:classifiers":[
        {
            "category":"Building & Trades",
            "subcategory":"Cleaning & Sanitation",
            "type":"Services"
        }
    ],
    "sg:phone":"+1 651 486 4886",
    "sg:postcode":"55337",
    "sg:province":"MN",
    "sg:tags":[
        "carpet"
    ],
    "wof:name":"Ritzy Clean",
    "wof:placetype":"venue"
},
  "geometry": {"coordinates":[-93.261837,44.788631],"type":"Point"}
}