{
  "type": "Feature",
  "properties": {
    "iso:country":"US",
    "sg:address":"3625 Colfax Ave S Apt 301",
    "sg:city":"Minneapolis",
    "sg:classifiers":[
        {
            "category":"Arts & Performance",
            "subcategory":"Theater",
            "type":"Entertainment"
        }
    ],
    "sg:phone":"+1 612 379 1952",
    "sg:postcode":"55409",
    "sg:province":"MN",
    "sg:tags":[
        "theatre"
    ],
    "sg:website":"http://www.theatreprorata.org",
    "wof:name":"Theatre Pro Rata",
    "wof:placetype":"venue"
},
  "geometry": {"coordinates":[-93.29203800000001,44.937236],"type":"Point"}
}