{
  "type": "Feature",
  "properties": {
    "addr:full":"965 Lawnview Ave Saint Paul MN 55126",
    "addr:housenumber":"965",
    "addr:postcode":"55126",
    "addr:street":"Lawnview Ave",
    "iso:country":"US",
    "sg:address":"965 Lawnview Ave",
    "sg:city":"Saint Paul",
    "sg:classifiers":[
        {
            "category":"Real Estate",
            "subcategory":"Real Estate Operator",
            "type":"Services"
        }
    ],
    "sg:phone":"+1 651 481 0101",
    "sg:postcode":"55126",
    "sg:province":"MN",
    "sg:tags":[
        "property",
        "lessor"
    ],
    "wof:name":"North Suburban Interim Home",
    "wof:placetype":"venue"
},
  "geometry": {"coordinates":[-93.141678,45.116998],"type":"Point"}
}