{
  "type": "Feature",
  "properties": {
    "addr:full":"3131 Excelsior Blvd Minneapolis MN 55416",
    "addr:housenumber":"3131",
    "addr:postcode":"55416",
    "addr:street":"Excelsior Blvd",
    "iso:country":"US",
    "sg:address":"3131 Excelsior Blvd",
    "sg:city":"Minneapolis",
    "sg:classifiers":[
        {
            "category":"Professional",
            "subcategory":"Management & Consulting",
            "type":"Services"
        }
    ],
    "sg:phone":"+1 763 504 7600",
    "sg:postcode":"55416",
    "sg:province":"MN",
    "wof:name":"Sonnesyn Associates",
    "wof:placetype":"venue"
},
  "geometry": {"coordinates":[-93.32080000000001,44.947434],"type":"Point"}
}