{
  "type": "Feature",
  "properties": {
    "addr:full":"11131 Washburn Ave S Minneapolis MN 55431",
    "addr:housenumber":"11131",
    "addr:postcode":"55431",
    "addr:street":"Washburn Ave S",
    "iso:country":"US",
    "sg:address":"11131 Washburn Ave S",
    "sg:city":"Minneapolis",
    "sg:classifiers":[
        {
            "category":"Building & Trades",
            "subcategory":"Landscaping Services",
            "type":"Services"
        },
        {
            "category":"Utilities",
            "subcategory":"Refuse",
            "type":"Services"
        },
        {
            "category":"Utilities",
            "subcategory":"Recycling",
            "type":"Services"
        },
        {
            "category":"Professional",
            "subcategory":"Printing & Photocopies",
            "type":"Services"
        },
        {
            "category":"Wholesale",
            "subcategory":"Photographic Equipment",
            "type":"Manufacturing & Wholesale Goods"
        }
    ],
    "sg:phone":"+1 612 598 2276",
    "sg:postcode":"55431",
    "sg:province":"MN",
    "sg:tags":[
        "excavating",
        "trash",
        "container",
        "garbage",
        "services-commercial",
        "hauling",
        "collection",
        "removal",
        "rubbish",
        "contractor",
        "landscape"
    ],
    "sg:website":"http://www.firstimpressionshd.com",
    "wof:name":"First Impressions Home Detailing",
    "wof:placetype":"venue"
},
  "geometry": {"coordinates":[-93.304981,44.860809],"type":"Point"}
}