{
  "type": "Feature",
  "properties": {
    "iso:country":"US",
    "sg:address":"201 E Nicollet Blvd",
    "sg:city":"Burnsville",
    "sg:classifiers":[
        {
            "category":"Professional",
            "subcategory":"Management & Consulting",
            "type":"Services"
        }
    ],
    "sg:phone":"+1 952 892 2055",
    "sg:postcode":"55337",
    "sg:province":"MN",
    "sg:tags":[
        "hospital",
        "health",
        "general"
    ],
    "wof:name":"Fairview Ridges Hospital",
    "wof:placetype":"venue"
},
  "geometry": {"coordinates":[-93.27741899999999,44.749504],"type":"Point"}
}