{
  "type": "Feature",
  "properties": {
    "addr:full":"420 Bean Ave Mora MN 55051",
    "addr:housenumber":"420",
    "addr:postcode":"55051",
    "addr:street":"Bean Ave",
    "iso:country":"US",
    "sg:address":"420 Bean Ave",
    "sg:city":"Mora",
    "sg:classifiers":[
        {
            "category":"Real Estate",
            "subcategory":"Real Estate Operator",
            "type":"Services"
        }
    ],
    "sg:phone":"+1 320 679 4789",
    "sg:postcode":"55051",
    "sg:province":"MN",
    "sg:tags":[
        "apartment"
    ],
    "wof:name":"Pine Crest Manor",
    "wof:placetype":"venue"
},
  "geometry": {"coordinates":[-93.30424600000001,45.873387],"type":"Point"}
}