{
  "type": "Feature",
  "properties": {
    "addr:full":"1152 Bush Ave St Paul MN 55106",
    "addr:housenumber":"1152",
    "addr:postcode":"55106",
    "addr:street":"Bush Ave",
    "iso:country":"US",
    "sg:address":"1152 Bush Ave",
    "sg:city":"St Paul",
    "sg:classifiers":[
        {
            "category":"Professional",
            "type":"Services"
        }
    ],
    "sg:phone":"+1 651 772 2098",
    "sg:postcode":"55106",
    "sg:province":"MN",
    "sg:tags":[
        "establishment"
    ],
    "wof:name":"Aseb",
    "wof:placetype":"venue"
},
  "geometry": {"coordinates":[-93.05176899999999,44.96481],"type":"Point"}
}