{
  "type": "Feature",
  "properties": {
    "addr:full":"27583 280th Ave Underwood MN 56586",
    "addr:housenumber":"27583",
    "addr:postcode":"56586",
    "addr:street":"280Th Ave",
    "iso:country":"US",
    "sg:address":"27583 280th Ave",
    "sg:city":"Underwood",
    "sg:phone":"+1 218 736 5004",
    "sg:postcode":"56586",
    "sg:province":"MN",
    "sg:tags":[
        "farm",
        "wheat",
        "grain",
        "cash"
    ],
    "wof:name":"Johnson Ellard",
    "wof:placetype":"venue"
},
  "geometry": {"coordinates":[-95.905265,46.367925],"type":"Point"}
}