{
  "type": "Feature",
  "properties": {
    "iso:country":"US",
    "sg:address":"15785 Nightingale St NW",
    "sg:city":"Anoka",
    "sg:classifiers":[
        {
            "category":"Retail",
            "subcategory":"Auto Repair",
            "type":"Services"
        }
    ],
    "sg:phone":"+1 763 434 9148",
    "sg:postcode":"55304",
    "sg:province":"MN",
    "sg:tags":[
        "body"
    ],
    "wof:name":"Cardinals Auto Body",
    "wof:placetype":"venue"
},
  "geometry": {"coordinates":[-93.316079,45.256868],"type":"Point"}
}