{
  "type": "Feature",
  "properties": {
    "iso:country":"US",
    "sg:address":"3109 Louisiana Ave N",
    "sg:city":"Minneapolis",
    "sg:classifiers":[
        {
            "category":"Wholesale",
            "subcategory":"Machinery & Supplies",
            "type":"Manufacturing & Wholesale Goods"
        }
    ],
    "sg:phone":"+1 763 546 9500",
    "sg:postcode":"55427",
    "sg:province":"MN",
    "sg:tags":[
        "salon",
        "beauty"
    ],
    "sg:website":"www.nationalsalon.com",
    "wof:name":"Mikara Corp",
    "wof:placetype":"venue"
},
  "geometry": {"coordinates":[-93.3703,45.014528],"type":"Point"}
}