{
  "type": "Feature",
  "properties": {
    "iso:country":"US",
    "sg:address":"517 2nd St",
    "sg:city":"Morgan",
    "sg:classifiers":[
        {
            "category":"Manufacturing",
            "subcategory":"Printing",
            "type":"Manufacturing & Wholesale Goods"
        }
    ],
    "sg:phone":"+1 507 249 3130",
    "sg:postcode":"56266",
    "sg:province":"MN",
    "sg:tags":[
        "newspaper"
    ],
    "wof:name":"Morgan Messenger",
    "wof:placetype":"venue"
},
  "geometry": {"coordinates":[-94.92739,44.416494],"type":"Point"}
}