{
  "type": "Feature",
  "properties": {
    "iso:country":"US",
    "sg:address":"316 Chestnut St W",
    "sg:city":"Virginia",
    "sg:classifiers":[
        {
            "category":"Manufacturing",
            "subcategory":"Printing",
            "type":"Manufacturing & Wholesale Goods"
        }
    ],
    "sg:phone":"+1 218 741 2868",
    "sg:postcode":"55792",
    "sg:province":"MN",
    "sg:tags":[
        "mfg"
    ],
    "wof:name":"Making Memories Last",
    "wof:placetype":"venue"
},
  "geometry": {"coordinates":[-92.53505800000001,47.523098],"type":"Point"}
}