{
  "type": "Feature",
  "properties": {
    "addr:full":"719 9th St Howard Lake MN 55349",
    "addr:housenumber":"719",
    "addr:postcode":"55349",
    "addr:street":"9Th St",
    "iso:country":"US",
    "sg:address":"719 9th St",
    "sg:city":"Howard Lake",
    "sg:classifiers":[
        {
            "category":"Organizations",
            "subcategory":"Religious Organization",
            "type":"Services"
        }
    ],
    "sg:phone":"+1 320 543 2806",
    "sg:postcode":"55349",
    "sg:province":"MN",
    "sg:tags":[
        "church"
    ],
    "wof:name":"First Presbyterian Church",
    "wof:placetype":"venue"
},
  "geometry": {"coordinates":[-94.06904299999999,45.057683],"type":"Point"}
}