{
  "type": "Feature",
  "properties": {
    "addr:full":"610 W 28th St Minneapolis MN 55408",
    "addr:housenumber":"610",
    "addr:postcode":"55408",
    "addr:street":"W 28Th St",
    "iso:country":"US",
    "sg:address":"610 W 28th St",
    "sg:city":"Minneapolis",
    "sg:classifiers":[
        {
            "category":"Arts & Performance",
            "subcategory":"Theater",
            "type":"Entertainment"
        },
        {
            "category":"Shopping",
            "type":"Retail Goods"
        }
    ],
    "sg:phone":"+1 612 623 9180",
    "sg:postcode":"55408",
    "sg:province":"MN",
    "sg:tags":[
        "theatrical",
        "merchandise"
    ],
    "wof:name":"Youth Performance Company",
    "wof:placetype":"venue"
},
  "geometry": {"coordinates":[-93.287961,44.952021],"type":"Point"}
}