{
  "type": "Feature",
  "properties": {
    "iso:country":"US",
    "sg:address":"20426 State Hwy 15",
    "sg:city":"Hutchinson",
    "sg:classifiers":[
        {
            "category":"Farming",
            "subcategory":"Farm",
            "type":"Manufacturing & Wholesale Goods"
        }
    ],
    "sg:phone":"+1 320 587 6700",
    "sg:postcode":"55350",
    "sg:province":"MN",
    "sg:tags":[
        "crop",
        "general"
    ],
    "wof:name":"Nelson Warren",
    "wof:placetype":"venue"
},
  "geometry": {"coordinates":[-94.36767500000001,44.912525],"type":"Point"}
}