{
  "type": "Feature",
  "properties": {
    "addr:full":"4401 Grand Ave S Minneapolis MN 55419",
    "addr:housenumber":"4401",
    "addr:postcode":"55419",
    "addr:street":"Grand Ave S",
    "iso:country":"US",
    "sg:address":"4401 Grand Ave S",
    "sg:city":"Minneapolis",
    "sg:classifiers":[
        {
            "category":"Wholesale",
            "subcategory":"Books, Periodicals, & Newspapers",
            "type":"Manufacturing & Wholesale Goods"
        }
    ],
    "sg:phone":"+1 612 827 2074",
    "sg:postcode":"55419",
    "sg:province":"MN",
    "sg:tags":[
        "publisher",
        "book"
    ],
    "wof:name":"Little Transport Maps",
    "wof:placetype":"venue"
},
  "geometry": {"coordinates":[-93.28441599999999,44.923199],"type":"Point"}
}