{
  "type": "Feature",
  "properties": {
    "addr:full":"4000 Lexington Ave N St Paul MN 55126",
    "addr:housenumber":"4000",
    "addr:postcode":"55126",
    "addr:street":"Lexington Ave N",
    "iso:country":"US",
    "sg:address":"4000 Lexington Ave N",
    "sg:city":"St Paul",
    "sg:classifiers":[
        {
            "category":"Professional",
            "subcategory":"Accounting & Tax Preparation",
            "type":"Services"
        }
    ],
    "sg:phone":"+1 651 636 6468",
    "sg:postcode":"55126",
    "sg:province":"MN",
    "sg:tags":[
        "accountant"
    ],
    "sg:website":"www.wipfli.com",
    "wof:name":"Wipfli & Consultants",
    "wof:placetype":"venue"
},
  "geometry": {"coordinates":[-93.147227,45.065815],"type":"Point"}
}