{
  "type": "Feature",
  "properties": {
    "addr:full":"467 273rd Ave NW Isanti MN 55040",
    "addr:housenumber":"467",
    "addr:postcode":"55040",
    "addr:street":"273Rd Ave Nw Isanti",
    "iso:country":"US",
    "sg:address":"467 273rd Ave NW",
    "sg:city":"Isanti",
    "sg:classifiers":[
        {
            "category":"Organizations",
            "subcategory":"Community Association",
            "type":"Services"
        }
    ],
    "sg:phone":"+1 763 444 5532",
    "sg:postcode":"55040",
    "sg:province":"MN",
    "wof:name":"Family Motor Coach Association",
    "wof:placetype":"venue"
},
  "geometry": {"coordinates":[-93.275868,45.464079],"type":"Point"}
}