{
  "type": "Feature",
  "properties": {
    "addr:full":"315 7th Ave NE Perham MN 56573",
    "addr:housenumber":"315",
    "addr:postcode":"56573",
    "addr:street":"7Th Ave Ne",
    "iso:country":"US",
    "sg:address":"315 7th Ave NE",
    "sg:city":"Perham",
    "sg:classifiers":[
        {
            "category":"Retail",
            "subcategory":"Auto Rental",
            "type":"Services"
        }
    ],
    "sg:phone":"+1 218 346 7499",
    "sg:postcode":"56573",
    "sg:province":"MN",
    "sg:tags":[
        "truck"
    ],
    "wof:name":"Ryder System Inc",
    "wof:placetype":"venue"
},
  "geometry": {"coordinates":[-95.56048699999999,46.59341],"type":"Point"}
}