{
  "type": "Feature",
  "properties": {
    "iso:country":"US",
    "sg:address":"1828 Old W Main St",
    "sg:city":"Red Wing",
    "sg:classifiers":[
        {
            "category":"Professional",
            "type":"Services"
        }
    ],
    "sg:phone":"+1 651 388 3158",
    "sg:postcode":"55066",
    "sg:province":"MN",
    "wof:name":"Annabells",
    "wof:placetype":"venue"
},
  "geometry": {"coordinates":[-92.55294000000001,44.563303],"type":"Point"}
}