{
  "type": "Feature",
  "properties": {
    "addr:full":"1001 6th St S Hopkins MN 55343",
    "addr:housenumber":"1001",
    "addr:postcode":"55343",
    "addr:street":"6Th St S",
    "iso:country":"US",
    "sg:address":"1001 6th St S",
    "sg:city":"Hopkins",
    "sg:classifiers":[
        {
            "category":"Recreation",
            "type":"Entertainment"
        }
    ],
    "sg:phone":"+1 952 945 0031",
    "sg:postcode":"55343",
    "sg:province":"MN",
    "sg:tags":[
        "amusement"
    ],
    "wof:name":"Excalibur Motor Sports",
    "wof:placetype":"venue"
},
  "geometry": {"coordinates":[-93.414276,44.915285],"type":"Point"}
}