{
  "type": "Feature",
  "properties": {
    "iso:country":"US",
    "sg:address":"550 Hazel Ln",
    "sg:city":"Owatonna",
    "sg:classifiers":[
        {
            "category":"Shopping",
            "subcategory":"Hobbies, Toys, & Games",
            "type":"Retail Goods"
        }
    ],
    "sg:phone":"+1 507 451 5503",
    "sg:postcode":"55060",
    "sg:province":"MN",
    "wof:name":"Pair-A-Dice Games",
    "wof:placetype":"venue"
},
  "geometry": {"coordinates":[-93.212175,44.09626],"type":"Point"}
}