{
  "type": "Feature",
  "properties": {
    "addr:full":"5051 Highway 7 Minneapolis MN 55416",
    "addr:housenumber":"5051",
    "addr:postcode":"55416",
    "addr:street":"Highway 7",
    "iso:country":"US",
    "sg:address":"5051 Highway 7",
    "sg:city":"Minneapolis",
    "sg:classifiers":[
        {
            "category":"Wholesale",
            "subcategory":"Computers",
            "type":"Manufacturing & Wholesale Goods"
        }
    ],
    "sg:phone":"+1 952 836 2000",
    "sg:postcode":"55416",
    "sg:province":"MN",
    "wof:name":"Datasource Hagen",
    "wof:placetype":"venue"
},
  "geometry": {"coordinates":[-93.342201,44.945],"type":"Point"}
}