{
  "type": "Feature",
  "properties": {
    "addr:full":"6109 Sherman Cir Edina MN 55436",
    "addr:housenumber":"6109",
    "addr:postcode":"55436",
    "addr:street":"Sherman Cir",
    "iso:country":"US",
    "sg:address":"6109 Sherman Cir",
    "sg:city":"Edina",
    "sg:classifiers":[
        {
            "category":"Professional",
            "subcategory":"Management & Consulting",
            "type":"Services"
        }
    ],
    "sg:phone":"+1 952 925 2892",
    "sg:postcode":"55436",
    "sg:province":"MN",
    "sg:tags":[
        "counselor",
        "public",
        "relations"
    ],
    "sg:website":"www.brucato.com",
    "wof:name":"Brucato & Halliday Ltd",
    "wof:placetype":"venue"
},
  "geometry": {"coordinates":[-93.38000599999999,44.898017],"type":"Point"}
}