{
  "type": "Feature",
  "properties": {
    "iso:country":"US",
    "sg:address":"130 SW Cleveland Ave",
    "sg:city":"Mcintosh",
    "sg:classifiers":[
        {
            "category":"Shopping",
            "subcategory":"Used Merchandise",
            "type":"Retail Goods"
        }
    ],
    "sg:phone":"+1 218 563 3322",
    "sg:postcode":"56556",
    "sg:province":"MN",
    "sg:tags":[
        "antique"
    ],
    "wof:name":"Shop",
    "wof:placetype":"venue"
},
  "geometry": {"coordinates":[-95.887878,47.636666],"type":"Point"}
}