{
  "type": "Feature",
  "properties": {
    "addr:full":"3270 Bellaire Ave Saint Paul MN 55110",
    "addr:housenumber":"3270",
    "addr:postcode":"55110",
    "addr:street":"Bellaire Ave",
    "iso:country":"US",
    "sg:address":"3270 Bellaire Ave",
    "sg:city":"Saint Paul",
    "sg:classifiers":[
        {
            "category":"Building & Trades",
            "subcategory":"Construction",
            "type":"Services"
        }
    ],
    "sg:phone":"+1 651 773 8780",
    "sg:postcode":"55110",
    "sg:province":"MN",
    "sg:tags":[
        "residential"
    ],
    "wof:name":"Southwind Homes Corp",
    "wof:placetype":"venue"
},
  "geometry": {"coordinates":[-92.994888,45.0416],"type":"Point"}
}