{
  "type": "Feature",
  "properties": {
    "iso:country":"US",
    "sg:address":"2925 Dean Pkwy Ste 300",
    "sg:city":"Minneapolis",
    "sg:classifiers":[
        {
            "category":"Sports & Exercise",
            "subcategory":"Gym",
            "type":"Entertainment"
        }
    ],
    "sg:phone":"+1 612 927 0500",
    "sg:postcode":"55416",
    "sg:province":"MN",
    "sg:website":"www.calhounbc.com",
    "wof:name":"Calhoun Beach Club",
    "wof:placetype":"venue"
},
  "geometry": {"coordinates":[-93.334991,44.964444],"type":"Point"}
}