{
  "type": "Feature",
  "properties": {
    "addr:full":"30181 273rd St Pierz MN 56364",
    "addr:housenumber":"30181",
    "addr:postcode":"56364",
    "addr:street":"273Rd St",
    "iso:country":"US",
    "sg:address":"30181 273rd St",
    "sg:city":"Pierz",
    "sg:classifiers":[
        {
            "category":"Farming",
            "subcategory":"Livestock Farm",
            "type":"Manufacturing & Wholesale Goods"
        }
    ],
    "sg:phone":"+1 320 277 3860",
    "sg:postcode":"56364",
    "sg:province":"MN",
    "sg:tags":[
        "beef",
        "corn",
        "crop",
        "field",
        "cattle",
        "feedlot"
    ],
    "wof:name":"Allen Woitalla",
    "wof:placetype":"venue"
},
  "geometry": {"coordinates":[-94.03430400000001,46.156525],"type":"Point"}
}