{
  "type": "Feature",
  "properties": {
    "addr:full":"308 Ring Ave N Canby MN 56220",
    "addr:housenumber":"308",
    "addr:postcode":"56220",
    "addr:street":"Ring Ave N",
    "iso:country":"US",
    "sg:address":"308 Ring Ave N",
    "sg:city":"Canby",
    "sg:classifiers":[
        {
            "category":"Personal",
            "type":"Services"
        }
    ],
    "sg:phone":"+1 507 223 7772",
    "sg:postcode":"56220",
    "sg:province":"MN",
    "wof:name":"Maintenance By Mercer",
    "wof:placetype":"venue"
},
  "geometry": {"coordinates":[-96.275431,44.712938],"type":"Point"}
}