{
  "type": "Feature",
  "properties": {
    "iso:country":"US",
    "sg:address":"900 Apollo Rd",
    "sg:city":"Eagan",
    "sg:classifiers":[
        {
            "category":"Manufacturing",
            "subcategory":"Rubber & Plastics",
            "type":"Manufacturing & Wholesale Goods"
        }
    ],
    "sg:phone":"+1 651 229 5300",
    "sg:postcode":"55121",
    "sg:province":"MN",
    "sg:website":"www.plastics-inc.com",
    "wof:name":"A & E Products Group Inc",
    "wof:placetype":"venue"
},
  "geometry": {"coordinates":[-93.131489,44.845106],"type":"Point"}
}