{
  "type": "Feature",
  "properties": {
    "addr:full":"6600 France Ave S Minneapolis MN 55435",
    "addr:housenumber":"6600",
    "addr:postcode":"55435",
    "addr:street":"France Ave S",
    "iso:country":"US",
    "sg:address":"6600 France Ave S",
    "sg:city":"Minneapolis",
    "sg:classifiers":[
        {
            "category":"Shopping",
            "subcategory":"Baby Store",
            "type":"Retail Goods"
        }
    ],
    "sg:phone":"+1 952 920 9070",
    "sg:postcode":"55435",
    "sg:province":"MN",
    "sg:tags":[
        "children's",
        "infant",
        "wear"
    ],
    "wof:name":"Hot Mama",
    "wof:placetype":"venue"
},
  "geometry": {"coordinates":[-93.329048,44.88282],"type":"Point"}
}