{
  "type": "Feature",
  "properties": {
    "iso:country":"US",
    "sg:address":"43370 541st Ave",
    "sg:city":"Courtland",
    "sg:phone":"+1 507 359 2566",
    "sg:postcode":"56021",
    "sg:province":"MN",
    "sg:tags":[
        "farm",
        "corn",
        "soybean"
    ],
    "wof:name":"Harmening Roman",
    "wof:placetype":"venue"
},
  "geometry": {"coordinates":[-94.351964,44.318732],"type":"Point"}
}