{
  "type": "Feature",
  "properties": {
    "iso:country":"US",
    "sg:address":"5600 Xylon Ave N",
    "sg:city":"New Hope",
    "sg:classifiers":[
        {
            "category":"Real Estate",
            "subcategory":"Real Estate Operator",
            "type":"Services"
        }
    ],
    "sg:phone":"+1 763 535 6497",
    "sg:postcode":"55428",
    "sg:province":"MN",
    "sg:tags":[
        "apartment"
    ],
    "wof:name":"New Hope Place Apartments",
    "wof:placetype":"venue"
},
  "geometry": {"coordinates":[-93.38623699999999,45.056805],"type":"Point"}
}