{
  "type": "Feature",
  "properties": {
    "addr:full":"9994 292nd St Chisago City MN 55013",
    "addr:housenumber":"9994",
    "addr:postcode":"55013",
    "addr:street":"292Nd St",
    "iso:country":"US",
    "sg:address":"9994 292nd St",
    "sg:city":"Chisago City",
    "sg:classifiers":[
        {
            "category":"Utilities",
            "subcategory":"Refuse",
            "type":"Services"
        }
    ],
    "sg:phone":"+1 651 257 6316",
    "sg:postcode":"55013",
    "sg:province":"MN",
    "sg:tags":[
        "garbage",
        "collection"
    ],
    "wof:name":"Croix Valley Pick-Up",
    "wof:placetype":"venue"
},
  "geometry": {"coordinates":[-92.90466000000001,45.371656],"type":"Point"}
}