{
  "type": "Feature",
  "properties": {
    "addr:full":"3156 50th St NE Buffalo MN 55313",
    "addr:housenumber":"3156",
    "addr:postcode":"55313",
    "addr:street":"50Th St Ne",
    "iso:country":"US",
    "sg:address":"3156 50th St NE",
    "sg:city":"Buffalo",
    "sg:classifiers":[
        {
            "category":"Building & Trades",
            "subcategory":"Construction",
            "type":"Services"
        }
    ],
    "sg:phone":"+1 763 682 9275",
    "sg:postcode":"55313",
    "sg:province":"MN",
    "sg:tags":[
        "concrete",
        "contractor"
    ],
    "wof:name":"A C Carr Construction Inc",
    "wof:placetype":"venue"
},
  "geometry": {"coordinates":[-93.819768,45.222931],"type":"Point"}
}