{
  "type": "Feature",
  "properties": {
    "iso:country":"US",
    "sg:address":"3732 W 2nd St",
    "sg:city":"Duluth",
    "sg:classifiers":[
        {
            "category":"Professional",
            "subcategory":"Advertising",
            "type":"Services"
        }
    ],
    "sg:phone":"+1 218 624 7072",
    "sg:postcode":"55807",
    "sg:province":"MN",
    "sg:tags":[
        "outdoor",
        "spec",
        "mfg"
    ],
    "wof:name":"Anderson Signs",
    "wof:placetype":"venue"
},
  "geometry": {"coordinates":[-92.148814,46.751871],"type":"Point"}
}