{
  "type": "Feature",
  "properties": {
    "addr:full":"10639 Hwy 71 NE Spicer MN 56288",
    "addr:housenumber":"10639",
    "addr:postcode":"56288",
    "addr:street":"Hwy 71 Ne",
    "iso:country":"US",
    "sg:address":"10639 Hwy 71 NE",
    "sg:city":"Spicer",
    "sg:classifiers":[
        {
            "category":"Organizations",
            "subcategory":"Religious Organization",
            "type":"Services"
        }
    ],
    "sg:phone":"+1 320 796 2031",
    "sg:postcode":"56288",
    "sg:province":"MN",
    "wof:name":"Lakeside Assembly",
    "wof:placetype":"venue"
},
  "geometry": {"coordinates":[-95.00114000000001,45.21611],"type":"Point"}
}