{
  "type": "Feature",
  "properties": {
    "iso:country":"US",
    "sg:address":"8241 Irving Ave N",
    "sg:city":"Minneapolis",
    "sg:classifiers":[
        {
            "category":"Wholesale",
            "subcategory":"Machinery & Supplies",
            "type":"Manufacturing & Wholesale Goods"
        }
    ],
    "sg:phone":"+1 763 566 0663",
    "sg:postcode":"55444",
    "sg:province":"MN",
    "sg:tags":[
        "equipment",
        "establishment"
    ],
    "wof:name":"Shadowhawk Industries Inc",
    "wof:placetype":"venue"
},
  "geometry": {"coordinates":[-93.302583,45.105279],"type":"Point"}
}