{
  "type": "Feature",
  "properties": {
    "addr:full":"4418 Haines Rd Duluth MN 55811",
    "addr:housenumber":"4418",
    "addr:postcode":"55811",
    "addr:street":"Haines Rd",
    "iso:country":"US",
    "sg:address":"4418 Haines Rd",
    "sg:city":"Duluth",
    "sg:classifiers":[
        {
            "category":"Shopping",
            "type":"Retail Goods"
        }
    ],
    "sg:phone":"+1 218 722 3420",
    "sg:postcode":"55811",
    "sg:province":"MN",
    "sg:tags":[
        "equipment",
        "medical",
        "supply"
    ],
    "wof:name":"Midwest Medical Eqp & Sups",
    "wof:placetype":"venue"
},
  "geometry": {"coordinates":[-92.174712,46.831614],"type":"Point"}
}