{
  "type": "Feature",
  "properties": {
    "iso:country":"US",
    "sg:address":"3445 116th Ln NW",
    "sg:city":"Minneapolis",
    "sg:classifiers":[
        {
            "category":"Retail",
            "subcategory":"Auto Repair",
            "type":"Services"
        }
    ],
    "sg:phone":"+1 763 443 8612",
    "sg:postcode":"55433",
    "sg:province":"MN",
    "sg:tags":[
        "general"
    ],
    "wof:name":"Auto Art",
    "wof:placetype":"venue"
},
  "geometry": {"coordinates":[-93.35468,45.182634],"type":"Point"}
}