{
  "type": "Feature",
  "properties": {
    "addr:full":"12126 Unity Cir NW Coon Rapids MN 55448",
    "addr:housenumber":"12126",
    "addr:postcode":"55448",
    "addr:street":"Unity Cir Nw",
    "iso:country":"US",
    "sg:address":"12126 Unity Cir NW",
    "sg:city":"Coon Rapids",
    "sg:classifiers":[
        {
            "category":"Sports & Exercise",
            "subcategory":"Gym",
            "type":"Entertainment"
        }
    ],
    "sg:phone":"+1 763 754 9722",
    "sg:postcode":"55448",
    "sg:province":"MN",
    "sg:tags":[
        "club",
        "health",
        "studio",
        "gymnasium"
    ],
    "wof:name":"Life Time Fitness",
    "wof:placetype":"venue"
},
  "geometry": {"coordinates":[-93.29343299999999,45.190526],"type":"Point"}
}