{
  "type": "Feature",
  "properties": {
    "iso:country":"US",
    "sg:address":"149 Norway Dr N",
    "sg:city":"Baxter",
    "sg:classifiers":[
        {
            "category":"Home & Garden",
            "subcategory":"Home Furnishings",
            "type":"Retail Goods"
        }
    ],
    "sg:phone":"+1 218 828 3087",
    "sg:postcode":"56425",
    "sg:province":"MN",
    "sg:tags":[
        "quilting"
    ],
    "wof:name":"Tangled Threads",
    "wof:placetype":"venue"
},
  "geometry": {"coordinates":[-94.30601,46.342687],"type":"Point"}
}