{
  "type": "Feature",
  "properties": {
    "addr:full":"2041 Roe Crest Dr North Mankato MN 56003",
    "addr:housenumber":"2041",
    "addr:postcode":"56003",
    "addr:street":"Roe Crest Dr North",
    "iso:country":"US",
    "sg:address":"2041 Roe Crest Dr",
    "sg:city":"North Mankato",
    "sg:classifiers":[
        {
            "category":"Manufacturing",
            "subcategory":"Printing",
            "type":"Manufacturing & Wholesale Goods"
        }
    ],
    "sg:phone":"+1 507 625 4302",
    "sg:postcode":"56003",
    "sg:province":"MN",
    "sg:tags":[
        "broker"
    ],
    "wof:name":"Burnell Co",
    "wof:placetype":"venue"
},
  "geometry": {"coordinates":[-94.038094,44.171078],"type":"Point"}
}