{
  "type": "Feature",
  "properties": {
    "addr:full":"10 Rosedale Center #305 Roseville MN 55113",
    "addr:housenumber":"10",
    "addr:postcode":"55113",
    "addr:street":"Rosedale Center # 305",
    "iso:country":"US",
    "sg:address":"10 Rosedale Center #305",
    "sg:city":"Roseville",
    "sg:classifiers":[
        {
            "category":"Shopping",
            "type":"Retail Goods"
        }
    ],
    "sg:phone":"+1 651 633 1461",
    "sg:postcode":"55113",
    "sg:province":"MN",
    "sg:website":"www.goldyslockerroom.com/",
    "wof:name":"Goldy's Locker Room",
    "wof:placetype":"venue"
},
  "geometry": {"coordinates":[-93.17610999999999,45.013184],"type":"Point"}
}