{
  "type": "Feature",
  "properties": {
    "iso:country":"US",
    "sg:address":"2400 S Broadway St",
    "sg:city":"New Ulm",
    "sg:classifiers":[
        {
            "category":"Retail",
            "subcategory":"Portrait Studio",
            "type":"Services"
        }
    ],
    "sg:phone":"+1 507 359 5455",
    "sg:postcode":"56073",
    "sg:province":"MN",
    "sg:tags":[
        "photo"
    ],
    "wof:name":"Inphoto",
    "wof:placetype":"venue"
},
  "geometry": {"coordinates":[-94.43662399999999,44.287635],"type":"Point"}
}