{
  "type": "Feature",
  "properties": {
    "iso:country":"US",
    "sg:address":"29777 Palm Ave",
    "sg:city":"Bigelow",
    "sg:classifiers":[
        {
            "category":"Farming",
            "subcategory":"Dairy Farm",
            "type":"Manufacturing & Wholesale Goods"
        }
    ],
    "sg:phone":"+1 507 372 4396",
    "sg:postcode":"56187",
    "sg:province":"MN",
    "wof:name":"Douglas Buntjer Dairy",
    "wof:placetype":"venue"
},
  "geometry": {"coordinates":[-95.633684,43.560833],"type":"Point"}
}