{
  "type": "Feature",
  "properties": {
    "addr:full":"34 Main St N Hutchinson MN 55350",
    "addr:housenumber":"34",
    "addr:postcode":"55350",
    "addr:street":"Main St N",
    "iso:country":"US",
    "sg:address":"34 Main St N",
    "sg:city":"Hutchinson",
    "sg:classifiers":[
        {
            "category":"Personal",
            "subcategory":"Barber",
            "type":"Services"
        }
    ],
    "sg:phone":"+1 320 587 3995",
    "sg:postcode":"55350",
    "sg:province":"MN",
    "wof:name":"Mark's On The Park",
    "wof:placetype":"venue"
},
  "geometry": {"coordinates":[-94.369399,44.893036],"type":"Point"}
}