{
  "type": "Feature",
  "properties": {
    "addr:full":"13 Riverside Cmn E Northfield MN 55057",
    "addr:housenumber":"13",
    "addr:postcode":"55057",
    "addr:street":"Riverside;E",
    "iso:country":"US",
    "sg:address":"13 Riverside Cmn E",
    "sg:city":"Northfield",
    "sg:classifiers":[
        {
            "category":"Insurance",
            "subcategory":"Life Insurance",
            "type":"Services"
        }
    ],
    "sg:phone":"+1 507 645 4483",
    "sg:postcode":"55057",
    "sg:province":"MN",
    "sg:tags":[
        "disability"
    ],
    "wof:name":"Herreid Agency",
    "wof:placetype":"venue"
},
  "geometry": {"coordinates":[-93.160681,44.456914],"type":"Point"}
}