{
  "type": "Feature",
  "properties": {
    "addr:full":"2 E Center Ave Mcgregor MN 55760",
    "addr:housenumber":"2",
    "addr:postcode":"55760",
    "addr:street":"Center Ave",
    "iso:country":"US",
    "sg:address":"2 E Center Ave",
    "sg:city":"Mcgregor",
    "sg:classifiers":[
        {
            "category":"Health Services",
            "subcategory":"Clinic",
            "type":"Services"
        },
        {
            "category":"Health Services",
            "subcategory":"Health Practitioner",
            "type":"Services"
        },
        {
            "category":"Community Center",
            "type":"Public Place"
        },
        {
            "category":"Health Services",
            "subcategory":"Hospital",
            "type":"Services"
        }
    ],
    "sg:phone":"+1 218 768 4011",
    "sg:postcode":"55760",
    "sg:province":"MN",
    "sg:tags":[
        "medical",
        "addiction-information",
        "therapist",
        "therapy",
        "treatment",
        "gambling",
        "physical"
    ],
    "sg:website":"http://www.riverwoodhealthcare.com",
    "wof:name":"Riverwood Healthcare Center",
    "wof:placetype":"venue"
},
  "geometry": {"coordinates":[-93.30761,46.6068],"type":"Point"}
}