{
  "type": "Feature",
  "properties": {
    "addr:full":"970 Prairie Center Dr Eden Prairie MN 55344",
    "addr:housenumber":"970",
    "addr:postcode":"55344",
    "addr:street":"Prairie Center Dr",
    "iso:country":"US",
    "sg:address":"970 Prairie Center Dr",
    "sg:city":"Eden Prairie",
    "sg:classifiers":[
        {
            "category":"Food & Beverages",
            "subcategory":"Groceries & Convenience Stores",
            "type":"Retail Goods"
        }
    ],
    "sg:phone":"+1 952 934 6595",
    "sg:postcode":"55344",
    "sg:province":"MN",
    "sg:tags":[
        "grocer"
    ],
    "wof:name":"Rainbow Foods 48",
    "wof:placetype":"venue"
},
  "geometry": {"coordinates":[-93.443405,44.866082],"type":"Point"}
}