{
  "type": "Feature",
  "properties": {
    "iso:country":"US",
    "sg:address":"2159 Nokomis Ave",
    "sg:city":"St Paul",
    "sg:classifiers":[
        {
            "category":"Retail",
            "subcategory":"Auto Repair",
            "type":"Services"
        }
    ],
    "sg:phone":"+1 651 248 1933",
    "sg:postcode":"55119",
    "sg:province":"MN",
    "sg:tags":[
        "wrecker"
    ],
    "wof:name":"J & J Towing",
    "wof:placetype":"venue"
},
  "geometry": {"coordinates":[-93.011706,44.968442],"type":"Point"}
}