{
  "type": "Feature",
  "properties": {
    "iso:country":"US",
    "sg:address":"190 2nd Ave SW",
    "sg:city":"Milaca",
    "sg:classifiers":[
        {
            "category":"Banks & Credit Unions",
            "subcategory":"Investment Brokerage",
            "type":"Services"
        }
    ],
    "sg:phone":"+1 320 983 1331",
    "sg:postcode":"56353",
    "sg:province":"MN",
    "sg:tags":[
        "consultant",
        "planning",
        "financial"
    ],
    "wof:name":"American Express Financial Adv",
    "wof:placetype":"venue"
},
  "geometry": {"coordinates":[-93.65288200000001,45.753692],"type":"Point"}
}