{
  "type": "Feature",
  "properties": {
    "addr:full":"735 W Main St Perham MN 56573",
    "addr:housenumber":"735",
    "addr:postcode":"56573",
    "addr:street":"W Main St",
    "iso:country":"US",
    "sg:address":"735 W Main St",
    "sg:city":"Perham",
    "sg:classifiers":[
        {
            "category":"Retail",
            "subcategory":"Car Wash",
            "type":"Services"
        }
    ],
    "sg:phone":"+1 218 346 6558",
    "sg:postcode":"56573",
    "sg:province":"MN",
    "sg:tags":[
        "polishing",
        "washing"
    ],
    "wof:name":"Ken's Car Cleaning",
    "wof:placetype":"venue"
},
  "geometry": {"coordinates":[-95.58079600000001,46.598588],"type":"Point"}
}