{
  "type": "Feature",
  "properties": {
    "addr:full":"101 E Church St Minneota MN 56264",
    "addr:housenumber":"101",
    "addr:postcode":"56264",
    "addr:street":"E Church St",
    "iso:country":"US",
    "sg:address":"101 E Church St",
    "sg:city":"Minneota",
    "sg:classifiers":[
        {
            "category":"Restaurant",
            "type":"Food & Drink"
        }
    ],
    "sg:phone":"+1 507 224 2228",
    "sg:postcode":"56264",
    "sg:province":"MN",
    "sg:tags":[
        "eating"
    ],
    "wof:name":"Other Place",
    "wof:placetype":"venue"
},
  "geometry": {"coordinates":[-96.04711399999999,44.717378],"type":"Point"}
}