{
  "type": "Feature",
  "properties": {
    "iso:country":"US",
    "sg:address":"17477 Center Rd NE",
    "sg:city":"Miltona",
    "sg:phone":"+1 218 943 4451",
    "sg:postcode":"56354",
    "sg:province":"MN",
    "sg:tags":[
        "farm",
        "corn"
    ],
    "wof:name":"Tim Zunker Farm",
    "wof:placetype":"venue"
},
  "geometry": {"coordinates":[-95.333662,46.073025],"type":"Point"}
}