{
  "type": "Feature",
  "properties": {
    "addr:full":"12132 Shieldsville Blvd Lonsdale MN 55046",
    "addr:housenumber":"12132",
    "addr:postcode":"55046",
    "addr:street":"Shieldsville Blvd",
    "iso:country":"US",
    "sg:address":"12132 Shieldsville Blvd",
    "sg:city":"Lonsdale",
    "sg:classifiers":[
        {
            "category":"Wholesale",
            "subcategory":"Hardware",
            "type":"Manufacturing & Wholesale Goods"
        }
    ],
    "sg:phone":"+1 507 744 5456",
    "sg:postcode":"55046",
    "sg:province":"MN",
    "sg:tags":[
        "plumbing"
    ],
    "wof:name":"Kaderlik Water Conditioning",
    "wof:placetype":"venue"
},
  "geometry": {"coordinates":[-93.44884999999999,44.411866],"type":"Point"}
}