{
  "type": "Feature",
  "properties": {
    "addr:full":"2570 Forest St Saint Paul MN 55109",
    "addr:housenumber":"2570",
    "addr:postcode":"55109",
    "addr:street":"Forest St",
    "iso:country":"US",
    "sg:address":"2570 Forest St",
    "sg:city":"Saint Paul",
    "sg:classifiers":[
        {
            "category":"Professional",
            "type":"Services"
        }
    ],
    "sg:phone":"+1 651 482 7665",
    "sg:postcode":"55109",
    "sg:province":"MN",
    "wof:name":"Smith Oltp Systems Inc",
    "wof:placetype":"venue"
},
  "geometry": {"coordinates":[-93.06083599999999,45.018292],"type":"Point"}
}