{
  "type": "Feature",
  "properties": {
    "addr:full":"206 5th Ave NW Kasson MN 55944",
    "addr:housenumber":"206",
    "addr:postcode":"55944",
    "addr:street":"5Th Ave Nw",
    "iso:country":"US",
    "sg:address":"206 5th Ave NW",
    "sg:city":"Kasson",
    "sg:classifiers":[
        {
            "category":"Banks & Credit Unions",
            "subcategory":"Investment Brokerage",
            "type":"Services"
        }
    ],
    "sg:phone":"+1 507 634 7270",
    "sg:postcode":"55944",
    "sg:province":"MN",
    "sg:tags":[
        "advisory",
        "financial"
    ],
    "wof:name":"Thompson Insurance",
    "wof:placetype":"venue"
},
  "geometry": {"coordinates":[-92.75441499999999,44.032189],"type":"Point"}
}