{
  "type": "Feature",
  "properties": {
    "iso:country":"US",
    "sg:address":"4554 Nicollet Ave",
    "sg:city":"Minneapolis",
    "sg:classifiers":[
        {
            "category":"Food & Beverages",
            "subcategory":"Bakery",
            "type":"Retail Goods"
        }
    ],
    "sg:phone":"+1 612 822 5401",
    "sg:postcode":"55419",
    "sg:province":"MN",
    "wof:name":"Brueggers Bagels",
    "wof:placetype":"venue"
},
  "geometry": {"coordinates":[-93.278018,44.920636],"type":"Point"}
}