{
  "type": "Feature",
  "properties": {
    "iso:country":"US",
    "sg:address":"1755 Co Rd 61",
    "sg:city":"Carlton",
    "sg:classifiers":[
        {
            "category":"Utilities",
            "subcategory":"Natural Gas",
            "type":"Services"
        }
    ],
    "sg:phone":"+1 218 384 3506",
    "sg:postcode":"55718",
    "sg:province":"MN",
    "sg:tags":[
        "distribution"
    ],
    "wof:name":"Great Lakes Gas Transmission",
    "wof:placetype":"venue"
},
  "geometry": {"coordinates":[-92.49381200000001,46.649783],"type":"Point"}
}