{
  "type": "Feature",
  "properties": {
    "addr:full":"821 12th Ave S Saint Cloud MN 56301",
    "addr:housenumber":"821",
    "addr:postcode":"56301",
    "addr:street":"12Th Ave S",
    "iso:country":"US",
    "sg:address":"821 12th Ave S",
    "sg:city":"Saint Cloud",
    "sg:classifiers":[
        {
            "category":"Social Services",
            "subcategory":"Child Care",
            "type":"Services"
        }
    ],
    "sg:phone":"+1 320 251 5113",
    "sg:postcode":"56301",
    "sg:province":"MN",
    "sg:tags":[
        "daycare",
        "provider"
    ],
    "wof:name":"Tanya M Shorter",
    "wof:placetype":"venue"
},
  "geometry": {"coordinates":[-94.16478499999999,45.550662],"type":"Point"}
}