{
  "type": "Feature",
  "properties": {
    "addr:full":"418 41st St Chandler MN 56122",
    "addr:housenumber":"418",
    "addr:postcode":"56122",
    "addr:street":"41St St",
    "iso:country":"US",
    "sg:address":"418 41st St",
    "sg:city":"Chandler",
    "sg:classifiers":[
        {
            "category":"Farming",
            "subcategory":"Dairy Farm",
            "type":"Manufacturing & Wholesale Goods"
        }
    ],
    "sg:phone":"+1 507 677 2566",
    "sg:postcode":"56122",
    "sg:province":"MN",
    "wof:name":"Leonard Hulstein",
    "wof:placetype":"venue"
},
  "geometry": {"coordinates":[-95.98040899999999,43.90689],"type":"Point"}
}