{
  "type": "Feature",
  "properties": {
    "addr:full":"20260 141st Ave N Rogers MN 55374",
    "addr:housenumber":"20260",
    "addr:postcode":"55374",
    "addr:street":"141St Ave N",
    "iso:country":"US",
    "sg:address":"20260 141st Ave N",
    "sg:city":"Rogers",
    "sg:classifiers":[
        {
            "category":"Farming",
            "subcategory":"Dairy Farm",
            "type":"Manufacturing & Wholesale Goods"
        }
    ],
    "sg:phone":"+1 763 428 2444",
    "sg:postcode":"55374",
    "sg:province":"MN",
    "wof:name":"Dehn Farms",
    "wof:placetype":"venue"
},
  "geometry": {"coordinates":[-93.5363,45.210192],"type":"Point"}
}