{
  "type": "Feature",
  "properties": {
    "addr:full":"7316 Aspen Ln N Minneapolis MN 55428",
    "addr:housenumber":"7316",
    "addr:postcode":"55428",
    "addr:street":"Aspen Ln N",
    "iso:country":"US",
    "sg:address":"7316 Aspen Ln N",
    "sg:city":"Minneapolis",
    "sg:classifiers":[
        {
            "category":"Wholesale",
            "subcategory":"Medical Equipment & Supplies",
            "type":"Manufacturing & Wholesale Goods"
        }
    ],
    "sg:phone":"+1 763 536 6960",
    "sg:postcode":"55428",
    "sg:province":"MN",
    "sg:tags":[
        "identification"
    ],
    "sg:website":"http://www.varitronicsystems.com",
    "wof:name":"Brady Worldwide, Inc.",
    "wof:placetype":"venue"
},
  "geometry": {"coordinates":[-93.389754,45.087617],"type":"Point"}
}