{
  "type": "Feature",
  "properties": {
    "iso:country":"US",
    "sg:address":"437 Wabasha St N",
    "sg:city":"Saint Paul",
    "sg:classifiers":[
        {
            "category":"Food & Beverages",
            "subcategory":"Groceries & Convenience Stores",
            "type":"Retail Goods"
        }
    ],
    "sg:phone":"+1 651 224 4828",
    "sg:postcode":"55102",
    "sg:province":"MN",
    "wof:name":"Rivertown",
    "wof:placetype":"venue"
},
  "geometry": {"coordinates":[-93.09681999999999,44.947931],"type":"Point"}
}