{
  "type": "Feature",
  "properties": {
    "addr:full":"840 W 65th St Minneapolis MN 55423",
    "addr:housenumber":"840",
    "addr:postcode":"55423",
    "addr:street":"W 65Th St",
    "iso:country":"US",
    "sg:address":"840 W 65th St",
    "sg:city":"Minneapolis",
    "sg:classifiers":[
        {
            "category":"Professional",
            "subcategory":"Secretarial Services",
            "type":"Services"
        }
    ],
    "sg:phone":"+1 612 869 1776",
    "sg:postcode":"55423",
    "sg:province":"MN",
    "sg:tags":[
        "reporting",
        "resume"
    ],
    "wof:name":"Cheap Resume & Typing While Yo",
    "wof:placetype":"venue"
},
  "geometry": {"coordinates":[-93.28821499999999,44.884397],"type":"Point"}
}