{
  "type": "Feature",
  "properties": {
    "addr:full":"15608 N Eden Dr Eden Prairie MN 55346",
    "addr:housenumber":"15608",
    "addr:postcode":"55346",
    "addr:street":"N Eden Dr",
    "iso:country":"US",
    "sg:address":"15608 N Eden Dr",
    "sg:city":"Eden Prairie",
    "sg:classifiers":[
        {
            "category":"Social Services",
            "subcategory":"Child Care",
            "type":"Services"
        }
    ],
    "sg:phone":"+1 952 949 2263",
    "sg:postcode":"55346",
    "sg:province":"MN",
    "sg:tags":[
        "day"
    ],
    "wof:name":"Olsen Embroidery",
    "wof:placetype":"venue"
},
  "geometry": {"coordinates":[-93.476947,44.89056],"type":"Point"}
}