{
  "type": "Feature",
  "properties": {
    "addr:full":"12605 Creek View Ave Savage MN 55378",
    "addr:housenumber":"12605",
    "addr:postcode":"55378",
    "addr:street":"Creek View Ave",
    "iso:country":"US",
    "sg:address":"12605 Creek View Ave",
    "sg:city":"Savage",
    "sg:classifiers":[
        {
            "category":"Home & Garden",
            "subcategory":"Building Materials",
            "type":"Retail Goods"
        }
    ],
    "sg:phone":"+1 866 985 3170",
    "sg:postcode":"55378",
    "sg:province":"MN",
    "sg:tags":[
        "window",
        "skylight"
    ],
    "sg:website":"http://www.windowoutfitters.com",
    "wof:name":"Window Outfitters Inc",
    "wof:placetype":"venue"
},
  "geometry": {"coordinates":[-93.383067,44.773752],"type":"Point"}
}