{
  "type": "Feature",
  "properties": {
    "addr:full":"180 Larpenteur Ave W Saint Paul MN 55113",
    "addr:housenumber":"180",
    "addr:postcode":"55113",
    "addr:street":"Larpenteur Ave W",
    "iso:country":"US",
    "sg:address":"180 Larpenteur Ave W",
    "sg:city":"Saint Paul",
    "sg:classifiers":[
        {
            "category":"Building & Trades",
            "subcategory":"Cleaning & Sanitation",
            "type":"Services"
        }
    ],
    "sg:phone":"+1 612 840 8328",
    "sg:postcode":"55113",
    "sg:province":"MN",
    "sg:tags":[
        "supplier",
        "janitorial",
        "supply"
    ],
    "wof:name":"Witty Inventions Inc",
    "wof:placetype":"venue"
},
  "geometry": {"coordinates":[-93.107495,44.991783],"type":"Point"}
}