{
  "type": "Feature",
  "properties": {
    "iso:country":"US",
    "sg:address":"811 E Maple Ave",
    "sg:city":"Mora",
    "sg:classifiers":[
        {
            "category":"Manufacturing",
            "subcategory":"Watercraft",
            "type":"Manufacturing & Wholesale Goods"
        }
    ],
    "sg:phone":"+1 320 679 3811",
    "sg:postcode":"55051",
    "sg:province":"MN",
    "sg:tags":[
        "boat"
    ],
    "sg:website":"www.bluewateryacht.com",
    "wof:name":"Bluewater",
    "wof:placetype":"venue"
},
  "geometry": {"coordinates":[-93.283417,45.878705],"type":"Point"}
}