{
  "type": "Feature",
  "properties": {
    "addr:full":"19455 Kenwood Trl Lakeville MN 55044",
    "addr:housenumber":"19455",
    "addr:postcode":"55044",
    "addr:street":"Kenwood Trl",
    "iso:country":"US",
    "sg:address":"19455 Kenwood Trl",
    "sg:city":"Lakeville",
    "sg:classifiers":[
        {
            "category":"Education",
            "subcategory":"School",
            "type":"Public Place"
        }
    ],
    "sg:phone":"+1 952 469 7157",
    "sg:postcode":"55044",
    "sg:province":"MN",
    "sg:website":"www.ktjh.isd194.k12.mn.us",
    "wof:name":"Kenwood Trail Jr High School",
    "wof:placetype":"venue"
},
  "geometry": {"coordinates":[-93.268113,44.666605],"type":"Point"}
}