{
  "type": "Feature",
  "properties": {
    "iso:country":"US",
    "sg:address":"148 Broadway St W",
    "sg:city":"Monticello",
    "sg:classifiers":[
        {
            "category":"Shopping",
            "subcategory":"Jewelry",
            "type":"Retail Goods"
        }
    ],
    "sg:phone":"+1 763 295 3771",
    "sg:postcode":"55362",
    "sg:province":"MN",
    "sg:tags":[
        "jeweler"
    ],
    "sg:website":"www.lochjewelers.com",
    "wof:name":"Loch Jewelers",
    "wof:placetype":"venue"
},
  "geometry": {"coordinates":[-93.79509,45.305874],"type":"Point"}
}