{
  "type": "Feature",
  "properties": {
    "iso:country":"US",
    "sg:address":"3053 185th Ln NE",
    "sg:city":"Wyoming",
    "sg:classifiers":[
        {
            "category":"Building & Trades",
            "subcategory":"Construction",
            "type":"Services"
        }
    ],
    "sg:phone":"+1 763 242 9928",
    "sg:postcode":"55092",
    "sg:province":"MN",
    "sg:tags":[
        "residential"
    ],
    "wof:name":"Amme Carsten Construction",
    "wof:placetype":"venue"
},
  "geometry": {"coordinates":[-93.192764,45.305706],"type":"Point"}
}