{
  "type": "Feature",
  "properties": {
    "iso:country":"US",
    "sg:address":"107 S Chestnut St",
    "sg:city":"Ellsworth",
    "sg:classifiers":[
        {
            "category":"Retail",
            "subcategory":"Auto Repair",
            "type":"Services"
        }
    ],
    "sg:phone":"+1 507 967 2277",
    "sg:postcode":"56129",
    "sg:province":"MN",
    "sg:tags":[
        "body",
        "automobile",
        "painting"
    ],
    "wof:name":"Greg's",
    "wof:placetype":"venue"
},
  "geometry": {"coordinates":[-96.021128,43.519935],"type":"Point"}
}