{
  "type": "Feature",
  "properties": {
    "addr:full":"850 Freeport Ave NW Elk River MN 55330",
    "addr:housenumber":"850",
    "addr:postcode":"55330",
    "addr:street":"Freeport Ave Nw",
    "iso:country":"US",
    "sg:address":"850 Freeport Ave NW",
    "sg:city":"Elk River",
    "sg:classifiers":[
        {
            "category":"Restaurant",
            "type":"Food & Drink"
        }
    ],
    "sg:menulink":"http://www.allmenus.com/mn/elk-river/190831-burger-king/menu/",
    "sg:phone":"+1 763 441 6050",
    "sg:postcode":"55330",
    "sg:province":"MN",
    "sg:tags":[
        "burger",
        "american"
    ],
    "wof:name":"Burger King",
    "wof:placetype":"venue"
},
  "geometry": {"coordinates":[-93.560672,45.31107],"type":"Point"}
}