{
  "type": "Feature",
  "properties": {
    "addr:full":"617 Armstrong Blvd N St James MN 56081",
    "addr:housenumber":"617",
    "addr:postcode":"56081",
    "addr:street":"Armstrong Blvd N St",
    "iso:country":"US",
    "sg:address":"617 Armstrong Blvd N",
    "sg:city":"St James",
    "sg:classifiers":[
        {
            "category":"Organizations",
            "subcategory":"Religious Organization",
            "type":"Services"
        }
    ],
    "sg:phone":"+1 507 375 4002",
    "sg:postcode":"56081",
    "sg:province":"MN",
    "sg:tags":[
        "clergy"
    ],
    "wof:name":"Assembly Of God Parsonage",
    "wof:placetype":"venue"
},
  "geometry": {"coordinates":[-94.62978200000001,43.987101],"type":"Point"}
}