{
  "type": "Feature",
  "properties": {
    "addr:full":"7400 Metro Blvd Edina MN 55439",
    "addr:postcode":"7400;55439",
    "addr:street":"Metro Blvd",
    "iso:country":"US",
    "sg:address":"7400 Metro Blvd",
    "sg:city":"Edina",
    "sg:classifiers":[
        {
            "category":"Wholesale",
            "subcategory":"Drugs",
            "type":"Manufacturing & Wholesale Goods"
        }
    ],
    "sg:phone":"+1 952 835 6100",
    "sg:postcode":"55439",
    "sg:province":"MN",
    "sg:tags":[
        "pharmaceutical",
        "product"
    ],
    "wof:name":"Purdue Frederick Co",
    "wof:placetype":"venue"
},
  "geometry": {"coordinates":[-93.351145,44.868979],"type":"Point"}
}