{
  "type": "Feature",
  "properties": {
    "addr:full":"318 Main St Lakefield MN 56150",
    "addr:housenumber":"318",
    "addr:postcode":"56150",
    "addr:street":"Main St",
    "iso:country":"US",
    "sg:address":"318 Main St",
    "sg:city":"Lakefield",
    "sg:classifiers":[
        {
            "category":"Restaurant",
            "type":"Food & Drink"
        }
    ],
    "sg:phone":"+1 507 662 6772",
    "sg:postcode":"56150",
    "sg:province":"MN",
    "wof:name":"Squeeze Inn",
    "wof:placetype":"venue"
},
  "geometry": {"coordinates":[-95.17196300000001,43.67833],"type":"Point"}
}