{
  "type": "Feature",
  "properties": {
    "addr:full":"1919 75th Ave SE Saint Cloud MN 56304",
    "addr:housenumber":"1919",
    "addr:postcode":"56304",
    "addr:street":"75Th Ave Se",
    "iso:country":"US",
    "sg:address":"1919 75th Ave SE",
    "sg:city":"Saint Cloud",
    "sg:phone":"+1 320 252 1979",
    "sg:postcode":"56304",
    "sg:province":"MN",
    "sg:tags":[
        "farm",
        "corn",
        "cash",
        "crop",
        "field",
        "grain"
    ],
    "wof:name":"Larry L Brambrink",
    "wof:placetype":"venue"
},
  "geometry": {"coordinates":[-94.006888,45.541412],"type":"Point"}
}