{
  "type": "Feature",
  "properties": {
    "addr:full":"11768 205th St W Lakeville MN 55044",
    "addr:housenumber":"11768",
    "addr:postcode":"55044",
    "addr:street":"205Th St W",
    "iso:country":"US",
    "sg:address":"11768 205th St W",
    "sg:city":"Lakeville",
    "sg:classifiers":[
        {
            "category":"Building & Trades",
            "subcategory":"Landscaping Services",
            "type":"Services"
        }
    ],
    "sg:phone":"+1 952 469 2283",
    "sg:postcode":"55044",
    "sg:province":"MN",
    "wof:name":"Rnr Lawn Service Co",
    "wof:placetype":"venue"
},
  "geometry": {"coordinates":[-93.302209,44.652287],"type":"Point"}
}