{
  "type": "Feature",
  "properties": {
    "iso:country":"US",
    "sg:address":"1013 Ford Rd",
    "sg:city":"Hopkins",
    "sg:classifiers":[
        {
            "category":"Professional",
            "subcategory":"Management & Consulting",
            "type":"Services"
        }
    ],
    "sg:phone":"+1 952 544 0266",
    "sg:postcode":"55305",
    "sg:province":"MN",
    "sg:tags":[
        "promotion",
        "sales"
    ],
    "wof:name":"Buyers Choice",
    "wof:placetype":"venue"
},
  "geometry": {"coordinates":[-93.40548800000001,44.970653],"type":"Point"}
}