{
  "type": "Feature",
  "properties": {
    "addr:full":"3112 Lyndale Ave N Minneapolis MN 55411",
    "addr:housenumber":"3112",
    "addr:postcode":"55411",
    "addr:street":"Lyndale Ave N",
    "iso:country":"US",
    "sg:address":"3112 Lyndale Ave N",
    "sg:city":"Minneapolis",
    "sg:classifiers":[
        {
            "category":"Professional",
            "type":"Services"
        }
    ],
    "sg:phone":"+1 612 522 1201",
    "sg:postcode":"55411",
    "sg:province":"MN",
    "sg:tags":[
        "establishment"
    ],
    "wof:name":"Minnesota Hindu Dharmic Sabha",
    "wof:placetype":"venue"
},
  "geometry": {"coordinates":[-93.287935,45.01309],"type":"Point"}
}