{
  "type": "Feature",
  "properties": {
    "iso:country":"US",
    "sg:address":"317 S Cleveland Ave",
    "sg:city":"St Paul",
    "sg:classifiers":[
        {
            "category":"Professional",
            "subcategory":"Art Services",
            "type":"Services"
        }
    ],
    "sg:phone":"+1 651 690 0671",
    "sg:postcode":"55105",
    "sg:province":"MN",
    "sg:tags":[
        "graphic",
        "designer"
    ],
    "wof:name":"Jerry Stenback Graphic Design",
    "wof:placetype":"venue"
},
  "geometry": {"coordinates":[-93.187454,44.932123],"type":"Point"}
}