{
  "type": "Feature",
  "properties": {
    "addr:full":"3600 American Blvd W Ste 200 Minneapolis MN 55431",
    "addr:housenumber":"3600",
    "addr:postcode":"55431",
    "addr:street":"American Blvd W Ste 200",
    "iso:country":"US",
    "sg:address":"3600 American Blvd W Ste 200",
    "sg:city":"Minneapolis",
    "sg:classifiers":[
        {
            "category":"Banks & Credit Unions",
            "subcategory":"Financial Services",
            "type":"Services"
        }
    ],
    "sg:phone":"+1 952 896 3456",
    "sg:postcode":"55431",
    "sg:province":"MN",
    "sg:tags":[
        "sharing",
        "profit",
        "annuity",
        "retirement",
        "planning",
        "plan",
        "insurance",
        "pension"
    ],
    "wof:name":"L H Hendrickson/Bank Compnsatn",
    "wof:placetype":"venue"
},
  "geometry": {"coordinates":[-93.324878,44.857195],"type":"Point"}
}