{
  "type": "Feature",
  "properties": {
    "iso:country":"US",
    "sg:address":"5010 Cheshire Ln N",
    "sg:city":"Plymouth",
    "sg:classifiers":[
        {
            "category":"Shopping",
            "subcategory":"Computers & Home Electronics",
            "type":"Retail Goods"
        }
    ],
    "sg:phone":"+1 763 746 2490",
    "sg:postcode":"55446",
    "sg:province":"MN",
    "sg:tags":[
        "equipment",
        "dealer"
    ],
    "wof:name":"Benchmark New Horizon Computer",
    "wof:placetype":"venue"
},
  "geometry": {"coordinates":[-93.457544,45.045737],"type":"Point"}
}