{
  "type": "Feature",
  "properties": {
    "addr:full":"55 Main St Easton MN 56025",
    "addr:housenumber":"55",
    "addr:postcode":"56025",
    "addr:street":"Main St",
    "iso:country":"US",
    "sg:address":"55 Main St",
    "sg:city":"Easton",
    "sg:classifiers":[
        {
            "category":"Shopping",
            "subcategory":"Clothing, Apparel, & Fashions",
            "type":"Retail Goods"
        }
    ],
    "sg:phone":"+1 507 787 2211",
    "sg:postcode":"56025",
    "sg:province":"MN",
    "sg:tags":[
        "shop",
        "bridal"
    ],
    "wof:name":"Silhouette Inc",
    "wof:placetype":"venue"
},
  "geometry": {"coordinates":[-93.90117499999999,43.766483],"type":"Point"}
}