{
  "type": "Feature",
  "properties": {
    "iso:country":"US",
    "sg:address":"425 SE 11th St",
    "sg:city":"Grand Rapids",
    "sg:classifiers":[
        {
            "category":"Freight",
            "type":"Transportation"
        }
    ],
    "sg:phone":"+1 218 326 8520",
    "sg:postcode":"55744",
    "sg:province":"MN",
    "sg:tags":[
        "courier"
    ],
    "wof:name":"UPS",
    "wof:placetype":"venue"
},
  "geometry": {"coordinates":[-93.521716,47.219984],"type":"Point"}
}