{
  "type": "Feature",
  "properties": {
    "addr:full":"229 Willow St Faribault MN 55021",
    "addr:housenumber":"229",
    "addr:postcode":"55021",
    "addr:street":"Willow St",
    "iso:country":"US",
    "sg:address":"229 Willow St",
    "sg:city":"Faribault",
    "sg:classifiers":[
        {
            "category":"Retail",
            "subcategory":"Auto Repair",
            "type":"Services"
        }
    ],
    "sg:phone":"+1 507 334 8108",
    "sg:postcode":"55021",
    "sg:province":"MN",
    "sg:tags":[
        "general"
    ],
    "wof:name":"Truax Service",
    "wof:placetype":"venue"
},
  "geometry": {"coordinates":[-93.266659,44.28888],"type":"Point"}
}