{
  "type": "Feature",
  "properties": {
    "iso:country":"US",
    "sg:address":"32580 Nottingham Ct",
    "sg:city":"Lindstrom",
    "sg:classifiers":[
        {
            "category":"Professional",
            "subcategory":"Art Services",
            "type":"Services"
        }
    ],
    "sg:phone":"+1 651 257 5184",
    "sg:postcode":"55045",
    "sg:province":"MN",
    "sg:tags":[
        "commercial",
        "design"
    ],
    "wof:name":"Idea Consulting Design",
    "wof:placetype":"venue"
},
  "geometry": {"coordinates":[-92.83684599999999,45.415606],"type":"Point"}
}