{
  "type": "Feature",
  "properties": {
    "addr:full":"140 S Main St Kiester MN 56051",
    "addr:housenumber":"140",
    "addr:postcode":"56051",
    "addr:street":"S Main St",
    "iso:country":"US",
    "sg:address":"140 S Main St",
    "sg:city":"Kiester",
    "sg:classifiers":[
        {
            "category":"Health Services",
            "subcategory":"Doctor",
            "type":"Services"
        }
    ],
    "sg:phone":"+1 507 294 3648",
    "sg:postcode":"56051",
    "sg:province":"MN",
    "wof:name":"Kiester Dental Office",
    "wof:placetype":"venue"
},
  "geometry": {"coordinates":[-93.712226,43.536529],"type":"Point"}
}