{
  "type": "Feature",
  "properties": {
    "addr:full":"20 Cedar Dr New Ulm MN 56073",
    "addr:housenumber":"20",
    "addr:postcode":"56073",
    "addr:street":"Cedar Dr",
    "iso:country":"US",
    "sg:address":"20 Cedar Dr",
    "sg:city":"New Ulm",
    "sg:classifiers":[
        {
            "category":"Social Services",
            "subcategory":"Child Care",
            "type":"Services"
        }
    ],
    "sg:phone":"+1 507 354 2936",
    "sg:postcode":"56073",
    "sg:province":"MN",
    "sg:tags":[
        "daycare",
        "provider"
    ],
    "wof:name":"Leann Rubey",
    "wof:placetype":"venue"
},
  "geometry": {"coordinates":[-94.484787,44.323968],"type":"Point"}
}