{
  "type": "Feature",
  "properties": {
    "addr:full":"4318 Cass Ct Webster MN 55088",
    "addr:housenumber":"4318",
    "addr:postcode":"55088",
    "addr:street":"Cass Ct",
    "iso:country":"US",
    "sg:address":"4318 Cass Ct",
    "sg:city":"Webster",
    "sg:classifiers":[
        {
            "category":"Building & Trades",
            "subcategory":"Construction",
            "type":"Services"
        }
    ],
    "sg:phone":"+1 952 652 2747",
    "sg:postcode":"55088",
    "sg:province":"MN",
    "sg:tags":[
        "house"
    ],
    "wof:name":"North American Custom Homes LL",
    "wof:placetype":"venue"
},
  "geometry": {"coordinates":[-93.328611,44.523943],"type":"Point"}
}