{
  "type": "Feature",
  "properties": {
    "addr:full":"117 Pleasant St SE Minneapolis MN 55455",
    "addr:housenumber":"117",
    "addr:postcode":"55455",
    "addr:street":"Pleasant St Se",
    "iso:country":"US",
    "sg:address":"117 Pleasant St SE",
    "sg:city":"Minneapolis",
    "sg:classifiers":[
        {
            "category":"Professional",
            "subcategory":"Research",
            "type":"Services"
        }
    ],
    "sg:phone":"+1 612 625 1818",
    "sg:postcode":"55455",
    "sg:province":"MN",
    "sg:tags":[
        "commercial",
        "physical"
    ],
    "sg:website":"www.dtc.umn.edu",
    "wof:name":"Supercomputing Institute",
    "wof:placetype":"venue"
},
  "geometry": {"coordinates":[-93.236492,44.976593],"type":"Point"}
}