{
  "type": "Feature",
  "properties": {
    "iso:country":"US",
    "sg:address":"1218 Goldenray Dr",
    "sg:city":"Faribault",
    "sg:classifiers":[
        {
            "category":"Place Of Worship",
            "type":"Public Place"
        }
    ],
    "sg:phone":"+1 507 334 5211",
    "sg:postcode":"55021",
    "sg:province":"MN",
    "sg:tags":[
        "church"
    ],
    "wof:name":"The Crux Church",
    "wof:placetype":"venue"
},
  "geometry": {"coordinates":[-93.249016,44.313027],"type":"Point"}
}