{
  "type": "Feature",
  "properties": {
    "iso:country":"US",
    "sg:address":"2521 E Hennepin Ave",
    "sg:city":"Minneapolis",
    "sg:classifiers":[
        {
            "category":"Personal",
            "subcategory":"Beauty Salon",
            "type":"Services"
        }
    ],
    "sg:phone":"+1 612 256 1770",
    "sg:postcode":"55413",
    "sg:province":"MN",
    "sg:tags":[
        "shop"
    ],
    "wof:name":"Custom Cuts of Minnesota",
    "wof:placetype":"venue"
},
  "geometry": {"coordinates":[-93.216604,44.99148],"type":"Point"}
}