{
  "type": "Feature",
  "properties": {
    "addr:full":"121 23rd Ave SW Rochester MN 55902",
    "addr:housenumber":"121",
    "addr:postcode":"55902",
    "addr:street":"23Rd Ave Sw",
    "iso:country":"US",
    "sg:address":"121 23rd Ave SW",
    "sg:city":"Rochester",
    "sg:classifiers":[
        {
            "category":"Wholesale",
            "subcategory":"Medical Equipment & Supplies",
            "type":"Manufacturing & Wholesale Goods"
        }
    ],
    "sg:phone":"+1 507 536 6128",
    "sg:postcode":"55902",
    "sg:province":"MN",
    "sg:tags":[
        "orthopedic",
        "appliance"
    ],
    "wof:name":"Ortho Innovations, Inc",
    "wof:placetype":"venue"
},
  "geometry": {"coordinates":[-92.498886,44.022335],"type":"Point"}
}