{
  "type": "Feature",
  "properties": {
    "iso:country":"US",
    "sg:address":"7100 Northland Cir N # 101",
    "sg:city":"Minneapolis",
    "sg:classifiers":[
        {
            "category":"Utilities",
            "subcategory":"Water",
            "type":"Services"
        },
        {
            "category":"Utilities",
            "subcategory":"Sewage",
            "type":"Services"
        }
    ],
    "sg:phone":"+1 763 537 9036",
    "sg:postcode":"55428",
    "sg:province":"MN",
    "sg:tags":[
        "work",
        "sewer",
        "contractor"
    ],
    "wof:name":"United Water & Sewer Co.",
    "wof:placetype":"venue"
},
  "geometry": {"coordinates":[-93.389977,45.085019],"type":"Point"}
}