{
  "type": "Feature",
  "properties": {
    "addr:full":"4115 Hwy 52 N Rochester MN 55901",
    "addr:housenumber":"4115",
    "addr:postcode":"55901",
    "addr:street":"Hwy 52 N",
    "iso:country":"US",
    "sg:address":"4115 Hwy 52 N",
    "sg:city":"Rochester",
    "sg:classifiers":[
        {
            "category":"Professional",
            "subcategory":"Computer Services",
            "type":"Services"
        }
    ],
    "sg:phone":"+1 507 287 2800",
    "sg:postcode":"55901",
    "sg:province":"MN",
    "sg:tags":[
        "prepackaged",
        "software"
    ],
    "wof:name":"Showcase",
    "wof:placetype":"venue"
},
  "geometry": {"coordinates":[-92.501994,44.068491],"type":"Point"}
}