{
  "type": "Feature",
  "properties": {
    "iso:country":"US",
    "sg:address":"1401 14th St NW",
    "sg:city":"Austin",
    "sg:classifiers":[
        {
            "category":"Travel",
            "subcategory":"Hotels & Motels",
            "type":"Entertainment"
        }
    ],
    "sg:phone":"+1 507 433 1801",
    "sg:postcode":"55912",
    "sg:province":"MN",
    "wof:name":"Super 8 Motel",
    "wof:placetype":"venue"
},
  "geometry": {"coordinates":[-92.99339500000001,43.678795],"type":"Point"}
}