{
  "type": "Feature",
  "properties": {
    "addr:full":"1692 Hague Ave St Paul MN 55104",
    "addr:housenumber":"1692",
    "addr:postcode":"55104",
    "addr:street":"Hague Ave",
    "iso:country":"US",
    "sg:address":"1692 Hague Ave",
    "sg:city":"St Paul",
    "sg:classifiers":[
        {
            "category":"Building & Trades",
            "subcategory":"Construction",
            "type":"Services"
        }
    ],
    "sg:phone":"+1 651 659 0221",
    "sg:postcode":"55104",
    "sg:province":"MN",
    "sg:tags":[
        "house",
        "general",
        "contractor"
    ],
    "wof:name":"Fleming Contracting",
    "wof:placetype":"venue"
},
  "geometry": {"coordinates":[-93.171406,44.94567],"type":"Point"}
}