{
  "type": "Feature",
  "properties": {
    "addr:full":"1754 Market Dr Stillwater MN 55082",
    "addr:housenumber":"1754",
    "addr:postcode":"55082",
    "addr:street":"Market Dr",
    "iso:country":"US",
    "sg:address":"1754 Market Dr",
    "sg:city":"Stillwater",
    "sg:classifiers":[
        {
            "category":"Professional",
            "subcategory":"Business Services",
            "type":"Services"
        }
    ],
    "sg:phone":"+1 651 439 3216",
    "sg:postcode":"55082",
    "sg:province":"MN",
    "sg:tags":[
        "interior",
        "consultant",
        "design",
        "decorator"
    ],
    "wof:name":"Neu Designs",
    "wof:placetype":"venue"
},
  "geometry": {"coordinates":[-92.84112,45.03902],"type":"Point"}
}