{
  "type": "Feature",
  "properties": {
    "addr:full":"24148 Skylark Dr NE Bethel MN 55005",
    "addr:housenumber":"24148",
    "addr:postcode":"55005",
    "addr:street":"Skylark Dr Ne",
    "iso:country":"US",
    "sg:address":"24148 Skylark Dr NE",
    "sg:city":"Bethel",
    "sg:classifiers":[
        {
            "category":"Banks & Credit Unions",
            "subcategory":"Financial Services",
            "type":"Services"
        }
    ],
    "sg:phone":"+1 763 434 3142",
    "sg:postcode":"55005",
    "sg:province":"MN",
    "sg:tags":[
        "company",
        "holding"
    ],
    "wof:name":"T & V Holdings LLC",
    "wof:placetype":"venue"
},
  "geometry": {"coordinates":[-93.255268,45.40638],"type":"Point"}
}