{
  "type": "Feature",
  "properties": {
    "iso:country":"US",
    "sg:address":"21575 Highview Ave",
    "sg:city":"Lakeville",
    "sg:classifiers":[
        {
            "category":"Home & Garden",
            "subcategory":"Building Materials",
            "type":"Retail Goods"
        }
    ],
    "sg:phone":"+1 952 469 3320",
    "sg:postcode":"55044",
    "sg:province":"MN",
    "sg:tags":[
        "lumber"
    ],
    "wof:name":"C H Carpenter",
    "wof:placetype":"venue"
},
  "geometry": {"coordinates":[-93.237983,44.634593],"type":"Point"}
}