{
  "type": "Feature",
  "properties": {
    "iso:country":"US",
    "sg:address":"2025 S Broadway",
    "sg:city":"Rochester",
    "sg:classifiers":[
        {
            "category":"Food & Beverages",
            "subcategory":"Groceries & Convenience Stores",
            "type":"Retail Goods"
        }
    ],
    "sg:phone":"+1 507 285 5557",
    "sg:postcode":"55904",
    "sg:province":"MN",
    "wof:name":"Superamerica",
    "wof:placetype":"venue"
},
  "geometry": {"coordinates":[-92.462734,43.992435],"type":"Point"}
}