{
  "type": "Feature",
  "properties": {
    "iso:country":"US",
    "sg:address":"680 151st St",
    "sg:city":"Lake Wilson",
    "sg:classifiers":[
        {
            "category":"Wholesale",
            "subcategory":"Machinery & Supplies",
            "type":"Manufacturing & Wholesale Goods"
        }
    ],
    "sg:phone":"+1 507 879 3513",
    "sg:postcode":"56151",
    "sg:province":"MN",
    "wof:name":"D&B Miller Farm",
    "wof:placetype":"venue"
},
  "geometry": {"coordinates":[-95.92782,44.065979],"type":"Point"}
}