{
  "type": "Feature",
  "properties": {
    "addr:full":"8790 Valley Forge Ln N Osseo MN 55369",
    "addr:housenumber":"8790",
    "addr:postcode":"55369",
    "addr:street":"Valley Forge Ln N",
    "iso:country":"US",
    "sg:address":"8790 Valley Forge Ln N",
    "sg:city":"Osseo",
    "sg:classifiers":[
        {
            "category":"Health Services",
            "subcategory":"Clinic",
            "type":"Services"
        }
    ],
    "sg:phone":"+1 763 424 7101",
    "sg:postcode":"55369",
    "sg:province":"MN",
    "wof:name":"Mc Kesson Corp",
    "wof:placetype":"venue"
},
  "geometry": {"coordinates":[-93.41556300000001,45.114321],"type":"Point"}
}