{
  "type": "Feature",
  "properties": {
    "iso:country":"US",
    "sg:address":"218 Birch Echo Rd",
    "sg:city":"Minnesota City",
    "sg:classifiers":[
        {
            "category":"Shopping",
            "subcategory":"Catalog Store",
            "type":"Retail Goods"
        }
    ],
    "sg:phone":"+1 507 313 9683",
    "sg:postcode":"55959",
    "sg:province":"MN",
    "sg:tags":[
        "utility",
        "computer",
        "software"
    ],
    "wof:name":"Spytech Software & Design Inc",
    "wof:placetype":"venue"
},
  "geometry": {"coordinates":[-91.73929099999999,44.081598],"type":"Point"}
}