{
  "type": "Feature",
  "properties": {
    "addr:full":"2058 Marshall Ave Saint Paul MN 55104",
    "addr:housenumber":"2058",
    "addr:postcode":"55104",
    "addr:street":"Marshall Ave",
    "iso:country":"US",
    "sg:address":"2058 Marshall Ave",
    "sg:city":"Saint Paul",
    "sg:classifiers":[
        {
            "category":"Arena",
            "subcategory":"Sports Club",
            "type":"Entertainment"
        }
    ],
    "sg:phone":"+1 651 647 6987",
    "sg:postcode":"55104",
    "sg:province":"MN",
    "sg:tags":[
        "martial art"
    ],
    "sg:website":"www.risingsunmartialartssupply.net",
    "wof:name":"Rising Sun Martial Arts Supply",
    "wof:placetype":"venue"
},
  "geometry": {"coordinates":[-93.187202,44.948502],"type":"Point"}
}