{
  "type": "Feature",
  "properties": {
    "iso:country":"US",
    "sg:address":"108 2nd St NE",
    "sg:city":"Aitkin",
    "sg:classifiers":[
        {
            "category":"Organizations",
            "subcategory":"Religious Organization",
            "type":"Services"
        }
    ],
    "sg:phone":"+1 218 927 4454",
    "sg:postcode":"56431",
    "sg:province":"MN",
    "sg:tags":[
        "church"
    ],
    "wof:name":"Church Of Jesus Christ Of Lds",
    "wof:placetype":"venue"
},
  "geometry": {"coordinates":[-93.704736,46.533465],"type":"Point"}
}