{
  "type": "Feature",
  "properties": {
    "addr:full":"102 Broadway Ave Elizabeth MN 56533",
    "addr:housenumber":"102",
    "addr:postcode":"56533",
    "addr:street":"Broadway Ave",
    "iso:country":"US",
    "sg:address":"102 Broadway Ave",
    "sg:city":"Elizabeth",
    "sg:classifiers":[
        {
            "category":"Autos & Motor Vehicles",
            "subcategory":"Fuel & Gas Station",
            "type":"Retail Goods"
        }
    ],
    "sg:phone":"+1 218 739 2132",
    "sg:postcode":"56533",
    "sg:province":"MN",
    "sg:tags":[
        "station"
    ],
    "wof:name":"Kowalski Donald",
    "wof:placetype":"venue"
},
  "geometry": {"coordinates":[-96.130321,46.379882],"type":"Point"}
}