{
  "type": "Feature",
  "properties": {
    "iso:country":"US",
    "sg:address":"6029 Pine Grove Rd",
    "sg:city":"Edina",
    "sg:classifiers":[
        {
            "category":"Organizations",
            "subcategory":"Religious Organization",
            "type":"Services"
        }
    ],
    "sg:phone":"+1 952 933 3154",
    "sg:postcode":"55436",
    "sg:province":"MN",
    "sg:tags":[
        "clergy"
    ],
    "wof:name":"Edna Mae Carlson",
    "wof:placetype":"venue"
},
  "geometry": {"coordinates":[-93.37730000000001,44.905979],"type":"Point"}
}