{
  "type": "Feature",
  "properties": {
    "addr:full":"4700 W 77th St Ste 130 Minneapolis MN 55435",
    "addr:housenumber":"4700",
    "addr:postcode":"55435",
    "addr:street":"W 77Th St Ste 130",
    "iso:country":"US",
    "sg:address":"4700 W 77th St Ste 130",
    "sg:city":"Minneapolis",
    "sg:classifiers":[
        {
            "category":"Communications",
            "subcategory":"Film & Video Production",
            "type":"Services"
        }
    ],
    "sg:phone":"+1 952 380 9871",
    "sg:postcode":"55435",
    "sg:province":"MN",
    "sg:tags":[
        "record",
        "tapes-wholesale",
        "manufacturer",
        "cd's"
    ],
    "sg:website":"http://www.redb2b.com",
    "wof:name":"Red Distribution Inc",
    "wof:placetype":"venue"
},
  "geometry": {"coordinates":[-93.345399,44.863178],"type":"Point"}
}