{
  "type": "Feature",
  "properties": {
    "addr:full":"3407 W 28th St Minneapolis MN 55416",
    "addr:housenumber":"3407",
    "addr:postcode":"55416",
    "addr:street":"W 28Th St",
    "iso:country":"US",
    "sg:address":"3407 W 28th St",
    "sg:city":"Minneapolis",
    "sg:classifiers":[
        {
            "category":"Education",
            "subcategory":"Special Training",
            "type":"Public Place"
        }
    ],
    "sg:phone":"+1 612 625 6175",
    "sg:postcode":"55416",
    "sg:province":"MN",
    "sg:tags":[
        "university",
        "professor"
    ],
    "wof:name":"Alexander M McBean",
    "wof:placetype":"venue"
},
  "geometry": {"coordinates":[-93.323251,44.952833],"type":"Point"}
}