{
  "type": "Feature",
  "properties": {
    "iso:country":"US",
    "sg:address":"3407 W 28th St",
    "sg:city":"Minneapolis",
    "sg:classifiers":[
        {
            "category":"Education",
            "subcategory":"Special Training",
            "type":"Public Place"
        }
    ],
    "sg:phone":"+1 612 625 6175",
    "sg:postcode":"55416",
    "sg:province":"MN",
    "sg:tags":[
        "university",
        "professor"
    ],
    "wof:name":"Alexander M McBean",
    "wof:placetype":"venue"
},
  "geometry": {"coordinates":[-93.323251,44.952833],"type":"Point"}
}