{
  "type": "Feature",
  "properties": {
    "iso:country":"US",
    "sg:address":"8401 73rd Ave N",
    "sg:city":"Minneapolis",
    "sg:classifiers":[
        {
            "category":"Wholesale",
            "subcategory":"Hardware",
            "type":"Manufacturing & Wholesale Goods"
        }
    ],
    "sg:phone":"+1 763 533 6996",
    "sg:postcode":"55428",
    "sg:province":"MN",
    "sg:tags":[
        "refrigeration"
    ],
    "wof:name":"Check Refrigeration Inc",
    "wof:placetype":"venue"
},
  "geometry": {"coordinates":[-93.389664,45.087371],"type":"Point"}
}