{
  "type": "Feature",
  "properties": {
    "addr:full":"4045 10th Ave NE Montevideo MN 56265",
    "addr:housenumber":"4045",
    "addr:postcode":"56265",
    "addr:street":"10Th Ave Ne",
    "iso:country":"US",
    "sg:address":"4045 10th Ave NE",
    "sg:city":"Montevideo",
    "sg:classifiers":[
        {
            "category":"Farming",
            "subcategory":"Farm",
            "type":"Manufacturing & Wholesale Goods"
        }
    ],
    "sg:phone":"+1 320 269 8690",
    "sg:postcode":"56265",
    "sg:province":"MN",
    "wof:name":"Christensen Family Farms",
    "wof:placetype":"venue"
},
  "geometry": {"coordinates":[-95.573374,45.089883],"type":"Point"}
}