{
  "type": "Feature",
  "properties": {
    "addr:full":"3020 Woodbury Dr Woodbury MN 55129",
    "addr:housenumber":"3020",
    "addr:postcode":"55129",
    "addr:street":"Woodbury Dr",
    "iso:country":"US",
    "sg:address":"3020 Woodbury Dr",
    "sg:city":"Woodbury",
    "sg:classifiers":[
        {
            "category":"Professional",
            "subcategory":"Accounting & Tax Preparation",
            "type":"Services"
        }
    ],
    "sg:phone":"+1 651 739 4277",
    "sg:postcode":"55129",
    "sg:province":"MN",
    "sg:tags":[
        "return",
        "filing"
    ],
    "wof:name":"Small Business Professionals",
    "wof:placetype":"venue"
},
  "geometry": {"coordinates":[-92.903492,44.903512],"type":"Point"}
}