{
  "type": "Feature",
  "properties": {
    "addr:full":"772 Linwood Ave Saint Paul MN 55105",
    "addr:housenumber":"772",
    "addr:postcode":"55105",
    "addr:street":"Linwood Ave",
    "iso:country":"US",
    "sg:address":"772 Linwood Ave",
    "sg:city":"Saint Paul",
    "sg:classifiers":[
        {
            "category":"Real Estate",
            "subcategory":"Real Estate Agent",
            "type":"Services"
        }
    ],
    "sg:phone":"+1 651 687 0023",
    "sg:postcode":"55105",
    "sg:province":"MN",
    "wof:name":"Lr Appraisal",
    "wof:placetype":"venue"
},
  "geometry": {"coordinates":[-93.13283,44.934601],"type":"Point"}
}