{
  "type": "Feature",
  "properties": {
    "iso:country":"US",
    "sg:address":"2605 Broadway Ave",
    "sg:city":"Slayton",
    "sg:classifiers":[
        {
            "category":"Professional",
            "subcategory":"Lawyer & Legal Services",
            "type":"Services"
        }
    ],
    "sg:phone":"+1 507 836 8581",
    "sg:postcode":"56172",
    "sg:province":"MN",
    "sg:tags":[
        "attorney"
    ],
    "wof:name":"Malone & Mailander",
    "wof:placetype":"venue"
},
  "geometry": {"coordinates":[-95.756265,43.987796],"type":"Point"}
}