{
  "type": "Feature",
  "properties": {
    "iso:country":"US",
    "sg:address":"1645 181st St",
    "sg:city":"Holland",
    "sg:phone":"+1 507 347 3204",
    "sg:postcode":"56139",
    "sg:province":"MN",
    "sg:tags":[
        "farm",
        "field",
        "corn",
        "soybean",
        "crop"
    ],
    "wof:name":"Nelson Dairy",
    "wof:placetype":"venue"
},
  "geometry": {"coordinates":[-96.137368,44.109681],"type":"Point"}
}