{
  "type": "Feature",
  "properties": {
    "addr:full":"104 4th St NW Aitkin MN 56431",
    "addr:housenumber":"104",
    "addr:postcode":"56431",
    "addr:street":"4Th St Nw",
    "iso:country":"US",
    "sg:address":"104 4th St NW",
    "sg:city":"Aitkin",
    "sg:classifiers":[
        {
            "category":"Health Services",
            "subcategory":"Chiropractor",
            "type":"Services"
        }
    ],
    "sg:phone":"+1 218 927 6383",
    "sg:postcode":"56431",
    "sg:province":"MN",
    "wof:name":"Paul A Kuiken Dr",
    "wof:placetype":"venue"
},
  "geometry": {"coordinates":[-93.70965700000001,46.535515],"type":"Point"}
}