{
  "type": "Feature",
  "properties": {
    "iso:country":"US",
    "sg:address":"9864 Palm St NW",
    "sg:city":"Minneapolis",
    "sg:classifiers":[
        {
            "category":"Professional",
            "subcategory":"Computer Services",
            "type":"Services"
        }
    ],
    "sg:phone":"+1 763 754 2315",
    "sg:postcode":"55433",
    "sg:province":"MN",
    "sg:tags":[
        "web",
        "hosting",
        "programing",
        "custom"
    ],
    "wof:name":"Gibbon Computer Products Inc",
    "wof:placetype":"venue"
},
  "geometry": {"coordinates":[-93.288068,45.14885],"type":"Point"}
}