{
  "type": "Feature",
  "properties": {
    "addr:full":"220 S Pennington Ave Thief River Falls MN 56701",
    "addr:housenumber":"220",
    "addr:postcode":"56701",
    "addr:street":"S Pennington Ave",
    "iso:country":"US",
    "sg:address":"220 S Pennington Ave",
    "sg:city":"Thief River Falls",
    "sg:classifiers":[
        {
            "category":"Health Services",
            "subcategory":"Clinic",
            "type":"Services"
        }
    ],
    "sg:phone":"+1 218 681 1403",
    "sg:postcode":"56701",
    "sg:province":"MN",
    "sg:tags":[
        "specialty",
        "outpatient"
    ],
    "wof:name":"Options",
    "wof:placetype":"venue"
},
  "geometry": {"coordinates":[-96.17304900000001,48.12468],"type":"Point"}
}