{
  "type": "Feature",
  "properties": {
    "addr:full":"21469 Killdeer St NW Cedar MN 55011",
    "addr:housenumber":"21469",
    "addr:postcode":"55011",
    "addr:street":"Killdeer St Nw Cedar",
    "iso:country":"US",
    "sg:address":"21469 Killdeer St NW",
    "sg:city":"Cedar",
    "sg:classifiers":[
        {
            "category":"Utilities",
            "subcategory":"Fuel Oil & Lpg",
            "type":"Services"
        }
    ],
    "sg:phone":"+1 763 753 0384",
    "sg:postcode":"55011",
    "sg:province":"MN",
    "sg:tags":[
        "oils-fuel"
    ],
    "wof:name":"Paul Toenyan",
    "wof:placetype":"venue"
},
  "geometry": {"coordinates":[-93.313228,45.3577],"type":"Point"}
}