{
  "type": "Feature",
  "properties": {
    "iso:country":"US",
    "sg:address":"6705 Wedgwood Court North",
    "sg:city":"Maple Grove",
    "sg:classifiers":[
        {
            "category":"Professional",
            "subcategory":"Research",
            "type":"Services"
        }
    ],
    "sg:phone":"+1 763 463 1595",
    "sg:postcode":"55311",
    "sg:province":"MN",
    "sg:website":"http://www.entellusmedical.com",
    "wof:name":"Entellus Medical",
    "wof:placetype":"venue"
},
  "geometry": {"coordinates":[-93.45060100000001,45.076819],"type":"Point"}
}