{
  "type": "Feature",
  "properties": {
    "iso:country":"US",
    "sg:address":"441 Hazel Ave E",
    "sg:city":"Kimball",
    "sg:classifiers":[
        {
            "category":"Organizations",
            "subcategory":"Religious Organization",
            "type":"Services"
        }
    ],
    "sg:phone":"+1 320 398 2211",
    "sg:postcode":"55353",
    "sg:province":"MN",
    "sg:tags":[
        "church"
    ],
    "wof:name":"St Anne Church",
    "wof:placetype":"venue"
},
  "geometry": {"coordinates":[-94.29458700000001,45.312336],"type":"Point"}
}