{
  "type": "Feature",
  "properties": {
    "addr:full":"401 2nd St S Minneapolis MN 55401",
    "addr:housenumber":"401",
    "addr:postcode":"55401",
    "addr:street":"2Nd St S",
    "iso:country":"US",
    "sg:address":"401 2nd St S",
    "sg:city":"Minneapolis",
    "sg:classifiers":[
        {
            "category":"Professional",
            "subcategory":"Lawyer & Legal Services",
            "type":"Services"
        }
    ],
    "sg:phone":"+1 612 338 4621",
    "sg:postcode":"55401",
    "sg:province":"MN",
    "wof:name":"Trawick & Smith",
    "wof:placetype":"venue"
},
  "geometry": {"coordinates":[-93.261579,44.980385],"type":"Point"}
}