{
  "type": "Feature",
  "properties": {
    "addr:full":"8524 Indigo Rd Saint Cloud MN 56301",
    "addr:housenumber":"8524",
    "addr:postcode":"56301",
    "addr:street":"Indigo Rd",
    "iso:country":"US",
    "sg:address":"8524 Indigo Rd",
    "sg:city":"Saint Cloud",
    "sg:classifiers":[
        {
            "category":"Farming",
            "subcategory":"Dairy Farm",
            "type":"Manufacturing & Wholesale Goods"
        }
    ],
    "sg:phone":"+1 320 252 5212",
    "sg:postcode":"56301",
    "sg:province":"MN",
    "wof:name":"David & Louise Bromenschenkel",
    "wof:placetype":"venue"
},
  "geometry": {"coordinates":[-94.283226,45.529252],"type":"Point"}
}