{
  "type": "Feature",
  "properties": {
    "iso:country":"US",
    "sg:address":"105 1st Ave",
    "sg:city":"Arlington",
    "sg:classifiers":[
        {
            "category":"Food & Beverages",
            "subcategory":"Groceries & Convenience Stores",
            "type":"Retail Goods"
        }
    ],
    "sg:phone":"+1 507 964 2246",
    "sg:postcode":"55307",
    "sg:province":"MN",
    "sg:tags":[
        "grocer"
    ],
    "wof:name":"Jerry's Home Quality Foods",
    "wof:placetype":"venue"
},
  "geometry": {"coordinates":[-94.07684500000001,44.607171],"type":"Point"}
}