{
  "type": "Feature",
  "properties": {
    "addr:full":"5567 Bishop Ave Inver Grove Heights MN 55076",
    "addr:housenumber":"5567",
    "addr:postcode":"55076",
    "addr:street":"Bishop Ave",
    "iso:country":"US",
    "sg:address":"5567 Bishop Ave",
    "sg:city":"Inver Grove Heights",
    "sg:classifiers":[
        {
            "category":"Cinema",
            "subcategory":"Movie Theater",
            "type":"Entertainment"
        }
    ],
    "sg:phone":"+1 651 453 1016",
    "sg:postcode":"55076",
    "sg:province":"MN",
    "sg:tags":[
        "motion",
        "picture"
    ],
    "wof:name":"Showplace 16 Kerasotes Theatre",
    "wof:placetype":"venue"
},
  "geometry": {"coordinates":[-93.05578800000001,44.868527],"type":"Point"}
}