{
  "type": "Feature",
  "properties": {
    "iso:country":"US",
    "sg:address":"120 7th Ave SE",
    "sg:city":"St Cloud",
    "sg:classifiers":[
        {
            "category":"Travel",
            "subcategory":"Hotels & Motels",
            "type":"Entertainment"
        }
    ],
    "sg:phone":"+1 320 252 8282",
    "sg:postcode":"56304",
    "sg:province":"MN",
    "wof:name":"Country Inn & Suites",
    "wof:placetype":"venue"
},
  "geometry": {"coordinates":[-94.14193299999999,45.566841],"type":"Point"}
}