{
  "type": "Feature",
  "properties": {
    "iso:country":"US",
    "sg:address":"3200 Chase Dr",
    "sg:city":"Hopkins",
    "sg:classifiers":[
        {
            "category":"Building & Trades",
            "subcategory":"Landscaping Services",
            "type":"Services"
        }
    ],
    "sg:phone":"+1 952 945 9551",
    "sg:postcode":"55305",
    "sg:province":"MN",
    "wof:name":"Stewards Home Maint Rmdlg",
    "wof:placetype":"venue"
},
  "geometry": {"coordinates":[-93.44911999999999,44.942772],"type":"Point"}
}