{
  "type": "Feature",
  "properties": {
    "iso:country":"US",
    "sg:address":"202 N Broadway Ave",
    "sg:city":"Albert Lea",
    "sg:classifiers":[
        {
            "category":"Real Estate",
            "subcategory":"Real Estate Agent",
            "type":"Services"
        }
    ],
    "sg:phone":"+1 507 373 1473",
    "sg:postcode":"56007",
    "sg:province":"MN",
    "sg:website":"www.c21obyrne.com",
    "wof:name":"O'Byrne Realty Inc",
    "wof:placetype":"venue"
},
  "geometry": {"coordinates":[-93.368652,43.651285],"type":"Point"}
}