{
  "type": "Feature",
  "properties": {
    "addr:full":"25232 Co Rd 139 Saint Cloud MN 56301",
    "addr:housenumber":"25232;139",
    "addr:postcode":"56301",
    "addr:street":"Co Rd",
    "iso:country":"US",
    "sg:address":"25232 Co Rd 139",
    "sg:city":"Saint Cloud",
    "sg:classifiers":[
        {
            "category":"Farming",
            "subcategory":"Livestock Farm",
            "type":"Manufacturing & Wholesale Goods"
        }
    ],
    "sg:phone":"+1 320 685 3018",
    "sg:postcode":"56301",
    "sg:province":"MN",
    "sg:tags":[
        "beef",
        "corn",
        "field",
        "soybean",
        "cattle",
        "feedlot"
    ],
    "wof:name":"Ed Massmann",
    "wof:placetype":"venue"
},
  "geometry": {"coordinates":[-94.343124,45.49056],"type":"Point"}
}