{
  "type": "Feature",
  "properties": {
    "iso:country":"US",
    "sg:address":"8125 33rd Pl N",
    "sg:city":"Minneapolis",
    "sg:classifiers":[
        {
            "category":"Social Services",
            "subcategory":"Child Care",
            "type":"Services"
        }
    ],
    "sg:phone":"+1 763 512 1552",
    "sg:postcode":"55427",
    "sg:province":"MN",
    "sg:tags":[
        "day"
    ],
    "wof:name":"Joel Edmund Loecken",
    "wof:placetype":"venue"
},
  "geometry": {"coordinates":[-93.38437999999999,45.017228],"type":"Point"}
}