{
  "type": "Feature",
  "properties": {
    "addr:full":"3465 124th Ave NW Minneapolis MN 55433",
    "addr:housenumber":"3465",
    "addr:postcode":"55433",
    "addr:street":"124Th Ave Nw",
    "iso:country":"US",
    "sg:address":"3465 124th Ave NW",
    "sg:city":"Minneapolis",
    "sg:classifiers":[
        {
            "category":"Fast Food",
            "type":"Food & Drink"
        }
    ],
    "sg:phone":"+1 763 421 7785",
    "sg:postcode":"55433",
    "sg:province":"MN",
    "wof:name":"White Castle",
    "wof:placetype":"venue"
},
  "geometry": {"coordinates":[-93.353649,45.197053],"type":"Point"}
}