{
  "type": "Feature",
  "properties": {
    "iso:country":"US",
    "sg:address":"2845 Abaca Rd",
    "sg:city":"Burtrum",
    "sg:classifiers":[
        {
            "category":"Farming",
            "subcategory":"Livestock Farm",
            "type":"Manufacturing & Wholesale Goods"
        }
    ],
    "sg:phone":"+1 320 573 2339",
    "sg:postcode":"56318",
    "sg:province":"MN",
    "sg:tags":[
        "beef",
        "trucking",
        "cattle",
        "operator",
        "local",
        "feedlot"
    ],
    "wof:name":"Walt Edin Trucking",
    "wof:placetype":"venue"
},
  "geometry": {"coordinates":[-94.598876,45.810296],"type":"Point"}
}