{
  "type": "Feature",
  "properties": {
    "iso:country":"US",
    "sg:address":"31 W Superior St",
    "sg:city":"Duluth",
    "sg:classifiers":[
        {
            "category":"Health Services",
            "subcategory":"Health Practitioner",
            "type":"Services"
        }
    ],
    "sg:phone":"+1 218 428 1893",
    "sg:postcode":"55802",
    "sg:province":"MN",
    "sg:tags":[
        "acupuncture"
    ],
    "wof:name":"Healing Point Of Duluth",
    "wof:placetype":"venue"
},
  "geometry": {"coordinates":[-92.09915100000001,46.786338],"type":"Point"}
}