{
  "type": "Feature",
  "properties": {
    "addr:full":"8495 Woodland Rd Eveleth MN 55734",
    "addr:housenumber":"8495",
    "addr:postcode":"55734",
    "addr:street":"Woodland Rd",
    "iso:country":"US",
    "sg:address":"8495 Woodland Rd",
    "sg:city":"Eveleth",
    "sg:classifiers":[
        {
            "category":"Autos & Motor Vehicles",
            "subcategory":"Automobile Sales",
            "type":"Retail Goods"
        }
    ],
    "sg:phone":"+1 218 744 5343",
    "sg:postcode":"55734",
    "sg:province":"MN",
    "sg:tags":[
        "new",
        "car"
    ],
    "wof:name":"Dba Dale Gregorich Auto Sales",
    "wof:placetype":"venue"
},
  "geometry": {"coordinates":[-92.579626,47.393944],"type":"Point"}
}