{
  "type": "Feature",
  "properties": {
    "addr:full":"2420 Nevada Ave N Golden Valley MN 55427",
    "addr:housenumber":"2420",
    "addr:postcode":"55427",
    "addr:street":"Nevada Ave N",
    "iso:country":"US",
    "sg:address":"2420 Nevada Ave N",
    "sg:city":"Golden Valley",
    "sg:classifiers":[
        {
            "category":"Manufacturing",
            "subcategory":"Printing",
            "type":"Manufacturing & Wholesale Goods"
        }
    ],
    "sg:phone":"+1 763 540 0419",
    "sg:postcode":"55427",
    "sg:province":"MN",
    "sg:tags":[
        "lithographic",
        "screen",
        "commercial"
    ],
    "wof:name":"C J Printing",
    "wof:placetype":"venue"
},
  "geometry": {"coordinates":[-93.37231199999999,45.004467],"type":"Point"}
}