{
  "type": "Feature",
  "properties": {
    "addr:full":"2552 US Hwy 10 St Paul MN 55112",
    "addr:housenumber":"2552",
    "addr:postcode":"55112",
    "addr:street":"Us Hwy 10",
    "iso:country":"US",
    "sg:address":"2552 US Hwy 10",
    "sg:city":"St Paul",
    "sg:classifiers":[
        {
            "category":"Health Services",
            "subcategory":"Chiropractor",
            "type":"Services"
        }
    ],
    "sg:phone":"+1 763 786 5581",
    "sg:postcode":"55112",
    "sg:province":"MN",
    "wof:name":"Silver View Chiropractic Ctr",
    "wof:placetype":"venue"
},
  "geometry": {"coordinates":[-93.210194,45.105722],"type":"Point"}
}