{
  "type": "Feature",
  "properties": {
    "addr:full":"13241 Co Rd 58 NW Brandon MN 56315",
    "addr:housenumber":"13241;58",
    "addr:postcode":"56315",
    "addr:street":"Co Rd;Nw",
    "iso:country":"US",
    "sg:address":"13241 Co Rd 58 NW",
    "sg:city":"Brandon",
    "sg:classifiers":[
        {
            "category":"Freight",
            "type":"Transportation"
        }
    ],
    "sg:phone":"+1 320 834 4778",
    "sg:postcode":"56315",
    "sg:province":"MN",
    "sg:tags":[
        "trucking"
    ],
    "wof:name":"Randt Trucking",
    "wof:placetype":"venue"
},
  "geometry": {"coordinates":[-95.572788,45.980421],"type":"Point"}
}