{
  "type": "Feature",
  "properties": {
    "addr:full":"1732 143rd Ln NE Anoka MN 55304",
    "addr:housenumber":"1732",
    "addr:postcode":"55304",
    "addr:street":"143Rd Ln Ne",
    "iso:country":"US",
    "sg:address":"1732 143rd Ln NE",
    "sg:city":"Anoka",
    "sg:classifiers":[
        {
            "category":"Shopping",
            "subcategory":"Luggage & Leather Goods",
            "type":"Retail Goods"
        }
    ],
    "sg:phone":"+1 763 862 2948",
    "sg:postcode":"55304",
    "sg:province":"MN",
    "wof:name":"American Gypsy",
    "wof:placetype":"venue"
},
  "geometry": {"coordinates":[-93.226297,45.232687],"type":"Point"}
}