{
  "type": "Feature",
  "properties": {
    "iso:country":"US",
    "sg:address":"13570 Grove Dr",
    "sg:city":"Osseo",
    "sg:classifiers":[
        {
            "category":"Professional",
            "subcategory":"Business Services",
            "type":"Services"
        }
    ],
    "sg:phone":"+1 612 940 1636",
    "sg:postcode":"55311",
    "sg:province":"MN",
    "wof:name":"Amerispec Hmes Inspections Svc",
    "wof:placetype":"venue"
},
  "geometry": {"coordinates":[-93.45235700000001,45.103008],"type":"Point"}
}