{
  "type": "Feature",
  "properties": {
    "addr:full":"9280 University Ave NW Coon Rapids MN 55448",
    "addr:housenumber":"9280",
    "addr:postcode":"55448",
    "addr:street":"University Ave Nw",
    "iso:country":"US",
    "sg:address":"9280 University Ave NW",
    "sg:city":"Coon Rapids",
    "sg:classifiers":[
        {
            "category":"Communications",
            "subcategory":"Film & Video Production",
            "type":"Services"
        }
    ],
    "sg:phone":"+1 612 558 7115",
    "sg:postcode":"55448",
    "sg:province":"MN",
    "sg:tags":[
        "audio",
        "creative"
    ],
    "wof:name":"Montage Creative Inc",
    "wof:placetype":"venue"
},
  "geometry": {"coordinates":[-93.266857,45.139936],"type":"Point"}
}