{
  "type": "Feature",
  "properties": {
    "iso:country":"US",
    "sg:address":"16696 Co Rd 52",
    "sg:city":"Avon",
    "sg:classifiers":[
        {
            "category":"Farming",
            "subcategory":"Dairy Farm",
            "type":"Manufacturing & Wholesale Goods"
        }
    ],
    "sg:phone":"+1 320 746 2302",
    "sg:postcode":"56310",
    "sg:province":"MN",
    "wof:name":"Tjs Farms",
    "wof:placetype":"venue"
},
  "geometry": {"coordinates":[-94.460324,45.673122],"type":"Point"}
}