{
  "type": "Feature",
  "properties": {
    "iso:country":"US",
    "sg:address":"18279 Minnetonka Blvd",
    "sg:city":"Wayzata",
    "sg:classifiers":[
        {
            "category":"Insurance",
            "subcategory":"Insurance Agent",
            "type":"Services"
        }
    ],
    "sg:phone":"+1 952 473 6584",
    "sg:postcode":"55391",
    "sg:province":"MN",
    "wof:name":"Port-Kimm Agency",
    "wof:placetype":"venue"
},
  "geometry": {"coordinates":[-93.512421,44.940399],"type":"Point"}
}