{
  "type": "Feature",
  "properties": {
    "iso:country":"US",
    "sg:address":"1795 Sundew Trl",
    "sg:city":"Remer",
    "sg:classifiers":[
        {
            "category":"Professional",
            "type":"Services"
        }
    ],
    "sg:phone":"+1 218 792 5706",
    "sg:postcode":"56672",
    "sg:province":"MN",
    "wof:name":"Michael C Wilder",
    "wof:placetype":"venue"
},
  "geometry": {"coordinates":[-93.968738,46.868712],"type":"Point"}
}