{
  "type": "Feature",
  "properties": {
    "iso:country":"US",
    "sg:address":"7999 Salo Rd",
    "sg:city":"Saginaw",
    "sg:classifiers":[
        {
            "category":"Professional",
            "subcategory":"Accounting & Tax Preparation",
            "type":"Services"
        }
    ],
    "sg:phone":"+1 218 345 6663",
    "sg:postcode":"55779",
    "sg:province":"MN",
    "sg:tags":[
        "return"
    ],
    "wof:name":"Barbara Solem Tax Service",
    "wof:placetype":"venue"
},
  "geometry": {"coordinates":[-92.512839,46.946305],"type":"Point"}
}