{
  "type": "Feature",
  "properties": {
    "addr:full":"16923 Trenton Ln Eden Prairie MN 55347",
    "addr:housenumber":"16923",
    "addr:postcode":"55347",
    "addr:street":"Trenton Ln",
    "iso:country":"US",
    "sg:address":"16923 Trenton Ln",
    "sg:city":"Eden Prairie",
    "sg:classifiers":[
        {
            "category":"Shopping",
            "subcategory":"Catalog Store",
            "type":"Retail Goods"
        }
    ],
    "sg:phone":"+1 612 418 3076",
    "sg:postcode":"55347",
    "sg:province":"MN",
    "wof:name":"Kenyon Rick",
    "wof:placetype":"venue"
},
  "geometry": {"coordinates":[-93.494935,44.841404],"type":"Point"}
}