{
  "type": "Feature",
  "properties": {
    "iso:country":"US",
    "sg:address":"2540 24th Ave S",
    "sg:city":"Minneapolis",
    "sg:classifiers":[
        {
            "category":"Shopping Center",
            "type":"Public Place"
        }
    ],
    "sg:phone":"+1 612 729 9000",
    "sg:postcode":"55406",
    "sg:province":"MN",
    "sg:tags":[
        "card",
        "printers-business"
    ],
    "wof:name":"Bct",
    "wof:placetype":"venue"
},
  "geometry": {"coordinates":[-93.23768,44.957076],"type":"Point"}
}