{
  "type": "Feature",
  "properties": {
    "iso:country":"US",
    "sg:address":"1680 Mayfield Heights Rd",
    "sg:city":"Saint Paul",
    "sg:classifiers":[
        {
            "category":"Retail",
            "subcategory":"Auto Repair",
            "type":"Services"
        }
    ],
    "sg:phone":"+1 651 687 9212",
    "sg:postcode":"55118",
    "sg:province":"MN",
    "sg:tags":[
        "automotive"
    ],
    "wof:name":"C Bolin and Co",
    "wof:placetype":"venue"
},
  "geometry": {"coordinates":[-93.143379,44.895554],"type":"Point"}
}