{
  "type": "Feature",
  "properties": {
    "addr:full":"5648 Girard Ave S Minneapolis MN 55419",
    "addr:housenumber":"5648",
    "addr:postcode":"55419",
    "addr:street":"Girard Ave S",
    "iso:country":"US",
    "sg:address":"5648 Girard Ave S",
    "sg:city":"Minneapolis",
    "sg:classifiers":[
        {
            "category":"Professional",
            "type":"Services"
        }
    ],
    "sg:phone":"+1 612 861 6700",
    "sg:postcode":"55419",
    "sg:province":"MN",
    "wof:name":"McDonald Moon Farms Inc",
    "wof:placetype":"venue"
},
  "geometry": {"coordinates":[-93.29727800000001,44.900568],"type":"Point"}
}