{
  "type": "Feature",
  "properties": {
    "iso:country":"US",
    "sg:address":"712 2nd St SE",
    "sg:city":"Ortonville",
    "sg:classifiers":[
        {
            "category":"Autos & Motor Vehicles",
            "subcategory":"Auto Supplies",
            "type":"Retail Goods"
        }
    ],
    "sg:phone":"+1 320 839 3717",
    "sg:postcode":"56278",
    "sg:province":"MN",
    "sg:tags":[
        "bulk",
        "petroleum",
        "tire"
    ],
    "wof:name":"Cashtown Service Inc",
    "wof:placetype":"venue"
},
  "geometry": {"coordinates":[-96.440477,45.299539],"type":"Point"}
}