{
  "type": "Feature",
  "properties": {
    "addr:full":"1209 1st St S St Cloud MN 56301",
    "addr:housenumber":"1209",
    "addr:postcode":"56301",
    "addr:street":"1St St S",
    "iso:country":"US",
    "sg:address":"1209 1st St S",
    "sg:city":"St Cloud",
    "sg:classifiers":[
        {
            "category":"Restaurant",
            "type":"Food & Drink"
        }
    ],
    "sg:phone":"+1 320 257 4992",
    "sg:postcode":"56301",
    "sg:province":"MN",
    "wof:name":"Little Caesars Pizza",
    "wof:placetype":"venue"
},
  "geometry": {"coordinates":[-94.16647500000001,45.556404],"type":"Point"}
}