{
  "type": "Feature",
  "properties": {
    "addr:full":"8484 Zanzibar Ln N Osseo MN 55311",
    "addr:housenumber":"8484",
    "addr:postcode":"55311",
    "addr:street":"Zanzibar Ln N",
    "iso:country":"US",
    "sg:address":"8484 Zanzibar Ln N",
    "sg:city":"Osseo",
    "sg:classifiers":[
        {
            "category":"Travel",
            "subcategory":"Hotels & Motels",
            "type":"Entertainment"
        }
    ],
    "sg:phone":"+1 763 420 4644",
    "sg:postcode":"55311",
    "sg:province":"MN",
    "sg:tags":[
        "operation"
    ],
    "wof:name":"WA GA Tha Ka Resort",
    "wof:placetype":"venue"
},
  "geometry": {"coordinates":[-93.488235,45.108411],"type":"Point"}
}