{
  "type": "Feature",
  "properties": {
    "addr:full":"1018 N 5th St Minneapolis MN 55411",
    "addr:housenumber":"1018",
    "addr:postcode":"55411",
    "addr:street":"N 5Th St",
    "iso:country":"US",
    "sg:address":"1018 N 5th St",
    "sg:city":"Minneapolis",
    "sg:classifiers":[
        {
            "category":"Professional",
            "subcategory":"Art Services",
            "type":"Services"
        },
        {
            "category":"Communications",
            "type":"Services"
        },
        {
            "category":"Professional",
            "subcategory":"Computer Services",
            "type":"Services"
        }
    ],
    "sg:phone":"+1 612 339 3039",
    "sg:postcode":"55411",
    "sg:province":"MN",
    "sg:tags":[
        "web",
        "graphic",
        "hosting",
        "site",
        "designer",
        "design"
    ],
    "sg:website":"www.fifthstreet.net",
    "wof:name":"Fifth Street Design",
    "wof:placetype":"venue"
},
  "geometry": {"coordinates":[-93.284302,44.988098],"type":"Point"}
}