{
  "type": "Feature",
  "properties": {
    "addr:full":"1375 Trout Brook Cir St Paul MN 55117",
    "addr:housenumber":"1375",
    "addr:postcode":"55117",
    "addr:street":"Trout Brook Cir",
    "iso:country":"US",
    "sg:address":"1375 Trout Brook Cir",
    "sg:city":"St Paul",
    "sg:classifiers":[
        {
            "category":"Professional",
            "subcategory":"Advertising",
            "type":"Services"
        }
    ],
    "sg:phone":"+1 651 697 1796",
    "sg:postcode":"55117",
    "sg:province":"MN",
    "sg:tags":[
        "distribution"
    ],
    "wof:name":"Northstar Surfaces",
    "wof:placetype":"venue"
},
  "geometry": {"coordinates":[-93.09813,44.983071],"type":"Point"}
}