{
  "type": "Feature",
  "properties": {
    "iso:country":"US",
    "sg:address":"1405 78th St",
    "sg:city":"Victoria",
    "sg:classifiers":[
        {
            "category":"Sports & Exercise",
            "subcategory":"Gym",
            "type":"Entertainment"
        }
    ],
    "sg:phone":"+1 952 361 9355",
    "sg:postcode":"55386",
    "sg:province":"MN",
    "sg:tags":[
        "yoga"
    ],
    "wof:name":"Studio Enso",
    "wof:placetype":"venue"
},
  "geometry": {"coordinates":[-93.652202,44.863153],"type":"Point"}
}