{
  "type": "Feature",
  "properties": {
    "addr:full":"216 N Main St Janesville MN 56048",
    "addr:housenumber":"216",
    "addr:postcode":"56048",
    "addr:street":"N Main St",
    "iso:country":"US",
    "sg:address":"216 N Main St",
    "sg:city":"Janesville",
    "sg:classifiers":[
        {
            "category":"Professional",
            "subcategory":"Lawyer & Legal Services",
            "type":"Services"
        }
    ],
    "sg:phone":"+1 507 234 5106",
    "sg:postcode":"56048",
    "sg:province":"MN",
    "sg:tags":[
        "attorney"
    ],
    "wof:name":"Gardner Law Office",
    "wof:placetype":"venue"
},
  "geometry": {"coordinates":[-93.70759099999999,44.116233],"type":"Point"}
}