{
  "type": "Feature",
  "properties": {
    "iso:country":"US",
    "sg:address":"12680 Arbor Lakes Pkwy N",
    "sg:city":"Osseo",
    "sg:classifiers":[
        {
            "category":"Education",
            "subcategory":"Special Training",
            "type":"Public Place"
        }
    ],
    "sg:phone":"+1 763 494 9676",
    "sg:postcode":"55369",
    "sg:province":"MN",
    "sg:tags":[
        "tutoring"
    ],
    "wof:name":"Sylvan Learning Ctr",
    "wof:placetype":"venue"
},
  "geometry": {"coordinates":[-93.441401,45.098384],"type":"Point"}
}