{
  "type": "Feature",
  "properties": {
    "iso:country":"US",
    "sg:address":"220 W Superior St",
    "sg:city":"Duluth",
    "sg:classifiers":[
        {
            "category":"Restaurant",
            "type":"Food & Drink"
        }
    ],
    "sg:phone":"+1 218 786 0119",
    "sg:postcode":"55802",
    "sg:province":"MN",
    "sg:tags":[
        "eating"
    ],
    "wof:name":"Y Buddy Place",
    "wof:placetype":"venue"
},
  "geometry": {"coordinates":[-92.10156499999999,46.784231],"type":"Point"}
}