{
  "type": "Feature",
  "properties": {
    "iso:country":"US",
    "sg:address":"1437 18th Ave NW",
    "sg:city":"Faribault",
    "sg:classifiers":[
        {
            "category":"Real Estate",
            "subcategory":"Real Estate Operator",
            "type":"Services"
        }
    ],
    "sg:phone":"+1 507 334 5456",
    "sg:postcode":"55021",
    "sg:province":"MN",
    "sg:tags":[
        "property",
        "lessor"
    ],
    "wof:name":"Richard Wobschall",
    "wof:placetype":"venue"
},
  "geometry": {"coordinates":[-93.29410300000001,44.306554],"type":"Point"}
}