{
  "type": "Feature",
  "properties": {
    "addr:full":"935 Wayzata Blvd Wayzata MN 55391",
    "addr:housenumber":"935",
    "addr:postcode":"55391",
    "addr:street":"Wayzata Blvd",
    "iso:country":"US",
    "sg:address":"935 Wayzata Blvd",
    "sg:city":"Wayzata",
    "sg:classifiers":[
        {
            "category":"Building & Trades",
            "subcategory":"Construction",
            "type":"Services"
        }
    ],
    "sg:phone":"+1 763 473 1231",
    "sg:postcode":"55391",
    "sg:province":"MN",
    "sg:tags":[
        "builder",
        "operative",
        "nonresidential"
    ],
    "wof:name":"US Home",
    "wof:placetype":"venue"
},
  "geometry": {"coordinates":[-93.54605599999999,44.981131],"type":"Point"}
}