{
  "type": "Feature",
  "properties": {
    "iso:country":"US",
    "sg:address":"3909 Auburn Dr",
    "sg:city":"Hopkins",
    "sg:classifiers":[
        {
            "category":"Professional",
            "subcategory":"Business Services",
            "type":"Services"
        }
    ],
    "sg:phone":"+1 952 933 4474",
    "sg:postcode":"55305",
    "sg:province":"MN",
    "wof:name":"Nancy Golden Design",
    "wof:placetype":"venue"
},
  "geometry": {"coordinates":[-93.433993,44.930027],"type":"Point"}
}