{
  "type": "Feature",
  "properties": {
    "iso:country":"US",
    "sg:address":"1604 1st St S",
    "sg:city":"Willmar",
    "sg:classifiers":[
        {
            "category":"Shopping",
            "subcategory":"Computers & Home Electronics",
            "type":"Retail Goods"
        }
    ],
    "sg:phone":"+1 320 235 1727",
    "sg:postcode":"56201",
    "sg:province":"MN",
    "sg:tags":[
        "television",
        "radio"
    ],
    "wof:name":"Roy's Television & Electronics",
    "wof:placetype":"venue"
},
  "geometry": {"coordinates":[-95.04276,45.106862],"type":"Point"}
}