{
  "type": "Feature",
  "properties": {
    "addr:full":"321 2nd Ave NW Roseau MN 56751",
    "addr:housenumber":"321",
    "addr:postcode":"56751",
    "addr:street":"2Nd Ave Nw",
    "iso:country":"US",
    "sg:address":"321 2nd Ave NW",
    "sg:city":"Roseau",
    "sg:classifiers":[
        {
            "category":"Recreation",
            "type":"Entertainment"
        }
    ],
    "sg:phone":"+1 218 463 9928",
    "sg:postcode":"56751",
    "sg:province":"MN",
    "sg:tags":[
        "skating",
        "rink"
    ],
    "wof:name":"Roseau Arena",
    "wof:placetype":"venue"
},
  "geometry": {"coordinates":[-95.763694,48.84884],"type":"Point"}
}