{
  "type": "Feature",
  "properties": {
    "iso:country":"US",
    "sg:address":"6531 Troendle Cir",
    "sg:city":"Chanhassen",
    "sg:classifiers":[
        {
            "category":"Professional",
            "subcategory":"Computer Services",
            "type":"Services"
        }
    ],
    "sg:phone":"+1 952 474 4026",
    "sg:postcode":"55317",
    "sg:province":"MN",
    "sg:tags":[
        "prepackaged",
        "software"
    ],
    "wof:name":"Graven Software Engineering",
    "wof:placetype":"venue"
},
  "geometry": {"coordinates":[-93.545591,44.885102],"type":"Point"}
}