{
  "type": "Feature",
  "properties": {
    "iso:country":"US",
    "sg:address":"17042 250th Ave",
    "sg:city":"Paynesville",
    "sg:classifiers":[
        {
            "category":"Building & Trades",
            "subcategory":"Construction",
            "type":"Services"
        }
    ],
    "sg:phone":"+1 320 453 2652",
    "sg:postcode":"56362",
    "sg:province":"MN",
    "sg:tags":[
        "concrete",
        "masonry",
        "contractor"
    ],
    "wof:name":"Doom Construction",
    "wof:placetype":"venue"
},
  "geometry": {"coordinates":[-94.633441,45.369389],"type":"Point"}
}