{
  "type": "Feature",
  "properties": {
    "iso:country":"US",
    "sg:address":"6500 Brooklyn Blvd",
    "sg:city":"Brooklyn Center",
    "sg:classifiers":[
        {
            "category":"Insurance",
            "subcategory":"Insurance Agent",
            "type":"Services"
        }
    ],
    "sg:phone":"+1 763 566 7299",
    "sg:postcode":"55429",
    "sg:province":"MN",
    "wof:name":"Germain Insurance Inc",
    "wof:placetype":"venue"
},
  "geometry": {"coordinates":[-93.330319,45.073164],"type":"Point"}
}