{
  "type": "Feature",
  "properties": {
    "iso:country":"US",
    "sg:address":"6620 235th St W",
    "sg:city":"Warsaw",
    "sg:classifiers":[
        {
            "category":"Manufacturing",
            "subcategory":"Lumber",
            "type":"Manufacturing & Wholesale Goods"
        }
    ],
    "sg:phone":"+1 507 685 4297",
    "sg:postcode":"55024",
    "sg:province":"MN",
    "sg:tags":[
        "wood",
        "carving"
    ],
    "wof:name":"Chiang MAI Lanna America",
    "wof:placetype":"venue"
},
  "geometry": {"coordinates":[-93.20247000000001,44.608826],"type":"Point"}
}