{
  "type": "Feature",
  "properties": {
    "addr:full":"14421 Johnny Cake Ridge Rd Saint Paul MN 55124",
    "addr:housenumber":"14421",
    "addr:postcode":"55124",
    "addr:street":"Johnny Cake Ridge Rd",
    "iso:country":"US",
    "sg:address":"14421 Johnny Cake Ridge Rd",
    "sg:city":"Saint Paul",
    "sg:classifiers":[
        {
            "category":"Government",
            "subcategory":"Office",
            "type":"Public Place"
        }
    ],
    "sg:phone":"+1 952 953 2390",
    "sg:postcode":"55124",
    "sg:province":"MN",
    "sg:tags":[
        "aquatic",
        "center"
    ],
    "wof:name":"Apple Valley Fmly Aquatic Ctr",
    "wof:placetype":"venue"
},
  "geometry": {"coordinates":[-93.187141,44.732481],"type":"Point"}
}