{
  "type": "Feature",
  "properties": {
    "addr:full":"6400 11th Ave S Richfield MN 55423",
    "addr:housenumber":"6400",
    "addr:postcode":"55423",
    "addr:street":"11Th Ave S",
    "iso:country":"US",
    "sg:address":"6400 11th Ave S",
    "sg:city":"Richfield",
    "sg:classifiers":[
        {
            "category":"Retail",
            "subcategory":"Animal Services",
            "type":"Services"
        }
    ],
    "sg:phone":"+1 612 869 6451",
    "sg:postcode":"55423",
    "sg:province":"MN",
    "sg:tags":[
        "training",
        "dog"
    ],
    "wof:name":"Best Friends Animal Behavior",
    "wof:placetype":"venue"
},
  "geometry": {"coordinates":[-93.259232,44.885372],"type":"Point"}
}