{
  "type": "Feature",
  "properties": {
    "addr:full":"810 S 7th St Minneapolis MN 55415",
    "addr:housenumber":"810",
    "addr:postcode":"55415",
    "addr:street":"S 7Th St",
    "iso:country":"US",
    "sg:address":"810 S 7th St",
    "sg:city":"Minneapolis",
    "sg:classifiers":[
        {
            "category":"Organizations",
            "subcategory":"Religious Organization",
            "type":"Services"
        }
    ],
    "sg:phone":"+1 612 278 1722",
    "sg:postcode":"55415",
    "sg:province":"MN",
    "wof:name":"Life Center of Prayer Inc",
    "wof:placetype":"venue"
},
  "geometry": {"coordinates":[-93.261002,44.972],"type":"Point"}
}