{
  "type": "Feature",
  "properties": {
    "iso:country":"US",
    "sg:address":"329 E Lake St",
    "sg:city":"Blaine",
    "sg:classifiers":[
        {
            "category":"Retail",
            "subcategory":"Auto Repair",
            "type":"Services"
        }
    ],
    "sg:phone":"+1 763 862 0300",
    "sg:postcode":"55408",
    "sg:province":"MN",
    "sg:tags":[
        "wrecker"
    ],
    "wof:name":"AAA Complete Towing",
    "wof:placetype":"venue"
},
  "geometry": {"coordinates":[-93.27040100000001,44.948278],"type":"Point"}
}