{
  "type": "Feature",
  "properties": {
    "iso:country":"US",
    "sg:address":"430 1st Ave N Ste 550",
    "sg:city":"Minneapolis",
    "sg:classifiers":[
        {
            "category":"Professional",
            "subcategory":"Business Services",
            "type":"Services"
        },
        {
            "category":"Wholesale",
            "subcategory":"Books, Periodicals, & Newspapers",
            "type":"Manufacturing & Wholesale Goods"
        }
    ],
    "sg:phone":"+1 612 338 8300",
    "sg:postcode":"55401",
    "sg:province":"MN",
    "sg:tags":[
        "consultant",
        "publishing",
        "representative",
        "publisher"
    ],
    "sg:website":"http://www.jlconline.com",
    "wof:name":"Hanley-Wood Custom Publishing",
    "wof:placetype":"venue"
},
  "geometry": {"coordinates":[-93.272885,44.980982],"type":"Point"}
}