{
  "type": "Feature",
  "properties": {
    "addr:full":"550 Vandalia St Saint Paul MN 55114",
    "addr:housenumber":"550",
    "addr:postcode":"55114",
    "addr:street":"Vandalia St",
    "iso:country":"US",
    "sg:address":"550 Vandalia St",
    "sg:city":"Saint Paul",
    "sg:classifiers":[
        {
            "category":"Communications",
            "type":"Services"
        }
    ],
    "sg:phone":"+1 651 287 0898",
    "sg:postcode":"55114",
    "sg:province":"MN",
    "sg:tags":[
        "recording",
        "rehearsal",
        "studio"
    ],
    "wof:name":"Another Level Records",
    "wof:placetype":"venue"
},
  "geometry": {"coordinates":[-93.191597,44.958302],"type":"Point"}
}