{
  "type": "Feature",
  "properties": {
    "iso:country":"US",
    "sg:address":"1009 East Ave",
    "sg:city":"Red Wing",
    "sg:classifiers":[
        {
            "category":"Retail",
            "subcategory":"Repair Shop",
            "type":"Services"
        }
    ],
    "sg:phone":"+1 651 388 6468",
    "sg:postcode":"55066",
    "sg:province":"MN",
    "sg:tags":[
        "lock",
        "locksmith"
    ],
    "wof:name":"B & K Key Shop",
    "wof:placetype":"venue"
},
  "geometry": {"coordinates":[-92.528938,44.558745],"type":"Point"}
}