{
  "type": "Feature",
  "properties": {
    "addr:full":"8220 Co Rd 101 Eden Prairie MN 55311",
    "addr:housenumber":"8220;101",
    "addr:postcode":"55311",
    "addr:street":"Co Rd",
    "iso:country":"US",
    "sg:address":"8220 Co Rd 101",
    "sg:city":"Eden Prairie",
    "sg:classifiers":[
        {
            "category":"Retail",
            "subcategory":"Auto Repair",
            "type":"Services"
        }
    ],
    "sg:phone":"+1 952 941 9238",
    "sg:postcode":"55311",
    "sg:province":"MN",
    "sg:tags":[
        "automotive",
        "inspection"
    ],
    "wof:name":"Inspection Services of America",
    "wof:placetype":"venue"
},
  "geometry": {"coordinates":[-93.51191,45.106202],"type":"Point"}
}