{
  "type": "Feature",
  "properties": {
    "addr:full":"13775 Frontier Ct Burnsville MN 55337",
    "addr:housenumber":"13775",
    "addr:postcode":"55337",
    "addr:street":"Frontier Ct",
    "iso:country":"US",
    "sg:address":"13775 Frontier Ct",
    "sg:city":"Burnsville",
    "sg:classifiers":[
        {
            "category":"Retail",
            "subcategory":"Photofinishing",
            "type":"Services"
        },
        {
            "category":"Professional",
            "subcategory":"Printing & Photocopies",
            "type":"Services"
        }
    ],
    "sg:phone":"+1 952 891 8700",
    "sg:postcode":"55337",
    "sg:province":"MN",
    "sg:tags":[
        "photo",
        "services-commercial",
        "duplicating",
        "copying",
        "laboratories-commercial"
    ],
    "sg:website":"http://www.cornerstonecopy.com",
    "wof:name":"Cornerstone Copy Center of Burnsville",
    "wof:placetype":"venue"
},
  "geometry": {"coordinates":[-93.25124700000001,44.754124],"type":"Point"}
}