{
  "type": "Feature",
  "properties": {
    "addr:full":"1001 Center Ave Moorhead MN 56560",
    "addr:housenumber":"1001",
    "addr:postcode":"56560",
    "addr:street":"Center Ave",
    "iso:country":"US",
    "sg:address":"1001 Center Ave",
    "sg:city":"Moorhead",
    "sg:classifiers":[
        {
            "category":"Wholesale",
            "subcategory":"Farm Supplies",
            "type":"Manufacturing & Wholesale Goods"
        }
    ],
    "sg:phone":"+1 218 233 3145",
    "sg:postcode":"56560",
    "sg:province":"MN",
    "sg:tags":[
        "bean"
    ],
    "wof:name":"ADM",
    "wof:placetype":"venue"
},
  "geometry": {"coordinates":[-96.76270700000001,46.87504],"type":"Point"}
}