{
  "type": "Feature",
  "properties": {
    "addr:full":"811 21st St SE Rochester MN 55904",
    "addr:housenumber":"811",
    "addr:postcode":"55904",
    "addr:street":"21St St Se",
    "iso:country":"US",
    "sg:address":"811 21st St SE",
    "sg:city":"Rochester",
    "sg:classifiers":[
        {
            "category":"Social Services",
            "subcategory":"Child Care",
            "type":"Services"
        }
    ],
    "sg:phone":"+1 507 289 3850",
    "sg:postcode":"55904",
    "sg:province":"MN",
    "sg:tags":[
        "day"
    ],
    "wof:name":"Luann C Haack",
    "wof:placetype":"venue"
},
  "geometry": {"coordinates":[-92.449743,43.992136],"type":"Point"}
}