{
  "type": "Feature",
  "properties": {
    "iso:country":"US",
    "sg:address":"4147 Minnehaha Ave",
    "sg:city":"Minneapolis",
    "sg:classifiers":[
        {
            "category":"Retail",
            "subcategory":"Auto Repair",
            "type":"Services"
        }
    ],
    "sg:phone":"+1 612 722 5182",
    "sg:postcode":"55406",
    "sg:province":"MN",
    "sg:tags":[
        "body",
        "repairing",
        "painting",
        "automobile"
    ],
    "wof:name":"Body Repair",
    "wof:placetype":"venue"
},
  "geometry": {"coordinates":[-93.218886,44.927617],"type":"Point"}
}