{
  "type": "Feature",
  "properties": {
    "iso:country":"US",
    "sg:address":"2900 Rice St",
    "sg:city":"Saint Paul",
    "sg:classifiers":[
        {
            "category":"Recreation",
            "type":"Entertainment"
        }
    ],
    "sg:phone":"+1 651 481 1500",
    "sg:postcode":"55113",
    "sg:province":"MN",
    "wof:name":"Lees World Tae Kwondo",
    "wof:placetype":"venue"
},
  "geometry": {"coordinates":[-93.106173,45.031582],"type":"Point"}
}