{
  "type": "Feature",
  "properties": {
    "iso:country":"US",
    "sg:address":"4147 Ruby Ln",
    "sg:city":"Eagan",
    "sg:classifiers":[
        {
            "category":"Health Services",
            "subcategory":"Health Practitioner",
            "type":"Services"
        }
    ],
    "sg:phone":"+1 651 405 0114",
    "sg:postcode":"55122",
    "sg:province":"MN",
    "sg:tags":[
        "psychologist"
    ],
    "wof:name":"Claire Birkeland",
    "wof:placetype":"venue"
},
  "geometry": {"coordinates":[-93.199684,44.806912],"type":"Point"}
}