{
  "type": "Feature",
  "properties": {
    "addr:full":"30922 Co Hwy 37 Brooten MN 56316",
    "addr:housenumber":"30922",
    "addr:postcode":"56316",
    "addr:street":"Co Hwy 37",
    "iso:country":"US",
    "sg:address":"30922 Co Hwy 37",
    "sg:city":"Brooten",
    "sg:classifiers":[
        {
            "category":"Farming",
            "subcategory":"Livestock Farm",
            "type":"Manufacturing & Wholesale Goods"
        }
    ],
    "sg:phone":"+1 320 346 2418",
    "sg:postcode":"56316",
    "sg:province":"MN",
    "sg:tags":[
        "beef",
        "feedlot",
        "cattle"
    ],
    "wof:name":"David Solbreken",
    "wof:placetype":"venue"
},
  "geometry": {"coordinates":[-95.19346899999999,45.465914],"type":"Point"}
}