{
  "type": "Feature",
  "properties": {
    "iso:country":"US",
    "sg:address":"20539 County 10 Blvd",
    "sg:city":"Zumbrota",
    "sg:classifiers":[
        {
            "category":"Social Services",
            "subcategory":"Child Care",
            "type":"Services"
        }
    ],
    "sg:phone":"+1 507 732 7143",
    "sg:postcode":"55992",
    "sg:province":"MN",
    "sg:tags":[
        "daycare",
        "provider"
    ],
    "wof:name":"Susan Flotterud",
    "wof:placetype":"venue"
},
  "geometry": {"coordinates":[-92.616027,44.293544],"type":"Point"}
}