{
  "type": "Feature",
  "properties": {
    "iso:country":"US",
    "sg:address":"50 France",
    "sg:city":"Minneapolis",
    "sg:classifiers":[
        {
            "category":"Shopping",
            "subcategory":"Shoes",
            "type":"Retail Goods"
        }
    ],
    "sg:phone":"+1 952 922 5574",
    "sg:postcode":"55410",
    "sg:province":"MN",
    "sg:tags":[
        "store"
    ],
    "sg:website":"www.baystreetshoes.com",
    "wof:name":"Bay Street Shoes & Accessories",
    "wof:placetype":"venue"
},
  "geometry": {"coordinates":[-93.31880200000001,44.909599],"type":"Point"}
}