{
  "type": "Feature",
  "properties": {
    "addr:full":"60 W Sycamore St St Paul MN 55117",
    "addr:housenumber":"60",
    "addr:postcode":"55117",
    "addr:street":"W Sycamore St",
    "iso:country":"US",
    "sg:address":"60 W Sycamore St",
    "sg:city":"St Paul",
    "sg:classifiers":[
        {
            "category":"Home & Garden",
            "subcategory":"Household Appliances",
            "type":"Retail Goods"
        }
    ],
    "sg:phone":"+1 651 222 0011",
    "sg:postcode":"55117",
    "sg:province":"MN",
    "sg:website":"www.warnersstellian.com",
    "wof:name":"Warners Stellian Appliance Co",
    "wof:placetype":"venue"
},
  "geometry": {"coordinates":[-93.10305099999999,44.964724],"type":"Point"}
}