{
  "type": "Feature",
  "properties": {
    "addr:full":"6334 Halifax Ave S Minneapolis MN 55424",
    "addr:housenumber":"6334",
    "addr:postcode":"55424",
    "addr:street":"Halifax Ave S",
    "iso:country":"US",
    "sg:address":"6334 Halifax Ave S",
    "sg:city":"Minneapolis",
    "sg:classifiers":[
        {
            "category":"Building & Trades",
            "subcategory":"Construction",
            "type":"Services"
        }
    ],
    "sg:phone":"+1 952 927 4620",
    "sg:postcode":"55424",
    "sg:province":"MN",
    "sg:tags":[
        "concrete",
        "contractor"
    ],
    "wof:name":"Findell Cement Inc",
    "wof:placetype":"venue"
},
  "geometry": {"coordinates":[-93.330606,44.889729],"type":"Point"}
}