{
  "type": "Feature",
  "properties": {
    "iso:country":"US",
    "sg:address":"320 4th St SW",
    "sg:city":"Willmar",
    "sg:classifiers":[
        {
            "category":"Government",
            "subcategory":"Office",
            "type":"Public Place"
        }
    ],
    "sg:phone":"+1 320 235 1061",
    "sg:postcode":"56201",
    "sg:province":"MN",
    "wof:name":"Congressman Collin C Peterson",
    "wof:placetype":"venue"
},
  "geometry": {"coordinates":[-95.048064,45.121205],"type":"Point"}
}