{
  "type": "Feature",
  "properties": {
    "addr:full":"24428 Greenway Ave Forest Lake MN 55025",
    "addr:housenumber":"24428",
    "addr:postcode":"55025",
    "addr:street":"Greenway Ave",
    "iso:country":"US",
    "sg:address":"24428 Greenway Ave",
    "sg:city":"Forest Lake",
    "sg:classifiers":[
        {
            "category":"Building & Trades",
            "subcategory":"Plumbing",
            "type":"Services"
        }
    ],
    "sg:phone":"+1 651 464 2988",
    "sg:postcode":"55025",
    "sg:province":"MN",
    "sg:tags":[
        "plumbing",
        "contractor"
    ],
    "wof:name":"Commercial Plumbing & Heating",
    "wof:placetype":"venue"
},
  "geometry": {"coordinates":[-92.97487700000001,45.309664],"type":"Point"}
}