{
  "type": "Feature",
  "properties": {
    "addr:full":"210 4th St NE Austin MN 55912",
    "addr:housenumber":"210",
    "addr:postcode":"55912",
    "addr:street":"4Th St Ne",
    "iso:country":"US",
    "sg:address":"210 4th St NE",
    "sg:city":"Austin",
    "sg:classifiers":[
        {
            "category":"Social Services",
            "type":"Services"
        }
    ],
    "sg:phone":"+1 507 437 1900",
    "sg:postcode":"55912",
    "sg:province":"MN",
    "sg:tags":[
        "youth",
        "organization",
        "center"
    ],
    "wof:name":"Extreme Youth Ctr",
    "wof:placetype":"venue"
},
  "geometry": {"coordinates":[-92.96973,43.668224],"type":"Point"}
}