{
  "type": "Feature",
  "properties": {
    "addr:full":"4615 Cottonwood Ln N Minneapolis MN 55442",
    "addr:housenumber":"4615",
    "addr:postcode":"55442",
    "addr:street":"Cottonwood Ln N",
    "iso:country":"US",
    "sg:address":"4615 Cottonwood Ln N",
    "sg:city":"Minneapolis",
    "sg:classifiers":[
        {
            "category":"Professional",
            "subcategory":"Business Services",
            "type":"Services"
        }
    ],
    "sg:phone":"+1 763 557 9062",
    "sg:postcode":"55442",
    "sg:province":"MN",
    "wof:name":"Jack Manders and Associates",
    "wof:placetype":"venue"
},
  "geometry": {"coordinates":[-93.425315,45.039743],"type":"Point"}
}