{
  "type": "Feature",
  "properties": {
    "iso:country":"US",
    "sg:address":"10 S 5th St Suite 525",
    "sg:city":"Minneapolis",
    "sg:classifiers":[
        {
            "category":"Professional",
            "subcategory":"Lawyer & Legal Services",
            "type":"Services"
        }
    ],
    "sg:phone":"+1 612 392 9629",
    "sg:postcode":"55402",
    "sg:province":"MN",
    "sg:tags":[
        "practice",
        "attorney",
        "criminal",
        "law"
    ],
    "sg:website":"http://www.tinaappleby.com",
    "wof:name":"Allan Caplan & Assoc",
    "wof:placetype":"venue"
},
  "geometry": {"coordinates":[-93.271004,44.979069],"type":"Point"}
}