{
  "type": "Feature",
  "properties": {
    "addr:full":"7694 160th St W Lakeville MN 55044",
    "addr:housenumber":"7694",
    "addr:postcode":"55044",
    "addr:street":"160Th St W",
    "iso:country":"US",
    "sg:address":"7694 160th St W",
    "sg:city":"Lakeville",
    "sg:classifiers":[
        {
            "category":"Shopping",
            "subcategory":"Clothing, Apparel, & Fashions",
            "type":"Retail Goods"
        }
    ],
    "sg:phone":"+1 952 953 2099",
    "sg:postcode":"55044",
    "sg:province":"MN",
    "sg:tags":[
        "costume"
    ],
    "sg:website":"www.stardanceapparel.com",
    "wof:name":"Star Dance Apparel",
    "wof:placetype":"venue"
},
  "geometry": {"coordinates":[-93.221434,44.717217],"type":"Point"}
}