{
  "type": "Feature",
  "properties": {
    "addr:full":"888 Arbor Dr Chaska MN 55318",
    "addr:housenumber":"888",
    "addr:postcode":"55318",
    "addr:street":"Arbor Dr",
    "iso:country":"US",
    "sg:address":"888 Arbor Dr",
    "sg:city":"Chaska",
    "sg:classifiers":[
        {
            "category":"Sports & Exercise",
            "subcategory":"Ice Rink",
            "type":"Entertainment"
        },
        {
            "category":"Education",
            "subcategory":"School",
            "type":"Public Place"
        }
    ],
    "sg:phone":"+1 952 466 9914",
    "sg:postcode":"55318",
    "sg:province":"MN",
    "sg:tags":[
        "skating"
    ],
    "wof:name":"The Hockey Training Center",
    "wof:placetype":"venue"
},
  "geometry": {"coordinates":[-93.581699,44.804355],"type":"Point"}
}