{
  "type": "Feature",
  "properties": {
    "addr:full":"721 33rd St S Saint Cloud MN 56301",
    "addr:housenumber":"721",
    "addr:postcode":"56301",
    "addr:street":"33Rd St S",
    "iso:country":"US",
    "sg:address":"721 33rd St S",
    "sg:city":"Saint Cloud",
    "sg:classifiers":[
        {
            "category":"Personal",
            "subcategory":"Beauty Salon",
            "type":"Services"
        }
    ],
    "sg:phone":"+1 320 654 1700",
    "sg:postcode":"56301",
    "sg:province":"MN",
    "sg:tags":[
        "shop"
    ],
    "wof:name":"Frankies Skin Care",
    "wof:placetype":"venue"
},
  "geometry": {"coordinates":[-94.15577999999999,45.515014],"type":"Point"}
}