{
  "type": "Feature",
  "properties": {
    "addr:full":"9050 93rd Ave N Brooklyn Park MN 55445",
    "addr:housenumber":"9050",
    "addr:postcode":"55445",
    "addr:street":"93Rd Ave N",
    "iso:country":"US",
    "sg:address":"9050 93rd Ave N",
    "sg:city":"Brooklyn Park",
    "sg:classifiers":[
        {
            "category":"Education",
            "subcategory":"School",
            "type":"Public Place"
        }
    ],
    "sg:phone":"+1 763 425 3970",
    "sg:postcode":"55445",
    "sg:province":"MN",
    "sg:website":"www.saintvdp.org",
    "wof:name":"St Vincent De Paul School",
    "wof:placetype":"venue"
},
  "geometry": {"coordinates":[-93.385457,45.123414],"type":"Point"}
}