{
  "type": "Feature",
  "properties": {
    "iso:country":"US",
    "sg:address":"6601 Shingle Creek Pkwy # 1400",
    "sg:city":"Minneapolis",
    "sg:classifiers":[
        {
            "category":"Banks & Credit Unions",
            "subcategory":"Financial Services",
            "type":"Services"
        }
    ],
    "sg:phone":"+1 763 549 7100",
    "sg:postcode":"55430",
    "sg:province":"MN",
    "sg:tags":[
        "money",
        "order"
    ],
    "wof:name":"Moneygram Payment Systems, Inc.",
    "wof:placetype":"venue"
},
  "geometry": {"coordinates":[-93.30555699999999,45.074829],"type":"Point"}
}