{
  "type": "Feature",
  "properties": {
    "addr:full":"2301 Central Ave NE Minneapolis MN 55418",
    "addr:housenumber":"2301",
    "addr:postcode":"55418",
    "addr:street":"Central Ave Ne",
    "iso:country":"US",
    "sg:address":"2301 Central Ave NE",
    "sg:city":"Minneapolis",
    "sg:classifiers":[
        {
            "category":"Retail",
            "subcategory":"Funeral Services",
            "type":"Services"
        }
    ],
    "sg:phone":"+1 763 447 4003",
    "sg:postcode":"55418",
    "sg:province":"MN",
    "sg:tags":[
        "director",
        "supply"
    ],
    "sg:website":"http://www.dexknows.com/rd?dku=http://caringcremationcenter.net%3Fmkt=65901",
    "wof:name":"Caring Cremation Center",
    "wof:placetype":"venue"
},
  "geometry": {"coordinates":[-93.24736,45.01086],"type":"Point"}
}