{
  "type": "Feature",
  "properties": {
    "addr:full":"6536 Timberline Trl Finland MN 55603",
    "addr:housenumber":"6536",
    "addr:postcode":"55603",
    "addr:street":"Timberline Trl",
    "iso:country":"US",
    "sg:address":"6536 Timberline Trl",
    "sg:city":"Finland",
    "sg:classifiers":[
        {
            "category":"Coffee & Tea",
            "type":"Food & Drink"
        },
        {
            "category":"Restaurant",
            "type":"Food & Drink"
        }
    ],
    "sg:phone":"+1 218 353 7640",
    "sg:postcode":"55603",
    "sg:province":"MN",
    "sg:tags":[
        "espresso"
    ],
    "wof:name":"Rosie S Cafe Lutsen Mts",
    "wof:placetype":"venue"
},
  "geometry": {"coordinates":[-91.21428299999999,47.403009],"type":"Point"}
}