{
  "type": "Feature",
  "properties": {
    "iso:country":"US",
    "sg:address":"123 Columbia Ct Ste 201",
    "sg:city":"Chaska",
    "sg:classifiers":[
        {
            "category":"Shopping",
            "subcategory":"Computers & Home Electronics",
            "type":"Retail Goods"
        }
    ],
    "sg:phone":"+1 952 448 5323",
    "sg:postcode":"55318",
    "sg:province":"MN",
    "wof:name":"Acoustical Surfaces",
    "wof:placetype":"venue"
},
  "geometry": {"coordinates":[-93.611397,44.8097],"type":"Point"}
}