{
  "type": "Feature",
  "properties": {
    "addr:full":"501 W 4th St Winona MN 55987",
    "addr:housenumber":"501",
    "addr:postcode":"55987",
    "addr:street":"W 4Th St",
    "iso:country":"US",
    "sg:address":"501 W 4th St",
    "sg:city":"Winona",
    "sg:classifiers":[
        {
            "category":"Food & Beverages",
            "subcategory":"Liquor & Beverages",
            "type":"Retail Goods"
        },
        {
            "category":"Bars & Pubs",
            "type":"Food & Drink"
        }
    ],
    "sg:phone":"+1 507 454 4380",
    "sg:postcode":"55987",
    "sg:province":"MN",
    "sg:tags":[
        "alcoholic"
    ],
    "wof:name":"Steve's Bar",
    "wof:placetype":"venue"
},
  "geometry": {"coordinates":[-91.65175000000001,44.05498],"type":"Point"}
}