{
  "type": "Feature",
  "properties": {
    "iso:country":"US",
    "sg:address":"509 W 5th St",
    "sg:city":"Red Wing",
    "sg:classifiers":[
        {
            "category":"Government",
            "subcategory":"Office",
            "type":"Public Place"
        }
    ],
    "sg:phone":"+1 651 385 3104",
    "sg:postcode":"55066",
    "sg:province":"MN",
    "sg:tags":[
        "county",
        "planning",
        "dev"
    ],
    "wof:name":"Goodhue County Zoning & Bldg",
    "wof:placetype":"venue"
},
  "geometry": {"coordinates":[-92.533906,44.562312],"type":"Point"}
}