{
  "type": "Feature",
  "properties": {
    "iso:country":"US",
    "sg:address":"34999 Co Rd 186",
    "sg:city":"Melrose",
    "sg:classifiers":[
        {
            "category":"Farming",
            "subcategory":"Dairy Farm",
            "type":"Manufacturing & Wholesale Goods"
        }
    ],
    "sg:phone":"+1 320 256 3892",
    "sg:postcode":"56352",
    "sg:province":"MN",
    "wof:name":"Joseph Roelike",
    "wof:placetype":"venue"
},
  "geometry": {"coordinates":[-94.84105700000001,45.672782],"type":"Point"}
}