{
  "type": "Feature",
  "properties": {
    "iso:country":"US",
    "sg:address":"4400 Lake Dr",
    "sg:city":"Minneapolis",
    "sg:classifiers":[
        {
            "category":"Professional",
            "type":"Services"
        },
        {
            "category":"Personal",
            "type":"Services"
        },
        {
            "category":"Building & Trades",
            "subcategory":"Construction",
            "type":"Services"
        }
    ],
    "sg:phone":"+1 763 504 2730",
    "sg:postcode":"55422",
    "sg:province":"MN",
    "sg:tags":[
        "skylight"
    ],
    "wof:name":"Small Job Specialist Inc",
    "wof:placetype":"venue"
},
  "geometry": {"coordinates":[-93.334356,45.034241],"type":"Point"}
}