{
  "type": "Feature",
  "properties": {
    "addr:full":"9819 Joliet Ave N Stillwater MN 55082",
    "addr:housenumber":"9819",
    "addr:postcode":"55082",
    "addr:street":"Joliet Ave N",
    "iso:country":"US",
    "sg:address":"9819 Joliet Ave N",
    "sg:city":"Stillwater",
    "sg:classifiers":[
        {
            "category":"Shopping",
            "subcategory":"Used Merchandise",
            "type":"Retail Goods"
        }
    ],
    "sg:phone":"+1 651 762 2936",
    "sg:postcode":"55082",
    "sg:province":"MN",
    "wof:name":"Jazzy Junk",
    "wof:placetype":"venue"
},
  "geometry": {"coordinates":[-92.90963499999999,45.093725],"type":"Point"}
}