{
  "type": "Feature",
  "properties": {
    "iso:country":"US",
    "sg:address":"604 E 11th St",
    "sg:city":"Duluth",
    "sg:classifiers":[
        {
            "category":"Banks & Credit Unions",
            "subcategory":"Investment Brokerage",
            "type":"Services"
        },
        {
            "category":"Insurance",
            "subcategory":"Hazard Insurance",
            "type":"Services"
        }
    ],
    "sg:phone":"+1 218 723 8874",
    "sg:postcode":"55805",
    "sg:province":"MN",
    "sg:tags":[
        "agent",
        "resume"
    ],
    "wof:name":"Longstreet, Klayton Farmers Insurance Agent",
    "wof:placetype":"venue"
},
  "geometry": {"coordinates":[-92.10271400000001,46.800049],"type":"Point"}
}