{
  "type": "Feature",
  "properties": {
    "iso:country":"US",
    "sg:address":"7022 Brooklyn Blvd",
    "sg:city":"Brooklyn Center",
    "sg:classifiers":[
        {
            "category":"Professional",
            "subcategory":"Lawyer & Legal Services",
            "type":"Services"
        }
    ],
    "sg:phone":"+1 763 566 4570",
    "sg:postcode":"55429",
    "sg:province":"MN",
    "sg:tags":[
        "attorney"
    ],
    "wof:name":"Lawrence P Marofsky Law Office",
    "wof:placetype":"venue"
},
  "geometry": {"coordinates":[-93.340901,45.083931],"type":"Point"}
}