{
  "type": "Feature",
  "properties": {
    "addr:full":"1983 Sloan St Saint Paul MN 55117",
    "addr:housenumber":"1983",
    "addr:postcode":"55117",
    "addr:street":"Sloan St",
    "iso:country":"US",
    "sg:address":"1983 Sloan St",
    "sg:city":"Saint Paul",
    "sg:classifiers":[
        {
            "category":"Railroad",
            "type":"Transportation"
        }
    ],
    "sg:phone":"+1 651 772 5976",
    "sg:postcode":"55117",
    "sg:province":"MN",
    "sg:tags":[
        "rail"
    ],
    "wof:name":"Canadian Pacific Railway",
    "wof:placetype":"venue"
},
  "geometry": {"coordinates":[-93.08819099999999,44.998229],"type":"Point"}
}