{
  "type": "Feature",
  "properties": {
    "iso:country":"US",
    "sg:address":"23921 Bulrush Dr",
    "sg:city":"Merrifield",
    "sg:classifiers":[
        {
            "category":"Professional",
            "type":"Services"
        }
    ],
    "sg:phone":"+1 218 765 3865",
    "sg:postcode":"56465",
    "sg:province":"MN",
    "sg:tags":[
        "establishment"
    ],
    "wof:name":"Wild Oaks",
    "wof:placetype":"venue"
},
  "geometry": {"coordinates":[-94.14427999999999,46.499637],"type":"Point"}
}