{
  "type": "Feature",
  "properties": {
    "addr:full":"6806 Drew Ave N Brooklyn Center MN 55429",
    "addr:housenumber":"6806",
    "addr:postcode":"55429",
    "addr:street":"Drew Ave N",
    "iso:country":"US",
    "sg:address":"6806 Drew Ave N",
    "sg:city":"Brooklyn Center",
    "sg:classifiers":[
        {
            "category":"Professional",
            "subcategory":"Computer Services",
            "type":"Services"
        }
    ],
    "sg:phone":"+1 612 701 8855",
    "sg:postcode":"55429",
    "sg:province":"MN",
    "sg:tags":[
        "consultant",
        "designer",
        "related"
    ],
    "wof:name":"Omnicom International",
    "wof:placetype":"venue"
},
  "geometry": {"coordinates":[-93.327877,45.080023],"type":"Point"}
}