{
  "type": "Feature",
  "properties": {
    "addr:full":"718 20th St NW Faribault MN 55021",
    "addr:housenumber":"718",
    "addr:postcode":"55021",
    "addr:street":"20Th St Nw",
    "iso:country":"US",
    "sg:address":"718 20th St NW",
    "sg:city":"Faribault",
    "sg:classifiers":[
        {
            "category":"Manufacturing",
            "subcategory":"Glass & Minerals",
            "type":"Manufacturing & Wholesale Goods"
        }
    ],
    "sg:phone":"+1 507 334 0046",
    "sg:postcode":"55021",
    "sg:province":"MN",
    "sg:tags":[
        "concrete",
        "product",
        "mfg"
    ],
    "wof:name":"Custom Precast and Masonary",
    "wof:placetype":"venue"
},
  "geometry": {"coordinates":[-93.279466,44.312512],"type":"Point"}
}