{
  "type": "Feature",
  "properties": {
    "addr:full":"409 17th St W Hastings MN 55033",
    "addr:housenumber":"409",
    "addr:postcode":"55033",
    "addr:street":"17Th St W",
    "iso:country":"US",
    "sg:address":"409 17th St W",
    "sg:city":"Hastings",
    "sg:classifiers":[
        {
            "category":"Retail",
            "subcategory":"Laundry & Dry Cleaning",
            "type":"Services"
        },
        {
            "category":"Building & Trades",
            "subcategory":"Cleaning & Sanitation",
            "type":"Services"
        }
    ],
    "sg:phone":"+1 651 437 8814",
    "sg:postcode":"55033",
    "sg:province":"MN",
    "sg:tags":[
        "cleaner",
        "house"
    ],
    "wof:name":"Dees Cleaning Services",
    "wof:placetype":"venue"
},
  "geometry": {"coordinates":[-92.856495,44.72871],"type":"Point"}
}