{
  "type": "Feature",
  "properties": {
    "addr:full":"1405 7th Ave E Alexandria MN 56308",
    "addr:housenumber":"1405",
    "addr:postcode":"56308",
    "addr:street":"7Th Ave E",
    "iso:country":"US",
    "sg:address":"1405 7th Ave E",
    "sg:city":"Alexandria",
    "sg:classifiers":[
        {
            "category":"Real Estate",
            "subcategory":"Real Estate Operator",
            "type":"Services"
        }
    ],
    "sg:phone":"+1 320 766 7774",
    "sg:postcode":"56308",
    "sg:province":"MN",
    "sg:tags":[
        "apartment"
    ],
    "wof:name":"Woodhill Apartments",
    "wof:placetype":"venue"
},
  "geometry": {"coordinates":[-95.35785,45.884659],"type":"Point"}
}