{
  "type": "Feature",
  "properties": {
    "iso:country":"US",
    "sg:address":"8645 239th Ln NE",
    "sg:city":"Stacy",
    "sg:classifiers":[
        {
            "category":"Retail",
            "subcategory":"Auto Repair",
            "type":"Services"
        }
    ],
    "sg:phone":"+1 651 462 3832",
    "sg:postcode":"55079",
    "sg:province":"MN",
    "sg:tags":[
        "body"
    ],
    "wof:name":"G & A Color Tech Inc",
    "wof:placetype":"venue"
},
  "geometry": {"coordinates":[-93.049278,45.402803],"type":"Point"}
}