{
  "type": "Feature",
  "properties": {
    "addr:full":"3700 Alabama Ave S Minneapolis MN 55416",
    "addr:housenumber":"3700",
    "addr:postcode":"55416",
    "addr:street":"Alabama Ave S",
    "iso:country":"US",
    "sg:address":"3700 Alabama Ave S",
    "sg:city":"Minneapolis",
    "sg:classifiers":[
        {
            "category":"Social Services",
            "subcategory":"Child Care",
            "type":"Services"
        }
    ],
    "sg:phone":"+1 952 929 7636",
    "sg:postcode":"55416",
    "sg:province":"MN",
    "sg:tags":[
        "day"
    ],
    "wof:name":"Kid Zone Child Care",
    "wof:placetype":"venue"
},
  "geometry": {"coordinates":[-93.356201,44.936501],"type":"Point"}
}