{
  "type": "Feature",
  "properties": {
    "iso:country":"US",
    "sg:address":"9850 Co Rd 135",
    "sg:city":"Young America",
    "sg:classifiers":[
        {
            "category":"Farming",
            "subcategory":"Dairy Farm",
            "type":"Manufacturing & Wholesale Goods"
        }
    ],
    "sg:phone":"+1 952 467 3597",
    "sg:postcode":"55397",
    "sg:province":"MN",
    "wof:name":"Norman Willems",
    "wof:placetype":"venue"
},
  "geometry": {"coordinates":[-93.92916200000001,44.826841],"type":"Point"}
}