{
  "type": "Feature",
  "properties": {
    "addr:full":"16623 200th St Red Lake Falls MN 56726",
    "addr:housenumber":"16623",
    "addr:postcode":"56726",
    "addr:street":"200Th St",
    "iso:country":"US",
    "sg:address":"16623 200th St",
    "sg:city":"Red Lake Falls",
    "sg:classifiers":[
        {
            "category":"Farming",
            "subcategory":"Livestock Farm",
            "type":"Manufacturing & Wholesale Goods"
        }
    ],
    "sg:phone":"+1 218 253 2297",
    "sg:postcode":"56726",
    "sg:province":"MN",
    "sg:tags":[
        "beef",
        "feedlot",
        "cattle"
    ],
    "wof:name":"Ronald Freyholtz",
    "wof:placetype":"venue"
},
  "geometry": {"coordinates":[-96.24683899999999,48.691325],"type":"Point"}
}