{
  "type": "Feature",
  "properties": {
    "iso:country":"US",
    "sg:address":"15435 224th St",
    "sg:city":"Cold Spring",
    "sg:classifiers":[
        {
            "category":"Building & Trades",
            "subcategory":"Electrical",
            "type":"Services"
        }
    ],
    "sg:phone":"+1 320 685 3950",
    "sg:postcode":"56320",
    "sg:province":"MN",
    "sg:tags":[
        "electric",
        "contractor"
    ],
    "wof:name":"Welle Electric",
    "wof:placetype":"venue"
},
  "geometry": {"coordinates":[-94.425991,45.447138],"type":"Point"}
}