{
  "type": "Feature",
  "properties": {
    "addr:full":"1521 Sherburne Dr Saint Cloud MN 56304",
    "addr:housenumber":"1521",
    "addr:postcode":"56304",
    "addr:street":"Sherburne Dr",
    "iso:country":"US",
    "sg:address":"1521 Sherburne Dr",
    "sg:city":"Saint Cloud",
    "sg:classifiers":[
        {
            "category":"Food & Beverages",
            "subcategory":"Specialty",
            "type":"Retail Goods"
        }
    ],
    "sg:phone":"+1 320 230 1926",
    "sg:postcode":"56304",
    "sg:province":"MN",
    "wof:name":"Natural Health Initiatives",
    "wof:placetype":"venue"
},
  "geometry": {"coordinates":[-94.130534,45.549713],"type":"Point"}
}