{
  "type": "Feature",
  "properties": {
    "addr:full":"14985 Glazier Ave, Ste 650, Apple Valley MN 55124",
    "addr:housenumber":"14985",
    "addr:postcode":"55124",
    "addr:street":"Glazier Ave Ste 650",
    "iso:country":"US",
    "sg:address":"14985 Glazier Ave, Ste 650,",
    "sg:city":"Apple Valley",
    "sg:classifiers":[
        {
            "category":"Banks & Credit Unions",
            "subcategory":"Investment Brokerage",
            "type":"Services"
        },
        {
            "category":"Banks & Credit Unions",
            "subcategory":"Financial Services",
            "type":"Services"
        }
    ],
    "sg:phone":"+1 952 431 6410",
    "sg:postcode":"55124",
    "sg:province":"MN",
    "sg:tags":[
        "investing",
        "advising"
    ],
    "sg:website":"ameripriseadvisors.com",
    "wof:name":"Ameriprise Financial Advisors - Jaros & Associates",
    "wof:placetype":"venue"
},
  "geometry": {"coordinates":[-93.214551,44.732774],"type":"Point"}
}