{
  "type": "Feature",
  "properties": {
    "iso:country":"US",
    "sg:address":"6433 Bergstrom Rd",
    "sg:city":"Saginaw",
    "sg:classifiers":[
        {
            "category":"Wholesale",
            "subcategory":"Construction Materials",
            "type":"Manufacturing & Wholesale Goods"
        }
    ],
    "sg:phone":"+1 218 729 7333",
    "sg:postcode":"55779",
    "sg:province":"MN",
    "wof:name":"La Hanson",
    "wof:placetype":"venue"
},
  "geometry": {"coordinates":[-92.36110100000001,46.923319],"type":"Point"}
}