{
  "type": "Feature",
  "properties": {
    "addr:full":"613 US Hwy 10 E Detroit Lakes MN 56501",
    "addr:housenumber":"613",
    "addr:postcode":"56501",
    "addr:street":"Us Hwy 10 E",
    "iso:country":"US",
    "sg:address":"613 US Hwy 10 E",
    "sg:city":"Detroit Lakes",
    "sg:classifiers":[
        {
            "category":"Banks & Credit Unions",
            "subcategory":"Investment Brokerage",
            "type":"Services"
        }
    ],
    "sg:phone":"+1 218 844 9109",
    "sg:postcode":"56501",
    "sg:province":"MN",
    "sg:tags":[
        "security"
    ],
    "wof:name":"Raymond James",
    "wof:placetype":"venue"
},
  "geometry": {"coordinates":[-95.83225400000001,46.813429],"type":"Point"}
}