{
  "type": "Feature",
  "properties": {
    "addr:full":"5890 Eureka Rd Excelsior MN 55331",
    "addr:housenumber":"5890",
    "addr:postcode":"55331",
    "addr:street":"Eureka Rd",
    "iso:country":"US",
    "sg:address":"5890 Eureka Rd",
    "sg:city":"Excelsior",
    "sg:classifiers":[
        {
            "category":"Shopping",
            "subcategory":"Stationery & Office Supplies",
            "type":"Retail Goods"
        }
    ],
    "sg:phone":"+1 952 470 7916",
    "sg:postcode":"55331",
    "sg:province":"MN",
    "sg:tags":[
        "equipment"
    ],
    "wof:name":"Lake Business Supply",
    "wof:placetype":"venue"
},
  "geometry": {"coordinates":[-93.603527,44.897171],"type":"Point"}
}