{
  "type": "Feature",
  "properties": {
    "addr:full":"978 E 4th St Winona MN 55987",
    "addr:housenumber":"978",
    "addr:postcode":"55987",
    "addr:street":"E 4Th St",
    "iso:country":"US",
    "sg:address":"978 E 4th St",
    "sg:city":"Winona",
    "sg:classifiers":[
        {
            "category":"Wholesale",
            "subcategory":"Non-durable Goods",
            "type":"Manufacturing & Wholesale Goods"
        }
    ],
    "sg:phone":"+1 507 454 6600",
    "sg:postcode":"55987",
    "sg:province":"MN",
    "sg:tags":[
        "product",
        "printing",
        "promotional",
        "screen",
        "doe"
    ],
    "sg:website":"www.formgraphics.biz",
    "wof:name":"Formgraphics Inc",
    "wof:placetype":"venue"
},
  "geometry": {"coordinates":[-91.61257000000001,44.044617],"type":"Point"}
}