{
  "type": "Feature",
  "properties": {
    "addr:full":"400 S 2nd St Princeton MN 55371",
    "addr:housenumber":"400",
    "addr:postcode":"55371",
    "addr:street":"S 2Nd St",
    "iso:country":"US",
    "sg:address":"400 S 2nd St",
    "sg:city":"Princeton",
    "sg:classifiers":[
        {
            "category":"Building & Trades",
            "subcategory":"Construction",
            "type":"Services"
        }
    ],
    "sg:phone":"+1 763 633 5898",
    "sg:postcode":"55371",
    "sg:province":"MN",
    "sg:tags":[
        "masonry",
        "contractor"
    ],
    "wof:name":"Hayes Quickstrom Masonry",
    "wof:placetype":"venue"
},
  "geometry": {"coordinates":[-93.580139,45.568386],"type":"Point"}
}