{
  "type": "Feature",
  "properties": {
    "addr:full":"560 University Ave W St Paul MN 55103",
    "addr:housenumber":"560",
    "addr:postcode":"55103",
    "addr:street":"University Ave W",
    "iso:country":"US",
    "sg:address":"560 University Ave W",
    "sg:city":"St Paul",
    "sg:classifiers":[
        {
            "category":"Shopping",
            "subcategory":"Discount & Variety Stores",
            "type":"Retail Goods"
        }
    ],
    "sg:phone":"+1 651 224 3929",
    "sg:postcode":"55103",
    "sg:province":"MN",
    "sg:tags":[
        "dollar"
    ],
    "wof:name":"Super Dollar Deals Inc",
    "wof:placetype":"venue"
},
  "geometry": {"coordinates":[-93.126351,44.955718],"type":"Point"}
}