{
  "type": "Feature",
  "properties": {
    "addr:full":"10024 County Road 81 Osseo MN 55369",
    "addr:housenumber":"10024",
    "addr:postcode":"55369",
    "addr:street":"County Road 81",
    "iso:country":"US",
    "sg:address":"10024 County Road 81",
    "sg:city":"Osseo",
    "sg:classifiers":[
        {
            "category":"Sports & Exercise",
            "subcategory":"Swimming Pool",
            "type":"Entertainment"
        }
    ],
    "sg:phone":"+1 763 424 8717",
    "sg:postcode":"55369",
    "sg:province":"MN",
    "sg:tags":[
        "diving"
    ],
    "wof:name":"Going Under Dive Center",
    "wof:placetype":"venue"
},
  "geometry": {"coordinates":[-93.41280399999999,45.119999],"type":"Point"}
}