{
  "type": "Feature",
  "properties": {
    "iso:country":"US",
    "sg:address":"2014 6th St S",
    "sg:city":"Moorhead",
    "sg:classifiers":[
        {
            "category":"Retail",
            "subcategory":"Animal Services",
            "type":"Services"
        }
    ],
    "sg:phone":"+1 218 790 4759",
    "sg:postcode":"56560",
    "sg:province":"MN",
    "sg:tags":[
        "pet",
        "crematory",
        "cemetery"
    ],
    "wof:name":"Pet Services",
    "wof:placetype":"venue"
},
  "geometry": {"coordinates":[-96.770956,46.853283],"type":"Point"}
}