{
  "type": "Feature",
  "properties": {
    "addr:full":"969 Heritage Dr Lonsdale MN 55057",
    "addr:housenumber":"969",
    "addr:postcode":"55057",
    "addr:street":"Heritage Dr",
    "iso:country":"US",
    "sg:address":"969 Heritage Dr",
    "sg:city":"Lonsdale",
    "sg:classifiers":[
        {
            "category":"Professional",
            "subcategory":"Business Services",
            "type":"Services"
        }
    ],
    "sg:phone":"+1 507 744 5452",
    "sg:postcode":"55057",
    "sg:province":"MN",
    "wof:name":"5 Guys Home Partners LLP",
    "wof:placetype":"venue"
},
  "geometry": {"coordinates":[-93.177549,44.435782],"type":"Point"}
}