{
  "type": "Feature",
  "properties": {
    "addr:full":"13767 Nicollet Ave Burnsville MN 55337",
    "addr:housenumber":"13767",
    "addr:postcode":"55337",
    "addr:street":"Nicollet Ave",
    "iso:country":"US",
    "sg:address":"13767 Nicollet Ave",
    "sg:city":"Burnsville",
    "sg:classifiers":[
        {
            "category":"Shopping",
            "subcategory":"Computers & Home Electronics",
            "type":"Retail Goods"
        }
    ],
    "sg:phone":"+1 952 892 7972",
    "sg:postcode":"55337",
    "sg:province":"MN",
    "wof:name":"P C Microtek Solutions Inc",
    "wof:placetype":"venue"
},
  "geometry": {"coordinates":[-93.277714,44.753875],"type":"Point"}
}