{
  "type": "Feature",
  "properties": {
    "iso:country":"US",
    "sg:address":"11815 Waterford Rd",
    "sg:city":"Eden Prairie",
    "sg:classifiers":[
        {
            "category":"Professional",
            "type":"Services"
        }
    ],
    "sg:phone":"+1 952 941 9859",
    "sg:postcode":"55347",
    "sg:province":"MN",
    "wof:name":"Jet Systems",
    "wof:placetype":"venue"
},
  "geometry": {"coordinates":[-93.42592,44.841123],"type":"Point"}
}