{
  "type": "Feature",
  "properties": {
    "iso:country":"US",
    "sg:address":"8151 University Ave NE",
    "sg:city":"Minneapolis",
    "sg:classifiers":[
        {
            "category":"Shopping",
            "subcategory":"Used Merchandise",
            "type":"Retail Goods"
        }
    ],
    "sg:phone":"+1 763 784 9545",
    "sg:postcode":"55432",
    "sg:province":"MN",
    "sg:tags":[
        "clothing"
    ],
    "wof:name":"Once Upon A Child",
    "wof:placetype":"venue"
},
  "geometry": {"coordinates":[-93.263468,45.115456],"type":"Point"}
}