{
  "type": "Feature",
  "properties": {
    "addr:full":"527 Rose St Duluth MN 55803",
    "addr:housenumber":"527",
    "addr:postcode":"55803",
    "addr:street":"Rose St",
    "iso:country":"US",
    "sg:address":"527 Rose St",
    "sg:city":"Duluth",
    "sg:classifiers":[
        {
            "category":"Building & Trades",
            "subcategory":"Construction",
            "type":"Services"
        }
    ],
    "sg:phone":"+1 218 525 7359",
    "sg:postcode":"55803",
    "sg:province":"MN",
    "sg:tags":[
        "heavy"
    ],
    "wof:name":"Sumac Construction",
    "wof:placetype":"venue"
},
  "geometry": {"coordinates":[-92.059715,46.839522],"type":"Point"}
}