{
  "type": "Feature",
  "properties": {
    "iso:country":"US",
    "sg:address":"1 W Lake St 75",
    "sg:city":"Minneapolis",
    "sg:classifiers":[
        {
            "category":"Real Estate",
            "subcategory":"Real Estate Services",
            "type":"Services"
        },
        {
            "category":"Professional",
            "subcategory":"Employment Agencies",
            "type":"Services"
        }
    ],
    "sg:phone":"+1 612 825 8612",
    "sg:postcode":"55408",
    "sg:province":"MN",
    "sg:tags":[
        "management",
        "condominium",
        "employer"
    ],
    "wof:name":"Intown On Lake Association",
    "wof:placetype":"venue"
},
  "geometry": {"coordinates":[-93.277931,44.94836],"type":"Point"}
}