{
  "type": "Feature",
  "properties": {
    "iso:country":"US",
    "sg:address":"27740 Co Rd 98",
    "sg:city":"Grey Eagle",
    "sg:classifiers":[
        {
            "category":"Organizations",
            "subcategory":"Religious Organization",
            "type":"Services"
        }
    ],
    "sg:phone":"+1 320 285 4731",
    "sg:postcode":"56336",
    "sg:province":"MN",
    "sg:tags":[
        "monastery",
        "convent"
    ],
    "wof:name":"Franciscan Sisters",
    "wof:placetype":"venue"
},
  "geometry": {"coordinates":[-94.807531,45.818067],"type":"Point"}
}