{
  "type": "Feature",
  "properties": {
    "addr:full":"503 South St Paynesville MN 56362",
    "addr:housenumber":"503",
    "addr:postcode":"56362",
    "addr:street":"South St",
    "iso:country":"US",
    "sg:address":"503 South St",
    "sg:city":"Paynesville",
    "sg:classifiers":[
        {
            "category":"Wholesale",
            "subcategory":"Construction Materials",
            "type":"Manufacturing & Wholesale Goods"
        }
    ],
    "sg:phone":"+1 320 243 3987",
    "sg:postcode":"56362",
    "sg:province":"MN",
    "sg:tags":[
        "sand",
        "gravel"
    ],
    "wof:name":"Koronis Sand & Gravel",
    "wof:placetype":"venue"
},
  "geometry": {"coordinates":[-94.708252,45.378554],"type":"Point"}
}