{
  "type": "Feature",
  "properties": {
    "iso:country":"US",
    "sg:address":"2724 Westwood Village",
    "sg:city":"Roseville",
    "sg:classifiers":[
        {
            "category":"Wholesale",
            "subcategory":"Furniture",
            "type":"Manufacturing & Wholesale Goods"
        }
    ],
    "sg:phone":"+1 651 402 6781",
    "sg:postcode":"55113",
    "sg:province":"MN",
    "sg:tags":[
        "equipment",
        "school"
    ],
    "wof:name":"Learning Square",
    "wof:placetype":"venue"
},
  "geometry": {"coordinates":[-93.117868,45.020811],"type":"Point"}
}