{
  "type": "Feature",
  "properties": {
    "iso:country":"US",
    "sg:address":"2495 117th St E",
    "sg:city":"Inver Grove Hts",
    "sg:classifiers":[
        {
            "category":"Utilities",
            "subcategory":"Refuse",
            "type":"Services"
        }
    ],
    "sg:phone":"+1 651 457 2778",
    "sg:postcode":"55077",
    "sg:province":"MN",
    "sg:tags":[
        "landfill"
    ],
    "wof:name":"Pine Bend Landfill Inc",
    "wof:placetype":"venue"
},
  "geometry": {"coordinates":[-93.05044599999999,44.779308],"type":"Point"}
}