{
  "type": "Feature",
  "properties": {
    "iso:country":"US",
    "sg:address":"306 4th St S",
    "sg:city":"Hoffman",
    "sg:classifiers":[
        {
            "category":"Retail",
            "subcategory":"Laundry & Dry Cleaning",
            "type":"Services"
        },
        {
            "category":"Building & Trades",
            "subcategory":"Cleaning & Sanitation",
            "type":"Services"
        }
    ],
    "sg:phone":"+1 320 986 2067",
    "sg:postcode":"56339",
    "sg:province":"MN",
    "sg:tags":[
        "cleaner",
        "house"
    ],
    "wof:name":"D L Floor Cleaning",
    "wof:placetype":"venue"
},
  "geometry": {"coordinates":[-95.787268,45.828698],"type":"Point"}
}