{
  "type": "Feature",
  "properties": {
    "addr:full":"813 3rd St Jackson MN 56143",
    "addr:housenumber":"813",
    "addr:postcode":"56143",
    "addr:street":"3Rd St",
    "iso:country":"US",
    "sg:address":"813 3rd St",
    "sg:city":"Jackson",
    "sg:classifiers":[
        {
            "category":"Retail",
            "subcategory":"Car Wash",
            "type":"Services"
        }
    ],
    "sg:phone":"+1 507 847 2301",
    "sg:postcode":"56143",
    "sg:province":"MN",
    "sg:tags":[
        "polishing",
        "washing"
    ],
    "wof:name":"Master Wash Inc",
    "wof:placetype":"venue"
},
  "geometry": {"coordinates":[-94.98927399999999,43.625155],"type":"Point"}
}