{
  "type": "Feature",
  "properties": {
    "iso:country":"US",
    "sg:address":"685 Young Dr",
    "sg:city":"Owatonna",
    "sg:classifiers":[
        {
            "category":"Professional",
            "subcategory":"Business Services",
            "type":"Services"
        }
    ],
    "sg:phone":"+1 507 451 2677",
    "sg:postcode":"55060",
    "sg:province":"MN",
    "wof:name":"Brittain & Associates",
    "wof:placetype":"venue"
},
  "geometry": {"coordinates":[-93.24427,44.078146],"type":"Point"}
}