{
  "type": "Feature",
  "properties": {
    "iso:country":"US",
    "sg:address":"4542 State Hwy 95",
    "sg:city":"Cambridge",
    "sg:classifiers":[
        {
            "category":"Manufacturing",
            "subcategory":"Lumber",
            "type":"Manufacturing & Wholesale Goods"
        }
    ],
    "sg:phone":"+1 763 689 3346",
    "sg:postcode":"55008",
    "sg:province":"MN",
    "sg:tags":[
        "timber",
        "ornamental",
        "operation",
        "nursery",
        "tract"
    ],
    "sg:website":"www.wolcyntreefarms.com",
    "wof:name":"Wolcyn Tree Farms & Nursery",
    "wof:placetype":"venue"
},
  "geometry": {"coordinates":[-93.381441,45.587011],"type":"Point"}
}