{
  "type": "Feature",
  "properties": {
    "addr:full":"21410 Oren Ave N Scandia MN 55073",
    "addr:postcode":"21410;55073",
    "addr:street":"Oren Ave N Scandia",
    "iso:country":"US",
    "sg:address":"21410 Oren Ave N",
    "sg:city":"Scandia",
    "sg:classifiers":[
        {
            "category":"Professional",
            "subcategory":"Engineering",
            "type":"Services"
        }
    ],
    "sg:phone":"+1 651 433 8148",
    "sg:postcode":"55073",
    "sg:province":"MN",
    "wof:name":"Westwind Design",
    "wof:placetype":"venue"
},
  "geometry": {"coordinates":[-92.808593,45.258095],"type":"Point"}
}