{
  "type": "Feature",
  "properties": {
    "iso:country":"US",
    "sg:address":"2571 W 150th St",
    "sg:city":"Shakopee",
    "sg:classifiers":[
        {
            "category":"Building & Trades",
            "subcategory":"Landscaping Services",
            "type":"Services"
        }
    ],
    "sg:phone":"+1 952 445 0940",
    "sg:postcode":"55379",
    "sg:province":"MN",
    "sg:tags":[
        "lawn",
        "maintenance",
        "grounds"
    ],
    "wof:name":"Priority 1 Lawn Mowing",
    "wof:placetype":"venue"
},
  "geometry": {"coordinates":[-93.574431,44.732657],"type":"Point"}
}