{
  "type": "Feature",
  "properties": {
    "addr:full":"921 Nicollet Mall Minneapolis MN 55402",
    "addr:housenumber":"921",
    "addr:postcode":"55402",
    "addr:street":"Nicollet Mall",
    "iso:country":"US",
    "sg:address":"921 Nicollet Mall",
    "sg:city":"Minneapolis",
    "sg:classifiers":[
        {
            "category":"Shopping",
            "subcategory":"Music",
            "type":"Retail Goods"
        },
        {
            "category":"Shopping",
            "subcategory":"Books",
            "type":"Retail Goods"
        }
    ],
    "sg:phone":"+1 612 338 1114",
    "sg:postcode":"55402",
    "sg:province":"MN",
    "sg:tags":[
        "bookstore",
        "dvd's"
    ],
    "sg:website":"www.lauriebooks.com",
    "wof:name":"James & Mary Laurie Booksellers",
    "wof:placetype":"venue"
},
  "geometry": {"coordinates":[-93.27419999999999,44.9744],"type":"Point"}
}