{
  "type": "Feature",
  "properties": {
    "iso:country":"US",
    "sg:address":"47995 132nd St",
    "sg:city":"Vernon Center",
    "sg:phone":"+1 507 435 4632",
    "sg:postcode":"56090",
    "sg:province":"MN",
    "sg:tags":[
        "farm",
        "soybean"
    ],
    "wof:name":"Ervin Arndt",
    "wof:placetype":"venue"
},
  "geometry": {"coordinates":[-94.343206,43.934749],"type":"Point"}
}