{
  "type": "Feature",
  "properties": {
    "addr:full":"12650 Ableman Rd Orr MN 55771",
    "addr:housenumber":"12650",
    "addr:postcode":"55771",
    "addr:street":"Ableman Rd",
    "iso:country":"US",
    "sg:address":"12650 Ableman Rd",
    "sg:city":"Orr",
    "sg:classifiers":[
        {
            "category":"Building & Trades",
            "subcategory":"Plumbing",
            "type":"Services"
        },
        {
            "category":"Building & Trades",
            "subcategory":"Cleaning & Sanitation",
            "type":"Services"
        }
    ],
    "sg:phone":"+1 218 787 2254",
    "sg:postcode":"55771",
    "sg:province":"MN",
    "sg:tags":[
        "cleaner",
        "repairer",
        "sewer",
        "plumbing-drain"
    ],
    "wof:name":"J & R Wastewater Services",
    "wof:placetype":"venue"
},
  "geometry": {"coordinates":[-93.03232,47.92349],"type":"Point"}
}