{
  "type": "Feature",
  "properties": {
    "iso:country":"US",
    "sg:address":"303 E Nicollet Blvd Ste 362",
    "sg:city":"Burnsville",
    "sg:classifiers":[
        {
            "category":"Health Services",
            "subcategory":"Doctor",
            "type":"Services"
        }
    ],
    "sg:phone":"+1 952 223 3040",
    "sg:postcode":"55337",
    "sg:province":"MN",
    "wof:name":"Zachary Cherie MD",
    "wof:placetype":"venue"
},
  "geometry": {"coordinates":[-93.273426,44.750119],"type":"Point"}
}