{
  "type": "Feature",
  "properties": {
    "iso:country":"US",
    "sg:address":"110 S Mill St",
    "sg:city":"Rushford",
    "sg:classifiers":[
        {
            "category":"Organizations",
            "subcategory":"Religious Organization",
            "type":"Services"
        }
    ],
    "sg:phone":"+1 507 864 2854",
    "sg:postcode":"55971",
    "sg:province":"MN",
    "wof:name":"Presbyterian Church",
    "wof:placetype":"venue"
},
  "geometry": {"coordinates":[-91.753074,43.810235],"type":"Point"}
}