{
  "type": "Feature",
  "properties": {
    "addr:full":"406 Center Ave Moorhead MN 56560",
    "addr:housenumber":"406",
    "addr:postcode":"56560",
    "addr:street":"Center Ave",
    "iso:country":"US",
    "sg:address":"406 Center Ave",
    "sg:city":"Moorhead",
    "sg:classifiers":[
        {
            "category":"Personal",
            "type":"Services"
        }
    ],
    "sg:phone":"+1 218 233 9426",
    "sg:postcode":"56560",
    "sg:province":"MN",
    "sg:tags":[
        "counseling"
    ],
    "wof:name":"Mental Health Counselors",
    "wof:placetype":"venue"
},
  "geometry": {"coordinates":[-96.773782,46.875097],"type":"Point"}
}