{
  "type": "Feature",
  "properties": {
    "addr:full":"45215 Red Pine Loop Perham MN 56573",
    "addr:housenumber":"45215",
    "addr:postcode":"56573",
    "addr:street":"Red Pine Loop",
    "iso:country":"US",
    "sg:address":"45215 Red Pine Loop",
    "sg:city":"Perham",
    "sg:classifiers":[
        {
            "category":"Personal",
            "subcategory":"Beauty Salon",
            "type":"Services"
        }
    ],
    "sg:phone":"+1 218 346 2599",
    "sg:postcode":"56573",
    "sg:province":"MN",
    "sg:tags":[
        "body",
        "wrap"
    ],
    "wof:name":"Body Wrap Island Style",
    "wof:placetype":"venue"
},
  "geometry": {"coordinates":[-95.549954,46.620432],"type":"Point"}
}