{
  "type": "Feature",
  "properties": {
    "addr:full":"9847 Lyndale Ave S Minneapolis MN 55420",
    "addr:housenumber":"9847",
    "addr:postcode":"55420",
    "addr:street":"Lyndale Ave S",
    "iso:country":"US",
    "sg:address":"9847 Lyndale Ave S",
    "sg:city":"Minneapolis",
    "sg:classifiers":[
        {
            "category":"Cinema",
            "subcategory":"Movie Rental",
            "type":"Entertainment"
        }
    ],
    "sg:phone":"+1 952 888 8465",
    "sg:postcode":"55420",
    "sg:province":"MN",
    "sg:tags":[
        "leasing",
        "video",
        "disc",
        "tape"
    ],
    "wof:name":"Blockbuster Video",
    "wof:placetype":"venue"
},
  "geometry": {"coordinates":[-93.28851299999999,44.824758],"type":"Point"}
}