{
  "type": "Feature",
  "properties": {
    "addr:full":"3400 221st Ave NW Anoka MN 55303",
    "addr:housenumber":"3400",
    "addr:postcode":"55303",
    "addr:street":"221St Ave Nw",
    "iso:country":"US",
    "sg:address":"3400 221st Ave NW",
    "sg:city":"Anoka",
    "sg:classifiers":[
        {
            "category":"Manufacturing",
            "subcategory":"Retail Goods",
            "type":"Manufacturing & Wholesale Goods"
        }
    ],
    "sg:phone":"+1 763 753 0434",
    "sg:postcode":"55303",
    "sg:province":"MN",
    "sg:tags":[
        "product",
        "mfg"
    ],
    "wof:name":"Jn Industries Inc",
    "wof:placetype":"venue"
},
  "geometry": {"coordinates":[-93.354473,45.370784],"type":"Point"}
}