{
  "type": "Feature",
  "properties": {
    "addr:full":"4154 Crow Wing Cir SW Pillager MN 56473",
    "addr:housenumber":"4154",
    "addr:postcode":"56473",
    "addr:street":"Crow Wing Cir Sw",
    "iso:country":"US",
    "sg:address":"4154 Crow Wing Cir SW",
    "sg:city":"Pillager",
    "sg:classifiers":[
        {
            "category":"Building & Trades",
            "subcategory":"Construction",
            "type":"Services"
        }
    ],
    "sg:phone":"+1 218 746 3631",
    "sg:postcode":"56473",
    "sg:province":"MN",
    "sg:tags":[
        "contractor"
    ],
    "wof:name":"D & H Drywall",
    "wof:placetype":"venue"
},
  "geometry": {"coordinates":[-94.49894500000001,46.319745],"type":"Point"}
}