{
  "type": "Feature",
  "properties": {
    "addr:full":"707 S Hamline Ave Saint Paul MN 55116",
    "addr:housenumber":"707",
    "addr:postcode":"55116",
    "addr:street":"S Hamline Ave",
    "iso:country":"US",
    "sg:address":"707 S Hamline Ave",
    "sg:city":"Saint Paul",
    "sg:classifiers":[
        {
            "category":"Social Services",
            "subcategory":"Child Care",
            "type":"Services"
        }
    ],
    "sg:phone":"+1 651 698 3385",
    "sg:postcode":"55116",
    "sg:province":"MN",
    "sg:tags":[
        "day"
    ],
    "wof:name":"Margaret Mooney",
    "wof:placetype":"venue"
},
  "geometry": {"coordinates":[-93.156907,44.92009],"type":"Point"}
}