{
  "type": "Feature",
  "properties": {
    "iso:country":"US",
    "sg:address":"146 Broadway St W",
    "sg:city":"Monticello",
    "sg:classifiers":[
        {
            "category":"Banks & Credit Unions",
            "subcategory":"Bank",
            "type":"Services"
        }
    ],
    "sg:phone":"+1 763 295 6669",
    "sg:postcode":"55362",
    "sg:province":"MN",
    "wof:name":"First National Bank",
    "wof:placetype":"venue"
},
  "geometry": {"coordinates":[-93.79511100000001,45.305884],"type":"Point"}
}