{
  "type": "Feature",
  "properties": {
    "addr:full":"8014 Highway 55 Suite 150 Minneapolis MN 55427",
    "addr:housenumber":"8014",
    "addr:postcode":"55427",
    "addr:street":"Highway 55 Suite 150",
    "iso:country":"US",
    "sg:address":"8014 Highway 55 Suite 150",
    "sg:city":"Minneapolis",
    "sg:classifiers":[
        {
            "category":"Organizations",
            "subcategory":"Professional Association",
            "type":"Services"
        },
        {
            "category":"Recreation",
            "type":"Entertainment"
        }
    ],
    "sg:phone":"+1 952 484 9186",
    "sg:postcode":"55427",
    "sg:province":"MN",
    "sg:tags":[
        "bureau",
        "agency",
        "entertainers-family",
        "business"
    ],
    "sg:website":"http://www.jivekore.biz",
    "wof:name":"Jive Kore Solutions, Inc.",
    "wof:placetype":"venue"
},
  "geometry": {"coordinates":[-93.381613,44.984068],"type":"Point"}
}