{
  "type": "Feature",
  "properties": {
    "addr:full":"160 Emory St Tracy MN 56175",
    "addr:housenumber":"160",
    "addr:postcode":"56175",
    "addr:street":"Emory St",
    "iso:country":"US",
    "sg:address":"160 Emory St",
    "sg:city":"Tracy",
    "sg:classifiers":[
        {
            "category":"Real Estate",
            "subcategory":"Real Estate Operator",
            "type":"Services"
        }
    ],
    "sg:phone":"+1 507 629 4662",
    "sg:postcode":"56175",
    "sg:province":"MN",
    "sg:tags":[
        "property",
        "lessor"
    ],
    "wof:name":"Perry Fales",
    "wof:placetype":"venue"
},
  "geometry": {"coordinates":[-95.614452,44.235385],"type":"Point"}
}