{
  "type": "Feature",
  "properties": {
    "addr:full":"8353 Crystal View Rd Eden Prairie MN 55344",
    "addr:housenumber":"8353",
    "addr:postcode":"55344",
    "addr:street":"Crystal View Rd",
    "iso:country":"US",
    "sg:address":"8353 Crystal View Rd",
    "sg:city":"Eden Prairie",
    "sg:classifiers":[
        {
            "category":"Banks & Credit Unions",
            "subcategory":"Bank",
            "type":"Services"
        }
    ],
    "sg:phone":"+1 952 918 1700",
    "sg:postcode":"55344",
    "sg:province":"MN",
    "sg:tags":[
        "loan",
        "real estate"
    ],
    "wof:name":"Wells Fargo Home Mortgage",
    "wof:placetype":"venue"
},
  "geometry": {"coordinates":[-93.432134,44.85319],"type":"Point"}
}