{
  "type": "Feature",
  "properties": {
    "iso:country":"US",
    "sg:address":"600 Canterbury Rd",
    "sg:city":"Shakopee",
    "sg:classifiers":[
        {
            "category":"Autos & Motor Vehicles",
            "subcategory":"Boat Sales",
            "type":"Retail Goods"
        }
    ],
    "sg:phone":"+1 952 496 1951",
    "sg:postcode":"55379",
    "sg:province":"MN",
    "sg:tags":[
        "dealer",
        "sales"
    ],
    "wof:name":"Twin City Outboard Motor Parts",
    "wof:placetype":"venue"
},
  "geometry": {"coordinates":[-93.46998000000001,44.796353],"type":"Point"}
}