{
  "type": "Feature",
  "properties": {
    "addr:full":"100 Pionk Dr Duluth MN 55810",
    "addr:housenumber":"100",
    "addr:postcode":"55810",
    "addr:street":"Pionk Dr",
    "iso:country":"US",
    "sg:address":"100 Pionk Dr",
    "sg:city":"Duluth",
    "sg:classifiers":[
        {
            "category":"Utilities",
            "subcategory":"Electric",
            "type":"Services"
        }
    ],
    "sg:phone":"+1 218 624 4055",
    "sg:postcode":"55810",
    "sg:province":"MN",
    "wof:name":"Proctor Public Utilities",
    "wof:placetype":"venue"
},
  "geometry": {"coordinates":[-92.226316,46.741336],"type":"Point"}
}