{
  "type": "Feature",
  "properties": {
    "addr:full":"905 Hollinger St Park Rapids MN 56470",
    "addr:housenumber":"905",
    "addr:postcode":"56470",
    "addr:street":"Hollinger St",
    "iso:country":"US",
    "sg:address":"905 Hollinger St",
    "sg:city":"Park Rapids",
    "sg:classifiers":[
        {
            "category":"Building & Trades",
            "subcategory":"Plumbing",
            "type":"Services"
        }
    ],
    "sg:phone":"+1 218 252 4775",
    "sg:postcode":"56470",
    "sg:province":"MN",
    "sg:tags":[
        "conditioning",
        "air",
        "system",
        "contractor"
    ],
    "wof:name":"Ellenson Heating & Cooling",
    "wof:placetype":"venue"
},
  "geometry": {"coordinates":[-95.042526,46.925124],"type":"Point"}
}