{
  "type": "Feature",
  "properties": {
    "iso:country":"US",
    "sg:address":"1616 Olive St W",
    "sg:city":"Stillwater",
    "sg:classifiers":[
        {
            "category":"Place Of Worship",
            "subcategory":"Church",
            "type":"Public Place"
        },
        {
            "category":"Place Of Worship",
            "type":"Public Place"
        }
    ],
    "sg:phone":"+1 651 439 5704",
    "sg:postcode":"55082",
    "sg:province":"MN",
    "sg:tags":[
        "lutheran",
        "america",
        "churches-lutheran",
        "churches-lutheran-evangelical"
    ],
    "sg:website":"http://www.oslcstillwater.org",
    "wof:name":"Our Saviour's Lutheran Church",
    "wof:placetype":"venue"
},
  "geometry": {"coordinates":[-92.828703,45.053051],"type":"Point"}
}