{
  "type": "Feature",
  "properties": {
    "addr:full":"6844 Shingle Creek Pkwy Brooklyn Center MN 55430",
    "addr:housenumber":"6844",
    "addr:postcode":"55430",
    "addr:street":"Shingle Creek Pkwy",
    "iso:country":"US",
    "sg:address":"6844 Shingle Creek Pkwy",
    "sg:city":"Brooklyn Center",
    "sg:classifiers":[
        {
            "category":"Government",
            "subcategory":"Office",
            "type":"Public Place"
        },
        {
            "category":"Building & Trades",
            "subcategory":"Construction",
            "type":"Services"
        }
    ],
    "sg:phone":"+1 763 569 3380",
    "sg:postcode":"55430",
    "sg:province":"MN",
    "sg:tags":[
        "marking",
        "transportation",
        "maintenance",
        "parking"
    ],
    "sg:website":"www.cityofbrooklyncenter.com",
    "wof:name":"Brooklyn Center Street Dept",
    "wof:placetype":"venue"
},
  "geometry": {"coordinates":[-93.310678,45.077989],"type":"Point"}
}