{
  "type": "Feature",
  "properties": {
    "iso:country":"US",
    "sg:address":"14054 Bank St",
    "sg:city":"Becker",
    "sg:classifiers":[
        {
            "category":"Insurance",
            "subcategory":"Insurance Agent",
            "type":"Services"
        }
    ],
    "sg:phone":"+1 763 261 4201",
    "sg:postcode":"55308",
    "sg:province":"MN",
    "wof:name":"Becker Insurance",
    "wof:placetype":"venue"
},
  "geometry": {"coordinates":[-93.86936900000001,45.389323],"type":"Point"}
}