{
  "type": "Feature",
  "properties": {
    "addr:full":"1232 Robert St S Saint Paul MN 55118",
    "addr:housenumber":"1232",
    "addr:postcode":"55118",
    "addr:street":"Robert St S",
    "iso:country":"US",
    "sg:address":"1232 Robert St S",
    "sg:city":"Saint Paul",
    "sg:classifiers":[
        {
            "category":"Restaurant",
            "type":"Food & Drink"
        }
    ],
    "sg:menulink":"http://www.allmenus.com/mn/west-st-paul/151163-subway/menu/",
    "sg:phone":"+1 651 451 7584",
    "sg:postcode":"55118",
    "sg:province":"MN",
    "sg:tags":[
        "american",
        "sandwich"
    ],
    "wof:name":"Subway",
    "wof:placetype":"venue"
},
  "geometry": {"coordinates":[-93.080612,44.90894],"type":"Point"}
}