{
  "type": "Feature",
  "properties": {
    "addr:full":"845 16th Ave S St Cloud MN 56301",
    "addr:housenumber":"845",
    "addr:postcode":"56301",
    "addr:street":"16Th Ave S",
    "iso:country":"US",
    "sg:address":"845 16th Ave S",
    "sg:city":"St Cloud",
    "sg:classifiers":[
        {
            "category":"Social Services",
            "type":"Services"
        }
    ],
    "sg:phone":"+1 320 255 1517",
    "sg:postcode":"56301",
    "sg:province":"MN",
    "sg:tags":[
        "organization",
        "welfare"
    ],
    "wof:name":"Rem South",
    "wof:placetype":"venue"
},
  "geometry": {"coordinates":[-94.169895,45.550401],"type":"Point"}
}