{
  "type": "Feature",
  "properties": {
    "iso:country":"US",
    "sg:address":"310 Wilson Ave NE",
    "sg:city":"Saint Cloud",
    "sg:classifiers":[
        {
            "category":"Organizations",
            "subcategory":"Membership Organization",
            "type":"Services"
        }
    ],
    "sg:phone":"+1 320 656 9286",
    "sg:postcode":"56304",
    "sg:province":"MN",
    "wof:name":"International Reading Assn",
    "wof:placetype":"venue"
},
  "geometry": {"coordinates":[-94.154929,45.569649],"type":"Point"}
}