{
  "type": "Feature",
  "properties": {
    "addr:full":"9100 W Bloomington Fwy Bloomington MN 55431",
    "addr:housenumber":"9100",
    "addr:postcode":"55431",
    "addr:street":"W Bloomington Fwy",
    "iso:country":"US",
    "sg:address":"9100 W Bloomington Fwy",
    "sg:city":"Bloomington",
    "sg:classifiers":[
        {
            "category":"Real Estate",
            "subcategory":"Real Estate Agent",
            "type":"Services"
        }
    ],
    "sg:phone":"+1 952 885 0675",
    "sg:postcode":"55431",
    "sg:province":"MN",
    "sg:tags":[
        "appraiser"
    ],
    "wof:name":"Comprehensive Appraisal Svcs",
    "wof:placetype":"venue"
},
  "geometry": {"coordinates":[-93.298897,44.840748],"type":"Point"}
}