{
  "type": "Feature",
  "properties": {
    "addr:full":"4660 Slater Rd Saint Paul MN 55122",
    "addr:housenumber":"4660",
    "addr:postcode":"55122",
    "addr:street":"Slater Rd",
    "iso:country":"US",
    "sg:address":"4660 Slater Rd",
    "sg:city":"Saint Paul",
    "sg:classifiers":[
        {
            "category":"Professional",
            "subcategory":"Lawyer & Legal Services",
            "type":"Services"
        }
    ],
    "sg:phone":"+1 651 452 2136",
    "sg:postcode":"55122",
    "sg:province":"MN",
    "sg:tags":[
        "attorney"
    ],
    "wof:name":"Firm Shafer Law",
    "wof:placetype":"venue"
},
  "geometry": {"coordinates":[-93.22286200000001,44.785561],"type":"Point"}
}