{
  "type": "Feature",
  "properties": {
    "addr:full":"7359 Bridlewood Curve Eden Prairie MN 55346",
    "addr:housenumber":"7359",
    "addr:postcode":"55346",
    "addr:street":"Bridlewood Curve",
    "iso:country":"US",
    "sg:address":"7359 Bridlewood Curve",
    "sg:city":"Eden Prairie",
    "sg:classifiers":[
        {
            "category":"Insurance",
            "subcategory":"Insurance Agent",
            "type":"Services"
        }
    ],
    "sg:phone":"+1 952 975 9094",
    "sg:postcode":"55346",
    "sg:province":"MN",
    "wof:name":"Eye Find-Casualty Adjusting",
    "wof:placetype":"venue"
},
  "geometry": {"coordinates":[-93.499015,44.870895],"type":"Point"}
}