{
  "type": "Feature",
  "properties": {
    "addr:full":"10420 Normandale Blvd Minneapolis MN 55437",
    "addr:housenumber":"10420",
    "addr:postcode":"55437",
    "addr:street":"Normandale Blvd",
    "iso:country":"US",
    "sg:address":"10420 Normandale Blvd",
    "sg:city":"Minneapolis",
    "sg:classifiers":[
        {
            "category":"Social Services",
            "subcategory":"Child Care",
            "type":"Services"
        }
    ],
    "sg:phone":"+1 952 888 4334",
    "sg:postcode":"55437",
    "sg:province":"MN",
    "sg:tags":[
        "day"
    ],
    "wof:name":"Noah's Ark Child Development Centers Inc",
    "wof:placetype":"venue"
},
  "geometry": {"coordinates":[-93.35050200000001,44.8139],"type":"Point"}
}