{
  "type": "Feature",
  "properties": {
    "iso:country":"US",
    "sg:address":"2120 Silver Lake Rd NW",
    "sg:city":"St Paul",
    "sg:classifiers":[
        {
            "category":"Shopping",
            "subcategory":"Pharmacy",
            "type":"Retail Goods"
        }
    ],
    "sg:phone":"+1 651 633 6441",
    "sg:postcode":"55112",
    "sg:province":"MN",
    "wof:name":"Snyder Drug Store",
    "wof:placetype":"venue"
},
  "geometry": {"coordinates":[-93.218987,45.084768],"type":"Point"}
}