{
  "type": "Feature",
  "properties": {
    "addr:full":"9010 Jeffery Ave S Cottage Grove MN 55016",
    "addr:housenumber":"9010",
    "addr:postcode":"55016",
    "addr:street":"Jeffery Ave S Cottage Grove",
    "iso:country":"US",
    "sg:address":"9010 Jeffery Ave S",
    "sg:city":"Cottage Grove",
    "sg:classifiers":[
        {
            "category":"Professional",
            "subcategory":"Business Services",
            "type":"Services"
        }
    ],
    "sg:phone":"+1 651 769 6870",
    "sg:postcode":"55016",
    "sg:province":"MN",
    "sg:tags":[
        "water",
        "treatment"
    ],
    "wof:name":"Pure Water",
    "wof:placetype":"venue"
},
  "geometry": {"coordinates":[-92.917912,44.817385],"type":"Point"}
}