{
  "type": "Feature",
  "properties": {
    "addr:full":"6932 Calgary Rd Saint Paul MN 55125",
    "addr:housenumber":"6932",
    "addr:postcode":"55125",
    "addr:street":"Calgary Rd",
    "iso:country":"US",
    "sg:address":"6932 Calgary Rd",
    "sg:city":"Saint Paul",
    "sg:classifiers":[
        {
            "category":"Professional",
            "subcategory":"Business Services",
            "type":"Services"
        }
    ],
    "sg:phone":"+1 651 578 9246",
    "sg:postcode":"55125",
    "sg:province":"MN",
    "wof:name":"Advancemedia",
    "wof:placetype":"venue"
},
  "geometry": {"coordinates":[-92.968271,44.911615],"type":"Point"}
}