{
  "type": "Feature",
  "properties": {
    "addr:full":"245 Northtown Dr NE Minneapolis MN 55434",
    "addr:housenumber":"245",
    "addr:postcode":"55434",
    "addr:street":"Northtown Dr Ne",
    "iso:country":"US",
    "sg:address":"245 Northtown Dr NE",
    "sg:city":"Minneapolis",
    "sg:classifiers":[
        {
            "category":"Shopping",
            "subcategory":"Clothing, Apparel, & Fashions",
            "type":"Retail Goods"
        }
    ],
    "sg:phone":"+1 763 784 2192",
    "sg:postcode":"55434",
    "sg:province":"MN",
    "wof:name":"Hot Topic Inc",
    "wof:placetype":"venue"
},
  "geometry": {"coordinates":[-93.260347,45.128555],"type":"Point"}
}