{
  "type": "Feature",
  "properties": {
    "iso:country":"US",
    "sg:address":"1624 Harmon Pl",
    "sg:city":"Minneapolis",
    "sg:classifiers":[
        {
            "category":"Banks & Credit Unions",
            "subcategory":"Investment Brokerage",
            "type":"Services"
        },
        {
            "category":"Banks & Credit Unions",
            "subcategory":"Bank",
            "type":"Services"
        },
        {
            "category":"Banks & Credit Unions",
            "subcategory":"Financial Services",
            "type":"Services"
        }
    ],
    "sg:phone":"+1 612 486 5890",
    "sg:postcode":"55403",
    "sg:province":"MN",
    "sg:tags":[
        "retirement",
        "annuity",
        "broker",
        "agent",
        "plan",
        "transfer",
        "security",
        "bond",
        "insurance",
        "stock"
    ],
    "wof:name":"First American Securities",
    "wof:placetype":"venue"
},
  "geometry": {"coordinates":[-93.286179,44.971127],"type":"Point"}
}