{
  "type": "Feature",
  "properties": {
    "addr:full":"305 Wollan St Starbuck MN 56381",
    "addr:housenumber":"305",
    "addr:postcode":"56381",
    "addr:street":"Wollan St",
    "iso:country":"US",
    "sg:address":"305 Wollan St",
    "sg:city":"Starbuck",
    "sg:classifiers":[
        {
            "category":"Retail",
            "subcategory":"Self-service Laundry",
            "type":"Services"
        }
    ],
    "sg:phone":"+1 320 239 4345",
    "sg:postcode":"56381",
    "sg:province":"MN",
    "sg:tags":[
        "coin"
    ],
    "wof:name":"Starbuck Laundromat",
    "wof:placetype":"venue"
},
  "geometry": {"coordinates":[-95.532544,45.611269],"type":"Point"}
}