{
  "type": "Feature",
  "properties": {
    "addr:full":"2731 181st Ave NW Cedar MN 55011",
    "addr:housenumber":"2731",
    "addr:postcode":"55011",
    "addr:street":"181St Ave Nw Cedar",
    "iso:country":"US",
    "sg:address":"2731 181st Ave NW",
    "sg:city":"Cedar",
    "sg:classifiers":[
        {
            "category":"Building & Trades",
            "subcategory":"Construction",
            "type":"Services"
        }
    ],
    "sg:phone":"+1 763 753 1194",
    "sg:postcode":"55011",
    "sg:province":"MN",
    "sg:tags":[
        "contractor"
    ],
    "wof:name":"Mueller Exteriors",
    "wof:placetype":"venue"
},
  "geometry": {"coordinates":[-93.335134,45.298198],"type":"Point"}
}