{
  "type": "Feature",
  "properties": {
    "addr:full":"212 Atlantic Ave Donnelly MN 56235",
    "addr:housenumber":"212",
    "addr:postcode":"56235",
    "addr:street":"Atlantic Ave",
    "iso:country":"US",
    "sg:address":"212 Atlantic Ave",
    "sg:city":"Donnelly",
    "sg:classifiers":[
        {
            "category":"Shopping",
            "subcategory":"Used Merchandise",
            "type":"Retail Goods"
        }
    ],
    "sg:phone":"+1 320 246 3327",
    "sg:postcode":"56235",
    "sg:province":"MN",
    "sg:tags":[
        "antique"
    ],
    "wof:name":"H D & Co",
    "wof:placetype":"venue"
},
  "geometry": {"coordinates":[-96.011636,45.689254],"type":"Point"}
}