{
  "type": "Feature",
  "properties": {
    "iso:country":"US",
    "sg:address":"7760 France Ave S",
    "sg:city":"Minneapolis",
    "sg:classifiers":[
        {
            "category":"Shopping",
            "subcategory":"Computers & Home Electronics",
            "type":"Retail Goods"
        }
    ],
    "sg:phone":"+1 952 832 9248",
    "sg:postcode":"55435",
    "sg:province":"MN",
    "wof:name":"Wireless Facilities Inc",
    "wof:placetype":"venue"
},
  "geometry": {"coordinates":[-93.328929,44.860934],"type":"Point"}
}