{
  "type": "Feature",
  "properties": {
    "addr:full":"6572 Co Rd 37 NW Maple Lake MN 55358",
    "addr:housenumber":"6572;37",
    "addr:postcode":"55358",
    "addr:street":"Co Rd;Nw Maple Lake",
    "iso:country":"US",
    "sg:address":"6572 Co Rd 37 NW",
    "sg:city":"Maple Lake",
    "sg:classifiers":[
        {
            "category":"Building & Trades",
            "subcategory":"Landscaping Services",
            "type":"Services"
        }
    ],
    "sg:phone":"+1 320 963 3214",
    "sg:postcode":"55358",
    "sg:province":"MN",
    "wof:name":"Liberty Landscaping",
    "wof:placetype":"venue"
},
  "geometry": {"coordinates":[-94.024714,45.231939],"type":"Point"}
}