{
  "type": "Feature",
  "properties": {
    "addr:full":"4724 Folwell Dr Minneapolis MN 55406",
    "addr:housenumber":"4724",
    "addr:postcode":"55406",
    "addr:street":"Folwell Dr",
    "iso:country":"US",
    "sg:address":"4724 Folwell Dr",
    "sg:city":"Minneapolis",
    "sg:classifiers":[
        {
            "category":"Manufacturing",
            "subcategory":"Food",
            "type":"Manufacturing & Wholesale Goods"
        },
        {
            "category":"Farming",
            "subcategory":"Farm",
            "type":"Manufacturing & Wholesale Goods"
        }
    ],
    "sg:phone":"+1 612 722 9891",
    "sg:postcode":"55406",
    "sg:province":"MN",
    "sg:tags":[
        "corn",
        "product"
    ],
    "wof:name":"Bruss, Algene",
    "wof:placetype":"venue"
},
  "geometry": {"coordinates":[-93.206091,44.929933],"type":"Point"}
}