{
  "type": "Feature",
  "properties": {
    "iso:country":"US",
    "sg:address":"3300 University Ave SE",
    "sg:city":"Minneapolis",
    "sg:classifiers":[
        {
            "category":"Retail",
            "subcategory":"Repair Shop",
            "type":"Services"
        },
        {
            "category":"Shopping",
            "subcategory":"Crafts & Fabrics",
            "type":"Retail Goods"
        },
        {
            "category":"Shopping",
            "subcategory":"Computers & Home Electronics",
            "type":"Retail Goods"
        }
    ],
    "sg:phone":"+1 612 331 5500",
    "sg:postcode":"55414",
    "sg:province":"MN",
    "sg:tags":[
        "stereo",
        "art",
        "supply",
        "video",
        "equipment-service",
        "audio",
        "consumer"
    ],
    "sg:website":"www.tierneybros.com",
    "wof:name":"Tierney Brothers Inc",
    "wof:placetype":"venue"
},
  "geometry": {"coordinates":[-93.210999,44.9692],"type":"Point"}
}