{
  "type": "Feature",
  "properties": {
    "addr:full":"359 Co Rd B E St Paul MN 55117",
    "addr:housenumber":"359",
    "addr:postcode":"55117",
    "addr:street":"Co Rd B E",
    "iso:country":"US",
    "sg:address":"359 Co Rd B E",
    "sg:city":"St Paul",
    "sg:classifiers":[
        {
            "category":"Professional",
            "subcategory":"Accounting & Tax Preparation",
            "type":"Services"
        }
    ],
    "sg:phone":"+1 651 774 2400",
    "sg:postcode":"55117",
    "sg:province":"MN",
    "sg:tags":[
        "accountant"
    ],
    "wof:name":"Margaret Conlin-Duevel CPA",
    "wof:placetype":"venue"
},
  "geometry": {"coordinates":[-93.084633,45.006335],"type":"Point"}
}