{
  "type": "Feature",
  "properties": {
    "iso:country":"US",
    "sg:address":"332 W Superior St",
    "sg:city":"Duluth",
    "sg:classifiers":[
        {
            "category":"Real Estate",
            "subcategory":"Real Estate Agent",
            "type":"Services"
        }
    ],
    "sg:phone":"+1 218 727 1000",
    "sg:postcode":"55802",
    "sg:province":"MN",
    "sg:tags":[
        "management"
    ],
    "wof:name":"Overman Property Management",
    "wof:placetype":"venue"
},
  "geometry": {"coordinates":[-92.102695,46.783392],"type":"Point"}
}