{
  "type": "Feature",
  "properties": {
    "iso:country":"US",
    "sg:address":"41281 200th St",
    "sg:city":"Roseau",
    "sg:classifiers":[
        {
            "category":"Autos & Motor Vehicles",
            "subcategory":"Automobile Sales",
            "type":"Retail Goods"
        }
    ],
    "sg:phone":"+1 218 425 3921",
    "sg:postcode":"56751",
    "sg:province":"MN",
    "sg:tags":[
        "used"
    ],
    "wof:name":"Deer Valley Auto Sales",
    "wof:placetype":"venue"
},
  "geometry": {"coordinates":[-95.708489,48.685052],"type":"Point"}
}