{
  "type": "Feature",
  "properties": {
    "addr:full":"5474 137th St N Hugo MN 55038",
    "addr:housenumber":"5474",
    "addr:postcode":"55038",
    "addr:street":"137Th St N Hugo",
    "iso:country":"US",
    "sg:address":"5474 137th St N",
    "sg:city":"Hugo",
    "sg:classifiers":[
        {
            "category":"Shopping",
            "subcategory":"Clothing, Apparel, & Fashions",
            "type":"Retail Goods"
        }
    ],
    "sg:phone":"+1 651 407 0714",
    "sg:postcode":"55038",
    "sg:province":"MN",
    "sg:tags":[
        "maternity"
    ],
    "wof:name":"Maternity Closet",
    "wof:placetype":"venue"
},
  "geometry": {"coordinates":[-92.995898,45.148574],"type":"Point"}
}