{
  "type": "Feature",
  "properties": {
    "addr:full":"1616 Opportunity Rd NW Rochester MN 55901",
    "addr:housenumber":"1616",
    "addr:postcode":"55901",
    "addr:street":"Opportunity Rd Nw",
    "iso:country":"US",
    "sg:address":"1616 Opportunity Rd NW",
    "sg:city":"Rochester",
    "sg:classifiers":[
        {
            "category":"Transit Center",
            "subcategory":"Freight",
            "type":"Transportation"
        },
        {
            "category":"Professional",
            "subcategory":"Business Services",
            "type":"Services"
        },
        {
            "category":"Taxi",
            "type":"Transportation"
        },
        {
            "category":"Government",
            "subcategory":"Post Office",
            "type":"Public Place"
        }
    ],
    "sg:phone":"+1 507 281 0468",
    "sg:postcode":"55901",
    "sg:province":"MN",
    "sg:tags":[
        "cargo",
        "courier",
        "package",
        "express",
        "shipping",
        "air",
        "delivery",
        "mail",
        "forwarding"
    ],
    "sg:website":"http://www.upsscs.com",
    "wof:name":"Ups",
    "wof:placetype":"venue"
},
  "geometry": {"coordinates":[-92.500597,44.038602],"type":"Point"}
}