{
  "type": "Feature",
  "properties": {
    "addr:full":"1350 Co Rd 42 W Burnsville MN 55337",
    "addr:housenumber":"1350;42",
    "addr:postcode":"55337",
    "addr:street":"Co Rd;W",
    "iso:country":"US",
    "sg:address":"1350 Co Rd 42 W",
    "sg:city":"Burnsville",
    "sg:classifiers":[
        {
            "category":"Home & Garden",
            "subcategory":"Furniture",
            "type":"Retail Goods"
        }
    ],
    "sg:phone":"+1 952 898 5577",
    "sg:postcode":"55337",
    "sg:province":"MN",
    "wof:name":"Wickes Furniture",
    "wof:placetype":"venue"
},
  "geometry": {"coordinates":[-93.29538700000001,44.746615],"type":"Point"}
}