{
  "type": "Feature",
  "properties": {
    "addr:full":"2001 E 24th St Minneapolis MN 55404",
    "addr:housenumber":"2001",
    "addr:postcode":"55404",
    "addr:street":"E 24Th St",
    "iso:country":"US",
    "sg:address":"2001 E 24th St",
    "sg:city":"Minneapolis",
    "sg:classifiers":[
        {
            "category":"Food & Beverages",
            "subcategory":"Meat & Fish",
            "type":"Retail Goods"
        }
    ],
    "sg:phone":"+1 612 746 0600",
    "sg:postcode":"55404",
    "sg:province":"MN",
    "sg:tags":[
        "processing"
    ],
    "sg:website":"http://www.wwjmeat.com",
    "wof:name":"W. W. Johnson Meat Company",
    "wof:placetype":"venue"
},
  "geometry": {"coordinates":[-93.24366000000001,44.959148],"type":"Point"}
}