{
  "type": "Feature",
  "properties": {
    "addr:full":"16240 Galena Ave W Rosemount MN 55068",
    "addr:housenumber":"16240",
    "addr:postcode":"55068",
    "addr:street":"Galena Ave W",
    "iso:country":"US",
    "sg:address":"16240 Galena Ave W",
    "sg:city":"Rosemount",
    "sg:classifiers":[
        {
            "category":"Building & Trades",
            "subcategory":"Construction",
            "type":"Services"
        }
    ],
    "sg:phone":"+1 612 414 6286",
    "sg:postcode":"55068",
    "sg:province":"MN",
    "sg:tags":[
        "general",
        "contractor"
    ],
    "wof:name":"R & J Construction",
    "wof:placetype":"venue"
},
  "geometry": {"coordinates":[-93.20820999999999,44.713634],"type":"Point"}
}