{
  "type": "Feature",
  "properties": {
    "addr:full":"11137 Excelsior Blvd Hopkins MN 55343",
    "addr:housenumber":"11137",
    "addr:postcode":"55343",
    "addr:street":"Excelsior Blvd",
    "iso:country":"US",
    "sg:address":"11137 Excelsior Blvd",
    "sg:city":"Hopkins",
    "sg:classifiers":[
        {
            "category":"Manufacturing",
            "subcategory":"Tools & Machinery",
            "type":"Manufacturing & Wholesale Goods"
        },
        {
            "category":"Industrial Area",
            "type":"Public Place"
        }
    ],
    "sg:phone":"+1 952 938 2202",
    "sg:postcode":"55343",
    "sg:province":"MN",
    "sg:tags":[
        "repair",
        "equipment-repairing",
        "machinery-rebuild"
    ],
    "wof:name":"Used Metalworking Machines",
    "wof:placetype":"venue"
},
  "geometry": {"coordinates":[-93.427483,44.920805],"type":"Point"}
}