{
  "type": "Feature",
  "properties": {
    "addr:full":"52 E 3rd St Winona MN 55987",
    "addr:housenumber":"52",
    "addr:postcode":"55987",
    "addr:street":"E 3Rd St",
    "iso:country":"US",
    "sg:address":"52 E 3rd St",
    "sg:city":"Winona",
    "sg:classifiers":[
        {
            "category":"Personal",
            "subcategory":"Beauty Salon",
            "type":"Services"
        }
    ],
    "sg:phone":"+1 507 454 0605",
    "sg:postcode":"55987",
    "sg:province":"MN",
    "sg:tags":[
        "manicuring"
    ],
    "wof:name":"Tips To Toes",
    "wof:placetype":"venue"
},
  "geometry": {"coordinates":[-91.635673,44.052257],"type":"Point"}
}