{
  "type": "Feature",
  "properties": {
    "iso:country":"US",
    "sg:address":"2247 3rd Ave NW",
    "sg:city":"Owatonna",
    "sg:classifiers":[
        {
            "category":"Sports & Exercise",
            "subcategory":"Bowling",
            "type":"Entertainment"
        }
    ],
    "sg:phone":"+1 507 451 3198",
    "sg:postcode":"55060",
    "sg:province":"MN",
    "sg:tags":[
        "center"
    ],
    "wof:name":"New Winthrop Lanes",
    "wof:placetype":"venue"
},
  "geometry": {"coordinates":[-93.231504,44.106445],"type":"Point"}
}