{
  "type": "Feature",
  "properties": {
    "iso:country":"US",
    "sg:address":"4300 W River Pkwy Apt 605",
    "sg:city":"Minneapolis",
    "sg:classifiers":[
        {
            "category":"Personal",
            "subcategory":"Beauty Salon",
            "type":"Services"
        }
    ],
    "sg:phone":"+1 612 721 3400",
    "sg:postcode":"55406",
    "sg:province":"MN",
    "sg:tags":[
        "hair"
    ],
    "sg:website":"www.becketwood.com",
    "wof:name":"Becketwood Beauty Salon",
    "wof:placetype":"venue"
},
  "geometry": {"coordinates":[-93.20369700000001,44.925201],"type":"Point"}
}