{
  "type": "Feature",
  "properties": {
    "addr:full":"10619 France Ave S Minneapolis MN 55431",
    "addr:postcode":"10619;55431",
    "addr:street":"Ave S",
    "iso:country":"US",
    "sg:address":"10619 France Ave S",
    "sg:city":"Minneapolis",
    "sg:classifiers":[
        {
            "category":"Shopping",
            "subcategory":"Tobacco",
            "type":"Retail Goods"
        }
    ],
    "sg:phone":"+1 952 888 6201",
    "sg:postcode":"55431",
    "sg:province":"MN",
    "sg:tags":[
        "shop"
    ],
    "wof:name":"City Smokeshop",
    "wof:placetype":"venue"
},
  "geometry": {"coordinates":[-93.329399,44.811199],"type":"Point"}
}