{
  "type": "Feature",
  "properties": {
    "iso:country":"US",
    "sg:address":"3637 Emerson Ave N",
    "sg:city":"Minneapolis",
    "sg:classifiers":[
        {
            "category":"Personal",
            "subcategory":"Beauty Salon",
            "type":"Services"
        }
    ],
    "sg:phone":"+1 612 521 3918",
    "sg:postcode":"55412",
    "sg:province":"MN",
    "sg:tags":[
        "shop"
    ],
    "wof:name":"Alexzines Hair Productions",
    "wof:placetype":"venue"
},
  "geometry": {"coordinates":[-93.294408,45.021497],"type":"Point"}
}