{
  "type": "Feature",
  "properties": {
    "addr:full":"1025 Rook Rd NE Sauk Rapids MN 56379",
    "addr:housenumber":"1025",
    "addr:postcode":"56379",
    "addr:street":"Rook Rd Ne",
    "iso:country":"US",
    "sg:address":"1025 Rook Rd NE",
    "sg:city":"Sauk Rapids",
    "sg:classifiers":[
        {
            "category":"Professional",
            "subcategory":"Advertising",
            "type":"Services"
        }
    ],
    "sg:phone":"+1 320 253 3000",
    "sg:postcode":"56379",
    "sg:province":"MN",
    "sg:website":"www.lamar.com",
    "wof:name":"Lamar Outdoor Advertising",
    "wof:placetype":"venue"
},
  "geometry": {"coordinates":[-94.067656,45.581353],"type":"Point"}
}