{
  "type": "Feature",
  "properties": {
    "addr:full":"5000 1st Ave S Minneapolis MN 55419",
    "addr:housenumber":"5000",
    "addr:postcode":"55419",
    "addr:street":"1St Ave S",
    "iso:country":"US",
    "sg:address":"5000 1st Ave S",
    "sg:city":"Minneapolis",
    "sg:classifiers":[
        {
            "category":"Real Estate",
            "subcategory":"Architect",
            "type":"Services"
        }
    ],
    "sg:phone":"+1 612 824 8822",
    "sg:postcode":"55419",
    "sg:province":"MN",
    "wof:name":"Jack Lindeman Specifications",
    "wof:placetype":"venue"
},
  "geometry": {"coordinates":[-93.276749,44.912414],"type":"Point"}
}