{
  "type": "Feature",
  "properties": {
    "addr:full":"7306 Cleve Ave E Inver Grove Heights MN 55076",
    "addr:housenumber":"7306",
    "addr:postcode":"55076",
    "addr:street":"Cleve Ave E",
    "iso:country":"US",
    "sg:address":"7306 Cleve Ave E",
    "sg:city":"Inver Grove Heights",
    "sg:classifiers":[
        {
            "category":"Retail",
            "subcategory":"Repair Shop",
            "type":"Services"
        }
    ],
    "sg:phone":"+1 651 457 1532",
    "sg:postcode":"55076",
    "sg:province":"MN",
    "wof:name":"Fastronic Service",
    "wof:placetype":"venue"
},
  "geometry": {"coordinates":[-93.03159100000001,44.842104],"type":"Point"}
}