{
  "type": "Feature",
  "properties": {
    "addr:full":"3550 W 200th St Jordan MN 55352",
    "addr:housenumber":"3550",
    "addr:postcode":"55352",
    "addr:street":"W 200Th St",
    "iso:country":"US",
    "sg:address":"3550 W 200th St",
    "sg:city":"Jordan",
    "sg:classifiers":[
        {
            "category":"Building & Trades",
            "subcategory":"Construction",
            "type":"Services"
        }
    ],
    "sg:phone":"+1 952 492 2147",
    "sg:postcode":"55352",
    "sg:province":"MN",
    "sg:tags":[
        "concrete",
        "contractor"
    ],
    "wof:name":"Weiers Concrete & Masonry Co",
    "wof:placetype":"venue"
},
  "geometry": {"coordinates":[-93.595094,44.659956],"type":"Point"}
}