{
  "type": "Feature",
  "properties": {
    "iso:country":"US",
    "sg:address":"240 E Pearl St",
    "sg:city":"Owatonna",
    "sg:classifiers":[
        {
            "category":"Manufacturing",
            "subcategory":"Printing",
            "type":"Manufacturing & Wholesale Goods"
        }
    ],
    "sg:phone":"+1 507 451 6500",
    "sg:postcode":"55060",
    "sg:province":"MN",
    "sg:tags":[
        "newspaper"
    ],
    "wof:name":"Star Tribune",
    "wof:placetype":"venue"
},
  "geometry": {"coordinates":[-93.222737,44.086804],"type":"Point"}
}