{
  "type": "Feature",
  "properties": {
    "iso:country":"US",
    "sg:address":"14220 Ostlund Trl N",
    "sg:city":"Marine St Croix",
    "sg:classifiers":[
        {
            "category":"Government",
            "subcategory":"Office",
            "type":"Public Place"
        },
        {
            "category":"Organizations",
            "subcategory":"Professional Association",
            "type":"Services"
        }
    ],
    "sg:phone":"+1 651 433 3676",
    "sg:postcode":"55047",
    "sg:province":"MN",
    "sg:tags":[
        "food"
    ],
    "wof:name":"Minnesota Food Assoc",
    "wof:placetype":"venue"
},
  "geometry": {"coordinates":[-92.811969,45.163962],"type":"Point"}
}