{
  "type": "Feature",
  "properties": {
    "iso:country":"US",
    "sg:address":"5011 31st Ave S",
    "sg:city":"Minneapolis",
    "sg:classifiers":[
        {
            "category":"Organizations",
            "subcategory":"Religious Organization",
            "type":"Services"
        }
    ],
    "sg:phone":"+1 612 729 2323",
    "sg:postcode":"55417",
    "sg:province":"MN",
    "sg:website":"www.lakenokomis.org",
    "wof:name":"Lake Nokomis Lutheran Church",
    "wof:placetype":"venue"
},
  "geometry": {"coordinates":[-93.22707200000001,44.912148],"type":"Point"}
}