{
  "type": "Feature",
  "properties": {
    "addr:full":"19472 Jade Ln Lakeville MN 55044",
    "addr:housenumber":"19472",
    "addr:postcode":"55044",
    "addr:street":"Jade Ln",
    "iso:country":"US",
    "sg:address":"19472 Jade Ln",
    "sg:city":"Lakeville",
    "sg:classifiers":[
        {
            "category":"Professional",
            "subcategory":"Business Services",
            "type":"Services"
        }
    ],
    "sg:phone":"+1 952 583 5074",
    "sg:postcode":"55044",
    "sg:province":"MN",
    "sg:tags":[
        "consultant",
        "coach"
    ],
    "wof:name":"Lsk Consulting",
    "wof:placetype":"venue"
},
  "geometry": {"coordinates":[-93.269497,44.666739],"type":"Point"}
}