{
  "type": "Feature",
  "properties": {
    "iso:country":"US",
    "sg:address":"1121 Riverwood Dr",
    "sg:city":"Burnsville",
    "sg:classifiers":[
        {
            "category":"Manufacturing",
            "subcategory":"Retail Goods",
            "type":"Manufacturing & Wholesale Goods"
        }
    ],
    "sg:phone":"+1 952 882 9494",
    "sg:postcode":"55337",
    "sg:province":"MN",
    "sg:tags":[
        "prototype"
    ],
    "wof:name":"Engineered Tooling & Atmtn LLC",
    "wof:placetype":"venue"
},
  "geometry": {"coordinates":[-93.258437,44.785184],"type":"Point"}
}