{
  "type": "Feature",
  "properties": {
    "addr:full":"3680 Kenyon Rd Owatonna MN 55060",
    "addr:housenumber":"3680",
    "addr:postcode":"55060",
    "addr:street":"Kenyon Rd",
    "iso:country":"US",
    "sg:address":"3680 Kenyon Rd",
    "sg:city":"Owatonna",
    "sg:phone":"+1 507 451 3081",
    "sg:postcode":"55060",
    "sg:province":"MN",
    "sg:tags":[
        "farm",
        "corn",
        "soybean"
    ],
    "wof:name":"Don Fisher",
    "wof:placetype":"venue"
},
  "geometry": {"coordinates":[-93.15369200000001,44.124355],"type":"Point"}
}