{
  "type": "Feature",
  "properties": {
    "iso:country":"US",
    "sg:address":"8102 90th St N",
    "sg:city":"Glyndon",
    "sg:classifiers":[
        {
            "category":"Retail",
            "subcategory":"Auto Repair",
            "type":"Services"
        }
    ],
    "sg:phone":"+1 218 236 1432",
    "sg:postcode":"56547",
    "sg:province":"MN",
    "sg:tags":[
        "general"
    ],
    "wof:name":"Jays Auto Truck Repair",
    "wof:placetype":"venue"
},
  "geometry": {"coordinates":[-96.610439,46.975461],"type":"Point"}
}