{
  "type": "Feature",
  "properties": {
    "iso:country":"US",
    "sg:address":"500 11th Ave S",
    "sg:city":"Minneapolis",
    "sg:classifiers":[
        {
            "category":"Utilities",
            "subcategory":"Cable",
            "type":"Services"
        }
    ],
    "sg:phone":"+1 612 630 8007",
    "sg:postcode":"55415",
    "sg:province":"MN",
    "sg:tags":[
        "satellite",
        "carrier"
    ],
    "wof:name":"VYVX Inc",
    "wof:placetype":"venue"
},
  "geometry": {"coordinates":[-93.256406,44.971529],"type":"Point"}
}