{
  "type": "Feature",
  "properties": {
    "addr:full":"309 S Oak St Waconia MN 55387",
    "addr:housenumber":"309",
    "addr:postcode":"55387",
    "addr:street":"S Oak St",
    "iso:country":"US",
    "sg:address":"309 S Oak St",
    "sg:city":"Waconia",
    "sg:classifiers":[
        {
            "category":"Building & Trades",
            "subcategory":"Electrical",
            "type":"Services"
        }
    ],
    "sg:phone":"+1 952 442 8796",
    "sg:postcode":"55387",
    "sg:province":"MN",
    "sg:tags":[
        "industrial",
        "electrician",
        "electric",
        "contractors-commercial"
    ],
    "wof:name":"Adm Electric Of Waconia",
    "wof:placetype":"venue"
},
  "geometry": {"coordinates":[-93.781564,44.846609],"type":"Point"}
}