{
  "type": "Feature",
  "properties": {
    "addr:full":"22351 Saint Croix Trl N Scandia MN 55073",
    "addr:housenumber":"22351",
    "addr:postcode":"55073",
    "addr:street":"Saint Croix Trl N Scandia",
    "iso:country":"US",
    "sg:address":"22351 Saint Croix Trl N",
    "sg:city":"Scandia",
    "sg:classifiers":[
        {
            "category":"Restaurant",
            "type":"Food & Drink"
        }
    ],
    "sg:phone":"+1 651 433 2711",
    "sg:postcode":"55073",
    "sg:province":"MN",
    "wof:name":"Chef Michael Ferraro",
    "wof:placetype":"venue"
},
  "geometry": {"coordinates":[-92.77752,45.271731],"type":"Point"}
}