{
  "type": "Feature",
  "properties": {
    "iso:country":"US",
    "sg:address":"824 2nd St",
    "sg:city":"Internatl Falls",
    "sg:classifiers":[
        {
            "category":"Professional",
            "type":"Services"
        }
    ],
    "sg:phone":"+1 218 283 8130",
    "sg:postcode":"56649",
    "sg:province":"MN",
    "sg:tags":[
        "establishment"
    ],
    "wof:name":"Boise Co House 2",
    "wof:placetype":"venue"
},
  "geometry": {"coordinates":[-93.411829,48.604001],"type":"Point"}
}