{
  "type": "Feature",
  "properties": {
    "iso:country":"US",
    "sg:address":"24000 Highway 7 Ste 201",
    "sg:city":"Excelsior",
    "sg:classifiers":[
        {
            "category":"Wholesale",
            "subcategory":"Computers",
            "type":"Manufacturing & Wholesale Goods"
        }
    ],
    "sg:phone":"+1 952 470 8181",
    "sg:postcode":"55331",
    "sg:province":"MN",
    "sg:tags":[
        "equipment"
    ],
    "wof:name":"Final Click, The",
    "wof:placetype":"venue"
},
  "geometry": {"coordinates":[-93.558708,44.901562],"type":"Point"}
}