{
  "type": "Feature",
  "properties": {
    "addr:full":"1411 Center Ave W Dilworth MN 56529",
    "addr:housenumber":"1411",
    "addr:postcode":"56529",
    "addr:street":"Center Ave W",
    "iso:country":"US",
    "sg:address":"1411 Center Ave W",
    "sg:city":"Dilworth",
    "sg:classifiers":[
        {
            "category":"Shopping",
            "subcategory":"Stationery & Office Supplies",
            "type":"Retail Goods"
        },
        {
            "category":"Wholesale",
            "subcategory":"Stationery",
            "type":"Manufacturing & Wholesale Goods"
        }
    ],
    "sg:phone":"+1 218 287 1101",
    "sg:postcode":"56529",
    "sg:province":"MN",
    "sg:website":"www.officemax.com",
    "wof:name":"Office Max",
    "wof:placetype":"venue"
},
  "geometry": {"coordinates":[-96.720563,46.876421],"type":"Point"}
}