{
  "type": "Feature",
  "properties": {
    "addr:full":"4697 Canosia Rd Saginaw MN 55779",
    "addr:housenumber":"4697",
    "addr:postcode":"55779",
    "addr:street":"Canosia Rd",
    "iso:country":"US",
    "sg:address":"4697 Canosia Rd",
    "sg:city":"Saginaw",
    "sg:classifiers":[
        {
            "category":"Building & Trades",
            "subcategory":"Construction",
            "type":"Services"
        }
    ],
    "sg:phone":"+1 218 729 9672",
    "sg:postcode":"55779",
    "sg:province":"MN",
    "sg:tags":[
        "downspouts",
        "gutter",
        "contractor"
    ],
    "wof:name":"Mainstream Gutters",
    "wof:placetype":"venue"
},
  "geometry": {"coordinates":[-92.364768,46.844099],"type":"Point"}
}