{
  "type": "Feature",
  "properties": {
    "addr:full":"16315 Terrey Pine Dr Eden Prairie MN 55344",
    "addr:postcode":"16315;55344",
    "addr:street":"Terrey Pine Dr",
    "iso:country":"US",
    "sg:address":"16315 Terrey Pine Dr",
    "sg:city":"Eden Prairie",
    "sg:classifiers":[
        {
            "category":"Professional",
            "type":"Services"
        }
    ],
    "sg:phone":"+1 952 934 7087",
    "sg:postcode":"55344",
    "sg:province":"MN",
    "wof:name":"Hallmark Reality",
    "wof:placetype":"venue"
},
  "geometry": {"coordinates":[-93.484983,44.861123],"type":"Point"}
}