{
  "type": "Feature",
  "properties": {
    "iso:country":"US",
    "sg:address":"503 W Main St",
    "sg:city":"Arlington",
    "sg:classifiers":[
        {
            "category":"Health Services",
            "subcategory":"Doctor",
            "type":"Services"
        }
    ],
    "sg:phone":"+1 507 964 2748",
    "sg:postcode":"55307",
    "sg:province":"MN",
    "sg:tags":[
        "dentist"
    ],
    "wof:name":"H Michael Noack DDS",
    "wof:placetype":"venue"
},
  "geometry": {"coordinates":[-94.08459000000001,44.607264],"type":"Point"}
}