{
  "type": "Feature",
  "properties": {
    "addr:full":"2650 Southdale Ctr Minneapolis MN 55435",
    "addr:housenumber":"2650",
    "addr:postcode":"55435",
    "addr:street":"Southdale Ctr",
    "iso:country":"US",
    "sg:address":"2650 Southdale Ctr",
    "sg:city":"Minneapolis",
    "sg:classifiers":[
        {
            "category":"Shopping",
            "subcategory":"Clothing, Apparel, & Fashions",
            "type":"Retail Goods"
        }
    ],
    "sg:phone":"+1 952 649 3082",
    "sg:postcode":"55435",
    "sg:province":"MN",
    "sg:tags":[
        "men's",
        "clothing",
        "store"
    ],
    "sg:website":"http://www.savviformalwear.com",
    "wof:name":"Savvi Formalwear",
    "wof:placetype":"venue"
},
  "geometry": {"coordinates":[-93.322774,44.882778],"type":"Point"}
}