{
  "type": "Feature",
  "properties": {
    "iso:country":"US",
    "sg:address":"14393 E Oakgreen Cir S",
    "sg:city":"Afton",
    "sg:classifiers":[
        {
            "category":"Building & Trades",
            "subcategory":"Construction",
            "type":"Services"
        }
    ],
    "sg:phone":"+1 651 436 8152",
    "sg:postcode":"55001",
    "sg:province":"MN",
    "sg:tags":[
        "contractor"
    ],
    "wof:name":"Earth Accents Contracting",
    "wof:placetype":"venue"
},
  "geometry": {"coordinates":[-92.82288699999999,44.89546],"type":"Point"}
}