{
  "type": "Feature",
  "properties": {
    "iso:country":"US",
    "sg:address":"4578 340th Ave",
    "sg:city":"Montevideo",
    "sg:phone":"+1 320 269 9151",
    "sg:postcode":"56265",
    "sg:province":"MN",
    "sg:tags":[
        "farm",
        "corn",
        "wheat"
    ],
    "wof:name":"Larry Danielson",
    "wof:placetype":"venue"
},
  "geometry": {"coordinates":[-95.72551799999999,44.891484],"type":"Point"}
}