{
  "type": "Feature",
  "properties": {
    "addr:full":"8045 40th Ave SE Maynard MN 56260",
    "addr:housenumber":"8045",
    "addr:postcode":"56260",
    "addr:street":"40Th Ave Se",
    "iso:country":"US",
    "sg:address":"8045 40th Ave SE",
    "sg:city":"Maynard",
    "sg:classifiers":[
        {
            "category":"Retail",
            "subcategory":"Repair Shop",
            "type":"Services"
        }
    ],
    "sg:phone":"+1 320 367 2482",
    "sg:postcode":"56260",
    "sg:province":"MN",
    "wof:name":"Hansen Sharpening Service",
    "wof:placetype":"venue"
},
  "geometry": {"coordinates":[-95.514009,44.904678],"type":"Point"}
}