{
  "type": "Feature",
  "properties": {
    "addr:full":"901 Parker Ave W Dassel MN 55325",
    "addr:housenumber":"901",
    "addr:postcode":"55325",
    "addr:street":"Parker Ave W",
    "iso:country":"US",
    "sg:address":"901 Parker Ave W",
    "sg:city":"Dassel",
    "sg:classifiers":[
        {
            "category":"Wholesale",
            "subcategory":"Machinery & Supplies",
            "type":"Manufacturing & Wholesale Goods"
        }
    ],
    "sg:phone":"+1 320 275 2737",
    "sg:postcode":"55325",
    "sg:province":"MN",
    "sg:tags":[
        "contractor"
    ],
    "wof:name":"Farm-Rite Equipment Inc",
    "wof:placetype":"venue"
},
  "geometry": {"coordinates":[-94.317677,45.081023],"type":"Point"}
}