{
  "type": "Feature",
  "properties": {
    "addr:full":"118 7th Ave N Waite Park MN 56387",
    "addr:housenumber":"118",
    "addr:postcode":"56387",
    "addr:street":"7Th Ave N",
    "iso:country":"US",
    "sg:address":"118 7th Ave N",
    "sg:city":"Waite Park",
    "sg:classifiers":[
        {
            "category":"Freight",
            "type":"Transportation"
        }
    ],
    "sg:phone":"+1 320 251 0736",
    "sg:postcode":"56387",
    "sg:province":"MN",
    "sg:tags":[
        "operator",
        "local",
        "trucking"
    ],
    "wof:name":"Art Keller Trucking",
    "wof:placetype":"venue"
},
  "geometry": {"coordinates":[-94.225328,45.556799],"type":"Point"}
}