{
  "type": "Feature",
  "properties": {
    "addr:full":"12125 Technology Drive Eden Prairie MN 55344",
    "addr:housenumber":"12125",
    "addr:postcode":"55344",
    "addr:street":"Technology Drive",
    "iso:country":"US",
    "sg:address":"12125 Technology Drive",
    "sg:city":"Eden Prairie",
    "sg:classifiers":[
        {
            "category":"Professional",
            "subcategory":"Management & Consulting",
            "type":"Services"
        }
    ],
    "sg:phone":"+1 952 833 7100",
    "sg:postcode":"55344",
    "sg:province":"MN",
    "sg:website":"http://www.ingenix.com",
    "wof:name":"Ingenix",
    "wof:placetype":"venue"
},
  "geometry": {"coordinates":[-93.43592099999999,44.862066],"type":"Point"}
}