{
  "type": "Feature",
  "properties": {
    "iso:country":"US",
    "sg:address":"6112 18th St N",
    "sg:city":"Saint Cloud",
    "sg:classifiers":[
        {
            "category":"Shopping",
            "subcategory":"Used Merchandise",
            "type":"Retail Goods"
        }
    ],
    "sg:phone":"+1 320 253 9664",
    "sg:postcode":"56303",
    "sg:province":"MN",
    "wof:name":"Antique Haven",
    "wof:placetype":"venue"
},
  "geometry": {"coordinates":[-94.245228,45.581379],"type":"Point"}
}