{
  "type": "Feature",
  "properties": {
    "iso:country":"US",
    "sg:address":"47430 391st Ln",
    "sg:city":"Saint Peter",
    "sg:classifiers":[
        {
            "category":"Farming",
            "subcategory":"Livestock Farm",
            "type":"Manufacturing & Wholesale Goods"
        }
    ],
    "sg:phone":"+1 507 625 7087",
    "sg:postcode":"56082",
    "sg:province":"MN",
    "sg:tags":[
        "hog",
        "or",
        "feedlot"
    ],
    "wof:name":"Donald Dallmann",
    "wof:placetype":"venue"
},
  "geometry": {"coordinates":[-94.049689,44.262731],"type":"Point"}
}