{
  "type": "Feature",
  "properties": {
    "iso:country":"US",
    "sg:address":"1885 E 134th St",
    "sg:city":"Burnsville",
    "sg:classifiers":[
        {
            "category":"Social Services",
            "subcategory":"Child Care",
            "type":"Services"
        },
        {
            "category":"Education",
            "subcategory":"Preschool",
            "type":"Public Place"
        },
        {
            "category":"Education",
            "subcategory":"School",
            "type":"Public Place"
        }
    ],
    "sg:phone":"+1 952 431 1779",
    "sg:postcode":"55337",
    "sg:province":"MN",
    "sg:tags":[
        "elementary",
        "day"
    ],
    "wof:name":"New Horizon Academy",
    "wof:placetype":"venue"
},
  "geometry": {"coordinates":[-93.248205,44.7614],"type":"Point"}
}