{
  "type": "Feature",
  "properties": {
    "iso:country":"US",
    "sg:address":"785 School Rd NW",
    "sg:city":"Hutchinson",
    "sg:classifiers":[
        {
            "category":"Manufacturing",
            "subcategory":"Tools & Machinery",
            "type":"Manufacturing & Wholesale Goods"
        }
    ],
    "sg:phone":"+1 320 587 4875",
    "sg:postcode":"55350",
    "sg:province":"MN",
    "sg:tags":[
        "food",
        "product",
        "mfg"
    ],
    "wof:name":"Freland Barlau",
    "wof:placetype":"venue"
},
  "geometry": {"coordinates":[-94.39093699999999,44.902883],"type":"Point"}
}