{
  "type": "Feature",
  "properties": {
    "addr:full":"1611 W Co Rd C St Paul MN 55113",
    "addr:housenumber":"1611",
    "addr:postcode":"55113",
    "addr:street":"W Co Rd C",
    "iso:country":"US",
    "sg:address":"1611 W Co Rd C",
    "sg:city":"St Paul",
    "sg:classifiers":[
        {
            "category":"Shopping",
            "subcategory":"Pharmacy",
            "type":"Retail Goods"
        }
    ],
    "sg:phone":"+1 651 636 9365",
    "sg:postcode":"55113",
    "sg:province":"MN",
    "wof:name":"Walgreens",
    "wof:placetype":"venue"
},
  "geometry": {"coordinates":[-93.168072,45.021091],"type":"Point"}
}