{
  "type": "Feature",
  "properties": {
    "iso:country":"US",
    "sg:address":"2358 Stinson Blvd",
    "sg:city":"Minneapolis",
    "sg:classifiers":[
        {
            "category":"Real Estate",
            "subcategory":"Architect",
            "type":"Services"
        }
    ],
    "sg:phone":"+1 612 781 2844",
    "sg:postcode":"55418",
    "sg:province":"MN",
    "sg:tags":[
        "architectural"
    ],
    "wof:name":"Gaetz Architects Inc",
    "wof:placetype":"venue"
},
  "geometry": {"coordinates":[-93.22692499999999,45.012679],"type":"Point"}
}