{
  "type": "Feature",
  "properties": {
    "addr:full":"1309 Hwy 29 N Alexandria MN 56308",
    "addr:housenumber":"1309",
    "addr:postcode":"56308",
    "addr:street":"Hwy 29 N",
    "iso:country":"US",
    "sg:address":"1309 Hwy 29 N",
    "sg:city":"Alexandria",
    "sg:classifiers":[
        {
            "category":"Banks & Credit Unions",
            "subcategory":"Bank",
            "type":"Services"
        }
    ],
    "sg:phone":"+1 320 763 7075",
    "sg:postcode":"56308",
    "sg:province":"MN",
    "wof:name":"National Bank Examiners",
    "wof:placetype":"venue"
},
  "geometry": {"coordinates":[-95.36499999999999,45.899909],"type":"Point"}
}