{
  "type": "Feature",
  "properties": {
    "iso:country":"US",
    "sg:address":"15050 Cedar Ave",
    "sg:city":"Apple Valley",
    "sg:classifiers":[
        {
            "category":"Shopping",
            "subcategory":"Florist",
            "type":"Retail Goods"
        }
    ],
    "sg:phone":"+1 952 432 2455",
    "sg:postcode":"55124",
    "sg:province":"MN",
    "sg:website":"www.theplantpatch.com",
    "wof:name":"Plant Patch",
    "wof:placetype":"venue"
},
  "geometry": {"coordinates":[-93.21766700000001,44.73168],"type":"Point"}
}