{
  "type": "Feature",
  "properties": {
    "iso:country":"US",
    "sg:address":"13876 Lakeland Rd",
    "sg:city":"Saint Joseph",
    "sg:classifiers":[
        {
            "category":"Real Estate",
            "subcategory":"Real Estate Operator",
            "type":"Services"
        }
    ],
    "sg:phone":"+1 320 363 4306",
    "sg:postcode":"56374",
    "sg:province":"MN",
    "sg:tags":[
        "property",
        "lessor"
    ],
    "wof:name":"Klockers Family Farm Inc",
    "wof:placetype":"venue"
},
  "geometry": {"coordinates":[-94.393748,45.559189],"type":"Point"}
}