{
  "type": "Feature",
  "properties": {
    "iso:country":"US",
    "sg:address":"800 Winnetka Ave",
    "sg:city":"Minneapolis",
    "sg:classifiers":[
        {
            "category":"Taxi",
            "type":"Transportation"
        }
    ],
    "sg:phone":"+1 612 333 0469",
    "sg:postcode":"55427",
    "sg:province":"MN",
    "sg:tags":[
        "taxicab"
    ],
    "wof:name":"Blue & White Cabs",
    "wof:placetype":"venue"
},
  "geometry": {"coordinates":[-93.380302,44.987148],"type":"Point"}
}