{
  "type": "Feature",
  "properties": {
    "iso:country":"US",
    "sg:address":"20 4th Ave NW",
    "sg:city":"Wells",
    "sg:classifiers":[
        {
            "category":"Personal",
            "type":"Services"
        }
    ],
    "sg:phone":"+1 507 553 6182",
    "sg:postcode":"56097",
    "sg:province":"MN",
    "sg:tags":[
        "therapist",
        "massage"
    ],
    "wof:name":"On Gerry's Table",
    "wof:placetype":"venue"
},
  "geometry": {"coordinates":[-93.73126499999999,43.745566],"type":"Point"}
}