{
  "type": "Feature",
  "properties": {
    "addr:full":"20 4th Ave NW Wells MN 56097",
    "addr:housenumber":"20",
    "addr:postcode":"56097",
    "addr:street":"4Th Ave Nw",
    "iso:country":"US",
    "sg:address":"20 4th Ave NW",
    "sg:city":"Wells",
    "sg:classifiers":[
        {
            "category":"Personal",
            "type":"Services"
        }
    ],
    "sg:phone":"+1 507 553 6182",
    "sg:postcode":"56097",
    "sg:province":"MN",
    "sg:tags":[
        "therapist",
        "massage"
    ],
    "wof:name":"On Gerry's Table",
    "wof:placetype":"venue"
},
  "geometry": {"coordinates":[-93.73126499999999,43.745566],"type":"Point"}
}