{
  "type": "Feature",
  "properties": {
    "addr:full":"109 Park St S Minnesota Lake MN 56068",
    "addr:housenumber":"109",
    "addr:postcode":"56068",
    "addr:street":"Park St S;Lake",
    "iso:country":"US",
    "sg:address":"109 Park St S",
    "sg:city":"Minnesota Lake",
    "sg:classifiers":[
        {
            "category":"Organizations",
            "subcategory":"Religious Organization",
            "type":"Services"
        }
    ],
    "sg:phone":"+1 507 462 3636",
    "sg:postcode":"56068",
    "sg:province":"MN",
    "sg:tags":[
        "church"
    ],
    "wof:name":"St John Baptist Catholic Chr",
    "wof:placetype":"venue"
},
  "geometry": {"coordinates":[-93.831943,43.838705],"type":"Point"}
}