{
  "type": "Feature",
  "properties": {
    "iso:country":"US",
    "sg:address":"1300 Unity Ave N",
    "sg:city":"Minneapolis",
    "sg:classifiers":[
        {
            "category":"Professional",
            "subcategory":"Business Services",
            "type":"Services"
        }
    ],
    "sg:phone":"+1 763 521 2928",
    "sg:postcode":"55422",
    "sg:province":"MN",
    "wof:name":"Two Rabbits Design",
    "wof:placetype":"venue"
},
  "geometry": {"coordinates":[-93.34722600000001,44.992111],"type":"Point"}
}