{
  "type": "Feature",
  "properties": {
    "iso:country":"US",
    "sg:address":"1324 W Oakes Dr",
    "sg:city":"Saint Cloud",
    "sg:classifiers":[
        {
            "category":"Professional",
            "subcategory":"Business Services",
            "type":"Services"
        }
    ],
    "sg:phone":"+1 320 654 8701",
    "sg:postcode":"56303",
    "sg:province":"MN",
    "wof:name":"Zager Investment Ltd",
    "wof:placetype":"venue"
},
  "geometry": {"coordinates":[-94.227965,45.575764],"type":"Point"}
}