{
  "type": "Feature",
  "properties": {
    "iso:country":"US",
    "sg:address":"9322 Zane Ave N",
    "sg:city":"Minneapolis",
    "sg:classifiers":[
        {
            "category":"Restaurant",
            "type":"Food & Drink"
        }
    ],
    "sg:menulink":"http://www.allmenus.com/mn/brooklyn-park/58377-dominos-pizza/menu/",
    "sg:phone":"+1 763 391 0909",
    "sg:postcode":"55443",
    "sg:province":"MN",
    "sg:tags":[
        "american",
        "wing",
        "pizza"
    ],
    "wof:name":"Domino's Pizza",
    "wof:placetype":"venue"
},
  "geometry": {"coordinates":[-93.356216,45.124227],"type":"Point"}
}