{
  "type": "Feature",
  "properties": {
    "addr:full":"1220 E Wabasha St Winona MN 55987",
    "addr:housenumber":"1220",
    "addr:postcode":"55987",
    "addr:street":"E Wabasha St",
    "iso:country":"US",
    "sg:address":"1220 E Wabasha St",
    "sg:city":"Winona",
    "sg:classifiers":[
        {
            "category":"Retail",
            "subcategory":"Laundry & Dry Cleaning",
            "type":"Services"
        },
        {
            "category":"Building & Trades",
            "subcategory":"Cleaning & Sanitation",
            "type":"Services"
        }
    ],
    "sg:phone":"+1 507 452 1898",
    "sg:postcode":"55987",
    "sg:province":"MN",
    "sg:tags":[
        "cleaner",
        "floor",
        "fire",
        "house",
        "rug",
        "damage",
        "water",
        "waxing",
        "restoration",
        "polishing",
        "janitorial",
        "carpet"
    ],
    "sg:website":"http://www.servicemasterclean.com/",
    "wof:name":"Service Master Co",
    "wof:placetype":"venue"
},
  "geometry": {"coordinates":[-91.607812,44.03985],"type":"Point"}
}