{
  "type": "Feature",
  "properties": {
    "iso:country":"US",
    "sg:address":"54529 179th St",
    "sg:city":"Good Thunder",
    "sg:classifiers":[
        {
            "category":"Farming",
            "subcategory":"Farm",
            "type":"Manufacturing & Wholesale Goods"
        }
    ],
    "sg:phone":"+1 507 278 3774",
    "sg:postcode":"56037",
    "sg:province":"MN",
    "sg:tags":[
        "bean",
        "livestock",
        "crop",
        "general"
    ],
    "wof:name":"Paul Stewig",
    "wof:placetype":"venue"
},
  "geometry": {"coordinates":[-94.093698,44.064889],"type":"Point"}
}