{
  "type": "Feature",
  "properties": {
    "iso:country":"US",
    "sg:address":"145 Main St",
    "sg:city":"Wahkon",
    "sg:classifiers":[
        {
            "category":"Government",
            "subcategory":"Post Office",
            "type":"Public Place"
        }
    ],
    "sg:phone":"+1 320 495 3542",
    "sg:postcode":"56386",
    "sg:province":"MN",
    "wof:name":"US Post Office",
    "wof:placetype":"venue"
},
  "geometry": {"coordinates":[-93.521112,46.121],"type":"Point"}
}