{
  "type": "Feature",
  "properties": {
    "addr:full":"35878 US Hwy 61 Lake City MN 55041",
    "addr:housenumber":"35878",
    "addr:postcode":"55041",
    "addr:street":"Us Hwy 61",
    "iso:country":"US",
    "sg:address":"35878 US Hwy 61",
    "sg:city":"Lake City",
    "sg:classifiers":[
        {
            "category":"Shopping",
            "type":"Retail Goods"
        }
    ],
    "sg:phone":"+1 651 345 3705",
    "sg:postcode":"55041",
    "sg:province":"MN",
    "sg:tags":[
        "miscellaneous",
        "store"
    ],
    "wof:name":"SVJ Creative Designs",
    "wof:placetype":"venue"
},
  "geometry": {"coordinates":[-92.31568900000001,44.498216],"type":"Point"}
}