{
  "type": "Feature",
  "properties": {
    "addr:full":"7126 State Hwy 61 Tofte MN 55615",
    "addr:housenumber":"7126",
    "addr:postcode":"55615",
    "addr:street":"State Hwy 61",
    "iso:country":"US",
    "sg:address":"7126 State Hwy 61",
    "sg:city":"Tofte",
    "sg:classifiers":[
        {
            "category":"Restaurant",
            "type":"Food & Drink"
        }
    ],
    "sg:phone":"+1 218 663 8032",
    "sg:postcode":"55615",
    "sg:province":"MN",
    "wof:name":"Coho Cafe",
    "wof:placetype":"venue"
},
  "geometry": {"coordinates":[-90.82468,47.57972],"type":"Point"}
}