{
  "type": "Feature",
  "properties": {
    "addr:full":"5137 McDonnell Rd Duluth MN 55804",
    "addr:postcode":"5137;55804",
    "addr:street":"Mcdonnell Rd",
    "iso:country":"US",
    "sg:address":"5137 McDonnell Rd",
    "sg:city":"Duluth",
    "sg:classifiers":[
        {
            "category":"Building & Trades",
            "subcategory":"Construction",
            "type":"Services"
        }
    ],
    "sg:phone":"+1 218 525 6793",
    "sg:postcode":"55804",
    "sg:province":"MN",
    "sg:tags":[
        "house",
        "general",
        "contractor"
    ],
    "wof:name":"Northland Builders & Remodeler",
    "wof:placetype":"venue"
},
  "geometry": {"coordinates":[-91.95249699999999,46.888594],"type":"Point"}
}