{
  "type": "Feature",
  "properties": {
    "iso:country":"US",
    "sg:address":"7581 170th St W",
    "sg:city":"Lakeville",
    "sg:classifiers":[
        {
            "category":"Building & Trades",
            "subcategory":"Plumbing",
            "type":"Services"
        },
        {
            "category":"Building & Trades",
            "subcategory":"Construction",
            "type":"Services"
        }
    ],
    "sg:phone":"+1 952 239 9122",
    "sg:postcode":"55044",
    "sg:province":"MN",
    "sg:tags":[
        "altering",
        "plumber",
        "remodeling",
        "contractor"
    ],
    "wof:name":"Stead Plumbing & Heating",
    "wof:placetype":"venue"
},
  "geometry": {"coordinates":[-93.219566,44.703352],"type":"Point"}
}