{
  "type": "Feature",
  "properties": {
    "addr:full":"PROFESSIONAL WEBSITE DESIGN STARTING @ $198 Minneapolis MN 55432",
    "addr:housenumber":"198",
    "addr:postcode":"55432",
    "iso:country":"US",
    "sg:address":"PROFESSIONAL WEBSITE DESIGN STARTING @ $198",
    "sg:city":"Minneapolis",
    "sg:classifiers":[
        {
            "category":"Professional",
            "subcategory":"Advertising",
            "type":"Services"
        },
        {
            "category":"Professional",
            "subcategory":"Computer Services",
            "type":"Services"
        }
    ],
    "sg:phone":"+1 612 298 3470",
    "sg:postcode":"55432",
    "sg:province":"MN",
    "sg:tags":[
        "web",
        "marketing",
        "hosting",
        "site",
        "internet"
    ],
    "sg:website":"http://www.MinneapolisWebMarketing.com",
    "wof:name":"Minneapolis Web Marketing",
    "wof:placetype":"venue"
},
  "geometry": {"coordinates":[-93.247704,45.071529],"type":"Point"}
}