{
  "type": "Feature",
  "properties": {
    "addr:full":"7300 Brataas Dr SW Rochester MN 55902",
    "addr:housenumber":"7300",
    "addr:postcode":"55902",
    "addr:street":"Brataas Dr Sw",
    "iso:country":"US",
    "sg:address":"7300 Brataas Dr SW",
    "sg:city":"Rochester",
    "sg:classifiers":[
        {
            "category":"Retail",
            "subcategory":"Auto Rental",
            "type":"Services"
        }
    ],
    "sg:phone":"+1 507 252 5045",
    "sg:postcode":"55902",
    "sg:province":"MN",
    "sg:tags":[
        "renting",
        "automobile"
    ],
    "wof:name":"Thrifty Car Rental",
    "wof:placetype":"venue"
},
  "geometry": {"coordinates":[-92.49579,43.91479],"type":"Point"}
}