{
  "type": "Feature",
  "properties": {
    "addr:full":"2382 State Hwy 55 Hamel MN 55340",
    "addr:housenumber":"2382",
    "addr:postcode":"55340",
    "addr:street":"State Hwy 55 Hamel",
    "iso:country":"US",
    "sg:address":"2382 State Hwy 55",
    "sg:city":"Hamel",
    "sg:classifiers":[
        {
            "category":"Building & Trades",
            "subcategory":"Construction",
            "type":"Services"
        }
    ],
    "sg:phone":"+1 763 478 6131",
    "sg:postcode":"55340",
    "sg:province":"MN",
    "sg:tags":[
        "commercial",
        "family",
        "contractor"
    ],
    "wof:name":"Lingen Construction Inc",
    "wof:placetype":"venue"
},
  "geometry": {"coordinates":[-93.58566399999999,45.057236],"type":"Point"}
}