{
  "type": "Feature",
  "properties": {
    "iso:country":"US",
    "sg:address":"31868 Co Rd 3",
    "sg:city":"Crosslake",
    "sg:classifiers":[
        {
            "category":"Building & Trades",
            "subcategory":"Plumbing",
            "type":"Services"
        }
    ],
    "sg:phone":"+1 218 765 4250",
    "sg:postcode":"56442",
    "sg:province":"MN",
    "sg:tags":[
        "conditioning",
        "air",
        "system",
        "contractor"
    ],
    "wof:name":"Paul Willmus Htg & Cooling LLP",
    "wof:placetype":"venue"
},
  "geometry": {"coordinates":[-94.13170599999999,46.615206],"type":"Point"}
}