{
  "type": "Feature",
  "properties": {
    "addr:full":"6523 117th St NW Maple Lake MN 55358",
    "addr:housenumber":"6523",
    "addr:postcode":"55358",
    "addr:street":"117Th St Nw",
    "iso:country":"US",
    "sg:address":"6523 117th St NW",
    "sg:city":"Maple Lake",
    "sg:classifiers":[
        {
            "category":"Health Services",
            "subcategory":"Clinic",
            "type":"Services"
        }
    ],
    "sg:phone":"+1 320 963 7571",
    "sg:postcode":"55358",
    "sg:province":"MN",
    "sg:tags":[
        "home"
    ],
    "wof:name":"Sugar Lake Supported Living",
    "wof:placetype":"venue"
},
  "geometry": {"coordinates":[-94.02421200000001,45.320557],"type":"Point"}
}