{
  "type": "Feature",
  "properties": {
    "addr:full":"12160 168th St W Lakeville MN 55044",
    "addr:housenumber":"12160",
    "addr:postcode":"55044",
    "addr:street":"168Th St W",
    "iso:country":"US",
    "sg:address":"12160 168th St W",
    "sg:city":"Lakeville",
    "sg:classifiers":[
        {
            "category":"Professional",
            "subcategory":"Computer Services",
            "type":"Services"
        }
    ],
    "sg:phone":"+1 952 435 5071",
    "sg:postcode":"55044",
    "sg:province":"MN",
    "sg:tags":[
        "related"
    ],
    "wof:name":"Advance Tech Inc",
    "wof:placetype":"venue"
},
  "geometry": {"coordinates":[-93.31067299999999,44.704983],"type":"Point"}
}