{
  "type": "Feature",
  "properties": {
    "addr:full":"1420 3rd Ave W Ste 1 Shakopee MN 55379",
    "addr:housenumber":"1420",
    "addr:postcode":"55379",
    "addr:street":"3Rd Ave W Ste 1",
    "iso:country":"US",
    "sg:address":"1420 3rd Ave W Ste 1",
    "sg:city":"Shakopee",
    "sg:classifiers":[
        {
            "category":"Building & Trades",
            "subcategory":"Plumbing",
            "type":"Services"
        }
    ],
    "sg:phone":"+1 952 445 4444",
    "sg:postcode":"55379",
    "sg:province":"MN",
    "sg:website":"www.mnplumbingandheating.com",
    "wof:name":"Minnesota Plumbing and Heating Inc",
    "wof:placetype":"venue"
},
  "geometry": {"coordinates":[-93.549103,44.7915],"type":"Point"}
}