{
  "type": "Feature",
  "properties": {
    "addr:full":"4130 W Division St St Cloud MN 56301",
    "addr:housenumber":"4130",
    "addr:postcode":"56301",
    "addr:street":"W Division St",
    "iso:country":"US",
    "sg:address":"4130 W Division St",
    "sg:city":"St Cloud",
    "sg:classifiers":[
        {
            "category":"Shopping",
            "subcategory":"Computers & Home Electronics",
            "type":"Retail Goods"
        }
    ],
    "sg:phone":"+1 320 259 5208",
    "sg:postcode":"56301",
    "sg:province":"MN",
    "sg:tags":[
        "supply",
        "electronic",
        "household",
        "appliance",
        "equipment",
        "consumer"
    ],
    "wof:name":"Best Buy",
    "wof:placetype":"venue"
},
  "geometry": {"coordinates":[-94.213131,45.553337],"type":"Point"}
}