{
  "type": "Feature",
  "properties": {
    "iso:country":"US",
    "sg:address":"2900 W 43rd St",
    "sg:city":"Minneapolis",
    "sg:classifiers":[
        {
            "category":"Education",
            "subcategory":"Library",
            "type":"Public Place"
        }
    ],
    "sg:phone":"+1 612 630 6750",
    "sg:postcode":"55410",
    "sg:province":"MN",
    "sg:website":"www.mplib.org",
    "wof:name":"Minneapolis Public Library",
    "wof:placetype":"venue"
},
  "geometry": {"coordinates":[-93.316498,44.9249],"type":"Point"}
}