{
  "type": "Feature",
  "properties": {
    "addr:full":"7801 Metro Pkwy Bloomington MN 55425",
    "addr:housenumber":"7801",
    "addr:postcode":"55425",
    "addr:street":"Metro Pkwy",
    "iso:country":"US",
    "sg:address":"7801 Metro Pkwy",
    "sg:city":"Bloomington",
    "sg:classifiers":[
        {
            "category":"Organizations",
            "subcategory":"Labor Organization",
            "type":"Services"
        }
    ],
    "sg:phone":"+1 952 851 3580",
    "sg:postcode":"55425",
    "sg:province":"MN",
    "wof:name":"AMFA",
    "wof:placetype":"venue"
},
  "geometry": {"coordinates":[-93.229148,44.860199],"type":"Point"}
}