{
  "type": "Feature",
  "properties": {
    "iso:country":"US",
    "sg:address":"23230 E Martin Lake Dr NE",
    "sg:city":"Stacy",
    "sg:classifiers":[
        {
            "category":"Building & Trades",
            "subcategory":"Construction",
            "type":"Services"
        }
    ],
    "sg:phone":"+1 651 462 5188",
    "sg:postcode":"55079",
    "sg:province":"MN",
    "sg:tags":[
        "home",
        "builder"
    ],
    "wof:name":"Carpenter Homes Inc",
    "wof:placetype":"venue"
},
  "geometry": {"coordinates":[-93.082353,45.390574],"type":"Point"}
}