{
  "type": "Feature",
  "properties": {
    "iso:country":"US",
    "sg:address":"4347 Fox Ridge Ct",
    "sg:city":"St Paul",
    "sg:classifiers":[
        {
            "category":"Professional",
            "subcategory":"Testing Lab",
            "type":"Services"
        },
        {
            "category":"Professional",
            "subcategory":"Business Services",
            "type":"Services"
        }
    ],
    "sg:phone":"+1 651 994 4832",
    "sg:postcode":"55122",
    "sg:province":"MN",
    "sg:tags":[
        "measuring",
        "air",
        "pollution"
    ],
    "wof:name":"Vector Environmental Testing",
    "wof:placetype":"venue"
},
  "geometry": {"coordinates":[-93.199078,44.797891],"type":"Point"}
}