{
  "type": "Feature",
  "properties": {
    "iso:country":"US",
    "sg:address":"5301 Edina Industrial Blvd",
    "sg:city":"Edina",
    "sg:classifiers":[
        {
            "category":"Recreation",
            "type":"Entertainment"
        }
    ],
    "sg:phone":"+1 952 832 0000",
    "sg:postcode":"55439",
    "sg:province":"MN",
    "sg:tags":[
        "instruction",
        "golf"
    ],
    "wof:name":"Driving Obsession Inc",
    "wof:placetype":"venue"
},
  "geometry": {"coordinates":[-93.35760999999999,44.863154],"type":"Point"}
}