{
  "type": "Feature",
  "properties": {
    "addr:full":"W Broadway Ave 607 W Broadway Minneapolis MN 55428",
    "addr:housenumber":"607",
    "addr:postcode":"55428",
    "addr:street":"W Broadway Ave;W Broadway",
    "iso:country":"US",
    "sg:address":"W Broadway Ave 607 W Broadway",
    "sg:city":"Minneapolis",
    "sg:classifiers":[
        {
            "category":"Professional",
            "subcategory":"Accounting & Tax Preparation",
            "type":"Services"
        },
        {
            "category":"Banks & Credit Unions",
            "subcategory":"Financial Services",
            "type":"Services"
        }
    ],
    "sg:phone":"+1 612 529 7729",
    "sg:postcode":"55428",
    "sg:province":"MN",
    "sg:tags":[
        "return",
        "preparation-business",
        "taxes-consultants",
        "loan",
        "reporting",
        "representative",
        "alternative",
        "bookkeeping"
    ],
    "sg:website":"http://www.hrblock.com",
    "wof:name":"H&R Block",
    "wof:placetype":"venue"
},
  "geometry": {"coordinates":[-93.35979500000001,45.049768],"type":"Point"}
}