{
  "type": "Feature",
  "properties": {
    "addr:full":"1429 Grant-Mcmahan Blvd Ely MN 55731",
    "addr:housenumber":"1429",
    "addr:postcode":"55731",
    "addr:street":"Grant-Mcmahan Blvd",
    "iso:country":"US",
    "sg:address":"1429 Grant-Mcmahan Blvd",
    "sg:city":"Ely",
    "sg:classifiers":[
        {
            "category":"Government",
            "subcategory":"Office",
            "type":"Public Place"
        }
    ],
    "sg:phone":"+1 218 365 7280",
    "sg:postcode":"55731",
    "sg:province":"MN",
    "sg:tags":[
        "state"
    ],
    "wof:name":"Fish & Wildlife Office",
    "wof:placetype":"venue"
},
  "geometry": {"coordinates":[-91.830327,47.921755],"type":"Point"}
}