{
  "type": "Feature",
  "properties": {
    "iso:country":"US",
    "sg:address":"1124 Highland Cir",
    "sg:city":"Farmington",
    "sg:classifiers":[
        {
            "category":"Building & Trades",
            "subcategory":"Construction",
            "type":"Services"
        }
    ],
    "sg:phone":"+1 651 463 8433",
    "sg:postcode":"55024",
    "sg:province":"MN",
    "sg:tags":[
        "wallcoverings-installation",
        "wallpaper",
        "painting",
        "contractor"
    ],
    "wof:name":"Blairs Painting",
    "wof:placetype":"venue"
},
  "geometry": {"coordinates":[-93.13864100000001,44.629665],"type":"Point"}
}