{
  "type": "Feature",
  "properties": {
    "iso:country":"US",
    "sg:address":"20974 680th Ave",
    "sg:city":"Alden",
    "sg:phone":"+1 507 874 3712",
    "sg:postcode":"56009",
    "sg:province":"MN",
    "sg:tags":[
        "farm",
        "corn"
    ],
    "wof:name":"David Behrends",
    "wof:placetype":"venue"
},
  "geometry": {"coordinates":[-93.50827,43.657716],"type":"Point"}
}