{
  "type": "Feature",
  "properties": {
    "iso:country":"US",
    "sg:address":"8400 Normandale Lake Blvd",
    "sg:city":"Minneapolis",
    "sg:classifiers":[
        {
            "category":"Professional",
            "subcategory":"Management & Consulting",
            "type":"Services"
        },
        {
            "category":"Banks & Credit Unions",
            "subcategory":"Financial Services",
            "type":"Services"
        }
    ],
    "sg:phone":"+1 952 921 8428",
    "sg:postcode":"55437",
    "sg:province":"MN",
    "sg:tags":[
        "consultant",
        "financing",
        "planning"
    ],
    "wof:name":"Douglas B Tenpas",
    "wof:placetype":"venue"
},
  "geometry": {"coordinates":[-93.356059,44.853567],"type":"Point"}
}