{
  "type": "Feature",
  "properties": {
    "iso:country":"US",
    "sg:address":"5850 Opus Pkwy",
    "sg:city":"Hopkins",
    "sg:classifiers":[
        {
            "category":"Professional",
            "subcategory":"Lawyer & Legal Services",
            "type":"Services"
        }
    ],
    "sg:phone":"+1 952 545 8755",
    "sg:postcode":"55343",
    "sg:province":"MN",
    "sg:tags":[
        "attorney"
    ],
    "wof:name":"Kondzella & Cyr",
    "wof:placetype":"venue"
},
  "geometry": {"coordinates":[-93.40860600000001,44.896675],"type":"Point"}
}