{
  "type": "Feature",
  "properties": {
    "iso:country":"US",
    "sg:address":"2533 14th Ave S",
    "sg:city":"Minneapolis",
    "sg:classifiers":[
        {
            "category":"Utilities",
            "subcategory":"Water",
            "type":"Services"
        },
        {
            "category":"Utilities",
            "type":"Services"
        }
    ],
    "sg:phone":"+1 612 722 1677",
    "sg:postcode":"55404",
    "sg:province":"MN",
    "sg:tags":[
        "consultant",
        "management",
        "public"
    ],
    "wof:name":"Grass Roots Public Policy",
    "wof:placetype":"venue"
},
  "geometry": {"coordinates":[-93.25496,44.956649],"type":"Point"}
}