{
  "type": "Feature",
  "properties": {
    "iso:country":"US",
    "sg:address":"12 S River St",
    "sg:city":"Cook",
    "sg:classifiers":[
        {
            "category":"Building & Trades",
            "subcategory":"Equipment Rental",
            "type":"Services"
        }
    ],
    "sg:phone":"+1 218 666 2290",
    "sg:postcode":"55723",
    "sg:province":"MN",
    "sg:tags":[
        "yard",
        "leasing",
        "contractors'",
        "equipment-renting",
        "store",
        "furniture"
    ],
    "wof:name":"Hadersbeck's Hometown Hardware & Rent-All",
    "wof:placetype":"venue"
},
  "geometry": {"coordinates":[-92.68888699999999,47.85361],"type":"Point"}
}