{
  "type": "Feature",
  "properties": {
    "addr:full":"525 W Paquin St Waterville MN 56096",
    "addr:housenumber":"525",
    "addr:postcode":"56096",
    "addr:street":"W Paquin St",
    "iso:country":"US",
    "sg:address":"525 W Paquin St",
    "sg:city":"Waterville",
    "sg:classifiers":[
        {
            "category":"Restaurant",
            "type":"Food & Drink"
        }
    ],
    "sg:phone":"+1 507 362 4497",
    "sg:postcode":"56096",
    "sg:province":"MN",
    "wof:name":"Shake It Up",
    "wof:placetype":"venue"
},
  "geometry": {"coordinates":[-93.57665,44.217719],"type":"Point"}
}