{
  "type": "Feature",
  "properties": {
    "iso:country":"US",
    "sg:address":"2520 10th St SW",
    "sg:city":"Buffalo",
    "sg:classifiers":[
        {
            "category":"Farming",
            "subcategory":"Livestock Farm",
            "type":"Manufacturing & Wholesale Goods"
        }
    ],
    "sg:phone":"+1 763 682 4607",
    "sg:postcode":"55313",
    "sg:province":"MN",
    "sg:tags":[
        "corn",
        "beef",
        "feedlot",
        "cattle"
    ],
    "wof:name":"Steve Frykholm",
    "wof:placetype":"venue"
},
  "geometry": {"coordinates":[-93.941542,45.137641],"type":"Point"}
}