{
  "type": "Feature",
  "properties": {
    "addr:full":"1804 Tyrol St Duluth MN 55811",
    "addr:postcode":"1804;55811",
    "addr:street":"Tyrol St",
    "iso:country":"US",
    "sg:address":"1804 Tyrol St",
    "sg:city":"Duluth",
    "sg:classifiers":[
        {
            "category":"Building & Trades",
            "subcategory":"Construction",
            "type":"Services"
        }
    ],
    "sg:phone":"+1 218 727 8467",
    "sg:postcode":"55811",
    "sg:province":"MN",
    "sg:tags":[
        "general",
        "contractor"
    ],
    "wof:name":"Superior Construction Co Inc",
    "wof:placetype":"venue"
},
  "geometry": {"coordinates":[-92.151957,46.773675],"type":"Point"}
}