{
  "type": "Feature",
  "properties": {
    "iso:country":"US",
    "sg:address":"200 Central Ave E",
    "sg:city":"St Michael",
    "sg:classifiers":[
        {
            "category":"Shopping",
            "subcategory":"Florist",
            "type":"Retail Goods"
        }
    ],
    "sg:phone":"+1 763 497 4234",
    "sg:postcode":"55376",
    "sg:province":"MN",
    "wof:name":"St Michael Floral Inc",
    "wof:placetype":"venue"
},
  "geometry": {"coordinates":[-93.6589,45.210094],"type":"Point"}
}