{
  "type": "Feature",
  "properties": {
    "iso:country":"US",
    "sg:address":"38223 460th Ave",
    "sg:city":"Windom",
    "sg:phone":"+1 507 831 3766",
    "sg:postcode":"56101",
    "sg:province":"MN",
    "sg:tags":[
        "farm",
        "corn",
        "grain",
        "cash"
    ],
    "wof:name":"Frank Kerkvliet",
    "wof:placetype":"venue"
},
  "geometry": {"coordinates":[-95.16027800000001,43.930647],"type":"Point"}
}