{
  "type": "Feature",
  "properties": {
    "iso:country":"US",
    "sg:address":"123 N Hwy 86",
    "sg:city":"Lakefield",
    "sg:classifiers":[
        {
            "category":"Manufacturing",
            "subcategory":"Motor Vehicles & Parts",
            "type":"Manufacturing & Wholesale Goods"
        }
    ],
    "sg:phone":"+1 507 840 1040",
    "sg:postcode":"56150",
    "sg:province":"MN",
    "sg:tags":[
        "designer",
        "trailer"
    ],
    "wof:name":"E & T Enterprises",
    "wof:placetype":"venue"
},
  "geometry": {"coordinates":[-95.174696,43.675298],"type":"Point"}
}