{
  "type": "Feature",
  "properties": {
    "addr:full":"20282 370th Ave Springfield MN 56087",
    "addr:housenumber":"20282",
    "addr:postcode":"56087",
    "addr:street":"370Th Ave",
    "iso:country":"US",
    "sg:address":"20282 370th Ave",
    "sg:city":"Springfield",
    "sg:classifiers":[
        {
            "category":"Retail",
            "subcategory":"Auto Repair",
            "type":"Services"
        }
    ],
    "sg:phone":"+1 507 723 5972",
    "sg:postcode":"56087",
    "sg:province":"MN",
    "sg:tags":[
        "automotive"
    ],
    "wof:name":"Moes Service",
    "wof:placetype":"venue"
},
  "geometry": {"coordinates":[-94.92678100000001,44.26759],"type":"Point"}
}