{
  "type": "Feature",
  "properties": {
    "iso:country":"US",
    "sg:address":"533 Cypress Ct",
    "sg:city":"Cold Spring",
    "sg:classifiers":[
        {
            "category":"Professional",
            "type":"Services"
        }
    ],
    "sg:phone":"+1 320 253 0230",
    "sg:postcode":"56320",
    "sg:province":"MN",
    "wof:name":"Jennifer A Herberg",
    "wof:placetype":"venue"
},
  "geometry": {"coordinates":[-94.346611,45.461505],"type":"Point"}
}