{
  "type": "Feature",
  "properties": {
    "addr:full":"1436 Cliff Rd E Burnsville MN 55337",
    "addr:housenumber":"1436",
    "addr:postcode":"55337",
    "addr:street":"Cliff Rd E",
    "iso:country":"US",
    "sg:address":"1436 Cliff Rd E",
    "sg:city":"Burnsville",
    "sg:classifiers":[
        {
            "category":"Wholesale",
            "subcategory":"Electrical",
            "type":"Manufacturing & Wholesale Goods"
        }
    ],
    "sg:phone":"+1 952 707 8600",
    "sg:postcode":"55337",
    "sg:province":"MN",
    "sg:tags":[
        "refuse",
        "system"
    ],
    "wof:name":"Speec Flourescent Recycling",
    "wof:placetype":"venue"
},
  "geometry": {"coordinates":[-93.256051,44.790417],"type":"Point"}
}