{
  "type": "Feature",
  "properties": {
    "iso:country":"US",
    "sg:address":"1013 Hart Blvd",
    "sg:city":"Monticello",
    "sg:classifiers":[
        {
            "category":"Building & Trades",
            "subcategory":"Construction",
            "type":"Services"
        },
        {
            "category":"Professional",
            "subcategory":"Management & Consulting",
            "type":"Services"
        }
    ],
    "sg:phone":"+1 763 295 1911",
    "sg:postcode":"55362",
    "sg:province":"MN",
    "sg:tags":[
        "general",
        "contractor"
    ],
    "wof:name":"Construction Analysis & Manage",
    "wof:placetype":"venue"
},
  "geometry": {"coordinates":[-93.779456,45.299948],"type":"Point"}
}