{
  "type": "Feature",
  "properties": {
    "addr:full":"407 Central Ave N Mapleton MN 56065",
    "addr:housenumber":"407",
    "addr:postcode":"56065",
    "addr:street":"Central Ave N",
    "iso:country":"US",
    "sg:address":"407 Central Ave N",
    "sg:city":"Mapleton",
    "sg:classifiers":[
        {
            "category":"Retail",
            "subcategory":"Auto Repair",
            "type":"Services"
        }
    ],
    "sg:phone":"+1 507 524 4766",
    "sg:postcode":"56065",
    "sg:province":"MN",
    "sg:tags":[
        "body",
        "automobile",
        "painting"
    ],
    "wof:name":"Scott's Body Shop-Mapleton Inc",
    "wof:placetype":"venue"
},
  "geometry": {"coordinates":[-93.958455,43.930348],"type":"Point"}
}