{
  "type": "Feature",
  "properties": {
    "addr:full":"1810 Whitetail Run Buffalo MN 55313",
    "addr:housenumber":"1810",
    "addr:postcode":"55313",
    "addr:street":"Whitetail Run",
    "iso:country":"US",
    "sg:address":"1810 Whitetail Run",
    "sg:city":"Buffalo",
    "sg:classifiers":[
        {
            "category":"Professional",
            "subcategory":"Business Services",
            "type":"Services"
        }
    ],
    "sg:phone":"+1 763 565 3054",
    "sg:postcode":"55313",
    "sg:province":"MN",
    "wof:name":"Kenyon Premier Enterprises",
    "wof:placetype":"venue"
},
  "geometry": {"coordinates":[-93.834006,45.200696],"type":"Point"}
}