{
  "type": "Feature",
  "properties": {
    "iso:country":"US",
    "sg:address":"3801 Leslee Curv",
    "sg:city":"Chanhassen",
    "sg:classifiers":[
        {
            "category":"Real Estate",
            "subcategory":"Real Estate Services",
            "type":"Services"
        }
    ],
    "sg:phone":"+1 952 474 4200",
    "sg:postcode":"55317",
    "sg:province":"MN",
    "wof:name":"Avalon Real Estate",
    "wof:placetype":"venue"
},
  "geometry": {"coordinates":[-93.55549600000001,44.862598],"type":"Point"}
}