{
  "type": "Feature",
  "properties": {
    "addr:full":"1610 Sherwood Dr North Mankato MN 56003",
    "addr:housenumber":"1610",
    "addr:postcode":"56003",
    "addr:street":"Sherwood Dr North",
    "iso:country":"US",
    "sg:address":"1610 Sherwood Dr",
    "sg:city":"North Mankato",
    "sg:classifiers":[
        {
            "category":"Health Services",
            "subcategory":"Doctor",
            "type":"Services"
        }
    ],
    "sg:phone":"+1 507 386 0847",
    "sg:postcode":"56003",
    "sg:province":"MN",
    "sg:tags":[
        "physician",
        "surgeon"
    ],
    "wof:name":"Severson Frederick Dr & Mary",
    "wof:placetype":"venue"
},
  "geometry": {"coordinates":[-94.024114,44.173184],"type":"Point"}
}