{
  "type": "Feature",
  "properties": {
    "addr:full":"129 Main St W Waconia MN 55387",
    "addr:housenumber":"129",
    "addr:postcode":"55387",
    "addr:street":"Main St W Waconia",
    "iso:country":"US",
    "sg:address":"129 Main St W",
    "sg:city":"Waconia",
    "sg:classifiers":[
        {
            "category":"Professional",
            "subcategory":"Accounting & Tax Preparation",
            "type":"Services"
        }
    ],
    "sg:phone":"+1 952 442 3727",
    "sg:postcode":"55387",
    "sg:province":"MN",
    "wof:name":"Bratsch Roebke Ltd",
    "wof:placetype":"venue"
},
  "geometry": {"coordinates":[-93.78881,44.850374],"type":"Point"}
}