{
  "type": "Feature",
  "properties": {
    "iso:country":"US",
    "sg:address":"12540 210th Ave SE",
    "sg:city":"Lake Lillian",
    "sg:phone":"+1 320 664 4843",
    "sg:postcode":"56253",
    "sg:province":"MN",
    "sg:tags":[
        "farm",
        "corn"
    ],
    "wof:name":"Nolan Jungclaus",
    "wof:placetype":"venue"
},
  "geometry": {"coordinates":[-94.870458,44.921397],"type":"Point"}
}