{
  "type": "Feature",
  "properties": {
    "addr:full":"7580 150th St W Apple Valley MN 55124",
    "addr:housenumber":"7580",
    "addr:postcode":"55124",
    "addr:street":"150Th St W",
    "iso:country":"US",
    "sg:address":"7580 150th St W",
    "sg:city":"Apple Valley",
    "sg:classifiers":[
        {
            "category":"Shopping",
            "type":"Retail Goods"
        }
    ],
    "sg:phone":"+1 952 431 3099",
    "sg:postcode":"55124",
    "sg:province":"MN",
    "sg:tags":[
        "picture",
        "frame"
    ],
    "wof:name":"Gallery Editions",
    "wof:placetype":"venue"
},
  "geometry": {"coordinates":[-93.218535,44.731808],"type":"Point"}
}