{
  "type": "Feature",
  "properties": {
    "addr:full":"19357 Spencer Rd Brainerd MN 56401",
    "addr:housenumber":"19357",
    "addr:postcode":"56401",
    "addr:street":"Spencer Rd",
    "iso:country":"US",
    "sg:address":"19357 Spencer Rd",
    "sg:city":"Brainerd",
    "sg:classifiers":[
        {
            "category":"Building & Trades",
            "subcategory":"Construction",
            "type":"Services"
        }
    ],
    "sg:phone":"+1 218 828 1417",
    "sg:postcode":"56401",
    "sg:province":"MN",
    "sg:tags":[
        "contractor",
        "co",
        "painter",
        "hanging"
    ],
    "wof:name":"Nelson's Drywall & Painting",
    "wof:placetype":"venue"
},
  "geometry": {"coordinates":[-94.176278,46.430965],"type":"Point"}
}