{
  "type": "Feature",
  "properties": {
    "iso:country":"US",
    "sg:address":"942 6th Ave S",
    "sg:city":"Saint Cloud",
    "sg:classifiers":[
        {
            "category":"Building & Trades",
            "subcategory":"Construction",
            "type":"Services"
        }
    ],
    "sg:phone":"+1 320 240 9254",
    "sg:postcode":"56301",
    "sg:province":"MN",
    "sg:tags":[
        "contractor"
    ],
    "wof:name":"P L M Striping",
    "wof:placetype":"venue"
},
  "geometry": {"coordinates":[-94.155868,45.550096],"type":"Point"}
}