{
  "type": "Feature",
  "properties": {
    "iso:country":"US",
    "sg:address":"140 W 98th St Ste 215",
    "sg:city":"Minneapolis",
    "sg:classifiers":[
        {
            "category":"Insurance",
            "subcategory":"Hazard Insurance",
            "type":"Services"
        }
    ],
    "sg:phone":"+1 952 888 7205",
    "sg:postcode":"55420",
    "sg:province":"MN",
    "sg:tags":[
        "commercial",
        "business"
    ],
    "wof:name":"United Claim Service Inc",
    "wof:placetype":"venue"
},
  "geometry": {"coordinates":[-93.281381,44.826359],"type":"Point"}
}