{
  "type": "Feature",
  "properties": {
    "addr:full":"232 Xerxes Ave N Minneapolis MN 55405",
    "addr:housenumber":"232",
    "addr:postcode":"55405",
    "addr:street":"Xerxes Ave N",
    "iso:country":"US",
    "sg:address":"232 Xerxes Ave N",
    "sg:city":"Minneapolis",
    "sg:classifiers":[
        {
            "category":"Building & Trades",
            "subcategory":"Landscaping Services",
            "type":"Services"
        }
    ],
    "sg:phone":"+1 612 377 4491",
    "sg:postcode":"55405",
    "sg:province":"MN",
    "sg:tags":[
        "gardener"
    ],
    "sg:website":"http://www.temenosgardens.com",
    "wof:name":"Temenos Garden Services",
    "wof:placetype":"venue"
},
  "geometry": {"coordinates":[-93.31849,44.978104],"type":"Point"}
}