{
  "type": "Feature",
  "properties": {
    "iso:country":"US",
    "sg:address":"3620 11th Ave S",
    "sg:city":"Minneapolis",
    "sg:classifiers":[
        {
            "category":"Professional",
            "subcategory":"Management & Consulting",
            "type":"Services"
        }
    ],
    "sg:phone":"+1 612 724 8114",
    "sg:postcode":"55407",
    "sg:province":"MN",
    "sg:tags":[
        "business"
    ],
    "wof:name":"Esther Derby Associates Inc",
    "wof:placetype":"venue"
},
  "geometry": {"coordinates":[-93.258802,44.936311],"type":"Point"}
}