{
  "type": "Feature",
  "properties": {
    "addr:full":"4707 Lyndale Ave N Minneapolis MN 55430",
    "addr:housenumber":"4707",
    "addr:postcode":"55430",
    "addr:street":"Lyndale Ave N",
    "iso:country":"US",
    "sg:address":"4707 Lyndale Ave N",
    "sg:city":"Minneapolis",
    "sg:classifiers":[
        {
            "category":"Professional",
            "subcategory":"Accounting & Tax Preparation",
            "type":"Services"
        }
    ],
    "sg:phone":"+1 612 287 8474",
    "sg:postcode":"55430",
    "sg:province":"MN",
    "sg:tags":[
        "return"
    ],
    "wof:name":"Lyndale Tax Services",
    "wof:placetype":"venue"
},
  "geometry": {"coordinates":[-93.286689,45.041934],"type":"Point"}
}