{
  "type": "Feature",
  "properties": {
    "addr:full":"1200 Main St E Sleepy Eye MN 56085",
    "addr:housenumber":"1200",
    "addr:postcode":"56085",
    "addr:street":"Main St E",
    "iso:country":"US",
    "sg:address":"1200 Main St E",
    "sg:city":"Sleepy Eye",
    "sg:classifiers":[
        {
            "category":"Home & Garden",
            "subcategory":"Hardware",
            "type":"Retail Goods"
        }
    ],
    "sg:phone":"+1 507 794 3611",
    "sg:postcode":"56085",
    "sg:province":"MN",
    "wof:name":"Mc Cabe's Ace Hardware",
    "wof:placetype":"venue"
},
  "geometry": {"coordinates":[-94.70763100000001,44.297428],"type":"Point"}
}