{
  "type": "Feature",
  "properties": {
    "addr:full":"7948 Douglas Dr N Minneapolis MN 55443",
    "addr:housenumber":"7948",
    "addr:postcode":"55443",
    "addr:street":"Douglas Dr N",
    "iso:country":"US",
    "sg:address":"7948 Douglas Dr N",
    "sg:city":"Minneapolis",
    "sg:classifiers":[
        {
            "category":"Building & Trades",
            "subcategory":"Construction",
            "type":"Services"
        }
    ],
    "sg:phone":"+1 763 561 7724",
    "sg:postcode":"55443",
    "sg:province":"MN",
    "sg:tags":[
        "concrete",
        "contractor"
    ],
    "wof:name":"Englert Cement LLC",
    "wof:placetype":"venue"
},
  "geometry": {"coordinates":[-93.36148300000001,45.100435],"type":"Point"}
}