{
  "type": "Feature",
  "properties": {
    "addr:full":"1201 Gilmore Ave Winona MN 55987",
    "addr:housenumber":"1201",
    "addr:postcode":"55987",
    "addr:street":"Gilmore Ave",
    "iso:country":"US",
    "sg:address":"1201 Gilmore Ave",
    "sg:city":"Winona",
    "sg:classifiers":[
        {
            "category":"Health Services",
            "subcategory":"Dentist",
            "type":"Services"
        }
    ],
    "sg:phone":"+1 507 452 8668",
    "sg:postcode":"55987",
    "sg:province":"MN",
    "wof:name":"Gary L Granseth Dds",
    "wof:placetype":"venue"
},
  "geometry": {"coordinates":[-91.668835,44.048531],"type":"Point"}
}