{
  "type": "Feature",
  "properties": {
    "iso:country":"US",
    "sg:address":"220 W Johnson Ave",
    "sg:city":"Warren",
    "sg:classifiers":[
        {
            "category":"Organizations",
            "subcategory":"Religious Organization",
            "type":"Services"
        }
    ],
    "sg:phone":"+1 218 745 4478",
    "sg:postcode":"56762",
    "sg:province":"MN",
    "sg:tags":[
        "church"
    ],
    "wof:name":"Our Savior's Lutheran Church",
    "wof:placetype":"venue"
},
  "geometry": {"coordinates":[-96.774722,48.19621],"type":"Point"}
}