{
  "type": "Feature",
  "properties": {
    "iso:country":"US",
    "sg:address":"14 University Ave NE",
    "sg:city":"Minneapolis",
    "sg:classifiers":[
        {
            "category":"Autos & Motor Vehicles",
            "subcategory":"Automobile Sales",
            "type":"Retail Goods"
        }
    ],
    "sg:phone":"+1 612 623 4440",
    "sg:postcode":"55413",
    "sg:province":"MN",
    "wof:name":"Jim Lupient Buick",
    "wof:placetype":"venue"
},
  "geometry": {"coordinates":[-93.25706700000001,44.988845],"type":"Point"}
}