{
  "type": "Feature",
  "properties": {
    "addr:full":"1225 6th Ave Worthington MN 56187",
    "addr:housenumber":"1225",
    "addr:postcode":"56187",
    "addr:street":"6Th Ave",
    "iso:country":"US",
    "sg:address":"1225 6th Ave",
    "sg:city":"Worthington",
    "sg:phone":"+1 507 376 4789",
    "sg:postcode":"56187",
    "sg:province":"MN",
    "sg:tags":[
        "farm",
        "corn",
        "soybean"
    ],
    "wof:name":"D Obermoller",
    "wof:placetype":"venue"
},
  "geometry": {"coordinates":[-95.595946,43.623998],"type":"Point"}
}