{
  "type": "Feature",
  "properties": {
    "addr:full":"41670 170th St Glencoe MN 55336",
    "addr:housenumber":"41670",
    "addr:postcode":"55336",
    "addr:street":"170Th St",
    "iso:country":"US",
    "sg:address":"41670 170th St",
    "sg:city":"Glencoe",
    "sg:classifiers":[
        {
            "category":"Social Services",
            "subcategory":"Child Care",
            "type":"Services"
        }
    ],
    "sg:phone":"+1 320 864 6640",
    "sg:postcode":"55336",
    "sg:province":"MN",
    "sg:tags":[
        "daycare",
        "provider"
    ],
    "wof:name":"Linda Becker",
    "wof:placetype":"venue"
},
  "geometry": {"coordinates":[-94.102726,44.702655],"type":"Point"}
}