{
  "type": "Feature",
  "properties": {
    "iso:country":"US",
    "sg:address":"20581 490th St",
    "sg:city":"Pine Island",
    "sg:phone":"+1 507 356 4060",
    "sg:postcode":"55963",
    "sg:province":"MN",
    "sg:tags":[
        "farm",
        "field",
        "crop"
    ],
    "wof:name":"Brian Morris",
    "wof:placetype":"venue"
},
  "geometry": {"coordinates":[-92.62104600000001,44.238606],"type":"Point"}
}