{
  "type": "Feature",
  "properties": {
    "iso:country":"US",
    "sg:address":"885 Pembina Trl",
    "sg:city":"Detroit Lakes",
    "sg:classifiers":[
        {
            "category":"Organizations",
            "subcategory":"Religious Organization",
            "type":"Services"
        }
    ],
    "sg:phone":"+1 218 847 4818",
    "sg:postcode":"56501",
    "sg:province":"MN",
    "sg:tags":[
        "church"
    ],
    "wof:name":"United Methodist Church",
    "wof:placetype":"venue"
},
  "geometry": {"coordinates":[-95.828136,46.8076],"type":"Point"}
}