{
  "type": "Feature",
  "properties": {
    "iso:country":"US",
    "sg:address":"12904 1st St",
    "sg:city":"Becker",
    "sg:classifiers":[
        {
            "category":"Retail",
            "subcategory":"Veterinary Services",
            "type":"Services"
        }
    ],
    "sg:phone":"+1 763 261 5595",
    "sg:postcode":"55308",
    "sg:province":"MN",
    "sg:tags":[
        "veterinarian"
    ],
    "wof:name":"Becker Veterinary Clinic",
    "wof:placetype":"venue"
},
  "geometry": {"coordinates":[-93.892273,45.402929],"type":"Point"}
}