{
  "type": "Feature",
  "properties": {
    "addr:full":"801 9th Ave Foley MN 56329",
    "addr:housenumber":"801",
    "addr:postcode":"56329",
    "addr:street":"9Th Ave",
    "iso:country":"US",
    "sg:address":"801 9th Ave",
    "sg:city":"Foley",
    "sg:classifiers":[
        {
            "category":"Real Estate",
            "subcategory":"Real Estate Operator",
            "type":"Services"
        }
    ],
    "sg:phone":"+1 320 968 8070",
    "sg:postcode":"56329",
    "sg:province":"MN",
    "sg:tags":[
        "mobile",
        "home",
        "site"
    ],
    "wof:name":"Foley Mobile Home Park",
    "wof:placetype":"venue"
},
  "geometry": {"coordinates":[-93.903215,45.67157],"type":"Point"}
}