{
  "type": "Feature",
  "properties": {
    "iso:country":"US",
    "sg:address":"5870 Beachwood Rd",
    "sg:city":"Mound",
    "sg:classifiers":[
        {
            "category":"Shopping",
            "subcategory":"Clothing, Apparel, & Fashions",
            "type":"Retail Goods"
        }
    ],
    "sg:phone":"+1 952 472 8521",
    "sg:postcode":"55364",
    "sg:province":"MN",
    "wof:name":"Gentle Men Movers Inc",
    "wof:placetype":"venue"
},
  "geometry": {"coordinates":[-93.67263,44.92868],"type":"Point"}
}