{
  "type": "Feature",
  "properties": {
    "addr:full":"1535 Rice St Saint Paul MN 55117",
    "addr:housenumber":"1535",
    "addr:postcode":"55117",
    "addr:street":"Rice St",
    "iso:country":"US",
    "sg:address":"1535 Rice St",
    "sg:city":"Saint Paul",
    "sg:classifiers":[
        {
            "category":"Restaurant",
            "type":"Food & Drink"
        }
    ],
    "sg:menulink":"http://www.allmenus.com/mn/st-paul/194036-mcdonalds/menu/",
    "sg:postcode":"55117",
    "sg:province":"MN",
    "sg:tags":[
        "burger",
        "american"
    ],
    "wof:name":"McDonald's",
    "wof:placetype":"venue"
},
  "geometry": {"coordinates":[-93.106244,44.987654],"type":"Point"}
}