{
  "type": "Feature",
  "properties": {
    "iso:country":"US",
    "sg:address":"164 Pioneer Trl",
    "sg:city":"Chaska",
    "sg:classifiers":[
        {
            "category":"Shopping",
            "subcategory":"Mobile Phones",
            "type":"Retail Goods"
        }
    ],
    "sg:phone":"+1 952 556 5679",
    "sg:postcode":"55318",
    "sg:province":"MN",
    "wof:name":"Embarq",
    "wof:placetype":"venue"
},
  "geometry": {"coordinates":[-93.601097,44.829716],"type":"Point"}
}