{
  "type": "Feature",
  "properties": {
    "iso:country":"US",
    "sg:address":"2593 Geranium Ave E",
    "sg:city":"Saint Paul",
    "sg:classifiers":[
        {
            "category":"Real Estate",
            "subcategory":"Real Estate Agent",
            "type":"Services"
        }
    ],
    "sg:phone":"+1 651 773 2511",
    "sg:postcode":"55119",
    "sg:province":"MN",
    "wof:name":"Fedora Punky-Burnet Realty",
    "wof:placetype":"venue"
},
  "geometry": {"coordinates":[-92.98629699999999,44.976645],"type":"Point"}
}