{
  "type": "Feature",
  "properties": {
    "addr:full":"14775 Canada Ave W Rosemount MN 55068",
    "addr:postcode":"14775;55068",
    "addr:street":"Canada Ave W",
    "iso:country":"US",
    "sg:address":"14775 Canada Ave W",
    "sg:city":"Rosemount",
    "sg:classifiers":[
        {
            "category":"Social Services",
            "subcategory":"Child Care",
            "type":"Services"
        }
    ],
    "sg:phone":"+1 651 423 3831",
    "sg:postcode":"55068",
    "sg:province":"MN",
    "sg:tags":[
        "daycare",
        "provider"
    ],
    "wof:name":"Colleen Hellickson",
    "wof:placetype":"venue"
},
  "geometry": {"coordinates":[-93.131282,44.734779],"type":"Point"}
}