{
  "type": "Feature",
  "properties": {
    "addr:full":"275 Market St Ste 560 Minneapolis MN 55405",
    "addr:housenumber":"275",
    "addr:postcode":"55405",
    "addr:street":"Market St Ste 560",
    "iso:country":"US",
    "sg:address":"275 Market St Ste 560",
    "sg:city":"Minneapolis",
    "sg:classifiers":[
        {
            "category":"Professional",
            "subcategory":"Art Services",
            "type":"Services"
        }
    ],
    "sg:phone":"+1 612 341 2452",
    "sg:postcode":"55405",
    "sg:province":"MN",
    "sg:tags":[
        "interior",
        "designer",
        "decorator"
    ],
    "wof:name":"Mullin Interior Designer",
    "wof:placetype":"venue"
},
  "geometry": {"coordinates":[-93.289466,44.980831],"type":"Point"}
}