{
  "type": "Feature",
  "properties": {
    "iso:country":"US",
    "sg:address":"2311 Scenic Dr",
    "sg:city":"Princeton",
    "sg:classifiers":[
        {
            "category":"Freight",
            "type":"Transportation"
        }
    ],
    "sg:phone":"+1 763 389 1374",
    "sg:postcode":"55371",
    "sg:province":"MN",
    "sg:tags":[
        "operator",
        "local",
        "trucking"
    ],
    "wof:name":"Vanderpoel Trucking",
    "wof:placetype":"venue"
},
  "geometry": {"coordinates":[-93.527978,45.575786],"type":"Point"}
}