{
  "type": "Feature",
  "properties": {
    "addr:full":"13020 Riverdale Dr NW Minneapolis MN 55448",
    "addr:housenumber":"13020",
    "addr:postcode":"55448",
    "addr:street":"Riverdale Dr Nw",
    "iso:country":"US",
    "sg:address":"13020 Riverdale Dr NW",
    "sg:city":"Minneapolis",
    "sg:classifiers":[
        {
            "category":"Restaurant",
            "type":"Food & Drink"
        }
    ],
    "sg:phone":"+1 763 576 8033",
    "sg:postcode":"55448",
    "sg:province":"MN",
    "wof:name":"McDonald's",
    "wof:placetype":"venue"
},
  "geometry": {"coordinates":[-93.35900100000001,45.206799],"type":"Point"}
}