{
  "type": "Feature",
  "properties": {
    "iso:country":"US",
    "sg:address":"8501 Golden Valley Rd",
    "sg:city":"Minneapolis",
    "sg:classifiers":[
        {
            "category":"Professional",
            "subcategory":"Lawyer & Legal Services",
            "type":"Services"
        }
    ],
    "sg:phone":"+1 763 593 5115",
    "sg:postcode":"55427",
    "sg:province":"MN",
    "sg:tags":[
        "attorney"
    ],
    "wof:name":"Rondoni & Schneider LTD",
    "wof:placetype":"venue"
},
  "geometry": {"coordinates":[-93.38827999999999,44.985993],"type":"Point"}
}