{
  "type": "Feature",
  "properties": {
    "iso:country":"US",
    "sg:address":"1940 Hennepin Ave",
    "sg:city":"Minneapolis",
    "sg:classifiers":[
        {
            "category":"Recreation",
            "type":"Entertainment"
        }
    ],
    "sg:phone":"+1 612 870 1795",
    "sg:postcode":"55403",
    "sg:province":"MN",
    "sg:tags":[
        "karate",
        "martial art",
        "instruction"
    ],
    "wof:name":"Midwest Karate Association",
    "wof:placetype":"venue"
},
  "geometry": {"coordinates":[-93.290398,44.964001],"type":"Point"}
}