{
  "type": "Feature",
  "properties": {
    "iso:country":"US",
    "sg:address":"418 Lowry Ct NW",
    "sg:city":"Rochester",
    "sg:classifiers":[
        {
            "category":"Professional",
            "type":"Services"
        }
    ],
    "sg:phone":"+1 507 284 8700",
    "sg:postcode":"55901",
    "sg:province":"MN",
    "sg:tags":[
        "lecturing"
    ],
    "wof:name":"Gregory J Gores",
    "wof:placetype":"venue"
},
  "geometry": {"coordinates":[-92.55513999999999,44.031915],"type":"Point"}
}