{
  "type": "Feature",
  "properties": {
    "addr:full":"201 Campbell St Welcome MN 56181",
    "addr:housenumber":"201",
    "addr:postcode":"56181",
    "addr:street":"Campbell St",
    "iso:country":"US",
    "sg:address":"201 Campbell St",
    "sg:city":"Welcome",
    "sg:classifiers":[
        {
            "category":"Real Estate",
            "subcategory":"Real Estate Operator",
            "type":"Services"
        }
    ],
    "sg:phone":"+1 507 345 1290",
    "sg:postcode":"56181",
    "sg:province":"MN",
    "sg:tags":[
        "apartment"
    ],
    "wof:name":"Campbell Street Apartments",
    "wof:placetype":"venue"
},
  "geometry": {"coordinates":[-94.618073,43.66811],"type":"Point"}
}