{
  "type": "Feature",
  "properties": {
    "addr:full":"802 3rd Ave N Sartell MN 56377",
    "addr:housenumber":"802",
    "addr:postcode":"56377",
    "addr:street":"3Rd Ave N",
    "iso:country":"US",
    "sg:address":"802 3rd Ave N",
    "sg:city":"Sartell",
    "sg:classifiers":[
        {
            "category":"Professional",
            "subcategory":"Business Services",
            "type":"Services"
        }
    ],
    "sg:phone":"+1 320 253 9331",
    "sg:postcode":"56377",
    "sg:province":"MN",
    "sg:tags":[
        "consultant",
        "coach"
    ],
    "wof:name":"Independent Kitchen Consultant",
    "wof:placetype":"venue"
},
  "geometry": {"coordinates":[-94.20911099999999,45.632117],"type":"Point"}
}