{
  "type": "Feature",
  "properties": {
    "iso:country":"US",
    "sg:address":"9792 Ulysses St NE",
    "sg:city":"Minneapolis",
    "sg:classifiers":[
        {
            "category":"Building & Trades",
            "subcategory":"Construction",
            "type":"Services"
        }
    ],
    "sg:phone":"+1 612 623 4544",
    "sg:postcode":"55434",
    "sg:province":"MN",
    "sg:tags":[
        "water",
        "restoration",
        "damage"
    ],
    "sg:website":"www.curewaterdamage.com",
    "wof:name":"Cure Water Damage Restoration",
    "wof:placetype":"venue"
},
  "geometry": {"coordinates":[-93.237207,45.146932],"type":"Point"}
}