{
  "type": "Feature",
  "properties": {
    "addr:full":"15355 Eland St NW Anoka MN 55303",
    "addr:housenumber":"15355",
    "addr:postcode":"55303",
    "addr:street":"Eland St Nw",
    "iso:country":"US",
    "sg:address":"15355 Eland St NW",
    "sg:city":"Anoka",
    "sg:classifiers":[
        {
            "category":"Social Services",
            "subcategory":"Child Care",
            "type":"Services"
        }
    ],
    "sg:phone":"+1 763 421 0157",
    "sg:postcode":"55303",
    "sg:province":"MN",
    "sg:tags":[
        "day"
    ],
    "wof:name":"Kems Kits",
    "wof:placetype":"venue"
},
  "geometry": {"coordinates":[-93.471384,45.249885],"type":"Point"}
}