{
  "type": "Feature",
  "properties": {
    "iso:country":"US",
    "sg:address":"708 13th Ave SE",
    "sg:city":"Rochester",
    "sg:classifiers":[
        {
            "category":"Building & Trades",
            "subcategory":"Construction",
            "type":"Services"
        }
    ],
    "sg:phone":"+1 507 288 8204",
    "sg:postcode":"55904",
    "sg:province":"MN",
    "sg:tags":[
        "hanging",
        "contractor"
    ],
    "wof:name":"Mikes Painting",
    "wof:placetype":"venue"
},
  "geometry": {"coordinates":[-92.44643600000001,44.015074],"type":"Point"}
}