{
  "type": "Feature",
  "properties": {
    "iso:country":"US",
    "sg:address":"10663 Washington Blvd NE",
    "sg:city":"Minneapolis",
    "sg:classifiers":[
        {
            "category":"Wholesale",
            "subcategory":"Vending Machines",
            "type":"Manufacturing & Wholesale Goods"
        }
    ],
    "sg:phone":"+1 763 755 4837",
    "sg:postcode":"55434",
    "sg:province":"MN",
    "sg:tags":[
        "operator"
    ],
    "wof:name":"Toots Vending",
    "wof:placetype":"venue"
},
  "geometry": {"coordinates":[-93.25708400000001,45.164267],"type":"Point"}
}