{
  "type": "Feature",
  "properties": {
    "iso:country":"US",
    "sg:address":"1124 Pond Curv",
    "sg:city":"Waconia",
    "sg:classifiers":[
        {
            "category":"Health Services",
            "subcategory":"Health Practitioner",
            "type":"Services"
        }
    ],
    "sg:phone":"+1 952 442 8859",
    "sg:postcode":"55387",
    "sg:province":"MN",
    "sg:tags":[
        "rehabilitation"
    ],
    "wof:name":"Rehabworks Inc",
    "wof:placetype":"venue"
},
  "geometry": {"coordinates":[-93.81805900000001,44.837631],"type":"Point"}
}