{
  "type": "Feature",
  "properties": {
    "addr:full":"3715 84th St NE Remer MN 56672",
    "addr:housenumber":"3715",
    "addr:postcode":"56672",
    "addr:street":"84Th St Ne",
    "iso:country":"US",
    "sg:address":"3715 84th St NE",
    "sg:city":"Remer",
    "sg:classifiers":[
        {
            "category":"Professional",
            "subcategory":"Lawyer & Legal Services",
            "type":"Services"
        }
    ],
    "sg:phone":"+1 218 566 2802",
    "sg:postcode":"56672",
    "sg:province":"MN",
    "sg:tags":[
        "attorney"
    ],
    "wof:name":"Mansur & O'Leary",
    "wof:placetype":"venue"
},
  "geometry": {"coordinates":[-94.08794,47.110841],"type":"Point"}
}