{
  "type": "Feature",
  "properties": {
    "addr:full":"803 2nd Ave E Sartell MN 56377",
    "addr:housenumber":"803",
    "addr:postcode":"56377",
    "addr:street":"2Nd Ave E",
    "iso:country":"US",
    "sg:address":"803 2nd Ave E",
    "sg:city":"Sartell",
    "sg:classifiers":[
        {
            "category":"Organizations",
            "subcategory":"Religious Organization",
            "type":"Services"
        }
    ],
    "sg:phone":"+1 320 253 1586",
    "sg:postcode":"56377",
    "sg:province":"MN",
    "sg:tags":[
        "clergy"
    ],
    "wof:name":"Brian Blauer",
    "wof:placetype":"venue"
},
  "geometry": {"coordinates":[-94.198412,45.624491],"type":"Point"}
}