{
  "type": "Feature",
  "properties": {
    "addr:full":"1110 S Riverfront Dr Mankato MN 56001",
    "addr:housenumber":"1110",
    "addr:postcode":"56001",
    "addr:street":"S Riverfront Dr",
    "iso:country":"US",
    "sg:address":"1110 S Riverfront Dr",
    "sg:city":"Mankato",
    "sg:phone":"+1 507 385 7733",
    "sg:postcode":"56001",
    "sg:province":"MN",
    "sg:website":"http://www.greatclips.com/",
    "wof:name":"Great Clips",
    "wof:placetype":"venue"
},
  "geometry": {"coordinates":[-94.014375,44.160442],"type":"Point"}
}