{
  "type": "Feature",
  "properties": {
    "addr:full":"508 Indiana Ave N Minneapolis MN 55422",
    "addr:housenumber":"508",
    "addr:postcode":"55422",
    "addr:street":"Indiana Ave N",
    "iso:country":"US",
    "sg:address":"508 Indiana Ave N",
    "sg:city":"Minneapolis",
    "sg:classifiers":[
        {
            "category":"Shopping",
            "subcategory":"Pets & Pet Supplies",
            "type":"Retail Goods"
        },
        {
            "category":"Retail",
            "subcategory":"Animal Services",
            "type":"Services"
        }
    ],
    "sg:phone":"+1 612 201 7090",
    "sg:postcode":"55422",
    "sg:province":"MN",
    "sg:tags":[
        "grooming",
        "dog",
        "cat"
    ],
    "wof:name":"Low Cost Dog And Cat Grooming",
    "wof:placetype":"venue"
},
  "geometry": {"coordinates":[-93.33251799999999,44.982653],"type":"Point"}
}