{
  "type": "Feature",
  "properties": {
    "iso:country":"US",
    "sg:address":"19352 460th St",
    "sg:city":"Zumbrota",
    "sg:classifiers":[
        {
            "category":"Building & Trades",
            "subcategory":"Construction",
            "type":"Services"
        }
    ],
    "sg:phone":"+1 507 732 7279",
    "sg:postcode":"55992",
    "sg:province":"MN",
    "sg:tags":[
        "carpentry",
        "contractor"
    ],
    "wof:name":"Thomas McNamara",
    "wof:placetype":"venue"
},
  "geometry": {"coordinates":[-92.647814,44.281902],"type":"Point"}
}