{
  "type": "Feature",
  "properties": {
    "addr:full":"1407 E College Dr Marshall MN 56258",
    "addr:housenumber":"1407",
    "addr:postcode":"56258",
    "addr:street":"E College Dr",
    "iso:country":"US",
    "sg:address":"1407 E College Dr",
    "sg:city":"Marshall",
    "sg:classifiers":[
        {
            "category":"Restaurant",
            "type":"Food & Drink"
        }
    ],
    "sg:phone":"+1 507 537 1988",
    "sg:postcode":"56258",
    "sg:province":"MN",
    "sg:tags":[
        "eating"
    ],
    "wof:name":"Chicken Connection",
    "wof:placetype":"venue"
},
  "geometry": {"coordinates":[-95.76437,44.45042],"type":"Point"}
}