{
  "type": "Feature",
  "properties": {
    "iso:country":"US",
    "sg:address":"405 7th St S",
    "sg:city":"Virginia",
    "sg:classifiers":[
        {
            "category":"Personal",
            "subcategory":"Beauty Salon",
            "type":"Services"
        }
    ],
    "sg:phone":"+1 218 741 2931",
    "sg:postcode":"55792",
    "sg:province":"MN",
    "sg:tags":[
        "shop"
    ],
    "wof:name":"Karen's Beauty Shop",
    "wof:placetype":"venue"
},
  "geometry": {"coordinates":[-92.538436,47.517017],"type":"Point"}
}