{
  "type": "Feature",
  "properties": {
    "addr:full":"1621 Adams St Mankato MN 56001",
    "addr:housenumber":"1621",
    "addr:postcode":"56001",
    "addr:street":"Adams St",
    "iso:country":"US",
    "sg:address":"1621 Adams St",
    "sg:city":"Mankato",
    "sg:classifiers":[
        {
            "category":"Manufacturing",
            "subcategory":"Printing",
            "type":"Manufacturing & Wholesale Goods"
        }
    ],
    "sg:phone":"+1 507 387 1690",
    "sg:postcode":"56001",
    "sg:province":"MN",
    "sg:tags":[
        "screen"
    ],
    "sg:website":"www.bstark.com",
    "wof:name":"B Stark & Co",
    "wof:placetype":"venue"
},
  "geometry": {"coordinates":[-93.962192,44.169811],"type":"Point"}
}