{
  "type": "Feature",
  "properties": {
    "iso:country":"US",
    "sg:address":"1561 1st Ave E",
    "sg:city":"Shakopee",
    "sg:classifiers":[
        {
            "category":"Restaurant",
            "type":"Food & Drink"
        },
        {
            "category":"Bakery",
            "type":"Food & Drink"
        }
    ],
    "sg:phone":"+1 952 445 2228",
    "sg:postcode":"55379",
    "sg:province":"MN",
    "sg:tags":[
        "italian"
    ],
    "sg:website":"www.panzanellabistro.com",
    "wof:name":"Panzanella Bistro",
    "wof:placetype":"venue"
},
  "geometry": {"coordinates":[-93.50949900000001,44.8008],"type":"Point"}
}