{
  "type": "Feature",
  "properties": {
    "iso:country":"US",
    "sg:address":"918 3 Lakes Rd",
    "sg:city":"Ottertail",
    "sg:classifiers":[
        {
            "category":"Professional",
            "type":"Services"
        }
    ],
    "sg:phone":"+1 218 367 3418",
    "sg:postcode":"56571",
    "sg:province":"MN",
    "sg:tags":[
        "establishment"
    ],
    "wof:name":"Anderson & Anderson",
    "wof:placetype":"venue"
},
  "geometry": {"coordinates":[-95.564365,46.465546],"type":"Point"}
}