{
  "type": "Feature",
  "properties": {
    "iso:country":"US",
    "sg:address":"8187 University Ave NE",
    "sg:city":"Minneapolis",
    "sg:classifiers":[
        {
            "category":"Shopping",
            "type":"Retail Goods"
        }
    ],
    "sg:phone":"+1 763 717 9777",
    "sg:postcode":"55432",
    "sg:province":"MN",
    "sg:tags":[
        "merchandise"
    ],
    "wof:name":"Superior Opportunities",
    "wof:placetype":"venue"
},
  "geometry": {"coordinates":[-93.263479,45.118415],"type":"Point"}
}