{
  "type": "Feature",
  "properties": {
    "addr:full":"33 S 6th St Ste 4200 Minneapolis MN 55402",
    "addr:housenumber":"33",
    "addr:postcode":"4200;55402",
    "addr:street":"S 6Th St Ste",
    "iso:country":"US",
    "sg:address":"33 S 6th St Ste 4200",
    "sg:city":"Minneapolis",
    "sg:classifiers":[
        {
            "category":"Professional",
            "subcategory":"Lawyer & Legal Services",
            "type":"Services"
        }
    ],
    "sg:phone":"+1 612 338 0661",
    "sg:postcode":"55402",
    "sg:province":"MN",
    "wof:name":"Hughes John C Atty",
    "wof:placetype":"venue"
},
  "geometry": {"coordinates":[-93.271103,44.976398],"type":"Point"}
}