{
  "type": "Feature",
  "properties": {
    "iso:country":"US",
    "sg:address":"3451 Feldman Ave SE",
    "sg:city":"Buffalo",
    "sg:classifiers":[
        {
            "category":"Social Services",
            "subcategory":"Child Care",
            "type":"Services"
        }
    ],
    "sg:phone":"+1 763 477 6039",
    "sg:postcode":"55313",
    "sg:province":"MN",
    "sg:tags":[
        "day"
    ],
    "wof:name":"Redline Consultants",
    "wof:placetype":"venue"
},
  "geometry": {"coordinates":[-93.77498900000001,45.101977],"type":"Point"}
}