{
  "type": "Feature",
  "properties": {
    "iso:country":"US",
    "sg:address":"304 Clubhouse Dr NE",
    "sg:city":"Stewartville",
    "sg:classifiers":[
        {
            "category":"Professional",
            "subcategory":"Business Services",
            "type":"Services"
        }
    ],
    "sg:phone":"+1 507 533 4500",
    "sg:postcode":"55976",
    "sg:province":"MN",
    "wof:name":"Jerry Dallmann Auctioneer",
    "wof:placetype":"venue"
},
  "geometry": {"coordinates":[-92.485283,43.866954],"type":"Point"}
}