{
  "type": "Feature",
  "properties": {
    "addr:full":"3921 W 143rd St Savage MN 55378",
    "addr:housenumber":"3921",
    "addr:postcode":"55378",
    "addr:street":"W 143Rd St",
    "iso:country":"US",
    "sg:address":"3921 W 143rd St",
    "sg:city":"Savage",
    "sg:classifiers":[
        {
            "category":"Banks & Credit Unions",
            "subcategory":"Financial Services",
            "type":"Services"
        }
    ],
    "sg:phone":"+1 952 894 4242",
    "sg:postcode":"55378",
    "sg:province":"MN",
    "sg:website":"www.hepinconline.com",
    "wof:name":"Hoeppner Insurance",
    "wof:placetype":"venue"
},
  "geometry": {"coordinates":[-93.328013,44.745145],"type":"Point"}
}