{
  "type": "Feature",
  "properties": {
    "addr:full":"16 Enterprise Dr N Virginia MN 55792",
    "addr:housenumber":"16",
    "addr:postcode":"55792",
    "addr:street":"Enterprise Dr N",
    "iso:country":"US",
    "sg:address":"16 Enterprise Dr N",
    "sg:city":"Virginia",
    "sg:classifiers":[
        {
            "category":"Wholesale",
            "subcategory":"Beer",
            "type":"Manufacturing & Wholesale Goods"
        }
    ],
    "sg:phone":"+1 218 741 2967",
    "sg:postcode":"55792",
    "sg:province":"MN",
    "sg:tags":[
        "distributor"
    ],
    "wof:name":"Norri Rental",
    "wof:placetype":"venue"
},
  "geometry": {"coordinates":[-92.56681399999999,47.51927],"type":"Point"}
}