{
  "type": "Feature",
  "properties": {
    "iso:country":"US",
    "sg:address":"10 1st St SE",
    "sg:city":"Hayfield",
    "sg:classifiers":[
        {
            "category":"Wholesale",
            "subcategory":"Toys & Hobbies",
            "type":"Manufacturing & Wholesale Goods"
        }
    ],
    "sg:phone":"+1 507 477 3900",
    "sg:postcode":"55940",
    "sg:province":"MN",
    "sg:tags":[
        "model",
        "supply"
    ],
    "wof:name":"Dave's Hobby",
    "wof:placetype":"venue"
},
  "geometry": {"coordinates":[-92.847678,43.889683],"type":"Point"}
}