{
  "type": "Feature",
  "properties": {
    "iso:country":"US",
    "sg:address":"9440 Inver Grove Trl",
    "sg:city":"Inver Grove Heights",
    "sg:classifiers":[
        {
            "category":"Real Estate",
            "subcategory":"Real Estate Agent",
            "type":"Services"
        }
    ],
    "sg:phone":"+1 651 455 5419",
    "sg:postcode":"55076",
    "sg:province":"MN",
    "wof:name":"Right Sales Inc",
    "wof:placetype":"venue"
},
  "geometry": {"coordinates":[-93.031071,44.810551],"type":"Point"}
}