{
  "type": "Feature",
  "properties": {
    "iso:country":"US",
    "sg:address":"1566 195th Ave SW",
    "sg:city":"Madison",
    "sg:phone":"+1 952 426 1355",
    "sg:postcode":"56216",
    "sg:province":"MN",
    "sg:tags":[
        "farm",
        "corn"
    ],
    "wof:name":"Kenneth Stamp",
    "wof:placetype":"venue"
},
  "geometry": {"coordinates":[-95.065181,44.935436],"type":"Point"}
}