{
  "type": "Feature",
  "properties": {
    "iso:country":"US",
    "sg:address":"18048 Gap Dr",
    "sg:city":"Spring Grove",
    "sg:classifiers":[
        {
            "category":"Professional",
            "subcategory":"Computer Services",
            "type":"Services"
        }
    ],
    "sg:phone":"+1 507 498 3279",
    "sg:postcode":"55974",
    "sg:province":"MN",
    "sg:tags":[
        "programing",
        "business",
        "custom"
    ],
    "wof:name":"AC Press",
    "wof:placetype":"venue"
},
  "geometry": {"coordinates":[-91.611248,43.59694],"type":"Point"}
}