{
  "type": "Feature",
  "properties": {
    "addr:full":"52896 Finch Rd Garden City MN 56034",
    "addr:housenumber":"52896",
    "addr:postcode":"56034",
    "addr:street":"Finch Rd",
    "iso:country":"US",
    "sg:address":"52896 Finch Rd",
    "sg:city":"Garden City",
    "sg:classifiers":[
        {
            "category":"Real Estate",
            "subcategory":"Real Estate Operator",
            "type":"Services"
        }
    ],
    "sg:phone":"+1 507 546 3053",
    "sg:postcode":"56034",
    "sg:province":"MN",
    "sg:tags":[
        "property",
        "lessor"
    ],
    "wof:name":"Fay Kelley",
    "wof:placetype":"venue"
},
  "geometry": {"coordinates":[-94.13985599999999,44.060609],"type":"Point"}
}