{
  "type": "Feature",
  "properties": {
    "addr:full":"310 Belgrade Ave Mankato MN 56003",
    "addr:housenumber":"310",
    "addr:postcode":"56003",
    "addr:street":"Belgrade Ave",
    "iso:country":"US",
    "sg:address":"310 Belgrade Ave",
    "sg:city":"Mankato",
    "sg:classifiers":[
        {
            "category":"Professional",
            "subcategory":"Business Services",
            "type":"Services"
        }
    ],
    "sg:phone":"+1 507 625 1586",
    "sg:postcode":"56003",
    "sg:province":"MN",
    "sg:tags":[
        "executive"
    ],
    "wof:name":"North Mankato Motor Vehcl Reg",
    "wof:placetype":"venue"
},
  "geometry": {"coordinates":[-94.008792,44.17023],"type":"Point"}
}