{
  "type": "Feature",
  "properties": {
    "addr:full":"28113 Lake Diane Rd Zimmerman MN 55398",
    "addr:housenumber":"28113",
    "addr:postcode":"55398",
    "addr:street":"Lake Diane Rd",
    "iso:country":"US",
    "sg:address":"28113 Lake Diane Rd",
    "sg:city":"Zimmerman",
    "sg:classifiers":[
        {
            "category":"Real Estate",
            "subcategory":"Real Estate Agent",
            "type":"Services"
        }
    ],
    "sg:phone":"+1 763 856 4775",
    "sg:postcode":"55398",
    "sg:province":"MN",
    "wof:name":"History Hardway",
    "wof:placetype":"venue"
},
  "geometry": {"coordinates":[-93.61070599999999,45.482076],"type":"Point"}
}