{
  "type": "Feature",
  "properties": {
    "iso:country":"US",
    "sg:address":"13623 80th Cir N",
    "sg:city":"Maple Grove",
    "sg:classifiers":[
        {
            "category":"Banks & Credit Unions",
            "subcategory":"Bank",
            "type":"Services"
        }
    ],
    "sg:phone":"+1 763 416 2800",
    "sg:postcode":"55369",
    "sg:province":"MN",
    "wof:name":"US Bank",
    "wof:placetype":"venue"
},
  "geometry": {"coordinates":[-93.453322,45.100882],"type":"Point"}
}