{
  "type": "Feature",
  "properties": {
    "addr:full":"314 3rd St NW Bemidji MN 56601",
    "addr:housenumber":"314",
    "addr:postcode":"56601",
    "addr:street":"3Rd St Nw",
    "iso:country":"US",
    "sg:address":"314 3rd St NW",
    "sg:city":"Bemidji",
    "sg:classifiers":[
        {
            "category":"Utilities",
            "subcategory":"Cable",
            "type":"Services"
        }
    ],
    "sg:phone":"+1 218 751 1154",
    "sg:postcode":"56601",
    "sg:province":"MN",
    "sg:tags":[
        "television"
    ],
    "wof:name":"Charter Cmmnctons Holdings LLC",
    "wof:placetype":"venue"
},
  "geometry": {"coordinates":[-94.88409,47.470433],"type":"Point"}
}