{
  "type": "Feature",
  "properties": {
    "iso:country":"US",
    "sg:address":"2498 150th Ave",
    "sg:city":"Lynd",
    "sg:phone":"+1 507 865 4520",
    "sg:postcode":"56157",
    "sg:province":"MN",
    "sg:tags":[
        "beef",
        "farm",
        "corn",
        "soybean",
        "cattle",
        "feedlot"
    ],
    "wof:name":"Paul Hoversten",
    "wof:placetype":"venue"
},
  "geometry": {"coordinates":[-95.99869,44.41082],"type":"Point"}
}