{
  "type": "Feature",
  "properties": {
    "iso:country":"US",
    "sg:address":"3825 Lynn Ave",
    "sg:city":"Minneapolis",
    "sg:classifiers":[
        {
            "category":"Professional",
            "subcategory":"Employment Agencies",
            "type":"Services"
        }
    ],
    "sg:phone":"+1 952 259 2244",
    "sg:postcode":"55416",
    "sg:province":"MN",
    "sg:tags":[
        "employee",
        "opportunity",
        "temporary",
        "telecommunication",
        "for"
    ],
    "wof:name":"Business Connections Group",
    "wof:placetype":"venue"
},
  "geometry": {"coordinates":[-93.336607,44.933774],"type":"Point"}
}