{
  "type": "Feature",
  "properties": {
    "addr:full":"1912 Pine St Hastings MN 55033",
    "addr:housenumber":"1912",
    "addr:postcode":"55033",
    "addr:street":"Pine St",
    "iso:country":"US",
    "sg:address":"1912 Pine St",
    "sg:city":"Hastings",
    "sg:classifiers":[
        {
            "category":"Social Services",
            "subcategory":"Child Care",
            "type":"Services"
        }
    ],
    "sg:phone":"+1 651 437 7759",
    "sg:postcode":"55033",
    "sg:province":"MN",
    "sg:tags":[
        "day",
        "provider"
    ],
    "wof:name":"Laura Ginther",
    "wof:placetype":"venue"
},
  "geometry": {"coordinates":[-92.862757,44.724224],"type":"Point"}
}