{
  "type": "Feature",
  "properties": {
    "addr:full":"200 NW 1st Ave Grand Rapids MN 55744",
    "addr:housenumber":"200",
    "addr:postcode":"55744",
    "addr:street":"Nw 1St Ave",
    "iso:country":"US",
    "sg:address":"200 NW 1st Ave",
    "sg:city":"Grand Rapids",
    "sg:classifiers":[
        {
            "category":"Building & Trades",
            "subcategory":"Construction",
            "type":"Services"
        }
    ],
    "sg:phone":"+1 218 326 8242",
    "sg:postcode":"55744",
    "sg:province":"MN",
    "sg:tags":[
        "general",
        "contractor"
    ],
    "wof:name":"Oscar J Boldt Construction",
    "wof:placetype":"venue"
},
  "geometry": {"coordinates":[-93.52987899999999,47.234909],"type":"Point"}
}