{
  "type": "Feature",
  "properties": {
    "iso:country":"US",
    "sg:address":"511 N High St",
    "sg:city":"Lake City",
    "sg:classifiers":[
        {
            "category":"Professional",
            "type":"Services"
        }
    ],
    "sg:phone":"+1 651 345 9986",
    "sg:postcode":"55041",
    "sg:province":"MN",
    "wof:name":"American Spa Covers",
    "wof:placetype":"venue"
},
  "geometry": {"coordinates":[-92.27312499999999,44.452081],"type":"Point"}
}