{
  "type": "Feature",
  "properties": {
    "iso:country":"US",
    "sg:address":"6315 16th Ave NW",
    "sg:city":"Rochester",
    "sg:classifiers":[
        {
            "category":"Freight",
            "type":"Transportation"
        }
    ],
    "sg:phone":"+1 507 289 4373",
    "sg:postcode":"55901",
    "sg:province":"MN",
    "sg:tags":[
        "cartage",
        "trucking"
    ],
    "wof:name":"Keefe Transfer Inc",
    "wof:placetype":"venue"
},
  "geometry": {"coordinates":[-92.485958,44.089803],"type":"Point"}
}