{
  "type": "Feature",
  "properties": {
    "iso:country":"US",
    "sg:address":"2623 W 2nd St",
    "sg:city":"Duluth",
    "sg:classifiers":[
        {
            "category":"Social Services",
            "type":"Services"
        }
    ],
    "sg:phone":"+1 218 727 1549",
    "sg:postcode":"55806",
    "sg:province":"MN",
    "sg:tags":[
        "organization",
        "welfare"
    ],
    "wof:name":"Boys & Girls Club Of Duluth",
    "wof:placetype":"venue"
},
  "geometry": {"coordinates":[-92.13373199999999,46.76283],"type":"Point"}
}