{
  "type": "Feature",
  "properties": {
    "addr:full":"18 S Erie St Aurora MN 55705",
    "addr:housenumber":"18",
    "addr:postcode":"55705",
    "addr:street":"S Erie St",
    "iso:country":"US",
    "sg:address":"18 S Erie St",
    "sg:city":"Aurora",
    "sg:classifiers":[
        {
            "category":"Personal",
            "subcategory":"Beauty Salon",
            "type":"Services"
        }
    ],
    "sg:phone":"+1 218 229 2959",
    "sg:postcode":"55705",
    "sg:province":"MN",
    "wof:name":"Stylistix Inc",
    "wof:placetype":"venue"
},
  "geometry": {"coordinates":[-92.250488,47.526642],"type":"Point"}
}