{
  "type": "Feature",
  "properties": {
    "addr:full":"6327 Cambridge St St Louis Park MN 55416",
    "addr:housenumber":"6327",
    "addr:postcode":"55416",
    "addr:street":"Cambridge St",
    "iso:country":"US",
    "sg:address":"6327 Cambridge St",
    "sg:city":"St Louis Park",
    "sg:classifiers":[
        {
            "category":"Freight",
            "type":"Transportation"
        }
    ],
    "sg:phone":"+1 952 929 8825",
    "sg:postcode":"55416",
    "sg:province":"MN",
    "sg:tags":[
        "commercial",
        "storage"
    ],
    "sg:website":"www.rentspace.com",
    "wof:name":"Business Center",
    "wof:placetype":"venue"
},
  "geometry": {"coordinates":[-93.358227,44.93335],"type":"Point"}
}