{
  "type": "Feature",
  "properties": {
    "addr:full":"111 Main St W New Prague MN 56071",
    "addr:housenumber":"111",
    "addr:postcode":"56071",
    "addr:street":"Main St W",
    "iso:country":"US",
    "sg:address":"111 Main St W",
    "sg:city":"New Prague",
    "sg:classifiers":[
        {
            "category":"Arts & Performance",
            "subcategory":"Theater",
            "type":"Entertainment"
        }
    ],
    "sg:phone":"+1 952 758 9300",
    "sg:postcode":"56071",
    "sg:province":"MN",
    "sg:tags":[
        "musician"
    ],
    "sg:website":"www.pianobrothers.com",
    "wof:name":"O'Neill Brothers",
    "wof:placetype":"venue"
},
  "geometry": {"coordinates":[-93.577457,44.543655],"type":"Point"}
}