{
  "type": "Feature",
  "properties": {
    "addr:full":"322 Jefferson St Alexandria MN 56308",
    "addr:housenumber":"322",
    "addr:postcode":"56308",
    "addr:street":"Jefferson St",
    "iso:country":"US",
    "sg:address":"322 Jefferson St",
    "sg:city":"Alexandria",
    "sg:classifiers":[
        {
            "category":"Building & Trades",
            "subcategory":"Construction",
            "type":"Services"
        }
    ],
    "sg:phone":"+1 320 763 4882",
    "sg:postcode":"56308",
    "sg:province":"MN",
    "sg:tags":[
        "home",
        "family",
        "contractor"
    ],
    "wof:name":"Phil Haabala Construction",
    "wof:placetype":"venue"
},
  "geometry": {"coordinates":[-95.37311699999999,45.889155],"type":"Point"}
}