{
  "type": "Feature",
  "properties": {
    "addr:full":"1032 W Lake Dr Detroit Lakes MN 56501",
    "addr:housenumber":"1032",
    "addr:postcode":"56501",
    "addr:street":"W Lake Dr",
    "iso:country":"US",
    "sg:address":"1032 W Lake Dr",
    "sg:city":"Detroit Lakes",
    "sg:classifiers":[
        {
            "category":"Building & Trades",
            "subcategory":"Electrical",
            "type":"Services"
        }
    ],
    "sg:phone":"+1 218 844 7777",
    "sg:postcode":"56501",
    "sg:province":"MN",
    "sg:tags":[
        "electric",
        "contractor"
    ],
    "wof:name":"Z Bell Electric",
    "wof:placetype":"venue"
},
  "geometry": {"coordinates":[-95.86317200000001,46.79987],"type":"Point"}
}