{
  "type": "Feature",
  "properties": {
    "iso:country":"US",
    "sg:address":"20455 Manor Rd",
    "sg:city":"Excelsior",
    "sg:classifiers":[
        {
            "category":"Banks & Credit Unions",
            "subcategory":"Investment Brokerage",
            "type":"Services"
        }
    ],
    "sg:phone":"+1 952 831 9231",
    "sg:postcode":"55331",
    "sg:province":"MN",
    "sg:tags":[
        "investing"
    ],
    "wof:name":"J E Peters Financial Services",
    "wof:placetype":"venue"
},
  "geometry": {"coordinates":[-93.53953199999999,44.911716],"type":"Point"}
}