{
  "type": "Feature",
  "properties": {
    "iso:country":"US",
    "sg:address":"229 Main St N",
    "sg:city":"Chatfield",
    "sg:classifiers":[
        {
            "category":"Banks & Credit Unions",
            "subcategory":"Bank",
            "type":"Services"
        }
    ],
    "sg:phone":"+1 507 867 1605",
    "sg:postcode":"55923",
    "sg:province":"MN",
    "sg:website":"www.fmcommunity.com",
    "wof:name":"F & M Community Bank",
    "wof:placetype":"venue"
},
  "geometry": {"coordinates":[-92.192683,43.848977],"type":"Point"}
}