{
  "type": "Feature",
  "properties": {
    "iso:country":"US",
    "sg:address":"1735 10th St SE",
    "sg:city":"Sunburg",
    "sg:classifiers":[
        {
            "category":"Farming",
            "subcategory":"Livestock Farm",
            "type":"Manufacturing & Wholesale Goods"
        }
    ],
    "sg:phone":"+1 320 366 3414",
    "sg:postcode":"56289",
    "sg:province":"MN",
    "sg:tags":[
        "hog",
        "or",
        "feedlot"
    ],
    "wof:name":"Dean Westheim",
    "wof:placetype":"venue"
},
  "geometry": {"coordinates":[-95.266081,45.310844],"type":"Point"}
}