{
  "type": "Feature",
  "properties": {
    "iso:country":"US",
    "sg:address":"2530 NE Madison St",
    "sg:city":"Minneapolis",
    "sg:classifiers":[
        {
            "category":"Retail",
            "subcategory":"Photofinishing",
            "type":"Services"
        }
    ],
    "sg:phone":"+1 612 788 3516",
    "sg:postcode":"55418",
    "sg:province":"MN",
    "sg:tags":[
        "photo",
        "finishing",
        "laboratory"
    ],
    "wof:name":"Great Prints One Hour Photo",
    "wof:placetype":"venue"
},
  "geometry": {"coordinates":[-93.254256,45.014417],"type":"Point"}
}