{
  "type": "Feature",
  "properties": {
    "addr:full":"1264 109th Ave NE Minneapolis MN 55434",
    "addr:housenumber":"1264",
    "addr:postcode":"55434",
    "addr:street":"109Th Ave Ne",
    "iso:country":"US",
    "sg:address":"1264 109th Ave NE",
    "sg:city":"Minneapolis",
    "sg:classifiers":[
        {
            "category":"Shopping",
            "subcategory":"Musical Instruments",
            "type":"Retail Goods"
        }
    ],
    "sg:phone":"+1 612 245 7377",
    "sg:postcode":"55434",
    "sg:province":"MN",
    "sg:tags":[
        "guitar",
        "amplifier"
    ],
    "wof:name":"Kindermusik",
    "wof:placetype":"venue"
},
  "geometry": {"coordinates":[-93.239198,45.16814],"type":"Point"}
}