{
  "type": "Feature",
  "properties": {
    "addr:full":"15120 400th St North Branch MN 55056",
    "addr:housenumber":"15120",
    "addr:postcode":"55056",
    "addr:street":"400Th St",
    "iso:country":"US",
    "sg:address":"15120 400th St",
    "sg:city":"North Branch",
    "sg:classifiers":[
        {
            "category":"Professional",
            "subcategory":"Advertising",
            "type":"Services"
        }
    ],
    "sg:phone":"+1 651 583 2800",
    "sg:postcode":"55056",
    "sg:province":"MN",
    "wof:name":"Dealerssyndicate.Com Inc",
    "wof:placetype":"venue"
},
  "geometry": {"coordinates":[-92.80118899999999,45.527683],"type":"Point"}
}