{
  "type": "Feature",
  "properties": {
    "iso:country":"US",
    "sg:address":"410 E Jackson St",
    "sg:city":"Mankato",
    "sg:classifiers":[
        {
            "category":"Government",
            "subcategory":"Office",
            "type":"Public Place"
        }
    ],
    "sg:phone":"+1 507 387 5643",
    "sg:postcode":"56001",
    "sg:province":"MN",
    "sg:tags":[
        "village"
    ],
    "wof:name":"Pemberton Region 9 Dev Comm",
    "wof:placetype":"venue"
},
  "geometry": {"coordinates":[-94.001446,44.162756],"type":"Point"}
}