{
  "type": "Feature",
  "properties": {
    "addr:full":"8126 Utah Ave S Minneapolis MN 55438",
    "addr:housenumber":"8126",
    "addr:postcode":"55438",
    "addr:street":"Utah Ave S",
    "iso:country":"US",
    "sg:address":"8126 Utah Ave S",
    "sg:city":"Minneapolis",
    "sg:classifiers":[
        {
            "category":"Professional",
            "subcategory":"Computer Services",
            "type":"Services"
        }
    ],
    "sg:phone":"+1 952 941 3624",
    "sg:postcode":"55438",
    "sg:province":"MN",
    "sg:tags":[
        "prepackaged",
        "software"
    ],
    "wof:name":"Diversified Acceptance Corp",
    "wof:placetype":"venue"
},
  "geometry": {"coordinates":[-93.38555599999999,44.854641],"type":"Point"}
}