{
  "type": "Feature",
  "properties": {
    "iso:country":"US",
    "sg:address":"2818 Eagle Valley Dr",
    "sg:city":"Saint Paul",
    "sg:classifiers":[
        {
            "category":"Professional",
            "subcategory":"Management & Consulting",
            "type":"Services"
        }
    ],
    "sg:phone":"+1 612 865 5502",
    "sg:postcode":"55129",
    "sg:province":"MN",
    "sg:tags":[
        "business"
    ],
    "wof:name":"R M Bennerotte & Associates",
    "wof:placetype":"venue"
},
  "geometry": {"coordinates":[-92.90051800000001,44.904193],"type":"Point"}
}