{
  "type": "Feature",
  "properties": {
    "addr:full":"813 Chandler Ave N Glencoe MN 55336",
    "addr:housenumber":"813",
    "addr:postcode":"55336",
    "addr:street":"Chandler Ave N",
    "iso:country":"US",
    "sg:address":"813 Chandler Ave N",
    "sg:city":"Glencoe",
    "sg:classifiers":[
        {
            "category":"Shopping",
            "subcategory":"Clothing, Apparel, & Fashions",
            "type":"Retail Goods"
        }
    ],
    "sg:phone":"+1 320 864 2878",
    "sg:postcode":"55336",
    "sg:province":"MN",
    "wof:name":"Patricias Boutique Inc",
    "wof:placetype":"venue"
},
  "geometry": {"coordinates":[-94.158503,44.767419],"type":"Point"}
}