{
  "type": "Feature",
  "properties": {
    "addr:full":"34064 State Hwy 47 Cambridge MN 55008",
    "addr:housenumber":"34064",
    "addr:postcode":"55008",
    "addr:street":"State Hwy 47",
    "iso:country":"US",
    "sg:address":"34064 State Hwy 47",
    "sg:city":"Cambridge",
    "sg:phone":"+1 763 689 4423",
    "sg:postcode":"55008",
    "sg:province":"MN",
    "sg:tags":[
        "farm",
        "corn",
        "grain",
        "cash",
        "sin"
    ],
    "wof:name":"Boeabher Safety LLC",
    "wof:placetype":"venue"
},
  "geometry": {"coordinates":[-93.389004,45.586855],"type":"Point"}
}