{
  "type": "Feature",
  "properties": {
    "iso:country":"US",
    "sg:address":"5010 Cheshire Ln N",
    "sg:city":"Minneapolis",
    "sg:classifiers":[
        {
            "category":"Wholesale",
            "subcategory":"Medical Equipment & Supplies",
            "type":"Manufacturing & Wholesale Goods"
        },
        {
            "category":"Utilities",
            "subcategory":"Natural Gas",
            "type":"Services"
        }
    ],
    "sg:phone":"+1 877 433 6373",
    "sg:postcode":"55446",
    "sg:province":"MN",
    "sg:tags":[
        "aids-manufacturers",
        "hearing",
        "device",
        "assistive",
        "aid"
    ],
    "sg:website":"http://www.miracle-ear.com",
    "wof:name":"Miracle-Ear",
    "wof:placetype":"venue"
},
  "geometry": {"coordinates":[-93.45761899999999,45.043806],"type":"Point"}
}