{
  "type": "Feature",
  "properties": {
    "iso:country":"US",
    "sg:address":"4905 State Hwy 84",
    "sg:city":"Longville",
    "sg:classifiers":[
        {
            "category":"Organizations",
            "subcategory":"Religious Organization",
            "type":"Services"
        }
    ],
    "sg:phone":"+1 218 363 2799",
    "sg:postcode":"56655",
    "sg:province":"MN",
    "sg:tags":[
        "church"
    ],
    "wof:name":"St Edwards Catholic Chr",
    "wof:placetype":"venue"
},
  "geometry": {"coordinates":[-94.20856999999999,46.982392],"type":"Point"}
}