{
  "type": "Feature",
  "properties": {
    "addr:full":"118 Broadway St W Monticello MN 55362",
    "addr:housenumber":"118",
    "addr:postcode":"55362",
    "addr:street":"Broadway St W",
    "iso:country":"US",
    "sg:address":"118 Broadway St W",
    "sg:city":"Monticello",
    "sg:classifiers":[
        {
            "category":"Insurance",
            "subcategory":"Insurance Agent",
            "type":"Services"
        }
    ],
    "sg:phone":"+1 763 295 3965",
    "sg:postcode":"55362",
    "sg:province":"MN",
    "wof:name":"D W Carlson Agency",
    "wof:placetype":"venue"
},
  "geometry": {"coordinates":[-93.795484,45.306023],"type":"Point"}
}