{
  "type": "Feature",
  "properties": {
    "iso:country":"US",
    "sg:address":"28 2nd St N",
    "sg:city":"Hallock",
    "sg:classifiers":[
        {
            "category":"Shopping",
            "subcategory":"Jewelry",
            "type":"Retail Goods"
        }
    ],
    "sg:phone":"+1 218 843 3681",
    "sg:postcode":"56728",
    "sg:province":"MN",
    "sg:tags":[
        "jeweler"
    ],
    "wof:name":"Gillie Jewelers",
    "wof:placetype":"venue"
},
  "geometry": {"coordinates":[-96.945943,48.777926],"type":"Point"}
}