{
  "type": "Feature",
  "properties": {
    "addr:full":"316 Elton Hills Dr NW Rochester MN 55901",
    "addr:housenumber":"316",
    "addr:postcode":"55901",
    "addr:street":"Elton Hills Dr Nw",
    "iso:country":"US",
    "sg:address":"316 Elton Hills Dr NW",
    "sg:city":"Rochester",
    "sg:classifiers":[
        {
            "category":"Professional",
            "type":"Services"
        }
    ],
    "sg:phone":"+1 507 536 0000",
    "sg:postcode":"55901",
    "sg:province":"MN",
    "sg:tags":[
        "establishment"
    ],
    "wof:name":"Earthlink",
    "wof:placetype":"venue"
},
  "geometry": {"coordinates":[-92.468418,44.044914],"type":"Point"}
}