{
  "type": "Feature",
  "properties": {
    "addr:full":"3927 Old Midway Rd Duluth MN 55810",
    "addr:housenumber":"3927",
    "addr:postcode":"55810",
    "addr:street":"Old Midway Rd",
    "iso:country":"US",
    "sg:address":"3927 Old Midway Rd",
    "sg:city":"Duluth",
    "sg:classifiers":[
        {
            "category":"Building & Trades",
            "subcategory":"Cleaning & Sanitation",
            "type":"Services"
        }
    ],
    "sg:phone":"+1 218 729 8640",
    "sg:postcode":"55810",
    "sg:province":"MN",
    "sg:tags":[
        "maintenance"
    ],
    "wof:name":"Ecklund Maintenance",
    "wof:placetype":"venue"
},
  "geometry": {"coordinates":[-92.280483,46.794954],"type":"Point"}
}