{
  "type": "Feature",
  "properties": {
    "iso:country":"US",
    "sg:address":"6541 Minnewashta Pkwy",
    "sg:city":"Excelsior",
    "sg:classifiers":[
        {
            "category":"Professional",
            "subcategory":"Business Services",
            "type":"Services"
        }
    ],
    "sg:phone":"+1 952 474 2886",
    "sg:postcode":"55331",
    "sg:province":"MN",
    "wof:name":"New Leaf Group Inc",
    "wof:placetype":"venue"
},
  "geometry": {"coordinates":[-93.617615,44.885882],"type":"Point"}
}