{
  "type": "Feature",
  "properties": {
    "iso:country":"US",
    "sg:address":"1237 97th Ave NE",
    "sg:city":"Minneapolis",
    "sg:classifiers":[
        {
            "category":"Manufacturing",
            "subcategory":"Rubber & Plastics",
            "type":"Manufacturing & Wholesale Goods"
        },
        {
            "category":"Home & Garden",
            "subcategory":"Building Materials",
            "type":"Retail Goods"
        }
    ],
    "sg:phone":"+1 763 786 2900",
    "sg:postcode":"55434",
    "sg:province":"MN",
    "sg:tags":[
        "insulation",
        "materials-wholesale",
        "manufacturer"
    ],
    "sg:website":"http://www.centralstatesinsulation.com",
    "wof:name":"Csi Supply",
    "wof:placetype":"venue"
},
  "geometry": {"coordinates":[-93.238866,45.14629],"type":"Point"}
}