{
  "type": "Feature",
  "properties": {
    "iso:country":"US",
    "sg:address":"5 W 1st St",
    "sg:city":"Duluth",
    "sg:classifiers":[
        {
            "category":"Organizations",
            "subcategory":"Non-profit Organization",
            "type":"Services"
        },
        {
            "category":"Organizations",
            "subcategory":"Professional Association",
            "type":"Services"
        }
    ],
    "sg:phone":"+1 218 727 8549",
    "sg:postcode":"55802",
    "sg:province":"MN",
    "sg:tags":[
        "business"
    ],
    "wof:name":"Greater Downtown Council",
    "wof:placetype":"venue"
},
  "geometry": {"coordinates":[-92.100587,46.786763],"type":"Point"}
}