{
  "type": "Feature",
  "properties": {
    "iso:country":"US",
    "sg:address":"1947 Shawnee Rd",
    "sg:city":"Eagan",
    "sg:classifiers":[
        {
            "category":"Wholesale",
            "subcategory":"Hardware",
            "type":"Manufacturing & Wholesale Goods"
        }
    ],
    "sg:phone":"+1 651 452 7600",
    "sg:postcode":"55122",
    "sg:province":"MN",
    "sg:tags":[
        "fastener"
    ],
    "wof:name":"Fastenal Co",
    "wof:placetype":"venue"
},
  "geometry": {"coordinates":[-93.202626,44.826145],"type":"Point"}
}