{
  "type": "Feature",
  "properties": {
    "iso:country":"US",
    "sg:address":"2480 Fairview Ave N",
    "sg:city":"Roseville",
    "sg:classifiers":[
        {
            "category":"Shopping",
            "subcategory":"Bridal",
            "type":"Retail Goods"
        }
    ],
    "sg:phone":"+1 651 633 4366",
    "sg:postcode":"55113",
    "sg:province":"MN",
    "sg:website":"www.dmbridal.net",
    "wof:name":"Dena Marie Bridal & Tux",
    "wof:placetype":"venue"
},
  "geometry": {"coordinates":[-93.177035,45.015489],"type":"Point"}
}