{
  "type": "Feature",
  "properties": {
    "addr:full":"101 14th St NW Austin MN 55912",
    "addr:housenumber":"101",
    "addr:postcode":"55912",
    "addr:street":"14Th St Nw",
    "iso:country":"US",
    "sg:address":"101 14th St NW",
    "sg:city":"Austin",
    "sg:classifiers":[
        {
            "category":"Health Services",
            "subcategory":"Doctor",
            "type":"Services"
        }
    ],
    "sg:phone":"+1 507 433 7001",
    "sg:postcode":"55912",
    "sg:province":"MN",
    "sg:tags":[
        "medical"
    ],
    "wof:name":"Act Program",
    "wof:placetype":"venue"
},
  "geometry": {"coordinates":[-92.992887,43.667497],"type":"Point"}
}