{
  "type": "Feature",
  "properties": {
    "iso:country":"US",
    "sg:address":"30879 850th Ave",
    "sg:city":"Danube",
    "sg:classifiers":[
        {
            "category":"Building & Trades",
            "subcategory":"Construction",
            "type":"Services"
        }
    ],
    "sg:phone":"+1 320 523 2493",
    "sg:postcode":"56230",
    "sg:province":"MN",
    "sg:tags":[
        "house"
    ],
    "wof:name":"Gorres Construction",
    "wof:placetype":"venue"
},
  "geometry": {"coordinates":[-95.0582,44.818084],"type":"Point"}
}