{
  "type": "Feature",
  "properties": {
    "iso:country":"US",
    "sg:address":"1274 E Como Blvd",
    "sg:city":"St Paul",
    "sg:classifiers":[
        {
            "category":"Education",
            "subcategory":"Special Training",
            "type":"Public Place"
        }
    ],
    "sg:phone":"+1 651 487 1794",
    "sg:postcode":"55117",
    "sg:province":"MN",
    "sg:tags":[
        "tutoring"
    ],
    "wof:name":"ETA Tutoring Svc",
    "wof:placetype":"venue"
},
  "geometry": {"coordinates":[-93.142719,44.984531],"type":"Point"}
}