{
  "type": "Feature",
  "properties": {
    "addr:full":"10595 350th Ave Comfrey MN 56019",
    "addr:housenumber":"10595",
    "addr:postcode":"56019",
    "addr:street":"350Th Ave",
    "iso:country":"US",
    "sg:address":"10595 350th Ave",
    "sg:city":"Comfrey",
    "sg:phone":"+1 507 877 4963",
    "sg:postcode":"56019",
    "sg:province":"MN",
    "sg:tags":[
        "farm",
        "grain",
        "cash"
    ],
    "wof:name":"Gerald Thor",
    "wof:placetype":"venue"
},
  "geometry": {"coordinates":[-94.87986600000001,44.117325],"type":"Point"}
}