{
  "type": "Feature",
  "properties": {
    "addr:full":"700 9th Ave S South Saint Paul MN 55075",
    "addr:housenumber":"700",
    "addr:postcode":"55075",
    "addr:street":"9Th Ave S South",
    "iso:country":"US",
    "sg:address":"700 9th Ave S",
    "sg:city":"South Saint Paul",
    "sg:classifiers":[
        {
            "category":"Restaurant",
            "type":"Food & Drink"
        }
    ],
    "sg:phone":"+1 651 450 1678",
    "sg:postcode":"55075",
    "sg:province":"MN",
    "sg:tags":[
        "eating"
    ],
    "wof:name":"Kellys Leona",
    "wof:placetype":"venue"
},
  "geometry": {"coordinates":[-93.044994,44.878087],"type":"Point"}
}