{
  "type": "Feature",
  "properties": {
    "addr:full":"5310 Ryan Rd Duluth MN 55804",
    "addr:housenumber":"5310",
    "addr:postcode":"55804",
    "addr:street":"Ryan Rd",
    "iso:country":"US",
    "sg:address":"5310 Ryan Rd",
    "sg:city":"Duluth",
    "sg:classifiers":[
        {
            "category":"Organizations",
            "subcategory":"Religious Organization",
            "type":"Services"
        }
    ],
    "sg:phone":"+1 218 525 5659",
    "sg:postcode":"55804",
    "sg:province":"MN",
    "wof:name":"French River Lutheran Church",
    "wof:placetype":"venue"
},
  "geometry": {"coordinates":[-91.894972,46.899222],"type":"Point"}
}