{
  "type": "Feature",
  "properties": {
    "iso:country":"US",
    "sg:address":"7675 Mitchell Rd",
    "sg:city":"Eden Prairie",
    "sg:classifiers":[
        {
            "category":"Retail",
            "subcategory":"Auto Repair",
            "type":"Services"
        }
    ],
    "sg:phone":"+1 952 937 2898",
    "sg:postcode":"55344",
    "sg:province":"MN",
    "wof:name":"Mark's Hwy 5 Amoco",
    "wof:placetype":"venue"
},
  "geometry": {"coordinates":[-93.45880099999999,44.864899],"type":"Point"}
}