{
  "type": "Feature",
  "properties": {
    "iso:country":"US",
    "sg:address":"16750 Hwy 18 E",
    "sg:city":"Brainerd",
    "sg:classifiers":[
        {
            "category":"Bars & Pubs",
            "type":"Food & Drink"
        }
    ],
    "sg:phone":"+1 320 692 4660",
    "sg:postcode":"56401",
    "sg:province":"MN",
    "wof:name":"Bird's Nest",
    "wof:placetype":"venue"
},
  "geometry": {"coordinates":[-94.04292,46.352169],"type":"Point"}
}