{
  "type": "Feature",
  "properties": {
    "iso:country":"US",
    "sg:address":"14630 Robert Trl S",
    "sg:city":"Rosemount",
    "sg:phone":"+1 651 423 2358",
    "sg:postcode":"55068",
    "sg:province":"MN",
    "sg:tags":[
        "oil"
    ],
    "wof:name":"V & N Oil Co",
    "wof:placetype":"venue"
},
  "geometry": {"coordinates":[-93.126026,44.737441],"type":"Point"}
}