{
  "type": "Feature",
  "properties": {
    "addr:full":"10861 Bloomington Ferry Rd Minneapolis MN 55438",
    "addr:housenumber":"10861",
    "addr:postcode":"55438",
    "addr:street":"Bloomington Ferry Rd",
    "iso:country":"US",
    "sg:address":"10861 Bloomington Ferry Rd",
    "sg:city":"Minneapolis",
    "sg:classifiers":[
        {
            "category":"Retail",
            "subcategory":"Veterinary Services",
            "type":"Services"
        }
    ],
    "sg:phone":"+1 612 884 8248",
    "sg:postcode":"55438",
    "sg:province":"MN",
    "sg:tags":[
        "clinic",
        "hospital"
    ],
    "wof:name":"Stephen Barghusen",
    "wof:placetype":"venue"
},
  "geometry": {"coordinates":[-93.38417699999999,44.806966],"type":"Point"}
}