{
  "type": "Feature",
  "properties": {
    "iso:country":"US",
    "sg:address":"11870 Cottonwood St NW",
    "sg:city":"Minneapolis",
    "sg:classifiers":[
        {
            "category":"Professional",
            "subcategory":"Management & Consulting",
            "type":"Services"
        }
    ],
    "sg:phone":"+1 763 755 8258",
    "sg:postcode":"55448",
    "sg:province":"MN",
    "sg:tags":[
        "business"
    ],
    "wof:name":"Hegarty Consulting Group",
    "wof:placetype":"venue"
},
  "geometry": {"coordinates":[-93.269047,45.186961],"type":"Point"}
}