{
  "type": "Feature",
  "properties": {
    "iso:country":"US",
    "sg:address":"40535 US Hwy 169",
    "sg:city":"Onamia",
    "sg:classifiers":[
        {
            "category":"Building & Trades",
            "subcategory":"Electrical",
            "type":"Services"
        }
    ],
    "sg:phone":"+1 320 532 3912",
    "sg:postcode":"56359",
    "sg:province":"MN",
    "sg:tags":[
        "electrical",
        "electric",
        "contractor"
    ],
    "wof:name":"Rogers Plumbing Heating & Elec",
    "wof:placetype":"venue"
},
  "geometry": {"coordinates":[-93.696264,46.136245],"type":"Point"}
}