{
  "type": "Feature",
  "properties": {
    "iso:country":"US",
    "sg:address":"1983 Sloan Pl",
    "sg:city":"St Paul",
    "sg:classifiers":[
        {
            "category":"Organizations",
            "subcategory":"Religious Organization",
            "type":"Services"
        }
    ],
    "sg:phone":"+1 651 488 3400",
    "sg:postcode":"55117",
    "sg:province":"MN",
    "wof:name":"New Kingdom Ministries Intl",
    "wof:placetype":"venue"
},
  "geometry": {"coordinates":[-93.087492,45.000988],"type":"Point"}
}