{
  "type": "Feature",
  "properties": {
    "addr:full":"421 14th Ave SE Minneapolis MN 55414",
    "addr:housenumber":"421",
    "addr:postcode":"55414",
    "addr:street":"14Th Ave Se",
    "iso:country":"US",
    "sg:address":"421 14th Ave SE",
    "sg:city":"Minneapolis",
    "sg:classifiers":[
        {
            "category":"Restaurant",
            "type":"Food & Drink"
        }
    ],
    "sg:menulink":"http://www.allmenus.com/mn/minneapolis/244009-kafe-421/menu/",
    "sg:phone":"+1 612 623 4900",
    "sg:postcode":"55414",
    "sg:province":"MN",
    "sg:tags":[
        "american"
    ],
    "wof:name":"Kafe 421",
    "wof:placetype":"venue"
},
  "geometry": {"coordinates":[-93.23560000000001,44.980698],"type":"Point"}
}