{
  "type": "Feature",
  "properties": {
    "addr:full":"722 5th Ave SE Minneapolis MN 55414",
    "addr:housenumber":"722",
    "addr:postcode":"55414",
    "addr:street":"5Th Ave Se",
    "iso:country":"US",
    "sg:address":"722 5th Ave SE",
    "sg:city":"Minneapolis",
    "sg:classifiers":[
        {
            "category":"Professional",
            "subcategory":"Computer Services",
            "type":"Services"
        }
    ],
    "sg:phone":"+1 612 379 0174",
    "sg:postcode":"55414",
    "sg:province":"MN",
    "sg:tags":[
        "consulting",
        "train",
        "related",
        "software"
    ],
    "wof:name":"About Computing",
    "wof:placetype":"venue"
},
  "geometry": {"coordinates":[-93.245223,44.989141],"type":"Point"}
}