{
  "type": "Feature",
  "properties": {
    "iso:country":"US",
    "sg:address":"32510 230th St",
    "sg:city":"Winnebago",
    "sg:phone":"+1 507 893 3773",
    "sg:postcode":"56098",
    "sg:province":"MN",
    "sg:tags":[
        "hog",
        "farm",
        "corn",
        "soybean",
        "or",
        "feedlot"
    ],
    "wof:name":"Henry Schenk",
    "wof:placetype":"venue"
},
  "geometry": {"coordinates":[-94.21684500000001,43.818198],"type":"Point"}
}