{
  "type": "Feature",
  "properties": {
    "iso:country":"US",
    "sg:address":"7900 International Dr Ste 300",
    "sg:city":"Minneapolis",
    "sg:classifiers":[
        {
            "category":"Wholesale",
            "subcategory":"Books, Periodicals, & Newspapers",
            "type":"Manufacturing & Wholesale Goods"
        }
    ],
    "sg:phone":"+1 952 851 4698",
    "sg:postcode":"55425",
    "sg:province":"MN",
    "sg:tags":[
        "magazine"
    ],
    "sg:website":"http://www.cornandsoybeandigest.com",
    "wof:name":"Primedia Business",
    "wof:placetype":"venue"
},
  "geometry": {"coordinates":[-93.226067,44.860458],"type":"Point"}
}