{
  "type": "Feature",
  "properties": {
    "addr:full":"25744 W Comfort Dr Wyoming MN 55092",
    "addr:housenumber":"25744",
    "addr:postcode":"55092",
    "addr:street":"W Comfort Dr",
    "iso:country":"US",
    "sg:address":"25744 W Comfort Dr",
    "sg:city":"Wyoming",
    "sg:classifiers":[
        {
            "category":"Building & Trades",
            "subcategory":"Construction",
            "type":"Services"
        }
    ],
    "sg:phone":"+1 651 462 2400",
    "sg:postcode":"55092",
    "sg:province":"MN",
    "sg:tags":[
        "general",
        "contractor"
    ],
    "wof:name":"David Walburg Company",
    "wof:placetype":"venue"
},
  "geometry": {"coordinates":[-92.956521,45.32256],"type":"Point"}
}