{
  "type": "Feature",
  "properties": {
    "addr:full":"37353 311th Ave Le Sueur MN 56058",
    "addr:housenumber":"37353",
    "addr:postcode":"56058",
    "addr:street":"311Th Ave",
    "iso:country":"US",
    "sg:address":"37353 311th Ave",
    "sg:city":"Le Sueur",
    "sg:classifiers":[
        {
            "category":"Farming",
            "subcategory":"Dairy Farm",
            "type":"Manufacturing & Wholesale Goods"
        }
    ],
    "sg:phone":"+1 507 665 3095",
    "sg:postcode":"56058",
    "sg:province":"MN",
    "sg:tags":[
        "hog",
        "cash",
        "grain",
        "soybean",
        "or",
        "feedlot"
    ],
    "wof:name":"Braun Farm Inc",
    "wof:placetype":"venue"
},
  "geometry": {"coordinates":[-93.889878,44.413157],"type":"Point"}
}