{
  "type": "Feature",
  "properties": {
    "iso:country":"US",
    "sg:address":"4601 Excelsior Blvd",
    "sg:city":"Minneapolis",
    "sg:classifiers":[
        {
            "category":"Banks & Credit Unions",
            "subcategory":"Financial Services",
            "type":"Services"
        }
    ],
    "sg:phone":"+1 952 926 8880",
    "sg:postcode":"55416",
    "sg:province":"MN",
    "sg:tags":[
        "investor"
    ],
    "wof:name":"Capital Corporate Financing",
    "wof:placetype":"venue"
},
  "geometry": {"coordinates":[-93.337431,44.934108],"type":"Point"}
}