{
  "type": "Feature",
  "properties": {
    "addr:full":"5353 Gamble Dr Minneapolis MN 55416",
    "addr:housenumber":"5353",
    "addr:postcode":"55416",
    "addr:street":"Gamble Dr",
    "iso:country":"US",
    "sg:address":"5353 Gamble Dr",
    "sg:city":"Minneapolis",
    "sg:classifiers":[
        {
            "category":"Professional",
            "subcategory":"Lawyer & Legal Services",
            "type":"Services"
        }
    ],
    "sg:phone":"+1 952 374 6164",
    "sg:postcode":"55416",
    "sg:province":"MN",
    "wof:name":"Jensen Law Firm Ltd",
    "wof:placetype":"venue"
},
  "geometry": {"coordinates":[-93.347419,44.965297],"type":"Point"}
}