{
  "type": "Feature",
  "properties": {
    "addr:full":"8221 Blaisdell Ave S Minneapolis MN 55420",
    "addr:housenumber":"8221",
    "addr:postcode":"55420",
    "addr:street":"Blaisdell Ave S",
    "iso:country":"US",
    "sg:address":"8221 Blaisdell Ave S",
    "sg:city":"Minneapolis",
    "sg:classifiers":[
        {
            "category":"Real Estate",
            "subcategory":"Real Estate Agent",
            "type":"Services"
        }
    ],
    "sg:phone":"+1 952 884 2947",
    "sg:postcode":"55420",
    "sg:province":"MN",
    "sg:tags":[
        "inspection"
    ],
    "wof:name":"CEMCI",
    "wof:placetype":"venue"
},
  "geometry": {"coordinates":[-93.279546,44.853888],"type":"Point"}
}