{
  "type": "Feature",
  "properties": {
    "iso:country":"US",
    "sg:address":"4720 W 62nd St",
    "sg:city":"Minneapolis",
    "sg:classifiers":[
        {
            "category":"Professional",
            "subcategory":"Management & Consulting",
            "type":"Services"
        }
    ],
    "sg:phone":"+1 952 929 1411",
    "sg:postcode":"55424",
    "sg:province":"MN",
    "sg:tags":[
        "business"
    ],
    "wof:name":"Nichols Consulting Inc",
    "wof:placetype":"venue"
},
  "geometry": {"coordinates":[-93.346481,44.89094],"type":"Point"}
}