{
  "type": "Feature",
  "properties": {
    "iso:country":"US",
    "sg:address":"3902 10th Ln",
    "sg:city":"Anoka",
    "sg:classifiers":[
        {
            "category":"Arts & Performance",
            "subcategory":"Music",
            "type":"Entertainment"
        }
    ],
    "sg:phone":"+1 763 421 8786",
    "sg:postcode":"55303",
    "sg:province":"MN",
    "sg:tags":[
        "arranger",
        "composer"
    ],
    "wof:name":"Custom Batons",
    "wof:placetype":"venue"
},
  "geometry": {"coordinates":[-93.369157,45.223268],"type":"Point"}
}