{
  "type": "Feature",
  "properties": {
    "addr:full":"214 N Central Ave Truman MN 56088",
    "addr:housenumber":"214",
    "addr:postcode":"56088",
    "addr:street":"N Central Ave",
    "iso:country":"US",
    "sg:address":"214 N Central Ave",
    "sg:city":"Truman",
    "sg:classifiers":[
        {
            "category":"Social Services",
            "subcategory":"Child Care",
            "type":"Services"
        }
    ],
    "sg:phone":"+1 507 776 2683",
    "sg:postcode":"56088",
    "sg:province":"MN",
    "sg:tags":[
        "day",
        "provides"
    ],
    "wof:name":"Amy M Werner",
    "wof:placetype":"venue"
},
  "geometry": {"coordinates":[-94.43558400000001,43.830436],"type":"Point"}
}