{
  "type": "Feature",
  "properties": {
    "addr:full":"1016 Washington Ave SE Minneapolis MN 55414",
    "addr:housenumber":"1016",
    "addr:postcode":"55414",
    "addr:street":"Washington Ave Se",
    "iso:country":"US",
    "sg:address":"1016 Washington Ave SE",
    "sg:city":"Minneapolis",
    "sg:classifiers":[
        {
            "category":"Fast Food",
            "type":"Food & Drink"
        },
        {
            "category":"Food & Beverages",
            "subcategory":"Bakery",
            "type":"Retail Goods"
        }
    ],
    "sg:phone":"+1 612 331 2757",
    "sg:postcode":"55414",
    "sg:province":"MN",
    "sg:tags":[
        "sandwich"
    ],
    "wof:name":"Arby's Restaurants",
    "wof:placetype":"venue"
},
  "geometry": {"coordinates":[-93.22350299999999,44.973499],"type":"Point"}
}