{
  "type": "Feature",
  "properties": {
    "addr:full":"2345 Maryland Ave E Saint Paul MN 55119",
    "addr:housenumber":"2345",
    "addr:postcode":"55119",
    "addr:street":"Maryland Ave E",
    "iso:country":"US",
    "sg:address":"2345 Maryland Ave E",
    "sg:city":"Saint Paul",
    "sg:classifiers":[
        {
            "category":"Professional",
            "subcategory":"Business Services",
            "type":"Services"
        }
    ],
    "sg:phone":"+1 651 773 0731",
    "sg:postcode":"55119",
    "sg:province":"MN",
    "wof:name":"91 Racing Inc",
    "wof:placetype":"venue"
},
  "geometry": {"coordinates":[-93.000615,44.977649],"type":"Point"}
}