{
  "type": "Feature",
  "properties": {
    "iso:country":"US",
    "sg:address":"1185 Town Centre Dr",
    "sg:city":"Eagan",
    "sg:classifiers":[
        {
            "category":"Banks & Credit Unions",
            "subcategory":"Bank",
            "type":"Services"
        }
    ],
    "sg:phone":"+1 952 212 5244",
    "sg:postcode":"55123",
    "sg:province":"MN",
    "sg:tags":[
        "loan"
    ],
    "sg:website":"www.alpinelending.com",
    "wof:name":"Michael Johnson Loan Officer",
    "wof:placetype":"venue"
},
  "geometry": {"coordinates":[-93.15230099999999,44.83117],"type":"Point"}
}