{
  "type": "Feature",
  "properties": {
    "addr:full":"890 Main St S Pine City MN 55063",
    "addr:housenumber":"890",
    "addr:postcode":"55063",
    "addr:street":"Main St S",
    "iso:country":"US",
    "sg:address":"890 Main St S",
    "sg:city":"Pine City",
    "sg:classifiers":[
        {
            "category":"Manufacturing",
            "subcategory":"Electronics",
            "type":"Manufacturing & Wholesale Goods"
        }
    ],
    "sg:phone":"+1 320 629 7100",
    "sg:postcode":"55063",
    "sg:province":"MN",
    "sg:tags":[
        "equipment",
        "electronic",
        "supply"
    ],
    "wof:name":"Trusses Plus Inc",
    "wof:placetype":"venue"
},
  "geometry": {"coordinates":[-92.970333,45.819258],"type":"Point"}
}