{
  "type": "Feature",
  "properties": {
    "addr:full":"8480 State Hwy 65 Minneapolis MN 55432",
    "addr:housenumber":"8480",
    "addr:postcode":"55432",
    "addr:street":"State Hwy 65",
    "iso:country":"US",
    "sg:address":"8480 State Hwy 65",
    "sg:city":"Minneapolis",
    "sg:classifiers":[
        {
            "category":"Manufacturing",
            "subcategory":"Printing",
            "type":"Manufacturing & Wholesale Goods"
        }
    ],
    "sg:phone":"+1 763 780 0792",
    "sg:postcode":"55432",
    "sg:province":"MN",
    "sg:tags":[
        "lithographic",
        "commercial",
        "photocopying"
    ],
    "wof:name":"Insty-Prints",
    "wof:placetype":"venue"
},
  "geometry": {"coordinates":[-93.23648799999999,45.12235],"type":"Point"}
}