{
  "type": "Feature",
  "properties": {
    "addr:full":"6200 Camden Ave N Minneapolis MN 55430",
    "addr:housenumber":"6200",
    "addr:postcode":"55430",
    "addr:street":"Camden Ave N",
    "iso:country":"US",
    "sg:address":"6200 Camden Ave N",
    "sg:city":"Minneapolis",
    "sg:classifiers":[
        {
            "category":"Professional",
            "subcategory":"Lawyer & Legal Services",
            "type":"Services"
        }
    ],
    "sg:phone":"+1 763 208 5724",
    "sg:postcode":"55430",
    "sg:province":"MN",
    "wof:name":"Fitzgerald & Fett Attys At Law",
    "wof:placetype":"venue"
},
  "geometry": {"coordinates":[-93.28875600000001,45.068031],"type":"Point"}
}