{
  "type": "Feature",
  "properties": {
    "addr:full":"51 8th St N Sauk Rapids MN 56379",
    "addr:housenumber":"51",
    "addr:postcode":"56379",
    "addr:street":"8Th St N Sauk",
    "iso:country":"US",
    "sg:address":"51 8th St N",
    "sg:city":"Sauk Rapids",
    "sg:classifiers":[
        {
            "category":"Manufacturing",
            "subcategory":"Tools & Machinery",
            "type":"Manufacturing & Wholesale Goods"
        }
    ],
    "sg:phone":"+1 320 253 0919",
    "sg:postcode":"56379",
    "sg:province":"MN",
    "sg:tags":[
        "physician",
        "surgeon"
    ],
    "sg:website":"www.auralens.com",
    "wof:name":"Aura Lens Products Inc",
    "wof:placetype":"venue"
},
  "geometry": {"coordinates":[-94.175099,45.594651],"type":"Point"}
}