{
  "type": "Feature",
  "properties": {
    "addr:full":"11303 25th St NE Foley MN 56329",
    "addr:housenumber":"11303",
    "addr:postcode":"56329",
    "addr:street":"25Th St Ne",
    "iso:country":"US",
    "sg:address":"11303 25th St NE",
    "sg:city":"Foley",
    "sg:classifiers":[
        {
            "category":"Farming",
            "subcategory":"Farm",
            "type":"Manufacturing & Wholesale Goods"
        }
    ],
    "sg:phone":"+1 320 968 7798",
    "sg:postcode":"56329",
    "sg:province":"MN",
    "sg:tags":[
        "crop",
        "general"
    ],
    "wof:name":"Dumonceaux Farms Inc",
    "wof:placetype":"venue"
},
  "geometry": {"coordinates":[-93.924328,45.604798],"type":"Point"}
}