{
  "type": "Feature",
  "properties": {
    "iso:country":"US",
    "sg:address":"10753 Fillmore St NE",
    "sg:city":"Minneapolis",
    "sg:classifiers":[
        {
            "category":"Retail",
            "subcategory":"Laundry & Dry Cleaning",
            "type":"Services"
        }
    ],
    "sg:phone":"+1 763 757 8361",
    "sg:postcode":"55434",
    "sg:province":"MN",
    "wof:name":"Carpet Express",
    "wof:placetype":"venue"
},
  "geometry": {"coordinates":[-93.242744,45.167079],"type":"Point"}
}