{
  "type": "Feature",
  "properties": {
    "addr:full":"2651 US Hwy 10 Saint Paul MN 55112",
    "addr:housenumber":"2651",
    "addr:postcode":"55112",
    "addr:street":"Us Hwy 10",
    "iso:country":"US",
    "sg:address":"2651 US Hwy 10",
    "sg:city":"Saint Paul",
    "sg:classifiers":[
        {
            "category":"Real Estate",
            "subcategory":"Real Estate Operator",
            "type":"Services"
        }
    ],
    "sg:phone":"+1 763 717 1285",
    "sg:postcode":"55112",
    "sg:province":"MN",
    "sg:tags":[
        "property",
        "management"
    ],
    "wof:name":"Silver Lake Commons Apartments",
    "wof:placetype":"venue"
},
  "geometry": {"coordinates":[-93.215007,45.108693],"type":"Point"}
}