{
  "type": "Feature",
  "properties": {
    "iso:country":"US",
    "sg:address":"524 19th St NW",
    "sg:city":"Bemidji",
    "sg:classifiers":[
        {
            "category":"Building & Trades",
            "subcategory":"Construction",
            "type":"Services"
        }
    ],
    "sg:phone":"+1 218 556 7814",
    "sg:postcode":"56601",
    "sg:province":"MN",
    "sg:tags":[
        "downspouts",
        "gutter"
    ],
    "wof:name":"3 D Seamless Gutters",
    "wof:placetype":"venue"
},
  "geometry": {"coordinates":[-94.88807,47.487087],"type":"Point"}
}