{
  "type": "Feature",
  "properties": {
    "addr:full":"411 1st Ave SW Rochester MN 55902",
    "addr:housenumber":"411",
    "addr:postcode":"55902",
    "addr:street":"1St Ave Sw",
    "iso:country":"US",
    "sg:address":"411 1st Ave SW",
    "sg:city":"Rochester",
    "sg:classifiers":[
        {
            "category":"Personal",
            "subcategory":"Beauty Salon",
            "type":"Services"
        }
    ],
    "sg:phone":"+1 507 285 0151",
    "sg:postcode":"55902",
    "sg:province":"MN",
    "sg:tags":[
        "shop"
    ],
    "wof:name":"Beauty Mirror",
    "wof:placetype":"venue"
},
  "geometry": {"coordinates":[-92.46457599999999,44.018273],"type":"Point"}
}