{
  "type": "Feature",
  "properties": {
    "iso:country":"US",
    "sg:address":"5789 139th St W",
    "sg:city":"Saint Paul",
    "sg:classifiers":[
        {
            "category":"Building & Trades",
            "subcategory":"Construction",
            "type":"Services"
        }
    ],
    "sg:phone":"+1 952 432 1223",
    "sg:postcode":"55124",
    "sg:province":"MN",
    "sg:tags":[
        "contractor"
    ],
    "wof:name":"All Pro Roofing",
    "wof:placetype":"venue"
},
  "geometry": {"coordinates":[-93.18341100000001,44.749363],"type":"Point"}
}