{
  "type": "Feature",
  "properties": {
    "addr:full":"25 E 26th St Minneapolis MN 55404",
    "addr:housenumber":"25",
    "addr:postcode":"55404",
    "addr:street":"E 26Th St",
    "iso:country":"US",
    "sg:address":"25 E 26th St",
    "sg:city":"Minneapolis",
    "sg:classifiers":[
        {
            "category":"Personal",
            "type":"Services"
        },
        {
            "category":"Shopping",
            "subcategory":"Thrift Store",
            "type":"Retail Goods"
        },
        {
            "category":"Shopping",
            "subcategory":"Used Merchandise",
            "type":"Retail Goods"
        }
    ],
    "sg:phone":"+1 612 872 8552",
    "sg:postcode":"55404",
    "sg:province":"MN",
    "sg:tags":[
        "vintage",
        "sewing",
        "consignment",
        "alteration"
    ],
    "sg:website":"www.blacklistvintage.com",
    "wof:name":"Blacklist Vintage",
    "wof:placetype":"venue"
},
  "geometry": {"coordinates":[-93.27755999999999,44.955489],"type":"Point"}
}