{
  "type": "Feature",
  "properties": {
    "addr:full":"917 Grand Ave Saint Paul MN 55105",
    "addr:housenumber":"917",
    "addr:postcode":"55105",
    "addr:street":"Grand Ave",
    "iso:country":"US",
    "sg:address":"917 Grand Ave",
    "sg:city":"Saint Paul",
    "sg:classifiers":[
        {
            "category":"Health Services",
            "subcategory":"Doctor",
            "type":"Services"
        }
    ],
    "sg:phone":"+1 651 221 1902",
    "sg:postcode":"55105",
    "sg:province":"MN",
    "wof:name":"Pdhc Ltd",
    "wof:placetype":"venue"
},
  "geometry": {"coordinates":[-93.137225,44.940014],"type":"Point"}
}