{
  "type": "Feature",
  "properties": {
    "addr:full":"212 Ridge Rd Albert Lea MN 56007",
    "addr:housenumber":"212",
    "addr:postcode":"56007",
    "addr:street":"Ridge Rd",
    "iso:country":"US",
    "sg:address":"212 Ridge Rd",
    "sg:city":"Albert Lea",
    "sg:classifiers":[
        {
            "category":"Professional",
            "subcategory":"Business Services",
            "type":"Services"
        }
    ],
    "sg:phone":"+1 507 377 8147",
    "sg:postcode":"56007",
    "sg:province":"MN",
    "wof:name":"Volunteers For Dorman",
    "wof:placetype":"venue"
},
  "geometry": {"coordinates":[-93.377708,43.662838],"type":"Point"}
}