{
  "type": "Feature",
  "properties": {
    "addr:full":"4971 50th Ave Princeton MN 55371",
    "addr:housenumber":"4971",
    "addr:postcode":"55371",
    "addr:street":"50Th Ave",
    "iso:country":"US",
    "sg:address":"4971 50th Ave",
    "sg:city":"Princeton",
    "sg:classifiers":[
        {
            "category":"Retail",
            "subcategory":"Repair Shop",
            "type":"Services"
        }
    ],
    "sg:phone":"+1 612 390 5531",
    "sg:postcode":"55371",
    "sg:province":"MN",
    "sg:tags":[
        "video"
    ],
    "wof:name":"Vcrs Plus",
    "wof:placetype":"venue"
},
  "geometry": {"coordinates":[-93.512213,45.615851],"type":"Point"}
}