{
  "type": "Feature",
  "properties": {
    "addr:full":"81638 200th St Hayward MN 56043",
    "addr:housenumber":"81638",
    "addr:postcode":"56043",
    "addr:street":"200Th St",
    "iso:country":"US",
    "sg:address":"81638 200th St",
    "sg:city":"Hayward",
    "sg:classifiers":[
        {
            "category":"Personal",
            "subcategory":"Beauty Salon",
            "type":"Services"
        }
    ],
    "sg:phone":"+1 507 373 7244",
    "sg:postcode":"56043",
    "sg:province":"MN",
    "wof:name":"Nancy's Hairitage",
    "wof:placetype":"venue"
},
  "geometry": {"coordinates":[-93.24453200000001,43.64381],"type":"Point"}
}