{
  "type": "Feature",
  "properties": {
    "iso:country":"US",
    "sg:address":"2728 Summer St NE",
    "sg:city":"Minneapolis",
    "sg:classifiers":[
        {
            "category":"Manufacturing",
            "subcategory":"Food",
            "type":"Manufacturing & Wholesale Goods"
        }
    ],
    "sg:phone":"+1 612 436 0800",
    "sg:postcode":"55413",
    "sg:province":"MN",
    "sg:tags":[
        "canned",
        "fruit",
        "specialty"
    ],
    "wof:name":"Sudarium Brands Corp",
    "wof:placetype":"venue"
},
  "geometry": {"coordinates":[-93.221979,44.996999],"type":"Point"}
}