{
  "type": "Feature",
  "properties": {
    "addr:full":"1367 Co Rd 5 Longville MN 56655",
    "addr:housenumber":"1367",
    "addr:postcode":"56655",
    "addr:street":"Co Rd 5 Longville",
    "iso:country":"US",
    "sg:address":"1367 Co Rd 5",
    "sg:city":"Longville",
    "sg:classifiers":[
        {
            "category":"Professional",
            "type":"Services"
        }
    ],
    "sg:phone":"+1 218 363 2771",
    "sg:postcode":"56655",
    "sg:province":"MN",
    "sg:tags":[
        "establishment"
    ],
    "wof:name":"Wodrich & Wodrich",
    "wof:placetype":"venue"
},
  "geometry": {"coordinates":[-94.21731800000001,46.989203],"type":"Point"}
}