{
  "type": "Feature",
  "properties": {
    "addr:full":"15 7th Ave S Waite Park MN 56387",
    "addr:housenumber":"15",
    "addr:postcode":"56387",
    "addr:street":"7Th Ave S Waite Park",
    "iso:country":"US",
    "sg:address":"15 7th Ave S",
    "sg:city":"Waite Park",
    "sg:classifiers":[
        {
            "category":"Manufacturing",
            "subcategory":"Signs",
            "type":"Manufacturing & Wholesale Goods"
        }
    ],
    "sg:phone":"+1 320 257 5555",
    "sg:postcode":"56387",
    "sg:province":"MN",
    "sg:website":"www.blacksigns.com",
    "wof:name":"BLACKSIGNS.COM",
    "wof:placetype":"venue"
},
  "geometry": {"coordinates":[-94.225613,45.550834],"type":"Point"}
}