{
  "type": "Feature",
  "properties": {
    "addr:full":"1109 Devito St Marshall MN 56258",
    "addr:housenumber":"1109",
    "addr:postcode":"56258",
    "addr:street":"Devito St",
    "iso:country":"US",
    "sg:address":"1109 Devito St",
    "sg:city":"Marshall",
    "sg:phone":"+1 507 532 5676",
    "sg:postcode":"56258",
    "sg:province":"MN",
    "sg:tags":[
        "farm",
        "corn",
        "soybean"
    ],
    "wof:name":"Robert Stassen",
    "wof:placetype":"venue"
},
  "geometry": {"coordinates":[-95.809263,44.432711],"type":"Point"}
}