{
  "type": "Feature",
  "properties": {
    "iso:country":"US",
    "sg:address":"19318 Perkins Valley Dr",
    "sg:city":"Houston",
    "sg:classifiers":[
        {
            "category":"Farming",
            "subcategory":"Livestock Farm",
            "type":"Manufacturing & Wholesale Goods"
        }
    ],
    "sg:phone":"+1 507 896 2285",
    "sg:postcode":"55943",
    "sg:province":"MN",
    "sg:tags":[
        "crop",
        "general"
    ],
    "wof:name":"Dennis Kinstler",
    "wof:placetype":"venue"
},
  "geometry": {"coordinates":[-91.64409499999999,43.783437],"type":"Point"}
}