{
  "type": "Feature",
  "properties": {
    "iso:country":"US",
    "sg:address":"1508 4th St NE",
    "sg:city":"Waseca",
    "sg:classifiers":[
        {
            "category":"Local Transit",
            "type":"Transportation"
        }
    ],
    "sg:phone":"+1 507 835 7704",
    "sg:postcode":"56093",
    "sg:province":"MN",
    "sg:tags":[
        "passenger",
        "ambulance"
    ],
    "wof:name":"North Ambulance Waseca",
    "wof:placetype":"venue"
},
  "geometry": {"coordinates":[-93.502926,44.09348],"type":"Point"}
}