{
  "type": "Feature",
  "properties": {
    "addr:full":"8448 Pillsbury Ave S Minneapolis MN 55420",
    "addr:housenumber":"8448",
    "addr:postcode":"55420",
    "addr:street":"Pillsbury Ave S",
    "iso:country":"US",
    "sg:address":"8448 Pillsbury Ave S",
    "sg:city":"Minneapolis",
    "sg:classifiers":[
        {
            "category":"Retail",
            "subcategory":"Auto Rental",
            "type":"Services"
        }
    ],
    "sg:phone":"+1 952 474 8866",
    "sg:postcode":"55420",
    "sg:province":"MN",
    "sg:tags":[
        "limousine"
    ],
    "wof:name":"Designer Transportation",
    "wof:placetype":"venue"
},
  "geometry": {"coordinates":[-93.282185,44.850648],"type":"Point"}
}