{
  "type": "Feature",
  "properties": {
    "addr:full":"20191 318th Ave Paynesville MN 56362",
    "addr:housenumber":"20191",
    "addr:postcode":"56362",
    "addr:street":"318Th Ave",
    "iso:country":"US",
    "sg:address":"20191 318th Ave",
    "sg:city":"Paynesville",
    "sg:classifiers":[
        {
            "category":"Farming",
            "subcategory":"Dairy Farm",
            "type":"Manufacturing & Wholesale Goods"
        }
    ],
    "sg:phone":"+1 320 243 4462",
    "sg:postcode":"56362",
    "sg:province":"MN",
    "wof:name":"Hemmesch Math",
    "wof:placetype":"venue"
},
  "geometry": {"coordinates":[-94.773606,45.424527],"type":"Point"}
}