{
  "type": "Feature",
  "properties": {
    "iso:country":"US",
    "sg:address":"815 38th Ave",
    "sg:city":"Winona",
    "sg:classifiers":[
        {
            "category":"Building & Trades",
            "subcategory":"Construction",
            "type":"Services"
        }
    ],
    "sg:phone":"+1 507 452 5264",
    "sg:postcode":"55987",
    "sg:province":"MN",
    "sg:tags":[
        "work",
        "drywall",
        "sheetrock"
    ],
    "wof:name":"G & D Drywall Inc",
    "wof:placetype":"venue"
},
  "geometry": {"coordinates":[-91.695161,44.059204],"type":"Point"}
}