{
  "type": "Feature",
  "properties": {
    "addr:full":"63 Otis Ave Saint Paul MN 55104",
    "addr:housenumber":"63",
    "addr:postcode":"55104",
    "addr:street":"Otis Ave",
    "iso:country":"US",
    "sg:address":"63 Otis Ave",
    "sg:city":"Saint Paul",
    "sg:classifiers":[
        {
            "category":"Health Services",
            "subcategory":"Doctor",
            "type":"Services"
        }
    ],
    "sg:phone":"+1 651 649 0227",
    "sg:postcode":"55104",
    "sg:province":"MN",
    "sg:tags":[
        "physician"
    ],
    "wof:name":"Karen Ringsred MD",
    "wof:placetype":"venue"
},
  "geometry": {"coordinates":[-93.193977,44.943767],"type":"Point"}
}