{
  "type": "Feature",
  "properties": {
    "iso:country":"US",
    "sg:address":"214 5th St NW",
    "sg:city":"Bemidji",
    "sg:classifiers":[
        {
            "category":"Professional",
            "subcategory":"Business Services",
            "type":"Services"
        },
        {
            "category":"Banks & Credit Unions",
            "subcategory":"Bank",
            "type":"Services"
        },
        {
            "category":"Banks & Credit Unions",
            "subcategory":"Financial Services",
            "type":"Services"
        }
    ],
    "sg:phone":"+1 218 751 5120",
    "sg:postcode":"56601",
    "sg:province":"MN",
    "sg:tags":[
        "holding"
    ],
    "wof:name":"First Federal Bank",
    "wof:placetype":"venue"
},
  "geometry": {"coordinates":[-94.88140300000001,47.472639],"type":"Point"}
}