{
  "type": "Feature",
  "properties": {
    "addr:full":"681 17th Ave NE Minneapolis MN 55413",
    "addr:housenumber":"681",
    "addr:postcode":"55413",
    "addr:street":"17Th Ave Ne",
    "iso:country":"US",
    "sg:address":"681 17th Ave NE",
    "sg:city":"Minneapolis",
    "sg:classifiers":[
        {
            "category":"Manufacturing",
            "subcategory":"Glass & Minerals",
            "type":"Manufacturing & Wholesale Goods"
        },
        {
            "category":"Utilities",
            "type":"Services"
        }
    ],
    "sg:phone":"+1 612 788 9755",
    "sg:postcode":"55413",
    "sg:province":"MN",
    "sg:tags":[
        "glassware-repair",
        "glass-wholesale",
        "shape",
        "china",
        "circle",
        "special",
        "manufacturer"
    ],
    "wof:name":"Too Cool Glass Inc",
    "wof:placetype":"venue"
},
  "geometry": {"coordinates":[-93.25372299999999,45.005131],"type":"Point"}
}