{
  "type": "Feature",
  "properties": {
    "addr:full":"12371 Olive St NW Minneapolis MN 55448",
    "addr:housenumber":"12371",
    "addr:postcode":"55448",
    "addr:street":"Olive St Nw",
    "iso:country":"US",
    "sg:address":"12371 Olive St NW",
    "sg:city":"Minneapolis",
    "sg:classifiers":[
        {
            "category":"Building & Trades",
            "subcategory":"Construction",
            "type":"Services"
        }
    ],
    "sg:phone":"+1 763 757 6319",
    "sg:postcode":"55448",
    "sg:province":"MN",
    "sg:tags":[
        "hanging",
        "contractor"
    ],
    "wof:name":"Dave Smiddle Painting",
    "wof:placetype":"venue"
},
  "geometry": {"coordinates":[-93.28649900000001,45.194267],"type":"Point"}
}