{
  "type": "Feature",
  "properties": {
    "iso:country":"US",
    "sg:address":"1415 1st St S",
    "sg:city":"Willmar",
    "sg:classifiers":[
        {
            "category":"Health Services",
            "subcategory":"Clinic",
            "type":"Services"
        }
    ],
    "sg:phone":"+1 320 235 5684",
    "sg:postcode":"56201",
    "sg:province":"MN",
    "wof:name":"Spectrum Community Health",
    "wof:placetype":"venue"
},
  "geometry": {"coordinates":[-95.04263400000001,45.10926],"type":"Point"}
}