{
  "type": "Feature",
  "properties": {
    "addr:full":"8620 Zenith Rd Minneapolis MN 55431",
    "addr:housenumber":"8620",
    "addr:postcode":"55431",
    "addr:street":"Zenith Rd",
    "iso:country":"US",
    "sg:address":"8620 Zenith Rd",
    "sg:city":"Minneapolis",
    "sg:classifiers":[
        {
            "category":"Structure",
            "subcategory":"Office Building",
            "type":"Public Place"
        }
    ],
    "sg:phone":"+1 952 835 6024",
    "sg:postcode":"55431",
    "sg:province":"MN",
    "sg:tags":[
        "park"
    ],
    "wof:name":"D'andrea Properties",
    "wof:placetype":"venue"
},
  "geometry": {"coordinates":[-93.320463,44.84768],"type":"Point"}
}