{
  "type": "Feature",
  "properties": {
    "iso:country":"US",
    "sg:address":"1215 Roselawn Ave W",
    "sg:city":"Roseville",
    "sg:classifiers":[
        {
            "category":"Organizations",
            "subcategory":"Religious Organization",
            "type":"Services"
        }
    ],
    "sg:phone":"+1 651 487 7752",
    "sg:postcode":"55113",
    "sg:province":"MN",
    "sg:tags":[
        "church"
    ],
    "sg:website":"www.rosevillelutheran.org",
    "wof:name":"Roseville Lutheran Church",
    "wof:placetype":"venue"
},
  "geometry": {"coordinates":[-93.15275,44.999211],"type":"Point"}
}