{
  "type": "Feature",
  "properties": {
    "addr:full":"461 Rice Creek Blvd NE Minneapolis MN 55432",
    "addr:housenumber":"461",
    "addr:postcode":"55432",
    "addr:street":"Rice Creek Blvd Ne",
    "iso:country":"US",
    "sg:address":"461 Rice Creek Blvd NE",
    "sg:city":"Minneapolis",
    "sg:classifiers":[
        {
            "category":"Banks & Credit Unions",
            "subcategory":"Investment Brokerage",
            "type":"Services"
        },
        {
            "category":"Banks & Credit Unions",
            "subcategory":"Financial Services",
            "type":"Services"
        }
    ],
    "sg:phone":"+1 763 571 5001",
    "sg:postcode":"55432",
    "sg:province":"MN",
    "sg:tags":[
        "advisory",
        "planner"
    ],
    "wof:name":"Osgood Financial Inc",
    "wof:placetype":"venue"
},
  "geometry": {"coordinates":[-93.261461,45.091071],"type":"Point"}
}