{
  "type": "Feature",
  "properties": {
    "addr:full":"13612 Co Rd 103 Crosslake MN 56442",
    "addr:housenumber":"13612;103",
    "addr:postcode":"56442",
    "addr:street":"Co Rd",
    "iso:country":"US",
    "sg:address":"13612 Co Rd 103",
    "sg:city":"Crosslake",
    "sg:classifiers":[
        {
            "category":"Building & Trades",
            "subcategory":"Landscaping Services",
            "type":"Services"
        }
    ],
    "sg:phone":"+1 218 692 2156",
    "sg:postcode":"56442",
    "sg:province":"MN",
    "sg:tags":[
        "landscape",
        "contractor"
    ],
    "wof:name":"Perkins Excavating",
    "wof:placetype":"venue"
},
  "geometry": {"coordinates":[-94.116043,46.645961],"type":"Point"}
}