{
  "type": "Feature",
  "properties": {
    "iso:country":"US",
    "sg:address":"1903 S Broadway",
    "sg:city":"Rochester",
    "sg:classifiers":[
        {
            "category":"Insurance",
            "subcategory":"Hazard Insurance",
            "type":"Services"
        }
    ],
    "sg:phone":"+1 507 282 3273",
    "sg:postcode":"55904",
    "sg:province":"MN",
    "sg:tags":[
        "profit",
        "sharing",
        "pension",
        "plan"
    ],
    "wof:name":"Lincoln Financial Advisors",
    "wof:placetype":"venue"
},
  "geometry": {"coordinates":[-92.462788,43.992714],"type":"Point"}
}