{
  "type": "Feature",
  "properties": {
    "addr:full":"810 1st St N Hopkins MN 55343",
    "addr:housenumber":"810",
    "addr:postcode":"55343",
    "addr:street":"1St St N",
    "iso:country":"US",
    "sg:address":"810 1st St N",
    "sg:city":"Hopkins",
    "sg:classifiers":[
        {
            "category":"Professional",
            "subcategory":"Lawyer & Legal Services",
            "type":"Services"
        }
    ],
    "sg:phone":"+1 952 908 0110",
    "sg:postcode":"55343",
    "sg:province":"MN",
    "sg:tags":[
        "attorney"
    ],
    "wof:name":"Sween Salazar LTD",
    "wof:placetype":"venue"
},
  "geometry": {"coordinates":[-93.41103,44.926054],"type":"Point"}
}