{
  "type": "Feature",
  "properties": {
    "addr:full":"7850 12th Ave S Minneapolis MN 55425",
    "addr:housenumber":"7850",
    "addr:postcode":"55425",
    "addr:street":"12Th Ave S",
    "iso:country":"US",
    "sg:address":"7850 12th Ave S",
    "sg:city":"Minneapolis",
    "sg:classifiers":[
        {
            "category":"Utilities",
            "subcategory":"Electric",
            "type":"Services"
        }
    ],
    "sg:phone":"+1 952 854 8624",
    "sg:postcode":"55425",
    "sg:province":"MN",
    "sg:tags":[
        "equipment",
        "supplies-repair",
        "electronic",
        "equipment-repair"
    ],
    "sg:website":"http://www.techcenter.com",
    "wof:name":"Tech Center",
    "wof:placetype":"venue"
},
  "geometry": {"coordinates":[-93.25799600000001,44.860838],"type":"Point"}
}