{
  "type": "Feature",
  "properties": {
    "iso:country":"US",
    "sg:address":"3732 3rd Pl NW",
    "sg:city":"Rochester",
    "sg:classifiers":[
        {
            "category":"Social Services",
            "subcategory":"Child Care",
            "type":"Services"
        }
    ],
    "sg:phone":"+1 507 281 1555",
    "sg:postcode":"55901",
    "sg:province":"MN",
    "sg:tags":[
        "daycare"
    ],
    "wof:name":"Sally K Caron",
    "wof:placetype":"venue"
},
  "geometry": {"coordinates":[-92.521861,44.027503],"type":"Point"}
}