{
  "type": "Feature",
  "properties": {
    "addr:full":"5685 Fawn Ln Saint Paul MN 55126",
    "addr:housenumber":"5685",
    "addr:postcode":"55126",
    "addr:street":"Fawn Ln",
    "iso:country":"US",
    "sg:address":"5685 Fawn Ln",
    "sg:city":"Saint Paul",
    "sg:classifiers":[
        {
            "category":"Professional",
            "subcategory":"Computer Services",
            "type":"Services"
        }
    ],
    "sg:phone":"+1 651 486 0872",
    "sg:postcode":"55126",
    "sg:province":"MN",
    "sg:tags":[
        "related"
    ],
    "wof:name":"Alex Elder",
    "wof:placetype":"venue"
},
  "geometry": {"coordinates":[-93.11273199999999,45.112897],"type":"Point"}
}