{
  "type": "Feature",
  "properties": {
    "iso:country":"US",
    "sg:address":"10212 Bridgewater Pkwy",
    "sg:city":"Saint Paul",
    "sg:classifiers":[
        {
            "category":"Professional",
            "type":"Services"
        }
    ],
    "sg:phone":"+1 651 734 9705",
    "sg:postcode":"55129",
    "sg:province":"MN",
    "wof:name":"Amy Clausen",
    "wof:placetype":"venue"
},
  "geometry": {"coordinates":[-92.898967,44.921231],"type":"Point"}
}