{
  "type": "Feature",
  "properties": {
    "iso:country":"US",
    "sg:address":"602 3rd St",
    "sg:city":"Prinsburg",
    "sg:classifiers":[
        {
            "category":"Building & Trades",
            "subcategory":"Construction",
            "type":"Services"
        },
        {
            "category":"Building & Trades",
            "subcategory":"Electrical",
            "type":"Services"
        }
    ],
    "sg:phone":"+1 320 978 8500",
    "sg:postcode":"56281",
    "sg:province":"MN",
    "sg:tags":[
        "industrial",
        "electrician",
        "electric",
        "system",
        "contractor",
        "air conditioning",
        "contractors-commercial"
    ],
    "wof:name":"Lloyd's Electric Service",
    "wof:placetype":"venue"
},
  "geometry": {"coordinates":[-95.19188699999999,44.940593],"type":"Point"}
}