{
  "type": "Feature",
  "properties": {
    "iso:country":"US",
    "sg:address":"8 Kistler Ct",
    "sg:city":"La Crescent",
    "sg:classifiers":[
        {
            "category":"Building & Trades",
            "subcategory":"Construction",
            "type":"Services"
        }
    ],
    "sg:phone":"+1 507 895 4070",
    "sg:postcode":"55947",
    "sg:province":"MN",
    "sg:tags":[
        "house"
    ],
    "wof:name":"Castle Rock Builders Inc",
    "wof:placetype":"venue"
},
  "geometry": {"coordinates":[-91.306263,43.814699],"type":"Point"}
}