{
  "type": "Feature",
  "properties": {
    "iso:country":"US",
    "sg:address":"914 E Jessamine Ave",
    "sg:city":"St Paul",
    "sg:classifiers":[
        {
            "category":"Taxi",
            "type":"Transportation"
        }
    ],
    "sg:phone":"+1 651 771 7914",
    "sg:postcode":"55106",
    "sg:province":"MN",
    "sg:tags":[
        "taxicab"
    ],
    "wof:name":"Prenosil Taxi Inc",
    "wof:placetype":"venue"
},
  "geometry": {"coordinates":[-93.06193500000001,44.974737],"type":"Point"}
}