{
  "type": "Feature",
  "properties": {
    "iso:country":"US",
    "sg:address":"2295 Rice St",
    "sg:city":"Roseville",
    "sg:classifiers":[
        {
            "category":"Autos & Motor Vehicles",
            "subcategory":"Fuel & Gas Station",
            "type":"Retail Goods"
        }
    ],
    "sg:phone":"+1 651 787 0733",
    "sg:postcode":"55113",
    "sg:province":"MN",
    "sg:tags":[
        "oil"
    ],
    "sg:website":"www.speedway.com",
    "wof:name":"Super America",
    "wof:placetype":"venue"
},
  "geometry": {"coordinates":[-93.10605700000001,45.010121],"type":"Point"}
}