{
  "type": "Feature",
  "properties": {
    "addr:full":"231 Courtland St Excelsior MN 55331",
    "addr:housenumber":"231",
    "addr:postcode":"55331",
    "addr:street":"Courtland St",
    "iso:country":"US",
    "sg:address":"231 Courtland St",
    "sg:city":"Excelsior",
    "sg:classifiers":[
        {
            "category":"Professional",
            "type":"Services"
        }
    ],
    "sg:phone":"+1 952 401 0573",
    "sg:postcode":"55331",
    "sg:province":"MN",
    "wof:name":"Kevin A McCary",
    "wof:placetype":"venue"
},
  "geometry": {"coordinates":[-93.569592,44.904439],"type":"Point"}
}