{
  "type": "Feature",
  "properties": {
    "addr:full":"803 E School St Owatonna MN 55060",
    "addr:housenumber":"803",
    "addr:postcode":"55060",
    "addr:street":"E School St",
    "iso:country":"US",
    "sg:address":"803 E School St",
    "sg:city":"Owatonna",
    "sg:classifiers":[
        {
            "category":"Health Services",
            "subcategory":"Podiatrist",
            "type":"Services"
        }
    ],
    "sg:phone":"+1 507 451 5950",
    "sg:postcode":"55060",
    "sg:province":"MN",
    "wof:name":"Advanced Foot & Ankle Clinics",
    "wof:placetype":"venue"
},
  "geometry": {"coordinates":[-93.20988800000001,44.080487],"type":"Point"}
}