{
  "type": "Feature",
  "properties": {
    "addr:full":"1004 Marquette Ave Ste 205 Minneapolis MN 55403",
    "addr:housenumber":"1004",
    "addr:postcode":"55403",
    "addr:street":"Marquette Ave Ste 205",
    "iso:country":"US",
    "sg:address":"1004 Marquette Ave Ste 205",
    "sg:city":"Minneapolis",
    "sg:classifiers":[
        {
            "category":"Education",
            "subcategory":"Music School",
            "type":"Public Place"
        }
    ],
    "sg:phone":"+1 612 375 0708",
    "sg:postcode":"55403",
    "sg:province":"MN",
    "sg:tags":[
        "instrument",
        "teacher",
        "musical"
    ],
    "wof:name":"Claire Givens Violins Inc",
    "wof:placetype":"venue"
},
  "geometry": {"coordinates":[-93.27330000000001,44.9734],"type":"Point"}
}