{
  "type": "Feature",
  "properties": {
    "addr:full":"21896 Co Hwy 22 Detroit Lakes MN 56501",
    "addr:housenumber":"21896",
    "addr:postcode":"56501",
    "addr:street":"Co Hwy 22",
    "iso:country":"US",
    "sg:address":"21896 Co Hwy 22",
    "sg:city":"Detroit Lakes",
    "sg:classifiers":[
        {
            "category":"Organizations",
            "subcategory":"Religious Organization",
            "type":"Services"
        }
    ],
    "sg:phone":"+1 218 439 3249",
    "sg:postcode":"56501",
    "sg:province":"MN",
    "wof:name":"Augustana Lutheran Church",
    "wof:placetype":"venue"
},
  "geometry": {"coordinates":[-95.945396,46.745992],"type":"Point"}
}