{
  "type": "Feature",
  "properties": {
    "addr:full":"7700 Hudson Rd Saint Paul MN 55125",
    "addr:housenumber":"7700",
    "addr:postcode":"55125",
    "addr:street":"Hudson Rd",
    "iso:country":"US",
    "sg:address":"7700 Hudson Rd",
    "sg:city":"Saint Paul",
    "sg:classifiers":[
        {
            "category":"Personal",
            "type":"Services"
        }
    ],
    "sg:phone":"+1 651 714 1828",
    "sg:postcode":"55125",
    "sg:province":"MN",
    "wof:name":"Center For Electrolysis Skin",
    "wof:placetype":"venue"
},
  "geometry": {"coordinates":[-92.951593,44.94747],"type":"Point"}
}