{
  "type": "Feature",
  "properties": {
    "addr:full":"702 E Southview Dr Marshall MN 56258",
    "addr:housenumber":"702",
    "addr:postcode":"56258",
    "addr:street":"E Southview Dr",
    "iso:country":"US",
    "sg:address":"702 E Southview Dr",
    "sg:city":"Marshall",
    "sg:classifiers":[
        {
            "category":"Social Services",
            "subcategory":"Child Care",
            "type":"Services"
        }
    ],
    "sg:phone":"+1 507 532 9503",
    "sg:postcode":"56258",
    "sg:province":"MN",
    "wof:name":"Discovery Center Preschool",
    "wof:placetype":"venue"
},
  "geometry": {"coordinates":[-95.78163000000001,44.43581],"type":"Point"}
}