{
  "type": "Feature",
  "properties": {
    "addr:full":"30065 Fir Trl Stacy MN 55079",
    "addr:housenumber":"30065",
    "addr:postcode":"55079",
    "addr:street":"Fir Trl",
    "iso:country":"US",
    "sg:address":"30065 Fir Trl",
    "sg:city":"Stacy",
    "sg:classifiers":[
        {
            "category":"Professional",
            "type":"Services"
        }
    ],
    "sg:phone":"+1 651 408 1055",
    "sg:postcode":"55079",
    "sg:province":"MN",
    "wof:name":"Timothy D Cashill",
    "wof:placetype":"venue"
},
  "geometry": {"coordinates":[-92.999709,45.384561],"type":"Point"}
}