{
  "type": "Feature",
  "properties": {
    "addr:full":"15841 52nd St NE Saint Michael MN 55376",
    "addr:housenumber":"15841",
    "addr:postcode":"55376",
    "addr:street":"52Nd St Ne Saint Michael",
    "iso:country":"US",
    "sg:address":"15841 52nd St NE",
    "sg:city":"Saint Michael",
    "sg:classifiers":[
        {
            "category":"Professional",
            "subcategory":"Computer Services",
            "type":"Services"
        }
    ],
    "sg:phone":"+1 763 428 3717",
    "sg:postcode":"55376",
    "sg:province":"MN",
    "sg:tags":[
        "information",
        "retrieval"
    ],
    "wof:name":"Sabre Travel Info Network",
    "wof:placetype":"venue"
},
  "geometry": {"coordinates":[-93.56549,45.226823],"type":"Point"}
}