{
  "type": "Feature",
  "properties": {
    "addr:full":"3325 Aquila Ave S St Louis Park MN 55426",
    "addr:housenumber":"3325",
    "addr:postcode":"55426",
    "addr:street":"Aquila Ave S",
    "iso:country":"US",
    "sg:address":"3325 Aquila Ave S",
    "sg:city":"St Louis Park",
    "sg:classifiers":[
        {
            "category":"Organizations",
            "subcategory":"Religious Organization",
            "type":"Services"
        }
    ],
    "sg:phone":"+1 952 945 9172",
    "sg:postcode":"55426",
    "sg:province":"MN",
    "sg:tags":[
        "church"
    ],
    "wof:name":"Resurrection Life Church",
    "wof:placetype":"venue"
},
  "geometry": {"coordinates":[-93.38941,44.942678],"type":"Point"}
}