{
  "type": "Feature",
  "properties": {
    "iso:country":"US",
    "sg:address":"1212 Moor Stone Dr NE",
    "sg:city":"Alexandria",
    "sg:classifiers":[
        {
            "category":"Social Services",
            "subcategory":"Child Care",
            "type":"Services"
        }
    ],
    "sg:phone":"+1 320 762 0872",
    "sg:postcode":"56308",
    "sg:province":"MN",
    "sg:tags":[
        "day",
        "provider"
    ],
    "wof:name":"Hodgson Virginia A",
    "wof:placetype":"venue"
},
  "geometry": {"coordinates":[-95.319343,45.905835],"type":"Point"}
}