{
  "type": "Feature",
  "properties": {
    "iso:country":"US",
    "sg:address":"10800 Mankato St NE",
    "sg:city":"Minneapolis",
    "sg:classifiers":[
        {
            "category":"Professional",
            "subcategory":"Business Services",
            "type":"Services"
        }
    ],
    "sg:phone":"+1 763 717 0773",
    "sg:postcode":"55449",
    "sg:province":"MN",
    "sg:tags":[
        "precision",
        "grinding"
    ],
    "wof:name":"Silvertip Associates",
    "wof:placetype":"venue"
},
  "geometry": {"coordinates":[-93.218692,45.166103],"type":"Point"}
}