{
  "type": "Feature",
  "properties": {
    "addr:full":"8950 Goodrich Rd Apt 305 Minneapolis MN 55437",
    "addr:housenumber":"8950;305",
    "addr:postcode":"55437",
    "addr:street":"Goodrich Rd Apt",
    "iso:country":"US",
    "sg:address":"8950 Goodrich Rd Apt 305",
    "sg:city":"Minneapolis",
    "sg:classifiers":[
        {
            "category":"Retail",
            "subcategory":"Laundry & Dry Cleaning",
            "type":"Services"
        },
        {
            "category":"Building & Trades",
            "subcategory":"Cleaning & Sanitation",
            "type":"Services"
        }
    ],
    "sg:phone":"+1 952 994 1795",
    "sg:postcode":"55437",
    "sg:province":"MN",
    "sg:tags":[
        "cleaner",
        "house"
    ],
    "wof:name":"Sunnyside Cleaning Services",
    "wof:placetype":"venue"
},
  "geometry": {"coordinates":[-93.33129099999999,44.843269],"type":"Point"}
}