{
  "type": "Feature",
  "properties": {
    "addr:full":"8332 State Hwy 7 Minneapolis MN 55426",
    "addr:housenumber":"8332",
    "addr:postcode":"55426",
    "addr:street":"State Hwy 7",
    "iso:country":"US",
    "sg:address":"8332 State Hwy 7",
    "sg:city":"Minneapolis",
    "sg:classifiers":[
        {
            "category":"Shopping",
            "subcategory":"Photographic Equipment",
            "type":"Retail Goods"
        }
    ],
    "sg:phone":"+1 952 935 1909",
    "sg:postcode":"55426",
    "sg:province":"MN",
    "sg:tags":[
        "camera",
        "fin",
        "film",
        "provides",
        "supply"
    ],
    "wof:name":"Wolf Camera and Video",
    "wof:placetype":"venue"
},
  "geometry": {"coordinates":[-93.38382,44.936049],"type":"Point"}
}