{
  "type": "Feature",
  "properties": {
    "iso:country":"US",
    "sg:address":"4760 White Bear Pkwy",
    "sg:city":"White Bear Lake",
    "sg:classifiers":[
        {
            "category":"Insurance",
            "subcategory":"Insurance Agent",
            "type":"Services"
        }
    ],
    "sg:phone":"+1 651 429 3868",
    "sg:postcode":"55110",
    "sg:province":"MN",
    "wof:name":"Jonathan Hind Financial Group",
    "wof:placetype":"venue"
},
  "geometry": {"coordinates":[-93.04841399999999,45.085429],"type":"Point"}
}