{
  "type": "Feature",
  "properties": {
    "iso:country":"US",
    "sg:address":"402 Main St N",
    "sg:city":"Stillwater",
    "sg:classifiers":[
        {
            "category":"Wholesale",
            "subcategory":"Non-durable Goods",
            "type":"Manufacturing & Wholesale Goods"
        }
    ],
    "sg:phone":"+1 651 351 2797",
    "sg:postcode":"55082",
    "sg:province":"MN",
    "sg:tags":[
        "dry",
        "goods-wholesale"
    ],
    "wof:name":"Montero Distributing",
    "wof:placetype":"venue"
},
  "geometry": {"coordinates":[-92.807323,45.059466],"type":"Point"}
}