{
  "type": "Feature",
  "properties": {
    "iso:country":"US",
    "sg:address":"3844 Inglewood Ave S",
    "sg:city":"Minneapolis",
    "sg:classifiers":[
        {
            "category":"Professional",
            "subcategory":"Advertising",
            "type":"Services"
        }
    ],
    "sg:phone":"+1 952 929 0636",
    "sg:postcode":"55416",
    "sg:province":"MN",
    "sg:tags":[
        "marketing",
        "consultant"
    ],
    "wof:name":"Design Jam",
    "wof:placetype":"venue"
},
  "geometry": {"coordinates":[-93.33295,44.933195],"type":"Point"}
}