{
  "type": "Feature",
  "properties": {
    "addr:full":"5809 Three Oaks Ave Maple Plain MN 55359",
    "addr:housenumber":"5809",
    "addr:postcode":"55359",
    "addr:street":"Three Oaks Ave",
    "iso:country":"US",
    "sg:address":"5809 Three Oaks Ave",
    "sg:city":"Maple Plain",
    "sg:classifiers":[
        {
            "category":"Retail",
            "subcategory":"Laundry & Dry Cleaning",
            "type":"Services"
        }
    ],
    "sg:phone":"+1 763 479 2094",
    "sg:postcode":"55359",
    "sg:province":"MN",
    "wof:name":"Alpha Rug Cleaning",
    "wof:placetype":"venue"
},
  "geometry": {"coordinates":[-93.67099,45.00454],"type":"Point"}
}