{
  "type": "Feature",
  "properties": {
    "addr:full":"1101 W 104th St Bloomington MN 55431",
    "addr:housenumber":"1101",
    "addr:postcode":"55431",
    "addr:street":"W 104Th St",
    "iso:country":"US",
    "sg:address":"1101 W 104th St",
    "sg:city":"Bloomington",
    "sg:classifiers":[
        {
            "category":"Building & Trades",
            "subcategory":"Construction",
            "type":"Services"
        }
    ],
    "sg:phone":"+1 952 346 0369",
    "sg:postcode":"55431",
    "sg:province":"MN",
    "sg:tags":[
        "roofing",
        "contractor"
    ],
    "wof:name":"Brian Conrad Construction",
    "wof:placetype":"venue"
},
  "geometry": {"coordinates":[-93.29877399999999,44.815128],"type":"Point"}
}