{
  "type": "Feature",
  "properties": {
    "addr:full":"120 E Broadway Minneapolis MN 55425",
    "addr:housenumber":"120",
    "addr:postcode":"55425",
    "addr:street":"E Broadway",
    "iso:country":"US",
    "sg:address":"120 E Broadway",
    "sg:city":"Minneapolis",
    "sg:classifiers":[
        {
            "category":"Museum",
            "subcategory":"Aquarium",
            "type":"Entertainment"
        }
    ],
    "sg:phone":"+1 952 232 0157",
    "sg:postcode":"55425",
    "sg:province":"MN",
    "sg:tags":[
        "supply"
    ],
    "sg:website":"http://twincities.citysearch.com/profile/external/35736324/bloomington_mn/underwater_adventures_aquarium.html?publisher=yellowpages&reference_id=1&placement=ypwebsitemip",
    "wof:name":"Underwater Adventures Aquarium",
    "wof:placetype":"venue"
},
  "geometry": {"coordinates":[-93.24043399999999,44.853769],"type":"Point"}
}