{
  "type": "Feature",
  "properties": {
    "addr:full":"506 Jefferson Hwy N Champlin MN 55316",
    "addr:housenumber":"506",
    "addr:postcode":"55316",
    "addr:street":"Jefferson Hwy N",
    "iso:country":"US",
    "sg:address":"506 Jefferson Hwy N",
    "sg:city":"Champlin",
    "sg:classifiers":[
        {
            "category":"Personal",
            "subcategory":"Beauty Salon",
            "type":"Services"
        },
        {
            "category":"Personal",
            "subcategory":"Hair Removal",
            "type":"Services"
        },
        {
            "category":"Personal",
            "subcategory":"Skin Care",
            "type":"Services"
        },
        {
            "category":"Personal",
            "subcategory":"Nail Salon",
            "type":"Services"
        }
    ],
    "sg:phone":"+1 877 257 6021",
    "sg:postcode":"55316",
    "sg:province":"MN",
    "sg:tags":[
        "braiding",
        "weaving",
        "stylist"
    ],
    "wof:name":"Trio Salon & Spa",
    "wof:placetype":"venue"
},
  "geometry": {"coordinates":[-93.396,45.153475],"type":"Point"}
}