{
  "type": "Feature",
  "properties": {
    "addr:full":"425 Park Ave Minneapolis MN 55415",
    "addr:housenumber":"425",
    "addr:postcode":"55415",
    "addr:street":"Park Ave",
    "iso:country":"US",
    "sg:address":"425 Park Ave",
    "sg:city":"Minneapolis",
    "sg:classifiers":[
        {
            "category":"Parking",
            "type":"Transportation"
        }
    ],
    "sg:phone":"+1 612 455 0702",
    "sg:postcode":"55415",
    "sg:province":"MN",
    "sg:website":"parksmartmpls.com",
    "wof:name":"Downtown East Municipal Parking Garage",
    "wof:placetype":"venue"
},
  "geometry": {"coordinates":[-93.26031399999999,44.975625],"type":"Point"}
}