{
  "type": "Feature",
  "properties": {
    "iso:country":"US",
    "sg:address":"995 University Ave W",
    "sg:city":"St Paul",
    "sg:classifiers":[
        {
            "category":"Banks & Credit Unions",
            "subcategory":"Bank",
            "type":"Services"
        }
    ],
    "sg:phone":"+1 651 209 6288",
    "sg:postcode":"55104",
    "sg:province":"MN",
    "sg:tags":[
        "loan"
    ],
    "wof:name":"World Lending Group",
    "wof:placetype":"venue"
},
  "geometry": {"coordinates":[-93.143822,44.955801],"type":"Point"}
}