{
  "type": "Feature",
  "properties": {
    "addr:full":"2328 Eagle Creek Blvd Shakopee MN 55379",
    "addr:housenumber":"2328",
    "addr:postcode":"55379",
    "addr:street":"Eagle Creek Blvd",
    "iso:country":"US",
    "sg:address":"2328 Eagle Creek Blvd",
    "sg:city":"Shakopee",
    "sg:classifiers":[
        {
            "category":"Social Services",
            "subcategory":"Child Care",
            "type":"Services"
        }
    ],
    "sg:phone":"+1 952 445 5274",
    "sg:postcode":"55379",
    "sg:province":"MN",
    "sg:tags":[
        "day",
        "provider"
    ],
    "wof:name":"Kathleen Stafford",
    "wof:placetype":"venue"
},
  "geometry": {"coordinates":[-93.494434,44.788287],"type":"Point"}
}