{
  "type": "Feature",
  "properties": {
    "iso:country":"US",
    "sg:address":"17755 Cannon City Path",
    "sg:city":"Faribault",
    "sg:classifiers":[
        {
            "category":"Building & Trades",
            "subcategory":"Landscaping Services",
            "type":"Services"
        }
    ],
    "sg:phone":"+1 507 334 7620",
    "sg:postcode":"55021",
    "sg:province":"MN",
    "wof:name":"G&N Landscaping Inc",
    "wof:placetype":"venue"
},
  "geometry": {"coordinates":[-93.207409,44.330405],"type":"Point"}
}