{
  "type": "Feature",
  "properties": {
    "iso:country":"US",
    "sg:address":"1146 W Central Ave",
    "sg:city":"Saint Paul",
    "sg:classifiers":[
        {
            "category":"Building & Trades",
            "subcategory":"Construction",
            "type":"Services"
        }
    ],
    "sg:phone":"+1 651 646 4349",
    "sg:postcode":"55104",
    "sg:province":"MN",
    "sg:tags":[
        "house",
        "residential"
    ],
    "wof:name":"Honey Do Repairs Inc",
    "wof:placetype":"venue"
},
  "geometry": {"coordinates":[-93.147809,44.952945],"type":"Point"}
}