{
  "type": "Feature",
  "properties": {
    "addr:full":"551 Valley Park Dr S Shakopee MN 55379",
    "addr:housenumber":"551",
    "addr:postcode":"55379",
    "addr:street":"Valley Park Dr S",
    "iso:country":"US",
    "sg:address":"551 Valley Park Dr S",
    "sg:city":"Shakopee",
    "sg:classifiers":[
        {
            "category":"Wholesale",
            "subcategory":"Machinery & Supplies",
            "type":"Manufacturing & Wholesale Goods"
        }
    ],
    "sg:phone":"+1 952 496 4216",
    "sg:postcode":"55379",
    "sg:province":"MN",
    "sg:tags":[
        "equipment",
        "establishment",
        "mfg"
    ],
    "wof:name":"Versapark",
    "wof:placetype":"venue"
},
  "geometry": {"coordinates":[-93.450304,44.796295],"type":"Point"}
}