{
  "type": "Feature",
  "properties": {
    "iso:country":"US",
    "sg:address":"8645 Colfax Ave S",
    "sg:city":"Bloomington",
    "sg:classifiers":[
        {
            "category":"Building & Trades",
            "subcategory":"Construction",
            "type":"Services"
        }
    ],
    "sg:phone":"+1 612 724 5943",
    "sg:postcode":"55420",
    "sg:province":"MN",
    "sg:tags":[
        "resurfacing",
        "laying",
        "refinishing",
        "floor"
    ],
    "wof:name":"William Brenner Floor Co",
    "wof:placetype":"venue"
},
  "geometry": {"coordinates":[-93.292248,44.843312],"type":"Point"}
}