{
  "type": "Feature",
  "properties": {
    "addr:full":"20316 Co Rd 13 New Ulm MN 56073",
    "addr:housenumber":"20316;13",
    "addr:postcode":"56073",
    "addr:street":"Co Rd",
    "iso:country":"US",
    "sg:address":"20316 Co Rd 13",
    "sg:city":"New Ulm",
    "sg:classifiers":[
        {
            "category":"Professional",
            "subcategory":"Computer Services",
            "type":"Services"
        }
    ],
    "sg:phone":"+1 507 354 7019",
    "sg:postcode":"56073",
    "sg:province":"MN",
    "sg:tags":[
        "design",
        "system"
    ],
    "wof:name":"Bruce Buntjers Computer Svcs",
    "wof:placetype":"venue"
},
  "geometry": {"coordinates":[-94.492188,44.243659],"type":"Point"}
}