{
  "type": "Feature",
  "properties": {
    "addr:full":"2310 Chestnut Ave W Minneapolis MN 55405",
    "addr:housenumber":"2310",
    "addr:postcode":"55405",
    "addr:street":"Chestnut Ave W",
    "iso:country":"US",
    "sg:address":"2310 Chestnut Ave W",
    "sg:city":"Minneapolis",
    "sg:classifiers":[
        {
            "category":"Manufacturing",
            "subcategory":"Metals",
            "type":"Manufacturing & Wholesale Goods"
        },
        {
            "category":"Manufacturing",
            "subcategory":"Tools & Machinery",
            "type":"Manufacturing & Wholesale Goods"
        }
    ],
    "sg:phone":"+1 612 381 1060",
    "sg:postcode":"55405",
    "sg:province":"MN",
    "sg:tags":[
        "driving",
        "power",
        "mfg",
        "drilling",
        "quick",
        "change"
    ],
    "sg:website":"www.instybit.com",
    "wof:name":"Insty Bit Inc",
    "wof:placetype":"venue"
},
  "geometry": {"coordinates":[-93.310785,44.977236],"type":"Point"}
}