{
  "type": "Feature",
  "properties": {
    "iso:country":"US",
    "sg:address":"40 5th St E",
    "sg:city":"Halstad",
    "sg:classifiers":[
        {
            "category":"Personal",
            "subcategory":"Beauty Salon",
            "type":"Services"
        }
    ],
    "sg:phone":"+1 218 456 2559",
    "sg:postcode":"56548",
    "sg:province":"MN",
    "wof:name":"Bonnie's Beauty Shop",
    "wof:placetype":"venue"
},
  "geometry": {"coordinates":[-96.824167,47.34977],"type":"Point"}
}