{
  "type": "Feature",
  "properties": {
    "addr:full":"1715 Yankee Doodle Rd Ste 200 Saint Paul MN 55121",
    "addr:housenumber":"1715",
    "addr:postcode":"55121",
    "addr:street":"Yankee Doodle Rd Ste 200",
    "iso:country":"US",
    "sg:address":"1715 Yankee Doodle Rd Ste 200",
    "sg:city":"Saint Paul",
    "sg:classifiers":[
        {
            "category":"Building & Trades",
            "subcategory":"Construction",
            "type":"Services"
        }
    ],
    "sg:phone":"+1 651 379 9090",
    "sg:postcode":"55121",
    "sg:province":"MN",
    "sg:tags":[
        "contractor"
    ],
    "sg:website":"www.amconconstruction.com",
    "wof:name":"Amcon Construction",
    "wof:placetype":"venue"
},
  "geometry": {"coordinates":[-93.18418800000001,44.83377],"type":"Point"}
}