{
  "type": "Feature",
  "properties": {
    "addr:full":"1825 Buerkle Rd Saint Paul MN 55110",
    "addr:housenumber":"1825",
    "addr:postcode":"55110",
    "addr:street":"Buerkle Rd",
    "iso:country":"US",
    "sg:address":"1825 Buerkle Rd",
    "sg:city":"Saint Paul",
    "sg:classifiers":[
        {
            "category":"Health Services",
            "subcategory":"Clinic",
            "type":"Services"
        }
    ],
    "sg:phone":"+1 651 777 0012",
    "sg:postcode":"55110",
    "sg:province":"MN",
    "wof:name":"Reflex Medical Inc",
    "wof:placetype":"venue"
},
  "geometry": {"coordinates":[-93.017905,45.039305],"type":"Point"}
}