{
  "type": "Feature",
  "properties": {
    "iso:country":"US",
    "sg:address":"3640 Ximines Ln N",
    "sg:city":"Minneapolis",
    "sg:classifiers":[
        {
            "category":"Professional",
            "subcategory":"Business Services",
            "type":"Services"
        }
    ],
    "sg:phone":"+1 763 545 2986",
    "sg:postcode":"55441",
    "sg:province":"MN",
    "wof:name":"Inner Expressions",
    "wof:placetype":"venue"
},
  "geometry": {"coordinates":[-93.418764,45.022634],"type":"Point"}
}