{
  "type": "Feature",
  "properties": {
    "addr:full":"9007 Springwood Dr Saint Paul MN 55125",
    "addr:housenumber":"9007",
    "addr:postcode":"55125",
    "addr:street":"Springwood Dr",
    "iso:country":"US",
    "sg:address":"9007 Springwood Dr",
    "sg:city":"Saint Paul",
    "sg:classifiers":[
        {
            "category":"Professional",
            "subcategory":"Advertising",
            "type":"Services"
        }
    ],
    "sg:phone":"+1 651 735 3962",
    "sg:postcode":"55125",
    "sg:province":"MN",
    "sg:tags":[
        "agency"
    ],
    "wof:name":"Park N See Advertising Inc",
    "wof:placetype":"venue"
},
  "geometry": {"coordinates":[-92.92750100000001,44.896782],"type":"Point"}
}