{
  "type": "Feature",
  "properties": {
    "iso:country":"US",
    "sg:address":"716 S Cleveland Ave",
    "sg:city":"St Paul",
    "sg:classifiers":[
        {
            "category":"Retail",
            "subcategory":"Repair Shop",
            "type":"Services"
        }
    ],
    "sg:phone":"+1 651 690 4443",
    "sg:postcode":"55116",
    "sg:province":"MN",
    "sg:tags":[
        "lock",
        "locksmith"
    ],
    "wof:name":"Babcock & Son Security Corp",
    "wof:placetype":"venue"
},
  "geometry": {"coordinates":[-93.18729999999999,44.920589],"type":"Point"}
}