{
  "type": "Feature",
  "properties": {
    "addr:full":"2505 University Ave SE Minneapolis MN 55414",
    "addr:housenumber":"2505",
    "addr:postcode":"55414",
    "addr:street":"University Ave Se",
    "iso:country":"US",
    "sg:address":"2505 University Ave SE",
    "sg:city":"Minneapolis",
    "sg:classifiers":[
        {
            "category":"Restaurant",
            "type":"Food & Drink"
        }
    ],
    "sg:phone":"+1 612 331 7474",
    "sg:postcode":"55414",
    "sg:province":"MN",
    "sg:tags":[
        "pizza"
    ],
    "wof:name":"Leaning Tower of Pizza",
    "wof:placetype":"venue"
},
  "geometry": {"coordinates":[-93.221001,44.9734],"type":"Point"}
}