{
  "type": "Feature",
  "properties": {
    "iso:country":"US",
    "sg:address":"103 E McKinley Ave",
    "sg:city":"Shelly",
    "sg:classifiers":[
        {
            "category":"Manufacturing",
            "subcategory":"Retail Goods",
            "type":"Manufacturing & Wholesale Goods"
        }
    ],
    "sg:phone":"+1 218 886 7001",
    "sg:postcode":"56581",
    "sg:province":"MN",
    "sg:tags":[
        "product",
        "mfg"
    ],
    "wof:name":"K K Rose Originals",
    "wof:placetype":"venue"
},
  "geometry": {"coordinates":[-96.819782,47.458666],"type":"Point"}
}