{
  "type": "Feature",
  "properties": {
    "addr:full":"15936 Linnet St NW Andover MN 55304",
    "addr:postcode":"15936;55304",
    "addr:street":"Linnet St Nw",
    "iso:country":"US",
    "sg:address":"15936 Linnet St NW",
    "sg:city":"Andover",
    "sg:classifiers":[
        {
            "category":"Building & Trades",
            "subcategory":"Landscaping Services",
            "type":"Services"
        }
    ],
    "sg:phone":"+1 763 434 4122",
    "sg:postcode":"55304",
    "sg:province":"MN",
    "sg:tags":[
        "lawn"
    ],
    "wof:name":"Home And Landscape Design Inc",
    "wof:placetype":"venue"
},
  "geometry": {"coordinates":[-93.313211,45.260555],"type":"Point"}
}