{
  "type": "Feature",
  "properties": {
    "addr:full":"914 3rd Ave NE Staples MN 56479",
    "addr:housenumber":"914",
    "addr:postcode":"56479",
    "addr:street":"3Rd Ave Ne",
    "iso:country":"US",
    "sg:address":"914 3rd Ave NE",
    "sg:city":"Staples",
    "sg:classifiers":[
        {
            "category":"Organizations",
            "subcategory":"Religious Organization",
            "type":"Services"
        }
    ],
    "sg:phone":"+1 218 894 1081",
    "sg:postcode":"56479",
    "sg:province":"MN",
    "sg:tags":[
        "place",
        "worship",
        "church"
    ],
    "wof:name":"Staples Assembly Of God",
    "wof:placetype":"venue"
},
  "geometry": {"coordinates":[-94.787522,46.356516],"type":"Point"}
}