{
  "type": "Feature",
  "properties": {
    "iso:country":"US",
    "sg:address":"20 2nd St NE",
    "sg:city":"Aitkin",
    "sg:classifiers":[
        {
            "category":"Food & Beverages",
            "subcategory":"Bakery",
            "type":"Retail Goods"
        }
    ],
    "sg:phone":"+1 218 927 4710",
    "sg:postcode":"56431",
    "sg:province":"MN",
    "sg:tags":[
        "cookie",
        "cracker"
    ],
    "wof:name":"Cookies N Things",
    "wof:placetype":"venue"
},
  "geometry": {"coordinates":[-93.706383,46.533449],"type":"Point"}
}