{
  "type": "Feature",
  "properties": {
    "addr:full":"5605 W 36th St Minneapolis MN 55416",
    "addr:housenumber":"5605",
    "addr:postcode":"55416",
    "addr:street":"W 36Th St",
    "iso:country":"US",
    "sg:address":"5605 W 36th St",
    "sg:city":"Minneapolis",
    "sg:classifiers":[
        {
            "category":"Shopping",
            "subcategory":"Pharmacy",
            "type":"Retail Goods"
        }
    ],
    "sg:phone":"+1 952 653 2117",
    "sg:postcode":"55416",
    "sg:province":"MN",
    "wof:name":"Homeopathic Integrative Hlthcr",
    "wof:placetype":"venue"
},
  "geometry": {"coordinates":[-93.351506,44.937692],"type":"Point"}
}