{
  "type": "Feature",
  "properties": {
    "iso:country":"US",
    "sg:address":"16071 Royal Rd",
    "sg:city":"Anoka",
    "sg:classifiers":[
        {
            "category":"Professional",
            "subcategory":"Business Services",
            "type":"Services"
        },
        {
            "category":"Shopping",
            "subcategory":"Crafts & Fabrics",
            "type":"Retail Goods"
        }
    ],
    "sg:phone":"+1 763 241 5545",
    "sg:postcode":"55303",
    "sg:province":"MN",
    "sg:tags":[
        "sewing",
        "embroidery"
    ],
    "wof:name":"In Stitches Custom Embroidery",
    "wof:placetype":"venue"
},
  "geometry": {"coordinates":[-93.48859899999999,45.264402],"type":"Point"}
}