{
  "type": "Feature",
  "properties": {
    "addr:full":"360 5th Ave Granite Falls MN 56241",
    "addr:housenumber":"360",
    "addr:postcode":"56241",
    "addr:street":"5Th Ave",
    "iso:country":"US",
    "sg:address":"360 5th Ave",
    "sg:city":"Granite Falls",
    "sg:classifiers":[
        {
            "category":"Personal",
            "type":"Services"
        }
    ],
    "sg:phone":"+1 320 564 3212",
    "sg:postcode":"56241",
    "sg:province":"MN",
    "wof:name":"Therapeutic Massage By Amber",
    "wof:placetype":"venue"
},
  "geometry": {"coordinates":[-95.543211,44.814108],"type":"Point"}
}