{
  "type": "Feature",
  "properties": {
    "iso:country":"US",
    "sg:address":"512 Paul Bunyan Dr SE",
    "sg:city":"Bemidji",
    "sg:classifiers":[
        {
            "category":"Restaurant",
            "type":"Food & Drink"
        }
    ],
    "sg:menulink":"http://www.allmenus.com/mn/bemidji/77480-papa-murphys/menu/",
    "sg:phone":"+1 218 444 7025",
    "sg:postcode":"56601",
    "sg:province":"MN",
    "sg:tags":[
        "american",
        "pizza"
    ],
    "wof:name":"Papa Murphy's",
    "wof:placetype":"venue"
},
  "geometry": {"coordinates":[-94.863572,47.456892],"type":"Point"}
}