{
  "type": "Feature",
  "properties": {
    "addr:full":"220 Adams St Anoka MN 55303",
    "addr:housenumber":"220",
    "addr:postcode":"55303",
    "addr:street":"Adams St",
    "iso:country":"US",
    "sg:address":"220 Adams St",
    "sg:city":"Anoka",
    "sg:classifiers":[
        {
            "category":"Social Services",
            "subcategory":"Child Care",
            "type":"Services"
        }
    ],
    "sg:phone":"+1 763 576 1080",
    "sg:postcode":"55303",
    "sg:province":"MN",
    "sg:tags":[
        "day"
    ],
    "wof:name":"Patricia A Paddock",
    "wof:placetype":"venue"
},
  "geometry": {"coordinates":[-93.387539,45.192839],"type":"Point"}
}