{
  "type": "Feature",
  "properties": {
    "addr:full":"21720 Flint Rd Mankato MN 56001",
    "addr:housenumber":"21720",
    "addr:postcode":"56001",
    "addr:street":"Flint Rd",
    "iso:country":"US",
    "sg:address":"21720 Flint Rd",
    "sg:city":"Mankato",
    "sg:classifiers":[
        {
            "category":"Farming",
            "subcategory":"Farm",
            "type":"Manufacturing & Wholesale Goods"
        }
    ],
    "sg:phone":"+1 507 947 3497",
    "sg:postcode":"56001",
    "sg:province":"MN",
    "sg:tags":[
        "crop",
        "general"
    ],
    "wof:name":"Owens Farms Inc",
    "wof:placetype":"venue"
},
  "geometry": {"coordinates":[-94.13899000000001,44.171738],"type":"Point"}
}