{
  "type": "Feature",
  "properties": {
    "iso:country":"US",
    "sg:address":"119 1st St NE",
    "sg:city":"Little Falls",
    "sg:classifiers":[
        {
            "category":"Insurance",
            "subcategory":"Insurance Agent",
            "type":"Services"
        }
    ],
    "sg:phone":"+1 320 632 2376",
    "sg:postcode":"56345",
    "sg:province":"MN",
    "wof:name":"Ken Hank Agency",
    "wof:placetype":"venue"
},
  "geometry": {"coordinates":[-94.36234399999999,45.977329],"type":"Point"}
}