{
  "type": "Feature",
  "properties": {
    "addr:full":"29688 840th Ave Danube MN 56230",
    "addr:housenumber":"29688",
    "addr:postcode":"56230",
    "addr:street":"840Th Ave",
    "iso:country":"US",
    "sg:address":"29688 840th Ave",
    "sg:city":"Danube",
    "sg:phone":"+1 320 826 2362",
    "sg:postcode":"56230",
    "sg:province":"MN",
    "sg:tags":[
        "farm",
        "corn",
        "soybean"
    ],
    "wof:name":"Henry Schneiderman",
    "wof:placetype":"venue"
},
  "geometry": {"coordinates":[-95.084318,44.803652],"type":"Point"}
}