{
  "type": "Feature",
  "properties": {
    "iso:country":"US",
    "sg:address":"41353 460th Ave",
    "sg:city":"Perham",
    "sg:classifiers":[
        {
            "category":"Wholesale",
            "subcategory":"Farm Supplies",
            "type":"Manufacturing & Wholesale Goods"
        }
    ],
    "sg:phone":"+1 218 346 9026",
    "sg:postcode":"56573",
    "sg:province":"MN",
    "sg:tags":[
        "equipment"
    ],
    "wof:name":"Picu Up Repair & Delivery",
    "wof:placetype":"venue"
},
  "geometry": {"coordinates":[-95.53256399999999,46.569345],"type":"Point"}
}