{
  "type": "Feature",
  "properties": {
    "addr:full":"80850 400th St Bird Island MN 55310",
    "addr:housenumber":"80850",
    "addr:postcode":"55310",
    "addr:street":"400Th St",
    "iso:country":"US",
    "sg:address":"80850 400th St",
    "sg:city":"Bird Island",
    "sg:classifiers":[
        {
            "category":"Health Services",
            "subcategory":"Clinic",
            "type":"Services"
        }
    ],
    "sg:phone":"+1 320 365 4419",
    "sg:postcode":"55310",
    "sg:province":"MN",
    "wof:name":"Tim Orth Memorial Foundation",
    "wof:placetype":"venue"
},
  "geometry": {"coordinates":[-94.87446199999999,44.747904],"type":"Point"}
}