{
  "type": "Feature",
  "properties": {
    "addr:full":"6001 Egan Dr Savage MN 55378",
    "addr:housenumber":"6001",
    "addr:postcode":"55378",
    "addr:street":"Egan Dr",
    "iso:country":"US",
    "sg:address":"6001 Egan Dr",
    "sg:city":"Savage",
    "sg:classifiers":[
        {
            "category":"Banks & Credit Unions",
            "subcategory":"Investment Brokerage",
            "type":"Services"
        }
    ],
    "sg:phone":"+1 952 226 6988",
    "sg:postcode":"55378",
    "sg:province":"MN",
    "sg:tags":[
        "funds",
        "mutual"
    ],
    "wof:name":"Edward Jones Co",
    "wof:placetype":"venue"
},
  "geometry": {"coordinates":[-93.354928,44.746568],"type":"Point"}
}