{
  "type": "Feature",
  "properties": {
    "addr:full":"594 E Magnolia Ave Saint Paul MN 55101",
    "addr:housenumber":"594",
    "addr:postcode":"55101",
    "addr:street":"E Magnolia Ave",
    "iso:country":"US",
    "sg:address":"594 E Magnolia Ave",
    "sg:city":"Saint Paul",
    "sg:classifiers":[
        {
            "category":"Professional",
            "subcategory":"Art Services",
            "type":"Services"
        }
    ],
    "sg:phone":"+1 651 774 9164",
    "sg:postcode":"55101",
    "sg:province":"MN",
    "sg:tags":[
        "commercial",
        "design"
    ],
    "wof:name":"Great F/X",
    "wof:placetype":"venue"
},
  "geometry": {"coordinates":[-93.07396199999999,44.97375],"type":"Point"}
}