{
  "type": "Feature",
  "properties": {
    "iso:country":"US",
    "sg:address":"109 E 26th St",
    "sg:city":"Minneapolis",
    "sg:classifiers":[
        {
            "category":"Bars & Pubs",
            "type":"Food & Drink"
        }
    ],
    "sg:phone":"+1 612 872 0629",
    "sg:postcode":"55404",
    "sg:province":"MN",
    "sg:tags":[
        "tavern"
    ],
    "wof:name":"Joes Bar",
    "wof:placetype":"venue"
},
  "geometry": {"coordinates":[-93.27566299999999,44.955459],"type":"Point"}
}