{
  "type": "Feature",
  "properties": {
    "iso:country":"US",
    "sg:address":"65756 350th St",
    "sg:city":"Gibbon",
    "sg:classifiers":[
        {
            "category":"Farming",
            "subcategory":"Farm",
            "type":"Manufacturing & Wholesale Goods"
        }
    ],
    "sg:phone":"+1 507 354 5720",
    "sg:postcode":"55335",
    "sg:province":"MN",
    "sg:tags":[
        "crop",
        "general"
    ],
    "wof:name":"Lynn Forst",
    "wof:placetype":"venue"
},
  "geometry": {"coordinates":[-94.58217999999999,44.44175],"type":"Point"}
}