{
  "type": "Feature",
  "properties": {
    "iso:country":"US",
    "sg:address":"900 W Lake St",
    "sg:city":"Chisholm",
    "sg:classifiers":[
        {
            "category":"Government",
            "subcategory":"Office",
            "type":"Public Place"
        }
    ],
    "sg:phone":"+1 218 254 2009",
    "sg:postcode":"55719",
    "sg:province":"MN",
    "sg:tags":[
        "armory",
        "national",
        "guard"
    ],
    "wof:name":"C Co",
    "wof:placetype":"venue"
},
  "geometry": {"coordinates":[-92.88582,47.489527],"type":"Point"}
}