{
  "type": "Feature",
  "properties": {
    "addr:full":"12619 W Swan River Dr Hibbing MN 55746",
    "addr:housenumber":"12619",
    "addr:postcode":"55746",
    "addr:street":"W Swan River Dr Hibbing",
    "iso:country":"US",
    "sg:address":"12619 W Swan River Dr",
    "sg:city":"Hibbing",
    "sg:classifiers":[
        {
            "category":"Professional",
            "subcategory":"Computer Services",
            "type":"Services"
        }
    ],
    "sg:phone":"+1 218 263 9557",
    "sg:postcode":"55746",
    "sg:province":"MN",
    "sg:tags":[
        "isp",
        "provider",
        "internet"
    ],
    "wof:name":"South 4 Craft.Com",
    "wof:placetype":"venue"
},
  "geometry": {"coordinates":[-93.01717499999999,47.262083],"type":"Point"}
}