{
  "type": "Feature",
  "properties": {
    "addr:full":"212 Regency Rd Le Sueur MN 56058",
    "addr:housenumber":"212",
    "addr:postcode":"56058",
    "addr:street":"Regency Rd",
    "iso:country":"US",
    "sg:address":"212 Regency Rd",
    "sg:city":"Le Sueur",
    "sg:classifiers":[
        {
            "category":"Professional",
            "subcategory":"Business Services",
            "type":"Services"
        }
    ],
    "sg:phone":"+1 507 665 3331",
    "sg:postcode":"56058",
    "sg:province":"MN",
    "wof:name":"Beech Club LLC",
    "wof:placetype":"venue"
},
  "geometry": {"coordinates":[-93.902694,44.455186],"type":"Point"}
}