{
  "type": "Feature",
  "properties": {
    "addr:full":"349 3rd St Farmington MN 55024",
    "addr:housenumber":"349",
    "addr:postcode":"55024",
    "addr:street":"3Rd St",
    "iso:country":"US",
    "sg:address":"349 3rd St",
    "sg:city":"Farmington",
    "sg:classifiers":[
        {
            "category":"Retail",
            "subcategory":"Portrait Studio",
            "type":"Services"
        }
    ],
    "sg:phone":"+1 651 460 8359",
    "sg:postcode":"55024",
    "sg:province":"MN",
    "sg:tags":[
        "photographer",
        "photo"
    ],
    "sg:website":"www.heikkilastudios.com",
    "wof:name":"Heikkila Studios",
    "wof:placetype":"venue"
},
  "geometry": {"coordinates":[-93.145121,44.6398],"type":"Point"}
}