{
  "type": "Feature",
  "properties": {
    "iso:country":"US",
    "sg:address":"8673 340th St",
    "sg:city":"Onamia",
    "sg:classifiers":[
        {
            "category":"Farming",
            "subcategory":"Fish & Marine Products",
            "type":"Manufacturing & Wholesale Goods"
        }
    ],
    "sg:phone":"+1 320 532 3384",
    "sg:postcode":"56359",
    "sg:province":"MN",
    "sg:tags":[
        "preserves",
        "fishing",
        "hunting"
    ],
    "wof:name":"Mille Lacs Hunting Lodge",
    "wof:placetype":"venue"
},
  "geometry": {"coordinates":[-93.592467,46.039709],"type":"Point"}
}