{
  "type": "Feature",
  "properties": {
    "addr:full":"322 2nd St Excelsior MN 55331",
    "addr:housenumber":"322",
    "addr:postcode":"55331",
    "addr:street":"2Nd St",
    "iso:country":"US",
    "sg:address":"322 2nd St",
    "sg:city":"Excelsior",
    "sg:classifiers":[
        {
            "category":"Organizations",
            "subcategory":"Religious Organization",
            "type":"Services"
        }
    ],
    "sg:phone":"+1 952 474 5263",
    "sg:postcode":"55331",
    "sg:province":"MN",
    "sg:website":"www.trinityexcelsior.org",
    "wof:name":"Trinity Episcopal Church",
    "wof:placetype":"venue"
},
  "geometry": {"coordinates":[-93.56720799999999,44.903976],"type":"Point"}
}