{
  "type": "Feature",
  "properties": {
    "iso:country":"US",
    "sg:address":"612 Broadway Ave NE",
    "sg:city":"Red Lake Falls",
    "sg:classifiers":[
        {
            "category":"Shopping",
            "subcategory":"Bicycles & Sporting Goods",
            "type":"Retail Goods"
        }
    ],
    "sg:phone":"+1 218 253 4209",
    "sg:postcode":"56750",
    "sg:province":"MN",
    "sg:tags":[
        "outfitter"
    ],
    "wof:name":"Two Rivers Outfitters",
    "wof:placetype":"venue"
},
  "geometry": {"coordinates":[-96.266734,47.889516],"type":"Point"}
}