{
  "type": "Feature",
  "properties": {
    "iso:country":"US",
    "sg:address":"20230 30th St N",
    "sg:city":"Georgetown",
    "sg:classifiers":[
        {
            "category":"Farming",
            "subcategory":"Livestock Farm",
            "type":"Manufacturing & Wholesale Goods"
        }
    ],
    "sg:phone":"+1 218 861 6579",
    "sg:postcode":"56546",
    "sg:province":"MN",
    "sg:tags":[
        "beef",
        "corn",
        "crop",
        "field",
        "cattle",
        "feedlot"
    ],
    "wof:name":"Alan Loe",
    "wof:placetype":"venue"
},
  "geometry": {"coordinates":[-96.732478,47.140716],"type":"Point"}
}