{
  "type": "Feature",
  "properties": {
    "addr:full":"401 Main Ave W Deer Creek MN 56527",
    "addr:housenumber":"401",
    "addr:postcode":"56527",
    "addr:street":"Main Ave W",
    "iso:country":"US",
    "sg:address":"401 Main Ave W",
    "sg:city":"Deer Creek",
    "sg:classifiers":[
        {
            "category":"Education",
            "subcategory":"School",
            "type":"Public Place"
        }
    ],
    "sg:phone":"+1 218 462 2505",
    "sg:postcode":"56527",
    "sg:province":"MN",
    "sg:website":"www.wdc2155.k12.mn.us",
    "wof:name":"Wadena/Deer Creek School Dist",
    "wof:placetype":"venue"
},
  "geometry": {"coordinates":[-95.327765,46.390924],"type":"Point"}
}