{
  "type": "Feature",
  "properties": {
    "addr:full":"4611 Excelsior Blvd Saint Louis Park MN 55416",
    "addr:housenumber":"4611",
    "addr:postcode":"55416",
    "addr:street":"Excelsior Blvd",
    "iso:country":"US",
    "sg:address":"4611 Excelsior Blvd",
    "sg:city":"Saint Louis Park",
    "sg:classifiers":[
        {
            "category":"Sports & Exercise",
            "subcategory":"Gym",
            "type":"Entertainment"
        }
    ],
    "sg:phone":"+1 612 922 9261",
    "sg:postcode":"55416",
    "sg:province":"MN",
    "sg:tags":[
        "yoga"
    ],
    "sg:website":"www.corepoweryoga.com",
    "wof:name":"Corepower Yoga",
    "wof:placetype":"venue"
},
  "geometry": {"coordinates":[-93.338418,44.933728],"type":"Point"}
}