{
  "type": "Feature",
  "properties": {
    "iso:country":"US",
    "sg:address":"6401 France Ave S",
    "sg:city":"Minneapolis",
    "sg:classifiers":[
        {
            "category":"Shopping",
            "subcategory":"Gifts & Souvenirs",
            "type":"Retail Goods"
        }
    ],
    "sg:phone":"+1 952 924 1344",
    "sg:postcode":"55435",
    "sg:province":"MN",
    "wof:name":"Fairview Southdale Gift Shop",
    "wof:placetype":"venue"
},
  "geometry": {"coordinates":[-93.32894899999999,44.885708],"type":"Point"}
}