{
  "type": "Feature",
  "properties": {
    "addr:full":"9450 Dunkirk Ln N Osseo MN 55311",
    "addr:housenumber":"9450",
    "addr:postcode":"55311",
    "addr:street":"Dunkirk Ln N",
    "iso:country":"US",
    "sg:address":"9450 Dunkirk Ln N",
    "sg:city":"Osseo",
    "sg:classifiers":[
        {
            "category":"Retail",
            "subcategory":"Photofinishing",
            "type":"Services"
        }
    ],
    "sg:phone":"+1 763 425 6674",
    "sg:postcode":"55311",
    "sg:province":"MN",
    "sg:tags":[
        "photo",
        "finishing"
    ],
    "wof:name":"Qualex Inc",
    "wof:placetype":"venue"
},
  "geometry": {"coordinates":[-93.491567,45.125316],"type":"Point"}
}