{
  "type": "Feature",
  "properties": {
    "addr:full":"4323 Woodberry Dr SE Bemidji MN 56601",
    "addr:housenumber":"4323",
    "addr:postcode":"56601",
    "addr:street":"Woodberry Dr Se",
    "iso:country":"US",
    "sg:address":"4323 Woodberry Dr SE",
    "sg:city":"Bemidji",
    "sg:classifiers":[
        {
            "category":"Building & Trades",
            "subcategory":"Construction",
            "type":"Services"
        }
    ],
    "sg:phone":"+1 218 751 4203",
    "sg:postcode":"56601",
    "sg:province":"MN",
    "wof:name":"Storlie Construction Co",
    "wof:placetype":"venue"
},
  "geometry": {"coordinates":[-94.806605,47.414265],"type":"Point"}
}