{
  "type": "Feature",
  "properties": {
    "addr:full":"407 11th Ave SW Forest Lake MN 55025",
    "addr:housenumber":"407",
    "addr:postcode":"55025",
    "addr:street":"11Th Ave Sw Forest",
    "iso:country":"US",
    "sg:address":"407 11th Ave SW",
    "sg:city":"Forest Lake",
    "sg:classifiers":[
        {
            "category":"Building & Trades",
            "subcategory":"Construction",
            "type":"Services"
        }
    ],
    "sg:phone":"+1 651 334 6012",
    "sg:postcode":"55025",
    "sg:province":"MN",
    "sg:tags":[
        "residential"
    ],
    "wof:name":"Rt Exteriors",
    "wof:placetype":"venue"
},
  "geometry": {"coordinates":[-92.988654,45.268509],"type":"Point"}
}