{
  "type": "Feature",
  "properties": {
    "addr:full":"1621 Patricia Dr St Cloud MN 56301",
    "addr:housenumber":"1621",
    "addr:postcode":"56301",
    "addr:street":"Patricia Dr",
    "iso:country":"US",
    "sg:address":"1621 Patricia Dr",
    "sg:city":"St Cloud",
    "sg:classifiers":[
        {
            "category":"Education",
            "subcategory":"Special Training",
            "type":"Public Place"
        }
    ],
    "sg:phone":"+1 320 203 8567",
    "sg:postcode":"56301",
    "sg:province":"MN",
    "sg:tags":[
        "instruction",
        "music"
    ],
    "wof:name":"Professional Music Instruction",
    "wof:placetype":"venue"
},
  "geometry": {"coordinates":[-94.182284,45.54241],"type":"Point"}
}