{
  "type": "Feature",
  "properties": {
    "addr:full":"35 NE 3rd St Cohasset MN 55721",
    "addr:housenumber":"35",
    "addr:postcode":"55721",
    "addr:street":"Ne 3Rd St",
    "iso:country":"US",
    "sg:address":"35 NE 3rd St",
    "sg:city":"Cohasset",
    "sg:classifiers":[
        {
            "category":"Recreation",
            "type":"Entertainment"
        }
    ],
    "sg:phone":"+1 218 328 5802",
    "sg:postcode":"55721",
    "sg:province":"MN",
    "sg:tags":[
        "instruction",
        "gymnastic"
    ],
    "wof:name":"Northern Pike Gymnastics",
    "wof:placetype":"venue"
},
  "geometry": {"coordinates":[-93.617971,47.263972],"type":"Point"}
}