{
  "type": "Feature",
  "properties": {
    "addr:full":"121 Main Ave N Braham MN 55006",
    "addr:housenumber":"121",
    "addr:postcode":"55006",
    "addr:street":"Main Ave N",
    "iso:country":"US",
    "sg:address":"121 Main Ave N",
    "sg:city":"Braham",
    "sg:classifiers":[
        {
            "category":"Real Estate",
            "subcategory":"Real Estate Services",
            "type":"Services"
        },
        {
            "category":"Banks & Credit Unions",
            "subcategory":"Bank",
            "type":"Services"
        },
        {
            "category":"Banks & Credit Unions",
            "subcategory":"Financial Services",
            "type":"Services"
        }
    ],
    "sg:phone":"+1 320 396 3377",
    "sg:postcode":"55006",
    "sg:province":"MN",
    "sg:tags":[
        "commercial",
        "loan",
        "saving"
    ],
    "sg:website":"http://www.brahambank.com",
    "wof:name":"Rural American Bank",
    "wof:placetype":"venue"
},
  "geometry": {"coordinates":[-93.170571,45.724807],"type":"Point"}
}