{
  "type": "Feature",
  "properties": {
    "addr:full":"1973 W Co Rd C Saint Paul MN 55113",
    "addr:housenumber":"1973",
    "addr:postcode":"55113",
    "addr:street":"W Co Rd C",
    "iso:country":"US",
    "sg:address":"1973 W Co Rd C",
    "sg:city":"Saint Paul",
    "sg:classifiers":[
        {
            "category":"Manufacturing",
            "subcategory":"Printing",
            "type":"Manufacturing & Wholesale Goods"
        }
    ],
    "sg:phone":"+1 651 633 2411",
    "sg:postcode":"55113",
    "sg:province":"MN",
    "sg:tags":[
        "commercial",
        "mailing",
        "offset"
    ],
    "wof:name":"Ink Well The",
    "wof:placetype":"venue"
},
  "geometry": {"coordinates":[-93.183255,45.02089],"type":"Point"}
}