{
  "type": "Feature",
  "properties": {
    "iso:country":"US",
    "sg:address":"100 S 5th St Ste 1900",
    "sg:city":"Minneapolis",
    "sg:classifiers":[
        {
            "category":"Professional",
            "subcategory":"Business Services",
            "type":"Services"
        }
    ],
    "sg:phone":"+1 612 746 5070",
    "sg:postcode":"55402",
    "sg:province":"MN",
    "sg:tags":[
        "management"
    ],
    "wof:name":"Antenna",
    "wof:placetype":"venue"
},
  "geometry": {"coordinates":[-93.269302,44.978222],"type":"Point"}
}