{
  "type": "Feature",
  "properties": {
    "addr:full":"35432 Moonshine Ln Pequot Lakes MN 56472",
    "addr:postcode":"35432;56472",
    "addr:street":"Moonshine Ln",
    "iso:country":"US",
    "sg:address":"35432 Moonshine Ln",
    "sg:city":"Pequot Lakes",
    "sg:classifiers":[
        {
            "category":"Professional",
            "type":"Services"
        }
    ],
    "sg:phone":"+1 218 543 4438",
    "sg:postcode":"56472",
    "sg:province":"MN",
    "sg:tags":[
        "establishment"
    ],
    "wof:name":"Pine Cone Group",
    "wof:placetype":"venue"
},
  "geometry": {"coordinates":[-94.256744,46.666643],"type":"Point"}
}