{
  "type": "Feature",
  "properties": {
    "addr:full":"446 E Main St Perham MN 56573",
    "addr:housenumber":"446",
    "addr:postcode":"56573",
    "addr:street":"E Main St",
    "iso:country":"US",
    "sg:address":"446 E Main St",
    "sg:city":"Perham",
    "sg:classifiers":[
        {
            "category":"Social Services",
            "subcategory":"Child Care",
            "type":"Services"
        }
    ],
    "sg:phone":"+1 218 346 4077",
    "sg:postcode":"56573",
    "sg:province":"MN",
    "sg:tags":[
        "daycare",
        "provider"
    ],
    "wof:name":"Kathys Day Care",
    "wof:placetype":"venue"
},
  "geometry": {"coordinates":[-95.56904400000001,46.591845],"type":"Point"}
}