{
  "type": "Feature",
  "properties": {
    "addr:full":"1972 495th St W Stanchfield MN 55080",
    "addr:housenumber":"1972",
    "addr:postcode":"55080",
    "addr:street":"495Th St W Stanchfield",
    "iso:country":"US",
    "sg:address":"1972 495th St W",
    "sg:city":"Stanchfield",
    "sg:classifiers":[
        {
            "category":"Farming",
            "subcategory":"Dairy Farm",
            "type":"Manufacturing & Wholesale Goods"
        }
    ],
    "sg:phone":"+1 320 396 2409",
    "sg:postcode":"55080",
    "sg:province":"MN",
    "wof:name":"Harold Eklund",
    "wof:placetype":"venue"
},
  "geometry": {"coordinates":[-93.134902,45.666052],"type":"Point"}
}