{
  "type": "Feature",
  "properties": {
    "iso:country":"US",
    "sg:address":"7562 Murphy Lake Rd",
    "sg:city":"Eveleth",
    "sg:classifiers":[
        {
            "category":"Government",
            "subcategory":"Fire Station",
            "type":"Public Place"
        }
    ],
    "sg:phone":"+1 218 744 3625",
    "sg:postcode":"55734",
    "sg:province":"MN",
    "sg:tags":[
        "department"
    ],
    "wof:name":"Central Lakes Fire Department",
    "wof:placetype":"venue"
},
  "geometry": {"coordinates":[-92.485107,47.306374],"type":"Point"}
}