{
  "type": "Feature",
  "properties": {
    "iso:country":"US",
    "sg:address":"275 33rd St W",
    "sg:city":"Hastings",
    "sg:classifiers":[
        {
            "category":"Sports & Exercise",
            "subcategory":"Gym",
            "type":"Entertainment"
        }
    ],
    "sg:phone":"+1 651 480 7981",
    "sg:postcode":"55033",
    "sg:province":"MN",
    "sg:tags":[
        "fitness",
        "physical",
        "facility"
    ],
    "wof:name":"It Figures",
    "wof:placetype":"venue"
},
  "geometry": {"coordinates":[-92.84840699999999,44.715228],"type":"Point"}
}