{
  "type": "Feature",
  "properties": {
    "iso:country":"US",
    "sg:address":"11995 Singletree Ln",
    "sg:city":"Eden Prairie",
    "sg:classifiers":[
        {
            "category":"Education",
            "subcategory":"Vocational School",
            "type":"Public Place"
        }
    ],
    "sg:phone":"+1 952 944 0080",
    "sg:postcode":"55344",
    "sg:province":"MN",
    "wof:name":"N T I",
    "wof:placetype":"venue"
},
  "geometry": {"coordinates":[-93.43046099999999,44.856845],"type":"Point"}
}