{
  "type": "Feature",
  "properties": {
    "iso:country":"US",
    "sg:address":"2327 27th Ave S",
    "sg:city":"Minneapolis",
    "sg:classifiers":[
        {
            "category":"Building & Trades",
            "subcategory":"Landscaping Services",
            "type":"Services"
        }
    ],
    "sg:phone":"+1 612 728 7221",
    "sg:postcode":"55406",
    "sg:province":"MN",
    "wof:name":"Western John Michael",
    "wof:placetype":"venue"
},
  "geometry": {"coordinates":[-93.232952,44.959934],"type":"Point"}
}