{
  "type": "Feature",
  "properties": {
    "addr:full":"6501 Radar Rd NW Bemidji MN 56601",
    "addr:housenumber":"6501",
    "addr:postcode":"56601",
    "addr:street":"Radar Rd Nw",
    "iso:country":"US",
    "sg:address":"6501 Radar Rd NW",
    "sg:city":"Bemidji",
    "sg:classifiers":[
        {
            "category":"Building & Trades",
            "subcategory":"Construction",
            "type":"Services"
        }
    ],
    "sg:phone":"+1 218 759 1734",
    "sg:postcode":"56601",
    "sg:province":"MN",
    "sg:tags":[
        "hanging",
        "contractor"
    ],
    "wof:name":"Tolman Painting & Wall Co",
    "wof:placetype":"venue"
},
  "geometry": {"coordinates":[-94.977397,47.571003],"type":"Point"}
}