{
  "type": "Feature",
  "properties": {
    "addr:full":"325 NW 2nd St Mcintosh MN 56556",
    "addr:housenumber":"325",
    "addr:postcode":"56556",
    "addr:street":"Nw 2Nd St",
    "iso:country":"US",
    "sg:address":"325 NW 2nd St",
    "sg:city":"Mcintosh",
    "sg:classifiers":[
        {
            "category":"Arts & Performance",
            "subcategory":"Theater",
            "type":"Entertainment"
        }
    ],
    "sg:phone":"+1 218 563 2480",
    "sg:postcode":"56556",
    "sg:province":"MN",
    "sg:tags":[
        "live",
        "music"
    ],
    "wof:name":"Sundown DJ Entertainment",
    "wof:placetype":"venue"
},
  "geometry": {"coordinates":[-95.890356,47.637826],"type":"Point"}
}