{
  "type": "Feature",
  "properties": {
    "addr:full":"9 Main St W Waconia MN 55387",
    "addr:housenumber":"9",
    "addr:postcode":"55387",
    "addr:street":"Main St W Waconia",
    "iso:country":"US",
    "sg:address":"9 Main St W",
    "sg:city":"Waconia",
    "sg:classifiers":[
        {
            "category":"Professional",
            "type":"Services"
        }
    ],
    "sg:phone":"+1 952 442 9760",
    "sg:postcode":"55387",
    "sg:province":"MN",
    "sg:tags":[
        "establishment"
    ],
    "wof:name":"K A Carlson LTD",
    "wof:placetype":"venue"
},
  "geometry": {"coordinates":[-93.787497,44.850366],"type":"Point"}
}