{
  "type": "Feature",
  "properties": {
    "iso:country":"US",
    "sg:address":"730 Washington Ave N",
    "sg:city":"Minneapolis",
    "sg:classifiers":[
        {
            "category":"Manufacturing",
            "subcategory":"Printing",
            "type":"Manufacturing & Wholesale Goods"
        }
    ],
    "sg:phone":"+1 612 672 0748",
    "sg:postcode":"55401",
    "sg:province":"MN",
    "sg:tags":[
        "miniature",
        "folding"
    ],
    "wof:name":"Folding Specialists Inc",
    "wof:placetype":"venue"
},
  "geometry": {"coordinates":[-93.278218,44.988457],"type":"Point"}
}