{
  "type": "Feature",
  "properties": {
    "addr:full":"1750 Excelsior Rd N Baxter MN 56425",
    "addr:housenumber":"1750",
    "addr:postcode":"56425",
    "addr:street":"Excelsior Rd N",
    "iso:country":"US",
    "sg:address":"1750 Excelsior Rd N",
    "sg:city":"Baxter",
    "sg:classifiers":[
        {
            "category":"Insurance",
            "subcategory":"Insurance Agent",
            "type":"Services"
        }
    ],
    "sg:phone":"+1 218 829 8728",
    "sg:postcode":"56425",
    "sg:province":"MN",
    "wof:name":"State Farm Insurance",
    "wof:placetype":"venue"
},
  "geometry": {"coordinates":[-94.24321999999999,46.35454],"type":"Point"}
}