{
  "type": "Feature",
  "properties": {
    "iso:country":"US",
    "sg:address":"33532 Star Lake Dr",
    "sg:city":"Dent",
    "sg:classifiers":[
        {
            "category":"Professional",
            "type":"Services"
        }
    ],
    "sg:phone":"+1 218 758 2798",
    "sg:postcode":"56528",
    "sg:province":"MN",
    "sg:tags":[
        "establishment"
    ],
    "wof:name":"Nyquist & Nyquist",
    "wof:placetype":"venue"
},
  "geometry": {"coordinates":[-95.79643299999999,46.54275],"type":"Point"}
}