{
  "type": "Feature",
  "properties": {
    "addr:full":"1517 8th St S Virginia MN 55792",
    "addr:housenumber":"1517",
    "addr:postcode":"55792",
    "addr:street":"8Th St S",
    "iso:country":"US",
    "sg:address":"1517 8th St S",
    "sg:city":"Virginia",
    "sg:classifiers":[
        {
            "category":"Retail",
            "subcategory":"Animal Services",
            "type":"Services"
        }
    ],
    "sg:phone":"+1 218 749 4335",
    "sg:postcode":"55792",
    "sg:province":"MN",
    "wof:name":"Iron Range Dog Training",
    "wof:placetype":"venue"
},
  "geometry": {"coordinates":[-92.55926599999999,47.516471],"type":"Point"}
}