{
  "type": "Feature",
  "properties": {
    "addr:full":"206 14th St N Benson MN 56215",
    "addr:housenumber":"206",
    "addr:postcode":"56215",
    "addr:street":"14Th St N",
    "iso:country":"US",
    "sg:address":"206 14th St N",
    "sg:city":"Benson",
    "sg:classifiers":[
        {
            "category":"Restaurant",
            "type":"Food & Drink"
        }
    ],
    "sg:menulink":"http://www.allmenus.com/mn/benson/190773-burger-king/menu/",
    "sg:phone":"+1 320 843 2505",
    "sg:postcode":"56215",
    "sg:province":"MN",
    "sg:tags":[
        "burger",
        "american"
    ],
    "wof:name":"Burger King",
    "wof:placetype":"venue"
},
  "geometry": {"coordinates":[-95.60096799999999,45.316107],"type":"Point"}
}