{
  "type": "Feature",
  "properties": {
    "iso:country":"US",
    "sg:address":"61334 470th St",
    "sg:city":"Sebeka",
    "sg:classifiers":[
        {
            "category":"Farming",
            "subcategory":"Dairy Farm",
            "type":"Manufacturing & Wholesale Goods"
        }
    ],
    "sg:phone":"+1 218 837 5493",
    "sg:postcode":"56477",
    "sg:province":"MN",
    "wof:name":"Jeremy Hultberg",
    "wof:placetype":"venue"
},
  "geometry": {"coordinates":[-95.20984199999999,46.644214],"type":"Point"}
}