{
  "type": "Feature",
  "properties": {
    "iso:country":"US",
    "sg:address":"14201 Grand Ave",
    "sg:city":"Burnsville",
    "sg:classifiers":[
        {
            "category":"Banks & Credit Unions",
            "subcategory":"Bank",
            "type":"Services"
        }
    ],
    "sg:phone":"+1 952 435 3036",
    "sg:postcode":"55337",
    "sg:province":"MN",
    "wof:name":"Richfield Bank",
    "wof:placetype":"venue"
},
  "geometry": {"coordinates":[-93.280998,44.7463],"type":"Point"}
}