{
  "type": "Feature",
  "properties": {
    "iso:country":"US",
    "sg:address":"202 North St",
    "sg:city":"Elmore",
    "sg:classifiers":[
        {
            "category":"Social Services",
            "type":"Services"
        }
    ],
    "sg:phone":"+1 507 943 3440",
    "sg:postcode":"56027",
    "sg:province":"MN",
    "sg:tags":[
        "government"
    ],
    "wof:name":"Elmore Academy Youth Svc",
    "wof:placetype":"venue"
},
  "geometry": {"coordinates":[-94.085713,43.507168],"type":"Point"}
}