{
  "type": "Feature",
  "properties": {
    "addr:full":"200 Grand Ave St Paul MN 55102",
    "addr:housenumber":"200",
    "addr:postcode":"55102",
    "addr:street":"Grand Ave",
    "iso:country":"US",
    "sg:address":"200 Grand Ave",
    "sg:city":"St Paul",
    "sg:classifiers":[
        {
            "category":"Building & Trades",
            "subcategory":"Construction",
            "type":"Services"
        },
        {
            "category":"Professional",
            "subcategory":"Management & Consulting",
            "type":"Services"
        }
    ],
    "sg:phone":"+1 651 291 7088",
    "sg:postcode":"55102",
    "sg:province":"MN",
    "sg:tags":[
        "nonresidential"
    ],
    "wof:name":"Kraus-Anderson Construction Co",
    "wof:placetype":"venue"
},
  "geometry": {"coordinates":[-93.10667599999999,44.941368],"type":"Point"}
}