{
  "type": "Feature",
  "properties": {
    "addr:full":"3336 Noble Ave N Minneapolis MN 55422",
    "addr:housenumber":"3336",
    "addr:postcode":"55422",
    "addr:street":"Noble Ave N",
    "iso:country":"US",
    "sg:address":"3336 Noble Ave N",
    "sg:city":"Minneapolis",
    "sg:classifiers":[
        {
            "category":"Retail",
            "subcategory":"Portrait Studio",
            "type":"Services"
        }
    ],
    "sg:phone":"+1 763 588 8177",
    "sg:postcode":"55422",
    "sg:province":"MN",
    "sg:tags":[
        "photo"
    ],
    "wof:name":"Fontanaland Photography",
    "wof:placetype":"venue"
},
  "geometry": {"coordinates":[-93.338724,45.016493],"type":"Point"}
}