{
  "type": "Feature",
  "properties": {
    "iso:country":"US",
    "sg:address":"836 Lake St S",
    "sg:city":"Forest Lake",
    "sg:classifiers":[
        {
            "category":"Shopping",
            "subcategory":"Bicycles & Sporting Goods",
            "type":"Retail Goods"
        }
    ],
    "sg:phone":"+1 651 464 5664",
    "sg:postcode":"55025",
    "sg:province":"MN",
    "wof:name":"Trail Cycle",
    "wof:placetype":"venue"
},
  "geometry": {"coordinates":[-92.98366300000001,45.270413],"type":"Point"}
}