{
  "type": "Feature",
  "properties": {
    "iso:country":"US",
    "sg:address":"525 18th St E",
    "sg:city":"Glencoe",
    "sg:classifiers":[
        {
            "category":"Health Services",
            "subcategory":"Doctor",
            "type":"Services"
        }
    ],
    "sg:phone":"+1 320 864 3116",
    "sg:postcode":"55336",
    "sg:province":"MN",
    "sg:tags":[
        "medical",
        "clinic"
    ],
    "wof:name":"Glencoe Regional Health Svcs",
    "wof:placetype":"venue"
},
  "geometry": {"coordinates":[-94.154871,44.7775],"type":"Point"}
}