{
  "type": "Feature",
  "properties": {
    "iso:country":"US",
    "sg:address":"12 6th St S",
    "sg:city":"Minneapolis",
    "sg:classifiers":[
        {
            "category":"Professional",
            "subcategory":"Business Services",
            "type":"Services"
        }
    ],
    "sg:phone":"+1 612 672 9141",
    "sg:postcode":"55402",
    "sg:province":"MN",
    "sg:tags":[
        "clipping",
        "bureau"
    ],
    "sg:website":"www.burrellesluce.com",
    "wof:name":"Minnesota Clipping Service",
    "wof:placetype":"venue"
},
  "geometry": {"coordinates":[-93.272274,44.97845],"type":"Point"}
}