{
  "type": "Feature",
  "properties": {
    "addr:full":"117 S Jackson St Houston MN 55943",
    "addr:housenumber":"117",
    "addr:postcode":"55943",
    "addr:street":"S Jackson St",
    "iso:country":"US",
    "sg:address":"117 S Jackson St",
    "sg:city":"Houston",
    "sg:classifiers":[
        {
            "category":"Travel",
            "subcategory":"Hotels & Motels",
            "type":"Entertainment"
        }
    ],
    "sg:phone":"+1 507 896 3010",
    "sg:postcode":"55943",
    "sg:province":"MN",
    "sg:tags":[
        "breakfast",
        "accommodation",
        "bed"
    ],
    "wof:name":"Addie's Attic",
    "wof:placetype":"venue"
},
  "geometry": {"coordinates":[-91.571848,43.763012],"type":"Point"}
}