{
  "type": "Feature",
  "properties": {
    "addr:full":"15060 50th St S Moorhead MN 56560",
    "addr:housenumber":"15060",
    "addr:postcode":"56560",
    "addr:street":"50Th St S",
    "iso:country":"US",
    "sg:address":"15060 50th St S",
    "sg:city":"Moorhead",
    "sg:phone":"+1 218 585 4187",
    "sg:postcode":"56560",
    "sg:province":"MN",
    "sg:tags":[
        "farm",
        "beet"
    ],
    "wof:name":"Brandt Farms",
    "wof:placetype":"venue"
},
  "geometry": {"coordinates":[-96.694959,46.673349],"type":"Point"}
}