{
  "type": "Feature",
  "properties": {
    "addr:full":"16709 325th St Red Wing MN 55066",
    "addr:housenumber":"16709",
    "addr:postcode":"55066",
    "addr:street":"325Th St",
    "iso:country":"US",
    "sg:address":"16709 325th St",
    "sg:city":"Red Wing",
    "sg:classifiers":[
        {
            "category":"Building & Trades",
            "subcategory":"Electrical",
            "type":"Services"
        }
    ],
    "sg:phone":"+1 651 258 4152",
    "sg:postcode":"55066",
    "sg:province":"MN",
    "sg:tags":[
        "electrical",
        "electric",
        "contractor"
    ],
    "wof:name":"Ringeisen Electric LLC",
    "wof:placetype":"venue"
},
  "geometry": {"coordinates":[-92.69316999999999,44.478296],"type":"Point"}
}