{
  "type": "Feature",
  "properties": {
    "addr:full":"16360 Harvard Dr Lakeville MN 55044",
    "addr:housenumber":"16360",
    "addr:postcode":"55044",
    "addr:street":"Harvard Dr",
    "iso:country":"US",
    "sg:address":"16360 Harvard Dr",
    "sg:city":"Lakeville",
    "sg:classifiers":[
        {
            "category":"Manufacturing",
            "subcategory":"Textiles",
            "type":"Manufacturing & Wholesale Goods"
        }
    ],
    "sg:phone":"+1 952 997 6117",
    "sg:postcode":"55044",
    "sg:province":"MN",
    "sg:tags":[
        "mill",
        "fabric",
        "cotton"
    ],
    "wof:name":"Cienna Prints",
    "wof:placetype":"venue"
},
  "geometry": {"coordinates":[-93.230599,44.712171],"type":"Point"}
}