{
  "type": "Feature",
  "properties": {
    "addr:full":"130 Main St S Hector MN 55342",
    "addr:housenumber":"130",
    "addr:postcode":"55342",
    "addr:street":"Main St S Hector",
    "iso:country":"US",
    "sg:address":"130 Main St S",
    "sg:city":"Hector",
    "sg:classifiers":[
        {
            "category":"Recreation",
            "type":"Entertainment"
        }
    ],
    "sg:phone":"+1 320 848 2710",
    "sg:postcode":"55342",
    "sg:province":"MN",
    "sg:tags":[
        "center"
    ],
    "wof:name":"Hector Community Building",
    "wof:placetype":"venue"
},
  "geometry": {"coordinates":[-94.715271,44.744703],"type":"Point"}
}