{
  "type": "Feature",
  "properties": {
    "addr:full":"18091 Aztec St NW Anoka MN 55304",
    "addr:housenumber":"18091",
    "addr:postcode":"55304",
    "addr:street":"Aztec St Nw",
    "iso:country":"US",
    "sg:address":"18091 Aztec St NW",
    "sg:city":"Anoka",
    "sg:classifiers":[
        {
            "category":"Professional",
            "subcategory":"Advertising",
            "type":"Services"
        }
    ],
    "sg:phone":"+1 763 753 9447",
    "sg:postcode":"55304",
    "sg:province":"MN",
    "sg:tags":[
        "mail",
        "direct"
    ],
    "wof:name":"Card Mailers",
    "wof:placetype":"venue"
},
  "geometry": {"coordinates":[-93.363479,45.298377],"type":"Point"}
}