{
  "type": "Feature",
  "properties": {
    "addr:full":"47281 210th St Sanborn MN 56083",
    "addr:housenumber":"47281",
    "addr:postcode":"56083",
    "addr:street":"210Th St",
    "iso:country":"US",
    "sg:address":"47281 210th St",
    "sg:city":"Sanborn",
    "sg:classifiers":[
        {
            "category":"Retail",
            "subcategory":"Animal Services",
            "type":"Services"
        }
    ],
    "sg:phone":"+1 507 833 0015",
    "sg:postcode":"56083",
    "sg:province":"MN",
    "wof:name":"Clip N Care Dog Stylist",
    "wof:placetype":"venue"
},
  "geometry": {"coordinates":[-95.135831,44.180634],"type":"Point"}
}