{
  "type": "Feature",
  "properties": {
    "iso:country":"US",
    "sg:address":"5600 Pioneer Creek Dr",
    "sg:city":"Maple Plain",
    "sg:classifiers":[
        {
            "category":"Professional",
            "subcategory":"Computer Services",
            "type":"Services"
        }
    ],
    "sg:phone":"+1 763 479 0769",
    "sg:postcode":"55359",
    "sg:province":"MN",
    "sg:tags":[
        "consultant",
        "designer"
    ],
    "wof:name":"MCH Technology",
    "wof:placetype":"venue"
},
  "geometry": {"coordinates":[-93.666213,45.011981],"type":"Point"}
}