{
  "type": "Feature",
  "properties": {
    "addr:full":"4410 Beard Ave S Minneapolis MN 55410",
    "addr:housenumber":"4410",
    "addr:postcode":"55410",
    "addr:street":"Beard Ave S",
    "iso:country":"US",
    "sg:address":"4410 Beard Ave S",
    "sg:city":"Minneapolis",
    "sg:classifiers":[
        {
            "category":"Professional",
            "subcategory":"Lawyer & Legal Services",
            "type":"Services"
        }
    ],
    "sg:phone":"+1 952 920 0216",
    "sg:postcode":"55410",
    "sg:province":"MN",
    "wof:name":"Richard S Baker",
    "wof:placetype":"venue"
},
  "geometry": {"coordinates":[-93.324071,44.9217],"type":"Point"}
}