{
  "type": "Feature",
  "properties": {
    "addr:full":"11857 Norway St NW Coon Rapids MN 55448",
    "addr:housenumber":"11857",
    "addr:postcode":"55448",
    "addr:street":"Norway St Nw",
    "iso:country":"US",
    "sg:address":"11857 Norway St NW",
    "sg:city":"Coon Rapids",
    "sg:classifiers":[
        {
            "category":"Retail",
            "subcategory":"Repair Shop",
            "type":"Services"
        },
        {
            "category":"Shopping",
            "subcategory":"Computers & Home Electronics",
            "type":"Retail Goods"
        }
    ],
    "sg:phone":"+1 763 754 1193",
    "sg:postcode":"55448",
    "sg:province":"MN",
    "sg:tags":[
        "equipment",
        "satellite",
        "system"
    ],
    "wof:name":"Lennys T V & Video Repair",
    "wof:placetype":"venue"
},
  "geometry": {"coordinates":[-93.28590199999999,45.185141],"type":"Point"}
}