{
  "type": "Feature",
  "properties": {
    "addr:full":"880 Hwy 10 S Motley MN 56466",
    "addr:housenumber":"880",
    "addr:postcode":"56466",
    "addr:street":"Hwy 10 S",
    "iso:country":"US",
    "sg:address":"880 Hwy 10 S",
    "sg:city":"Motley",
    "sg:classifiers":[
        {
            "category":"Restaurant",
            "type":"Food & Drink"
        }
    ],
    "sg:phone":"+1 218 352 6777",
    "sg:postcode":"56466",
    "sg:province":"MN",
    "wof:name":"Countryside Restaurant",
    "wof:placetype":"venue"
},
  "geometry": {"coordinates":[-94.64766400000001,46.32854],"type":"Point"}
}