{
  "type": "Feature",
  "properties": {
    "addr:full":"9001 E Bloomington Fwy Bloomington MN 55420",
    "addr:housenumber":"9001",
    "addr:postcode":"55420",
    "addr:street":"E Bloomington Fwy",
    "iso:country":"US",
    "sg:address":"9001 E Bloomington Fwy",
    "sg:city":"Bloomington",
    "sg:classifiers":[
        {
            "category":"Professional",
            "subcategory":"Lawyer & Legal Services",
            "type":"Services"
        }
    ],
    "sg:phone":"+1 952 888 0090",
    "sg:postcode":"55420",
    "sg:province":"MN",
    "sg:tags":[
        "attorney"
    ],
    "wof:name":"James E Schaefer",
    "wof:placetype":"venue"
},
  "geometry": {"coordinates":[-93.29687699999999,44.837137],"type":"Point"}
}