{
  "type": "Feature",
  "properties": {
    "addr:full":"2660 Cleveland Ave N Saint Paul MN 55113",
    "addr:housenumber":"2660",
    "addr:postcode":"55113",
    "addr:street":"Cleveland Ave N",
    "iso:country":"US",
    "sg:address":"2660 Cleveland Ave N",
    "sg:city":"Saint Paul",
    "sg:classifiers":[
        {
            "category":"Professional",
            "subcategory":"Employment Agencies",
            "type":"Services"
        }
    ],
    "sg:phone":"+1 651 633 7090",
    "sg:postcode":"55113",
    "sg:province":"MN",
    "sg:tags":[
        "help",
        "supply"
    ],
    "wof:name":"Prodrivers",
    "wof:placetype":"venue"
},
  "geometry": {"coordinates":[-93.187253,45.021346],"type":"Point"}
}