{
  "type": "Feature",
  "properties": {
    "addr:full":"41331 331st Ave Laporte MN 56461",
    "addr:housenumber":"41331",
    "addr:postcode":"56461",
    "addr:street":"331St Ave",
    "iso:country":"US",
    "sg:address":"41331 331st Ave",
    "sg:city":"Laporte",
    "sg:classifiers":[
        {
            "category":"Professional",
            "subcategory":"Business Services",
            "type":"Services"
        }
    ],
    "sg:phone":"+1 218 224 2639",
    "sg:postcode":"56461",
    "sg:province":"MN",
    "wof:name":"Linda Frizzell",
    "wof:placetype":"venue"
},
  "geometry": {"coordinates":[-94.674313,47.25675],"type":"Point"}
}