{
  "type": "Feature",
  "properties": {
    "addr:full":"445 24th Ave N St Cloud MN 56303",
    "addr:housenumber":"445",
    "addr:postcode":"56303",
    "addr:street":"24Th Ave N",
    "iso:country":"US",
    "sg:address":"445 24th Ave N",
    "sg:city":"St Cloud",
    "sg:classifiers":[
        {
            "category":"Personal",
            "subcategory":"Beauty Salon",
            "type":"Services"
        }
    ],
    "sg:phone":"+1 320 259 0355",
    "sg:postcode":"56303",
    "sg:province":"MN",
    "sg:tags":[
        "shop"
    ],
    "wof:name":"Under Cut",
    "wof:placetype":"venue"
},
  "geometry": {"coordinates":[-94.18662500000001,45.561362],"type":"Point"}
}