{
  "type": "Feature",
  "properties": {
    "addr:full":"1635 Coon Rapids Blvd NW Ste 210 Minneapolis MN 55433",
    "addr:housenumber":"1635",
    "addr:postcode":"55433",
    "addr:street":"Coon Rapids Blvd Nw Ste 210",
    "iso:country":"US",
    "sg:address":"1635 Coon Rapids Blvd NW Ste 210",
    "sg:city":"Minneapolis",
    "sg:classifiers":[
        {
            "category":"Insurance",
            "subcategory":"Hazard Insurance",
            "type":"Services"
        }
    ],
    "sg:phone":"+1 763 493 2828",
    "sg:postcode":"55433",
    "sg:province":"MN",
    "sg:tags":[
        "commercial",
        "group",
        "business"
    ],
    "wof:name":"Park Grove Agency Inc",
    "wof:placetype":"venue"
},
  "geometry": {"coordinates":[-93.3085,45.156071],"type":"Point"}
}