{
  "type": "Feature",
  "properties": {
    "addr:full":"207 E James Ave Marshall MN 56258",
    "addr:housenumber":"207",
    "addr:postcode":"56258",
    "addr:street":"E James Ave",
    "iso:country":"US",
    "sg:address":"207 E James Ave",
    "sg:city":"Marshall",
    "sg:classifiers":[
        {
            "category":"Retail",
            "subcategory":"Laundry & Dry Cleaning",
            "type":"Services"
        },
        {
            "category":"Retail",
            "subcategory":"Repair Shop",
            "type":"Services"
        }
    ],
    "sg:phone":"+1 507 532 4452",
    "sg:postcode":"56258",
    "sg:province":"MN",
    "sg:tags":[
        "cleaner",
        "rug",
        "carpet"
    ],
    "sg:website":"http://www.chemdry.com",
    "wof:name":"Chem-Dry",
    "wof:placetype":"venue"
},
  "geometry": {"coordinates":[-95.788918,44.438622],"type":"Point"}
}