{
  "type": "Feature",
  "properties": {
    "iso:country":"US",
    "sg:address":"8481 15th St NW",
    "sg:city":"Willmar",
    "sg:classifiers":[
        {
            "category":"Farming",
            "subcategory":"Poultry Farm",
            "type":"Manufacturing & Wholesale Goods"
        }
    ],
    "sg:phone":"+1 320 235 5751",
    "sg:postcode":"56201",
    "sg:province":"MN",
    "sg:tags":[
        "turkey",
        "egg"
    ],
    "wof:name":"Orsten Turkeys Inc",
    "wof:placetype":"venue"
},
  "geometry": {"coordinates":[-95.062506,45.210952],"type":"Point"}
}