{
  "type": "Feature",
  "properties": {
    "iso:country":"US",
    "sg:address":"10275 Greenbrier Rd",
    "sg:city":"Hopkins",
    "sg:classifiers":[
        {
            "category":"Real Estate",
            "subcategory":"Real Estate Operator",
            "type":"Services"
        }
    ],
    "sg:phone":"+1 952 593 1475",
    "sg:postcode":"55305",
    "sg:province":"MN",
    "sg:tags":[
        "building",
        "apartment"
    ],
    "wof:name":"Woodlands Of Minnetonka",
    "wof:placetype":"venue"
},
  "geometry": {"coordinates":[-93.41077199999999,44.952278],"type":"Point"}
}