{
  "type": "Feature",
  "properties": {
    "addr:full":"2137 Sciota Trl W Northfield MN 55057",
    "addr:housenumber":"2137",
    "addr:postcode":"55057",
    "addr:street":"Sciota Trl W",
    "iso:country":"US",
    "sg:address":"2137 Sciota Trl W",
    "sg:city":"Northfield",
    "sg:classifiers":[
        {
            "category":"Professional",
            "subcategory":"Management & Consulting",
            "type":"Services"
        }
    ],
    "sg:phone":"+1 507 645 0245",
    "sg:postcode":"55057",
    "sg:province":"MN",
    "wof:name":"Navigant Consulting Inc",
    "wof:placetype":"venue"
},
  "geometry": {"coordinates":[-93.10743100000001,44.493423],"type":"Point"}
}