{
  "type": "Feature",
  "properties": {
    "iso:country":"US",
    "sg:address":"1161 170th St",
    "sg:city":"Welcome",
    "sg:phone":"+1 507 728 8798",
    "sg:postcode":"56181",
    "sg:province":"MN",
    "sg:tags":[
        "farm",
        "grain",
        "cash"
    ],
    "wof:name":"Loren Kuehl",
    "wof:placetype":"venue"
},
  "geometry": {"coordinates":[-94.641531,43.732293],"type":"Point"}
}