{
  "type": "Feature",
  "properties": {
    "addr:full":"313 W Main St Marshall MN 56258",
    "addr:housenumber":"313",
    "addr:postcode":"56258",
    "addr:street":"W Main St",
    "iso:country":"US",
    "sg:address":"313 W Main St",
    "sg:city":"Marshall",
    "sg:classifiers":[
        {
            "category":"Shopping",
            "subcategory":"Books",
            "type":"Retail Goods"
        }
    ],
    "sg:phone":"+1 507 537 4000",
    "sg:postcode":"56258",
    "sg:province":"MN",
    "wof:name":"Once Upon A Time Scrapbook Sup",
    "wof:placetype":"venue"
},
  "geometry": {"coordinates":[-95.790949,44.448424],"type":"Point"}
}