{
  "type": "Feature",
  "properties": {
    "iso:country":"US",
    "sg:address":"1711 18th St NE",
    "sg:city":"Willmar",
    "sg:classifiers":[
        {
            "category":"Professional",
            "subcategory":"Computer Services",
            "type":"Services"
        },
        {
            "category":"Wholesale",
            "subcategory":"Computers",
            "type":"Manufacturing & Wholesale Goods"
        }
    ],
    "sg:phone":"+1 320 235 8880",
    "sg:postcode":"56201",
    "sg:province":"MN",
    "sg:tags":[
        "equipment",
        "cd-rom",
        "software"
    ],
    "wof:name":"MidWest Data",
    "wof:placetype":"venue"
},
  "geometry": {"coordinates":[-95.016357,45.141121],"type":"Point"}
}