{
  "type": "Feature",
  "properties": {
    "addr:full":"515 10th St Worthington MN 56187",
    "addr:housenumber":"515",
    "addr:postcode":"56187",
    "addr:street":"10Th St",
    "iso:country":"US",
    "sg:address":"515 10th St",
    "sg:city":"Worthington",
    "sg:classifiers":[
        {
            "category":"Health Services",
            "subcategory":"Doctor",
            "type":"Services"
        }
    ],
    "sg:phone":"+1 507 376 5665",
    "sg:postcode":"56187",
    "sg:province":"MN",
    "sg:tags":[
        "physician",
        "surgeon"
    ],
    "wof:name":"Iowa Lakes Orthopaedics",
    "wof:placetype":"venue"
},
  "geometry": {"coordinates":[-95.599074,43.621753],"type":"Point"}
}