{
  "type": "Feature",
  "properties": {
    "addr:full":"511 2nd Ave NW Rochester MN 55901",
    "addr:housenumber":"511",
    "addr:postcode":"55901",
    "addr:street":"2Nd Ave Nw",
    "iso:country":"US",
    "sg:address":"511 2nd Ave NW",
    "sg:city":"Rochester",
    "sg:classifiers":[
        {
            "category":"Retail",
            "subcategory":"Auto Repair",
            "type":"Services"
        }
    ],
    "sg:phone":"+1 507 281 3362",
    "sg:postcode":"55901",
    "sg:province":"MN",
    "sg:tags":[
        "repairing",
        "automobile"
    ],
    "wof:name":"B & H Auto Svc",
    "wof:placetype":"venue"
},
  "geometry": {"coordinates":[-92.465974,44.02935],"type":"Point"}
}