{
  "type": "Feature",
  "properties": {
    "iso:country":"US",
    "sg:address":"2939 Bunker Lake Blvd NW",
    "sg:city":"Andover",
    "sg:classifiers":[
        {
            "category":"Education",
            "subcategory":"School",
            "type":"Public Place"
        }
    ],
    "sg:phone":"+1 763 506 2100",
    "sg:postcode":"55304",
    "sg:province":"MN",
    "wof:name":"Crooked Lake Elementary School",
    "wof:placetype":"venue"
},
  "geometry": {"coordinates":[-93.34085899999999,45.219711],"type":"Point"}
}