{
  "type": "Feature",
  "properties": {
    "addr:full":"4735 123rd St W Savage MN 55378",
    "addr:housenumber":"4735",
    "addr:postcode":"55378",
    "addr:street":"123Rd St W",
    "iso:country":"US",
    "sg:address":"4735 123rd St W",
    "sg:city":"Savage",
    "sg:classifiers":[
        {
            "category":"Real Estate",
            "subcategory":"Surveying",
            "type":"Services"
        }
    ],
    "sg:phone":"+1 952 895 9212",
    "sg:postcode":"55378",
    "sg:province":"MN",
    "sg:tags":[
        "surveyor"
    ],
    "wof:name":"Bohlen Land Surveying Inc",
    "wof:placetype":"venue"
},
  "geometry": {"coordinates":[-93.33877699999999,44.778337],"type":"Point"}
}