{
  "type": "Feature",
  "properties": {
    "addr:full":"9970 Co Rd 81 Osseo MN 55369",
    "addr:housenumber":"9970;81",
    "addr:postcode":"55369",
    "addr:street":"Co Rd",
    "iso:country":"US",
    "sg:address":"9970 Co Rd 81",
    "sg:city":"Osseo",
    "sg:classifiers":[
        {
            "category":"Banks & Credit Unions",
            "subcategory":"Investment Brokerage",
            "type":"Services"
        }
    ],
    "sg:phone":"+1 763 424 2756",
    "sg:postcode":"55369",
    "sg:province":"MN",
    "sg:tags":[
        "advisory",
        "financial"
    ],
    "wof:name":"Midwest Financial Processing",
    "wof:placetype":"venue"
},
  "geometry": {"coordinates":[-93.41087,45.119008],"type":"Point"}
}