{
  "type": "Feature",
  "properties": {
    "iso:country":"US",
    "sg:address":"400 Richmond St E",
    "sg:city":"South St Paul",
    "sg:classifiers":[
        {
            "category":"Government",
            "subcategory":"Office",
            "type":"Public Place"
        }
    ],
    "sg:phone":"+1 651 554 3225",
    "sg:postcode":"55075",
    "sg:province":"MN",
    "sg:tags":[
        "village"
    ],
    "wof:name":"South St Paul Maintenance Dept",
    "wof:placetype":"venue"
},
  "geometry": {"coordinates":[-93.027835,44.87337],"type":"Point"}
}