{
  "type": "Feature",
  "properties": {
    "iso:country":"US",
    "sg:address":"104 Minnesota Ave W",
    "sg:city":"Glenwood",
    "sg:classifiers":[
        {
            "category":"Restaurant",
            "type":"Food & Drink"
        }
    ],
    "sg:menulink":"http://www.allmenus.com/mn/glenwood/151133-subway/menu/",
    "sg:phone":"+1 320 634 5195",
    "sg:postcode":"56334",
    "sg:province":"MN",
    "sg:tags":[
        "american",
        "sandwich"
    ],
    "wof:name":"Subway",
    "wof:placetype":"venue"
},
  "geometry": {"coordinates":[-95.391713,45.650232],"type":"Point"}
}