{
  "type": "Feature",
  "properties": {
    "addr:full":"110 S Main St Janesville MN 56048",
    "addr:housenumber":"110",
    "addr:postcode":"56048",
    "addr:street":"S Main St",
    "iso:country":"US",
    "sg:address":"110 S Main St",
    "sg:city":"Janesville",
    "sg:classifiers":[
        {
            "category":"Professional",
            "type":"Services"
        }
    ],
    "sg:phone":"+1 507 234 9904",
    "sg:postcode":"56048",
    "sg:province":"MN",
    "sg:tags":[
        "establishment"
    ],
    "wof:name":"Rhinestone's",
    "wof:placetype":"venue"
},
  "geometry": {"coordinates":[-93.70758600000001,44.116103],"type":"Point"}
}