{
  "type": "Feature",
  "properties": {
    "iso:country":"US",
    "sg:address":"1251 Mississippi St",
    "sg:city":"Saint Paul",
    "sg:classifiers":[
        {
            "category":"Shopping",
            "subcategory":"Pharmacy",
            "type":"Retail Goods"
        }
    ],
    "sg:phone":"+1 651 631 8266",
    "sg:postcode":"55112",
    "sg:province":"MN",
    "sg:tags":[
        "drug"
    ],
    "wof:name":"Robert Anderson Drug",
    "wof:placetype":"venue"
},
  "geometry": {"coordinates":[-93.20349299999999,45.08529],"type":"Point"}
}