{
  "type": "Feature",
  "properties": {
    "iso:country":"US",
    "sg:address":"1010 2nd St SW",
    "sg:city":"Madelia",
    "sg:classifiers":[
        {
            "category":"Manufacturing",
            "subcategory":"Metals",
            "type":"Manufacturing & Wholesale Goods"
        },
        {
            "category":"Train Station",
            "subcategory":"Rail",
            "type":"Transportation"
        },
        {
            "category":"Manufacturing",
            "subcategory":"Building Materials",
            "type":"Manufacturing & Wholesale Goods"
        },
        {
            "category":"Building & Trades",
            "subcategory":"Construction",
            "type":"Services"
        }
    ],
    "sg:phone":"+1 507 642 3181",
    "sg:postcode":"56062",
    "sg:province":"MN",
    "sg:tags":[
        "steel",
        "stairway",
        "sheet",
        "work",
        "rails",
        "accessory",
        "iron",
        "railing",
        "work-manufacturers",
        "fabricator",
        "mill",
        "welder"
    ],
    "sg:website":"http://www.unitstep.com",
    "wof:name":"Form Unit Step Co Inc",
    "wof:placetype":"venue"
},
  "geometry": {"coordinates":[-94.43042800000001,44.048784],"type":"Point"}
}