{
  "type": "Feature",
  "properties": {
    "addr:full":"8770 Deer Run Dr Victoria MN 55386",
    "addr:housenumber":"8770",
    "addr:postcode":"55386",
    "addr:street":"Deer Run Dr",
    "iso:country":"US",
    "sg:address":"8770 Deer Run Dr",
    "sg:city":"Victoria",
    "sg:classifiers":[
        {
            "category":"Banks & Credit Unions",
            "subcategory":"Financial Services",
            "type":"Services"
        }
    ],
    "sg:phone":"+1 952 443 0152",
    "sg:postcode":"55386",
    "sg:province":"MN",
    "sg:tags":[
        "investment",
        "closed"
    ],
    "wof:name":"Nhba",
    "wof:placetype":"venue"
},
  "geometry": {"coordinates":[-93.65779999999999,44.847778],"type":"Point"}
}