{
  "type": "Feature",
  "properties": {
    "addr:full":"202 E Blue Earth Ave Fairmont MN 56031",
    "addr:housenumber":"202",
    "addr:postcode":"56031",
    "addr:street":"E Blue Earth Ave",
    "iso:country":"US",
    "sg:address":"202 E Blue Earth Ave",
    "sg:city":"Fairmont",
    "sg:classifiers":[
        {
            "category":"Restaurant",
            "type":"Food & Drink"
        },
        {
            "category":"Food & Beverages",
            "subcategory":"Groceries & Convenience Stores",
            "type":"Retail Goods"
        }
    ],
    "sg:menulink":"http://www.allmenus.com/mn/fairmont/225899-caseys-general-store/menu/",
    "sg:phone":"+1 507 238 4423",
    "sg:postcode":"56031",
    "sg:province":"MN",
    "sg:tags":[
        "american",
        "pizza"
    ],
    "wof:name":"Casey's General Store",
    "wof:placetype":"venue"
},
  "geometry": {"coordinates":[-94.46065900000001,43.652064],"type":"Point"}
}