{
  "type": "Feature",
  "properties": {
    "iso:country":"US",
    "sg:address":"6049 Davern Ave NE",
    "sg:city":"Monticello",
    "sg:phone":"+1 763 682 1599",
    "sg:postcode":"55362",
    "sg:province":"MN",
    "sg:tags":[
        "farm",
        "grain",
        "cash"
    ],
    "wof:name":"Decker Gahart",
    "wof:placetype":"venue"
},
  "geometry": {"coordinates":[-93.820194,45.251566],"type":"Point"}
}