{
  "type": "Feature",
  "properties": {
    "addr:full":"5430 Highlands Trl N Lake Elmo MN 55042",
    "addr:housenumber":"5430",
    "addr:postcode":"55042",
    "addr:street":"Highlands Trl N",
    "iso:country":"US",
    "sg:address":"5430 Highlands Trl N",
    "sg:city":"Lake Elmo",
    "sg:classifiers":[
        {
            "category":"Social Services",
            "subcategory":"Child Care",
            "type":"Services"
        }
    ],
    "sg:phone":"+1 651 770 5220",
    "sg:postcode":"55042",
    "sg:province":"MN",
    "sg:tags":[
        "day"
    ],
    "wof:name":"Julie A Coyle",
    "wof:placetype":"venue"
},
  "geometry": {"coordinates":[-92.95155200000001,45.027301],"type":"Point"}
}