{
  "type": "Feature",
  "properties": {
    "addr:full":"7740 Main St Maple Grove MN 55369",
    "addr:housenumber":"7740",
    "addr:postcode":"55369",
    "addr:street":"Main St",
    "iso:country":"US",
    "sg:address":"7740 Main St",
    "sg:city":"Maple Grove",
    "sg:classifiers":[
        {
            "category":"Shopping",
            "type":"Retail Goods"
        },
        {
            "category":"Home & Garden",
            "subcategory":"Home Furnishings",
            "type":"Retail Goods"
        }
    ],
    "sg:phone":"+1 763 494 8311",
    "sg:postcode":"55369",
    "sg:province":"MN",
    "sg:tags":[
        "art",
        "gallery",
        "dealer"
    ],
    "wof:name":"Art & Frame Warehouse",
    "wof:placetype":"venue"
},
  "geometry": {"coordinates":[-93.441586,45.096331],"type":"Point"}
}