{
  "type": "Feature",
  "properties": {
    "iso:country":"US",
    "sg:address":"453 7th St W",
    "sg:city":"St Paul",
    "sg:classifiers":[
        {
            "category":"Shopping",
            "subcategory":"Used Merchandise",
            "type":"Retail Goods"
        }
    ],
    "sg:phone":"+1 651 224 1357",
    "sg:postcode":"55102",
    "sg:province":"MN",
    "sg:tags":[
        "antique"
    ],
    "sg:website":"www.sophiejoes.com",
    "wof:name":"Sophie Joe's Emporium",
    "wof:placetype":"venue"
},
  "geometry": {"coordinates":[-93.111582,44.938066],"type":"Point"}
}