{
  "type": "Feature",
  "properties": {
    "iso:country":"US",
    "sg:address":"1121 8th Ave N",
    "sg:city":"Saint Cloud",
    "sg:classifiers":[
        {
            "category":"Professional",
            "subcategory":"Employment Agencies",
            "type":"Services"
        }
    ],
    "sg:phone":"+1 320 251 8928",
    "sg:postcode":"56303",
    "sg:province":"MN",
    "sg:tags":[
        "help",
        "supply"
    ],
    "wof:name":"James M Gammell",
    "wof:placetype":"venue"
},
  "geometry": {"coordinates":[-94.171252,45.57076],"type":"Point"}
}