{
  "type": "Feature",
  "properties": {
    "iso:country":"US",
    "sg:address":"131 Wentworth Ave E",
    "sg:city":"West St Paul",
    "sg:classifiers":[
        {
            "category":"Food & Beverages",
            "subcategory":"Liquor & Beverages",
            "type":"Retail Goods"
        }
    ],
    "sg:phone":"+1 651 457 6111",
    "sg:postcode":"55118",
    "sg:province":"MN",
    "wof:name":"Booze Mart",
    "wof:placetype":"venue"
},
  "geometry": {"coordinates":[-93.079207,44.898097],"type":"Point"}
}