{
  "type": "Feature",
  "properties": {
    "addr:full":"415 Fillmore St Alexandria MN 56308",
    "addr:housenumber":"415",
    "addr:postcode":"56308",
    "addr:street":"Fillmore St",
    "iso:country":"US",
    "sg:address":"415 Fillmore St",
    "sg:city":"Alexandria",
    "sg:classifiers":[
        {
            "category":"Communications",
            "subcategory":"Television Station",
            "type":"Services"
        }
    ],
    "sg:phone":"+1 320 763 5729",
    "sg:postcode":"56308",
    "sg:province":"MN",
    "sg:tags":[
        "broadcasting",
        "co"
    ],
    "sg:website":"www.ksax.com",
    "wof:name":"KSAX",
    "wof:placetype":"venue"
},
  "geometry": {"coordinates":[-95.37911800000001,45.888123],"type":"Point"}
}