{
  "type": "Feature",
  "properties": {
    "addr:full":"313 S 1st St W Montevideo MN 56265",
    "addr:housenumber":"313",
    "addr:postcode":"56265",
    "addr:street":"S 1St St W",
    "iso:country":"US",
    "sg:address":"313 S 1st St W",
    "sg:city":"Montevideo",
    "sg:phone":"+1 320 269 3067",
    "sg:postcode":"56265",
    "sg:province":"MN",
    "sg:tags":[
        "farm"
    ],
    "wof:name":"Boettcher Vegetable Farm",
    "wof:placetype":"venue"
},
  "geometry": {"coordinates":[-95.724197,44.942482],"type":"Point"}
}