{
  "type": "Feature",
  "properties": {
    "addr:full":"35707 Co Rd 126 Ashby MN 56386",
    "addr:housenumber":"126",
    "addr:postcode":"35707;56386",
    "addr:street":"Co Rd",
    "iso:country":"US",
    "sg:address":"35707 Co Rd 126",
    "sg:city":"Ashby",
    "sg:classifiers":[
        {
            "category":"Home & Garden",
            "subcategory":"Building Materials",
            "type":"Retail Goods"
        }
    ],
    "sg:phone":"+1 218 747 2013",
    "sg:postcode":"56386",
    "sg:province":"MN",
    "wof:name":"Eagle Lake Lumber",
    "wof:placetype":"venue"
},
  "geometry": {"coordinates":[-93.49504,46.064901],"type":"Point"}
}