{
  "type": "Feature",
  "properties": {
    "addr:full":"2002 Airport Rd Grand Rapids MN 55744",
    "addr:housenumber":"2002",
    "addr:postcode":"55744",
    "addr:street":"Airport Rd",
    "iso:country":"US",
    "sg:address":"2002 Airport Rd",
    "sg:city":"Grand Rapids",
    "sg:classifiers":[
        {
            "category":"Retail",
            "subcategory":"Repair Shop",
            "type":"Services"
        },
        {
            "category":"Airport",
            "type":"Transportation"
        }
    ],
    "sg:phone":"+1 218 326 1226",
    "sg:postcode":"55744",
    "sg:province":"MN",
    "sg:tags":[
        "aircraft",
        "maintenance"
    ],
    "wof:name":"Airways Aviation Center",
    "wof:placetype":"venue"
},
  "geometry": {"coordinates":[-93.517966,47.211416],"type":"Point"}
}