{
  "type": "Feature",
  "properties": {
    "iso:country":"US",
    "sg:address":"219 E 3rd St",
    "sg:city":"Redwood Falls",
    "sg:classifiers":[
        {
            "category":"Insurance",
            "subcategory":"Insurance Agent",
            "type":"Services"
        }
    ],
    "sg:phone":"+1 507 637 2348",
    "sg:postcode":"56283",
    "sg:province":"MN",
    "wof:name":"Makarrall Insurance Agency",
    "wof:placetype":"venue"
},
  "geometry": {"coordinates":[-95.11769700000001,44.539657],"type":"Point"}
}