{
  "type": "Feature",
  "properties": {
    "addr:full":"38705 Branch Ave North Branch MN 55056",
    "addr:housenumber":"38705",
    "addr:postcode":"55056",
    "addr:street":"Branch Ave",
    "iso:country":"US",
    "sg:address":"38705 Branch Ave",
    "sg:city":"North Branch",
    "sg:classifiers":[
        {
            "category":"Education",
            "subcategory":"School",
            "type":"Public Place"
        }
    ],
    "sg:phone":"+1 651 674 1200",
    "sg:postcode":"55056",
    "sg:province":"MN",
    "wof:name":"North Branch Primary School",
    "wof:placetype":"venue"
},
  "geometry": {"coordinates":[-92.981607,45.509956],"type":"Point"}
}