{
  "type": "Feature",
  "properties": {
    "iso:country":"US",
    "sg:address":"1310 N German St",
    "sg:city":"New Ulm",
    "sg:classifiers":[
        {
            "category":"Building & Trades",
            "subcategory":"Landscaping Services",
            "type":"Services"
        }
    ],
    "sg:phone":"+1 507 359 2760",
    "sg:postcode":"56073",
    "sg:province":"MN",
    "sg:tags":[
        "tree"
    ],
    "wof:name":"Scharfencamp Tree Svc",
    "wof:placetype":"venue"
},
  "geometry": {"coordinates":[-94.470463,44.327617],"type":"Point"}
}