{
  "type": "Feature",
  "properties": {
    "addr:full":"2185 Holy Name Dr Wayzata MN 55391",
    "addr:housenumber":"2185",
    "addr:postcode":"55391",
    "addr:street":"Holy Name Dr",
    "iso:country":"US",
    "sg:address":"2185 Holy Name Dr",
    "sg:city":"Wayzata",
    "sg:classifiers":[
        {
            "category":"Banks & Credit Unions",
            "subcategory":"Financial Services",
            "type":"Services"
        }
    ],
    "sg:phone":"+1 763 473 0754",
    "sg:postcode":"55391",
    "sg:province":"MN",
    "sg:tags":[
        "investor"
    ],
    "wof:name":"Bennis Investment Prpts LLP",
    "wof:placetype":"venue"
},
  "geometry": {"coordinates":[-93.52715600000001,45.016349],"type":"Point"}
}