{
  "type": "Feature",
  "properties": {
    "iso:country":"US",
    "sg:address":"6866 10th St",
    "sg:city":"Fort Ripley",
    "sg:classifiers":[
        {
            "category":"Retail",
            "subcategory":"Repair Shop",
            "type":"Services"
        }
    ],
    "sg:phone":"+1 218 829 3176",
    "sg:postcode":"56449",
    "sg:province":"MN",
    "sg:tags":[
        "sporting"
    ],
    "wof:name":"Eckelman Gun Sp Shooting Range",
    "wof:placetype":"venue"
},
  "geometry": {"coordinates":[-94.268045,46.17173],"type":"Point"}
}