{
  "type": "Feature",
  "properties": {
    "addr:full":"3557 State Hwy 23 Cottonwood MN 56229",
    "addr:housenumber":"3557",
    "addr:postcode":"56229",
    "addr:street":"State Hwy 23",
    "iso:country":"US",
    "sg:address":"3557 State Hwy 23",
    "sg:city":"Cottonwood",
    "sg:classifiers":[
        {
            "category":"Farming",
            "subcategory":"Livestock Farm",
            "type":"Manufacturing & Wholesale Goods"
        }
    ],
    "sg:phone":"+1 507 423 6362",
    "sg:postcode":"56229",
    "sg:province":"MN",
    "sg:tags":[
        "corn",
        "beef",
        "feedlot",
        "cattle"
    ],
    "wof:name":"Kenneth Persoon",
    "wof:placetype":"venue"
},
  "geometry": {"coordinates":[-95.726592,44.562879],"type":"Point"}
}