{
  "type": "Feature",
  "properties": {
    "iso:country":"US",
    "sg:address":"1209 Hwy 12 E",
    "sg:city":"Willmar",
    "sg:classifiers":[
        {
            "category":"Wholesale",
            "subcategory":"Electrical",
            "type":"Manufacturing & Wholesale Goods"
        }
    ],
    "sg:phone":"+1 320 235 2255",
    "sg:postcode":"56201",
    "sg:province":"MN",
    "sg:tags":[
        "equipment",
        "electric",
        "supply"
    ],
    "wof:name":"Minnesota Electric Supply Co",
    "wof:placetype":"venue"
},
  "geometry": {"coordinates":[-95.03139,45.123798],"type":"Point"}
}