{
  "type": "Feature",
  "properties": {
    "iso:country":"US",
    "sg:address":"12496 Plaza Dr",
    "sg:city":"Eden Prairie",
    "sg:classifiers":[
        {
            "category":"Social Services",
            "subcategory":"Child Care",
            "type":"Services"
        }
    ],
    "sg:phone":"+1 952 944 5633",
    "sg:postcode":"55344",
    "sg:province":"MN",
    "wof:name":"Prairie View Montessori School",
    "wof:placetype":"venue"
},
  "geometry": {"coordinates":[-93.438177,44.863901],"type":"Point"}
}