{
  "type": "Feature",
  "properties": {
    "addr:full":"7887 Fuller Rd Hopkins MN 55344",
    "addr:housenumber":"7887",
    "addr:postcode":"55344",
    "addr:street":"Fuller Rd",
    "iso:country":"US",
    "sg:address":"7887 Fuller Rd",
    "sg:city":"Hopkins",
    "sg:classifiers":[
        {
            "category":"Manufacturing",
            "subcategory":"Tools & Machinery",
            "type":"Manufacturing & Wholesale Goods"
        }
    ],
    "sg:phone":"+1 952 949 2026",
    "sg:postcode":"55344",
    "sg:province":"MN",
    "sg:tags":[
        "test",
        "environmental",
        "mfg",
        "chambers"
    ],
    "wof:name":"Thermotron Industries",
    "wof:placetype":"venue"
},
  "geometry": {"coordinates":[-93.479851,44.861652],"type":"Point"}
}