{
  "type": "Feature",
  "properties": {
    "iso:country":"US",
    "sg:address":"9920 Wayzata Blvd",
    "sg:city":"Minneapolis",
    "sg:classifiers":[
        {
            "category":"Bars & Pubs",
            "type":"Food & Drink"
        },
        {
            "category":"Restaurant",
            "type":"Food & Drink"
        },
        {
            "category":"Professional",
            "type":"Services"
        }
    ],
    "sg:phone":"+1 952 546 6722",
    "sg:postcode":"55426",
    "sg:province":"MN",
    "sg:tags":[
        "style",
        "family",
        "greek",
        "seafood",
        "mediterranean",
        "dining",
        "lunch",
        "caterer",
        "brunch",
        "fine",
        "breakfast"
    ],
    "wof:name":"Santorini Tavern & Grill",
    "wof:placetype":"venue"
},
  "geometry": {"coordinates":[-93.406234,44.973769],"type":"Point"}
}