{
  "type": "Feature",
  "properties": {
    "iso:country":"US",
    "sg:address":"8991 Ferndale Ln",
    "sg:city":"Eden Prairie",
    "sg:classifiers":[
        {
            "category":"Manufacturing",
            "subcategory":"Toys & Sporting Goods",
            "type":"Manufacturing & Wholesale Goods"
        }
    ],
    "sg:phone":"+1 612 868 9569",
    "sg:postcode":"55347",
    "sg:province":"MN",
    "sg:tags":[
        "mfg"
    ],
    "wof:name":"Divotool",
    "wof:placetype":"venue"
},
  "geometry": {"coordinates":[-93.461923,44.841381],"type":"Point"}
}