{
  "type": "Feature",
  "properties": {
    "iso:country":"US",
    "sg:address":"780 Manor St",
    "sg:city":"St Paul",
    "sg:classifiers":[
        {
            "category":"Restaurant",
            "type":"Food & Drink"
        }
    ],
    "sg:phone":"+1 651 489 2256",
    "sg:postcode":"55127",
    "sg:province":"MN",
    "wof:name":"Asian Cuisine",
    "wof:placetype":"venue"
},
  "geometry": {"coordinates":[-93.06768,45.038417],"type":"Point"}
}