{
  "type": "Feature",
  "properties": {
    "addr:full":"427 E Oxford St Duluth MN 55803",
    "addr:housenumber":"427",
    "addr:postcode":"55803",
    "addr:street":"E Oxford St",
    "iso:country":"US",
    "sg:address":"427 E Oxford St",
    "sg:city":"Duluth",
    "sg:classifiers":[
        {
            "category":"Wholesale",
            "subcategory":"Motor Vehicles",
            "type":"Manufacturing & Wholesale Goods"
        }
    ],
    "sg:phone":"+1 218 728 0366",
    "sg:postcode":"55803",
    "sg:province":"MN",
    "wof:name":"Due North Collectbls",
    "wof:placetype":"venue"
},
  "geometry": {"coordinates":[-92.06439,46.833981],"type":"Point"}
}