{
  "type": "Feature",
  "properties": {
    "iso:country":"US",
    "sg:address":"4016 81st Ave N",
    "sg:city":"Minneapolis",
    "sg:classifiers":[
        {
            "category":"Professional",
            "subcategory":"Engineering",
            "type":"Services"
        }
    ],
    "sg:phone":"+1 763 560 5873",
    "sg:postcode":"55443",
    "sg:province":"MN",
    "wof:name":"Boomtown Design",
    "wof:placetype":"venue"
},
  "geometry": {"coordinates":[-93.333533,45.102455],"type":"Point"}
}