{
  "type": "Feature",
  "properties": {
    "addr:full":"715 Cloquet Ave Cloquet MN 55720",
    "addr:housenumber":"715",
    "addr:postcode":"55720",
    "addr:street":"Cloquet Ave",
    "iso:country":"US",
    "sg:address":"715 Cloquet Ave",
    "sg:city":"Cloquet",
    "sg:classifiers":[
        {
            "category":"Social Services",
            "subcategory":"Job Training",
            "type":"Services"
        }
    ],
    "sg:phone":"+1 218 878 4414",
    "sg:postcode":"55720",
    "sg:province":"MN",
    "sg:tags":[
        "employment"
    ],
    "wof:name":"Northeast Minnesota Office",
    "wof:placetype":"venue"
},
  "geometry": {"coordinates":[-92.456614,46.721844],"type":"Point"}
}