{
  "type": "Feature",
  "properties": {
    "addr:full":"7958 Sunkist Blvd Minneapolis MN 55444",
    "addr:housenumber":"7958",
    "addr:postcode":"55444",
    "addr:street":"Sunkist Blvd",
    "iso:country":"US",
    "sg:address":"7958 Sunkist Blvd",
    "sg:city":"Minneapolis",
    "sg:classifiers":[
        {
            "category":"Professional",
            "subcategory":"Computer Services",
            "type":"Services"
        }
    ],
    "sg:phone":"+1 763 560 4696",
    "sg:postcode":"55444",
    "sg:province":"MN",
    "sg:tags":[
        "processing",
        "datum"
    ],
    "sg:website":"http://www.staxsales.com",
    "wof:name":"Data Compression Technology",
    "wof:placetype":"venue"
},
  "geometry": {"coordinates":[-93.28355500000001,45.098981],"type":"Point"}
}