{
  "type": "Feature",
  "properties": {
    "addr:full":"650 37th Ave NE Minneapolis MN 55421",
    "addr:housenumber":"650",
    "addr:postcode":"55421",
    "addr:street":"37Th Ave Ne",
    "iso:country":"US",
    "sg:address":"650 37th Ave NE",
    "sg:city":"Minneapolis",
    "sg:classifiers":[
        {
            "category":"Professional",
            "type":"Services"
        }
    ],
    "sg:phone":"+1 612 789 6047",
    "sg:postcode":"55421",
    "sg:province":"MN",
    "wof:name":"Troy Thomas Breitkreutz",
    "wof:placetype":"venue"
},
  "geometry": {"coordinates":[-93.253851,45.035547],"type":"Point"}
}