{
  "type": "Feature",
  "properties": {
    "addr:full":"10417 Excelsior Blvd # 3 Hopkins MN 55343",
    "addr:housenumber":"10417",
    "addr:postcode":"55343",
    "addr:street":"Excelsior Blvd # 3",
    "iso:country":"US",
    "sg:address":"10417 Excelsior Blvd # 3",
    "sg:city":"Hopkins",
    "sg:classifiers":[
        {
            "category":"Health Services",
            "subcategory":"Clinic",
            "type":"Services"
        },
        {
            "category":"Health Services",
            "subcategory":"Health Practitioner",
            "type":"Services"
        }
    ],
    "sg:phone":"+1 952 932 0902",
    "sg:postcode":"55343",
    "sg:province":"MN",
    "sg:tags":[
        "information",
        "addiction-information",
        "treatment",
        "alcoholism",
        "gambling"
    ],
    "wof:name":"Rehabilitation Counselors Inc",
    "wof:placetype":"venue"
},
  "geometry": {"coordinates":[-93.427483,44.920805],"type":"Point"}
}