{
  "type": "Feature",
  "properties": {
    "iso:country":"US",
    "sg:address":"6298 Bury Dr",
    "sg:city":"Eden Prairie",
    "sg:classifiers":[
        {
            "category":"Wholesale",
            "subcategory":"Machinery & Supplies",
            "type":"Manufacturing & Wholesale Goods"
        },
        {
            "category":"Wholesale",
            "subcategory":"Hardware",
            "type":"Manufacturing & Wholesale Goods"
        }
    ],
    "sg:phone":"+1 952 934 7480",
    "sg:postcode":"55346",
    "sg:province":"MN",
    "sg:tags":[
        "fastener",
        "industrial"
    ],
    "wof:name":"Prodex Supply Inc",
    "wof:placetype":"venue"
},
  "geometry": {"coordinates":[-93.45246899999999,44.890592],"type":"Point"}
}