{
  "type": "Feature",
  "properties": {
    "iso:country":"US",
    "sg:address":"3025 Harbor Ln N",
    "sg:city":"Minneapolis",
    "sg:classifiers":[
        {
            "category":"Shopping",
            "subcategory":"Computers & Home Electronics",
            "type":"Retail Goods"
        }
    ],
    "sg:phone":"+1 763 591 5995",
    "sg:postcode":"55447",
    "sg:province":"MN",
    "sg:tags":[
        "software"
    ],
    "wof:name":"SFA Solutions",
    "wof:placetype":"venue"
},
  "geometry": {"coordinates":[-93.461262,45.014061],"type":"Point"}
}