{
  "type": "Feature",
  "properties": {
    "addr:full":"1604 London Rd Duluth MN 55812",
    "addr:housenumber":"1604",
    "addr:postcode":"55812",
    "addr:street":"London Rd",
    "iso:country":"US",
    "sg:address":"1604 London Rd",
    "sg:city":"Duluth",
    "sg:classifiers":[
        {
            "category":"Retail",
            "subcategory":"Portrait Studio",
            "type":"Services"
        }
    ],
    "sg:phone":"+1 218 728 2800",
    "sg:postcode":"55812",
    "sg:province":"MN",
    "sg:tags":[
        "photo"
    ],
    "wof:name":"Advanced Phtgraphy By Patricia",
    "wof:placetype":"venue"
},
  "geometry": {"coordinates":[-92.074873,46.801446],"type":"Point"}
}