{
  "type": "Feature",
  "properties": {
    "addr:full":"132 3rd St W Halstad MN 56548",
    "addr:housenumber":"132",
    "addr:postcode":"56548",
    "addr:street":"3Rd St W",
    "iso:country":"US",
    "sg:address":"132 3rd St W",
    "sg:city":"Halstad",
    "sg:classifiers":[
        {
            "category":"Health Services",
            "subcategory":"Dentist",
            "type":"Services"
        }
    ],
    "sg:phone":"+1 218 456 2182",
    "sg:postcode":"56548",
    "sg:province":"MN",
    "wof:name":"Dr Joy's Dental Clinic",
    "wof:placetype":"venue"
},
  "geometry": {"coordinates":[-96.827022,47.351754],"type":"Point"}
}