{
  "type": "Feature",
  "properties": {
    "addr:full":"864 E 6th St St Paul MN 55106",
    "addr:housenumber":"864",
    "addr:postcode":"55106",
    "addr:street":"E 6Th St",
    "iso:country":"US",
    "sg:address":"864 E 6th St",
    "sg:city":"St Paul",
    "sg:classifiers":[
        {
            "category":"Professional",
            "subcategory":"Business Services",
            "type":"Services"
        }
    ],
    "sg:phone":"+1 651 774 9393",
    "sg:postcode":"55106",
    "sg:province":"MN",
    "sg:tags":[
        "recording",
        "studio"
    ],
    "wof:name":"Hired Gun Mobile Audio",
    "wof:placetype":"venue"
},
  "geometry": {"coordinates":[-93.064685,44.960273],"type":"Point"}
}