{
  "type": "Feature",
  "properties": {
    "iso:country":"US",
    "sg:address":"681 Lake St E",
    "sg:city":"Wayzata",
    "sg:classifiers":[
        {
            "category":"Banks & Credit Unions",
            "subcategory":"Investment Brokerage",
            "type":"Services"
        }
    ],
    "sg:phone":"+1 952 473 1080",
    "sg:postcode":"55391",
    "sg:province":"MN",
    "sg:tags":[
        "advisory"
    ],
    "wof:name":"Regan Investment Advisors Inc",
    "wof:placetype":"venue"
},
  "geometry": {"coordinates":[-93.512823,44.969583],"type":"Point"}
}