{
  "type": "Feature",
  "properties": {
    "addr:full":"809 W Church St Belle Plaine MN 56011",
    "addr:housenumber":"809",
    "addr:postcode":"56011",
    "addr:street":"W Church St;Plaine",
    "iso:country":"US",
    "sg:address":"809 W Church St",
    "sg:city":"Belle Plaine",
    "sg:classifiers":[
        {
            "category":"Building & Trades",
            "subcategory":"Construction",
            "type":"Services"
        }
    ],
    "sg:phone":"+1 952 873 2858",
    "sg:postcode":"56011",
    "sg:province":"MN",
    "sg:tags":[
        "floor",
        "laying",
        "contractor"
    ],
    "wof:name":"Arizona Zellman",
    "wof:placetype":"venue"
},
  "geometry": {"coordinates":[-93.77848,44.624073],"type":"Point"}
}