{
  "type": "Feature",
  "properties": {
    "iso:country":"US",
    "sg:address":"5808 Boone Ave N",
    "sg:city":"Minneapolis",
    "sg:classifiers":[
        {
            "category":"Retail",
            "subcategory":"Photofinishing",
            "type":"Services"
        }
    ],
    "sg:phone":"+1 763 533 4209",
    "sg:postcode":"55428",
    "sg:province":"MN",
    "sg:tags":[
        "laboratory"
    ],
    "wof:name":"A Photo Montage",
    "wof:placetype":"venue"
},
  "geometry": {"coordinates":[-93.390381,45.058402],"type":"Point"}
}