{
  "type": "Feature",
  "properties": {
    "iso:country":"US",
    "sg:address":"109 W 4th St",
    "sg:city":"Duluth",
    "sg:classifiers":[
        {
            "category":"Shopping",
            "subcategory":"Used Merchandise",
            "type":"Retail Goods"
        }
    ],
    "sg:phone":"+1 218 624 7379",
    "sg:postcode":"55806",
    "sg:province":"MN",
    "wof:name":"Saint Vincent Depaul Salvage",
    "wof:placetype":"venue"
},
  "geometry": {"coordinates":[-92.105028,46.787829],"type":"Point"}
}