{
  "type": "Feature",
  "properties": {
    "iso:country":"US",
    "sg:address":"887 Smith Ave S",
    "sg:city":"West St Paul",
    "sg:classifiers":[
        {
            "category":"Professional",
            "type":"Services"
        }
    ],
    "sg:phone":"+1 651 453 2100",
    "sg:postcode":"55118",
    "sg:province":"MN",
    "sg:tags":[
        "establishment"
    ],
    "wof:name":"Caleb's Happy Feet",
    "wof:placetype":"venue"
},
  "geometry": {"coordinates":[-93.10186,44.918998],"type":"Point"}
}