{
  "type": "Feature",
  "properties": {
    "addr:full":"2841 34th Ave S Minneapolis MN 55406",
    "addr:housenumber":"2841",
    "addr:postcode":"55406",
    "addr:street":"34Th Ave S",
    "iso:country":"US",
    "sg:address":"2841 34th Ave S",
    "sg:city":"Minneapolis",
    "sg:classifiers":[
        {
            "category":"Personal",
            "subcategory":"Barber",
            "type":"Services"
        }
    ],
    "sg:phone":"+1 612 722 5664",
    "sg:postcode":"55406",
    "sg:province":"MN",
    "wof:name":"R J & J Barber Shop",
    "wof:placetype":"venue"
},
  "geometry": {"coordinates":[-93.222846,44.950905],"type":"Point"}
}