{
  "type": "Feature",
  "properties": {
    "addr:full":"611 Walnut St Ste 2 Monticello MN 55362",
    "addr:housenumber":"611",
    "addr:postcode":"55362",
    "addr:street":"Walnut St Ste 2",
    "iso:country":"US",
    "sg:address":"611 Walnut St Ste 2",
    "sg:city":"Monticello",
    "sg:classifiers":[
        {
            "category":"Health Services",
            "subcategory":"Health Practitioner",
            "type":"Services"
        },
        {
            "category":"Health Services",
            "subcategory":"Chiropractor",
            "type":"Services"
        }
    ],
    "sg:phone":"+1 763 295 4301",
    "sg:postcode":"55362",
    "sg:province":"MN",
    "sg:tags":[
        "acupuncture",
        "medicine",
        "alternative",
        "chiropractic"
    ],
    "sg:website":"http://www.wholehealthfamilychiro.com",
    "wof:name":"Whole Health Family Chiropractic",
    "wof:placetype":"venue"
},
  "geometry": {"coordinates":[-93.798511,45.301967],"type":"Point"}
}