{
  "type": "Feature",
  "properties": {
    "addr:full":"4420 Wilson St Minnetonka MN 55345",
    "addr:housenumber":"4420",
    "addr:postcode":"55345",
    "addr:street":"Wilson St",
    "iso:country":"US",
    "sg:address":"4420 Wilson St",
    "sg:city":"Minnetonka",
    "sg:classifiers":[
        {
            "category":"Professional",
            "subcategory":"Business Services",
            "type":"Services"
        }
    ],
    "sg:phone":"+1 952 930 3385",
    "sg:postcode":"55345",
    "sg:province":"MN",
    "wof:name":"Scott Burns Group Inc",
    "wof:placetype":"venue"
},
  "geometry": {"coordinates":[-93.480391,44.925994],"type":"Point"}
}