{
  "type": "Feature",
  "properties": {
    "iso:country":"US",
    "sg:address":"1040 Highway Ave",
    "sg:city":"Bird Island",
    "sg:phone":"+1 320 365 4765",
    "sg:postcode":"55310",
    "sg:province":"MN",
    "sg:tags":[
        "farm",
        "corn"
    ],
    "wof:name":"Jerry Kopel",
    "wof:placetype":"venue"
},
  "geometry": {"coordinates":[-94.900559,44.767608],"type":"Point"}
}