{
  "type": "Feature",
  "properties": {
    "iso:country":"US",
    "sg:address":"3420 Lachencrest Ln NW",
    "sg:city":"Rochester",
    "sg:classifiers":[
        {
            "category":"Health Services",
            "subcategory":"Doctor",
            "type":"Services"
        }
    ],
    "sg:phone":"+1 507 288 4427",
    "sg:postcode":"55901",
    "sg:province":"MN",
    "wof:name":"Brent E Larson DDS Msd",
    "wof:placetype":"venue"
},
  "geometry": {"coordinates":[-92.51499699999999,44.026125],"type":"Point"}
}