{
  "type": "Feature",
  "properties": {
    "addr:full":"33307 795th Ave Ellendale MN 56026",
    "addr:housenumber":"33307",
    "addr:postcode":"56026",
    "addr:street":"795Th Ave",
    "iso:country":"US",
    "sg:address":"33307 795th Ave",
    "sg:city":"Ellendale",
    "sg:classifiers":[
        {
            "category":"Manufacturing",
            "subcategory":"Food",
            "type":"Manufacturing & Wholesale Goods"
        },
        {
            "category":"Farming",
            "subcategory":"Farm",
            "type":"Manufacturing & Wholesale Goods"
        }
    ],
    "sg:phone":"+1 507 256 4631",
    "sg:postcode":"56026",
    "sg:province":"MN",
    "sg:tags":[
        "corn",
        "product"
    ],
    "wof:name":"Gary Viktora",
    "wof:placetype":"venue"
},
  "geometry": {"coordinates":[-93.27909099999999,43.830707],"type":"Point"}
}