{
  "type": "Feature",
  "properties": {
    "addr:full":"711 Roosevelt St Alexandria MN 56308",
    "addr:housenumber":"711",
    "addr:postcode":"56308",
    "addr:street":"Roosevelt St",
    "iso:country":"US",
    "sg:address":"711 Roosevelt St",
    "sg:city":"Alexandria",
    "sg:classifiers":[
        {
            "category":"Shopping",
            "subcategory":"Bicycles & Sporting Goods",
            "type":"Retail Goods"
        }
    ],
    "sg:phone":"+1 320 762 8574",
    "sg:postcode":"56308",
    "sg:province":"MN",
    "sg:tags":[
        "tackle",
        "shop"
    ],
    "wof:name":"Alexandria Sport & Tackle",
    "wof:placetype":"venue"
},
  "geometry": {"coordinates":[-95.36075,45.884558],"type":"Point"}
}