{
  "type": "Feature",
  "properties": {
    "iso:country":"US",
    "sg:address":"3941 Garfield Ave S",
    "sg:city":"Minneapolis",
    "sg:classifiers":[
        {
            "category":"Professional",
            "subcategory":"Business Services",
            "type":"Services"
        }
    ],
    "sg:phone":"+1 612 822 5825",
    "sg:postcode":"55409",
    "sg:province":"MN",
    "wof:name":"UPS Stores The",
    "wof:placetype":"venue"
},
  "geometry": {"coordinates":[-93.28689199999999,44.931194],"type":"Point"}
}