{
  "type": "Feature",
  "properties": {
    "addr:full":"200 N Minnesota St New Ulm MN 56073",
    "addr:housenumber":"200",
    "addr:postcode":"56073",
    "addr:street":"N Minnesota St",
    "iso:country":"US",
    "sg:address":"200 N Minnesota St",
    "sg:city":"New Ulm",
    "sg:classifiers":[
        {
            "category":"Utilities",
            "subcategory":"Cable",
            "type":"Services"
        }
    ],
    "sg:phone":"+1 507 354 4191",
    "sg:postcode":"56073",
    "sg:province":"MN",
    "sg:tags":[
        "tv"
    ],
    "wof:name":"Time Warner",
    "wof:placetype":"venue"
},
  "geometry": {"coordinates":[-94.46176199999999,44.316255],"type":"Point"}
}