{
  "type": "Feature",
  "properties": {
    "iso:country":"US",
    "sg:address":"2116 Greenbrier St",
    "sg:city":"Saint Paul",
    "sg:classifiers":[
        {
            "category":"Social Services",
            "subcategory":"Job Training",
            "type":"Services"
        }
    ],
    "sg:phone":"+1 651 771 3446",
    "sg:postcode":"55117",
    "sg:province":"MN",
    "sg:tags":[
        "related"
    ],
    "wof:name":"Marlene Palkovich",
    "wof:placetype":"venue"
},
  "geometry": {"coordinates":[-93.070785,45.005337],"type":"Point"}
}