{
  "type": "Feature",
  "properties": {
    "iso:country":"US",
    "sg:address":"504 Division St S",
    "sg:city":"Northfield",
    "sg:classifiers":[
        {
            "category":"Shopping",
            "subcategory":"Used Merchandise",
            "type":"Retail Goods"
        }
    ],
    "sg:phone":"+1 507 663 6099",
    "sg:postcode":"55057",
    "sg:province":"MN",
    "sg:tags":[
        "book",
        "rare",
        "dealer"
    ],
    "wof:name":"Bookfellows Inc",
    "wof:placetype":"venue"
},
  "geometry": {"coordinates":[-93.160231,44.45505],"type":"Point"}
}