{
  "type": "Feature",
  "properties": {
    "iso:country":"US",
    "sg:address":"9746 Fenner Ave SE",
    "sg:city":"Delano",
    "sg:classifiers":[
        {
            "category":"Professional",
            "type":"Services"
        }
    ],
    "sg:phone":"+1 763 972 2489",
    "sg:postcode":"55328",
    "sg:province":"MN",
    "sg:tags":[
        "craft",
        "supplies-wholesale",
        "manufacturer"
    ],
    "wof:name":"Geojazz",
    "wof:placetype":"venue"
},
  "geometry": {"coordinates":[-93.77430099999999,45.01032],"type":"Point"}
}