{
  "type": "Feature",
  "properties": {
    "iso:country":"US",
    "sg:address":"116 3rd St NE",
    "sg:city":"Aitkin",
    "sg:classifiers":[
        {
            "category":"Organizations",
            "subcategory":"Religious Organization",
            "type":"Services"
        }
    ],
    "sg:phone":"+1 218 927 2760",
    "sg:postcode":"56431",
    "sg:province":"MN",
    "wof:name":"Haines Rev Roy & Alana",
    "wof:placetype":"venue"
},
  "geometry": {"coordinates":[-93.70280099999999,46.534761],"type":"Point"}
}