{
  "type": "Feature",
  "properties": {
    "iso:country":"US",
    "sg:address":"1530 153rd Ln NW",
    "sg:city":"Anoka",
    "sg:classifiers":[
        {
            "category":"Recreation",
            "type":"Entertainment"
        }
    ],
    "sg:phone":"+1 763 434 6717",
    "sg:postcode":"55304",
    "sg:province":"MN",
    "wof:name":"B T Holiday Accents",
    "wof:placetype":"venue"
},
  "geometry": {"coordinates":[-93.303365,45.248536],"type":"Point"}
}