{
  "type": "Feature",
  "properties": {
    "iso:country":"US",
    "sg:address":"369 W 4th St",
    "sg:city":"Winona",
    "sg:classifiers":[
        {
            "category":"Professional",
            "subcategory":"Art Services",
            "type":"Services"
        }
    ],
    "sg:phone":"+1 507 452 6477",
    "sg:postcode":"55987",
    "sg:province":"MN",
    "sg:tags":[
        "commercial",
        "design"
    ],
    "wof:name":"Blackwatch Graphics",
    "wof:placetype":"venue"
},
  "geometry": {"coordinates":[-91.645881,44.053792],"type":"Point"}
}