{
  "type": "Feature",
  "properties": {
    "iso:country":"US",
    "sg:address":"240 W 4th St",
    "sg:city":"Rush City",
    "sg:classifiers":[
        {
            "category":"Social Services",
            "type":"Services"
        }
    ],
    "sg:phone":"+1 320 358 3611",
    "sg:postcode":"55069",
    "sg:province":"MN",
    "sg:tags":[
        "senior",
        "citizen"
    ],
    "wof:name":"Catholic Charities Senior Dine",
    "wof:placetype":"venue"
},
  "geometry": {"coordinates":[-92.963972,45.684675],"type":"Point"}
}