{
  "type": "Feature",
  "properties": {
    "addr:full":"5677 147th St N Hugo MN 55038",
    "addr:housenumber":"5677",
    "addr:postcode":"55038",
    "addr:street":"147Th St N Hugo",
    "iso:country":"US",
    "sg:address":"5677 147th St N",
    "sg:city":"Hugo",
    "sg:classifiers":[
        {
            "category":"Health Services",
            "subcategory":"Doctor",
            "type":"Services"
        }
    ],
    "sg:phone":"+1 651 426 1639",
    "sg:postcode":"55038",
    "sg:province":"MN",
    "sg:tags":[
        "dentist"
    ],
    "wof:name":"Hugo Dental Care P A",
    "wof:placetype":"venue"
},
  "geometry": {"coordinates":[-92.99199299999999,45.163412],"type":"Point"}
}