{
  "type": "Feature",
  "properties": {
    "iso:country":"US",
    "sg:address":"7691 Berkshire Way",
    "sg:city":"Osseo",
    "sg:classifiers":[
        {
            "category":"Professional",
            "subcategory":"Accounting & Tax Preparation",
            "type":"Services"
        }
    ],
    "sg:phone":"+1 763 420 3015",
    "sg:postcode":"55311",
    "sg:province":"MN",
    "wof:name":"Karen Enfield CPA",
    "wof:placetype":"venue"
},
  "geometry": {"coordinates":[-93.455078,45.095146],"type":"Point"}
}