{
  "type": "Feature",
  "properties": {
    "addr:full":"123 Village Center Dr Saint Paul MN 55127",
    "addr:housenumber":"123",
    "addr:postcode":"55127",
    "addr:street":"Village Center Dr",
    "iso:country":"US",
    "sg:address":"123 Village Center Dr",
    "sg:city":"Saint Paul",
    "sg:classifiers":[
        {
            "category":"Shopping",
            "subcategory":"Jewelry",
            "type":"Retail Goods"
        }
    ],
    "sg:phone":"+1 651 481 9750",
    "sg:postcode":"55127",
    "sg:province":"MN",
    "sg:tags":[
        "store"
    ],
    "wof:name":"Geller Jewelry",
    "wof:placetype":"venue"
},
  "geometry": {"coordinates":[-93.114435,45.07997],"type":"Point"}
}