{
  "type": "Feature",
  "properties": {
    "addr:full":"11521 Eagle St NW Ste 3 Minneapolis MN 55448",
    "addr:housenumber":"11521",
    "addr:postcode":"55448",
    "addr:street":"Eagle St Nw Ste 3",
    "iso:country":"US",
    "sg:address":"11521 Eagle St NW Ste 3",
    "sg:city":"Minneapolis",
    "sg:classifiers":[
        {
            "category":"Building & Trades",
            "subcategory":"Construction",
            "type":"Services"
        }
    ],
    "sg:phone":"+1 763 434 0716",
    "sg:postcode":"55448",
    "sg:province":"MN",
    "sg:tags":[
        "contractor"
    ],
    "wof:name":"Skogman Flooring",
    "wof:placetype":"venue"
},
  "geometry": {"coordinates":[-93.30705399999999,45.179718],"type":"Point"}
}