{
  "type": "Feature",
  "properties": {
    "addr:full":"850 Wayzata Blvd Wayzata MN 55356",
    "addr:housenumber":"850",
    "addr:postcode":"55356",
    "addr:street":"Wayzata Blvd",
    "iso:country":"US",
    "sg:address":"850 Wayzata Blvd",
    "sg:city":"Wayzata",
    "sg:classifiers":[
        {
            "category":"Organizations",
            "subcategory":"Religious Organization",
            "type":"Services"
        }
    ],
    "sg:phone":"+1 952 475 1990",
    "sg:postcode":"55356",
    "sg:province":"MN",
    "sg:tags":[
        "church"
    ],
    "wof:name":"Conerstone New Testament Chr",
    "wof:placetype":"venue"
},
  "geometry": {"coordinates":[-93.544988,44.980007],"type":"Point"}
}