{
  "type": "Feature",
  "properties": {
    "iso:country":"US",
    "sg:address":"92 Mahtomedi Ave",
    "sg:city":"Mahtomedi",
    "sg:classifiers":[
        {
            "category":"Personal",
            "subcategory":"Beauty Salon",
            "type":"Services"
        }
    ],
    "sg:phone":"+1 651 429 9777",
    "sg:postcode":"55115",
    "sg:province":"MN",
    "wof:name":"ACO Salon",
    "wof:placetype":"venue"
},
  "geometry": {"coordinates":[-92.960655,45.056283],"type":"Point"}
}