{
  "type": "Feature",
  "properties": {
    "iso:country":"US",
    "sg:address":"1721 5th St S",
    "sg:city":"Moorhead",
    "sg:classifiers":[
        {
            "category":"Shopping",
            "subcategory":"Computers & Home Electronics",
            "type":"Retail Goods"
        }
    ],
    "sg:phone":"+1 218 236 0501",
    "sg:postcode":"56560",
    "sg:province":"MN",
    "sg:tags":[
        "software"
    ],
    "wof:name":"Interstate Software",
    "wof:placetype":"venue"
},
  "geometry": {"coordinates":[-96.77259100000001,46.85776],"type":"Point"}
}