{
  "type": "Feature",
  "properties": {
    "addr:full":"14171 Cobbler Ave Rosemount MN 55068",
    "addr:housenumber":"14171",
    "addr:postcode":"55068",
    "addr:street":"Cobbler Ave",
    "iso:country":"US",
    "sg:address":"14171 Cobbler Ave",
    "sg:city":"Rosemount",
    "sg:classifiers":[
        {
            "category":"Building & Trades",
            "subcategory":"Construction",
            "type":"Services"
        }
    ],
    "sg:phone":"+1 651 423 1989",
    "sg:postcode":"55068",
    "sg:province":"MN",
    "sg:tags":[
        "house"
    ],
    "wof:name":"Thoroughbred Home Builders",
    "wof:placetype":"venue"
},
  "geometry": {"coordinates":[-93.142264,44.743429],"type":"Point"}
}