{
  "type": "Feature",
  "properties": {
    "addr:full":"336 E Franklin Ave Minneapolis MN 55404",
    "addr:housenumber":"336",
    "addr:postcode":"55404",
    "addr:street":"E Franklin Ave",
    "iso:country":"US",
    "sg:address":"336 E Franklin Ave",
    "sg:city":"Minneapolis",
    "sg:classifiers":[
        {
            "category":"Arts & Performance",
            "subcategory":"Art Gallery",
            "type":"Entertainment"
        },
        {
            "category":"Farming",
            "subcategory":"Fish & Marine Products",
            "type":"Manufacturing & Wholesale Goods"
        },
        {
            "category":"Retail",
            "subcategory":"Repair Shop",
            "type":"Services"
        },
        {
            "category":"Shopping",
            "subcategory":"Antiques",
            "type":"Retail Goods"
        }
    ],
    "sg:phone":"+1 612 870 0702",
    "sg:postcode":"55404",
    "sg:province":"MN",
    "sg:tags":[
        "picture",
        "consultant",
        "frame",
        "galleries",
        "restoration",
        "framing"
    ],
    "sg:website":"http://www.pastpresentfuture.net",
    "wof:name":"Past Present Future",
    "wof:placetype":"venue"
},
  "geometry": {"coordinates":[-93.27130099999999,44.962601],"type":"Point"}
}