{
  "type": "Feature",
  "properties": {
    "iso:country":"US",
    "sg:address":"7455 Davidson Ave NE",
    "sg:city":"Monticello",
    "sg:classifiers":[
        {
            "category":"Farming",
            "subcategory":"Farm",
            "type":"Manufacturing & Wholesale Goods"
        }
    ],
    "sg:phone":"+1 763 295 5195",
    "sg:postcode":"55362",
    "sg:province":"MN",
    "sg:tags":[
        "crop",
        "general"
    ],
    "wof:name":"Chester Desmarais",
    "wof:placetype":"venue"
},
  "geometry": {"coordinates":[-93.817334,45.256224],"type":"Point"}
}