{
  "type": "Feature",
  "properties": {
    "addr:full":"2497 7th Ave E Saint Paul MN 55109",
    "addr:housenumber":"2497",
    "addr:postcode":"55109",
    "addr:street":"7Th Ave E",
    "iso:country":"US",
    "sg:address":"2497 7th Ave E",
    "sg:city":"Saint Paul",
    "sg:classifiers":[
        {
            "category":"Professional",
            "subcategory":"Lawyer & Legal Services",
            "type":"Services"
        }
    ],
    "sg:phone":"+1 651 777 6446",
    "sg:postcode":"55109",
    "sg:province":"MN",
    "sg:tags":[
        "law"
    ],
    "wof:name":"Arndt & Benton PA",
    "wof:placetype":"venue"
},
  "geometry": {"coordinates":[-92.99655199999999,45.009527],"type":"Point"}
}