{
  "type": "Feature",
  "properties": {
    "addr:full":"6695 131st St W Apple Valley MN 55124",
    "addr:housenumber":"6695",
    "addr:postcode":"55124",
    "addr:street":"131St St W",
    "iso:country":"US",
    "sg:address":"6695 131st St W",
    "sg:city":"Apple Valley",
    "sg:classifiers":[
        {
            "category":"Building & Trades",
            "subcategory":"Landscaping Services",
            "type":"Services"
        }
    ],
    "sg:phone":"+1 952 890 8384",
    "sg:postcode":"55124",
    "sg:province":"MN",
    "sg:tags":[
        "tree"
    ],
    "wof:name":"B & J Tree Care",
    "wof:placetype":"venue"
},
  "geometry": {"coordinates":[-93.200097,44.75942],"type":"Point"}
}