{
  "type": "Feature",
  "properties": {
    "iso:country":"US",
    "sg:address":"10650 Co Rd 81",
    "sg:city":"Osseo",
    "sg:classifiers":[
        {
            "category":"Banks & Credit Unions",
            "subcategory":"Bank",
            "type":"Services"
        }
    ],
    "sg:phone":"+1 763 488 9740",
    "sg:postcode":"55369",
    "sg:province":"MN",
    "sg:tags":[
        "mortgage",
        "loan",
        "broker",
        "real estate"
    ],
    "wof:name":"Arbor Lakes Mortgage Inc",
    "wof:placetype":"venue"
},
  "geometry": {"coordinates":[-93.415908,45.1203],"type":"Point"}
}