{
  "type": "Feature",
  "properties": {
    "iso:country":"US",
    "sg:address":"2125 Tower Dr",
    "sg:city":"Saint Paul",
    "sg:classifiers":[
        {
            "category":"Organizations",
            "subcategory":"Religious Organization",
            "type":"Services"
        }
    ],
    "sg:phone":"+1 651 738 0045",
    "sg:postcode":"55125",
    "sg:province":"MN",
    "sg:tags":[
        "church"
    ],
    "wof:name":"Trinity Presbyterian Church",
    "wof:placetype":"venue"
},
  "geometry": {"coordinates":[-92.94406499999999,44.917255],"type":"Point"}
}