{
  "type": "Feature",
  "properties": {
    "iso:country":"US",
    "sg:address":"100 Washington St",
    "sg:city":"Brainerd",
    "sg:classifiers":[
        {
            "category":"Home & Garden",
            "subcategory":"Furniture",
            "type":"Retail Goods"
        }
    ],
    "sg:phone":"+1 218 828 4970",
    "sg:postcode":"56401",
    "sg:province":"MN",
    "wof:name":"Backwood Furniture",
    "wof:placetype":"venue"
},
  "geometry": {"coordinates":[-94.20667,46.35814],"type":"Point"}
}