{
  "type": "Feature",
  "properties": {
    "iso:country":"US",
    "sg:address":"1700 E Lake St",
    "sg:city":"Minneapolis",
    "sg:classifiers":[
        {
            "category":"Food & Beverages",
            "subcategory":"Groceries & Convenience Stores",
            "type":"Retail Goods"
        }
    ],
    "sg:phone":"+1 612 728 1647",
    "sg:postcode":"55407",
    "sg:province":"MN",
    "wof:name":"Cedar Petroleum Inc",
    "wof:placetype":"venue"
},
  "geometry": {"coordinates":[-93.24867999999999,44.94837],"type":"Point"}
}