{
  "type": "Feature",
  "properties": {
    "addr:full":"384 Bench St SW Chatfield MN 55923",
    "addr:housenumber":"384",
    "addr:postcode":"55923",
    "addr:street":"Bench St Sw",
    "iso:country":"US",
    "sg:address":"384 Bench St SW",
    "sg:city":"Chatfield",
    "sg:classifiers":[
        {
            "category":"Shopping",
            "subcategory":"Crafts & Fabrics",
            "type":"Retail Goods"
        }
    ],
    "sg:phone":"+1 651 257 1737",
    "sg:postcode":"55923",
    "sg:province":"MN",
    "sg:tags":[
        "sewing"
    ],
    "wof:name":"Buzy Bee Embroidery",
    "wof:placetype":"venue"
},
  "geometry": {"coordinates":[-92.189243,43.842937],"type":"Point"}
}