{
  "type": "Feature",
  "properties": {
    "iso:country":"US",
    "sg:address":"24349 Hill Valley Rd",
    "sg:city":"Red Wing",
    "sg:classifiers":[
        {
            "category":"Farming",
            "subcategory":"Livestock Farm",
            "type":"Manufacturing & Wholesale Goods"
        }
    ],
    "sg:phone":"+1 651 388 3465",
    "sg:postcode":"55066",
    "sg:province":"MN",
    "sg:tags":[
        "hog",
        "or",
        "feedlot"
    ],
    "wof:name":"Harold Augustin",
    "wof:placetype":"venue"
},
  "geometry": {"coordinates":[-92.536102,44.470302],"type":"Point"}
}