{
  "type": "Feature",
  "properties": {
    "iso:country":"US",
    "sg:address":"1082 Bellecrest Dr N",
    "sg:city":"Saint Paul",
    "sg:classifiers":[
        {
            "category":"Freight",
            "type":"Transportation"
        }
    ],
    "sg:phone":"+1 651 483 6313",
    "sg:postcode":"55109",
    "sg:province":"MN",
    "sg:tags":[
        "trucking"
    ],
    "wof:name":"Dietz Trucking",
    "wof:placetype":"venue"
},
  "geometry": {"coordinates":[-93.05451600000001,45.018048],"type":"Point"}
}