{
  "type": "Feature",
  "properties": {
    "addr:full":"26199 Galen Dr Wyoming MN 55092",
    "addr:housenumber":"26199",
    "addr:postcode":"55092",
    "addr:street":"Galen Dr",
    "iso:country":"US",
    "sg:address":"26199 Galen Dr",
    "sg:city":"Wyoming",
    "sg:classifiers":[
        {
            "category":"Professional",
            "subcategory":"Computer Services",
            "type":"Services"
        }
    ],
    "sg:phone":"+1 651 462 5346",
    "sg:postcode":"55092",
    "sg:province":"MN",
    "sg:tags":[
        "graphic"
    ],
    "wof:name":"Nisbet Web Design",
    "wof:placetype":"venue"
},
  "geometry": {"coordinates":[-92.98722100000001,45.327325],"type":"Point"}
}