{
  "type": "Feature",
  "properties": {
    "addr:full":"1700 W 82nd St Ste 125 Minneapolis MN 55431",
    "addr:housenumber":"1700",
    "addr:postcode":"55431",
    "addr:street":"W 82Nd St Ste 125",
    "iso:country":"US",
    "sg:address":"1700 W 82nd St Ste 125",
    "sg:city":"Minneapolis",
    "sg:classifiers":[
        {
            "category":"Shopping",
            "subcategory":"Tobacco",
            "type":"Retail Goods"
        }
    ],
    "sg:phone":"+1 952 885 0026",
    "sg:postcode":"55431",
    "sg:province":"MN",
    "sg:tags":[
        "cigarette",
        "cigar"
    ],
    "wof:name":"Philip Morris",
    "wof:placetype":"venue"
},
  "geometry": {"coordinates":[-93.301147,44.855301],"type":"Point"}
}