{
  "type": "Feature",
  "properties": {
    "addr:full":"208 Circle Dr St Charles MN 55972",
    "addr:housenumber":"208",
    "addr:postcode":"55972",
    "addr:street":"Circle Dr",
    "iso:country":"US",
    "sg:address":"208 Circle Dr",
    "sg:city":"St Charles",
    "sg:classifiers":[
        {
            "category":"Insurance",
            "subcategory":"Insurance Agent",
            "type":"Services"
        }
    ],
    "sg:phone":"+1 507 932 4679",
    "sg:postcode":"55972",
    "sg:province":"MN",
    "wof:name":"New York Life Insurance",
    "wof:placetype":"venue"
},
  "geometry": {"coordinates":[-92.065344,43.978618],"type":"Point"}
}