{
  "type": "Feature",
  "properties": {
    "iso:country":"US",
    "sg:address":"6329 Langer Ln",
    "sg:city":"Hugo",
    "sg:classifiers":[
        {
            "category":"Professional",
            "subcategory":"Detective & Security Services",
            "type":"Services"
        }
    ],
    "sg:phone":"+1 651 762 3995",
    "sg:postcode":"55038",
    "sg:province":"MN",
    "sg:tags":[
        "information",
        "bureau"
    ],
    "wof:name":"Jungwirth Appraisal Services, Inc.",
    "wof:placetype":"venue"
},
  "geometry": {"coordinates":[-93.024503,45.140424],"type":"Point"}
}