{
  "type": "Feature",
  "properties": {
    "addr:full":"301 4th St E Thief River Falls MN 56701",
    "addr:housenumber":"301",
    "addr:postcode":"56701",
    "addr:street":"4Th St",
    "iso:country":"US",
    "sg:address":"301 4th St E",
    "sg:city":"Thief River Falls",
    "sg:classifiers":[
        {
            "category":"Local Transit",
            "type":"Transportation"
        }
    ],
    "sg:phone":"+1 218 681 6760",
    "sg:postcode":"56701",
    "sg:province":"MN",
    "sg:tags":[
        "bus",
        "line"
    ],
    "wof:name":"Bus-Heartland Ex Dispatch Off",
    "wof:placetype":"venue"
},
  "geometry": {"coordinates":[-96.17843999999999,48.120169],"type":"Point"}
}