{
  "type": "Feature",
  "properties": {
    "iso:country":"US",
    "sg:address":"17535 Chisholm St NE",
    "sg:city":"Andover",
    "sg:classifiers":[
        {
            "category":"Building & Trades",
            "subcategory":"Cleaning & Sanitation",
            "type":"Services"
        },
        {
            "category":"Building & Trades",
            "subcategory":"Construction",
            "type":"Services"
        }
    ],
    "sg:phone":"+1 763 434 6464",
    "sg:postcode":"55304",
    "sg:province":"MN",
    "sg:tags":[
        "repair",
        "system",
        "specialty",
        "furnaces-repairing",
        "heating",
        "contractor",
        "air conditioning"
    ],
    "sg:website":"http://www.andersonburnerservice.com",
    "wof:name":"Anderson Burner Service",
    "wof:placetype":"venue"
},
  "geometry": {"coordinates":[-93.230655,45.290648],"type":"Point"}
}