{
  "type": "Feature",
  "properties": {
    "iso:country":"US",
    "sg:address":"1415 5th St S",
    "sg:city":"Hopkins",
    "sg:classifiers":[
        {
            "category":"Wholesale",
            "subcategory":"Home Furnishings",
            "type":"Manufacturing & Wholesale Goods"
        }
    ],
    "sg:phone":"+1 952 238 7272",
    "sg:postcode":"55343",
    "sg:province":"MN",
    "sg:tags":[
        "closet",
        "accessory"
    ],
    "wof:name":"Contemporary Closets",
    "wof:placetype":"venue"
},
  "geometry": {"coordinates":[-93.419346,44.917188],"type":"Point"}
}