{
  "type": "Feature",
  "properties": {
    "addr:full":"575 Havana Rd Owatonna MN 55060",
    "addr:housenumber":"575",
    "addr:postcode":"55060",
    "addr:street":"Havana Rd",
    "iso:country":"US",
    "sg:address":"575 Havana Rd",
    "sg:city":"Owatonna",
    "sg:classifiers":[
        {
            "category":"Building & Trades",
            "subcategory":"Construction",
            "type":"Services"
        }
    ],
    "sg:phone":"+1 507 451 6647",
    "sg:postcode":"55060",
    "sg:province":"MN",
    "sg:tags":[
        "general",
        "contractor"
    ],
    "wof:name":"Gary Jones",
    "wof:placetype":"venue"
},
  "geometry": {"coordinates":[-93.214659,44.073293],"type":"Point"}
}