{
  "type": "Feature",
  "properties": {
    "iso:country":"US",
    "sg:address":"75 W 5th St",
    "sg:city":"St Paul",
    "sg:classifiers":[
        {
            "category":"Organizations",
            "subcategory":"Non-profit Organization",
            "type":"Services"
        }
    ],
    "sg:phone":"+1 651 484 9094",
    "sg:postcode":"55102",
    "sg:province":"MN",
    "wof:name":"American Association-Wdtrnrs",
    "wof:placetype":"venue"
},
  "geometry": {"coordinates":[-93.097606,44.945119],"type":"Point"}
}