{
  "type": "Feature",
  "properties": {
    "addr:full":"2525 Nevada Ave N Minneapolis MN 55427",
    "addr:housenumber":"2525",
    "addr:postcode":"55427",
    "addr:street":"Nevada Ave N",
    "iso:country":"US",
    "sg:address":"2525 Nevada Ave N",
    "sg:city":"Minneapolis",
    "sg:classifiers":[
        {
            "category":"Building & Trades",
            "subcategory":"Electrical",
            "type":"Services"
        }
    ],
    "sg:phone":"+1 763 545 2002",
    "sg:postcode":"55427",
    "sg:province":"MN",
    "sg:tags":[
        "electric",
        "contractor"
    ],
    "wof:name":"J Z Electric",
    "wof:placetype":"venue"
},
  "geometry": {"coordinates":[-93.372466,45.006935],"type":"Point"}
}