{
  "type": "Feature",
  "properties": {
    "addr:full":"6113 Upper 35th St N Saint Paul MN 55128",
    "addr:housenumber":"6113",
    "addr:postcode":"55128",
    "addr:street":"Upper 35Th St N",
    "iso:country":"US",
    "sg:address":"6113 Upper 35th St N",
    "sg:city":"Saint Paul",
    "sg:classifiers":[
        {
            "category":"Real Estate",
            "subcategory":"Real Estate Agent",
            "type":"Services"
        }
    ],
    "sg:phone":"+1 651 429 6211",
    "sg:postcode":"55128",
    "sg:province":"MN",
    "wof:name":"Weidner Appraisal Service",
    "wof:placetype":"venue"
},
  "geometry": {"coordinates":[-92.98072500000001,44.999108],"type":"Point"}
}