{
  "type": "Feature",
  "properties": {
    "addr:full":"11070 Tobys Ave SE Alexandria MN 56308",
    "addr:housenumber":"11070",
    "addr:postcode":"56308",
    "addr:street":"Tobys Ave Se",
    "iso:country":"US",
    "sg:address":"11070 Tobys Ave SE",
    "sg:city":"Alexandria",
    "sg:classifiers":[
        {
            "category":"Bars & Pubs",
            "type":"Food & Drink"
        }
    ],
    "sg:phone":"+1 320 762 1635",
    "sg:postcode":"56308",
    "sg:province":"MN",
    "wof:name":"Muddy Boot Bar & Grill",
    "wof:placetype":"venue"
},
  "geometry": {"coordinates":[-95.354403,45.791456],"type":"Point"}
}