{
  "type": "Feature",
  "properties": {
    "addr:full":"720 Evergreen Dr Burnsville MN 55337",
    "addr:housenumber":"720",
    "addr:postcode":"55337",
    "addr:street":"Evergreen Dr",
    "iso:country":"US",
    "sg:address":"720 Evergreen Dr",
    "sg:city":"Burnsville",
    "sg:classifiers":[
        {
            "category":"Building & Trades",
            "subcategory":"Cleaning & Sanitation",
            "type":"Services"
        }
    ],
    "sg:phone":"+1 952 997 7437",
    "sg:postcode":"55337",
    "sg:province":"MN",
    "sg:tags":[
        "maintenance"
    ],
    "wof:name":"Neat Sweeps Inc",
    "wof:placetype":"venue"
},
  "geometry": {"coordinates":[-93.265051,44.748202],"type":"Point"}
}