{
  "type": "Feature",
  "properties": {
    "addr:full":"28753 Water Street Rd Underwood MN 56586",
    "addr:housenumber":"28753",
    "addr:postcode":"56586",
    "addr:street":"Water Street Rd",
    "iso:country":"US",
    "sg:address":"28753 Water Street Rd",
    "sg:city":"Underwood",
    "sg:classifiers":[
        {
            "category":"Real Estate",
            "subcategory":"Real Estate Agent",
            "type":"Services"
        }
    ],
    "sg:phone":"+1 218 495 2000",
    "sg:postcode":"56586",
    "sg:province":"MN",
    "wof:name":"Northern Realty & Mortgage LLC",
    "wof:placetype":"venue"
},
  "geometry": {"coordinates":[-95.898392,46.388913],"type":"Point"}
}