{
  "type": "Feature",
  "properties": {
    "addr:full":"9373 Tewsbury Gate Osseo MN 55311",
    "addr:housenumber":"9373",
    "addr:postcode":"55311",
    "addr:street":"Tewsbury Gate",
    "iso:country":"US",
    "sg:address":"9373 Tewsbury Gate",
    "sg:city":"Osseo",
    "sg:classifiers":[
        {
            "category":"Professional",
            "subcategory":"Business Services",
            "type":"Services"
        }
    ],
    "sg:phone":"+1 763 416 0228",
    "sg:postcode":"55311",
    "sg:province":"MN",
    "sg:tags":[
        "development",
        "plan"
    ],
    "wof:name":"Jbdata Resources",
    "wof:placetype":"venue"
},
  "geometry": {"coordinates":[-93.519623,45.124898],"type":"Point"}
}