{
  "type": "Feature",
  "properties": {
    "addr:full":"400 1st St E Canby MN 56220",
    "addr:housenumber":"400",
    "addr:postcode":"56220",
    "addr:street":"1St St E",
    "iso:country":"US",
    "sg:address":"400 1st St E",
    "sg:city":"Canby",
    "sg:classifiers":[
        {
            "category":"Retail",
            "subcategory":"Auto Repair",
            "type":"Services"
        }
    ],
    "sg:phone":"+1 507 223 7353",
    "sg:postcode":"56220",
    "sg:province":"MN",
    "sg:tags":[
        "body",
        "automobile",
        "painting"
    ],
    "wof:name":"Jerome's Body Shop",
    "wof:placetype":"venue"
},
  "geometry": {"coordinates":[-96.27298999999999,44.706179],"type":"Point"}
}