{
  "type": "Feature",
  "properties": {
    "addr:full":"10000 Fremont Ave S Minneapolis MN 55431",
    "addr:housenumber":"10000",
    "addr:postcode":"55431",
    "addr:street":"Fremont Ave S",
    "iso:country":"US",
    "sg:address":"10000 Fremont Ave S",
    "sg:city":"Minneapolis",
    "sg:classifiers":[
        {
            "category":"Real Estate",
            "subcategory":"Real Estate Services",
            "type":"Services"
        },
        {
            "category":"Real Estate",
            "subcategory":"Real Estate Agent",
            "type":"Services"
        }
    ],
    "sg:phone":"+1 952 884 1000",
    "sg:postcode":"55431",
    "sg:province":"MN",
    "sg:tags":[
        "buyer",
        "management",
        "broker"
    ],
    "wof:name":"Wondra Properties",
    "wof:placetype":"venue"
},
  "geometry": {"coordinates":[-93.296204,44.82267],"type":"Point"}
}