{
  "type": "Feature",
  "properties": {
    "iso:country":"US",
    "sg:address":"5901 Raleigh St",
    "sg:city":"Duluth",
    "sg:classifiers":[
        {
            "category":"Professional",
            "subcategory":"Business Services",
            "type":"Services"
        }
    ],
    "sg:phone":"+1 218 628 0433",
    "sg:postcode":"55807",
    "sg:province":"MN",
    "wof:name":"Edison Project",
    "wof:placetype":"venue"
},
  "geometry": {"coordinates":[-92.173384,46.731259],"type":"Point"}
}