{
  "type": "Feature",
  "properties": {
    "iso:country":"US",
    "sg:address":"1609 County Road 42 W",
    "sg:city":"Burnsville",
    "sg:classifiers":[
        {
            "category":"Professional",
            "subcategory":"Printing & Photocopies",
            "type":"Services"
        }
    ],
    "sg:phone":"+1 952 892 6600",
    "sg:postcode":"55306",
    "sg:province":"MN",
    "wof:name":"Ups Store the",
    "wof:placetype":"venue"
},
  "geometry": {"coordinates":[-93.299797,44.7463],"type":"Point"}
}