{
  "type": "Feature",
  "properties": {
    "addr:full":"3770 Robin Ln Saint Paul MN 55122",
    "addr:housenumber":"3770",
    "addr:postcode":"55122",
    "addr:street":"Robin Ln",
    "iso:country":"US",
    "sg:address":"3770 Robin Ln",
    "sg:city":"Saint Paul",
    "sg:classifiers":[
        {
            "category":"Professional",
            "type":"Services"
        }
    ],
    "sg:phone":"+1 651 994 9322",
    "sg:postcode":"55122",
    "sg:province":"MN",
    "wof:name":"Joy Hedding",
    "wof:placetype":"venue"
},
  "geometry": {"coordinates":[-93.194627,44.822493],"type":"Point"}
}