{
  "type": "Feature",
  "properties": {
    "addr:full":"449 W 5th St Saint Charles MN 55972",
    "addr:housenumber":"449",
    "addr:postcode":"55972",
    "addr:street":"W 5Th St",
    "iso:country":"US",
    "sg:address":"449 W 5th St",
    "sg:city":"Saint Charles",
    "sg:classifiers":[
        {
            "category":"Freight",
            "type":"Transportation"
        }
    ],
    "sg:phone":"+1 507 932 3220",
    "sg:postcode":"55972",
    "sg:province":"MN",
    "sg:tags":[
        "operator",
        "local",
        "trucking"
    ],
    "wof:name":"Kieffers Trucking Service",
    "wof:placetype":"venue"
},
  "geometry": {"coordinates":[-92.070464,43.972873],"type":"Point"}
}