{
  "type": "Feature",
  "properties": {
    "iso:country":"US",
    "sg:address":"101 4th Ave N",
    "sg:city":"Princeton",
    "sg:classifiers":[
        {
            "category":"Retail",
            "subcategory":"Auto Repair",
            "type":"Services"
        }
    ],
    "sg:phone":"+1 763 389 3811",
    "sg:postcode":"55371",
    "sg:province":"MN",
    "sg:tags":[
        "general"
    ],
    "wof:name":"Rum River Automotive Inc",
    "wof:placetype":"venue"
},
  "geometry": {"coordinates":[-93.578614,45.569747],"type":"Point"}
}