{
  "type": "Feature",
  "properties": {
    "addr:full":"1751 Meadowlark Rd Saint Paul MN 55122",
    "addr:housenumber":"1751",
    "addr:postcode":"55122",
    "addr:street":"Meadowlark Rd",
    "iso:country":"US",
    "sg:address":"1751 Meadowlark Rd",
    "sg:city":"Saint Paul",
    "sg:classifiers":[
        {
            "category":"Home & Garden",
            "subcategory":"Household Appliances",
            "type":"Retail Goods"
        }
    ],
    "sg:phone":"+1 651 683 9298",
    "sg:postcode":"55122",
    "sg:province":"MN",
    "wof:name":"Fridge Guard Inc",
    "wof:placetype":"venue"
},
  "geometry": {"coordinates":[-93.192087,44.808507],"type":"Point"}
}