{
  "type": "Feature",
  "properties": {
    "addr:full":"1218 4th St NW Rochester MN 55901",
    "addr:housenumber":"1218",
    "addr:postcode":"55901",
    "addr:street":"4Th St Nw",
    "iso:country":"US",
    "sg:address":"1218 4th St NW",
    "sg:city":"Rochester",
    "sg:classifiers":[
        {
            "category":"Social Services",
            "subcategory":"Child Care",
            "type":"Services"
        }
    ],
    "sg:phone":"+1 507 282 9312",
    "sg:postcode":"55901",
    "sg:province":"MN",
    "sg:tags":[
        "daycare",
        "provider"
    ],
    "wof:name":"Ness Connie Day Care",
    "wof:placetype":"venue"
},
  "geometry": {"coordinates":[-92.48234600000001,44.026782],"type":"Point"}
}