{
  "type": "Feature",
  "properties": {
    "addr:full":"210 3rd St S St Cloud MN 56301",
    "addr:housenumber":"210",
    "addr:postcode":"56301",
    "addr:street":"3Rd St S",
    "iso:country":"US",
    "sg:address":"210 3rd St S",
    "sg:city":"St Cloud",
    "sg:classifiers":[
        {
            "category":"Real Estate",
            "subcategory":"Real Estate Operator",
            "type":"Services"
        }
    ],
    "sg:phone":"+1 320 255 5545",
    "sg:postcode":"56301",
    "sg:province":"MN",
    "sg:tags":[
        "apartment"
    ],
    "wof:name":"Highbanks Apartments",
    "wof:placetype":"venue"
},
  "geometry": {"coordinates":[-94.153218,45.559269],"type":"Point"}
}