{
  "type": "Feature",
  "properties": {
    "addr:full":"19750 Muirfield Cir Excelsior MN 55331",
    "addr:housenumber":"19750",
    "addr:postcode":"55331",
    "addr:street":"Muirfield Cir",
    "iso:country":"US",
    "sg:address":"19750 Muirfield Cir",
    "sg:city":"Excelsior",
    "sg:classifiers":[
        {
            "category":"Professional",
            "subcategory":"Computer Services",
            "type":"Services"
        }
    ],
    "sg:phone":"+1 952 380 0182",
    "sg:postcode":"55331",
    "sg:province":"MN",
    "sg:tags":[
        "datum"
    ],
    "wof:name":"Corey Franklin",
    "wof:placetype":"venue"
},
  "geometry": {"coordinates":[-93.531948,44.903985],"type":"Point"}
}