{
  "type": "Feature",
  "properties": {
    "iso:country":"US",
    "sg:address":"402 S 7th St",
    "sg:city":"Brainerd",
    "sg:classifiers":[
        {
            "category":"Communications",
            "type":"Services"
        }
    ],
    "sg:phone":"+1 218 829 9547",
    "sg:postcode":"56401",
    "sg:province":"MN",
    "wof:name":"FSH Communications",
    "wof:placetype":"venue"
},
  "geometry": {"coordinates":[-94.199224,46.354728],"type":"Point"}
}