{
  "type": "Feature",
  "properties": {
    "addr:full":"210 S 4th St Beaver Creek MN 56116",
    "addr:housenumber":"210",
    "addr:postcode":"56116",
    "addr:street":"S 4Th St",
    "iso:country":"US",
    "sg:address":"210 S 4th St",
    "sg:city":"Beaver Creek",
    "sg:classifiers":[
        {
            "category":"Building & Trades",
            "subcategory":"Construction",
            "type":"Services"
        }
    ],
    "sg:phone":"+1 507 673 2548",
    "sg:postcode":"56116",
    "sg:province":"MN",
    "sg:tags":[
        "insulation",
        "heat",
        "contractor"
    ],
    "wof:name":"New Prairie Insulation Inc",
    "wof:placetype":"venue"
},
  "geometry": {"coordinates":[-96.36270500000001,43.613019],"type":"Point"}
}