{
  "type": "Feature",
  "properties": {
    "addr:full":"6075 McKinley Pl Excelsior MN 55331",
    "addr:housenumber":"6075",
    "addr:postcode":"55331",
    "addr:street":"Mckinley Pl",
    "iso:country":"US",
    "sg:address":"6075 McKinley Pl",
    "sg:city":"Excelsior",
    "sg:classifiers":[
        {
            "category":"Shopping",
            "subcategory":"Music",
            "type":"Retail Goods"
        }
    ],
    "sg:phone":"+1 952 470 0105",
    "sg:postcode":"55331",
    "sg:province":"MN",
    "wof:name":"Play Hooky Records",
    "wof:placetype":"venue"
},
  "geometry": {"coordinates":[-93.52426199999999,44.895135],"type":"Point"}
}