{
  "type": "Feature",
  "properties": {
    "iso:country":"US",
    "sg:address":"10950 175th Ct W",
    "sg:city":"Lakeville",
    "sg:classifiers":[
        {
            "category":"Restaurant",
            "type":"Food & Drink"
        },
        {
            "category":"Ice Cream",
            "type":"Food & Drink"
        }
    ],
    "sg:menulink":"http://www.allmenus.com/mn/lakeville/168301-dairy-queen/menu/",
    "sg:phone":"+1 952 892 5001",
    "sg:postcode":"55044",
    "sg:province":"MN",
    "sg:tags":[
        "burger",
        "american",
        "ice",
        "cream"
    ],
    "wof:name":"Dairy Queen",
    "wof:placetype":"venue"
},
  "geometry": {"coordinates":[-93.287565,44.695002],"type":"Point"}
}