{
  "type": "Feature",
  "properties": {
    "iso:country":"US",
    "sg:address":"2109 S Broadway",
    "sg:city":"Rochester",
    "sg:classifiers":[
        {
            "category":"Home & Garden",
            "subcategory":"Household Appliances",
            "type":"Retail Goods"
        }
    ],
    "sg:phone":"+1 507 281 7686",
    "sg:postcode":"55904",
    "sg:province":"MN",
    "sg:tags":[
        "cleaners",
        "vacuum"
    ],
    "wof:name":"Kirby Co",
    "wof:placetype":"venue"
},
  "geometry": {"coordinates":[-92.46250999999999,43.99145],"type":"Point"}
}