{
  "type": "Feature",
  "properties": {
    "addr:full":"113 6th Ave Tower MN 55721",
    "addr:housenumber":"113",
    "addr:postcode":"55721",
    "addr:street":"6Th Ave",
    "iso:country":"US",
    "sg:address":"113 6th Ave",
    "sg:city":"Tower",
    "sg:classifiers":[
        {
            "category":"Travel",
            "subcategory":"Hotels & Motels",
            "type":"Entertainment"
        }
    ],
    "sg:phone":"+1 218 342 2141",
    "sg:postcode":"55721",
    "sg:province":"MN",
    "sg:tags":[
        "operation"
    ],
    "wof:name":"Homestead Motel",
    "wof:placetype":"venue"
},
  "geometry": {"coordinates":[-93.629687,47.262143],"type":"Point"}
}