{
  "type": "Feature",
  "properties": {
    "addr:full":"110 N Sunset Blvd Caledonia MN 55921",
    "addr:housenumber":"110",
    "addr:postcode":"55921",
    "addr:street":"N Sunset Blvd",
    "iso:country":"US",
    "sg:address":"110 N Sunset Blvd",
    "sg:city":"Caledonia",
    "sg:classifiers":[
        {
            "category":"Autos & Motor Vehicles",
            "subcategory":"Fuel & Gas Station",
            "type":"Retail Goods"
        }
    ],
    "sg:phone":"+1 507 724 2906",
    "sg:postcode":"55921",
    "sg:province":"MN",
    "sg:tags":[
        "convenience",
        "station",
        "store"
    ],
    "wof:name":"KWIK Trip",
    "wof:placetype":"venue"
},
  "geometry": {"coordinates":[-91.50434,43.6351],"type":"Point"}
}