{
  "type": "Feature",
  "properties": {
    "addr:full":"809 6th St S Virginia MN 55792",
    "addr:housenumber":"809",
    "addr:postcode":"55792",
    "addr:street":"6Th St S",
    "iso:country":"US",
    "sg:address":"809 6th St S",
    "sg:city":"Virginia",
    "sg:classifiers":[
        {
            "category":"Building & Trades",
            "subcategory":"Construction",
            "type":"Services"
        }
    ],
    "sg:phone":"+1 218 749 3862",
    "sg:postcode":"55792",
    "sg:province":"MN",
    "sg:tags":[
        "house"
    ],
    "wof:name":"Meglen Construction",
    "wof:placetype":"venue"
},
  "geometry": {"coordinates":[-92.544838,47.517512],"type":"Point"}
}