{
  "type": "Feature",
  "properties": {
    "iso:country":"US",
    "sg:address":"6801 Hickory St NE",
    "sg:city":"Minneapolis",
    "sg:classifiers":[
        {
            "category":"Shopping",
            "subcategory":"Hobbies, Toys, & Games",
            "type":"Retail Goods"
        }
    ],
    "sg:phone":"+1 763 571 0011",
    "sg:postcode":"55432",
    "sg:province":"MN",
    "sg:tags":[
        "toy",
        "store",
        "supply"
    ],
    "wof:name":"J&B Crafts",
    "wof:placetype":"venue"
},
  "geometry": {"coordinates":[-93.27423899999999,45.091911],"type":"Point"}
}