{
  "type": "Feature",
  "properties": {
    "addr:full":"6783 690th Ave Wheaton MN 56296",
    "addr:housenumber":"6783",
    "addr:postcode":"56296",
    "addr:street":"690Th Ave",
    "iso:country":"US",
    "sg:address":"6783 690th Ave",
    "sg:city":"Wheaton",
    "sg:classifiers":[
        {
            "category":"Professional",
            "subcategory":"Lawyer & Legal Services",
            "type":"Services"
        }
    ],
    "sg:phone":"+1 320 563 8644",
    "sg:postcode":"56296",
    "sg:province":"MN",
    "sg:tags":[
        "attorney"
    ],
    "wof:name":"Lundquist Family, Llp",
    "wof:placetype":"venue"
},
  "geometry": {"coordinates":[-96.448593,45.843689],"type":"Point"}
}