{
  "type": "Feature",
  "properties": {
    "addr:full":"1417 Fish Hook Ave Park Rapids MN 56470",
    "addr:housenumber":"1417",
    "addr:postcode":"56470",
    "addr:street":"Fish Hook Ave",
    "iso:country":"US",
    "sg:address":"1417 Fish Hook Ave",
    "sg:city":"Park Rapids",
    "sg:classifiers":[
        {
            "category":"Travel",
            "subcategory":"Hotels & Motels",
            "type":"Entertainment"
        }
    ],
    "sg:phone":"+1 218 732 0366",
    "sg:postcode":"56470",
    "sg:province":"MN",
    "sg:tags":[
        "operation"
    ],
    "wof:name":"Red Bridge Inn",
    "wof:placetype":"venue"
},
  "geometry": {"coordinates":[-95.047856,46.908462],"type":"Point"}
}