{
  "type": "Feature",
  "properties": {
    "addr:full":"1553 Larpenteur Ave W St Paul MN 55113",
    "addr:housenumber":"1553",
    "addr:postcode":"55113",
    "addr:street":"Larpenteur Ave W",
    "iso:country":"US",
    "sg:address":"1553 Larpenteur Ave W",
    "sg:city":"St Paul",
    "sg:classifiers":[
        {
            "category":"Shopping",
            "subcategory":"Tobacco",
            "type":"Retail Goods"
        }
    ],
    "sg:phone":"+1 651 917 3572",
    "sg:postcode":"55113",
    "sg:province":"MN",
    "sg:tags":[
        "cigarette",
        "cigar",
        "dealer"
    ],
    "wof:name":"W J Tobacco",
    "wof:placetype":"venue"
},
  "geometry": {"coordinates":[-93.165294,44.991854],"type":"Point"}
}