{
  "type": "Feature",
  "properties": {
    "addr:full":"2600 26th Ave S Ste 200 Minneapolis MN 55406",
    "addr:housenumber":"2600",
    "addr:postcode":"55406",
    "addr:street":"26Th Ave S Ste 200",
    "iso:country":"US",
    "sg:address":"2600 26th Ave S Ste 200",
    "sg:city":"Minneapolis",
    "sg:classifiers":[
        {
            "category":"Wholesale",
            "subcategory":"Computers",
            "type":"Manufacturing & Wholesale Goods"
        },
        {
            "category":"Professional",
            "subcategory":"Computer Services",
            "type":"Services"
        }
    ],
    "sg:phone":"+1 612 623 9144",
    "sg:postcode":"55406",
    "sg:province":"MN",
    "sg:tags":[
        "repair"
    ],
    "sg:website":"quecomputers.com/",
    "wof:name":"Que Computers",
    "wof:placetype":"venue"
},
  "geometry": {"coordinates":[-93.235524,44.955034],"type":"Point"}
}