{
  "type": "Feature",
  "properties": {
    "addr:full":"66366 Co Rd 21 New Ulm MN 56073",
    "addr:housenumber":"66366;21",
    "addr:postcode":"56073",
    "addr:street":"Co Rd",
    "iso:country":"US",
    "sg:address":"66366 Co Rd 21",
    "sg:city":"New Ulm",
    "sg:classifiers":[
        {
            "category":"Wholesale",
            "subcategory":"Machinery & Supplies",
            "type":"Manufacturing & Wholesale Goods"
        },
        {
            "category":"Home & Garden",
            "subcategory":"Garden Supply",
            "type":"Retail Goods"
        }
    ],
    "sg:phone":"+1 507 359 5000",
    "sg:postcode":"56073",
    "sg:province":"MN",
    "sg:tags":[
        "engine",
        "equipment",
        "industrial"
    ],
    "wof:name":"Brian's Repair",
    "wof:placetype":"venue"
},
  "geometry": {"coordinates":[-94.615241,44.392208],"type":"Point"}
}