{
  "type": "Feature",
  "properties": {
    "iso:country":"US",
    "sg:address":"1105 Industry Ave",
    "sg:city":"Cloquet",
    "sg:classifiers":[
        {
            "category":"Home & Garden",
            "subcategory":"Building Materials",
            "type":"Retail Goods"
        }
    ],
    "sg:phone":"+1 218 879 4344",
    "sg:postcode":"55720",
    "sg:province":"MN",
    "sg:tags":[
        "mixed",
        "concrete"
    ],
    "wof:name":"Cloquet Ready Mix",
    "wof:placetype":"venue"
},
  "geometry": {"coordinates":[-92.44934000000001,46.725215],"type":"Point"}
}