{
  "type": "Feature",
  "properties": {
    "addr:full":"420 N 5th St Ste 935 Minneapolis MN 55401",
    "addr:housenumber":"420",
    "addr:postcode":"55401",
    "addr:street":"N 5Th St Ste 935",
    "iso:country":"US",
    "sg:address":"420 N 5th St Ste 935",
    "sg:city":"Minneapolis",
    "sg:classifiers":[
        {
            "category":"Education",
            "subcategory":"Library",
            "type":"Public Place"
        }
    ],
    "sg:phone":"+1 612 435 0830",
    "sg:postcode":"55401",
    "sg:province":"MN",
    "sg:tags":[
        "research"
    ],
    "wof:name":"Intune Professional Document Services, Inc.",
    "wof:placetype":"venue"
},
  "geometry": {"coordinates":[-93.277576,44.983211],"type":"Point"}
}