{
  "type": "Feature",
  "properties": {
    "addr:full":"2216 Co Rd D W Saint Paul MN 55112",
    "addr:housenumber":"2216",
    "addr:postcode":"55112",
    "addr:street":"Co Rd D W",
    "iso:country":"US",
    "sg:address":"2216 Co Rd D W",
    "sg:city":"Saint Paul",
    "sg:classifiers":[
        {
            "category":"Food & Beverages",
            "subcategory":"Liquor & Beverages",
            "type":"Retail Goods"
        }
    ],
    "sg:phone":"+1 651 639 0122",
    "sg:postcode":"55112",
    "sg:province":"MN",
    "sg:tags":[
        "store"
    ],
    "wof:name":"Tower Glen Inc",
    "wof:placetype":"venue"
},
  "geometry": {"coordinates":[-93.192307,45.035383],"type":"Point"}
}