{
  "type": "Feature",
  "properties": {
    "addr:full":"511 Main St Henderson MN 56044",
    "addr:housenumber":"511",
    "addr:postcode":"56044",
    "addr:street":"Main St",
    "iso:country":"US",
    "sg:address":"511 Main St",
    "sg:city":"Henderson",
    "sg:classifiers":[
        {
            "category":"Professional",
            "subcategory":"Lawyer & Legal Services",
            "type":"Services"
        }
    ],
    "sg:phone":"+1 507 248 3245",
    "sg:postcode":"56044",
    "sg:province":"MN",
    "sg:tags":[
        "attorney"
    ],
    "wof:name":"Nelson & Jones",
    "wof:placetype":"venue"
},
  "geometry": {"coordinates":[-93.907056,44.528175],"type":"Point"}
}