{
  "type": "Feature",
  "properties": {
    "addr:full":"109 1st Ave W Upsala MN 56360",
    "addr:housenumber":"109",
    "addr:postcode":"56360",
    "addr:street":"1St Ave W",
    "iso:country":"US",
    "sg:address":"109 1st Ave W",
    "sg:city":"Upsala",
    "sg:classifiers":[
        {
            "category":"Home & Garden",
            "subcategory":"Building Materials",
            "type":"Retail Goods"
        }
    ],
    "sg:phone":"+1 320 573 4527",
    "sg:postcode":"56360",
    "sg:province":"MN",
    "sg:tags":[
        "glass",
        "window",
        "plate"
    ],
    "wof:name":"Mike Nelson Auto Glass",
    "wof:placetype":"venue"
},
  "geometry": {"coordinates":[-95.153897,45.869],"type":"Point"}
}