{
  "type": "Feature",
  "properties": {
    "addr:full":"215 Main St N Greenbush MN 56726",
    "addr:housenumber":"215",
    "addr:postcode":"56726",
    "addr:street":"Main St N",
    "iso:country":"US",
    "sg:address":"215 Main St N",
    "sg:city":"Greenbush",
    "sg:classifiers":[
        {
            "category":"Home & Garden",
            "subcategory":"Hardware",
            "type":"Retail Goods"
        }
    ],
    "sg:phone":"+1 218 782 2110",
    "sg:postcode":"56726",
    "sg:province":"MN",
    "wof:name":"Ace Hardware",
    "wof:placetype":"venue"
},
  "geometry": {"coordinates":[-96.18179499999999,48.701566],"type":"Point"}
}