{
  "type": "Feature",
  "properties": {
    "iso:country":"US",
    "sg:address":"402 NE Clark Dr",
    "sg:city":"Verndale",
    "sg:classifiers":[
        {
            "category":"Manufacturing",
            "subcategory":"Building Materials",
            "type":"Manufacturing & Wholesale Goods"
        }
    ],
    "sg:phone":"+1 218 445 5130",
    "sg:postcode":"56481",
    "sg:province":"MN",
    "sg:tags":[
        "member",
        "mfg",
        "wood",
        "structural"
    ],
    "wof:name":"Verndale Truss Inc",
    "wof:placetype":"venue"
},
  "geometry": {"coordinates":[-95.009231,46.397735],"type":"Point"}
}