{
  "type": "Feature",
  "properties": {
    "iso:country":"US",
    "sg:address":"1150 Queens Ln",
    "sg:city":"Anoka",
    "sg:classifiers":[
        {
            "category":"Shopping",
            "subcategory":"Antiques",
            "type":"Retail Goods"
        }
    ],
    "sg:phone":"+1 763 576 1935",
    "sg:postcode":"55303",
    "sg:province":"MN",
    "wof:name":"The Clock Shop",
    "wof:placetype":"venue"
},
  "geometry": {"coordinates":[-93.374802,45.1852],"type":"Point"}
}