{
  "type": "Feature",
  "properties": {
    "addr:full":"1314 W Oakland Ave Austin MN 55912",
    "addr:housenumber":"1314",
    "addr:postcode":"55912",
    "addr:street":"W Oakland Ave",
    "iso:country":"US",
    "sg:address":"1314 W Oakland Ave",
    "sg:city":"Austin",
    "sg:classifiers":[
        {
            "category":"Autos & Motor Vehicles",
            "subcategory":"Automobile Sales",
            "type":"Retail Goods"
        }
    ],
    "sg:phone":"+1 507 433 2397",
    "sg:postcode":"55912",
    "sg:province":"MN",
    "sg:tags":[
        "used"
    ],
    "wof:name":"Usem Chevrolet",
    "wof:placetype":"venue"
},
  "geometry": {"coordinates":[-92.992529,43.666662],"type":"Point"}
}