{
  "type": "Feature",
  "properties": {
    "addr:full":"6440 Flying Cloud Dr Eden Prairie MN 55344",
    "addr:housenumber":"6440",
    "addr:postcode":"55344",
    "addr:street":"Flying Cloud Dr",
    "iso:country":"US",
    "sg:address":"6440 Flying Cloud Dr",
    "sg:city":"Eden Prairie",
    "sg:classifiers":[
        {
            "category":"Manufacturing",
            "subcategory":"Tools & Machinery",
            "type":"Manufacturing & Wholesale Goods"
        }
    ],
    "sg:phone":"+1 952 943 2378",
    "sg:postcode":"55344",
    "sg:province":"MN",
    "sg:tags":[
        "auto",
        "devices",
        "mfg"
    ],
    "wof:name":"Rein Tracker",
    "wof:placetype":"venue"
},
  "geometry": {"coordinates":[-93.402117,44.886769],"type":"Point"}
}