{
  "type": "Feature",
  "properties": {
    "iso:country":"US",
    "sg:address":"4035 Lancaster Ln N",
    "sg:city":"Plymouth",
    "sg:classifiers":[
        {
            "category":"Banks & Credit Unions",
            "subcategory":"Investment Brokerage",
            "type":"Services"
        }
    ],
    "sg:phone":"+1 763 542 0188",
    "sg:postcode":"55441",
    "sg:province":"MN",
    "sg:tags":[
        "security"
    ],
    "wof:name":"Lancaster Financial Group",
    "wof:placetype":"venue"
},
  "geometry": {"coordinates":[-93.401462,45.025673],"type":"Point"}
}