{
  "type": "Feature",
  "properties": {
    "addr:full":"6800 France Ave S Edina MN 55435",
    "addr:housenumber":"6800",
    "addr:postcode":"55435",
    "addr:street":"France Ave S",
    "iso:country":"US",
    "sg:address":"6800 France Ave S",
    "sg:city":"Edina",
    "sg:classifiers":[
        {
            "category":"Banks & Credit Unions",
            "subcategory":"Investment Brokerage",
            "type":"Services"
        },
        {
            "category":"Insurance",
            "subcategory":"Insurance Agent",
            "type":"Services"
        }
    ],
    "sg:phone":"+1 952 885 2714",
    "sg:postcode":"55435",
    "sg:province":"MN",
    "sg:tags":[
        "advisory",
        "administrator",
        "financial",
        "third",
        "pension",
        "party"
    ],
    "wof:name":"Octagon Retirement Plan Svcs",
    "wof:placetype":"venue"
},
  "geometry": {"coordinates":[-93.328957,44.878161],"type":"Point"}
}