{
  "type": "Feature",
  "properties": {
    "addr:full":"1120 NW 4th St Grand Rapids MN 55744",
    "addr:housenumber":"1120",
    "addr:postcode":"55744",
    "addr:street":"Nw 4Th St",
    "iso:country":"US",
    "sg:address":"1120 NW 4th St",
    "sg:city":"Grand Rapids",
    "sg:classifiers":[
        {
            "category":"Building & Trades",
            "subcategory":"Plumbing",
            "type":"Services"
        }
    ],
    "sg:phone":"+1 218 326 5297",
    "sg:postcode":"55744",
    "sg:province":"MN",
    "sg:tags":[
        "heating",
        "business",
        "contractor"
    ],
    "wof:name":"Centsible Heating & Air Cond",
    "wof:placetype":"venue"
},
  "geometry": {"coordinates":[-93.54494699999999,47.235927],"type":"Point"}
}