{
  "type": "Feature",
  "properties": {
    "addr:full":"20511 550th Ave Grove City MN 56243",
    "addr:housenumber":"20511",
    "addr:postcode":"56243",
    "addr:street":"550Th Ave",
    "iso:country":"US",
    "sg:address":"20511 550th Ave",
    "sg:city":"Grove City",
    "sg:phone":"+1 320 857 2662",
    "sg:postcode":"56243",
    "sg:province":"MN",
    "sg:tags":[
        "farm",
        "corn",
        "soybean"
    ],
    "wof:name":"Wilfred Huisman",
    "wof:placetype":"venue"
},
  "geometry": {"coordinates":[-94.66575899999999,45.051413],"type":"Point"}
}