{
  "type": "Feature",
  "properties": {
    "addr:full":"32205 Co Rd 9 Mountain Lake MN 56159",
    "addr:housenumber":"32205",
    "addr:postcode":"56159",
    "addr:street":"Co Rd 9",
    "iso:country":"US",
    "sg:address":"32205 Co Rd 9",
    "sg:city":"Mountain Lake",
    "sg:classifiers":[
        {
            "category":"Farming",
            "subcategory":"Farm",
            "type":"Manufacturing & Wholesale Goods"
        }
    ],
    "sg:phone":"+1 507 427 8987",
    "sg:postcode":"56159",
    "sg:province":"MN",
    "wof:name":"Clarson Family Farms",
    "wof:placetype":"venue"
},
  "geometry": {"coordinates":[-94.999584,44.018916],"type":"Point"}
}