{
  "type": "Feature",
  "properties": {
    "addr:full":"16 Bridge Sq Northfield MN 55057",
    "addr:housenumber":"16",
    "addr:postcode":"55057",
    "addr:street":"Bridge Sq",
    "iso:country":"US",
    "sg:address":"16 Bridge Sq",
    "sg:city":"Northfield",
    "sg:classifiers":[
        {
            "category":"Building & Trades",
            "subcategory":"Construction",
            "type":"Services"
        }
    ],
    "sg:phone":"+1 507 645 2452",
    "sg:postcode":"55057",
    "sg:province":"MN",
    "sg:tags":[
        "repairing",
        "remodeling",
        "contractor"
    ],
    "wof:name":"Circa Restoration Studio",
    "wof:placetype":"venue"
},
  "geometry": {"coordinates":[-93.16090699999999,44.456071],"type":"Point"}
}