{
  "type": "Feature",
  "properties": {
    "iso:country":"US",
    "sg:address":"1260 Grey Fox Rd",
    "sg:city":"Arden Hills",
    "sg:classifiers":[
        {
            "category":"Retail",
            "subcategory":"Auto Rental",
            "type":"Services"
        }
    ],
    "sg:phone":"+1 651 490 0332",
    "sg:postcode":"55112",
    "sg:province":"MN",
    "sg:tags":[
        "renting",
        "truck",
        "leasing"
    ],
    "wof:name":"Allstate Leasing",
    "wof:placetype":"venue"
},
  "geometry": {"coordinates":[-93.156339,45.053747],"type":"Point"}
}