{
  "type": "Feature",
  "properties": {
    "addr:full":"701 25th Ave S Sste 200 Minneapolis MN 55454",
    "addr:housenumber":"701;200",
    "addr:postcode":"55454",
    "addr:street":"25Th Ave S Sste",
    "iso:country":"US",
    "sg:address":"701 25th Ave S Sste 200",
    "sg:city":"Minneapolis",
    "sg:classifiers":[
        {
            "category":"Health Services",
            "subcategory":"Doctor",
            "type":"Services"
        },
        {
            "category":"Health Services",
            "subcategory":"Clinic",
            "type":"Services"
        }
    ],
    "sg:phone":"+1 612 339 2836",
    "sg:postcode":"55454",
    "sg:province":"MN",
    "sg:tags":[
        "physician",
        "medical",
        "surgeons",
        "otorhinolaryngology",
        "nose",
        "throat",
        "surgeon",
        "ear"
    ],
    "sg:website":"http://www.pehni.com",
    "wof:name":"Paparella Ear Head and Neck Institute",
    "wof:placetype":"venue"
},
  "geometry": {"coordinates":[-93.23616800000001,44.966599],"type":"Point"}
}