{
  "type": "Feature",
  "properties": {
    "addr:full":"1761 Geneva Ave N St Paul MN 55128",
    "addr:housenumber":"1761",
    "addr:postcode":"55128",
    "addr:street":"Geneva Ave N",
    "iso:country":"US",
    "sg:address":"1761 Geneva Ave N",
    "sg:city":"St Paul",
    "sg:classifiers":[
        {
            "category":"Building & Trades",
            "subcategory":"Construction",
            "type":"Services"
        }
    ],
    "sg:phone":"+1 651 578 2994",
    "sg:postcode":"55128",
    "sg:province":"MN",
    "sg:tags":[
        "masonry",
        "contractor"
    ],
    "wof:name":"Anderson Masonry Xmlam Cncrt",
    "wof:placetype":"venue"
},
  "geometry": {"coordinates":[-92.984703,44.974623],"type":"Point"}
}