{
  "type": "Feature",
  "properties": {
    "iso:country":"US",
    "sg:address":"230 Chestnut St W",
    "sg:city":"Virginia",
    "sg:classifiers":[
        {
            "category":"Organizations",
            "subcategory":"Religious Organization",
            "type":"Services"
        }
    ],
    "sg:phone":"+1 218 749 1627",
    "sg:postcode":"55792",
    "sg:province":"MN",
    "sg:tags":[
        "membership"
    ],
    "wof:name":"Salvation Army Store",
    "wof:placetype":"venue"
},
  "geometry": {"coordinates":[-92.534339,47.523117],"type":"Point"}
}