{
  "type": "Feature",
  "properties": {
    "addr:full":"1701 E Hennepin Ave # 150 Minneapolis MN 55414",
    "addr:housenumber":"1701",
    "addr:postcode":"55414",
    "addr:street":"E Hennepin Ave # 150",
    "iso:country":"US",
    "sg:address":"1701 E Hennepin Ave # 150",
    "sg:city":"Minneapolis",
    "sg:classifiers":[
        {
            "category":"Wholesale",
            "subcategory":"Photographic Equipment",
            "type":"Manufacturing & Wholesale Goods"
        }
    ],
    "sg:phone":"+1 612 378 4767",
    "sg:postcode":"55414",
    "sg:province":"MN",
    "sg:tags":[
        "supplies-wholesale",
        "manufacturer"
    ],
    "wof:name":"T R I",
    "wof:placetype":"venue"
},
  "geometry": {"coordinates":[-93.228326,44.99148],"type":"Point"}
}