{
  "type": "Feature",
  "properties": {
    "addr:full":"2520 Broadway St NE # 200 Minneapolis MN 55413",
    "addr:housenumber":"2520",
    "addr:postcode":"55413",
    "addr:street":"Broadway St Ne # 200",
    "iso:country":"US",
    "sg:address":"2520 Broadway St NE # 200",
    "sg:city":"Minneapolis",
    "sg:classifiers":[
        {
            "category":"Professional",
            "subcategory":"Employment Agencies",
            "type":"Services"
        }
    ],
    "sg:phone":"+1 651 331 8302",
    "sg:postcode":"55413",
    "sg:province":"MN",
    "sg:tags":[
        "employer"
    ],
    "wof:name":"Office & Prof Employees Intern",
    "wof:placetype":"venue"
},
  "geometry": {"coordinates":[-93.225245,44.998715],"type":"Point"}
}