{
  "type": "Feature",
  "properties": {
    "iso:country":"US",
    "sg:address":"68549 300th St",
    "sg:city":"Litchfield",
    "sg:classifiers":[
        {
            "category":"Wholesale",
            "subcategory":"Farm Supplies",
            "type":"Manufacturing & Wholesale Goods"
        }
    ],
    "sg:phone":"+1 320 693 5884",
    "sg:postcode":"55355",
    "sg:province":"MN",
    "sg:tags":[
        "livestock"
    ],
    "wof:name":"K Bar K Cattle Co",
    "wof:placetype":"venue"
},
  "geometry": {"coordinates":[-94.388187,45.181105],"type":"Point"}
}