{
  "type": "Feature",
  "properties": {
    "iso:country":"US",
    "sg:address":"3978 Oak Ln NE",
    "sg:city":"Circle Pines",
    "sg:classifiers":[
        {
            "category":"Building & Trades",
            "subcategory":"Cleaning & Sanitation",
            "type":"Services"
        }
    ],
    "sg:phone":"+1 612 925 1373",
    "sg:postcode":"55014",
    "sg:province":"MN",
    "sg:tags":[
        "janitor"
    ],
    "wof:name":"Dinius Drain Cleaning",
    "wof:placetype":"venue"
},
  "geometry": {"coordinates":[-93.16951,45.144097],"type":"Point"}
}