{
  "type": "Feature",
  "properties": {
    "addr:full":"1681 Commerce Dr North Mankato MN 56003",
    "addr:housenumber":"1681",
    "addr:postcode":"56003",
    "addr:street":"Commerce Dr North",
    "iso:country":"US",
    "sg:address":"1681 Commerce Dr",
    "sg:city":"North Mankato",
    "sg:classifiers":[
        {
            "category":"Health Services",
            "subcategory":"Health Practitioner",
            "type":"Services"
        }
    ],
    "sg:phone":"+1 507 625 8017",
    "sg:postcode":"56003",
    "sg:province":"MN",
    "sg:tags":[
        "therapist",
        "physical"
    ],
    "wof:name":"Wenger Physical Therapy",
    "wof:placetype":"venue"
},
  "geometry": {"coordinates":[-94.033124,44.179369],"type":"Point"}
}