{
  "type": "Feature",
  "properties": {
    "iso:country":"US",
    "sg:address":"5650 Polk St NE",
    "sg:city":"Minneapolis",
    "sg:classifiers":[
        {
            "category":"Professional",
            "subcategory":"Business Services",
            "type":"Services"
        }
    ],
    "sg:phone":"+1 612 388 5321",
    "sg:postcode":"55432",
    "sg:province":"MN",
    "sg:tags":[
        "recording",
        "studio"
    ],
    "wof:name":"Misunderstood Rec",
    "wof:placetype":"venue"
},
  "geometry": {"coordinates":[-93.24504399999999,45.069918],"type":"Point"}
}