{
  "type": "Feature",
  "properties": {
    "addr:full":"14560 Shannon Pkwy # 601 Rosemount MN 55068",
    "addr:housenumber":"14560;601",
    "addr:postcode":"55068",
    "addr:street":"Shannon Pkwy #;Rosemount",
    "iso:country":"US",
    "sg:address":"14560 Shannon Pkwy # 601",
    "sg:city":"Rosemount",
    "sg:classifiers":[
        {
            "category":"Professional",
            "subcategory":"Computer Services",
            "type":"Services"
        }
    ],
    "sg:phone":"+1 651 983 8089",
    "sg:postcode":"55068",
    "sg:province":"MN",
    "sg:tags":[
        "graphic"
    ],
    "sg:website":"http://www.digicitymn.com",
    "wof:name":"Digicity Inc",
    "wof:placetype":"venue"
},
  "geometry": {"coordinates":[-93.146303,44.737745],"type":"Point"}
}