{
  "type": "Feature",
  "properties": {
    "addr:full":"16366 County Road 30 Osseo MN 55311",
    "addr:housenumber":"16366",
    "addr:postcode":"55311",
    "addr:street":"County Road 30",
    "iso:country":"US",
    "sg:address":"16366 County Road 30",
    "sg:city":"Osseo",
    "sg:classifiers":[
        {
            "category":"Personal",
            "subcategory":"Day Spa",
            "type":"Services"
        }
    ],
    "sg:phone":"+1 763 416 1700",
    "sg:postcode":"55311",
    "sg:province":"MN",
    "wof:name":"Karrin's Concept Salon",
    "wof:placetype":"venue"
},
  "geometry": {"coordinates":[-93.488297,45.1273],"type":"Point"}
}