{
  "type": "Feature",
  "properties": {
    "addr:full":"20601 Jasmine Path Lakeville MN 55044",
    "addr:housenumber":"20601",
    "addr:postcode":"55044",
    "addr:street":"Jasmine Path",
    "iso:country":"US",
    "sg:address":"20601 Jasmine Path",
    "sg:city":"Lakeville",
    "sg:classifiers":[
        {
            "category":"Shopping",
            "subcategory":"Catalog Store",
            "type":"Retail Goods"
        }
    ],
    "sg:phone":"+1 952 469 3575",
    "sg:postcode":"55044",
    "sg:province":"MN",
    "sg:tags":[
        "mail",
        "order"
    ],
    "wof:name":"Amtpro",
    "wof:placetype":"venue"
},
  "geometry": {"coordinates":[-93.277072,44.65101],"type":"Point"}
}