{
  "type": "Feature",
  "properties": {
    "addr:full":"1108 Nicollet Ave Ste 210 Minneapolis MN 55403",
    "addr:housenumber":"1108",
    "addr:postcode":"55403",
    "addr:street":"Nicollet Ave Ste 210",
    "iso:country":"US",
    "sg:address":"1108 Nicollet Ave Ste 210",
    "sg:city":"Minneapolis",
    "sg:classifiers":[
        {
            "category":"Professional",
            "subcategory":"Lawyer & Legal Services",
            "type":"Services"
        }
    ],
    "sg:phone":"+1 612 333 8225",
    "sg:postcode":"55403",
    "sg:province":"MN",
    "wof:name":"Zimmerman & Bix Ltd",
    "wof:placetype":"venue"
},
  "geometry": {"coordinates":[-93.277793,44.969822],"type":"Point"}
}