{
  "type": "Feature",
  "properties": {
    "addr:full":"32317 Co Rd 21 Browerville MN 56438",
    "addr:housenumber":"32317;21",
    "addr:postcode":"56438",
    "addr:street":"Co Rd",
    "iso:country":"US",
    "sg:address":"32317 Co Rd 21",
    "sg:city":"Browerville",
    "sg:classifiers":[
        {
            "category":"Retail",
            "subcategory":"Auto Repair",
            "type":"Services"
        }
    ],
    "sg:phone":"+1 320 594 2257",
    "sg:postcode":"56438",
    "sg:province":"MN",
    "sg:tags":[
        "body",
        "automobile",
        "painting"
    ],
    "wof:name":"Strack's Collision Ctr",
    "wof:placetype":"venue"
},
  "geometry": {"coordinates":[-94.865206,46.096301],"type":"Point"}
}