{
  "type": "Feature",
  "properties": {
    "iso:country":"US",
    "sg:address":"1810 Morningside Ave",
    "sg:city":"Duluth",
    "sg:classifiers":[
        {
            "category":"Banks & Credit Unions",
            "subcategory":"Financial Services",
            "type":"Services"
        }
    ],
    "sg:phone":"+1 218 525 7970",
    "sg:postcode":"55803",
    "sg:province":"MN",
    "sg:tags":[
        "company",
        "holding"
    ],
    "wof:name":"Harris House Holdings Inc",
    "wof:placetype":"venue"
},
  "geometry": {"coordinates":[-92.05835999999999,46.83847],"type":"Point"}
}