{
  "type": "Feature",
  "properties": {
    "iso:country":"US",
    "sg:address":"206 Red River Ave S",
    "sg:city":"Cold Spring",
    "sg:classifiers":[
        {
            "category":"Restaurant",
            "type":"Food & Drink"
        }
    ],
    "sg:menulink":"http://www.allmenus.com/mn/cold-spring/243969-jimmys-pizza/menu/",
    "sg:phone":"+1 320 685 3151",
    "sg:postcode":"56320",
    "sg:province":"MN",
    "sg:tags":[
        "american",
        "pizza"
    ],
    "wof:name":"Jimmy's Pizza",
    "wof:placetype":"venue"
},
  "geometry": {"coordinates":[-94.42896399999999,45.453769],"type":"Point"}
}