{
  "type": "Feature",
  "properties": {
    "iso:country":"US",
    "sg:address":"410 7th St NE",
    "sg:city":"Buffalo",
    "sg:classifiers":[
        {
            "category":"Manufacturing",
            "subcategory":"Tools & Machinery",
            "type":"Manufacturing & Wholesale Goods"
        }
    ],
    "sg:phone":"+1 763 682 5813",
    "sg:postcode":"55313",
    "sg:province":"MN",
    "sg:tags":[
        "machine",
        "shop"
    ],
    "wof:name":"North Star Machining",
    "wof:placetype":"venue"
},
  "geometry": {"coordinates":[-93.864886,45.177718],"type":"Point"}
}