{
  "type": "Feature",
  "properties": {
    "addr:full":"9661 Fernbrook Ln N Osseo MN 55369",
    "addr:housenumber":"9661",
    "addr:postcode":"55369",
    "addr:street":"Fernbrook Ln N",
    "iso:country":"US",
    "sg:address":"9661 Fernbrook Ln N",
    "sg:city":"Osseo",
    "sg:classifiers":[
        {
            "category":"Education",
            "subcategory":"School",
            "type":"Public Place"
        }
    ],
    "sg:phone":"+1 763 420 8888",
    "sg:postcode":"55369",
    "sg:province":"MN",
    "wof:name":"Fernbrook Elementary School",
    "wof:placetype":"venue"
},
  "geometry": {"coordinates":[-93.462097,45.129299],"type":"Point"}
}