{
  "type": "Feature",
  "properties": {
    "iso:country":"US",
    "sg:address":"2216 117th St E",
    "sg:city":"Burnsville",
    "sg:classifiers":[
        {
            "category":"Professional",
            "subcategory":"Computer Services",
            "type":"Services"
        }
    ],
    "sg:phone":"+1 952 894 6247",
    "sg:postcode":"55337",
    "sg:province":"MN",
    "sg:tags":[
        "development",
        "custom",
        "software"
    ],
    "wof:name":"Pictographics Intl Corp",
    "wof:placetype":"venue"
},
  "geometry": {"coordinates":[-93.239643,44.793976],"type":"Point"}
}