{
  "type": "Feature",
  "properties": {
    "addr:full":"825 Pembroke Ave Wabasha MN 55981",
    "addr:housenumber":"825",
    "addr:postcode":"55981",
    "addr:street":"Pembroke Ave",
    "iso:country":"US",
    "sg:address":"825 Pembroke Ave",
    "sg:city":"Wabasha",
    "sg:classifiers":[
        {
            "category":"Food & Beverages",
            "subcategory":"Groceries & Convenience Stores",
            "type":"Retail Goods"
        }
    ],
    "sg:phone":"+1 651 565 2324",
    "sg:postcode":"55981",
    "sg:province":"MN",
    "wof:name":"Budget Mart",
    "wof:placetype":"venue"
},
  "geometry": {"coordinates":[-92.034611,44.377532],"type":"Point"}
}