{
  "type": "Feature",
  "properties": {
    "addr:full":"301 McAndrews Rd W Burnsville MN 55337",
    "addr:housenumber":"301",
    "addr:postcode":"55337",
    "addr:street":"Mcandrews Rd W",
    "iso:country":"US",
    "sg:address":"301 McAndrews Rd W",
    "sg:city":"Burnsville",
    "sg:classifiers":[
        {
            "category":"Building & Trades",
            "subcategory":"Construction",
            "type":"Services"
        }
    ],
    "sg:phone":"+1 651 503 3632",
    "sg:postcode":"55337",
    "sg:province":"MN",
    "sg:tags":[
        "general",
        "contractor"
    ],
    "wof:name":"P H Sanchez Construction",
    "wof:placetype":"venue"
},
  "geometry": {"coordinates":[-93.282708,44.752878],"type":"Point"}
}