{
  "type": "Feature",
  "properties": {
    "iso:country":"US",
    "sg:address":"113 S Lake St",
    "sg:city":"Mora",
    "sg:classifiers":[
        {
            "category":"Organizations",
            "subcategory":"Community Association",
            "type":"Services"
        }
    ],
    "sg:phone":"+1 320 679 9229",
    "sg:postcode":"55051",
    "sg:province":"MN",
    "sg:tags":[
        "club"
    ],
    "wof:name":"Club Fuel",
    "wof:placetype":"venue"
},
  "geometry": {"coordinates":[-93.295571,45.876709],"type":"Point"}
}