{
  "type": "Feature",
  "properties": {
    "iso:country":"US",
    "sg:address":"25 4th St NW",
    "sg:city":"Harmony",
    "sg:classifiers":[
        {
            "category":"Retail",
            "subcategory":"Auto Repair",
            "type":"Services"
        }
    ],
    "sg:phone":"+1 507 886 3534",
    "sg:postcode":"55939",
    "sg:province":"MN",
    "sg:tags":[
        "body",
        "automobile",
        "painting",
        "repairing"
    ],
    "wof:name":"Harmony Body Shop",
    "wof:placetype":"venue"
},
  "geometry": {"coordinates":[-92.010266,43.558449],"type":"Point"}
}