{
  "type": "Feature",
  "properties": {
    "iso:country":"US",
    "sg:address":"1506 E 66th St",
    "sg:city":"Minneapolis",
    "sg:classifiers":[
        {
            "category":"Insurance",
            "subcategory":"Hazard Insurance",
            "type":"Services"
        },
        {
            "category":"Insurance",
            "subcategory":"Insurance Agent",
            "type":"Services"
        },
        {
            "category":"Insurance",
            "subcategory":"Life Insurance",
            "type":"Services"
        },
        {
            "category":"Insurance",
            "subcategory":"Title Insurance",
            "type":"Services"
        }
    ],
    "sg:phone":"+1 612 455 1590",
    "sg:postcode":"55423",
    "sg:province":"MN",
    "sg:tags":[
        "property",
        "casualty",
        "homeowner"
    ],
    "sg:website":"http://www.amfam.com/agentlocator/BANDERS7?sourceid=yp9",
    "wof:name":"American Family Insurance- Brandon Anderson",
    "wof:placetype":"venue"
},
  "geometry": {"coordinates":[-93.25384699999999,44.883511],"type":"Point"}
}