{
  "type": "Feature",
  "properties": {
    "addr:full":"7801 E Bush Lake Rd Edina MN 55439",
    "addr:housenumber":"7801",
    "addr:postcode":"55439",
    "addr:street":"E Bush Lake Rd",
    "iso:country":"US",
    "sg:address":"7801 E Bush Lake Rd",
    "sg:city":"Edina",
    "sg:classifiers":[
        {
            "category":"Professional",
            "type":"Services"
        }
    ],
    "sg:phone":"+1 952 893 1084",
    "sg:postcode":"55439",
    "sg:province":"MN",
    "sg:tags":[
        "establishment"
    ],
    "wof:name":"Paramount Plaza",
    "wof:placetype":"venue"
},
  "geometry": {"coordinates":[-93.361351,44.861954],"type":"Point"}
}