{
  "type": "Feature",
  "properties": {
    "addr:full":"5230 W 6th St Winona MN 55987",
    "addr:housenumber":"5230",
    "addr:postcode":"55987",
    "addr:street":"W 6Th St",
    "iso:country":"US",
    "sg:address":"5230 W 6th St",
    "sg:city":"Winona",
    "sg:classifiers":[
        {
            "category":"Building & Trades",
            "subcategory":"Construction",
            "type":"Services"
        }
    ],
    "sg:phone":"+1 507 474 1177",
    "sg:postcode":"55987",
    "sg:province":"MN",
    "sg:tags":[
        "floor",
        "laying",
        "contractor"
    ],
    "wof:name":"Commercial Flooring Solutions",
    "wof:placetype":"venue"
},
  "geometry": {"coordinates":[-91.706639,44.068305],"type":"Point"}
}