{
  "type": "Feature",
  "properties": {
    "addr:full":"1125 Washington Ave S So Minneapolis MN 55415",
    "addr:housenumber":"1125",
    "addr:postcode":"55415",
    "addr:street":"Washington Ave S So",
    "iso:country":"US",
    "sg:address":"1125 Washington Ave S So",
    "sg:city":"Minneapolis",
    "sg:classifiers":[
        {
            "category":"Wholesale",
            "subcategory":"Hardware",
            "type":"Manufacturing & Wholesale Goods"
        },
        {
            "category":"Home & Garden",
            "subcategory":"Garden Supply",
            "type":"Retail Goods"
        },
        {
            "category":"Retail",
            "subcategory":"Repair Shop",
            "type":"Services"
        }
    ],
    "sg:phone":"+1 612 332 8571",
    "sg:postcode":"55415",
    "sg:province":"MN",
    "sg:tags":[
        "renting",
        "lawn",
        "outdoor",
        "power",
        "landscaping",
        "equipment-sales",
        "equipment",
        "saw"
    ],
    "sg:website":"http://www.stihlusa.com/",
    "wof:name":"LANGFORD TOOL & DRILL",
    "wof:placetype":"venue"
},
  "geometry": {"coordinates":[-93.252876,44.975188],"type":"Point"}
}