{
  "type": "Feature",
  "properties": {
    "addr:full":"1671 County Road C W Saint Paul MN 55113",
    "addr:housenumber":"1671",
    "addr:postcode":"55113",
    "addr:street":"County Road C W",
    "iso:country":"US",
    "sg:address":"1671 County Road C W",
    "sg:city":"Saint Paul",
    "sg:classifiers":[
        {
            "category":"Personal",
            "subcategory":"Tanning Parlor",
            "type":"Services"
        }
    ],
    "sg:phone":"+1 651 636 6434",
    "sg:postcode":"55113",
    "sg:province":"MN",
    "sg:website":"www.planetbeach.com",
    "wof:name":"Planet Beach",
    "wof:placetype":"venue"
},
  "geometry": {"coordinates":[-93.17051499999999,45.021291],"type":"Point"}
}