{
  "type": "Feature",
  "properties": {
    "iso:country":"US",
    "sg:address":"5905 Raleigh St",
    "sg:city":"Duluth",
    "sg:classifiers":[
        {
            "category":"Education",
            "subcategory":"School",
            "type":"Public Place"
        }
    ],
    "sg:phone":"+1 218 628 0697",
    "sg:postcode":"55807",
    "sg:province":"MN",
    "wof:name":"Raleigh Edison Prmry & Elmntry",
    "wof:placetype":"venue"
},
  "geometry": {"coordinates":[-92.173345,46.731334],"type":"Point"}
}