{
  "type": "Feature",
  "properties": {
    "iso:country":"US",
    "sg:address":"121 NW 16th Ave",
    "sg:city":"Grand Rapids",
    "sg:classifiers":[
        {
            "category":"Professional",
            "subcategory":"Business Services",
            "type":"Services"
        }
    ],
    "sg:phone":"+1 218 326 4158",
    "sg:postcode":"55744",
    "sg:province":"MN",
    "sg:tags":[
        "information",
        "bureau",
        "convention"
    ],
    "wof:name":"Showboat",
    "wof:placetype":"venue"
},
  "geometry": {"coordinates":[-93.552848,47.233718],"type":"Point"}
}