{
  "type": "Feature",
  "properties": {
    "addr:full":"44544 Birch Leaf Rd Grey Eagle MN 56336",
    "addr:housenumber":"44544",
    "addr:postcode":"56336",
    "addr:street":"Birch Leaf Rd",
    "iso:country":"US",
    "sg:address":"44544 Birch Leaf Rd",
    "sg:city":"Grey Eagle",
    "sg:classifiers":[
        {
            "category":"Real Estate",
            "subcategory":"Real Estate Agent",
            "type":"Services"
        }
    ],
    "sg:phone":"+1 320 256 4700",
    "sg:postcode":"56336",
    "sg:province":"MN",
    "wof:name":"Benchmark",
    "wof:placetype":"venue"
},
  "geometry": {"coordinates":[-94.809,45.7695],"type":"Point"}
}