{
  "type": "Feature",
  "properties": {
    "iso:country":"US",
    "sg:address":"2820 Vicksburg Ln N",
    "sg:city":"Minneapolis",
    "sg:classifiers":[
        {
            "category":"Wholesale",
            "subcategory":"Medical Equipment & Supplies",
            "type":"Manufacturing & Wholesale Goods"
        }
    ],
    "sg:phone":"+1 763 550 9486",
    "sg:postcode":"55447",
    "sg:province":"MN",
    "sg:tags":[
        "physician",
        "surgeon"
    ],
    "wof:name":"Elim Preferred Services Inc",
    "wof:placetype":"venue"
},
  "geometry": {"coordinates":[-93.48165,45.013217],"type":"Point"}
}