{
  "type": "Feature",
  "properties": {
    "iso:country":"US",
    "sg:address":"14791 710th Ave",
    "sg:city":"Taopi",
    "sg:phone":"+1 507 582 3389",
    "sg:postcode":"55977",
    "sg:province":"MN",
    "sg:tags":[
        "farm",
        "corn"
    ],
    "wof:name":"Clifford Kieffer",
    "wof:placetype":"venue"
},
  "geometry": {"coordinates":[-92.62889300000001,43.569],"type":"Point"}
}