{
  "type": "Feature",
  "properties": {
    "addr:full":"21039 Heron Way Lakeville MN 55044",
    "addr:housenumber":"21039",
    "addr:postcode":"55044",
    "addr:street":"Heron Way",
    "iso:country":"US",
    "sg:address":"21039 Heron Way",
    "sg:city":"Lakeville",
    "sg:classifiers":[
        {
            "category":"Building & Trades",
            "subcategory":"Construction",
            "type":"Services"
        }
    ],
    "sg:phone":"+1 952 985 0965",
    "sg:postcode":"55044",
    "sg:province":"MN",
    "sg:tags":[
        "home",
        "builder"
    ],
    "wof:name":"Robert Mc Nearney Custom Home",
    "wof:placetype":"venue"
},
  "geometry": {"coordinates":[-93.230512,44.643878],"type":"Point"}
}