{
  "type": "Feature",
  "properties": {
    "iso:country":"US",
    "sg:address":"200 General Sieben Dr",
    "sg:city":"Hastings",
    "sg:classifiers":[
        {
            "category":"Education",
            "subcategory":"School",
            "type":"Public Place"
        }
    ],
    "sg:phone":"+1 651 480 0205",
    "sg:postcode":"55033",
    "sg:province":"MN",
    "sg:website":"www.hastings.k12.mn.us",
    "wof:name":"Hastings High School",
    "wof:placetype":"venue"
},
  "geometry": {"coordinates":[-92.888569,44.744479],"type":"Point"}
}