{
  "type": "Feature",
  "properties": {
    "addr:full":"14735 State Hwy 65 Andover MN 55304",
    "addr:housenumber":"14735",
    "addr:postcode":"55304",
    "addr:street":"State Hwy 65",
    "iso:country":"US",
    "sg:address":"14735 State Hwy 65",
    "sg:city":"Andover",
    "sg:classifiers":[
        {
            "category":"Organizations",
            "subcategory":"Professional Association",
            "type":"Services"
        }
    ],
    "sg:phone":"+1 763 434 3011",
    "sg:postcode":"55304",
    "sg:province":"MN",
    "sg:tags":[
        "chambers",
        "business",
        "commerce"
    ],
    "wof:name":"Ham Lake Chamber Of Commerce",
    "wof:placetype":"venue"
},
  "geometry": {"coordinates":[-93.234865,45.237561],"type":"Point"}
}