{
  "type": "Feature",
  "properties": {
    "addr:full":"2810 120th St NW Pennock MN 56279",
    "addr:housenumber":"2810",
    "addr:postcode":"56279",
    "addr:street":"120Th St Nw",
    "iso:country":"US",
    "sg:address":"2810 120th St NW",
    "sg:city":"Pennock",
    "sg:classifiers":[
        {
            "category":"Building & Trades",
            "subcategory":"Plumbing",
            "type":"Services"
        }
    ],
    "sg:phone":"+1 320 599 4474",
    "sg:postcode":"56279",
    "sg:province":"MN",
    "sg:tags":[
        "heating",
        "contractor"
    ],
    "wof:name":"Magnuson Sheet Metal Inc",
    "wof:placetype":"venue"
},
  "geometry": {"coordinates":[-95.206164,45.152984],"type":"Point"}
}