{
  "type": "Feature",
  "properties": {
    "iso:country":"US",
    "sg:address":"6500 Excelsior Blvd",
    "sg:city":"Minneapolis",
    "sg:classifiers":[
        {
            "category":"Health Services",
            "subcategory":"Hospital",
            "type":"Services"
        }
    ],
    "sg:phone":"+1 952 993 5486",
    "sg:postcode":"55426",
    "sg:province":"MN",
    "sg:tags":[
        "general"
    ],
    "wof:name":"Lutheran Hospital",
    "wof:placetype":"venue"
},
  "geometry": {"coordinates":[-93.361,44.927087],"type":"Point"}
}