{
  "type": "Feature",
  "properties": {
    "addr:full":"4078 Hwy 71 NE Willmar MN 56201",
    "addr:housenumber":"4078",
    "addr:postcode":"56201",
    "addr:street":"Hwy 71 Ne",
    "iso:country":"US",
    "sg:address":"4078 Hwy 71 NE",
    "sg:city":"Willmar",
    "sg:classifiers":[
        {
            "category":"Organizations",
            "subcategory":"Non-profit Organization",
            "type":"Services"
        }
    ],
    "sg:phone":"+1 320 231 2704",
    "sg:postcode":"56201",
    "sg:province":"MN",
    "sg:tags":[
        "human"
    ],
    "sg:website":"www.habitatwcm.org",
    "wof:name":"Habitat For Humanity",
    "wof:placetype":"venue"
},
  "geometry": {"coordinates":[-95.01563899999999,45.164677],"type":"Point"}
}