{
  "type": "Feature",
  "properties": {
    "addr:full":"1516 Yosemite Ave Duluth MN 55811",
    "addr:housenumber":"1516",
    "addr:postcode":"55811",
    "addr:street":"Yosemite Ave",
    "iso:country":"US",
    "sg:address":"1516 Yosemite Ave",
    "sg:city":"Duluth",
    "sg:classifiers":[
        {
            "category":"Real Estate",
            "subcategory":"Real Estate Agent",
            "type":"Services"
        }
    ],
    "sg:phone":"+1 218 727 6616",
    "sg:postcode":"55811",
    "sg:province":"MN",
    "wof:name":"Duncan Realty",
    "wof:placetype":"venue"
},
  "geometry": {"coordinates":[-92.15854899999999,46.816585],"type":"Point"}
}