{
  "type": "Feature",
  "properties": {
    "addr:full":"3755 Co Rd 7 Gary MN 56545",
    "addr:housenumber":"3755;7",
    "addr:postcode":"56545",
    "addr:street":"Co Rd",
    "iso:country":"US",
    "sg:address":"3755 Co Rd 7",
    "sg:city":"Gary",
    "sg:phone":"+1 218 945 6116",
    "sg:postcode":"56545",
    "sg:province":"MN",
    "sg:tags":[
        "farm",
        "corn",
        "wheat",
        "soybean",
        "f"
    ],
    "wof:name":"Kevin Chisholm",
    "wof:placetype":"venue"
},
  "geometry": {"coordinates":[-96.27082299999999,47.456516],"type":"Point"}
}