{
  "type": "Feature",
  "properties": {
    "addr:full":"15255 State Highway 15 Kimball MN 55353",
    "addr:housenumber":"15255",
    "addr:postcode":"55353",
    "addr:street":"State Highway 15",
    "iso:country":"US",
    "sg:address":"15255 State Highway 15",
    "sg:city":"Kimball",
    "sg:classifiers":[
        {
            "category":"Transit Center",
            "subcategory":"Freight",
            "type":"Transportation"
        },
        {
            "category":"Freight",
            "type":"Transportation"
        }
    ],
    "sg:phone":"+1 320 398 3436",
    "sg:postcode":"55353",
    "sg:province":"MN",
    "sg:tags":[
        "local",
        "trucking-motor",
        "trucking"
    ],
    "wof:name":"Schiefelbein Trucking",
    "wof:placetype":"venue"
},
  "geometry": {"coordinates":[-94.28834999999999,45.348923],"type":"Point"}
}