{
  "type": "Feature",
  "properties": {
    "addr:full":"408 1st Ave NW Rochester MN 55901",
    "addr:housenumber":"408",
    "addr:postcode":"55901",
    "addr:street":"1St Ave Nw",
    "iso:country":"US",
    "sg:address":"408 1st Ave NW",
    "sg:city":"Rochester",
    "sg:classifiers":[
        {
            "category":"Professional",
            "subcategory":"Accounting & Tax Preparation",
            "type":"Services"
        }
    ],
    "sg:phone":"+1 507 288 2200",
    "sg:postcode":"55901",
    "sg:province":"MN",
    "sg:tags":[
        "return",
        "accountants-certified",
        "preparation-business",
        "public"
    ],
    "wof:name":"Carpenter Kelly Brenno Act",
    "wof:placetype":"venue"
},
  "geometry": {"coordinates":[-92.464411,44.0272],"type":"Point"}
}