{
  "type": "Feature",
  "properties": {
    "addr:full":"35853 US Hwy 61 Lake City MN 55041",
    "addr:postcode":"35853;55041",
    "addr:street":"Us Hwy 61",
    "iso:country":"US",
    "sg:address":"35853 US Hwy 61",
    "sg:city":"Lake City",
    "sg:classifiers":[
        {
            "category":"Recreation",
            "type":"Entertainment"
        }
    ],
    "sg:phone":"+1 651 345 6282",
    "sg:postcode":"55041",
    "sg:province":"MN",
    "sg:tags":[
        "charter",
        "boat"
    ],
    "wof:name":"Sailboats Inc",
    "wof:placetype":"venue"
},
  "geometry": {"coordinates":[-92.315635,44.49855],"type":"Point"}
}