{
  "type": "Feature",
  "properties": {
    "addr:full":"9001 Grand Ave S Minneapolis MN 55420",
    "addr:housenumber":"9001",
    "addr:postcode":"55420",
    "addr:street":"Grand Ave S",
    "iso:country":"US",
    "sg:address":"9001 Grand Ave S",
    "sg:city":"Minneapolis",
    "sg:classifiers":[
        {
            "category":"Retail",
            "subcategory":"Auto Repair",
            "type":"Services"
        }
    ],
    "sg:phone":"+1 952 884 8884",
    "sg:postcode":"55420",
    "sg:province":"MN",
    "sg:tags":[
        "body",
        "shop"
    ],
    "sg:website":"walser.com",
    "wof:name":"Walser Collision and Glass",
    "wof:placetype":"venue"
},
  "geometry": {"coordinates":[-93.28510300000001,44.840099],"type":"Point"}
}