{
  "type": "Feature",
  "properties": {
    "iso:country":"US",
    "sg:address":"506 Central Ave",
    "sg:city":"Osseo",
    "sg:classifiers":[
        {
            "category":"Insurance",
            "subcategory":"Insurance Agent",
            "type":"Services"
        },
        {
            "category":"Insurance",
            "subcategory":"Hazard Insurance",
            "type":"Services"
        },
        {
            "category":"Insurance",
            "subcategory":"Title Insurance",
            "type":"Services"
        }
    ],
    "sg:phone":"+1 763 424 2222",
    "sg:postcode":"55369",
    "sg:province":"MN",
    "sg:tags":[
        "property",
        "casualty",
        "homeowner"
    ],
    "sg:website":"http://www.amfam.com/agentlocator?sourceid=yp9",
    "wof:name":"American Family Insurance- Kristen Brisky",
    "wof:placetype":"venue"
},
  "geometry": {"coordinates":[-93.40212099999999,45.121119],"type":"Point"}
}