{
  "type": "Feature",
  "properties": {
    "addr:full":"114 Brick St S Stillwater MN 55082",
    "addr:housenumber":"114",
    "addr:postcode":"55082",
    "addr:street":"Brick St S",
    "iso:country":"US",
    "sg:address":"114 Brick St S",
    "sg:city":"Stillwater",
    "sg:classifiers":[
        {
            "category":"Communications",
            "subcategory":"Radio Station",
            "type":"Services"
        }
    ],
    "sg:phone":"+1 651 430 4922",
    "sg:postcode":"55082",
    "sg:province":"MN",
    "sg:tags":[
        "company",
        "broadcasting"
    ],
    "wof:name":"Endurance Broadcasting",
    "wof:placetype":"venue"
},
  "geometry": {"coordinates":[-92.827268,45.054928],"type":"Point"}
}