{
  "type": "Feature",
  "properties": {
    "iso:country":"US",
    "sg:address":"11740 Xeon Blvd NW",
    "sg:city":"Minneapolis",
    "sg:classifiers":[
        {
            "category":"Government",
            "subcategory":"Office",
            "type":"Public Place"
        }
    ],
    "sg:phone":"+1 763 755 3630",
    "sg:postcode":"55448",
    "sg:province":"MN",
    "sg:tags":[
        "executive"
    ],
    "wof:name":"Grassland Housing",
    "wof:placetype":"venue"
},
  "geometry": {"coordinates":[-93.304134,45.183065],"type":"Point"}
}