{
  "type": "Feature",
  "properties": {
    "addr:full":"1104 5th St NE Stewartville MN 55976",
    "addr:housenumber":"1104",
    "addr:postcode":"55976",
    "addr:street":"5Th St Ne",
    "iso:country":"US",
    "sg:address":"1104 5th St NE",
    "sg:city":"Stewartville",
    "sg:classifiers":[
        {
            "category":"Building & Trades",
            "subcategory":"Construction",
            "type":"Services"
        }
    ],
    "sg:phone":"+1 507 533 6310",
    "sg:postcode":"55976",
    "sg:province":"MN",
    "sg:tags":[
        "house"
    ],
    "wof:name":"Hildebarndt Construction",
    "wof:placetype":"venue"
},
  "geometry": {"coordinates":[-92.472745,43.858665],"type":"Point"}
}