{
  "type": "Feature",
  "properties": {
    "addr:full":"3948 W 50th St Ste 207 Minneapolis MN 55424",
    "addr:housenumber":"3948",
    "addr:postcode":"55424",
    "addr:street":"W 50Th St Ste 207",
    "iso:country":"US",
    "sg:address":"3948 W 50th St Ste 207",
    "sg:city":"Minneapolis",
    "sg:classifiers":[
        {
            "category":"Shopping",
            "subcategory":"Florist",
            "type":"Retail Goods"
        }
    ],
    "sg:phone":"+1 952 920 5665",
    "sg:postcode":"55424",
    "sg:province":"MN",
    "wof:name":"Edina Five-O Florist Inc",
    "wof:placetype":"venue"
},
  "geometry": {"coordinates":[-93.330299,44.912498],"type":"Point"}
}