{
  "type": "Feature",
  "properties": {
    "iso:country":"US",
    "sg:address":"14045 325th Ave NW",
    "sg:city":"Princeton",
    "sg:classifiers":[
        {
            "category":"Freight",
            "type":"Transportation"
        }
    ],
    "sg:phone":"+1 763 389 4374",
    "sg:postcode":"55371",
    "sg:province":"MN",
    "sg:tags":[
        "operator",
        "local",
        "trucking"
    ],
    "wof:name":"Edmonds Trucking",
    "wof:placetype":"venue"
},
  "geometry": {"coordinates":[-93.626087,45.559373],"type":"Point"}
}