{
  "type": "Feature",
  "properties": {
    "addr:full":"7600 Olson Memorial Hwy Minneapolis MN 55427",
    "addr:housenumber":"7600",
    "addr:postcode":"55427",
    "addr:street":"Olson Memorial Hwy",
    "iso:country":"US",
    "sg:address":"7600 Olson Memorial Hwy",
    "sg:city":"Minneapolis",
    "sg:classifiers":[
        {
            "category":"Restaurant",
            "type":"Food & Drink"
        }
    ],
    "sg:phone":"+1 763 546 5011",
    "sg:postcode":"55427",
    "sg:province":"MN",
    "sg:tags":[
        "eating"
    ],
    "wof:name":"KFC",
    "wof:placetype":"venue"
},
  "geometry": {"coordinates":[-93.374712,44.983055],"type":"Point"}
}