{
  "type": "Feature",
  "properties": {
    "iso:country":"US",
    "sg:address":"89843 440th St",
    "sg:city":"Hector",
    "sg:phone":"+1 320 848 2800",
    "sg:postcode":"55342",
    "sg:province":"MN",
    "sg:tags":[
        "farm",
        "corn"
    ],
    "wof:name":"Thomas Koeberl",
    "wof:placetype":"venue"
},
  "geometry": {"coordinates":[-94.793626,44.887673],"type":"Point"}
}