{
  "type": "Feature",
  "properties": {
    "addr:full":"57528 127th Ln Mapleton MN 56065",
    "addr:housenumber":"57528",
    "addr:postcode":"56065",
    "addr:street":"127Th Ln",
    "iso:country":"US",
    "sg:address":"57528 127th Ln",
    "sg:city":"Mapleton",
    "sg:classifiers":[
        {
            "category":"Wholesale",
            "subcategory":"Books, Periodicals, & Newspapers",
            "type":"Manufacturing & Wholesale Goods"
        }
    ],
    "sg:phone":"+1 507 524 3253",
    "sg:postcode":"56065",
    "sg:province":"MN",
    "sg:tags":[
        "publisher",
        "book"
    ],
    "wof:name":"Maple River Design & Graphics",
    "wof:placetype":"venue"
},
  "geometry": {"coordinates":[-93.983694,43.920622],"type":"Point"}
}