{
  "type": "Feature",
  "properties": {
    "iso:country":"US",
    "sg:address":"1105 Duckwood Trl",
    "sg:city":"Saint Paul",
    "sg:classifiers":[
        {
            "category":"Professional",
            "type":"Services"
        }
    ],
    "sg:phone":"+1 952 681 0854",
    "sg:postcode":"55123",
    "sg:province":"MN",
    "wof:name":"J Lee Berget & Wendy S",
    "wof:placetype":"venue"
},
  "geometry": {"coordinates":[-93.147777,44.828054],"type":"Point"}
}