{
  "type": "Feature",
  "properties": {
    "iso:country":"US",
    "sg:address":"13900 58th Ave N",
    "sg:city":"Minneapolis",
    "sg:classifiers":[
        {
            "category":"Professional",
            "subcategory":"Computer Services",
            "type":"Services"
        }
    ],
    "sg:phone":"+1 763 553 9596",
    "sg:postcode":"55446",
    "sg:province":"MN",
    "sg:tags":[
        "related"
    ],
    "wof:name":"Cobol Consulting",
    "wof:placetype":"venue"
},
  "geometry": {"coordinates":[-93.456543,45.058754],"type":"Point"}
}