{
  "type": "Feature",
  "properties": {
    "addr:full":"14054 Bank St Becker MN 55308",
    "addr:housenumber":"14054",
    "addr:postcode":"55308",
    "addr:street":"Bank St",
    "iso:country":"US",
    "sg:address":"14054 Bank St",
    "sg:city":"Becker",
    "sg:classifiers":[
        {
            "category":"Building & Trades",
            "subcategory":"Construction",
            "type":"Services"
        }
    ],
    "sg:phone":"+1 763 262 2222",
    "sg:postcode":"55308",
    "sg:province":"MN",
    "sg:tags":[
        "siding",
        "contractor"
    ],
    "wof:name":"Country Exteriors",
    "wof:placetype":"venue"
},
  "geometry": {"coordinates":[-93.86936900000001,45.389323],"type":"Point"}
}