{
  "type": "Feature",
  "properties": {
    "iso:country":"US",
    "sg:address":"2919 26th Ave S",
    "sg:city":"Minneapolis",
    "sg:classifiers":[
        {
            "category":"Food & Beverages",
            "subcategory":"Groceries & Convenience Stores",
            "type":"Retail Goods"
        }
    ],
    "sg:phone":"+1 612 724 4605",
    "sg:postcode":"55406",
    "sg:province":"MN",
    "sg:tags":[
        "grocer",
        "supermarket"
    ],
    "wof:name":"Rainbow Foods 44",
    "wof:placetype":"venue"
},
  "geometry": {"coordinates":[-93.234694,44.949266],"type":"Point"}
}