{
  "type": "Feature",
  "properties": {
    "iso:country":"US",
    "sg:address":"17615 10th Ave N",
    "sg:city":"Minneapolis",
    "sg:classifiers":[
        {
            "category":"Wholesale",
            "subcategory":"Groceries",
            "type":"Manufacturing & Wholesale Goods"
        }
    ],
    "sg:phone":"+1 763 473 5593",
    "sg:postcode":"55447",
    "sg:province":"MN",
    "sg:tags":[
        "general"
    ],
    "wof:name":"Tom Dierks Sysco",
    "wof:placetype":"venue"
},
  "geometry": {"coordinates":[-93.505821,44.988991],"type":"Point"}
}