{
  "type": "Feature",
  "properties": {
    "addr:full":"4911 Hodgson Rd St Paul MN 55126",
    "addr:housenumber":"4911",
    "addr:postcode":"55126",
    "addr:street":"Hodgson Rd",
    "iso:country":"US",
    "sg:address":"4911 Hodgson Rd",
    "sg:city":"St Paul",
    "sg:classifiers":[
        {
            "category":"Organizations",
            "subcategory":"Religious Organization",
            "type":"Services"
        }
    ],
    "sg:phone":"+1 651 486 6243",
    "sg:postcode":"55126",
    "sg:province":"MN",
    "sg:tags":[
        "church"
    ],
    "sg:website":"www.hopemn.com",
    "wof:name":"Hope Christian Church",
    "wof:placetype":"venue"
},
  "geometry": {"coordinates":[-93.12448999999999,45.088957],"type":"Point"}
}