{
  "type": "Feature",
  "properties": {
    "addr:full":"7324 Lakeland Ave N Minneapolis MN 55428",
    "addr:housenumber":"7324",
    "addr:postcode":"55428",
    "addr:street":"Lakeland Ave N",
    "iso:country":"US",
    "sg:address":"7324 Lakeland Ave N",
    "sg:city":"Minneapolis",
    "sg:classifiers":[
        {
            "category":"Social Services",
            "type":"Services"
        }
    ],
    "sg:phone":"+1 763 493 9065",
    "sg:postcode":"55428",
    "sg:province":"MN",
    "sg:tags":[
        "individual",
        "family",
        "therapist",
        "marriage",
        "child",
        "counselor"
    ],
    "wof:name":"St Therese Inc",
    "wof:placetype":"venue"
},
  "geometry": {"coordinates":[-93.37896000000001,45.087329],"type":"Point"}
}