{
  "type": "Feature",
  "properties": {
    "iso:country":"US",
    "sg:address":"1522 Warren St",
    "sg:city":"Mankato",
    "sg:classifiers":[
        {
            "category":"Real Estate",
            "subcategory":"Real Estate Operator",
            "type":"Services"
        }
    ],
    "sg:phone":"+1 507 388 7459",
    "sg:postcode":"56001",
    "sg:province":"MN",
    "sg:tags":[
        "apartment"
    ],
    "wof:name":"Campus Village Apartments",
    "wof:placetype":"venue"
},
  "geometry": {"coordinates":[-93.994308,44.146801],"type":"Point"}
}