{
  "type": "Feature",
  "properties": {
    "addr:full":"2446 University Ave W Ste 100 Minneapolis MN 55114",
    "addr:housenumber":"2446",
    "addr:postcode":"55114",
    "addr:street":"University Ave W Ste 100",
    "iso:country":"US",
    "sg:address":"2446 University Ave W Ste 100",
    "sg:city":"Minneapolis",
    "sg:classifiers":[
        {
            "category":"Education",
            "subcategory":"Special Training",
            "type":"Public Place"
        }
    ],
    "sg:phone":"+1 651 644 1912",
    "sg:postcode":"55114",
    "sg:province":"MN",
    "sg:tags":[
        "adult"
    ],
    "sg:website":"www.ifpmn.org",
    "wof:name":"IFP Minnesota Center for Media Arts",
    "wof:placetype":"venue"
},
  "geometry": {"coordinates":[-93.19970600000001,44.963923],"type":"Point"}
}