{
  "type": "Feature",
  "properties": {
    "iso:country":"US",
    "sg:address":"56783 Co Rd 16",
    "sg:city":"Grove City",
    "sg:classifiers":[
        {
            "category":"Freight",
            "type":"Transportation"
        }
    ],
    "sg:phone":"+1 320 857 2700",
    "sg:postcode":"56243",
    "sg:province":"MN",
    "sg:tags":[
        "operator",
        "local",
        "trucking"
    ],
    "wof:name":"Knisley Trucking Inc",
    "wof:placetype":"venue"
},
  "geometry": {"coordinates":[-94.633256,45.210566],"type":"Point"}
}