{
  "type": "Feature",
  "properties": {
    "iso:country":"US",
    "sg:address":"15020 Peteler Ln",
    "sg:city":"Minnetonka",
    "sg:classifiers":[
        {
            "category":"Manufacturing",
            "subcategory":"Printing",
            "type":"Manufacturing & Wholesale Goods"
        }
    ],
    "sg:phone":"+1 952 934 6892",
    "sg:postcode":"55345",
    "sg:province":"MN",
    "sg:tags":[
        "lithographic",
        "printer",
        "commercial"
    ],
    "wof:name":"Alann Graphics & Binder Svcs",
    "wof:placetype":"venue"
},
  "geometry": {"coordinates":[-93.469943,44.903998],"type":"Point"}
}