{
  "type": "Feature",
  "properties": {
    "addr:full":"5695 Geneva Ave N Oakdale MN 55128",
    "addr:housenumber":"5695",
    "addr:postcode":"55128",
    "addr:street":"Geneva Ave N",
    "iso:country":"US",
    "sg:address":"5695 Geneva Ave N",
    "sg:city":"Oakdale",
    "sg:classifiers":[
        {
            "category":"Shopping",
            "subcategory":"Florist",
            "type":"Retail Goods"
        }
    ],
    "sg:phone":"+1 651 777 6260",
    "sg:postcode":"55128",
    "sg:province":"MN",
    "wof:name":"Flower Affair",
    "wof:placetype":"venue"
},
  "geometry": {"coordinates":[-92.98469799999999,45.031244],"type":"Point"}
}