{
  "type": "Feature",
  "properties": {
    "iso:country":"US",
    "sg:address":"102 8th St N",
    "sg:city":"Sartell",
    "sg:classifiers":[
        {
            "category":"Food & Beverages",
            "subcategory":"Liquor & Beverages",
            "type":"Retail Goods"
        }
    ],
    "sg:phone":"+1 320 203 1581",
    "sg:postcode":"56377",
    "sg:province":"MN",
    "sg:tags":[
        "alcoholic"
    ],
    "wof:name":"Pine Cone Liquor",
    "wof:placetype":"venue"
},
  "geometry": {"coordinates":[-94.208202,45.632541],"type":"Point"}
}