{
  "type": "Feature",
  "properties": {
    "addr:full":"9810 Aspen Ave NW Bemidji MN 56601",
    "addr:housenumber":"9810",
    "addr:postcode":"56601",
    "addr:street":"Aspen Ave Nw",
    "iso:country":"US",
    "sg:address":"9810 Aspen Ave NW",
    "sg:city":"Bemidji",
    "sg:classifiers":[
        {
            "category":"Manufacturing",
            "subcategory":"Tools & Machinery",
            "type":"Manufacturing & Wholesale Goods"
        }
    ],
    "sg:phone":"+1 218 751 7276",
    "sg:postcode":"56601",
    "sg:province":"MN",
    "sg:tags":[
        "control",
        "electronic",
        "mfg"
    ],
    "wof:name":"Digital Design",
    "wof:placetype":"venue"
},
  "geometry": {"coordinates":[-94.906431,47.56967],"type":"Point"}
}