{
  "type": "Feature",
  "properties": {
    "iso:country":"US",
    "sg:address":"46998 380th St",
    "sg:city":"Sauk Centre",
    "sg:classifiers":[
        {
            "category":"Farming",
            "subcategory":"Dairy Farm",
            "type":"Manufacturing & Wholesale Goods"
        }
    ],
    "sg:phone":"+1 320 352 6308",
    "sg:postcode":"56378",
    "sg:province":"MN",
    "sg:tags":[
        "corn"
    ],
    "wof:name":"Tom Uphus Farm",
    "wof:placetype":"venue"
},
  "geometry": {"coordinates":[-95.097015,45.672333],"type":"Point"}
}