{
  "type": "Feature",
  "properties": {
    "addr:full":"33521 400th Ave NE Grygla MN 56727",
    "addr:housenumber":"33521",
    "addr:postcode":"56727",
    "addr:street":"400Th Ave Ne",
    "iso:country":"US",
    "sg:address":"33521 400th Ave NE",
    "sg:city":"Grygla",
    "sg:phone":"+1 218 294 6216",
    "sg:postcode":"56727",
    "sg:province":"MN",
    "sg:tags":[
        "farm",
        "grain",
        "dairy",
        "cash"
    ],
    "wof:name":"Wayne Nelson",
    "wof:placetype":"venue"
},
  "geometry": {"coordinates":[-95.614689,48.365428],"type":"Point"}
}