{
  "type": "Feature",
  "properties": {
    "iso:country":"US",
    "sg:address":"18187 Wren St NW",
    "sg:city":"Cedar",
    "sg:classifiers":[
        {
            "category":"Wholesale",
            "subcategory":"Durable Goods & Equipment",
            "type":"Manufacturing & Wholesale Goods"
        }
    ],
    "sg:phone":"+1 763 566 5761",
    "sg:postcode":"55011",
    "sg:province":"MN",
    "sg:tags":[
        "beef",
        "feedlot",
        "cattle"
    ],
    "wof:name":"Darrel Waldock",
    "wof:placetype":"venue"
},
  "geometry": {"coordinates":[-93.327939,45.299685],"type":"Point"}
}