{
  "type": "Feature",
  "properties": {
    "iso:country":"US",
    "sg:address":"4837 Azelia Ave N",
    "sg:city":"Minneapolis",
    "sg:classifiers":[
        {
            "category":"Building & Trades",
            "subcategory":"Construction",
            "type":"Services"
        }
    ],
    "sg:phone":"+1 763 533 2228",
    "sg:postcode":"55429",
    "sg:province":"MN",
    "sg:tags":[
        "a",
        "center",
        "for",
        "retailer",
        "distribution",
        "furniture"
    ],
    "wof:name":"Wickes Furniture Company Inc",
    "wof:placetype":"venue"
},
  "geometry": {"coordinates":[-93.33429700000001,45.044261],"type":"Point"}
}