{
  "type": "Feature",
  "properties": {
    "addr:full":"1250 Little Rock Rd NE Rice MN 56367",
    "addr:housenumber":"1250",
    "addr:postcode":"56367",
    "addr:street":"Little Rock Rd Ne",
    "iso:country":"US",
    "sg:address":"1250 Little Rock Rd NE",
    "sg:city":"Rice",
    "sg:classifiers":[
        {
            "category":"Restaurant",
            "type":"Food & Drink"
        }
    ],
    "sg:phone":"+1 320 393 4780",
    "sg:postcode":"56367",
    "sg:province":"MN",
    "wof:name":"The Olive Branch Retreat Inc",
    "wof:placetype":"venue"
},
  "geometry": {"coordinates":[-94.145854,45.706076],"type":"Point"}
}