{
  "type": "Feature",
  "properties": {
    "addr:full":"5601 Grandview Blvd Apt 5 Mound MN 55364",
    "addr:housenumber":"5601;5",
    "addr:postcode":"55364",
    "addr:street":"Grandview Blvd Apt",
    "iso:country":"US",
    "sg:address":"5601 Grandview Blvd Apt 5",
    "sg:city":"Mound",
    "sg:classifiers":[
        {
            "category":"Manufacturing",
            "subcategory":"Wood Products",
            "type":"Manufacturing & Wholesale Goods"
        }
    ],
    "sg:phone":"+1 952 472 1976",
    "sg:postcode":"55364",
    "sg:province":"MN",
    "sg:tags":[
        "millwork-wholesale",
        "millwork",
        "manufacturer"
    ],
    "wof:name":"Stephen Jesmer",
    "wof:placetype":"venue"
},
  "geometry": {"coordinates":[-93.66596199999999,44.942959],"type":"Point"}
}