{
  "type": "Feature",
  "properties": {
    "iso:country":"US",
    "sg:address":"1771 Premiere Dr",
    "sg:city":"Mankato",
    "sg:classifiers":[
        {
            "category":"Home & Garden",
            "subcategory":"Building Materials",
            "type":"Retail Goods"
        }
    ],
    "sg:phone":"+1 507 387 3400",
    "sg:postcode":"56001",
    "sg:province":"MN",
    "wof:name":"Menards",
    "wof:placetype":"venue"
},
  "geometry": {"coordinates":[-93.952105,44.183472],"type":"Point"}
}