{
  "type": "Feature",
  "properties": {
    "addr:full":"4033 44th Ave S Minneapolis MN 55406",
    "addr:housenumber":"4033",
    "addr:postcode":"55406",
    "addr:street":"44Th Ave S",
    "iso:country":"US",
    "sg:address":"4033 44th Ave S",
    "sg:city":"Minneapolis",
    "sg:classifiers":[
        {
            "category":"Structure",
            "subcategory":"Office Building",
            "type":"Public Place"
        }
    ],
    "sg:phone":"+1 612 673 7633",
    "sg:postcode":"55406",
    "sg:province":"MN",
    "sg:tags":[
        "park"
    ],
    "wof:name":"Seasun Properties",
    "wof:placetype":"venue"
},
  "geometry": {"coordinates":[-93.21019699999999,44.930056],"type":"Point"}
}