{
  "type": "Feature",
  "properties": {
    "iso:country":"US",
    "sg:address":"6849 Hallmark Dr",
    "sg:city":"Eden Prairie",
    "sg:classifiers":[
        {
            "category":"Building & Trades",
            "subcategory":"Construction",
            "type":"Services"
        }
    ],
    "sg:phone":"+1 612 861 5011",
    "sg:postcode":"55346",
    "sg:province":"MN",
    "sg:tags":[
        "house",
        "contractor",
        "concrete"
    ],
    "wof:name":"A Step Ahead-Morris Concrete",
    "wof:placetype":"venue"
},
  "geometry": {"coordinates":[-93.47386400000001,44.87959],"type":"Point"}
}