{
  "type": "Feature",
  "properties": {
    "addr:full":"11140 Upton Ave S Minneapolis MN 55431",
    "addr:housenumber":"11140",
    "addr:postcode":"55431",
    "addr:street":"Upton Ave S",
    "iso:country":"US",
    "sg:address":"11140 Upton Ave S",
    "sg:city":"Minneapolis",
    "sg:classifiers":[
        {
            "category":"Professional",
            "type":"Services"
        }
    ],
    "sg:phone":"+1 952 888 4941",
    "sg:postcode":"55431",
    "sg:province":"MN",
    "wof:name":"Julia K Rossini",
    "wof:placetype":"venue"
},
  "geometry": {"coordinates":[-93.31567099999999,44.802979],"type":"Point"}
}