{
  "type": "Feature",
  "properties": {
    "addr:full":"9936 Columbus Ave S Minneapolis MN 55420",
    "addr:housenumber":"9936",
    "addr:postcode":"55420",
    "addr:street":"Columbus Ave S",
    "iso:country":"US",
    "sg:address":"9936 Columbus Ave S",
    "sg:city":"Minneapolis",
    "sg:classifiers":[
        {
            "category":"Professional",
            "subcategory":"Business Services",
            "type":"Services"
        }
    ],
    "sg:phone":"+1 952 881 5763",
    "sg:postcode":"55420",
    "sg:province":"MN",
    "wof:name":"Bloomington Sign Co",
    "wof:placetype":"venue"
},
  "geometry": {"coordinates":[-93.264628,44.823337],"type":"Point"}
}