{
  "type": "Feature",
  "properties": {
    "iso:country":"US",
    "sg:address":"200 9th St",
    "sg:city":"Internatl Falls",
    "sg:classifiers":[
        {
            "category":"Taxi",
            "type":"Transportation"
        }
    ],
    "sg:phone":"+1 218 283 8635",
    "sg:postcode":"56649",
    "sg:province":"MN",
    "sg:tags":[
        "taxicab"
    ],
    "sg:website":"www.citycab.com",
    "wof:name":"City Cab & Van Svc",
    "wof:placetype":"venue"
},
  "geometry": {"coordinates":[-93.40313500000001,48.596457],"type":"Point"}
}