{
  "type": "Feature",
  "properties": {
    "addr:full":"100 Knollwood St W Annandale MN 55302",
    "addr:housenumber":"100",
    "addr:postcode":"55302",
    "addr:street":"Knollwood St W",
    "iso:country":"US",
    "sg:address":"100 Knollwood St W",
    "sg:city":"Annandale",
    "sg:classifiers":[
        {
            "category":"Home & Garden",
            "subcategory":"Home Furnishings",
            "type":"Retail Goods"
        }
    ],
    "sg:phone":"+1 320 274 3810",
    "sg:postcode":"55302",
    "sg:province":"MN",
    "sg:tags":[
        "curtain",
        "made",
        "drapery"
    ],
    "wof:name":"Decorator's Post",
    "wof:placetype":"venue"
},
  "geometry": {"coordinates":[-94.124494,45.257991],"type":"Point"}
}