{
  "type": "Feature",
  "properties": {
    "iso:country":"US",
    "sg:address":"19694 Enterprise Dr",
    "sg:city":"Park Rapids",
    "sg:classifiers":[
        {
            "category":"Travel",
            "subcategory":"Hotels & Motels",
            "type":"Entertainment"
        }
    ],
    "sg:phone":"+1 218 732 1213",
    "sg:postcode":"56470",
    "sg:province":"MN",
    "wof:name":"Terrace View Motor Lodge Inc",
    "wof:placetype":"venue"
},
  "geometry": {"coordinates":[-95.083894,46.943803],"type":"Point"}
}