{
  "type": "Feature",
  "properties": {
    "iso:country":"US",
    "sg:address":"20870 Co Rd 29",
    "sg:city":"New Ulm",
    "sg:classifiers":[
        {
            "category":"Farming",
            "subcategory":"Livestock Farm",
            "type":"Manufacturing & Wholesale Goods"
        }
    ],
    "sg:phone":"+1 507 354 5153",
    "sg:postcode":"56073",
    "sg:province":"MN",
    "sg:tags":[
        "feedlot",
        "corn",
        "soybean",
        "beef",
        "cattle"
    ],
    "wof:name":"Schmid Glennis",
    "wof:placetype":"venue"
},
  "geometry": {"coordinates":[-94.592905,44.357891],"type":"Point"}
}