{
  "type": "Feature",
  "properties": {
    "addr:full":"7800 Golden Valley Rd Minneapolis MN 55427",
    "addr:housenumber":"7800",
    "addr:postcode":"55427",
    "addr:street":"Golden Valley Rd",
    "iso:country":"US",
    "sg:address":"7800 Golden Valley Rd",
    "sg:city":"Minneapolis",
    "sg:classifiers":[
        {
            "category":"Organizations",
            "subcategory":"Non-profit Organization",
            "type":"Services"
        }
    ],
    "sg:phone":"+1 763 593 8054",
    "sg:postcode":"55427",
    "sg:province":"MN",
    "sg:tags":[
        "social"
    ],
    "wof:name":"Golden Vly Crime Prvntion Fund",
    "wof:placetype":"venue"
},
  "geometry": {"coordinates":[-93.380363,44.9855],"type":"Point"}
}