{
  "type": "Feature",
  "properties": {
    "iso:country":"US",
    "sg:address":"2837 Anthony Ln S",
    "sg:city":"Minneapolis",
    "sg:classifiers":[
        {
            "category":"Wholesale",
            "subcategory":"Stationery",
            "type":"Manufacturing & Wholesale Goods"
        }
    ],
    "sg:phone":"+1 612 706 2200",
    "sg:postcode":"55418",
    "sg:province":"MN",
    "sg:tags":[
        "packaging",
        "material"
    ],
    "sg:website":"www.thewinstoncompany.com",
    "wof:name":"Twincomm",
    "wof:placetype":"venue"
},
  "geometry": {"coordinates":[-93.209976,45.01969],"type":"Point"}
}