{
  "type": "Feature",
  "properties": {
    "iso:country":"US",
    "sg:address":"16962 Kenrick Ave",
    "sg:city":"Lakeville",
    "sg:classifiers":[
        {
            "category":"Real Estate",
            "subcategory":"Developer",
            "type":"Services"
        },
        {
            "category":"Real Estate",
            "subcategory":"Real Estate Operator",
            "type":"Services"
        }
    ],
    "sg:phone":"+1 952 435 5541",
    "sg:postcode":"55044",
    "sg:province":"MN",
    "sg:tags":[
        "mobile",
        "home",
        "site"
    ],
    "wof:name":"Connelly's Mobile Home Park",
    "wof:placetype":"venue"
},
  "geometry": {"coordinates":[-93.28505800000001,44.703572],"type":"Point"}
}