{
  "type": "Feature",
  "properties": {
    "addr:full":"714 1st Ave NW Faribault MN 55021",
    "addr:housenumber":"714",
    "addr:postcode":"55021",
    "addr:street":"1St Ave Nw",
    "iso:country":"US",
    "sg:address":"714 1st Ave NW",
    "sg:city":"Faribault",
    "sg:classifiers":[
        {
            "category":"Professional",
            "type":"Services"
        }
    ],
    "sg:phone":"+1 507 332 7446",
    "sg:postcode":"55021",
    "sg:province":"MN",
    "wof:name":"Jrj African Imports",
    "wof:placetype":"venue"
},
  "geometry": {"coordinates":[-93.270093,44.299089],"type":"Point"}
}