{
  "type": "Feature",
  "properties": {
    "addr:full":"214 W King St St Paul MN 55107",
    "addr:housenumber":"214",
    "addr:postcode":"55107",
    "addr:street":"W King St",
    "iso:country":"US",
    "sg:address":"214 W King St",
    "sg:city":"St Paul",
    "sg:classifiers":[
        {
            "category":"Retail",
            "subcategory":"Auto Repair",
            "type":"Services"
        }
    ],
    "sg:phone":"+1 612 817 1469",
    "sg:postcode":"55107",
    "sg:province":"MN",
    "sg:tags":[
        "automobile",
        "customizing"
    ],
    "wof:name":"Supreme Custom Coach",
    "wof:placetype":"venue"
},
  "geometry": {"coordinates":[-93.095799,44.927504],"type":"Point"}
}