{
  "type": "Feature",
  "properties": {
    "iso:country":"US",
    "sg:address":"549 154th Ave NE",
    "sg:city":"Andover",
    "sg:classifiers":[
        {
            "category":"Real Estate",
            "subcategory":"Real Estate Services",
            "type":"Services"
        }
    ],
    "sg:phone":"+1 763 434 7825",
    "sg:postcode":"55304",
    "sg:province":"MN",
    "sg:tags":[
        "inspection"
    ],
    "sg:website":"http://www.stmarys-wbl.org",
    "wof:name":"Mortenson Home Inspection",
    "wof:placetype":"venue"
},
  "geometry": {"coordinates":[-93.255737,45.248049],"type":"Point"}
}