{
  "type": "Feature",
  "properties": {
    "addr:full":"1213 E Lyon St Marshall MN 56258",
    "addr:housenumber":"1213",
    "addr:postcode":"56258",
    "addr:street":"E Lyon St",
    "iso:country":"US",
    "sg:address":"1213 E Lyon St",
    "sg:city":"Marshall",
    "sg:classifiers":[
        {
            "category":"Shopping",
            "subcategory":"Beauty & Cosmetics",
            "type":"Retail Goods"
        }
    ],
    "sg:phone":"+1 507 537 1122",
    "sg:postcode":"56258",
    "sg:province":"MN",
    "sg:tags":[
        "perfume",
        "salons-equipment",
        "supply"
    ],
    "wof:name":"Janet Chapman Inc",
    "wof:placetype":"venue"
},
  "geometry": {"coordinates":[-95.772369,44.44313],"type":"Point"}
}