{
  "type": "Feature",
  "properties": {
    "iso:country":"US",
    "sg:address":"215 1st St NE",
    "sg:city":"Mcintosh",
    "sg:classifiers":[
        {
            "category":"Professional",
            "subcategory":"Detective & Security Services",
            "type":"Services"
        }
    ],
    "sg:phone":"+1 218 563 2690",
    "sg:postcode":"56556",
    "sg:province":"MN",
    "sg:tags":[
        "information",
        "bureau"
    ],
    "wof:name":"Sugarbrooke Creative Svcs",
    "wof:placetype":"venue"
},
  "geometry": {"coordinates":[-95.88458,47.636871],"type":"Point"}
}