{
  "type": "Feature",
  "properties": {
    "iso:country":"US",
    "sg:address":"18 2nd St NE",
    "sg:city":"Cass Lake",
    "sg:classifiers":[
        {
            "category":"Organizations",
            "subcategory":"Religious Organization",
            "type":"Services"
        }
    ],
    "sg:phone":"+1 218 335 8531",
    "sg:postcode":"56633",
    "sg:province":"MN",
    "sg:tags":[
        "church"
    ],
    "wof:name":"Lighthouse Pentecostal Chr-God",
    "wof:placetype":"venue"
},
  "geometry": {"coordinates":[-94.602924,47.379151],"type":"Point"}
}