{
  "type": "Feature",
  "properties": {
    "iso:country":"US",
    "sg:address":"700 Paul Bunyan Dr S",
    "sg:city":"Bemidji",
    "sg:classifiers":[
        {
            "category":"Ice Cream",
            "type":"Food & Drink"
        }
    ],
    "sg:menulink":"http://www.allmenus.com/mn/bemidji/168210-dairy-queen/menu/",
    "sg:phone":"+1 218 444 2108",
    "sg:postcode":"56601",
    "sg:province":"MN",
    "sg:tags":[
        "burger",
        "american"
    ],
    "wof:name":"Dairy Queen",
    "wof:placetype":"venue"
},
  "geometry": {"coordinates":[-94.87433799999999,47.465355],"type":"Point"}
}