{
  "type": "Feature",
  "properties": {
    "addr:full":"6322 Timber Trl Minneapolis MN 55439",
    "addr:housenumber":"6322",
    "addr:postcode":"55439",
    "addr:street":"Timber Trl",
    "iso:country":"US",
    "sg:address":"6322 Timber Trl",
    "sg:city":"Minneapolis",
    "sg:classifiers":[
        {
            "category":"Professional",
            "subcategory":"Management & Consulting",
            "type":"Services"
        }
    ],
    "sg:phone":"+1 952 903 0345",
    "sg:postcode":"55439",
    "sg:province":"MN",
    "sg:tags":[
        "consultant",
        "search",
        "executive"
    ],
    "wof:name":"Csa",
    "wof:placetype":"venue"
},
  "geometry": {"coordinates":[-93.39182700000001,44.889055],"type":"Point"}
}