{
  "type": "Feature",
  "properties": {
    "addr:full":"7103 42nd St N Moorhead MN 56560",
    "addr:housenumber":"7103",
    "addr:postcode":"56560",
    "addr:street":"42Nd St N",
    "iso:country":"US",
    "sg:address":"7103 42nd St N",
    "sg:city":"Moorhead",
    "sg:classifiers":[
        {
            "category":"Manufacturing",
            "subcategory":"Buildings",
            "type":"Manufacturing & Wholesale Goods"
        },
        {
            "category":"Building & Trades",
            "subcategory":"Construction",
            "type":"Services"
        }
    ],
    "sg:phone":"+1 218 261 2604",
    "sg:postcode":"56560",
    "sg:province":"MN",
    "sg:tags":[
        "home",
        "builder",
        "contractor"
    ],
    "wof:name":"Ueland Construction",
    "wof:placetype":"venue"
},
  "geometry": {"coordinates":[-96.711022,46.952385],"type":"Point"}
}