{
  "type": "Feature",
  "properties": {
    "iso:country":"US",
    "sg:address":"7 2nd St NW",
    "sg:city":"Buffalo",
    "sg:classifiers":[
        {
            "category":"Real Estate",
            "subcategory":"Real Estate Services",
            "type":"Services"
        }
    ],
    "sg:phone":"+1 763 682 1252",
    "sg:postcode":"55313",
    "sg:province":"MN",
    "wof:name":"Campbell Abstract Co",
    "wof:placetype":"venue"
},
  "geometry": {"coordinates":[-93.878226,45.174643],"type":"Point"}
}