{
  "type": "Feature",
  "properties": {
    "iso:country":"US",
    "sg:address":"7100 Northland Cir N",
    "sg:city":"Minneapolis",
    "sg:classifiers":[
        {
            "category":"Professional",
            "subcategory":"Management & Consulting",
            "type":"Services"
        }
    ],
    "sg:phone":"+1 952 832 0678",
    "sg:postcode":"55428",
    "sg:province":"MN",
    "wof:name":"Shrader & Associates",
    "wof:placetype":"venue"
},
  "geometry": {"coordinates":[-93.390022,45.082297],"type":"Point"}
}