{
  "type": "Feature",
  "properties": {
    "addr:full":"2658 White Tail Ridge Red Wing MN 55066",
    "addr:housenumber":"2658",
    "addr:postcode":"55066",
    "addr:street":"White Tail Ridge",
    "iso:country":"US",
    "sg:address":"2658 White Tail Ridge",
    "sg:city":"Red Wing",
    "sg:classifiers":[
        {
            "category":"Wholesale",
            "subcategory":"Farm Supplies",
            "type":"Manufacturing & Wholesale Goods"
        }
    ],
    "sg:phone":"+1 651 388 7161",
    "sg:postcode":"55066",
    "sg:province":"MN",
    "wof:name":"F & D Supply Inc",
    "wof:placetype":"venue"
},
  "geometry": {"coordinates":[-92.532228,44.530783],"type":"Point"}
}