{
  "type": "Feature",
  "properties": {
    "addr:full":"232 2nd St S Winsted MN 55395",
    "addr:housenumber":"232",
    "addr:postcode":"55395",
    "addr:street":"2Nd St S",
    "iso:country":"US",
    "sg:address":"232 2nd St S",
    "sg:city":"Winsted",
    "sg:classifiers":[
        {
            "category":"Health Services",
            "subcategory":"Health Practitioner",
            "type":"Services"
        }
    ],
    "sg:phone":"+1 320 485 4446",
    "sg:postcode":"55395",
    "sg:province":"MN",
    "sg:tags":[
        "therapist",
        "physical"
    ],
    "wof:name":"Winsted Therapeutic Massage",
    "wof:placetype":"venue"
},
  "geometry": {"coordinates":[-94.04830200000001,44.96212],"type":"Point"}
}