{
  "type": "Feature",
  "properties": {
    "addr:full":"26305 Edgewood Rd Excelsior MN 55331",
    "addr:housenumber":"26305",
    "addr:postcode":"55331",
    "addr:street":"Edgewood Rd",
    "iso:country":"US",
    "sg:address":"26305 Edgewood Rd",
    "sg:city":"Excelsior",
    "sg:classifiers":[
        {
            "category":"Building & Trades",
            "subcategory":"Construction",
            "type":"Services"
        }
    ],
    "sg:phone":"+1 952 470 5422",
    "sg:postcode":"55331",
    "sg:province":"MN",
    "sg:tags":[
        "contractor"
    ],
    "wof:name":"Special Additons Inc",
    "wof:placetype":"venue"
},
  "geometry": {"coordinates":[-93.61350299999999,44.906101],"type":"Point"}
}