{
  "type": "Feature",
  "properties": {
    "addr:full":"620 31st St NW Rochester MN 55901",
    "addr:housenumber":"620",
    "addr:postcode":"55901",
    "addr:street":"31St St Nw",
    "iso:country":"US",
    "sg:address":"620 31st St NW",
    "sg:city":"Rochester",
    "sg:classifiers":[
        {
            "category":"Professional",
            "subcategory":"Computer Services",
            "type":"Services"
        }
    ],
    "sg:phone":"+1 507 289 8244",
    "sg:postcode":"55901",
    "sg:province":"MN",
    "sg:tags":[
        "processing",
        "datum"
    ],
    "wof:name":"P C Discovery Inc",
    "wof:placetype":"venue"
},
  "geometry": {"coordinates":[-92.474104,44.055629],"type":"Point"}
}