{
  "type": "Feature",
  "properties": {
    "iso:country":"US",
    "sg:address":"8831 Hastings St NE",
    "sg:city":"Minneapolis",
    "sg:classifiers":[
        {
            "category":"Building & Trades",
            "subcategory":"Landscaping Services",
            "type":"Services"
        }
    ],
    "sg:phone":"+1 763 780 8335",
    "sg:postcode":"55449",
    "sg:province":"MN",
    "sg:tags":[
        "snow",
        "plowing"
    ],
    "wof:name":"Pavey Contracting Company",
    "wof:placetype":"venue"
},
  "geometry": {"coordinates":[-93.225132,45.131465],"type":"Point"}
}