{
  "type": "Feature",
  "properties": {
    "addr:full":"8130 Spring Valley Rd Waconia MN 55387",
    "addr:housenumber":"8130",
    "addr:postcode":"55387",
    "addr:street":"Spring Valley Rd",
    "iso:country":"US",
    "sg:address":"8130 Spring Valley Rd",
    "sg:city":"Waconia",
    "sg:classifiers":[
        {
            "category":"Travel",
            "subcategory":"Travel Agent",
            "type":"Entertainment"
        }
    ],
    "sg:phone":"+1 952 442 4035",
    "sg:postcode":"55387",
    "sg:province":"MN",
    "sg:tags":[
        "agency"
    ],
    "wof:name":"Victorias Travels",
    "wof:placetype":"venue"
},
  "geometry": {"coordinates":[-93.717978,44.858488],"type":"Point"}
}