{
  "type": "Feature",
  "properties": {
    "addr:full":"7601 Northland Dr N Ste 1 Minneapolis MN 55428",
    "addr:housenumber":"7601",
    "addr:postcode":"55428",
    "addr:street":"Northland Dr N Ste 1",
    "iso:country":"US",
    "sg:address":"7601 Northland Dr N Ste 1",
    "sg:city":"Minneapolis",
    "sg:classifiers":[
        {
            "category":"Health Services",
            "subcategory":"Hospital",
            "type":"Services"
        }
    ],
    "sg:phone":"+1 952 922 8427",
    "sg:postcode":"55428",
    "sg:province":"MN",
    "sg:tags":[
        "equipment",
        "supply"
    ],
    "wof:name":"Midstim Usa Inc",
    "wof:placetype":"venue"
},
  "geometry": {"coordinates":[-93.39582900000001,45.092333],"type":"Point"}
}