{
  "type": "Feature",
  "properties": {
    "addr:full":"9436 W Highway 61 Schroeder MN 55613",
    "addr:housenumber":"9436",
    "addr:postcode":"55613",
    "addr:street":"W Highway 61 Schroeder",
    "iso:country":"US",
    "sg:address":"9436 W Highway 61",
    "sg:city":"Schroeder",
    "sg:classifiers":[
        {
            "category":"Travel",
            "subcategory":"Hotels & Motels",
            "type":"Entertainment"
        },
        {
            "category":"Travel",
            "subcategory":"Bed & Breakfast",
            "type":"Entertainment"
        }
    ],
    "sg:phone":"+1 218 663 7574",
    "sg:postcode":"55613",
    "sg:province":"MN",
    "sg:tags":[
        "cottage",
        "inn"
    ],
    "wof:name":"Mckeever Well Drilling, Inc.",
    "wof:placetype":"venue"
},
  "geometry": {"coordinates":[-91.014931,47.470425],"type":"Point"}
}