{
  "type": "Feature",
  "properties": {
    "iso:country":"US",
    "sg:address":"9725 Pleasant Ave S",
    "sg:city":"Minneapolis",
    "sg:classifiers":[
        {
            "category":"Real Estate",
            "subcategory":"Real Estate Operator",
            "type":"Services"
        }
    ],
    "sg:phone":"+1 952 881 3639",
    "sg:postcode":"55420",
    "sg:province":"MN",
    "sg:tags":[
        "apartment"
    ],
    "wof:name":"International Village Apartments",
    "wof:placetype":"venue"
},
  "geometry": {"coordinates":[-93.283227,44.827036],"type":"Point"}
}