{
  "type": "Feature",
  "properties": {
    "iso:country":"US",
    "sg:address":"17025 Round Lake Blvd NW",
    "sg:city":"Andover",
    "sg:classifiers":[
        {
            "category":"Manufacturing",
            "subcategory":"Signs",
            "type":"Manufacturing & Wholesale Goods"
        }
    ],
    "sg:phone":"+1 763 753 4633",
    "sg:postcode":"55304",
    "sg:province":"MN",
    "sg:tags":[
        "body",
        "auto",
        "specialty",
        "mfg"
    ],
    "sg:website":"www.signstation.com",
    "wof:name":"Sign Station",
    "wof:placetype":"venue"
},
  "geometry": {"coordinates":[-93.34687099999999,45.279989],"type":"Point"}
}