{
  "type": "Feature",
  "properties": {
    "iso:country":"US",
    "sg:address":"336 Robert St N",
    "sg:city":"St Paul",
    "sg:classifiers":[
        {
            "category":"Autos & Motor Vehicles",
            "subcategory":"Automobile Sales",
            "type":"Retail Goods"
        }
    ],
    "sg:phone":"+1 651 291 9811",
    "sg:postcode":"55101",
    "sg:province":"MN",
    "sg:tags":[
        "car",
        "dealer"
    ],
    "sg:website":"www.autooutsource.com",
    "wof:name":"Auto Outsource",
    "wof:placetype":"venue"
},
  "geometry": {"coordinates":[-93.090684,44.94735],"type":"Point"}
}