{
  "type": "Feature",
  "properties": {
    "addr:full":"43356 Co Rd 112 Sauk Centre MN 56378",
    "addr:housenumber":"43356",
    "addr:postcode":"56378",
    "addr:street":"Co Rd 112",
    "iso:country":"US",
    "sg:address":"43356 Co Rd 112",
    "sg:city":"Sauk Centre",
    "sg:classifiers":[
        {
            "category":"Bars & Pubs",
            "type":"Food & Drink"
        }
    ],
    "sg:phone":"+1 320 351 3505",
    "sg:postcode":"56378",
    "sg:province":"MN",
    "wof:name":"Bear Trap",
    "wof:placetype":"venue"
},
  "geometry": {"coordinates":[-94.938833,45.750425],"type":"Point"}
}