{
  "type": "Feature",
  "properties": {
    "addr:full":"2700 E 28th St Ste 120 Minneapolis MN 55406",
    "addr:housenumber":"2700",
    "addr:postcode":"55406",
    "addr:street":"E 28Th St Ste 120",
    "iso:country":"US",
    "sg:address":"2700 E 28th St Ste 120",
    "sg:city":"Minneapolis",
    "sg:classifiers":[
        {
            "category":"Wholesale",
            "subcategory":"Electrical",
            "type":"Manufacturing & Wholesale Goods"
        }
    ],
    "sg:phone":"+1 612 226 1248",
    "sg:postcode":"55406",
    "sg:province":"MN",
    "sg:tags":[
        "semiconductor",
        "device"
    ],
    "wof:name":"The Iiian Company",
    "wof:placetype":"venue"
},
  "geometry": {"coordinates":[-93.23313899999999,44.951981],"type":"Point"}
}