{
  "type": "Feature",
  "properties": {
    "iso:country":"US",
    "sg:address":"11506 20th St N",
    "sg:city":"Moorhead",
    "sg:phone":"+1 218 233 4332",
    "sg:postcode":"56560",
    "sg:province":"MN",
    "sg:tags":[
        "farm",
        "soybean"
    ],
    "wof:name":"Norby Farms",
    "wof:placetype":"venue"
},
  "geometry": {"coordinates":[-96.753141,47.013618],"type":"Point"}
}