{
  "type": "Feature",
  "properties": {
    "iso:country":"US",
    "sg:address":"4330 Cedar Lake Rd S",
    "sg:city":"St Louis Park",
    "sg:classifiers":[
        {
            "category":"Social Services",
            "type":"Services"
        }
    ],
    "sg:phone":"+1 763 732 0610",
    "sg:postcode":"55416",
    "sg:province":"MN",
    "sg:tags":[
        "organization",
        "welfare"
    ],
    "wof:name":"Necha-Jewish Response-Diaster",
    "wof:placetype":"venue"
},
  "geometry": {"coordinates":[-93.33197699999999,44.961907],"type":"Point"}
}