{
  "type": "Feature",
  "properties": {
    "iso:country":"US",
    "sg:address":"2025 105th Ave NE",
    "sg:city":"Minneapolis",
    "sg:classifiers":[
        {
            "category":"Manufacturing",
            "subcategory":"Aerospace",
            "type":"Manufacturing & Wholesale Goods"
        }
    ],
    "sg:phone":"+1 763 784 5330",
    "sg:postcode":"55449",
    "sg:province":"MN",
    "sg:tags":[
        "shop",
        "aircraft",
        "machine",
        "equipment",
        "job",
        "part",
        "manufacturer",
        "supplies-wholesale",
        "replacement"
    ],
    "wof:name":"A&B Tool & Gauge",
    "wof:placetype":"venue"
},
  "geometry": {"coordinates":[-93.21899500000001,45.160766],"type":"Point"}
}