{
  "type": "Feature",
  "properties": {
    "iso:country":"US",
    "sg:address":"240 North Rd",
    "sg:city":"Cloquet",
    "sg:classifiers":[
        {
            "category":"Professional",
            "subcategory":"Accounting & Tax Preparation",
            "type":"Services"
        }
    ],
    "sg:phone":"+1 218 879 1775",
    "sg:postcode":"55720",
    "sg:province":"MN",
    "sg:tags":[
        "accountant"
    ],
    "wof:name":"Ronald E Peterson LTD",
    "wof:placetype":"venue"
},
  "geometry": {"coordinates":[-92.466577,46.735582],"type":"Point"}
}