{
  "type": "Feature",
  "properties": {
    "iso:country":"US",
    "sg:address":"1334 Wood Duck Trl",
    "sg:city":"Shakopee",
    "sg:classifiers":[
        {
            "category":"Food & Beverages",
            "subcategory":"Specialty",
            "type":"Retail Goods"
        },
        {
            "category":"Food & Beverages",
            "subcategory":"Groceries & Convenience Stores",
            "type":"Retail Goods"
        }
    ],
    "sg:phone":"+1 952 233 5200",
    "sg:postcode":"55379",
    "sg:province":"MN",
    "sg:tags":[
        "product",
        "health",
        "diet"
    ],
    "wof:name":"The Hub Natural Foods",
    "wof:placetype":"venue"
},
  "geometry": {"coordinates":[-93.507698,44.752701],"type":"Point"}
}