{
  "type": "Feature",
  "properties": {
    "addr:full":"1405 Xenium Ln N Minneapolis MN 55441",
    "addr:housenumber":"1405",
    "addr:postcode":"55441",
    "addr:street":"Xenium Ln N",
    "iso:country":"US",
    "sg:address":"1405 Xenium Ln N",
    "sg:city":"Minneapolis",
    "sg:classifiers":[
        {
            "category":"Railroad",
            "type":"Transportation"
        },
        {
            "category":"Train Station",
            "subcategory":"Rail",
            "type":"Transportation"
        }
    ],
    "sg:phone":"+1 763 383 2839",
    "sg:postcode":"55441",
    "sg:province":"MN",
    "sg:tags":[
        "agency",
        "railroads-ticket"
    ],
    "sg:website":"http://www.amtrak.com",
    "wof:name":"Amtrak",
    "wof:placetype":"venue"
},
  "geometry": {"coordinates":[-93.45115800000001,44.993131],"type":"Point"}
}