{
  "type": "Feature",
  "properties": {
    "addr:full":"6500 Brooklyn Blvd Minneapolis MN 55429",
    "addr:housenumber":"6500",
    "addr:postcode":"55429",
    "addr:street":"Brooklyn Blvd",
    "iso:country":"US",
    "sg:address":"6500 Brooklyn Blvd",
    "sg:city":"Minneapolis",
    "sg:classifiers":[
        {
            "category":"Health Services",
            "subcategory":"Nursing And Care Facility",
            "type":"Services"
        }
    ],
    "sg:phone":"+1 763 566 5063",
    "sg:postcode":"55429",
    "sg:province":"MN",
    "wof:name":"Home Care & PCA Services LLC",
    "wof:placetype":"venue"
},
  "geometry": {"coordinates":[-93.330319,45.073164],"type":"Point"}
}