{
  "type": "Feature",
  "properties": {
    "iso:country":"US",
    "sg:address":"4830 Union Terrace Ln N",
    "sg:city":"Minneapolis",
    "sg:classifiers":[
        {
            "category":"Professional",
            "subcategory":"Engineering",
            "type":"Services"
        }
    ],
    "sg:phone":"+1 763 744 1224",
    "sg:postcode":"55442",
    "sg:province":"MN",
    "sg:tags":[
        "engineer"
    ],
    "wof:name":"Northport Engineering Nexlight",
    "wof:placetype":"venue"
},
  "geometry": {"coordinates":[-93.413791,45.041272],"type":"Point"}
}