{
  "type": "Feature",
  "properties": {
    "addr:full":"101 Main St E Pipestone MN 56164",
    "addr:housenumber":"101",
    "addr:postcode":"56164",
    "addr:street":"Main St E",
    "iso:country":"US",
    "sg:address":"101 Main St E",
    "sg:city":"Pipestone",
    "sg:classifiers":[
        {
            "category":"Shopping",
            "subcategory":"Pharmacy",
            "type":"Retail Goods"
        }
    ],
    "sg:phone":"+1 507 825 3100",
    "sg:postcode":"56164",
    "sg:province":"MN",
    "wof:name":"A & S Drugs",
    "wof:placetype":"venue"
},
  "geometry": {"coordinates":[-96.317617,44.000505],"type":"Point"}
}