{
  "type": "Feature",
  "properties": {
    "addr:full":"9575 Sucker Creek Rd NW Rice MN 56367",
    "addr:postcode":"9575;56367",
    "addr:street":"Sucker Creek Rd Nw",
    "iso:country":"US",
    "sg:address":"9575 Sucker Creek Rd NW",
    "sg:city":"Rice",
    "sg:classifiers":[
        {
            "category":"Retail",
            "subcategory":"Repair Shop",
            "type":"Services"
        }
    ],
    "sg:phone":"+1 320 393 3120",
    "sg:postcode":"56367",
    "sg:province":"MN",
    "wof:name":"Craigs Bike Shop",
    "wof:placetype":"venue"
},
  "geometry": {"coordinates":[-94.16471799999999,45.707282],"type":"Point"}
}