{
  "type": "Feature",
  "properties": {
    "addr:full":"19157 770th Ave Sacred Heart MN 56285",
    "addr:housenumber":"19157",
    "addr:postcode":"56285",
    "addr:street":"770Th Ave",
    "iso:country":"US",
    "sg:address":"19157 770th Ave",
    "sg:city":"Sacred Heart",
    "sg:classifiers":[
        {
            "category":"Organizations",
            "subcategory":"Religious Organization",
            "type":"Services"
        }
    ],
    "sg:phone":"+1 320 765 2215",
    "sg:postcode":"56285",
    "sg:province":"MN",
    "sg:tags":[
        "church"
    ],
    "wof:name":"Opdal Church & Chapel",
    "wof:placetype":"venue"
},
  "geometry": {"coordinates":[-95.296677,44.701514],"type":"Point"}
}