{
  "type": "Feature",
  "properties": {
    "addr:full":"4180 Thielman Ln St Cloud MN 56301",
    "addr:housenumber":"4180",
    "addr:postcode":"56301",
    "addr:street":"Thielman Ln",
    "iso:country":"US",
    "sg:address":"4180 Thielman Ln",
    "sg:city":"St Cloud",
    "sg:classifiers":[
        {
            "category":"Retail",
            "subcategory":"Veterinary Services",
            "type":"Services"
        }
    ],
    "sg:phone":"+1 320 258 3481",
    "sg:postcode":"56301",
    "sg:province":"MN",
    "sg:tags":[
        "veterinarian"
    ],
    "wof:name":"Affiliated Emergency Vet Svc",
    "wof:placetype":"venue"
},
  "geometry": {"coordinates":[-94.21379899999999,45.54851],"type":"Point"}
}