{
  "type": "Feature",
  "properties": {
    "addr:full":"682 60th Ave Dunnell MN 56127",
    "addr:housenumber":"682",
    "addr:postcode":"56127",
    "addr:street":"60Th Ave",
    "iso:country":"US",
    "sg:address":"682 60th Ave",
    "sg:city":"Dunnell",
    "sg:classifiers":[
        {
            "category":"Manufacturing",
            "subcategory":"Food",
            "type":"Manufacturing & Wholesale Goods"
        },
        {
            "category":"Farming",
            "subcategory":"Farm",
            "type":"Manufacturing & Wholesale Goods"
        }
    ],
    "sg:phone":"+1 507 695 2544",
    "sg:postcode":"56127",
    "sg:province":"MN",
    "sg:tags":[
        "corn",
        "product"
    ],
    "wof:name":"Michael Honnette",
    "wof:placetype":"venue"
},
  "geometry": {"coordinates":[-94.754289,43.582946],"type":"Point"}
}