{
  "type": "Feature",
  "properties": {
    "iso:country":"US",
    "sg:address":"556 Rice St",
    "sg:city":"St Paul",
    "sg:classifiers":[
        {
            "category":"Professional",
            "subcategory":"Engineering",
            "type":"Services"
        }
    ],
    "sg:phone":"+1 651 225 9789",
    "sg:postcode":"55103",
    "sg:province":"MN",
    "sg:tags":[
        "consulting",
        "engineer"
    ],
    "sg:website":"www.rani.com",
    "wof:name":"Rani Engineering Inc",
    "wof:placetype":"venue"
},
  "geometry": {"coordinates":[-93.10590999999999,44.957896],"type":"Point"}
}