{
  "type": "Feature",
  "properties": {
    "addr:full":"12387 150th St N Stillwater MN 55082",
    "addr:housenumber":"12387",
    "addr:postcode":"55082",
    "addr:street":"150Th St N",
    "iso:country":"US",
    "sg:address":"12387 150th St N",
    "sg:city":"Stillwater",
    "sg:classifiers":[
        {
            "category":"Building & Trades",
            "subcategory":"Landscaping Services",
            "type":"Services"
        }
    ],
    "sg:phone":"+1 651 433 3458",
    "sg:postcode":"55082",
    "sg:province":"MN",
    "sg:tags":[
        "lawn"
    ],
    "wof:name":"Mierow Landscapes",
    "wof:placetype":"venue"
},
  "geometry": {"coordinates":[-92.852683,45.167921],"type":"Point"}
}