{
  "type": "Feature",
  "properties": {
    "iso:country":"US",
    "sg:address":"2062 Jade Ln",
    "sg:city":"Saint Paul",
    "sg:classifiers":[
        {
            "category":"Travel",
            "subcategory":"Travel Agent",
            "type":"Entertainment"
        }
    ],
    "sg:phone":"+1 651 452 0431",
    "sg:postcode":"55122",
    "sg:province":"MN",
    "sg:tags":[
        "agency"
    ],
    "wof:name":"Dream Catcher Travel",
    "wof:placetype":"venue"
},
  "geometry": {"coordinates":[-93.20815899999999,44.808146],"type":"Point"}
}