{
  "type": "Feature",
  "properties": {
    "iso:country":"US",
    "sg:address":"7005 Wayzata Blvd",
    "sg:city":"Minneapolis",
    "sg:classifiers":[
        {
            "category":"Autos & Motor Vehicles",
            "subcategory":"Auto Supplies",
            "type":"Retail Goods"
        },
        {
            "category":"Retail",
            "subcategory":"Auto Repair",
            "type":"Services"
        }
    ],
    "sg:phone":"+1 952 544 0355",
    "sg:postcode":"55426",
    "sg:province":"MN",
    "sg:tags":[
        "shop",
        "installation",
        "exchange",
        "automobile",
        "engine",
        "machine",
        "equipment-service",
        "rebuilding",
        "air conditioning",
        "clutch"
    ],
    "sg:website":"http://stephsgaragerepair.com",
    "wof:name":"Steph's Garage",
    "wof:placetype":"venue"
},
  "geometry": {"coordinates":[-93.36856299999999,44.970881],"type":"Point"}
}