{
  "type": "Feature",
  "properties": {
    "addr:full":"313 Chestnut Ave Carlton MN 55718",
    "addr:housenumber":"313",
    "addr:postcode":"55718",
    "addr:street":"Chestnut Ave",
    "iso:country":"US",
    "sg:address":"313 Chestnut Ave",
    "sg:city":"Carlton",
    "sg:classifiers":[
        {
            "category":"Government",
            "subcategory":"Post Office",
            "type":"Public Place"
        }
    ],
    "sg:phone":"+1 218 384 4519",
    "sg:postcode":"55718",
    "sg:province":"MN",
    "wof:name":"US Post Office",
    "wof:placetype":"venue"
},
  "geometry": {"coordinates":[-92.42462500000001,46.664111],"type":"Point"}
}