{
  "type": "Feature",
  "properties": {
    "iso:country":"US",
    "sg:address":"1076 7th St W",
    "sg:city":"St Paul",
    "sg:classifiers":[
        {
            "category":"Health Services",
            "subcategory":"Doctor",
            "type":"Services"
        }
    ],
    "sg:phone":"+1 651 917 7237",
    "sg:postcode":"55102",
    "sg:province":"MN",
    "sg:tags":[
        "dentist"
    ],
    "wof:name":"Quality Care Clinic",
    "wof:placetype":"venue"
},
  "geometry": {"coordinates":[-93.13023699999999,44.925341],"type":"Point"}
}