{
  "type": "Feature",
  "properties": {
    "iso:country":"US",
    "sg:address":"1381 Knollwood Dr",
    "sg:city":"Worthington",
    "sg:classifiers":[
        {
            "category":"Social Services",
            "type":"Services"
        }
    ],
    "sg:phone":"+1 507 376 6095",
    "sg:postcode":"56187",
    "sg:province":"MN",
    "sg:tags":[
        "organization",
        "welfare"
    ],
    "wof:name":"Ridgewood",
    "wof:placetype":"venue"
},
  "geometry": {"coordinates":[-95.623718,43.60485],"type":"Point"}
}