{
  "type": "Feature",
  "properties": {
    "addr:full":"8210 Co Rd 10 Waconia MN 55387",
    "addr:housenumber":"8210;10",
    "addr:postcode":"55387",
    "addr:street":"Co Rd",
    "iso:country":"US",
    "sg:address":"8210 Co Rd 10",
    "sg:city":"Waconia",
    "sg:classifiers":[
        {
            "category":"Wholesale",
            "subcategory":"Toys & Hobbies",
            "type":"Manufacturing & Wholesale Goods"
        }
    ],
    "sg:phone":"+1 952 442 1638",
    "sg:postcode":"55387",
    "sg:province":"MN",
    "wof:name":"Laserscraps LLC",
    "wof:placetype":"venue"
},
  "geometry": {"coordinates":[-93.733183,44.819866],"type":"Point"}
}