{
  "type": "Feature",
  "properties": {
    "iso:country":"US",
    "sg:address":"7557 Camp 3 Rd NE",
    "sg:city":"Forest Lake",
    "sg:classifiers":[
        {
            "category":"Shopping",
            "subcategory":"Gifts & Souvenirs",
            "type":"Retail Goods"
        }
    ],
    "sg:phone":"+1 651 257 1438",
    "sg:postcode":"55025",
    "sg:province":"MN",
    "sg:tags":[
        "shop"
    ],
    "wof:name":"Sincerely Inc",
    "wof:placetype":"venue"
},
  "geometry": {"coordinates":[-93.07565200000001,45.254486],"type":"Point"}
}