{
  "type": "Feature",
  "properties": {
    "addr:full":"31399 Co Rd 100 Springfield MN 56087",
    "addr:housenumber":"31399;100",
    "addr:postcode":"56087",
    "addr:street":"Co Rd",
    "iso:country":"US",
    "sg:address":"31399 Co Rd 100",
    "sg:city":"Springfield",
    "sg:classifiers":[
        {
            "category":"Farming",
            "subcategory":"Farm",
            "type":"Manufacturing & Wholesale Goods"
        }
    ],
    "sg:phone":"+1 507 794 6761",
    "sg:postcode":"56087",
    "sg:province":"MN",
    "sg:tags":[
        "livestock",
        "crop",
        "general"
    ],
    "wof:name":"Donald & Marilyn Mathoiwetz",
    "wof:placetype":"venue"
},
  "geometry": {"coordinates":[-94.819485,44.195638],"type":"Point"}
}