{
  "type": "Feature",
  "properties": {
    "iso:country":"US",
    "sg:address":"230 Broadway St NE",
    "sg:city":"Minneapolis",
    "sg:classifiers":[
        {
            "category":"Health Services",
            "subcategory":"Doctor",
            "type":"Services"
        }
    ],
    "sg:phone":"+1 612 379 2300",
    "sg:postcode":"55413",
    "sg:province":"MN",
    "sg:tags":[
        "dental",
        "clinic"
    ],
    "sg:website":"http://www.doroschakdental.com",
    "wof:name":"Doroschak Dental",
    "wof:placetype":"venue"
},
  "geometry": {"coordinates":[-93.26460299999999,44.998699],"type":"Point"}
}