{
  "type": "Feature",
  "properties": {
    "iso:country":"US",
    "sg:address":"133 Phelps St",
    "sg:city":"Owatonna",
    "sg:classifiers":[
        {
            "category":"Arts & Performance",
            "subcategory":"Theater",
            "type":"Entertainment"
        }
    ],
    "sg:phone":"+1 507 451 9022",
    "sg:postcode":"55060",
    "sg:province":"MN",
    "sg:tags":[
        "theatrical"
    ],
    "wof:name":"Merlin Players",
    "wof:placetype":"venue"
},
  "geometry": {"coordinates":[-93.225419,44.079464],"type":"Point"}
}