{
  "type": "Feature",
  "properties": {
    "addr:full":"341 Plainview St Owatonna MN 55060",
    "addr:housenumber":"341",
    "addr:postcode":"55060",
    "addr:street":"Plainview St",
    "iso:country":"US",
    "sg:address":"341 Plainview St",
    "sg:city":"Owatonna",
    "sg:classifiers":[
        {
            "category":"Building & Trades",
            "subcategory":"Construction",
            "type":"Services"
        }
    ],
    "sg:phone":"+1 507 214 4663",
    "sg:postcode":"55060",
    "sg:province":"MN",
    "sg:tags":[
        "home",
        "builder"
    ],
    "wof:name":"Home Owner's Journal",
    "wof:placetype":"venue"
},
  "geometry": {"coordinates":[-93.232004,44.076181],"type":"Point"}
}