{
  "type": "Feature",
  "properties": {
    "addr:full":"10504 Hwy 32 N Hitterdal MN 56552",
    "addr:housenumber":"10504",
    "addr:postcode":"56552",
    "addr:street":"Hwy 32 N",
    "iso:country":"US",
    "sg:address":"10504 Hwy 32 N",
    "sg:city":"Hitterdal",
    "sg:classifiers":[
        {
            "category":"Farming",
            "subcategory":"Livestock Farm",
            "type":"Manufacturing & Wholesale Goods"
        }
    ],
    "sg:phone":"+1 218 962 3320",
    "sg:postcode":"56552",
    "sg:province":"MN",
    "sg:tags":[
        "beef",
        "feedlot",
        "cattle"
    ],
    "wof:name":"Joe Gerner",
    "wof:placetype":"venue"
},
  "geometry": {"coordinates":[-96.25785500000001,47.00562],"type":"Point"}
}