{
  "type": "Feature",
  "properties": {
    "iso:country":"US",
    "sg:address":"203 Marsh St",
    "sg:city":"Glenwood",
    "sg:classifiers":[
        {
            "category":"Bars & Pubs",
            "type":"Food & Drink"
        }
    ],
    "sg:phone":"+1 320 268 3276",
    "sg:postcode":"56334",
    "sg:province":"MN",
    "sg:tags":[
        "drinking"
    ],
    "wof:name":"Bobs Place",
    "wof:placetype":"venue"
},
  "geometry": {"coordinates":[-95.24802,45.575517],"type":"Point"}
}