{
  "type": "Feature",
  "properties": {
    "addr:full":"5216 W Broadway Ave Minneapolis MN 55429",
    "addr:housenumber":"5216",
    "addr:postcode":"55429",
    "addr:street":"W Broadway Ave",
    "iso:country":"US",
    "sg:address":"5216 W Broadway Ave",
    "sg:city":"Minneapolis",
    "sg:classifiers":[
        {
            "category":"Bars & Pubs",
            "type":"Food & Drink"
        },
        {
            "category":"Restaurant",
            "type":"Food & Drink"
        }
    ],
    "sg:phone":"+1 763 533 2977",
    "sg:postcode":"55429",
    "sg:province":"MN",
    "sg:tags":[
        "bar",
        "rest"
    ],
    "wof:name":"Jake's Sports Cafe",
    "wof:placetype":"venue"
},
  "geometry": {"coordinates":[-93.359408,45.049406],"type":"Point"}
}