{
  "type": "Feature",
  "properties": {
    "addr:full":"3926 Vera Cruz Ave N Minneapolis MN 55422",
    "addr:housenumber":"3926",
    "addr:postcode":"55422",
    "addr:street":"Vera Cruz Ave N",
    "iso:country":"US",
    "sg:address":"3926 Vera Cruz Ave N",
    "sg:city":"Minneapolis",
    "sg:phone":"+1 612 618 7635",
    "sg:postcode":"55422",
    "sg:province":"MN",
    "wof:name":"Color Glo International N",
    "wof:placetype":"venue"
},
  "geometry": {"coordinates":[-93.34948199999999,45.026437],"type":"Point"}
}