{
  "type": "Feature",
  "properties": {
    "addr:full":"457 Main St S Browerville MN 56438",
    "addr:housenumber":"457",
    "addr:postcode":"56438",
    "addr:street":"Main St S Browerville",
    "iso:country":"US",
    "sg:address":"457 Main St S",
    "sg:city":"Browerville",
    "sg:classifiers":[
        {
            "category":"Manufacturing",
            "subcategory":"Petroleum Products",
            "type":"Manufacturing & Wholesale Goods"
        },
        {
            "category":"Wholesale",
            "subcategory":"Petroleum",
            "type":"Manufacturing & Wholesale Goods"
        },
        {
            "category":"Food & Beverages",
            "subcategory":"Groceries & Convenience Stores",
            "type":"Retail Goods"
        }
    ],
    "sg:phone":"+1 320 594 6220",
    "sg:postcode":"56438",
    "sg:province":"MN",
    "sg:tags":[
        "manufacturer",
        "products-wholesale",
        "oils-petroleum"
    ],
    "sg:website":"http://www.tesoropetroleum.com",
    "wof:name":"Total Express",
    "wof:placetype":"venue"
},
  "geometry": {"coordinates":[-94.86724,46.083836],"type":"Point"}
}