{
  "type": "Feature",
  "properties": {
    "iso:country":"US",
    "sg:address":"12701 Polk St NE",
    "sg:city":"Minneapolis",
    "sg:classifiers":[
        {
            "category":"Building & Trades",
            "subcategory":"Construction",
            "type":"Services"
        }
    ],
    "sg:phone":"+1 763 755 4661",
    "sg:postcode":"55434",
    "sg:province":"MN",
    "sg:tags":[
        "house"
    ],
    "wof:name":"Toms Decks & Patios",
    "wof:placetype":"venue"
},
  "geometry": {"coordinates":[-93.24567399999999,45.200333],"type":"Point"}
}