{
  "type": "Feature",
  "properties": {
    "addr:full":"1500 Albion Ave Fairmont MN 56031",
    "addr:housenumber":"1500",
    "addr:postcode":"56031",
    "addr:street":"Albion Ave",
    "iso:country":"US",
    "sg:address":"1500 Albion Ave",
    "sg:city":"Fairmont",
    "sg:classifiers":[
        {
            "category":"Restaurant",
            "type":"Food & Drink"
        }
    ],
    "sg:phone":"+1 507 235 8210",
    "sg:postcode":"56031",
    "sg:province":"MN",
    "sg:tags":[
        "eating"
    ],
    "wof:name":"Goose",
    "wof:placetype":"venue"
},
  "geometry": {"coordinates":[-94.462474,43.634423],"type":"Point"}
}