{
  "type": "Feature",
  "properties": {
    "iso:country":"US",
    "sg:address":"57124 Co Rd 31",
    "sg:city":"Northome",
    "sg:classifiers":[
        {
            "category":"Farming",
            "subcategory":"Livestock Farm",
            "type":"Manufacturing & Wholesale Goods"
        }
    ],
    "sg:phone":"+1 218 659 4599",
    "sg:postcode":"56661",
    "sg:province":"MN",
    "sg:tags":[
        "beef",
        "feedlot",
        "cattle"
    ],
    "wof:name":"Ted Winkelman",
    "wof:placetype":"venue"
},
  "geometry": {"coordinates":[-94.055511,47.818102],"type":"Point"}
}