{
  "type": "Feature",
  "properties": {
    "addr:full":"117 W 9th St Duluth MN 55806",
    "addr:housenumber":"117",
    "addr:postcode":"55806",
    "addr:street":"W 9Th St",
    "iso:country":"US",
    "sg:address":"117 W 9th St",
    "sg:city":"Duluth",
    "sg:classifiers":[
        {
            "category":"Manufacturing",
            "subcategory":"Leather Goods",
            "type":"Manufacturing & Wholesale Goods"
        }
    ],
    "sg:phone":"+1 218 279 5349",
    "sg:postcode":"55806",
    "sg:province":"MN",
    "sg:tags":[
        "mfg"
    ],
    "wof:name":"Ravenwind Designs",
    "wof:placetype":"venue"
},
  "geometry": {"coordinates":[-92.11034100000001,46.791091],"type":"Point"}
}