{
  "type": "Feature",
  "properties": {
    "iso:country":"US",
    "sg:address":"7455 Currell Blvd",
    "sg:city":"St Paul",
    "sg:classifiers":[
        {
            "category":"Utilities",
            "subcategory":"Mobile Phone",
            "type":"Services"
        }
    ],
    "sg:phone":"+1 651 738 0371",
    "sg:postcode":"55125",
    "sg:province":"MN",
    "sg:tags":[
        "telephone",
        "cellular"
    ],
    "wof:name":"Advanced Wireless Comm",
    "wof:placetype":"venue"
},
  "geometry": {"coordinates":[-92.954241,44.925645],"type":"Point"}
}