{
  "type": "Feature",
  "properties": {
    "iso:country":"US",
    "sg:address":"987 Selby Ave",
    "sg:city":"Saint Paul",
    "sg:classifiers":[
        {
            "category":"Shopping",
            "subcategory":"Gifts & Souvenirs",
            "type":"Retail Goods"
        }
    ],
    "sg:phone":"+1 651 917 3964",
    "sg:postcode":"55104",
    "sg:province":"MN",
    "wof:name":"Pasar Seni Gifts & Furnishings",
    "wof:placetype":"venue"
},
  "geometry": {"coordinates":[-93.143912,44.946685],"type":"Point"}
}