{
  "type": "Feature",
  "properties": {
    "addr:full":"9450 290th Ave Pierz MN 56364",
    "addr:housenumber":"9450",
    "addr:postcode":"56364",
    "addr:street":"290Th Ave",
    "iso:country":"US",
    "sg:address":"9450 290th Ave",
    "sg:city":"Pierz",
    "sg:phone":"+1 320 468 6536",
    "sg:postcode":"56364",
    "sg:province":"MN",
    "sg:tags":[
        "farm",
        "corn",
        "cash",
        "crop",
        "field",
        "grain",
        "dairy"
    ],
    "wof:name":"Ronald & Janice Przybilla",
    "wof:placetype":"venue"
},
  "geometry": {"coordinates":[-94.051469,45.900185],"type":"Point"}
}