{
  "type": "Feature",
  "properties": {
    "addr:full":"2742 Northland Ln NW Walker MN 56484",
    "addr:housenumber":"2742",
    "addr:postcode":"56484",
    "addr:street":"Northland Ln Nw",
    "iso:country":"US",
    "sg:address":"2742 Northland Ln NW",
    "sg:city":"Walker",
    "sg:classifiers":[
        {
            "category":"Professional",
            "type":"Services"
        }
    ],
    "sg:phone":"+1 218 836 2574",
    "sg:postcode":"56484",
    "sg:province":"MN",
    "sg:tags":[
        "establishment"
    ],
    "wof:name":"Lazear & Lazear",
    "wof:placetype":"venue"
},
  "geometry": {"coordinates":[-94.422781,47.072209],"type":"Point"}
}