{
  "type": "Feature",
  "properties": {
    "addr:full":"6309 Grand Ave Duluth MN 55807",
    "addr:housenumber":"6309",
    "addr:postcode":"55807",
    "addr:street":"Grand Ave",
    "iso:country":"US",
    "sg:address":"6309 Grand Ave",
    "sg:city":"Duluth",
    "sg:classifiers":[
        {
            "category":"Shopping",
            "subcategory":"Hobbies, Toys, & Games",
            "type":"Retail Goods"
        }
    ],
    "sg:phone":"+1 218 624 2483",
    "sg:postcode":"55807",
    "sg:province":"MN",
    "sg:tags":[
        "model",
        "supply"
    ],
    "wof:name":"Lakes Superior Hobby",
    "wof:placetype":"venue"
},
  "geometry": {"coordinates":[-92.177812,46.733007],"type":"Point"}
}