{
  "type": "Feature",
  "properties": {
    "iso:country":"US",
    "sg:address":"149 49th Ave NE",
    "sg:city":"Minneapolis",
    "sg:classifiers":[
        {
            "category":"Professional",
            "subcategory":"Accounting & Tax Preparation",
            "type":"Services"
        }
    ],
    "sg:phone":"+1 763 572 8814",
    "sg:postcode":"55421",
    "sg:province":"MN",
    "wof:name":"Arne C Simengaard P A",
    "wof:placetype":"venue"
},
  "geometry": {"coordinates":[-93.265506,45.057294],"type":"Point"}
}