{
  "type": "Feature",
  "properties": {
    "iso:country":"US",
    "sg:address":"11200 Stillwater Blvd N",
    "sg:city":"Lake Elmo",
    "sg:classifiers":[
        {
            "category":"Professional",
            "subcategory":"Engineering",
            "type":"Services"
        }
    ],
    "sg:phone":"+1 651 203 0415",
    "sg:postcode":"55042",
    "sg:province":"MN",
    "sg:tags":[
        "engineer"
    ],
    "wof:name":"Telemedicine",
    "wof:placetype":"venue"
},
  "geometry": {"coordinates":[-92.879927,45.002326],"type":"Point"}
}