{
  "type": "Feature",
  "properties": {
    "addr:full":"4005 State Hwy 210 Fergus Falls MN 56537",
    "addr:housenumber":"4005",
    "addr:postcode":"56537",
    "addr:street":"State Hwy 210",
    "iso:country":"US",
    "sg:address":"4005 State Hwy 210",
    "sg:city":"Fergus Falls",
    "sg:classifiers":[
        {
            "category":"Farming",
            "subcategory":"Farm & Veterinary Services",
            "type":"Manufacturing & Wholesale Goods"
        }
    ],
    "sg:phone":"+1 218 736 7220",
    "sg:postcode":"56537",
    "sg:province":"MN",
    "sg:tags":[
        "aerial",
        "applicator"
    ],
    "wof:name":"West Central Aerial Sprayers",
    "wof:placetype":"venue"
},
  "geometry": {"coordinates":[-96.134529,46.289648],"type":"Point"}
}