{
  "type": "Feature",
  "properties": {
    "addr:full":"1617 Highway 12 E Willmar MN 56201",
    "addr:housenumber":"1617",
    "addr:postcode":"56201",
    "addr:street":"Highway 12 E",
    "iso:country":"US",
    "sg:address":"1617 Highway 12 E",
    "sg:city":"Willmar",
    "sg:classifiers":[
        {
            "category":"Insurance",
            "subcategory":"Insurance Agent",
            "type":"Services"
        },
        {
            "category":"Insurance",
            "subcategory":"Hazard Insurance",
            "type":"Services"
        },
        {
            "category":"Insurance",
            "subcategory":"Title Insurance",
            "type":"Services"
        }
    ],
    "sg:phone":"+1 320 235 0542",
    "sg:postcode":"56201",
    "sg:province":"MN",
    "sg:tags":[
        "auto",
        "homeowner"
    ],
    "sg:website":"http://apps.amfam.com/agentlocator/GHERN?sourceid=yp3",
    "wof:name":"American Family Insurance- Gary Hern",
    "wof:placetype":"venue"
},
  "geometry": {"coordinates":[-95.022165,45.124017],"type":"Point"}
}