{
  "type": "Feature",
  "properties": {
    "addr:full":"1123 W Lake St Minneapolis MN 55408",
    "addr:housenumber":"1123",
    "addr:postcode":"55408",
    "addr:street":"W Lake St",
    "iso:country":"US",
    "sg:address":"1123 W Lake St",
    "sg:city":"Minneapolis",
    "sg:classifiers":[
        {
            "category":"Restaurant",
            "type":"Food & Drink"
        }
    ],
    "sg:phone":"+1 612 824 6342",
    "sg:postcode":"55408",
    "sg:province":"MN",
    "sg:tags":[
        "vegetarian",
        "indian"
    ],
    "sg:website":"www.delightsofindia.com",
    "wof:name":"Delights Of India",
    "wof:placetype":"venue"
},
  "geometry": {"coordinates":[-93.29410300000001,44.94834],"type":"Point"}
}