{
  "type": "Feature",
  "properties": {
    "addr:full":"405 Atlantic Ave Morris MN 56267",
    "addr:housenumber":"405",
    "addr:postcode":"56267",
    "addr:street":"Atlantic Ave",
    "iso:country":"US",
    "sg:address":"405 Atlantic Ave",
    "sg:city":"Morris",
    "sg:classifiers":[
        {
            "category":"Autos & Motor Vehicles",
            "subcategory":"Automobile Sales",
            "type":"Retail Goods"
        }
    ],
    "sg:phone":"+1 320 589 2787",
    "sg:postcode":"56267",
    "sg:province":"MN",
    "sg:tags":[
        "car",
        "dealer"
    ],
    "wof:name":"Auto Mall 2000",
    "wof:placetype":"venue"
},
  "geometry": {"coordinates":[-95.913342,45.585154],"type":"Point"}
}