{
  "type": "Feature",
  "properties": {
    "addr:full":"303 S Union St Isanti MN 55051",
    "addr:housenumber":"303",
    "addr:postcode":"55051",
    "addr:street":"S Union St",
    "iso:country":"US",
    "sg:address":"303 S Union St",
    "sg:city":"Isanti",
    "sg:classifiers":[
        {
            "category":"Shopping",
            "type":"Retail Goods"
        }
    ],
    "sg:phone":"+1 763 444 4998",
    "sg:postcode":"55051",
    "sg:province":"MN",
    "sg:tags":[
        "pet",
        "food",
        "supply"
    ],
    "wof:name":"Pitter Patter Paws Inc",
    "wof:placetype":"venue"
},
  "geometry": {"coordinates":[-93.29707500000001,45.874224],"type":"Point"}
}