{
  "type": "Feature",
  "properties": {
    "addr:full":"19751 Co Rd 21 Glenwood MN 56334",
    "addr:housenumber":"19751;21",
    "addr:postcode":"56334",
    "addr:street":"Co Rd",
    "iso:country":"US",
    "sg:address":"19751 Co Rd 21",
    "sg:city":"Glenwood",
    "sg:phone":"+1 320 634 4161",
    "sg:postcode":"56334",
    "sg:province":"MN",
    "sg:tags":[
        "farm",
        "wheat",
        "corn",
        "grain",
        "cash"
    ],
    "wof:name":"Swenson Farms",
    "wof:placetype":"venue"
},
  "geometry": {"coordinates":[-95.366416,45.617992],"type":"Point"}
}