{
  "type": "Feature",
  "properties": {
    "iso:country":"US",
    "sg:address":"1185 Town Centre Dr",
    "sg:city":"Eagan",
    "sg:classifiers":[
        {
            "category":"Real Estate",
            "subcategory":"Real Estate Services",
            "type":"Services"
        }
    ],
    "sg:phone":"+1 651 905 1300",
    "sg:postcode":"55123",
    "sg:province":"MN",
    "sg:tags":[
        "company",
        "title"
    ],
    "wof:name":"Metro Title",
    "wof:placetype":"venue"
},
  "geometry": {"coordinates":[-93.15230099999999,44.83117],"type":"Point"}
}