{
  "type": "Feature",
  "properties": {
    "addr:full":"5633 Emerson Ave S Minneapolis MN 55419",
    "addr:housenumber":"5633",
    "addr:postcode":"55419",
    "addr:street":"Emerson Ave S",
    "iso:country":"US",
    "sg:address":"5633 Emerson Ave S",
    "sg:city":"Minneapolis",
    "sg:classifiers":[
        {
            "category":"Real Estate",
            "subcategory":"Real Estate Operator",
            "type":"Services"
        }
    ],
    "sg:phone":"+1 612 221 1322",
    "sg:postcode":"55419",
    "sg:province":"MN",
    "sg:tags":[
        "property",
        "management"
    ],
    "wof:name":"Hartley Properties Inc",
    "wof:placetype":"venue"
},
  "geometry": {"coordinates":[-93.294579,44.900267],"type":"Point"}
}