{
  "type": "Feature",
  "properties": {
    "iso:country":"US",
    "sg:address":"3800 W 80th St",
    "sg:city":"Bloomington",
    "sg:classifiers":[
        {
            "category":"Banks & Credit Unions",
            "subcategory":"Investment Brokerage",
            "type":"Services"
        }
    ],
    "sg:phone":"+1 952 832 9445",
    "sg:postcode":"55431",
    "sg:province":"MN",
    "sg:tags":[
        "advisory"
    ],
    "wof:name":"Rbs Investments",
    "wof:placetype":"venue"
},
  "geometry": {"coordinates":[-93.328053,44.855769],"type":"Point"}
}