{
  "type": "Feature",
  "properties": {
    "addr:full":"5656 Wooddale Ave Minneapolis MN 55424",
    "addr:housenumber":"5656",
    "addr:postcode":"55424",
    "addr:street":"Wooddale Ave",
    "iso:country":"US",
    "sg:address":"5656 Wooddale Ave",
    "sg:city":"Minneapolis",
    "sg:classifiers":[
        {
            "category":"Personal",
            "type":"Services"
        }
    ],
    "sg:phone":"+1 952 926 1254",
    "sg:postcode":"55424",
    "sg:province":"MN",
    "sg:tags":[
        "electrolysis"
    ],
    "wof:name":"Body Care Professionals",
    "wof:placetype":"venue"
},
  "geometry": {"coordinates":[-93.339235,44.900225],"type":"Point"}
}