{
  "type": "Feature",
  "properties": {
    "addr:full":"3740 Burgundy Dr St Paul MN 55122",
    "addr:housenumber":"3740",
    "addr:postcode":"55122",
    "addr:street":"Burgundy Dr",
    "iso:country":"US",
    "sg:address":"3740 Burgundy Dr",
    "sg:city":"St Paul",
    "sg:classifiers":[
        {
            "category":"Travel",
            "subcategory":"Travel Agent",
            "type":"Entertainment"
        }
    ],
    "sg:phone":"+1 651 687 9846",
    "sg:postcode":"55122",
    "sg:province":"MN",
    "sg:tags":[
        "consultant",
        "agency"
    ],
    "wof:name":"Echo Travel",
    "wof:placetype":"venue"
},
  "geometry": {"coordinates":[-93.204202,44.821879],"type":"Point"}
}