{
  "type": "Feature",
  "properties": {
    "addr:full":"101 Main St E Isanti MN 55040",
    "addr:housenumber":"101",
    "addr:postcode":"55040",
    "addr:street":"Main St E Isanti",
    "iso:country":"US",
    "sg:address":"101 Main St E",
    "sg:city":"Isanti",
    "sg:classifiers":[
        {
            "category":"Retail",
            "subcategory":"Auto Repair",
            "type":"Services"
        }
    ],
    "sg:phone":"+1 763 444 8797",
    "sg:postcode":"55040",
    "sg:province":"MN",
    "sg:tags":[
        "body",
        "automobile",
        "painting",
        "repairing"
    ],
    "wof:name":"Mitch's Auto Body",
    "wof:placetype":"venue"
},
  "geometry": {"coordinates":[-93.246262,45.490288],"type":"Point"}
}