{
  "type": "Feature",
  "properties": {
    "iso:country":"US",
    "sg:address":"44 Riverside Ter",
    "sg:city":"Watertown",
    "sg:classifiers":[
        {
            "category":"Professional",
            "subcategory":"Art Services",
            "type":"Services"
        }
    ],
    "sg:phone":"+1 952 955 2666",
    "sg:postcode":"55388",
    "sg:province":"MN",
    "sg:tags":[
        "interior",
        "designer",
        "decorator"
    ],
    "wof:name":"R Berhows Interior Svc",
    "wof:placetype":"venue"
},
  "geometry": {"coordinates":[-93.841193,44.966159],"type":"Point"}
}