{
  "type": "Feature",
  "properties": {
    "addr:full":"2958 Upton Ave N Minneapolis MN 55411",
    "addr:housenumber":"2958",
    "addr:postcode":"55411",
    "addr:street":"Upton Ave N",
    "iso:country":"US",
    "sg:address":"2958 Upton Ave N",
    "sg:city":"Minneapolis",
    "sg:classifiers":[
        {
            "category":"Building & Trades",
            "subcategory":"Construction",
            "type":"Services"
        }
    ],
    "sg:phone":"+1 612 701 8183",
    "sg:postcode":"55411",
    "sg:province":"MN",
    "sg:tags":[
        "resurfacing",
        "laying",
        "refinishing",
        "floor"
    ],
    "wof:name":"Harmer Hardwoods Inc",
    "wof:placetype":"venue"
},
  "geometry": {"coordinates":[-93.314517,45.010381],"type":"Point"}
}