{
  "type": "Feature",
  "properties": {
    "iso:country":"US",
    "sg:address":"15130 Garnet St NW",
    "sg:city":"Anoka",
    "sg:classifiers":[
        {
            "category":"Building & Trades",
            "subcategory":"Landscaping Services",
            "type":"Services"
        }
    ],
    "sg:phone":"+1 763 213 8200",
    "sg:postcode":"55303",
    "sg:province":"MN",
    "sg:tags":[
        "landscape"
    ],
    "wof:name":"Bahns Ldscp Design & Cnstr",
    "wof:placetype":"venue"
},
  "geometry": {"coordinates":[-93.440337,45.247228],"type":"Point"}
}