{
  "type": "Feature",
  "properties": {
    "iso:country":"US",
    "sg:address":"7032 Little Rock Rd NE",
    "sg:city":"Foley",
    "sg:classifiers":[
        {
            "category":"Farming",
            "subcategory":"Dairy Farm",
            "type":"Manufacturing & Wholesale Goods"
        }
    ],
    "sg:phone":"+1 320 387 2651",
    "sg:postcode":"56329",
    "sg:province":"MN",
    "wof:name":"Molitor Farm",
    "wof:placetype":"venue"
},
  "geometry": {"coordinates":[-94.015581,45.713065],"type":"Point"}
}