{
  "type": "Feature",
  "properties": {
    "iso:country":"US",
    "sg:address":"2722 Highway 25",
    "sg:city":"Watertown",
    "sg:classifiers":[
        {
            "category":"Retail",
            "subcategory":"Auto Repair",
            "type":"Services"
        }
    ],
    "sg:phone":"+1 952 955 2683",
    "sg:postcode":"55388",
    "sg:province":"MN",
    "wof:name":"A J's Exp Transmissions",
    "wof:placetype":"venue"
},
  "geometry": {"coordinates":[-93.858963,44.955018],"type":"Point"}
}