{
  "type": "Feature",
  "properties": {
    "iso:country":"US",
    "sg:address":"4825 W 86th St",
    "sg:city":"Minneapolis",
    "sg:classifiers":[
        {
            "category":"Professional",
            "subcategory":"Computer Services",
            "type":"Services"
        }
    ],
    "sg:phone":"+1 952 835 7069",
    "sg:postcode":"55437",
    "sg:province":"MN",
    "sg:tags":[
        "publisher",
        "developer",
        "software"
    ],
    "sg:website":"http://www.isgonline.com",
    "wof:name":"Interactiver Strategies Group",
    "wof:placetype":"venue"
},
  "geometry": {"coordinates":[-93.340394,44.84763],"type":"Point"}
}