{
  "type": "Feature",
  "properties": {
    "iso:country":"US",
    "sg:address":"8085 Century Blvd none",
    "sg:city":"Chanhassen",
    "sg:classifiers":[
        {
            "category":"Shopping",
            "subcategory":"Computers & Home Electronics",
            "type":"Retail Goods"
        }
    ],
    "sg:phone":"+1 800 229 2901",
    "sg:postcode":"55317",
    "sg:province":"MN",
    "sg:website":"www.heartlandamerica.com",
    "wof:name":"Heartland America",
    "wof:placetype":"venue"
},
  "geometry": {"coordinates":[-93.593422,44.857671],"type":"Point"}
}