{
  "type": "Feature",
  "properties": {
    "addr:full":"208 4th St SW Kasson MN 55944",
    "addr:housenumber":"208",
    "addr:postcode":"55944",
    "addr:street":"4Th St Sw",
    "iso:country":"US",
    "sg:address":"208 4th St SW",
    "sg:city":"Kasson",
    "sg:classifiers":[
        {
            "category":"Manufacturing",
            "subcategory":"Retail Goods",
            "type":"Manufacturing & Wholesale Goods"
        }
    ],
    "sg:phone":"+1 507 634 7920",
    "sg:postcode":"55944",
    "sg:province":"MN",
    "sg:tags":[
        "product",
        "mfg"
    ],
    "wof:name":"Ashdown Publishing",
    "wof:placetype":"venue"
},
  "geometry": {"coordinates":[-92.750845,44.025793],"type":"Point"}
}