{
  "type": "Feature",
  "properties": {
    "addr:full":"1870 Eagle Ridge Dr Saint Paul MN 55118",
    "addr:housenumber":"1870",
    "addr:postcode":"55118",
    "addr:street":"Eagle Ridge Dr",
    "iso:country":"US",
    "sg:address":"1870 Eagle Ridge Dr",
    "sg:city":"Saint Paul",
    "sg:classifiers":[
        {
            "category":"Professional",
            "subcategory":"Computer Services",
            "type":"Services"
        }
    ],
    "sg:phone":"+1 952 454 1993",
    "sg:postcode":"55118",
    "sg:province":"MN",
    "sg:tags":[
        "prepackaged",
        "software"
    ],
    "wof:name":"Data Consulting Inc",
    "wof:placetype":"venue"
},
  "geometry": {"coordinates":[-93.133887,44.889642],"type":"Point"}
}