{
  "type": "Feature",
  "properties": {
    "addr:full":"204 Nevada St Northfield MN 55057",
    "addr:housenumber":"204",
    "addr:postcode":"55057",
    "addr:street":"Nevada St",
    "iso:country":"US",
    "sg:address":"204 Nevada St",
    "sg:city":"Northfield",
    "sg:classifiers":[
        {
            "category":"Organizations",
            "subcategory":"Religious Organization",
            "type":"Services"
        }
    ],
    "sg:phone":"+1 507 645 4665",
    "sg:postcode":"55057",
    "sg:province":"MN",
    "wof:name":"Nancy L Brown Rev",
    "wof:placetype":"venue"
},
  "geometry": {"coordinates":[-93.15240900000001,44.458468],"type":"Point"}
}