{
  "type": "Feature",
  "properties": {
    "addr:full":"33747 770th Ave Olivia MN 56277",
    "addr:housenumber":"33747",
    "addr:postcode":"56277",
    "addr:street":"770Th Ave",
    "iso:country":"US",
    "sg:address":"33747 770th Ave",
    "sg:city":"Olivia",
    "sg:classifiers":[
        {
            "category":"Farming",
            "subcategory":"Farm",
            "type":"Manufacturing & Wholesale Goods"
        }
    ],
    "sg:phone":"+1 320 523 2408",
    "sg:postcode":"56277",
    "sg:province":"MN",
    "sg:tags":[
        "crop",
        "general"
    ],
    "wof:name":"Keith Herdina",
    "wof:placetype":"venue"
},
  "geometry": {"coordinates":[-95.001897,44.70149],"type":"Point"}
}