{
  "type": "Feature",
  "properties": {
    "addr:full":"1639 N Broadway Rochester MN 55906",
    "addr:housenumber":"1639",
    "addr:postcode":"55906",
    "addr:street":"N Broadway",
    "iso:country":"US",
    "sg:address":"1639 N Broadway",
    "sg:city":"Rochester",
    "sg:classifiers":[
        {
            "category":"Food & Beverages",
            "subcategory":"Groceries & Convenience Stores",
            "type":"Retail Goods"
        }
    ],
    "sg:phone":"+1 507 285 4454",
    "sg:postcode":"55906",
    "sg:province":"MN",
    "sg:tags":[
        "grocer"
    ],
    "wof:name":"World Market",
    "wof:placetype":"venue"
},
  "geometry": {"coordinates":[-92.461299,44.040697],"type":"Point"}
}