{
  "type": "Feature",
  "properties": {
    "addr:full":"221 2nd St SE Dodge Center MN 55927",
    "addr:housenumber":"221",
    "addr:postcode":"55927",
    "addr:street":"2Nd St Se",
    "iso:country":"US",
    "sg:address":"221 2nd St SE",
    "sg:city":"Dodge Center",
    "sg:classifiers":[
        {
            "category":"Building & Trades",
            "subcategory":"Construction",
            "type":"Services"
        }
    ],
    "sg:phone":"+1 507 374 2418",
    "sg:postcode":"55927",
    "sg:province":"MN",
    "sg:tags":[
        "house"
    ],
    "wof:name":"Darrell D Darr",
    "wof:placetype":"venue"
},
  "geometry": {"coordinates":[-92.85157100000001,44.026202],"type":"Point"}
}