{
  "type": "Feature",
  "properties": {
    "addr:full":"322 1st Ave Minneapolis MN 55401",
    "addr:housenumber":"322",
    "addr:postcode":"55401",
    "addr:street":"1St Ave",
    "iso:country":"US",
    "sg:address":"322 1st Ave",
    "sg:city":"Minneapolis",
    "sg:classifiers":[
        {
            "category":"Bars & Pubs",
            "type":"Food & Drink"
        },
        {
            "category":"Restaurant",
            "type":"Food & Drink"
        },
        {
            "category":"Bars & Pubs",
            "subcategory":"Nightclub",
            "type":"Food & Drink"
        },
        {
            "category":"Recreation",
            "subcategory":"Dance Hall",
            "type":"Entertainment"
        }
    ],
    "sg:phone":"+1 612 746 4004",
    "sg:postcode":"55401",
    "sg:province":"MN",
    "sg:tags":[
        "traditional",
        "american",
        "club",
        "night"
    ],
    "sg:website":"www.elixirmpls.com/",
    "wof:name":"Elixir Lounge",
    "wof:placetype":"venue"
},
  "geometry": {"coordinates":[-93.272434,44.98178],"type":"Point"}
}