{
  "type": "Feature",
  "properties": {
    "addr:full":"10208 Orleans Ln N Osseo MN 55369",
    "addr:housenumber":"10208",
    "addr:postcode":"55369",
    "addr:street":"Orleans Ln N",
    "iso:country":"US",
    "sg:address":"10208 Orleans Ln N",
    "sg:city":"Osseo",
    "sg:classifiers":[
        {
            "category":"Building & Trades",
            "subcategory":"Cleaning & Sanitation",
            "type":"Services"
        }
    ],
    "sg:phone":"+1 763 315 4757",
    "sg:postcode":"55369",
    "sg:province":"MN",
    "sg:tags":[
        "maintenance"
    ],
    "wof:name":"Frank F Otten",
    "wof:placetype":"venue"
},
  "geometry": {"coordinates":[-93.408755,45.139239],"type":"Point"}
}