{
  "type": "Feature",
  "properties": {
    "addr:full":"4175 Trillium Ln E Mound MN 55364",
    "addr:housenumber":"4175",
    "addr:postcode":"55364",
    "addr:street":"Trillium Ln E Mound",
    "iso:country":"US",
    "sg:address":"4175 Trillium Ln E",
    "sg:city":"Mound",
    "sg:classifiers":[
        {
            "category":"Real Estate",
            "subcategory":"Real Estate Operator",
            "type":"Services"
        }
    ],
    "sg:phone":"+1 952 943 2898",
    "sg:postcode":"55364",
    "sg:province":"MN",
    "sg:tags":[
        "holding"
    ],
    "wof:name":"Walburn Ltd Inc",
    "wof:placetype":"venue"
},
  "geometry": {"coordinates":[-93.679192,44.897546],"type":"Point"}
}