{
  "type": "Feature",
  "properties": {
    "addr:full":"16390 Albany Ave SE Prior Lake MN 55372",
    "addr:housenumber":"16390",
    "addr:postcode":"55372",
    "addr:street":"Albany Ave Se",
    "iso:country":"US",
    "sg:address":"16390 Albany Ave SE",
    "sg:city":"Prior Lake",
    "sg:classifiers":[
        {
            "category":"Retail",
            "subcategory":"Repair Shop",
            "type":"Services"
        }
    ],
    "sg:phone":"+1 952 447 2655",
    "sg:postcode":"55372",
    "sg:province":"MN",
    "wof:name":"Cates Clock Repair",
    "wof:placetype":"venue"
},
  "geometry": {"coordinates":[-93.433633,44.711652],"type":"Point"}
}