{
  "type": "Feature",
  "properties": {
    "iso:country":"US",
    "sg:address":"3947 Excelsior Blvd",
    "sg:city":"Minneapolis",
    "sg:classifiers":[
        {
            "category":"Shopping",
            "subcategory":"Used Merchandise",
            "type":"Retail Goods"
        }
    ],
    "sg:phone":"+1 952 924 0186",
    "sg:postcode":"55416",
    "sg:province":"MN",
    "sg:tags":[
        "dealer",
        "carpet",
        "floor",
        "rug",
        "covering"
    ],
    "wof:name":"R Franklin Hort Orientl Rug Co",
    "wof:placetype":"venue"
},
  "geometry": {"coordinates":[-93.330139,44.93976],"type":"Point"}
}