{
  "type": "Feature",
  "properties": {
    "addr:full":"4420 Fremont Ave S Minneapolis MN 55419",
    "addr:housenumber":"4420",
    "addr:postcode":"55419",
    "addr:street":"Fremont Ave S",
    "iso:country":"US",
    "sg:address":"4420 Fremont Ave S",
    "sg:city":"Minneapolis",
    "sg:classifiers":[
        {
            "category":"Shopping",
            "subcategory":"Music",
            "type":"Retail Goods"
        }
    ],
    "sg:phone":"+1 612 825 9496",
    "sg:postcode":"55419",
    "sg:province":"MN",
    "wof:name":"One By One Records",
    "wof:placetype":"venue"
},
  "geometry": {"coordinates":[-93.295941,44.919924],"type":"Point"}
}