{
  "type": "Feature",
  "properties": {
    "iso:country":"US",
    "sg:address":"1120 E 80th St",
    "sg:city":"Minneapolis",
    "sg:classifiers":[
        {
            "category":"Organizations",
            "subcategory":"Religious Organization",
            "type":"Services"
        }
    ],
    "sg:phone":"+1 952 854 2580",
    "sg:postcode":"55420",
    "sg:province":"MN",
    "wof:name":"Surrendering Heart Biblical Co",
    "wof:placetype":"venue"
},
  "geometry": {"coordinates":[-93.261838,44.857706],"type":"Point"}
}