{
  "type": "Feature",
  "properties": {
    "addr:full":"550 25th Ave N Saint Cloud MN 56303",
    "addr:housenumber":"550",
    "addr:postcode":"56303",
    "addr:street":"25Th Ave N",
    "iso:country":"US",
    "sg:address":"550 25th Ave N",
    "sg:city":"Saint Cloud",
    "sg:classifiers":[
        {
            "category":"Professional",
            "subcategory":"Business Services",
            "type":"Services"
        }
    ],
    "sg:phone":"+1 320 529 9587",
    "sg:postcode":"56303",
    "sg:province":"MN",
    "wof:name":"Keepers Metro LLC",
    "wof:placetype":"venue"
},
  "geometry": {"coordinates":[-94.187794,45.563271],"type":"Point"}
}