{
  "type": "Feature",
  "properties": {
    "iso:country":"US",
    "sg:address":"331 W Broadway Ave",
    "sg:city":"Bloomington",
    "sg:classifiers":[
        {
            "category":"Government",
            "subcategory":"Post Office",
            "type":"Public Place"
        }
    ],
    "sg:phone":"+1 952 854 5552",
    "sg:postcode":"55411",
    "sg:province":"MN",
    "wof:name":"Us Govt Post Ofc",
    "wof:placetype":"venue"
},
  "geometry": {"coordinates":[-93.284233,44.999062],"type":"Point"}
}