{
  "type": "Feature",
  "properties": {
    "addr:full":"7010 W 280th St New Prague MN 56071",
    "addr:housenumber":"7010",
    "addr:postcode":"56071",
    "addr:street":"W 280Th St",
    "iso:country":"US",
    "sg:address":"7010 W 280th St",
    "sg:city":"New Prague",
    "sg:classifiers":[
        {
            "category":"Bars & Pubs",
            "type":"Food & Drink"
        }
    ],
    "sg:phone":"+1 952 758 4239",
    "sg:postcode":"56071",
    "sg:province":"MN",
    "sg:tags":[
        "drinking"
    ],
    "wof:name":"Hucks Union Hill Bar",
    "wof:placetype":"venue"
},
  "geometry": {"coordinates":[-93.66627800000001,44.544024],"type":"Point"}
}