{
  "type": "Feature",
  "properties": {
    "iso:country":"US",
    "sg:address":"7525 147th St W",
    "sg:city":"Saint Paul",
    "sg:classifiers":[
        {
            "category":"Autos & Motor Vehicles",
            "subcategory":"Fuel & Gas Station",
            "type":"Retail Goods"
        },
        {
            "category":"Autos & Motor Vehicles",
            "subcategory":"Auto Supplies",
            "type":"Retail Goods"
        },
        {
            "category":"Personal",
            "type":"Services"
        },
        {
            "category":"Retail",
            "subcategory":"Auto Repair",
            "type":"Services"
        }
    ],
    "sg:phone":"+1 952 432 5200",
    "sg:postcode":"55124",
    "sg:province":"MN",
    "sg:tags":[
        "towing",
        "tire"
    ],
    "wof:name":"South Cedar Service",
    "wof:placetype":"venue"
},
  "geometry": {"coordinates":[-93.21910099999999,44.7351],"type":"Point"}
}