{
  "type": "Feature",
  "properties": {
    "addr:full":"465 6th St NW Plainview MN 55964",
    "addr:housenumber":"465",
    "addr:postcode":"55964",
    "addr:street":"6Th St Nw",
    "iso:country":"US",
    "sg:address":"465 6th St NW",
    "sg:city":"Plainview",
    "sg:classifiers":[
        {
            "category":"Building & Trades",
            "subcategory":"Construction",
            "type":"Services"
        }
    ],
    "sg:phone":"+1 507 534 2618",
    "sg:postcode":"55964",
    "sg:province":"MN",
    "sg:tags":[
        "house"
    ],
    "wof:name":"Rodney L Bartsh",
    "wof:placetype":"venue"
},
  "geometry": {"coordinates":[-92.17469,44.170135],"type":"Point"}
}