{
  "type": "Feature",
  "properties": {
    "addr:full":"23850 N Beard Ave Lakeville MN 55044",
    "addr:housenumber":"23850",
    "addr:postcode":"55044",
    "addr:street":"N Beard Ave",
    "iso:country":"US",
    "sg:address":"23850 N Beard Ave",
    "sg:city":"Lakeville",
    "sg:classifiers":[
        {
            "category":"Freight",
            "type":"Transportation"
        }
    ],
    "sg:phone":"+1 952 469 1885",
    "sg:postcode":"55044",
    "sg:province":"MN",
    "sg:tags":[
        "warehouse",
        "public"
    ],
    "wof:name":"Ewing County Road 42",
    "wof:placetype":"venue"
},
  "geometry": {"coordinates":[-93.32411500000001,44.602228],"type":"Point"}
}