{
  "type": "Feature",
  "properties": {
    "addr:full":"1240 Bryant Ave South Saint Paul MN 55075",
    "addr:housenumber":"1240",
    "addr:postcode":"55075",
    "addr:street":"Bryant Ave South",
    "iso:country":"US",
    "sg:address":"1240 Bryant Ave",
    "sg:city":"South Saint Paul",
    "sg:classifiers":[
        {
            "category":"Social Services",
            "subcategory":"Child Care",
            "type":"Services"
        }
    ],
    "sg:phone":"+1 651 306 1278",
    "sg:postcode":"55075",
    "sg:province":"MN",
    "sg:tags":[
        "day"
    ],
    "wof:name":"Mary T Thompson",
    "wof:placetype":"venue"
},
  "geometry": {"coordinates":[-93.051411,44.904339],"type":"Point"}
}