{
  "type": "Feature",
  "properties": {
    "addr:full":"110 Terrace Blvd Waverly MN 55390",
    "addr:housenumber":"110",
    "addr:postcode":"55390",
    "addr:street":"Terrace Blvd",
    "iso:country":"US",
    "sg:address":"110 Terrace Blvd",
    "sg:city":"Waverly",
    "sg:classifiers":[
        {
            "category":"Real Estate",
            "subcategory":"Real Estate Operator",
            "type":"Services"
        }
    ],
    "sg:phone":"+1 763 658 4610",
    "sg:postcode":"55390",
    "sg:province":"MN",
    "sg:tags":[
        "building",
        "nonresidential"
    ],
    "wof:name":"Cck Properties LLC",
    "wof:placetype":"venue"
},
  "geometry": {"coordinates":[-93.960556,45.078926],"type":"Point"}
}