{
  "type": "Feature",
  "properties": {
    "iso:country":"US",
    "sg:address":"7153 Northland Dr N",
    "sg:city":"Minneapolis",
    "sg:classifiers":[
        {
            "category":"Banks & Credit Unions",
            "subcategory":"Financial Services",
            "type":"Services"
        }
    ],
    "sg:phone":"+1 763 504 3500",
    "sg:postcode":"55428",
    "sg:province":"MN",
    "sg:tags":[
        "company",
        "holding"
    ],
    "wof:name":"Stein Holdings Inc",
    "wof:placetype":"venue"
},
  "geometry": {"coordinates":[-93.393348,45.082243],"type":"Point"}
}