{
  "type": "Feature",
  "properties": {
    "iso:country":"US",
    "sg:address":"317 W. 48th St",
    "sg:city":"Minneapolis",
    "sg:classifiers":[
        {
            "category":"Shopping",
            "subcategory":"Clothing, Apparel, & Fashions",
            "type":"Retail Goods"
        },
        {
            "category":"Home & Garden",
            "subcategory":"Home Furnishings",
            "type":"Retail Goods"
        }
    ],
    "sg:phone":"+1 612 822 6161",
    "sg:postcode":"55419",
    "sg:province":"MN",
    "sg:tags":[
        "decor"
    ],
    "sg:website":"www.ethiquenouveau.com",
    "wof:name":"?thique Nouveau",
    "wof:placetype":"venue"
},
  "geometry": {"coordinates":[-93.283351,44.915951],"type":"Point"}
}