{
  "type": "Feature",
  "properties": {
    "iso:country":"US",
    "sg:address":"8601 239th Ln NE",
    "sg:city":"Stacy",
    "sg:classifiers":[
        {
            "category":"Shopping",
            "type":"Retail Goods"
        }
    ],
    "sg:phone":"+1 651 248 9412",
    "sg:postcode":"55079",
    "sg:province":"MN",
    "sg:tags":[
        "merchandise"
    ],
    "wof:name":"Walls Of Art",
    "wof:placetype":"venue"
},
  "geometry": {"coordinates":[-93.050011,45.402734],"type":"Point"}
}