{
  "type": "Feature",
  "properties": {
    "addr:full":"8990 Springbrook Dr NW Minneapolis MN 55433",
    "addr:housenumber":"8990",
    "addr:postcode":"55433",
    "addr:street":"Springbrook Dr Nw",
    "iso:country":"US",
    "sg:address":"8990 Springbrook Dr NW",
    "sg:city":"Minneapolis",
    "sg:classifiers":[
        {
            "category":"Shopping",
            "subcategory":"Computers & Home Electronics",
            "type":"Retail Goods"
        }
    ],
    "sg:phone":"+1 651 784 4148",
    "sg:postcode":"55433",
    "sg:province":"MN",
    "wof:name":"Radio Shack",
    "wof:placetype":"venue"
},
  "geometry": {"coordinates":[-93.272881,45.133506],"type":"Point"}
}