{
  "type": "Feature",
  "properties": {
    "iso:country":"US",
    "sg:address":"421 Central Ave N",
    "sg:city":"Faribault",
    "sg:classifiers":[
        {
            "category":"Home & Garden",
            "subcategory":"Building Materials",
            "type":"Retail Goods"
        },
        {
            "category":"Manufacturing",
            "subcategory":"Building Materials",
            "type":"Manufacturing & Wholesale Goods"
        }
    ],
    "sg:phone":"+1 507 334 0385",
    "sg:postcode":"55021",
    "sg:province":"MN",
    "sg:tags":[
        "frames",
        "window",
        "doors",
        "accessory"
    ],
    "wof:name":"Exteriors Plus",
    "wof:placetype":"venue"
},
  "geometry": {"coordinates":[-93.26838499999999,44.29499],"type":"Point"}
}