{
  "type": "Feature",
  "properties": {
    "addr:full":"4340 Maine Ave SE Rochester MN 55904",
    "addr:housenumber":"4340",
    "addr:postcode":"55904",
    "addr:street":"Maine Ave Se",
    "iso:country":"US",
    "sg:address":"4340 Maine Ave SE",
    "sg:city":"Rochester",
    "sg:classifiers":[
        {
            "category":"Retail",
            "subcategory":"Event Space",
            "type":"Services"
        },
        {
            "category":"Cinema",
            "subcategory":"Movie Theater",
            "type":"Entertainment"
        }
    ],
    "sg:phone":"+1 507 216 5064",
    "sg:postcode":"55904",
    "sg:province":"MN",
    "sg:tags":[
        "ticket",
        "sale"
    ],
    "sg:website":"http://www.wehrenberg.com",
    "wof:name":"Wehrenberg Rochester Galaxy 14 Theatre",
    "wof:placetype":"venue"
},
  "geometry": {"coordinates":[-92.461412,43.958708],"type":"Point"}
}