{
  "type": "Feature",
  "properties": {
    "addr:full":"21940 Minnetonka Blvd Excelsior MN 55331",
    "addr:housenumber":"21940",
    "addr:postcode":"55331",
    "addr:street":"Minnetonka Blvd",
    "iso:country":"US",
    "sg:address":"21940 Minnetonka Blvd",
    "sg:city":"Excelsior",
    "sg:classifiers":[
        {
            "category":"Professional",
            "subcategory":"Advertising",
            "type":"Services"
        }
    ],
    "sg:phone":"+1 952 470 8830",
    "sg:postcode":"55331",
    "sg:province":"MN",
    "sg:tags":[
        "counselor",
        "agency"
    ],
    "wof:name":"Zimmerman Group Inc",
    "wof:placetype":"venue"
},
  "geometry": {"coordinates":[-93.558474,44.907362],"type":"Point"}
}