{
  "type": "Feature",
  "properties": {
    "addr:full":"3857 Pillsbury Ave S Minneapolis MN 55409",
    "addr:housenumber":"3857",
    "addr:postcode":"55409",
    "addr:street":"Pillsbury Ave S",
    "iso:country":"US",
    "sg:address":"3857 Pillsbury Ave S",
    "sg:city":"Minneapolis",
    "sg:classifiers":[
        {
            "category":"Manufacturing",
            "subcategory":"Retail Goods",
            "type":"Manufacturing & Wholesale Goods"
        }
    ],
    "sg:phone":"+1 612 823 6160",
    "sg:postcode":"55409",
    "sg:province":"MN",
    "sg:tags":[
        "pen"
    ],
    "wof:name":"Chaperones",
    "wof:placetype":"venue"
},
  "geometry": {"coordinates":[-93.281344,44.933335],"type":"Point"}
}