{
  "type": "Feature",
  "properties": {
    "iso:country":"US",
    "sg:address":"604 Thomas Ave S",
    "sg:city":"Minneapolis",
    "sg:classifiers":[
        {
            "category":"Wholesale",
            "subcategory":"Durable Goods & Equipment",
            "type":"Manufacturing & Wholesale Goods"
        }
    ],
    "sg:phone":"+1 612 377 2077",
    "sg:postcode":"55405",
    "sg:province":"MN",
    "sg:tags":[
        "professional",
        "industrial"
    ],
    "wof:name":"Torvac",
    "wof:placetype":"venue"
},
  "geometry": {"coordinates":[-93.31353300000001,44.971052],"type":"Point"}
}