{
  "type": "Feature",
  "properties": {
    "addr:full":"214 E Ahola Rd Ely MN 55731",
    "addr:housenumber":"214",
    "addr:postcode":"55731",
    "addr:street":"E Ahola Rd",
    "iso:country":"US",
    "sg:address":"214 E Ahola Rd",
    "sg:city":"Ely",
    "sg:classifiers":[
        {
            "category":"Retail",
            "subcategory":"Laundry & Dry Cleaning",
            "type":"Services"
        }
    ],
    "sg:phone":"+1 218 349 5851",
    "sg:postcode":"55731",
    "sg:province":"MN",
    "wof:name":"Reel Clean Carpet Care",
    "wof:placetype":"venue"
},
  "geometry": {"coordinates":[-91.86297999999999,47.891373],"type":"Point"}
}