{
  "type": "Feature",
  "properties": {
    "addr:full":"600 E Park Ave Olivia MN 56277",
    "addr:housenumber":"600",
    "addr:postcode":"56277",
    "addr:street":"E Park Ave",
    "iso:country":"US",
    "sg:address":"600 E Park Ave",
    "sg:city":"Olivia",
    "sg:classifiers":[
        {
            "category":"Health Services",
            "subcategory":"Doctor",
            "type":"Services"
        }
    ],
    "sg:phone":"+1 320 523 1460",
    "sg:postcode":"56277",
    "sg:province":"MN",
    "sg:tags":[
        "medicine",
        "physician",
        "practice",
        "surgeons",
        "family"
    ],
    "wof:name":"Prairie Family Practice",
    "wof:placetype":"venue"
},
  "geometry": {"coordinates":[-94.984009,44.773319],"type":"Point"}
}