{
  "type": "Feature",
  "properties": {
    "addr:full":"28804 Stull Rd Detroit Lakes MN 56501",
    "addr:postcode":"28804;56501",
    "addr:street":"Stull Rd",
    "iso:country":"US",
    "sg:address":"28804 Stull Rd",
    "sg:city":"Detroit Lakes",
    "sg:classifiers":[
        {
            "category":"Real Estate",
            "subcategory":"Real Estate Operator",
            "type":"Services"
        }
    ],
    "sg:phone":"+1 218 847 8012",
    "sg:postcode":"56501",
    "sg:province":"MN",
    "sg:tags":[
        "property",
        "lessor"
    ],
    "wof:name":"Clyde Stull",
    "wof:placetype":"venue"
},
  "geometry": {"coordinates":[-95.79993899999999,46.850898],"type":"Point"}
}