{
  "type": "Feature",
  "properties": {
    "addr:full":"542 Jefferson St SE Hutchinson MN 55350",
    "addr:housenumber":"542",
    "addr:postcode":"55350",
    "addr:street":"Jefferson St Se",
    "iso:country":"US",
    "sg:address":"542 Jefferson St SE",
    "sg:city":"Hutchinson",
    "sg:classifiers":[
        {
            "category":"Building & Trades",
            "subcategory":"Construction",
            "type":"Services"
        }
    ],
    "sg:phone":"+1 320 587 2293",
    "sg:postcode":"55350",
    "sg:province":"MN",
    "sg:tags":[
        "carpentry",
        "contractor"
    ],
    "wof:name":"John K Lofdahl Carpentry",
    "wof:placetype":"venue"
},
  "geometry": {"coordinates":[-94.36643100000001,44.885545],"type":"Point"}
}