{
  "type": "Feature",
  "properties": {
    "iso:country":"US",
    "sg:address":"1636 University Ave W",
    "sg:city":"Saint Paul",
    "sg:classifiers":[
        {
            "category":"Shopping",
            "subcategory":"Pawn Shop",
            "type":"Retail Goods"
        }
    ],
    "sg:phone":"+1 651 633 2274",
    "sg:postcode":"55104",
    "sg:province":"MN",
    "sg:website":"www.pawnamerica.com",
    "wof:name":"Pawn America",
    "wof:placetype":"venue"
},
  "geometry": {"coordinates":[-93.169296,44.9557],"type":"Point"}
}