{
  "type": "Feature",
  "properties": {
    "addr:full":"4497 Churchill St Saint Paul MN 55126",
    "addr:housenumber":"4497",
    "addr:postcode":"55126",
    "addr:street":"Churchill St",
    "iso:country":"US",
    "sg:address":"4497 Churchill St",
    "sg:city":"Saint Paul",
    "sg:classifiers":[
        {
            "category":"Banks & Credit Unions",
            "subcategory":"Bank",
            "type":"Services"
        }
    ],
    "sg:phone":"+1 651 490 3469",
    "sg:postcode":"55126",
    "sg:province":"MN",
    "sg:tags":[
        "mortgage"
    ],
    "wof:name":"Allied American Mortgage Inc",
    "wof:placetype":"venue"
},
  "geometry": {"coordinates":[-93.144988,45.076691],"type":"Point"}
}