{
  "type": "Feature",
  "properties": {
    "iso:country":"US",
    "sg:address":"4080 W Broadway Ave",
    "sg:city":"Minneapolis",
    "sg:classifiers":[
        {
            "category":"Bars & Pubs",
            "type":"Food & Drink"
        }
    ],
    "sg:phone":"+1 763 531 8411",
    "sg:postcode":"55422",
    "sg:province":"MN",
    "sg:tags":[
        "personal",
        "drinking",
        "restaurant"
    ],
    "wof:name":"Break-Away Bar & Grill",
    "wof:placetype":"venue"
},
  "geometry": {"coordinates":[-93.336304,45.0289],"type":"Point"}
}