{
  "type": "Feature",
  "properties": {
    "iso:country":"US",
    "sg:address":"41385 US Hwy 71",
    "sg:city":"Windom",
    "sg:classifiers":[
        {
            "category":"Sports & Exercise",
            "subcategory":"Bowling",
            "type":"Entertainment"
        }
    ],
    "sg:phone":"+1 507 831 4250",
    "sg:postcode":"56101",
    "sg:province":"MN",
    "sg:tags":[
        "center"
    ],
    "wof:name":"Sun Bowl",
    "wof:placetype":"venue"
},
  "geometry": {"coordinates":[-95.120403,43.88634],"type":"Point"}
}