{
  "type": "Feature",
  "properties": {
    "iso:country":"US",
    "sg:address":"21905 Woodbine St NW",
    "sg:city":"Anoka",
    "sg:classifiers":[
        {
            "category":"Professional",
            "type":"Services"
        }
    ],
    "sg:phone":"+1 612 581 2346",
    "sg:postcode":"55303",
    "sg:province":"MN",
    "sg:tags":[
        "establishment"
    ],
    "wof:name":"Obsidian Inc",
    "wof:placetype":"venue"
},
  "geometry": {"coordinates":[-93.360077,45.368893],"type":"Point"}
}