{
  "type": "Feature",
  "properties": {
    "addr:full":"114 W James St Paynesville MN 56362",
    "addr:housenumber":"114",
    "addr:postcode":"56362",
    "addr:street":"W James St",
    "iso:country":"US",
    "sg:address":"114 W James St",
    "sg:city":"Paynesville",
    "sg:classifiers":[
        {
            "category":"Retail",
            "subcategory":"Portrait Studio",
            "type":"Services"
        }
    ],
    "sg:phone":"+1 320 260 6174",
    "sg:postcode":"56362",
    "sg:province":"MN",
    "sg:tags":[
        "photo"
    ],
    "wof:name":"Tiff Wolff Photography",
    "wof:placetype":"venue"
},
  "geometry": {"coordinates":[-94.714286,45.381954],"type":"Point"}
}