{
  "type": "Feature",
  "properties": {
    "addr:full":"160 Park Ave Middle River MN 56737",
    "addr:housenumber":"160",
    "addr:postcode":"56737",
    "addr:street":"Park Ave",
    "iso:country":"US",
    "sg:address":"160 Park Ave",
    "sg:city":"Middle River",
    "sg:classifiers":[
        {
            "category":"Retail",
            "subcategory":"Funeral Services",
            "type":"Services"
        }
    ],
    "sg:phone":"+1 218 222 3510",
    "sg:postcode":"56737",
    "sg:province":"MN",
    "sg:tags":[
        "director"
    ],
    "wof:name":"Collins Funeral Homes Inc",
    "wof:placetype":"venue"
},
  "geometry": {"coordinates":[-96.165284,48.437582],"type":"Point"}
}