{
  "type": "Feature",
  "properties": {
    "iso:country":"US",
    "sg:address":"3204 W 44th St",
    "sg:city":"Minneapolis",
    "sg:classifiers":[
        {
            "category":"Manufacturing",
            "subcategory":"Printing",
            "type":"Manufacturing & Wholesale Goods"
        }
    ],
    "sg:phone":"+1 612 927 6021",
    "sg:postcode":"55410",
    "sg:province":"MN",
    "sg:tags":[
        "horn",
        "music",
        "sales",
        "publishing"
    ],
    "wof:name":"McCoys Horn Library",
    "wof:placetype":"venue"
},
  "geometry": {"coordinates":[-93.321404,44.923406],"type":"Point"}
}