{
  "type": "Feature",
  "properties": {
    "iso:country":"US",
    "sg:address":"7566 Island View Dr NE",
    "sg:city":"Bemidji",
    "sg:classifiers":[
        {
            "category":"Building & Trades",
            "subcategory":"Construction",
            "type":"Services"
        }
    ],
    "sg:phone":"+1 218 586 2820",
    "sg:postcode":"56601",
    "sg:province":"MN",
    "sg:tags":[
        "general",
        "contractor"
    ],
    "wof:name":"Halvorson Construction",
    "wof:placetype":"venue"
},
  "geometry": {"coordinates":[-94.768306,47.594902],"type":"Point"}
}