{
  "type": "Feature",
  "properties": {
    "addr:full":"1600 11th Ave SE Rochester MN 55904",
    "addr:housenumber":"1600",
    "addr:postcode":"55904",
    "addr:street":"11Th Ave Se",
    "iso:country":"US",
    "sg:address":"1600 11th Ave SE",
    "sg:city":"Rochester",
    "sg:classifiers":[
        {
            "category":"Place Of Worship",
            "subcategory":"Church",
            "type":"Public Place"
        },
        {
            "category":"Place Of Worship",
            "type":"Public Place"
        },
        {
            "category":"Organizations",
            "subcategory":"Religious Organization",
            "type":"Services"
        }
    ],
    "sg:phone":"+1 507 288 5528",
    "sg:postcode":"55904",
    "sg:province":"MN",
    "sg:tags":[
        "churches-catholic-traditional",
        "churches-catholic"
    ],
    "wof:name":"Church Of The Resurrection Inc",
    "wof:placetype":"venue"
},
  "geometry": {"coordinates":[-92.446083,44.000511],"type":"Point"}
}