{
  "type": "Feature",
  "properties": {
    "iso:country":"US",
    "sg:address":"14732 260th St",
    "sg:city":"Cold Spring",
    "sg:classifiers":[
        {
            "category":"Farming",
            "subcategory":"Livestock Farm",
            "type":"Manufacturing & Wholesale Goods"
        }
    ],
    "sg:phone":"+1 320 685 3132",
    "sg:postcode":"56320",
    "sg:province":"MN",
    "sg:tags":[
        "beef",
        "feedlot",
        "cattle"
    ],
    "wof:name":"James Johannes",
    "wof:placetype":"venue"
},
  "geometry": {"coordinates":[-94.40525100000001,45.500201],"type":"Point"}
}