{
  "type": "Feature",
  "properties": {
    "addr:full":"3100 California St NE Minneapolis MN 55418",
    "addr:housenumber":"3100",
    "addr:postcode":"55418",
    "addr:street":"California St Ne",
    "iso:country":"US",
    "sg:address":"3100 California St NE",
    "sg:city":"Minneapolis",
    "sg:classifiers":[
        {
            "category":"Building & Trades",
            "subcategory":"Construction",
            "type":"Services"
        }
    ],
    "sg:phone":"+1 612 522 0662",
    "sg:postcode":"55418",
    "sg:province":"MN",
    "sg:tags":[
        "hanging",
        "contractor"
    ],
    "wof:name":"Pro Line Painting",
    "wof:placetype":"venue"
},
  "geometry": {"coordinates":[-93.26897099999999,45.024573],"type":"Point"}
}