{
  "type": "Feature",
  "properties": {
    "addr:full":"3 Enterprise Dr S Virginia MN 55792",
    "addr:housenumber":"3",
    "addr:postcode":"55792",
    "addr:street":"Enterprise Dr S",
    "iso:country":"US",
    "sg:address":"3 Enterprise Dr S",
    "sg:city":"Virginia",
    "sg:classifiers":[
        {
            "category":"Home & Garden",
            "subcategory":"Furniture",
            "type":"Retail Goods"
        }
    ],
    "sg:phone":"+1 218 741 5363",
    "sg:postcode":"55792",
    "sg:province":"MN",
    "wof:name":"Brownie's Mattress Express",
    "wof:placetype":"venue"
},
  "geometry": {"coordinates":[-92.57252200000001,47.517379],"type":"Point"}
}