{
  "type": "Feature",
  "properties": {
    "iso:country":"US",
    "sg:address":"3600 American Blvd W # 100",
    "sg:city":"Minneapolis",
    "sg:classifiers":[
        {
            "category":"Insurance",
            "subcategory":"Insurance Agent",
            "type":"Services"
        },
        {
            "category":"Insurance",
            "subcategory":"Hazard Insurance",
            "type":"Services"
        },
        {
            "category":"Insurance",
            "subcategory":"Health Insurance",
            "type":"Services"
        },
        {
            "category":"Insurance",
            "subcategory":"Life Insurance",
            "type":"Services"
        }
    ],
    "sg:phone":"+1 952 893 0214",
    "sg:postcode":"55431",
    "sg:province":"MN",
    "sg:tags":[
        "business",
        "fire",
        "auto",
        "commercial",
        "benefit",
        "employee",
        "property",
        "casualty"
    ],
    "sg:website":"http://www.amica.com",
    "wof:name":"Amica Mutual Insurance Company",
    "wof:placetype":"venue"
},
  "geometry": {"coordinates":[-93.324878,44.857195],"type":"Point"}
}