{
  "type": "Feature",
  "properties": {
    "addr:full":"1246 Saddlebrook Ln Saint Paul MN 55125",
    "addr:housenumber":"1246",
    "addr:postcode":"55125",
    "addr:street":"Saddlebrook Ln",
    "iso:country":"US",
    "sg:address":"1246 Saddlebrook Ln",
    "sg:city":"Saint Paul",
    "sg:classifiers":[
        {
            "category":"Retail",
            "subcategory":"Photofinishing",
            "type":"Services"
        }
    ],
    "sg:phone":"+1 651 738 6403",
    "sg:postcode":"55125",
    "sg:province":"MN",
    "sg:tags":[
        "laboratory"
    ],
    "wof:name":"Aerial Adventures",
    "wof:placetype":"venue"
},
  "geometry": {"coordinates":[-92.92449000000001,44.930705],"type":"Point"}
}