{
  "type": "Feature",
  "properties": {
    "iso:country":"US",
    "sg:address":"418 Co Rd D E",
    "sg:city":"Saint Paul",
    "sg:classifiers":[
        {
            "category":"Professional",
            "subcategory":"Management & Consulting",
            "type":"Services"
        }
    ],
    "sg:phone":"+1 651 483 2600",
    "sg:postcode":"55117",
    "sg:province":"MN",
    "wof:name":"Hennessey Financial",
    "wof:placetype":"venue"
},
  "geometry": {"coordinates":[-93.07998000000001,45.035376],"type":"Point"}
}