{
  "type": "Feature",
  "properties": {
    "iso:country":"US",
    "sg:address":"216 Red River Ave N",
    "sg:city":"Cold Spring",
    "sg:classifiers":[
        {
            "category":"Autos & Motor Vehicles",
            "subcategory":"Fuel & Gas Station",
            "type":"Retail Goods"
        }
    ],
    "sg:phone":"+1 320 685 3583",
    "sg:postcode":"56320",
    "sg:province":"MN",
    "sg:tags":[
        "oil"
    ],
    "wof:name":"Conoco Cold Springs",
    "wof:placetype":"venue"
},
  "geometry": {"coordinates":[-94.428918,45.45828],"type":"Point"}
}