{
  "type": "Feature",
  "properties": {
    "addr:full":"632 E 134th St Burnsville MN 55337",
    "addr:housenumber":"632",
    "addr:postcode":"55337",
    "addr:street":"E 134Th St",
    "iso:country":"US",
    "sg:address":"632 E 134th St",
    "sg:city":"Burnsville",
    "sg:classifiers":[
        {
            "category":"Professional",
            "subcategory":"Management & Consulting",
            "type":"Services"
        }
    ],
    "sg:phone":"+1 952 894 3527",
    "sg:postcode":"55337",
    "sg:province":"MN",
    "wof:name":"Performance Focus",
    "wof:placetype":"venue"
},
  "geometry": {"coordinates":[-93.266406,44.761285],"type":"Point"}
}