{
  "type": "Feature",
  "properties": {
    "addr:full":"200 E 5th St Morris MN 56267",
    "addr:housenumber":"200",
    "addr:postcode":"56267",
    "addr:street":"E 5Th St",
    "iso:country":"US",
    "sg:address":"200 E 5th St",
    "sg:city":"Morris",
    "sg:classifiers":[
        {
            "category":"Organizations",
            "subcategory":"Religious Organization",
            "type":"Services"
        }
    ],
    "sg:phone":"+1 320 589 3242",
    "sg:postcode":"56267",
    "sg:province":"MN",
    "sg:tags":[
        "church"
    ],
    "sg:website":"www.firstlutheranmorris.org",
    "wof:name":"First Lutheran Church Inc",
    "wof:placetype":"venue"
},
  "geometry": {"coordinates":[-95.910088,45.587917],"type":"Point"}
}