{
  "type": "Feature",
  "properties": {
    "addr:full":"16124 Co Rd 124 Paynesville MN 56362",
    "addr:housenumber":"16124",
    "addr:postcode":"56362",
    "addr:street":"Co Rd 124",
    "iso:country":"US",
    "sg:address":"16124 Co Rd 124",
    "sg:city":"Paynesville",
    "sg:classifiers":[
        {
            "category":"Building & Trades",
            "subcategory":"Construction",
            "type":"Services"
        }
    ],
    "sg:phone":"+1 320 243 8101",
    "sg:postcode":"56362",
    "sg:province":"MN",
    "sg:tags":[
        "general",
        "contractor"
    ],
    "wof:name":"Highline Construction Inc",
    "wof:placetype":"venue"
},
  "geometry": {"coordinates":[-94.702495,45.356984],"type":"Point"}
}