{
  "type": "Feature",
  "properties": {
    "addr:full":"1811 Greenview Pl SW Rochester MN 55902",
    "addr:housenumber":"1811",
    "addr:postcode":"55902",
    "addr:street":"Greenview Pl Sw",
    "iso:country":"US",
    "sg:address":"1811 Greenview Pl SW",
    "sg:city":"Rochester",
    "sg:classifiers":[
        {
            "category":"Insurance",
            "subcategory":"Insurance Agent",
            "type":"Services"
        }
    ],
    "sg:phone":"+1 507 252 1058",
    "sg:postcode":"55902",
    "sg:province":"MN",
    "wof:name":"John F Whelan CLU",
    "wof:placetype":"venue"
},
  "geometry": {"coordinates":[-92.48947099999999,44.000866],"type":"Point"}
}