{
  "type": "Feature",
  "properties": {
    "iso:country":"US",
    "sg:address":"4825 Wood Ave",
    "sg:city":"Saint Paul",
    "sg:classifiers":[
        {
            "category":"Professional",
            "subcategory":"Business Services",
            "type":"Services"
        }
    ],
    "sg:phone":"+1 651 653 8041",
    "sg:postcode":"55110",
    "sg:province":"MN",
    "wof:name":"Wg Fabricators Incorporated",
    "wof:placetype":"venue"
},
  "geometry": {"coordinates":[-93.020594,45.086652],"type":"Point"}
}