{
  "type": "Feature",
  "properties": {
    "iso:country":"US",
    "sg:address":"1387 Lawrence Rd",
    "sg:city":"Cloquet",
    "sg:classifiers":[
        {
            "category":"Home & Garden",
            "subcategory":"Building Materials",
            "type":"Retail Goods"
        }
    ],
    "sg:phone":"+1 218 879 8911",
    "sg:postcode":"55720",
    "sg:province":"MN",
    "wof:name":"Petersens Door Service",
    "wof:placetype":"venue"
},
  "geometry": {"coordinates":[-92.45306600000001,46.68531],"type":"Point"}
}