{
  "type": "Feature",
  "properties": {
    "iso:country":"US",
    "sg:address":"3844 Johnson St NE",
    "sg:city":"Minneapolis",
    "sg:classifiers":[
        {
            "category":"Government",
            "subcategory":"Office",
            "type":"Public Place"
        }
    ],
    "sg:phone":"+1 612 618 3995",
    "sg:postcode":"55421",
    "sg:province":"MN",
    "sg:tags":[
        "educational",
        "program",
        "administrative"
    ],
    "wof:name":"Education Across Borders",
    "wof:placetype":"venue"
},
  "geometry": {"coordinates":[-93.237195,45.036325],"type":"Point"}
}