{
  "type": "Feature",
  "properties": {
    "iso:country":"US",
    "sg:address":"5354 Twig Blvd",
    "sg:city":"Saginaw",
    "sg:classifiers":[
        {
            "category":"Manufacturing",
            "subcategory":"Tools & Machinery",
            "type":"Manufacturing & Wholesale Goods"
        }
    ],
    "sg:phone":"+1 218 729 8721",
    "sg:postcode":"55779",
    "sg:province":"MN",
    "sg:tags":[
        "equipment",
        "welding",
        "supply"
    ],
    "sg:website":"www.flatwaterfleet.com",
    "wof:name":"Flatwater Fleet Truck Ctr",
    "wof:placetype":"venue"
},
  "geometry": {"coordinates":[-92.372552,46.900278],"type":"Point"}
}