{
  "type": "Feature",
  "properties": {
    "addr:full":"21336 Cooley Dr Brainerd MN 56401",
    "addr:housenumber":"21336",
    "addr:postcode":"56401",
    "addr:street":"Cooley Dr",
    "iso:country":"US",
    "sg:address":"21336 Cooley Dr",
    "sg:city":"Brainerd",
    "sg:classifiers":[
        {
            "category":"Farming",
            "subcategory":"Livestock Farm",
            "type":"Manufacturing & Wholesale Goods"
        }
    ],
    "sg:phone":"+1 218 764 3185",
    "sg:postcode":"56401",
    "sg:province":"MN",
    "sg:tags":[
        "beef",
        "feedlot",
        "cattle"
    ],
    "wof:name":"Roy Kraklau",
    "wof:placetype":"venue"
},
  "geometry": {"coordinates":[-93.950418,46.228784],"type":"Point"}
}