{
  "type": "Feature",
  "properties": {
    "iso:country":"US",
    "sg:address":"956 4th Ave",
    "sg:city":"Windom",
    "sg:classifiers":[
        {
            "category":"Personal",
            "subcategory":"Beauty Salon",
            "type":"Services"
        }
    ],
    "sg:phone":"+1 507 831 1863",
    "sg:postcode":"56101",
    "sg:province":"MN",
    "sg:tags":[
        "shop"
    ],
    "wof:name":"Mane Attraction of Windom",
    "wof:placetype":"venue"
},
  "geometry": {"coordinates":[-95.117779,43.865903],"type":"Point"}
}