{
  "type": "Feature",
  "properties": {
    "addr:full":"30 W Water St St Paul MN 55107",
    "addr:housenumber":"30",
    "addr:postcode":"55107",
    "addr:street":"W Water St",
    "iso:country":"US",
    "sg:address":"30 W Water St",
    "sg:city":"St Paul",
    "sg:classifiers":[
        {
            "category":"Wholesale",
            "subcategory":"Electrical",
            "type":"Manufacturing & Wholesale Goods"
        }
    ],
    "sg:phone":"+1 651 292 0102",
    "sg:postcode":"55107",
    "sg:province":"MN",
    "sg:tags":[
        "telecommunication"
    ],
    "wof:name":"Ideacom Mid America",
    "wof:placetype":"venue"
},
  "geometry": {"coordinates":[-93.09453999999999,44.937138],"type":"Point"}
}