{
  "type": "Feature",
  "properties": {
    "iso:country":"US",
    "sg:address":"2307 4th St NW",
    "sg:city":"Austin",
    "sg:classifiers":[
        {
            "category":"Building & Trades",
            "subcategory":"Equipment Rental",
            "type":"Services"
        }
    ],
    "sg:phone":"+1 507 433 5751",
    "sg:postcode":"55912",
    "sg:province":"MN",
    "wof:name":"Faribault Rental Equipment",
    "wof:placetype":"venue"
},
  "geometry": {"coordinates":[-92.979659,43.690673],"type":"Point"}
}