{
  "type": "Feature",
  "properties": {
    "addr:full":"1512 11th Ave NE Rochester MN 55906",
    "addr:housenumber":"1512",
    "addr:postcode":"55906",
    "addr:street":"11Th Ave Ne",
    "iso:country":"US",
    "sg:address":"1512 11th Ave NE",
    "sg:city":"Rochester",
    "sg:classifiers":[
        {
            "category":"Health Services",
            "subcategory":"Clinic",
            "type":"Services"
        }
    ],
    "sg:phone":"+1 507 284 3507",
    "sg:postcode":"55906",
    "sg:province":"MN",
    "sg:tags":[
        "home",
        "care"
    ],
    "wof:name":"Jim Fuehrer",
    "wof:placetype":"venue"
},
  "geometry": {"coordinates":[-92.448685,44.03893],"type":"Point"}
}