{
  "type": "Feature",
  "properties": {
    "iso:country":"US",
    "sg:address":"3224 128th Ave NE",
    "sg:city":"Minneapolis",
    "sg:classifiers":[
        {
            "category":"Building & Trades",
            "subcategory":"Construction",
            "type":"Services"
        }
    ],
    "sg:phone":"+1 763 780 9448",
    "sg:postcode":"55449",
    "sg:province":"MN",
    "sg:tags":[
        "excavation",
        "contractor"
    ],
    "wof:name":"Freedom Excavating, Inc.",
    "wof:placetype":"venue"
},
  "geometry": {"coordinates":[-93.174831,45.202223],"type":"Point"}
}