{
  "type": "Feature",
  "properties": {
    "addr:full":"609 Bemidji Ave N Bemidji MN 56601",
    "addr:housenumber":"609",
    "addr:postcode":"56601",
    "addr:street":"Bemidji Ave N",
    "iso:country":"US",
    "sg:address":"609 Bemidji Ave N",
    "sg:city":"Bemidji",
    "sg:classifiers":[
        {
            "category":"Building & Trades",
            "subcategory":"Landscaping Services",
            "type":"Services"
        }
    ],
    "sg:phone":"+1 218 751 2882",
    "sg:postcode":"56601",
    "sg:province":"MN",
    "sg:tags":[
        "designer",
        "landscape"
    ],
    "wof:name":"Rose & Assoc",
    "wof:placetype":"venue"
},
  "geometry": {"coordinates":[-94.879656,47.474621],"type":"Point"}
}