{
  "type": "Feature",
  "properties": {
    "iso:country":"US",
    "sg:address":"7145 Oakland Ave",
    "sg:city":"Minneapolis",
    "sg:classifiers":[
        {
            "category":"Building & Trades",
            "subcategory":"Plumbing",
            "type":"Services"
        }
    ],
    "sg:phone":"+1 612 243 3965",
    "sg:postcode":"55423",
    "sg:province":"MN",
    "sg:tags":[
        "plumber",
        "industrial",
        "contractors-commercial"
    ],
    "wof:name":"Johnson Plumbing & Heating",
    "wof:placetype":"venue"
},
  "geometry": {"coordinates":[-93.266757,44.873697],"type":"Point"}
}