{
  "type": "Feature",
  "properties": {
    "iso:country":"US",
    "sg:address":"4347 Upton Ave N",
    "sg:city":"Minneapolis",
    "sg:classifiers":[
        {
            "category":"Social Services",
            "subcategory":"Child Care",
            "type":"Services"
        }
    ],
    "sg:phone":"+1 612 522 8869",
    "sg:postcode":"55412",
    "sg:province":"MN",
    "sg:tags":[
        "daycare",
        "provider"
    ],
    "wof:name":"Mary Vondrachek",
    "wof:placetype":"venue"
},
  "geometry": {"coordinates":[-93.315017,45.034485],"type":"Point"}
}