{
  "type": "Feature",
  "properties": {
    "iso:country":"US",
    "sg:address":"2922 68th Ln N",
    "sg:city":"Minneapolis",
    "sg:classifiers":[
        {
            "category":"Building & Trades",
            "subcategory":"Electrical",
            "type":"Services"
        }
    ],
    "sg:phone":"+1 763 566 4127",
    "sg:postcode":"55430",
    "sg:province":"MN",
    "sg:tags":[
        "electrical",
        "contractor"
    ],
    "wof:name":"Steve Castor",
    "wof:placetype":"venue"
},
  "geometry": {"coordinates":[-93.31938599999999,45.077349],"type":"Point"}
}