{
  "type": "Feature",
  "properties": {
    "iso:country":"US",
    "sg:address":"9244 Telford Bay",
    "sg:city":"Minneapolis",
    "sg:classifiers":[
        {
            "category":"Professional",
            "subcategory":"Computer Services",
            "type":"Services"
        }
    ],
    "sg:phone":"+1 763 315 4111",
    "sg:postcode":"55443",
    "sg:province":"MN",
    "sg:tags":[
        "repair"
    ],
    "wof:name":"Dinonet Dot Net",
    "wof:placetype":"venue"
},
  "geometry": {"coordinates":[-93.314499,45.1217],"type":"Point"}
}