{
  "type": "Feature",
  "properties": {
    "iso:country":"US",
    "sg:address":"1835 Northwestern Ave",
    "sg:city":"Stillwater",
    "sg:classifiers":[
        {
            "category":"Real Estate",
            "subcategory":"Real Estate Agent",
            "type":"Services"
        }
    ],
    "sg:phone":"+1 651 351 5000",
    "sg:postcode":"55082",
    "sg:province":"MN",
    "wof:name":"Re Max Resources",
    "wof:placetype":"venue"
},
  "geometry": {"coordinates":[-92.82811,45.039413],"type":"Point"}
}