{
  "type": "Feature",
  "properties": {
    "addr:full":"1021 2nd Ave N Moorhead MN 56560",
    "addr:housenumber":"1021",
    "addr:postcode":"56560",
    "addr:street":"2Nd Ave N",
    "iso:country":"US",
    "sg:address":"1021 2nd Ave N",
    "sg:city":"Moorhead",
    "sg:classifiers":[
        {
            "category":"Building & Trades",
            "subcategory":"Construction",
            "type":"Services"
        }
    ],
    "sg:phone":"+1 218 233 5314",
    "sg:postcode":"56560",
    "sg:province":"MN",
    "sg:tags":[
        "excavating",
        "contractor"
    ],
    "wof:name":"Henry Brothers Excavating Inc",
    "wof:placetype":"venue"
},
  "geometry": {"coordinates":[-96.763114,46.877075],"type":"Point"}
}