{
  "type": "Feature",
  "properties": {
    "addr:full":"17316 553rd Ave Good Thunder MN 56037",
    "addr:housenumber":"17316",
    "addr:postcode":"56037",
    "addr:street":"553Rd Ave",
    "iso:country":"US",
    "sg:address":"17316 553rd Ave",
    "sg:city":"Good Thunder",
    "sg:classifiers":[
        {
            "category":"Building & Trades",
            "subcategory":"Construction",
            "type":"Services"
        }
    ],
    "sg:phone":"+1 507 278 3818",
    "sg:postcode":"56037",
    "sg:province":"MN",
    "sg:tags":[
        "house"
    ],
    "wof:name":"Garman Construction",
    "wof:placetype":"venue"
},
  "geometry": {"coordinates":[-94.064046,44.045673],"type":"Point"}
}