{
  "type": "Feature",
  "properties": {
    "addr:full":"3310 5th St NE Minneapolis MN 55418",
    "addr:housenumber":"3310",
    "addr:postcode":"55418",
    "addr:street":"5Th St Ne",
    "iso:country":"US",
    "sg:address":"3310 5th St NE",
    "sg:city":"Minneapolis",
    "sg:classifiers":[
        {
            "category":"Manufacturing",
            "subcategory":"Tools & Machinery",
            "type":"Manufacturing & Wholesale Goods"
        }
    ],
    "sg:phone":"+1 612 782 8205",
    "sg:postcode":"55418",
    "sg:province":"MN",
    "sg:tags":[
        "equipment",
        "woodworking",
        "supply"
    ],
    "sg:website":"www.benchdog.com",
    "wof:name":"Bench Dog Inc",
    "wof:placetype":"venue"
},
  "geometry": {"coordinates":[-93.259975,45.030006],"type":"Point"}
}