{
  "type": "Feature",
  "properties": {
    "iso:country":"US",
    "sg:address":"32245 296th St",
    "sg:city":"Red Wing",
    "sg:classifiers":[
        {
            "category":"Building & Trades",
            "subcategory":"Construction",
            "type":"Services"
        }
    ],
    "sg:phone":"+1 651 388 5888",
    "sg:postcode":"55066",
    "sg:province":"MN",
    "sg:tags":[
        "excavation",
        "contractor"
    ],
    "wof:name":"Mahoney Excavating",
    "wof:placetype":"venue"
},
  "geometry": {"coordinates":[-92.38776,44.518809],"type":"Point"}
}