{
  "type": "Feature",
  "properties": {
    "iso:country":"US",
    "sg:address":"41482 840th Ave",
    "sg:city":"Bird Island",
    "sg:phone":"+1 320 365 3028",
    "sg:postcode":"55310",
    "sg:province":"MN",
    "sg:tags":[
        "farm",
        "corn"
    ],
    "wof:name":"Larry Posl",
    "wof:placetype":"venue"
},
  "geometry": {"coordinates":[-94.844455,44.804513],"type":"Point"}
}