{
  "type": "Feature",
  "properties": {
    "iso:country":"US",
    "sg:address":"17100 Rogers Rd",
    "sg:city":"Eden Prairie",
    "sg:classifiers":[
        {
            "category":"Professional",
            "subcategory":"Business Services",
            "type":"Services"
        }
    ],
    "sg:phone":"+1 952 906 2877",
    "sg:postcode":"55347",
    "sg:province":"MN",
    "wof:name":"C Kruse & Associates Inc",
    "wof:placetype":"venue"
},
  "geometry": {"coordinates":[-93.495583,44.837646],"type":"Point"}
}