{
  "type": "Feature",
  "properties": {
    "iso:country":"US",
    "sg:address":"36778 Co Rd 13",
    "sg:city":"Warroad",
    "sg:classifiers":[
        {
            "category":"Retail",
            "subcategory":"Laundry & Dry Cleaning",
            "type":"Services"
        }
    ],
    "sg:phone":"+1 218 386 3118",
    "sg:postcode":"56756",
    "sg:province":"MN",
    "wof:name":"Newgard Carpet & Uphl Clrs",
    "wof:placetype":"venue"
},
  "geometry": {"coordinates":[-95.505645,48.923689],"type":"Point"}
}