{
  "type": "Feature",
  "properties": {
    "addr:full":"108 S Washington St Lake City MN 55041",
    "addr:housenumber":"108",
    "addr:postcode":"55041",
    "addr:street":"S Washington St",
    "iso:country":"US",
    "sg:address":"108 S Washington St",
    "sg:city":"Lake City",
    "sg:classifiers":[
        {
            "category":"Home & Garden",
            "subcategory":"Carpets & Floor Coverings",
            "type":"Retail Goods"
        }
    ],
    "sg:phone":"+1 651 345 3213",
    "sg:postcode":"55041",
    "sg:province":"MN",
    "sg:tags":[
        "draper"
    ],
    "wof:name":"Bryce Floor Cvg & Dctg Suppli",
    "wof:placetype":"venue"
},
  "geometry": {"coordinates":[-92.266183,44.449808],"type":"Point"}
}