{
  "type": "Feature",
  "properties": {
    "addr:full":"1620 Central Ave NE Minneapolis MN 55413",
    "addr:housenumber":"1620",
    "addr:postcode":"55413",
    "addr:street":"Central Ave Ne",
    "iso:country":"US",
    "sg:address":"1620 Central Ave NE",
    "sg:city":"Minneapolis",
    "sg:classifiers":[
        {
            "category":"Home & Garden",
            "subcategory":"Furniture",
            "type":"Retail Goods"
        }
    ],
    "sg:phone":"+1 612 781 1903",
    "sg:postcode":"55413",
    "sg:province":"MN",
    "sg:tags":[
        "cabinet"
    ],
    "wof:name":"Peterson Custom Furniture",
    "wof:placetype":"venue"
},
  "geometry": {"coordinates":[-93.247378,45.003498],"type":"Point"}
}