{
  "type": "Feature",
  "properties": {
    "iso:country":"US",
    "sg:address":"375 S Cretin Ave",
    "sg:city":"Saint Paul",
    "sg:classifiers":[
        {
            "category":"Professional",
            "subcategory":"Management & Consulting",
            "type":"Services"
        }
    ],
    "sg:phone":"+1 651 696 0032",
    "sg:postcode":"55105",
    "sg:province":"MN",
    "sg:tags":[
        "retail",
        "direct",
        "sales"
    ],
    "wof:name":"Dinnerwhere LLC",
    "wof:placetype":"venue"
},
  "geometry": {"coordinates":[-93.19256300000001,44.930265],"type":"Point"}
}