{
  "type": "Feature",
  "properties": {
    "iso:country":"US",
    "sg:address":"10717 10th Ave N",
    "sg:city":"Minneapolis",
    "sg:classifiers":[
        {
            "category":"Building & Trades",
            "subcategory":"Landscaping Services",
            "type":"Services"
        }
    ],
    "sg:phone":"+1 612 282 7103",
    "sg:postcode":"55441",
    "sg:province":"MN",
    "sg:tags":[
        "lawn",
        "maintenance",
        "grounds"
    ],
    "wof:name":"Yardwerx",
    "wof:placetype":"venue"
},
  "geometry": {"coordinates":[-93.415729,44.989392],"type":"Point"}
}