{
  "type": "Feature",
  "properties": {
    "addr:full":"28361 Co Rd 34 Paynesville MN 56362",
    "addr:housenumber":"28361;34",
    "addr:postcode":"56362",
    "addr:street":"Co Rd",
    "iso:country":"US",
    "sg:address":"28361 Co Rd 34",
    "sg:city":"Paynesville",
    "sg:classifiers":[
        {
            "category":"Manufacturing",
            "subcategory":"Lumber",
            "type":"Manufacturing & Wholesale Goods"
        }
    ],
    "sg:phone":"+1 320 243 8505",
    "sg:postcode":"56362",
    "sg:province":"MN",
    "sg:tags":[
        "operation",
        "timber",
        "tract"
    ],
    "wof:name":"Quercus Forest Products Inc",
    "wof:placetype":"venue"
},
  "geometry": {"coordinates":[-94.70659499999999,45.372597],"type":"Point"}
}