{
  "type": "Feature",
  "properties": {
    "addr:full":"1051 Grand Ave St Paul MN 55105",
    "addr:housenumber":"1051",
    "addr:postcode":"55105",
    "addr:street":"Grand Ave",
    "iso:country":"US",
    "sg:address":"1051 Grand Ave",
    "sg:city":"St Paul",
    "sg:classifiers":[
        {
            "category":"Shopping",
            "type":"Retail Goods"
        },
        {
            "category":"Recreation",
            "type":"Entertainment"
        }
    ],
    "sg:phone":"+1 651 224 0600",
    "sg:postcode":"55105",
    "sg:province":"MN",
    "sg:tags":[
        "art",
        "gallery",
        "dealer"
    ],
    "wof:name":"Tibet Art",
    "wof:placetype":"venue"
},
  "geometry": {"coordinates":[-93.146293,44.940071],"type":"Point"}
}