{
  "type": "Feature",
  "properties": {
    "iso:country":"US",
    "sg:address":"223 Main St S",
    "sg:city":"Stillwater",
    "sg:classifiers":[
        {
            "category":"Shopping",
            "subcategory":"Clothing, Apparel, & Fashions",
            "type":"Retail Goods"
        }
    ],
    "sg:phone":"+1 651 275 1290",
    "sg:postcode":"55082",
    "sg:province":"MN",
    "wof:name":"Sammies Womens Casual Attire",
    "wof:placetype":"venue"
},
  "geometry": {"coordinates":[-92.80546099999999,45.055133],"type":"Point"}
}