{
  "type": "Feature",
  "properties": {
    "addr:full":"1240 Washburn Ave N Minneapolis MN 55411",
    "addr:housenumber":"1240",
    "addr:postcode":"55411",
    "addr:street":"Washburn Ave N",
    "iso:country":"US",
    "sg:address":"1240 Washburn Ave N",
    "sg:city":"Minneapolis",
    "sg:classifiers":[
        {
            "category":"Utilities",
            "subcategory":"Telephone",
            "type":"Services"
        }
    ],
    "sg:phone":"+1 612 302 7915",
    "sg:postcode":"55411",
    "sg:province":"MN",
    "sg:tags":[
        "website",
        "entertainment"
    ],
    "wof:name":"Mindworks Entertainment Inc",
    "wof:placetype":"venue"
},
  "geometry": {"coordinates":[-93.317116,44.990988],"type":"Point"}
}