{
  "type": "Feature",
  "properties": {
    "iso:country":"US",
    "sg:address":"21130 Chippendale Ave W",
    "sg:city":"Farmington",
    "sg:classifiers":[
        {
            "category":"Wholesale",
            "subcategory":"Construction Materials",
            "type":"Manufacturing & Wholesale Goods"
        }
    ],
    "sg:phone":"+1 651 460 6626",
    "sg:postcode":"55024",
    "sg:province":"MN",
    "sg:tags":[
        "building"
    ],
    "wof:name":"Wausau Supply Co",
    "wof:placetype":"venue"
},
  "geometry": {"coordinates":[-93.13707599999999,44.642122],"type":"Point"}
}