{
  "type": "Feature",
  "properties": {
    "addr:full":"1223 E Superior St Duluth MN 55802",
    "addr:housenumber":"1223",
    "addr:postcode":"55802",
    "addr:street":"E Superior St",
    "iso:country":"US",
    "sg:address":"1223 E Superior St",
    "sg:city":"Duluth",
    "sg:classifiers":[
        {
            "category":"Wholesale",
            "subcategory":"Hardware",
            "type":"Manufacturing & Wholesale Goods"
        }
    ],
    "sg:phone":"+1 218 728 4207",
    "sg:postcode":"55802",
    "sg:province":"MN",
    "sg:tags":[
        "purifying",
        "cleaning",
        "air"
    ],
    "wof:name":"Pure Living",
    "wof:placetype":"venue"
},
  "geometry": {"coordinates":[-92.082336,46.799164],"type":"Point"}
}