{
  "type": "Feature",
  "properties": {
    "iso:country":"US",
    "sg:address":"324 Court St",
    "sg:city":"Albert Lea",
    "sg:classifiers":[
        {
            "category":"Utilities",
            "subcategory":"Telephone",
            "type":"Services"
        }
    ],
    "sg:phone":"+1 507 373 0424",
    "sg:postcode":"56007",
    "sg:province":"MN",
    "sg:tags":[
        "communications"
    ],
    "wof:name":"Hector Medrano",
    "wof:placetype":"venue"
},
  "geometry": {"coordinates":[-93.37042599999999,43.646308],"type":"Point"}
}