{
  "type": "Feature",
  "properties": {
    "addr:full":"1414 N Star Dr Zumbrota MN 55992",
    "addr:housenumber":"1414",
    "addr:postcode":"55992",
    "addr:street":"N Star Dr",
    "iso:country":"US",
    "sg:address":"1414 N Star Dr",
    "sg:city":"Zumbrota",
    "sg:classifiers":[
        {
            "category":"Social Services",
            "type":"Services"
        }
    ],
    "sg:phone":"+1 507 732 7391",
    "sg:postcode":"55992",
    "sg:province":"MN",
    "sg:tags":[
        "action",
        "agency",
        "human",
        "community"
    ],
    "sg:website":"www.threeriverscap.org",
    "wof:name":"Three Rivers Community Action",
    "wof:placetype":"venue"
},
  "geometry": {"coordinates":[-92.682478,44.300344],"type":"Point"}
}