{
  "type": "Feature",
  "properties": {
    "addr:full":"32156 Peony Ln Pequot Lakes MN 56472",
    "addr:housenumber":"32156",
    "addr:postcode":"56472",
    "addr:street":"Peony Ln",
    "iso:country":"US",
    "sg:address":"32156 Peony Ln",
    "sg:city":"Pequot Lakes",
    "sg:classifiers":[
        {
            "category":"Wholesale",
            "subcategory":"Groceries",
            "type":"Manufacturing & Wholesale Goods"
        }
    ],
    "sg:phone":"+1 218 562 4406",
    "sg:postcode":"56472",
    "sg:province":"MN",
    "sg:tags":[
        "frozen",
        "packaged"
    ],
    "wof:name":"Frosty Pine Foods",
    "wof:placetype":"venue"
},
  "geometry": {"coordinates":[-94.186188,46.618847],"type":"Point"}
}