{
  "type": "Feature",
  "properties": {
    "iso:country":"US",
    "sg:address":"10087 20th St SE",
    "sg:city":"Clara City",
    "sg:phone":"+1 320 847 2144",
    "sg:postcode":"56222",
    "sg:province":"MN",
    "sg:tags":[
        "farm",
        "corn",
        "soybean"
    ],
    "wof:name":"Calvin Harms",
    "wof:placetype":"venue"
},
  "geometry": {"coordinates":[-95.389876,44.992648],"type":"Point"}
}