{
  "type": "Feature",
  "properties": {
    "iso:country":"US",
    "sg:address":"878 113th Ln NE",
    "sg:city":"Minneapolis",
    "sg:classifiers":[
        {
            "category":"Utilities",
            "subcategory":"Telephone",
            "type":"Services"
        }
    ],
    "sg:phone":"+1 763 757 5331",
    "sg:postcode":"55434",
    "sg:province":"MN",
    "sg:tags":[
        "telecommunication"
    ],
    "wof:name":"3 Pro Telecom",
    "wof:placetype":"venue"
},
  "geometry": {"coordinates":[-93.249295,45.176084],"type":"Point"}
}