{
  "type": "Feature",
  "properties": {
    "addr:full":"312 5th Ave SE Osseo MN 55369",
    "addr:housenumber":"312",
    "addr:postcode":"55369",
    "addr:street":"5Th Ave Se",
    "iso:country":"US",
    "sg:address":"312 5th Ave SE",
    "sg:city":"Osseo",
    "sg:classifiers":[
        {
            "category":"Building & Trades",
            "subcategory":"Construction",
            "type":"Services"
        },
        {
            "category":"Home & Garden",
            "subcategory":"Carpets & Floor Coverings",
            "type":"Retail Goods"
        }
    ],
    "sg:phone":"+1 763 425 0679",
    "sg:postcode":"55369",
    "sg:province":"MN",
    "sg:tags":[
        "bathroom",
        "rug",
        "planning",
        "remodeling",
        "kitchen"
    ],
    "wof:name":"Abbey Carpet Northwest Inc",
    "wof:placetype":"venue"
},
  "geometry": {"coordinates":[-93.396062,45.11198],"type":"Point"}
}