{
  "type": "Feature",
  "properties": {
    "addr:full":"1817 E Lake St Minneapolis MN 55407",
    "addr:housenumber":"1817",
    "addr:postcode":"55407",
    "addr:street":"E Lake St",
    "iso:country":"US",
    "sg:address":"1817 E Lake St",
    "sg:city":"Minneapolis",
    "sg:classifiers":[
        {
            "category":"Shopping",
            "subcategory":"Clothing, Apparel, & Fashions",
            "type":"Retail Goods"
        }
    ],
    "sg:phone":"+1 612 724 3774",
    "sg:postcode":"55407",
    "sg:province":"MN",
    "sg:tags":[
        "western"
    ],
    "wof:name":"El Primo",
    "wof:placetype":"venue"
},
  "geometry": {"coordinates":[-93.248065,44.948296],"type":"Point"}
}