{
  "type": "Feature",
  "properties": {
    "iso:country":"US",
    "sg:address":"10801 Nesbitt Ave. South",
    "sg:city":"Bloomington",
    "sg:classifiers":[
        {
            "category":"Professional",
            "subcategory":"Computer Services",
            "type":"Services"
        }
    ],
    "sg:postcode":"55437",
    "sg:province":"MN",
    "sg:website":"http://www.plato.com/",
    "wof:name":"Plato Learning",
    "wof:placetype":"venue"
},
  "geometry": {"coordinates":[-93.35842100000001,44.807888],"type":"Point"}
}