{
  "type": "Feature",
  "properties": {
    "addr:full":"17709 Kenwood Trl Lakeville MN 55044",
    "addr:housenumber":"17709",
    "addr:postcode":"55044",
    "addr:street":"Kenwood Trl",
    "iso:country":"US",
    "sg:address":"17709 Kenwood Trl",
    "sg:city":"Lakeville",
    "sg:classifiers":[
        {
            "category":"Restaurant",
            "type":"Food & Drink"
        }
    ],
    "sg:phone":"+1 952 898 1388",
    "sg:postcode":"55044",
    "sg:province":"MN",
    "sg:tags":[
        "eating"
    ],
    "wof:name":"Tak Shing Chinese Restaurant",
    "wof:placetype":"venue"
},
  "geometry": {"coordinates":[-93.282909,44.690967],"type":"Point"}
}