{
  "type": "Feature",
  "properties": {
    "addr:full":"2212 Aldrich Ave S Minneapolis MN 55405",
    "addr:housenumber":"2212",
    "addr:postcode":"55405",
    "addr:street":"Aldrich Ave S",
    "iso:country":"US",
    "sg:address":"2212 Aldrich Ave S",
    "sg:city":"Minneapolis",
    "sg:classifiers":[
        {
            "category":"Shopping",
            "subcategory":"Shoes",
            "type":"Retail Goods"
        }
    ],
    "sg:phone":"+1 612 374 5423",
    "sg:postcode":"55405",
    "sg:province":"MN",
    "wof:name":"Nightingale AR",
    "wof:placetype":"venue"
},
  "geometry": {"coordinates":[-93.28936400000001,44.959231],"type":"Point"}
}