{
  "type": "Feature",
  "properties": {
    "addr:full":"1349 14th St N St Cloud MN 56303",
    "addr:housenumber":"1349",
    "addr:postcode":"56303",
    "addr:street":"14Th St N",
    "iso:country":"US",
    "sg:address":"1349 14th St N",
    "sg:city":"St Cloud",
    "sg:classifiers":[
        {
            "category":"Real Estate",
            "subcategory":"Real Estate Operator",
            "type":"Services"
        }
    ],
    "sg:phone":"+1 320 255 5471",
    "sg:postcode":"56303",
    "sg:province":"MN",
    "sg:tags":[
        "townhouses"
    ],
    "wof:name":"Cedar Terrace Townhouses",
    "wof:placetype":"venue"
},
  "geometry": {"coordinates":[-94.178911,45.574395],"type":"Point"}
}