{
  "type": "Feature",
  "properties": {
    "addr:full":"15802 370th St Rothsay MN 56579",
    "addr:housenumber":"15802",
    "addr:postcode":"56579",
    "addr:street":"370Th St",
    "iso:country":"US",
    "sg:address":"15802 370th St",
    "sg:city":"Rothsay",
    "sg:phone":"+1 218 867 2515",
    "sg:postcode":"56579",
    "sg:province":"MN",
    "sg:tags":[
        "farm",
        "corn",
        "soybean"
    ],
    "wof:name":"Anderson Farm",
    "wof:placetype":"venue"
},
  "geometry": {"coordinates":[-96.157561,46.500321],"type":"Point"}
}