{
  "type": "Feature",
  "properties": {
    "addr:full":"1532 10th St SE Rochester MN 55904",
    "addr:housenumber":"1532",
    "addr:postcode":"55904",
    "addr:street":"10Th St Se",
    "iso:country":"US",
    "sg:address":"1532 10th St SE",
    "sg:city":"Rochester",
    "sg:classifiers":[
        {
            "category":"Professional",
            "subcategory":"Business Services",
            "type":"Services"
        }
    ],
    "sg:phone":"+1 507 288 5509",
    "sg:postcode":"55904",
    "sg:province":"MN",
    "sg:tags":[
        "lecture",
        "bureau",
        "seminar"
    ],
    "wof:name":"Zone Sitting Seminars",
    "wof:placetype":"venue"
},
  "geometry": {"coordinates":[-92.441276,44.011082],"type":"Point"}
}