{
  "type": "Feature",
  "properties": {
    "addr:full":"10128 45th St NE Saint Michael MN 55376",
    "addr:housenumber":"10128",
    "addr:postcode":"55376",
    "addr:street":"45Th St Ne Saint Michael",
    "iso:country":"US",
    "sg:address":"10128 45th St NE",
    "sg:city":"Saint Michael",
    "sg:classifiers":[
        {
            "category":"Professional",
            "subcategory":"Management & Consulting",
            "type":"Services"
        }
    ],
    "sg:phone":"+1 763 497 7855",
    "sg:postcode":"55376",
    "sg:province":"MN",
    "wof:name":"Ivision Human Resources LLC",
    "wof:placetype":"venue"
},
  "geometry": {"coordinates":[-93.677666,45.213384],"type":"Point"}
}