{
  "type": "Feature",
  "properties": {
    "addr:full":"1330 Industrial Blvd NE Minneapolis MN 55413",
    "addr:housenumber":"1330",
    "addr:postcode":"55413",
    "addr:street":"Industrial Blvd Ne",
    "iso:country":"US",
    "sg:address":"1330 Industrial Blvd NE",
    "sg:city":"Minneapolis",
    "sg:classifiers":[
        {
            "category":"Shopping",
            "subcategory":"Computers & Home Electronics",
            "type":"Retail Goods"
        }
    ],
    "sg:phone":"+1 612 331 7912",
    "sg:postcode":"55413",
    "sg:province":"MN",
    "sg:tags":[
        "audio"
    ],
    "wof:name":"Presentation Services",
    "wof:placetype":"venue"
},
  "geometry": {"coordinates":[-93.21162,44.9957],"type":"Point"}
}