{
  "type": "Feature",
  "properties": {
    "addr:full":"1231 S Oak Ave Owatonna MN 55060",
    "addr:housenumber":"1231",
    "addr:postcode":"55060",
    "addr:street":"S Oak Ave",
    "iso:country":"US",
    "sg:address":"1231 S Oak Ave",
    "sg:city":"Owatonna",
    "sg:classifiers":[
        {
            "category":"Building & Trades",
            "subcategory":"Construction",
            "type":"Services"
        }
    ],
    "sg:phone":"+1 507 451 5916",
    "sg:postcode":"55060",
    "sg:province":"MN",
    "sg:tags":[
        "repairing",
        "altering",
        "remodeling",
        "contractor"
    ],
    "wof:name":"Quality Electric Service Inc",
    "wof:placetype":"venue"
},
  "geometry": {"coordinates":[-93.228442,44.071185],"type":"Point"}
}