{
  "type": "Feature",
  "properties": {
    "iso:country":"US",
    "sg:address":"2430 Pillsbury Ave S",
    "sg:city":"Minneapolis",
    "sg:classifiers":[
        {
            "category":"Building & Trades",
            "subcategory":"Construction",
            "type":"Services"
        }
    ],
    "sg:phone":"+1 612 874 6937",
    "sg:postcode":"55404",
    "sg:province":"MN",
    "sg:tags":[
        "equipment",
        "contractor",
        "drywall",
        "supply"
    ],
    "wof:name":"Rws Paint & Drywall",
    "wof:placetype":"venue"
},
  "geometry": {"coordinates":[-93.28128100000001,44.958555],"type":"Point"}
}