{
  "type": "Feature",
  "properties": {
    "iso:country":"US",
    "sg:address":"1831 Central Ave NE",
    "sg:city":"Minneapolis",
    "sg:classifiers":[
        {
            "category":"Restaurant",
            "type":"Food & Drink"
        }
    ],
    "sg:postcode":"55418",
    "sg:province":"MN",
    "sg:tags":[
        "afghan"
    ],
    "wof:name":"Bilal's Restaurant",
    "wof:placetype":"venue"
},
  "geometry": {"coordinates":[-93.247326,45.007013],"type":"Point"}
}