{
  "type": "Feature",
  "properties": {
    "addr:full":"1831 Central Ave NE Minneapolis MN 55418",
    "addr:housenumber":"1831",
    "addr:postcode":"55418",
    "addr:street":"Central Ave Ne",
    "iso:country":"US",
    "sg:address":"1831 Central Ave NE",
    "sg:city":"Minneapolis",
    "sg:classifiers":[
        {
            "category":"Restaurant",
            "type":"Food & Drink"
        }
    ],
    "sg:postcode":"55418",
    "sg:province":"MN",
    "sg:tags":[
        "afghan"
    ],
    "wof:name":"Bilal's Restaurant",
    "wof:placetype":"venue"
},
  "geometry": {"coordinates":[-93.247326,45.007013],"type":"Point"}
}