{
  "type": "Feature",
  "properties": {
    "iso:country":"US",
    "sg:address":"45604 Co Rd 3",
    "sg:city":"Windom",
    "sg:phone":"+1 507 831 4120",
    "sg:postcode":"56101",
    "sg:province":"MN",
    "sg:tags":[
        "farm",
        "grain",
        "cash"
    ],
    "wof:name":"David Muller",
    "wof:placetype":"venue"
},
  "geometry": {"coordinates":[-95.172864,43.985308],"type":"Point"}
}