{
  "type": "Feature",
  "properties": {
    "iso:country":"US",
    "sg:address":"431 7th St S",
    "sg:city":"Minneapolis",
    "sg:classifiers":[
        {
            "category":"Professional",
            "subcategory":"Lawyer & Legal Services",
            "type":"Services"
        }
    ],
    "sg:phone":"+1 612 344 1555",
    "sg:postcode":"55415",
    "sg:province":"MN",
    "sg:tags":[
        "attorney"
    ],
    "sg:website":"www.basslaw.com",
    "wof:name":"Louis Bass",
    "wof:placetype":"venue"
},
  "geometry": {"coordinates":[-93.265747,44.974118],"type":"Point"}
}