{
  "type": "Feature",
  "properties": {
    "iso:country":"US",
    "sg:address":"300 Pebble Creek Dr",
    "sg:city":"Mankato",
    "sg:classifiers":[
        {
            "category":"Manufacturing",
            "subcategory":"Buildings",
            "type":"Manufacturing & Wholesale Goods"
        },
        {
            "category":"Building & Trades",
            "subcategory":"Construction",
            "type":"Services"
        }
    ],
    "sg:phone":"+1 507 380 5060",
    "sg:postcode":"56001",
    "sg:province":"MN",
    "sg:tags":[
        "excavation",
        "home",
        "builder",
        "contractor"
    ],
    "wof:name":"Cooney Construction",
    "wof:placetype":"venue"
},
  "geometry": {"coordinates":[-93.964752,44.190609],"type":"Point"}
}