{
  "type": "Feature",
  "properties": {
    "addr:full":"426 Main St St Thomas MN 58276",
    "addr:housenumber":"426",
    "addr:postcode":"58276",
    "addr:street":"Main St",
    "iso:country":"US",
    "sg:address":"426 Main St",
    "sg:city":"St Thomas",
    "sg:classifiers":[
        {
            "category":"Personal",
            "subcategory":"Beauty Salon",
            "type":"Services"
        }
    ],
    "sg:phone":"+1 701 257 6550",
    "sg:postcode":"58276",
    "sg:province":"MN",
    "wof:name":"T L Hair Care",
    "wof:placetype":"venue"
},
  "geometry": {"coordinates":[-97.448882,48.61888],"type":"Point"}
}