{
  "type": "Feature",
  "properties": {
    "iso:country":"US",
    "sg:address":"2011 S 6th St",
    "sg:city":"Brainerd",
    "sg:classifiers":[
        {
            "category":"Health Services",
            "subcategory":"Clinic",
            "type":"Services"
        }
    ],
    "sg:phone":"+1 218 825 0512",
    "sg:postcode":"56401",
    "sg:province":"MN",
    "sg:tags":[
        "home",
        "care"
    ],
    "wof:name":"Extended Family Homecare",
    "wof:placetype":"venue"
},
  "geometry": {"coordinates":[-94.20064600000001,46.335088],"type":"Point"}
}