{
  "type": "Feature",
  "properties": {
    "addr:full":"7879 Copper Rd Cushing MN 56443",
    "addr:housenumber":"7879",
    "addr:postcode":"56443",
    "addr:street":"Copper Rd",
    "iso:country":"US",
    "sg:address":"7879 Copper Rd",
    "sg:city":"Cushing",
    "sg:classifiers":[
        {
            "category":"Travel",
            "subcategory":"Hotels & Motels",
            "type":"Entertainment"
        }
    ],
    "sg:phone":"+1 218 575 2131",
    "sg:postcode":"56443",
    "sg:province":"MN",
    "sg:tags":[
        "resort",
        "operation"
    ],
    "wof:name":"Shady Inn Resort",
    "wof:placetype":"venue"
},
  "geometry": {"coordinates":[-94.499112,46.208769],"type":"Point"}
}