{
  "type": "Feature",
  "properties": {
    "addr:full":"24818 Town Ave Worthington MN 56187",
    "addr:housenumber":"24818",
    "addr:postcode":"56187",
    "addr:street":"Town Ave",
    "iso:country":"US",
    "sg:address":"24818 Town Ave",
    "sg:city":"Worthington",
    "sg:classifiers":[
        {
            "category":"Farming",
            "subcategory":"Poultry Farm",
            "type":"Manufacturing & Wholesale Goods"
        }
    ],
    "sg:phone":"+1 507 376 5244",
    "sg:postcode":"56187",
    "sg:province":"MN",
    "sg:tags":[
        "egg"
    ],
    "wof:name":"T & M Farms",
    "wof:placetype":"venue"
},
  "geometry": {"coordinates":[-95.512728,43.633782],"type":"Point"}
}