{
  "type": "Feature",
  "properties": {
    "addr:full":"78667 State Hwy 4 Hector MN 55342",
    "addr:housenumber":"78667",
    "addr:postcode":"55342",
    "addr:street":"State Hwy 4 Hector",
    "iso:country":"US",
    "sg:address":"78667 State Hwy 4",
    "sg:city":"Hector",
    "sg:phone":"+1 320 848 6396",
    "sg:postcode":"55342",
    "sg:province":"MN",
    "sg:tags":[
        "farm",
        "corn",
        "soybean"
    ],
    "wof:name":"Brad Fosland",
    "wof:placetype":"venue"
},
  "geometry": {"coordinates":[-94.721423,44.722953],"type":"Point"}
}