{
  "type": "Feature",
  "properties": {
    "addr:full":"2608 Blaisdell Ave Minneapolis MN 55408",
    "addr:housenumber":"2608",
    "addr:postcode":"55408",
    "addr:street":"Blaisdell Ave",
    "iso:country":"US",
    "sg:address":"2608 Blaisdell Ave",
    "sg:city":"Minneapolis",
    "sg:classifiers":[
        {
            "category":"Social Services",
            "subcategory":"Child Care",
            "type":"Services"
        }
    ],
    "sg:phone":"+1 612 872 1741",
    "sg:postcode":"55408",
    "sg:province":"MN",
    "sg:tags":[
        "nursery",
        "day"
    ],
    "wof:name":"Sister Saint Joseph, The",
    "wof:placetype":"venue"
},
  "geometry": {"coordinates":[-93.27964,44.955373],"type":"Point"}
}