{
  "type": "Feature",
  "properties": {
    "iso:country":"US",
    "sg:address":"4534 Berg Rd",
    "sg:city":"Duluth",
    "sg:classifiers":[
        {
            "category":"Building & Trades",
            "subcategory":"Construction",
            "type":"Services"
        }
    ],
    "sg:phone":"+1 218 721 5162",
    "sg:postcode":"55803",
    "sg:province":"MN",
    "sg:tags":[
        "contractor"
    ],
    "wof:name":"Rail Dismantling and Salv Co",
    "wof:placetype":"venue"
},
  "geometry": {"coordinates":[-92.15398399999999,47.002566],"type":"Point"}
}