{
  "type": "Feature",
  "properties": {
    "addr:full":"4020 Old Sibley Memorial Hwy Eagan MN 55122",
    "addr:housenumber":"4020",
    "addr:postcode":"55122",
    "addr:street":"Old Sibley Memorial Hwy",
    "iso:country":"US",
    "sg:address":"4020 Old Sibley Memorial Hwy",
    "sg:city":"Eagan",
    "sg:classifiers":[
        {
            "category":"Retail",
            "subcategory":"Animal Services",
            "type":"Services"
        }
    ],
    "sg:phone":"+1 651 882 2211",
    "sg:postcode":"55122",
    "sg:province":"MN",
    "sg:tags":[
        "pet",
        "boarding",
        "sitting"
    ],
    "wof:name":"Four Paws Pet Resort",
    "wof:placetype":"venue"
},
  "geometry": {"coordinates":[-93.223208,44.808195],"type":"Point"}
}