{
  "type": "Feature",
  "properties": {
    "iso:country":"US",
    "sg:address":"5880 Henry St",
    "sg:city":"Maple Plain",
    "sg:classifiers":[
        {
            "category":"Building & Trades",
            "subcategory":"Landscaping Services",
            "type":"Services"
        }
    ],
    "sg:phone":"+1 763 479 2888",
    "sg:postcode":"55359",
    "sg:province":"MN",
    "sg:tags":[
        "plowing",
        "landscape",
        "contractor"
    ],
    "wof:name":"Groundscape Maintenanace",
    "wof:placetype":"venue"
},
  "geometry": {"coordinates":[-93.675415,45.006409],"type":"Point"}
}