{
  "type": "Feature",
  "properties": {
    "addr:full":"333 Ash St Tyler MN 56178",
    "addr:housenumber":"333",
    "addr:postcode":"56178",
    "addr:street":"Ash St",
    "iso:country":"US",
    "sg:address":"333 Ash St",
    "sg:city":"Tyler",
    "sg:classifiers":[
        {
            "category":"Utilities",
            "subcategory":"Electric",
            "type":"Services"
        }
    ],
    "sg:phone":"+1 507 247 5300",
    "sg:postcode":"56178",
    "sg:province":"MN",
    "sg:tags":[
        "generation",
        "prov",
        "spec",
        "power"
    ],
    "wof:name":"Windpower Partners 1993",
    "wof:placetype":"venue"
},
  "geometry": {"coordinates":[-96.124819,44.271266],"type":"Point"}
}