{
  "type": "Feature",
  "properties": {
    "addr:full":"28 W Main St Madelia MN 56062",
    "addr:housenumber":"28",
    "addr:postcode":"56062",
    "addr:street":"W Main St",
    "iso:country":"US",
    "sg:address":"28 W Main St",
    "sg:city":"Madelia",
    "sg:classifiers":[
        {
            "category":"Shopping",
            "subcategory":"Florist",
            "type":"Retail Goods"
        }
    ],
    "sg:phone":"+1 507 642 8967",
    "sg:postcode":"56062",
    "sg:province":"MN",
    "wof:name":"Mainstreet Floral & Gifts",
    "wof:placetype":"venue"
},
  "geometry": {"coordinates":[-94.417248,44.05075],"type":"Point"}
}