{
  "type": "Feature",
  "properties": {
    "iso:country":"US",
    "sg:address":"13910 Knollway Dr N",
    "sg:city":"Hopkins",
    "sg:classifiers":[
        {
            "category":"Shopping",
            "type":"Retail Goods"
        }
    ],
    "sg:phone":"+1 952 545 3791",
    "sg:postcode":"55305",
    "sg:province":"MN",
    "sg:tags":[
        "merchandise"
    ],
    "wof:name":"N Hand Home",
    "wof:placetype":"venue"
},
  "geometry": {"coordinates":[-93.455929,44.974575],"type":"Point"}
}