{
  "type": "Feature",
  "properties": {
    "addr:full":"3771 130th St W Faribault MN 55021",
    "addr:housenumber":"3771",
    "addr:postcode":"55021",
    "addr:street":"130Th St W",
    "iso:country":"US",
    "sg:address":"3771 130th St W",
    "sg:city":"Faribault",
    "sg:classifiers":[
        {
            "category":"Retail",
            "subcategory":"Repair Shop",
            "type":"Services"
        }
    ],
    "sg:phone":"+1 507 645 4308",
    "sg:postcode":"55021",
    "sg:province":"MN",
    "wof:name":"Brennan Taxidermy",
    "wof:placetype":"venue"
},
  "geometry": {"coordinates":[-93.33948700000001,44.399671],"type":"Point"}
}