{
  "type": "Feature",
  "properties": {
    "iso:country":"US",
    "sg:address":"8379 Sunrise Trl",
    "sg:city":"Britt",
    "sg:classifiers":[
        {
            "category":"Organizations",
            "subcategory":"Community Association",
            "type":"Services"
        }
    ],
    "sg:phone":"+1 218 741 0207",
    "sg:postcode":"55710",
    "sg:province":"MN",
    "wof:name":"Sons of Norway",
    "wof:placetype":"venue"
},
  "geometry": {"coordinates":[-92.569744,47.641468],"type":"Point"}
}