{
  "type": "Feature",
  "properties": {
    "addr:full":"220 Zenith St Lanesboro MN 55949",
    "addr:housenumber":"220",
    "addr:postcode":"55949",
    "addr:street":"Zenith St",
    "iso:country":"US",
    "sg:address":"220 Zenith St",
    "sg:city":"Lanesboro",
    "sg:classifiers":[
        {
            "category":"Retail",
            "subcategory":"Repair Shop",
            "type":"Services"
        }
    ],
    "sg:phone":"+1 507 467 3483",
    "sg:postcode":"55949",
    "sg:province":"MN",
    "sg:tags":[
        "upholsterer"
    ],
    "wof:name":"Thomas Bryan Hatleli",
    "wof:placetype":"venue"
},
  "geometry": {"coordinates":[-91.968887,43.709258],"type":"Point"}
}