{
  "type": "Feature",
  "properties": {
    "addr:full":"91 Janell Ave La Crescent MN 55947",
    "addr:housenumber":"91",
    "addr:postcode":"55947",
    "addr:street":"Janell Ave",
    "iso:country":"US",
    "sg:address":"91 Janell Ave",
    "sg:city":"La Crescent",
    "sg:classifiers":[
        {
            "category":"Freight",
            "type":"Transportation"
        }
    ],
    "sg:phone":"+1 507 895 4285",
    "sg:postcode":"55947",
    "sg:province":"MN",
    "wof:name":"Herman E Gady",
    "wof:placetype":"venue"
},
  "geometry": {"coordinates":[-91.32222,43.819198],"type":"Point"}
}