{
  "type": "Feature",
  "properties": {
    "addr:full":"Calhoun Square Minneapolis MN 55467",
    "addr:postcode":"55467",
    "addr:street":"Calhoun Square",
    "iso:country":"US",
    "sg:address":"Calhoun Square",
    "sg:city":"Minneapolis",
    "sg:classifiers":[
        {
            "category":"Restaurant",
            "type":"Food & Drink"
        }
    ],
    "sg:postcode":"55467",
    "sg:province":"MN",
    "sg:tags":[
        "pizza"
    ],
    "wof:name":"Rotiserria",
    "wof:placetype":"venue"
},
  "geometry": {"coordinates":[-93.303613,44.941427],"type":"Point"}
}