{
  "type": "Feature",
  "properties": {
    "iso:country":"US",
    "sg:address":"35902 Co Rd 173",
    "sg:city":"Melrose",
    "sg:classifiers":[
        {
            "category":"Building & Trades",
            "subcategory":"Construction",
            "type":"Services"
        }
    ],
    "sg:phone":"+1 320 256 7411",
    "sg:postcode":"56352",
    "sg:province":"MN",
    "sg:tags":[
        "floor",
        "laying",
        "contractor"
    ],
    "wof:name":"Professional Wood Floors",
    "wof:placetype":"venue"
},
  "geometry": {"coordinates":[-94.787927,45.643424],"type":"Point"}
}