{
  "type": "Feature",
  "properties": {
    "addr:full":"49197 Elysian Rd Elysian MN 56028",
    "addr:housenumber":"49197",
    "addr:postcode":"56028",
    "addr:street":"Elysian Rd",
    "iso:country":"US",
    "sg:address":"49197 Elysian Rd",
    "sg:city":"Elysian",
    "sg:classifiers":[
        {
            "category":"Real Estate",
            "subcategory":"Real Estate Operator",
            "type":"Services"
        }
    ],
    "sg:phone":"+1 507 267 4484",
    "sg:postcode":"56028",
    "sg:province":"MN",
    "sg:tags":[
        "property",
        "lessor"
    ],
    "wof:name":"Alvin Bittner",
    "wof:placetype":"venue"
},
  "geometry": {"coordinates":[-93.725714,44.239551],"type":"Point"}
}