{
  "type": "Feature",
  "properties": {
    "iso:country":"US",
    "sg:address":"17837 George Moran Dr",
    "sg:city":"Eden Prairie",
    "sg:classifiers":[
        {
            "category":"Professional",
            "subcategory":"Computer Services",
            "type":"Services"
        }
    ],
    "sg:phone":"+1 952 975 9643",
    "sg:postcode":"55347",
    "sg:province":"MN",
    "sg:tags":[
        "related"
    ],
    "wof:name":"Broeks Consulting Service",
    "wof:placetype":"venue"
},
  "geometry": {"coordinates":[-93.50552399999999,44.855591],"type":"Point"}
}