{
  "type": "Feature",
  "properties": {
    "iso:country":"US",
    "sg:address":"23186 Kerry St NW",
    "sg:city":"Saint Francis",
    "sg:classifiers":[
        {
            "category":"Building & Trades",
            "subcategory":"Construction",
            "type":"Services"
        }
    ],
    "sg:phone":"+1 763 753 9895",
    "sg:postcode":"55070",
    "sg:province":"MN",
    "sg:tags":[
        "house"
    ],
    "wof:name":"White Rob",
    "wof:placetype":"venue"
},
  "geometry": {"coordinates":[-93.34499,45.390402],"type":"Point"}
}