{
  "type": "Feature",
  "properties": {
    "addr:full":"4375 204th St E Faribault MN 55021",
    "addr:housenumber":"4375",
    "addr:postcode":"55021",
    "addr:street":"204Th St E",
    "iso:country":"US",
    "sg:address":"4375 204th St E",
    "sg:city":"Faribault",
    "sg:classifiers":[
        {
            "category":"Professional",
            "type":"Services"
        }
    ],
    "sg:phone":"+1 507 332 5000",
    "sg:postcode":"55021",
    "sg:province":"MN",
    "sg:tags":[
        "establishment"
    ],
    "wof:name":"D & L Specialties",
    "wof:placetype":"venue"
},
  "geometry": {"coordinates":[-93.212833,44.292411],"type":"Point"}
}