{
  "type": "Feature",
  "properties": {
    "addr:full":"8500 State Hwy 7 Minneapolis MN 55426",
    "addr:housenumber":"8500",
    "addr:postcode":"55426",
    "addr:street":"State Hwy 7",
    "iso:country":"US",
    "sg:address":"8500 State Hwy 7",
    "sg:city":"Minneapolis",
    "sg:classifiers":[
        {
            "category":"Restaurant",
            "type":"Food & Drink"
        }
    ],
    "sg:phone":"+1 952 935 1099",
    "sg:postcode":"55426",
    "sg:province":"MN",
    "wof:name":"Kiko's Rice Bowl",
    "wof:placetype":"venue"
},
  "geometry": {"coordinates":[-93.382848,44.936241],"type":"Point"}
}