{
  "type": "Feature",
  "properties": {
    "iso:country":"US",
    "sg:address":"6228 Penn Ave S",
    "sg:city":"Minneapolis",
    "sg:classifiers":[
        {
            "category":"Coffee & Tea",
            "type":"Food & Drink"
        },
        {
            "category":"Restaurant",
            "type":"Food & Drink"
        }
    ],
    "sg:menulink":"http://www.allmenus.com/mn/richfield/58676-caribou-coffee/menu/",
    "sg:phone":"+1 612 243 1581",
    "sg:postcode":"55423",
    "sg:province":"MN",
    "sg:tags":[
        "tea",
        "coffee",
        "american"
    ],
    "wof:name":"Caribou Coffee",
    "wof:placetype":"venue"
},
  "geometry": {"coordinates":[-93.30936199999999,44.889594],"type":"Point"}
}