{
  "type": "Feature",
  "properties": {
    "iso:country":"US",
    "sg:address":"10420 US Hwy 169",
    "sg:city":"Amboy",
    "sg:classifiers":[
        {
            "category":"Wholesale",
            "subcategory":"Construction Materials",
            "type":"Manufacturing & Wholesale Goods"
        },
        {
            "category":"Freight",
            "type":"Transportation"
        }
    ],
    "sg:phone":"+1 507 674 3222",
    "sg:postcode":"56010",
    "sg:province":"MN",
    "sg:tags":[
        "operator",
        "sand",
        "gravel",
        "local",
        "trucking"
    ],
    "wof:name":"Paul D Mc Cue Trucking",
    "wof:placetype":"venue"
},
  "geometry": {"coordinates":[-94.16856300000001,43.858144],"type":"Point"}
}