{
  "type": "Feature",
  "properties": {
    "addr:full":"1169 Larpenteur Ave W Roseville MN 55113",
    "addr:housenumber":"1169",
    "addr:postcode":"55113",
    "addr:street":"Larpenteur Ave W",
    "iso:country":"US",
    "sg:address":"1169 Larpenteur Ave W",
    "sg:city":"Roseville",
    "sg:classifiers":[
        {
            "category":"Autos & Motor Vehicles",
            "subcategory":"Auto Supplies",
            "type":"Retail Goods"
        }
    ],
    "sg:phone":"+1 651 488 6676",
    "sg:postcode":"55113",
    "sg:province":"MN",
    "sg:tags":[
        "automobile",
        "parts",
        "store"
    ],
    "sg:website":"www.cskauto.com",
    "wof:name":"Checker Auto Parts 1812",
    "wof:placetype":"venue"
},
  "geometry": {"coordinates":[-93.150913,44.991993],"type":"Point"}
}