{
  "type": "Feature",
  "properties": {
    "addr:full":"12458 Zea St NW Minneapolis MN 55433",
    "addr:postcode":"12458;55433",
    "addr:street":"Zea St Nw",
    "iso:country":"US",
    "sg:address":"12458 Zea St NW",
    "sg:city":"Minneapolis",
    "sg:classifiers":[
        {
            "category":"Wholesale",
            "subcategory":"Vending Machines",
            "type":"Manufacturing & Wholesale Goods"
        }
    ],
    "sg:phone":"+1 763 506 0242",
    "sg:postcode":"55433",
    "sg:province":"MN",
    "sg:tags":[
        "operator"
    ],
    "wof:name":"D&T Vending",
    "wof:placetype":"venue"
},
  "geometry": {"coordinates":[-93.361234,45.196053],"type":"Point"}
}