{
  "type": "Feature",
  "properties": {
    "iso:country":"US",
    "sg:address":"83036 255th St",
    "sg:city":"Albert Lea",
    "sg:classifiers":[
        {
            "category":"Farming",
            "subcategory":"Farm",
            "type":"Manufacturing & Wholesale Goods"
        }
    ],
    "sg:phone":"+1 507 256 4708",
    "sg:postcode":"56007",
    "sg:province":"MN",
    "sg:tags":[
        "firm",
        "general",
        "crop",
        "trucking"
    ],
    "wof:name":"Wangen Bros Farm",
    "wof:placetype":"venue"
},
  "geometry": {"coordinates":[-93.189362,43.720991],"type":"Point"}
}