{
  "type": "Feature",
  "properties": {
    "addr:full":"1301 Commonwealth Ave Duluth MN 55808",
    "addr:housenumber":"1301",
    "addr:postcode":"55808",
    "addr:street":"Commonwealth Ave",
    "iso:country":"US",
    "sg:address":"1301 Commonwealth Ave",
    "sg:city":"Duluth",
    "sg:classifiers":[
        {
            "category":"Food & Beverages",
            "subcategory":"Groceries & Convenience Stores",
            "type":"Retail Goods"
        }
    ],
    "sg:phone":"+1 218 626 3397",
    "sg:postcode":"55808",
    "sg:province":"MN",
    "wof:name":"The Little Store",
    "wof:placetype":"venue"
},
  "geometry": {"coordinates":[-92.226463,46.670349],"type":"Point"}
}