{
  "type": "Feature",
  "properties": {
    "iso:country":"US",
    "sg:address":"3424 Pleasant Ave S",
    "sg:city":"Minneapolis",
    "sg:classifiers":[
        {
            "category":"Food & Beverages",
            "subcategory":"Groceries & Convenience Stores",
            "type":"Retail Goods"
        }
    ],
    "sg:phone":"+1 612 823 1147",
    "sg:postcode":"55408",
    "sg:province":"MN",
    "wof:name":"Luckygirl Gourmet Grocery",
    "wof:placetype":"venue"
},
  "geometry": {"coordinates":[-93.28313300000001,44.939971],"type":"Point"}
}