{
  "type": "Feature",
  "properties": {
    "addr:full":"524 Rensvold Blvd Moorhead MN 56560",
    "addr:housenumber":"524",
    "addr:postcode":"56560",
    "addr:street":"Rensvold Blvd",
    "iso:country":"US",
    "sg:address":"524 Rensvold Blvd",
    "sg:city":"Moorhead",
    "sg:classifiers":[
        {
            "category":"Building & Trades",
            "subcategory":"Landscaping Services",
            "type":"Services"
        }
    ],
    "sg:phone":"+1 218 233 6732",
    "sg:postcode":"56560",
    "sg:province":"MN",
    "sg:tags":[
        "landscape"
    ],
    "wof:name":"Ultimate Landscaping",
    "wof:placetype":"venue"
},
  "geometry": {"coordinates":[-96.737799,46.868403],"type":"Point"}
}