{
  "type": "Feature",
  "properties": {
    "iso:country":"US",
    "sg:address":"33034 Mac Cir",
    "sg:city":"Vergas",
    "sg:classifiers":[
        {
            "category":"Professional",
            "type":"Services"
        }
    ],
    "sg:phone":"+1 218 342 3842",
    "sg:postcode":"56528",
    "sg:province":"MN",
    "sg:tags":[
        "establishment"
    ],
    "wof:name":"Mason & Mason",
    "wof:placetype":"venue"
},
  "geometry": {"coordinates":[-95.797714,46.579483],"type":"Point"}
}