{
  "type": "Feature",
  "properties": {
    "iso:country":"US",
    "sg:address":"2421 Winter Cir",
    "sg:city":"Wayzata",
    "sg:classifiers":[
        {
            "category":"Professional",
            "subcategory":"Research",
            "type":"Services"
        }
    ],
    "sg:phone":"+1 952 473 8349",
    "sg:postcode":"55391",
    "sg:province":"MN",
    "sg:tags":[
        "nonphysical",
        "commercial"
    ],
    "wof:name":"Healthcore Research LLC",
    "wof:placetype":"venue"
},
  "geometry": {"coordinates":[-93.46998000000001,44.956665],"type":"Point"}
}