{
  "type": "Feature",
  "properties": {
    "addr:full":"13059 Ridgedale Dr Hopkins MN 55305",
    "addr:housenumber":"13059",
    "addr:postcode":"55305",
    "addr:street":"Ridgedale Dr",
    "iso:country":"US",
    "sg:address":"13059 Ridgedale Dr",
    "sg:city":"Hopkins",
    "sg:classifiers":[
        {
            "category":"Restaurant",
            "type":"Food & Drink"
        }
    ],
    "sg:phone":"+1 952 544 2808",
    "sg:postcode":"55305",
    "sg:province":"MN",
    "sg:tags":[
        "eating"
    ],
    "wof:name":"Wanderers Garden",
    "wof:placetype":"venue"
},
  "geometry": {"coordinates":[-93.450795,44.97059],"type":"Point"}
}