{
  "type": "Feature",
  "properties": {
    "iso:country":"US",
    "sg:address":"2001 W Lincoln Ave",
    "sg:city":"Fergus Falls",
    "sg:classifiers":[
        {
            "category":"Health Services",
            "subcategory":"Doctor",
            "type":"Services"
        }
    ],
    "sg:phone":"+1 218 739 5281",
    "sg:postcode":"56537",
    "sg:province":"MN",
    "sg:tags":[
        "a",
        "medical",
        "clinic",
        "as",
        "operates"
    ],
    "wof:name":"Westridge Mall Clinic",
    "wof:placetype":"venue"
},
  "geometry": {"coordinates":[-96.110934,46.288393],"type":"Point"}
}