{
  "type": "Feature",
  "properties": {
    "iso:country":"US",
    "sg:address":"122 2nd St NW",
    "sg:city":"Faribault",
    "sg:classifiers":[
        {
            "category":"Government",
            "subcategory":"Fire Station",
            "type":"Public Place"
        }
    ],
    "sg:phone":"+1 507 334 8773",
    "sg:postcode":"55021",
    "sg:province":"MN",
    "sg:tags":[
        "department",
        "protection"
    ],
    "wof:name":"Faribault Fire Department",
    "wof:placetype":"venue"
},
  "geometry": {"coordinates":[-93.271201,44.29257],"type":"Point"}
}