{
  "type": "Feature",
  "properties": {
    "addr:full":"1750 Tower Blvd Ste 209 Victoria MN 55386",
    "addr:housenumber":"1750",
    "addr:postcode":"55386",
    "addr:street":"Tower Blvd Ste 209",
    "iso:country":"US",
    "sg:address":"1750 Tower Blvd Ste 209",
    "sg:city":"Victoria",
    "sg:classifiers":[
        {
            "category":"Banks & Credit Unions",
            "subcategory":"Atm",
            "type":"Services"
        }
    ],
    "sg:phone":"+1 952 443 4004",
    "sg:postcode":"55386",
    "sg:province":"MN",
    "sg:tags":[
        "bankruptcy"
    ],
    "sg:website":"meclawfirm.com",
    "wof:name":"Czuchry Law Firm Llc",
    "wof:placetype":"venue"
},
  "geometry": {"coordinates":[-93.66152200000001,44.859433],"type":"Point"}
}