{
  "type": "Feature",
  "properties": {
    "iso:country":"US",
    "sg:address":"38203 Maple Valley Ln",
    "sg:city":"Cohasset",
    "sg:classifiers":[
        {
            "category":"Professional",
            "subcategory":"Computer Services",
            "type":"Services"
        }
    ],
    "sg:phone":"+1 218 327 8960",
    "sg:postcode":"55721",
    "sg:province":"MN",
    "wof:name":"P C Rescue",
    "wof:placetype":"venue"
},
  "geometry": {"coordinates":[-93.66708,47.135263],"type":"Point"}
}