{
  "type": "Feature",
  "properties": {
    "addr:full":"19170 Jasper St NW Anoka MN 55303",
    "addr:housenumber":"19170",
    "addr:postcode":"55303",
    "addr:street":"Jasper St Nw",
    "iso:country":"US",
    "sg:address":"19170 Jasper St NW",
    "sg:city":"Anoka",
    "sg:classifiers":[
        {
            "category":"Professional",
            "subcategory":"Engineering",
            "type":"Services"
        },
        {
            "category":"Home & Garden",
            "subcategory":"Building Materials",
            "type":"Retail Goods"
        },
        {
            "category":"Building & Trades",
            "subcategory":"Construction",
            "type":"Services"
        },
        {
            "category":"Building & Trades",
            "subcategory":"Electrical",
            "type":"Services"
        },
        {
            "category":"Utilities",
            "subcategory":"Sewage",
            "type":"Services"
        }
    ],
    "sg:phone":"+1 763 753 6623",
    "sg:postcode":"55303",
    "sg:province":"MN",
    "sg:tags":[
        "repair",
        "systems-cleaning",
        "furnace",
        "tank",
        "septic",
        "supply",
        "systems-repairing",
        "specialty",
        "system",
        "equipment",
        "furnaces-heating",
        "part",
        "ventilating",
        "contractor",
        "heating",
        "air conditioning"
    ],
    "sg:website":"http://find.trane.com/tcs-dealer-413639?utm_source=YP&utm_medium=banner&utm_campaign=TL",
    "wof:name":"Air Comfort Htg & A/C Inc.",
    "wof:placetype":"venue"
},
  "geometry": {"coordinates":[-93.44445899999999,45.317903],"type":"Point"}
}