{
  "type": "Feature",
  "properties": {
    "iso:country":"US",
    "sg:address":"6824 Old Viking Blvd NW",
    "sg:city":"Anoka",
    "sg:classifiers":[
        {
            "category":"Farming",
            "subcategory":"Farm",
            "type":"Manufacturing & Wholesale Goods"
        }
    ],
    "sg:phone":"+1 763 753 1476",
    "sg:postcode":"55303",
    "sg:province":"MN",
    "sg:tags":[
        "livestock",
        "crop"
    ],
    "wof:name":"Leon Swanson",
    "wof:placetype":"venue"
},
  "geometry": {"coordinates":[-93.44006899999999,45.33322],"type":"Point"}
}