{
  "type": "Feature",
  "properties": {
    "addr:full":"306 S East St Caledonia MN 55921",
    "addr:housenumber":"306",
    "addr:postcode":"55921",
    "addr:street":"S East St",
    "iso:country":"US",
    "sg:address":"306 S East St",
    "sg:city":"Caledonia",
    "sg:classifiers":[
        {
            "category":"Real Estate",
            "subcategory":"Real Estate Operator",
            "type":"Services"
        }
    ],
    "sg:phone":"+1 507 725 2797",
    "sg:postcode":"55921",
    "sg:province":"MN",
    "sg:tags":[
        "building",
        "apartment"
    ],
    "wof:name":"Whispering Pines",
    "wof:placetype":"venue"
},
  "geometry": {"coordinates":[-91.492515,43.632743],"type":"Point"}
}