{
  "type": "Feature",
  "properties": {
    "addr:full":"6359 Maple Grove Rd Cloquet MN 55720",
    "addr:housenumber":"6359",
    "addr:postcode":"55720",
    "addr:street":"Maple Grove Rd",
    "iso:country":"US",
    "sg:address":"6359 Maple Grove Rd",
    "sg:city":"Cloquet",
    "sg:classifiers":[
        {
            "category":"Wholesale",
            "subcategory":"Non-durable Goods",
            "type":"Manufacturing & Wholesale Goods"
        }
    ],
    "sg:phone":"+1 218 729 5208",
    "sg:postcode":"55720",
    "sg:province":"MN",
    "wof:name":"7th Heaven Gifts & Cllctbls",
    "wof:placetype":"venue"
},
  "geometry": {"coordinates":[-92.34954999999999,46.808174],"type":"Point"}
}