{
  "type": "Feature",
  "properties": {
    "iso:country":"US",
    "sg:address":"314 Clifton Ave",
    "sg:city":"Minneapolis",
    "sg:classifiers":[
        {
            "category":"Professional",
            "subcategory":"Employment Agencies",
            "type":"Services"
        }
    ],
    "sg:phone":"+1 612 871 6900",
    "sg:postcode":"55403",
    "sg:province":"MN",
    "wof:name":"Myers Search",
    "wof:placetype":"venue"
},
  "geometry": {"coordinates":[-93.283298,44.965877],"type":"Point"}
}