{
  "type": "Feature",
  "properties": {
    "addr:full":"14142 110th St Glencoe MN 55336",
    "addr:housenumber":"14142",
    "addr:postcode":"55336",
    "addr:street":"110Th St",
    "iso:country":"US",
    "sg:address":"14142 110th St",
    "sg:city":"Glencoe",
    "sg:classifiers":[
        {
            "category":"Wholesale",
            "subcategory":"Durable Goods & Equipment",
            "type":"Manufacturing & Wholesale Goods"
        }
    ],
    "sg:phone":"+1 320 864 5389",
    "sg:postcode":"55336",
    "sg:province":"MN",
    "sg:tags":[
        "professional",
        "recreational",
        "vehicle"
    ],
    "wof:name":"Performance Engineering",
    "wof:placetype":"venue"
},
  "geometry": {"coordinates":[-94.27464999999999,44.775745],"type":"Point"}
}