{
  "type": "Feature",
  "properties": {
    "iso:country":"US",
    "sg:address":"8731 Girard Ave S",
    "sg:city":"Minneapolis",
    "sg:classifiers":[
        {
            "category":"Professional",
            "subcategory":"Computer Services",
            "type":"Services"
        }
    ],
    "sg:phone":"+1 952 884 3847",
    "sg:postcode":"55420",
    "sg:province":"MN",
    "sg:tags":[
        "consultant",
        "designer"
    ],
    "wof:name":"T L Compu Svc",
    "wof:placetype":"venue"
},
  "geometry": {"coordinates":[-93.297185,44.843072],"type":"Point"}
}