{
  "type": "Feature",
  "properties": {
    "addr:full":"403 Oppegard Ave NW Twin Valley MN 56584",
    "addr:housenumber":"403",
    "addr:postcode":"56584",
    "addr:street":"Oppegard Ave Nw",
    "iso:country":"US",
    "sg:address":"403 Oppegard Ave NW",
    "sg:city":"Twin Valley",
    "sg:classifiers":[
        {
            "category":"Retail",
            "subcategory":"Laundry & Dry Cleaning",
            "type":"Services"
        }
    ],
    "sg:phone":"+1 218 584 8333",
    "sg:postcode":"56584",
    "sg:province":"MN",
    "sg:tags":[
        "cleaners",
        "rug",
        "carpet"
    ],
    "wof:name":"Mervs Carpet & Tile Floor Cle",
    "wof:placetype":"venue"
},
  "geometry": {"coordinates":[-96.26769899999999,47.264671],"type":"Point"}
}