{
  "type": "Feature",
  "properties": {
    "iso:country":"US",
    "sg:address":"6415 Long Bow Trl NW",
    "sg:city":"Walker",
    "sg:classifiers":[
        {
            "category":"Manufacturing",
            "subcategory":"Printing",
            "type":"Manufacturing & Wholesale Goods"
        }
    ],
    "sg:phone":"+1 218 547 4973",
    "sg:postcode":"56484",
    "sg:province":"MN",
    "sg:tags":[
        "publisher",
        "software"
    ],
    "wof:name":"Gravitech Development",
    "wof:placetype":"venue"
},
  "geometry": {"coordinates":[-94.624746,47.172792],"type":"Point"}
}