{
  "type": "Feature",
  "properties": {
    "addr:full":"10852 Cedar Beach Dr NW Oronoco MN 55960",
    "addr:housenumber":"10852",
    "addr:postcode":"55960",
    "addr:street":"Cedar Beach Dr Nw",
    "iso:country":"US",
    "sg:address":"10852 Cedar Beach Dr NW",
    "sg:city":"Oronoco",
    "sg:classifiers":[
        {
            "category":"Shopping",
            "type":"Retail Goods"
        }
    ],
    "sg:phone":"+1 507 367 4644",
    "sg:postcode":"55960",
    "sg:province":"MN",
    "sg:tags":[
        "merchandise"
    ],
    "wof:name":"Zumbro Valley Rabbitry",
    "wof:placetype":"venue"
},
  "geometry": {"coordinates":[-92.46487999999999,44.160066],"type":"Point"}
}