{
  "type": "Feature",
  "properties": {
    "addr:full":"12612 360th St Eagle Bend MN 56446",
    "addr:housenumber":"12612",
    "addr:postcode":"56446",
    "addr:street":"360Th St",
    "iso:country":"US",
    "sg:address":"12612 360th St",
    "sg:city":"Eagle Bend",
    "sg:classifiers":[
        {
            "category":"Farming",
            "subcategory":"Dairy Farm",
            "type":"Manufacturing & Wholesale Goods"
        }
    ],
    "sg:phone":"+1 218 738 5438",
    "sg:postcode":"56446",
    "sg:province":"MN",
    "wof:name":"Zeilder Bruce Farmer",
    "wof:placetype":"venue"
},
  "geometry": {"coordinates":[-95.098699,46.150487],"type":"Point"}
}