{
  "type": "Feature",
  "properties": {
    "iso:country":"US",
    "sg:address":"1210 Riverside Dr",
    "sg:city":"Detroit Lakes",
    "sg:classifiers":[
        {
            "category":"Social Services",
            "subcategory":"Child Care",
            "type":"Services"
        }
    ],
    "sg:phone":"+1 218 847 6460",
    "sg:postcode":"56501",
    "sg:province":"MN",
    "sg:tags":[
        "daycare",
        "provider"
    ],
    "wof:name":"Thomas Olson",
    "wof:placetype":"venue"
},
  "geometry": {"coordinates":[-95.823674,46.825011],"type":"Point"}
}