{
  "type": "Feature",
  "properties": {
    "iso:country":"US",
    "sg:address":"2640 Oakland Rd",
    "sg:city":"Hopkins",
    "sg:classifiers":[
        {
            "category":"Professional",
            "type":"Services"
        }
    ],
    "sg:phone":"+1 952 591 1554",
    "sg:postcode":"55305",
    "sg:province":"MN",
    "wof:name":"Denise Rebers",
    "wof:placetype":"venue"
},
  "geometry": {"coordinates":[-93.451492,44.953284],"type":"Point"}
}