{
  "type": "Feature",
  "properties": {
    "addr:full":"5000 Quail Ave N Minneapolis MN 55429",
    "addr:housenumber":"5000",
    "addr:postcode":"55429",
    "addr:street":"Quail Ave N",
    "iso:country":"US",
    "sg:address":"5000 Quail Ave N",
    "sg:city":"Minneapolis",
    "sg:classifiers":[
        {
            "category":"Manufacturing",
            "subcategory":"Printing",
            "type":"Manufacturing & Wholesale Goods"
        }
    ],
    "sg:phone":"+1 763 533 0474",
    "sg:postcode":"55429",
    "sg:province":"MN",
    "sg:tags":[
        "advisory",
        "investment",
        "periodical"
    ],
    "wof:name":"Hidden Value Stock",
    "wof:placetype":"venue"
},
  "geometry": {"coordinates":[-93.343605,45.045424],"type":"Point"}
}