{
  "type": "Feature",
  "properties": {
    "iso:country":"US",
    "sg:address":"10750 55th Pl N",
    "sg:city":"Minneapolis",
    "sg:classifiers":[
        {
            "category":"Organizations",
            "subcategory":"Membership Organization",
            "type":"Services"
        }
    ],
    "sg:phone":"+1 612 607 7266",
    "sg:postcode":"55442",
    "sg:province":"MN",
    "wof:name":"Groot Virginia A Foundation",
    "wof:placetype":"venue"
},
  "geometry": {"coordinates":[-93.416631,45.054189],"type":"Point"}
}