{
  "type": "Feature",
  "properties": {
    "iso:country":"US",
    "sg:address":"122 Forest Ave",
    "sg:city":"Mahtomedi",
    "sg:classifiers":[
        {
            "category":"Professional",
            "subcategory":"Research",
            "type":"Services"
        }
    ],
    "sg:phone":"+1 651 426 0880",
    "sg:postcode":"55115",
    "sg:province":"MN",
    "sg:tags":[
        "environmental",
        "ecological"
    ],
    "wof:name":"PBI Environmental Svc",
    "wof:placetype":"venue"
},
  "geometry": {"coordinates":[-92.957155,45.057575],"type":"Point"}
}