{
  "type": "Feature",
  "properties": {
    "addr:full":"7460 Unity Dr SW Kensington MN 56343",
    "addr:housenumber":"7460",
    "addr:postcode":"56343",
    "addr:street":"Unity Dr Sw",
    "iso:country":"US",
    "sg:address":"7460 Unity Dr SW",
    "sg:city":"Kensington",
    "sg:classifiers":[
        {
            "category":"Personal",
            "type":"Services"
        },
        {
            "category":"Building & Trades",
            "subcategory":"Construction",
            "type":"Services"
        }
    ],
    "sg:phone":"+1 320 986 2943",
    "sg:postcode":"56343",
    "sg:province":"MN",
    "sg:tags":[
        "handyman"
    ],
    "wof:name":"Dave Gosch Handyman Service",
    "wof:placetype":"venue"
},
  "geometry": {"coordinates":[-95.737711,45.824665],"type":"Point"}
}