{
  "type": "Feature",
  "properties": {
    "iso:country":"US",
    "sg:address":"6004 Highland St",
    "sg:city":"Duluth",
    "sg:classifiers":[
        {
            "category":"Building & Trades",
            "subcategory":"Construction",
            "type":"Services"
        }
    ],
    "sg:phone":"+1 218 590 5123",
    "sg:postcode":"55807",
    "sg:province":"MN",
    "sg:tags":[
        "repair",
        "general",
        "contractor"
    ],
    "wof:name":"C & E Upholstery & Restoration",
    "wof:placetype":"venue"
},
  "geometry": {"coordinates":[-92.172167,46.748298],"type":"Point"}
}