{
  "type": "Feature",
  "properties": {
    "addr:full":"140 Cedar Lake Rd S Minneapolis MN 55405",
    "addr:housenumber":"140",
    "addr:postcode":"55405",
    "addr:street":"Cedar Lake Rd",
    "iso:country":"US",
    "sg:address":"140 Cedar Lake Rd S",
    "sg:city":"Minneapolis",
    "sg:classifiers":[
        {
            "category":"Social Services",
            "subcategory":"Child Care",
            "type":"Services"
        },
        {
            "category":"Personal",
            "type":"Services"
        }
    ],
    "sg:phone":"+1 612 374 5226",
    "sg:postcode":"55405",
    "sg:province":"MN",
    "sg:tags":[
        "day"
    ],
    "wof:name":"Jaki's Daycare Inc",
    "wof:placetype":"venue"
},
  "geometry": {"coordinates":[-93.305126,44.975605],"type":"Point"}
}