{
  "type": "Feature",
  "properties": {
    "iso:country":"US",
    "sg:address":"214 E Blue Earth Ave",
    "sg:city":"Fairmont",
    "sg:classifiers":[
        {
            "category":"Insurance",
            "subcategory":"Insurance Agent",
            "type":"Services"
        }
    ],
    "sg:phone":"+1 507 238 9417",
    "sg:postcode":"56031",
    "sg:province":"MN",
    "wof:name":"AFLAC",
    "wof:placetype":"venue"
},
  "geometry": {"coordinates":[-94.460705,43.652072],"type":"Point"}
}