{
  "type": "Feature",
  "properties": {
    "iso:country":"US",
    "sg:address":"141 9th Ave N",
    "sg:city":"South Saint Paul",
    "sg:classifiers":[
        {
            "category":"Retail",
            "subcategory":"Repair Shop",
            "type":"Services"
        }
    ],
    "sg:phone":"+1 651 552 8167",
    "sg:postcode":"55075",
    "sg:province":"MN",
    "wof:name":"Wallaces Sno Mower Outdoor",
    "wof:placetype":"venue"
},
  "geometry": {"coordinates":[-93.04503,44.890744],"type":"Point"}
}