{
  "type": "Feature",
  "properties": {
    "iso:country":"US",
    "sg:address":"6545 France Ave S",
    "sg:city":"Minneapolis",
    "sg:classifiers":[
        {
            "category":"Health Services",
            "subcategory":"Doctor",
            "type":"Services"
        }
    ],
    "sg:phone":"+1 952 925 2525",
    "sg:postcode":"55435",
    "sg:province":"MN",
    "sg:tags":[
        "oral"
    ],
    "wof:name":"Metropltnral Mxllfcial Srgeons",
    "wof:placetype":"venue"
},
  "geometry": {"coordinates":[-93.328863,44.884544],"type":"Point"}
}