{
  "type": "Feature",
  "properties": {
    "iso:country":"US",
    "sg:address":"1402 Broadway St",
    "sg:city":"Alexandria",
    "sg:classifiers":[
        {
            "category":"Personal",
            "subcategory":"Beauty Salon",
            "type":"Services"
        }
    ],
    "sg:phone":"+1 320 763 5151",
    "sg:postcode":"56308",
    "sg:province":"MN",
    "wof:name":"Great Clips",
    "wof:placetype":"venue"
},
  "geometry": {"coordinates":[-95.377814,45.876574],"type":"Point"}
}