{
  "type": "Feature",
  "properties": {
    "addr:full":"2960 Yorkton Blvd Little Canada MN 55117",
    "addr:postcode":"2960;55117",
    "addr:street":"Yorkton Blvd",
    "iso:country":"US",
    "sg:address":"2960 Yorkton Blvd",
    "sg:city":"Little Canada",
    "sg:classifiers":[
        {
            "category":"Wholesale",
            "subcategory":"Scrap",
            "type":"Manufacturing & Wholesale Goods"
        }
    ],
    "sg:phone":"+1 651 766 7422",
    "sg:postcode":"55117",
    "sg:province":"MN",
    "sg:tags":[
        "recycling",
        "center"
    ],
    "sg:website":"www.retrofitcompanies.com",
    "wof:name":"Retrofit Recycling Inc",
    "wof:placetype":"venue"
},
  "geometry": {"coordinates":[-93.100189,45.030399],"type":"Point"}
}