{
  "type": "Feature",
  "properties": {
    "addr:full":"1450 Northland Dr Mendota Heights MN 55120",
    "addr:housenumber":"1450",
    "addr:postcode":"55120",
    "addr:street":"Northland Dr",
    "iso:country":"US",
    "sg:address":"1450 Northland Dr",
    "sg:city":"Mendota Heights",
    "sg:classifiers":[
        {
            "category":"Manufacturing",
            "subcategory":"Paper Products",
            "type":"Manufacturing & Wholesale Goods"
        }
    ],
    "sg:phone":"+1 651 686 7044",
    "sg:postcode":"55120",
    "sg:province":"MN",
    "sg:tags":[
        "par",
        "gift",
        "creates",
        "bag",
        "produce",
        "designed",
        "market"
    ],
    "sg:website":"www.garveninc.com",
    "wof:name":"Garven Inc",
    "wof:placetype":"venue"
},
  "geometry": {"coordinates":[-93.167314,44.863558],"type":"Point"}
}