{
  "type": "Feature",
  "properties": {
    "addr:full":"1307 3rd St NE Roseau MN 56751",
    "addr:housenumber":"1307",
    "addr:postcode":"56751",
    "addr:street":"3Rd St Ne",
    "iso:country":"US",
    "sg:address":"1307 3rd St NE",
    "sg:city":"Roseau",
    "sg:classifiers":[
        {
            "category":"Professional",
            "subcategory":"Business Services",
            "type":"Services"
        }
    ],
    "sg:phone":"+1 218 463 0095",
    "sg:postcode":"56751",
    "sg:province":"MN",
    "wof:name":"Roseau Business Plaza",
    "wof:placetype":"venue"
},
  "geometry": {"coordinates":[-95.741939,48.84803],"type":"Point"}
}