{
  "type": "Feature",
  "properties": {
    "addr:full":"25717 Brekke Lake Rd Fergus Falls MN 56537",
    "addr:postcode":"25717;56537",
    "addr:street":"Lake Rd",
    "iso:country":"US",
    "sg:address":"25717 Brekke Lake Rd",
    "sg:city":"Fergus Falls",
    "sg:classifiers":[
        {
            "category":"Organizations",
            "subcategory":"Religious Organization",
            "type":"Services"
        }
    ],
    "sg:phone":"+1 218 739 9291",
    "sg:postcode":"56537",
    "sg:province":"MN",
    "wof:name":"Aid Assoc For Lutherans",
    "wof:placetype":"venue"
},
  "geometry": {"coordinates":[-95.960632,46.339992],"type":"Point"}
}