{
  "type": "Feature",
  "properties": {
    "iso:country":"US",
    "sg:address":"224 W Lake St",
    "sg:city":"Waconia",
    "sg:classifiers":[
        {
            "category":"Building & Trades",
            "subcategory":"Construction",
            "type":"Services"
        }
    ],
    "sg:phone":"+1 952 442 1119",
    "sg:postcode":"55387",
    "sg:province":"MN",
    "sg:tags":[
        "designer"
    ],
    "wof:name":"F C Foss Assoc Inc",
    "wof:placetype":"venue"
},
  "geometry": {"coordinates":[-93.789384,44.851642],"type":"Point"}
}