{
  "type": "Feature",
  "properties": {
    "iso:country":"US",
    "sg:address":"56 E 6th St",
    "sg:city":"Saint Paul",
    "sg:classifiers":[
        {
            "category":"Shopping",
            "subcategory":"Gifts & Souvenirs",
            "type":"Retail Goods"
        }
    ],
    "sg:phone":"+1 651 222 0266",
    "sg:postcode":"55101",
    "sg:province":"MN",
    "sg:tags":[
        "cards",
        "collectible",
        "fine"
    ],
    "wof:name":"Karens Hallmark",
    "wof:placetype":"venue"
},
  "geometry": {"coordinates":[-93.093082,44.947387],"type":"Point"}
}