{
  "type": "Feature",
  "properties": {
    "addr:full":"1500 Franklin Ave SE Minneapolis MN 55414",
    "addr:housenumber":"1500",
    "addr:postcode":"55414",
    "addr:street":"Franklin Ave Se",
    "iso:country":"US",
    "sg:address":"1500 Franklin Ave SE",
    "sg:city":"Minneapolis",
    "sg:classifiers":[
        {
            "category":"Organizations",
            "subcategory":"Religious Organization",
            "type":"Services"
        }
    ],
    "sg:phone":"+1 612 339 3023",
    "sg:postcode":"55414",
    "sg:province":"MN",
    "sg:tags":[
        "church"
    ],
    "sg:website":"www.cabrinimn.org",
    "wof:name":"Saint Frances Cabrini Church",
    "wof:placetype":"venue"
},
  "geometry": {"coordinates":[-93.216599,44.964698],"type":"Point"}
}