{
  "type": "Feature",
  "properties": {
    "iso:country":"US",
    "sg:address":"710 11th St E",
    "sg:city":"Glencoe",
    "sg:classifiers":[
        {
            "category":"Shopping",
            "subcategory":"Pharmacy",
            "type":"Retail Goods"
        }
    ],
    "sg:phone":"+1 320 864 5192",
    "sg:postcode":"55336",
    "sg:province":"MN",
    "sg:tags":[
        "shop",
        "drug",
        "store",
        "gift"
    ],
    "wof:name":"Snyder Drug Store",
    "wof:placetype":"venue"
},
  "geometry": {"coordinates":[-94.151831,44.769975],"type":"Point"}
}