{
  "type": "Feature",
  "properties": {
    "addr:full":"2497 Highway 7 Excelsior MN 55331",
    "addr:housenumber":"2497",
    "addr:postcode":"55331",
    "addr:street":"Highway 7",
    "iso:country":"US",
    "sg:address":"2497 Highway 7",
    "sg:city":"Excelsior",
    "sg:classifiers":[
        {
            "category":"Shopping",
            "subcategory":"Gifts & Souvenirs",
            "type":"Retail Goods"
        },
        {
            "category":"Home & Garden",
            "subcategory":"Home Furnishings",
            "type":"Retail Goods"
        },
        {
            "category":"Shopping",
            "subcategory":"Discount & Variety Stores",
            "type":"Retail Goods"
        }
    ],
    "sg:phone":"+1 952 943 2267",
    "sg:postcode":"55331",
    "sg:province":"MN",
    "sg:tags":[
        "housewares",
        "shop"
    ],
    "sg:website":"http://www.tuesdaymorning.com",
    "wof:name":"Tuesday Morning",
    "wof:placetype":"venue"
},
  "geometry": {"coordinates":[-93.558708,44.901562],"type":"Point"}
}