{
  "type": "Feature",
  "properties": {
    "iso:country":"US",
    "sg:address":"2001 E Main St",
    "sg:city":"Albert Lea",
    "sg:classifiers":[
        {
            "category":"Retail",
            "subcategory":"Auto Rental",
            "type":"Services"
        }
    ],
    "sg:phone":"+1 507 373 8336",
    "sg:postcode":"56007",
    "sg:province":"MN",
    "sg:tags":[
        "truck"
    ],
    "wof:name":"Ryder Truck Rental One WA",
    "wof:placetype":"venue"
},
  "geometry": {"coordinates":[-93.34302099999999,43.653144],"type":"Point"}
}