{
  "type": "Feature",
  "properties": {
    "addr:full":"5005 Minnetonka Blvd St Louis Park MN 55416",
    "addr:housenumber":"5005",
    "addr:postcode":"55416",
    "addr:street":"Minnetonka Blvd",
    "iso:country":"US",
    "sg:address":"5005 Minnetonka Blvd",
    "sg:city":"St Louis Park",
    "sg:classifiers":[
        {
            "category":"Government",
            "subcategory":"Fire Station",
            "type":"Public Place"
        }
    ],
    "sg:phone":"+1 952 924 2595",
    "sg:postcode":"55416",
    "sg:province":"MN",
    "sg:tags":[
        "department"
    ],
    "sg:website":"www.stlouispark.org",
    "wof:name":"St Louis Park Fire Dept",
    "wof:placetype":"venue"
},
  "geometry": {"coordinates":[-93.34347,44.948397],"type":"Point"}
}