{
  "type": "Feature",
  "properties": {
    "addr:full":"2456 Arkwright St St Paul MN 55117",
    "addr:housenumber":"2456",
    "addr:postcode":"55117",
    "addr:street":"Arkwright St",
    "iso:country":"US",
    "sg:address":"2456 Arkwright St",
    "sg:city":"St Paul",
    "sg:classifiers":[
        {
            "category":"Social Services",
            "subcategory":"Child Care",
            "type":"Services"
        },
        {
            "category":"Education",
            "subcategory":"Vocational School",
            "type":"Public Place"
        }
    ],
    "sg:phone":"+1 651 221 0587",
    "sg:postcode":"55117",
    "sg:province":"MN",
    "sg:tags":[
        "placement",
        "nanny"
    ],
    "wof:name":"Nanny Professionals",
    "wof:placetype":"venue"
},
  "geometry": {"coordinates":[-93.08320999999999,45.015332],"type":"Point"}
}