{
  "type": "Feature",
  "properties": {
    "addr:full":"584 23rd Ave NW Saint Paul MN 55112",
    "addr:housenumber":"584",
    "addr:postcode":"55112",
    "addr:street":"23Rd Ave Nw",
    "iso:country":"US",
    "sg:address":"584 23rd Ave NW",
    "sg:city":"Saint Paul",
    "sg:classifiers":[
        {
            "category":"Wholesale",
            "subcategory":"Chemicals & Plastics",
            "type":"Manufacturing & Wholesale Goods"
        }
    ],
    "sg:phone":"+1 651 633 5751",
    "sg:postcode":"55112",
    "sg:province":"MN",
    "wof:name":"Arnold Rudi",
    "wof:placetype":"venue"
},
  "geometry": {"coordinates":[-93.215988,45.059438],"type":"Point"}
}