{
  "type": "Feature",
  "properties": {
    "addr:full":"4331 Metcalf Dr Saint Paul MN 55122",
    "addr:housenumber":"4331",
    "addr:postcode":"55122",
    "addr:street":"Metcalf Dr",
    "iso:country":"US",
    "sg:address":"4331 Metcalf Dr",
    "sg:city":"Saint Paul",
    "sg:classifiers":[
        {
            "category":"Professional",
            "subcategory":"Business Services",
            "type":"Services"
        }
    ],
    "sg:phone":"+1 651 894 3914",
    "sg:postcode":"55122",
    "sg:province":"MN",
    "wof:name":"Inland Trading Co",
    "wof:placetype":"venue"
},
  "geometry": {"coordinates":[-93.22509599999999,44.800587],"type":"Point"}
}