{
  "type": "Feature",
  "properties": {
    "addr:full":"15570 Scandia Trl N Scandia MN 55073",
    "addr:postcode":"15570;55073",
    "addr:street":"Scandia Trl N Scandia",
    "iso:country":"US",
    "sg:address":"15570 Scandia Trl N",
    "sg:city":"Scandia",
    "sg:classifiers":[
        {
            "category":"Wholesale",
            "subcategory":"Machinery & Supplies",
            "type":"Manufacturing & Wholesale Goods"
        }
    ],
    "sg:phone":"+1 651 433 4280",
    "sg:postcode":"55073",
    "sg:province":"MN",
    "sg:tags":[
        "fire",
        "department",
        "equipment"
    ],
    "wof:name":"Kirvida Fire",
    "wof:placetype":"venue"
},
  "geometry": {"coordinates":[-92.793406,45.256591],"type":"Point"}
}