{
  "type": "Feature",
  "properties": {
    "iso:country":"US",
    "sg:address":"7839 Southtown Ctr",
    "sg:city":"Minneapolis",
    "sg:classifiers":[
        {
            "category":"Shopping",
            "subcategory":"Hobbies, Toys, & Games",
            "type":"Retail Goods"
        },
        {
            "category":"Shopping",
            "subcategory":"Crafts & Fabrics",
            "type":"Retail Goods"
        }
    ],
    "sg:phone":"+1 952 881 0287",
    "sg:postcode":"55431",
    "sg:province":"MN",
    "sg:tags":[
        "toy",
        "art",
        "store",
        "supply"
    ],
    "sg:website":"http://www.toysrus.com",
    "wof:name":"Toys \"R\" Us",
    "wof:placetype":"venue"
},
  "geometry": {"coordinates":[-93.301804,44.860944],"type":"Point"}
}