{
  "type": "Feature",
  "properties": {
    "iso:country":"US",
    "sg:address":"612 8th Ave SW",
    "sg:city":"Austin",
    "sg:classifiers":[
        {
            "category":"Retail",
            "subcategory":"Repair Shop",
            "type":"Services"
        }
    ],
    "sg:phone":"+1 507 437 6878",
    "sg:postcode":"55912",
    "sg:province":"MN",
    "wof:name":"Scotts T V Service",
    "wof:placetype":"venue"
},
  "geometry": {"coordinates":[-92.981126,43.659406],"type":"Point"}
}