{
  "type": "Feature",
  "properties": {
    "iso:country":"US",
    "sg:address":"2010 Adams St",
    "sg:city":"Mankato",
    "sg:phone":"+1 507 625 9070",
    "sg:postcode":"56001",
    "sg:province":"MN",
    "sg:website":"http://www.hy-vee.com",
    "wof:name":"Hy-Vee",
    "wof:placetype":"venue"
},
  "geometry": {"coordinates":[-93.946279,44.170454],"type":"Point"}
}