{
  "type": "Feature",
  "properties": {
    "addr:full":"2127 Cliff Rd Saint Paul MN 55122",
    "addr:housenumber":"2127",
    "addr:postcode":"55122",
    "addr:street":"Cliff Rd",
    "iso:country":"US",
    "sg:address":"2127 Cliff Rd",
    "sg:city":"Saint Paul",
    "sg:classifiers":[
        {
            "category":"Professional",
            "subcategory":"Employment Agencies",
            "type":"Services"
        }
    ],
    "sg:phone":"+1 651 405 1100",
    "sg:postcode":"55122",
    "sg:province":"MN",
    "sg:website":"www.accustaff.com",
    "wof:name":"Accustaff",
    "wof:placetype":"venue"
},
  "geometry": {"coordinates":[-93.215739,44.79038],"type":"Point"}
}