{
  "type": "Feature",
  "properties": {
    "addr:full":"11201 Utah Ave N Champlin MN 55316",
    "addr:housenumber":"11201",
    "addr:postcode":"55316",
    "addr:street":"Utah Ave N",
    "iso:country":"US",
    "sg:address":"11201 Utah Ave N",
    "sg:city":"Champlin",
    "sg:classifiers":[
        {
            "category":"Home & Garden",
            "subcategory":"Building Materials",
            "type":"Retail Goods"
        }
    ],
    "sg:phone":"+1 763 425 2227",
    "sg:postcode":"55316",
    "sg:province":"MN",
    "sg:tags":[
        "windows"
    ],
    "sg:website":"www.windowlite.com",
    "wof:name":"Window Lite Home Improvements",
    "wof:placetype":"venue"
},
  "geometry": {"coordinates":[-93.382063,45.158266],"type":"Point"}
}