{
  "type": "Feature",
  "properties": {
    "addr:full":"6375 395th St Rice MN 56367",
    "addr:housenumber":"6375",
    "addr:postcode":"56367",
    "addr:street":"395Th St",
    "iso:country":"US",
    "sg:address":"6375 395th St",
    "sg:city":"Rice",
    "sg:classifiers":[
        {
            "category":"Farming",
            "subcategory":"Dairy Farm",
            "type":"Manufacturing & Wholesale Goods"
        }
    ],
    "sg:phone":"+1 320 251 2269",
    "sg:postcode":"56367",
    "sg:province":"MN",
    "wof:name":"Slivnik Dairy",
    "wof:placetype":"venue"
},
  "geometry": {"coordinates":[-94.243427,45.695695],"type":"Point"}
}