{
  "type": "Feature",
  "properties": {
    "addr:full":"9122 Ketola Rd Britt MN 55710",
    "addr:postcode":"9122;55710",
    "addr:street":"Ketola Rd",
    "iso:country":"US",
    "sg:address":"9122 Ketola Rd",
    "sg:city":"Britt",
    "sg:classifiers":[
        {
            "category":"Building & Trades",
            "subcategory":"Construction",
            "type":"Services"
        }
    ],
    "sg:phone":"+1 218 749 2869",
    "sg:postcode":"55710",
    "sg:province":"MN",
    "sg:tags":[
        "general",
        "contractor"
    ],
    "wof:name":"A To Z Carpentry",
    "wof:placetype":"venue"
},
  "geometry": {"coordinates":[-92.649991,47.665674],"type":"Point"}
}