{
  "type": "Feature",
  "properties": {
    "addr:full":"8525 Cottonwood St NW Minneapolis MN 55433",
    "addr:housenumber":"8525",
    "addr:postcode":"55433",
    "addr:street":"Cottonwood St Nw",
    "iso:country":"US",
    "sg:address":"8525 Cottonwood St NW",
    "sg:city":"Minneapolis",
    "sg:classifiers":[
        {
            "category":"Bars & Pubs",
            "type":"Food & Drink"
        },
        {
            "category":"Bars & Pubs",
            "subcategory":"Sports Bar",
            "type":"Food & Drink"
        }
    ],
    "sg:phone":"+1 763 780 1585",
    "sg:postcode":"55433",
    "sg:province":"MN",
    "sg:tags":[
        "hall",
        "pool"
    ],
    "sg:website":"http://www.crssportsbar.com",
    "wof:name":"C R Billiards Sports Bar",
    "wof:placetype":"venue"
},
  "geometry": {"coordinates":[-93.27187000000001,45.124587],"type":"Point"}
}