{
  "type": "Feature",
  "properties": {
    "addr:full":"115 S Broad St Mankato MN 56001",
    "addr:housenumber":"115",
    "addr:postcode":"56001",
    "addr:street":"S Broad St",
    "iso:country":"US",
    "sg:address":"115 S Broad St",
    "sg:city":"Mankato",
    "sg:classifiers":[
        {
            "category":"Insurance",
            "subcategory":"Insurance Agent",
            "type":"Services"
        }
    ],
    "sg:phone":"+1 507 625 8121",
    "sg:postcode":"56001",
    "sg:province":"MN",
    "wof:name":"Anderson Insurance",
    "wof:placetype":"venue"
},
  "geometry": {"coordinates":[-94.000128,44.16601],"type":"Point"}
}