{
  "type": "Feature",
  "properties": {
    "addr:full":"21835 Hwy 371 Little Falls MN 56345",
    "addr:housenumber":"21835",
    "addr:postcode":"56345",
    "addr:street":"Hwy 371",
    "iso:country":"US",
    "sg:address":"21835 Hwy 371",
    "sg:city":"Little Falls",
    "sg:classifiers":[
        {
            "category":"Autos & Motor Vehicles",
            "subcategory":"Fuel & Gas Station",
            "type":"Retail Goods"
        }
    ],
    "sg:phone":"+1 320 632 5826",
    "sg:postcode":"56345",
    "sg:province":"MN",
    "sg:tags":[
        "grocery",
        "station",
        "gasoline"
    ],
    "wof:name":"Country Store",
    "wof:placetype":"venue"
},
  "geometry": {"coordinates":[-94.328186,46.077939],"type":"Point"}
}