{
  "type": "Feature",
  "properties": {
    "addr:full":"444 1st Ave E Shakopee MN 55379",
    "addr:housenumber":"444",
    "addr:postcode":"55379",
    "addr:street":"1St Ave E",
    "iso:country":"US",
    "sg:address":"444 1st Ave E",
    "sg:city":"Shakopee",
    "sg:classifiers":[
        {
            "category":"Autos & Motor Vehicles",
            "subcategory":"Fuel & Gas Station",
            "type":"Retail Goods"
        }
    ],
    "sg:phone":"+1 952 445 4450",
    "sg:postcode":"55379",
    "sg:province":"MN",
    "sg:tags":[
        "convenience",
        "store"
    ],
    "sg:website":"www.holidaystationstores.com",
    "wof:name":"Holiday Stationstores",
    "wof:placetype":"venue"
},
  "geometry": {"coordinates":[-93.521749,44.799042],"type":"Point"}
}