{
  "type": "Feature",
  "properties": {
    "iso:country":"US",
    "sg:address":"7493 147th St W Ste 100",
    "sg:city":"Saint Paul",
    "sg:classifiers":[
        {
            "category":"Health Services",
            "subcategory":"Dentist",
            "type":"Services"
        }
    ],
    "sg:phone":"+1 952 432 7145",
    "sg:postcode":"55124",
    "sg:province":"MN",
    "wof:name":"Fitzsimmons Carl B",
    "wof:placetype":"venue"
},
  "geometry": {"coordinates":[-93.216044,44.735073],"type":"Point"}
}