{
  "type": "Feature",
  "properties": {
    "iso:country":"US",
    "sg:address":"2600 E Lake St",
    "sg:city":"Minneapolis",
    "sg:classifiers":[
        {
            "category":"Shopping",
            "subcategory":"Clothing, Apparel, & Fashions",
            "type":"Retail Goods"
        },
        {
            "category":"Shopping",
            "subcategory":"Shoes",
            "type":"Retail Goods"
        }
    ],
    "sg:phone":"+1 612 728 0928",
    "sg:postcode":"55406",
    "sg:province":"MN",
    "sg:tags":[
        "accessory",
        "store",
        "women's"
    ],
    "sg:website":"www.payless.com",
    "wof:name":"Payless Shoesource",
    "wof:placetype":"venue"
},
  "geometry": {"coordinates":[-93.233902,44.948299],"type":"Point"}
}