{
  "type": "Feature",
  "properties": {
    "addr:full":"432 E University St Owatonna MN 55060",
    "addr:housenumber":"432",
    "addr:postcode":"55060",
    "addr:street":"E University St",
    "iso:country":"US",
    "sg:address":"432 E University St",
    "sg:city":"Owatonna",
    "sg:classifiers":[
        {
            "category":"Social Services",
            "subcategory":"Adult Care",
            "type":"Services"
        }
    ],
    "sg:phone":"+1 507 451 6272",
    "sg:postcode":"55060",
    "sg:province":"MN",
    "sg:tags":[
        "home",
        "group"
    ],
    "wof:name":"Rem-Woodvale Waiver Inc",
    "wof:placetype":"venue"
},
  "geometry": {"coordinates":[-93.217415,44.0785],"type":"Point"}
}