{
  "type": "Feature",
  "properties": {
    "iso:country":"US",
    "sg:address":"9030 Forestview Ln N",
    "sg:city":"Osseo",
    "sg:classifiers":[
        {
            "category":"Government",
            "subcategory":"Office",
            "type":"Public Place"
        }
    ],
    "sg:phone":"+1 763 509 5950",
    "sg:postcode":"55369",
    "sg:province":"MN",
    "sg:tags":[
        "works"
    ],
    "wof:name":"Public Works",
    "wof:placetype":"venue"
},
  "geometry": {"coordinates":[-93.429607,45.118731],"type":"Point"}
}