{
  "type": "Feature",
  "properties": {
    "iso:country":"US",
    "sg:address":"231 E 8th St",
    "sg:city":"Duluth",
    "sg:classifiers":[
        {
            "category":"Professional",
            "subcategory":"Computer Services",
            "type":"Services"
        }
    ],
    "sg:phone":"+1 218 720 5801",
    "sg:postcode":"55805",
    "sg:province":"MN",
    "sg:tags":[
        "internet"
    ],
    "wof:name":"Skypoint Communications Inc",
    "wof:placetype":"venue"
},
  "geometry": {"coordinates":[-92.103562,46.794921],"type":"Point"}
}