{
  "type": "Feature",
  "properties": {
    "iso:country":"US",
    "sg:address":"16222 Urbank St NE",
    "sg:city":"Andover",
    "sg:classifiers":[
        {
            "category":"Home & Garden",
            "subcategory":"Garden Supply",
            "type":"Retail Goods"
        }
    ],
    "sg:phone":"+1 763 434 0792",
    "sg:postcode":"55304",
    "sg:province":"MN",
    "sg:tags":[
        "nurseryman"
    ],
    "wof:name":"Northwoods Nursery & Lawn",
    "wof:placetype":"venue"
},
  "geometry": {"coordinates":[-93.20733300000001,45.264974],"type":"Point"}
}