{
  "type": "Feature",
  "properties": {
    "addr:full":"431 S 7th St Ste 2540 Minneapolis MN 55415",
    "addr:housenumber":"431",
    "addr:postcode":"2540;55415",
    "addr:street":"S 7Th St Ste",
    "iso:country":"US",
    "sg:address":"431 S 7th St Ste 2540",
    "sg:city":"Minneapolis",
    "sg:classifiers":[
        {
            "category":"Social Services",
            "type":"Services"
        },
        {
            "category":"Organizations",
            "subcategory":"Non-profit Organization",
            "type":"Services"
        }
    ],
    "sg:phone":"+1 612 333 7740",
    "sg:postcode":"55415",
    "sg:province":"MN",
    "sg:tags":[
        "service/non-profit",
        "community"
    ],
    "sg:website":"http://www.serveminnesota.org",
    "wof:name":"Serveminnesota",
    "wof:placetype":"venue"
},
  "geometry": {"coordinates":[-93.26638699999999,44.974404],"type":"Point"}
}