{
  "type": "Feature",
  "properties": {
    "addr:full":"88 S 6th St Minneapolis MN 55402",
    "addr:housenumber":"88",
    "addr:postcode":"55402",
    "addr:street":"S 6Th St",
    "iso:country":"US",
    "sg:address":"88 S 6th St",
    "sg:city":"Minneapolis",
    "sg:classifiers":[
        {
            "category":"Bars & Pubs",
            "subcategory":"Lounge",
            "type":"Food & Drink"
        }
    ],
    "sg:phone":"+1 612 333 4006",
    "sg:postcode":"55402",
    "sg:province":"MN",
    "sg:website":"www.westin.com",
    "wof:name":"Midland Bank Bar at Westin Hotel",
    "wof:placetype":"venue"
},
  "geometry": {"coordinates":[-93.270613,44.977508],"type":"Point"}
}