{
  "type": "Feature",
  "properties": {
    "iso:country":"US",
    "sg:address":"6190 Golden Hills Dr",
    "sg:city":"Minneapolis",
    "sg:classifiers":[
        {
            "category":"Professional",
            "subcategory":"Engineering",
            "type":"Services"
        }
    ],
    "sg:phone":"+1 763 591 5400",
    "sg:postcode":"55416",
    "sg:province":"MN",
    "sg:tags":[
        "consulting",
        "management",
        "arc"
    ],
    "sg:website":"www.hdrinc.com",
    "wof:name":"HDR Engineering Inc",
    "wof:placetype":"venue"
},
  "geometry": {"coordinates":[-93.35493099999999,44.972937],"type":"Point"}
}