{
  "type": "Feature",
  "properties": {
    "iso:country":"US",
    "sg:address":"2686 Rice St",
    "sg:city":"St Paul",
    "sg:classifiers":[
        {
            "category":"Personal",
            "subcategory":"Tanning Parlor",
            "type":"Services"
        }
    ],
    "sg:phone":"+1 651 490 7880",
    "sg:postcode":"55113",
    "sg:province":"MN",
    "sg:tags":[
        "salon"
    ],
    "wof:name":"Perfect Tan",
    "wof:placetype":"venue"
},
  "geometry": {"coordinates":[-93.10602799999999,45.022022],"type":"Point"}
}