{
  "type": "Feature",
  "properties": {
    "iso:country":"US",
    "sg:address":"834 Lake St E",
    "sg:city":"Wayzata",
    "sg:classifiers":[
        {
            "category":"Personal",
            "subcategory":"Beauty Salon",
            "type":"Services"
        }
    ],
    "sg:phone":"+1 952 475 0346",
    "sg:postcode":"55391",
    "sg:province":"MN",
    "wof:name":"Karen's Salon Of Wayzata Inc",
    "wof:placetype":"venue"
},
  "geometry": {"coordinates":[-93.50426400000001,44.967378],"type":"Point"}
}