{
  "type": "Feature",
  "properties": {
    "iso:country":"US",
    "sg:address":"28734 Co Rd 6",
    "sg:city":"Grey Eagle",
    "sg:classifiers":[
        {
            "category":"Farming",
            "subcategory":"Dairy Farm",
            "type":"Manufacturing & Wholesale Goods"
        }
    ],
    "sg:phone":"+1 320 285 3175",
    "sg:postcode":"56336",
    "sg:province":"MN",
    "wof:name":"Dolence Dairy",
    "wof:placetype":"venue"
},
  "geometry": {"coordinates":[-94.778772,45.839219],"type":"Point"}
}