{
  "type": "Feature",
  "properties": {
    "iso:country":"US",
    "sg:address":"107 River Oaks Dr",
    "sg:city":"Cold Spring",
    "sg:classifiers":[
        {
            "category":"Building & Trades",
            "subcategory":"Construction",
            "type":"Services"
        }
    ],
    "sg:phone":"+1 320 685 4339",
    "sg:postcode":"56320",
    "sg:province":"MN",
    "sg:tags":[
        "house"
    ],
    "wof:name":"Timothy C Kiffmeyer",
    "wof:placetype":"venue"
},
  "geometry": {"coordinates":[-94.427426,45.46165],"type":"Point"}
}