{
  "type": "Feature",
  "properties": {
    "iso:country":"US",
    "sg:address":"510 Chestnut St W",
    "sg:city":"Virginia",
    "sg:classifiers":[
        {
            "category":"Museum",
            "type":"Entertainment"
        }
    ],
    "sg:phone":"+1 218 741 5577",
    "sg:postcode":"55792",
    "sg:province":"MN",
    "sg:tags":[
        "organization",
        "arts",
        "information"
    ],
    "wof:name":"Lyric Center For The Arts",
    "wof:placetype":"venue"
},
  "geometry": {"coordinates":[-92.54043799999999,47.523043],"type":"Point"}
}