{
  "type": "Feature",
  "properties": {
    "iso:country":"US",
    "sg:address":"1440 Skyline Dr",
    "sg:city":"Minneapolis",
    "sg:classifiers":[
        {
            "category":"Professional",
            "subcategory":"Computer Services",
            "type":"Services"
        }
    ],
    "sg:phone":"+1 763 522 2631",
    "sg:postcode":"55422",
    "sg:province":"MN",
    "sg:tags":[
        "co",
        "related"
    ],
    "wof:name":"Simon & Arrington Inc",
    "wof:placetype":"venue"
},
  "geometry": {"coordinates":[-93.32964,44.994441],"type":"Point"}
}