{
  "type": "Feature",
  "properties": {
    "iso:country":"US",
    "sg:address":"709 Main St NW",
    "sg:city":"Elk River",
    "sg:classifiers":[
        {
            "category":"Restaurant",
            "type":"Food & Drink"
        }
    ],
    "sg:phone":"+1 763 241 5595",
    "sg:postcode":"55330",
    "sg:province":"MN",
    "sg:tags":[
        "eating"
    ],
    "wof:name":"Daddy-Os Cafe",
    "wof:placetype":"venue"
},
  "geometry": {"coordinates":[-93.552516,45.312712],"type":"Point"}
}