{
  "type": "Feature",
  "properties": {
    "iso:country":"US",
    "sg:address":"901 E Ripley St",
    "sg:city":"Litchfield",
    "sg:classifiers":[
        {
            "category":"Building & Trades",
            "subcategory":"Electrical",
            "type":"Services"
        }
    ],
    "sg:phone":"+1 320 693 2843",
    "sg:postcode":"55355",
    "sg:province":"MN",
    "sg:tags":[
        "electrical",
        "contractor"
    ],
    "wof:name":"Lectric Shop Co",
    "wof:placetype":"venue"
},
  "geometry": {"coordinates":[-94.51150199999999,45.123824],"type":"Point"}
}