{
  "type": "Feature",
  "properties": {
    "iso:country":"US",
    "sg:address":"5096 Woodbury Dr",
    "sg:city":"St Paul",
    "sg:classifiers":[
        {
            "category":"Building & Trades",
            "subcategory":"Cleaning & Sanitation",
            "type":"Services"
        }
    ],
    "sg:phone":"+1 651 769 0960",
    "sg:postcode":"55129",
    "sg:province":"MN",
    "sg:tags":[
        "janitor"
    ],
    "wof:name":"Pat's Building Maintenance Inc",
    "wof:placetype":"venue"
},
  "geometry": {"coordinates":[-92.903291,44.875022],"type":"Point"}
}