{
  "type": "Feature",
  "properties": {
    "iso:country":"US",
    "sg:address":"4754 Washington Ave",
    "sg:city":"Saint Paul",
    "sg:classifiers":[
        {
            "category":"Health Services",
            "subcategory":"Doctor",
            "type":"Services"
        }
    ],
    "sg:phone":"+1 651 426 9499",
    "sg:postcode":"55110",
    "sg:province":"MN",
    "sg:tags":[
        "dentist"
    ],
    "wof:name":"Washington Square Dental",
    "wof:placetype":"venue"
},
  "geometry": {"coordinates":[-93.00900799999999,45.084362],"type":"Point"}
}