{
  "type": "Feature",
  "properties": {
    "addr:full":"14344 Burnhaven Dr Burnsville MN 55306",
    "addr:housenumber":"14344",
    "addr:postcode":"55306",
    "addr:street":"Burnhaven Dr",
    "iso:country":"US",
    "sg:address":"14344 Burnhaven Dr",
    "sg:city":"Burnsville",
    "sg:classifiers":[
        {
            "category":"Health Services",
            "subcategory":"Doctor",
            "type":"Services"
        }
    ],
    "sg:phone":"+1 952 435 8525",
    "sg:postcode":"55306",
    "sg:province":"MN",
    "sg:tags":[
        "dentist"
    ],
    "wof:name":"Metro Dental Care",
    "wof:placetype":"venue"
},
  "geometry": {"coordinates":[-93.290283,44.741458],"type":"Point"}
}