{
  "type": "Feature",
  "properties": {
    "addr:full":"11251 National St NE Minneapolis MN 55449",
    "addr:housenumber":"11251",
    "addr:postcode":"55449",
    "addr:street":"National St Ne",
    "iso:country":"US",
    "sg:address":"11251 National St NE",
    "sg:city":"Minneapolis",
    "sg:classifiers":[
        {
            "category":"Manufacturing",
            "subcategory":"Tools & Machinery",
            "type":"Manufacturing & Wholesale Goods"
        }
    ],
    "sg:phone":"+1 763 780 0301",
    "sg:postcode":"55449",
    "sg:province":"MN",
    "sg:tags":[
        "computer",
        "electronic",
        "cu",
        "mfg"
    ],
    "wof:name":"Computers By Design of MN",
    "wof:placetype":"venue"
},
  "geometry": {"coordinates":[-93.149747,45.175552],"type":"Point"}
}