{
  "type": "Feature",
  "properties": {
    "iso:country":"US",
    "sg:address":"222 2nd Ave SW",
    "sg:city":"Pipestone",
    "sg:classifiers":[
        {
            "category":"Health Services",
            "subcategory":"Chiropractor",
            "type":"Services"
        }
    ],
    "sg:phone":"+1 507 825 2214",
    "sg:postcode":"56164",
    "sg:province":"MN",
    "sg:tags":[
        "chiropractic"
    ],
    "sg:website":"http://www.pipestonefamilychiropractic.com",
    "wof:name":"Pipestone Family Chiropractic",
    "wof:placetype":"venue"
},
  "geometry": {"coordinates":[-96.319087,43.999163],"type":"Point"}
}