{
  "type": "Feature",
  "properties": {
    "iso:country":"US",
    "sg:address":"1610 West Lake Street",
    "sg:city":"Minneapolis",
    "sg:classifiers":[
        {
            "category":"Real Estate",
            "subcategory":"Architect",
            "type":"Services"
        }
    ],
    "sg:phone":"+1 612 353 4920",
    "sg:postcode":"55408",
    "sg:province":"MN",
    "sg:website":"www.pkarch.com",
    "wof:name":"Peterssen/Keller Architecture",
    "wof:placetype":"venue"
},
  "geometry": {"coordinates":[-93.302243,44.948392],"type":"Point"}
}