{
  "type": "Feature",
  "properties": {
    "iso:country":"US",
    "sg:address":"2475 Doswell Ave",
    "sg:city":"St Paul",
    "sg:classifiers":[
        {
            "category":"Home & Garden",
            "subcategory":"Home Furnishings",
            "type":"Retail Goods"
        },
        {
            "category":"Home & Garden",
            "subcategory":"Furniture",
            "type":"Retail Goods"
        }
    ],
    "sg:phone":"+1 651 917 3838",
    "sg:postcode":"55108",
    "sg:province":"MN",
    "sg:tags":[
        "decor",
        "store"
    ],
    "sg:website":"www.riverofgoodshome.com",
    "wof:name":"River of Goods",
    "wof:placetype":"venue"
},
  "geometry": {"coordinates":[-93.204651,44.981816],"type":"Point"}
}