{
  "type": "Feature",
  "properties": {
    "addr:full":"395 Hillcrest Dr Saint Michael MN 55376",
    "addr:housenumber":"395",
    "addr:postcode":"55376",
    "addr:street":"Hillcrest Dr Saint Michael",
    "iso:country":"US",
    "sg:address":"395 Hillcrest Dr",
    "sg:city":"Saint Michael",
    "sg:classifiers":[
        {
            "category":"Professional",
            "type":"Services"
        }
    ],
    "sg:phone":"+1 763 497 2971",
    "sg:postcode":"55376",
    "sg:province":"MN",
    "wof:name":"Haller Inc",
    "wof:placetype":"venue"
},
  "geometry": {"coordinates":[-93.656705,45.20882],"type":"Point"}
}