{
  "type": "Feature",
  "properties": {
    "iso:country":"US",
    "sg:address":"825 Transfer Rd",
    "sg:city":"St Paul",
    "sg:classifiers":[
        {
            "category":"Manufacturing",
            "subcategory":"Furniture",
            "type":"Manufacturing & Wholesale Goods"
        }
    ],
    "sg:phone":"+1 651 645 3787",
    "sg:postcode":"55114",
    "sg:province":"MN",
    "sg:tags":[
        "mattress"
    ],
    "wof:name":"Sealy Mattress Co",
    "wof:placetype":"venue"
},
  "geometry": {"coordinates":[-93.184321,44.968271],"type":"Point"}
}