{
  "type": "Feature",
  "properties": {
    "iso:country":"US",
    "sg:address":"13903 Leaf River Rd",
    "sg:city":"Wadena",
    "sg:classifiers":[
        {
            "category":"Restaurant",
            "type":"Food & Drink"
        }
    ],
    "sg:phone":"+1 218 631 5928",
    "sg:postcode":"56482",
    "sg:province":"MN",
    "wof:name":"Silvers Joe Raymond",
    "wof:placetype":"venue"
},
  "geometry": {"coordinates":[-95.072228,46.488629],"type":"Point"}
}