{
  "type": "Feature",
  "properties": {
    "addr:full":"1841 Carl St Saint Paul MN 55113",
    "addr:housenumber":"1841",
    "addr:postcode":"55113",
    "addr:street":"Carl St",
    "iso:country":"US",
    "sg:address":"1841 Carl St",
    "sg:city":"Saint Paul",
    "sg:classifiers":[
        {
            "category":"Communications",
            "subcategory":"Film & Video Production",
            "type":"Services"
        }
    ],
    "sg:phone":"+1 651 917 2723",
    "sg:postcode":"55113",
    "sg:province":"MN",
    "sg:tags":[
        "motion"
    ],
    "wof:name":"Vieng Production",
    "wof:placetype":"venue"
},
  "geometry": {"coordinates":[-93.20126500000001,44.99623],"type":"Point"}
}