{
  "type": "Feature",
  "properties": {
    "addr:full":"305 2nd St NW New Brighton MN 55112",
    "addr:housenumber":"305",
    "addr:postcode":"55112",
    "addr:street":"2Nd St Nw",
    "iso:country":"US",
    "sg:address":"305 2nd St NW",
    "sg:city":"New Brighton",
    "sg:phone":"+1 651 628 4848",
    "sg:postcode":"55112",
    "sg:province":"MN",
    "sg:tags":[
        "bulk",
        "gas"
    ],
    "sg:website":"www.twincityoxygen.com",
    "wof:name":"Twin City Oxygen",
    "wof:placetype":"venue"
},
  "geometry": {"coordinates":[-93.19237699999999,45.052574],"type":"Point"}
}