{
  "type": "Feature",
  "properties": {
    "addr:full":"4900 Broadway Ave N Crystal MN 55429",
    "addr:housenumber":"4900",
    "addr:postcode":"55429",
    "addr:street":"Broadway Ave N",
    "iso:country":"US",
    "sg:address":"4900 Broadway Ave N",
    "sg:city":"Crystal",
    "sg:classifiers":[
        {
            "category":"Restaurant",
            "type":"Food & Drink"
        }
    ],
    "sg:phone":"+1 763 537 5970",
    "sg:postcode":"55429",
    "sg:province":"MN",
    "sg:tags":[
        "traditional",
        "american"
    ],
    "wof:name":"Steve O's",
    "wof:placetype":"venue"
},
  "geometry": {"coordinates":[-93.35057500000001,45.041921],"type":"Point"}
}