{
  "type": "Feature",
  "properties": {
    "addr:full":"213 Downtown Plz Fairmont MN 56031",
    "addr:postcode":"56031",
    "iso:country":"US",
    "sg:address":"213 Downtown Plz",
    "sg:city":"Fairmont",
    "sg:classifiers":[
        {
            "category":"Social Services",
            "type":"Services"
        }
    ],
    "sg:phone":"+1 507 235 6016",
    "sg:postcode":"56031",
    "sg:province":"MN",
    "sg:tags":[
        "youth",
        "organization",
        "center"
    ],
    "wof:name":"Martin County Youth For Christ",
    "wof:placetype":"venue"
},
  "geometry": {"coordinates":[-94.462456,43.654737],"type":"Point"}
}