{
  "type": "Feature",
  "properties": {
    "addr:full":"5328 Chicago Ave S Minneapolis MN 55417",
    "addr:housenumber":"5328",
    "addr:postcode":"55417",
    "addr:street":"Chicago Ave S",
    "iso:country":"US",
    "sg:address":"5328 Chicago Ave S",
    "sg:city":"Minneapolis",
    "sg:classifiers":[
        {
            "category":"Professional",
            "subcategory":"Computer Services",
            "type":"Services"
        }
    ],
    "sg:phone":"+1 612 823 7648",
    "sg:postcode":"55417",
    "sg:province":"MN",
    "sg:tags":[
        "consultant",
        "designer"
    ],
    "wof:name":"D K Micro",
    "wof:placetype":"venue"
},
  "geometry": {"coordinates":[-93.26269600000001,44.90576],"type":"Point"}
}