{
  "type": "Feature",
  "properties": {
    "iso:country":"US",
    "sg:address":"22281 Lake Francis Rd",
    "sg:city":"Elysian",
    "sg:classifiers":[
        {
            "category":"Building & Trades",
            "subcategory":"Construction",
            "type":"Services"
        }
    ],
    "sg:phone":"+1 507 267 4781",
    "sg:postcode":"56028",
    "sg:province":"MN",
    "sg:tags":[
        "house"
    ],
    "wof:name":"Timothy F Bengtson",
    "wof:placetype":"venue"
},
  "geometry": {"coordinates":[-93.701493,44.225134],"type":"Point"}
}