{
  "type": "Feature",
  "properties": {
    "addr:full":"701 Garfield St S Cambridge MN 55008",
    "addr:housenumber":"701",
    "addr:postcode":"55008",
    "addr:street":"Garfield St S",
    "iso:country":"US",
    "sg:address":"701 Garfield St S",
    "sg:city":"Cambridge",
    "sg:classifiers":[
        {
            "category":"Wholesale",
            "subcategory":"Hardware",
            "type":"Manufacturing & Wholesale Goods"
        }
    ],
    "sg:phone":"+1 763 689 4242",
    "sg:postcode":"55008",
    "sg:province":"MN",
    "sg:tags":[
        "fastener"
    ],
    "wof:name":"Fastenal Co",
    "wof:placetype":"venue"
},
  "geometry": {"coordinates":[-93.216443,45.566575],"type":"Point"}
}