{
  "type": "Feature",
  "properties": {
    "addr:full":"2983 Chatsworth St N Roseville MN 55113",
    "addr:housenumber":"2983",
    "addr:postcode":"55113",
    "addr:street":"Chatsworth St N",
    "iso:country":"US",
    "sg:address":"2983 Chatsworth St N",
    "sg:city":"Roseville",
    "sg:classifiers":[
        {
            "category":"Professional",
            "subcategory":"Business Services",
            "type":"Services"
        }
    ],
    "sg:phone":"+1 651 486 9757",
    "sg:postcode":"55113",
    "sg:province":"MN",
    "sg:tags":[
        "interior",
        "consultant",
        "design",
        "studio",
        "decorator"
    ],
    "wof:name":"Joan Breen Interior Design Etc",
    "wof:placetype":"venue"
},
  "geometry": {"coordinates":[-93.141783,45.030066],"type":"Point"}
}