{
  "type": "Feature",
  "properties": {
    "addr:full":"2452 160th St Tyler MN 56115",
    "addr:housenumber":"2452",
    "addr:postcode":"56115",
    "addr:street":"160Th St",
    "iso:country":"US",
    "sg:address":"2452 160th St",
    "sg:city":"Tyler",
    "sg:classifiers":[
        {
            "category":"Farming",
            "subcategory":"Farm",
            "type":"Manufacturing & Wholesale Goods"
        }
    ],
    "sg:phone":"+1 507 247 5399",
    "sg:postcode":"56115",
    "sg:province":"MN",
    "sg:tags":[
        "crop",
        "general"
    ],
    "wof:name":"Tom Ruppert",
    "wof:placetype":"venue"
},
  "geometry": {"coordinates":[-95.80547900000001,44.282897],"type":"Point"}
}