{
  "type": "Feature",
  "properties": {
    "addr:full":"250 Marquette Ave Minneapolis MN 55401",
    "addr:housenumber":"250",
    "addr:postcode":"55401",
    "addr:street":"Marquette Ave",
    "iso:country":"US",
    "sg:address":"250 Marquette Ave",
    "sg:city":"Minneapolis",
    "sg:classifiers":[
        {
            "category":"Government",
            "subcategory":"Office",
            "type":"Public Place"
        }
    ],
    "sg:phone":"+1 612 336 8402",
    "sg:postcode":"55401",
    "sg:province":"MN",
    "sg:tags":[
        "government-state"
    ],
    "wof:name":"Minnesota Cyber Task Forc",
    "wof:placetype":"venue"
},
  "geometry": {"coordinates":[-93.26690000000001,44.981037],"type":"Point"}
}