{
  "type": "Feature",
  "properties": {
    "addr:full":"1345 3rd St S Stillwater MN 55082",
    "addr:housenumber":"1345",
    "addr:postcode":"55082",
    "addr:street":"3Rd St S",
    "iso:country":"US",
    "sg:address":"1345 3rd St S",
    "sg:city":"Stillwater",
    "sg:classifiers":[
        {
            "category":"Professional",
            "subcategory":"Computer Services",
            "type":"Services"
        }
    ],
    "sg:phone":"+1 651 275 5988",
    "sg:postcode":"55082",
    "sg:province":"MN",
    "sg:tags":[
        "datum"
    ],
    "wof:name":"Joan Berry",
    "wof:placetype":"venue"
},
  "geometry": {"coordinates":[-92.806212,45.043645],"type":"Point"}
}