{
  "type": "Feature",
  "properties": {
    "addr:full":"7369 State Hwy 13 Savage MN 55378",
    "addr:housenumber":"7369",
    "addr:postcode":"55378",
    "addr:street":"State Hwy 13",
    "iso:country":"US",
    "sg:address":"7369 State Hwy 13",
    "sg:city":"Savage",
    "sg:classifiers":[
        {
            "category":"Retail",
            "subcategory":"Auto Repair",
            "type":"Services"
        }
    ],
    "sg:phone":"+1 952 894 4316",
    "sg:postcode":"55378",
    "sg:province":"MN",
    "sg:tags":[
        "repairing",
        "automobile"
    ],
    "wof:name":"Marti & Gary's Auto Svc",
    "wof:placetype":"venue"
},
  "geometry": {"coordinates":[-93.37147400000001,44.778448],"type":"Point"}
}