{
  "type": "Feature",
  "properties": {
    "iso:country":"US",
    "sg:address":"113 N Powers Ave",
    "sg:city":"Alden",
    "sg:classifiers":[
        {
            "category":"Farming",
            "subcategory":"Farm",
            "type":"Manufacturing & Wholesale Goods"
        }
    ],
    "sg:phone":"+1 507 874 2656",
    "sg:postcode":"56009",
    "sg:province":"MN",
    "sg:tags":[
        "livestock",
        "crop",
        "general"
    ],
    "wof:name":"Kevin Swenson",
    "wof:placetype":"venue"
},
  "geometry": {"coordinates":[-93.56829999999999,43.670192],"type":"Point"}
}