{
  "type": "Feature",
  "properties": {
    "iso:country":"US",
    "sg:address":"34404 Sunrise Blvd",
    "sg:city":"Crosslake",
    "sg:classifiers":[
        {
            "category":"Professional",
            "subcategory":"Management & Consulting",
            "type":"Services"
        }
    ],
    "sg:phone":"+1 218 692 2345",
    "sg:postcode":"56442",
    "sg:province":"MN",
    "wof:name":"Transfo Inc",
    "wof:placetype":"venue"
},
  "geometry": {"coordinates":[-94.147341,46.651459],"type":"Point"}
}