{
  "type": "Feature",
  "properties": {
    "addr:full":"250 Marquette Ave Ste 525 Minneapolis MN 55401",
    "addr:housenumber":"250",
    "addr:postcode":"55401",
    "addr:street":"Marquette Ave Ste 525",
    "iso:country":"US",
    "sg:address":"250 Marquette Ave Ste 525",
    "sg:city":"Minneapolis",
    "sg:classifiers":[
        {
            "category":"Government",
            "subcategory":"Office",
            "type":"Public Place"
        }
    ],
    "sg:phone":"+1 612 343 7759",
    "sg:postcode":"55401",
    "sg:province":"MN",
    "sg:tags":[
        "security",
        "homeland"
    ],
    "wof:name":"Defense Contract Audit Agency",
    "wof:placetype":"venue"
},
  "geometry": {"coordinates":[-93.26690000000001,44.981037],"type":"Point"}
}