{
  "type": "Feature",
  "properties": {
    "iso:country":"US",
    "sg:address":"544 1st Ave S",
    "sg:city":"South St Paul",
    "sg:classifiers":[
        {
            "category":"Building & Trades",
            "subcategory":"Construction",
            "type":"Services"
        }
    ],
    "sg:phone":"+1 651 451 8199",
    "sg:postcode":"55075",
    "sg:province":"MN",
    "sg:tags":[
        "hanging",
        "painter",
        "contractor"
    ],
    "wof:name":"Kammerers Decorating",
    "wof:placetype":"venue"
},
  "geometry": {"coordinates":[-93.03483799999999,44.882489],"type":"Point"}
}