{
  "type": "Feature",
  "properties": {
    "iso:country":"US",
    "sg:address":"9328 Valleyhigh Rd NW",
    "sg:city":"Byron",
    "sg:classifiers":[
        {
            "category":"Restaurant",
            "type":"Food & Drink"
        }
    ],
    "sg:phone":"+1 507 775 2186",
    "sg:postcode":"55920",
    "sg:province":"MN",
    "wof:name":"Frank N Stein Of Byron",
    "wof:placetype":"venue"
},
  "geometry": {"coordinates":[-92.629233,44.072189],"type":"Point"}
}