{
  "type": "Feature",
  "properties": {
    "addr:full":"6001 Penn Ave S Minneapolis MN 55419",
    "addr:housenumber":"6001",
    "addr:postcode":"55419",
    "addr:street":"Penn Ave S",
    "iso:country":"US",
    "sg:address":"6001 Penn Ave S",
    "sg:city":"Minneapolis",
    "sg:classifiers":[
        {
            "category":"Autos & Motor Vehicles",
            "subcategory":"Fuel & Gas Station",
            "type":"Retail Goods"
        }
    ],
    "sg:phone":"+1 612 869 4272",
    "sg:postcode":"55419",
    "sg:province":"MN",
    "sg:tags":[
        "automotive",
        "station",
        "gasoline",
        "repair"
    ],
    "wof:name":"Penn Mobil",
    "wof:placetype":"venue"
},
  "geometry": {"coordinates":[-93.308662,44.892554],"type":"Point"}
}