{
  "type": "Feature",
  "properties": {
    "addr:full":"53 State Hwy 5 Waconia MN 55387",
    "addr:housenumber":"53",
    "addr:postcode":"55387",
    "addr:street":"State Hwy 5 Waconia",
    "iso:country":"US",
    "sg:address":"53 State Hwy 5",
    "sg:city":"Waconia",
    "sg:classifiers":[
        {
            "category":"Autos & Motor Vehicles",
            "subcategory":"Auto Supplies",
            "type":"Retail Goods"
        }
    ],
    "sg:phone":"+1 952 442 2168",
    "sg:postcode":"55387",
    "sg:province":"MN",
    "sg:tags":[
        "automobile",
        "parts"
    ],
    "wof:name":"Car-Co Auto Parts",
    "wof:placetype":"venue"
},
  "geometry": {"coordinates":[-93.78654400000001,44.843464],"type":"Point"}
}