{
  "type": "Feature",
  "properties": {
    "addr:full":"2317 Prospect Ave Cloquet MN 55720",
    "addr:housenumber":"2317",
    "addr:postcode":"55720",
    "addr:street":"Prospect Ave",
    "iso:country":"US",
    "sg:address":"2317 Prospect Ave",
    "sg:city":"Cloquet",
    "sg:classifiers":[
        {
            "category":"Social Services",
            "subcategory":"Adult Care",
            "type":"Services"
        }
    ],
    "sg:phone":"+1 218 879 6660",
    "sg:postcode":"55720",
    "sg:province":"MN",
    "sg:tags":[
        "home",
        "group"
    ],
    "wof:name":"Pine Ridge Homes Inc",
    "wof:placetype":"venue"
},
  "geometry": {"coordinates":[-92.43710299999999,46.714091],"type":"Point"}
}