{
  "type": "Feature",
  "properties": {
    "addr:full":"511 17th St Windom MN 56101",
    "addr:housenumber":"511",
    "addr:postcode":"56101",
    "addr:street":"17Th St",
    "iso:country":"US",
    "sg:address":"511 17th St",
    "sg:city":"Windom",
    "sg:classifiers":[
        {
            "category":"Farming",
            "subcategory":"Farm",
            "type":"Manufacturing & Wholesale Goods"
        }
    ],
    "sg:phone":"+1 507 831 5744",
    "sg:postcode":"56101",
    "sg:province":"MN",
    "sg:tags":[
        "crop",
        "general"
    ],
    "wof:name":"Tom Jurgens",
    "wof:placetype":"venue"
},
  "geometry": {"coordinates":[-95.119128,43.873929],"type":"Point"}
}