{
  "type": "Feature",
  "properties": {
    "addr:full":"808 S Kniss Ave Luverne MN 56156",
    "addr:housenumber":"808",
    "addr:postcode":"56156",
    "addr:street":"S Kniss Ave",
    "iso:country":"US",
    "sg:address":"808 S Kniss Ave",
    "sg:city":"Luverne",
    "sg:classifiers":[
        {
            "category":"Professional",
            "subcategory":"Accounting & Tax Preparation",
            "type":"Services"
        }
    ],
    "sg:phone":"+1 507 283 9083",
    "sg:postcode":"56156",
    "sg:province":"MN",
    "sg:tags":[
        "return",
        "real estate"
    ],
    "wof:name":"H & R Block",
    "wof:placetype":"venue"
},
  "geometry": {"coordinates":[-96.213247,43.645377],"type":"Point"}
}