{
  "type": "Feature",
  "properties": {
    "iso:country":"US",
    "sg:address":"536 Redwood Ln",
    "sg:city":"Saint Paul",
    "sg:classifiers":[
        {
            "category":"Wholesale",
            "subcategory":"Medical Equipment & Supplies",
            "type":"Manufacturing & Wholesale Goods"
        }
    ],
    "sg:phone":"+1 651 628 4063",
    "sg:postcode":"55112",
    "sg:province":"MN",
    "sg:tags":[
        "resell"
    ],
    "wof:name":"Prime Time Medical Inc",
    "wof:placetype":"venue"
},
  "geometry": {"coordinates":[-93.219763,45.060152],"type":"Point"}
}