{
  "type": "Feature",
  "properties": {
    "addr:full":"23661 Meridian Ave Belle Plaine MN 56011",
    "addr:housenumber":"23661",
    "addr:postcode":"56011",
    "addr:street":"Meridian Ave Belle Plaine",
    "iso:country":"US",
    "sg:address":"23661 Meridian Ave",
    "sg:city":"Belle Plaine",
    "sg:classifiers":[
        {
            "category":"Freight",
            "type":"Transportation"
        }
    ],
    "sg:phone":"+1 952 873 6296",
    "sg:postcode":"56011",
    "sg:province":"MN",
    "sg:tags":[
        "over",
        "road",
        "trucking"
    ],
    "wof:name":"Stier Farm & Trucking",
    "wof:placetype":"venue"
},
  "geometry": {"coordinates":[-93.76804799999999,44.605832],"type":"Point"}
}