{
  "type": "Feature",
  "properties": {
    "addr:full":"4011 State Hwy 13 Savage MN 55378",
    "addr:housenumber":"4011",
    "addr:postcode":"55378",
    "addr:street":"State Hwy 13",
    "iso:country":"US",
    "sg:address":"4011 State Hwy 13",
    "sg:city":"Savage",
    "sg:classifiers":[
        {
            "category":"Organizations",
            "subcategory":"Religious Organization",
            "type":"Services"
        }
    ],
    "sg:phone":"+1 952 895 0745",
    "sg:postcode":"55378",
    "sg:province":"MN",
    "sg:website":"www.unityvalley.org",
    "wof:name":"Unity Of The Valley Church",
    "wof:placetype":"venue"
},
  "geometry": {"coordinates":[-93.329786,44.778398],"type":"Point"}
}