{
  "type": "Feature",
  "properties": {
    "addr:full":"13837 Lincoln St NE Anoka MN 55304",
    "addr:housenumber":"13837",
    "addr:postcode":"55304",
    "addr:street":"Lincoln St Ne",
    "iso:country":"US",
    "sg:address":"13837 Lincoln St NE",
    "sg:city":"Anoka",
    "sg:classifiers":[
        {
            "category":"Real Estate",
            "subcategory":"Architect",
            "type":"Services"
        }
    ],
    "sg:phone":"+1 763 755 1211",
    "sg:postcode":"55304",
    "sg:province":"MN",
    "sg:tags":[
        "architectural"
    ],
    "wof:name":"Leonard Lampert Architects PA",
    "wof:placetype":"venue"
},
  "geometry": {"coordinates":[-93.238951,45.219379],"type":"Point"}
}