{
  "type": "Feature",
  "properties": {
    "iso:country":"US",
    "sg:address":"10894 US Hwy 14",
    "sg:city":"Claremont",
    "sg:phone":"+1 507 528 2583",
    "sg:postcode":"55924",
    "sg:province":"MN",
    "sg:tags":[
        "farm",
        "corn",
        "soybean"
    ],
    "wof:name":"Lawrence Christey",
    "wof:placetype":"venue"
},
  "geometry": {"coordinates":[-93.028322,44.052014],"type":"Point"}
}