{
  "type": "Feature",
  "properties": {
    "addr:full":"102 17th Ave NW Rochester MN 55901",
    "addr:housenumber":"102",
    "addr:postcode":"55901",
    "addr:street":"17Th Ave Nw",
    "iso:country":"US",
    "sg:address":"102 17th Ave NW",
    "sg:city":"Rochester",
    "sg:classifiers":[
        {
            "category":"Restaurant",
            "type":"Food & Drink"
        }
    ],
    "sg:phone":"+1 507 529 2922",
    "sg:postcode":"55901",
    "sg:province":"MN",
    "sg:tags":[
        "parlor",
        "eating",
        "ice",
        "cream"
    ],
    "wof:name":"Chocolate Twist",
    "wof:placetype":"venue"
},
  "geometry": {"coordinates":[-92.487449,44.025317],"type":"Point"}
}