{
  "type": "Feature",
  "properties": {
    "addr:full":"928 6th St Howard Lake MN 55349",
    "addr:housenumber":"928",
    "addr:postcode":"55349",
    "addr:street":"6Th St",
    "iso:country":"US",
    "sg:address":"928 6th St",
    "sg:city":"Howard Lake",
    "sg:classifiers":[
        {
            "category":"Restaurant",
            "type":"Food & Drink"
        }
    ],
    "sg:phone":"+1 320 543 3223",
    "sg:postcode":"55349",
    "sg:province":"MN",
    "wof:name":"Bergie's Pizza & Subs",
    "wof:placetype":"venue"
},
  "geometry": {"coordinates":[-94.072541,45.060677],"type":"Point"}
}