{
  "type": "Feature",
  "properties": {
    "addr:full":"16544 W 78th St Eden Prairie MN 55346",
    "addr:housenumber":"16544",
    "addr:postcode":"55346",
    "addr:street":"W 78Th St",
    "iso:country":"US",
    "sg:address":"16544 W 78th St",
    "sg:city":"Eden Prairie",
    "sg:classifiers":[
        {
            "category":"Education",
            "subcategory":"Vocational School",
            "type":"Public Place"
        }
    ],
    "sg:phone":"+1 952 949 6799",
    "sg:postcode":"55346",
    "sg:province":"MN",
    "sg:tags":[
        "cooking"
    ],
    "wof:name":"Way Cool",
    "wof:placetype":"venue"
},
  "geometry": {"coordinates":[-93.48851999999999,44.862993],"type":"Point"}
}