{
  "type": "Feature",
  "properties": {
    "addr:full":"11270 54th St NE Spicer MN 56288",
    "addr:housenumber":"11270",
    "addr:postcode":"56288",
    "addr:street":"54Th St Ne",
    "iso:country":"US",
    "sg:address":"11270 54th St NE",
    "sg:city":"Spicer",
    "sg:classifiers":[
        {
            "category":"Building & Trades",
            "subcategory":"Plumbing",
            "type":"Services"
        }
    ],
    "sg:phone":"+1 320 796 3039",
    "sg:postcode":"56288",
    "sg:province":"MN",
    "sg:tags":[
        "plumbing",
        "contractor"
    ],
    "wof:name":"Johnson's Plumbing Heating",
    "wof:placetype":"venue"
},
  "geometry": {"coordinates":[-94.969419,45.229106],"type":"Point"}
}