{
  "type": "Feature",
  "properties": {
    "addr:full":"1700 Highway 36 W Saint Paul MN 55113",
    "addr:housenumber":"1700",
    "addr:postcode":"55113",
    "addr:street":"Highway 36 W",
    "iso:country":"US",
    "sg:address":"1700 Highway 36 W",
    "sg:city":"Saint Paul",
    "sg:classifiers":[
        {
            "category":"Health Services",
            "subcategory":"Clinic",
            "type":"Services"
        },
        {
            "category":"Organizations",
            "subcategory":"Religious Organization",
            "type":"Services"
        }
    ],
    "sg:phone":"+1 651 631 1090",
    "sg:postcode":"55113",
    "sg:province":"MN",
    "sg:tags":[
        "counseling",
        "mental"
    ],
    "wof:name":"Albert and Associates",
    "wof:placetype":"venue"
},
  "geometry": {"coordinates":[-93.17150100000001,45.009602],"type":"Point"}
}