{
  "type": "Feature",
  "properties": {
    "iso:country":"US",
    "sg:address":"312 S Prairie St",
    "sg:city":"Lake City",
    "sg:classifiers":[
        {
            "category":"Building & Trades",
            "subcategory":"Electrical",
            "type":"Services"
        }
    ],
    "sg:phone":"+1 651 345 5083",
    "sg:postcode":"55041",
    "sg:province":"MN",
    "sg:tags":[
        "electric",
        "contractor"
    ],
    "wof:name":"Halpaus Electric",
    "wof:placetype":"venue"
},
  "geometry": {"coordinates":[-92.26825100000001,44.444884],"type":"Point"}
}