{
  "type": "Feature",
  "properties": {
    "iso:country":"US",
    "sg:address":"112 High Forest St",
    "sg:city":"Winona",
    "sg:classifiers":[
        {
            "category":"Organizations",
            "subcategory":"Community Association",
            "type":"Services"
        }
    ],
    "sg:phone":"+1 507 454 3372",
    "sg:postcode":"55987",
    "sg:province":"MN",
    "wof:name":"Improved Order of Redmen",
    "wof:placetype":"venue"
},
  "geometry": {"coordinates":[-91.617512,44.047857],"type":"Point"}
}