{
  "type": "Feature",
  "properties": {
    "addr:full":"2113 Western Ave NW Faribault MN 55021",
    "addr:housenumber":"2113",
    "addr:postcode":"55021",
    "addr:street":"Western Ave Nw",
    "iso:country":"US",
    "sg:address":"2113 Western Ave NW",
    "sg:city":"Faribault",
    "sg:classifiers":[
        {
            "category":"Wholesale",
            "subcategory":"Construction Materials",
            "type":"Manufacturing & Wholesale Goods"
        },
        {
            "category":"Wholesale",
            "subcategory":"Home Furnishings",
            "type":"Manufacturing & Wholesale Goods"
        }
    ],
    "sg:phone":"+1 507 332 8791",
    "sg:postcode":"55021",
    "sg:province":"MN",
    "sg:tags":[
        "mattresses-wholesale",
        "makers'",
        "mattress",
        "manufacturer",
        "supply"
    ],
    "sg:website":"http://www.kodiakfurniture.com",
    "wof:name":"Minneapolis Furniture Discounters, Inc.",
    "wof:placetype":"venue"
},
  "geometry": {"coordinates":[-93.302992,44.31204],"type":"Point"}
}