{
  "type": "Feature",
  "properties": {
    "addr:full":"275 Market St Minneapolis MN 55405",
    "addr:housenumber":"275",
    "addr:postcode":"55405",
    "addr:street":"Market St",
    "iso:country":"US",
    "sg:address":"275 Market St",
    "sg:city":"Minneapolis",
    "sg:classifiers":[
        {
            "category":"Home & Garden",
            "subcategory":"Furniture",
            "type":"Retail Goods"
        }
    ],
    "sg:phone":"+1 612 335 9335",
    "sg:postcode":"55405",
    "sg:province":"MN",
    "sg:tags":[
        "store"
    ],
    "wof:name":"G Maxwell Collections",
    "wof:placetype":"venue"
},
  "geometry": {"coordinates":[-93.289855,44.980623],"type":"Point"}
}