{
  "type": "Feature",
  "properties": {
    "iso:country":"US",
    "sg:address":"119 Main St S",
    "sg:city":"Chatfield",
    "sg:classifiers":[
        {
            "category":"Home & Garden",
            "subcategory":"Furniture",
            "type":"Retail Goods"
        }
    ],
    "sg:phone":"+1 507 867 4300",
    "sg:postcode":"55923",
    "sg:province":"MN",
    "wof:name":"S & K Custom Furniture",
    "wof:placetype":"venue"
},
  "geometry": {"coordinates":[-92.189764,43.846135],"type":"Point"}
}