{
  "type": "Feature",
  "properties": {
    "addr:full":"5334 Miller Trunk Hwy Duluth MN 55811",
    "addr:housenumber":"5334",
    "addr:postcode":"55811",
    "addr:street":"Miller Trunk Hwy",
    "iso:country":"US",
    "sg:address":"5334 Miller Trunk Hwy",
    "sg:city":"Duluth",
    "sg:classifiers":[
        {
            "category":"Wholesale",
            "subcategory":"Hardware",
            "type":"Manufacturing & Wholesale Goods"
        }
    ],
    "sg:phone":"+1 218 729 5060",
    "sg:postcode":"55811",
    "sg:province":"MN",
    "sg:tags":[
        "equipment",
        "hot",
        "sauna",
        "tub",
        "spa"
    ],
    "wof:name":"Tubby Checker Pool & Spa Ctr",
    "wof:placetype":"venue"
},
  "geometry": {"coordinates":[-92.248458,46.839879],"type":"Point"}
}