{
  "type": "Feature",
  "properties": {
    "iso:country":"US",
    "sg:address":"2188 4th St",
    "sg:city":"White Bear Lake",
    "sg:classifiers":[
        {
            "category":"Shopping",
            "subcategory":"Clothing, Apparel, & Fashions",
            "type":"Retail Goods"
        }
    ],
    "sg:phone":"+1 651 407 2579",
    "sg:postcode":"55110",
    "sg:province":"MN",
    "wof:name":"Chico's",
    "wof:placetype":"venue"
},
  "geometry": {"coordinates":[-93.008246,45.085312],"type":"Point"}
}