{
  "type": "Feature",
  "properties": {
    "iso:country":"US",
    "sg:address":"11399 Maryland Ave N",
    "sg:city":"Champlin",
    "sg:classifiers":[
        {
            "category":"Building & Trades",
            "subcategory":"Locksmith",
            "type":"Services"
        }
    ],
    "sg:phone":"+1 612 216 0089",
    "sg:postcode":"55316",
    "sg:province":"MN",
    "sg:tags":[
        "key"
    ],
    "wof:name":"0 Alwayes 1 24 A Locksmith",
    "wof:placetype":"venue"
},
  "geometry": {"coordinates":[-93.37286400000001,45.160923],"type":"Point"}
}