{
  "type": "Feature",
  "properties": {
    "addr:full":"1512 Commercial Ave Victoria MN 55386",
    "addr:housenumber":"1512",
    "addr:postcode":"55386",
    "addr:street":"Commercial Ave",
    "iso:country":"US",
    "sg:address":"1512 Commercial Ave",
    "sg:city":"Victoria",
    "sg:classifiers":[
        {
            "category":"Food & Beverages",
            "subcategory":"Liquor & Beverages",
            "type":"Retail Goods"
        }
    ],
    "sg:phone":"+1 952 443 3483",
    "sg:postcode":"55386",
    "sg:province":"MN",
    "sg:tags":[
        "beer",
        "spirit",
        "wine"
    ],
    "wof:name":"Hi-Five Liquor Store",
    "wof:placetype":"venue"
},
  "geometry": {"coordinates":[-93.65619700000001,44.8601],"type":"Point"}
}