{
  "type": "Feature",
  "properties": {
    "addr:full":"813 US Hwy 52 Preston MN 55965",
    "addr:housenumber":"813",
    "addr:postcode":"55965",
    "addr:street":"Us Hwy 52",
    "iso:country":"US",
    "sg:address":"813 US Hwy 52",
    "sg:city":"Preston",
    "sg:classifiers":[
        {
            "category":"Government",
            "subcategory":"Office",
            "type":"Public Place"
        }
    ],
    "sg:phone":"+1 507 765 2100",
    "sg:postcode":"55965",
    "sg:province":"MN",
    "sg:tags":[
        "city",
        "program",
        "adm"
    ],
    "wof:name":"Preston Tourism Office",
    "wof:placetype":"venue"
},
  "geometry": {"coordinates":[-92.07213900000001,43.673643],"type":"Point"}
}