{
  "type": "Feature",
  "properties": {
    "addr:full":"102 2nd St SE Roseau MN 56751",
    "addr:housenumber":"102",
    "addr:postcode":"56751",
    "addr:street":"2Nd St Se",
    "iso:country":"US",
    "sg:address":"102 2nd St SE",
    "sg:city":"Roseau",
    "sg:classifiers":[
        {
            "category":"Professional",
            "subcategory":"Accounting & Tax Preparation",
            "type":"Services"
        }
    ],
    "sg:phone":"+1 218 463 1750",
    "sg:postcode":"56751",
    "sg:province":"MN",
    "sg:tags":[
        "accountant"
    ],
    "wof:name":"Hayes & Czeh",
    "wof:placetype":"venue"
},
  "geometry": {"coordinates":[-95.76284699999999,48.845133],"type":"Point"}
}