{
  "type": "Feature",
  "properties": {
    "addr:full":"1718 Greeley Ave N Glencoe MN 55336",
    "addr:housenumber":"1718",
    "addr:postcode":"55336",
    "addr:street":"Greeley Ave N",
    "iso:country":"US",
    "sg:address":"1718 Greeley Ave N",
    "sg:city":"Glencoe",
    "sg:classifiers":[
        {
            "category":"Social Services",
            "subcategory":"Child Care",
            "type":"Services"
        }
    ],
    "sg:phone":"+1 320 864 3746",
    "sg:postcode":"55336",
    "sg:province":"MN",
    "sg:tags":[
        "day"
    ],
    "wof:name":"Kathy Schlueter",
    "wof:placetype":"venue"
},
  "geometry": {"coordinates":[-94.153147,44.776867],"type":"Point"}
}