{
  "type": "Feature",
  "properties": {
    "addr:full":"110 2nd St NW Wadena MN 56482",
    "addr:housenumber":"110",
    "addr:postcode":"56482",
    "addr:street":"2Nd St Nw",
    "iso:country":"US",
    "sg:address":"110 2nd St NW",
    "sg:city":"Wadena",
    "sg:classifiers":[
        {
            "category":"Travel",
            "subcategory":"Travel Agent",
            "type":"Entertainment"
        }
    ],
    "sg:phone":"+1 218 631 2521",
    "sg:postcode":"56482",
    "sg:province":"MN",
    "sg:tags":[
        "agency"
    ],
    "wof:name":"Area Travel Service",
    "wof:placetype":"venue"
},
  "geometry": {"coordinates":[-95.138007,46.444032],"type":"Point"}
}