{
  "type": "Feature",
  "properties": {
    "iso:country":"US",
    "sg:address":"3220 Southdale Cir",
    "sg:city":"Edina",
    "sg:classifiers":[
        {
            "category":"Restaurant",
            "type":"Food & Drink"
        }
    ],
    "sg:phone":"+1 952 925 3130",
    "sg:postcode":"55435",
    "sg:province":"MN",
    "wof:name":"Mc Donald's",
    "wof:placetype":"venue"
},
  "geometry": {"coordinates":[-93.320566,44.882717],"type":"Point"}
}