{
  "type": "Feature",
  "properties": {
    "iso:country":"US",
    "sg:address":"1471 Brewster St",
    "sg:city":"Saint Paul",
    "sg:classifiers":[
        {
            "category":"Professional",
            "subcategory":"Advertising",
            "type":"Services"
        }
    ],
    "sg:phone":"+1 651 917 7365",
    "sg:postcode":"55108",
    "sg:province":"MN",
    "sg:tags":[
        "mail",
        "direct"
    ],
    "wof:name":"Rob Lord and Assot",
    "wof:placetype":"venue"
},
  "geometry": {"coordinates":[-93.16493699999999,44.974937],"type":"Point"}
}