{
  "type": "Feature",
  "properties": {
    "addr:full":"2610 Broadway Ave Slayton MN 56172",
    "addr:housenumber":"2610",
    "addr:postcode":"56172",
    "addr:street":"Broadway Ave",
    "iso:country":"US",
    "sg:address":"2610 Broadway Ave",
    "sg:city":"Slayton",
    "sg:classifiers":[
        {
            "category":"Manufacturing",
            "subcategory":"Printing",
            "type":"Manufacturing & Wholesale Goods"
        }
    ],
    "sg:phone":"+1 507 836 6883",
    "sg:postcode":"56172",
    "sg:province":"MN",
    "sg:tags":[
        "printer"
    ],
    "wof:name":"Page 1 Commercial Printing",
    "wof:placetype":"venue"
},
  "geometry": {"coordinates":[-95.756416,43.987718],"type":"Point"}
}