{
  "type": "Feature",
  "properties": {
    "addr:full":"301 Shelard Pkwy Minneapolis MN 55426",
    "addr:housenumber":"301",
    "addr:postcode":"55426",
    "addr:street":"Shelard Pkwy",
    "iso:country":"US",
    "sg:address":"301 Shelard Pkwy",
    "sg:city":"Minneapolis",
    "sg:classifiers":[
        {
            "category":"Communications",
            "subcategory":"Radio Station",
            "type":"Services"
        }
    ],
    "sg:phone":"+1 952 593 0976",
    "sg:postcode":"55426",
    "sg:province":"MN",
    "sg:tags":[
        "education"
    ],
    "wof:name":"Beulah Mounger",
    "wof:placetype":"venue"
},
  "geometry": {"coordinates":[-93.410295,44.976815],"type":"Point"}
}