{
  "type": "Feature",
  "properties": {
    "addr:full":"8259 185th Ave Becker MN 55308",
    "addr:housenumber":"8259",
    "addr:postcode":"55308",
    "addr:street":"185Th Ave",
    "iso:country":"US",
    "sg:address":"8259 185th Ave",
    "sg:city":"Becker",
    "sg:classifiers":[
        {
            "category":"Building & Trades",
            "subcategory":"Construction",
            "type":"Services"
        },
        {
            "category":"Building & Trades",
            "subcategory":"Plumbing",
            "type":"Services"
        }
    ],
    "sg:phone":"+1 763 263 7219",
    "sg:postcode":"55308",
    "sg:province":"MN",
    "sg:tags":[
        "excavation",
        "tank",
        "septic",
        "contractor"
    ],
    "wof:name":"D & M and Sons Inc",
    "wof:placetype":"venue"
},
  "geometry": {"coordinates":[-93.778711,45.450392],"type":"Point"}
}