{
  "type": "Feature",
  "properties": {
    "iso:country":"US",
    "sg:address":"720 Marigold Ter",
    "sg:city":"Minneapolis",
    "sg:classifiers":[
        {
            "category":"Social Services",
            "subcategory":"Child Care",
            "type":"Services"
        }
    ],
    "sg:phone":"+1 763 571 6535",
    "sg:postcode":"55432",
    "sg:province":"MN",
    "sg:tags":[
        "daycare",
        "provider"
    ],
    "wof:name":"Cheryl Knaresboro",
    "wof:placetype":"venue"
},
  "geometry": {"coordinates":[-93.251693,45.073832],"type":"Point"}
}