{
  "type": "Feature",
  "properties": {
    "addr:full":"313 S Mill St Fergus Falls MN 56537",
    "addr:housenumber":"313",
    "addr:postcode":"56537",
    "addr:street":"S Mill St",
    "iso:country":"US",
    "sg:address":"313 S Mill St",
    "sg:city":"Fergus Falls",
    "sg:classifiers":[
        {
            "category":"Social Services",
            "type":"Services"
        }
    ],
    "sg:phone":"+1 218 739 4617",
    "sg:postcode":"56537",
    "sg:province":"MN",
    "sg:tags":[
        "senior",
        "citizen"
    ],
    "wof:name":"West Central Area Agency",
    "wof:placetype":"venue"
},
  "geometry": {"coordinates":[-96.074139,46.281307],"type":"Point"}
}