{
  "type": "Feature",
  "properties": {
    "iso:country":"US",
    "sg:address":"675 E Nicollet Blvd",
    "sg:city":"Burnsville",
    "sg:classifiers":[
        {
            "category":"Health Services",
            "subcategory":"Doctor",
            "type":"Services"
        }
    ],
    "sg:phone":"+1 952 898 5000",
    "sg:postcode":"55337",
    "sg:province":"MN",
    "sg:tags":[
        "physician",
        "surgeon"
    ],
    "wof:name":"Minneapolis Clinic-Neurology",
    "wof:placetype":"venue"
},
  "geometry": {"coordinates":[-93.266256,44.752084],"type":"Point"}
}