{
  "type": "Feature",
  "properties": {
    "addr:full":"13450 Rogers Dr Rogers MN 55374",
    "addr:housenumber":"13450",
    "addr:postcode":"55374",
    "addr:street":"Rogers Dr",
    "iso:country":"US",
    "sg:address":"13450 Rogers Dr",
    "sg:city":"Rogers",
    "sg:classifiers":[
        {
            "category":"Restaurant",
            "type":"Food & Drink"
        }
    ],
    "sg:menulink":"http://www.allmenus.com/mn/rogers/6900-dennys/menu/",
    "sg:phone":"+1 763 428 1574",
    "sg:postcode":"55374",
    "sg:province":"MN",
    "sg:tags":[
        "american",
        "diner"
    ],
    "wof:name":"Denny's",
    "wof:placetype":"venue"
},
  "geometry": {"coordinates":[-93.550149,45.198594],"type":"Point"}
}