{
  "type": "Feature",
  "properties": {
    "addr:full":"920 Anthony Way Victoria MN 55386",
    "addr:housenumber":"920",
    "addr:postcode":"55386",
    "addr:street":"Anthony Way",
    "iso:country":"US",
    "sg:address":"920 Anthony Way",
    "sg:city":"Victoria",
    "sg:classifiers":[
        {
            "category":"Real Estate",
            "subcategory":"Real Estate Services",
            "type":"Services"
        },
        {
            "category":"Real Estate",
            "subcategory":"Real Estate Agent",
            "type":"Services"
        }
    ],
    "sg:phone":"+1 952 448 2777",
    "sg:postcode":"55386",
    "sg:province":"MN",
    "sg:tags":[
        "buyer",
        "broker"
    ],
    "wof:name":"Steven And Kathys Realty",
    "wof:placetype":"venue"
},
  "geometry": {"coordinates":[-93.637702,44.86376],"type":"Point"}
}