{
  "type": "Feature",
  "properties": {
    "addr:full":"5421 Dufferin Dr Savage MN 55378",
    "addr:housenumber":"5421",
    "addr:postcode":"55378",
    "addr:street":"Dufferin Dr",
    "iso:country":"US",
    "sg:address":"5421 Dufferin Dr",
    "sg:city":"Savage",
    "sg:classifiers":[
        {
            "category":"Manufacturing",
            "subcategory":"Building Materials",
            "type":"Manufacturing & Wholesale Goods"
        }
    ],
    "sg:phone":"+1 952 440 3912",
    "sg:postcode":"55378",
    "sg:province":"MN",
    "sg:tags":[
        "mfg",
        "wood",
        "kitchen",
        "cabinet"
    ],
    "wof:name":"David Grotta Custom",
    "wof:placetype":"venue"
},
  "geometry": {"coordinates":[-93.34815999999999,44.735005],"type":"Point"}
}