{
  "type": "Feature",
  "properties": {
    "iso:country":"US",
    "sg:address":"1137 Franklin Dr N",
    "sg:city":"Baxter",
    "sg:classifiers":[
        {
            "category":"Real Estate",
            "subcategory":"Real Estate Agent",
            "type":"Services"
        }
    ],
    "sg:phone":"+1 218 828 9343",
    "sg:postcode":"56425",
    "sg:province":"MN",
    "wof:name":"Realty Connections",
    "wof:placetype":"venue"
},
  "geometry": {"coordinates":[-94.25398199999999,46.368134],"type":"Point"}
}