{
  "type": "Feature",
  "properties": {
    "addr:full":"418 Co Rd D E St Paul MN 55117",
    "addr:housenumber":"418",
    "addr:postcode":"55117",
    "addr:street":"Co Rd D E",
    "iso:country":"US",
    "sg:address":"418 Co Rd D E",
    "sg:city":"St Paul",
    "sg:classifiers":[
        {
            "category":"Building & Trades",
            "subcategory":"Construction",
            "type":"Services"
        }
    ],
    "sg:phone":"+1 651 294 2160",
    "sg:postcode":"55117",
    "sg:province":"MN",
    "sg:tags":[
        "home",
        "builder"
    ],
    "wof:name":"Argus Homes",
    "wof:placetype":"venue"
},
  "geometry": {"coordinates":[-93.07998000000001,45.035376],"type":"Point"}
}