{
  "type": "Feature",
  "properties": {
    "addr:full":"405 Nelson Blvd Montrose MN 55363",
    "addr:housenumber":"405",
    "addr:postcode":"55363",
    "addr:street":"Nelson Blvd",
    "iso:country":"US",
    "sg:address":"405 Nelson Blvd",
    "sg:city":"Montrose",
    "sg:classifiers":[
        {
            "category":"Building & Trades",
            "subcategory":"Construction",
            "type":"Services"
        }
    ],
    "sg:phone":"+1 763 675 3750",
    "sg:postcode":"55363",
    "sg:province":"MN",
    "sg:tags":[
        "general",
        "contractor"
    ],
    "wof:name":"B J Construction",
    "wof:placetype":"venue"
},
  "geometry": {"coordinates":[-93.91477399999999,45.064981],"type":"Point"}
}