{
  "type": "Feature",
  "properties": {
    "addr:full":"619 Camden Dr Marshall MN 56258",
    "addr:housenumber":"619",
    "addr:postcode":"56258",
    "addr:street":"Camden Dr",
    "iso:country":"US",
    "sg:address":"619 Camden Dr",
    "sg:city":"Marshall",
    "sg:classifiers":[
        {
            "category":"Social Services",
            "subcategory":"Child Care",
            "type":"Services"
        }
    ],
    "sg:phone":"+1 507 532 3682",
    "sg:postcode":"56258",
    "sg:province":"MN",
    "sg:tags":[
        "daycare",
        "provider"
    ],
    "wof:name":"Precious Times",
    "wof:placetype":"venue"
},
  "geometry": {"coordinates":[-95.799932,44.437398],"type":"Point"}
}