{
  "type": "Feature",
  "properties": {
    "iso:country":"US",
    "sg:address":"12825 Far Portage Dr",
    "sg:city":"Park Rapids",
    "sg:classifiers":[
        {
            "category":"Building & Trades",
            "subcategory":"Construction",
            "type":"Services"
        }
    ],
    "sg:phone":"+1 218 732 0374",
    "sg:postcode":"56470",
    "sg:province":"MN",
    "sg:tags":[
        "contractor"
    ],
    "wof:name":"Terry Bliss Building",
    "wof:placetype":"venue"
},
  "geometry": {"coordinates":[-95.110955,46.966881],"type":"Point"}
}