{
  "type": "Feature",
  "properties": {
    "addr:full":"421 9th Ave Saint Paul Park MN 55071",
    "addr:housenumber":"421",
    "addr:postcode":"55071",
    "addr:street":"9Th Ave;Park",
    "iso:country":"US",
    "sg:address":"421 9th Ave",
    "sg:city":"Saint Paul Park",
    "sg:classifiers":[
        {
            "category":"Professional",
            "subcategory":"Management & Consulting",
            "type":"Services"
        }
    ],
    "sg:phone":"+1 651 459 6522",
    "sg:postcode":"55071",
    "sg:province":"MN",
    "wof:name":"Osterbeahrs Inc",
    "wof:placetype":"venue"
},
  "geometry": {"coordinates":[-92.993779,44.842318],"type":"Point"}
}