{
  "type": "Feature",
  "properties": {
    "addr:full":"10820 Co Hwy 5 Pelican Rapids MN 56572",
    "addr:housenumber":"10820",
    "addr:postcode":"56572",
    "addr:street":"Co Hwy 5",
    "iso:country":"US",
    "sg:address":"10820 Co Hwy 5",
    "sg:city":"Pelican Rapids",
    "sg:classifiers":[
        {
            "category":"Professional",
            "type":"Services"
        },
        {
            "category":"Professional",
            "subcategory":"Business Services",
            "type":"Services"
        }
    ],
    "sg:phone":"+1 218 532 3732",
    "sg:postcode":"56572",
    "sg:province":"MN",
    "sg:tags":[
        "establishment"
    ],
    "wof:name":"Cormorant Bottle Shop The LL",
    "wof:placetype":"venue"
},
  "geometry": {"coordinates":[-96.078622,46.739687],"type":"Point"}
}