{
  "type": "Feature",
  "properties": {
    "iso:country":"US",
    "sg:address":"12175 Aberdeen St NE",
    "sg:city":"Minneapolis",
    "sg:classifiers":[
        {
            "category":"Health Services",
            "subcategory":"Doctor",
            "type":"Services"
        }
    ],
    "sg:phone":"+1 612 868 3763",
    "sg:postcode":"55449",
    "sg:province":"MN",
    "sg:tags":[
        "medical"
    ],
    "wof:name":"David Holth MD",
    "wof:placetype":"venue"
},
  "geometry": {"coordinates":[-93.23315599999999,45.191311],"type":"Point"}
}