{
  "type": "Feature",
  "properties": {
    "iso:country":"US",
    "sg:address":"2080 Grand Ave",
    "sg:city":"Saint Paul",
    "sg:classifiers":[
        {
            "category":"Professional",
            "type":"Services"
        }
    ],
    "sg:phone":"+1 651 698 4520",
    "sg:postcode":"55105",
    "sg:province":"MN",
    "wof:name":"Dizzy Kid Inc",
    "wof:placetype":"venue"
},
  "geometry": {"coordinates":[-93.18931499999999,44.940042],"type":"Point"}
}