{
  "type": "Feature",
  "properties": {
    "iso:country":"US",
    "sg:address":"8040 Nicollet Ave S",
    "sg:city":"Minneapolis",
    "sg:classifiers":[
        {
            "category":"Restaurant",
            "type":"Food & Drink"
        }
    ],
    "sg:menulink":"http://www.allmenus.com/mn/bloomington/193895-mcdonalds/menu/",
    "sg:postcode":"55420",
    "sg:province":"MN",
    "sg:tags":[
        "burger",
        "american"
    ],
    "wof:name":"McDonald's",
    "wof:placetype":"venue"
},
  "geometry": {"coordinates":[-93.278317,44.857636],"type":"Point"}
}