{
  "type": "Feature",
  "properties": {
    "addr:full":"230 159th Ave NE Anoka MN 55304",
    "addr:housenumber":"230",
    "addr:postcode":"55304",
    "addr:street":"159Th Ave Ne",
    "iso:country":"US",
    "sg:address":"230 159th Ave NE",
    "sg:city":"Anoka",
    "sg:classifiers":[
        {
            "category":"Organizations",
            "subcategory":"Religious Organization",
            "type":"Services"
        }
    ],
    "sg:phone":"+1 763 413 8877",
    "sg:postcode":"55304",
    "sg:province":"MN",
    "wof:name":"House of Jesus Christ",
    "wof:placetype":"venue"
},
  "geometry": {"coordinates":[-93.263384,45.258711],"type":"Point"}
}