{
  "type": "Feature",
  "properties": {
    "iso:country":"US",
    "sg:address":"4045 Brookside Ave",
    "sg:city":"Minneapolis",
    "sg:classifiers":[
        {
            "category":"Health Services",
            "subcategory":"Dentist",
            "type":"Services"
        }
    ],
    "sg:phone":"+1 952 924 0709",
    "sg:postcode":"55416",
    "sg:province":"MN",
    "wof:name":"Brookside Dentistry",
    "wof:placetype":"venue"
},
  "geometry": {"coordinates":[-93.355681,44.927363],"type":"Point"}
}