{
  "type": "Feature",
  "properties": {
    "iso:country":"US",
    "sg:address":"6341 University Ave NE",
    "sg:city":"Minneapolis",
    "sg:classifiers":[
        {
            "category":"Health Services",
            "subcategory":"Doctor",
            "type":"Services"
        }
    ],
    "sg:phone":"+1 612 722 6611",
    "sg:postcode":"55432",
    "sg:province":"MN",
    "sg:tags":[
        "medical"
    ],
    "wof:name":"Andrew Leung MD",
    "wof:placetype":"venue"
},
  "geometry": {"coordinates":[-93.263356,45.079998],"type":"Point"}
}