{
  "type": "Feature",
  "properties": {
    "addr:full":"15301 State Hwy 55 Minneapolis MN 55447",
    "addr:housenumber":"15301",
    "addr:postcode":"55447",
    "addr:street":"State Hwy 55",
    "iso:country":"US",
    "sg:address":"15301 State Hwy 55",
    "sg:city":"Minneapolis",
    "sg:classifiers":[
        {
            "category":"Manufacturing",
            "subcategory":"Electronics",
            "type":"Manufacturing & Wholesale Goods"
        }
    ],
    "sg:phone":"+1 763 557 0087",
    "sg:postcode":"55447",
    "sg:province":"MN",
    "sg:tags":[
        "semiconductor",
        "mfr"
    ],
    "wof:name":"Union Semiconductor Technology",
    "wof:placetype":"venue"
},
  "geometry": {"coordinates":[-93.47661600000001,45.017345],"type":"Point"}
}