{
  "type": "Feature",
  "properties": {
    "addr:full":"3120 Galleria Minneapolis MN 55435",
    "addr:housenumber":"3120",
    "addr:postcode":"55435",
    "addr:street":"Galleria Minneapolis",
    "iso:country":"US",
    "sg:address":"3120 Galleria",
    "sg:city":"Minneapolis",
    "sg:classifiers":[
        {
            "category":"Sports & Exercise",
            "subcategory":"Gym",
            "type":"Entertainment"
        }
    ],
    "sg:phone":"+1 952 922 2660",
    "sg:postcode":"55435",
    "sg:province":"MN",
    "sg:tags":[
        "instruction",
        "gymnastics"
    ],
    "wof:name":"J W Tumbles",
    "wof:placetype":"venue"
},
  "geometry": {"coordinates":[-93.321924,44.877964],"type":"Point"}
}