{
  "type": "Feature",
  "properties": {
    "addr:full":"15751 Eland St NW Anoka MN 55303",
    "addr:housenumber":"15751",
    "addr:postcode":"55303",
    "addr:street":"Eland St Nw",
    "iso:country":"US",
    "sg:address":"15751 Eland St NW",
    "sg:city":"Anoka",
    "sg:classifiers":[
        {
            "category":"Building & Trades",
            "subcategory":"Landscaping Services",
            "type":"Services"
        }
    ],
    "sg:phone":"+1 612 419 3643",
    "sg:postcode":"55303",
    "sg:province":"MN",
    "sg:tags":[
        "lawn",
        "maintenance",
        "grounds"
    ],
    "wof:name":"Teff's Lawn & Snow Svc",
    "wof:placetype":"venue"
},
  "geometry": {"coordinates":[-93.47149,45.257552],"type":"Point"}
}