{
  "type": "Feature",
  "properties": {
    "addr:full":"10670 Lehigh Rd S Hastings MN 55033",
    "addr:housenumber":"10670",
    "addr:postcode":"55033",
    "addr:street":"Lehigh Rd S Hastings",
    "iso:country":"US",
    "sg:address":"10670 Lehigh Rd S",
    "sg:city":"Hastings",
    "sg:classifiers":[
        {
            "category":"Building & Trades",
            "subcategory":"Construction",
            "type":"Services"
        }
    ],
    "sg:phone":"+1 651 459 6494",
    "sg:postcode":"55033",
    "sg:province":"MN",
    "sg:tags":[
        "excavation",
        "industrial",
        "contractors-commercial",
        "contractor"
    ],
    "wof:name":"Eagan Excavating Co",
    "wof:placetype":"venue"
},
  "geometry": {"coordinates":[-92.86664399999999,44.79655],"type":"Point"}
}