{
  "type": "Feature",
  "properties": {
    "iso:country":"US",
    "sg:address":"10 Rosedale Shopping Center",
    "sg:city":"Saint Paul",
    "sg:classifiers":[
        {
            "category":"Shopping",
            "type":"Retail Goods"
        }
    ],
    "sg:phone":"+1 651 636 5169",
    "sg:postcode":"55113",
    "sg:province":"MN",
    "sg:tags":[
        "merchandise"
    ],
    "wof:name":"Verizon",
    "wof:placetype":"venue"
},
  "geometry": {"coordinates":[-93.17129300000001,45.014121],"type":"Point"}
}