{
  "type": "Feature",
  "properties": {
    "addr:full":"101 Minnesota Ave SW Bemidji MN 56601",
    "addr:housenumber":"101",
    "addr:postcode":"56601",
    "addr:street":"Minnesota Ave Sw",
    "iso:country":"US",
    "sg:address":"101 Minnesota Ave SW",
    "sg:city":"Bemidji",
    "sg:classifiers":[
        {
            "category":"Wholesale",
            "subcategory":"Machinery & Supplies",
            "type":"Manufacturing & Wholesale Goods"
        }
    ],
    "sg:phone":"+1 218 751 1550",
    "sg:postcode":"56601",
    "sg:province":"MN",
    "sg:tags":[
        "janitor"
    ],
    "wof:name":"Bemidji Paper Sales",
    "wof:placetype":"venue"
},
  "geometry": {"coordinates":[-94.882706,47.468792],"type":"Point"}
}