{
  "type": "Feature",
  "properties": {
    "addr:full":"29118 US Hwy 59 Callaway MN 56521",
    "addr:postcode":"29118;56521",
    "addr:street":"Us Hwy 59",
    "iso:country":"US",
    "sg:address":"29118 US Hwy 59",
    "sg:city":"Callaway",
    "sg:classifiers":[
        {
            "category":"Professional",
            "subcategory":"Business Services",
            "type":"Services"
        }
    ],
    "sg:phone":"+1 218 375 2291",
    "sg:postcode":"56521",
    "sg:province":"MN",
    "wof:name":"Franklin Enterprises",
    "wof:placetype":"venue"
},
  "geometry": {"coordinates":[-95.912693,46.992694],"type":"Point"}
}