{
  "type": "Feature",
  "properties": {
    "iso:country":"US",
    "sg:address":"3445 Commonwealth Ave",
    "sg:city":"Saint Paul",
    "sg:classifiers":[
        {
            "category":"Real Estate",
            "subcategory":"Real Estate Agent",
            "type":"Services"
        }
    ],
    "sg:phone":"+1 651 730 7175",
    "sg:postcode":"55125",
    "sg:province":"MN",
    "wof:name":"Moore & Assocs Realty",
    "wof:placetype":"venue"
},
  "geometry": {"coordinates":[-92.950293,44.899096],"type":"Point"}
}