{
  "type": "Feature",
  "properties": {
    "iso:country":"US",
    "sg:address":"2914 Constance Blvd NE",
    "sg:city":"Anoka",
    "sg:classifiers":[
        {
            "category":"Building & Trades",
            "subcategory":"Construction",
            "type":"Services"
        }
    ],
    "sg:phone":"+1 763 434 5429",
    "sg:postcode":"55304",
    "sg:province":"MN",
    "sg:tags":[
        "house"
    ],
    "wof:name":"Gillund Construction Inc",
    "wof:placetype":"venue"
},
  "geometry": {"coordinates":[-93.193021,45.265632],"type":"Point"}
}