{
  "type": "Feature",
  "properties": {
    "addr:full":"3755 25th St SE Rochester MN 55904",
    "addr:housenumber":"3755",
    "addr:postcode":"55904",
    "addr:street":"25Th St Se",
    "iso:country":"US",
    "sg:address":"3755 25th St SE",
    "sg:city":"Rochester",
    "sg:classifiers":[
        {
            "category":"Wholesale",
            "subcategory":"Metals & Minerals",
            "type":"Manufacturing & Wholesale Goods"
        }
    ],
    "sg:phone":"+1 507 285 5389",
    "sg:postcode":"55904",
    "sg:province":"MN",
    "sg:tags":[
        "pipe"
    ],
    "wof:name":"Minnesota Pipe & Equipment",
    "wof:placetype":"venue"
},
  "geometry": {"coordinates":[-92.39971300000001,43.985395],"type":"Point"}
}