{
  "type": "Feature",
  "properties": {
    "addr:full":"1311 Bemidji Ave N Bemidji MN 56601",
    "addr:housenumber":"1311",
    "addr:postcode":"56601",
    "addr:street":"Bemidji Ave N",
    "iso:country":"US",
    "sg:address":"1311 Bemidji Ave N",
    "sg:city":"Bemidji",
    "sg:classifiers":[
        {
            "category":"Health Services",
            "subcategory":"Doctor",
            "type":"Services"
        }
    ],
    "sg:phone":"+1 218 751 1111",
    "sg:postcode":"56601",
    "sg:province":"MN",
    "sg:tags":[
        "dentist"
    ],
    "wof:name":"North Country Dental Svc",
    "wof:placetype":"venue"
},
  "geometry": {"coordinates":[-94.879683,47.48149],"type":"Point"}
}