{
  "type": "Feature",
  "properties": {
    "iso:country":"US",
    "sg:address":"580 Westwood Ln",
    "sg:city":"Chaska",
    "sg:classifiers":[
        {
            "category":"Banks & Credit Unions",
            "subcategory":"Financial Services",
            "type":"Services"
        }
    ],
    "sg:phone":"+1 952 448 7073",
    "sg:postcode":"55318",
    "sg:province":"MN",
    "sg:tags":[
        "trust",
        "investment",
        "real estate"
    ],
    "wof:name":"Westwood Investments LLC",
    "wof:placetype":"venue"
},
  "geometry": {"coordinates":[-93.613713,44.812209],"type":"Point"}
}