{
  "type": "Feature",
  "properties": {
    "iso:country":"US",
    "sg:address":"6248 Lakeland Ave N",
    "sg:city":"Minneapolis",
    "sg:classifiers":[
        {
            "category":"Shopping",
            "type":"Retail Goods"
        }
    ],
    "sg:phone":"+1 763 537 3422",
    "sg:postcode":"55428",
    "sg:province":"MN",
    "sg:tags":[
        "trophy",
        "metal",
        "plaque",
        "medallion"
    ],
    "wof:name":"Viking Trophies Incorporated",
    "wof:placetype":"venue"
},
  "geometry": {"coordinates":[-93.36536700000001,45.065681],"type":"Point"}
}