{
  "type": "Feature",
  "properties": {
    "addr:full":"5500 Riverwood Ln Savage MN 55378",
    "addr:housenumber":"5500",
    "addr:postcode":"55378",
    "addr:street":"Riverwood Ln",
    "iso:country":"US",
    "sg:address":"5500 Riverwood Ln",
    "sg:city":"Savage",
    "sg:classifiers":[
        {
            "category":"Building & Trades",
            "subcategory":"Construction",
            "type":"Services"
        }
    ],
    "sg:phone":"+1 612 750 1824",
    "sg:postcode":"55378",
    "sg:province":"MN",
    "sg:tags":[
        "painter"
    ],
    "wof:name":"GTR Execucare",
    "wof:placetype":"venue"
},
  "geometry": {"coordinates":[-93.348857,44.765353],"type":"Point"}
}