{
  "type": "Feature",
  "properties": {
    "addr:full":"2101 Carnelian Ln Saint Paul MN 55122",
    "addr:housenumber":"2101",
    "addr:postcode":"55122",
    "addr:street":"Carnelian Ln",
    "iso:country":"US",
    "sg:address":"2101 Carnelian Ln",
    "sg:city":"Saint Paul",
    "sg:classifiers":[
        {
            "category":"Building & Trades",
            "subcategory":"Construction",
            "type":"Services"
        }
    ],
    "sg:phone":"+1 651 405 8824",
    "sg:postcode":"55122",
    "sg:province":"MN",
    "sg:tags":[
        "hanging",
        "contractor"
    ],
    "wof:name":"Martens Paul Painting Inc",
    "wof:placetype":"venue"
},
  "geometry": {"coordinates":[-93.213443,44.810445],"type":"Point"}
}