{
  "type": "Feature",
  "properties": {
    "iso:country":"US",
    "sg:address":"12940 Revere Ln N",
    "sg:city":"Champlin",
    "sg:classifiers":[
        {
            "category":"Social Services",
            "subcategory":"Child Care",
            "type":"Services"
        }
    ],
    "sg:phone":"+1 763 427 8601",
    "sg:postcode":"55316",
    "sg:province":"MN",
    "sg:tags":[
        "day"
    ],
    "wof:name":"Theresa Nauer",
    "wof:placetype":"venue"
},
  "geometry": {"coordinates":[-93.41271399999999,45.18883],"type":"Point"}
}