{
  "type": "Feature",
  "properties": {
    "addr:full":"280 3rd St SW Cokato MN 55321",
    "addr:housenumber":"280",
    "addr:postcode":"55321",
    "addr:street":"3Rd St Sw",
    "iso:country":"US",
    "sg:address":"280 3rd St SW",
    "sg:city":"Cokato",
    "sg:classifiers":[
        {
            "category":"Organizations",
            "subcategory":"Religious Organization",
            "type":"Services"
        }
    ],
    "sg:phone":"+1 320 286 5964",
    "sg:postcode":"55321",
    "sg:province":"MN",
    "sg:tags":[
        "church"
    ],
    "wof:name":"Evangelical Lutheran Church",
    "wof:placetype":"venue"
},
  "geometry": {"coordinates":[-94.19214599999999,45.076229],"type":"Point"}
}