{
  "type": "Feature",
  "properties": {
    "iso:country":"US",
    "sg:address":"7225 Ohms Ln Ste 160",
    "sg:city":"Minneapolis",
    "sg:classifiers":[
        {
            "category":"Professional",
            "subcategory":"Engineering",
            "type":"Services"
        }
    ],
    "sg:phone":"+1 952 831 1180",
    "sg:postcode":"55439",
    "sg:province":"MN",
    "sg:tags":[
        "consulting",
        "electrical",
        "mechanical",
        "electronic",
        "engineer"
    ],
    "wof:name":"Wentz Associates Inc",
    "wof:placetype":"venue"
},
  "geometry": {"coordinates":[-93.354958,44.871843],"type":"Point"}
}