{
  "type": "Feature",
  "properties": {
    "iso:country":"US",
    "sg:address":"22881 178th Ave",
    "sg:city":"Cold Spring",
    "sg:classifiers":[
        {
            "category":"Organizations",
            "subcategory":"Religious Organization",
            "type":"Services"
        }
    ],
    "sg:phone":"+1 320 597 7777",
    "sg:postcode":"56320",
    "sg:province":"MN",
    "sg:website":"www.riveroflifeag.org",
    "wof:name":"River Of Life Assembly Of God",
    "wof:placetype":"venue"
},
  "geometry": {"coordinates":[-94.475767,45.454859],"type":"Point"}
}