{
  "type": "Feature",
  "properties": {
    "iso:country":"US",
    "sg:address":"318 3rd St NW",
    "sg:city":"East Grand Forks",
    "sg:classifiers":[
        {
            "category":"Organizations",
            "subcategory":"Non-profit Organization",
            "type":"Services"
        }
    ],
    "sg:phone":"+1 218 773 6100",
    "sg:postcode":"56721",
    "sg:province":"MN",
    "sg:tags":[
        "disability"
    ],
    "wof:name":"Options Interstate Resource",
    "wof:placetype":"venue"
},
  "geometry": {"coordinates":[-97.025508,47.929054],"type":"Point"}
}