{
  "type": "Feature",
  "properties": {
    "addr:full":"27895 Hwy 71 Belgrade MN 56312",
    "addr:housenumber":"27895",
    "addr:postcode":"56312",
    "addr:street":"Hwy 71",
    "iso:country":"US",
    "sg:address":"27895 Hwy 71",
    "sg:city":"Belgrade",
    "sg:classifiers":[
        {
            "category":"Farming",
            "subcategory":"Dairy Farm",
            "type":"Manufacturing & Wholesale Goods"
        }
    ],
    "sg:phone":"+1 320 697 5689",
    "sg:postcode":"56312",
    "sg:province":"MN",
    "wof:name":"Gary Felling",
    "wof:placetype":"venue"
},
  "geometry": {"coordinates":[-94.947759,45.521077],"type":"Point"}
}