{
  "type": "Feature",
  "properties": {
    "addr:full":"6141 Brookview Ave Minneapolis MN 55424",
    "addr:housenumber":"6141",
    "addr:postcode":"55424",
    "addr:street":"Brookview Ave",
    "iso:country":"US",
    "sg:address":"6141 Brookview Ave",
    "sg:city":"Minneapolis",
    "sg:classifiers":[
        {
            "category":"Communications",
            "subcategory":"Film & Video Production",
            "type":"Services"
        }
    ],
    "sg:phone":"+1 952 925 2352",
    "sg:postcode":"55424",
    "sg:province":"MN",
    "sg:tags":[
        "motion",
        "tv",
        "radio",
        "companies-film"
    ],
    "wof:name":"Wayward Girls Films",
    "wof:placetype":"venue"
},
  "geometry": {"coordinates":[-93.335325,44.891745],"type":"Point"}
}