{
  "type": "Feature",
  "properties": {
    "addr:full":"14 E Derrynane St Le Center MN 56057",
    "addr:housenumber":"14",
    "addr:postcode":"56057",
    "addr:street":"E Derrynane St",
    "iso:country":"US",
    "sg:address":"14 E Derrynane St",
    "sg:city":"Le Center",
    "sg:classifiers":[
        {
            "category":"Cinema",
            "subcategory":"Movie Rental",
            "type":"Entertainment"
        }
    ],
    "sg:phone":"+1 507 357 4773",
    "sg:postcode":"56057",
    "sg:province":"MN",
    "sg:tags":[
        "leasing",
        "video",
        "disc",
        "tape"
    ],
    "wof:name":"Lecenter Video & More",
    "wof:placetype":"venue"
},
  "geometry": {"coordinates":[-93.731407,44.384458],"type":"Point"}
}