{
  "type": "Feature",
  "properties": {
    "addr:full":"8081 45th Ave SW Raymond MN 56282",
    "addr:housenumber":"8081",
    "addr:postcode":"56282",
    "addr:street":"45Th Ave Sw",
    "iso:country":"US",
    "sg:address":"8081 45th Ave SW",
    "sg:city":"Raymond",
    "sg:classifiers":[
        {
            "category":"Farming",
            "subcategory":"Livestock Farm",
            "type":"Manufacturing & Wholesale Goods"
        }
    ],
    "sg:phone":"+1 320 231 1052",
    "sg:postcode":"56282",
    "sg:province":"MN",
    "sg:tags":[
        "hog",
        "broker"
    ],
    "wof:name":"Midwest Direct Feeder Pigs",
    "wof:placetype":"venue"
},
  "geometry": {"coordinates":[-95.154685,45.080685],"type":"Point"}
}