{
  "type": "Feature",
  "properties": {
    "iso:country":"US",
    "sg:address":"1120 220th St W",
    "sg:city":"Farmington",
    "sg:classifiers":[
        {
            "category":"Manufacturing",
            "subcategory":"Electronics",
            "type":"Manufacturing & Wholesale Goods"
        }
    ],
    "sg:phone":"+1 651 460 6616",
    "sg:postcode":"55024",
    "sg:province":"MN",
    "sg:tags":[
        "mfg",
        "equipment",
        "industrial",
        "communication"
    ],
    "wof:name":"Genave Nrc Inc",
    "wof:placetype":"venue"
},
  "geometry": {"coordinates":[-93.08766,44.630388],"type":"Point"}
}