{
  "type": "Feature",
  "properties": {
    "addr:full":"470 Rice Creek Blvd Minneapolis MN 55432",
    "addr:housenumber":"470",
    "addr:postcode":"55432",
    "addr:street":"Rice Creek Blvd",
    "iso:country":"US",
    "sg:address":"470 Rice Creek Blvd",
    "sg:city":"Minneapolis",
    "sg:classifiers":[
        {
            "category":"Real Estate",
            "subcategory":"Real Estate Agent",
            "type":"Services"
        }
    ],
    "sg:phone":"+1 763 574 9551",
    "sg:postcode":"55432",
    "sg:province":"MN",
    "wof:name":"Grey Fox Realty Inc",
    "wof:placetype":"venue"
},
  "geometry": {"coordinates":[-93.260935,45.090473],"type":"Point"}
}