{
  "type": "Feature",
  "properties": {
    "addr:full":"1501 Hennepin Ave Minneapolis MN 55403",
    "addr:housenumber":"1501",
    "addr:postcode":"55403",
    "addr:street":"Hennepin Ave",
    "iso:country":"US",
    "sg:address":"1501 Hennepin Ave",
    "sg:city":"Minneapolis",
    "sg:classifiers":[
        {
            "category":"Education",
            "subcategory":"University",
            "type":"Public Place"
        }
    ],
    "sg:phone":"+1 612 341 7000",
    "sg:postcode":"55403",
    "sg:province":"MN",
    "sg:tags":[
        "college"
    ],
    "sg:website":"www.minneapolis.edu",
    "wof:name":"Minneapolis Community and Technical College",
    "wof:placetype":"venue"
},
  "geometry": {"coordinates":[-93.284103,44.973202],"type":"Point"}
}