{
  "type": "Feature",
  "properties": {
    "addr:full":"24615 Pine Ridge Rd Pierz MN 56364",
    "addr:housenumber":"24615",
    "addr:postcode":"56364",
    "addr:street":"Pine Ridge Rd",
    "iso:country":"US",
    "sg:address":"24615 Pine Ridge Rd",
    "sg:city":"Pierz",
    "sg:classifiers":[
        {
            "category":"Autos & Motor Vehicles",
            "subcategory":"Auto Supplies",
            "type":"Retail Goods"
        }
    ],
    "sg:phone":"+1 320 468 6983",
    "sg:postcode":"56364",
    "sg:province":"MN",
    "sg:tags":[
        "tavern",
        "grocery",
        "tire",
        "operates"
    ],
    "wof:name":"R & R Tire Service",
    "wof:placetype":"venue"
},
  "geometry": {"coordinates":[-94.143371,45.968824],"type":"Point"}
}