{
  "type": "Feature",
  "properties": {
    "iso:country":"US",
    "sg:address":"1439 State Hwy 120",
    "sg:city":"St Paul",
    "sg:classifiers":[
        {
            "category":"Professional",
            "subcategory":"Accounting & Tax Preparation",
            "type":"Services"
        }
    ],
    "sg:phone":"+1 651 774 2861",
    "sg:postcode":"55128",
    "sg:province":"MN",
    "sg:tags":[
        "return",
        "filing"
    ],
    "wof:name":"Mielke's Tax Svc",
    "wof:placetype":"venue"
},
  "geometry": {"coordinates":[-92.98475999999999,44.969773],"type":"Point"}
}