{
  "type": "Feature",
  "properties": {
    "addr:full":"207 1st St S Montgomery MN 56069",
    "addr:housenumber":"207",
    "addr:postcode":"56069",
    "addr:street":"1St St S",
    "iso:country":"US",
    "sg:address":"207 1st St S",
    "sg:city":"Montgomery",
    "sg:classifiers":[
        {
            "category":"Health Services",
            "subcategory":"Chiropractor",
            "type":"Services"
        }
    ],
    "sg:phone":"+1 507 364 8608",
    "sg:postcode":"56069",
    "sg:province":"MN",
    "wof:name":"Montgomery Chiropractic Clinic",
    "wof:placetype":"venue"
},
  "geometry": {"coordinates":[-93.581035,44.437658],"type":"Point"}
}