{
  "type": "Feature",
  "properties": {
    "iso:country":"US",
    "sg:address":"107 Main St N",
    "sg:city":"Aurora",
    "sg:classifiers":[
        {
            "category":"Insurance",
            "subcategory":"Insurance Agent",
            "type":"Services"
        },
        {
            "category":"Insurance",
            "subcategory":"Hazard Insurance",
            "type":"Services"
        },
        {
            "category":"Insurance",
            "subcategory":"Title Insurance",
            "type":"Services"
        }
    ],
    "sg:phone":"+1 218 229 3811",
    "sg:postcode":"55705",
    "sg:province":"MN",
    "sg:tags":[
        "auto",
        "homeowner"
    ],
    "sg:website":"http://apps.amfam.com/agentlocator/TCRAMER?sourceid=yp3",
    "wof:name":"American Family Insurance- Thomas P Cramer",
    "wof:placetype":"venue"
},
  "geometry": {"coordinates":[-92.236817,47.528057],"type":"Point"}
}