{
  "type": "Feature",
  "properties": {
    "iso:country":"US",
    "sg:address":"9840 Norma Ln",
    "sg:city":"Saint Paul",
    "sg:classifiers":[
        {
            "category":"Travel",
            "subcategory":"Hotels & Motels",
            "type":"Entertainment"
        }
    ],
    "sg:phone":"+1 651 702 0200",
    "sg:postcode":"55125",
    "sg:province":"MN",
    "sg:tags":[
        "operation"
    ],
    "wof:name":"Holiday Inn",
    "wof:placetype":"venue"
},
  "geometry": {"coordinates":[-92.90494,44.946795],"type":"Point"}
}