{
  "type": "Feature",
  "properties": {
    "iso:country":"US",
    "sg:address":"2070 W 96th St",
    "sg:city":"Minneapolis",
    "sg:classifiers":[
        {
            "category":"Health Services",
            "subcategory":"Health Practitioner",
            "type":"Services"
        }
    ],
    "sg:phone":"+1 952 888 9549",
    "sg:postcode":"55431",
    "sg:province":"MN",
    "sg:tags":[
        "therapy",
        "physical"
    ],
    "wof:name":"Body Balance For Performance",
    "wof:placetype":"venue"
},
  "geometry": {"coordinates":[-93.306658,44.830063],"type":"Point"}
}