{
  "type": "Feature",
  "properties": {
    "iso:country":"US",
    "sg:address":"1533 Roundhouse Cir S",
    "sg:city":"Shakopee",
    "sg:classifiers":[
        {
            "category":"Retail",
            "subcategory":"Car Wash",
            "type":"Services"
        }
    ],
    "sg:phone":"+1 952 233 0613",
    "sg:postcode":"55379",
    "sg:province":"MN",
    "sg:tags":[
        "carwash"
    ],
    "wof:name":"Every Last Detail",
    "wof:placetype":"venue"
},
  "geometry": {"coordinates":[-93.503817,44.791321],"type":"Point"}
}