{
  "type": "Feature",
  "properties": {
    "addr:full":"510 Douglas Ave Henning MN 56551",
    "addr:housenumber":"510",
    "addr:postcode":"56551",
    "addr:street":"Douglas Ave",
    "iso:country":"US",
    "sg:address":"510 Douglas Ave",
    "sg:city":"Henning",
    "sg:classifiers":[
        {
            "category":"Food & Beverages",
            "subcategory":"Groceries & Convenience Stores",
            "type":"Retail Goods"
        }
    ],
    "sg:phone":"+1 218 583 2732",
    "sg:postcode":"56551",
    "sg:province":"MN",
    "sg:tags":[
        "grocer"
    ],
    "wof:name":"B & D Town & Country Foods",
    "wof:placetype":"venue"
},
  "geometry": {"coordinates":[-95.444467,46.320924],"type":"Point"}
}