{
  "type": "Feature",
  "properties": {
    "addr:full":"8183 Mayhew Lake Rd NE Sauk Rapids MN 56379",
    "addr:housenumber":"8183",
    "addr:postcode":"56379",
    "addr:street":"Mayhew Lake Rd Ne",
    "iso:country":"US",
    "sg:address":"8183 Mayhew Lake Rd NE",
    "sg:city":"Sauk Rapids",
    "sg:classifiers":[
        {
            "category":"Farming",
            "subcategory":"Dairy Farm",
            "type":"Manufacturing & Wholesale Goods"
        }
    ],
    "sg:phone":"+1 320 251 9201",
    "sg:postcode":"56379",
    "sg:province":"MN",
    "sg:tags":[
        "beef",
        "feedlot",
        "cattle"
    ],
    "wof:name":"Lyle Nelson",
    "wof:placetype":"venue"
},
  "geometry": {"coordinates":[-94.120189,45.680804],"type":"Point"}
}