{
  "type": "Feature",
  "properties": {
    "iso:country":"US",
    "sg:address":"1013 Cliff Rd E",
    "sg:city":"Burnsville",
    "sg:classifiers":[
        {
            "category":"Wholesale",
            "subcategory":"Machinery & Supplies",
            "type":"Manufacturing & Wholesale Goods"
        }
    ],
    "sg:phone":"+1 952 890 4466",
    "sg:postcode":"55337",
    "sg:province":"MN",
    "sg:tags":[
        "glass",
        "product",
        "fiber",
        "manufacturer",
        "chemicals-wholesale"
    ],
    "wof:name":"Chemflo Of Minnesota",
    "wof:placetype":"venue"
},
  "geometry": {"coordinates":[-93.26331500000001,44.790331],"type":"Point"}
}