{
  "type": "Feature",
  "properties": {
    "iso:country":"US",
    "sg:address":"30673 Clear Lake Rd",
    "sg:city":"Albany",
    "sg:classifiers":[
        {
            "category":"Professional",
            "subcategory":"Management & Consulting",
            "type":"Services"
        }
    ],
    "sg:phone":"+1 320 845 4841",
    "sg:postcode":"56307",
    "sg:province":"MN",
    "sg:tags":[
        "retail",
        "direct",
        "sales"
    ],
    "wof:name":"Midway Edibles",
    "wof:placetype":"venue"
},
  "geometry": {"coordinates":[-94.53662300000001,45.568524],"type":"Point"}
}