{
  "type": "Feature",
  "properties": {
    "iso:country":"US",
    "sg:address":"223 Chestnut St E",
    "sg:city":"Stillwater",
    "sg:classifiers":[
        {
            "category":"Retail",
            "subcategory":"Repair Shop",
            "type":"Services"
        }
    ],
    "sg:phone":"+1 651 439 3919",
    "sg:postcode":"55082",
    "sg:province":"MN",
    "sg:tags":[
        "antique",
        "restoring"
    ],
    "wof:name":"Antique Radio Co",
    "wof:placetype":"venue"
},
  "geometry": {"coordinates":[-92.806611,45.055562],"type":"Point"}
}