{
  "type": "Feature",
  "properties": {
    "addr:full":"10909 105th St N Stillwater MN 55082",
    "addr:housenumber":"10909",
    "addr:postcode":"55082",
    "addr:street":"105Th St N",
    "iso:country":"US",
    "sg:address":"10909 105th St N",
    "sg:city":"Stillwater",
    "sg:classifiers":[
        {
            "category":"Building & Trades",
            "subcategory":"Cleaning & Sanitation",
            "type":"Services"
        }
    ],
    "sg:phone":"+1 651 439 1466",
    "sg:postcode":"55082",
    "sg:province":"MN",
    "sg:tags":[
        "house"
    ],
    "wof:name":"Molly Maid Of Ne Metro",
    "wof:placetype":"venue"
},
  "geometry": {"coordinates":[-92.88383899999999,45.101138],"type":"Point"}
}