{
  "type": "Feature",
  "properties": {
    "addr:full":"7651 State Hwy 65 Fridley MN 55432",
    "addr:housenumber":"7651",
    "addr:postcode":"55432",
    "addr:street":"State Hwy 65",
    "iso:country":"US",
    "sg:address":"7651 State Hwy 65",
    "sg:city":"Fridley",
    "sg:classifiers":[
        {
            "category":"Restaurant",
            "type":"Food & Drink"
        }
    ],
    "sg:phone":"+1 763 717 4190",
    "sg:postcode":"55432",
    "sg:province":"MN",
    "sg:tags":[
        "personal",
        "eating"
    ],
    "wof:name":"Minnesota Sports Cafe",
    "wof:placetype":"venue"
},
  "geometry": {"coordinates":[-93.243801,45.107034],"type":"Point"}
}