{
  "type": "Feature",
  "properties": {
    "addr:full":"947 Snelling Ave S Saint Paul MN 55116",
    "addr:housenumber":"947",
    "addr:postcode":"55116",
    "addr:street":"Snelling Ave S",
    "iso:country":"US",
    "sg:address":"947 Snelling Ave S",
    "sg:city":"Saint Paul",
    "sg:classifiers":[
        {
            "category":"Utilities",
            "subcategory":"Telephone",
            "type":"Services"
        }
    ],
    "sg:phone":"+1 952 888 7280",
    "sg:postcode":"55116",
    "sg:province":"MN",
    "sg:tags":[
        "communications"
    ],
    "wof:name":"Global E Science",
    "wof:placetype":"venue"
},
  "geometry": {"coordinates":[-93.167119,44.91316],"type":"Point"}
}