{
  "type": "Feature",
  "properties": {
    "iso:country":"US",
    "sg:address":"8101 Old Carriage Ct",
    "sg:city":"Shakopee",
    "sg:classifiers":[
        {
            "category":"Professional",
            "subcategory":"Art Services",
            "type":"Services"
        }
    ],
    "sg:phone":"+1 952 403 6085",
    "sg:postcode":"55379",
    "sg:province":"MN",
    "sg:tags":[
        "photographers-portrait",
        "videography",
        "photography"
    ],
    "wof:name":"Picture Me Portrait Studios",
    "wof:placetype":"venue"
},
  "geometry": {"coordinates":[-93.415192,44.777679],"type":"Point"}
}