{
  "type": "Feature",
  "properties": {
    "iso:country":"US",
    "sg:address":"1001 Washington Avenue South",
    "sg:city":"Minneapolis",
    "sg:classifiers":[
        {
            "category":"Sports & Exercise",
            "subcategory":"Playing Field",
            "type":"Entertainment"
        }
    ],
    "sg:phone":"+1 612 872 6400",
    "sg:postcode":"55415",
    "sg:province":"MN",
    "sg:tags":[
        "instruction",
        "fitness"
    ],
    "sg:website":"www.flexappealstudios.com",
    "wof:name":"Flex Appeal Studio",
    "wof:placetype":"venue"
},
  "geometry": {"coordinates":[-93.254509,44.975555],"type":"Point"}
}