{
  "type": "Feature",
  "properties": {
    "addr:full":"404 Hope St Mankato MN 56001",
    "addr:housenumber":"404",
    "addr:postcode":"56001",
    "addr:street":"Hope St",
    "iso:country":"US",
    "sg:address":"404 Hope St",
    "sg:city":"Mankato",
    "sg:classifiers":[
        {
            "category":"Wholesale",
            "subcategory":"Medical Equipment & Supplies",
            "type":"Manufacturing & Wholesale Goods"
        }
    ],
    "sg:phone":"+1 507 388 6820",
    "sg:postcode":"56001",
    "sg:province":"MN",
    "wof:name":"Hope Medical Supply Inc",
    "wof:placetype":"venue"
},
  "geometry": {"coordinates":[-93.97448199999999,44.165691],"type":"Point"}
}