{
  "type": "Feature",
  "properties": {
    "addr:full":"2978 Cleveland Ave N St Paul MN 55113",
    "addr:housenumber":"2978",
    "addr:postcode":"55113",
    "addr:street":"Cleveland Ave N",
    "iso:country":"US",
    "sg:address":"2978 Cleveland Ave N",
    "sg:city":"St Paul",
    "sg:classifiers":[
        {
            "category":"Wholesale",
            "subcategory":"Home Furnishings",
            "type":"Manufacturing & Wholesale Goods"
        }
    ],
    "sg:phone":"+1 651 633 3343",
    "sg:postcode":"55113",
    "sg:province":"MN",
    "sg:tags":[
        "material",
        "floor"
    ],
    "wof:name":"T & G Hardwood Inc",
    "wof:placetype":"venue"
},
  "geometry": {"coordinates":[-93.187547,45.032552],"type":"Point"}
}