{
  "type": "Feature",
  "properties": {
    "iso:country":"US",
    "sg:address":"3258 Minnehaha Ave",
    "sg:city":"Minneapolis",
    "sg:classifiers":[
        {
            "category":"Professional",
            "subcategory":"Art Services",
            "type":"Services"
        }
    ],
    "sg:phone":"+1 612 722 3848",
    "sg:postcode":"55406",
    "sg:province":"MN",
    "sg:tags":[
        "photographer"
    ],
    "wof:name":"Greg R Anderson Photography",
    "wof:placetype":"venue"
},
  "geometry": {"coordinates":[-93.230391,44.942974],"type":"Point"}
}