{
  "type": "Feature",
  "properties": {
    "iso:country":"US",
    "sg:address":"8000 Audubon Rd",
    "sg:city":"Chanhassen",
    "sg:classifiers":[
        {
            "category":"Manufacturing",
            "subcategory":"Food",
            "type":"Manufacturing & Wholesale Goods"
        }
    ],
    "sg:phone":"+1 952 474 7444",
    "sg:postcode":"55317",
    "sg:province":"MN",
    "sg:tags":[
        "frozen",
        "fruit"
    ],
    "wof:name":"Pillsbury Inc",
    "wof:placetype":"venue"
},
  "geometry": {"coordinates":[-93.561729,44.859677],"type":"Point"}
}