{
  "type": "Feature",
  "properties": {
    "addr:full":"1206 W Front St Albert Lea MN 56007",
    "addr:housenumber":"1206",
    "addr:postcode":"56007",
    "addr:street":"W Front St",
    "iso:country":"US",
    "sg:address":"1206 W Front St",
    "sg:city":"Albert Lea",
    "sg:classifiers":[
        {
            "category":"Health Services",
            "subcategory":"Optometrist",
            "type":"Services"
        }
    ],
    "sg:phone":"+1 507 373 8214",
    "sg:postcode":"56007",
    "sg:province":"MN",
    "wof:name":"Albert Lea Eye Clinic",
    "wof:placetype":"venue"
},
  "geometry": {"coordinates":[-93.383049,43.644103],"type":"Point"}
}