{
  "type": "Feature",
  "properties": {
    "iso:country":"US",
    "sg:address":"325 Co Rd 81",
    "sg:city":"Osseo",
    "sg:classifiers":[
        {
            "category":"Manufacturing",
            "subcategory":"Chemicals & Compounds",
            "type":"Manufacturing & Wholesale Goods"
        }
    ],
    "sg:phone":"+1 763 424 2044",
    "sg:postcode":"55369",
    "sg:province":"MN",
    "sg:tags":[
        "adhesive",
        "sealant"
    ],
    "wof:name":"Ceram-Traz Corp",
    "wof:placetype":"venue"
},
  "geometry": {"coordinates":[-93.407117,45.11821],"type":"Point"}
}