{
  "type": "Feature",
  "properties": {
    "addr:full":"1205 W Lincoln Ave Fergus Falls MN 56537",
    "addr:housenumber":"1205",
    "addr:postcode":"56537",
    "addr:street":"W Lincoln Ave",
    "iso:country":"US",
    "sg:address":"1205 W Lincoln Ave",
    "sg:city":"Fergus Falls",
    "sg:classifiers":[
        {
            "category":"Food & Beverages",
            "subcategory":"Groceries & Convenience Stores",
            "type":"Retail Goods"
        }
    ],
    "sg:phone":"+1 218 739 5272",
    "sg:postcode":"56537",
    "sg:province":"MN",
    "sg:tags":[
        "grocer"
    ],
    "wof:name":"Sun Mart",
    "wof:placetype":"venue"
},
  "geometry": {"coordinates":[-96.102419,46.284454],"type":"Point"}
}