{
  "type": "Feature",
  "properties": {
    "addr:full":"6980 Oxford St St Louis Park MN 55426",
    "addr:housenumber":"6980",
    "addr:postcode":"55426",
    "addr:street":"Oxford St",
    "iso:country":"US",
    "sg:address":"6980 Oxford St",
    "sg:city":"St Louis Park",
    "sg:classifiers":[
        {
            "category":"Manufacturing",
            "subcategory":"Tools & Machinery",
            "type":"Manufacturing & Wholesale Goods"
        }
    ],
    "sg:phone":"+1 952 922 8890",
    "sg:postcode":"55426",
    "sg:province":"MN",
    "sg:tags":[
        "water"
    ],
    "wof:name":"US Filter",
    "wof:placetype":"venue"
},
  "geometry": {"coordinates":[-93.369314,44.933101],"type":"Point"}
}