{
  "type": "Feature",
  "properties": {
    "addr:full":"44437 330th St Gaylord MN 55334",
    "addr:housenumber":"44437",
    "addr:postcode":"55334",
    "addr:street":"330Th St",
    "iso:country":"US",
    "sg:address":"44437 330th St",
    "sg:city":"Gaylord",
    "sg:classifiers":[
        {
            "category":"Wholesale",
            "subcategory":"Groceries",
            "type":"Manufacturing & Wholesale Goods"
        }
    ],
    "sg:phone":"+1 507 237 2079",
    "sg:postcode":"55334",
    "sg:province":"MN",
    "sg:tags":[
        "general"
    ],
    "wof:name":"B&E Egg Farms",
    "wof:placetype":"venue"
},
  "geometry": {"coordinates":[-94.157279,44.470933],"type":"Point"}
}