{
  "type": "Feature",
  "properties": {
    "iso:country":"US",
    "sg:address":"1857 State 6 NE",
    "sg:city":"Remer",
    "sg:classifiers":[
        {
            "category":"Farming",
            "subcategory":"Aquatic Farm",
            "type":"Manufacturing & Wholesale Goods"
        }
    ],
    "sg:phone":"+1 218 792 5164",
    "sg:postcode":"56672",
    "sg:province":"MN",
    "sg:tags":[
        "hatchery",
        "state",
        "trout"
    ],
    "wof:name":"Spire Valley State Fish Htchy",
    "wof:placetype":"venue"
},
  "geometry": {"coordinates":[-93.94670499999999,46.869528],"type":"Point"}
}