{
  "type": "Feature",
  "properties": {
    "addr:full":"27504 350th St Browerville MN 56438",
    "addr:housenumber":"27504",
    "addr:postcode":"56438",
    "addr:street":"350Th St",
    "iso:country":"US",
    "sg:address":"27504 350th St",
    "sg:city":"Browerville",
    "sg:classifiers":[
        {
            "category":"Manufacturing",
            "subcategory":"Food",
            "type":"Manufacturing & Wholesale Goods"
        },
        {
            "category":"Autos & Motor Vehicles",
            "subcategory":"Auto Supplies",
            "type":"Retail Goods"
        },
        {
            "category":"Farming",
            "subcategory":"Farm",
            "type":"Manufacturing & Wholesale Goods"
        }
    ],
    "sg:phone":"+1 320 594 2402",
    "sg:postcode":"56438",
    "sg:province":"MN",
    "sg:tags":[
        "alfalfa",
        "corn",
        "product"
    ],
    "wof:name":"Dale Katterhagen",
    "wof:placetype":"venue"
},
  "geometry": {"coordinates":[-94.79230200000001,46.13625],"type":"Point"}
}