{
  "type": "Feature",
  "properties": {
    "iso:country":"US",
    "sg:address":"12154 Ensign Ave N",
    "sg:city":"Champlin",
    "sg:classifiers":[
        {
            "category":"Education",
            "subcategory":"Library",
            "type":"Public Place"
        }
    ],
    "sg:phone":"+1 763 427 7982",
    "sg:postcode":"55316",
    "sg:province":"MN",
    "wof:name":"Champlin Branch Hennepin County Library",
    "wof:placetype":"venue"
},
  "geometry": {"coordinates":[-93.394203,45.1745],"type":"Point"}
}