{
  "type": "Feature",
  "properties": {
    "addr:full":"34117 Redwing Ave Shafer MN 55074",
    "addr:housenumber":"34117",
    "addr:postcode":"55074",
    "addr:street":"Redwing Ave",
    "iso:country":"US",
    "sg:address":"34117 Redwing Ave",
    "sg:city":"Shafer",
    "sg:classifiers":[
        {
            "category":"Retail",
            "subcategory":"Repair Shop",
            "type":"Services"
        }
    ],
    "sg:phone":"+1 651 257 3322",
    "sg:postcode":"55074",
    "sg:province":"MN",
    "wof:name":"Advanced Inhome Services",
    "wof:placetype":"venue"
},
  "geometry": {"coordinates":[-92.739392,45.429125],"type":"Point"}
}