{
  "type": "Feature",
  "properties": {
    "iso:country":"US",
    "sg:address":"8901 Lyndale Ave S",
    "sg:city":"Bloomington",
    "sg:classifiers":[
        {
            "category":"Building & Trades",
            "subcategory":"Construction",
            "type":"Services"
        }
    ],
    "sg:phone":"+1 952 346 8161",
    "sg:postcode":"55420",
    "sg:province":"MN",
    "sg:tags":[
        "repairing",
        "house",
        "remodeling",
        "family",
        "contractor"
    ],
    "sg:website":"www.truelinebuilders.com",
    "wof:name":"True Line Builders",
    "wof:placetype":"venue"
},
  "geometry": {"coordinates":[-93.28850300000001,44.841956],"type":"Point"}
}