{
  "type": "Feature",
  "properties": {
    "addr:full":"1075 Diffley Rd Eagan MN 55123",
    "addr:housenumber":"1075",
    "addr:postcode":"55123",
    "addr:street":"Diffley Rd",
    "iso:country":"US",
    "sg:address":"1075 Diffley Rd",
    "sg:city":"Eagan",
    "sg:classifiers":[
        {
            "category":"Restaurant",
            "type":"Food & Drink"
        }
    ],
    "sg:phone":"+1 651 405 1332",
    "sg:postcode":"55123",
    "sg:province":"MN",
    "wof:name":"Mc Donald's",
    "wof:placetype":"venue"
},
  "geometry": {"coordinates":[-93.142624,44.804696],"type":"Point"}
}