{
  "type": "Feature",
  "properties": {
    "iso:country":"US",
    "sg:address":"922 Broadway Ave N",
    "sg:city":"Rochester",
    "sg:classifiers":[
        {
            "category":"Professional",
            "subcategory":"Management & Consulting",
            "type":"Services"
        }
    ],
    "sg:phone":"+1 507 285 5757",
    "sg:postcode":"55906",
    "sg:province":"MN",
    "sg:tags":[
        "consultant"
    ],
    "wof:name":"Bishop Management",
    "wof:placetype":"venue"
},
  "geometry": {"coordinates":[-92.46302,44.032471],"type":"Point"}
}