{
  "type": "Feature",
  "properties": {
    "iso:country":"US",
    "sg:address":"9978 Gappa Rd",
    "sg:city":"Ray",
    "sg:classifiers":[
        {
            "category":"Travel",
            "subcategory":"Hotels & Motels",
            "type":"Entertainment"
        }
    ],
    "sg:phone":"+1 218 875 2161",
    "sg:postcode":"56669",
    "sg:province":"MN",
    "sg:tags":[
        "operation"
    ],
    "wof:name":"Pine Aire Resort",
    "wof:placetype":"venue"
},
  "geometry": {"coordinates":[-93.031102,48.444534],"type":"Point"}
}