{
  "type": "Feature",
  "properties": {
    "iso:country":"US",
    "sg:address":"190 E 5th St",
    "sg:city":"St Paul",
    "sg:classifiers":[
        {
            "category":"Health Services",
            "subcategory":"Doctor",
            "type":"Services"
        }
    ],
    "sg:phone":"+1 651 767 1400",
    "sg:postcode":"55101",
    "sg:province":"MN",
    "sg:tags":[
        "physician",
        "surgeon"
    ],
    "sg:website":"www.stpaulradiology.com",
    "wof:name":"Midwest Radiology",
    "wof:placetype":"venue"
},
  "geometry": {"coordinates":[-93.088792,44.948162],"type":"Point"}
}