{
  "type": "Feature",
  "properties": {
    "iso:country":"US",
    "sg:address":"1137 Robin Ln",
    "sg:city":"Saint Paul",
    "sg:classifiers":[
        {
            "category":"Travel",
            "subcategory":"Travel Agent",
            "type":"Entertainment"
        }
    ],
    "sg:phone":"+1 651 771 5326",
    "sg:postcode":"55112",
    "sg:province":"MN",
    "sg:tags":[
        "agency"
    ],
    "wof:name":"Jamaican Journeys LLC",
    "wof:placetype":"venue"
},
  "geometry": {"coordinates":[-93.21377,45.066964],"type":"Point"}
}