{
  "type": "Feature",
  "properties": {
    "iso:country":"US",
    "sg:address":"11809 Undercliff St NW",
    "sg:city":"Minneapolis",
    "sg:classifiers":[
        {
            "category":"Freight",
            "type":"Transportation"
        }
    ],
    "sg:phone":"+1 763 422 8720",
    "sg:postcode":"55433",
    "sg:province":"MN",
    "sg:tags":[
        "interstate",
        "trucking"
    ],
    "wof:name":"Dash-Hound Express Inc",
    "wof:placetype":"venue"
},
  "geometry": {"coordinates":[-93.358971,45.184938],"type":"Point"}
}