{
  "type": "Feature",
  "properties": {
    "addr:full":"497 14th St Newport MN 55055",
    "addr:housenumber":"497",
    "addr:postcode":"55055",
    "addr:street":"14Th St",
    "iso:country":"US",
    "sg:address":"497 14th St",
    "sg:city":"Newport",
    "sg:classifiers":[
        {
            "category":"Building & Trades",
            "subcategory":"Construction",
            "type":"Services"
        }
    ],
    "sg:phone":"+1 651 768 8262",
    "sg:postcode":"55055",
    "sg:province":"MN",
    "sg:tags":[
        "excavation",
        "contractor"
    ],
    "wof:name":"Bruhn Excavating",
    "wof:placetype":"venue"
},
  "geometry": {"coordinates":[-93.00299699999999,44.869251],"type":"Point"}
}