{
  "type": "Feature",
  "properties": {
    "addr:full":"540 Gateway Blvd Ste 200 Burnsville MN 55337",
    "addr:housenumber":"540",
    "addr:postcode":"55337",
    "addr:street":"Gateway Blvd Ste 200",
    "iso:country":"US",
    "sg:address":"540 Gateway Blvd Ste 200",
    "sg:city":"Burnsville",
    "sg:classifiers":[
        {
            "category":"Banks & Credit Unions",
            "subcategory":"Financial Services",
            "type":"Services"
        }
    ],
    "sg:phone":"+1 952 895 4707",
    "sg:postcode":"55337",
    "sg:province":"MN",
    "sg:tags":[
        "broker",
        "mortgage"
    ],
    "sg:website":"www.edinarealty.com",
    "wof:name":"Edina Realty Mortgage",
    "wof:placetype":"venue"
},
  "geometry": {"coordinates":[-93.2855,44.771702],"type":"Point"}
}