{
  "type": "Feature",
  "properties": {
    "addr:full":"426 NW 4th St Grand Rapids MN 55744",
    "addr:housenumber":"426",
    "addr:postcode":"55744",
    "addr:street":"Nw 4Th St",
    "iso:country":"US",
    "sg:address":"426 NW 4th St",
    "sg:city":"Grand Rapids",
    "sg:classifiers":[
        {
            "category":"Professional",
            "subcategory":"Lawyer & Legal Services",
            "type":"Services"
        }
    ],
    "sg:phone":"+1 218 326 2062",
    "sg:postcode":"55744",
    "sg:province":"MN",
    "wof:name":"Jonak Law Office",
    "wof:placetype":"venue"
},
  "geometry": {"coordinates":[-93.534817,47.235864],"type":"Point"}
}