{
  "type": "Feature",
  "properties": {
    "iso:country":"US",
    "sg:address":"6855 Greenfield Rd",
    "sg:city":"Loretto",
    "sg:classifiers":[
        {
            "category":"Home & Garden",
            "subcategory":"Furniture",
            "type":"Retail Goods"
        }
    ],
    "sg:phone":"+1 763 498 8411",
    "sg:postcode":"55357",
    "sg:province":"MN",
    "sg:tags":[
        "carpentry",
        "contractor"
    ],
    "wof:name":"Custom Design Wood Products",
    "wof:placetype":"venue"
},
  "geometry": {"coordinates":[-93.68675500000001,45.075346],"type":"Point"}
}