{
  "type": "Feature",
  "properties": {
    "iso:country":"US",
    "sg:address":"2501 Humboldt Ave S",
    "sg:city":"Minneapolis",
    "sg:classifiers":[
        {
            "category":"Professional",
            "subcategory":"Business Services",
            "type":"Services"
        }
    ],
    "sg:phone":"+1 612 374 3866",
    "sg:postcode":"55405",
    "sg:province":"MN",
    "sg:tags":[
        "inspection"
    ],
    "wof:name":"Willibby's",
    "wof:placetype":"venue"
},
  "geometry": {"coordinates":[-93.298187,44.957321],"type":"Point"}
}