{
  "type": "Feature",
  "properties": {
    "iso:country":"US",
    "sg:address":"11253 91st Ave N",
    "sg:city":"Osseo",
    "sg:classifiers":[
        {
            "category":"Building & Trades",
            "subcategory":"Construction",
            "type":"Services"
        }
    ],
    "sg:phone":"+1 763 425 7496",
    "sg:postcode":"55369",
    "sg:province":"MN",
    "wof:name":"Aquacare International Inc",
    "wof:placetype":"venue"
},
  "geometry": {"coordinates":[-93.424055,45.119888],"type":"Point"}
}