{
  "type": "Feature",
  "properties": {
    "addr:full":"7031 Hwy 23 SW Raymond MN 56282",
    "addr:housenumber":"7031",
    "addr:postcode":"56282",
    "addr:street":"Hwy 23 Sw",
    "iso:country":"US",
    "sg:address":"7031 Hwy 23 SW",
    "sg:city":"Raymond",
    "sg:classifiers":[
        {
            "category":"Farming",
            "subcategory":"Poultry Farm",
            "type":"Manufacturing & Wholesale Goods"
        }
    ],
    "sg:phone":"+1 320 599 4312",
    "sg:postcode":"56282",
    "sg:province":"MN",
    "sg:tags":[
        "turkey"
    ],
    "wof:name":"Jennie-O Turkey",
    "wof:placetype":"venue"
},
  "geometry": {"coordinates":[-95.124431,45.078032],"type":"Point"}
}