{
  "type": "Feature",
  "properties": {
    "addr:full":"2001 Milwaukee Ave Minneapolis MN 55404",
    "addr:housenumber":"2001",
    "addr:postcode":"55404",
    "addr:street":"Milwaukee Ave",
    "iso:country":"US",
    "sg:address":"2001 Milwaukee Ave",
    "sg:city":"Minneapolis",
    "sg:classifiers":[
        {
            "category":"Retail",
            "subcategory":"Portrait Studio",
            "type":"Services"
        },
        {
            "category":"Professional",
            "subcategory":"Art Services",
            "type":"Services"
        },
        {
            "category":"Professional",
            "subcategory":"Printing & Photocopies",
            "type":"Services"
        }
    ],
    "sg:phone":"+1 612 375 1222",
    "sg:postcode":"55404",
    "sg:province":"MN",
    "sg:tags":[
        "photographers-portrait",
        "darkroom",
        "rental",
        "photographers-commercial",
        "photographic"
    ],
    "wof:name":"Steven Sietzer Studio Inc",
    "wof:placetype":"venue"
},
  "geometry": {"coordinates":[-93.240013,44.962761],"type":"Point"}
}