{
  "type": "Feature",
  "properties": {
    "iso:country":"US",
    "sg:address":"3540 Hoffman Rd E",
    "sg:city":"St Paul",
    "sg:classifiers":[
        {
            "category":"Professional",
            "subcategory":"Testing Lab",
            "type":"Services"
        }
    ],
    "sg:phone":"+1 651 770 2003",
    "sg:postcode":"55110",
    "sg:province":"MN",
    "sg:tags":[
        "laboratory"
    ],
    "sg:website":"www.atctest.com",
    "wof:name":"American Test CTR-Atc",
    "wof:placetype":"venue"
},
  "geometry": {"coordinates":[-93.031564,45.049215],"type":"Point"}
}