{
  "type": "Feature",
  "properties": {
    "addr:full":"2610 E 32nd St Minneapolis MN 55406",
    "addr:housenumber":"2610",
    "addr:postcode":"55406",
    "addr:street":"E 32Nd St",
    "iso:country":"US",
    "sg:address":"2610 E 32nd St",
    "sg:city":"Minneapolis",
    "sg:classifiers":[
        {
            "category":"Autos & Motor Vehicles",
            "subcategory":"Motorcycle Sales",
            "type":"Retail Goods"
        }
    ],
    "sg:phone":"+1 612 729 7200",
    "sg:postcode":"55406",
    "sg:province":"MN",
    "sg:website":"motoprimo.net",
    "wof:name":"Motoprimo Motorsports",
    "wof:placetype":"venue"
},
  "geometry": {"coordinates":[-93.23429899999999,44.944599],"type":"Point"}
}