{
  "type": "Feature",
  "properties": {
    "iso:country":"US",
    "sg:address":"509 Peck St",
    "sg:city":"Murdock",
    "sg:classifiers":[
        {
            "category":"Professional",
            "subcategory":"Lawyer & Legal Services",
            "type":"Services"
        }
    ],
    "sg:phone":"+1 320 875 4531",
    "sg:postcode":"56271",
    "sg:province":"MN",
    "sg:tags":[
        "elder",
        "attorney",
        "law"
    ],
    "wof:name":"Margaret Laughlin",
    "wof:placetype":"venue"
},
  "geometry": {"coordinates":[-95.39144899999999,45.22414],"type":"Point"}
}