{
  "type": "Feature",
  "properties": {
    "addr:full":"805 1st Ave E Alexandria MN 56308",
    "addr:housenumber":"805",
    "addr:postcode":"56308",
    "addr:street":"1St Ave E",
    "iso:country":"US",
    "sg:address":"805 1st Ave E",
    "sg:city":"Alexandria",
    "sg:classifiers":[
        {
            "category":"Shopping",
            "subcategory":"Bicycles & Sporting Goods",
            "type":"Retail Goods"
        }
    ],
    "sg:phone":"+1 320 762 8493",
    "sg:postcode":"56308",
    "sg:province":"MN",
    "wof:name":"Bike & Fitness Co",
    "wof:placetype":"venue"
},
  "geometry": {"coordinates":[-95.366302,45.891089],"type":"Point"}
}