{
  "type": "Feature",
  "properties": {
    "addr:full":"20997 Co Rd K Rollingstone MN 55940",
    "addr:housenumber":"20997",
    "addr:postcode":"55940",
    "addr:street":"Co Rd;Rollingstone",
    "iso:country":"US",
    "sg:address":"20997 Co Rd K",
    "sg:city":"Rollingstone",
    "sg:classifiers":[
        {
            "category":"Retail",
            "subcategory":"Auto Repair",
            "type":"Services"
        }
    ],
    "sg:phone":"+1 507 689 4342",
    "sg:postcode":"55940",
    "sg:province":"MN",
    "sg:tags":[
        "automotive"
    ],
    "wof:name":"Radiator Specialties",
    "wof:placetype":"venue"
},
  "geometry": {"coordinates":[-92.819362,43.935619],"type":"Point"}
}