{
  "type": "Feature",
  "properties": {
    "iso:country":"US",
    "sg:address":"13223 Sunset Trl",
    "sg:city":"Welch",
    "sg:classifiers":[
        {
            "category":"Professional",
            "subcategory":"Management & Consulting",
            "type":"Services"
        }
    ],
    "sg:phone":"+1 651 258 4632",
    "sg:postcode":"55089",
    "sg:province":"MN",
    "wof:name":"Welch Business Services",
    "wof:placetype":"venue"
},
  "geometry": {"coordinates":[-92.77106499999999,44.538516],"type":"Point"}
}