{
  "type": "Feature",
  "properties": {
    "addr:full":"3456 Fairfax Ln Saint Paul MN 55129",
    "addr:housenumber":"3456",
    "addr:postcode":"55129",
    "addr:street":"Fairfax Ln",
    "iso:country":"US",
    "sg:address":"3456 Fairfax Ln",
    "sg:city":"Saint Paul",
    "sg:classifiers":[
        {
            "category":"Home & Garden",
            "subcategory":"Home Furnishings",
            "type":"Retail Goods"
        }
    ],
    "sg:phone":"+1 612 385 8546",
    "sg:postcode":"55129",
    "sg:province":"MN",
    "wof:name":"Windows of Woodbury",
    "wof:placetype":"venue"
},
  "geometry": {"coordinates":[-92.902422,44.899544],"type":"Point"}
}