{
  "type": "Feature",
  "properties": {
    "iso:country":"US",
    "sg:address":"4604 Birchridge Dr",
    "sg:city":"Nisswa",
    "sg:classifiers":[
        {
            "category":"Sports & Exercise",
            "subcategory":"Golf",
            "type":"Entertainment"
        }
    ],
    "sg:phone":"+1 218 963 7451",
    "sg:postcode":"56468",
    "sg:province":"MN",
    "sg:tags":[
        "course",
        "public"
    ],
    "wof:name":"Izod Club",
    "wof:placetype":"venue"
},
  "geometry": {"coordinates":[-94.304261,46.518011],"type":"Point"}
}