{
  "type": "Feature",
  "properties": {
    "iso:country":"US",
    "sg:address":"304 Bloomer St W",
    "sg:city":"Morristown",
    "sg:classifiers":[
        {
            "category":"Home & Garden",
            "subcategory":"Carpets & Floor Coverings",
            "type":"Retail Goods"
        }
    ],
    "sg:phone":"+1 507 685 2464",
    "sg:postcode":"55052",
    "sg:province":"MN",
    "sg:tags":[
        "dealer",
        "rug"
    ],
    "wof:name":"Jerry's Flooring & Cabinets",
    "wof:placetype":"venue"
},
  "geometry": {"coordinates":[-93.448824,44.228345],"type":"Point"}
}