{
  "type": "Feature",
  "properties": {
    "iso:country":"US",
    "sg:address":"2800 Campus Dr #10",
    "sg:city":"Minneapolis",
    "sg:classifiers":[
        {
            "category":"Health Services",
            "subcategory":"Doctor",
            "type":"Services"
        }
    ],
    "sg:phone":"+1 763 515 1688",
    "sg:postcode":"55441",
    "sg:province":"MN",
    "sg:tags":[
        "physician",
        "radiology",
        "family",
        "practice",
        "surgeons",
        "medicine"
    ],
    "sg:website":"http://www.mplsrad.com",
    "wof:name":"Minneapolis Radiology Business Office",
    "wof:placetype":"venue"
},
  "geometry": {"coordinates":[-93.44921100000001,45.010201],"type":"Point"}
}