{
  "type": "Feature",
  "properties": {
    "iso:country":"US",
    "sg:address":"8001 177th Ave NW",
    "sg:city":"Anoka",
    "sg:classifiers":[
        {
            "category":"Professional",
            "type":"Services"
        }
    ],
    "sg:phone":"+1 763 274 0259",
    "sg:postcode":"55303",
    "sg:province":"MN",
    "wof:name":"Howry Residential Service",
    "wof:placetype":"venue"
},
  "geometry": {"coordinates":[-93.471209,45.292179],"type":"Point"}
}