{
  "type": "Feature",
  "properties": {
    "addr:full":"137 Main St Emmons MN 56029",
    "addr:housenumber":"137",
    "addr:postcode":"56029",
    "addr:street":"Main St",
    "iso:country":"US",
    "sg:address":"137 Main St",
    "sg:city":"Emmons",
    "sg:classifiers":[
        {
            "category":"Personal",
            "subcategory":"Beauty Salon",
            "type":"Services"
        }
    ],
    "sg:phone":"+1 507 297 5683",
    "sg:postcode":"56029",
    "sg:province":"MN",
    "wof:name":"Mona's Styles",
    "wof:placetype":"venue"
},
  "geometry": {"coordinates":[-93.48866700000001,43.500206],"type":"Point"}
}