{
  "type": "Feature",
  "properties": {
    "iso:country":"US",
    "sg:address":"7072 Cahill Rd",
    "sg:city":"Edina",
    "sg:classifiers":[
        {
            "category":"Professional",
            "subcategory":"Management & Consulting",
            "type":"Services"
        }
    ],
    "sg:phone":"+1 952 829 1777",
    "sg:postcode":"55439",
    "sg:province":"MN",
    "sg:tags":[
        "consultant",
        "business"
    ],
    "sg:website":"www.lemoncella.com",
    "wof:name":"P 10 Performance Consultants",
    "wof:placetype":"venue"
},
  "geometry": {"coordinates":[-93.363494,44.87639],"type":"Point"}
}