{
  "type": "Feature",
  "properties": {
    "iso:country":"US",
    "sg:address":"5926 Oakwood Mnr NE",
    "sg:city":"Minneapolis",
    "sg:classifiers":[
        {
            "category":"Communications",
            "subcategory":"Television Station",
            "type":"Services"
        }
    ],
    "sg:phone":"+1 763 572 2610",
    "sg:postcode":"55432",
    "sg:province":"MN",
    "sg:tags":[
        "satellite",
        "cable"
    ],
    "wof:name":"Vertex Rch Cable",
    "wof:placetype":"venue"
},
  "geometry": {"coordinates":[-93.231841,45.075135],"type":"Point"}
}