{
  "type": "Feature",
  "properties": {
    "addr:full":"36 Teepeota Cir Wabasha MN 55981",
    "addr:housenumber":"36",
    "addr:postcode":"55981",
    "addr:street":"Teepeota Cir",
    "iso:country":"US",
    "sg:address":"36 Teepeota Cir",
    "sg:city":"Wabasha",
    "sg:classifiers":[
        {
            "category":"Professional",
            "subcategory":"Lawyer & Legal Services",
            "type":"Services"
        }
    ],
    "sg:phone":"+1 651 565 2063",
    "sg:postcode":"55981",
    "sg:province":"MN",
    "wof:name":"Law Office Frederic N Bro",
    "wof:placetype":"venue"
},
  "geometry": {"coordinates":[-91.968824,44.349002],"type":"Point"}
}