{
  "type": "Feature",
  "properties": {
    "iso:country":"US",
    "sg:address":"3948 W 50th St Ste 212",
    "sg:city":"Minneapolis",
    "sg:classifiers":[
        {
            "category":"Professional",
            "subcategory":"Advertising",
            "type":"Services"
        }
    ],
    "sg:phone":"+1 952 915 6065",
    "sg:postcode":"55424",
    "sg:province":"MN",
    "sg:tags":[
        "agency"
    ],
    "sg:website":"http://www.ianinc.net",
    "wof:name":"I.A.N",
    "wof:placetype":"venue"
},
  "geometry": {"coordinates":[-93.32969799999999,44.912537],"type":"Point"}
}