{
  "type": "Feature",
  "properties": {
    "addr:full":"2524 14th St NE Faribault MN 55021",
    "addr:housenumber":"2524",
    "addr:postcode":"55021",
    "addr:street":"14Th St Ne",
    "iso:country":"US",
    "sg:address":"2524 14th St NE",
    "sg:city":"Faribault",
    "sg:classifiers":[
        {
            "category":"Professional",
            "subcategory":"Business Services",
            "type":"Services"
        }
    ],
    "sg:phone":"+1 507 333 9022",
    "sg:postcode":"55021",
    "sg:province":"MN",
    "wof:name":"B & S Turning Point",
    "wof:placetype":"venue"
},
  "geometry": {"coordinates":[-93.249289,44.316286],"type":"Point"}
}