{
  "type": "Feature",
  "properties": {
    "addr:full":"62836 320th St Wadena MN 56482",
    "addr:housenumber":"62836",
    "addr:postcode":"56482",
    "addr:street":"320Th St",
    "iso:country":"US",
    "sg:address":"62836 320th St",
    "sg:city":"Wadena",
    "sg:classifiers":[
        {
            "category":"Manufacturing",
            "subcategory":"Building Materials",
            "type":"Manufacturing & Wholesale Goods"
        }
    ],
    "sg:phone":"+1 218 631 4165",
    "sg:postcode":"56482",
    "sg:province":"MN",
    "sg:tags":[
        "cabinet",
        "wood",
        "kitchen",
        "mfg"
    ],
    "wof:name":"Goeden Woodworking",
    "wof:placetype":"venue"
},
  "geometry": {"coordinates":[-95.183384,46.427036],"type":"Point"}
}