{
  "type": "Feature",
  "properties": {
    "iso:country":"US",
    "sg:address":"920 102nd Ln NE",
    "sg:city":"Minneapolis",
    "sg:classifiers":[
        {
            "category":"Professional",
            "type":"Services"
        }
    ],
    "sg:phone":"+1 763 783 0188",
    "sg:postcode":"55434",
    "sg:province":"MN",
    "wof:name":"William Momo Giddings and Flax",
    "wof:placetype":"venue"
},
  "geometry": {"coordinates":[-93.247238,45.15673],"type":"Point"}
}