{
  "type": "Feature",
  "properties": {
    "iso:country":"US",
    "sg:address":"10527 202nd St W",
    "sg:city":"Lakeville",
    "sg:classifiers":[
        {
            "category":"Building & Trades",
            "subcategory":"Landscaping Services",
            "type":"Services"
        }
    ],
    "sg:phone":"+1 952 469 2418",
    "sg:postcode":"55044",
    "sg:province":"MN",
    "sg:tags":[
        "business"
    ],
    "wof:name":"Allstate Crane Service",
    "wof:placetype":"venue"
},
  "geometry": {"coordinates":[-93.27814100000001,44.656192],"type":"Point"}
}