{
  "type": "Feature",
  "properties": {
    "iso:country":"US",
    "sg:address":"26025 3rd St W",
    "sg:city":"Zimmerman",
    "sg:classifiers":[
        {
            "category":"Food & Beverages",
            "subcategory":"Liquor & Beverages",
            "type":"Retail Goods"
        }
    ],
    "sg:phone":"+1 763 856 5350",
    "sg:postcode":"55398",
    "sg:province":"MN",
    "sg:tags":[
        "alcoholic"
    ],
    "wof:name":"P & A Liquor LLC",
    "wof:placetype":"venue"
},
  "geometry": {"coordinates":[-93.59180499999999,45.44201],"type":"Point"}
}