{
  "type": "Feature",
  "properties": {
    "addr:full":"1 Main St SE Ste 600 Minneapolis MN 55414",
    "addr:housenumber":"1",
    "addr:postcode":"55414",
    "addr:street":"Main St Se Ste 600",
    "iso:country":"US",
    "sg:address":"1 Main St SE Ste 600",
    "sg:city":"Minneapolis",
    "sg:classifiers":[
        {
            "category":"Communications",
            "subcategory":"Television Station",
            "type":"Services"
        }
    ],
    "sg:phone":"+1 612 486 9500",
    "sg:postcode":"55414",
    "sg:province":"MN",
    "wof:name":"Fox Sports Net North",
    "wof:placetype":"venue"
},
  "geometry": {"coordinates":[-93.25905899999999,44.986996],"type":"Point"}
}