{
  "type": "Feature",
  "properties": {
    "addr:full":"3740 Centerville Rd St Paul MN 55127",
    "addr:housenumber":"3740",
    "addr:postcode":"55127",
    "addr:street":"Centerville Rd",
    "iso:country":"US",
    "sg:address":"3740 Centerville Rd",
    "sg:city":"St Paul",
    "sg:classifiers":[
        {
            "category":"Building & Trades",
            "subcategory":"Construction",
            "type":"Services"
        }
    ],
    "sg:phone":"+1 651 429 9271",
    "sg:postcode":"55127",
    "sg:province":"MN",
    "sg:tags":[
        "excavating",
        "contractor"
    ],
    "wof:name":"Sun Excavating",
    "wof:placetype":"venue"
},
  "geometry": {"coordinates":[-93.062484,45.054618],"type":"Point"}
}