{
  "type": "Feature",
  "properties": {
    "iso:country":"US",
    "sg:address":"22446 690th Ave",
    "sg:city":"Alden",
    "sg:phone":"+1 507 874 3388",
    "sg:postcode":"56009",
    "sg:province":"MN",
    "sg:tags":[
        "farm",
        "corn",
        "soybean"
    ],
    "wof:name":"Dokken Wilford",
    "wof:placetype":"venue"
},
  "geometry": {"coordinates":[-93.48869500000001,43.687349],"type":"Point"}
}