{
  "type": "Feature",
  "properties": {
    "iso:country":"US",
    "sg:address":"3200 Lexington Ave N",
    "sg:city":"Shoreview",
    "sg:classifiers":[
        {
            "category":"Health Services",
            "subcategory":"Doctor",
            "type":"Services"
        }
    ],
    "sg:phone":"+1 651 484 7887",
    "sg:postcode":"55126",
    "sg:province":"MN",
    "sg:tags":[
        "dentist"
    ],
    "wof:name":"Posavad",
    "wof:placetype":"venue"
},
  "geometry": {"coordinates":[-93.146902,45.038589],"type":"Point"}
}