{
  "type": "Feature",
  "properties": {
    "addr:full":"13700 275 Ave Detroit Lakes MN 56501",
    "addr:housenumber":"13700",
    "addr:postcode":"56501",
    "addr:street":"275 Ave",
    "iso:country":"US",
    "sg:address":"13700 275 Ave",
    "sg:city":"Detroit Lakes",
    "sg:classifiers":[
        {
            "category":"Professional",
            "subcategory":"Business Services",
            "type":"Services"
        }
    ],
    "sg:phone":"+1 218 847 6178",
    "sg:postcode":"56501",
    "sg:province":"MN",
    "wof:name":"Woodland Outpost Trading Co",
    "wof:placetype":"venue"
},
  "geometry": {"coordinates":[-95.849113,46.774609],"type":"Point"}
}