{
  "type": "Feature",
  "properties": {
    "addr:full":"2400 Stevens Ave Minneapolis MN 55404",
    "addr:housenumber":"2400",
    "addr:postcode":"55404",
    "addr:street":"Stevens Ave",
    "iso:country":"US",
    "sg:address":"2400 Stevens Ave",
    "sg:city":"Minneapolis",
    "sg:classifiers":[
        {
            "category":"Travel",
            "subcategory":"Hotels & Motels",
            "type":"Entertainment"
        },
        {
            "category":"Travel",
            "subcategory":"Hostel",
            "type":"Entertainment"
        }
    ],
    "sg:phone":"+1 612 522 5000",
    "sg:postcode":"55404",
    "sg:province":"MN",
    "sg:tags":[
        "lodging"
    ],
    "wof:name":"Minneapolis International Hostel",
    "wof:placetype":"venue"
},
  "geometry": {"coordinates":[-93.275291,44.95919],"type":"Point"}
}