{
  "type": "Feature",
  "properties": {
    "addr:full":"217 S Jefferson St Minneota MN 56264",
    "addr:housenumber":"217",
    "addr:postcode":"56264",
    "addr:street":"S Jefferson St",
    "iso:country":"US",
    "sg:address":"217 S Jefferson St",
    "sg:city":"Minneota",
    "sg:classifiers":[
        {
            "category":"Insurance",
            "subcategory":"Hazard Insurance",
            "type":"Services"
        }
    ],
    "sg:phone":"+1 507 872 6124",
    "sg:postcode":"56264",
    "sg:province":"MN",
    "sg:tags":[
        "commercial",
        "business"
    ],
    "sg:website":"http://www.swins.com",
    "wof:name":"Doyle Insurance Services",
    "wof:placetype":"venue"
},
  "geometry": {"coordinates":[-95.991103,44.556205],"type":"Point"}
}