{
  "type": "Feature",
  "properties": {
    "iso:country":"US",
    "sg:address":"937 Tile Dr",
    "sg:city":"Red Wing",
    "sg:classifiers":[
        {
            "category":"Building & Trades",
            "subcategory":"Plumbing",
            "type":"Services"
        }
    ],
    "sg:phone":"+1 651 388 2917",
    "sg:postcode":"55066",
    "sg:province":"MN",
    "sg:tags":[
        "plumbing",
        "contractor"
    ],
    "wof:name":"Glenn Klair Plumbing & Heating",
    "wof:placetype":"venue"
},
  "geometry": {"coordinates":[-92.558807,44.556885],"type":"Point"}
}