{
  "type": "Feature",
  "properties": {
    "iso:country":"US",
    "sg:address":"8401 Xerxes Ave S",
    "sg:city":"Bloomington",
    "sg:classifiers":[
        {
            "category":"Education",
            "subcategory":"School",
            "type":"Public Place"
        }
    ],
    "sg:phone":"+1 952 681 5500",
    "sg:postcode":"55431",
    "sg:province":"MN",
    "wof:name":"Washburn Elementary School",
    "wof:placetype":"venue"
},
  "geometry": {"coordinates":[-93.31897600000001,44.8498],"type":"Point"}
}