{
  "type": "Feature",
  "properties": {
    "addr:full":"2224 4th Ave Anoka MN 55303",
    "addr:housenumber":"2224",
    "addr:postcode":"55303",
    "addr:street":"4Th Ave",
    "iso:country":"US",
    "sg:address":"2224 4th Ave",
    "sg:city":"Anoka",
    "sg:classifiers":[
        {
            "category":"Personal",
            "subcategory":"Beauty Salon",
            "type":"Services"
        }
    ],
    "sg:phone":"+1 763 427 3087",
    "sg:postcode":"55303",
    "sg:province":"MN",
    "wof:name":"Lisa Beauty",
    "wof:placetype":"venue"
},
  "geometry": {"coordinates":[-93.385397,45.20038],"type":"Point"}
}