{
  "type": "Feature",
  "properties": {
    "addr:full":"7214 80th St S Sabin MN 56580",
    "addr:housenumber":"7214",
    "addr:postcode":"56580",
    "addr:street":"80Th St S Sabin",
    "iso:country":"US",
    "sg:address":"7214 80th St S",
    "sg:city":"Sabin",
    "sg:classifiers":[
        {
            "category":"Building & Trades",
            "subcategory":"Construction",
            "type":"Services"
        }
    ],
    "sg:phone":"+1 218 790 2844",
    "sg:postcode":"56580",
    "sg:province":"MN",
    "sg:tags":[
        "concrete",
        "contractor"
    ],
    "wof:name":"Saign Construction",
    "wof:placetype":"venue"
},
  "geometry": {"coordinates":[-96.63079399999999,46.786885],"type":"Point"}
}