{
  "type": "Feature",
  "properties": {
    "addr:full":"1870 2nd Ave SE Cambridge MN 55008",
    "addr:housenumber":"1870",
    "addr:postcode":"55008",
    "addr:street":"2Nd Ave Se",
    "iso:country":"US",
    "sg:address":"1870 2nd Ave SE",
    "sg:city":"Cambridge",
    "sg:classifiers":[
        {
            "category":"Shopping",
            "subcategory":"Department Store",
            "type":"Retail Goods"
        },
        {
            "category":"Shopping",
            "type":"Retail Goods"
        }
    ],
    "sg:phone":"+1 763 552 2355",
    "sg:postcode":"55008",
    "sg:province":"MN",
    "sg:tags":[
        "merchandise",
        "variety"
    ],
    "wof:name":"Dollar Bell",
    "wof:placetype":"venue"
},
  "geometry": {"coordinates":[-93.20502399999999,45.571152],"type":"Point"}
}