{
  "type": "Feature",
  "properties": {
    "addr:full":"37558 Co Rd 9 Avon MN 56310",
    "addr:housenumber":"37558;9",
    "addr:postcode":"56310",
    "addr:street":"Co Rd",
    "iso:country":"US",
    "sg:address":"37558 Co Rd 9",
    "sg:city":"Avon",
    "sg:classifiers":[
        {
            "category":"Retail",
            "subcategory":"Repair Shop",
            "type":"Services"
        }
    ],
    "sg:phone":"+1 320 356 7646",
    "sg:postcode":"56310",
    "sg:province":"MN",
    "sg:tags":[
        "mfg"
    ],
    "wof:name":"Upholstery Shop",
    "wof:placetype":"venue"
},
  "geometry": {"coordinates":[-94.47730799999999,45.667123],"type":"Point"}
}