{
  "type": "Feature",
  "properties": {
    "addr:full":"7971 Victoria Dr Victoria MN 55386",
    "addr:housenumber":"7971",
    "addr:postcode":"55386",
    "addr:street":"Victoria Dr",
    "iso:country":"US",
    "sg:address":"7971 Victoria Dr",
    "sg:city":"Victoria",
    "sg:classifiers":[
        {
            "category":"Professional",
            "subcategory":"Accounting & Tax Preparation",
            "type":"Services"
        }
    ],
    "sg:phone":"+1 952 443 2200",
    "sg:postcode":"55386",
    "sg:province":"MN",
    "sg:tags":[
        "accountant"
    ],
    "wof:name":"Storms & Alpaugh",
    "wof:placetype":"venue"
},
  "geometry": {"coordinates":[-93.66181400000001,44.858915],"type":"Point"}
}