{
  "type": "Feature",
  "properties": {
    "addr:full":"511 Third Ave NW Melrose MN 56352",
    "addr:housenumber":"511",
    "addr:postcode":"56352",
    "addr:street":"Third Ave Nw",
    "iso:country":"US",
    "sg:address":"511 Third Ave NW",
    "sg:city":"Melrose",
    "sg:classifiers":[
        {
            "category":"Retail",
            "subcategory":"Repair Shop",
            "type":"Services"
        }
    ],
    "sg:phone":"+1 320 256 3900",
    "sg:postcode":"56352",
    "sg:province":"MN",
    "sg:tags":[
        "welding"
    ],
    "wof:name":"CAP Enterprises",
    "wof:placetype":"venue"
},
  "geometry": {"coordinates":[-94.819185,45.681678],"type":"Point"}
}