{
  "type": "Feature",
  "properties": {
    "addr:full":"7095 Centerville Rd Hugo MN 55038",
    "addr:housenumber":"7095",
    "addr:postcode":"55038",
    "addr:street":"Centerville Rd",
    "iso:country":"US",
    "sg:address":"7095 Centerville Rd",
    "sg:city":"Hugo",
    "sg:classifiers":[
        {
            "category":"Insurance",
            "subcategory":"Insurance Agent",
            "type":"Services"
        }
    ],
    "sg:phone":"+1 651 429 0215",
    "sg:postcode":"55038",
    "sg:province":"MN",
    "wof:name":"Michael R Hall Insurance Agcy",
    "wof:placetype":"venue"
},
  "geometry": {"coordinates":[-93.056293,45.163812],"type":"Point"}
}