{
  "type": "Feature",
  "properties": {
    "iso:country":"US",
    "sg:address":"101 14th St NE",
    "sg:city":"Buffalo",
    "sg:classifiers":[
        {
            "category":"Sports & Exercise",
            "subcategory":"Gym",
            "type":"Entertainment"
        }
    ],
    "sg:phone":"+1 763 682 4300",
    "sg:postcode":"55313",
    "sg:province":"MN",
    "sg:tags":[
        "club",
        "health"
    ],
    "wof:name":"Monticello Athletic Club Inc",
    "wof:placetype":"venue"
},
  "geometry": {"coordinates":[-93.871979,45.18622],"type":"Point"}
}