{
  "type": "Feature",
  "properties": {
    "iso:country":"US",
    "sg:address":"128 S Broadway Ave",
    "sg:city":"Spring Valley",
    "sg:classifiers":[
        {
            "category":"Real Estate",
            "subcategory":"Real Estate Agent",
            "type":"Services"
        }
    ],
    "sg:phone":"+1 507 346 2011",
    "sg:postcode":"55975",
    "sg:province":"MN",
    "sg:tags":[
        "appraiser"
    ],
    "wof:name":"Al Austin Appraisal",
    "wof:placetype":"venue"
},
  "geometry": {"coordinates":[-92.391007,43.686652],"type":"Point"}
}