{
  "type": "Feature",
  "properties": {
    "iso:country":"US",
    "sg:address":"4 11th Ave NE",
    "sg:city":"Hutchinson",
    "sg:classifiers":[
        {
            "category":"Social Services",
            "subcategory":"Child Care",
            "type":"Services"
        }
    ],
    "sg:phone":"+1 320 587 7212",
    "sg:postcode":"55350",
    "sg:province":"MN",
    "sg:tags":[
        "daycare",
        "provider"
    ],
    "wof:name":"Doreen K Burks",
    "wof:placetype":"venue"
},
  "geometry": {"coordinates":[-94.36828,44.906032],"type":"Point"}
}