{
  "type": "Feature",
  "properties": {
    "addr:full":"14260 Brockton Ln N Rogers MN 55374",
    "addr:housenumber":"14260",
    "addr:postcode":"55374",
    "addr:street":"Brockton Ln N",
    "iso:country":"US",
    "sg:address":"14260 Brockton Ln N",
    "sg:city":"Rogers",
    "sg:classifiers":[
        {
            "category":"Retail",
            "subcategory":"Animal Services",
            "type":"Services"
        }
    ],
    "sg:phone":"+1 763 428 4001",
    "sg:postcode":"55374",
    "sg:province":"MN",
    "sg:tags":[
        "boarding",
        "kennel"
    ],
    "wof:name":"Northwood Valley Kennels",
    "wof:placetype":"venue"
},
  "geometry": {"coordinates":[-93.52366499999999,45.218666],"type":"Point"}
}