{
  "type": "Feature",
  "properties": {
    "addr:full":"2197 20th St Slayton MN 56172",
    "addr:housenumber":"2197",
    "addr:postcode":"56172",
    "addr:street":"20Th St",
    "iso:country":"US",
    "sg:address":"2197 20th St",
    "sg:city":"Slayton",
    "sg:classifiers":[
        {
            "category":"Farming",
            "subcategory":"Farm & Veterinary Services",
            "type":"Manufacturing & Wholesale Goods"
        }
    ],
    "sg:phone":"+1 507 836 8006",
    "sg:postcode":"56172",
    "sg:province":"MN",
    "sg:tags":[
        "livestock"
    ],
    "wof:name":"Marvs Hometown Meats",
    "wof:placetype":"venue"
},
  "geometry": {"coordinates":[-95.760957,43.993169],"type":"Point"}
}