{
  "type": "Feature",
  "properties": {
    "iso:country":"US",
    "sg:address":"3619 85th Ave N",
    "sg:city":"Minneapolis",
    "sg:classifiers":[
        {
            "category":"Communications",
            "subcategory":"Film & Video Production",
            "type":"Services"
        }
    ],
    "sg:phone":"+1 763 493 4300",
    "sg:postcode":"55443",
    "sg:province":"MN",
    "sg:tags":[
        "motion",
        "picture"
    ],
    "wof:name":"Communications Unlimited Video",
    "wof:placetype":"venue"
},
  "geometry": {"coordinates":[-93.32776800000001,45.108817],"type":"Point"}
}