{
  "type": "Feature",
  "properties": {
    "iso:country":"US",
    "sg:address":"1111 E Lake St",
    "sg:city":"Minneapolis",
    "sg:classifiers":[
        {
            "category":"Retail",
            "subcategory":"Auto Repair",
            "type":"Services"
        }
    ],
    "sg:phone":"+1 612 724 8389",
    "sg:postcode":"55407",
    "sg:province":"MN",
    "wof:name":"Bryan Auto Repair",
    "wof:placetype":"venue"
},
  "geometry": {"coordinates":[-93.258698,44.948502],"type":"Point"}
}