{
  "type": "Feature",
  "properties": {
    "iso:country":"US",
    "sg:address":"7260 University Ave NE",
    "sg:city":"Fridley",
    "sg:classifiers":[
        {
            "category":"Banks & Credit Unions",
            "subcategory":"Bank",
            "type":"Services"
        }
    ],
    "sg:phone":"+1 763 571 8900",
    "sg:postcode":"55432",
    "sg:province":"MN",
    "sg:tags":[
        "loan",
        "real estate"
    ],
    "wof:name":"Minnesota Mortgage Solutions",
    "wof:placetype":"venue"
},
  "geometry": {"coordinates":[-93.263474,45.094548],"type":"Point"}
}