{
  "type": "Feature",
  "properties": {
    "addr:full":"776 Marie Ave W Saint Paul MN 55118",
    "addr:housenumber":"776",
    "addr:postcode":"55118",
    "addr:street":"Marie Ave W",
    "iso:country":"US",
    "sg:address":"776 Marie Ave W",
    "sg:city":"Saint Paul",
    "sg:classifiers":[
        {
            "category":"Professional",
            "subcategory":"Management & Consulting",
            "type":"Services"
        }
    ],
    "sg:phone":"+1 651 688 7089",
    "sg:postcode":"55118",
    "sg:province":"MN",
    "sg:tags":[
        "consultant",
        "construction",
        "commercial"
    ],
    "wof:name":"Tom Hastings & Associates",
    "wof:placetype":"venue"
},
  "geometry": {"coordinates":[-93.12101800000001,44.89073],"type":"Point"}
}