{
  "type": "Feature",
  "properties": {
    "addr:full":"1879 Co Rd 8 Ghent MN 56239",
    "addr:housenumber":"1879;8",
    "addr:postcode":"56239",
    "addr:street":"Co Rd",
    "iso:country":"US",
    "sg:address":"1879 Co Rd 8",
    "sg:city":"Ghent",
    "sg:classifiers":[
        {
            "category":"Building & Trades",
            "subcategory":"Landscaping Services",
            "type":"Services"
        }
    ],
    "sg:phone":"+1 507 428 3555",
    "sg:postcode":"56239",
    "sg:province":"MN",
    "wof:name":"Lalemans Septic Pumping Svc",
    "wof:placetype":"venue"
},
  "geometry": {"coordinates":[-95.92216999999999,44.51622],"type":"Point"}
}