{
  "type": "Feature",
  "properties": {
    "iso:country":"US",
    "sg:address":"22480 Sunset Ln",
    "sg:city":"Rogers",
    "sg:classifiers":[
        {
            "category":"Building & Trades",
            "subcategory":"Construction",
            "type":"Services"
        }
    ],
    "sg:phone":"+1 612 269 9520",
    "sg:postcode":"55374",
    "sg:province":"MN",
    "sg:tags":[
        "painter"
    ],
    "wof:name":"Coachman Painting & Svc",
    "wof:placetype":"venue"
},
  "geometry": {"coordinates":[-93.606825,45.147908],"type":"Point"}
}