{
  "type": "Feature",
  "properties": {
    "addr:full":"246 Ruth St N St Paul MN 55119",
    "addr:housenumber":"246",
    "addr:postcode":"55119",
    "addr:street":"Ruth St N",
    "iso:country":"US",
    "sg:address":"246 Ruth St N",
    "sg:city":"St Paul",
    "sg:classifiers":[
        {
            "category":"Social Services",
            "type":"Services"
        }
    ],
    "sg:phone":"+1 651 714 1552",
    "sg:postcode":"55119",
    "sg:province":"MN",
    "sg:tags":[
        "organization",
        "welfare"
    ],
    "wof:name":"People Inc",
    "wof:placetype":"venue"
},
  "geometry": {"coordinates":[-93.015039,44.949392],"type":"Point"}
}