{
  "type": "Feature",
  "properties": {
    "addr:full":"110 S 7th St Minneapolis MN 55402",
    "addr:housenumber":"110",
    "addr:postcode":"55402",
    "addr:street":"S 7Th St",
    "iso:country":"US",
    "sg:address":"110 S 7th St",
    "sg:city":"Minneapolis",
    "sg:classifiers":[
        {
            "category":"Parking",
            "type":"Transportation"
        }
    ],
    "sg:phone":"+1 612 333 6127",
    "sg:postcode":"55402",
    "sg:province":"MN",
    "wof:name":"Northstar Ramp",
    "wof:placetype":"venue"
},
  "geometry": {"coordinates":[-93.27069899999999,44.976299],"type":"Point"}
}