{
  "type": "Feature",
  "properties": {
    "iso:country":"US",
    "sg:address":"6412 Fallbrook Rd",
    "sg:city":"Eden Prairie",
    "sg:classifiers":[
        {
            "category":"Building & Trades",
            "subcategory":"Landscaping Services",
            "type":"Services"
        }
    ],
    "sg:phone":"+1 952 942 7884",
    "sg:postcode":"55344",
    "sg:province":"MN",
    "wof:name":"Morningside Tree & Landscape",
    "wof:placetype":"venue"
},
  "geometry": {"coordinates":[-93.42865399999999,44.888824],"type":"Point"}
}