{
  "type": "Feature",
  "properties": {
    "iso:country":"US",
    "sg:address":"1681 W Saunders Ave",
    "sg:city":"Saint Paul",
    "sg:classifiers":[
        {
            "category":"Professional",
            "subcategory":"Business Services",
            "type":"Services"
        }
    ],
    "sg:phone":"+1 651 690 9999",
    "sg:postcode":"55116",
    "sg:province":"MN",
    "wof:name":"Anselmo C Castelan",
    "wof:placetype":"venue"
},
  "geometry": {"coordinates":[-93.170582,44.914417],"type":"Point"}
}