{
  "type": "Feature",
  "properties": {
    "iso:country":"US",
    "sg:address":"500 Central Ave",
    "sg:city":"Lester Prairie",
    "sg:classifiers":[
        {
            "category":"Banks & Credit Unions",
            "subcategory":"Bank",
            "type":"Services"
        }
    ],
    "sg:phone":"+1 320 395 2515",
    "sg:postcode":"55354",
    "sg:province":"MN",
    "wof:name":"First Community Bank",
    "wof:placetype":"venue"
},
  "geometry": {"coordinates":[-94.04076000000001,44.884522],"type":"Point"}
}