{
  "type": "Feature",
  "properties": {
    "iso:country":"US",
    "sg:address":"14802 County Road 5",
    "sg:city":"Burnsville",
    "sg:classifiers":[
        {
            "category":"Real Estate",
            "subcategory":"Real Estate Operator",
            "type":"Services"
        }
    ],
    "sg:phone":"+1 952 435 2119",
    "sg:postcode":"55306",
    "sg:province":"MN",
    "sg:tags":[
        "apartment"
    ],
    "wof:name":"Southcross Village Townhomes",
    "wof:placetype":"venue"
},
  "geometry": {"coordinates":[-93.298401,44.735401],"type":"Point"}
}