{
  "type": "Feature",
  "properties": {
    "addr:full":"14926 Florence Trl Saint Paul MN 55124",
    "addr:housenumber":"14926",
    "addr:postcode":"55124",
    "addr:street":"Florence Trl",
    "iso:country":"US",
    "sg:address":"14926 Florence Trl",
    "sg:city":"Saint Paul",
    "sg:classifiers":[
        {
            "category":"Shopping",
            "subcategory":"Department Store",
            "type":"Retail Goods"
        }
    ],
    "sg:phone":"+1 952 997 3000",
    "sg:postcode":"55124",
    "sg:province":"MN",
    "sg:website":"www.kohls.com",
    "wof:name":"Kohl's",
    "wof:placetype":"venue"
},
  "geometry": {"coordinates":[-93.201103,44.7328],"type":"Point"}
}