{
  "type": "Feature",
  "properties": {
    "addr:full":"4655 Ximines Ln N Minneapolis MN 55442",
    "addr:housenumber":"4655",
    "addr:postcode":"55442",
    "addr:street":"Ximines Ln N",
    "iso:country":"US",
    "sg:address":"4655 Ximines Ln N",
    "sg:city":"Minneapolis",
    "sg:classifiers":[
        {
            "category":"Wholesale",
            "subcategory":"Non-durable Goods",
            "type":"Manufacturing & Wholesale Goods"
        }
    ],
    "sg:phone":"+1 763 559 6612",
    "sg:postcode":"55442",
    "sg:province":"MN",
    "wof:name":"Laurier Box Co LLC",
    "wof:placetype":"venue"
},
  "geometry": {"coordinates":[-93.41875,45.039221],"type":"Point"}
}