{
  "type": "Feature",
  "properties": {
    "addr:full":"306 N State St New Ulm MN 56073",
    "addr:housenumber":"306",
    "addr:postcode":"56073",
    "addr:street":"N State St",
    "iso:country":"US",
    "sg:address":"306 N State St",
    "sg:city":"New Ulm",
    "sg:classifiers":[
        {
            "category":"Social Services",
            "subcategory":"Adult Care",
            "type":"Services"
        }
    ],
    "sg:phone":"+1 507 354 3584",
    "sg:postcode":"56073",
    "sg:province":"MN",
    "sg:tags":[
        "home",
        "group"
    ],
    "wof:name":"Habilitative Services",
    "wof:placetype":"venue"
},
  "geometry": {"coordinates":[-94.465435,44.315835],"type":"Point"}
}