{
  "type": "Feature",
  "properties": {
    "addr:full":"1818 Buerkle Rd St Paul MN 55110",
    "addr:housenumber":"1818",
    "addr:postcode":"55110",
    "addr:street":"Buerkle Rd",
    "iso:country":"US",
    "sg:address":"1818 Buerkle Rd",
    "sg:city":"St Paul",
    "sg:classifiers":[
        {
            "category":"Wholesale",
            "subcategory":"Furniture",
            "type":"Manufacturing & Wholesale Goods"
        },
        {
            "category":"Manufacturing",
            "subcategory":"Tools & Machinery",
            "type":"Manufacturing & Wholesale Goods"
        }
    ],
    "sg:phone":"+1 651 747 0492",
    "sg:postcode":"55110",
    "sg:province":"MN",
    "sg:tags":[
        "supply",
        "equipment",
        "automation",
        "library",
        "mfg"
    ],
    "wof:name":"Tech Logic Corp",
    "wof:placetype":"venue"
},
  "geometry": {"coordinates":[-93.017774,45.03915],"type":"Point"}
}