{
  "type": "Feature",
  "properties": {
    "iso:country":"US",
    "sg:address":"302 Chestnut St W",
    "sg:city":"Virginia",
    "sg:classifiers":[
        {
            "category":"Banks & Credit Unions",
            "subcategory":"Investment Brokerage",
            "type":"Services"
        }
    ],
    "sg:phone":"+1 218 749 4031",
    "sg:postcode":"55792",
    "sg:province":"MN",
    "sg:tags":[
        "security"
    ],
    "wof:name":"Edward Jones 05649",
    "wof:placetype":"venue"
},
  "geometry": {"coordinates":[-92.534875,47.523104],"type":"Point"}
}