{
  "type": "Feature",
  "properties": {
    "addr:full":"206 Market St Minneapolis MN 55405",
    "addr:housenumber":"206",
    "addr:postcode":"55405",
    "addr:street":"Market St",
    "iso:country":"US",
    "sg:address":"206 Market St",
    "sg:city":"Minneapolis",
    "sg:classifiers":[
        {
            "category":"Shopping",
            "type":"Retail Goods"
        }
    ],
    "sg:phone":"+1 952 851 9322",
    "sg:postcode":"55405",
    "sg:province":"MN",
    "sg:tags":[
        "personal",
        "product",
        "care"
    ],
    "wof:name":"Bath & Body Works Inc",
    "wof:placetype":"venue"
},
  "geometry": {"coordinates":[-93.289733,44.980684],"type":"Point"}
}