{
  "type": "Feature",
  "properties": {
    "iso:country":"US",
    "sg:address":"5211 Winnetka Ave N",
    "sg:city":"Minneapolis",
    "sg:classifiers":[
        {
            "category":"Professional",
            "subcategory":"Management & Consulting",
            "type":"Services"
        },
        {
            "category":"Banks & Credit Unions",
            "subcategory":"Financial Services",
            "type":"Services"
        }
    ],
    "sg:phone":"+1 763 746 5160",
    "sg:postcode":"55428",
    "sg:province":"MN",
    "sg:tags":[
        "consultant",
        "financing",
        "planning",
        "mortgage"
    ],
    "wof:name":"Stepping Stone Financial Services Inc",
    "wof:placetype":"venue"
},
  "geometry": {"coordinates":[-93.38041800000001,45.049141],"type":"Point"}
}