{
  "type": "Feature",
  "properties": {
    "iso:country":"US",
    "sg:address":"1700 Emma St",
    "sg:city":"Brainerd",
    "sg:classifiers":[
        {
            "category":"Personal",
            "subcategory":"Beauty Salon",
            "type":"Services"
        }
    ],
    "sg:phone":"+1 218 829 4861",
    "sg:postcode":"56401",
    "sg:province":"MN",
    "sg:tags":[
        "shop"
    ],
    "wof:name":"Hair Design By Jan Inc",
    "wof:placetype":"venue"
},
  "geometry": {"coordinates":[-94.2076,46.34131],"type":"Point"}
}