{
  "type": "Feature",
  "properties": {
    "iso:country":"US",
    "sg:address":"105 Harper St",
    "sg:city":"Inver Grove Hts",
    "sg:classifiers":[
        {
            "category":"Professional",
            "subcategory":"Accounting & Tax Preparation",
            "type":"Services"
        }
    ],
    "sg:phone":"+1 651 451 6057",
    "sg:postcode":"55076",
    "sg:province":"MN",
    "sg:tags":[
        "bookkeeping",
        "general"
    ],
    "wof:name":"Organized Office Options",
    "wof:placetype":"venue"
},
  "geometry": {"coordinates":[-93.021371,44.839904],"type":"Point"}
}