{
  "type": "Feature",
  "properties": {
    "addr:full":"81 Bryan St Saint Paul MN 55117",
    "addr:housenumber":"81",
    "addr:postcode":"55117",
    "addr:street":"Bryan St",
    "iso:country":"US",
    "sg:address":"81 Bryan St",
    "sg:city":"Saint Paul",
    "sg:classifiers":[
        {
            "category":"Building & Trades",
            "subcategory":"Construction",
            "type":"Services"
        }
    ],
    "sg:phone":"+1 651 484 4654",
    "sg:postcode":"55117",
    "sg:province":"MN",
    "sg:tags":[
        "nonresidential"
    ],
    "wof:name":"Robert Debace",
    "wof:placetype":"venue"
},
  "geometry": {"coordinates":[-93.098001,45.026229],"type":"Point"}
}