{
  "type": "Feature",
  "properties": {
    "addr:full":"7800 Zane Ave N Minneapolis MN 55443",
    "addr:housenumber":"7800",
    "addr:postcode":"55443",
    "addr:street":"Zane Ave N",
    "iso:country":"US",
    "sg:address":"7800 Zane Ave N",
    "sg:city":"Minneapolis",
    "sg:classifiers":[
        {
            "category":"Restaurant",
            "type":"Food & Drink"
        }
    ],
    "sg:phone":"+1 763 566 1990",
    "sg:postcode":"55443",
    "sg:province":"MN",
    "wof:name":"Great Pearl Restaurant",
    "wof:placetype":"venue"
},
  "geometry": {"coordinates":[-93.35633900000001,45.096298],"type":"Point"}
}