{
  "type": "Feature",
  "properties": {
    "addr:full":"232 Labree Ave S Thief River Fls MN 56701",
    "addr:housenumber":"232",
    "addr:postcode":"56701",
    "addr:street":"Labree Ave S Thief River Fls",
    "iso:country":"US",
    "sg:address":"232 Labree Ave S",
    "sg:city":"Thief River Fls",
    "sg:classifiers":[
        {
            "category":"Manufacturing",
            "subcategory":"Textiles",
            "type":"Manufacturing & Wholesale Goods"
        }
    ],
    "sg:phone":"+1 218 681 3919",
    "sg:postcode":"56701",
    "sg:province":"MN",
    "sg:tags":[
        "linen"
    ],
    "sg:website":"www.trlinen.com",
    "wof:name":"Thief River Linen",
    "wof:placetype":"venue"
},
  "geometry": {"coordinates":[-96.180094,48.116558],"type":"Point"}
}