{
  "type": "Feature",
  "properties": {
    "addr:full":"301 Saint Paul St NW Preston MN 55965",
    "addr:housenumber":"301",
    "addr:postcode":"55965",
    "addr:street":"Saint Paul St Nw",
    "iso:country":"US",
    "sg:address":"301 Saint Paul St NW",
    "sg:city":"Preston",
    "sg:classifiers":[
        {
            "category":"Health Services",
            "subcategory":"Hospital",
            "type":"Services"
        }
    ],
    "sg:phone":"+1 507 765 2788",
    "sg:postcode":"55965",
    "sg:province":"MN",
    "sg:tags":[
        "mental"
    ],
    "wof:name":"Zumbro Valley Mhc Fillmore",
    "wof:placetype":"venue"
},
  "geometry": {"coordinates":[-92.08304,43.6737],"type":"Point"}
}