{
  "type": "Feature",
  "properties": {
    "addr:full":"13032 Saratoga Ln N Champlin MN 55316",
    "addr:housenumber":"13032",
    "addr:postcode":"55316",
    "addr:street":"Saratoga Ln N",
    "iso:country":"US",
    "sg:address":"13032 Saratoga Ln N",
    "sg:city":"Champlin",
    "sg:classifiers":[
        {
            "category":"Social Services",
            "subcategory":"Child Care",
            "type":"Services"
        }
    ],
    "sg:phone":"+1 763 427 8390",
    "sg:postcode":"55316",
    "sg:province":"MN",
    "sg:tags":[
        "nursery",
        "day"
    ],
    "wof:name":"Beth Mcdaniel",
    "wof:placetype":"venue"
},
  "geometry": {"coordinates":[-93.413978,45.190861],"type":"Point"}
}