{
  "type": "Feature",
  "properties": {
    "addr:full":"1661 Utah Dr Minneapolis MN 55426",
    "addr:housenumber":"1661",
    "addr:postcode":"55426",
    "addr:street":"Utah Dr",
    "iso:country":"US",
    "sg:address":"1661 Utah Dr",
    "sg:city":"Minneapolis",
    "sg:classifiers":[
        {
            "category":"Banks & Credit Unions",
            "subcategory":"Bank",
            "type":"Services"
        }
    ],
    "sg:phone":"+1 952 797 0490",
    "sg:postcode":"55426",
    "sg:province":"MN",
    "sg:tags":[
        "mortgage"
    ],
    "wof:name":"Ceresota Funding LLC",
    "wof:placetype":"venue"
},
  "geometry": {"coordinates":[-93.383674,44.966404],"type":"Point"}
}