{
  "type": "Feature",
  "properties": {
    "addr:full":"1486 Vixen Ln Delano MN 55328",
    "addr:housenumber":"1486",
    "addr:postcode":"55328",
    "addr:street":"Vixen Ln",
    "iso:country":"US",
    "sg:address":"1486 Vixen Ln",
    "sg:city":"Delano",
    "sg:classifiers":[
        {
            "category":"Professional",
            "subcategory":"Business Services",
            "type":"Services"
        }
    ],
    "sg:phone":"+1 763 972 9171",
    "sg:postcode":"55328",
    "sg:province":"MN",
    "sg:tags":[
        "russian",
        "linguist"
    ],
    "wof:name":"Anthony A Troussov",
    "wof:placetype":"venue"
},
  "geometry": {"coordinates":[-93.76878000000001,45.033483],"type":"Point"}
}