{
  "type": "Feature",
  "properties": {
    "iso:country":"US",
    "sg:address":"1667 E Ross Ave",
    "sg:city":"Saint Paul",
    "sg:classifiers":[
        {
            "category":"Organizations",
            "subcategory":"Religious Organization",
            "type":"Services"
        }
    ],
    "sg:phone":"+1 651 771 9221",
    "sg:postcode":"55106",
    "sg:province":"MN",
    "wof:name":"Greens On 7th Inc",
    "wof:placetype":"venue"
},
  "geometry": {"coordinates":[-93.028051,44.965907],"type":"Point"}
}