{
  "type": "Feature",
  "properties": {
    "iso:country":"US",
    "sg:address":"55121 211th Ln",
    "sg:city":"Mankato",
    "sg:classifiers":[
        {
            "category":"Building & Trades",
            "subcategory":"Construction",
            "type":"Services"
        }
    ],
    "sg:phone":"+1 507 387 1209",
    "sg:postcode":"56001",
    "sg:province":"MN",
    "sg:tags":[
        "contractor"
    ],
    "wof:name":"P R Construction",
    "wof:placetype":"venue"
},
  "geometry": {"coordinates":[-94.07285400000001,44.152437],"type":"Point"}
}