{
  "type": "Feature",
  "properties": {
    "iso:country":"US",
    "sg:address":"26615 133rd Ave",
    "sg:city":"Cold Spring",
    "sg:classifiers":[
        {
            "category":"Professional",
            "subcategory":"Business Services",
            "type":"Services"
        }
    ],
    "sg:phone":"+1 320 685 3665",
    "sg:postcode":"56320",
    "sg:province":"MN",
    "wof:name":"Van Briesen Ike Auction Servi",
    "wof:placetype":"venue"
},
  "geometry": {"coordinates":[-94.38456499999999,45.508939],"type":"Point"}
}