{
  "type": "Feature",
  "properties": {
    "addr:full":"1316 10th St SE Buffalo MN 55313",
    "addr:housenumber":"1316",
    "addr:postcode":"55313",
    "addr:street":"10Th St Se",
    "iso:country":"US",
    "sg:address":"1316 10th St SE",
    "sg:city":"Buffalo",
    "sg:classifiers":[
        {
            "category":"Building & Trades",
            "subcategory":"Plumbing",
            "type":"Services"
        }
    ],
    "sg:phone":"+1 763 682 5411",
    "sg:postcode":"55313",
    "sg:province":"MN",
    "sg:tags":[
        "plumber",
        "industrial",
        "contractors-commercial",
        "clean",
        "boilers-repair"
    ],
    "wof:name":"Neil's Plumbing",
    "wof:placetype":"venue"
},
  "geometry": {"coordinates":[-93.858861,45.137517],"type":"Point"}
}