{
  "type": "Feature",
  "properties": {
    "addr:full":"6103 Blue Circle Drive Minnetonka MN 55343",
    "addr:housenumber":"6103",
    "addr:postcode":"55343",
    "addr:street":"Blue Circle Drive",
    "iso:country":"US",
    "sg:address":"6103 Blue Circle Drive",
    "sg:city":"Minnetonka",
    "sg:classifiers":[
        {
            "category":"Professional",
            "subcategory":"Computer Services",
            "type":"Services"
        }
    ],
    "sg:phone":"+1 952 374 5300",
    "sg:postcode":"55343",
    "sg:province":"MN",
    "sg:website":"http://nexusmn.com",
    "wof:name":"Nexus Information Systems",
    "wof:placetype":"venue"
},
  "geometry": {"coordinates":[-93.40789700000001,44.891998],"type":"Point"}
}