{
  "type": "Feature",
  "properties": {
    "iso:country":"US",
    "sg:address":"6421 Hazeltine Blvd",
    "sg:city":"Excelsior",
    "sg:classifiers":[
        {
            "category":"Education",
            "subcategory":"School",
            "type":"Public Place"
        }
    ],
    "sg:phone":"+1 952 401 5300",
    "sg:postcode":"55331",
    "sg:province":"MN",
    "wof:name":"Minnetonka Middle School West",
    "wof:placetype":"venue"
},
  "geometry": {"coordinates":[-93.58090199999999,44.889],"type":"Point"}
}