{
  "type": "Feature",
  "properties": {
    "addr:full":"16901 351st Ave Hamburg MN 55338",
    "addr:housenumber":"16901",
    "addr:postcode":"55338",
    "addr:street":"351St Ave",
    "iso:country":"US",
    "sg:address":"16901 351st Ave",
    "sg:city":"Hamburg",
    "sg:classifiers":[
        {
            "category":"Farming",
            "subcategory":"Livestock Farm",
            "type":"Manufacturing & Wholesale Goods"
        }
    ],
    "sg:phone":"+1 952 467 4404",
    "sg:postcode":"55338",
    "sg:province":"MN",
    "sg:tags":[
        "beef",
        "feedlot",
        "cattle"
    ],
    "wof:name":"Dan Justen",
    "wof:placetype":"venue"
},
  "geometry": {"coordinates":[-93.969982,44.703541],"type":"Point"}
}