{
  "type": "Feature",
  "properties": {
    "iso:country":"US",
    "sg:address":"13613 Orchard Rd",
    "sg:city":"Hopkins",
    "sg:classifiers":[
        {
            "category":"Place Of Worship",
            "subcategory":"Synagogue",
            "type":"Public Place"
        },
        {
            "category":"Place Of Worship",
            "type":"Public Place"
        }
    ],
    "sg:phone":"+1 952 933 8525",
    "sg:postcode":"55305",
    "sg:province":"MN",
    "sg:tags":[
        "synagogues-reform",
        "church"
    ],
    "sg:website":"http://www.betshalom.org",
    "wof:name":"Bet Shalom Reform Congregation",
    "wof:placetype":"venue"
},
  "geometry": {"coordinates":[-93.451319,44.934657],"type":"Point"}
}