{
  "type": "Feature",
  "properties": {
    "addr:full":"445 N Etna St Saint Paul MN 55106",
    "addr:housenumber":"445",
    "addr:postcode":"55106",
    "addr:street":"N Etna St",
    "iso:country":"US",
    "sg:address":"445 N Etna St",
    "sg:city":"Saint Paul",
    "sg:classifiers":[
        {
            "category":"Airline",
            "type":"Transportation"
        }
    ],
    "sg:phone":"+1 800 463 3339",
    "sg:postcode":"55106",
    "sg:province":"MN",
    "sg:tags":[
        "courier",
        "air"
    ],
    "wof:name":"Fedex",
    "wof:placetype":"venue"
},
  "geometry": {"coordinates":[-93.041562,44.955571],"type":"Point"}
}