{
  "type": "Feature",
  "properties": {
    "iso:country":"US",
    "sg:address":"11613 US Hwy 14",
    "sg:city":"St Charles",
    "sg:classifiers":[
        {
            "category":"Health Services",
            "subcategory":"Doctor",
            "type":"Services"
        }
    ],
    "sg:phone":"+1 507 932 5364",
    "sg:postcode":"55972",
    "sg:province":"MN",
    "sg:tags":[
        "physician",
        "surgeon"
    ],
    "wof:name":"Wayne Ode MD",
    "wof:placetype":"venue"
},
  "geometry": {"coordinates":[-92.082335,43.970986],"type":"Point"}
}