{
  "type": "Feature",
  "properties": {
    "addr:full":"300 5th St W Northfield MN 55057",
    "addr:housenumber":"300",
    "addr:postcode":"55057",
    "addr:street":"5Th St W",
    "iso:country":"US",
    "sg:address":"300 5th St W",
    "sg:city":"Northfield",
    "sg:classifiers":[
        {
            "category":"Government",
            "subcategory":"Office",
            "type":"Public Place"
        }
    ],
    "sg:phone":"+1 507 663 9322",
    "sg:postcode":"55057",
    "sg:province":"MN",
    "wof:name":"South Cntl DRG Invstgtion Unit",
    "wof:placetype":"venue"
},
  "geometry": {"coordinates":[-93.164115,44.455021],"type":"Point"}
}