{
  "type": "Feature",
  "properties": {
    "iso:country":"US",
    "sg:address":"12180 Hancock St",
    "sg:city":"Becker",
    "sg:classifiers":[
        {
            "category":"Shopping",
            "subcategory":"Used Merchandise",
            "type":"Retail Goods"
        }
    ],
    "sg:phone":"+1 763 263 8188",
    "sg:postcode":"55308",
    "sg:province":"MN",
    "sg:tags":[
        "antique"
    ],
    "wof:name":"Pedal Inn Antiques",
    "wof:placetype":"venue"
},
  "geometry": {"coordinates":[-93.87707399999999,45.393231],"type":"Point"}
}