{
  "type": "Feature",
  "properties": {
    "addr:full":"5920 13th Ave S Minneapolis MN 55417",
    "addr:housenumber":"5920",
    "addr:postcode":"55417",
    "addr:street":"13Th Ave S",
    "iso:country":"US",
    "sg:address":"5920 13th Ave S",
    "sg:city":"Minneapolis",
    "sg:classifiers":[
        {
            "category":"Travel",
            "subcategory":"Travel Agent",
            "type":"Entertainment"
        }
    ],
    "sg:phone":"+1 612 722 0427",
    "sg:postcode":"55417",
    "sg:province":"MN",
    "sg:tags":[
        "agency",
        "services-commercial"
    ],
    "wof:name":"Haite Travel",
    "wof:placetype":"venue"
},
  "geometry": {"coordinates":[-93.25658799999999,44.895453],"type":"Point"}
}