{
  "type": "Feature",
  "properties": {
    "addr:full":"1427 89th Ave W Duluth MN 55808",
    "addr:housenumber":"1427",
    "addr:postcode":"55808",
    "addr:street":"89Th Ave W",
    "iso:country":"US",
    "sg:address":"1427 89th Ave W",
    "sg:city":"Duluth",
    "sg:classifiers":[
        {
            "category":"Wholesale",
            "subcategory":"Meat",
            "type":"Manufacturing & Wholesale Goods"
        }
    ],
    "sg:phone":"+1 218 391 8625",
    "sg:postcode":"55808",
    "sg:province":"MN",
    "sg:tags":[
        "mfg",
        "prepared"
    ],
    "wof:name":"Tile-N-Aters",
    "wof:placetype":"venue"
},
  "geometry": {"coordinates":[-92.212203,46.685088],"type":"Point"}
}