{
  "type": "Feature",
  "properties": {
    "iso:country":"US",
    "sg:address":"27741 County Road 17",
    "sg:city":"Winona",
    "sg:classifiers":[
        {
            "category":"Farming",
            "subcategory":"Farm",
            "type":"Manufacturing & Wholesale Goods"
        }
    ],
    "sg:phone":"+1 507 454 5798",
    "sg:postcode":"55987",
    "sg:province":"MN",
    "wof:name":"Farmer",
    "wof:placetype":"venue"
},
  "geometry": {"coordinates":[-91.61806900000001,43.929001],"type":"Point"}
}