{
  "type": "Feature",
  "properties": {
    "addr:full":"5156 Barnum Rd NW Hackensack MN 56452",
    "addr:housenumber":"5156",
    "addr:postcode":"56452",
    "addr:street":"Barnum Rd Nw",
    "iso:country":"US",
    "sg:address":"5156 Barnum Rd NW",
    "sg:city":"Hackensack",
    "sg:classifiers":[
        {
            "category":"Manufacturing",
            "subcategory":"Wood Products",
            "type":"Manufacturing & Wholesale Goods"
        }
    ],
    "sg:phone":"+1 218 682 2198",
    "sg:postcode":"56452",
    "sg:province":"MN",
    "sg:tags":[
        "mfg"
    ],
    "wof:name":"Wood Creations",
    "wof:placetype":"venue"
},
  "geometry": {"coordinates":[-94.314767,46.984199],"type":"Point"}
}