{
  "type": "Feature",
  "properties": {
    "iso:country":"US",
    "sg:address":"4445 W 77th St",
    "sg:city":"Minneapolis",
    "sg:classifiers":[
        {
            "category":"Professional",
            "subcategory":"Management & Consulting",
            "type":"Services"
        }
    ],
    "sg:phone":"+1 952 960 2233",
    "sg:postcode":"55435",
    "sg:province":"MN",
    "sg:tags":[
        "consultant",
        "energy",
        "conservation"
    ],
    "wof:name":"Colonial Resources",
    "wof:placetype":"venue"
},
  "geometry": {"coordinates":[-93.341255,44.863119],"type":"Point"}
}