{
  "type": "Feature",
  "properties": {
    "addr:full":"115 Frontage Rd Byron MN 55920",
    "addr:housenumber":"115",
    "addr:postcode":"55920",
    "addr:street":"Frontage Rd",
    "iso:country":"US",
    "sg:address":"115 Frontage Rd",
    "sg:city":"Byron",
    "sg:classifiers":[
        {
            "category":"Restaurant",
            "type":"Food & Drink"
        }
    ],
    "sg:phone":"+1 507 775 2820",
    "sg:postcode":"55920",
    "sg:province":"MN",
    "wof:name":"T J's Deli",
    "wof:placetype":"venue"
},
  "geometry": {"coordinates":[-92.647516,44.029072],"type":"Point"}
}