{
  "type": "Feature",
  "properties": {
    "iso:country":"US",
    "sg:address":"115 Frontage Rd",
    "sg:city":"Byron",
    "sg:classifiers":[
        {
            "category":"Restaurant",
            "type":"Food & Drink"
        }
    ],
    "sg:phone":"+1 507 775 2820",
    "sg:postcode":"55920",
    "sg:province":"MN",
    "wof:name":"T J's Deli",
    "wof:placetype":"venue"
},
  "geometry": {"coordinates":[-92.647516,44.029072],"type":"Point"}
}