{
  "type": "Feature",
  "properties": {
    "addr:full":"17173 232nd Ave NW Big Lake MN 55309",
    "addr:housenumber":"17173",
    "addr:postcode":"55309",
    "addr:street":"232Nd Ave Nw",
    "iso:country":"US",
    "sg:address":"17173 232nd Ave NW",
    "sg:city":"Big Lake",
    "sg:classifiers":[
        {
            "category":"Professional",
            "type":"Services"
        }
    ],
    "sg:phone":"+1 763 263 7506",
    "sg:postcode":"55309",
    "sg:province":"MN",
    "wof:name":"Two Guys Painting",
    "wof:placetype":"venue"
},
  "geometry": {"coordinates":[-93.700332,45.391407],"type":"Point"}
}