{
  "type": "Feature",
  "properties": {
    "addr:full":"1903 Kathleen Dr St Paul MN 55118",
    "addr:housenumber":"1903",
    "addr:postcode":"55118",
    "addr:street":"Kathleen Dr",
    "iso:country":"US",
    "sg:address":"1903 Kathleen Dr",
    "sg:city":"St Paul",
    "sg:classifiers":[
        {
            "category":"Professional",
            "subcategory":"Management & Consulting",
            "type":"Services"
        }
    ],
    "sg:phone":"+1 651 307 3245",
    "sg:postcode":"55118",
    "sg:province":"MN",
    "sg:tags":[
        "consultant"
    ],
    "wof:name":"Indoor Air Qual Advisory Grp",
    "wof:placetype":"venue"
},
  "geometry": {"coordinates":[-93.079376,44.889183],"type":"Point"}
}