{
  "type": "Feature",
  "properties": {
    "iso:country":"US",
    "sg:address":"1539 Grand Ave",
    "sg:city":"Saint Paul",
    "sg:classifiers":[
        {
            "category":"Professional",
            "subcategory":"Lawyer & Legal Services",
            "type":"Services"
        }
    ],
    "sg:phone":"+1 651 698 5506",
    "sg:postcode":"55105",
    "sg:province":"MN",
    "wof:name":"Tarrant Karen Atty",
    "wof:placetype":"venue"
},
  "geometry": {"coordinates":[-93.16529800000001,44.939899],"type":"Point"}
}