{
  "type": "Feature",
  "properties": {
    "iso:country":"US",
    "sg:address":"1610 Hwy 71",
    "sg:city":"Internatl Falls",
    "sg:classifiers":[
        {
            "category":"Education",
            "subcategory":"Library",
            "type":"Public Place"
        },
        {
            "category":"Wholesale",
            "subcategory":"Groceries",
            "type":"Manufacturing & Wholesale Goods"
        }
    ],
    "sg:phone":"+1 218 283 9000",
    "sg:postcode":"56649",
    "sg:province":"MN",
    "sg:tags":[
        "food",
        "product",
        "health"
    ],
    "wof:name":"Nature's Olive Branch",
    "wof:placetype":"venue"
},
  "geometry": {"coordinates":[-93.43019099999999,48.594297],"type":"Point"}
}