{
  "type": "Feature",
  "properties": {
    "iso:country":"US",
    "sg:address":"2885 Water Tower Pl",
    "sg:city":"Chanhassen",
    "sg:classifiers":[
        {
            "category":"Sports & Exercise",
            "subcategory":"Gym",
            "type":"Entertainment"
        }
    ],
    "sg:phone":"+1 952 474 4076",
    "sg:postcode":"55317",
    "sg:province":"MN",
    "sg:tags":[
        "trainer"
    ],
    "sg:website":"www.hipfit.net",
    "wof:name":"Club Hipfit",
    "wof:placetype":"venue"
},
  "geometry": {"coordinates":[-93.59557599999999,44.859033],"type":"Point"}
}