{
  "type": "Feature",
  "properties": {
    "iso:country":"US",
    "sg:address":"24688 Co Hwy 6",
    "sg:city":"Detroit Lakes",
    "sg:classifiers":[
        {
            "category":"Organizations",
            "subcategory":"Religious Organization",
            "type":"Services"
        }
    ],
    "sg:phone":"+1 218 847 1040",
    "sg:postcode":"56501",
    "sg:province":"MN",
    "sg:website":"www.faithlutheran.truepath.com",
    "wof:name":"Faith Free Lutheran Church",
    "wof:placetype":"venue"
},
  "geometry": {"coordinates":[-95.88919199999999,46.796955],"type":"Point"}
}