{
  "type": "Feature",
  "properties": {
    "addr:full":"215 Carver Creek Pl S Carver MN 55315",
    "addr:housenumber":"215",
    "addr:postcode":"55315",
    "addr:street":"Carver Creek Pl S Carver",
    "iso:country":"US",
    "sg:address":"215 Carver Creek Pl S",
    "sg:city":"Carver",
    "sg:classifiers":[
        {
            "category":"Manufacturing",
            "subcategory":"Printing",
            "type":"Manufacturing & Wholesale Goods"
        }
    ],
    "sg:phone":"+1 952 361 9795",
    "sg:postcode":"55315",
    "sg:province":"MN",
    "sg:tags":[
        "publisher",
        "software"
    ],
    "wof:name":"Elytix",
    "wof:placetype":"venue"
},
  "geometry": {"coordinates":[-93.641938,44.747278],"type":"Point"}
}