{
  "type": "Feature",
  "properties": {
    "iso:country":"US",
    "sg:address":"1687 Wedgewood Cir",
    "sg:city":"Saint Paul",
    "sg:classifiers":[
        {
            "category":"Building & Trades",
            "subcategory":"Construction",
            "type":"Services"
        }
    ],
    "sg:phone":"+1 651 633 9059",
    "sg:postcode":"55112",
    "sg:province":"MN",
    "sg:tags":[
        "commercial",
        "remodeling"
    ],
    "wof:name":"Cirks Construction Inc",
    "wof:placetype":"venue"
},
  "geometry": {"coordinates":[-93.170236,45.071518],"type":"Point"}
}