{
  "type": "Feature",
  "properties": {
    "addr:full":"54738 210th St Grove City MN 56243",
    "addr:housenumber":"54738",
    "addr:postcode":"56243",
    "addr:street":"210Th St",
    "iso:country":"US",
    "sg:address":"54738 210th St",
    "sg:city":"Grove City",
    "sg:classifiers":[
        {
            "category":"Farming",
            "subcategory":"Dairy Farm",
            "type":"Manufacturing & Wholesale Goods"
        }
    ],
    "sg:phone":"+1 320 857 2369",
    "sg:postcode":"56243",
    "sg:province":"MN",
    "wof:name":"Snowpine",
    "wof:placetype":"venue"
},
  "geometry": {"coordinates":[-94.67103899999999,45.051625],"type":"Point"}
}