{
  "type": "Feature",
  "properties": {
    "addr:full":"900 6th Ave SE Ste 100 Minneapolis MN 55414",
    "addr:housenumber":"900",
    "addr:postcode":"55414",
    "addr:street":"6Th Ave Se Ste 100",
    "iso:country":"US",
    "sg:address":"900 6th Ave SE Ste 100",
    "sg:city":"Minneapolis",
    "sg:classifiers":[
        {
            "category":"Home & Garden",
            "subcategory":"Kitchen Supply",
            "type":"Retail Goods"
        }
    ],
    "sg:phone":"+1 612 465 8107",
    "sg:postcode":"55414",
    "sg:province":"MN",
    "sg:tags":[
        "utensil",
        "cookware"
    ],
    "wof:name":"Mu Kitchen",
    "wof:placetype":"venue"
},
  "geometry": {"coordinates":[-93.243347,44.989328],"type":"Point"}
}