{
  "type": "Feature",
  "properties": {
    "addr:full":"5805 Co Rd 146 South Haven MN 55382",
    "addr:housenumber":"5805",
    "addr:postcode":"55382",
    "addr:street":"Co Rd 146",
    "iso:country":"US",
    "sg:address":"5805 Co Rd 146",
    "sg:city":"South Haven",
    "sg:classifiers":[
        {
            "category":"Building & Trades",
            "subcategory":"Landscaping Services",
            "type":"Services"
        }
    ],
    "sg:phone":"+1 320 398 2828",
    "sg:postcode":"55382",
    "sg:province":"MN",
    "sg:tags":[
        "durable",
        "good"
    ],
    "wof:name":"Big Sky Ranch",
    "wof:placetype":"venue"
},
  "geometry": {"coordinates":[-94.220451,45.39957],"type":"Point"}
}