{
  "type": "Feature",
  "properties": {
    "addr:full":"1901 E Madison Ave # 610 Mankato MN 56001",
    "addr:housenumber":"1901",
    "addr:postcode":"56001",
    "addr:street":"E Madison Ave # 610",
    "iso:country":"US",
    "sg:address":"1901 E Madison Ave # 610",
    "sg:city":"Mankato",
    "sg:classifiers":[
        {
            "category":"Shopping",
            "subcategory":"Pets & Pet Supplies",
            "type":"Retail Goods"
        },
        {
            "category":"Museum",
            "subcategory":"Aquarium",
            "type":"Entertainment"
        },
        {
            "category":"Retail",
            "subcategory":"Animal Services",
            "type":"Services"
        }
    ],
    "sg:phone":"+1 507 388 4755",
    "sg:postcode":"56001",
    "sg:province":"MN",
    "sg:tags":[
        "food",
        "dog",
        "cat",
        "furnishing",
        "grooming",
        "store"
    ],
    "sg:website":"http://www.petco.com",
    "wof:name":"PETCO",
    "wof:placetype":"venue"
},
  "geometry": {"coordinates":[-93.948463,44.166801],"type":"Point"}
}