{
  "type": "Feature",
  "properties": {
    "addr:full":"1200 Roberts Rd SW Hutchinson MN 55350",
    "addr:housenumber":"1200",
    "addr:postcode":"55350",
    "addr:street":"Roberts Rd Sw",
    "iso:country":"US",
    "sg:address":"1200 Roberts Rd SW",
    "sg:city":"Hutchinson",
    "sg:classifiers":[
        {
            "category":"Education",
            "subcategory":"School",
            "type":"Public Place"
        }
    ],
    "sg:phone":"+1 320 587 2151",
    "sg:postcode":"55350",
    "sg:province":"MN",
    "sg:tags":[
        "high"
    ],
    "wof:name":"Hutchinson Senior High School",
    "wof:placetype":"venue"
},
  "geometry": {"coordinates":[-94.39340199999999,44.88533],"type":"Point"}
}