{
  "type": "Feature",
  "properties": {
    "addr:full":"7381 Kurvers Point Rd Chanhassen MN 55317",
    "addr:housenumber":"7381",
    "addr:postcode":"55317",
    "addr:street":"Kurvers Point Rd",
    "iso:country":"US",
    "sg:address":"7381 Kurvers Point Rd",
    "sg:city":"Chanhassen",
    "sg:classifiers":[
        {
            "category":"Communications",
            "subcategory":"Film & Video Production",
            "type":"Services"
        }
    ],
    "sg:phone":"+1 952 949 3107",
    "sg:postcode":"55317",
    "sg:province":"MN",
    "sg:tags":[
        "motion",
        "picture"
    ],
    "wof:name":"Polar Eyes Video Production",
    "wof:placetype":"venue"
},
  "geometry": {"coordinates":[-93.522193,44.870252],"type":"Point"}
}