{
  "type": "Feature",
  "properties": {
    "addr:full":"116 Central Ave Buffalo MN 55313",
    "addr:housenumber":"116",
    "addr:postcode":"55313",
    "addr:street":"Central Ave",
    "iso:country":"US",
    "sg:address":"116 Central Ave",
    "sg:city":"Buffalo",
    "sg:classifiers":[
        {
            "category":"Professional",
            "subcategory":"Lawyer & Legal Services",
            "type":"Services"
        }
    ],
    "sg:phone":"+1 763 682 0032",
    "sg:postcode":"55313",
    "sg:province":"MN",
    "wof:name":"Richard D Clough",
    "wof:placetype":"venue"
},
  "geometry": {"coordinates":[-93.876127,45.173898],"type":"Point"}
}