{
  "type": "Feature",
  "properties": {
    "addr:full":"5534 E Grandview Rd Duluth MN 55810",
    "addr:housenumber":"5534",
    "addr:postcode":"55810",
    "addr:street":"E Grandview Rd",
    "iso:country":"US",
    "sg:address":"5534 E Grandview Rd",
    "sg:city":"Duluth",
    "sg:classifiers":[
        {
            "category":"Insurance",
            "subcategory":"Insurance Agent",
            "type":"Services"
        }
    ],
    "sg:phone":"+1 218 624 5020",
    "sg:postcode":"55810",
    "sg:province":"MN",
    "wof:name":"Lund Financial Services",
    "wof:placetype":"venue"
},
  "geometry": {"coordinates":[-92.26150199999999,46.713252],"type":"Point"}
}