{
  "type": "Feature",
  "properties": {
    "addr:full":"177 Fairview Ln Red Wing MN 55066",
    "addr:housenumber":"177",
    "addr:postcode":"55066",
    "addr:street":"Fairview Ln",
    "iso:country":"US",
    "sg:address":"177 Fairview Ln",
    "sg:city":"Red Wing",
    "sg:classifiers":[
        {
            "category":"Wholesale",
            "subcategory":"Vending Machines",
            "type":"Manufacturing & Wholesale Goods"
        }
    ],
    "sg:phone":"+1 651 388 7762",
    "sg:postcode":"55066",
    "sg:province":"MN",
    "sg:tags":[
        "operator"
    ],
    "wof:name":"Accent Vending",
    "wof:placetype":"venue"
},
  "geometry": {"coordinates":[-92.57753099999999,44.567021],"type":"Point"}
}