{
  "type": "Feature",
  "properties": {
    "addr:full":"3008 E 26th St Minneapolis MN 55406",
    "addr:housenumber":"3008",
    "addr:postcode":"55406",
    "addr:street":"E 26Th St",
    "iso:country":"US",
    "sg:address":"3008 E 26th St",
    "sg:city":"Minneapolis",
    "sg:classifiers":[
        {
            "category":"Wholesale",
            "subcategory":"Non-durable Goods",
            "type":"Manufacturing & Wholesale Goods"
        }
    ],
    "sg:phone":"+1 612 721 8702",
    "sg:postcode":"55406",
    "sg:province":"MN",
    "wof:name":"Creative Placemat Service",
    "wof:placetype":"venue"
},
  "geometry": {"coordinates":[-93.22708,44.955657],"type":"Point"}
}