{
  "type": "Feature",
  "properties": {
    "addr:full":"2480 Fairview Ave N Saint Paul MN 55113",
    "addr:housenumber":"2480",
    "addr:postcode":"55113",
    "addr:street":"Fairview Ave N",
    "iso:country":"US",
    "sg:address":"2480 Fairview Ave N",
    "sg:city":"Saint Paul",
    "sg:classifiers":[
        {
            "category":"Sports & Exercise",
            "subcategory":"Gym",
            "type":"Entertainment"
        }
    ],
    "sg:phone":"+1 651 633 4444",
    "sg:postcode":"55113",
    "sg:province":"MN",
    "sg:tags":[
        "club",
        "studio",
        "health",
        "gymnasium"
    ],
    "sg:website":"www.lifetimefitness.com",
    "wof:name":"Life Time Fitness",
    "wof:placetype":"venue"
},
  "geometry": {"coordinates":[-93.177002,45.015499],"type":"Point"}
}