{
  "type": "Feature",
  "properties": {
    "iso:country":"US",
    "sg:address":"34841 370th Ave NW",
    "sg:city":"Argyle",
    "sg:phone":"+1 218 437 6418",
    "sg:postcode":"56713",
    "sg:province":"MN",
    "sg:tags":[
        "farm",
        "grain",
        "cash"
    ],
    "wof:name":"Gerald Dufault",
    "wof:placetype":"venue"
},
  "geometry": {"coordinates":[-96.84579100000001,48.372114],"type":"Point"}
}