{
  "type": "Feature",
  "properties": {
    "iso:country":"US",
    "sg:address":"921 Minnesota St S",
    "sg:city":"Shakopee",
    "sg:classifiers":[
        {
            "category":"Social Services",
            "subcategory":"Child Care",
            "type":"Services"
        }
    ],
    "sg:phone":"+1 952 496 1953",
    "sg:postcode":"55379",
    "sg:province":"MN",
    "sg:tags":[
        "daycare",
        "provider"
    ],
    "wof:name":"Barbara Cordes",
    "wof:placetype":"venue"
},
  "geometry": {"coordinates":[-93.51589199999999,44.788664],"type":"Point"}
}