{
  "type": "Feature",
  "properties": {
    "iso:country":"US",
    "sg:address":"615 W 5th St",
    "sg:city":"Red Wing",
    "sg:classifiers":[
        {
            "category":"Organizations",
            "subcategory":"Religious Organization",
            "type":"Services"
        }
    ],
    "sg:phone":"+1 651 388 9311",
    "sg:postcode":"55066",
    "sg:province":"MN",
    "sg:tags":[
        "church"
    ],
    "wof:name":"First Lutheran Church-Elca",
    "wof:placetype":"venue"
},
  "geometry": {"coordinates":[-92.534837,44.56196],"type":"Point"}
}