{
  "type": "Feature",
  "properties": {
    "addr:full":"4168 W Broadway Ave Minneapolis MN 55422",
    "addr:housenumber":"4168",
    "addr:postcode":"55422",
    "addr:street":"W Broadway Ave",
    "iso:country":"US",
    "sg:address":"4168 W Broadway Ave",
    "sg:city":"Minneapolis",
    "sg:classifiers":[
        {
            "category":"Restaurant",
            "type":"Food & Drink"
        }
    ],
    "sg:phone":"+1 763 533 8225",
    "sg:postcode":"55422",
    "sg:province":"MN",
    "wof:name":"13 Moons Inc",
    "wof:placetype":"venue"
},
  "geometry": {"coordinates":[-93.33893500000001,45.030964],"type":"Point"}
}