{
  "type": "Feature",
  "properties": {
    "addr:full":"110 W Luverne St Luverne MN 56156",
    "addr:housenumber":"110",
    "addr:postcode":"56156",
    "addr:street":"W Luverne St",
    "iso:country":"US",
    "sg:address":"110 W Luverne St",
    "sg:city":"Luverne",
    "sg:classifiers":[
        {
            "category":"Wholesale",
            "subcategory":"Electrical",
            "type":"Manufacturing & Wholesale Goods"
        }
    ],
    "sg:phone":"+1 507 283 8453",
    "sg:postcode":"56156",
    "sg:province":"MN",
    "sg:tags":[
        "equipment"
    ],
    "wof:name":"Winpower Sales & Service",
    "wof:placetype":"venue"
},
  "geometry": {"coordinates":[-96.210939,43.656362],"type":"Point"}
}