{
  "type": "Feature",
  "properties": {
    "iso:country":"US",
    "sg:address":"517 Garfield Ave",
    "sg:city":"Duluth",
    "sg:classifiers":[
        {
            "category":"Building & Trades",
            "subcategory":"Construction",
            "type":"Services"
        }
    ],
    "sg:phone":"+1 218 726 1192",
    "sg:postcode":"55802",
    "sg:province":"MN",
    "sg:tags":[
        "general",
        "contractor"
    ],
    "wof:name":"Builders Commonwealth",
    "wof:placetype":"venue"
},
  "geometry": {"coordinates":[-92.11087999999999,46.761971],"type":"Point"}
}