{
  "type": "Feature",
  "properties": {
    "addr:full":"2144 University Ave W Saint Paul MN 55114",
    "addr:housenumber":"2144",
    "addr:postcode":"55114",
    "addr:street":"University Ave W",
    "iso:country":"US",
    "sg:address":"2144 University Ave W",
    "sg:city":"Saint Paul",
    "sg:classifiers":[
        {
            "category":"Travel",
            "subcategory":"Hotels & Motels",
            "type":"Entertainment"
        }
    ],
    "sg:phone":"+1 651 646 4770",
    "sg:postcode":"55114",
    "sg:province":"MN",
    "wof:name":"Midwest Hotel",
    "wof:placetype":"venue"
},
  "geometry": {"coordinates":[-93.18890399999999,44.960499],"type":"Point"}
}