{
  "type": "Feature",
  "properties": {
    "addr:full":"19826 325th Ave Hillman MN 56338",
    "addr:housenumber":"19826",
    "addr:postcode":"56338",
    "addr:street":"325Th Ave",
    "iso:country":"US",
    "sg:address":"19826 325th Ave",
    "sg:city":"Hillman",
    "sg:classifiers":[
        {
            "category":"Farming",
            "subcategory":"Dairy Farm",
            "type":"Manufacturing & Wholesale Goods"
        }
    ],
    "sg:phone":"+1 320 468 2150",
    "sg:postcode":"56338",
    "sg:province":"MN",
    "sg:tags":[
        "corn"
    ],
    "wof:name":"Jaco Co",
    "wof:placetype":"venue"
},
  "geometry": {"coordinates":[-93.988375,46.048761],"type":"Point"}
}