{
  "type": "Feature",
  "properties": {
    "addr:full":"350 Johnson Ave SE Pine City MN 55063",
    "addr:housenumber":"350",
    "addr:postcode":"55063",
    "addr:street":"Johnson Ave Se",
    "iso:country":"US",
    "sg:address":"350 Johnson Ave SE",
    "sg:city":"Pine City",
    "sg:classifiers":[
        {
            "category":"Real Estate",
            "subcategory":"Developer",
            "type":"Services"
        }
    ],
    "sg:phone":"+1 320 629 6059",
    "sg:postcode":"55063",
    "sg:province":"MN",
    "sg:tags":[
        "mobile",
        "home"
    ],
    "wof:name":"Pine Terrace Mobile Home Park",
    "wof:placetype":"venue"
},
  "geometry": {"coordinates":[-92.96894899999999,45.817309],"type":"Point"}
}