{
  "type": "Feature",
  "properties": {
    "addr:full":"48187 80th Ave Kenyon MN 55946",
    "addr:housenumber":"48187",
    "addr:postcode":"55946",
    "addr:street":"80Th Ave Kenyon",
    "iso:country":"US",
    "sg:address":"48187 80th Ave",
    "sg:city":"Kenyon",
    "sg:classifiers":[
        {
            "category":"Professional",
            "type":"Services"
        }
    ],
    "sg:phone":"+1 507 789 6601",
    "sg:postcode":"55946",
    "sg:province":"MN",
    "wof:name":"Bernard Mattson",
    "wof:placetype":"venue"
},
  "geometry": {"coordinates":[-92.87209900000001,44.252051],"type":"Point"}
}