{
  "type": "Feature",
  "properties": {
    "addr:full":"487 2nd St NE Richmond MN 56368",
    "addr:housenumber":"487",
    "addr:postcode":"56368",
    "addr:street":"2Nd St Ne",
    "iso:country":"US",
    "sg:address":"487 2nd St NE",
    "sg:city":"Richmond",
    "sg:classifiers":[
        {
            "category":"Real Estate",
            "subcategory":"Real Estate Operator",
            "type":"Services"
        }
    ],
    "sg:phone":"+1 320 597 3091",
    "sg:postcode":"56368",
    "sg:province":"MN",
    "sg:tags":[
        "apartment"
    ],
    "wof:name":"Maple Apartments",
    "wof:placetype":"venue"
},
  "geometry": {"coordinates":[-94.51105200000001,45.455975],"type":"Point"}
}