{
  "type": "Feature",
  "properties": {
    "iso:country":"US",
    "sg:address":"1012 2nd St SE",
    "sg:city":"Willmar",
    "sg:classifiers":[
        {
            "category":"Professional",
            "type":"Services"
        }
    ],
    "sg:phone":"+1 320 214 5660",
    "sg:postcode":"56201",
    "sg:province":"MN",
    "sg:tags":[
        "establishment"
    ],
    "wof:name":"Bethesda Willmar",
    "wof:placetype":"venue"
},
  "geometry": {"coordinates":[-95.041342,45.114074],"type":"Point"}
}