{
  "type": "Feature",
  "properties": {
    "addr:full":"6316 70th Ave N Minneapolis MN 55429",
    "addr:housenumber":"6316",
    "addr:postcode":"55429",
    "addr:street":"70Th Ave N",
    "iso:country":"US",
    "sg:address":"6316 70th Ave N",
    "sg:city":"Minneapolis",
    "sg:classifiers":[
        {
            "category":"Building & Trades",
            "subcategory":"Landscaping Services",
            "type":"Services"
        }
    ],
    "sg:phone":"+1 763 576 9278",
    "sg:postcode":"55429",
    "sg:province":"MN",
    "sg:tags":[
        "lawn",
        "landscape",
        "contractor"
    ],
    "wof:name":"Ambassador Landscaping",
    "wof:placetype":"venue"
},
  "geometry": {"coordinates":[-93.361771,45.082771],"type":"Point"}
}