{
  "type": "Feature",
  "properties": {
    "iso:country":"US",
    "sg:address":"3329 University Ave SE",
    "sg:city":"Minneapolis",
    "sg:classifiers":[
        {
            "category":"Organizations",
            "subcategory":"Non-profit Organization",
            "type":"Services"
        }
    ],
    "sg:phone":"+1 612 638 2282",
    "sg:postcode":"55414",
    "sg:province":"MN",
    "sg:tags":[
        "information",
        "alcoholism",
        "treatment"
    ],
    "wof:name":"Avalon Prospect Park",
    "wof:placetype":"venue"
},
  "geometry": {"coordinates":[-93.20946499999999,44.968867],"type":"Point"}
}