{
  "type": "Feature",
  "properties": {
    "addr:full":"2613 4th St SE Minneapolis MN 55414",
    "addr:housenumber":"2613",
    "addr:postcode":"55414",
    "addr:street":"4Th St Se",
    "iso:country":"US",
    "sg:address":"2613 4th St SE",
    "sg:city":"Minneapolis",
    "sg:classifiers":[
        {
            "category":"Wholesale",
            "subcategory":"Machinery & Supplies",
            "type":"Manufacturing & Wholesale Goods"
        },
        {
            "category":"Wholesale",
            "subcategory":"Chemicals & Plastics",
            "type":"Manufacturing & Wholesale Goods"
        }
    ],
    "sg:phone":"+1 612 379 7711",
    "sg:postcode":"55414",
    "sg:province":"MN",
    "sg:tags":[
        "equipment",
        "establishment"
    ],
    "sg:website":"www.savoiesupply.com",
    "wof:name":"Savoie Supply Co Inc",
    "wof:placetype":"venue"
},
  "geometry": {"coordinates":[-93.22054199999999,44.974396],"type":"Point"}
}