{
  "type": "Feature",
  "properties": {
    "iso:country":"US",
    "sg:address":"15612 Highway 7 Ste 334",
    "sg:city":"Minnetonka",
    "sg:classifiers":[
        {
            "category":"Wholesale",
            "subcategory":"Fruits & Vegetables",
            "type":"Manufacturing & Wholesale Goods"
        }
    ],
    "sg:phone":"+1 952 933 3644",
    "sg:postcode":"55345",
    "sg:province":"MN",
    "sg:tags":[
        "vegetables-wholesale"
    ],
    "wof:name":"Dole",
    "wof:placetype":"venue"
},
  "geometry": {"coordinates":[-93.47911999999999,44.920258],"type":"Point"}
}