{
  "type": "Feature",
  "properties": {
    "addr:full":"2191 Silver Lake Rd NW Saint Paul MN 55112",
    "addr:housenumber":"2191",
    "addr:postcode":"55112",
    "addr:street":"Silver Lake Rd Nw",
    "iso:country":"US",
    "sg:address":"2191 Silver Lake Rd NW",
    "sg:city":"Saint Paul",
    "sg:classifiers":[
        {
            "category":"Organizations",
            "subcategory":"Community Association",
            "type":"Services"
        }
    ],
    "sg:phone":"+1 651 633 4440",
    "sg:postcode":"55112",
    "sg:province":"MN",
    "wof:name":"Royal Oaks Estates Homeowners",
    "wof:placetype":"venue"
},
  "geometry": {"coordinates":[-93.21883699999999,45.083538],"type":"Point"}
}