{
  "type": "Feature",
  "properties": {
    "addr:full":"301 E Lake St Minneapolis MN 55408",
    "addr:housenumber":"301",
    "addr:postcode":"55408",
    "addr:street":"E Lake St",
    "iso:country":"US",
    "sg:address":"301 E Lake St",
    "sg:city":"Minneapolis",
    "sg:classifiers":[
        {
            "category":"Restaurant",
            "type":"Food & Drink"
        },
        {
            "category":"Ice Cream",
            "type":"Food & Drink"
        }
    ],
    "sg:phone":"+1 612 822 3700",
    "sg:postcode":"55408",
    "sg:province":"MN",
    "sg:tags":[
        "frozen",
        "dessert"
    ],
    "wof:name":"Ice Cream Pineda Inc",
    "wof:placetype":"venue"
},
  "geometry": {"coordinates":[-93.272858,44.94836],"type":"Point"}
}