{
  "type": "Feature",
  "properties": {
    "addr:full":"7601 34th Ave S Minneapolis MN 55450",
    "addr:housenumber":"7601",
    "addr:postcode":"55450",
    "addr:street":"34Th Ave S",
    "iso:country":"US",
    "sg:address":"7601 34th Ave S",
    "sg:city":"Minneapolis",
    "sg:classifiers":[
        {
            "category":"Real Estate",
            "subcategory":"Developer",
            "type":"Services"
        }
    ],
    "sg:phone":"+1 612 726 1127",
    "sg:postcode":"55450",
    "sg:province":"MN",
    "sg:tags":[
        "cemetery"
    ],
    "wof:name":"Ft Snelling National Cemetery",
    "wof:placetype":"venue"
},
  "geometry": {"coordinates":[-93.22301400000001,44.865293],"type":"Point"}
}