{
  "type": "Feature",
  "properties": {
    "iso:country":"US",
    "sg:address":"1100 Silver Lake Rd NW",
    "sg:city":"New Brighton",
    "sg:classifiers":[
        {
            "category":"Autos & Motor Vehicles",
            "subcategory":"Automobile Sales",
            "type":"Retail Goods"
        }
    ],
    "sg:phone":"+1 651 633 9010",
    "sg:postcode":"55112",
    "sg:province":"MN",
    "sg:tags":[
        "car",
        "dealer"
    ],
    "sg:website":"www.newbrightonford.com",
    "wof:name":"New Brighton Ford",
    "wof:placetype":"venue"
},
  "geometry": {"coordinates":[-93.218615,45.067608],"type":"Point"}
}