{
  "type": "Feature",
  "properties": {
    "addr:full":"4457 University Ave NE Minneapolis MN 55421",
    "addr:housenumber":"4457",
    "addr:postcode":"55421",
    "addr:street":"University Ave Ne",
    "iso:country":"US",
    "sg:address":"4457 University Ave NE",
    "sg:city":"Minneapolis",
    "sg:classifiers":[
        {
            "category":"Personal",
            "type":"Services"
        },
        {
            "category":"Retail",
            "subcategory":"Auto Repair",
            "type":"Services"
        }
    ],
    "sg:phone":"+1 763 572 1621",
    "sg:postcode":"55421",
    "sg:province":"MN",
    "sg:tags":[
        "towing"
    ],
    "sg:website":"www.napaautocare.com",
    "wof:name":"Lowell's Auto Repair",
    "wof:placetype":"venue"
},
  "geometry": {"coordinates":[-93.26300000000001,45.0494],"type":"Point"}
}