{
  "type": "Feature",
  "properties": {
    "addr:full":"1665 Highwood Dr Chaska MN 55318",
    "addr:housenumber":"1665",
    "addr:postcode":"55318",
    "addr:street":"Highwood Dr",
    "iso:country":"US",
    "sg:address":"1665 Highwood Dr",
    "sg:city":"Chaska",
    "sg:classifiers":[
        {
            "category":"Building & Trades",
            "subcategory":"Electrical",
            "type":"Services"
        },
        {
            "category":"Utilities",
            "subcategory":"Electric",
            "type":"Services"
        }
    ],
    "sg:phone":"+1 952 448 1789",
    "sg:postcode":"55318",
    "sg:province":"MN",
    "sg:tags":[
        "contractor"
    ],
    "wof:name":"River City Electric",
    "wof:placetype":"venue"
},
  "geometry": {"coordinates":[-93.60269700000001,44.807006],"type":"Point"}
}