{
  "type": "Feature",
  "properties": {
    "addr:full":"1252 10th Ave Pipestone MN 56164",
    "addr:housenumber":"1252",
    "addr:postcode":"56164",
    "addr:street":"10Th Ave",
    "iso:country":"US",
    "sg:address":"1252 10th Ave",
    "sg:city":"Pipestone",
    "sg:classifiers":[
        {
            "category":"Farming",
            "subcategory":"Farm",
            "type":"Manufacturing & Wholesale Goods"
        }
    ],
    "sg:phone":"+1 507 825 2797",
    "sg:postcode":"56164",
    "sg:province":"MN",
    "sg:tags":[
        "crop",
        "general"
    ],
    "wof:name":"Wayne Brockberg",
    "wof:placetype":"venue"
},
  "geometry": {"coordinates":[-96.4482,44.03343],"type":"Point"}
}