{
  "type": "Feature",
  "properties": {
    "iso:country":"US",
    "sg:address":"42612 370th Ave",
    "sg:city":"Dent",
    "sg:classifiers":[
        {
            "category":"Health Services",
            "subcategory":"Nursing And Care Facility",
            "type":"Services"
        }
    ],
    "sg:phone":"+1 218 346 2875",
    "sg:postcode":"56528",
    "sg:province":"MN",
    "wof:name":"Peleske Group Home",
    "wof:placetype":"venue"
},
  "geometry": {"coordinates":[-95.720586,46.579615],"type":"Point"}
}