{
  "type": "Feature",
  "properties": {
    "iso:country":"US",
    "sg:address":"2019 Minnehaha Ave E",
    "sg:city":"St Paul",
    "sg:classifiers":[
        {
            "category":"Food & Beverages",
            "subcategory":"Groceries & Convenience Stores",
            "type":"Retail Goods"
        }
    ],
    "sg:phone":"+1 651 735 2246",
    "sg:postcode":"55119",
    "sg:province":"MN",
    "sg:tags":[
        "grocer"
    ],
    "wof:name":"Minni Market",
    "wof:placetype":"venue"
},
  "geometry": {"coordinates":[-93.01265600000001,44.96306],"type":"Point"}
}