{
  "type": "Feature",
  "properties": {
    "addr:full":"3357 University Ave SE Minneapolis MN 55414",
    "addr:housenumber":"3357",
    "addr:postcode":"55414",
    "addr:street":"University Ave Se",
    "iso:country":"US",
    "sg:address":"3357 University Ave SE",
    "sg:city":"Minneapolis",
    "sg:classifiers":[
        {
            "category":"Autos & Motor Vehicles",
            "subcategory":"Fuel & Gas Station",
            "type":"Retail Goods"
        }
    ],
    "sg:phone":"+1 612 379 7829",
    "sg:postcode":"55414",
    "sg:province":"MN",
    "sg:tags":[
        "oil"
    ],
    "wof:name":"Super America",
    "wof:placetype":"venue"
},
  "geometry": {"coordinates":[-93.20998299999999,44.969159],"type":"Point"}
}