{
  "type": "Feature",
  "properties": {
    "iso:country":"US",
    "sg:address":"943 9th Ave SW",
    "sg:city":"Forest Lake",
    "sg:classifiers":[
        {
            "category":"Education",
            "subcategory":"School",
            "type":"Public Place"
        }
    ],
    "sg:phone":"+1 651 982 8700",
    "sg:postcode":"55025",
    "sg:province":"MN",
    "sg:website":"www.forestlake.k12.mn.us",
    "wof:name":"Southwest Junior High School",
    "wof:placetype":"venue"
},
  "geometry": {"coordinates":[-92.994575,45.27042],"type":"Point"}
}