{
  "type": "Feature",
  "properties": {
    "iso:country":"US",
    "sg:address":"308 1st St S",
    "sg:city":"Canby",
    "sg:classifiers":[
        {
            "category":"Retail",
            "subcategory":"Auto Repair",
            "type":"Services"
        }
    ],
    "sg:phone":"+1 507 223 7788",
    "sg:postcode":"56220",
    "sg:province":"MN",
    "sg:tags":[
        "body",
        "automobile",
        "painting"
    ],
    "wof:name":"Bob's Collision",
    "wof:placetype":"venue"
},
  "geometry": {"coordinates":[-96.28033600000001,44.709934],"type":"Point"}
}