{
  "type": "Feature",
  "properties": {
    "iso:country":"US",
    "sg:address":"1985 Valley Pine Cir",
    "sg:city":"Internatl Falls",
    "sg:classifiers":[
        {
            "category":"Home & Garden",
            "subcategory":"Building Materials",
            "type":"Retail Goods"
        }
    ],
    "sg:phone":"+1 218 283 4605",
    "sg:postcode":"56649",
    "sg:province":"MN",
    "sg:tags":[
        "center"
    ],
    "wof:name":"Menards",
    "wof:placetype":"venue"
},
  "geometry": {"coordinates":[-93.440758,48.588075],"type":"Point"}
}