{
  "type": "Feature",
  "properties": {
    "addr:full":"115 5th Ave NW Aitkin MN 56431",
    "addr:housenumber":"115",
    "addr:postcode":"56431",
    "addr:street":"5Th Ave Nw",
    "iso:country":"US",
    "sg:address":"115 5th Ave NW",
    "sg:city":"Aitkin",
    "sg:classifiers":[
        {
            "category":"Retail",
            "subcategory":"Repair Shop",
            "type":"Services"
        }
    ],
    "sg:phone":"+1 218 927 6256",
    "sg:postcode":"56431",
    "sg:province":"MN",
    "wof:name":"Ricks Piano Service",
    "wof:placetype":"venue"
},
  "geometry": {"coordinates":[-93.714204,46.533201],"type":"Point"}
}