{
  "type": "Feature",
  "properties": {
    "addr:full":"224 Church St SE Minneapolis MN 55455",
    "addr:housenumber":"224",
    "addr:postcode":"55455",
    "addr:street":"Church St Se",
    "iso:country":"US",
    "sg:address":"224 Church St SE",
    "sg:city":"Minneapolis",
    "sg:classifiers":[
        {
            "category":"Professional",
            "type":"Services"
        }
    ],
    "sg:phone":"+1 612 624 3694",
    "sg:postcode":"55455",
    "sg:province":"MN",
    "sg:tags":[
        "establishment"
    ],
    "wof:name":"Twin Cities Intl Program",
    "wof:placetype":"venue"
},
  "geometry": {"coordinates":[-93.233819,44.974731],"type":"Point"}
}