{
  "type": "Feature",
  "properties": {
    "addr:full":"1937 Ashland Ave Saint Paul MN 55104",
    "addr:housenumber":"1937",
    "addr:postcode":"55104",
    "addr:street":"Ashland Ave",
    "iso:country":"US",
    "sg:address":"1937 Ashland Ave",
    "sg:city":"Saint Paul",
    "sg:classifiers":[
        {
            "category":"Shopping",
            "subcategory":"Shoes",
            "type":"Retail Goods"
        }
    ],
    "sg:phone":"+1 651 642 9636",
    "sg:postcode":"55104",
    "sg:province":"MN",
    "wof:name":"Feet First",
    "wof:placetype":"venue"
},
  "geometry": {"coordinates":[-93.181682,44.944051],"type":"Point"}
}