{
  "type": "Feature",
  "properties": {
    "iso:country":"US",
    "sg:address":"3943 Thames Ave",
    "sg:city":"Saint Paul",
    "sg:classifiers":[
        {
            "category":"Professional",
            "subcategory":"Secretarial Services",
            "type":"Services"
        }
    ],
    "sg:phone":"+1 651 452 7026",
    "sg:postcode":"55123",
    "sg:province":"MN",
    "sg:tags":[
        "reporting",
        "public",
        "relations"
    ],
    "wof:name":"Welle Written",
    "wof:placetype":"venue"
},
  "geometry": {"coordinates":[-93.11108900000001,44.81212],"type":"Point"}
}