{
  "type": "Feature",
  "properties": {
    "addr:full":"6417 Penn Ave S Lowr Minneapolis MN 55423",
    "addr:housenumber":"6417",
    "addr:postcode":"55423",
    "addr:street":"Penn Ave S Lowr",
    "iso:country":"US",
    "sg:address":"6417 Penn Ave S Lowr",
    "sg:city":"Minneapolis",
    "sg:classifiers":[
        {
            "category":"Real Estate",
            "subcategory":"Real Estate Services",
            "type":"Services"
        },
        {
            "category":"Real Estate",
            "subcategory":"Real Estate Agent",
            "type":"Services"
        }
    ],
    "sg:phone":"+1 612 250 4200",
    "sg:postcode":"55423",
    "sg:province":"MN",
    "sg:tags":[
        "management"
    ],
    "wof:name":"Primera Real Estate Company Inc",
    "wof:placetype":"venue"
},
  "geometry": {"coordinates":[-93.30867000000001,44.886841],"type":"Point"}
}