{
  "type": "Feature",
  "properties": {
    "iso:country":"US",
    "sg:address":"16771 Co Rd 30 SW",
    "sg:city":"Cokato",
    "sg:classifiers":[
        {
            "category":"Organizations",
            "subcategory":"Religious Organization",
            "type":"Services"
        }
    ],
    "sg:phone":"+1 320 286 2865",
    "sg:postcode":"55321",
    "sg:province":"MN",
    "wof:name":"Bob Lea",
    "wof:placetype":"venue"
},
  "geometry": {"coordinates":[-94.23052300000001,45.035696],"type":"Point"}
}