{
  "type": "Feature",
  "properties": {
    "iso:country":"US",
    "sg:address":"2101 W 2nd St",
    "sg:city":"Duluth",
    "sg:classifiers":[
        {
            "category":"Organizations",
            "subcategory":"Religious Organization",
            "type":"Services"
        }
    ],
    "sg:phone":"+1 218 722 5451",
    "sg:postcode":"55806",
    "sg:province":"MN",
    "sg:tags":[
        "church"
    ],
    "sg:website":"www.firstcovchurch.org",
    "wof:name":"First Covenant Church",
    "wof:placetype":"venue"
},
  "geometry": {"coordinates":[-92.127737,46.767317],"type":"Point"}
}