{
  "type": "Feature",
  "properties": {
    "iso:country":"US",
    "sg:address":"875 170th Ave SW",
    "sg:city":"Appleton",
    "sg:phone":"+1 320 289 1615",
    "sg:postcode":"56208",
    "sg:province":"MN",
    "sg:tags":[
        "farm",
        "corn"
    ],
    "wof:name":"Knob Hill",
    "wof:placetype":"venue"
},
  "geometry": {"coordinates":[-95.919411,45.200742],"type":"Point"}
}