{
  "type": "Feature",
  "properties": {
    "addr:full":"10215 330th St W Northfield MN 55057",
    "addr:housenumber":"10215",
    "addr:postcode":"55057",
    "addr:street":"330Th St W",
    "iso:country":"US",
    "sg:address":"10215 330th St W",
    "sg:city":"Northfield",
    "sg:classifiers":[
        {
            "category":"Education",
            "subcategory":"Special Training",
            "type":"Public Place"
        }
    ],
    "sg:phone":"+1 507 663 1798",
    "sg:postcode":"55057",
    "sg:province":"MN",
    "wof:name":"Milestone Learning Company",
    "wof:placetype":"venue"
},
  "geometry": {"coordinates":[-93.276174,44.471914],"type":"Point"}
}