{
  "type": "Feature",
  "properties": {
    "iso:country":"US",
    "sg:address":"1688 Lexington Ave N",
    "sg:city":"Saint Paul",
    "sg:classifiers":[
        {
            "category":"Home & Garden",
            "subcategory":"Hardware",
            "type":"Retail Goods"
        }
    ],
    "sg:phone":"+1 651 488 0511",
    "sg:postcode":"55113",
    "sg:province":"MN",
    "sg:tags":[
        "store"
    ],
    "wof:name":"True Value",
    "wof:placetype":"venue"
},
  "geometry": {"coordinates":[-93.14636900000001,44.993589],"type":"Point"}
}