{
  "type": "Feature",
  "properties": {
    "addr:full":"9275 Sage Rd Hillman MN 56338",
    "addr:housenumber":"9275",
    "addr:postcode":"56338",
    "addr:street":"Sage Rd",
    "iso:country":"US",
    "sg:address":"9275 Sage Rd",
    "sg:city":"Hillman",
    "sg:classifiers":[
        {
            "category":"Wholesale",
            "subcategory":"Machinery & Supplies",
            "type":"Manufacturing & Wholesale Goods"
        }
    ],
    "sg:phone":"+1 320 355 2500",
    "sg:postcode":"56338",
    "sg:province":"MN",
    "wof:name":"Gotvald Implement",
    "wof:placetype":"venue"
},
  "geometry": {"coordinates":[-93.850607,45.887906],"type":"Point"}
}