{
  "type": "Feature",
  "properties": {
    "iso:country":"US",
    "sg:address":"3608 Rae Ln",
    "sg:city":"Saint Paul",
    "sg:classifiers":[
        {
            "category":"Shopping",
            "subcategory":"Bicycles & Sporting Goods",
            "type":"Retail Goods"
        }
    ],
    "sg:phone":"+1 651 735 5650",
    "sg:postcode":"55125",
    "sg:province":"MN",
    "wof:name":"Winning Team Sports",
    "wof:placetype":"venue"
},
  "geometry": {"coordinates":[-92.907028,44.897267],"type":"Point"}
}