{
  "type": "Feature",
  "properties": {
    "addr:full":"2116 Dunedin Ave Duluth MN 55803",
    "addr:housenumber":"2116",
    "addr:postcode":"55803",
    "addr:street":"Dunedin Ave",
    "iso:country":"US",
    "sg:address":"2116 Dunedin Ave",
    "sg:city":"Duluth",
    "sg:classifiers":[
        {
            "category":"Professional",
            "type":"Services"
        }
    ],
    "sg:phone":"+1 218 728 2377",
    "sg:postcode":"55803",
    "sg:province":"MN",
    "wof:name":"Bluewater Diversfd Companies",
    "wof:placetype":"venue"
},
  "geometry": {"coordinates":[-92.078597,46.831033],"type":"Point"}
}