{
  "type": "Feature",
  "properties": {
    "addr:full":"2950 Matthew Dr Windom MN 56101",
    "addr:housenumber":"2950",
    "addr:postcode":"56101",
    "addr:street":"Matthew Dr",
    "iso:country":"US",
    "sg:address":"2950 Matthew Dr",
    "sg:city":"Windom",
    "sg:classifiers":[
        {
            "category":"Government",
            "subcategory":"Office",
            "type":"Public Place"
        }
    ],
    "sg:phone":"+1 507 831 5244",
    "sg:postcode":"56101",
    "sg:province":"MN",
    "sg:tags":[
        "management"
    ],
    "wof:name":"Minnesota Municipal Utilities",
    "wof:placetype":"venue"
},
  "geometry": {"coordinates":[-95.149106,43.887386],"type":"Point"}
}