{
  "type": "Feature",
  "properties": {
    "addr:full":"485 Highway 71 SW Tenstrike MN 56683",
    "addr:housenumber":"485",
    "addr:postcode":"56683",
    "addr:street":"Highway 71 Sw",
    "iso:country":"US",
    "sg:address":"485 Highway 71 SW",
    "sg:city":"Tenstrike",
    "sg:classifiers":[
        {
            "category":"Health Services",
            "subcategory":"Doctor",
            "type":"Services"
        }
    ],
    "sg:phone":"+1 218 586 2927",
    "sg:postcode":"56683",
    "sg:province":"MN",
    "sg:tags":[
        "psychologist"
    ],
    "wof:name":"Eric Graham Ms Ma",
    "wof:placetype":"venue"
},
  "geometry": {"coordinates":[-94.674986,47.671433],"type":"Point"}
}