{
  "type": "Feature",
  "properties": {
    "iso:country":"US",
    "sg:address":"383 E Jessamine Ave",
    "sg:city":"Saint Paul",
    "sg:classifiers":[
        {
            "category":"Professional",
            "subcategory":"Business Services",
            "type":"Services"
        }
    ],
    "sg:phone":"+1 651 776 6459",
    "sg:postcode":"55101",
    "sg:province":"MN",
    "wof:name":"Softech Web Solutions",
    "wof:placetype":"venue"
},
  "geometry": {"coordinates":[-93.085078,44.974692],"type":"Point"}
}