{
  "type": "Feature",
  "properties": {
    "iso:country":"US",
    "sg:address":"12969 Fremont Ave",
    "sg:city":"Zimmerman",
    "sg:classifiers":[
        {
            "category":"Manufacturing",
            "subcategory":"Lumber",
            "type":"Manufacturing & Wholesale Goods"
        }
    ],
    "sg:phone":"+1 763 856 4826",
    "sg:postcode":"55398",
    "sg:province":"MN",
    "sg:tags":[
        "government"
    ],
    "sg:website":"www.dnr.state.mn.us",
    "wof:name":"Mn Dnr Div Of Forestry",
    "wof:placetype":"venue"
},
  "geometry": {"coordinates":[-93.59875099999999,45.443467],"type":"Point"}
}