{
  "type": "Feature",
  "properties": {
    "iso:country":"US",
    "sg:address":"7501 Portland Ave S",
    "sg:city":"Richfield",
    "sg:classifiers":[
        {
            "category":"Wholesale",
            "subcategory":"Vending Machines",
            "type":"Manufacturing & Wholesale Goods"
        }
    ],
    "sg:phone":"+1 612 866 0533",
    "sg:postcode":"55423",
    "sg:province":"MN",
    "wof:name":"Frontier Vending Co",
    "wof:placetype":"venue"
},
  "geometry": {"coordinates":[-93.268112,44.865517],"type":"Point"}
}