{
  "type": "Feature",
  "properties": {
    "iso:country":"US",
    "sg:address":"2730 Stillwater Rd",
    "sg:city":"Maplewood",
    "sg:classifiers":[
        {
            "category":"Shopping",
            "subcategory":"Pharmacy",
            "type":"Retail Goods"
        }
    ],
    "sg:phone":"+1 651 735 2300",
    "sg:postcode":"55119",
    "sg:province":"MN",
    "sg:tags":[
        "drug",
        "store"
    ],
    "wof:name":"Oakdale Pharmacy",
    "wof:placetype":"venue"
},
  "geometry": {"coordinates":[-92.989853,44.973361],"type":"Point"}
}