{
  "type": "Feature",
  "properties": {
    "addr:full":"7940 Penn Ave N Minneapolis MN 55444",
    "addr:housenumber":"7940",
    "addr:postcode":"55444",
    "addr:street":"Penn Ave N",
    "iso:country":"US",
    "sg:address":"7940 Penn Ave N",
    "sg:city":"Minneapolis",
    "sg:classifiers":[
        {
            "category":"Home & Garden",
            "subcategory":"Carpets & Floor Coverings",
            "type":"Retail Goods"
        }
    ],
    "sg:phone":"+1 612 296 1827",
    "sg:postcode":"55444",
    "sg:province":"MN",
    "sg:tags":[
        "hardwood",
        "flooring",
        "contractor"
    ],
    "sg:website":"http://www.bluecanoewoodfloors.com/",
    "wof:name":"Blue Canoe Wood Floors, Inc",
    "wof:placetype":"venue"
},
  "geometry": {"coordinates":[-93.311736,45.099148],"type":"Point"}
}