{
  "type": "Feature",
  "properties": {
    "addr:full":"10325 Lyndale Ave S Minneapolis MN 55420",
    "addr:housenumber":"10325",
    "addr:postcode":"55420",
    "addr:street":"Lyndale Ave S",
    "iso:country":"US",
    "sg:address":"10325 Lyndale Ave S",
    "sg:city":"Minneapolis",
    "sg:classifiers":[
        {
            "category":"Education",
            "subcategory":"School",
            "type":"Public Place"
        }
    ],
    "sg:phone":"+1 952 888 6065",
    "sg:postcode":"55420",
    "sg:province":"MN",
    "sg:tags":[
        "handicapped",
        "residence",
        "for"
    ],
    "wof:name":"Lyndale Court",
    "wof:placetype":"venue"
},
  "geometry": {"coordinates":[-93.288546,44.817578],"type":"Point"}
}