{
  "type": "Feature",
  "properties": {
    "addr:full":"7550 France Ave S Minneapolis MN 55435",
    "addr:housenumber":"7550",
    "addr:postcode":"55435",
    "addr:street":"France Ave S",
    "iso:country":"US",
    "sg:address":"7550 France Ave S",
    "sg:city":"Minneapolis",
    "sg:classifiers":[
        {
            "category":"Real Estate",
            "subcategory":"Real Estate Agent",
            "type":"Services"
        },
        {
            "category":"Professional",
            "subcategory":"Management & Consulting",
            "type":"Services"
        }
    ],
    "sg:phone":"+1 952 920 8800",
    "sg:postcode":"55435",
    "sg:province":"MN",
    "sg:tags":[
        "business"
    ],
    "wof:name":"Burnet Realty Inc",
    "wof:placetype":"venue"
},
  "geometry": {"coordinates":[-93.32895000000001,44.865714],"type":"Point"}
}