{
  "type": "Feature",
  "properties": {
    "addr:full":"669 241st St Jasper MN 56164",
    "addr:housenumber":"669",
    "addr:postcode":"56164",
    "addr:street":"241St St",
    "iso:country":"US",
    "sg:address":"669 241st St",
    "sg:city":"Jasper",
    "sg:phone":"+1 507 348 7837",
    "sg:postcode":"56164",
    "sg:province":"MN",
    "sg:tags":[
        "farm",
        "corn",
        "soybean"
    ],
    "wof:name":"Wayne Uilk",
    "wof:placetype":"venue"
},
  "geometry": {"coordinates":[-96.33186000000001,44.197272],"type":"Point"}
}