{
  "type": "Feature",
  "properties": {
    "iso:country":"US",
    "sg:address":"2412 University Ave SE A",
    "sg:city":"Minneapolis",
    "sg:classifiers":[
        {
            "category":"Professional",
            "subcategory":"Printing & Photocopies",
            "type":"Services"
        }
    ],
    "sg:phone":"+1 612 672 9181",
    "sg:postcode":"55414",
    "sg:province":"MN",
    "sg:tags":[
        "photographers-commercial"
    ],
    "wof:name":"Image Group Photogphr",
    "wof:placetype":"venue"
},
  "geometry": {"coordinates":[-93.221959,44.973617],"type":"Point"}
}