{
  "type": "Feature",
  "properties": {
    "addr:full":"204 6th St E Ada MN 56510",
    "addr:housenumber":"204",
    "addr:postcode":"56510",
    "addr:street":"6Th St E",
    "iso:country":"US",
    "sg:address":"204 6th St E",
    "sg:city":"Ada",
    "sg:classifiers":[
        {
            "category":"Personal",
            "subcategory":"Barber",
            "type":"Services"
        }
    ],
    "sg:phone":"+1 218 784 2911",
    "sg:postcode":"56510",
    "sg:province":"MN",
    "wof:name":"Denny's Barber Shop",
    "wof:placetype":"venue"
},
  "geometry": {"coordinates":[-96.505398,47.299404],"type":"Point"}
}