{
  "type": "Feature",
  "properties": {
    "addr:full":"20285 Quentin Ave Hastings MN 55033",
    "addr:housenumber":"20285",
    "addr:postcode":"55033",
    "addr:street":"Quentin Ave",
    "iso:country":"US",
    "sg:address":"20285 Quentin Ave",
    "sg:city":"Hastings",
    "sg:classifiers":[
        {
            "category":"Professional",
            "type":"Services"
        }
    ],
    "sg:phone":"+1 651 437 9243",
    "sg:postcode":"55033",
    "sg:province":"MN",
    "wof:name":"Bits & Spurs Equine Services",
    "wof:placetype":"venue"
},
  "geometry": {"coordinates":[-92.75017099999999,44.653427],"type":"Point"}
}