{
  "type": "Feature",
  "properties": {
    "iso:country":"US",
    "sg:address":"116 2nd Ave SW",
    "sg:city":"Chisholm",
    "sg:classifiers":[
        {
            "category":"Building & Trades",
            "subcategory":"Construction",
            "type":"Services"
        }
    ],
    "sg:phone":"+1 218 254 2747",
    "sg:postcode":"55719",
    "sg:province":"MN",
    "sg:tags":[
        "excavation",
        "home",
        "builder",
        "concrete",
        "contractor"
    ],
    "wof:name":"E J Goroni Construction",
    "wof:placetype":"venue"
},
  "geometry": {"coordinates":[-92.882195,47.488071],"type":"Point"}
}