{
  "type": "Feature",
  "properties": {
    "iso:country":"US",
    "sg:address":"520 N Main St",
    "sg:city":"Stewartville",
    "sg:classifiers":[
        {
            "category":"Restaurant",
            "type":"Food & Drink"
        }
    ],
    "sg:menulink":"http://www.allmenus.com/mn/stewartville/225608-caseys-general-store/menu/",
    "sg:phone":"+1 507 533 7757",
    "sg:postcode":"55976",
    "sg:province":"MN",
    "sg:tags":[
        "american",
        "pizza"
    ],
    "wof:name":"Casey's General Store",
    "wof:placetype":"venue"
},
  "geometry": {"coordinates":[-92.4885,43.858822],"type":"Point"}
}