{
  "type": "Feature",
  "properties": {
    "iso:country":"US",
    "sg:address":"181 83rd Ave NE",
    "sg:city":"Minneapolis",
    "sg:classifiers":[
        {
            "category":"Building & Trades",
            "subcategory":"Construction",
            "type":"Services"
        }
    ],
    "sg:phone":"+1 763 717 4681",
    "sg:postcode":"55432",
    "sg:province":"MN",
    "sg:tags":[
        "hanging",
        "contractor"
    ],
    "wof:name":"Eric Love Painting Comp",
    "wof:placetype":"venue"
},
  "geometry": {"coordinates":[-93.26433900000001,45.11881],"type":"Point"}
}