{
  "type": "Feature",
  "properties": {
    "iso:country":"US",
    "sg:address":"4180 Lexington Ave S",
    "sg:city":"Saint Paul",
    "sg:classifiers":[
        {
            "category":"Organizations",
            "subcategory":"Religious Organization",
            "type":"Services"
        }
    ],
    "sg:phone":"+1 651 681 0219",
    "sg:postcode":"55123",
    "sg:province":"MN",
    "wof:name":"Episcpal Chrch S S Martha Mary",
    "wof:placetype":"venue"
},
  "geometry": {"coordinates":[-93.146162,44.808061],"type":"Point"}
}