{
  "type": "Feature",
  "properties": {
    "iso:country":"US",
    "sg:address":"1350 Larc Industrial Blvd",
    "sg:city":"Burnsville",
    "sg:classifiers":[
        {
            "category":"Wholesale",
            "subcategory":"Computers",
            "type":"Manufacturing & Wholesale Goods"
        }
    ],
    "sg:phone":"+1 952 894 6154",
    "sg:postcode":"55337",
    "sg:province":"MN",
    "sg:website":"www.atrix.com",
    "wof:name":"Atrix International Inc",
    "wof:placetype":"venue"
},
  "geometry": {"coordinates":[-93.254402,44.787498],"type":"Point"}
}