{
  "type": "Feature",
  "properties": {
    "iso:country":"US",
    "sg:address":"2044 230th St",
    "sg:city":"Truman",
    "sg:phone":"+1 507 776 5051",
    "sg:postcode":"56088",
    "sg:province":"MN",
    "sg:tags":[
        "farm",
        "corn",
        "soybean"
    ],
    "wof:name":"Tony Weihe",
    "wof:placetype":"venue"
},
  "geometry": {"coordinates":[-94.46051199999999,43.818257],"type":"Point"}
}