{
  "type": "Feature",
  "properties": {
    "addr:full":"15 E Main St Crosby MN 56441",
    "addr:housenumber":"15",
    "addr:postcode":"56441",
    "addr:street":"E Main St",
    "iso:country":"US",
    "sg:address":"15 E Main St",
    "sg:city":"Crosby",
    "sg:classifiers":[
        {
            "category":"Social Services",
            "type":"Services"
        }
    ],
    "sg:phone":"+1 218 546 8188",
    "sg:postcode":"56441",
    "sg:province":"MN",
    "sg:tags":[
        "organization",
        "welfare"
    ],
    "wof:name":"Head Start",
    "wof:placetype":"venue"
},
  "geometry": {"coordinates":[-93.952116,46.482495],"type":"Point"}
}