{
  "type": "Feature",
  "properties": {
    "iso:country":"US",
    "sg:address":"6 11th St",
    "sg:city":"Cloquet",
    "sg:classifiers":[
        {
            "category":"Professional",
            "subcategory":"Lawyer & Legal Services",
            "type":"Services"
        }
    ],
    "sg:phone":"+1 218 879 1990",
    "sg:postcode":"55720",
    "sg:province":"MN",
    "sg:tags":[
        "attorney"
    ],
    "wof:name":"Dennis Korman Law Office",
    "wof:placetype":"venue"
},
  "geometry": {"coordinates":[-92.452483,46.721573],"type":"Point"}
}