{
  "type": "Feature",
  "properties": {
    "iso:country":"US",
    "sg:address":"13400 Staring Lake Pkwy",
    "sg:city":"Eden Prairie",
    "sg:classifiers":[
        {
            "category":"Education",
            "subcategory":"School",
            "type":"Public Place"
        }
    ],
    "sg:phone":"+1 952 975 7600",
    "sg:postcode":"55347",
    "sg:province":"MN",
    "wof:name":"Oak Point Intermediate",
    "wof:placetype":"venue"
},
  "geometry": {"coordinates":[-93.449175,44.842261],"type":"Point"}
}