{
  "type": "Feature",
  "properties": {
    "addr:full":"4915 Matterhorn Dr Duluth MN 55811",
    "addr:housenumber":"4915",
    "addr:postcode":"55811",
    "addr:street":"Matterhorn Dr",
    "iso:country":"US",
    "sg:address":"4915 Matterhorn Dr",
    "sg:city":"Duluth",
    "sg:classifiers":[
        {
            "category":"Health Services",
            "subcategory":"Doctor",
            "type":"Services"
        }
    ],
    "sg:phone":"+1 218 722 2806",
    "sg:postcode":"55811",
    "sg:province":"MN",
    "wof:name":"Family Dentistry",
    "wof:placetype":"venue"
},
  "geometry": {"coordinates":[-92.169374,46.805568],"type":"Point"}
}