{
  "type": "Feature",
  "properties": {
    "addr:full":"5508 Hunter St Edina MN 55436",
    "addr:housenumber":"5508",
    "addr:postcode":"55436",
    "addr:street":"Hunter St",
    "iso:country":"US",
    "sg:address":"5508 Hunter St",
    "sg:city":"Edina",
    "sg:classifiers":[
        {
            "category":"Professional",
            "subcategory":"Art Services",
            "type":"Services"
        }
    ],
    "sg:phone":"+1 952 929 1882",
    "sg:postcode":"55436",
    "sg:province":"MN",
    "sg:tags":[
        "graphic",
        "designer"
    ],
    "wof:name":"Moorhead & Co",
    "wof:placetype":"venue"
},
  "geometry": {"coordinates":[-93.365432,44.893639],"type":"Point"}
}