{
  "type": "Feature",
  "properties": {
    "addr:full":"2421 Pillsbury Ave S Minneapolis MN 55404",
    "addr:housenumber":"2421",
    "addr:postcode":"55404",
    "addr:street":"Pillsbury Ave S",
    "iso:country":"US",
    "sg:address":"2421 Pillsbury Ave S",
    "sg:city":"Minneapolis",
    "sg:classifiers":[
        {
            "category":"Professional",
            "subcategory":"Business Services",
            "type":"Services"
        }
    ],
    "sg:phone":"+1 612 879 5027",
    "sg:postcode":"55404",
    "sg:province":"MN",
    "wof:name":"Convergent Capital",
    "wof:placetype":"venue"
},
  "geometry": {"coordinates":[-93.28122999999999,44.957692],"type":"Point"}
}