{
  "type": "Feature",
  "properties": {
    "iso:country":"US",
    "sg:address":"6607 18th Ave S",
    "sg:city":"Minneapolis",
    "sg:classifiers":[
        {
            "category":"Health Services",
            "subcategory":"Health Practitioner",
            "type":"Services"
        }
    ],
    "sg:phone":"+1 763 783 7179",
    "sg:postcode":"55423",
    "sg:province":"MN",
    "wof:name":"Ralph A Rovner PHD T A",
    "wof:placetype":"venue"
},
  "geometry": {"coordinates":[-93.249078,44.881809],"type":"Point"}
}