{
  "type": "Feature",
  "properties": {
    "addr:full":"601 2nd Ave Wanamingo MN 55983",
    "addr:housenumber":"601",
    "addr:postcode":"55983",
    "addr:street":"2Nd Ave",
    "iso:country":"US",
    "sg:address":"601 2nd Ave",
    "sg:city":"Wanamingo",
    "sg:phone":"+1 507 824 2417",
    "sg:postcode":"55983",
    "sg:province":"MN",
    "sg:tags":[
        "farm",
        "corn"
    ],
    "wof:name":"Richard Loken",
    "wof:placetype":"venue"
},
  "geometry": {"coordinates":[-92.789294,44.29962],"type":"Point"}
}