{
  "type": "Feature",
  "properties": {
    "iso:country":"US",
    "sg:address":"43187 218th St",
    "sg:city":"Osage",
    "sg:classifiers":[
        {
            "category":"Retail",
            "subcategory":"Auto Repair",
            "type":"Services"
        }
    ],
    "sg:phone":"+1 218 847 2034",
    "sg:postcode":"56570",
    "sg:province":"MN",
    "sg:tags":[
        "body",
        "painting",
        "repairing",
        "automobile"
    ],
    "wof:name":"Mark's Auto Body",
    "wof:placetype":"venue"
},
  "geometry": {"coordinates":[-95.49601,46.886567],"type":"Point"}
}