{
  "type": "Feature",
  "properties": {
    "iso:country":"US",
    "sg:address":"12901 89th Ave N",
    "sg:city":"Maple Grove",
    "sg:classifiers":[
        {
            "category":"Building & Trades",
            "subcategory":"Construction",
            "type":"Services"
        },
        {
            "category":"Home & Garden",
            "subcategory":"Furniture",
            "type":"Retail Goods"
        }
    ],
    "sg:phone":"+1 763 420 5099",
    "sg:postcode":"55369",
    "sg:province":"MN",
    "sg:tags":[
        "cabinet",
        "carpentry",
        "contractor"
    ],
    "wof:name":"Gray's Woodworking",
    "wof:placetype":"venue"
},
  "geometry": {"coordinates":[-93.444389,45.116329],"type":"Point"}
}