{
  "type": "Feature",
  "properties": {
    "addr:full":"79655 505th St Hector MN 55342",
    "addr:housenumber":"79655",
    "addr:postcode":"55342",
    "addr:street":"505Th St Hector",
    "iso:country":"US",
    "sg:address":"79655 505th St",
    "sg:city":"Hector",
    "sg:phone":"+1 320 848 2681",
    "sg:postcode":"55342",
    "sg:province":"MN",
    "sg:tags":[
        "farm",
        "corn",
        "soybean"
    ],
    "wof:name":"Witte Edna & Lloyd",
    "wof:placetype":"venue"
},
  "geometry": {"coordinates":[-94.66030600000001,44.740871],"type":"Point"}
}