{
  "type": "Feature",
  "properties": {
    "addr:full":"3707 Grand Ave St Louis Park MN 55409",
    "addr:housenumber":"3707",
    "addr:postcode":"55409",
    "addr:street":"Grand Ave",
    "iso:country":"US",
    "sg:address":"3707 Grand Ave",
    "sg:city":"St Louis Park",
    "sg:classifiers":[
        {
            "category":"Real Estate",
            "subcategory":"Real Estate Operator",
            "type":"Services"
        }
    ],
    "sg:phone":"+1 952 920 8807",
    "sg:postcode":"55409",
    "sg:province":"MN",
    "sg:tags":[
        "condominium"
    ],
    "wof:name":"Excelsior & Grand Condos",
    "wof:placetype":"venue"
},
  "geometry": {"coordinates":[-93.28428700000001,44.934206],"type":"Point"}
}