{
  "type": "Feature",
  "properties": {
    "addr:full":"945 Wescott Rd Eagan MN 55123",
    "addr:housenumber":"945",
    "addr:postcode":"55123",
    "addr:street":"Wescott Rd",
    "iso:country":"US",
    "sg:address":"945 Wescott Rd",
    "sg:city":"Eagan",
    "sg:classifiers":[
        {
            "category":"Education",
            "subcategory":"School",
            "type":"Public Place"
        }
    ],
    "sg:phone":"+1 651 683 6990",
    "sg:postcode":"55123",
    "sg:province":"MN",
    "sg:website":"www.district196.org",
    "wof:name":"Woodland Elementary School",
    "wof:placetype":"venue"
},
  "geometry": {"coordinates":[-93.13251099999999,44.819017],"type":"Point"}
}