{
  "type": "Feature",
  "properties": {
    "iso:country":"US",
    "sg:address":"5251 W 73rd St",
    "sg:city":"Minneapolis",
    "sg:classifiers":[
        {
            "category":"Food & Beverages",
            "subcategory":"Liquor & Beverages",
            "type":"Retail Goods"
        },
        {
            "category":"Professional",
            "subcategory":"Art Services",
            "type":"Services"
        }
    ],
    "sg:phone":"+1 952 224 9164",
    "sg:postcode":"55439",
    "sg:province":"MN",
    "sg:tags":[
        "development",
        "designing",
        "alcoholic",
        "package"
    ],
    "wof:name":"Retail Package Design Inc",
    "wof:placetype":"venue"
},
  "geometry": {"coordinates":[-93.356979,44.870669],"type":"Point"}
}