{
  "type": "Feature",
  "properties": {
    "iso:country":"US",
    "sg:address":"26175 Fremont Dr",
    "sg:city":"Zimmerman",
    "sg:classifiers":[
        {
            "category":"Restaurant",
            "type":"Food & Drink"
        }
    ],
    "sg:phone":"+1 763 856 4334",
    "sg:postcode":"55398",
    "sg:province":"MN",
    "sg:tags":[
        "eating"
    ],
    "wof:name":"Longhorn Cafe",
    "wof:placetype":"venue"
},
  "geometry": {"coordinates":[-93.58404400000001,45.445022],"type":"Point"}
}