{
  "type": "Feature",
  "properties": {
    "addr:full":"2884 W Owasso Blvd Saint Paul MN 55113",
    "addr:housenumber":"2884",
    "addr:postcode":"55113",
    "addr:street":"W Owasso Blvd",
    "iso:country":"US",
    "sg:address":"2884 W Owasso Blvd",
    "sg:city":"Saint Paul",
    "sg:classifiers":[
        {
            "category":"Building & Trades",
            "subcategory":"Construction",
            "type":"Services"
        }
    ],
    "sg:phone":"+1 651 484 1221",
    "sg:postcode":"55113",
    "sg:province":"MN",
    "sg:tags":[
        "concrete",
        "contractor"
    ],
    "wof:name":"Anderson Gary Cement & Masonry",
    "wof:placetype":"venue"
},
  "geometry": {"coordinates":[-93.132963,45.029472],"type":"Point"}
}