{
  "type": "Feature",
  "properties": {
    "iso:country":"US",
    "sg:address":"1020 Summit Ave",
    "sg:city":"Detroit Lakes",
    "sg:classifiers":[
        {
            "category":"Social Services",
            "subcategory":"Child Care",
            "type":"Services"
        }
    ],
    "sg:phone":"+1 218 847 2849",
    "sg:postcode":"56501",
    "sg:province":"MN",
    "sg:tags":[
        "day",
        "provides"
    ],
    "wof:name":"Artistic Impressions",
    "wof:placetype":"venue"
},
  "geometry": {"coordinates":[-95.84983800000001,46.815576],"type":"Point"}
}