{
  "type": "Feature",
  "properties": {
    "iso:country":"US",
    "sg:address":"5101 Thimsen Ave",
    "sg:city":"Minnetonka",
    "sg:classifiers":[
        {
            "category":"Professional",
            "subcategory":"Lawyer & Legal Services",
            "type":"Services"
        }
    ],
    "sg:phone":"+1 952 473 5405",
    "sg:postcode":"55345",
    "sg:province":"MN",
    "wof:name":"Ahern Paul B Attys",
    "wof:placetype":"venue"
},
  "geometry": {"coordinates":[-93.50509599999999,44.9128],"type":"Point"}
}