{
  "type": "Feature",
  "properties": {
    "addr:full":"2212 Centerview Ln Mound MN 55364",
    "addr:housenumber":"2212",
    "addr:postcode":"55364",
    "addr:street":"Centerview Ln",
    "iso:country":"US",
    "sg:address":"2212 Centerview Ln",
    "sg:city":"Mound",
    "sg:classifiers":[
        {
            "category":"Wholesale",
            "subcategory":"Machinery & Supplies",
            "type":"Manufacturing & Wholesale Goods"
        }
    ],
    "sg:phone":"+1 952 472 6081",
    "sg:postcode":"55364",
    "sg:province":"MN",
    "sg:tags":[
        "equipment",
        "industrial"
    ],
    "wof:name":"S & S Exports",
    "wof:placetype":"venue"
},
  "geometry": {"coordinates":[-93.65834599999999,44.939814],"type":"Point"}
}