{
  "type": "Feature",
  "properties": {
    "addr:full":"5410 125th Ave NE Eyota MN 55934",
    "addr:housenumber":"5410",
    "addr:postcode":"55934",
    "addr:street":"125Th Ave Ne",
    "iso:country":"US",
    "sg:address":"5410 125th Ave NE",
    "sg:city":"Eyota",
    "sg:classifiers":[
        {
            "category":"Building & Trades",
            "subcategory":"Plumbing",
            "type":"Services"
        }
    ],
    "sg:phone":"+1 507 280 9460",
    "sg:postcode":"55934",
    "sg:province":"MN",
    "sg:tags":[
        "sheet",
        "work",
        "metal",
        "contractor"
    ],
    "wof:name":"Progressive Sheet Metal",
    "wof:placetype":"venue"
},
  "geometry": {"coordinates":[-92.229285,44.078064],"type":"Point"}
}