{
  "type": "Feature",
  "properties": {
    "iso:country":"US",
    "sg:address":"701 Xenia Ave S",
    "sg:city":"Minneapolis",
    "sg:classifiers":[
        {
            "category":"Restaurant",
            "type":"Food & Drink"
        }
    ],
    "sg:menulink":"http://www.allmenus.com/mn/golden-valley/236036-pickermans-soup--sandwiches/menu/",
    "sg:phone":"+1 763 582 0433",
    "sg:postcode":"55416",
    "sg:province":"MN",
    "sg:tags":[
        "wrap",
        "soup",
        "american",
        "sandwich",
        "salad"
    ],
    "wof:name":"Pickerman's Soup & Sandwiches",
    "wof:placetype":"venue"
},
  "geometry": {"coordinates":[-93.350855,44.973743],"type":"Point"}
}