{
  "type": "Feature",
  "properties": {
    "iso:country":"US",
    "sg:address":"41765 365th Ave",
    "sg:city":"Aitkin",
    "sg:classifiers":[
        {
            "category":"Retail",
            "subcategory":"Auto Repair",
            "type":"Services"
        }
    ],
    "sg:phone":"+1 218 391 6572",
    "sg:postcode":"56431",
    "sg:province":"MN",
    "sg:tags":[
        "automobile",
        "customizing"
    ],
    "wof:name":"Fine Line Auto Graphics",
    "wof:placetype":"venue"
},
  "geometry": {"coordinates":[-93.622938,46.618681],"type":"Point"}
}