{
  "type": "Feature",
  "properties": {
    "iso:country":"US",
    "sg:address":"227 Chestnut St E",
    "sg:city":"Stillwater",
    "sg:classifiers":[
        {
            "category":"Manufacturing",
            "subcategory":"Printing",
            "type":"Manufacturing & Wholesale Goods"
        }
    ],
    "sg:phone":"+1 651 351 0886",
    "sg:postcode":"55082",
    "sg:province":"MN",
    "sg:tags":[
        "publisher",
        "software"
    ],
    "wof:name":"Citilabs",
    "wof:placetype":"venue"
},
  "geometry": {"coordinates":[-92.806629,45.055556],"type":"Point"}
}