{
  "type": "Feature",
  "properties": {
    "addr:full":"600 E Park Ave Olivia MN 56277",
    "addr:housenumber":"600",
    "addr:postcode":"56277",
    "addr:street":"E Park Ave",
    "iso:country":"US",
    "sg:address":"600 E Park Ave",
    "sg:city":"Olivia",
    "sg:classifiers":[
        {
            "category":"Professional",
            "subcategory":"Research",
            "type":"Services"
        }
    ],
    "sg:phone":"+1 320 523 2435",
    "sg:postcode":"56277",
    "sg:province":"MN",
    "sg:tags":[
        "laboratory"
    ],
    "wof:name":"Smithkline Beecham Clinical",
    "wof:placetype":"venue"
},
  "geometry": {"coordinates":[-94.984027,44.773354],"type":"Point"}
}