{
  "type": "Feature",
  "properties": {
    "iso:country":"US",
    "sg:address":"15590 620th Ave",
    "sg:city":"Litchfield",
    "sg:classifiers":[
        {
            "category":"Education",
            "subcategory":"Special Training",
            "type":"Public Place"
        }
    ],
    "sg:phone":"+1 320 587 9809",
    "sg:postcode":"55355",
    "sg:province":"MN",
    "wof:name":"Die Kinder Music Studio",
    "wof:placetype":"venue"
},
  "geometry": {"coordinates":[-94.522379,44.976073],"type":"Point"}
}