{
  "type": "Feature",
  "properties": {
    "addr:full":"15445 Cedar Ave Apple Valley MN 55124",
    "addr:housenumber":"15445",
    "addr:postcode":"55124",
    "addr:street":"Cedar Ave",
    "iso:country":"US",
    "sg:address":"15445 Cedar Ave",
    "sg:city":"Apple Valley",
    "sg:classifiers":[
        {
            "category":"Autos & Motor Vehicles",
            "subcategory":"Auto Supplies",
            "type":"Retail Goods"
        },
        {
            "category":"Wholesale",
            "subcategory":"Electrical",
            "type":"Manufacturing & Wholesale Goods"
        }
    ],
    "sg:phone":"+1 952 891 2300",
    "sg:postcode":"55124",
    "sg:province":"MN",
    "sg:tags":[
        "battery",
        "equipment",
        "merchandise"
    ],
    "wof:name":"Batteries Plus",
    "wof:placetype":"venue"
},
  "geometry": {"coordinates":[-93.217822,44.725574],"type":"Point"}
}