{
  "type": "Feature",
  "properties": {
    "iso:country":"US",
    "sg:address":"7596 State Hwy 64 SW",
    "sg:city":"Motley",
    "sg:classifiers":[
        {
            "category":"Food & Beverages",
            "subcategory":"Groceries & Convenience Stores",
            "type":"Retail Goods"
        }
    ],
    "sg:phone":"+1 218 397 2412",
    "sg:postcode":"56466",
    "sg:province":"MN",
    "wof:name":"Leader Amoco",
    "wof:placetype":"venue"
},
  "geometry": {"coordinates":[-94.654781,46.538932],"type":"Point"}
}