{
  "type": "Feature",
  "properties": {
    "iso:country":"US",
    "sg:address":"1113 High Ave NE",
    "sg:city":"Willmar",
    "sg:classifiers":[
        {
            "category":"Retail",
            "subcategory":"Laundry & Dry Cleaning",
            "type":"Services"
        }
    ],
    "sg:phone":"+1 320 235 2565",
    "sg:postcode":"56201",
    "sg:province":"MN",
    "sg:tags":[
        "uniform",
        "supply"
    ],
    "wof:name":"Cintas Corp",
    "wof:placetype":"venue"
},
  "geometry": {"coordinates":[-95.028273,45.127309],"type":"Point"}
}