{
  "type": "Feature",
  "properties": {
    "iso:country":"US",
    "sg:address":"2525 Burnham Rd",
    "sg:city":"Minneapolis",
    "sg:classifiers":[
        {
            "category":"Real Estate",
            "subcategory":"Real Estate Services",
            "type":"Services"
        }
    ],
    "sg:phone":"+1 612 670 5203",
    "sg:postcode":"55416",
    "sg:province":"MN",
    "sg:tags":[
        "commercial"
    ],
    "wof:name":"Compendium Business Strategies",
    "wof:placetype":"venue"
},
  "geometry": {"coordinates":[-93.316396,44.956861],"type":"Point"}
}