{
  "type": "Feature",
  "properties": {
    "iso:country":"US",
    "sg:address":"4851 2nd St NE",
    "sg:city":"Minneapolis",
    "sg:classifiers":[
        {
            "category":"Communications",
            "subcategory":"Film & Video Production",
            "type":"Services"
        }
    ],
    "sg:phone":"+1 612 201 2538",
    "sg:postcode":"55421",
    "sg:province":"MN",
    "sg:tags":[
        "tape",
        "editing",
        "services-commercial",
        "audio-visual"
    ],
    "sg:website":"http://www.glimpsesoflife.net",
    "wof:name":"Glimpses of Life Productions",
    "wof:placetype":"venue"
},
  "geometry": {"coordinates":[-93.266716,45.05635],"type":"Point"}
}