{
  "type": "Feature",
  "properties": {
    "iso:country":"US",
    "sg:address":"9848 Upper 173rd Ct W",
    "sg:city":"Lakeville",
    "sg:classifiers":[
        {
            "category":"Wholesale",
            "subcategory":"Computers",
            "type":"Manufacturing & Wholesale Goods"
        }
    ],
    "sg:phone":"+1 952 898 5093",
    "sg:postcode":"55044",
    "sg:province":"MN",
    "wof:name":"Paul Preston Inc",
    "wof:placetype":"venue"
},
  "geometry": {"coordinates":[-93.265337,44.699046],"type":"Point"}
}