{
  "type": "Feature",
  "properties": {
    "iso:country":"US",
    "sg:address":"6945 Nicollet Ave",
    "sg:city":"Minneapolis",
    "sg:classifiers":[
        {
            "category":"Shopping",
            "subcategory":"Department Store",
            "type":"Retail Goods"
        }
    ],
    "sg:phone":"+1 612 861 9000",
    "sg:postcode":"55423",
    "sg:province":"MN",
    "sg:tags":[
        "insurance"
    ],
    "sg:website":"www.cornerstonemn.com",
    "wof:name":"Cornerstone Real Estate",
    "wof:placetype":"venue"
},
  "geometry": {"coordinates":[-93.278091,44.877002],"type":"Point"}
}