{
  "type": "Feature",
  "properties": {
    "addr:full":"560 Beverly St Wanamingo MN 55983",
    "addr:housenumber":"560",
    "addr:postcode":"55983",
    "addr:street":"Beverly St",
    "iso:country":"US",
    "sg:address":"560 Beverly St",
    "sg:city":"Wanamingo",
    "sg:classifiers":[
        {
            "category":"Restaurant",
            "type":"Food & Drink"
        }
    ],
    "sg:phone":"+1 507 824 3216",
    "sg:postcode":"55983",
    "sg:province":"MN",
    "sg:tags":[
        "eating"
    ],
    "wof:name":"Area 57 Coffee Cafe Inc",
    "wof:placetype":"venue"
},
  "geometry": {"coordinates":[-92.782605,44.299532],"type":"Point"}
}