{
  "type": "Feature",
  "properties": {
    "addr:full":"221 E Clark St Albert Lea MN 56007",
    "addr:housenumber":"221",
    "addr:postcode":"56007",
    "addr:street":"E Clark St",
    "iso:country":"US",
    "sg:address":"221 E Clark St",
    "sg:city":"Albert Lea",
    "sg:classifiers":[
        {
            "category":"Recreation",
            "type":"Entertainment"
        }
    ],
    "sg:phone":"+1 507 377 4370",
    "sg:postcode":"56007",
    "sg:province":"MN",
    "sg:tags":[
        "parks"
    ],
    "wof:name":"Albert Lea Park & Recreation",
    "wof:placetype":"venue"
},
  "geometry": {"coordinates":[-93.367176,43.649825],"type":"Point"}
}