{
  "type": "Feature",
  "properties": {
    "addr:full":"2020 Girard Ave S Minneapolis MN 55405",
    "addr:housenumber":"2020",
    "addr:postcode":"55405",
    "addr:street":"Girard Ave S",
    "iso:country":"US",
    "sg:address":"2020 Girard Ave S",
    "sg:city":"Minneapolis",
    "sg:classifiers":[
        {
            "category":"Manufacturing",
            "subcategory":"Printing",
            "type":"Manufacturing & Wholesale Goods"
        }
    ],
    "sg:phone":"+1 612 377 0155",
    "sg:postcode":"55405",
    "sg:province":"MN",
    "sg:tags":[
        "periodical"
    ],
    "wof:name":"SL Market Letter Inc",
    "wof:placetype":"venue"
},
  "geometry": {"coordinates":[-93.296994,44.961104],"type":"Point"}
}