{
  "type": "Feature",
  "properties": {
    "iso:country":"US",
    "sg:address":"1601 2nd Ave",
    "sg:city":"Internatl Falls",
    "sg:classifiers":[
        {
            "category":"Autos & Motor Vehicles",
            "subcategory":"Fuel & Gas Station",
            "type":"Retail Goods"
        }
    ],
    "sg:phone":"+1 218 283 9300",
    "sg:postcode":"56649",
    "sg:province":"MN",
    "sg:tags":[
        "station",
        "gasoline",
        "oil"
    ],
    "wof:name":"Koerter's Amoco & Car Wash",
    "wof:placetype":"venue"
},
  "geometry": {"coordinates":[-93.40255999999999,48.58829],"type":"Point"}
}