{
  "type": "Feature",
  "properties": {
    "addr:full":"663 University Ave W St Paul MN 55104",
    "addr:housenumber":"663",
    "addr:postcode":"55104",
    "addr:street":"University Ave W",
    "iso:country":"US",
    "sg:address":"663 University Ave W",
    "sg:city":"St Paul",
    "sg:classifiers":[
        {
            "category":"Banks & Credit Unions",
            "subcategory":"Financial Services",
            "type":"Services"
        }
    ],
    "sg:phone":"+1 651 290 8100",
    "sg:postcode":"55104",
    "sg:province":"MN",
    "sg:tags":[
        "company",
        "holding"
    ],
    "sg:website":"www.western-bank.com",
    "wof:name":"Western Bancshares Inc",
    "wof:placetype":"venue"
},
  "geometry": {"coordinates":[-93.12815500000001,44.955794],"type":"Point"}
}