{
  "type": "Feature",
  "properties": {
    "iso:country":"US",
    "sg:address":"5102 Hwy 71 NE",
    "sg:city":"Willmar",
    "sg:classifiers":[
        {
            "category":"Autos & Motor Vehicles",
            "subcategory":"Recreational Vehicle Sales",
            "type":"Retail Goods"
        }
    ],
    "sg:phone":"+1 320 231 0431",
    "sg:postcode":"56201",
    "sg:province":"MN",
    "wof:name":"R V's Plus",
    "wof:placetype":"venue"
},
  "geometry": {"coordinates":[-95.014534,45.172743],"type":"Point"}
}