{
  "type": "Feature",
  "properties": {
    "addr:full":"595 Randolph Ave Saint Paul MN 55102",
    "addr:housenumber":"595",
    "addr:postcode":"55102",
    "addr:street":"Randolph Ave",
    "iso:country":"US",
    "sg:address":"595 Randolph Ave",
    "sg:city":"Saint Paul",
    "sg:classifiers":[
        {
            "category":"Manufacturing",
            "subcategory":"Glass & Minerals",
            "type":"Manufacturing & Wholesale Goods"
        }
    ],
    "sg:phone":"+1 651 290 0898",
    "sg:postcode":"55102",
    "sg:province":"MN",
    "sg:tags":[
        "mfg",
        "etched"
    ],
    "wof:name":"Ice Nine Glass Design",
    "wof:placetype":"venue"
},
  "geometry": {"coordinates":[-93.125046,44.926912],"type":"Point"}
}