{
  "type": "Feature",
  "properties": {
    "addr:full":"5612 Corvallis Ave N Minneapolis MN 55429",
    "addr:housenumber":"5612",
    "addr:postcode":"55429",
    "addr:street":"Corvallis Ave N",
    "iso:country":"US",
    "sg:address":"5612 Corvallis Ave N",
    "sg:city":"Minneapolis",
    "sg:classifiers":[
        {
            "category":"Building & Trades",
            "subcategory":"Landscaping Services",
            "type":"Services"
        }
    ],
    "sg:phone":"+1 763 535 5839",
    "sg:postcode":"55429",
    "sg:province":"MN",
    "sg:tags":[
        "arborist",
        "tree"
    ],
    "wof:name":"Tim's Tree Svc Inc",
    "wof:placetype":"venue"
},
  "geometry": {"coordinates":[-93.351275,45.04564],"type":"Point"}
}