{
  "type": "Feature",
  "properties": {
    "iso:country":"US",
    "sg:address":"6900 Wedgwood Rd",
    "sg:city":"Maple Grove",
    "sg:classifiers":[
        {
            "category":"Communications",
            "type":"Services"
        }
    ],
    "sg:phone":"+1 763 416 0053",
    "sg:postcode":"55311",
    "sg:province":"MN",
    "wof:name":"Terago Communications",
    "wof:placetype":"venue"
},
  "geometry": {"coordinates":[-93.449754,45.080093],"type":"Point"}
}