{
  "type": "Feature",
  "properties": {
    "iso:country":"US",
    "sg:address":"220 Hardman Ave N",
    "sg:city":"South Saint Paul",
    "sg:classifiers":[
        {
            "category":"Shopping",
            "subcategory":"Discount & Variety Stores",
            "type":"Retail Goods"
        }
    ],
    "sg:phone":"+1 612 207 9542",
    "sg:postcode":"55075",
    "sg:province":"MN",
    "sg:tags":[
        "merchandise",
        "general"
    ],
    "wof:name":"Electronics Online LLC",
    "wof:placetype":"venue"
},
  "geometry": {"coordinates":[-93.031237,44.895304],"type":"Point"}
}