{
  "type": "Feature",
  "properties": {
    "iso:country":"US",
    "sg:address":"3366 Oakdale Ave N",
    "sg:city":"Robbinsdale",
    "sg:classifiers":[
        {
            "category":"Shopping",
            "subcategory":"Pharmacy",
            "type":"Retail Goods"
        }
    ],
    "sg:phone":"+1 763 520 5284",
    "sg:postcode":"55422",
    "sg:province":"MN",
    "wof:name":"North Drug",
    "wof:placetype":"venue"
},
  "geometry": {"coordinates":[-93.320993,45.013973],"type":"Point"}
}