{
  "type": "Feature",
  "properties": {
    "addr:full":"119 N Driftwood St Royalton MN 56373",
    "addr:housenumber":"119",
    "addr:postcode":"56373",
    "addr:street":"N Driftwood St",
    "iso:country":"US",
    "sg:address":"119 N Driftwood St",
    "sg:city":"Royalton",
    "sg:classifiers":[
        {
            "category":"Education",
            "subcategory":"School",
            "type":"Public Place"
        }
    ],
    "sg:phone":"+1 320 584 5551",
    "sg:postcode":"56373",
    "sg:province":"MN",
    "sg:tags":[
        "elementary"
    ],
    "wof:name":"Royalton Elementary School",
    "wof:placetype":"venue"
},
  "geometry": {"coordinates":[-94.29022999999999,45.828885],"type":"Point"}
}