{
  "type": "Feature",
  "properties": {
    "addr:full":"6556 Central Ave NE Minneapolis MN 55432",
    "addr:housenumber":"6556",
    "addr:postcode":"55432",
    "addr:street":"Central Ave Ne",
    "iso:country":"US",
    "sg:address":"6556 Central Ave NE",
    "sg:city":"Minneapolis",
    "sg:classifiers":[
        {
            "category":"Professional",
            "type":"Services"
        }
    ],
    "sg:phone":"+1 763 574 0052",
    "sg:postcode":"55432",
    "sg:province":"MN",
    "wof:name":"Old Cntral Cndo Hmowners Assoc",
    "wof:placetype":"venue"
},
  "geometry": {"coordinates":[-93.23787799999999,45.086116],"type":"Point"}
}