{
  "type": "Feature",
  "properties": {
    "iso:country":"US",
    "sg:address":"2730 Piedmont Ave",
    "sg:city":"Duluth",
    "sg:classifiers":[
        {
            "category":"Health Services",
            "subcategory":"Doctor",
            "type":"Services"
        }
    ],
    "sg:phone":"+1 218 722 1846",
    "sg:postcode":"55811",
    "sg:province":"MN",
    "sg:tags":[
        "dentist"
    ],
    "wof:name":"Summit Dental",
    "wof:placetype":"venue"
},
  "geometry": {"coordinates":[-92.159621,46.782184],"type":"Point"}
}