{
  "type": "Feature",
  "properties": {
    "iso:country":"US",
    "sg:address":"154 E Broadway St",
    "sg:city":"Monticello",
    "sg:classifiers":[
        {
            "category":"Professional",
            "type":"Services"
        },
        {
            "category":"Coffee & Tea",
            "type":"Food & Drink"
        },
        {
            "category":"Restaurant",
            "type":"Food & Drink"
        }
    ],
    "sg:phone":"+1 763 295 5100",
    "sg:postcode":"55362",
    "sg:province":"MN",
    "sg:tags":[
        "style",
        "espresso",
        "family",
        "caterer"
    ],
    "wof:name":"Monticello Corner Cafe",
    "wof:placetype":"venue"
},
  "geometry": {"coordinates":[-93.793429,45.305385],"type":"Point"}
}