{
  "type": "Feature",
  "properties": {
    "addr:full":"1300 Willow St Faribault MN 55021",
    "addr:housenumber":"1300",
    "addr:postcode":"55021",
    "addr:street":"Willow St",
    "iso:country":"US",
    "sg:address":"1300 Willow St",
    "sg:city":"Faribault",
    "sg:classifiers":[
        {
            "category":"Freight",
            "type":"Transportation"
        }
    ],
    "sg:phone":"+1 507 334 9249",
    "sg:postcode":"55021",
    "sg:province":"MN",
    "sg:tags":[
        "trucking"
    ],
    "wof:name":"Extreme Trucking",
    "wof:placetype":"venue"
},
  "geometry": {"coordinates":[-93.27278,44.275191],"type":"Point"}
}