{
  "type": "Feature",
  "properties": {
    "iso:country":"US",
    "sg:address":"210 3rd St S",
    "sg:city":"New Ulm",
    "sg:classifiers":[
        {
            "category":"Building & Trades",
            "subcategory":"Construction",
            "type":"Services"
        }
    ],
    "sg:phone":"+1 507 354 3174",
    "sg:postcode":"56073",
    "sg:province":"MN",
    "sg:tags":[
        "general",
        "contractor"
    ],
    "wof:name":"Heymann Construction Co",
    "wof:placetype":"venue"
},
  "geometry": {"coordinates":[-94.45230599999999,44.312241],"type":"Point"}
}