{
  "type": "Feature",
  "properties": {
    "iso:country":"US",
    "sg:address":"20320 115th St NE",
    "sg:city":"New London",
    "sg:classifiers":[
        {
            "category":"Farming",
            "subcategory":"Farm & Veterinary Services",
            "type":"Manufacturing & Wholesale Goods"
        }
    ],
    "sg:phone":"+1 320 354 2749",
    "sg:postcode":"56273",
    "sg:province":"MN",
    "wof:name":"Five-Star Pumping",
    "wof:placetype":"venue"
},
  "geometry": {"coordinates":[-94.886244,45.31692],"type":"Point"}
}