{
  "type": "Feature",
  "properties": {
    "addr:full":"236 Main St E Sleepy Eye MN 56085",
    "addr:housenumber":"236",
    "addr:postcode":"56085",
    "addr:street":"Main St E",
    "iso:country":"US",
    "sg:address":"236 Main St E",
    "sg:city":"Sleepy Eye",
    "sg:classifiers":[
        {
            "category":"Health Services",
            "subcategory":"Health Practitioner",
            "type":"Services"
        }
    ],
    "sg:phone":"+1 507 794 7480",
    "sg:postcode":"56085",
    "sg:province":"MN",
    "wof:name":"Miracle Massage & Foot Care",
    "wof:placetype":"venue"
},
  "geometry": {"coordinates":[-94.720912,44.297349],"type":"Point"}
}