{
  "type": "Feature",
  "properties": {
    "addr:full":"2004 Hennepin Ave Minneapolis MN 55405",
    "addr:housenumber":"2004",
    "addr:postcode":"55405",
    "addr:street":"Hennepin Ave",
    "iso:country":"US",
    "sg:address":"2004 Hennepin Ave",
    "sg:city":"Minneapolis",
    "sg:classifiers":[
        {
            "category":"Personal",
            "subcategory":"Beauty Salon",
            "type":"Services"
        }
    ],
    "sg:phone":"+1 612 871 1962",
    "sg:postcode":"55405",
    "sg:province":"MN",
    "sg:tags":[
        "hair"
    ],
    "wof:name":"Terrace Hair Stylists",
    "wof:placetype":"venue"
},
  "geometry": {"coordinates":[-93.291527,44.962579],"type":"Point"}
}