{
  "type": "Feature",
  "properties": {
    "addr:full":"30 5th Ave S St Cloud MN 56301",
    "addr:housenumber":"30",
    "addr:postcode":"56301",
    "addr:street":"5Th Ave S",
    "iso:country":"US",
    "sg:address":"30 5th Ave S",
    "sg:city":"St Cloud",
    "sg:classifiers":[
        {
            "category":"Restaurant",
            "type":"Food & Drink"
        }
    ],
    "sg:phone":"+1 320 251 5524",
    "sg:postcode":"56301",
    "sg:province":"MN",
    "sg:tags":[
        "eating",
        "caterer"
    ],
    "wof:name":"Hemsing's Deli & Sandwich Shop",
    "wof:placetype":"venue"
},
  "geometry": {"coordinates":[-94.157464,45.560452],"type":"Point"}
}