{
  "type": "Feature",
  "properties": {
    "iso:country":"US",
    "sg:address":"500 Co Rd 9",
    "sg:city":"Watson",
    "sg:classifiers":[
        {
            "category":"Real Estate",
            "subcategory":"Real Estate Agent",
            "type":"Services"
        }
    ],
    "sg:phone":"+1 320 269 6855",
    "sg:postcode":"56265",
    "sg:province":"MN",
    "wof:name":"First Minnesota Realty Inc",
    "wof:placetype":"venue"
},
  "geometry": {"coordinates":[-95.795928,45.028183],"type":"Point"}
}