{
  "type": "Feature",
  "properties": {
    "addr:full":"6750 E Frontage Rd Medford MN 55049",
    "addr:housenumber":"6750",
    "addr:postcode":"55049",
    "addr:street":"E Frontage Rd",
    "iso:country":"US",
    "sg:address":"6750 E Frontage Rd",
    "sg:city":"Medford",
    "sg:classifiers":[
        {
            "category":"Shopping",
            "subcategory":"Catalog Store",
            "type":"Retail Goods"
        }
    ],
    "sg:phone":"+1 507 455 0372",
    "sg:postcode":"55049",
    "sg:province":"MN",
    "sg:tags":[
        "food",
        "mail",
        "house"
    ],
    "wof:name":"Harry and David",
    "wof:placetype":"venue"
},
  "geometry": {"coordinates":[-93.256917,44.153645],"type":"Point"}
}