{
  "type": "Feature",
  "properties": {
    "addr:full":"1600 65th St NW Rochester MN 55901",
    "addr:housenumber":"1600",
    "addr:postcode":"55901",
    "addr:street":"65Th St Nw",
    "iso:country":"US",
    "sg:address":"1600 65th St NW",
    "sg:city":"Rochester",
    "sg:classifiers":[
        {
            "category":"Utilities",
            "subcategory":"Telephone",
            "type":"Services"
        }
    ],
    "sg:phone":"+1 507 289 4501",
    "sg:postcode":"55901",
    "sg:province":"MN",
    "sg:tags":[
        "communications"
    ],
    "wof:name":"AT&T",
    "wof:placetype":"venue"
},
  "geometry": {"coordinates":[-92.48589699999999,44.091577],"type":"Point"}
}