{
  "type": "Feature",
  "properties": {
    "addr:full":"6000 W 35th St Minneapolis MN 55416",
    "addr:housenumber":"6000",
    "addr:postcode":"55416",
    "addr:street":"W 35Th St",
    "iso:country":"US",
    "sg:address":"6000 W 35th St",
    "sg:city":"Minneapolis",
    "sg:classifiers":[
        {
            "category":"Building & Trades",
            "subcategory":"Landscaping Services",
            "type":"Services"
        }
    ],
    "sg:phone":"+1 651 639 1100",
    "sg:postcode":"55416",
    "sg:province":"MN",
    "sg:tags":[
        "tree"
    ],
    "wof:name":"Urban Tree Care",
    "wof:placetype":"venue"
},
  "geometry": {"coordinates":[-93.356003,44.93996],"type":"Point"}
}