{
  "type": "Feature",
  "properties": {
    "addr:full":"11978 Riverwood Dr Burnsville MN 55337",
    "addr:housenumber":"11978",
    "addr:postcode":"55337",
    "addr:street":"Riverwood Dr",
    "iso:country":"US",
    "sg:address":"11978 Riverwood Dr",
    "sg:city":"Burnsville",
    "sg:classifiers":[
        {
            "category":"Building & Trades",
            "subcategory":"Landscaping Services",
            "type":"Services"
        }
    ],
    "sg:phone":"+1 952 882 0064",
    "sg:postcode":"55337",
    "sg:province":"MN",
    "sg:tags":[
        "landscape",
        "contractor"
    ],
    "wof:name":"Precision Landscaping",
    "wof:placetype":"venue"
},
  "geometry": {"coordinates":[-93.261199,44.788333],"type":"Point"}
}