{
  "type": "Feature",
  "properties": {
    "addr:full":"207 2nd St S Buffalo MN 55313",
    "addr:housenumber":"207",
    "addr:postcode":"55313",
    "addr:street":"2Nd St S",
    "iso:country":"US",
    "sg:address":"207 2nd St S",
    "sg:city":"Buffalo",
    "sg:classifiers":[
        {
            "category":"Building & Trades",
            "subcategory":"Construction",
            "type":"Services"
        }
    ],
    "sg:phone":"+1 763 682 6958",
    "sg:postcode":"55313",
    "sg:province":"MN",
    "sg:tags":[
        "residential"
    ],
    "wof:name":"Timberwolf Contracting",
    "wof:placetype":"venue"
},
  "geometry": {"coordinates":[-93.87330900000001,45.169981],"type":"Point"}
}