{
  "type": "Feature",
  "properties": {
    "addr:full":"6363 France Ave S Minneapolis MN 55435",
    "addr:housenumber":"6363",
    "addr:postcode":"55435",
    "addr:street":"France Ave S",
    "iso:country":"US",
    "sg:address":"6363 France Ave S",
    "sg:city":"Minneapolis",
    "sg:classifiers":[
        {
            "category":"Health Services",
            "subcategory":"Doctor",
            "type":"Services"
        }
    ],
    "sg:phone":"+1 612 929 1131",
    "sg:postcode":"55435",
    "sg:province":"MN",
    "sg:tags":[
        "medical"
    ],
    "wof:name":"Edwin H Ryan Jr",
    "wof:placetype":"venue"
},
  "geometry": {"coordinates":[-93.328896,44.888303],"type":"Point"}
}