{
  "type": "Feature",
  "properties": {
    "iso:country":"US",
    "sg:address":"470 Lake St",
    "sg:city":"Excelsior",
    "sg:classifiers":[
        {
            "category":"Banks & Credit Unions",
            "subcategory":"Financial Services",
            "type":"Services"
        }
    ],
    "sg:phone":"+1 320 974 8122",
    "sg:postcode":"55331",
    "sg:province":"MN",
    "sg:tags":[
        "investment",
        "real estate"
    ],
    "wof:name":"Jel and Associates",
    "wof:placetype":"venue"
},
  "geometry": {"coordinates":[-93.563266,44.90282],"type":"Point"}
}