{
  "type": "Feature",
  "properties": {
    "addr:full":"3116 Fairview Ave N Saint Paul MN 55113",
    "addr:housenumber":"3116",
    "addr:postcode":"55113",
    "addr:street":"Fairview Ave N",
    "iso:country":"US",
    "sg:address":"3116 Fairview Ave N",
    "sg:city":"Saint Paul",
    "sg:classifiers":[
        {
            "category":"Social Services",
            "type":"Services"
        }
    ],
    "sg:phone":"+1 651 484 5234",
    "sg:postcode":"55113",
    "sg:province":"MN",
    "wof:name":"Young Life Nthrn Twin Cities",
    "wof:placetype":"venue"
},
  "geometry": {"coordinates":[-93.177393,45.031447],"type":"Point"}
}