{
  "type": "Feature",
  "properties": {
    "iso:country":"US",
    "sg:address":"300 Elm St",
    "sg:city":"Farmington",
    "sg:classifiers":[
        {
            "category":"Restaurant",
            "type":"Food & Drink"
        }
    ],
    "sg:menulink":"http://www.allmenus.com/mn/farmington/151275-subway/menu/",
    "sg:phone":"+1 651 463 2487",
    "sg:postcode":"55024",
    "sg:province":"MN",
    "sg:tags":[
        "american",
        "sandwich"
    ],
    "wof:name":"Subway",
    "wof:placetype":"venue"
},
  "geometry": {"coordinates":[-93.145004,44.640165],"type":"Point"}
}