{
  "type": "Feature",
  "properties": {
    "addr:full":"1506 W Lake St Minneapolis MN 55408",
    "addr:housenumber":"1506",
    "addr:postcode":"55408",
    "addr:street":"W Lake St",
    "iso:country":"US",
    "sg:address":"1506 W Lake St",
    "sg:city":"Minneapolis",
    "sg:classifiers":[
        {
            "category":"Tea Room",
            "subcategory":"None",
            "type":"Food & Drink"
        },
        {
            "category":"Coffee & Tea",
            "type":"Food & Drink"
        },
        {
            "category":"Restaurant",
            "type":"Food & Drink"
        }
    ],
    "sg:phone":"+1 612 827 5094",
    "sg:postcode":"55408",
    "sg:province":"MN",
    "sg:tags":[
        "shop",
        "espresso"
    ],
    "wof:name":"Dunn Bros Coffee",
    "wof:placetype":"venue"
},
  "geometry": {"coordinates":[-93.30089099999999,44.948371],"type":"Point"}
}