{
  "type": "Feature",
  "properties": {
    "iso:country":"US",
    "sg:address":"14326 Park Ave",
    "sg:city":"Burnsville",
    "sg:classifiers":[
        {
            "category":"Real Estate",
            "subcategory":"Real Estate Agent",
            "type":"Services"
        }
    ],
    "sg:phone":"+1 952 997 7285",
    "sg:postcode":"55337",
    "sg:province":"MN",
    "wof:name":"Cte Appraisals Inc",
    "wof:placetype":"venue"
},
  "geometry": {"coordinates":[-93.261253,44.743235],"type":"Point"}
}