{
  "type": "Feature",
  "properties": {
    "iso:country":"US",
    "sg:address":"15871 850th Ave",
    "sg:city":"Glenville",
    "sg:classifiers":[
        {
            "category":"Manufacturing",
            "subcategory":"Food",
            "type":"Manufacturing & Wholesale Goods"
        },
        {
            "category":"Farming",
            "subcategory":"Farm",
            "type":"Manufacturing & Wholesale Goods"
        }
    ],
    "sg:phone":"+1 507 448 3349",
    "sg:postcode":"56036",
    "sg:province":"MN",
    "sg:tags":[
        "corn",
        "product"
    ],
    "wof:name":"Ronald Belshan",
    "wof:placetype":"venue"
},
  "geometry": {"coordinates":[-93.169068,43.577956],"type":"Point"}
}