{
  "type": "Feature",
  "properties": {
    "addr:full":"69 Nelson Dr Silver Bay MN 55614",
    "addr:housenumber":"69",
    "addr:postcode":"55614",
    "addr:street":"Nelson Dr",
    "iso:country":"US",
    "sg:address":"69 Nelson Dr",
    "sg:city":"Silver Bay",
    "sg:classifiers":[
        {
            "category":"Insurance",
            "subcategory":"Insurance Agent",
            "type":"Services"
        }
    ],
    "sg:phone":"+1 218 226 3442",
    "sg:postcode":"55614",
    "sg:province":"MN",
    "wof:name":"Zinter Financial Services",
    "wof:placetype":"venue"
},
  "geometry": {"coordinates":[-91.288511,47.288317],"type":"Point"}
}