{
  "type": "Feature",
  "properties": {
    "iso:country":"US",
    "sg:address":"2304 Pillsbury Ave S",
    "sg:city":"Minneapolis",
    "sg:classifiers":[
        {
            "category":"Real Estate",
            "subcategory":"Real Estate Operator",
            "type":"Services"
        }
    ],
    "sg:phone":"+1 612 871 9999",
    "sg:postcode":"55404",
    "sg:province":"MN",
    "sg:tags":[
        "boarding",
        "house"
    ],
    "wof:name":"Deputat Board & Lodge",
    "wof:placetype":"venue"
},
  "geometry": {"coordinates":[-93.281375,44.960057],"type":"Point"}
}