{
  "type": "Feature",
  "properties": {
    "addr:full":"5055 Nicollet Ave Minneapolis MN 55419",
    "addr:housenumber":"5055",
    "addr:postcode":"55419",
    "addr:street":"Nicollet Ave",
    "iso:country":"US",
    "sg:address":"5055 Nicollet Ave",
    "sg:city":"Minneapolis",
    "sg:classifiers":[
        {
            "category":"Communications",
            "subcategory":"Film & Video Production",
            "type":"Services"
        }
    ],
    "sg:phone":"+1 612 825 5024",
    "sg:postcode":"55419",
    "sg:province":"MN",
    "sg:tags":[
        "motion",
        "picture"
    ],
    "wof:name":"9 DOT Inc",
    "wof:placetype":"venue"
},
  "geometry": {"coordinates":[-93.27795500000001,44.911804],"type":"Point"}
}