{
  "type": "Feature",
  "properties": {
    "iso:country":"US",
    "sg:address":"18509 Lakeview Point Dr NE",
    "sg:city":"Wyoming",
    "sg:classifiers":[
        {
            "category":"Professional",
            "subcategory":"Advertising",
            "type":"Services"
        }
    ],
    "sg:phone":"+1 763 413 0863",
    "sg:postcode":"55092",
    "sg:province":"MN",
    "sg:tags":[
        "representative"
    ],
    "wof:name":"Virg F Paulson Inc",
    "wof:placetype":"venue"
},
  "geometry": {"coordinates":[-93.17832300000001,45.30383],"type":"Point"}
}