{
  "type": "Feature",
  "properties": {
    "addr:full":"125 Main St Bird Island MN 55370",
    "addr:housenumber":"125",
    "addr:postcode":"55370",
    "addr:street":"Main St",
    "iso:country":"US",
    "sg:address":"125 Main St",
    "sg:city":"Bird Island",
    "sg:classifiers":[
        {
            "category":"Food & Beverages",
            "subcategory":"Groceries & Convenience Stores",
            "type":"Retail Goods"
        }
    ],
    "sg:phone":"+1 320 365 3200",
    "sg:postcode":"55370",
    "sg:province":"MN",
    "sg:tags":[
        "grocer"
    ],
    "wof:name":"Maynard's Of Bird Island",
    "wof:placetype":"venue"
},
  "geometry": {"coordinates":[-94.039343,44.772532],"type":"Point"}
}