{
  "type": "Feature",
  "properties": {
    "iso:country":"US",
    "sg:address":"501 Quixote Ave N",
    "sg:city":"Lakeland",
    "sg:classifiers":[
        {
            "category":"Professional",
            "subcategory":"Business Services",
            "type":"Services"
        }
    ],
    "sg:phone":"+1 651 436 8133",
    "sg:postcode":"55043",
    "sg:province":"MN",
    "sg:tags":[
        "interior",
        "decorator"
    ],
    "sg:website":"www.prisminteriordesigns.com",
    "wof:name":"Prism Interiors",
    "wof:placetype":"venue"
},
  "geometry": {"coordinates":[-92.763666,44.955818],"type":"Point"}
}