{
  "type": "Feature",
  "properties": {
    "iso:country":"US",
    "sg:address":"566 W 78th St",
    "sg:city":"Chanhassen",
    "sg:classifiers":[
        {
            "category":"Restaurant",
            "type":"Food & Drink"
        }
    ],
    "sg:phone":"+1 952 949 1125",
    "sg:postcode":"55317",
    "sg:province":"MN",
    "sg:tags":[
        "thai"
    ],
    "wof:name":"Na's Thai Cafe",
    "wof:placetype":"venue"
},
  "geometry": {"coordinates":[-93.534927,44.862225],"type":"Point"}
}