{
  "type": "Feature",
  "properties": {
    "iso:country":"US",
    "sg:address":"117 N Main St",
    "sg:city":"Kiester",
    "sg:classifiers":[
        {
            "category":"Restaurant",
            "type":"Food & Drink"
        }
    ],
    "sg:phone":"+1 507 294 3140",
    "sg:postcode":"56051",
    "sg:province":"MN",
    "wof:name":"Maple Cafe",
    "wof:placetype":"venue"
},
  "geometry": {"coordinates":[-93.712225,43.537797],"type":"Point"}
}