{
  "type": "Feature",
  "properties": {
    "iso:country":"US",
    "sg:address":"1566 Wexford Ct",
    "sg:city":"Saint Paul",
    "sg:classifiers":[
        {
            "category":"Building & Trades",
            "subcategory":"Construction",
            "type":"Services"
        }
    ],
    "sg:phone":"+1 651 456 0674",
    "sg:postcode":"55122",
    "sg:province":"MN",
    "sg:tags":[
        "house"
    ],
    "wof:name":"Kathy Trimble Custom Homes",
    "wof:placetype":"venue"
},
  "geometry": {"coordinates":[-93.177595,44.801654],"type":"Point"}
}