{
  "type": "Feature",
  "properties": {
    "addr:full":"1822 Park Ave Apt 26 Minneapolis MN 55404",
    "addr:housenumber":"1822;26",
    "addr:postcode":"55404",
    "addr:street":"Park Ave Apt",
    "iso:country":"US",
    "sg:address":"1822 Park Ave Apt 26",
    "sg:city":"Minneapolis",
    "sg:classifiers":[
        {
            "category":"Health Services",
            "subcategory":"Nursing And Care Facility",
            "type":"Services"
        },
        {
            "category":"Social Services",
            "subcategory":"Retirement Home",
            "type":"Services"
        }
    ],
    "sg:phone":"+1 612 871 5800",
    "sg:postcode":"55404",
    "sg:province":"MN",
    "sg:tags":[
        "living",
        "assisted",
        "convalescent",
        "homes-intermediate"
    ],
    "wof:name":"Oaka Grove Treatment Center",
    "wof:placetype":"venue"
},
  "geometry": {"coordinates":[-93.26512099999999,44.964938],"type":"Point"}
}