{
  "type": "Feature",
  "properties": {
    "iso:country":"US",
    "sg:address":"47 Main St",
    "sg:city":"Easton",
    "sg:classifiers":[
        {
            "category":"Building & Trades",
            "subcategory":"Construction",
            "type":"Services"
        }
    ],
    "sg:phone":"+1 507 787 2225",
    "sg:postcode":"56025",
    "sg:province":"MN",
    "sg:tags":[
        "excavating",
        "contractor"
    ],
    "wof:name":"Swehla Trucking Excavating",
    "wof:placetype":"venue"
},
  "geometry": {"coordinates":[-93.901098,43.764563],"type":"Point"}
}