{
  "type": "Feature",
  "properties": {
    "iso:country":"US",
    "sg:address":"6380 N Oaks Ct NE",
    "sg:city":"Rochester",
    "sg:classifiers":[
        {
            "category":"Building & Trades",
            "subcategory":"Landscaping Services",
            "type":"Services"
        }
    ],
    "sg:phone":"+1 507 259 8068",
    "sg:postcode":"55906",
    "sg:province":"MN",
    "sg:tags":[
        "landscape",
        "contractor"
    ],
    "wof:name":"L & L Landscaping",
    "wof:placetype":"venue"
},
  "geometry": {"coordinates":[-92.423869,44.092224],"type":"Point"}
}