{
  "type": "Feature",
  "properties": {
    "addr:full":"36689 410th Ave Aitkin MN 56431",
    "addr:housenumber":"36689",
    "addr:postcode":"56431",
    "addr:street":"410Th Ave",
    "iso:country":"US",
    "sg:address":"36689 410th Ave",
    "sg:city":"Aitkin",
    "sg:classifiers":[
        {
            "category":"Professional",
            "subcategory":"Business Services",
            "type":"Services"
        }
    ],
    "sg:phone":"+1 218 927 5602",
    "sg:postcode":"56431",
    "sg:province":"MN",
    "wof:name":"Emerald Design Landscape Inc",
    "wof:placetype":"venue"
},
  "geometry": {"coordinates":[-93.707641,46.541626],"type":"Point"}
}