{
  "type": "Feature",
  "properties": {
    "addr:full":"440 Ferndale Rd W Wayzata MN 55391",
    "addr:housenumber":"440",
    "addr:postcode":"55391",
    "addr:street":"Ferndale Rd W",
    "iso:country":"US",
    "sg:address":"440 Ferndale Rd W",
    "sg:city":"Wayzata",
    "sg:classifiers":[
        {
            "category":"Restaurant",
            "type":"Food & Drink"
        }
    ],
    "sg:phone":"+1 952 476 1929",
    "sg:postcode":"55391",
    "sg:province":"MN",
    "sg:tags":[
        "eating"
    ],
    "wof:name":"Wayzata Tea Room & Antiques",
    "wof:placetype":"venue"
},
  "geometry": {"coordinates":[-93.53563699999999,44.963677],"type":"Point"}
}