{
  "type": "Feature",
  "properties": {
    "addr:full":"18578 87th Ave N Osseo MN 55311",
    "addr:housenumber":"18578",
    "addr:postcode":"55311",
    "addr:street":"87Th Ave N",
    "iso:country":"US",
    "sg:address":"18578 87th Ave N",
    "sg:city":"Osseo",
    "sg:classifiers":[
        {
            "category":"Wholesale",
            "subcategory":"Computers",
            "type":"Manufacturing & Wholesale Goods"
        }
    ],
    "sg:phone":"+1 763 420 2609",
    "sg:postcode":"55311",
    "sg:province":"MN",
    "wof:name":"Vanguard Computers",
    "wof:placetype":"venue"
},
  "geometry": {"coordinates":[-93.51553699999999,45.112939],"type":"Point"}
}