{
  "type": "Feature",
  "properties": {
    "addr:full":"8182 75th St NE Foley MN 56329",
    "addr:housenumber":"8182",
    "addr:postcode":"56329",
    "addr:street":"75Th St Ne",
    "iso:country":"US",
    "sg:address":"8182 75th St NE",
    "sg:city":"Foley",
    "sg:classifiers":[
        {
            "category":"Professional",
            "type":"Services"
        }
    ],
    "sg:phone":"+1 320 387 2762",
    "sg:postcode":"56329",
    "sg:province":"MN",
    "wof:name":"Rick Grundhoefer",
    "wof:placetype":"venue"
},
  "geometry": {"coordinates":[-93.99165600000001,45.676805],"type":"Point"}
}