{
  "type": "Feature",
  "properties": {
    "addr:full":"2405 8th St S Moorhead MN 56560",
    "addr:housenumber":"2405",
    "addr:postcode":"56560",
    "addr:street":"8Th St S",
    "iso:country":"US",
    "sg:address":"2405 8th St S",
    "sg:city":"Moorhead",
    "sg:classifiers":[
        {
            "category":"Banks & Credit Unions",
            "subcategory":"Bank",
            "type":"Services"
        }
    ],
    "sg:phone":"+1 218 233 2371",
    "sg:postcode":"56560",
    "sg:province":"MN",
    "sg:tags":[
        "commercial",
        "saving"
    ],
    "sg:website":"http://www.nwbanks.com",
    "wof:name":"Northwestern Bank",
    "wof:placetype":"venue"
},
  "geometry": {"coordinates":[-96.768208,46.851016],"type":"Point"}
}