{
  "type": "Feature",
  "properties": {
    "addr:full":"119 Broadway E Little Falls MN 56345",
    "addr:housenumber":"119",
    "addr:postcode":"56345",
    "addr:street":"Broadway E",
    "iso:country":"US",
    "sg:address":"119 Broadway E",
    "sg:city":"Little Falls",
    "sg:classifiers":[
        {
            "category":"Restaurant",
            "type":"Food & Drink"
        }
    ],
    "sg:phone":"+1 320 632 2664",
    "sg:postcode":"56345",
    "sg:province":"MN",
    "sg:tags":[
        "eating"
    ],
    "wof:name":"West Side Cafe",
    "wof:placetype":"venue"
},
  "geometry": {"coordinates":[-94.362315,45.97648],"type":"Point"}
}