{
  "type": "Feature",
  "properties": {
    "iso:country":"US",
    "sg:address":"251 Snelling Ave S",
    "sg:city":"Saint Paul",
    "sg:classifiers":[
        {
            "category":"Shopping",
            "subcategory":"Hobbies, Toys, & Games",
            "type":"Retail Goods"
        }
    ],
    "sg:phone":"+1 651 695 5559",
    "sg:postcode":"55105",
    "sg:province":"MN",
    "sg:tags":[
        "baby",
        "gear",
        "furniture"
    ],
    "sg:website":"www.peapods.com",
    "wof:name":"Peapods Natural Toys & Baby Care",
    "wof:placetype":"venue"
},
  "geometry": {"coordinates":[-93.166901,44.933601],"type":"Point"}
}