{
  "type": "Feature",
  "properties": {
    "iso:country":"US",
    "sg:address":"10580 Kumquat St NW Ste 9",
    "sg:city":"Minneapolis",
    "sg:phone":"+1 763 755 5586",
    "sg:postcode":"55448",
    "sg:province":"MN",
    "wof:name":"Lida Rental",
    "wof:placetype":"venue"
},
  "geometry": {"coordinates":[-93.281842,45.162166],"type":"Point"}
}