{
  "type": "Feature",
  "properties": {
    "iso:country":"US",
    "sg:address":"100 Kirkwood St E",
    "sg:city":"Lanesboro",
    "sg:classifiers":[
        {
            "category":"Social Services",
            "subcategory":"Child Care",
            "type":"Services"
        }
    ],
    "sg:phone":"+1 507 467 2354",
    "sg:postcode":"55949",
    "sg:province":"MN",
    "sg:tags":[
        "nursery",
        "day"
    ],
    "wof:name":"Lanesboro Public Schools Child Care Center",
    "wof:placetype":"venue"
},
  "geometry": {"coordinates":[-91.97683000000001,43.71653],"type":"Point"}
}