{
  "type": "Feature",
  "properties": {
    "iso:country":"US",
    "sg:address":"373 Ruth St N",
    "sg:city":"Saint Paul",
    "sg:classifiers":[
        {
            "category":"Autos & Motor Vehicles",
            "subcategory":"Fuel & Gas Station",
            "type":"Retail Goods"
        }
    ],
    "sg:phone":"+1 651 735 3444",
    "sg:postcode":"55119",
    "sg:province":"MN",
    "sg:tags":[
        "station",
        "gasoline"
    ],
    "wof:name":"Four Season Automotives",
    "wof:placetype":"venue"
},
  "geometry": {"coordinates":[-93.01521,44.953153],"type":"Point"}
}