{
  "type": "Feature",
  "properties": {
    "iso:country":"US",
    "sg:address":"15204 Crystal Lake Ter",
    "sg:city":"Burnsville",
    "sg:classifiers":[
        {
            "category":"Professional",
            "subcategory":"Management & Consulting",
            "type":"Services"
        }
    ],
    "sg:phone":"+1 612 386 3577",
    "sg:postcode":"55306",
    "sg:province":"MN",
    "sg:tags":[
        "business"
    ],
    "wof:name":"E Service Solutions",
    "wof:placetype":"venue"
},
  "geometry": {"coordinates":[-93.26907,44.726226],"type":"Point"}
}