{
  "type": "Feature",
  "properties": {
    "addr:full":"3131 Nicollet Ave Minneapolis MN 55408",
    "addr:housenumber":"3131",
    "addr:postcode":"55408",
    "addr:street":"Nicollet Ave",
    "iso:country":"US",
    "sg:address":"3131 Nicollet Ave",
    "sg:city":"Minneapolis",
    "sg:classifiers":[
        {
            "category":"Personal",
            "subcategory":"Tattoo Parlor",
            "type":"Services"
        },
        {
            "category":"Personal",
            "subcategory":"Piercing",
            "type":"Services"
        }
    ],
    "sg:phone":"+1 612 824 8181",
    "sg:postcode":"55408",
    "sg:province":"MN",
    "sg:tags":[
        "body"
    ],
    "sg:website":"www.twincitytattoo.com",
    "wof:name":"Twin City Tattoo Llc",
    "wof:placetype":"venue"
},
  "geometry": {"coordinates":[-93.277736,44.946088],"type":"Point"}
}