{
  "type": "Feature",
  "properties": {
    "addr:full":"2647 Bloomington Ave Minneapolis MN 55407",
    "addr:housenumber":"2647",
    "addr:postcode":"55407",
    "addr:street":"Bloomington Ave",
    "iso:country":"US",
    "sg:address":"2647 Bloomington Ave",
    "sg:city":"Minneapolis",
    "sg:classifiers":[
        {
            "category":"Place Of Worship",
            "subcategory":"Church",
            "type":"Public Place"
        },
        {
            "category":"Place Of Worship",
            "type":"Public Place"
        }
    ],
    "sg:phone":"+1 612 724 3510",
    "sg:postcode":"55407",
    "sg:province":"MN",
    "sg:tags":[
        "churches-apostolic",
        "churches-pentecostal-apostolic"
    ],
    "wof:name":"Shiloh Temple-South Side",
    "wof:placetype":"venue"
},
  "geometry": {"coordinates":[-93.25242900000001,44.954691],"type":"Point"}
}