{
  "type": "Feature",
  "properties": {
    "addr:full":"705 Century Ave N Maplewood MN 55119",
    "addr:housenumber":"705",
    "addr:postcode":"55119",
    "addr:street":"Century Ave N",
    "iso:country":"US",
    "sg:address":"705 Century Ave N",
    "sg:city":"Maplewood",
    "sg:classifiers":[
        {
            "category":"Manufacturing",
            "subcategory":"Signs",
            "type":"Manufacturing & Wholesale Goods"
        }
    ],
    "sg:phone":"+1 651 578 2465",
    "sg:postcode":"55119",
    "sg:province":"MN",
    "wof:name":"Design Innovations",
    "wof:placetype":"venue"
},
  "geometry": {"coordinates":[-92.984814,44.964152],"type":"Point"}
}