{
  "type": "Feature",
  "properties": {
    "addr:full":"1076 Maryland Ave E Saint Paul MN 55106",
    "addr:housenumber":"1076",
    "addr:postcode":"55106",
    "addr:street":"Maryland Ave E",
    "iso:country":"US",
    "sg:address":"1076 Maryland Ave E",
    "sg:city":"Saint Paul",
    "sg:classifiers":[
        {
            "category":"Shopping",
            "subcategory":"Used Merchandise",
            "type":"Retail Goods"
        }
    ],
    "sg:phone":"+1 651 776 6287",
    "sg:postcode":"55106",
    "sg:province":"MN",
    "sg:tags":[
        "business"
    ],
    "wof:name":"Dannys Auction Co",
    "wof:placetype":"venue"
},
  "geometry": {"coordinates":[-93.053742,44.977465],"type":"Point"}
}