{
  "type": "Feature",
  "properties": {
    "addr:full":"11347 Viking Dr Eden Prairie MN 55344",
    "addr:housenumber":"11347",
    "addr:postcode":"55344",
    "addr:street":"Viking Dr",
    "iso:country":"US",
    "sg:address":"11347 Viking Dr",
    "sg:city":"Eden Prairie",
    "sg:classifiers":[
        {
            "category":"Restaurant",
            "type":"Food & Drink"
        }
    ],
    "sg:menulink":"http://www.allmenus.com/mn/eden-prairie/10275-don-pablos/menu/",
    "sg:phone":"+1 952 943 2877",
    "sg:postcode":"55344",
    "sg:province":"MN",
    "sg:tags":[
        "sandwich",
        "mexican",
        "salad",
        "soup",
        "american",
        "wrap",
        "tex-mex"
    ],
    "wof:name":"Don Pablo's",
    "wof:placetype":"venue"
},
  "geometry": {"coordinates":[-93.42007099999999,44.862867],"type":"Point"}
}