{
  "type": "Feature",
  "properties": {
    "iso:country":"US",
    "sg:address":"6532 W Lake St",
    "sg:city":"Minneapolis",
    "sg:classifiers":[
        {
            "category":"Organizations",
            "subcategory":"Non-profit Organization",
            "type":"Services"
        }
    ],
    "sg:phone":"+1 952 848 0307",
    "sg:postcode":"55426",
    "sg:province":"MN",
    "sg:tags":[
        "social"
    ],
    "wof:name":"Midwest Avian Adoption Rescue",
    "wof:placetype":"venue"
},
  "geometry": {"coordinates":[-93.360602,44.941714],"type":"Point"}
}