{
  "type": "Feature",
  "properties": {
    "iso:country":"US",
    "sg:address":"12641 63rd Ave N",
    "sg:city":"Osseo",
    "sg:classifiers":[
        {
            "category":"Building & Trades",
            "subcategory":"Construction",
            "type":"Services"
        }
    ],
    "sg:phone":"+1 763 559 9332",
    "sg:postcode":"55369",
    "sg:province":"MN",
    "sg:tags":[
        "house"
    ],
    "wof:name":"Verns Complete Home",
    "wof:placetype":"venue"
},
  "geometry": {"coordinates":[-93.43975500000001,45.069545],"type":"Point"}
}