{
  "type": "Feature",
  "properties": {
    "iso:country":"US",
    "sg:address":"709 2nd St",
    "sg:city":"Carlton",
    "sg:classifiers":[
        {
            "category":"Insurance",
            "subcategory":"Insurance Agent",
            "type":"Services"
        }
    ],
    "sg:phone":"+1 218 384 9498",
    "sg:postcode":"55718",
    "sg:province":"MN",
    "wof:name":"Total Relocation LLC",
    "wof:placetype":"venue"
},
  "geometry": {"coordinates":[-92.426383,46.668491],"type":"Point"}
}