{
  "type": "Feature",
  "properties": {
    "iso:country":"US",
    "sg:address":"11060 Cottonwood St NW",
    "sg:city":"Minneapolis",
    "sg:classifiers":[
        {
            "category":"Professional",
            "subcategory":"Management & Consulting",
            "type":"Services"
        }
    ],
    "sg:phone":"+1 612 927 8974",
    "sg:postcode":"55448",
    "sg:province":"MN",
    "sg:tags":[
        "book",
        "business"
    ],
    "wof:name":"Quality Curriculum Inc",
    "wof:placetype":"venue"
},
  "geometry": {"coordinates":[-93.270262,45.170372],"type":"Point"}
}