{
  "type": "Feature",
  "properties": {
    "addr:full":"2240 105th Ln NW Minneapolis MN 55433",
    "addr:housenumber":"2240",
    "addr:postcode":"55433",
    "addr:street":"105Th Ln Nw",
    "iso:country":"US",
    "sg:address":"2240 105th Ln NW",
    "sg:city":"Minneapolis",
    "sg:classifiers":[
        {
            "category":"Local Transit",
            "type":"Transportation"
        }
    ],
    "sg:phone":"+1 763 757 0189",
    "sg:postcode":"55433",
    "sg:province":"MN",
    "sg:tags":[
        "passenger",
        "limo"
    ],
    "wof:name":"A Dream Ride Limo",
    "wof:placetype":"venue"
},
  "geometry": {"coordinates":[-93.323196,45.161999],"type":"Point"}
}