{
  "type": "Feature",
  "properties": {
    "iso:country":"US",
    "sg:address":"2822 Oak St",
    "sg:city":"Brainerd",
    "sg:classifiers":[
        {
            "category":"Organizations",
            "subcategory":"Religious Organization",
            "type":"Services"
        }
    ],
    "sg:phone":"+1 218 829 1676",
    "sg:postcode":"56401",
    "sg:province":"MN",
    "wof:name":"Seventh-Day Adventist Church",
    "wof:placetype":"venue"
},
  "geometry": {"coordinates":[-94.168072,46.352392],"type":"Point"}
}