{
  "type": "Feature",
  "properties": {
    "iso:country":"US",
    "sg:address":"3563 168th Ln NW",
    "sg:city":"Anoka",
    "sg:classifiers":[
        {
            "category":"Real Estate",
            "subcategory":"Real Estate Operator",
            "type":"Services"
        }
    ],
    "sg:phone":"+1 763 753 3075",
    "sg:postcode":"55304",
    "sg:province":"MN",
    "sg:tags":[
        "property",
        "lessor"
    ],
    "wof:name":"Blue Water Properties Llc",
    "wof:placetype":"venue"
},
  "geometry": {"coordinates":[-93.35686200000001,45.276388],"type":"Point"}
}