{
  "type": "Feature",
  "properties": {
    "iso:country":"US",
    "sg:address":"3301 W 166th St",
    "sg:city":"Jordan",
    "sg:classifiers":[
        {
            "category":"Autos & Motor Vehicles",
            "subcategory":"Motorcycle Sales",
            "type":"Retail Goods"
        }
    ],
    "sg:phone":"+1 952 492 2715",
    "sg:postcode":"55352",
    "sg:province":"MN",
    "sg:tags":[
        "scooter"
    ],
    "wof:name":"Sport Wheels",
    "wof:placetype":"venue"
},
  "geometry": {"coordinates":[-93.588815,44.70867],"type":"Point"}
}