{
  "type": "Feature",
  "properties": {
    "iso:country":"US",
    "sg:address":"3912 Natchez Ave S",
    "sg:city":"Minneapolis",
    "sg:classifiers":[
        {
            "category":"Professional",
            "type":"Services"
        }
    ],
    "sg:phone":"+1 952 922 1374",
    "sg:postcode":"55416",
    "sg:province":"MN",
    "sg:tags":[
        "publication",
        "editorial"
    ],
    "wof:name":"Ira Phil Freshman",
    "wof:placetype":"venue"
},
  "geometry": {"coordinates":[-93.339241,44.932049],"type":"Point"}
}