{
  "type": "Feature",
  "properties": {
    "addr:full":"9942 US Hwy 10 Elk River MN 55309",
    "addr:housenumber":"9942",
    "addr:postcode":"55309",
    "addr:street":"Us Hwy 10",
    "iso:country":"US",
    "sg:address":"9942 US Hwy 10",
    "sg:city":"Elk River",
    "sg:classifiers":[
        {
            "category":"Manufacturing",
            "subcategory":"Tools & Machinery",
            "type":"Manufacturing & Wholesale Goods"
        }
    ],
    "sg:phone":"+1 763 274 0809",
    "sg:postcode":"55309",
    "sg:province":"MN",
    "sg:tags":[
        "machine",
        "shop"
    ],
    "wof:name":"Dimensional Concepts",
    "wof:placetype":"venue"
},
  "geometry": {"coordinates":[-93.695683,45.332412],"type":"Point"}
}