{
  "type": "Feature",
  "properties": {
    "iso:country":"US",
    "sg:address":"8945 Lyndale Ave S",
    "sg:city":"Minneapolis",
    "sg:classifiers":[
        {
            "category":"Retail",
            "subcategory":"Auto Repair",
            "type":"Services"
        }
    ],
    "sg:phone":"+1 952 884 2507",
    "sg:postcode":"55420",
    "sg:province":"MN",
    "sg:tags":[
        "repairing",
        "automobile"
    ],
    "wof:name":"Dee's Auto Repair",
    "wof:placetype":"venue"
},
  "geometry": {"coordinates":[-93.28850199999999,44.842236],"type":"Point"}
}