{
  "type": "Feature",
  "properties": {
    "iso:country":"US",
    "sg:address":"1422 Bemidji Ave N",
    "sg:city":"Bemidji",
    "sg:classifiers":[
        {
            "category":"Retail",
            "subcategory":"Auto Repair",
            "type":"Services"
        }
    ],
    "sg:phone":"+1 218 759 1264",
    "sg:postcode":"56601",
    "sg:province":"MN",
    "sg:tags":[
        "exhaust"
    ],
    "wof:name":"Exhaust Pros",
    "wof:placetype":"venue"
},
  "geometry": {"coordinates":[-94.879536,47.482649],"type":"Point"}
}