{
  "type": "Feature",
  "properties": {
    "addr:full":"11953 Bradford Rd Hopkins MN 55343",
    "addr:housenumber":"11953",
    "addr:postcode":"55343",
    "addr:street":"Bradford Rd",
    "iso:country":"US",
    "sg:address":"11953 Bradford Rd",
    "sg:city":"Hopkins",
    "sg:classifiers":[
        {
            "category":"Social Services",
            "type":"Services"
        }
    ],
    "sg:phone":"+1 952 259 1351",
    "sg:postcode":"55343",
    "sg:province":"MN",
    "wof:name":"Mary Elizabeth Counseling",
    "wof:placetype":"venue"
},
  "geometry": {"coordinates":[-93.431231,44.924307],"type":"Point"}
}