{
  "type": "Feature",
  "properties": {
    "iso:country":"US",
    "sg:address":"1810 Northdale Blvd NW",
    "sg:city":"Minneapolis",
    "sg:classifiers":[
        {
            "category":"Professional",
            "subcategory":"Advertising",
            "type":"Services"
        }
    ],
    "sg:phone":"+1 763 767 1700",
    "sg:postcode":"55448",
    "sg:province":"MN",
    "sg:tags":[
        "print",
        "shop"
    ],
    "wof:name":"Office Etc The",
    "wof:placetype":"venue"
},
  "geometry": {"coordinates":[-93.30994800000001,45.18261],"type":"Point"}
}