{
  "type": "Feature",
  "properties": {
    "addr:full":"12580 Johnson Memorial Dr Shakopee MN 55379",
    "addr:housenumber":"12580",
    "addr:postcode":"55379",
    "addr:street":"Johnson Memorial Dr",
    "iso:country":"US",
    "sg:address":"12580 Johnson Memorial Dr",
    "sg:city":"Shakopee",
    "sg:classifiers":[
        {
            "category":"Autos & Motor Vehicles",
            "subcategory":"Motorcycle Sales",
            "type":"Retail Goods"
        }
    ],
    "sg:phone":"+1 952 445 2565",
    "sg:postcode":"55379",
    "sg:province":"MN",
    "wof:name":"Midwest Sport Center",
    "wof:placetype":"venue"
},
  "geometry": {"coordinates":[-93.572304,44.770802],"type":"Point"}
}