{
  "type": "Feature",
  "properties": {
    "addr:full":"7721 Chanhassen Rd Chanhassen MN 55317",
    "addr:housenumber":"7721",
    "addr:postcode":"55317",
    "addr:street":"Chanhassen Rd",
    "iso:country":"US",
    "sg:address":"7721 Chanhassen Rd",
    "sg:city":"Chanhassen",
    "sg:classifiers":[
        {
            "category":"Building & Trades",
            "subcategory":"Locksmith",
            "type":"Services"
        }
    ],
    "sg:phone":"+1 952 562 0081",
    "sg:postcode":"55317",
    "sg:province":"MN",
    "sg:tags":[
        "key"
    ],
    "wof:name":"1 7 A 24 A Locksmith",
    "wof:placetype":"venue"
},
  "geometry": {"coordinates":[-93.523555,44.863768],"type":"Point"}
}