{
  "type": "Feature",
  "properties": {
    "iso:country":"US",
    "sg:address":"1997 Gold Trl",
    "sg:city":"Saint Paul",
    "sg:classifiers":[
        {
            "category":"Professional",
            "type":"Services"
        }
    ],
    "sg:phone":"+1 651 994 1792",
    "sg:postcode":"55122",
    "sg:province":"MN",
    "wof:name":"Larry J Foster Inc",
    "wof:placetype":"venue"
},
  "geometry": {"coordinates":[-93.20661200000001,44.817187],"type":"Point"}
}