{
  "type": "Feature",
  "properties": {
    "addr:full":"5 Ash Ave NE Wadena MN 56482",
    "addr:housenumber":"5",
    "addr:postcode":"56482",
    "addr:street":"Ash Ave Ne",
    "iso:country":"US",
    "sg:address":"5 Ash Ave NE",
    "sg:city":"Wadena",
    "sg:classifiers":[
        {
            "category":"Food & Beverages",
            "subcategory":"Groceries & Convenience Stores",
            "type":"Retail Goods"
        }
    ],
    "sg:phone":"+1 218 631 1434",
    "sg:postcode":"56482",
    "sg:province":"MN",
    "wof:name":"Orton's",
    "wof:placetype":"venue"
},
  "geometry": {"coordinates":[-95.136025,46.442164],"type":"Point"}
}