{
  "type": "Feature",
  "properties": {
    "addr:full":"3450 Washington Dr Eagan MN 55122",
    "addr:housenumber":"3450",
    "addr:postcode":"55122",
    "addr:street":"Washington Dr",
    "iso:country":"US",
    "sg:address":"3450 Washington Dr",
    "sg:city":"Eagan",
    "sg:classifiers":[
        {
            "category":"Travel",
            "subcategory":"Hotels & Motels",
            "type":"Entertainment"
        }
    ],
    "sg:phone":"+1 651 452 0100",
    "sg:postcode":"55122",
    "sg:province":"MN",
    "sg:website":"www.bwyankeesquareinn.com",
    "wof:name":"Best Western Inn",
    "wof:placetype":"venue"
},
  "geometry": {"coordinates":[-93.16944700000001,44.831759],"type":"Point"}
}