{
  "type": "Feature",
  "properties": {
    "iso:country":"US",
    "sg:address":"3701 W 103rd St",
    "sg:city":"Minneapolis",
    "sg:classifiers":[
        {
            "category":"Shopping",
            "subcategory":"Clothing, Apparel, & Fashions",
            "type":"Retail Goods"
        },
        {
            "category":"Building & Trades",
            "subcategory":"Construction",
            "type":"Services"
        }
    ],
    "sg:phone":"+1 763 315 5010",
    "sg:postcode":"55431",
    "sg:province":"MN",
    "sg:tags":[
        "contractor",
        "clothing",
        "women's"
    ],
    "wof:name":"New Concepts",
    "wof:placetype":"venue"
},
  "geometry": {"coordinates":[-93.32694100000001,44.817613],"type":"Point"}
}