{
  "type": "Feature",
  "properties": {
    "addr:full":"6071 3rd St NE Minneapolis MN 55432",
    "addr:housenumber":"6071",
    "addr:postcode":"55432",
    "addr:street":"3Rd St Ne",
    "iso:country":"US",
    "sg:address":"6071 3rd St NE",
    "sg:city":"Minneapolis",
    "sg:classifiers":[
        {
            "category":"Professional",
            "subcategory":"Management & Consulting",
            "type":"Services"
        },
        {
            "category":"Professional",
            "subcategory":"Advertising",
            "type":"Services"
        }
    ],
    "sg:phone":"+1 763 502 8800",
    "sg:postcode":"55432",
    "sg:province":"MN",
    "sg:tags":[
        "marketing",
        "program",
        "consultant"
    ],
    "wof:name":"Destination Marketing Associates",
    "wof:placetype":"venue"
},
  "geometry": {"coordinates":[-93.264515,45.078426],"type":"Point"}
}