{
  "type": "Feature",
  "properties": {
    "addr:full":"10799 290th Ave Waseca MN 56093",
    "addr:housenumber":"10799",
    "addr:postcode":"56093",
    "addr:street":"290Th Ave",
    "iso:country":"US",
    "sg:address":"10799 290th Ave",
    "sg:city":"Waseca",
    "sg:classifiers":[
        {
            "category":"Farming",
            "subcategory":"Dairy Farm",
            "type":"Manufacturing & Wholesale Goods"
        }
    ],
    "sg:phone":"+1 507 835 2878",
    "sg:postcode":"56093",
    "sg:province":"MN",
    "wof:name":"David Kuhns",
    "wof:placetype":"venue"
},
  "geometry": {"coordinates":[-93.56667899999999,43.978698],"type":"Point"}
}