{
  "type": "Feature",
  "properties": {
    "addr:full":"9555 Dogwood Cir Eden Prairie MN 55347",
    "addr:housenumber":"9555",
    "addr:postcode":"55347",
    "addr:street":"Dogwood Cir",
    "iso:country":"US",
    "sg:address":"9555 Dogwood Cir",
    "sg:city":"Eden Prairie",
    "sg:classifiers":[
        {
            "category":"Professional",
            "subcategory":"Business Services",
            "type":"Services"
        }
    ],
    "sg:phone":"+1 612 670 7220",
    "sg:postcode":"55347",
    "sg:province":"MN",
    "wof:name":"Colliton Envmtl Cnsulting Corp",
    "wof:placetype":"venue"
},
  "geometry": {"coordinates":[-93.407158,44.829722],"type":"Point"}
}