{
  "type": "Feature",
  "properties": {
    "addr:full":"100 S 5th St Suite 2250 Minneapolis MN 55402",
    "addr:housenumber":"100",
    "addr:postcode":"55402",
    "addr:street":"S 5Th St Suite 2250",
    "iso:country":"US",
    "sg:address":"100 S 5th St Suite 2250",
    "sg:city":"Minneapolis",
    "sg:classifiers":[
        {
            "category":"Professional",
            "subcategory":"Lawyer & Legal Services",
            "type":"Services"
        }
    ],
    "sg:phone":"+1 612 573 2000",
    "sg:postcode":"55402",
    "sg:province":"MN",
    "sg:tags":[
        "attorney",
        "copyright",
        "patent",
        "trademark",
        "plan",
        "law"
    ],
    "sg:website":"http://www.dbclaw.com",
    "wof:name":"Dicke , Steven E. - Dicke, Billig & Czaj",
    "wof:placetype":"venue"
},
  "geometry": {"coordinates":[-93.269302,44.978222],"type":"Point"}
}