{
  "type": "Feature",
  "properties": {
    "addr:full":"2067 Co Rd 61 Carlton MN 55718",
    "addr:housenumber":"2067;61",
    "addr:postcode":"55718",
    "addr:street":"Co Rd;Carlton",
    "iso:country":"US",
    "sg:address":"2067 Co Rd 61",
    "sg:city":"Carlton",
    "sg:classifiers":[
        {
            "category":"Home & Garden",
            "subcategory":"Building Materials",
            "type":"Retail Goods"
        },
        {
            "category":"Manufacturing",
            "subcategory":"Glass & Minerals",
            "type":"Manufacturing & Wholesale Goods"
        }
    ],
    "sg:phone":"+1 218 384 3781",
    "sg:postcode":"55718",
    "sg:province":"MN",
    "sg:tags":[
        "ready",
        "concrete",
        "plant",
        "mixed",
        "mix"
    ],
    "wof:name":"Lambert Ready Mix Inc",
    "wof:placetype":"venue"
},
  "geometry": {"coordinates":[-92.51175499999999,46.639631],"type":"Point"}
}