{
  "type": "Feature",
  "properties": {
    "addr:full":"4101 Linden Hills Blvd Minneapolis MN 55410",
    "addr:housenumber":"4101",
    "addr:postcode":"55410",
    "addr:street":"Linden Hills Blvd",
    "iso:country":"US",
    "sg:address":"4101 Linden Hills Blvd",
    "sg:city":"Minneapolis",
    "sg:classifiers":[
        {
            "category":"Professional",
            "subcategory":"Business Services",
            "type":"Services"
        },
        {
            "category":"Real Estate",
            "subcategory":"Architect",
            "type":"Services"
        }
    ],
    "sg:phone":"+1 612 922 2055",
    "sg:postcode":"55410",
    "sg:province":"MN",
    "wof:name":"Urban Design Perspectives",
    "wof:placetype":"venue"
},
  "geometry": {"coordinates":[-93.311401,44.929001],"type":"Point"}
}