{
  "type": "Feature",
  "properties": {
    "addr:full":"28194 Randolph Rd Detroit Lakes MN 56501",
    "addr:postcode":"28194;56501",
    "addr:street":"Randolph Rd",
    "iso:country":"US",
    "sg:address":"28194 Randolph Rd",
    "sg:city":"Detroit Lakes",
    "sg:classifiers":[
        {
            "category":"Building & Trades",
            "subcategory":"Construction",
            "type":"Services"
        }
    ],
    "sg:phone":"+1 218 844 7325",
    "sg:postcode":"56501",
    "sg:province":"MN",
    "sg:tags":[
        "concrete",
        "contractor"
    ],
    "wof:name":"Sealcoat Service Inc",
    "wof:placetype":"venue"
},
  "geometry": {"coordinates":[-95.81371900000001,46.805884],"type":"Point"}
}