{
  "type": "Feature",
  "properties": {
    "addr:full":"10265 Amsden Way Eden Prairie MN 55347",
    "addr:housenumber":"10265",
    "addr:postcode":"55347",
    "addr:street":"Amsden Way",
    "iso:country":"US",
    "sg:address":"10265 Amsden Way",
    "sg:city":"Eden Prairie",
    "sg:classifiers":[
        {
            "category":"Personal",
            "type":"Services"
        }
    ],
    "sg:phone":"+1 952 942 6995",
    "sg:postcode":"55347",
    "sg:province":"MN",
    "wof:name":"Carefree Custom",
    "wof:placetype":"venue"
},
  "geometry": {"coordinates":[-93.408798,44.83266],"type":"Point"}
}