{
  "type": "Feature",
  "properties": {
    "iso:country":"US",
    "sg:address":"7953 College Rd Ste 105",
    "sg:city":"Baxter",
    "sg:classifiers":[
        {
            "category":"Utilities",
            "subcategory":"Water",
            "type":"Services"
        },
        {
            "category":"Building & Trades",
            "subcategory":"Plumbing",
            "type":"Services"
        },
        {
            "category":"Home & Garden",
            "subcategory":"Hardware",
            "type":"Retail Goods"
        }
    ],
    "sg:phone":"+1 218 828 1314",
    "sg:postcode":"56425",
    "sg:province":"MN",
    "sg:tags":[
        "work",
        "filtration",
        "softening",
        "supply",
        "companies-bottled",
        "purification",
        "bulk",
        "equipment",
        "conditioning"
    ],
    "sg:website":"http://www.ecowater.com",
    "wof:name":"EcoWater Systems",
    "wof:placetype":"venue"
},
  "geometry": {"coordinates":[-94.235516,46.344751],"type":"Point"}
}