{
  "type": "Feature",
  "properties": {
    "addr:full":"407 Wabasha St S St Paul MN 55107",
    "addr:housenumber":"407",
    "addr:postcode":"55107",
    "addr:street":"Wabasha St S",
    "iso:country":"US",
    "sg:address":"407 Wabasha St S",
    "sg:city":"St Paul",
    "sg:classifiers":[
        {
            "category":"Restaurant",
            "type":"Food & Drink"
        }
    ],
    "sg:phone":"+1 651 222 8226",
    "sg:postcode":"55107",
    "sg:province":"MN",
    "sg:tags":[
        "mexican"
    ],
    "sg:website":"www.bocachicatacohouse.com",
    "wof:name":"Taco House",
    "wof:placetype":"venue"
},
  "geometry": {"coordinates":[-93.084491,44.933304],"type":"Point"}
}