{
  "type": "Feature",
  "properties": {
    "iso:country":"US",
    "sg:address":"2408 E 115th St",
    "sg:city":"Burnsville",
    "sg:classifiers":[
        {
            "category":"Manufacturing",
            "subcategory":"Tools & Machinery",
            "type":"Manufacturing & Wholesale Goods"
        }
    ],
    "sg:phone":"+1 952 882 0277",
    "sg:postcode":"55337",
    "sg:province":"MN",
    "sg:tags":[
        "cutting",
        "gear"
    ],
    "wof:name":"Career Gear Inc",
    "wof:placetype":"venue"
},
  "geometry": {"coordinates":[-93.240111,44.79724],"type":"Point"}
}