{
  "type": "Feature",
  "properties": {
    "addr:full":"13906 130th St Fergus Falls MN 56537",
    "addr:housenumber":"13906",
    "addr:postcode":"56537",
    "addr:street":"130Th St",
    "iso:country":"US",
    "sg:address":"13906 130th St",
    "sg:city":"Fergus Falls",
    "sg:classifiers":[
        {
            "category":"Farming",
            "subcategory":"Farm",
            "type":"Manufacturing & Wholesale Goods"
        }
    ],
    "sg:phone":"+1 218 736 4048",
    "sg:postcode":"56537",
    "sg:province":"MN",
    "sg:tags":[
        "crop",
        "general"
    ],
    "wof:name":"James Borowski",
    "wof:placetype":"venue"
},
  "geometry": {"coordinates":[-96.195454,46.152075],"type":"Point"}
}