{
  "type": "Feature",
  "properties": {
    "iso:country":"US",
    "sg:address":"2105 Cliff Rd Ste 5",
    "sg:city":"Saint Paul",
    "sg:classifiers":[
        {
            "category":"Bakery",
            "type":"Food & Drink"
        }
    ],
    "sg:phone":"+1 651 686 0112",
    "sg:postcode":"55122",
    "sg:province":"MN",
    "wof:name":"Bittersweet",
    "wof:placetype":"venue"
},
  "geometry": {"coordinates":[-93.214917,44.790377],"type":"Point"}
}