{
  "type": "Feature",
  "properties": {
    "iso:country":"US",
    "sg:address":"26 Main Ave N",
    "sg:city":"Harmony",
    "sg:classifiers":[
        {
            "category":"Building & Trades",
            "subcategory":"Plumbing",
            "type":"Services"
        }
    ],
    "sg:phone":"+1 507 886 5420",
    "sg:postcode":"55939",
    "sg:province":"MN",
    "sg:tags":[
        "plumbing",
        "contractor"
    ],
    "wof:name":"Harmony Plumbing & Heating",
    "wof:placetype":"venue"
},
  "geometry": {"coordinates":[-92.009905,43.555085],"type":"Point"}
}