{
  "type": "Feature",
  "properties": {
    "addr:full":"2400 Cliff Rd E Burnsville MN 55337",
    "addr:housenumber":"2400",
    "addr:postcode":"55337",
    "addr:street":"Cliff Rd E",
    "iso:country":"US",
    "sg:address":"2400 Cliff Rd E",
    "sg:city":"Burnsville",
    "sg:classifiers":[
        {
            "category":"Restaurant",
            "type":"Food & Drink"
        }
    ],
    "sg:menulink":"http://www.allmenus.com/mn/burnsville/6912-dennys/menu/",
    "sg:phone":"+1 952 894 5583",
    "sg:postcode":"55337",
    "sg:province":"MN",
    "sg:tags":[
        "american",
        "diner"
    ],
    "wof:name":"Denny's",
    "wof:placetype":"venue"
},
  "geometry": {"coordinates":[-93.24101899999999,44.790448],"type":"Point"}
}