{
  "type": "Feature",
  "properties": {
    "addr:full":"5101 36th Ave N Minneapolis MN 55422",
    "addr:housenumber":"5101",
    "addr:postcode":"55422",
    "addr:street":"36Th Ave N",
    "iso:country":"US",
    "sg:address":"5101 36th Ave N",
    "sg:city":"Minneapolis",
    "sg:classifiers":[
        {
            "category":"Shopping",
            "subcategory":"Hobbies, Toys, & Games",
            "type":"Retail Goods"
        }
    ],
    "sg:phone":"+1 763 521 0041",
    "sg:postcode":"55422",
    "sg:province":"MN",
    "wof:name":"Gamestop",
    "wof:placetype":"venue"
},
  "geometry": {"coordinates":[-93.347832,45.020508],"type":"Point"}
}