{
  "type": "Feature",
  "properties": {
    "iso:country":"US",
    "sg:address":"5101 36th Ave N",
    "sg:city":"Minneapolis",
    "sg:classifiers":[
        {
            "category":"Shopping",
            "subcategory":"Hobbies, Toys, & Games",
            "type":"Retail Goods"
        }
    ],
    "sg:phone":"+1 763 521 0041",
    "sg:postcode":"55422",
    "sg:province":"MN",
    "wof:name":"Gamestop",
    "wof:placetype":"venue"
},
  "geometry": {"coordinates":[-93.347832,45.020508],"type":"Point"}
}