{
  "type": "Feature",
  "properties": {
    "addr:full":"3801 Wooddale Ave S Minneapolis MN 55416",
    "addr:housenumber":"3801",
    "addr:postcode":"55416",
    "addr:street":"Wooddale Ave S",
    "iso:country":"US",
    "sg:address":"3801 Wooddale Ave S",
    "sg:city":"Minneapolis",
    "sg:classifiers":[
        {
            "category":"Organizations",
            "subcategory":"Religious Organization",
            "type":"Services"
        }
    ],
    "sg:phone":"+1 952 929 6725",
    "sg:postcode":"55416",
    "sg:province":"MN",
    "wof:name":"Aldersgate Untd Methdst Church",
    "wof:placetype":"venue"
},
  "geometry": {"coordinates":[-93.35089000000001,44.933341],"type":"Point"}
}