{
  "type": "Feature",
  "properties": {
    "iso:country":"US",
    "sg:address":"451 Taft St NE Ste 20",
    "sg:city":"Minneapolis",
    "sg:classifiers":[
        {
            "category":"Professional",
            "subcategory":"Advertising",
            "type":"Services"
        },
        {
            "category":"Professional",
            "subcategory":"Printing & Photocopies",
            "type":"Services"
        },
        {
            "category":"Manufacturing",
            "subcategory":"Signs",
            "type":"Manufacturing & Wholesale Goods"
        }
    ],
    "sg:phone":"+1 612 789 9150",
    "sg:postcode":"55413",
    "sg:province":"MN",
    "sg:tags":[
        "screen",
        "specialty"
    ],
    "wof:name":"Supermarket Of Signs, The",
    "wof:placetype":"venue"
},
  "geometry": {"coordinates":[-93.224109,44.994343],"type":"Point"}
}