{
  "type": "Feature",
  "properties": {
    "iso:country":"US",
    "sg:address":"1203 26th Ave S",
    "sg:city":"Moorhead",
    "sg:classifiers":[
        {
            "category":"Manufacturing",
            "subcategory":"Tools & Machinery",
            "type":"Manufacturing & Wholesale Goods"
        }
    ],
    "sg:phone":"+1 218 233 1545",
    "sg:postcode":"56560",
    "sg:province":"MN",
    "sg:tags":[
        "ophthalmic"
    ],
    "wof:name":"Eyewear For Less",
    "wof:placetype":"venue"
},
  "geometry": {"coordinates":[-96.760689,46.849465],"type":"Point"}
}