{
  "type": "Feature",
  "properties": {
    "iso:country":"US",
    "sg:address":"3739 Bridge St NW",
    "sg:city":"Saint Francis",
    "sg:classifiers":[
        {
            "category":"Restaurant",
            "type":"Food & Drink"
        }
    ],
    "sg:menulink":"http://www.allmenus.com/mn/st-francis/151299-subway/menu/",
    "sg:phone":"+1 763 753 8511",
    "sg:postcode":"55070",
    "sg:province":"MN",
    "sg:tags":[
        "american",
        "sandwich"
    ],
    "wof:name":"Subway",
    "wof:placetype":"venue"
},
  "geometry": {"coordinates":[-93.36091999999999,45.386978],"type":"Point"}
}