{
  "type": "Feature",
  "properties": {
    "addr:full":"3050 Red Wing Blvd Hastings MN 55033",
    "addr:housenumber":"3050",
    "addr:postcode":"55033",
    "addr:street":"Red Wing Blvd",
    "iso:country":"US",
    "sg:address":"3050 Red Wing Blvd",
    "sg:city":"Hastings",
    "sg:classifiers":[
        {
            "category":"Government",
            "subcategory":"Office",
            "type":"Public Place"
        }
    ],
    "sg:phone":"+1 651 282 4481",
    "sg:postcode":"55033",
    "sg:province":"MN",
    "sg:tags":[
        "state",
        "security"
    ],
    "wof:name":"Air National Guard",
    "wof:placetype":"venue"
},
  "geometry": {"coordinates":[-92.846807,44.716911],"type":"Point"}
}