{
  "type": "Feature",
  "properties": {
    "addr:full":"505 E Main St Lewiston MN 55952",
    "addr:housenumber":"505",
    "addr:postcode":"55952",
    "addr:street":"E Main St",
    "iso:country":"US",
    "sg:address":"505 E Main St",
    "sg:city":"Lewiston",
    "sg:classifiers":[
        {
            "category":"Health Services",
            "subcategory":"Nursing And Care Facility",
            "type":"Services"
        }
    ],
    "sg:phone":"+1 507 523 2123",
    "sg:postcode":"55952",
    "sg:province":"MN",
    "sg:tags":[
        "home",
        "convalescent"
    ],
    "wof:name":"Lewiston Villa",
    "wof:placetype":"venue"
},
  "geometry": {"coordinates":[-91.862083,43.984155],"type":"Point"}
}