{
  "type": "Feature",
  "properties": {
    "addr:full":"3566 Blue Jay Way St Paul MN 55123",
    "addr:housenumber":"3566",
    "addr:postcode":"55123",
    "addr:street":"Blue Jay Way",
    "iso:country":"US",
    "sg:address":"3566 Blue Jay Way",
    "sg:city":"St Paul",
    "sg:classifiers":[
        {
            "category":"Shopping",
            "subcategory":"Gifts & Souvenirs",
            "type":"Retail Goods"
        }
    ],
    "sg:phone":"+1 651 683 9166",
    "sg:postcode":"55123",
    "sg:province":"MN",
    "sg:tags":[
        "collectible"
    ],
    "wof:name":"Collectsource Of Minnesota",
    "wof:placetype":"venue"
},
  "geometry": {"coordinates":[-93.14279000000001,44.82724],"type":"Point"}
}