{
  "type": "Feature",
  "properties": {
    "addr:full":"4814 W 41st St Minneapolis MN 55416",
    "addr:housenumber":"4814",
    "addr:postcode":"55416",
    "addr:street":"W 41St St",
    "iso:country":"US",
    "sg:address":"4814 W 41st St",
    "sg:city":"Minneapolis",
    "sg:classifiers":[
        {
            "category":"Communications",
            "subcategory":"Film & Video Production",
            "type":"Services"
        }
    ],
    "sg:phone":"+1 952 927 4161",
    "sg:postcode":"55416",
    "sg:province":"MN",
    "sg:tags":[
        "motion",
        "picture"
    ],
    "wof:name":"Dyna Venture Inc",
    "wof:placetype":"venue"
},
  "geometry": {"coordinates":[-93.34113600000001,44.929091],"type":"Point"}
}