{
  "type": "Feature",
  "properties": {
    "iso:country":"US",
    "sg:address":"106 E 2nd St",
    "sg:city":"Winona",
    "sg:classifiers":[
        {
            "category":"Place Of Worship",
            "subcategory":"Church",
            "type":"Public Place"
        },
        {
            "category":"Place Of Worship",
            "type":"Public Place"
        }
    ],
    "sg:phone":"+1 507 454 4640",
    "sg:postcode":"55987",
    "sg:province":"MN",
    "sg:tags":[
        "lutheran",
        "america",
        "churches-lutheran",
        "churches-lutheran-evangelical"
    ],
    "sg:website":"http://gundluth.org",
    "wof:name":"Dundersen, Lutheran, Winona",
    "wof:placetype":"venue"
},
  "geometry": {"coordinates":[-91.634517,44.052879],"type":"Point"}
}