{
  "type": "Feature",
  "properties": {
    "addr:full":"5350 Miller Trunk Hwy Hermantown MN 55811",
    "addr:housenumber":"5350",
    "addr:postcode":"55811",
    "addr:street":"Miller Trunk Hwy",
    "iso:country":"US",
    "sg:address":"5350 Miller Trunk Hwy",
    "sg:city":"Hermantown",
    "sg:classifiers":[
        {
            "category":"Professional",
            "type":"Services"
        }
    ],
    "sg:phone":"+1 218 729 5196",
    "sg:postcode":"55811",
    "sg:province":"MN",
    "sg:tags":[
        "establishment"
    ],
    "wof:name":"Mr Qwik Wrench Your RV Ctr",
    "wof:placetype":"venue"
},
  "geometry": {"coordinates":[-92.24704699999999,46.839257],"type":"Point"}
}