{
  "type": "Feature",
  "properties": {
    "addr:full":"10732 France Ave S Minneapolis MN 55431",
    "addr:postcode":"10732;55431",
    "addr:street":"Ave S",
    "iso:country":"US",
    "sg:address":"10732 France Ave S",
    "sg:city":"Minneapolis",
    "sg:classifiers":[
        {
            "category":"Professional",
            "type":"Services"
        }
    ],
    "sg:phone":"+1 952 888 5652",
    "sg:postcode":"55431",
    "sg:province":"MN",
    "sg:tags":[
        "caterer"
    ],
    "wof:name":"Ala Carte Catering",
    "wof:placetype":"venue"
},
  "geometry": {"coordinates":[-93.329697,44.809299],"type":"Point"}
}