{
  "type": "Feature",
  "properties": {
    "addr:full":"13409 Brenda Blvd Becker MN 55308",
    "addr:housenumber":"13409",
    "addr:postcode":"55308",
    "addr:street":"Brenda Blvd",
    "iso:country":"US",
    "sg:address":"13409 Brenda Blvd",
    "sg:city":"Becker",
    "sg:classifiers":[
        {
            "category":"Building & Trades",
            "subcategory":"Construction",
            "type":"Services"
        }
    ],
    "sg:phone":"+1 763 263 8022",
    "sg:postcode":"55308",
    "sg:province":"MN",
    "sg:tags":[
        "refinishing",
        "flooring",
        "floor",
        "laying",
        "contractor",
        "resurfacing"
    ],
    "wof:name":"Elk Hardwood Flooring LLC",
    "wof:placetype":"venue"
},
  "geometry": {"coordinates":[-93.890762,45.403013],"type":"Point"}
}