{
  "type": "Feature",
  "properties": {
    "addr:full":"5670 146th Ave NW Anoka MN 55303",
    "addr:housenumber":"5670",
    "addr:postcode":"55303",
    "addr:street":"146Th Ave Nw",
    "iso:country":"US",
    "sg:address":"5670 146th Ave NW",
    "sg:city":"Anoka",
    "sg:classifiers":[
        {
            "category":"Manufacturing",
            "subcategory":"Chemicals & Compounds",
            "type":"Manufacturing & Wholesale Goods"
        }
    ],
    "sg:phone":"+1 763 323 0366",
    "sg:postcode":"55303",
    "sg:province":"MN",
    "sg:tags":[
        "preparation",
        "pharmaceutical",
        "mfg"
    ],
    "wof:name":"Eli Lilly and Company",
    "wof:placetype":"venue"
},
  "geometry": {"coordinates":[-93.410364,45.235396],"type":"Point"}
}