{
  "type": "Feature",
  "properties": {
    "addr:full":"3435 38th Ave S Minneapolis MN 55406",
    "addr:housenumber":"3435",
    "addr:postcode":"55406",
    "addr:street":"38Th Ave S",
    "iso:country":"US",
    "sg:address":"3435 38th Ave S",
    "sg:city":"Minneapolis",
    "sg:classifiers":[
        {
            "category":"Manufacturing",
            "subcategory":"Building Materials",
            "type":"Manufacturing & Wholesale Goods"
        }
    ],
    "sg:phone":"+1 612 724 2812",
    "sg:postcode":"55406",
    "sg:province":"MN",
    "sg:tags":[
        "mfg"
    ],
    "wof:name":"Larry's Custom Millwork",
    "wof:placetype":"venue"
},
  "geometry": {"coordinates":[-93.21778,44.940249],"type":"Point"}
}