{
  "type": "Feature",
  "properties": {
    "iso:country":"US",
    "sg:address":"1920 S 1st St Apt 1109",
    "sg:city":"Minneapolis",
    "sg:classifiers":[
        {
            "category":"Education",
            "subcategory":"School",
            "type":"Public Place"
        }
    ],
    "sg:phone":"+1 952 881 4866",
    "sg:postcode":"55454",
    "sg:province":"MN",
    "wof:name":"Tvi",
    "wof:placetype":"venue"
},
  "geometry": {"coordinates":[-93.24567999999999,44.97555],"type":"Point"}
}