{
  "type": "Feature",
  "properties": {
    "iso:country":"US",
    "sg:address":"5130 Washburn Ave S",
    "sg:city":"Minneapolis",
    "sg:classifiers":[
        {
            "category":"Restaurant",
            "type":"Food & Drink"
        }
    ],
    "sg:phone":"+1 612 929 3067",
    "sg:postcode":"55410",
    "sg:province":"MN",
    "sg:tags":[
        "caterer"
    ],
    "wof:name":"Phantom Chef Catering",
    "wof:placetype":"venue"
},
  "geometry": {"coordinates":[-93.317634,44.90938],"type":"Point"}
}