{
  "type": "Feature",
  "properties": {
    "addr:full":"109 Washington St NE Brainerd MN 56401",
    "addr:housenumber":"109",
    "addr:postcode":"56401",
    "addr:street":"Washington St Ne",
    "iso:country":"US",
    "sg:address":"109 Washington St NE",
    "sg:city":"Brainerd",
    "sg:classifiers":[
        {
            "category":"Shopping",
            "subcategory":"Clothing, Apparel, & Fashions",
            "type":"Retail Goods"
        }
    ],
    "sg:phone":"+1 218 824 7299",
    "sg:postcode":"56401",
    "sg:province":"MN",
    "sg:tags":[
        "lingerie"
    ],
    "wof:name":"Exotic Beginnings",
    "wof:placetype":"venue"
},
  "geometry": {"coordinates":[-94.187242,46.359968],"type":"Point"}
}