{
  "type": "Feature",
  "properties": {
    "addr:full":"1530 E 43rd St Minneapolis MN 55407",
    "addr:housenumber":"1530",
    "addr:postcode":"55407",
    "addr:street":"E 43Rd St",
    "iso:country":"US",
    "sg:address":"1530 E 43rd St",
    "sg:city":"Minneapolis",
    "sg:classifiers":[
        {
            "category":"Education",
            "subcategory":"Special Training",
            "type":"Public Place"
        }
    ],
    "sg:phone":"+1 612 721 6759",
    "sg:postcode":"55407",
    "sg:province":"MN",
    "wof:name":"Akhepran Society",
    "wof:placetype":"venue"
},
  "geometry": {"coordinates":[-93.251183,44.92522],"type":"Point"}
}