{
  "type": "Feature",
  "properties": {
    "iso:country":"US",
    "sg:address":"26748 Hwy 63",
    "sg:city":"Racine",
    "sg:classifiers":[
        {
            "category":"Building & Trades",
            "subcategory":"Construction",
            "type":"Services"
        }
    ],
    "sg:phone":"+1 507 378 2468",
    "sg:postcode":"55967",
    "sg:province":"MN",
    "sg:tags":[
        "house"
    ],
    "wof:name":"Mathison Construction",
    "wof:placetype":"venue"
},
  "geometry": {"coordinates":[-92.47929999999999,43.739582],"type":"Point"}
}