{
  "type": "Feature",
  "properties": {
    "addr:full":"2232 55th Ave Trimont MN 56176",
    "addr:housenumber":"2232",
    "addr:postcode":"56176",
    "addr:street":"55Th Ave",
    "iso:country":"US",
    "sg:address":"2232 55th Ave",
    "sg:city":"Trimont",
    "sg:classifiers":[
        {
            "category":"Farming",
            "subcategory":"Livestock Farm",
            "type":"Manufacturing & Wholesale Goods"
        }
    ],
    "sg:phone":"+1 507 639 2201",
    "sg:postcode":"56176",
    "sg:province":"MN",
    "sg:tags":[
        "feedlot",
        "cattle",
        "crop",
        "beef",
        "general"
    ],
    "wof:name":"Leslie Anderson",
    "wof:placetype":"venue"
},
  "geometry": {"coordinates":[-94.764396,43.817782],"type":"Point"}
}