{
  "type": "Feature",
  "properties": {
    "addr:full":"2109 Adams Ave NW Bemidji MN 56601",
    "addr:housenumber":"2109",
    "addr:postcode":"56601",
    "addr:street":"Adams Ave Nw",
    "iso:country":"US",
    "sg:address":"2109 Adams Ave NW",
    "sg:city":"Bemidji",
    "sg:classifiers":[
        {
            "category":"Home & Garden",
            "subcategory":"Building Materials",
            "type":"Retail Goods"
        }
    ],
    "sg:phone":"+1 218 759 8810",
    "sg:postcode":"56601",
    "sg:province":"MN",
    "sg:tags":[
        "glass",
        "window",
        "plate"
    ],
    "wof:name":"Darrell's Auto Glass",
    "wof:placetype":"venue"
},
  "geometry": {"coordinates":[-94.927582,47.488501],"type":"Point"}
}