{
  "type": "Feature",
  "properties": {
    "iso:country":"US",
    "sg:address":"710 E 24th St Ste 205",
    "sg:city":"Minneapolis",
    "sg:classifiers":[
        {
            "category":"Health Services",
            "subcategory":"Doctor",
            "type":"Services"
        }
    ],
    "sg:phone":"+1 612 336 5000",
    "sg:postcode":"55404",
    "sg:province":"MN",
    "sg:tags":[
        "physician",
        "surgeon"
    ],
    "wof:name":"Mulmed Lawrence N MD",
    "wof:placetype":"venue"
},
  "geometry": {"coordinates":[-93.26486199999999,44.95911],"type":"Point"}
}