{
  "type": "Feature",
  "properties": {
    "iso:country":"US",
    "sg:address":"1500 1st Ave NE",
    "sg:city":"Rochester",
    "sg:classifiers":[
        {
            "category":"Banks & Credit Unions",
            "subcategory":"Bank",
            "type":"Services"
        }
    ],
    "sg:phone":"+1 507 281 2999",
    "sg:postcode":"55906",
    "sg:province":"MN",
    "sg:tags":[
        "mortgage"
    ],
    "wof:name":"Mortgage Outlet",
    "wof:placetype":"venue"
},
  "geometry": {"coordinates":[-92.460536,44.037915],"type":"Point"}
}