{
  "type": "Feature",
  "properties": {
    "iso:country":"US",
    "sg:address":"407 E Travelers Trl",
    "sg:city":"Burnsville",
    "sg:classifiers":[
        {
            "category":"Manufacturing",
            "subcategory":"Electronics",
            "type":"Manufacturing & Wholesale Goods"
        }
    ],
    "sg:phone":"+1 952 890 6850",
    "sg:postcode":"55337",
    "sg:province":"MN",
    "sg:tags":[
        "marking",
        "computer",
        "devices",
        "mfg"
    ],
    "wof:name":"Datakey Inc",
    "wof:placetype":"venue"
},
  "geometry": {"coordinates":[-93.27121200000001,44.777929],"type":"Point"}
}