{
  "type": "Feature",
  "properties": {
    "iso:country":"US",
    "sg:address":"1700 Livingston Ave",
    "sg:city":"West St Paul",
    "sg:classifiers":[
        {
            "category":"Professional",
            "subcategory":"Accounting & Tax Preparation",
            "type":"Services"
        }
    ],
    "sg:phone":"+1 651 450 7127",
    "sg:postcode":"55118",
    "sg:province":"MN",
    "sg:tags":[
        "billing"
    ],
    "wof:name":"Trans-Medic",
    "wof:placetype":"venue"
},
  "geometry": {"coordinates":[-93.082437,44.897165],"type":"Point"}
}