{
  "type": "Feature",
  "properties": {
    "iso:country":"US",
    "sg:address":"2474 Territorial Rd",
    "sg:city":"St Paul",
    "sg:classifiers":[
        {
            "category":"Manufacturing",
            "subcategory":"Signs",
            "type":"Manufacturing & Wholesale Goods"
        },
        {
            "category":"Professional",
            "subcategory":"Computer Services",
            "type":"Services"
        }
    ],
    "sg:phone":"+1 651 645 2745",
    "sg:postcode":"55114",
    "sg:province":"MN",
    "sg:tags":[
        "computerized",
        "graphics"
    ],
    "sg:website":"www.budgetsignshop.com",
    "wof:name":"Budget Sign Graphics Inc",
    "wof:placetype":"venue"
},
  "geometry": {"coordinates":[-93.199896,44.966436],"type":"Point"}
}