{
  "type": "Feature",
  "properties": {
    "iso:country":"US",
    "sg:address":"5101 Thimsen Ave",
    "sg:city":"Minnetonka",
    "sg:classifiers":[
        {
            "category":"Real Estate",
            "subcategory":"Real Estate Operator",
            "type":"Services"
        }
    ],
    "sg:phone":"+1 952 401 8022",
    "sg:postcode":"55345",
    "sg:province":"MN",
    "sg:tags":[
        "building",
        "nonresidential"
    ],
    "wof:name":"AJW Properties",
    "wof:placetype":"venue"
},
  "geometry": {"coordinates":[-93.50502899999999,44.91267],"type":"Point"}
}