{
  "type": "Feature",
  "properties": {
    "iso:country":"US",
    "sg:address":"399 Elm St",
    "sg:city":"Circle Pines",
    "sg:classifiers":[
        {
            "category":"Education",
            "subcategory":"School",
            "type":"Public Place"
        }
    ],
    "sg:phone":"+1 763 792 5400",
    "sg:postcode":"55014",
    "sg:province":"MN",
    "wof:name":"Centennial Middle School",
    "wof:placetype":"venue"
},
  "geometry": {"coordinates":[-93.12341499999999,45.16769],"type":"Point"}
}