{
  "type": "Feature",
  "properties": {
    "addr:full":"1121 Jackson St NE Minneapolis MN 55413",
    "addr:housenumber":"1121",
    "addr:postcode":"55413",
    "addr:street":"Jackson St Ne",
    "iso:country":"US",
    "sg:address":"1121 Jackson St NE",
    "sg:city":"Minneapolis",
    "sg:classifiers":[
        {
            "category":"Building & Trades",
            "subcategory":"Electrical",
            "type":"Services"
        }
    ],
    "sg:phone":"+1 612 871 3003",
    "sg:postcode":"55413",
    "sg:province":"MN",
    "sg:tags":[
        "electric",
        "contractor"
    ],
    "wof:name":"Legacy Electric Inc",
    "wof:placetype":"venue"
},
  "geometry": {"coordinates":[-93.249774,44.999642],"type":"Point"}
}