{
  "type": "Feature",
  "properties": {
    "addr:full":"40 Wilhelmina Dr Carlton MN 55718",
    "addr:housenumber":"40",
    "addr:postcode":"55718",
    "addr:street":"Wilhelmina Dr",
    "iso:country":"US",
    "sg:address":"40 Wilhelmina Dr",
    "sg:city":"Carlton",
    "sg:classifiers":[
        {
            "category":"Social Services",
            "subcategory":"Child Care",
            "type":"Services"
        }
    ],
    "sg:phone":"+1 218 384 9456",
    "sg:postcode":"55718",
    "sg:province":"MN",
    "sg:tags":[
        "daycare",
        "provider"
    ],
    "wof:name":"Lisa Johnson",
    "wof:placetype":"venue"
},
  "geometry": {"coordinates":[-92.41791499999999,46.652382],"type":"Point"}
}