{
  "type": "Feature",
  "properties": {
    "addr:full":"636 Mendelssohn Ave N Minneapolis MN 55427",
    "addr:housenumber":"636",
    "addr:postcode":"55427",
    "addr:street":"Mendelssohn Ave N",
    "iso:country":"US",
    "sg:address":"636 Mendelssohn Ave N",
    "sg:city":"Minneapolis",
    "sg:classifiers":[
        {
            "category":"Education",
            "subcategory":"Vocational School",
            "type":"Public Place"
        }
    ],
    "sg:phone":"+1 763 546 0072",
    "sg:postcode":"55427",
    "sg:province":"MN",
    "sg:tags":[
        "training",
        "computer",
        "consulting"
    ],
    "wof:name":"Interntnal Inst For Sftwr Tstg",
    "wof:placetype":"venue"
},
  "geometry": {"coordinates":[-93.39970599999999,44.988919],"type":"Point"}
}