{
  "type": "Feature",
  "properties": {
    "addr:full":"902 W Lincoln Ave Olivia MN 56277",
    "addr:housenumber":"902",
    "addr:postcode":"56277",
    "addr:street":"W Lincoln Ave",
    "iso:country":"US",
    "sg:address":"902 W Lincoln Ave",
    "sg:city":"Olivia",
    "sg:classifiers":[
        {
            "category":"Health Services",
            "subcategory":"Optometrist",
            "type":"Services"
        }
    ],
    "sg:phone":"+1 320 523 2020",
    "sg:postcode":"56277",
    "sg:province":"MN",
    "wof:name":"Family Eye Ctr/Eye Looks",
    "wof:placetype":"venue"
},
  "geometry": {"coordinates":[-94.99023099999999,44.77655],"type":"Point"}
}