{
  "type": "Feature",
  "properties": {
    "iso:country":"US",
    "sg:address":"1463 W Minnehaha Ave",
    "sg:city":"St Paul",
    "sg:classifiers":[
        {
            "category":"Organizations",
            "subcategory":"Non-profit Organization",
            "type":"Services"
        }
    ],
    "sg:phone":"+1 651 644 4438",
    "sg:postcode":"55104",
    "sg:province":"MN",
    "sg:website":"www.clcmn.org",
    "wof:name":"Children Law Ctr Of Minnesota",
    "wof:placetype":"venue"
},
  "geometry": {"coordinates":[-93.16363800000001,44.962965],"type":"Point"}
}