{
  "type": "Feature",
  "properties": {
    "iso:country":"US",
    "sg:address":"1315 Glenwood Ave",
    "sg:city":"Minneapolis",
    "sg:classifiers":[
        {
            "category":"Professional",
            "subcategory":"Employment Agencies",
            "type":"Services"
        }
    ],
    "sg:phone":"+1 612 374 4596",
    "sg:postcode":"55405",
    "sg:province":"MN",
    "sg:tags":[
        "help",
        "supply"
    ],
    "wof:name":"Econotemp Personnel Services",
    "wof:placetype":"venue"
},
  "geometry": {"coordinates":[-93.298084,44.980694],"type":"Point"}
}