{
  "type": "Feature",
  "properties": {
    "addr:full":"306 1st St S Raymond MN 56282",
    "addr:housenumber":"306",
    "addr:postcode":"56282",
    "addr:street":"1St St S",
    "iso:country":"US",
    "sg:address":"306 1st St S",
    "sg:city":"Raymond",
    "sg:classifiers":[
        {
            "category":"Organizations",
            "subcategory":"Religious Organization",
            "type":"Services"
        }
    ],
    "sg:phone":"+1 320 967 4721",
    "sg:postcode":"56282",
    "sg:province":"MN",
    "sg:tags":[
        "church"
    ],
    "wof:name":"Raymond Christian Reformed",
    "wof:placetype":"venue"
},
  "geometry": {"coordinates":[-95.237144,45.015602],"type":"Point"}
}