{
  "type": "Feature",
  "properties": {
    "iso:country":"US",
    "sg:address":"615 Mina Ct",
    "sg:city":"Saint Paul",
    "sg:classifiers":[
        {
            "category":"Shopping",
            "subcategory":"Pharmacy",
            "type":"Retail Goods"
        }
    ],
    "sg:phone":"+1 651 221 0019",
    "sg:postcode":"55115",
    "sg:province":"MN",
    "wof:name":"Country Valu Pharmacy Inc",
    "wof:placetype":"venue"
},
  "geometry": {"coordinates":[-92.979444,45.056154],"type":"Point"}
}