{
  "type": "Feature",
  "properties": {
    "addr:full":"650 Hennepin Ave Minneapolis MN 55403",
    "addr:housenumber":"650",
    "addr:postcode":"55403",
    "addr:street":"Hennepin Ave",
    "iso:country":"US",
    "sg:address":"650 Hennepin Ave",
    "sg:city":"Minneapolis",
    "sg:classifiers":[
        {
            "category":"Arts & Performance",
            "subcategory":"Music",
            "type":"Entertainment"
        },
        {
            "category":"Bars & Pubs",
            "type":"Food & Drink"
        },
        {
            "category":"Restaurant",
            "type":"Food & Drink"
        },
        {
            "category":"Bars & Pubs",
            "subcategory":"Nightclub",
            "type":"Food & Drink"
        },
        {
            "category":"Recreation",
            "type":"Entertainment"
        }
    ],
    "sg:phone":"+1 612 337 6700",
    "sg:postcode":"55403",
    "sg:province":"MN",
    "sg:tags":[
        "business",
        "club",
        "venue",
        "traditional",
        "american",
        "entertainers-family",
        "night"
    ],
    "sg:website":"www.theshouthouse.com/Minneapoli...",
    "wof:name":"Shout House Dueling Pianos",
    "wof:placetype":"venue"
},
  "geometry": {"coordinates":[-93.274748,44.977985],"type":"Point"}
}