{
  "type": "Feature",
  "properties": {
    "iso:country":"US",
    "sg:address":"1210 Northland Dr",
    "sg:city":"St Paul",
    "sg:classifiers":[
        {
            "category":"Professional",
            "subcategory":"Computer Services",
            "type":"Services"
        }
    ],
    "sg:phone":"+1 651 452 0300",
    "sg:postcode":"55120",
    "sg:province":"MN",
    "sg:website":"www.ddvc.com",
    "wof:name":"Digital Data Voice Corp",
    "wof:placetype":"venue"
},
  "geometry": {"coordinates":[-93.15410300000001,44.86298],"type":"Point"}
}