{
  "type": "Feature",
  "properties": {
    "addr:full":"19800 Stieg Rd Rogers MN 55374",
    "addr:postcode":"19800;55374",
    "addr:street":"Stieg Rd",
    "iso:country":"US",
    "sg:address":"19800 Stieg Rd",
    "sg:city":"Rogers",
    "sg:classifiers":[
        {
            "category":"Banks & Credit Unions",
            "subcategory":"Investment Brokerage",
            "type":"Services"
        }
    ],
    "sg:phone":"+1 763 420 3196",
    "sg:postcode":"55374",
    "sg:province":"MN",
    "sg:tags":[
        "advisory"
    ],
    "wof:name":"King Investments Inc",
    "wof:placetype":"venue"
},
  "geometry": {"coordinates":[-93.538774,45.145609],"type":"Point"}
}