{
  "type": "Feature",
  "properties": {
    "iso:country":"US",
    "sg:address":"115 E Howard St",
    "sg:city":"Hibbing",
    "sg:classifiers":[
        {
            "category":"Organizations",
            "subcategory":"Community Association",
            "type":"Services"
        }
    ],
    "sg:phone":"+1 218 262 5565",
    "sg:postcode":"55746",
    "sg:province":"MN",
    "wof:name":"Northern Lake Girl Scouts",
    "wof:placetype":"venue"
},
  "geometry": {"coordinates":[-92.94069,47.427522],"type":"Point"}
}