{
  "type": "Feature",
  "properties": {
    "addr:full":"417 Wall St W Jasper MN 56144",
    "addr:housenumber":"417",
    "addr:postcode":"56144",
    "addr:street":"Wall St W",
    "iso:country":"US",
    "sg:address":"417 Wall St W",
    "sg:city":"Jasper",
    "sg:classifiers":[
        {
            "category":"Retail",
            "subcategory":"Funeral Services",
            "type":"Services"
        }
    ],
    "sg:phone":"+1 507 348 4321",
    "sg:postcode":"56144",
    "sg:province":"MN",
    "sg:tags":[
        "director"
    ],
    "wof:name":"Foster Hartquist Funeral Home",
    "wof:placetype":"venue"
},
  "geometry": {"coordinates":[-96.40330400000001,43.849958],"type":"Point"}
}