{
  "type": "Feature",
  "properties": {
    "addr:full":"1690 University Ave W St Paul MN 55104",
    "addr:housenumber":"1690",
    "addr:postcode":"55104",
    "addr:street":"University Ave W",
    "iso:country":"US",
    "sg:address":"1690 University Ave W",
    "sg:city":"St Paul",
    "sg:classifiers":[
        {
            "category":"Health Services",
            "subcategory":"Doctor",
            "type":"Services"
        }
    ],
    "sg:phone":"+1 651 646 2581",
    "sg:postcode":"55104",
    "sg:province":"MN",
    "sg:tags":[
        "physician",
        "surgeon"
    ],
    "wof:name":"Ophthalmic Plastic & Recnstrct",
    "wof:placetype":"venue"
},
  "geometry": {"coordinates":[-93.171463,44.955586],"type":"Point"}
}