{
  "type": "Feature",
  "properties": {
    "addr:full":"302 Elm Ave Moose Lake MN 55767",
    "addr:housenumber":"302",
    "addr:postcode":"55767",
    "addr:street":"Elm Ave",
    "iso:country":"US",
    "sg:address":"302 Elm Ave",
    "sg:city":"Moose Lake",
    "sg:classifiers":[
        {
            "category":"Professional",
            "subcategory":"Lawyer & Legal Services",
            "type":"Services"
        }
    ],
    "sg:phone":"+1 218 485 4489",
    "sg:postcode":"55767",
    "sg:province":"MN",
    "sg:tags":[
        "attorney"
    ],
    "wof:name":"Dodge & Warp Law Offices",
    "wof:placetype":"venue"
},
  "geometry": {"coordinates":[-92.76188500000001,46.453792],"type":"Point"}
}