{
  "type": "Feature",
  "properties": {
    "addr:full":"17773 Cascade Dr Eden Prairie MN 55347",
    "addr:housenumber":"17773",
    "addr:postcode":"55347",
    "addr:street":"Cascade Dr",
    "iso:country":"US",
    "sg:address":"17773 Cascade Dr",
    "sg:city":"Eden Prairie",
    "sg:classifiers":[
        {
            "category":"Wholesale",
            "subcategory":"Non-durable Goods",
            "type":"Manufacturing & Wholesale Goods"
        }
    ],
    "sg:phone":"+1 952 294 9873",
    "sg:postcode":"55347",
    "sg:province":"MN",
    "wof:name":"Iron Tree Distributors",
    "wof:placetype":"venue"
},
  "geometry": {"coordinates":[-93.507998,44.853031],"type":"Point"}
}