{
  "type": "Feature",
  "properties": {
    "addr:full":"3820 E Lake St Minneapolis MN 55406",
    "addr:housenumber":"3820",
    "addr:postcode":"55406",
    "addr:street":"E Lake St",
    "iso:country":"US",
    "sg:address":"3820 E Lake St",
    "sg:city":"Minneapolis",
    "sg:classifiers":[
        {
            "category":"Shopping",
            "subcategory":"Music",
            "type":"Retail Goods"
        }
    ],
    "sg:phone":"+1 612 729 8890",
    "sg:postcode":"55406",
    "sg:province":"MN",
    "sg:tags":[
        "record",
        "vinyl"
    ],
    "sg:website":"www.hymiesrecords.com",
    "wof:name":"Hymie's Vintage Records",
    "wof:placetype":"venue"
},
  "geometry": {"coordinates":[-93.21756600000001,44.948341],"type":"Point"}
}