{
  "type": "Feature",
  "properties": {
    "iso:country":"US",
    "sg:address":"2451 Nicollet Ave",
    "sg:city":"Minneapolis",
    "sg:classifiers":[
        {
            "category":"Food & Beverages",
            "subcategory":"Specialty",
            "type":"Retail Goods"
        }
    ],
    "sg:phone":"+1 612 871 3177",
    "sg:postcode":"55404",
    "sg:province":"MN",
    "sg:tags":[
        "tea",
        "coffee"
    ],
    "wof:name":"Spyhouse Espresso Bad Gallery",
    "wof:placetype":"venue"
},
  "geometry": {"coordinates":[-93.277782,44.958243],"type":"Point"}
}