{
  "type": "Feature",
  "properties": {
    "iso:country":"US",
    "sg:address":"3929 Aldrich Ave S",
    "sg:city":"Minneapolis",
    "sg:classifiers":[
        {
            "category":"Building & Trades",
            "subcategory":"Construction",
            "type":"Services"
        }
    ],
    "sg:phone":"+1 612 827 7312",
    "sg:postcode":"55409",
    "sg:province":"MN",
    "sg:tags":[
        "hanging",
        "contractor"
    ],
    "wof:name":"Decorative Painted Finishes",
    "wof:placetype":"venue"
},
  "geometry": {"coordinates":[-93.28944300000001,44.930959],"type":"Point"}
}