{
  "type": "Feature",
  "properties": {
    "addr:full":"11470 Galtier Dr Burnsville MN 55337",
    "addr:housenumber":"11470",
    "addr:postcode":"55337",
    "addr:street":"Galtier Dr",
    "iso:country":"US",
    "sg:address":"11470 Galtier Dr",
    "sg:city":"Burnsville",
    "sg:classifiers":[
        {
            "category":"Banks & Credit Unions",
            "subcategory":"Investment Brokerage",
            "type":"Services"
        }
    ],
    "sg:phone":"+1 952 894 2842",
    "sg:postcode":"55337",
    "sg:province":"MN",
    "sg:tags":[
        "security"
    ],
    "wof:name":"Adambeck Assoc",
    "wof:placetype":"venue"
},
  "geometry": {"coordinates":[-93.229378,44.797103],"type":"Point"}
}