{
  "type": "Feature",
  "properties": {
    "addr:full":"104 NW 2nd St Fulda MN 56131",
    "addr:housenumber":"104",
    "addr:postcode":"56131",
    "addr:street":"Nw 2Nd St",
    "iso:country":"US",
    "sg:address":"104 NW 2nd St",
    "sg:city":"Fulda",
    "sg:classifiers":[
        {
            "category":"Organizations",
            "subcategory":"Community Association",
            "type":"Services"
        }
    ],
    "sg:phone":"+1 507 425 2484",
    "sg:postcode":"56131",
    "sg:province":"MN",
    "sg:tags":[
        "club"
    ],
    "wof:name":"Fulda Senior Citizen Inc",
    "wof:placetype":"venue"
},
  "geometry": {"coordinates":[-95.600919,43.870806],"type":"Point"}
}