{
  "type": "Feature",
  "properties": {
    "addr:full":"5141 80th Ave Bowlus MN 56314",
    "addr:housenumber":"5141",
    "addr:postcode":"56314",
    "addr:street":"80Th Ave",
    "iso:country":"US",
    "sg:address":"5141 80th Ave",
    "sg:city":"Bowlus",
    "sg:classifiers":[
        {
            "category":"Freight",
            "type":"Transportation"
        }
    ],
    "sg:phone":"+1 320 573 2422",
    "sg:postcode":"56314",
    "sg:province":"MN",
    "sg:tags":[
        "operations",
        "trucking"
    ],
    "wof:name":"Northern Express",
    "wof:placetype":"venue"
},
  "geometry": {"coordinates":[-94.493499,45.834889],"type":"Point"}
}