{
  "type": "Feature",
  "properties": {
    "addr:full":"1137 2nd St SW Rochester MN 55902",
    "addr:housenumber":"1137",
    "addr:postcode":"55902",
    "addr:street":"2Nd St Sw",
    "iso:country":"US",
    "sg:address":"1137 2nd St SW",
    "sg:city":"Rochester",
    "sg:classifiers":[
        {
            "category":"Professional",
            "type":"Services"
        },
        {
            "category":"Shopping",
            "subcategory":"Crafts & Fabrics",
            "type":"Retail Goods"
        }
    ],
    "sg:phone":"+1 507 285 5345",
    "sg:postcode":"55902",
    "sg:province":"MN",
    "sg:tags":[
        "yarn"
    ],
    "wof:name":"Kristen's Knits",
    "wof:placetype":"venue"
},
  "geometry": {"coordinates":[-92.480476,44.021708],"type":"Point"}
}