{
  "type": "Feature",
  "properties": {
    "addr:full":"1119 11th St N Sauk Rapids MN 56379",
    "addr:housenumber":"1119",
    "addr:postcode":"56379",
    "addr:street":"11Th St N Sauk",
    "iso:country":"US",
    "sg:address":"1119 11th St N",
    "sg:city":"Sauk Rapids",
    "sg:classifiers":[
        {
            "category":"Social Services",
            "subcategory":"Adult Care",
            "type":"Services"
        }
    ],
    "sg:phone":"+1 320 258 3245",
    "sg:postcode":"56379",
    "sg:province":"MN",
    "sg:tags":[
        "residential",
        "foster"
    ],
    "wof:name":"Opportunity Manor Foster Seven",
    "wof:placetype":"venue"
},
  "geometry": {"coordinates":[-94.15927000000001,45.602673],"type":"Point"}
}