{
  "type": "Feature",
  "properties": {
    "addr:full":"10991 Co Rd 131 Rice MN 56367",
    "addr:housenumber":"10991;131",
    "addr:postcode":"56367",
    "addr:street":"Co Rd",
    "iso:country":"US",
    "sg:address":"10991 Co Rd 131",
    "sg:city":"Rice",
    "sg:classifiers":[
        {
            "category":"Farming",
            "subcategory":"Dairy Farm",
            "type":"Manufacturing & Wholesale Goods"
        }
    ],
    "sg:phone":"+1 320 253 0774",
    "sg:postcode":"56367",
    "sg:province":"MN",
    "wof:name":"Patrick Frank Jr & Ione",
    "wof:placetype":"venue"
},
  "geometry": {"coordinates":[-94.332486,45.717365],"type":"Point"}
}