{
  "type": "Feature",
  "properties": {
    "addr:full":"1717 3rd Ave E Hibbing MN 55746",
    "addr:housenumber":"1717",
    "addr:postcode":"55746",
    "addr:street":"3Rd Ave E Hibbing",
    "iso:country":"US",
    "sg:address":"1717 3rd Ave E",
    "sg:city":"Hibbing",
    "sg:classifiers":[
        {
            "category":"Bars & Pubs",
            "type":"Food & Drink"
        }
    ],
    "sg:phone":"+1 218 263 9313",
    "sg:postcode":"55746",
    "sg:province":"MN",
    "wof:name":"Palmers Tavern",
    "wof:placetype":"venue"
},
  "geometry": {"coordinates":[-92.939555,47.430958],"type":"Point"}
}