{
  "type": "Feature",
  "properties": {
    "addr:full":"13657 67th Ave N Osseo MN 55311",
    "addr:housenumber":"13657",
    "addr:postcode":"55311",
    "addr:street":"67Th Ave N",
    "iso:country":"US",
    "sg:address":"13657 67th Ave N",
    "sg:city":"Osseo",
    "sg:classifiers":[
        {
            "category":"Professional",
            "subcategory":"Art Services",
            "type":"Services"
        }
    ],
    "sg:phone":"+1 763 559 5413",
    "sg:postcode":"55311",
    "sg:province":"MN",
    "sg:tags":[
        "lithographic",
        "commercial",
        "design",
        "p"
    ],
    "wof:name":"Inksmith Prtg & Graphics Co",
    "wof:placetype":"venue"
},
  "geometry": {"coordinates":[-93.452698,45.07666],"type":"Point"}
}