{
  "type": "Feature",
  "properties": {
    "iso:country":"US",
    "sg:address":"2 21st Ave S",
    "sg:city":"St Cloud",
    "sg:classifiers":[
        {
            "category":"Home & Garden",
            "subcategory":"Building Materials",
            "type":"Retail Goods"
        },
        {
            "category":"Retail",
            "subcategory":"Auto Repair",
            "type":"Services"
        }
    ],
    "sg:phone":"+1 320 259 1000",
    "sg:postcode":"56301",
    "sg:province":"MN",
    "sg:tags":[
        "plate",
        "window",
        "installation",
        "glass"
    ],
    "wof:name":"Safelite Auto Glass",
    "wof:placetype":"venue"
},
  "geometry": {"coordinates":[-94.18276,45.55131],"type":"Point"}
}