{
  "type": "Feature",
  "properties": {
    "iso:country":"US",
    "sg:address":"1584 Finch Ln",
    "sg:city":"Mound",
    "sg:classifiers":[
        {
            "category":"Building & Trades",
            "subcategory":"Landscaping Services",
            "type":"Services"
        }
    ],
    "sg:phone":"+1 612 310 4766",
    "sg:postcode":"55364",
    "sg:province":"MN",
    "sg:tags":[
        "landscape"
    ],
    "wof:name":"Earthscape",
    "wof:placetype":"venue"
},
  "geometry": {"coordinates":[-93.651572,44.949364],"type":"Point"}
}