{
  "type": "Feature",
  "properties": {
    "iso:country":"US",
    "sg:address":"5425 W 132nd St",
    "sg:city":"Savage",
    "sg:classifiers":[
        {
            "category":"Building & Trades",
            "subcategory":"Locksmith",
            "type":"Services"
        }
    ],
    "sg:phone":"+1 952 563 0092",
    "sg:postcode":"55378",
    "sg:province":"MN",
    "sg:tags":[
        "key"
    ],
    "wof:name":"Locksmith Asap",
    "wof:placetype":"venue"
},
  "geometry": {"coordinates":[-93.34808,44.76397],"type":"Point"}
}