{
  "type": "Feature",
  "properties": {
    "iso:country":"US",
    "sg:address":"3436 Yukon Ave S",
    "sg:city":"Minneapolis",
    "sg:classifiers":[
        {
            "category":"Professional",
            "subcategory":"Business Services",
            "type":"Services"
        }
    ],
    "sg:phone":"+1 612 867 7153",
    "sg:postcode":"55426",
    "sg:province":"MN",
    "wof:name":"Bloom Enterprises",
    "wof:placetype":"venue"
},
  "geometry": {"coordinates":[-93.38707700000001,44.941632],"type":"Point"}
}