{
  "type": "Feature",
  "properties": {
    "addr:full":"5101 36 Ave Minneapolis MN 55485",
    "addr:housenumber":"5101",
    "addr:postcode":"55485",
    "addr:street":"36 Ave",
    "iso:country":"US",
    "sg:address":"5101 36 Ave",
    "sg:city":"Minneapolis",
    "sg:classifiers":[
        {
            "category":"Personal",
            "subcategory":"Nail Salon",
            "type":"Services"
        }
    ],
    "sg:phone":"+1 763 588 0222",
    "sg:postcode":"55485",
    "sg:province":"MN",
    "wof:name":"Great Nails",
    "wof:placetype":"venue"
},
  "geometry": {"coordinates":[-93.220286,44.910762],"type":"Point"}
}