{
  "type": "Feature",
  "properties": {
    "iso:country":"US",
    "sg:address":"507 E Travelers Trl",
    "sg:city":"Burnsville",
    "sg:classifiers":[
        {
            "category":"Banks & Credit Unions",
            "subcategory":"Bank",
            "type":"Services"
        }
    ],
    "sg:phone":"+1 952 895 7254",
    "sg:postcode":"55337",
    "sg:province":"MN",
    "wof:name":"Intersavings Bank",
    "wof:placetype":"venue"
},
  "geometry": {"coordinates":[-93.269243,44.779094],"type":"Point"}
}