{
  "type": "Feature",
  "properties": {
    "iso:country":"US",
    "sg:address":"1950 W Highland Pkwy",
    "sg:city":"St Paul",
    "sg:classifiers":[
        {
            "category":"Wholesale",
            "subcategory":"Motor Vehicles",
            "type":"Manufacturing & Wholesale Goods"
        }
    ],
    "sg:phone":"+1 612 790 1364",
    "sg:postcode":"55116",
    "sg:province":"MN",
    "sg:tags":[
        "automobile",
        "truck",
        "broker"
    ],
    "wof:name":"Fohrman Motors LTD",
    "wof:placetype":"venue"
},
  "geometry": {"coordinates":[-93.18086599999999,44.919777],"type":"Point"}
}