{
  "type": "Feature",
  "properties": {
    "iso:country":"US",
    "sg:address":"624 Main St W",
    "sg:city":"Pipestone",
    "sg:classifiers":[
        {
            "category":"Banks & Credit Unions",
            "subcategory":"Financial Services",
            "type":"Services"
        }
    ],
    "sg:phone":"+1 507 825 3516",
    "sg:postcode":"56164",
    "sg:province":"MN",
    "sg:tags":[
        "trust",
        "management"
    ],
    "wof:name":"Hunsted Family Living Trust",
    "wof:placetype":"venue"
},
  "geometry": {"coordinates":[-96.32616,44.000432],"type":"Point"}
}