{
  "type": "Feature",
  "properties": {
    "addr:full":"142 Jay Cooke Rd Esko MN 55733",
    "addr:housenumber":"142",
    "addr:postcode":"55733",
    "addr:street":"Jay Cooke Rd",
    "iso:country":"US",
    "sg:address":"142 Jay Cooke Rd",
    "sg:city":"Esko",
    "sg:classifiers":[
        {
            "category":"Professional",
            "subcategory":"Detective & Security Services",
            "type":"Services"
        }
    ],
    "sg:phone":"+1 218 879 9709",
    "sg:postcode":"55733",
    "sg:province":"MN",
    "sg:tags":[
        "information",
        "bureau"
    ],
    "wof:name":"Cloquet Emergency Service",
    "wof:placetype":"venue"
},
  "geometry": {"coordinates":[-92.343712,46.68768],"type":"Point"}
}