{
  "type": "Feature",
  "properties": {
    "addr:full":"14450 S Robert Trl # 101 Rosemount MN 55068",
    "addr:housenumber":"14450",
    "addr:postcode":"55068",
    "addr:street":"S Robert Trl # 101",
    "iso:country":"US",
    "sg:address":"14450 S Robert Trl # 101",
    "sg:city":"Rosemount",
    "sg:classifiers":[
        {
            "category":"Health Services",
            "subcategory":"Podiatrist",
            "type":"Services"
        }
    ],
    "sg:phone":"+1 651 322 7384",
    "sg:postcode":"55068",
    "sg:province":"MN",
    "sg:tags":[
        "equipment",
        "supply"
    ],
    "wof:name":"P & J Medical, Inc.",
    "wof:placetype":"venue"
},
  "geometry": {"coordinates":[-93.126091,44.739523],"type":"Point"}
}