{
  "type": "Feature",
  "properties": {
    "iso:country":"US",
    "sg:address":"12348 Drake St NW",
    "sg:city":"Coon Rapids",
    "sg:classifiers":[
        {
            "category":"Building & Trades",
            "subcategory":"Construction",
            "type":"Services"
        }
    ],
    "sg:phone":"+1 763 757 5707",
    "sg:postcode":"55448",
    "sg:province":"MN",
    "sg:tags":[
        "dry wall",
        "contractor"
    ],
    "wof:name":"Sterling Drywall",
    "wof:placetype":"venue"
},
  "geometry": {"coordinates":[-93.303775,45.193558],"type":"Point"}
}