{
  "type": "Feature",
  "properties": {
    "iso:country":"US",
    "sg:address":"14195 Bank St",
    "sg:city":"Becker",
    "sg:classifiers":[
        {
            "category":"Retail",
            "subcategory":"Auto Repair",
            "type":"Services"
        }
    ],
    "sg:phone":"+1 763 262 4441",
    "sg:postcode":"55308",
    "sg:province":"MN",
    "sg:tags":[
        "repairing",
        "automobile"
    ],
    "wof:name":"Becker Tire & Auto Ctr Inc",
    "wof:placetype":"venue"
},
  "geometry": {"coordinates":[-93.866604,45.387666],"type":"Point"}
}