{
  "type": "Feature",
  "properties": {
    "addr:full":"6551 Jansen Ave NE Albertville MN 55301",
    "addr:housenumber":"6551",
    "addr:postcode":"55301",
    "addr:street":"Jansen Ave Ne",
    "iso:country":"US",
    "sg:address":"6551 Jansen Ave NE",
    "sg:city":"Albertville",
    "sg:classifiers":[
        {
            "category":"Retail",
            "subcategory":"Repair Shop",
            "type":"Services"
        }
    ],
    "sg:phone":"+1 763 497 0183",
    "sg:postcode":"55301",
    "sg:province":"MN",
    "sg:tags":[
        "med",
        "medical",
        "retailer",
        "related",
        "equipment",
        "maintenance"
    ],
    "wof:name":"Midwest Science & Biocenter",
    "wof:placetype":"venue"
},
  "geometry": {"coordinates":[-93.688979,45.248278],"type":"Point"}
}