{
  "type": "Feature",
  "properties": {
    "addr:full":"13503 State Hwy 24 South Haven MN 55382",
    "addr:housenumber":"13503",
    "addr:postcode":"55382",
    "addr:street":"State Hwy 24;Haven",
    "iso:country":"US",
    "sg:address":"13503 State Hwy 24",
    "sg:city":"South Haven",
    "sg:classifiers":[
        {
            "category":"Manufacturing",
            "subcategory":"Tools & Machinery",
            "type":"Manufacturing & Wholesale Goods"
        }
    ],
    "sg:phone":"+1 320 274 8673",
    "sg:postcode":"55382",
    "sg:province":"MN",
    "sg:tags":[
        "farm",
        "mfg"
    ],
    "wof:name":"Peterson Products",
    "wof:placetype":"venue"
},
  "geometry": {"coordinates":[-94.07516,45.352205],"type":"Point"}
}