{
  "type": "Feature",
  "properties": {
    "addr:full":"600 Twelve Oaks Center Dr Dd Wayzata MN 55391",
    "addr:housenumber":"600",
    "addr:postcode":"55391",
    "addr:street":"Twelve;Center Dr",
    "iso:country":"US",
    "sg:address":"600 Twelve Oaks Center Dr Dd",
    "sg:city":"Wayzata",
    "sg:classifiers":[
        {
            "category":"Wholesale",
            "subcategory":"Non-durable Goods",
            "type":"Manufacturing & Wholesale Goods"
        },
        {
            "category":"Professional",
            "subcategory":"Business Services",
            "type":"Services"
        }
    ],
    "sg:phone":"+1 952 404 1421",
    "sg:postcode":"55391",
    "sg:province":"MN",
    "sg:tags":[
        "broker",
        "merchandise",
        "merchandise-wholesale"
    ],
    "wof:name":"Ndc Inc",
    "wof:placetype":"venue"
},
  "geometry": {"coordinates":[-93.474869,44.971542],"type":"Point"}
}