{
  "type": "Feature",
  "properties": {
    "addr:full":"15 Broadway Grand Marais MN 55604",
    "addr:housenumber":"15",
    "addr:postcode":"55604",
    "addr:street":"Broadway",
    "iso:country":"US",
    "sg:address":"15 Broadway",
    "sg:city":"Grand Marais",
    "sg:classifiers":[
        {
            "category":"Government",
            "subcategory":"Office",
            "type":"Public Place"
        }
    ],
    "sg:phone":"+1 218 387 1848",
    "sg:postcode":"55604",
    "sg:province":"MN",
    "sg:tags":[
        "govt",
        "city"
    ],
    "wof:name":"Grand Marais Utilities Comm",
    "wof:placetype":"venue"
},
  "geometry": {"coordinates":[-90.333184,47.748205],"type":"Point"}
}