{
  "type": "Feature",
  "properties": {
    "iso:country":"US",
    "sg:address":"1106 Minnesota Ave",
    "sg:city":"Duluth",
    "sg:classifiers":[
        {
            "category":"Building & Trades",
            "subcategory":"Construction",
            "type":"Services"
        }
    ],
    "sg:phone":"+1 218 727 5238",
    "sg:postcode":"55802",
    "sg:province":"MN",
    "sg:tags":[
        "house",
        "nonresidential"
    ],
    "wof:name":"Medlin Construction",
    "wof:placetype":"venue"
},
  "geometry": {"coordinates":[-92.089015,46.7721],"type":"Point"}
}