{
  "type": "Feature",
  "properties": {
    "addr:full":"43620 66th Avenue Way Kenyon MN 55946",
    "addr:housenumber":"43620",
    "addr:postcode":"55946",
    "addr:street":"66Th Avenue Way Kenyon",
    "iso:country":"US",
    "sg:address":"43620 66th Avenue Way",
    "sg:city":"Kenyon",
    "sg:phone":"+1 507 789 6660",
    "sg:postcode":"55946",
    "sg:province":"MN",
    "sg:tags":[
        "farm",
        "corn",
        "dairy",
        "soybean"
    ],
    "wof:name":"L Vangsness",
    "wof:placetype":"venue"
},
  "geometry": {"coordinates":[-92.902001,44.31927],"type":"Point"}
}