{
  "type": "Feature",
  "properties": {
    "addr:full":"310 Main St S Stillwater MN 55082",
    "addr:housenumber":"310",
    "addr:postcode":"55082",
    "addr:street":"Main St S",
    "iso:country":"US",
    "sg:address":"310 Main St S",
    "sg:city":"Stillwater",
    "sg:classifiers":[
        {
            "category":"Shopping",
            "type":"Retail Goods"
        }
    ],
    "sg:phone":"+1 651 439 6246",
    "sg:postcode":"55082",
    "sg:province":"MN",
    "sg:tags":[
        "art",
        "gallery",
        "merchandise",
        "dealer"
    ],
    "wof:name":"Kelley Frame & Fine Art Gllry",
    "wof:placetype":"venue"
},
  "geometry": {"coordinates":[-92.80535999999999,45.054527],"type":"Point"}
}