{
  "type": "Feature",
  "properties": {
    "addr:full":"4005 W 65th St Minneapolis MN 55435",
    "addr:housenumber":"4005",
    "addr:postcode":"55435",
    "addr:street":"W 65Th St",
    "iso:country":"US",
    "sg:address":"4005 W 65th St",
    "sg:city":"Minneapolis",
    "sg:classifiers":[
        {
            "category":"Social Services",
            "type":"Services"
        }
    ],
    "sg:phone":"+1 952 929 1819",
    "sg:postcode":"55435",
    "sg:province":"MN",
    "sg:tags":[
        "counselor",
        "marriage",
        "family"
    ],
    "wof:name":"Nicky Bredeson & Assoc",
    "wof:placetype":"venue"
},
  "geometry": {"coordinates":[-93.33335700000001,44.886051],"type":"Point"}
}