{
  "type": "Feature",
  "properties": {
    "iso:country":"US",
    "sg:address":"434 E Lyndale Ave N Ste 100",
    "sg:city":"Minneapolis",
    "sg:classifiers":[
        {
            "category":"Manufacturing",
            "subcategory":"Paper Products",
            "type":"Manufacturing & Wholesale Goods"
        }
    ],
    "sg:phone":"+1 612 343 4300",
    "sg:postcode":"55405",
    "sg:province":"MN",
    "sg:tags":[
        "products-wholesale",
        "manufacturer"
    ],
    "wof:name":"Litin Everything Party-n-Paper",
    "wof:placetype":"venue"
},
  "geometry": {"coordinates":[-93.28687600000001,44.982142],"type":"Point"}
}