{
  "type": "Feature",
  "properties": {
    "iso:country":"US",
    "sg:address":"1240 W 98th St",
    "sg:city":"Minneapolis",
    "sg:classifiers":[
        {
            "category":"Wholesale",
            "subcategory":"Furniture",
            "type":"Manufacturing & Wholesale Goods"
        }
    ],
    "sg:phone":"+1 952 854 2348",
    "sg:postcode":"55431",
    "sg:province":"MN",
    "wof:name":"Furniture Distributors",
    "wof:placetype":"venue"
},
  "geometry": {"coordinates":[-93.296251,44.826378],"type":"Point"}
}