{
  "type": "Feature",
  "properties": {
    "addr:full":"162 41st St Hills MN 56144",
    "addr:housenumber":"162",
    "addr:postcode":"56144",
    "addr:street":"41St St",
    "iso:country":"US",
    "sg:address":"162 41st St",
    "sg:city":"Hills",
    "sg:classifiers":[
        {
            "category":"Farming",
            "subcategory":"Dairy Farm",
            "type":"Manufacturing & Wholesale Goods"
        }
    ],
    "sg:phone":"+1 507 962 3402",
    "sg:postcode":"56144",
    "sg:province":"MN",
    "sg:tags":[
        "hog",
        "beef",
        "corn",
        "cattle",
        "or",
        "feedlot"
    ],
    "wof:name":"Boeve Partnership",
    "wof:placetype":"venue"
},
  "geometry": {"coordinates":[-96.43488000000001,43.907365],"type":"Point"}
}