{
  "type": "Feature",
  "properties": {
    "addr:full":"32257 Co Rd 21 Browerville MN 56438",
    "addr:housenumber":"21",
    "addr:postcode":"32257;56438",
    "addr:street":"Co Rd",
    "iso:country":"US",
    "sg:address":"32257 Co Rd 21",
    "sg:city":"Browerville",
    "sg:classifiers":[
        {
            "category":"Wholesale",
            "subcategory":"Meat",
            "type":"Manufacturing & Wholesale Goods"
        }
    ],
    "sg:phone":"+1 320 594 6560",
    "sg:postcode":"56438",
    "sg:province":"MN",
    "sg:tags":[
        "packer"
    ],
    "wof:name":"Riverside Meats & Processing",
    "wof:placetype":"venue"
},
  "geometry": {"coordinates":[-94.865236,46.096962],"type":"Point"}
}