{
  "type": "Feature",
  "properties": {
    "addr:full":"23223 Kodak Ave Wabasso MN 56293",
    "addr:postcode":"23223;56293",
    "addr:street":"Kodak Ave",
    "iso:country":"US",
    "sg:address":"23223 Kodak Ave",
    "sg:city":"Wabasso",
    "sg:classifiers":[
        {
            "category":"Freight",
            "type":"Transportation"
        },
        {
            "category":"Wholesale",
            "subcategory":"Farm Supplies",
            "type":"Manufacturing & Wholesale Goods"
        }
    ],
    "sg:phone":"+1 507 342 5189",
    "sg:postcode":"56293",
    "sg:province":"MN",
    "sg:tags":[
        "grain",
        "elevator"
    ],
    "wof:name":"Rowena Community Elevator",
    "wof:placetype":"venue"
},
  "geometry": {"coordinates":[-95.153774,44.388476],"type":"Point"}
}