{
  "type": "Feature",
  "properties": {
    "addr:full":"6963 Kenmare Dr Minneapolis MN 55438",
    "addr:housenumber":"6963",
    "addr:postcode":"55438",
    "addr:street":"Kenmare Dr",
    "iso:country":"US",
    "sg:address":"6963 Kenmare Dr",
    "sg:city":"Minneapolis",
    "sg:classifiers":[
        {
            "category":"Banks & Credit Unions",
            "subcategory":"Investment Brokerage",
            "type":"Services"
        }
    ],
    "sg:phone":"+1 952 944 2835",
    "sg:postcode":"55438",
    "sg:province":"MN",
    "sg:tags":[
        "security"
    ],
    "wof:name":"Elftmann Family Ltd Partn",
    "wof:placetype":"venue"
},
  "geometry": {"coordinates":[-93.37524500000001,44.795774],"type":"Point"}
}