{
  "type": "Feature",
  "properties": {
    "addr:full":"1008 Davis Ave Gibbon MN 55335",
    "addr:housenumber":"1008",
    "addr:postcode":"55335",
    "addr:street":"Davis Ave",
    "iso:country":"US",
    "sg:address":"1008 Davis Ave",
    "sg:city":"Gibbon",
    "sg:classifiers":[
        {
            "category":"Retail",
            "subcategory":"Auto Repair",
            "type":"Services"
        }
    ],
    "sg:phone":"+1 507 834 6820",
    "sg:postcode":"55335",
    "sg:province":"MN",
    "sg:tags":[
        "body",
        "automobile",
        "painting"
    ],
    "wof:name":"Steve's Body Shop",
    "wof:placetype":"venue"
},
  "geometry": {"coordinates":[-94.521451,44.533195],"type":"Point"}
}