{
  "type": "Feature",
  "properties": {
    "iso:country":"US",
    "sg:address":"18030 State Hwy 7",
    "sg:city":"New Germany",
    "sg:classifiers":[
        {
            "category":"Farming",
            "subcategory":"Dairy Farm",
            "type":"Manufacturing & Wholesale Goods"
        }
    ],
    "sg:phone":"+1 952 353 2131",
    "sg:postcode":"55367",
    "sg:province":"MN",
    "wof:name":"Kubasch Farms",
    "wof:placetype":"venue"
},
  "geometry": {"coordinates":[-93.982753,44.906566],"type":"Point"}
}