{
  "type": "Feature",
  "properties": {
    "addr:full":"1903 W Pinehurst Ave Saint Paul MN 55116",
    "addr:housenumber":"1903",
    "addr:postcode":"55116",
    "addr:street":"W Pinehurst Ave",
    "iso:country":"US",
    "sg:address":"1903 W Pinehurst Ave",
    "sg:city":"Saint Paul",
    "sg:classifiers":[
        {
            "category":"Professional",
            "subcategory":"Management & Consulting",
            "type":"Services"
        }
    ],
    "sg:phone":"+1 651 698 5852",
    "sg:postcode":"55116",
    "sg:province":"MN",
    "sg:tags":[
        "environmental",
        "health",
        "safety"
    ],
    "wof:name":"Environmental Health & Safety",
    "wof:placetype":"venue"
},
  "geometry": {"coordinates":[-93.177199,44.918859],"type":"Point"}
}