{
  "type": "Feature",
  "properties": {
    "iso:country":"US",
    "sg:address":"13 W Main St",
    "sg:city":"Kasson",
    "sg:classifiers":[
        {
            "category":"Professional",
            "subcategory":"Detective & Security Services",
            "type":"Services"
        }
    ],
    "sg:phone":"+1 507 634 3210",
    "sg:postcode":"55944",
    "sg:province":"MN",
    "sg:tags":[
        "investigator"
    ],
    "wof:name":"Spriggle Private Investigation",
    "wof:placetype":"venue"
},
  "geometry": {"coordinates":[-92.74829099999999,44.029581],"type":"Point"}
}