{
  "type": "Feature",
  "properties": {
    "addr:full":"6328 7th St N Saint Paul MN 55128",
    "addr:housenumber":"6328",
    "addr:postcode":"55128",
    "addr:street":"7Th St N",
    "iso:country":"US",
    "sg:address":"6328 7th St N",
    "sg:city":"Saint Paul",
    "sg:classifiers":[
        {
            "category":"Manufacturing",
            "subcategory":"Tools & Machinery",
            "type":"Manufacturing & Wholesale Goods"
        }
    ],
    "sg:phone":"+1 651 739 6384",
    "sg:postcode":"55128",
    "sg:province":"MN",
    "sg:tags":[
        "electrical",
        "mfg"
    ],
    "wof:name":"Xebec Electronics Co",
    "wof:placetype":"venue"
},
  "geometry": {"coordinates":[-92.977577,44.959126],"type":"Point"}
}