{
  "type": "Feature",
  "properties": {
    "iso:country":"US",
    "sg:address":"311 10th Ave NE",
    "sg:city":"Brainerd",
    "sg:classifiers":[
        {
            "category":"Education",
            "subcategory":"School",
            "type":"Public Place"
        }
    ],
    "sg:phone":"+1 218 829 2915",
    "sg:postcode":"56401",
    "sg:province":"MN",
    "wof:name":"Area Education Ctr",
    "wof:placetype":"venue"
},
  "geometry": {"coordinates":[-94.174548,46.362096],"type":"Point"}
}