{
  "type": "Feature",
  "properties": {
    "iso:country":"US",
    "sg:address":"601 Park St S",
    "sg:city":"Fairfax",
    "sg:classifiers":[
        {
            "category":"Retail",
            "subcategory":"Funeral Services",
            "type":"Services"
        }
    ],
    "sg:phone":"+1 507 426 7274",
    "sg:postcode":"55332",
    "sg:province":"MN",
    "sg:tags":[
        "director"
    ],
    "wof:name":"Hauser-Hantge Funeral Home",
    "wof:placetype":"venue"
},
  "geometry": {"coordinates":[-94.720662,44.525624],"type":"Point"}
}