{
  "type": "Feature",
  "properties": {
    "addr:full":"2100 E Hennepin Ave Minneapolis MN 55413",
    "addr:housenumber":"2100",
    "addr:postcode":"55413",
    "addr:street":"E Hennepin Ave",
    "iso:country":"US",
    "sg:address":"2100 E Hennepin Ave",
    "sg:city":"Minneapolis",
    "sg:classifiers":[
        {
            "category":"Autos & Motor Vehicles",
            "subcategory":"Fuel & Gas Station",
            "type":"Retail Goods"
        }
    ],
    "sg:phone":"+1 612 331 4295",
    "sg:postcode":"55413",
    "sg:province":"MN",
    "sg:tags":[
        "repair",
        "oil",
        "gasoline",
        "automotive"
    ],
    "wof:name":"East Hennepin Auto Service Inc",
    "wof:placetype":"venue"
},
  "geometry": {"coordinates":[-93.222397,44.991402],"type":"Point"}
}