{
  "type": "Feature",
  "properties": {
    "addr:full":"809 1st St E Park Rapids MN 56470",
    "addr:housenumber":"809",
    "addr:postcode":"56470",
    "addr:street":"1St St E",
    "iso:country":"US",
    "sg:address":"809 1st St E",
    "sg:city":"Park Rapids",
    "sg:classifiers":[
        {
            "category":"Restaurant",
            "type":"Food & Drink"
        },
        {
            "category":"Ice Cream",
            "type":"Food & Drink"
        }
    ],
    "sg:menulink":"http://www.allmenus.com/mn/park-rapids/168358-dairy-queen/menu/",
    "sg:phone":"+1 218 732 5947",
    "sg:postcode":"56470",
    "sg:province":"MN",
    "sg:tags":[
        "burger",
        "american",
        "ice",
        "cream"
    ],
    "wof:name":"Dairy Queen",
    "wof:placetype":"venue"
},
  "geometry": {"coordinates":[-95.04753100000001,46.922203],"type":"Point"}
}