{
  "type": "Feature",
  "properties": {
    "iso:country":"US",
    "sg:address":"339 8th St NW",
    "sg:city":"New Brighton",
    "sg:classifiers":[
        {
            "category":"Travel",
            "subcategory":"Travel Agent",
            "type":"Entertainment"
        }
    ],
    "sg:phone":"+1 612 781 3438",
    "sg:postcode":"55112",
    "sg:province":"MN",
    "sg:tags":[
        "bureau",
        "passenger",
        "agency",
        "transportation",
        "arrangement"
    ],
    "wof:name":"All Star Travel Inc",
    "wof:placetype":"venue"
},
  "geometry": {"coordinates":[-93.191503,45.062711],"type":"Point"}
}