{
  "type": "Feature",
  "properties": {
    "addr:full":"56 5th Ave St Paul MN 55128",
    "addr:housenumber":"56",
    "addr:postcode":"55128",
    "addr:street":"5Th Ave",
    "iso:country":"US",
    "sg:address":"56 5th Ave",
    "sg:city":"St Paul",
    "sg:classifiers":[
        {
            "category":"Restaurant",
            "type":"Food & Drink"
        }
    ],
    "sg:phone":"+1 651 225 4300",
    "sg:postcode":"55128",
    "sg:province":"MN",
    "wof:name":"Zantigo Mexican American",
    "wof:placetype":"venue"
},
  "geometry": {"coordinates":[-92.973955,44.952024],"type":"Point"}
}