{
  "type": "Feature",
  "properties": {
    "iso:country":"US",
    "sg:address":"113 W 1st St",
    "sg:city":"Duluth",
    "sg:classifiers":[
        {
            "category":"Bars & Pubs",
            "type":"Food & Drink"
        }
    ],
    "sg:phone":"+1 218 722 2905",
    "sg:postcode":"55802",
    "sg:province":"MN",
    "sg:tags":[
        "bar"
    ],
    "wof:name":"Norman's Bar",
    "wof:placetype":"venue"
},
  "geometry": {"coordinates":[-92.100568,46.786673],"type":"Point"}
}