{
  "type": "Feature",
  "properties": {
    "iso:country":"US",
    "sg:address":"28901 109th Ave N",
    "sg:city":"Hanover",
    "sg:classifiers":[
        {
            "category":"Real Estate",
            "subcategory":"Real Estate Operator",
            "type":"Services"
        }
    ],
    "sg:phone":"+1 763 498 8774",
    "sg:postcode":"55341",
    "sg:province":"MN",
    "sg:tags":[
        "property",
        "lessor"
    ],
    "wof:name":"Kottke Gerhard",
    "wof:placetype":"venue"
},
  "geometry": {"coordinates":[-93.64859300000001,45.152404],"type":"Point"}
}