{
  "type": "Feature",
  "properties": {
    "addr:full":"23633 410th St Belview MN 56214",
    "addr:housenumber":"23633",
    "addr:postcode":"56214",
    "addr:street":"410Th St",
    "iso:country":"US",
    "sg:address":"23633 410th St",
    "sg:city":"Belview",
    "sg:classifiers":[
        {
            "category":"Place Of Worship",
            "subcategory":"Church",
            "type":"Public Place"
        },
        {
            "category":"Place Of Worship",
            "type":"Public Place"
        }
    ],
    "sg:phone":"+1 507 938 4235",
    "sg:postcode":"56214",
    "sg:province":"MN",
    "sg:tags":[
        "lutheran",
        "america",
        "churches-lutheran",
        "churches-lutheran-evangelical"
    ],
    "wof:name":"Rock Dell Lutheran Church",
    "wof:placetype":"venue"
},
  "geometry": {"coordinates":[-95.308628,44.64324],"type":"Point"}
}