{
  "type": "Feature",
  "properties": {
    "addr:full":"209 3rd St W Brandon MN 56315",
    "addr:housenumber":"209",
    "addr:postcode":"56315",
    "addr:street":"3Rd St W",
    "iso:country":"US",
    "sg:address":"209 3rd St W",
    "sg:city":"Brandon",
    "sg:classifiers":[
        {
            "category":"Social Services",
            "subcategory":"Child Care",
            "type":"Services"
        }
    ],
    "sg:phone":"+1 320 834 4764",
    "sg:postcode":"56315",
    "sg:province":"MN",
    "sg:tags":[
        "daycare",
        "provider"
    ],
    "wof:name":"Cheryl Gebhardt",
    "wof:placetype":"venue"
},
  "geometry": {"coordinates":[-95.600492,45.967081],"type":"Point"}
}