{
  "type": "Feature",
  "properties": {
    "addr:full":"616 Frontier Dr Fergus Falls MN 56537",
    "addr:housenumber":"616",
    "addr:postcode":"56537",
    "addr:street":"Frontier Dr",
    "iso:country":"US",
    "sg:address":"616 Frontier Dr",
    "sg:city":"Fergus Falls",
    "sg:classifiers":[
        {
            "category":"Shopping",
            "subcategory":"Bicycles & Sporting Goods",
            "type":"Retail Goods"
        }
    ],
    "sg:phone":"+1 218 736 4531",
    "sg:postcode":"56537",
    "sg:province":"MN",
    "wof:name":"Minnesota Guns Accessories",
    "wof:placetype":"venue"
},
  "geometry": {"coordinates":[-96.121583,46.294936],"type":"Point"}
}