{
  "type": "Feature",
  "properties": {
    "iso:country":"US",
    "sg:address":"624 Fuller Ave",
    "sg:city":"St Paul",
    "sg:classifiers":[
        {
            "category":"Professional",
            "type":"Services"
        }
    ],
    "sg:phone":"+1 612 978 8629",
    "sg:postcode":"55104",
    "sg:province":"MN",
    "sg:tags":[
        "establishment"
    ],
    "wof:name":"Hmong Union",
    "wof:placetype":"venue"
},
  "geometry": {"coordinates":[-93.12875099999999,44.953846],"type":"Point"}
}