{
  "type": "Feature",
  "properties": {
    "iso:country":"US",
    "sg:address":"3960 Minnehaha Ave",
    "sg:city":"Minneapolis",
    "sg:classifiers":[
        {
            "category":"Communications",
            "subcategory":"Film & Video Production",
            "type":"Services"
        }
    ],
    "sg:phone":"+1 612 722 3109",
    "sg:postcode":"55406",
    "sg:province":"MN",
    "sg:tags":[
        "motion",
        "picture"
    ],
    "wof:name":"David M Jacobs",
    "wof:placetype":"venue"
},
  "geometry": {"coordinates":[-93.22192800000001,44.931617],"type":"Point"}
}