{
  "type": "Feature",
  "properties": {
    "iso:country":"US",
    "sg:address":"1834 3rd Ave",
    "sg:city":"Newport",
    "sg:classifiers":[
        {
            "category":"Building & Trades",
            "subcategory":"Construction",
            "type":"Services"
        }
    ],
    "sg:phone":"+1 651 768 9191",
    "sg:postcode":"55055",
    "sg:province":"MN",
    "sg:tags":[
        "resurfacing",
        "laying",
        "refinishing",
        "floor"
    ],
    "wof:name":"Grace & Glory Hardwood Floors",
    "wof:placetype":"venue"
},
  "geometry": {"coordinates":[-93.00561999999999,44.877255],"type":"Point"}
}