{
  "type": "Feature",
  "properties": {
    "addr:full":"532 Apollo Dr Circle Pines MN 55014",
    "addr:housenumber":"532",
    "addr:postcode":"55014",
    "addr:street":"Apollo Dr Circle",
    "iso:country":"US",
    "sg:address":"532 Apollo Dr",
    "sg:city":"Circle Pines",
    "sg:classifiers":[
        {
            "category":"Manufacturing",
            "subcategory":"Tools & Machinery",
            "type":"Manufacturing & Wholesale Goods"
        },
        {
            "category":"Wholesale",
            "subcategory":"Electrical",
            "type":"Manufacturing & Wholesale Goods"
        }
    ],
    "sg:phone":"+1 763 780 9599",
    "sg:postcode":"55014",
    "sg:province":"MN",
    "sg:tags":[
        "shop",
        "job",
        "laser"
    ],
    "wof:name":"Laser & Cutting Technology Inc",
    "wof:placetype":"venue"
},
  "geometry": {"coordinates":[-93.11739799999999,45.18009],"type":"Point"}
}