{
  "type": "Feature",
  "properties": {
    "addr:full":"1212 Locust St Farmington MN 55024",
    "addr:housenumber":"1212",
    "addr:postcode":"55024",
    "addr:street":"Locust St",
    "iso:country":"US",
    "sg:address":"1212 Locust St",
    "sg:city":"Farmington",
    "sg:classifiers":[
        {
            "category":"Professional",
            "subcategory":"Accounting & Tax Preparation",
            "type":"Services"
        }
    ],
    "sg:phone":"+1 651 463 1346",
    "sg:postcode":"55024",
    "sg:province":"MN",
    "sg:tags":[
        "bookkeeping",
        "billing"
    ],
    "wof:name":"Akin Administrative",
    "wof:placetype":"venue"
},
  "geometry": {"coordinates":[-93.130056,44.63552],"type":"Point"}
}