{
  "type": "Feature",
  "properties": {
    "addr:full":"38753 260th Ave Freeport MN 56331",
    "addr:housenumber":"38753",
    "addr:postcode":"56331",
    "addr:street":"260Th Ave",
    "iso:country":"US",
    "sg:address":"38753 260th Ave",
    "sg:city":"Freeport",
    "sg:classifiers":[
        {
            "category":"Farming",
            "subcategory":"Farm",
            "type":"Manufacturing & Wholesale Goods"
        }
    ],
    "sg:phone":"+1 320 836 2956",
    "sg:postcode":"56331",
    "sg:province":"MN",
    "sg:tags":[
        "crop",
        "general"
    ],
    "wof:name":"Don Schmidt",
    "wof:placetype":"venue"
},
  "geometry": {"coordinates":[-94.65445099999999,45.686701],"type":"Point"}
}