{
  "type": "Feature",
  "properties": {
    "addr:full":"19175 Vine Ridge Ct Excelsior MN 55331",
    "addr:housenumber":"19175",
    "addr:postcode":"55331",
    "addr:street":"Vine Ridge Ct",
    "iso:country":"US",
    "sg:address":"19175 Vine Ridge Ct",
    "sg:city":"Excelsior",
    "sg:classifiers":[
        {
            "category":"Professional",
            "subcategory":"Management & Consulting",
            "type":"Services"
        }
    ],
    "sg:phone":"+1 952 474 8065",
    "sg:postcode":"55331",
    "sg:province":"MN",
    "wof:name":"Workforce Strategies LLC",
    "wof:placetype":"venue"
},
  "geometry": {"coordinates":[-93.52528700000001,44.913761],"type":"Point"}
}