{
  "type": "Feature",
  "properties": {
    "addr:full":"3650 Colfax Ave S Minneapolis MN 55409",
    "addr:housenumber":"3650",
    "addr:postcode":"55409",
    "addr:street":"Colfax Ave S",
    "iso:country":"US",
    "sg:address":"3650 Colfax Ave S",
    "sg:city":"Minneapolis",
    "sg:classifiers":[
        {
            "category":"Retail",
            "subcategory":"Repair Shop",
            "type":"Services"
        }
    ],
    "sg:phone":"+1 952 496 1797",
    "sg:postcode":"55409",
    "sg:province":"MN",
    "wof:name":"Quality Asrn & Calibration Co",
    "wof:placetype":"venue"
},
  "geometry": {"coordinates":[-93.292125,44.936824],"type":"Point"}
}