{
  "type": "Feature",
  "properties": {
    "addr:full":"11961 Noon Dr Dayton MN 55327",
    "addr:postcode":"11961;55327",
    "addr:street":"Noon Dr",
    "iso:country":"US",
    "sg:address":"11961 Noon Dr",
    "sg:city":"Dayton",
    "sg:classifiers":[
        {
            "category":"Education",
            "subcategory":"Special Training",
            "type":"Public Place"
        }
    ],
    "sg:phone":"+1 763 323 0204",
    "sg:postcode":"55327",
    "sg:province":"MN",
    "wof:name":"Twin Cities Visalia Club",
    "wof:placetype":"venue"
},
  "geometry": {"coordinates":[-93.433049,45.204807],"type":"Point"}
}