{
  "type": "Feature",
  "properties": {
    "addr:full":"14710 State Hwy 19 Welch MN 55089",
    "addr:housenumber":"14710",
    "addr:postcode":"55089",
    "addr:street":"State Hwy 19",
    "iso:country":"US",
    "sg:address":"14710 State Hwy 19",
    "sg:city":"Welch",
    "sg:classifiers":[
        {
            "category":"Professional",
            "type":"Services"
        }
    ],
    "sg:phone":"+1 651 258 4013",
    "sg:postcode":"55089",
    "sg:province":"MN",
    "wof:name":"Vasa Gardens",
    "wof:placetype":"venue"
},
  "geometry": {"coordinates":[-92.738417,44.505121],"type":"Point"}
}