{
  "type": "Feature",
  "properties": {
    "addr:full":"610 Cleveland Ave SE Saint Paul MN 55112",
    "addr:housenumber":"610",
    "addr:postcode":"55112",
    "addr:street":"Cleveland Ave Se",
    "iso:country":"US",
    "sg:address":"610 Cleveland Ave SE",
    "sg:city":"Saint Paul",
    "sg:classifiers":[
        {
            "category":"Professional",
            "subcategory":"Business Services",
            "type":"Services"
        }
    ],
    "sg:phone":"+1 651 639 0456",
    "sg:postcode":"55112",
    "sg:province":"MN",
    "wof:name":"Pro Tech Fitness Co",
    "wof:placetype":"venue"
},
  "geometry": {"coordinates":[-93.18778500000001,45.040066],"type":"Point"}
}