{
  "type": "Feature",
  "properties": {
    "iso:country":"US",
    "sg:address":"11735 50th Pl N",
    "sg:city":"Minneapolis",
    "sg:classifiers":[
        {
            "category":"Shopping",
            "subcategory":"Beauty & Cosmetics",
            "type":"Retail Goods"
        }
    ],
    "sg:phone":"+1 763 553 1377",
    "sg:postcode":"55442",
    "sg:province":"MN",
    "sg:tags":[
        "salons-equipment",
        "merchandise",
        "supply"
    ],
    "wof:name":"Jacquelyn Radichel",
    "wof:placetype":"venue"
},
  "geometry": {"coordinates":[-93.428169,45.045747],"type":"Point"}
}