{
  "type": "Feature",
  "properties": {
    "addr:full":"733 Sanford St Red Wing MN 55066",
    "addr:housenumber":"733",
    "addr:postcode":"55066",
    "addr:street":"Sanford St",
    "iso:country":"US",
    "sg:address":"733 Sanford St",
    "sg:city":"Red Wing",
    "sg:classifiers":[
        {
            "category":"Professional",
            "type":"Services"
        }
    ],
    "sg:phone":"+1 651 388 7510",
    "sg:postcode":"55066",
    "sg:province":"MN",
    "wof:name":"Indented Line LLC",
    "wof:placetype":"venue"
},
  "geometry": {"coordinates":[-92.53417399999999,44.556187],"type":"Point"}
}