{
  "type": "Feature",
  "properties": {
    "addr:full":"5930 Afton Rd Excelsior MN 55331",
    "addr:housenumber":"5930",
    "addr:postcode":"55331",
    "addr:street":"Afton Rd",
    "iso:country":"US",
    "sg:address":"5930 Afton Rd",
    "sg:city":"Excelsior",
    "sg:classifiers":[
        {
            "category":"Retail",
            "subcategory":"Laundry & Dry Cleaning",
            "type":"Services"
        },
        {
            "category":"Home & Garden",
            "subcategory":"Carpets & Floor Coverings",
            "type":"Retail Goods"
        }
    ],
    "sg:phone":"+1 952 474 2095",
    "sg:postcode":"55331",
    "sg:province":"MN",
    "sg:tags":[
        "repairing",
        "repair",
        "rug"
    ],
    "wof:name":"Twin City Interiors Inc",
    "wof:placetype":"venue"
},
  "geometry": {"coordinates":[-93.621911,44.896386],"type":"Point"}
}