{
  "type": "Feature",
  "properties": {
    "addr:full":"10792 143rd Ave SE Becker MN 55308",
    "addr:housenumber":"10792",
    "addr:postcode":"55308",
    "addr:street":"143Rd Ave Se",
    "iso:country":"US",
    "sg:address":"10792 143rd Ave SE",
    "sg:city":"Becker",
    "sg:classifiers":[
        {
            "category":"Real Estate",
            "subcategory":"Real Estate Operator",
            "type":"Services"
        }
    ],
    "sg:phone":"+1 612 221 1995",
    "sg:postcode":"55308",
    "sg:province":"MN",
    "sg:tags":[
        "apartment"
    ],
    "wof:name":"Woodview Homes Inc",
    "wof:placetype":"venue"
},
  "geometry": {"coordinates":[-93.86444899999999,45.414445],"type":"Point"}
}