{
  "type": "Feature",
  "properties": {
    "iso:country":"US",
    "sg:address":"5909 Portland Ave S",
    "sg:city":"Minneapolis",
    "sg:classifiers":[
        {
            "category":"Health Services",
            "subcategory":"Doctor",
            "type":"Services"
        }
    ],
    "sg:phone":"+1 612 861 1679",
    "sg:postcode":"55417",
    "sg:province":"MN",
    "wof:name":"Dinh Quan DDS",
    "wof:placetype":"venue"
},
  "geometry": {"coordinates":[-93.26771599999999,44.894383],"type":"Point"}
}