{
  "type": "Feature",
  "properties": {
    "iso:country":"US",
    "sg:address":"515 Central Ave N",
    "sg:city":"Faribault",
    "sg:classifiers":[
        {
            "category":"Retail",
            "subcategory":"Auto Repair",
            "type":"Services"
        }
    ],
    "sg:phone":"+1 507 333 0086",
    "sg:postcode":"55021",
    "sg:province":"MN",
    "sg:tags":[
        "general"
    ],
    "wof:name":"Herr Auto Repair",
    "wof:placetype":"venue"
},
  "geometry": {"coordinates":[-93.26834700000001,44.29685],"type":"Point"}
}