{
  "type": "Feature",
  "properties": {
    "iso:country":"US",
    "sg:address":"114 S 65th Ave W",
    "sg:city":"Duluth",
    "sg:classifiers":[
        {
            "category":"Professional",
            "subcategory":"Management & Consulting",
            "type":"Services"
        }
    ],
    "sg:phone":"+1 218 628 0164",
    "sg:postcode":"55807",
    "sg:province":"MN",
    "sg:tags":[
        "business"
    ],
    "wof:name":"Soho Duluth LLC",
    "wof:placetype":"venue"
},
  "geometry": {"coordinates":[-92.179992,46.731475],"type":"Point"}
}