{
  "type": "Feature",
  "properties": {
    "addr:full":"731 3rd St S Virginia MN 55792",
    "addr:housenumber":"731",
    "addr:postcode":"55792",
    "addr:street":"3Rd St S",
    "iso:country":"US",
    "sg:address":"731 3rd St S",
    "sg:city":"Virginia",
    "sg:classifiers":[
        {
            "category":"Health Services",
            "subcategory":"Nursing And Care Facility",
            "type":"Services"
        }
    ],
    "sg:phone":"+1 218 741 9630",
    "sg:postcode":"55792",
    "sg:province":"MN",
    "sg:tags":[
        "home",
        "convalescent",
        "intermediate"
    ],
    "sg:website":"http://www.merritthousemn.com",
    "wof:name":"Merritt House",
    "wof:placetype":"venue"
},
  "geometry": {"coordinates":[-92.54296600000001,47.520392],"type":"Point"}
}