{
  "type": "Feature",
  "properties": {
    "addr:full":"3904 Grand Ave Duluth MN 55807",
    "addr:housenumber":"3904",
    "addr:postcode":"55807",
    "addr:street":"Grand Ave",
    "iso:country":"US",
    "sg:address":"3904 Grand Ave",
    "sg:city":"Duluth",
    "sg:classifiers":[
        {
            "category":"Food & Beverages",
            "subcategory":"Liquor & Beverages",
            "type":"Retail Goods"
        }
    ],
    "sg:phone":"+1 218 728 2900",
    "sg:postcode":"55807",
    "sg:province":"MN",
    "wof:name":"Sportsmen's Liquor",
    "wof:placetype":"venue"
},
  "geometry": {"coordinates":[-92.15116399999999,46.75158],"type":"Point"}
}