{
  "type": "Feature",
  "properties": {
    "iso:country":"US",
    "sg:address":"601 Grant Ave",
    "sg:city":"Eveleth",
    "sg:classifiers":[
        {
            "category":"Social Services",
            "type":"Services"
        }
    ],
    "sg:phone":"+1 218 744 2421",
    "sg:postcode":"55734",
    "sg:province":"MN",
    "wof:name":"Spectrum Health",
    "wof:placetype":"venue"
},
  "geometry": {"coordinates":[-92.540193,47.466032],"type":"Point"}
}