{
  "type": "Feature",
  "properties": {
    "iso:country":"US",
    "sg:address":"500 S 59th Ave W 500",
    "sg:city":"Duluth",
    "sg:classifiers":[
        {
            "category":"Shopping",
            "subcategory":"Gifts & Souvenirs",
            "type":"Retail Goods"
        },
        {
            "category":"Manufacturing",
            "subcategory":"Paper Products",
            "type":"Manufacturing & Wholesale Goods"
        }
    ],
    "sg:phone":"+1 218 624 8945",
    "sg:postcode":"55807",
    "sg:province":"MN",
    "sg:tags":[
        "packaging",
        "materials-wholesale",
        "material",
        "wrapping",
        "manufacturer"
    ],
    "sg:website":"http://www.voidfillers.com",
    "wof:name":"Superior Packaging Company",
    "wof:placetype":"venue"
},
  "geometry": {"coordinates":[-92.171967,46.727589],"type":"Point"}
}