{
  "type": "Feature",
  "properties": {
    "addr:full":"7828 Market Blvd Chanhassen MN 55317",
    "addr:housenumber":"7828",
    "addr:postcode":"55317",
    "addr:street":"Market Blvd",
    "iso:country":"US",
    "sg:address":"7828 Market Blvd",
    "sg:city":"Chanhassen",
    "sg:classifiers":[
        {
            "category":"Personal",
            "subcategory":"Beauty Salon",
            "type":"Services"
        }
    ],
    "sg:phone":"+1 952 915 2900",
    "sg:postcode":"55317",
    "sg:province":"MN",
    "sg:tags":[
        "care",
        "skin"
    ],
    "wof:name":"Spalon Montage",
    "wof:placetype":"venue"
},
  "geometry": {"coordinates":[-93.538071,44.861431],"type":"Point"}
}