{
  "type": "Feature",
  "properties": {
    "addr:full":"206 S Broadway Ave Rochester MN 55904",
    "addr:housenumber":"206",
    "addr:postcode":"55904",
    "addr:street":"S Broadway Ave",
    "iso:country":"US",
    "sg:address":"206 S Broadway Ave",
    "sg:city":"Rochester",
    "sg:classifiers":[
        {
            "category":"Professional",
            "subcategory":"Lawyer & Legal Services",
            "type":"Services"
        }
    ],
    "sg:phone":"+1 507 529 2204",
    "sg:postcode":"55904",
    "sg:province":"MN",
    "sg:tags":[
        "attorney"
    ],
    "wof:name":"Law Office Rodney D Anderson",
    "wof:placetype":"venue"
},
  "geometry": {"coordinates":[-92.462953,44.020517],"type":"Point"}
}