{
  "type": "Feature",
  "properties": {
    "iso:country":"US",
    "sg:address":"3137 Hennepin Ave S",
    "sg:city":"Minneapolis",
    "sg:classifiers":[
        {
            "category":"Personal",
            "type":"Services"
        }
    ],
    "sg:phone":"+1 612 821 1416",
    "sg:postcode":"55408",
    "sg:province":"MN",
    "sg:tags":[
        "therapist",
        "massage"
    ],
    "wof:name":"Barbara Glommen Massage Thrpy",
    "wof:placetype":"venue"
},
  "geometry": {"coordinates":[-93.298238,44.945382],"type":"Point"}
}