{
  "type": "Feature",
  "properties": {
    "addr:full":"407 NW 1st Ave Grand Rapids MN 55744",
    "addr:housenumber":"407",
    "addr:postcode":"55744",
    "addr:street":"Nw 1St Ave",
    "iso:country":"US",
    "sg:address":"407 NW 1st Ave",
    "sg:city":"Grand Rapids",
    "sg:classifiers":[
        {
            "category":"Shopping",
            "subcategory":"Gifts & Souvenirs",
            "type":"Retail Goods"
        }
    ],
    "sg:phone":"+1 218 326 1707",
    "sg:postcode":"55744",
    "sg:province":"MN",
    "sg:tags":[
        "party",
        "supply"
    ],
    "wof:name":"Grand Celebrations",
    "wof:placetype":"venue"
},
  "geometry": {"coordinates":[-93.529954,47.235987],"type":"Point"}
}