{
  "type": "Feature",
  "properties": {
    "addr:full":"15020 Everleigh Cir Rosemount MN 55068",
    "addr:postcode":"15020;55068",
    "addr:street":"Everleigh Cir",
    "iso:country":"US",
    "sg:address":"15020 Everleigh Cir",
    "sg:city":"Rosemount",
    "sg:classifiers":[
        {
            "category":"Building & Trades",
            "subcategory":"Construction",
            "type":"Services"
        }
    ],
    "sg:phone":"+1 651 423 4850",
    "sg:postcode":"55068",
    "sg:province":"MN",
    "sg:tags":[
        "contractor"
    ],
    "wof:name":"D & B Cleaning",
    "wof:placetype":"venue"
},
  "geometry": {"coordinates":[-93.15511100000001,44.730814],"type":"Point"}
}