{
  "type": "Feature",
  "properties": {
    "addr:full":"720 E 7th St Duluth MN 55805",
    "addr:housenumber":"720",
    "addr:postcode":"55805",
    "addr:street":"E 7Th St",
    "iso:country":"US",
    "sg:address":"720 E 7th St",
    "sg:city":"Duluth",
    "sg:classifiers":[
        {
            "category":"Freight",
            "type":"Transportation"
        }
    ],
    "sg:phone":"+1 218 722 4206",
    "sg:postcode":"55805",
    "sg:province":"MN",
    "sg:tags":[
        "operator",
        "local",
        "trucking"
    ],
    "wof:name":"ABT Wilson Inc",
    "wof:placetype":"venue"
},
  "geometry": {"coordinates":[-92.09604400000001,46.799015],"type":"Point"}
}