{
  "type": "Feature",
  "properties": {
    "addr:full":"7965 Lost Lake Rd Nisswa MN 56468",
    "addr:housenumber":"7965",
    "addr:postcode":"56468",
    "addr:street":"Lost Lake Rd",
    "iso:country":"US",
    "sg:address":"7965 Lost Lake Rd",
    "sg:city":"Nisswa",
    "sg:classifiers":[
        {
            "category":"Travel",
            "subcategory":"Hotels & Motels",
            "type":"Entertainment"
        },
        {
            "category":"Travel",
            "subcategory":"Resort",
            "type":"Entertainment"
        }
    ],
    "sg:phone":"+1 218 963 2681",
    "sg:postcode":"56468",
    "sg:province":"MN",
    "sg:tags":[
        "lodging"
    ],
    "sg:website":"http://www.lostlake.com",
    "wof:name":"Lost Lake Lodge",
    "wof:placetype":"venue"
},
  "geometry": {"coordinates":[-94.340309,46.515356],"type":"Point"}
}