{
  "type": "Feature",
  "properties": {
    "addr:full":"11073 Hwy 37 Hibbing MN 55746",
    "addr:housenumber":"11073",
    "addr:postcode":"55746",
    "addr:street":"Hwy 37",
    "iso:country":"US",
    "sg:address":"11073 Hwy 37",
    "sg:city":"Hibbing",
    "sg:classifiers":[
        {
            "category":"Bars & Pubs",
            "type":"Food & Drink"
        }
    ],
    "sg:phone":"+1 218 263 9801",
    "sg:postcode":"55746",
    "sg:province":"MN",
    "sg:tags":[
        "drinking",
        "eating"
    ],
    "wof:name":"Airway Inn",
    "wof:placetype":"venue"
},
  "geometry": {"coordinates":[-92.845978,47.394406],"type":"Point"}
}