{
  "type": "Feature",
  "properties": {
    "addr:full":"29693 Co Rd 25 Browerville MN 56438",
    "addr:housenumber":"29693;25",
    "addr:postcode":"56438",
    "addr:street":"Co Rd",
    "iso:country":"US",
    "sg:address":"29693 Co Rd 25",
    "sg:city":"Browerville",
    "sg:phone":"+1 320 594 6033",
    "sg:postcode":"56438",
    "sg:province":"MN",
    "sg:tags":[
        "farm",
        "corn",
        "dairy"
    ],
    "wof:name":"Wayne & Gail Cartensen",
    "wof:placetype":"venue"
},
  "geometry": {"coordinates":[-94.81347700000001,46.066561],"type":"Point"}
}