{
  "type": "Feature",
  "properties": {
    "addr:full":"360 Garfield St S Cambridge MN 55008",
    "addr:housenumber":"360",
    "addr:postcode":"55008",
    "addr:street":"Garfield St S",
    "iso:country":"US",
    "sg:address":"360 Garfield St S",
    "sg:city":"Cambridge",
    "sg:classifiers":[
        {
            "category":"Personal",
            "subcategory":"Beauty Salon",
            "type":"Services"
        }
    ],
    "sg:phone":"+1 763 689 3202",
    "sg:postcode":"55008",
    "sg:province":"MN",
    "sg:tags":[
        "shop"
    ],
    "wof:name":"Hair Studio",
    "wof:placetype":"venue"
},
  "geometry": {"coordinates":[-93.213962,45.569535],"type":"Point"}
}