{
  "type": "Feature",
  "properties": {
    "iso:country":"US",
    "sg:address":"5100 Eden Ave Ste 102",
    "sg:city":"Minneapolis",
    "sg:classifiers":[
        {
            "category":"Insurance",
            "subcategory":"Hazard Insurance",
            "type":"Services"
        },
        {
            "category":"Banks & Credit Unions",
            "subcategory":"Bank",
            "type":"Services"
        }
    ],
    "sg:phone":"+1 952 928 0455",
    "sg:postcode":"55436",
    "sg:province":"MN",
    "sg:tags":[
        "commercial",
        "saving",
        "business"
    ],
    "sg:website":"http://statefarm.com",
    "wof:name":"Boockmeier Matt",
    "wof:placetype":"venue"
},
  "geometry": {"coordinates":[-93.35204299999999,44.909679],"type":"Point"}
}