{
  "type": "Feature",
  "properties": {
    "addr:full":"8693 SE 34th Ave Owatonna MN 55060",
    "addr:housenumber":"8693",
    "addr:postcode":"55060",
    "addr:street":"Se 34Th Ave",
    "iso:country":"US",
    "sg:address":"8693 SE 34th Ave",
    "sg:city":"Owatonna",
    "sg:classifiers":[
        {
            "category":"Building & Trades",
            "subcategory":"Plumbing",
            "type":"Services"
        }
    ],
    "sg:phone":"+1 507 451 9123",
    "sg:postcode":"55060",
    "sg:province":"MN",
    "sg:tags":[
        "contractor"
    ],
    "wof:name":"General Sprinkler Corp",
    "wof:placetype":"venue"
},
  "geometry": {"coordinates":[-93.165764,43.965564],"type":"Point"}
}