{
  "type": "Feature",
  "properties": {
    "addr:full":"541 43rd Ave NW Backus MN 56435",
    "addr:housenumber":"541",
    "addr:postcode":"56435",
    "addr:street":"43Rd Ave Nw Backus",
    "iso:country":"US",
    "sg:address":"541 43rd Ave NW",
    "sg:city":"Backus",
    "sg:classifiers":[
        {
            "category":"Social Services",
            "subcategory":"Child Care",
            "type":"Services"
        }
    ],
    "sg:phone":"+1 218 947 3571",
    "sg:postcode":"56435",
    "sg:province":"MN",
    "sg:tags":[
        "day"
    ],
    "wof:name":"Pine Mountain Daycare",
    "wof:placetype":"venue"
},
  "geometry": {"coordinates":[-94.507642,46.825669],"type":"Point"}
}