{
  "type": "Feature",
  "properties": {
    "iso:country":"US",
    "sg:address":"5511 E Bavarian Pass",
    "sg:city":"Minneapolis",
    "sg:classifiers":[
        {
            "category":"Real Estate",
            "subcategory":"Real Estate Agent",
            "type":"Services"
        }
    ],
    "sg:phone":"+1 651 430 7559",
    "sg:postcode":"55432",
    "sg:province":"MN",
    "sg:tags":[
        "broker"
    ],
    "wof:name":"Wyatt Inc",
    "wof:placetype":"venue"
},
  "geometry": {"coordinates":[-93.22807899999999,45.06668],"type":"Point"}
}