{
  "type": "Feature",
  "properties": {
    "iso:country":"US",
    "sg:address":"710 Mendelssohn Ave N",
    "sg:city":"Golden Valley",
    "sg:classifiers":[
        {
            "category":"Insurance",
            "subcategory":"Insurance Agent",
            "type":"Services"
        }
    ],
    "sg:phone":"+1 763 543 2496",
    "sg:postcode":"55427",
    "sg:province":"MN",
    "wof:name":"Wellner Insurance Inc",
    "wof:placetype":"venue"
},
  "geometry": {"coordinates":[-93.39991499999999,44.988051],"type":"Point"}
}