{
  "type": "Feature",
  "properties": {
    "addr:full":"4529 Margaret St Saint Paul MN 55110",
    "addr:housenumber":"4529",
    "addr:postcode":"55110",
    "addr:street":"Margaret St",
    "iso:country":"US",
    "sg:address":"4529 Margaret St",
    "sg:city":"Saint Paul",
    "sg:classifiers":[
        {
            "category":"Organizations",
            "subcategory":"Community Association",
            "type":"Services"
        }
    ],
    "sg:phone":"+1 651 426 9164",
    "sg:postcode":"55110",
    "sg:province":"MN",
    "sg:tags":[
        "civic",
        "social"
    ],
    "wof:name":"Ackerman Terrace Homeowne",
    "wof:placetype":"venue"
},
  "geometry": {"coordinates":[-93.030176,45.07876],"type":"Point"}
}