{
  "type": "Feature",
  "properties": {
    "addr:full":"739 Summit Ave Saint Paul MN 55105",
    "addr:housenumber":"739",
    "addr:postcode":"55105",
    "addr:street":"Summit Ave",
    "iso:country":"US",
    "sg:address":"739 Summit Ave",
    "sg:city":"Saint Paul",
    "sg:classifiers":[
        {
            "category":"Organizations",
            "subcategory":"Religious Organization",
            "type":"Services"
        }
    ],
    "sg:phone":"+1 651 290 2348",
    "sg:postcode":"55105",
    "sg:province":"MN",
    "sg:tags":[
        "church"
    ],
    "wof:name":"River of Life Christian Center",
    "wof:placetype":"venue"
},
  "geometry": {"coordinates":[-93.128761,44.941356],"type":"Point"}
}