{
  "type": "Feature",
  "properties": {
    "addr:full":"465 E 220th St Jordan MN 55372",
    "addr:housenumber":"465",
    "addr:postcode":"55372",
    "addr:street":"E 220Th St",
    "iso:country":"US",
    "sg:address":"465 E 220th St",
    "sg:city":"Jordan",
    "sg:classifiers":[
        {
            "category":"Travel",
            "subcategory":"Travel Agent",
            "type":"Entertainment"
        }
    ],
    "sg:phone":"+1 952 492 5825",
    "sg:postcode":"55372",
    "sg:province":"MN",
    "sg:tags":[
        "agency"
    ],
    "wof:name":"J R Travel",
    "wof:placetype":"venue"
},
  "geometry": {"coordinates":[-93.51699000000001,44.630516],"type":"Point"}
}