{
  "type": "Feature",
  "properties": {
    "addr:full":"4212 Minnetonka Blvd Minneapolis MN 55416",
    "addr:housenumber":"4212",
    "addr:postcode":"55416",
    "addr:street":"Minnetonka Blvd",
    "iso:country":"US",
    "sg:address":"4212 Minnetonka Blvd",
    "sg:city":"Minneapolis",
    "sg:classifiers":[
        {
            "category":"Shopping",
            "subcategory":"Books",
            "type":"Retail Goods"
        }
    ],
    "sg:phone":"+1 952 926 4433",
    "sg:postcode":"55416",
    "sg:province":"MN",
    "sg:tags":[
        "bookstore"
    ],
    "wof:name":"Elijah's Cup",
    "wof:placetype":"venue"
},
  "geometry": {"coordinates":[-93.332802,44.948601],"type":"Point"}
}