{
  "type": "Feature",
  "properties": {
    "iso:country":"US",
    "sg:address":"18597 555th Ave",
    "sg:city":"Litchfield",
    "sg:phone":"+1 320 857 2162",
    "sg:postcode":"55355",
    "sg:province":"MN",
    "sg:tags":[
        "farm",
        "grain",
        "cash"
    ],
    "wof:name":"Dale Pearson",
    "wof:placetype":"venue"
},
  "geometry": {"coordinates":[-94.655587,45.025209],"type":"Point"}
}