{
  "type": "Feature",
  "properties": {
    "iso:country":"US",
    "sg:address":"51197 360th St",
    "sg:city":"Paynesville",
    "sg:phone":"+1 320 276 8639",
    "sg:postcode":"56362",
    "sg:province":"MN",
    "sg:tags":[
        "farm",
        "corn",
        "soybean"
    ],
    "wof:name":"Loren Pearson",
    "wof:placetype":"venue"
},
  "geometry": {"coordinates":[-94.743787,45.268263],"type":"Point"}
}