{
  "type": "Feature",
  "properties": {
    "addr:full":"8107 Vincent Ave S Minneapolis MN 55431",
    "addr:housenumber":"8107",
    "addr:postcode":"55431",
    "addr:street":"Vincent Ave S",
    "iso:country":"US",
    "sg:address":"8107 Vincent Ave S",
    "sg:city":"Minneapolis",
    "sg:classifiers":[
        {
            "category":"Building & Trades",
            "subcategory":"Construction",
            "type":"Services"
        }
    ],
    "sg:phone":"+1 952 884 5188",
    "sg:postcode":"55431",
    "sg:province":"MN",
    "sg:tags":[
        "foundation",
        "contractor"
    ],
    "wof:name":"Ddc Contracting Inc",
    "wof:placetype":"venue"
},
  "geometry": {"coordinates":[-93.316926,44.8582],"type":"Point"}
}