{
  "type": "Feature",
  "properties": {
    "iso:country":"US",
    "sg:address":"404 W 3rd Ave N",
    "sg:city":"Aurora",
    "sg:classifiers":[
        {
            "category":"Organizations",
            "subcategory":"Religious Organization",
            "type":"Services"
        }
    ],
    "sg:phone":"+1 218 229 3831",
    "sg:postcode":"55705",
    "sg:province":"MN",
    "wof:name":"Grace & Truth Bible Church",
    "wof:placetype":"venue"
},
  "geometry": {"coordinates":[-92.246272,47.530166],"type":"Point"}
}