{
  "type": "Feature",
  "properties": {
    "addr:full":"119 E 7th St Red Wing MN 55066",
    "addr:housenumber":"119",
    "addr:postcode":"55066",
    "addr:street":"E 7Th St",
    "iso:country":"US",
    "sg:address":"119 E 7th St",
    "sg:city":"Red Wing",
    "sg:classifiers":[
        {
            "category":"Social Services",
            "subcategory":"Child Care",
            "type":"Services"
        }
    ],
    "sg:phone":"+1 651 388 4584",
    "sg:postcode":"55066",
    "sg:province":"MN",
    "sg:tags":[
        "day"
    ],
    "wof:name":"Lynette A Roper",
    "wof:placetype":"venue"
},
  "geometry": {"coordinates":[-92.525527,44.564847],"type":"Point"}
}