{
  "type": "Feature",
  "properties": {
    "addr:full":"3300 Edinborough Way Edina MN 55435",
    "addr:housenumber":"3300",
    "addr:postcode":"55435",
    "addr:street":"Edinborough Way",
    "iso:country":"US",
    "sg:address":"3300 Edinborough Way",
    "sg:city":"Edina",
    "sg:classifiers":[
        {
            "category":"Professional",
            "subcategory":"Business Services",
            "type":"Services"
        },
        {
            "category":"Manufacturing",
            "subcategory":"Printing",
            "type":"Manufacturing & Wholesale Goods"
        }
    ],
    "sg:phone":"+1 952 896 1900",
    "sg:postcode":"55435",
    "sg:province":"MN",
    "sg:tags":[
        "lecture",
        "book",
        "bureau",
        "seminar"
    ],
    "wof:name":"Winninger Institute",
    "wof:placetype":"venue"
},
  "geometry": {"coordinates":[-93.323814,44.862328],"type":"Point"}
}