{
  "type": "Feature",
  "properties": {
    "iso:country":"US",
    "sg:address":"1983 70th Ave",
    "sg:city":"Pipestone",
    "sg:phone":"+1 507 825 2838",
    "sg:postcode":"56164",
    "sg:province":"MN",
    "sg:tags":[
        "farm",
        "corn",
        "soybean"
    ],
    "wof:name":"David Cruisdmark",
    "wof:placetype":"venue"
},
  "geometry": {"coordinates":[-96.327629,44.12815],"type":"Point"}
}