{
  "type": "Feature",
  "properties": {
    "addr:full":"605 5th Ave S St Cloud MN 56301",
    "addr:housenumber":"605",
    "addr:postcode":"56301",
    "addr:street":"5Th Ave S",
    "iso:country":"US",
    "sg:address":"605 5th Ave S",
    "sg:city":"St Cloud",
    "sg:classifiers":[
        {
            "category":"Real Estate",
            "subcategory":"Real Estate Agent",
            "type":"Services"
        }
    ],
    "sg:phone":"+1 320 259 9434",
    "sg:postcode":"56301",
    "sg:province":"MN",
    "wof:name":"T K Meyer Properties",
    "wof:placetype":"venue"
},
  "geometry": {"coordinates":[-94.15465500000001,45.552694],"type":"Point"}
}