{
  "type": "Feature",
  "properties": {
    "iso:country":"US",
    "sg:address":"1131 Mesaba Ave",
    "sg:city":"Duluth",
    "sg:classifiers":[
        {
            "category":"Government",
            "subcategory":"Police Station",
            "type":"Public Place"
        }
    ],
    "sg:phone":"+1 218 723 4888",
    "sg:postcode":"55811",
    "sg:province":"MN",
    "sg:tags":[
        "state",
        "protection"
    ],
    "sg:website":"www.dps.state.mn.us",
    "wof:name":"MN State Patrol",
    "wof:placetype":"venue"
},
  "geometry": {"coordinates":[-92.107006,46.798664],"type":"Point"}
}