{
  "type": "Feature",
  "properties": {
    "iso:country":"US",
    "sg:address":"135 Jefferson Ave",
    "sg:city":"Zumbrota",
    "sg:classifiers":[
        {
            "category":"Utilities",
            "subcategory":"Electric",
            "type":"Services"
        }
    ],
    "sg:phone":"+1 507 732 5815",
    "sg:postcode":"55992",
    "sg:province":"MN",
    "sg:tags":[
        "gas"
    ],
    "wof:name":"XCEL Energy",
    "wof:placetype":"venue"
},
  "geometry": {"coordinates":[-92.68174,44.301182],"type":"Point"}
}