{
  "type": "Feature",
  "properties": {
    "iso:country":"US",
    "sg:address":"11530 Hudson Blvd N",
    "sg:city":"Lake Elmo",
    "sg:classifiers":[
        {
            "category":"Professional",
            "type":"Services"
        }
    ],
    "sg:phone":"+1 651 998 0102",
    "sg:postcode":"55042",
    "sg:province":"MN",
    "wof:name":"Frontier Land Corporation",
    "wof:placetype":"venue"
},
  "geometry": {"coordinates":[-92.872362,44.949341],"type":"Point"}
}