{
  "type": "Feature",
  "properties": {
    "iso:country":"US",
    "sg:address":"1996 Cliff Rd E",
    "sg:city":"Burnsville",
    "sg:classifiers":[
        {
            "category":"Restaurant",
            "type":"Food & Drink"
        }
    ],
    "sg:phone":"+1 952 895 1111",
    "sg:postcode":"55337",
    "sg:province":"MN",
    "sg:tags":[
        "pizza"
    ],
    "wof:name":"Zeppelin Pizza",
    "wof:placetype":"venue"
},
  "geometry": {"coordinates":[-93.246966,44.790539],"type":"Point"}
}