{
  "type": "Feature",
  "properties": {
    "iso:country":"US",
    "sg:address":"3766 Towndale Dr",
    "sg:city":"Minneapolis",
    "sg:classifiers":[
        {
            "category":"Real Estate",
            "subcategory":"Architect",
            "type":"Services"
        }
    ],
    "sg:phone":"+1 952 831 0682",
    "sg:postcode":"55431",
    "sg:province":"MN",
    "sg:tags":[
        "architectural"
    ],
    "wof:name":"Ralph B Shimer Architects",
    "wof:placetype":"venue"
},
  "geometry": {"coordinates":[-93.328732,44.855291],"type":"Point"}
}