{
  "type": "Feature",
  "properties": {
    "addr:full":"1434 NE Grand St Minneapolis MN 55413",
    "addr:housenumber":"1434",
    "addr:postcode":"55413",
    "addr:street":"Ne Grand St",
    "iso:country":"US",
    "sg:address":"1434 NE Grand St",
    "sg:city":"Minneapolis",
    "sg:classifiers":[
        {
            "category":"Professional",
            "subcategory":"Computer Services",
            "type":"Services"
        }
    ],
    "sg:phone":"+1 612 850 1400",
    "sg:postcode":"55413",
    "sg:province":"MN",
    "sg:tags":[
        "consulting",
        "related"
    ],
    "wof:name":"Golden Triangle Entps Inc",
    "wof:placetype":"venue"
},
  "geometry": {"coordinates":[-93.270189,45.003493],"type":"Point"}
}