{
  "type": "Feature",
  "properties": {
    "addr:full":"12856 Zilla St NW Minneapolis MN 55448",
    "addr:postcode":"12856;55448",
    "addr:street":"Zilla St Nw",
    "iso:country":"US",
    "sg:address":"12856 Zilla St NW",
    "sg:city":"Minneapolis",
    "sg:classifiers":[
        {
            "category":"Sports & Exercise",
            "subcategory":"Gym",
            "type":"Entertainment"
        }
    ],
    "sg:phone":"+1 763 323 4600",
    "sg:postcode":"55448",
    "sg:province":"MN",
    "sg:tags":[
        "equipment",
        "gymnasium",
        "fitness"
    ],
    "wof:name":"Gym Works Inc",
    "wof:placetype":"venue"
},
  "geometry": {"coordinates":[-93.299047,45.204184],"type":"Point"}
}