{
  "type": "Feature",
  "properties": {
    "addr:full":"481 Desnoyer Ave Saint Paul MN 55104",
    "addr:housenumber":"481",
    "addr:postcode":"55104",
    "addr:street":"Desnoyer Ave",
    "iso:country":"US",
    "sg:address":"481 Desnoyer Ave",
    "sg:city":"Saint Paul",
    "sg:classifiers":[
        {
            "category":"Professional",
            "subcategory":"Lawyer & Legal Services",
            "type":"Services"
        }
    ],
    "sg:phone":"+1 651 644 0460",
    "sg:postcode":"55104",
    "sg:province":"MN",
    "wof:name":"Robert C Onan Jr",
    "wof:placetype":"venue"
},
  "geometry": {"coordinates":[-93.203925,44.95556],"type":"Point"}
}