{
  "type": "Feature",
  "properties": {
    "iso:country":"US",
    "sg:address":"5030 Nokomis Ave S",
    "sg:city":"Minneapolis",
    "sg:classifiers":[
        {
            "category":"Professional",
            "subcategory":"Art Services",
            "type":"Services"
        }
    ],
    "sg:phone":"+1 612 276 0151",
    "sg:postcode":"55417",
    "sg:province":"MN",
    "sg:tags":[
        "photographer"
    ],
    "wof:name":"Brian Droege Photography",
    "wof:placetype":"venue"
},
  "geometry": {"coordinates":[-93.228483,44.911346],"type":"Point"}
}