{
  "type": "Feature",
  "properties": {
    "addr:full":"5110 Morgan Ave N Minneapolis MN 55430",
    "addr:housenumber":"5110",
    "addr:postcode":"55430",
    "addr:street":"Morgan Ave N",
    "iso:country":"US",
    "sg:address":"5110 Morgan Ave N",
    "sg:city":"Minneapolis",
    "sg:classifiers":[
        {
            "category":"Organizations",
            "subcategory":"Professional Association",
            "type":"Services"
        }
    ],
    "sg:phone":"+1 612 521 0090",
    "sg:postcode":"55430",
    "sg:province":"MN",
    "sg:tags":[
        "business"
    ],
    "wof:name":"World Goals",
    "wof:placetype":"venue"
},
  "geometry": {"coordinates":[-93.30545100000001,45.04919],"type":"Point"}
}