{
  "type": "Feature",
  "properties": {
    "addr:full":"5345 W 125th St Savage MN 55378",
    "addr:housenumber":"5345",
    "addr:postcode":"55378",
    "addr:street":"W 125Th St",
    "iso:country":"US",
    "sg:address":"5345 W 125th St",
    "sg:city":"Savage",
    "sg:classifiers":[
        {
            "category":"Wholesale",
            "subcategory":"Machinery & Supplies",
            "type":"Manufacturing & Wholesale Goods"
        }
    ],
    "sg:phone":"+1 952 895 9050",
    "sg:postcode":"55378",
    "sg:province":"MN",
    "sg:tags":[
        "industrial",
        "mfg",
        "material",
        "equipment",
        "handling",
        "furniture"
    ],
    "sg:website":"www.modernbin.com",
    "wof:name":"Modern Bin Equipment Co",
    "wof:placetype":"venue"
},
  "geometry": {"coordinates":[-93.350695,44.775671],"type":"Point"}
}