{
  "type": "Feature",
  "properties": {
    "addr:full":"5635 Yucca Ln N Minneapolis MN 55446",
    "addr:housenumber":"5635",
    "addr:postcode":"55446",
    "addr:street":"Yucca Ln N",
    "iso:country":"US",
    "sg:address":"5635 Yucca Ln N",
    "sg:city":"Minneapolis",
    "sg:classifiers":[
        {
            "category":"Sports & Exercise",
            "subcategory":"Golf",
            "type":"Entertainment"
        }
    ],
    "sg:phone":"+1 763 559 7574",
    "sg:postcode":"55446",
    "sg:province":"MN",
    "sg:tags":[
        "course",
        "public"
    ],
    "sg:website":"www.beginoaksgolf.com",
    "wof:name":"Begin Oaks Golf Inc",
    "wof:placetype":"venue"
},
  "geometry": {"coordinates":[-93.45273400000001,45.056745],"type":"Point"}
}