{
  "type": "Feature",
  "properties": {
    "iso:country":"US",
    "sg:address":"216 3rd Ave S",
    "sg:city":"Saint Cloud",
    "sg:classifiers":[
        {
            "category":"Organizations",
            "subcategory":"Religious Organization",
            "type":"Services"
        }
    ],
    "sg:phone":"+1 320 251 2872",
    "sg:postcode":"56301",
    "sg:province":"MN",
    "wof:name":"Sacred Heart Church",
    "wof:placetype":"venue"
},
  "geometry": {"coordinates":[-94.153397,45.55945],"type":"Point"}
}