{
  "type": "Feature",
  "properties": {
    "iso:country":"US",
    "sg:address":"2155 Niagara Ln N",
    "sg:city":"Minneapolis",
    "sg:classifiers":[
        {
            "category":"Shopping",
            "type":"Retail Goods"
        }
    ],
    "sg:phone":"+1 763 476 5907",
    "sg:postcode":"55447",
    "sg:province":"MN",
    "sg:tags":[
        "merchandise"
    ],
    "wof:name":"Pink Coconut International",
    "wof:placetype":"venue"
},
  "geometry": {"coordinates":[-93.471644,45.003043],"type":"Point"}
}