{
  "type": "Feature",
  "properties": {
    "iso:country":"US",
    "sg:address":"15500 Wayzata Blvd",
    "sg:city":"Wayzata",
    "sg:classifiers":[
        {
            "category":"Real Estate",
            "subcategory":"Real Estate Agent",
            "type":"Services"
        }
    ],
    "sg:phone":"+1 952 404 1141",
    "sg:postcode":"55391",
    "sg:province":"MN",
    "wof:name":"Brighton Corporation",
    "wof:placetype":"venue"
},
  "geometry": {"coordinates":[-93.47614799999999,44.971471],"type":"Point"}
}