{
  "type": "Feature",
  "properties": {
    "iso:country":"US",
    "sg:address":"224 E Main St",
    "sg:city":"Luverne",
    "sg:classifiers":[
        {
            "category":"Insurance",
            "subcategory":"Insurance Agent",
            "type":"Services"
        }
    ],
    "sg:phone":"+1 507 283 4085",
    "sg:postcode":"56156",
    "sg:province":"MN",
    "wof:name":"Heidebrink & Assoc",
    "wof:placetype":"venue"
},
  "geometry": {"coordinates":[-96.207596,43.654155],"type":"Point"}
}