{
  "type": "Feature",
  "properties": {
    "addr:full":"32021 Co Hwy 4 Vergas MN 56587",
    "addr:postcode":"32021;56587",
    "addr:street":"Co Hwy 4",
    "iso:country":"US",
    "sg:address":"32021 Co Hwy 4",
    "sg:city":"Vergas",
    "sg:classifiers":[
        {
            "category":"Food & Beverages",
            "subcategory":"Groceries & Convenience Stores",
            "type":"Retail Goods"
        }
    ],
    "sg:phone":"+1 218 342 2233",
    "sg:postcode":"56587",
    "sg:province":"MN",
    "wof:name":"Heisler Country Store",
    "wof:placetype":"venue"
},
  "geometry": {"coordinates":[-95.824721,46.642781],"type":"Point"}
}