{
  "type": "Feature",
  "properties": {
    "addr:full":"23873 740th Ave Albert Lea MN 56007",
    "addr:housenumber":"23873",
    "addr:postcode":"56007",
    "addr:street":"740Th Ave",
    "iso:country":"US",
    "sg:address":"23873 740th Ave",
    "sg:city":"Albert Lea",
    "sg:classifiers":[
        {
            "category":"Freight",
            "type":"Transportation"
        }
    ],
    "sg:phone":"+1 507 826 3707",
    "sg:postcode":"56007",
    "sg:province":"MN",
    "sg:tags":[
        "operator",
        "local",
        "trucking"
    ],
    "wof:name":"Johnson Trucking",
    "wof:placetype":"venue"
},
  "geometry": {"coordinates":[-93.388944,43.700216],"type":"Point"}
}