{
  "type": "Feature",
  "properties": {
    "addr:full":"601 Marquette Ave Minneapolis MN 55402",
    "addr:housenumber":"601",
    "addr:postcode":"55402",
    "addr:street":"Marquette Ave",
    "iso:country":"US",
    "sg:address":"601 Marquette Ave",
    "sg:city":"Minneapolis",
    "sg:classifiers":[
        {
            "category":"Restaurant",
            "type":"Food & Drink"
        }
    ],
    "sg:phone":"+1 612 333 4949",
    "sg:postcode":"55402",
    "sg:province":"MN",
    "sg:tags":[
        "italian"
    ],
    "wof:name":"Di Napoli Cafe",
    "wof:placetype":"venue"
},
  "geometry": {"coordinates":[-93.270042,44.977253],"type":"Point"}
}