{
  "type": "Feature",
  "properties": {
    "iso:country":"US",
    "sg:address":"3701 12th St N",
    "sg:city":"St Cloud",
    "sg:classifiers":[
        {
            "category":"Insurance",
            "subcategory":"Insurance Agent",
            "type":"Services"
        }
    ],
    "sg:phone":"+1 320 258 3993",
    "sg:postcode":"56303",
    "sg:province":"MN",
    "wof:name":"Shawn Brannan",
    "wof:placetype":"venue"
},
  "geometry": {"coordinates":[-94.20453500000001,45.573026],"type":"Point"}
}