{
  "type": "Feature",
  "properties": {
    "addr:full":"36078 Co Rd 17 Redwood Falls MN 56283",
    "addr:housenumber":"17",
    "addr:postcode":"36078;56283",
    "addr:street":"Co Rd",
    "iso:country":"US",
    "sg:address":"36078 Co Rd 17",
    "sg:city":"Redwood Falls",
    "sg:classifiers":[
        {
            "category":"Building & Trades",
            "subcategory":"Plumbing",
            "type":"Services"
        }
    ],
    "sg:phone":"+1 507 641 5550",
    "sg:postcode":"56283",
    "sg:province":"MN",
    "sg:tags":[
        "contractor"
    ],
    "wof:name":"Rural Services",
    "wof:placetype":"venue"
},
  "geometry": {"coordinates":[-95.147305,44.570708],"type":"Point"}
}