{
  "type": "Feature",
  "properties": {
    "addr:full":"27484 110th St Lowry MN 56349",
    "addr:housenumber":"27484",
    "addr:postcode":"56349",
    "addr:street":"110Th St",
    "iso:country":"US",
    "sg:address":"27484 110th St",
    "sg:city":"Lowry",
    "sg:classifiers":[
        {
            "category":"Farming",
            "subcategory":"Dairy Farm",
            "type":"Manufacturing & Wholesale Goods"
        }
    ],
    "sg:phone":"+1 320 283 5344",
    "sg:postcode":"56349",
    "sg:province":"MN",
    "wof:name":"Orville Chan",
    "wof:placetype":"venue"
},
  "geometry": {"coordinates":[-95.50538899999999,45.744579],"type":"Point"}
}