{
  "type": "Feature",
  "properties": {
    "addr:full":"121 2nd St NW Waseca MN 56093",
    "addr:housenumber":"121",
    "addr:postcode":"56093",
    "addr:street":"2Nd St Nw",
    "iso:country":"US",
    "sg:address":"121 2nd St NW",
    "sg:city":"Waseca",
    "sg:classifiers":[
        {
            "category":"Home & Garden",
            "subcategory":"Hardware",
            "type":"Retail Goods"
        }
    ],
    "sg:phone":"+1 507 835 1097",
    "sg:postcode":"56093",
    "sg:province":"MN",
    "wof:name":"Charles OK Hardware Inc",
    "wof:placetype":"venue"
},
  "geometry": {"coordinates":[-93.50885100000001,44.078365],"type":"Point"}
}