{
  "type": "Feature",
  "properties": {
    "addr:full":"38150 Reed Ave Taylors Falls MN 55084",
    "addr:housenumber":"38150",
    "addr:postcode":"55084",
    "addr:street":"Reed Ave",
    "iso:country":"US",
    "sg:address":"38150 Reed Ave",
    "sg:city":"Taylors Falls",
    "sg:classifiers":[
        {
            "category":"Building & Trades",
            "subcategory":"Electrical",
            "type":"Services"
        }
    ],
    "sg:phone":"+1 651 583 2181",
    "sg:postcode":"55084",
    "sg:province":"MN",
    "sg:tags":[
        "electrical",
        "merchandise",
        "contractor"
    ],
    "wof:name":"Christiansen Electric Co",
    "wof:placetype":"venue"
},
  "geometry": {"coordinates":[-92.755196,45.501505],"type":"Point"}
}