{
  "type": "Feature",
  "properties": {
    "iso:country":"US",
    "sg:address":"112 1st Ave NE",
    "sg:city":"Dilworth",
    "sg:classifiers":[
        {
            "category":"Education",
            "subcategory":"Special Training",
            "type":"Public Place"
        }
    ],
    "sg:phone":"+1 218 284 6148",
    "sg:postcode":"56529",
    "sg:province":"MN",
    "sg:tags":[
        "center"
    ],
    "wof:name":"Head Start Clay Wilkin",
    "wof:placetype":"venue"
},
  "geometry": {"coordinates":[-96.70049899999999,46.877615],"type":"Point"}
}