{
  "type": "Feature",
  "properties": {
    "addr:full":"836 E Magnolia Ave Saint Paul MN 55106",
    "addr:housenumber":"836",
    "addr:postcode":"55106",
    "addr:street":"E Magnolia Ave",
    "iso:country":"US",
    "sg:address":"836 E Magnolia Ave",
    "sg:city":"Saint Paul",
    "sg:classifiers":[
        {
            "category":"Organizations",
            "subcategory":"Religious Organization",
            "type":"Services"
        }
    ],
    "sg:phone":"+1 651 776 1986",
    "sg:postcode":"55106",
    "sg:province":"MN",
    "wof:name":"Trinity Mission",
    "wof:placetype":"venue"
},
  "geometry": {"coordinates":[-93.063924,44.973831],"type":"Point"}
}