{
  "type": "Feature",
  "properties": {
    "iso:country":"US",
    "sg:address":"7920 University Ave NE",
    "sg:city":"Fridley",
    "sg:classifiers":[
        {
            "category":"Professional",
            "subcategory":"Management & Consulting",
            "type":"Services"
        }
    ],
    "sg:phone":"+1 763 792 2100",
    "sg:postcode":"55432",
    "sg:province":"MN",
    "sg:tags":[
        "consultant"
    ],
    "wof:name":"CCA",
    "wof:placetype":"venue"
},
  "geometry": {"coordinates":[-93.26361799999999,45.114803],"type":"Point"}
}