{
  "type": "Feature",
  "properties": {
    "iso:country":"US",
    "sg:address":"7275 Bush Lake Rd",
    "sg:city":"Minneapolis",
    "sg:classifiers":[
        {
            "category":"Shopping",
            "subcategory":"Used Merchandise",
            "type":"Retail Goods"
        }
    ],
    "sg:phone":"+1 952 897 3500",
    "sg:postcode":"55439",
    "sg:province":"MN",
    "sg:tags":[
        "computer"
    ],
    "wof:name":"Select Biomedical",
    "wof:placetype":"venue"
},
  "geometry": {"coordinates":[-93.35973,44.869791],"type":"Point"}
}