{
  "type": "Feature",
  "properties": {
    "addr:full":"1537 Broadway Ave Bigelow MN 56117",
    "addr:housenumber":"1537",
    "addr:postcode":"56117",
    "addr:street":"Broadway Ave",
    "iso:country":"US",
    "sg:address":"1537 Broadway Ave",
    "sg:city":"Bigelow",
    "sg:classifiers":[
        {
            "category":"Government",
            "subcategory":"Office",
            "type":"Public Place"
        }
    ],
    "sg:phone":"+1 507 683 2441",
    "sg:postcode":"56117",
    "sg:province":"MN",
    "sg:tags":[
        "executive"
    ],
    "wof:name":"City of Bigelow",
    "wof:placetype":"venue"
},
  "geometry": {"coordinates":[-95.689504,43.505077],"type":"Point"}
}