{
  "type": "Feature",
  "properties": {
    "iso:country":"US",
    "sg:address":"230 Oak Grove St Ofc",
    "sg:city":"Minneapolis",
    "sg:classifiers":[
        {
            "category":"Real Estate",
            "subcategory":"Real Estate Operator",
            "type":"Services"
        }
    ],
    "sg:phone":"+1 612 870 8741",
    "sg:postcode":"55403",
    "sg:province":"MN",
    "sg:tags":[
        "apartment"
    ],
    "wof:name":"Oak Grove Apartment Hotel",
    "wof:placetype":"venue"
},
  "geometry": {"coordinates":[-93.281403,44.966499],"type":"Point"}
}