{
  "type": "Feature",
  "properties": {
    "iso:country":"US",
    "sg:address":"3939 W 50th St",
    "sg:city":"Minneapolis",
    "sg:classifiers":[
        {
            "category":"Health Services",
            "subcategory":"Doctor",
            "type":"Services"
        }
    ],
    "sg:phone":"+1 952 922 2313",
    "sg:postcode":"55424",
    "sg:province":"MN",
    "wof:name":"Michael A Ronald",
    "wof:placetype":"venue"
},
  "geometry": {"coordinates":[-93.331294,44.912456],"type":"Point"}
}