{
  "type": "Feature",
  "properties": {
    "addr:full":"31238 County 24 Blvd Cannon Falls MN 55009",
    "addr:housenumber":"31238",
    "addr:postcode":"55009",
    "addr:street":"County 24 Blvd",
    "iso:country":"US",
    "sg:address":"31238 County 24 Blvd",
    "sg:city":"Cannon Falls",
    "sg:classifiers":[
        {
            "category":"Insurance",
            "subcategory":"Insurance Agent",
            "type":"Services"
        }
    ],
    "sg:phone":"+1 507 263 3622",
    "sg:postcode":"55009",
    "sg:province":"MN",
    "wof:name":"State Farm Insurance",
    "wof:placetype":"venue"
},
  "geometry": {"coordinates":[-92.905934,44.493427],"type":"Point"}
}