{
  "type": "Feature",
  "properties": {
    "iso:country":"US",
    "sg:address":"2050 Snelling Ave N",
    "sg:city":"Saint Paul",
    "sg:classifiers":[
        {
            "category":"Restaurant",
            "type":"Food & Drink"
        }
    ],
    "sg:menulink":"http://www.allmenus.com/mn/falcon-heights/267644-chianti-grill/menu/",
    "sg:phone":"+1 651 644 2808",
    "sg:postcode":"55113",
    "sg:province":"MN",
    "sg:tags":[
        "italian"
    ],
    "wof:name":"Chianti Grill",
    "wof:placetype":"venue"
},
  "geometry": {"coordinates":[-93.16543,45.003027],"type":"Point"}
}