{
  "type": "Feature",
  "properties": {
    "iso:country":"US",
    "sg:address":"10250 Valley View Rd",
    "sg:city":"Eden Prairie",
    "sg:classifiers":[
        {
            "category":"Manufacturing",
            "subcategory":"Printing",
            "type":"Manufacturing & Wholesale Goods"
        }
    ],
    "sg:phone":"+1 952 829 8999",
    "sg:postcode":"55344",
    "sg:province":"MN",
    "sg:tags":[
        "publishes",
        "discount",
        "book"
    ],
    "wof:name":"Entertaining Fund Raising",
    "wof:placetype":"venue"
},
  "geometry": {"coordinates":[-93.408305,44.870774],"type":"Point"}
}