{
  "type": "Feature",
  "properties": {
    "iso:country":"US",
    "sg:address":"284 Twin Lake Trl",
    "sg:city":"St Paul",
    "sg:classifiers":[
        {
            "category":"Building & Trades",
            "subcategory":"Construction",
            "type":"Services"
        }
    ],
    "sg:phone":"+1 651 483 9563",
    "sg:postcode":"55127",
    "sg:province":"MN",
    "sg:tags":[
        "general",
        "contractor"
    ],
    "wof:name":"Wescot Construction & Dev Inc",
    "wof:placetype":"venue"
},
  "geometry": {"coordinates":[-93.08971,45.038113],"type":"Point"}
}