{
  "type": "Feature",
  "properties": {
    "addr:full":"412 E Main St Ada MN 56510",
    "addr:housenumber":"412",
    "addr:postcode":"56510",
    "addr:street":"E Main St",
    "iso:country":"US",
    "sg:address":"412 E Main St",
    "sg:city":"Ada",
    "sg:classifiers":[
        {
            "category":"Banks & Credit Unions",
            "subcategory":"Bank",
            "type":"Services"
        }
    ],
    "sg:phone":"+1 218 784 7151",
    "sg:postcode":"56510",
    "sg:province":"MN",
    "wof:name":"Bank Of The West",
    "wof:placetype":"venue"
},
  "geometry": {"coordinates":[-96.515412,47.300808],"type":"Point"}
}