{
  "type": "Feature",
  "properties": {
    "iso:country":"US",
    "sg:address":"11002 45th Ave SW",
    "sg:city":"Pillager",
    "sg:classifiers":[
        {
            "category":"Building & Trades",
            "subcategory":"Landscaping Services",
            "type":"Services"
        }
    ],
    "sg:phone":"+1 218 746 3514",
    "sg:postcode":"56473",
    "sg:province":"MN",
    "sg:tags":[
        "tree"
    ],
    "wof:name":"Altrichter & Altrichter",
    "wof:placetype":"venue"
},
  "geometry": {"coordinates":[-94.518146,46.405485],"type":"Point"}
}