{
  "type": "Feature",
  "properties": {
    "addr:full":"5005 W 60th St Minneapolis MN 55436",
    "addr:housenumber":"5005",
    "addr:postcode":"55436",
    "addr:street":"W 60Th St",
    "iso:country":"US",
    "sg:address":"5005 W 60th St",
    "sg:city":"Minneapolis",
    "sg:classifiers":[
        {
            "category":"Social Services",
            "subcategory":"Child Care",
            "type":"Services"
        }
    ],
    "sg:phone":"+1 952 925 4030",
    "sg:postcode":"55436",
    "sg:province":"MN",
    "sg:tags":[
        "daycare",
        "provider"
    ],
    "wof:name":"Janet Koukal",
    "wof:placetype":"venue"
},
  "geometry": {"coordinates":[-93.351299,44.895156],"type":"Point"}
}