{
  "type": "Feature",
  "properties": {
    "iso:country":"US",
    "sg:address":"19729 680th St",
    "sg:city":"Dodge Center",
    "sg:classifiers":[
        {
            "category":"Farming",
            "subcategory":"Livestock Farm",
            "type":"Manufacturing & Wholesale Goods"
        }
    ],
    "sg:phone":"+1 507 374 2193",
    "sg:postcode":"55927",
    "sg:province":"MN",
    "sg:tags":[
        "hog",
        "beef",
        "far",
        "corn",
        "cattle",
        "or",
        "feedlot"
    ],
    "wof:name":"Moenning Farms",
    "wof:placetype":"venue"
},
  "geometry": {"coordinates":[-92.845867,43.964674],"type":"Point"}
}