{
  "type": "Feature",
  "properties": {
    "addr:full":"300 E Main St Eitzen MN 55931",
    "addr:housenumber":"300",
    "addr:postcode":"55931",
    "addr:street":"E Main St",
    "iso:country":"US",
    "sg:address":"300 E Main St",
    "sg:city":"Eitzen",
    "sg:classifiers":[
        {
            "category":"Bars & Pubs",
            "type":"Food & Drink"
        }
    ],
    "sg:phone":"+1 507 495 3599",
    "sg:postcode":"55931",
    "sg:province":"MN",
    "sg:tags":[
        "drinking"
    ],
    "wof:name":"Rosco's Bar & Grill",
    "wof:placetype":"venue"
},
  "geometry": {"coordinates":[-91.45397800000001,43.507877],"type":"Point"}
}