{
  "type": "Feature",
  "properties": {
    "iso:country":"US",
    "sg:address":"8010 Portland Ave S",
    "sg:city":"Bloomington",
    "sg:classifiers":[
        {
            "category":"Banks & Credit Unions",
            "subcategory":"Bank",
            "type":"Services"
        }
    ],
    "sg:phone":"+1 952 888 1446",
    "sg:postcode":"55420",
    "sg:province":"MN",
    "sg:tags":[
        "mortgage",
        "loan",
        "broker",
        "real estate"
    ],
    "wof:name":"TCS Mortgage Funding Inc",
    "wof:placetype":"venue"
},
  "geometry": {"coordinates":[-93.268249,44.859488],"type":"Point"}
}