{
  "type": "Feature",
  "properties": {
    "addr:full":"3045 Sibley Memorial Hwy St Paul MN 55121",
    "addr:housenumber":"3045",
    "addr:postcode":"55121",
    "addr:street":"Sibley Memorial Hwy",
    "iso:country":"US",
    "sg:address":"3045 Sibley Memorial Hwy",
    "sg:city":"St Paul",
    "sg:classifiers":[
        {
            "category":"Building & Trades",
            "subcategory":"Construction",
            "type":"Services"
        }
    ],
    "sg:phone":"+1 651 287 9700",
    "sg:postcode":"55121",
    "sg:province":"MN",
    "sg:tags":[
        "steel",
        "erectors"
    ],
    "wof:name":"Sowles Co",
    "wof:placetype":"venue"
},
  "geometry": {"coordinates":[-93.18378300000001,44.84635],"type":"Point"}
}