{
  "type": "Feature",
  "properties": {
    "addr:full":"26077 Co Hwy 5 Battle Lake MN 56515",
    "addr:housenumber":"26077",
    "addr:postcode":"56515",
    "addr:street":"Co Hwy 5",
    "iso:country":"US",
    "sg:address":"26077 Co Hwy 5",
    "sg:city":"Battle Lake",
    "sg:phone":"+1 218 367 2679",
    "sg:postcode":"56515",
    "sg:province":"MN",
    "sg:tags":[
        "farm",
        "corn",
        "grain",
        "cash"
    ],
    "wof:name":"Daryl Carter",
    "wof:placetype":"venue"
},
  "geometry": {"coordinates":[-95.610653,46.33667],"type":"Point"}
}