{
  "type": "Feature",
  "properties": {
    "addr:full":"751 Mill St E Edgerton MN 56128",
    "addr:housenumber":"751",
    "addr:postcode":"56128",
    "addr:street":"Mill St E",
    "iso:country":"US",
    "sg:address":"751 Mill St E",
    "sg:city":"Edgerton",
    "sg:classifiers":[
        {
            "category":"Transit Center",
            "subcategory":"Freight",
            "type":"Transportation"
        },
        {
            "category":"Freight",
            "type":"Transportation"
        }
    ],
    "sg:phone":"+1 507 631 3824",
    "sg:postcode":"56128",
    "sg:province":"MN",
    "sg:tags":[
        "trucking-motor",
        "trucking"
    ],
    "wof:name":"Bolluyt Trucking",
    "wof:placetype":"venue"
},
  "geometry": {"coordinates":[-96.126227,43.87043],"type":"Point"}
}