{
  "type": "Feature",
  "properties": {
    "iso:country":"US",
    "sg:address":"6600 France Ave S",
    "sg:city":"Edina",
    "sg:classifiers":[
        {
            "category":"Banks & Credit Unions",
            "subcategory":"Investment Brokerage",
            "type":"Services"
        }
    ],
    "sg:phone":"+1 952 920 4848",
    "sg:postcode":"55435",
    "sg:province":"MN",
    "sg:tags":[
        "advisory",
        "management",
        "financial",
        "money"
    ],
    "sg:website":"www.markman.com",
    "wof:name":"Markman Capital Management Inc",
    "wof:placetype":"venue"
},
  "geometry": {"coordinates":[-93.32894899999999,44.879861],"type":"Point"}
}