{
  "type": "Feature",
  "properties": {
    "iso:country":"US",
    "sg:address":"3001 Hennepin Ave B102",
    "sg:city":"Minneapolis",
    "sg:classifiers":[
        {
            "category":"Shopping",
            "subcategory":"Clothing, Apparel, & Fashions",
            "type":"Retail Goods"
        }
    ],
    "sg:phone":"+1 612 332 0381",
    "sg:postcode":"55408",
    "sg:province":"MN",
    "sg:tags":[
        "clothing",
        "boys'"
    ],
    "wof:name":"Suit Up",
    "wof:placetype":"venue"
},
  "geometry": {"coordinates":[-93.298271,44.948372],"type":"Point"}
}