{
  "type": "Feature",
  "properties": {
    "iso:country":"US",
    "sg:address":"13254 162nd Ave",
    "sg:city":"Foreston",
    "sg:classifiers":[
        {
            "category":"Building & Trades",
            "subcategory":"Construction",
            "type":"Services"
        }
    ],
    "sg:phone":"+1 320 294 5494",
    "sg:postcode":"56330",
    "sg:province":"MN",
    "sg:tags":[
        "painter"
    ],
    "wof:name":"T & S Painting",
    "wof:placetype":"venue"
},
  "geometry": {"coordinates":[-93.74601199999999,45.738405],"type":"Point"}
}