{
  "type": "Feature",
  "properties": {
    "iso:country":"US",
    "sg:address":"4930 W 35th St",
    "sg:city":"Minneapolis",
    "sg:classifiers":[
        {
            "category":"Wholesale",
            "subcategory":"Construction Materials",
            "type":"Manufacturing & Wholesale Goods"
        }
    ],
    "sg:phone":"+1 952 746 3003",
    "sg:postcode":"55416",
    "sg:province":"MN",
    "sg:tags":[
        "garage",
        "organizer",
        "cabinet"
    ],
    "wof:name":"Perfect Garage",
    "wof:placetype":"venue"
},
  "geometry": {"coordinates":[-93.342688,44.940786],"type":"Point"}
}