{
  "type": "Feature",
  "properties": {
    "addr:full":"25272 280th Ave Sleepy Eye MN 56085",
    "addr:housenumber":"25272",
    "addr:postcode":"56085",
    "addr:street":"280Th Ave",
    "iso:country":"US",
    "sg:address":"25272 280th Ave",
    "sg:city":"Sleepy Eye",
    "sg:phone":"+1 507 794 7789",
    "sg:postcode":"56085",
    "sg:province":"MN",
    "sg:tags":[
        "farm",
        "corn",
        "equine"
    ],
    "wof:name":"James Sommerfeld",
    "wof:placetype":"venue"
},
  "geometry": {"coordinates":[-94.745712,44.297673],"type":"Point"}
}