{
  "type": "Feature",
  "properties": {
    "iso:country":"US",
    "sg:address":"3904 Oakland Ave",
    "sg:city":"Minneapolis",
    "sg:classifiers":[
        {
            "category":"Health Services",
            "subcategory":"Health Practitioner",
            "type":"Services"
        }
    ],
    "sg:phone":"+1 612 827 0070",
    "sg:postcode":"55407",
    "sg:province":"MN",
    "sg:tags":[
        "aromatherapy"
    ],
    "sg:website":"http://www.minneapolistm.com",
    "wof:name":"Meditation Trancendental Meditation",
    "wof:placetype":"venue"
},
  "geometry": {"coordinates":[-93.266273,44.932294],"type":"Point"}
}