{
  "type": "Feature",
  "properties": {
    "addr:full":"7712 Riverdale Dr N Brooklyn Park MN 55444",
    "addr:housenumber":"7712",
    "addr:postcode":"55444",
    "addr:street":"Riverdale Dr N",
    "iso:country":"US",
    "sg:address":"7712 Riverdale Dr N",
    "sg:city":"Brooklyn Park",
    "sg:classifiers":[
        {
            "category":"Manufacturing",
            "subcategory":"Paper Products",
            "type":"Manufacturing & Wholesale Goods"
        }
    ],
    "sg:phone":"+1 763 566 5872",
    "sg:postcode":"55444",
    "sg:province":"MN",
    "sg:tags":[
        "packaging",
        "material"
    ],
    "wof:name":"Cooper Flexible Packaging Inc",
    "wof:placetype":"venue"
},
  "geometry": {"coordinates":[-93.284903,45.095703],"type":"Point"}
}