{
  "type": "Feature",
  "properties": {
    "iso:country":"US",
    "sg:address":"1011 State Hwy 95",
    "sg:city":"Cambridge",
    "sg:classifiers":[
        {
            "category":"Banks & Credit Unions",
            "subcategory":"Bank",
            "type":"Services"
        }
    ],
    "sg:phone":"+1 763 552 7070",
    "sg:postcode":"55008",
    "sg:province":"MN",
    "sg:tags":[
        "mortgage",
        "personal",
        "loan",
        "real estate",
        "institution"
    ],
    "wof:name":"Centennial Mortgage & Funding",
    "wof:placetype":"venue"
},
  "geometry": {"coordinates":[-93.213016,45.572814],"type":"Point"}
}