{
  "type": "Feature",
  "properties": {
    "addr:full":"106 N Farwell St Verndale MN 56481",
    "addr:housenumber":"106",
    "addr:postcode":"56481",
    "addr:street":"N Farwell St",
    "iso:country":"US",
    "sg:address":"106 N Farwell St",
    "sg:city":"Verndale",
    "sg:classifiers":[
        {
            "category":"Shopping",
            "subcategory":"Discount & Variety Stores",
            "type":"Retail Goods"
        }
    ],
    "sg:phone":"+1 218 445 5566",
    "sg:postcode":"56481",
    "sg:province":"MN",
    "wof:name":"General Instrument",
    "wof:placetype":"venue"
},
  "geometry": {"coordinates":[-95.011516,46.399695],"type":"Point"}
}