{
  "type": "Feature",
  "properties": {
    "addr:full":"221 W Union St St Peter MN 56082",
    "addr:housenumber":"221",
    "addr:postcode":"56082",
    "addr:street":"W Union St",
    "iso:country":"US",
    "sg:address":"221 W Union St",
    "sg:city":"St Peter",
    "sg:classifiers":[
        {
            "category":"Travel",
            "subcategory":"Hotels & Motels",
            "type":"Entertainment"
        }
    ],
    "sg:phone":"+1 507 931 3100",
    "sg:postcode":"56082",
    "sg:province":"MN",
    "wof:name":"Saint Peter Motel",
    "wof:placetype":"venue"
},
  "geometry": {"coordinates":[-93.95063399999999,44.333877],"type":"Point"}
}