{
  "type": "Feature",
  "properties": {
    "addr:full":"10485 Drake St NW Minneapolis MN 55433",
    "addr:housenumber":"10485",
    "addr:postcode":"55433",
    "addr:street":"Drake St Nw",
    "iso:country":"US",
    "sg:address":"10485 Drake St NW",
    "sg:city":"Minneapolis",
    "sg:classifiers":[
        {
            "category":"Building & Trades",
            "subcategory":"Locksmith",
            "type":"Services"
        }
    ],
    "sg:phone":"+1 763 354 1846",
    "sg:postcode":"55433",
    "sg:province":"MN",
    "sg:tags":[
        "key"
    ],
    "wof:name":"Aaland 24 Hour Locksmith",
    "wof:placetype":"venue"
},
  "geometry": {"coordinates":[-93.304079,45.160001],"type":"Point"}
}