{
  "type": "Feature",
  "properties": {
    "iso:country":"US",
    "sg:address":"450 Southview Blvd",
    "sg:city":"South St Paul",
    "sg:classifiers":[
        {
            "category":"Arts & Performance",
            "subcategory":"Theater",
            "type":"Entertainment"
        }
    ],
    "sg:phone":"+1 651 455 5005",
    "sg:postcode":"55075",
    "sg:province":"MN",
    "sg:tags":[
        "entertainer",
        "business"
    ],
    "wof:name":"Flyers",
    "wof:placetype":"venue"
},
  "geometry": {"coordinates":[-93.039377,44.888997],"type":"Point"}
}