{
  "type": "Feature",
  "properties": {
    "addr:full":"1614 Frank Hall Dr Albert Lea MN 56007",
    "addr:housenumber":"1614",
    "addr:postcode":"56007",
    "addr:street":"Frank Hall Dr",
    "iso:country":"US",
    "sg:address":"1614 Frank Hall Dr",
    "sg:city":"Albert Lea",
    "sg:classifiers":[
        {
            "category":"Social Services",
            "subcategory":"Child Care",
            "type":"Services"
        }
    ],
    "sg:phone":"+1 507 377 2508",
    "sg:postcode":"56007",
    "sg:province":"MN",
    "sg:tags":[
        "daycare",
        "provider"
    ],
    "wof:name":"Kimberly J Stiernagle",
    "wof:placetype":"venue"
},
  "geometry": {"coordinates":[-93.35374400000001,43.632305],"type":"Point"}
}