{
  "type": "Feature",
  "properties": {
    "addr:full":"7880 Minar Ave N Stillwater MN 55082",
    "addr:housenumber":"7880",
    "addr:postcode":"55082",
    "addr:street":"Minar Ave N",
    "iso:country":"US",
    "sg:address":"7880 Minar Ave N",
    "sg:city":"Stillwater",
    "sg:classifiers":[
        {
            "category":"Building & Trades",
            "subcategory":"Landscaping Services",
            "type":"Services"
        }
    ],
    "sg:phone":"+1 651 269 2088",
    "sg:postcode":"55082",
    "sg:province":"MN",
    "sg:tags":[
        "lawn"
    ],
    "wof:name":"Acct Closed C H Landscape",
    "wof:placetype":"venue"
},
  "geometry": {"coordinates":[-92.84884599999999,45.06357],"type":"Point"}
}