{
  "type": "Feature",
  "properties": {
    "addr:full":"15 1st St S Minneapolis MN 55401",
    "addr:housenumber":"15",
    "addr:postcode":"55401",
    "addr:street":"1St St S",
    "iso:country":"US",
    "sg:address":"15 1st St S",
    "sg:city":"Minneapolis",
    "sg:classifiers":[
        {
            "category":"Professional",
            "subcategory":"Management & Consulting",
            "type":"Services"
        }
    ],
    "sg:phone":"+1 612 339 9092",
    "sg:postcode":"55401",
    "sg:province":"MN",
    "sg:tags":[
        "consultant",
        "business"
    ],
    "wof:name":"Gail E Lorenz",
    "wof:placetype":"venue"
},
  "geometry": {"coordinates":[-93.265345,44.983127],"type":"Point"}
}