{
  "type": "Feature",
  "properties": {
    "iso:country":"US",
    "sg:address":"196 6th St S",
    "sg:city":"Bayport",
    "sg:classifiers":[
        {
            "category":"Professional",
            "subcategory":"Art Services",
            "type":"Services"
        }
    ],
    "sg:phone":"+1 651 439 0950",
    "sg:postcode":"55003",
    "sg:province":"MN",
    "sg:tags":[
        "commercial",
        "design"
    ],
    "wof:name":"Carlson Graphics LLC",
    "wof:placetype":"venue"
},
  "geometry": {"coordinates":[-92.78389799999999,45.016335],"type":"Point"}
}