{
  "type": "Feature",
  "properties": {
    "addr:full":"901 Willmar Ave SE Willmar MN 56201",
    "addr:housenumber":"901",
    "addr:postcode":"56201",
    "addr:street":"Willmar Ave Se",
    "iso:country":"US",
    "sg:address":"901 Willmar Ave SE",
    "sg:city":"Willmar",
    "sg:classifiers":[
        {
            "category":"Social Services",
            "subcategory":"Adult Care",
            "type":"Services"
        }
    ],
    "sg:phone":"+1 320 235 1353",
    "sg:postcode":"56201",
    "sg:province":"MN",
    "sg:tags":[
        "home",
        "residential"
    ],
    "sg:website":"www.bethesdawillmar.com",
    "wof:name":"Bethesda Willmar",
    "wof:placetype":"venue"
},
  "geometry": {"coordinates":[-95.032527,45.110552],"type":"Point"}
}