{
  "type": "Feature",
  "properties": {
    "addr:full":"8600 347th St Stacy MN 55079",
    "addr:housenumber":"8600",
    "addr:postcode":"55079",
    "addr:street":"347Th St",
    "iso:country":"US",
    "sg:address":"8600 347th St",
    "sg:city":"Stacy",
    "sg:classifiers":[
        {
            "category":"Retail",
            "subcategory":"Repair Shop",
            "type":"Services"
        }
    ],
    "sg:phone":"+1 651 462 1839",
    "sg:postcode":"55079",
    "sg:province":"MN",
    "wof:name":"North Star Cleaning",
    "wof:placetype":"venue"
},
  "geometry": {"coordinates":[-92.928151,45.45077],"type":"Point"}
}