{
  "type": "Feature",
  "properties": {
    "iso:country":"US",
    "sg:address":"202 4th Ave NE",
    "sg:city":"Kasson",
    "sg:classifiers":[
        {
            "category":"Professional",
            "subcategory":"Business Services",
            "type":"Services"
        }
    ],
    "sg:phone":"+1 507 634 6706",
    "sg:postcode":"55944",
    "sg:province":"MN",
    "wof:name":"Klocke & Associates LLC",
    "wof:placetype":"venue"
},
  "geometry": {"coordinates":[-92.743726,44.031345],"type":"Point"}
}