{
  "type": "Feature",
  "properties": {
    "addr:full":"1917 State Ave Anoka MN 55303",
    "addr:housenumber":"1917",
    "addr:postcode":"55303",
    "addr:street":"State Ave",
    "iso:country":"US",
    "sg:address":"1917 State Ave",
    "sg:city":"Anoka",
    "sg:classifiers":[
        {
            "category":"Manufacturing",
            "subcategory":"Rubber & Plastics",
            "type":"Manufacturing & Wholesale Goods"
        }
    ],
    "sg:phone":"+1 763 421 2146",
    "sg:postcode":"55303",
    "sg:province":"MN",
    "sg:tags":[
        "mfg",
        "automotive",
        "weather",
        "strip"
    ],
    "wof:name":"Dry-Gate Weather Seals",
    "wof:placetype":"venue"
},
  "geometry": {"coordinates":[-93.396344,45.199115],"type":"Point"}
}