{
  "type": "Feature",
  "properties": {
    "iso:country":"US",
    "sg:address":"8650 Aldrich Ave S",
    "sg:city":"Minneapolis",
    "sg:classifiers":[
        {
            "category":"Manufacturing",
            "subcategory":"Electronics",
            "type":"Manufacturing & Wholesale Goods"
        },
        {
            "category":"Shopping",
            "subcategory":"Computers & Home Electronics",
            "type":"Retail Goods"
        }
    ],
    "sg:phone":"+1 952 261 1230",
    "sg:postcode":"55420",
    "sg:province":"MN",
    "sg:tags":[
        "supplies-wholesale",
        "manufacturer",
        "electronic",
        "consumer",
        "equipment"
    ],
    "wof:name":"Sheys Gadgets & Stuff",
    "wof:placetype":"venue"
},
  "geometry": {"coordinates":[-93.289838,44.846525],"type":"Point"}
}