{
  "type": "Feature",
  "properties": {
    "addr:full":"9210 Wyoming Ave N Brooklyn Park MN 55445",
    "addr:housenumber":"9210",
    "addr:postcode":"55445",
    "addr:street":"Wyoming Ave N",
    "iso:country":"US",
    "sg:address":"9210 Wyoming Ave N",
    "sg:city":"Brooklyn Park",
    "sg:classifiers":[
        {
            "category":"Organizations",
            "subcategory":"Religious Organization",
            "type":"Services"
        }
    ],
    "sg:phone":"+1 763 493 0091",
    "sg:postcode":"55445",
    "sg:province":"MN",
    "sg:tags":[
        "church"
    ],
    "wof:name":"Promised Land",
    "wof:placetype":"venue"
},
  "geometry": {"coordinates":[-93.38185300000001,45.120449],"type":"Point"}
}