{
  "type": "Feature",
  "properties": {
    "iso:country":"US",
    "sg:address":"527 Marquette Ave S",
    "sg:city":"Minneapolis",
    "sg:classifiers":[
        {
            "category":"Banks & Credit Unions",
            "subcategory":"Financial Services",
            "type":"Services"
        }
    ],
    "sg:phone":"+1 612 338 1000",
    "sg:postcode":"55402",
    "sg:province":"MN",
    "sg:tags":[
        "investment",
        "real estate"
    ],
    "wof:name":"Litchfield Center Partners LLC",
    "wof:placetype":"venue"
},
  "geometry": {"coordinates":[-93.269257,44.978232],"type":"Point"}
}