{
  "type": "Feature",
  "properties": {
    "iso:country":"US",
    "sg:address":"17565 Highway 65 NE",
    "sg:city":"Andover",
    "sg:classifiers":[
        {
            "category":"Education",
            "subcategory":"Special Training",
            "type":"Public Place"
        },
        {
            "category":"Social Services",
            "subcategory":"Child Care",
            "type":"Services"
        }
    ],
    "sg:phone":"+1 763 432 3897",
    "sg:postcode":"55304",
    "sg:province":"MN",
    "sg:tags":[
        "educational",
        "nursery",
        "day"
    ],
    "wof:name":"Learn And Grow Child Care And Learning Center",
    "wof:placetype":"venue"
},
  "geometry": {"coordinates":[-93.23544099999999,45.269824],"type":"Point"}
}