{
  "type": "Feature",
  "properties": {
    "addr:full":"1005 High Ave Willmar MN 56201",
    "addr:housenumber":"1005",
    "addr:postcode":"56201",
    "addr:street":"High Ave",
    "iso:country":"US",
    "sg:address":"1005 High Ave",
    "sg:city":"Willmar",
    "sg:classifiers":[
        {
            "category":"Professional",
            "subcategory":"Detective & Security Services",
            "type":"Services"
        }
    ],
    "sg:phone":"+1 320 231 0008",
    "sg:postcode":"56201",
    "sg:province":"MN",
    "sg:tags":[
        "information",
        "bureau"
    ],
    "wof:name":"Prairie Country Resource Conservation And Development Council",
    "wof:placetype":"venue"
},
  "geometry": {"coordinates":[-95.03279000000001,45.126824],"type":"Point"}
}