{
  "type": "Feature",
  "properties": {
    "addr:full":"3304 W 44th St Minneapolis MN 55410",
    "addr:housenumber":"3304",
    "addr:postcode":"55410",
    "addr:street":"W 44Th St",
    "iso:country":"US",
    "sg:address":"3304 W 44th St",
    "sg:city":"Minneapolis",
    "sg:classifiers":[
        {
            "category":"Health Services",
            "subcategory":"Doctor",
            "type":"Services"
        },
        {
            "category":"Health Services",
            "subcategory":"Clinic",
            "type":"Services"
        },
        {
            "category":"Community Center",
            "type":"Public Place"
        },
        {
            "category":"Health Services",
            "subcategory":"Chiropractor",
            "type":"Services"
        }
    ],
    "sg:phone":"+1 612 929 2168",
    "sg:postcode":"55410",
    "sg:province":"MN",
    "sg:tags":[
        "physician",
        "medical",
        "surgeon",
        "chiropractic"
    ],
    "wof:name":"Life In Light",
    "wof:placetype":"venue"
},
  "geometry": {"coordinates":[-93.321478,44.923359],"type":"Point"}
}