{
  "type": "Feature",
  "properties": {
    "addr:full":"8332 State Hwy 7 Minneapolis MN 55426",
    "addr:housenumber":"8332",
    "addr:postcode":"55426",
    "addr:street":"State Hwy 7",
    "iso:country":"US",
    "sg:address":"8332 State Hwy 7",
    "sg:city":"Minneapolis",
    "sg:classifiers":[
        {
            "category":"Restaurant",
            "type":"Food & Drink"
        }
    ],
    "sg:phone":"+1 952 938 2610",
    "sg:postcode":"55426",
    "sg:province":"MN",
    "sg:tags":[
        "eating"
    ],
    "wof:name":"Pizza & Sub Express Inc",
    "wof:placetype":"venue"
},
  "geometry": {"coordinates":[-93.38382,44.936049],"type":"Point"}
}