{
  "type": "Feature",
  "properties": {
    "addr:full":"6441 Country Ln SW Farwell MN 56327",
    "addr:housenumber":"6441",
    "addr:postcode":"56327",
    "addr:street":"Country Ln Sw",
    "iso:country":"US",
    "sg:address":"6441 Country Ln SW",
    "sg:city":"Farwell",
    "sg:classifiers":[
        {
            "category":"Health Services",
            "subcategory":"Medical Lab",
            "type":"Services"
        }
    ],
    "sg:phone":"+1 320 886 2994",
    "sg:postcode":"56327",
    "sg:province":"MN",
    "sg:tags":[
        "laboratory"
    ],
    "wof:name":"Professional Crown & Bridge",
    "wof:placetype":"venue"
},
  "geometry": {"coordinates":[-95.54975,45.833496],"type":"Point"}
}