{
  "type": "Feature",
  "properties": {
    "addr:full":"46445 350th St Gaylord MN 55334",
    "addr:housenumber":"46445",
    "addr:postcode":"55334",
    "addr:street":"350Th St",
    "iso:country":"US",
    "sg:address":"46445 350th St",
    "sg:city":"Gaylord",
    "sg:phone":"+1 507 246 5251",
    "sg:postcode":"55334",
    "sg:province":"MN",
    "sg:tags":[
        "farm",
        "soybean"
    ],
    "wof:name":"Spencer Schott",
    "wof:placetype":"venue"
},
  "geometry": {"coordinates":[-94.196316,44.441844],"type":"Point"}
}