{
  "type": "Feature",
  "properties": {
    "iso:country":"US",
    "sg:address":"10913 Butternut St NW",
    "sg:city":"Minneapolis",
    "sg:classifiers":[
        {
            "category":"Social Services",
            "type":"Services"
        }
    ],
    "sg:phone":"+1 763 755 0514",
    "sg:postcode":"55448",
    "sg:province":"MN",
    "wof:name":"REM Wavered Services",
    "wof:placetype":"venue"
},
  "geometry": {"coordinates":[-93.26963000000001,45.16855],"type":"Point"}
}