{
  "type": "Feature",
  "properties": {
    "addr:full":"2500 Co Rd B W St Paul MN 55113",
    "addr:housenumber":"2500",
    "addr:postcode":"55113",
    "addr:street":"Co Rd;W St",
    "iso:country":"US",
    "sg:address":"2500 Co Rd B W",
    "sg:city":"St Paul",
    "sg:classifiers":[
        {
            "category":"Manufacturing",
            "subcategory":"Metals",
            "type":"Manufacturing & Wholesale Goods"
        }
    ],
    "sg:phone":"+1 651 639 0009",
    "sg:postcode":"55113",
    "sg:province":"MN",
    "sg:tags":[
        "steel"
    ],
    "wof:name":"D & M Iron Work Inc",
    "wof:placetype":"venue"
},
  "geometry": {"coordinates":[-93.203872,45.006055],"type":"Point"}
}