{
  "type": "Feature",
  "properties": {
    "addr:full":"35904 190th Ave Goodhue MN 55027",
    "addr:housenumber":"35904",
    "addr:postcode":"55027",
    "addr:street":"190Th Ave",
    "iso:country":"US",
    "sg:address":"35904 190th Ave",
    "sg:city":"Goodhue",
    "sg:classifiers":[
        {
            "category":"Farming",
            "subcategory":"Dairy Farm",
            "type":"Manufacturing & Wholesale Goods"
        }
    ],
    "sg:phone":"+1 651 923 4910",
    "sg:postcode":"55027",
    "sg:province":"MN",
    "wof:name":"D B Holsteins",
    "wof:placetype":"venue"
},
  "geometry": {"coordinates":[-92.651567,44.428417],"type":"Point"}
}