{
  "type": "Feature",
  "properties": {
    "addr:full":"28823 290th Ave Sleepy Eye MN 56085",
    "addr:housenumber":"28823",
    "addr:postcode":"56085",
    "addr:street":"290Th Ave",
    "iso:country":"US",
    "sg:address":"28823 290th Ave",
    "sg:city":"Sleepy Eye",
    "sg:phone":"+1 507 794 7891",
    "sg:postcode":"56085",
    "sg:province":"MN",
    "sg:tags":[
        "hog",
        "wheat",
        "farm",
        "corn",
        "cash",
        "grain",
        "or"
    ],
    "wof:name":"Mark Rasmussen",
    "wof:placetype":"venue"
},
  "geometry": {"coordinates":[-94.765216,44.382772],"type":"Point"}
}