{
  "type": "Feature",
  "properties": {
    "iso:country":"US",
    "sg:address":"4500 Park Glen Rd",
    "sg:city":"Minneapolis",
    "sg:classifiers":[
        {
            "category":"Health Services",
            "subcategory":"Doctor",
            "type":"Services"
        }
    ],
    "sg:phone":"+1 952 929 9478",
    "sg:postcode":"55416",
    "sg:province":"MN",
    "sg:tags":[
        "physician",
        "surgeon"
    ],
    "wof:name":"Douglas A Hedlund MD",
    "wof:placetype":"venue"
},
  "geometry": {"coordinates":[-93.339327,44.942485],"type":"Point"}
}