{
  "type": "Feature",
  "properties": {
    "iso:country":"US",
    "sg:address":"2625 Dupont Ave S",
    "sg:city":"Minneapolis",
    "sg:classifiers":[
        {
            "category":"Building & Trades",
            "subcategory":"Construction",
            "type":"Services"
        }
    ],
    "sg:phone":"+1 612 377 0000",
    "sg:postcode":"55408",
    "sg:province":"MN",
    "sg:tags":[
        "house",
        "nonresidential"
    ],
    "wof:name":"Arien Contracting",
    "wof:placetype":"venue"
},
  "geometry": {"coordinates":[-93.293083,44.954182],"type":"Point"}
}