{
  "type": "Feature",
  "properties": {
    "iso:country":"US",
    "sg:address":"1125 S Frontage Rd",
    "sg:city":"Hastings",
    "sg:classifiers":[
        {
            "category":"Travel",
            "subcategory":"Hotels & Motels",
            "type":"Entertainment"
        }
    ],
    "sg:phone":"+1 651 480 2090",
    "sg:postcode":"55033",
    "sg:province":"MN",
    "sg:tags":[
        "resort"
    ],
    "wof:name":"Midwest Outdoor Resorts LLC",
    "wof:placetype":"venue"
},
  "geometry": {"coordinates":[-92.87127099999999,44.738029],"type":"Point"}
}