{
  "type": "Feature",
  "properties": {
    "addr:full":"2135 90th St SW Appleton MN 56208",
    "addr:housenumber":"2135",
    "addr:postcode":"56208",
    "addr:street":"90Th St Sw",
    "iso:country":"US",
    "sg:address":"2135 90th St SW",
    "sg:city":"Appleton",
    "sg:classifiers":[
        {
            "category":"Restaurant",
            "type":"Food & Drink"
        }
    ],
    "sg:phone":"+1 320 289 2582",
    "sg:postcode":"56208",
    "sg:province":"MN",
    "sg:tags":[
        "pizza"
    ],
    "wof:name":"Austria Florante",
    "wof:placetype":"venue"
},
  "geometry": {"coordinates":[-96.000815,45.195531],"type":"Point"}
}