{
  "type": "Feature",
  "properties": {
    "addr:full":"8197 Savanna Valley Way Victoria MN 55386",
    "addr:housenumber":"8197",
    "addr:postcode":"55386",
    "addr:street":"Savanna Valley Way",
    "iso:country":"US",
    "sg:address":"8197 Savanna Valley Way",
    "sg:city":"Victoria",
    "sg:classifiers":[
        {
            "category":"Building & Trades",
            "subcategory":"Construction",
            "type":"Services"
        }
    ],
    "sg:phone":"+1 952 443 4138",
    "sg:postcode":"55386",
    "sg:province":"MN",
    "sg:tags":[
        "home",
        "builder"
    ],
    "wof:name":"Rottlund Homes",
    "wof:placetype":"venue"
},
  "geometry": {"coordinates":[-93.647522,44.856448],"type":"Point"}
}