{
  "type": "Feature",
  "properties": {
    "addr:full":"28795 611th Ave Gibbon MN 55335",
    "addr:housenumber":"28795",
    "addr:postcode":"55335",
    "addr:street":"611Th Ave",
    "iso:country":"US",
    "sg:address":"28795 611th Ave",
    "sg:city":"Gibbon",
    "sg:classifiers":[
        {
            "category":"Insurance",
            "subcategory":"Hazard Insurance",
            "type":"Services"
        }
    ],
    "sg:phone":"+1 507 834 9784",
    "sg:postcode":"55335",
    "sg:province":"MN",
    "wof:name":"Gregory Ross Wickenhauser",
    "wof:placetype":"venue"
},
  "geometry": {"coordinates":[-94.49198699999999,44.530261],"type":"Point"}
}