{
  "type": "Feature",
  "properties": {
    "iso:country":"US",
    "sg:address":"111 Golf Course Rd",
    "sg:city":"Grand Rapids",
    "sg:classifiers":[
        {
            "category":"Health Services",
            "subcategory":"Health Practitioner",
            "type":"Services"
        }
    ],
    "sg:phone":"+1 218 327 7257",
    "sg:postcode":"55744",
    "sg:province":"MN",
    "sg:tags":[
        "therapist",
        "physical"
    ],
    "wof:name":"Radtke Physical Therapy West",
    "wof:placetype":"venue"
},
  "geometry": {"coordinates":[-93.530345,47.221262],"type":"Point"}
}