{
  "type": "Feature",
  "properties": {
    "addr:full":"330 8th St Walnut Grove MN 56180",
    "addr:housenumber":"330",
    "addr:postcode":"56180",
    "addr:street":"8Th St",
    "iso:country":"US",
    "sg:address":"330 8th St",
    "sg:city":"Walnut Grove",
    "sg:classifiers":[
        {
            "category":"Museum",
            "type":"Entertainment"
        }
    ],
    "sg:phone":"+1 507 859 2358",
    "sg:postcode":"56180",
    "sg:province":"MN",
    "sg:tags":[
        "gallery"
    ],
    "wof:name":"Wilder Museum and Info Ctr",
    "wof:placetype":"venue"
},
  "geometry": {"coordinates":[-95.472601,44.224711],"type":"Point"}
}