{
  "type": "Feature",
  "properties": {
    "iso:country":"US",
    "sg:address":"5922 167th Ave NW",
    "sg:city":"Ramsey",
    "sg:classifiers":[
        {
            "category":"Personal",
            "subcategory":"Beauty Salon",
            "type":"Services"
        }
    ],
    "sg:phone":"+1 763 213 8140",
    "sg:postcode":"55303",
    "sg:province":"MN",
    "wof:name":"Pure Bliss Hair Design",
    "wof:placetype":"venue"
},
  "geometry": {"coordinates":[-93.41740299999999,45.273728],"type":"Point"}
}