{
  "type": "Feature",
  "properties": {
    "addr:full":"4344 131st Ct Savage MN 55378",
    "addr:housenumber":"4344",
    "addr:postcode":"55378",
    "addr:street":"131St Ct",
    "iso:country":"US",
    "sg:address":"4344 131st Ct",
    "sg:city":"Savage",
    "sg:classifiers":[
        {
            "category":"Social Services",
            "subcategory":"Child Care",
            "type":"Services"
        }
    ],
    "sg:phone":"+1 952 882 0847",
    "sg:postcode":"55378",
    "sg:province":"MN",
    "sg:tags":[
        "daycare",
        "provider"
    ],
    "wof:name":"Becky Saeger",
    "wof:placetype":"venue"
},
  "geometry": {"coordinates":[-93.334435,44.766155],"type":"Point"}
}