{
  "type": "Feature",
  "properties": {
    "iso:country":"US",
    "sg:address":"11819 Bemidji Rd NE",
    "sg:city":"Bemidji",
    "sg:classifiers":[
        {
            "category":"Building & Trades",
            "subcategory":"Construction",
            "type":"Services"
        }
    ],
    "sg:phone":"+1 218 586 3325",
    "sg:postcode":"56601",
    "sg:province":"MN",
    "sg:tags":[
        "excavation",
        "excavating",
        "contractor"
    ],
    "wof:name":"Jason Verlund Bobcat Service",
    "wof:placetype":"venue"
},
  "geometry": {"coordinates":[-94.790086,47.58404],"type":"Point"}
}