{
  "type": "Feature",
  "properties": {
    "addr:full":"2100 Nicollet Ave Minneapolis MN 55404",
    "addr:housenumber":"2100",
    "addr:postcode":"55404",
    "addr:street":"Nicollet Ave",
    "iso:country":"US",
    "sg:address":"2100 Nicollet Ave",
    "sg:city":"Minneapolis",
    "sg:classifiers":[
        {
            "category":"Health Services",
            "subcategory":"Clinic",
            "type":"Services"
        }
    ],
    "sg:phone":"+1 612 871 9044",
    "sg:postcode":"55404",
    "sg:province":"MN",
    "sg:tags":[
        "welfare"
    ],
    "wof:name":"Hannaya Health Care Inc",
    "wof:placetype":"venue"
},
  "geometry": {"coordinates":[-93.277805,44.961781],"type":"Point"}
}