{
  "type": "Feature",
  "properties": {
    "iso:country":"US",
    "sg:address":"1854 Grand Ave",
    "sg:city":"Saint Paul",
    "sg:classifiers":[
        {
            "category":"Insurance",
            "subcategory":"Insurance Agent",
            "type":"Services"
        }
    ],
    "sg:phone":"+1 651 690 0056",
    "sg:postcode":"55105",
    "sg:province":"MN",
    "wof:name":"Allstate",
    "wof:placetype":"venue"
},
  "geometry": {"coordinates":[-93.178624,44.940022],"type":"Point"}
}