{
  "type": "Feature",
  "properties": {
    "addr:full":"1545 Industrial Dr Blue Earth MN 56013",
    "addr:housenumber":"1545",
    "addr:postcode":"56013",
    "addr:street":"Industrial Dr",
    "iso:country":"US",
    "sg:address":"1545 Industrial Dr",
    "sg:city":"Blue Earth",
    "sg:classifiers":[
        {
            "category":"Manufacturing",
            "subcategory":"Motor Vehicles & Parts",
            "type":"Manufacturing & Wholesale Goods"
        }
    ],
    "sg:phone":"+1 507 526 3247",
    "sg:postcode":"56013",
    "sg:province":"MN",
    "sg:tags":[
        "body",
        "running",
        "truck",
        "boards",
        "mfg"
    ],
    "wof:name":"Tafco Equipment Co",
    "wof:placetype":"venue"
},
  "geometry": {"coordinates":[-94.11994900000001,43.646609],"type":"Point"}
}