{
  "type": "Feature",
  "properties": {
    "addr:full":"572 E 2nd St Winona MN 55987",
    "addr:housenumber":"572",
    "addr:postcode":"55987",
    "addr:street":"E 2Nd St",
    "iso:country":"US",
    "sg:address":"572 E 2nd St",
    "sg:city":"Winona",
    "sg:classifiers":[
        {
            "category":"Building & Trades",
            "subcategory":"Construction",
            "type":"Services"
        }
    ],
    "sg:phone":"+1 507 454 4375",
    "sg:postcode":"55987",
    "sg:province":"MN",
    "sg:tags":[
        "general",
        "contractor"
    ],
    "wof:name":"Al's Construction",
    "wof:placetype":"venue"
},
  "geometry": {"coordinates":[-91.62220000000001,44.049502],"type":"Point"}
}