{
  "type": "Feature",
  "properties": {
    "addr:full":"16116 Gleason Lake Dr Wayzata MN 55391",
    "addr:housenumber":"16116",
    "addr:postcode":"wayzata;55391",
    "addr:street":"Gleason Lake Dr",
    "iso:country":"US",
    "sg:address":"16116 Gleason Lake Dr",
    "sg:city":"Wayzata",
    "sg:classifiers":[
        {
            "category":"Personal",
            "type":"Services"
        },
        {
            "category":"Building & Trades",
            "subcategory":"Construction",
            "type":"Services"
        }
    ],
    "sg:phone":"+1 952 404 9500",
    "sg:postcode":"55391",
    "sg:province":"MN",
    "sg:tags":[
        "painter",
        "contractor"
    ],
    "wof:name":"A & P Finishing Contractors",
    "wof:placetype":"venue"
},
  "geometry": {"coordinates":[-93.482018,44.978441],"type":"Point"}
}