{
  "type": "Feature",
  "properties": {
    "addr:full":"2424 150th St W Faribault MN 55021",
    "addr:housenumber":"2424",
    "addr:postcode":"55021",
    "addr:street":"150Th St W",
    "iso:country":"US",
    "sg:address":"2424 150th St W",
    "sg:city":"Faribault",
    "sg:classifiers":[
        {
            "category":"Bars & Pubs",
            "type":"Food & Drink"
        }
    ],
    "sg:phone":"+1 507 333 5488",
    "sg:postcode":"55021",
    "sg:province":"MN",
    "sg:tags":[
        "drinking"
    ],
    "wof:name":"Breath of Life Studio",
    "wof:placetype":"venue"
},
  "geometry": {"coordinates":[-93.312803,44.370626],"type":"Point"}
}