{
  "type": "Feature",
  "properties": {
    "addr:full":"318 4th St Gaylord MN 55334",
    "addr:housenumber":"318",
    "addr:postcode":"55334",
    "addr:street":"4Th St",
    "iso:country":"US",
    "sg:address":"318 4th St",
    "sg:city":"Gaylord",
    "sg:classifiers":[
        {
            "category":"Place Of Worship",
            "subcategory":"Church",
            "type":"Public Place"
        },
        {
            "category":"Place Of Worship",
            "type":"Public Place"
        }
    ],
    "sg:phone":"+1 507 237 2595",
    "sg:postcode":"55334",
    "sg:province":"MN",
    "sg:tags":[
        "testament",
        "christ-new",
        "churches-church",
        "christ"
    ],
    "wof:name":"United Church Of Christ",
    "wof:placetype":"venue"
},
  "geometry": {"coordinates":[-94.220578,44.554357],"type":"Point"}
}