{
  "type": "Feature",
  "properties": {
    "iso:country":"US",
    "sg:address":"17 Thomas Ln",
    "sg:city":"Buffalo",
    "sg:classifiers":[
        {
            "category":"Professional",
            "subcategory":"Accounting & Tax Preparation",
            "type":"Services"
        }
    ],
    "sg:phone":"+1 763 682 3859",
    "sg:postcode":"55318",
    "sg:province":"MN",
    "wof:name":"Edwin A Sherwin",
    "wof:placetype":"venue"
},
  "geometry": {"coordinates":[-93.58869,44.806309],"type":"Point"}
}