{
  "type": "Feature",
  "properties": {
    "iso:country":"US",
    "sg:address":"4453 State Hwy 95",
    "sg:city":"Cambridge",
    "sg:classifiers":[
        {
            "category":"Retail",
            "subcategory":"Car Wash",
            "type":"Services"
        }
    ],
    "sg:phone":"+1 763 689 3525",
    "sg:postcode":"55008",
    "sg:province":"MN",
    "sg:tags":[
        "carwash"
    ],
    "wof:name":"Auto Crafters Plus",
    "wof:placetype":"venue"
},
  "geometry": {"coordinates":[-93.153566,45.558162],"type":"Point"}
}