{
  "type": "Feature",
  "properties": {
    "iso:country":"US",
    "sg:address":"3601 W 76th St Ste 200",
    "sg:city":"Minneapolis",
    "sg:classifiers":[
        {
            "category":"Professional",
            "subcategory":"Computer Services",
            "type":"Services"
        }
    ],
    "sg:phone":"+1 952 897 4500",
    "sg:postcode":"55435",
    "sg:province":"MN",
    "sg:tags":[
        "consultant",
        "designer",
        "system"
    ],
    "sg:website":"http://www.analysts.com",
    "wof:name":"Analysts International Corporation",
    "wof:placetype":"venue"
},
  "geometry": {"coordinates":[-93.324973,44.865142],"type":"Point"}
}