{
  "type": "Feature",
  "properties": {
    "addr:full":"1272 Co Rd 112 SW Montrose MN 55363",
    "addr:housenumber":"1272",
    "addr:postcode":"55363",
    "addr:street":"Co Rd 112 Sw",
    "iso:country":"US",
    "sg:address":"1272 Co Rd 112 SW",
    "sg:city":"Montrose",
    "sg:phone":"+1 952 955 1785",
    "sg:postcode":"55363",
    "sg:province":"MN",
    "sg:tags":[
        "farm",
        "soybean"
    ],
    "wof:name":"Gene Janikula",
    "wof:placetype":"venue"
},
  "geometry": {"coordinates":[-93.91610900000001,44.985688],"type":"Point"}
}