{
  "type": "Feature",
  "properties": {
    "addr:full":"16920 15th St SE Blomkest MN 56216",
    "addr:housenumber":"16920",
    "addr:postcode":"56216",
    "addr:street":"15Th St Se",
    "iso:country":"US",
    "sg:address":"16920 15th St SE",
    "sg:city":"Blomkest",
    "sg:classifiers":[
        {
            "category":"Shopping",
            "subcategory":"Hobbies, Toys, & Games",
            "type":"Retail Goods"
        }
    ],
    "sg:phone":"+1 320 995 6588",
    "sg:postcode":"56216",
    "sg:province":"MN",
    "sg:tags":[
        "item"
    ],
    "wof:name":"Anderson Enterprises",
    "wof:placetype":"venue"
},
  "geometry": {"coordinates":[-95.023371,44.959176],"type":"Point"}
}