{
  "type": "Feature",
  "properties": {
    "iso:country":"US",
    "sg:address":"118 12th St",
    "sg:city":"Cloquet",
    "sg:classifiers":[
        {
            "category":"Retail",
            "subcategory":"Animal Services",
            "type":"Services"
        }
    ],
    "sg:phone":"+1 218 878 1857",
    "sg:postcode":"55720",
    "sg:province":"MN",
    "sg:tags":[
        "pet",
        "grooming",
        "washing"
    ],
    "wof:name":"Groomingdale's",
    "wof:placetype":"venue"
},
  "geometry": {"coordinates":[-92.45129900000001,46.719561],"type":"Point"}
}