{
  "type": "Feature",
  "properties": {
    "addr:full":"525 Game Farm Rd N Maple Plain MN 55359",
    "addr:housenumber":"525",
    "addr:postcode":"55359",
    "addr:street":"Game Farm Rd N;Plain",
    "iso:country":"US",
    "sg:address":"525 Game Farm Rd N",
    "sg:city":"Maple Plain",
    "sg:classifiers":[
        {
            "category":"Wholesale",
            "subcategory":"Auto Parts",
            "type":"Manufacturing & Wholesale Goods"
        }
    ],
    "sg:phone":"+1 763 479 2129",
    "sg:postcode":"55359",
    "sg:province":"MN",
    "wof:name":"Rosenthal Sales",
    "wof:placetype":"venue"
},
  "geometry": {"coordinates":[-93.70647,44.969527],"type":"Point"}
}