{
  "type": "Feature",
  "properties": {
    "addr:full":"7570 State Hwy 65 Minneapolis MN 55432",
    "addr:housenumber":"7570",
    "addr:postcode":"55432",
    "addr:street":"State Hwy 65",
    "iso:country":"US",
    "sg:address":"7570 State Hwy 65",
    "sg:city":"Minneapolis",
    "sg:classifiers":[
        {
            "category":"Wholesale",
            "subcategory":"Non-durable Goods",
            "type":"Manufacturing & Wholesale Goods"
        },
        {
            "category":"Wholesale",
            "subcategory":"Durable Goods & Equipment",
            "type":"Manufacturing & Wholesale Goods"
        }
    ],
    "sg:phone":"+1 763 783 7338",
    "sg:postcode":"55432",
    "sg:province":"MN",
    "sg:tags":[
        "importer"
    ],
    "wof:name":"Island Import & Exports",
    "wof:placetype":"venue"
},
  "geometry": {"coordinates":[-93.24394599999999,45.104409],"type":"Point"}
}