{
  "type": "Feature",
  "properties": {
    "addr:full":"2685 Quail Ave N Minneapolis MN 55422",
    "addr:housenumber":"2685",
    "addr:postcode":"55422",
    "addr:street":"Quail Ave N",
    "iso:country":"US",
    "sg:address":"2685 Quail Ave N",
    "sg:city":"Minneapolis",
    "sg:classifiers":[
        {
            "category":"Shopping",
            "subcategory":"Computers & Home Electronics",
            "type":"Retail Goods"
        }
    ],
    "sg:phone":"+1 763 588 2559",
    "sg:postcode":"55422",
    "sg:province":"MN",
    "wof:name":"Ira Hackner",
    "wof:placetype":"venue"
},
  "geometry": {"coordinates":[-93.342921,45.00481],"type":"Point"}
}