{
  "type": "Feature",
  "properties": {
    "iso:country":"US",
    "sg:address":"3579 Blue Jay Way",
    "sg:city":"Saint Paul",
    "sg:classifiers":[
        {
            "category":"Banks & Credit Unions",
            "subcategory":"Financial Services",
            "type":"Services"
        }
    ],
    "sg:phone":"+1 651 452 9055",
    "sg:postcode":"55123",
    "sg:province":"MN",
    "sg:tags":[
        "investor"
    ],
    "wof:name":"Let It Ride Investment Club",
    "wof:placetype":"venue"
},
  "geometry": {"coordinates":[-93.142673,44.826868],"type":"Point"}
}