{
  "type": "Feature",
  "properties": {
    "addr:full":"24 Leroy Ave Farwell MN 56327",
    "addr:housenumber":"24",
    "addr:postcode":"56327",
    "addr:street":"Leroy Ave",
    "iso:country":"US",
    "sg:address":"24 Leroy Ave",
    "sg:city":"Farwell",
    "sg:classifiers":[
        {
            "category":"Professional",
            "type":"Services"
        }
    ],
    "sg:phone":"+1 320 283 5084",
    "sg:postcode":"56327",
    "sg:province":"MN",
    "sg:tags":[
        "establishment"
    ],
    "wof:name":"MBJ Assoc",
    "wof:placetype":"venue"
},
  "geometry": {"coordinates":[-95.616046,45.752199],"type":"Point"}
}