{
  "type": "Feature",
  "properties": {
    "iso:country":"US",
    "sg:address":"1001 Mainstreet",
    "sg:city":"Hopkins",
    "sg:classifiers":[
        {
            "category":"Personal",
            "subcategory":"Tanning Parlor",
            "type":"Services"
        },
        {
            "category":"Personal",
            "type":"Services"
        }
    ],
    "sg:phone":"+1 952 933 6666",
    "sg:postcode":"55343",
    "sg:province":"MN",
    "sg:tags":[
        "salon"
    ],
    "wof:name":"Tropical Minnesota Inc",
    "wof:placetype":"venue"
},
  "geometry": {"coordinates":[-93.413963,44.924369],"type":"Point"}
}