{
  "type": "Feature",
  "properties": {
    "addr:full":"740 24th Ave SE Minneapolis MN 55414",
    "addr:housenumber":"740",
    "addr:postcode":"55414",
    "addr:street":"24Th Ave Se",
    "iso:country":"US",
    "sg:address":"740 24th Ave SE",
    "sg:city":"Minneapolis",
    "sg:classifiers":[
        {
            "category":"Autos & Motor Vehicles",
            "subcategory":"Auto Supplies",
            "type":"Retail Goods"
        }
    ],
    "sg:phone":"+1 612 378 0505",
    "sg:postcode":"55414",
    "sg:province":"MN",
    "sg:tags":[
        "tire"
    ],
    "wof:name":"Gcr Truck Tire Center",
    "wof:placetype":"venue"
},
  "geometry": {"coordinates":[-93.21839900000001,44.983501],"type":"Point"}
}