{
  "type": "Feature",
  "properties": {
    "iso:country":"US",
    "sg:address":"401 N 3rd St Ste 676",
    "sg:city":"Minneapolis",
    "sg:classifiers":[
        {
            "category":"Arts & Performance",
            "subcategory":"Theater",
            "type":"Entertainment"
        }
    ],
    "sg:phone":"+1 612 339 5693",
    "sg:postcode":"55401",
    "sg:province":"MN",
    "sg:tags":[
        "theatrical",
        "agency"
    ],
    "sg:website":"http://www.hawthornegroupinc.com",
    "wof:name":"Hawthorne Management",
    "wof:placetype":"venue"
},
  "geometry": {"coordinates":[-93.275581,44.985058],"type":"Point"}
}