{
  "type": "Feature",
  "properties": {
    "addr:full":"1011 Osborne Rd NE Minneapolis MN 55432",
    "addr:housenumber":"1011",
    "addr:postcode":"55432",
    "addr:street":"Osborne Rd Ne",
    "iso:country":"US",
    "sg:address":"1011 Osborne Rd NE",
    "sg:city":"Minneapolis",
    "sg:classifiers":[
        {
            "category":"Building & Trades",
            "subcategory":"Construction",
            "type":"Services"
        }
    ],
    "sg:phone":"+1 763 533 3752",
    "sg:postcode":"55432",
    "sg:province":"MN",
    "sg:tags":[
        "house",
        "contractor"
    ],
    "wof:name":"Family One Builders",
    "wof:placetype":"venue"
},
  "geometry": {"coordinates":[-93.245446,45.107943],"type":"Point"}
}