{
  "type": "Feature",
  "properties": {
    "iso:country":"US",
    "sg:address":"1619 Division St",
    "sg:city":"Waite Park",
    "sg:classifiers":[
        {
            "category":"Health Services",
            "subcategory":"Clinic",
            "type":"Services"
        }
    ],
    "sg:phone":"+1 320 255 0333",
    "sg:postcode":"56387",
    "sg:province":"MN",
    "sg:tags":[
        "specialty",
        "outpatient"
    ],
    "wof:name":"Stubbe & Associates",
    "wof:placetype":"venue"
},
  "geometry": {"coordinates":[-94.237073,45.553782],"type":"Point"}
}