{
  "type": "Feature",
  "properties": {
    "iso:country":"US",
    "sg:address":"7701 Arlington Ave N",
    "sg:city":"Minneapolis",
    "sg:classifiers":[
        {
            "category":"Shopping",
            "subcategory":"Gifts & Souvenirs",
            "type":"Retail Goods"
        }
    ],
    "sg:phone":"+1 763 566 6386",
    "sg:postcode":"55443",
    "sg:province":"MN",
    "wof:name":"Tisket A Tasket",
    "wof:placetype":"venue"
},
  "geometry": {"coordinates":[-93.347984,45.096911],"type":"Point"}
}