{
  "type": "Feature",
  "properties": {
    "addr:full":"2700 Stevens Ave S Minneapolis MN 55408",
    "addr:housenumber":"2700",
    "addr:postcode":"55408",
    "addr:street":"Stevens Ave S",
    "iso:country":"US",
    "sg:address":"2700 Stevens Ave S",
    "sg:city":"Minneapolis",
    "sg:classifiers":[
        {
            "category":"Organizations",
            "subcategory":"Religious Organization",
            "type":"Services"
        }
    ],
    "sg:phone":"+1 612 874 7622",
    "sg:postcode":"55408",
    "sg:province":"MN",
    "sg:tags":[
        "church"
    ],
    "wof:name":"Seventh-Day Adventist Church",
    "wof:placetype":"venue"
},
  "geometry": {"coordinates":[-93.275368,44.951941],"type":"Point"}
}