{
  "type": "Feature",
  "properties": {
    "iso:country":"US",
    "sg:address":"364 Cedardale Dr SE",
    "sg:city":"Owatonna",
    "sg:classifiers":[
        {
            "category":"Health Services",
            "subcategory":"Nursing And Care Facility",
            "type":"Services"
        }
    ],
    "sg:phone":"+1 507 446 8600",
    "sg:postcode":"55060",
    "sg:province":"MN",
    "sg:tags":[
        "skilled"
    ],
    "wof:name":"Clare Bridge Cottage Owatonna",
    "wof:placetype":"venue"
},
  "geometry": {"coordinates":[-93.219534,44.060713],"type":"Point"}
}