{
  "type": "Feature",
  "properties": {
    "iso:country":"US",
    "sg:address":"16386 83rd Ave",
    "sg:city":"Kimball",
    "sg:classifiers":[
        {
            "category":"Manufacturing",
            "subcategory":"Retail Goods",
            "type":"Manufacturing & Wholesale Goods"
        }
    ],
    "sg:phone":"+1 320 398 8944",
    "sg:postcode":"55353",
    "sg:province":"MN",
    "sg:tags":[
        "product",
        "mfg"
    ],
    "wof:name":"Jag Iron",
    "wof:placetype":"venue"
},
  "geometry": {"coordinates":[-94.279585,45.360212],"type":"Point"}
}