{
  "type": "Feature",
  "properties": {
    "iso:country":"US",
    "sg:address":"10621 Nassau St NE",
    "sg:city":"Blaine",
    "sg:classifiers":[
        {
            "category":"Wholesale",
            "subcategory":"Machinery & Supplies",
            "type":"Manufacturing & Wholesale Goods"
        }
    ],
    "sg:phone":"+1 763 792 9123",
    "sg:postcode":"55449",
    "sg:province":"MN",
    "sg:tags":[
        "contractor"
    ],
    "wof:name":"Gary Carlson Equipment Co",
    "wof:placetype":"venue"
},
  "geometry": {"coordinates":[-93.217637,45.16347],"type":"Point"}
}