{
  "type": "Feature",
  "properties": {
    "iso:country":"US",
    "sg:address":"4100 W 42nd St",
    "sg:city":"Minneapolis",
    "sg:classifiers":[
        {
            "category":"Education",
            "subcategory":"Preschool",
            "type":"Public Place"
        },
        {
            "category":"Education",
            "subcategory":"School",
            "type":"Public Place"
        }
    ],
    "sg:phone":"+1 952 929 4211",
    "sg:postcode":"55416",
    "sg:province":"MN",
    "sg:tags":[
        "elementary"
    ],
    "wof:name":"Golden Years Montessori Pre School",
    "wof:placetype":"venue"
},
  "geometry": {"coordinates":[-93.333,44.927101],"type":"Point"}
}