{
  "type": "Feature",
  "properties": {
    "addr:full":"6895 Rosemary Rd Eden Prairie MN 55346",
    "addr:housenumber":"6895",
    "addr:postcode":"55346",
    "addr:street":"Rosemary Rd",
    "iso:country":"US",
    "sg:address":"6895 Rosemary Rd",
    "sg:city":"Eden Prairie",
    "sg:classifiers":[
        {
            "category":"Social Services",
            "subcategory":"Child Care",
            "type":"Services"
        }
    ],
    "sg:phone":"+1 952 949 6756",
    "sg:postcode":"55346",
    "sg:province":"MN",
    "sg:tags":[
        "day"
    ],
    "wof:name":"Jody Schroepfer",
    "wof:placetype":"venue"
},
  "geometry": {"coordinates":[-93.45410099999999,44.877789],"type":"Point"}
}