{
  "type": "Feature",
  "properties": {
    "iso:country":"US",
    "sg:address":"3900 Arrowhead Dr",
    "sg:city":"Hamel",
    "sg:classifiers":[
        {
            "category":"Professional",
            "subcategory":"Management & Consulting",
            "type":"Services"
        }
    ],
    "sg:phone":"+1 763 478 6014",
    "sg:postcode":"55340",
    "sg:province":"MN",
    "sg:tags":[
        "consultant"
    ],
    "sg:website":"http://www.loram.com",
    "wof:name":"Loram Admin",
    "wof:placetype":"venue"
},
  "geometry": {"coordinates":[-93.563282,45.045595],"type":"Point"}
}