{
  "type": "Feature",
  "properties": {
    "addr:full":"6604 Warren Ave Minneapolis MN 55439",
    "addr:housenumber":"6604",
    "addr:postcode":"55439",
    "addr:street":"Warren Ave",
    "iso:country":"US",
    "sg:address":"6604 Warren Ave",
    "sg:city":"Minneapolis",
    "sg:classifiers":[
        {
            "category":"Wholesale",
            "subcategory":"Non-durable Goods",
            "type":"Manufacturing & Wholesale Goods"
        }
    ],
    "sg:phone":"+1 952 941 7328",
    "sg:postcode":"55439",
    "sg:province":"MN",
    "sg:tags":[
        "advertising",
        "specialty"
    ],
    "wof:name":"Advertising Specialties",
    "wof:placetype":"venue"
},
  "geometry": {"coordinates":[-93.357373,44.882574],"type":"Point"}
}