{
  "type": "Feature",
  "properties": {
    "addr:full":"471 Log Hoist Ct NW Tenstrike MN 56683",
    "addr:housenumber":"471",
    "addr:postcode":"56683",
    "addr:street":"Log Hoist Ct Nw Tenstrike",
    "iso:country":"US",
    "sg:address":"471 Log Hoist Ct NW",
    "sg:city":"Tenstrike",
    "sg:classifiers":[
        {
            "category":"Freight",
            "type":"Transportation"
        }
    ],
    "sg:phone":"+1 218 586 5007",
    "sg:postcode":"56683",
    "sg:province":"MN",
    "sg:tags":[
        "operator",
        "local",
        "trucking"
    ],
    "wof:name":"Sturman Trucking",
    "wof:placetype":"venue"
},
  "geometry": {"coordinates":[-94.686166,47.658529],"type":"Point"}
}