{
  "type": "Feature",
  "properties": {
    "iso:country":"US",
    "sg:address":"9117 13th St NE",
    "sg:city":"Saint Michael",
    "sg:classifiers":[
        {
            "category":"Social Services",
            "subcategory":"Child Care",
            "type":"Services"
        }
    ],
    "sg:phone":"+1 763 497 1810",
    "sg:postcode":"55376",
    "sg:province":"MN",
    "sg:tags":[
        "day"
    ],
    "wof:name":"Stephanie A Hahn",
    "wof:placetype":"venue"
},
  "geometry": {"coordinates":[-93.705879,45.171957],"type":"Point"}
}