{
  "type": "Feature",
  "properties": {
    "addr:full":"709 85th Ave N Minneapolis MN 55444",
    "addr:housenumber":"709",
    "addr:postcode":"55444",
    "addr:street":"85Th Ave N",
    "iso:country":"US",
    "sg:address":"709 85th Ave N",
    "sg:city":"Minneapolis",
    "sg:classifiers":[
        {
            "category":"Building & Trades",
            "subcategory":"Construction",
            "type":"Services"
        }
    ],
    "sg:phone":"+1 763 566 0051",
    "sg:postcode":"55444",
    "sg:province":"MN",
    "sg:tags":[
        "industrial",
        "system",
        "altering",
        "heating",
        "specialty",
        "contractors-commercial",
        "contractor",
        "remodeling",
        "air conditioning"
    ],
    "wof:name":"Glenmark Construction Inc",
    "wof:placetype":"venue"
},
  "geometry": {"coordinates":[-93.290064,45.108614],"type":"Point"}
}