{
  "type": "Feature",
  "properties": {
    "addr:full":"10083 Austin Rd Blooming Prairie MN 55917",
    "addr:housenumber":"10083",
    "addr:postcode":"55917",
    "addr:street":"Austin Rd",
    "iso:country":"US",
    "sg:address":"10083 Austin Rd",
    "sg:city":"Blooming Prairie",
    "sg:phone":"+1 507 583 7182",
    "sg:postcode":"55917",
    "sg:province":"MN",
    "sg:tags":[
        "farm",
        "corn"
    ],
    "wof:name":"David Kaplan",
    "wof:placetype":"venue"
},
  "geometry": {"coordinates":[-93.08582699999999,43.957415],"type":"Point"}
}