{
  "type": "Feature",
  "properties": {
    "iso:country":"US",
    "sg:address":"46050 Goose Creek Rd",
    "sg:city":"Harris",
    "sg:classifiers":[
        {
            "category":"Freight",
            "type":"Transportation"
        }
    ],
    "sg:phone":"+1 651 674 4719",
    "sg:postcode":"55032",
    "sg:province":"MN",
    "sg:tags":[
        "hauling",
        "trucking"
    ],
    "wof:name":"Dis Trucking",
    "wof:placetype":"venue"
},
  "geometry": {"coordinates":[-92.98654399999999,45.615182],"type":"Point"}
}