{
  "type": "Feature",
  "properties": {
    "addr:full":"321 Bush St Red Wing MN 55066",
    "addr:housenumber":"321",
    "addr:postcode":"55066",
    "addr:street":"Bush St",
    "iso:country":"US",
    "sg:address":"321 Bush St",
    "sg:city":"Red Wing",
    "sg:classifiers":[
        {
            "category":"Shopping",
            "subcategory":"Clothing, Apparel, & Fashions",
            "type":"Retail Goods"
        }
    ],
    "sg:phone":"+1 651 388 4874",
    "sg:postcode":"55066",
    "sg:province":"MN",
    "sg:tags":[
        "lingerie"
    ],
    "wof:name":"Expressions Fine Lingerie & Ta",
    "wof:placetype":"venue"
},
  "geometry": {"coordinates":[-92.533829,44.56513],"type":"Point"}
}