{
  "type": "Feature",
  "properties": {
    "addr:full":"18040 Co Hwy 2 Fergus Falls MN 56537",
    "addr:housenumber":"18040",
    "addr:postcode":"56537",
    "addr:street":"Co Hwy 2",
    "iso:country":"US",
    "sg:address":"18040 Co Hwy 2",
    "sg:city":"Fergus Falls",
    "sg:classifiers":[
        {
            "category":"Professional",
            "subcategory":"Business Services",
            "type":"Services"
        }
    ],
    "sg:phone":"+1 218 736 5030",
    "sg:postcode":"56537",
    "sg:province":"MN",
    "wof:name":"George Sund",
    "wof:placetype":"venue"
},
  "geometry": {"coordinates":[-96.103537,46.209863],"type":"Point"}
}