{
  "type": "Feature",
  "properties": {
    "addr:full":"12200 101st Ave N Osseo MN 55369",
    "addr:housenumber":"12200",
    "addr:postcode":"55369",
    "addr:street":"101St Ave N",
    "iso:country":"US",
    "sg:address":"12200 101st Ave N",
    "sg:city":"Osseo",
    "sg:classifiers":[
        {
            "category":"Communications",
            "type":"Services"
        }
    ],
    "sg:phone":"+1 763 549 5414",
    "sg:postcode":"55369",
    "sg:province":"MN",
    "sg:tags":[
        "communication"
    ],
    "wof:name":"Larsen Communication Serv",
    "wof:placetype":"venue"
},
  "geometry": {"coordinates":[-93.435714,45.137268],"type":"Point"}
}