{
  "type": "Feature",
  "properties": {
    "addr:full":"2090 70th St NE Montevideo MN 56265",
    "addr:housenumber":"2090",
    "addr:postcode":"56265",
    "addr:street":"70Th St Ne",
    "iso:country":"US",
    "sg:address":"2090 70th St NE",
    "sg:city":"Montevideo",
    "sg:classifiers":[
        {
            "category":"Building & Trades",
            "subcategory":"Construction",
            "type":"Services"
        }
    ],
    "sg:phone":"+1 320 843 4639",
    "sg:postcode":"56265",
    "sg:province":"MN",
    "sg:tags":[
        "nonresidential"
    ],
    "wof:name":"FW Construction Inc",
    "wof:placetype":"venue"
},
  "geometry": {"coordinates":[-95.55235,45.122755],"type":"Point"}
}