{
  "type": "Feature",
  "properties": {
    "iso:country":"US",
    "sg:address":"555 Harriet Ave",
    "sg:city":"St Paul",
    "sg:classifiers":[
        {
            "category":"Organizations",
            "subcategory":"Membership Organization",
            "type":"Services"
        }
    ],
    "sg:phone":"+1 651 271 1065",
    "sg:postcode":"55126",
    "sg:province":"MN",
    "wof:name":"Lithuanian Cultural Orgnztn",
    "wof:placetype":"venue"
},
  "geometry": {"coordinates":[-93.12642,45.046766],"type":"Point"}
}