{
  "type": "Feature",
  "properties": {
    "addr:full":"4048 Hunters Hill Way Minnetonka MN 55345",
    "addr:housenumber":"4048",
    "addr:postcode":"55345",
    "addr:street":"Hunters Hill Way",
    "iso:country":"US",
    "sg:address":"4048 Hunters Hill Way",
    "sg:city":"Minnetonka",
    "sg:classifiers":[
        {
            "category":"Real Estate",
            "subcategory":"Real Estate Operator",
            "type":"Services"
        }
    ],
    "sg:phone":"+1 952 473 4576",
    "sg:postcode":"55345",
    "sg:province":"MN",
    "sg:tags":[
        "building",
        "apartment"
    ],
    "wof:name":"Twin Towers Enterprises",
    "wof:placetype":"venue"
},
  "geometry": {"coordinates":[-93.506972,44.930211],"type":"Point"}
}