{
  "type": "Feature",
  "properties": {
    "addr:full":"4861 144th St W Apple Valley MN 55124",
    "addr:housenumber":"4861",
    "addr:postcode":"55124",
    "addr:street":"144Th St W",
    "iso:country":"US",
    "sg:address":"4861 144th St W",
    "sg:city":"Apple Valley",
    "sg:classifiers":[
        {
            "category":"Professional",
            "subcategory":"Computer Services",
            "type":"Services"
        }
    ],
    "sg:phone":"+1 952 423 7419",
    "sg:postcode":"55124",
    "sg:province":"MN",
    "sg:tags":[
        "internet"
    ],
    "sg:website":"www.debswebs.com",
    "wof:name":"DEBSWEBS.COM",
    "wof:placetype":"venue"
},
  "geometry": {"coordinates":[-93.16367200000001,44.739695],"type":"Point"}
}