{
  "type": "Feature",
  "properties": {
    "iso:country":"US",
    "sg:address":"1044 3rd Ave",
    "sg:city":"Windom",
    "sg:classifiers":[
        {
            "category":"Professional",
            "subcategory":"Lawyer & Legal Services",
            "type":"Services"
        }
    ],
    "sg:phone":"+1 507 831 3114",
    "sg:postcode":"56101",
    "sg:province":"MN",
    "sg:tags":[
        "attorney"
    ],
    "wof:name":"L Douglas Storey",
    "wof:placetype":"venue"
},
  "geometry": {"coordinates":[-95.116388,43.867181],"type":"Point"}
}