{
  "type": "Feature",
  "properties": {
    "addr:full":"1301 36th St SW Rochester MN 55902",
    "addr:housenumber":"1301",
    "addr:postcode":"55902",
    "addr:street":"36Th St Sw",
    "iso:country":"US",
    "sg:address":"1301 36th St SW",
    "sg:city":"Rochester",
    "sg:classifiers":[
        {
            "category":"Building & Trades",
            "subcategory":"Construction",
            "type":"Services"
        }
    ],
    "sg:phone":"+1 507 288 6736",
    "sg:postcode":"55902",
    "sg:province":"MN",
    "sg:tags":[
        "floor",
        "laying",
        "contractor"
    ],
    "wof:name":"Viking Carpet",
    "wof:placetype":"venue"
},
  "geometry": {"coordinates":[-92.48438899999999,43.96871],"type":"Point"}
}