{
  "type": "Feature",
  "properties": {
    "addr:full":"2001 Killebrew Dr Minneapolis MN 55425",
    "addr:housenumber":"2001",
    "addr:postcode":"55425",
    "addr:street":"Killebrew Dr",
    "iso:country":"US",
    "sg:address":"2001 Killebrew Dr",
    "sg:city":"Minneapolis",
    "sg:classifiers":[
        {
            "category":"Manufacturing",
            "subcategory":"Motor Vehicles & Parts",
            "type":"Manufacturing & Wholesale Goods"
        }
    ],
    "sg:phone":"+1 952 854 2318",
    "sg:postcode":"55425",
    "sg:province":"MN",
    "sg:tags":[
        "automotive",
        "supply"
    ],
    "wof:name":"Northrop Grumman Space",
    "wof:placetype":"venue"
},
  "geometry": {"coordinates":[-93.23898800000001,44.852191],"type":"Point"}
}