{
  "type": "Feature",
  "properties": {
    "addr:full":"120 Butler Ave South Saint Paul MN 55075",
    "addr:housenumber":"120",
    "addr:postcode":"55075",
    "addr:street":"Butler Ave South",
    "iso:country":"US",
    "sg:address":"120 Butler Ave",
    "sg:city":"South Saint Paul",
    "sg:classifiers":[
        {
            "category":"Professional",
            "subcategory":"Management & Consulting",
            "type":"Services"
        }
    ],
    "sg:phone":"+1 651 455 7788",
    "sg:postcode":"55075",
    "sg:province":"MN",
    "wof:name":"K&R Assoc Inc",
    "wof:placetype":"venue"
},
  "geometry": {"coordinates":[-93.054822,44.912517],"type":"Point"}
}