{
  "type": "Feature",
  "properties": {
    "iso:country":"US",
    "sg:address":"830 N Riverfront Dr",
    "sg:city":"Mankato",
    "sg:classifiers":[
        {
            "category":"Autos & Motor Vehicles",
            "subcategory":"Automobile Sales",
            "type":"Retail Goods"
        }
    ],
    "sg:phone":"+1 507 625 6001",
    "sg:postcode":"56001",
    "sg:province":"MN",
    "sg:tags":[
        "car",
        "used",
        "dealer"
    ],
    "wof:name":"Buck's Motors Unlimited",
    "wof:placetype":"venue"
},
  "geometry": {"coordinates":[-93.99577499999999,44.174698],"type":"Point"}
}