{
  "type": "Feature",
  "properties": {
    "iso:country":"US",
    "sg:address":"5751 German Lake Rd NW",
    "sg:city":"Isanti",
    "sg:phone":"+1 763 444 5931",
    "sg:postcode":"55040",
    "sg:province":"MN",
    "sg:tags":[
        "farm",
        "corn"
    ],
    "wof:name":"Theodore Erickson",
    "wof:placetype":"venue"
},
  "geometry": {"coordinates":[-93.409381,45.468894],"type":"Point"}
}