{
  "type": "Feature",
  "properties": {
    "iso:country":"US",
    "sg:address":"109 1st Ave E",
    "sg:city":"Hanley Falls",
    "sg:classifiers":[
        {
            "category":"Government",
            "subcategory":"Office",
            "type":"Public Place"
        }
    ],
    "sg:phone":"+1 507 768 3570",
    "sg:postcode":"56245",
    "sg:province":"MN",
    "sg:tags":[
        "city"
    ],
    "wof:name":"Hanley Falls City Clerk",
    "wof:placetype":"venue"
},
  "geometry": {"coordinates":[-95.61863700000001,44.692224],"type":"Point"}
}