{
  "type": "Feature",
  "properties": {
    "addr:full":"18 1st St SE Madelia MN 56062",
    "addr:housenumber":"18",
    "addr:postcode":"56062",
    "addr:street":"1St St Se Madelia",
    "iso:country":"US",
    "sg:address":"18 1st St SE",
    "sg:city":"Madelia",
    "sg:phone":"+1 507 642 3834",
    "sg:postcode":"56062",
    "sg:province":"MN",
    "sg:tags":[
        "farm",
        "corn"
    ],
    "wof:name":"Mike Teigum",
    "wof:placetype":"venue"
},
  "geometry": {"coordinates":[-94.41638,44.049708],"type":"Point"}
}