{
  "type": "Feature",
  "properties": {
    "iso:country":"US",
    "sg:address":"16760 N Hillcrest Ct",
    "sg:city":"Eden Prairie",
    "sg:classifiers":[
        {
            "category":"Wholesale",
            "subcategory":"Vending Machines",
            "type":"Manufacturing & Wholesale Goods"
        }
    ],
    "sg:phone":"+1 612 369 3962",
    "sg:postcode":"55346",
    "sg:province":"MN",
    "sg:tags":[
        "operator"
    ],
    "wof:name":"Maverick Vending",
    "wof:placetype":"venue"
},
  "geometry": {"coordinates":[-93.488894,44.875165],"type":"Point"}
}