{
  "type": "Feature",
  "properties": {
    "addr:full":"3657 Cedar Ave S Minneapolis MN 55407",
    "addr:housenumber":"3657",
    "addr:postcode":"55407",
    "addr:street":"Cedar Ave S",
    "iso:country":"US",
    "sg:address":"3657 Cedar Ave S",
    "sg:city":"Minneapolis",
    "sg:classifiers":[
        {
            "category":"Real Estate",
            "subcategory":"Real Estate Agent",
            "type":"Services"
        }
    ],
    "sg:phone":"+1 612 272 7274",
    "sg:postcode":"55407",
    "sg:province":"MN",
    "wof:name":"Monopoly Realty",
    "wof:placetype":"venue"
},
  "geometry": {"coordinates":[-93.24727799999999,44.93696],"type":"Point"}
}