{
  "type": "Feature",
  "properties": {
    "addr:full":"1509 Fillmore St Alexandria MN 56308",
    "addr:housenumber":"1509",
    "addr:postcode":"56308",
    "addr:street":"Fillmore St",
    "iso:country":"US",
    "sg:address":"1509 Fillmore St",
    "sg:city":"Alexandria",
    "sg:classifiers":[
        {
            "category":"Professional",
            "subcategory":"Management & Consulting",
            "type":"Services"
        }
    ],
    "sg:phone":"+1 320 763 3874",
    "sg:postcode":"56308",
    "sg:province":"MN",
    "sg:tags":[
        "business"
    ],
    "wof:name":"Northcountry Publishing Co",
    "wof:placetype":"venue"
},
  "geometry": {"coordinates":[-95.37926899999999,45.875348],"type":"Point"}
}