{
  "type": "Feature",
  "properties": {
    "addr:full":"101 W Burnsville Pkwy Burnsville MN 55337",
    "addr:housenumber":"101",
    "addr:postcode":"55337",
    "addr:street":"W Burnsville Pkwy",
    "iso:country":"US",
    "sg:address":"101 W Burnsville Pkwy",
    "sg:city":"Burnsville",
    "sg:classifiers":[
        {
            "category":"Banks & Credit Unions",
            "subcategory":"Bank",
            "type":"Services"
        }
    ],
    "sg:phone":"+1 952 224 9082",
    "sg:postcode":"55337",
    "sg:province":"MN",
    "sg:tags":[
        "loan",
        "real estate"
    ],
    "wof:name":"Eagle View Mortgage",
    "wof:placetype":"venue"
},
  "geometry": {"coordinates":[-93.27913100000001,44.771916],"type":"Point"}
}