{
  "type": "Feature",
  "properties": {
    "addr:full":"8994 E Viking Blvd Chisago City MN 55013",
    "addr:housenumber":"8994",
    "addr:postcode":"55013",
    "addr:street":"E Viking Blvd",
    "iso:country":"US",
    "sg:address":"8994 E Viking Blvd",
    "sg:city":"Chisago City",
    "sg:classifiers":[
        {
            "category":"Building & Trades",
            "subcategory":"Plumbing",
            "type":"Services"
        }
    ],
    "sg:phone":"+1 651 257 2865",
    "sg:postcode":"55013",
    "sg:province":"MN",
    "sg:tags":[
        "plumbing",
        "contractor"
    ],
    "wof:name":"Marine Plumbing",
    "wof:placetype":"venue"
},
  "geometry": {"coordinates":[-92.91676,45.360259],"type":"Point"}
}