{
  "type": "Feature",
  "properties": {
    "iso:country":"US",
    "sg:address":"676 Mendelssohn Ave N",
    "sg:city":"Minneapolis",
    "sg:classifiers":[
        {
            "category":"Professional",
            "type":"Services"
        }
    ],
    "sg:phone":"+1 763 551 0052",
    "sg:postcode":"55427",
    "sg:province":"MN",
    "sg:tags":[
        "establishment"
    ],
    "wof:name":"WDS",
    "wof:placetype":"venue"
},
  "geometry": {"coordinates":[-93.399925,44.988471],"type":"Point"}
}