{
  "type": "Feature",
  "properties": {
    "addr:full":"71 Jefferson Ave Zumbrota MN 55992",
    "addr:housenumber":"71",
    "addr:postcode":"55992",
    "addr:street":"Jefferson Ave",
    "iso:country":"US",
    "sg:address":"71 Jefferson Ave",
    "sg:city":"Zumbrota",
    "sg:classifiers":[
        {
            "category":"Retail",
            "subcategory":"Auto Repair",
            "type":"Services"
        }
    ],
    "sg:phone":"+1 507 732 7352",
    "sg:postcode":"55992",
    "sg:province":"MN",
    "sg:tags":[
        "repairing",
        "automobile"
    ],
    "wof:name":"Tom's Repair",
    "wof:placetype":"venue"
},
  "geometry": {"coordinates":[-92.690186,44.306963],"type":"Point"}
}