{
  "type": "Feature",
  "properties": {
    "addr:full":"130 8th St S Minneapolis MN 55404",
    "addr:housenumber":"130",
    "addr:postcode":"55404",
    "addr:street":"8Th St S",
    "iso:country":"US",
    "sg:address":"130 8th St S",
    "sg:city":"Minneapolis",
    "sg:classifiers":[
        {
            "category":"Government",
            "subcategory":"Post Office",
            "type":"Public Place"
        }
    ],
    "sg:phone":"+1 612 349 4976",
    "sg:postcode":"55404",
    "sg:province":"MN",
    "wof:name":"US Post Office",
    "wof:placetype":"venue"
},
  "geometry": {"coordinates":[-93.271705,44.975308],"type":"Point"}
}