{
  "type": "Feature",
  "properties": {
    "iso:country":"US",
    "sg:address":"28706 Garden Ave",
    "sg:city":"Vesta",
    "sg:classifiers":[
        {
            "category":"Retail",
            "subcategory":"Auto Repair",
            "type":"Services"
        }
    ],
    "sg:phone":"+1 507 984 5459",
    "sg:postcode":"56292",
    "sg:province":"MN",
    "sg:tags":[
        "body",
        "automobile",
        "used"
    ],
    "wof:name":"Rohlik Auto",
    "wof:placetype":"venue"
},
  "geometry": {"coordinates":[-95.35011799999999,44.466219],"type":"Point"}
}