{
  "type": "Feature",
  "properties": {
    "iso:country":"US",
    "sg:address":"7344 Cedar Ave S",
    "sg:city":"Minneapolis",
    "sg:classifiers":[
        {
            "category":"Professional",
            "subcategory":"Lawyer & Legal Services",
            "type":"Services"
        }
    ],
    "sg:phone":"+1 612 872 6727",
    "sg:postcode":"55423",
    "sg:province":"MN",
    "sg:tags":[
        "attorney"
    ],
    "sg:website":"www.baquerolaw.com",
    "wof:name":"Mary Baquero Law Office",
    "wof:placetype":"venue"
},
  "geometry": {"coordinates":[-93.247984,44.869924],"type":"Point"}
}