{
  "type": "Feature",
  "properties": {
    "iso:country":"US",
    "sg:address":"629 N 11th St",
    "sg:city":"Montevideo",
    "sg:classifiers":[
        {
            "category":"Government",
            "subcategory":"Police Station",
            "type":"Public Place"
        }
    ],
    "sg:phone":"+1 320 269 2121",
    "sg:postcode":"56265",
    "sg:province":"MN",
    "sg:tags":[
        "protection"
    ],
    "wof:name":"Sheriffs Office",
    "wof:placetype":"venue"
},
  "geometry": {"coordinates":[-95.7136,44.950127],"type":"Point"}
}