{
  "type": "Feature",
  "properties": {
    "iso:country":"US",
    "sg:address":"1556 Como Ave",
    "sg:city":"Saint Paul",
    "sg:classifiers":[
        {
            "category":"Professional",
            "subcategory":"Business Services",
            "type":"Services"
        }
    ],
    "sg:phone":"+1 651 644 3889",
    "sg:postcode":"55108",
    "sg:province":"MN",
    "wof:name":"Como Community Council",
    "wof:placetype":"venue"
},
  "geometry": {"coordinates":[-93.166905,44.977232],"type":"Point"}
}