{
  "type": "Feature",
  "properties": {
    "addr:full":"4950 235th St E Elko MN 55020",
    "addr:housenumber":"4950",
    "addr:postcode":"55020",
    "addr:street":"235Th St E",
    "iso:country":"US",
    "sg:address":"4950 235th St E",
    "sg:city":"Elko",
    "sg:phone":"+1 952 461 2570",
    "sg:postcode":"55020",
    "sg:province":"MN",
    "sg:tags":[
        "farm",
        "corn",
        "grain",
        "cash"
    ],
    "wof:name":"Norman Sticha",
    "wof:placetype":"venue"
},
  "geometry": {"coordinates":[-93.437988,44.608847],"type":"Point"}
}