{
  "type": "Feature",
  "properties": {
    "iso:country":"US",
    "sg:address":"6453 Howard Gnesen Rd",
    "sg:city":"Duluth",
    "sg:classifiers":[
        {
            "category":"Social Services",
            "subcategory":"Child Care",
            "type":"Services"
        }
    ],
    "sg:phone":"+1 218 721 4608",
    "sg:postcode":"55803",
    "sg:province":"MN",
    "sg:tags":[
        "day",
        "provides"
    ],
    "wof:name":"Terri L Restad",
    "wof:placetype":"venue"
},
  "geometry": {"coordinates":[-92.11169599999999,46.979738],"type":"Point"}
}