{
  "type": "Feature",
  "properties": {
    "iso:country":"US",
    "sg:address":"10125 Crosstown Cir",
    "sg:city":"Eden Prairie",
    "sg:classifiers":[
        {
            "category":"Wholesale",
            "subcategory":"Machinery & Supplies",
            "type":"Manufacturing & Wholesale Goods"
        }
    ],
    "sg:phone":"+1 952 944 8292",
    "sg:postcode":"55344",
    "sg:province":"MN",
    "sg:tags":[
        "spraying",
        "equipment"
    ],
    "wof:name":"Spraying Systems Co",
    "wof:placetype":"venue"
},
  "geometry": {"coordinates":[-93.4057,44.886906],"type":"Point"}
}