{
  "type": "Feature",
  "properties": {
    "addr:full":"2086 Edgerton St St Paul MN 55117",
    "addr:housenumber":"2086",
    "addr:postcode":"55117",
    "addr:street":"Edgerton St",
    "iso:country":"US",
    "sg:address":"2086 Edgerton St",
    "sg:city":"St Paul",
    "sg:classifiers":[
        {
            "category":"Autos & Motor Vehicles",
            "subcategory":"Fuel & Gas Station",
            "type":"Retail Goods"
        }
    ],
    "sg:phone":"+1 651 776 9244",
    "sg:postcode":"55117",
    "sg:province":"MN",
    "sg:tags":[
        "oil"
    ],
    "wof:name":"Ron's Service",
    "wof:placetype":"venue"
},
  "geometry": {"coordinates":[-93.076256,45.004981],"type":"Point"}
}