{
  "type": "Feature",
  "properties": {
    "addr:full":"11720 Urban Ave Norwood MN 55368",
    "addr:housenumber":"11720",
    "addr:postcode":"55368",
    "addr:street":"Urban Ave",
    "iso:country":"US",
    "sg:address":"11720 Urban Ave",
    "sg:city":"Norwood",
    "sg:classifiers":[
        {
            "category":"Farming",
            "subcategory":"Dairy Farm",
            "type":"Manufacturing & Wholesale Goods"
        }
    ],
    "sg:phone":"+1 952 467 3200",
    "sg:postcode":"55368",
    "sg:province":"MN",
    "wof:name":"Clarence Maschke",
    "wof:placetype":"venue"
},
  "geometry": {"coordinates":[-93.944838,44.788663],"type":"Point"}
}