{
  "type": "Feature",
  "properties": {
    "iso:country":"US",
    "sg:address":"2910 82nd Street",
    "sg:city":"Chaska",
    "sg:classifiers":[
        {
            "category":"Shopping",
            "subcategory":"Pets & Pet Supplies",
            "type":"Retail Goods"
        },
        {
            "category":"Retail",
            "subcategory":"Pet Boarding",
            "type":"Services"
        }
    ],
    "sg:phone":"+1 952 361 9663",
    "sg:postcode":"55317",
    "sg:province":"MN",
    "sg:tags":[
        "boarding/pet",
        "groomers",
        "sitting"
    ],
    "wof:name":"The Canine Club and Spa",
    "wof:placetype":"venue"
},
  "geometry": {"coordinates":[-93.59500199999999,44.856703],"type":"Point"}
}