{
  "type": "Feature",
  "properties": {
    "iso:country":"US",
    "sg:address":"594 W 78th St",
    "sg:city":"Chanhassen",
    "sg:classifiers":[
        {
            "category":"Food & Beverages",
            "subcategory":"Groceries & Convenience Stores",
            "type":"Retail Goods"
        }
    ],
    "sg:phone":"+1 952 949 2837",
    "sg:postcode":"55317",
    "sg:province":"MN",
    "wof:name":"Twin Cities Stores Inc",
    "wof:placetype":"venue"
},
  "geometry": {"coordinates":[-93.534853,44.862252],"type":"Point"}
}