{
  "type": "Feature",
  "properties": {
    "iso:country":"US",
    "sg:address":"17715 24th Ave N",
    "sg:city":"Minneapolis",
    "sg:classifiers":[
        {
            "category":"Professional",
            "subcategory":"Art Services",
            "type":"Services"
        }
    ],
    "sg:phone":"+1 763 208 4948",
    "sg:postcode":"55447",
    "sg:province":"MN",
    "sg:tags":[
        "designer",
        "display",
        "producer"
    ],
    "wof:name":"Central Plains Design",
    "wof:placetype":"venue"
},
  "geometry": {"coordinates":[-93.505312,45.004453],"type":"Point"}
}