{
  "type": "Feature",
  "properties": {
    "iso:country":"US",
    "sg:address":"2355 US Hwy 59",
    "sg:city":"Garvin",
    "sg:phone":"+1 507 746 4468",
    "sg:postcode":"56132",
    "sg:province":"MN",
    "sg:tags":[
        "farm",
        "corn",
        "cash",
        "crop",
        "field",
        "grain",
        "soybean"
    ],
    "wof:name":"Furen Delma Farm",
    "wof:placetype":"venue"
},
  "geometry": {"coordinates":[-95.755723,44.394051],"type":"Point"}
}