{
  "type": "Feature",
  "properties": {
    "addr:full":"13700 Vincent Ave S Burnsville MN 55337",
    "addr:housenumber":"13700",
    "addr:postcode":"55337",
    "addr:street":"Vincent Ave S",
    "iso:country":"US",
    "sg:address":"13700 Vincent Ave S",
    "sg:city":"Burnsville",
    "sg:classifiers":[
        {
            "category":"Building & Trades",
            "subcategory":"Construction",
            "type":"Services"
        }
    ],
    "sg:phone":"+1 952 894 8716",
    "sg:postcode":"55337",
    "sg:province":"MN",
    "sg:tags":[
        "hanging",
        "contractor"
    ],
    "wof:name":"Leeman Gordon Painting Corp",
    "wof:placetype":"venue"
},
  "geometry": {"coordinates":[-93.314689,44.753876],"type":"Point"}
}