{
  "type": "Feature",
  "properties": {
    "iso:country":"US",
    "sg:address":"25434 Co Rd 30",
    "sg:city":"Albany",
    "sg:classifiers":[
        {
            "category":"Farming",
            "subcategory":"Dairy Farm",
            "type":"Manufacturing & Wholesale Goods"
        }
    ],
    "sg:phone":"+1 320 845 2451",
    "sg:postcode":"56307",
    "sg:province":"MN",
    "wof:name":"Dale Christen",
    "wof:placetype":"venue"
},
  "geometry": {"coordinates":[-94.642167,45.585119],"type":"Point"}
}