{
  "type": "Feature",
  "properties": {
    "iso:country":"US",
    "sg:address":"215 N Central Ave",
    "sg:city":"Duluth",
    "sg:classifiers":[
        {
            "category":"Sports & Exercise",
            "subcategory":"Gym",
            "type":"Entertainment"
        }
    ],
    "sg:phone":"+1 218 624 1311",
    "sg:postcode":"55807",
    "sg:province":"MN",
    "sg:tags":[
        "club",
        "health",
        "studio",
        "gymnasium"
    ],
    "wof:name":"Anytime Fitness",
    "wof:placetype":"venue"
},
  "geometry": {"coordinates":[-92.166602,46.737484],"type":"Point"}
}