{
  "type": "Feature",
  "properties": {
    "addr:full":"103 S Broadway Wells MN 56097",
    "addr:housenumber":"103",
    "addr:postcode":"56097",
    "addr:street":"S Broadway",
    "iso:country":"US",
    "sg:address":"103 S Broadway",
    "sg:city":"Wells",
    "sg:classifiers":[
        {
            "category":"Cinema",
            "subcategory":"Movie Rental",
            "type":"Entertainment"
        }
    ],
    "sg:phone":"+1 507 553 5158",
    "sg:postcode":"56097",
    "sg:province":"MN",
    "sg:tags":[
        "leasing",
        "video",
        "disc",
        "tape"
    ],
    "wof:name":"Wells Family Video",
    "wof:placetype":"venue"
},
  "geometry": {"coordinates":[-93.72540600000001,43.744115],"type":"Point"}
}