{
  "type": "Feature",
  "properties": {
    "addr:full":"2432 280th Ave Marshall MN 56258",
    "addr:housenumber":"2432",
    "addr:postcode":"56258",
    "addr:street":"280Th Ave",
    "iso:country":"US",
    "sg:address":"2432 280th Ave",
    "sg:city":"Marshall",
    "sg:phone":"+1 507 532 9730",
    "sg:postcode":"56258",
    "sg:province":"MN",
    "sg:tags":[
        "farm",
        "corn",
        "soybean"
    ],
    "wof:name":"Tim Deutz",
    "wof:placetype":"venue"
},
  "geometry": {"coordinates":[-95.73521,44.414269],"type":"Point"}
}