{
  "type": "Feature",
  "properties": {
    "addr:full":"16270 110th St N Stillwater MN 55082",
    "addr:housenumber":"16270",
    "addr:postcode":"55082",
    "addr:street":"110Th St N",
    "iso:country":"US",
    "sg:address":"16270 110th St N",
    "sg:city":"Stillwater",
    "sg:classifiers":[
        {
            "category":"Professional",
            "subcategory":"Computer Services",
            "type":"Services"
        }
    ],
    "sg:phone":"+1 651 303 9501",
    "sg:postcode":"55082",
    "sg:province":"MN",
    "sg:tags":[
        "education",
        "software"
    ],
    "wof:name":"Lodestar Learning Corporation",
    "wof:placetype":"venue"
},
  "geometry": {"coordinates":[-92.773044,45.108038],"type":"Point"}
}