{
  "type": "Feature",
  "properties": {
    "addr:full":"23180 Co Hwy 6 Detroit Lakes MN 56501",
    "addr:housenumber":"23180",
    "addr:postcode":"56501",
    "addr:street":"Co Hwy 6",
    "iso:country":"US",
    "sg:address":"23180 Co Hwy 6",
    "sg:city":"Detroit Lakes",
    "sg:classifiers":[
        {
            "category":"Home & Garden",
            "subcategory":"Building Materials",
            "type":"Retail Goods"
        }
    ],
    "sg:phone":"+1 218 847 7290",
    "sg:postcode":"56501",
    "sg:province":"MN",
    "sg:tags":[
        "mixed",
        "concrete"
    ],
    "wof:name":"Strata Concrete",
    "wof:placetype":"venue"
},
  "geometry": {"coordinates":[-95.92095,46.796917],"type":"Point"}
}