{
  "type": "Feature",
  "properties": {
    "addr:full":"26520 W Timberhill Rd Zimmerman MN 55398",
    "addr:housenumber":"26520",
    "addr:postcode":"55398",
    "addr:street":"W Timberhill Rd",
    "iso:country":"US",
    "sg:address":"26520 W Timberhill Rd",
    "sg:city":"Zimmerman",
    "sg:classifiers":[
        {
            "category":"Building & Trades",
            "subcategory":"Construction",
            "type":"Services"
        }
    ],
    "sg:phone":"+1 763 856 5597",
    "sg:postcode":"55398",
    "sg:province":"MN",
    "sg:tags":[
        "residential"
    ],
    "wof:name":"Arden R Kirkendall",
    "wof:placetype":"venue"
},
  "geometry": {"coordinates":[-93.610907,45.450057],"type":"Point"}
}