{
  "type": "Feature",
  "properties": {
    "iso:country":"US",
    "sg:address":"8732 W 35W Svc Rd NE",
    "sg:city":"Minneapolis",
    "sg:classifiers":[
        {
            "category":"Professional",
            "subcategory":"Business Services",
            "type":"Services"
        }
    ],
    "sg:phone":"+1 763 783 9411",
    "sg:postcode":"55449",
    "sg:province":"MN",
    "sg:tags":[
        "printing",
        "digital",
        "sign"
    ],
    "wof:name":"Visual Impact",
    "wof:placetype":"venue"
},
  "geometry": {"coordinates":[-93.18933699999999,45.128601],"type":"Point"}
}