{
  "type": "Feature",
  "properties": {
    "addr:full":"12840 Watercrest Dr Houston MN 55943",
    "addr:housenumber":"12840",
    "addr:postcode":"55943",
    "addr:street":"Watercrest Dr",
    "iso:country":"US",
    "sg:address":"12840 Watercrest Dr",
    "sg:city":"Houston",
    "sg:classifiers":[
        {
            "category":"Sports & Exercise",
            "subcategory":"Gym",
            "type":"Entertainment"
        }
    ],
    "sg:phone":"+1 507 896 2567",
    "sg:postcode":"55943",
    "sg:province":"MN",
    "sg:tags":[
        "fitness",
        "physical",
        "facility"
    ],
    "wof:name":"Houstons Fitness Center",
    "wof:placetype":"venue"
},
  "geometry": {"coordinates":[-91.510384,43.832814],"type":"Point"}
}