{
  "type": "Feature",
  "properties": {
    "addr:full":"1030 160th Ave Balaton MN 56115",
    "addr:housenumber":"1030",
    "addr:postcode":"56115",
    "addr:street":"160Th Ave",
    "iso:country":"US",
    "sg:address":"1030 160th Ave",
    "sg:city":"Balaton",
    "sg:phone":"+1 507 658 3553",
    "sg:postcode":"56115",
    "sg:province":"MN",
    "sg:tags":[
        "farm",
        "corn"
    ],
    "wof:name":"Donald Mealmen",
    "wof:placetype":"venue"
},
  "geometry": {"coordinates":[-95.977299,44.196693],"type":"Point"}
}