{
  "type": "Feature",
  "properties": {
    "addr:full":"8351 Lake Dr Circle Pines MN 55014",
    "addr:housenumber":"8351",
    "addr:postcode":"55014",
    "addr:street":"Lake Dr Circle",
    "iso:country":"US",
    "sg:address":"8351 Lake Dr",
    "sg:city":"Circle Pines",
    "sg:classifiers":[
        {
            "category":"Retail",
            "subcategory":"Auto Repair",
            "type":"Services"
        }
    ],
    "sg:phone":"+1 651 783 7322",
    "sg:postcode":"55014",
    "sg:province":"MN",
    "sg:tags":[
        "body"
    ],
    "wof:name":"Plastec Blasting LLC",
    "wof:placetype":"venue"
},
  "geometry": {"coordinates":[-93.09427700000001,45.209155],"type":"Point"}
}