{
  "type": "Feature",
  "properties": {
    "iso:country":"US",
    "sg:address":"8009 34th Ave S Ste 975",
    "sg:city":"Minneapolis",
    "sg:classifiers":[
        {
            "category":"Banks & Credit Unions",
            "subcategory":"Investment Brokerage",
            "type":"Services"
        },
        {
            "category":"Banks & Credit Unions",
            "subcategory":"Bank",
            "type":"Services"
        },
        {
            "category":"Banks & Credit Unions",
            "subcategory":"Financial Services",
            "type":"Services"
        }
    ],
    "sg:phone":"+1 952 253 0777",
    "sg:postcode":"55425",
    "sg:province":"MN",
    "sg:tags":[
        "advisory",
        "retirement",
        "planner",
        "annuity",
        "broker",
        "agent",
        "planning",
        "plan",
        "consultant",
        "bond",
        "security",
        "stock",
        "insurance",
        "transfer"
    ],
    "sg:website":"http://www.raymondjames.com/JohnStanley",
    "wof:name":"Raymond James",
    "wof:placetype":"venue"
},
  "geometry": {"coordinates":[-93.222977,44.858481],"type":"Point"}
}