{
  "type": "Feature",
  "properties": {
    "addr:full":"105 Main St W New Prague MN 56071",
    "addr:housenumber":"105",
    "addr:postcode":"56071",
    "addr:street":"Main St W",
    "iso:country":"US",
    "sg:address":"105 Main St W",
    "sg:city":"New Prague",
    "sg:classifiers":[
        {
            "category":"Insurance",
            "subcategory":"Insurance Agent",
            "type":"Services"
        }
    ],
    "sg:phone":"+1 952 758 2879",
    "sg:postcode":"56071",
    "sg:province":"MN",
    "wof:name":"Ron Schoenecker Agency",
    "wof:placetype":"venue"
},
  "geometry": {"coordinates":[-93.57729500000001,44.543654],"type":"Point"}
}