{
  "type": "Feature",
  "properties": {
    "addr:full":"830 Elm St E Annandale MN 55302",
    "addr:housenumber":"830",
    "addr:postcode":"55302",
    "addr:street":"Elm St E",
    "iso:country":"US",
    "sg:address":"830 Elm St E",
    "sg:city":"Annandale",
    "sg:classifiers":[
        {
            "category":"Home & Garden",
            "subcategory":"Garden Supply",
            "type":"Retail Goods"
        }
    ],
    "sg:phone":"+1 320 236 7406",
    "sg:postcode":"55302",
    "sg:province":"MN",
    "sg:tags":[
        "sprinkler"
    ],
    "sg:website":"www.airliftdoors.com",
    "wof:name":"Carefree Lawn",
    "wof:placetype":"venue"
},
  "geometry": {"coordinates":[-94.110293,45.256276],"type":"Point"}
}