{
  "type": "Feature",
  "properties": {
    "addr:full":"2829 University Ave SE Minneapolis MN 55414",
    "addr:housenumber":"2829",
    "addr:postcode":"55414",
    "addr:street":"University Ave Se",
    "iso:country":"US",
    "sg:address":"2829 University Ave SE",
    "sg:city":"Minneapolis",
    "sg:classifiers":[
        {
            "category":"Government",
            "subcategory":"Office",
            "type":"Public Place"
        }
    ],
    "sg:phone":"+1 612 617 2222",
    "sg:postcode":"55414",
    "sg:province":"MN",
    "sg:tags":[
        "examiner",
        "board",
        "chiropractic"
    ],
    "wof:name":"Chiropractic Examiners Minn Bd",
    "wof:placetype":"venue"
},
  "geometry": {"coordinates":[-93.215616,44.971274],"type":"Point"}
}