{
  "type": "Feature",
  "properties": {
    "iso:country":"US",
    "sg:address":"1209 Geneva Ave N",
    "sg:city":"Oakdale",
    "sg:classifiers":[
        {
            "category":"Recreation",
            "subcategory":"Amusement Park",
            "type":"Entertainment"
        },
        {
            "category":"Recreation",
            "subcategory":"Arcade",
            "type":"Entertainment"
        }
    ],
    "sg:phone":"+1 651 578 1741",
    "sg:postcode":"55128",
    "sg:province":"MN",
    "sg:tags":[
        "casino",
        "park"
    ],
    "wof:name":"Pull Tab Parlor",
    "wof:placetype":"venue"
},
  "geometry": {"coordinates":[-92.984686,44.965703],"type":"Point"}
}