{
  "type": "Feature",
  "properties": {
    "addr:full":"14887 Pine Edge Dr Wadena MN 56482",
    "addr:housenumber":"14887",
    "addr:postcode":"56482",
    "addr:street":"Pine Edge Dr",
    "iso:country":"US",
    "sg:address":"14887 Pine Edge Dr",
    "sg:city":"Wadena",
    "sg:classifiers":[
        {
            "category":"Retail",
            "subcategory":"Repair Shop",
            "type":"Services"
        }
    ],
    "sg:phone":"+1 218 631 1955",
    "sg:postcode":"56482",
    "sg:province":"MN",
    "sg:tags":[
        "refrigeration",
        "appliance"
    ],
    "wof:name":"Mike's Refrigeration & Appl",
    "wof:placetype":"venue"
},
  "geometry": {"coordinates":[-95.112799,46.440506],"type":"Point"}
}