{
  "type": "Feature",
  "properties": {
    "addr:full":"2780 Snelling Ave N Roseville MN 55113",
    "addr:housenumber":"2780",
    "addr:postcode":"55113",
    "addr:street":"Snelling Ave N",
    "iso:country":"US",
    "sg:address":"2780 Snelling Ave N",
    "sg:city":"Roseville",
    "sg:classifiers":[
        {
            "category":"Insurance",
            "subcategory":"Insurance Agent",
            "type":"Services"
        }
    ],
    "sg:phone":"+1 651 635 0500",
    "sg:postcode":"55113",
    "sg:province":"MN",
    "sg:website":"www.thrivent.com",
    "wof:name":"Thrivent Financial-Lutherans",
    "wof:placetype":"venue"
},
  "geometry": {"coordinates":[-93.166999,45.021509],"type":"Point"}
}