{
  "type": "Feature",
  "properties": {
    "iso:country":"US",
    "sg:address":"409 N Sibley Ave",
    "sg:city":"Litchfield",
    "sg:classifiers":[
        {
            "category":"Professional",
            "subcategory":"Lawyer & Legal Services",
            "type":"Services"
        }
    ],
    "sg:phone":"+1 320 693 9321",
    "sg:postcode":"55355",
    "sg:province":"MN",
    "wof:name":"Henretta Cross Ness and Dolan",
    "wof:placetype":"venue"
},
  "geometry": {"coordinates":[-94.528239,45.130974],"type":"Point"}
}