{
  "type": "Feature",
  "properties": {
    "addr:full":"3605 85th Ave Princeton MN 55371",
    "addr:housenumber":"3605",
    "addr:postcode":"55371",
    "addr:street":"85Th Ave",
    "iso:country":"US",
    "sg:address":"3605 85th Ave",
    "sg:city":"Princeton",
    "sg:classifiers":[
        {
            "category":"Wholesale",
            "subcategory":"Machinery & Supplies",
            "type":"Manufacturing & Wholesale Goods"
        }
    ],
    "sg:phone":"+1 763 389 2436",
    "sg:postcode":"55371",
    "sg:province":"MN",
    "sg:tags":[
        "farm",
        "equipment"
    ],
    "wof:name":"Hoeft's Implement",
    "wof:placetype":"venue"
},
  "geometry": {"coordinates":[-93.58413299999999,45.595368],"type":"Point"}
}