{
  "type": "Feature",
  "properties": {
    "iso:country":"US",
    "sg:address":"11234 Forest Ct NE",
    "sg:city":"Minneapolis",
    "sg:classifiers":[
        {
            "category":"Professional",
            "subcategory":"Business Services",
            "type":"Services"
        }
    ],
    "sg:phone":"+1 763 783 1288",
    "sg:postcode":"55449",
    "sg:province":"MN",
    "wof:name":"Tinklenberg Group",
    "wof:placetype":"venue"
},
  "geometry": {"coordinates":[-93.19985200000001,45.174449],"type":"Point"}
}