{
  "type": "Feature",
  "properties": {
    "addr:full":"113 25th Ave S St Cloud MN 56301",
    "addr:housenumber":"113",
    "addr:postcode":"56301",
    "addr:street":"25Th Ave S",
    "iso:country":"US",
    "sg:address":"113 25th Ave S",
    "sg:city":"St Cloud",
    "sg:classifiers":[
        {
            "category":"Banks & Credit Unions",
            "subcategory":"Investment Brokerage",
            "type":"Services"
        }
    ],
    "sg:phone":"+1 320 230 6500",
    "sg:postcode":"56301",
    "sg:province":"MN",
    "sg:tags":[
        "advisory",
        "financial"
    ],
    "wof:name":"Flat Irons Capital Mgmt",
    "wof:placetype":"venue"
},
  "geometry": {"coordinates":[-94.18803200000001,45.549873],"type":"Point"}
}