{
  "type": "Feature",
  "properties": {
    "addr:full":"4600 Juneau Ln N Minneapolis MN 55446",
    "addr:housenumber":"4600",
    "addr:postcode":"55446",
    "addr:street":"Juneau Ln N",
    "iso:country":"US",
    "sg:address":"4600 Juneau Ln N",
    "sg:city":"Minneapolis",
    "sg:classifiers":[
        {
            "category":"Real Estate",
            "subcategory":"Real Estate Agent",
            "type":"Services"
        }
    ],
    "sg:phone":"+1 763 559 6089",
    "sg:postcode":"55446",
    "sg:province":"MN",
    "wof:name":"Raydar Properties LLC",
    "wof:placetype":"venue"
},
  "geometry": {"coordinates":[-93.46715399999999,45.038643],"type":"Point"}
}