{
  "type": "Feature",
  "properties": {
    "iso:country":"US",
    "sg:address":"135 60th Ave SE",
    "sg:city":"Maynard",
    "sg:phone":"+1 320 367 2936",
    "sg:postcode":"56260",
    "sg:province":"MN",
    "sg:tags":[
        "farm",
        "corn",
        "soybean"
    ],
    "wof:name":"Curtis Dirksen",
    "wof:placetype":"venue"
},
  "geometry": {"coordinates":[-95.472855,45.020675],"type":"Point"}
}