{
  "type": "Feature",
  "properties": {
    "iso:country":"US",
    "sg:address":"6150 Saint Croix Ave N",
    "sg:city":"Minneapolis",
    "sg:classifiers":[
        {
            "category":"Real Estate",
            "subcategory":"Real Estate Operator",
            "type":"Services"
        }
    ],
    "sg:phone":"+1 763 545 8084",
    "sg:postcode":"55422",
    "sg:province":"MN",
    "sg:tags":[
        "apartment"
    ],
    "wof:name":"Golden Valley Arms",
    "wof:placetype":"venue"
},
  "geometry": {"coordinates":[-93.35880299999999,44.9981],"type":"Point"}
}