{
  "type": "Feature",
  "properties": {
    "iso:country":"US",
    "sg:address":"69824 460th St",
    "sg:city":"Fairfax",
    "sg:classifiers":[
        {
            "category":"Farming",
            "subcategory":"Farm",
            "type":"Manufacturing & Wholesale Goods"
        }
    ],
    "sg:phone":"+1 507 426 7690",
    "sg:postcode":"55332",
    "sg:province":"MN",
    "sg:tags":[
        "crop",
        "general"
    ],
    "wof:name":"Francis Schweiss",
    "wof:placetype":"venue"
},
  "geometry": {"coordinates":[-94.751554,44.592081],"type":"Point"}
}