{
  "type": "Feature",
  "properties": {
    "addr:full":"600 60th St NW Willmar MN 56201",
    "addr:housenumber":"600",
    "addr:postcode":"56201",
    "addr:street":"60Th St Nw",
    "iso:country":"US",
    "sg:address":"600 60th St NW",
    "sg:city":"Willmar",
    "sg:classifiers":[
        {
            "category":"Farming",
            "subcategory":"Farm",
            "type":"Manufacturing & Wholesale Goods"
        }
    ],
    "sg:phone":"+1 320 235 0987",
    "sg:postcode":"56201",
    "sg:province":"MN",
    "sg:tags":[
        "crop",
        "general"
    ],
    "wof:name":"Mike Arends",
    "wof:placetype":"venue"
},
  "geometry": {"coordinates":[-95.12423099999999,45.131275],"type":"Point"}
}