{
  "type": "Feature",
  "properties": {
    "addr:full":"337 Oak Grove St Minneapolis MN 55403",
    "addr:housenumber":"337",
    "addr:postcode":"55403",
    "addr:street":"Oak Grove St",
    "iso:country":"US",
    "sg:address":"337 Oak Grove St",
    "sg:city":"Minneapolis",
    "sg:classifiers":[
        {
            "category":"Bus Charters",
            "type":"Transportation"
        }
    ],
    "sg:phone":"+1 612 870 8405",
    "sg:postcode":"55403",
    "sg:province":"MN",
    "wof:name":"Abash Bus Co",
    "wof:placetype":"venue"
},
  "geometry": {"coordinates":[-93.284032,44.966905],"type":"Point"}
}