{
  "type": "Feature",
  "properties": {
    "iso:country":"US",
    "sg:address":"3153 263rd St W",
    "sg:city":"Northfield",
    "sg:classifiers":[
        {
            "category":"Professional",
            "subcategory":"Business Services",
            "type":"Services"
        }
    ],
    "sg:phone":"+1 651 460 6177",
    "sg:postcode":"55057",
    "sg:province":"MN",
    "sg:tags":[
        "engraving"
    ],
    "wof:name":"Tag Me",
    "wof:placetype":"venue"
},
  "geometry": {"coordinates":[-93.12888599999999,44.568134],"type":"Point"}
}