{
  "type": "Feature",
  "properties": {
    "addr:full":"510 18th Ave W Eveleth MN 55734",
    "addr:housenumber":"510",
    "addr:postcode":"55734",
    "addr:street":"18Th Ave W Eveleth",
    "iso:country":"US",
    "sg:address":"510 18th Ave W",
    "sg:city":"Eveleth",
    "sg:classifiers":[
        {
            "category":"Health Services",
            "subcategory":"Nursing And Care Facility",
            "type":"Services"
        }
    ],
    "sg:phone":"+1 218 744 2133",
    "sg:postcode":"55734",
    "sg:province":"MN",
    "sg:tags":[
        "skilled"
    ],
    "wof:name":"Northern Health & Fitness Plus",
    "wof:placetype":"venue"
},
  "geometry": {"coordinates":[-92.579803,47.458912],"type":"Point"}
}