{
  "type": "Feature",
  "properties": {
    "iso:country":"US",
    "sg:address":"4711 Clark Ave",
    "sg:city":"Saint Paul",
    "sg:classifiers":[
        {
            "category":"Professional",
            "subcategory":"Engineering",
            "type":"Services"
        }
    ],
    "sg:phone":"+1 651 762 2663",
    "sg:postcode":"55110",
    "sg:province":"MN",
    "wof:name":"Staus Gary",
    "wof:placetype":"venue"
},
  "geometry": {"coordinates":[-93.010079,45.082711],"type":"Point"}
}