{
  "type": "Feature",
  "properties": {
    "iso:country":"US",
    "sg:address":"13895 Industrial Park Blvd",
    "sg:city":"Minneapolis",
    "sg:classifiers":[
        {
            "category":"Insurance",
            "subcategory":"Insurance Agent",
            "type":"Services"
        },
        {
            "category":"Insurance",
            "subcategory":"Hazard Insurance",
            "type":"Services"
        },
        {
            "category":"Insurance",
            "subcategory":"Title Insurance",
            "type":"Services"
        },
        {
            "category":"Insurance",
            "subcategory":"Life Insurance",
            "type":"Services"
        }
    ],
    "sg:phone":"+1 763 557 7139",
    "sg:postcode":"55441",
    "sg:province":"MN",
    "sg:tags":[
        "auto",
        "commercial",
        "business",
        "homeowner"
    ],
    "sg:website":"http://www.farmersagent.com/jspear/",
    "wof:name":"Jeffrey Spear - Farmers Insurance",
    "wof:placetype":"venue"
},
  "geometry": {"coordinates":[-93.44455000000001,45.002604],"type":"Point"}
}