{
  "type": "Feature",
  "properties": {
    "iso:country":"US",
    "sg:address":"123 Central Ave S",
    "sg:city":"Lancaster",
    "sg:classifiers":[
        {
            "category":"Government",
            "subcategory":"Office",
            "type":"Public Place"
        }
    ],
    "sg:phone":"+1 218 762 4090",
    "sg:postcode":"56716",
    "sg:province":"MN",
    "sg:tags":[
        "village"
    ],
    "wof:name":"Municipal Liquor Store",
    "wof:placetype":"venue"
},
  "geometry": {"coordinates":[-96.61438,47.768976],"type":"Point"}
}