{
  "type": "Feature",
  "properties": {
    "addr:full":"3122 15th Ave S Minneapolis MN 55407",
    "addr:housenumber":"3122",
    "addr:postcode":"55407",
    "addr:street":"15Th Ave S",
    "iso:country":"US",
    "sg:address":"3122 15th Ave S",
    "sg:city":"Minneapolis",
    "sg:classifiers":[
        {
            "category":"Professional",
            "type":"Services"
        }
    ],
    "sg:phone":"+1 612 722 3274",
    "sg:postcode":"55407",
    "sg:province":"MN",
    "sg:tags":[
        "motion",
        "technician",
        "picture"
    ],
    "wof:name":"Ensembleworks",
    "wof:placetype":"venue"
},
  "geometry": {"coordinates":[-93.253755,44.946154],"type":"Point"}
}