{
  "type": "Feature",
  "properties": {
    "addr:full":"4089 Abbott Dr Willmar MN 56201",
    "addr:housenumber":"4089",
    "addr:postcode":"56201",
    "addr:street":"Abbott Dr",
    "iso:country":"US",
    "sg:address":"4089 Abbott Dr",
    "sg:city":"Willmar",
    "sg:classifiers":[
        {
            "category":"Wholesale",
            "subcategory":"Office Equipment",
            "type":"Manufacturing & Wholesale Goods"
        }
    ],
    "sg:phone":"+1 320 235 7850",
    "sg:postcode":"56201",
    "sg:province":"MN",
    "wof:name":"IKON Office Solutions",
    "wof:placetype":"venue"
},
  "geometry": {"coordinates":[-95.041989,45.083636],"type":"Point"}
}