{
  "type": "Feature",
  "properties": {
    "iso:country":"US",
    "sg:address":"1875 Woodwinds Dr",
    "sg:city":"Saint Paul",
    "sg:classifiers":[
        {
            "category":"Health Services",
            "subcategory":"Health Practitioner",
            "type":"Services"
        }
    ],
    "sg:phone":"+1 651 232 6830",
    "sg:postcode":"55125",
    "sg:province":"MN",
    "sg:tags":[
        "consulting",
        "management"
    ],
    "wof:name":"Natural Care Ctr At Woodwinds",
    "wof:placetype":"venue"
},
  "geometry": {"coordinates":[-92.980034,44.920544],"type":"Point"}
}