{
  "type": "Feature",
  "properties": {
    "iso:country":"US",
    "sg:address":"2131 Cliff Rd",
    "sg:city":"Eagan",
    "sg:classifiers":[
        {
            "category":"Personal",
            "subcategory":"Beauty Salon",
            "type":"Services"
        }
    ],
    "sg:phone":"+1 651 454 1390",
    "sg:postcode":"55122",
    "sg:province":"MN",
    "sg:tags":[
        "shop",
        "spa",
        "day"
    ],
    "sg:website":"www.colessalon.com",
    "wof:name":"Cole's Salon",
    "wof:placetype":"venue"
},
  "geometry": {"coordinates":[-93.21682699999999,44.790256],"type":"Point"}
}