{
  "type": "Feature",
  "properties": {
    "iso:country":"US",
    "sg:address":"1065 W Central Ave",
    "sg:city":"St Paul",
    "sg:classifiers":[
        {
            "category":"Organizations",
            "subcategory":"Religious Organization",
            "type":"Services"
        }
    ],
    "sg:phone":"+1 651 644 3015",
    "sg:postcode":"55104",
    "sg:province":"MN",
    "sg:tags":[
        "clergy"
    ],
    "wof:name":"Robert L Graham MD",
    "wof:placetype":"venue"
},
  "geometry": {"coordinates":[-93.145889,44.953115],"type":"Point"}
}