{
  "type": "Feature",
  "properties": {
    "iso:country":"US",
    "sg:address":"2050 Black Oaks Ln N",
    "sg:city":"Minneapolis",
    "sg:classifiers":[
        {
            "category":"Professional",
            "subcategory":"Computer Services",
            "type":"Services"
        }
    ],
    "sg:phone":"+1 763 449 6840",
    "sg:postcode":"55447",
    "sg:province":"MN",
    "sg:tags":[
        "programing",
        "custom"
    ],
    "wof:name":"Aequare Inc",
    "wof:placetype":"venue"
},
  "geometry": {"coordinates":[-93.49045599999999,45.001001],"type":"Point"}
}