{
  "type": "Feature",
  "properties": {
    "iso:country":"US",
    "sg:address":"1620 W 98th St",
    "sg:city":"Bloomington",
    "sg:classifiers":[
        {
            "category":"Education",
            "subcategory":"Special Training",
            "type":"Public Place"
        }
    ],
    "sg:phone":"+1 952 884 4880",
    "sg:postcode":"55431",
    "sg:province":"MN",
    "sg:tags":[
        "educational"
    ],
    "sg:website":"www.projectread.com",
    "wof:name":"Language Circle Enterprises",
    "wof:placetype":"venue"
},
  "geometry": {"coordinates":[-93.30110000000001,44.826387],"type":"Point"}
}