{
  "type": "Feature",
  "properties": {
    "addr:full":"901 Mainstreet Minnetonka MN 55343",
    "addr:housenumber":"901",
    "addr:postcode":"55343",
    "addr:street":"Mainstreet",
    "iso:country":"US",
    "sg:address":"901 Mainstreet",
    "sg:city":"Minnetonka",
    "sg:classifiers":[
        {
            "category":"Professional",
            "subcategory":"Computer Services",
            "type":"Services"
        }
    ],
    "sg:phone":"+1 952 935 0554",
    "sg:postcode":"55343",
    "sg:province":"MN",
    "sg:tags":[
        "website",
        "design"
    ],
    "sg:website":"www.soundconcept.net",
    "wof:name":"SOUNDCONCEPT.NET",
    "wof:placetype":"venue"
},
  "geometry": {"coordinates":[-93.412689,44.924377],"type":"Point"}
}