{
  "type": "Feature",
  "properties": {
    "addr:full":"405 Penn Ave S Minneapolis MN 55405",
    "addr:housenumber":"405",
    "addr:postcode":"55405",
    "addr:street":"Penn Ave S",
    "iso:country":"US",
    "sg:address":"405 Penn Ave S",
    "sg:city":"Minneapolis",
    "sg:classifiers":[
        {
            "category":"Retail",
            "subcategory":"Repair Shop",
            "type":"Services"
        }
    ],
    "sg:phone":"+1 612 381 0669",
    "sg:postcode":"55405",
    "sg:province":"MN",
    "sg:tags":[
        "reupholstery",
        "upholsterer",
        "furniture"
    ],
    "sg:website":"http://www.djsuph.com",
    "wof:name":"Dj's Upholstery Inc",
    "wof:placetype":"venue"
},
  "geometry": {"coordinates":[-93.30819700000001,44.973598],"type":"Point"}
}