{
  "type": "Feature",
  "properties": {
    "addr:full":"6620 Penn Ave S Minneapolis MN 55423",
    "addr:housenumber":"6620",
    "addr:postcode":"55423",
    "addr:street":"Penn Ave S",
    "iso:country":"US",
    "sg:address":"6620 Penn Ave S",
    "sg:city":"Minneapolis",
    "sg:classifiers":[
        {
            "category":"Insurance",
            "subcategory":"Insurance Agent",
            "type":"Services"
        }
    ],
    "sg:phone":"+1 612 869 5313",
    "sg:postcode":"55423",
    "sg:province":"MN",
    "wof:name":"Roger Karjalahti Insurance",
    "wof:placetype":"venue"
},
  "geometry": {"coordinates":[-93.308694,44.882104],"type":"Point"}
}