{
  "type": "Feature",
  "properties": {
    "iso:country":"US",
    "sg:address":"9401 James Ave S",
    "sg:city":"Minneapolis",
    "sg:classifiers":[
        {
            "category":"Professional",
            "type":"Services"
        },
        {
            "category":"Manufacturing",
            "subcategory":"Tools & Machinery",
            "type":"Manufacturing & Wholesale Goods"
        }
    ],
    "sg:phone":"+1 952 885 0500",
    "sg:postcode":"55431",
    "sg:province":"MN",
    "sg:tags":[
        "physician",
        "medical",
        "devices",
        "equipment",
        "surgeon",
        "man",
        "developer"
    ],
    "wof:name":"Ray Medica Inc",
    "wof:placetype":"venue"
},
  "geometry": {"coordinates":[-93.301132,44.831672],"type":"Point"}
}