{
  "type": "Feature",
  "properties": {
    "iso:country":"US",
    "sg:address":"8160 Hwy 52 N",
    "sg:city":"Oronoco",
    "sg:classifiers":[
        {
            "category":"Wholesale",
            "subcategory":"Machinery & Supplies",
            "type":"Manufacturing & Wholesale Goods"
        }
    ],
    "sg:phone":"+1 507 288 3402",
    "sg:postcode":"55960",
    "sg:province":"MN",
    "sg:tags":[
        "farm",
        "equipment"
    ],
    "wof:name":"St Joseph Equipment",
    "wof:placetype":"venue"
},
  "geometry": {"coordinates":[-92.517336,44.11359],"type":"Point"}
}