{
  "type": "Feature",
  "properties": {
    "addr:full":"5116 Gateway St SE Prior Lake MN 55372",
    "addr:housenumber":"5116",
    "addr:postcode":"55372",
    "addr:street":"Gateway St Se",
    "iso:country":"US",
    "sg:address":"5116 Gateway St SE",
    "sg:city":"Prior Lake",
    "sg:classifiers":[
        {
            "category":"Social Services",
            "subcategory":"Child Care",
            "type":"Services"
        }
    ],
    "sg:phone":"+1 952 447 8845",
    "sg:postcode":"55372",
    "sg:province":"MN",
    "sg:tags":[
        "day"
    ],
    "wof:name":"Prior Lake Montessori Day Care",
    "wof:placetype":"venue"
},
  "geometry": {"coordinates":[-93.414985,44.718415],"type":"Point"}
}