{
  "type": "Feature",
  "properties": {
    "addr:full":"419 Division St S Northfield MN 55057",
    "addr:housenumber":"419",
    "addr:postcode":"55057",
    "addr:street":"Division St S",
    "iso:country":"US",
    "sg:address":"419 Division St S",
    "sg:city":"Northfield",
    "sg:classifiers":[
        {
            "category":"Shopping",
            "subcategory":"Gifts & Souvenirs",
            "type":"Retail Goods"
        }
    ],
    "sg:phone":"+1 507 645 9131",
    "sg:postcode":"55057",
    "sg:province":"MN",
    "wof:name":"Present Perfect",
    "wof:placetype":"venue"
},
  "geometry": {"coordinates":[-93.16008100000001,44.455841],"type":"Point"}
}