{
  "type": "Feature",
  "properties": {
    "addr:full":"551 11th Ave NW Saint Paul MN 55112",
    "addr:housenumber":"551",
    "addr:postcode":"55112",
    "addr:street":"11Th Ave Nw",
    "iso:country":"US",
    "sg:address":"551 11th Ave NW",
    "sg:city":"Saint Paul",
    "sg:classifiers":[
        {
            "category":"Professional",
            "type":"Services"
        }
    ],
    "sg:phone":"+1 651 493 1985",
    "sg:postcode":"55112",
    "sg:province":"MN",
    "wof:name":"Lake Region Exteriors Inc",
    "wof:placetype":"venue"
},
  "geometry": {"coordinates":[-93.20183,45.058279],"type":"Point"}
}