{
  "type": "Feature",
  "properties": {
    "iso:country":"US",
    "sg:address":"2300 Superior Dr NW Ste 3",
    "sg:city":"Rochester",
    "sg:classifiers":[
        {
            "category":"Personal",
            "subcategory":"Hair Removal",
            "type":"Services"
        },
        {
            "category":"Personal",
            "subcategory":"Day Spa",
            "type":"Services"
        },
        {
            "category":"Personal",
            "subcategory":"Nail Salon",
            "type":"Services"
        },
        {
            "category":"Personal",
            "subcategory":"Skin Care",
            "type":"Services"
        },
        {
            "category":"Personal",
            "subcategory":"Beauty Salon",
            "type":"Services"
        },
        {
            "category":"Personal",
            "subcategory":"Massage",
            "type":"Services"
        }
    ],
    "sg:phone":"+1 507 289 2986",
    "sg:postcode":"55901",
    "sg:province":"MN",
    "sg:tags":[
        "braiding",
        "therapist",
        "stylist"
    ],
    "sg:website":"http://www.hairstudio52.com",
    "wof:name":"Hair Studio 52 & Day Spa",
    "wof:placetype":"venue"
},
  "geometry": {"coordinates":[-92.522499,44.046299],"type":"Point"}
}