{
  "type": "Feature",
  "properties": {
    "iso:country":"US",
    "sg:address":"26061 Main St",
    "sg:city":"Zimmerman",
    "sg:classifiers":[
        {
            "category":"Professional",
            "subcategory":"Accounting & Tax Preparation",
            "type":"Services"
        }
    ],
    "sg:phone":"+1 763 856 0897",
    "sg:postcode":"55398",
    "sg:province":"MN",
    "sg:tags":[
        "accountant"
    ],
    "wof:name":"Maki Tax & Accounting Inc",
    "wof:placetype":"venue"
},
  "geometry": {"coordinates":[-93.588165,45.44319],"type":"Point"}
}