{
  "type": "Feature",
  "properties": {
    "iso:country":"US",
    "sg:address":"222 W 1st St",
    "sg:city":"Duluth",
    "sg:classifiers":[
        {
            "category":"Government",
            "subcategory":"Office",
            "type":"Public Place"
        }
    ],
    "sg:phone":"+1 218 723 8813",
    "sg:postcode":"55802",
    "sg:province":"MN",
    "wof:name":"Oberstar For Congress",
    "wof:placetype":"venue"
},
  "geometry": {"coordinates":[-92.102712,46.784927],"type":"Point"}
}