{
  "type": "Feature",
  "properties": {
    "addr:full":"2743 State Hwy 65 Mora MN 55051",
    "addr:housenumber":"2743",
    "addr:postcode":"55051",
    "addr:street":"State Hwy 65",
    "iso:country":"US",
    "sg:address":"2743 State Hwy 65",
    "sg:city":"Mora",
    "sg:classifiers":[
        {
            "category":"Travel",
            "subcategory":"Hotels & Motels",
            "type":"Entertainment"
        }
    ],
    "sg:phone":"+1 320 679 1977",
    "sg:postcode":"55051",
    "sg:province":"MN",
    "sg:tags":[
        "resort"
    ],
    "wof:name":"Captain Dan's Crows Nest Rsrt",
    "wof:placetype":"venue"
},
  "geometry": {"coordinates":[-93.279985,45.987939],"type":"Point"}
}