{
  "type": "Feature",
  "properties": {
    "iso:country":"US",
    "sg:address":"2121 Cliff Dr",
    "sg:city":"Eagan",
    "sg:classifiers":[
        {
            "category":"Banks & Credit Unions",
            "subcategory":"Bank",
            "type":"Services"
        }
    ],
    "sg:phone":"+1 651 365 0220",
    "sg:postcode":"55122",
    "sg:province":"MN",
    "sg:tags":[
        "loan",
        "real estate"
    ],
    "wof:name":"US Bank Home Mortgage",
    "wof:placetype":"venue"
},
  "geometry": {"coordinates":[-93.21535299999999,44.790206],"type":"Point"}
}