{
  "type": "Feature",
  "properties": {
    "iso:country":"US",
    "sg:address":"16394 Klamath Trl",
    "sg:city":"Lakeville",
    "sg:classifiers":[
        {
            "category":"Building & Trades",
            "subcategory":"Construction",
            "type":"Services"
        }
    ],
    "sg:phone":"+1 952 898 5822",
    "sg:postcode":"55044",
    "sg:province":"MN",
    "sg:tags":[
        "contractor"
    ],
    "wof:name":"Sellers Stone Werx",
    "wof:placetype":"venue"
},
  "geometry": {"coordinates":[-93.303015,44.711489],"type":"Point"}
}