{
  "type": "Feature",
  "properties": {
    "addr:full":"7500 France Ave S Minneapolis MN 55435",
    "addr:housenumber":"7500",
    "addr:postcode":"55435",
    "addr:street":"France Ave S",
    "iso:country":"US",
    "sg:address":"7500 France Ave S",
    "sg:city":"Minneapolis",
    "sg:classifiers":[
        {
            "category":"Insurance",
            "subcategory":"Insurance Agent",
            "type":"Services"
        }
    ],
    "sg:phone":"+1 952 830 9100",
    "sg:postcode":"55435",
    "sg:province":"MN",
    "sg:tags":[
        "claim"
    ],
    "wof:name":"State Farm Insurance",
    "wof:placetype":"venue"
},
  "geometry": {"coordinates":[-93.328974,44.867219],"type":"Point"}
}