{
  "type": "Feature",
  "properties": {
    "addr:full":"2396 US Hwy 59 Marshall MN 56258",
    "addr:housenumber":"2396",
    "addr:postcode":"56258",
    "addr:street":"Us Hwy 59",
    "iso:country":"US",
    "sg:address":"2396 US Hwy 59",
    "sg:city":"Marshall",
    "sg:classifiers":[
        {
            "category":"Autos & Motor Vehicles",
            "subcategory":"Automobile Sales",
            "type":"Retail Goods"
        }
    ],
    "sg:phone":"+1 507 532 0223",
    "sg:postcode":"56258",
    "sg:province":"MN",
    "sg:tags":[
        "car",
        "dealer"
    ],
    "wof:name":"RAM Auto",
    "wof:placetype":"venue"
},
  "geometry": {"coordinates":[-95.755501,44.397654],"type":"Point"}
}