{
  "type": "Feature",
  "properties": {
    "iso:country":"US",
    "sg:address":"181 Heavenly Acres Rd",
    "sg:city":"Esko",
    "sg:classifiers":[
        {
            "category":"Retail",
            "subcategory":"Repair Shop",
            "type":"Services"
        }
    ],
    "sg:phone":"+1 218 393 1230",
    "sg:postcode":"55733",
    "sg:province":"MN",
    "wof:name":"Budget Septic Pumping",
    "wof:placetype":"venue"
},
  "geometry": {"coordinates":[-92.342578,46.734416],"type":"Point"}
}