{
  "type": "Feature",
  "properties": {
    "addr:full":"29157 156th Ave Cold Spring MN 56320",
    "addr:housenumber":"29157",
    "addr:postcode":"56320",
    "addr:street":"156Th Ave",
    "iso:country":"US",
    "sg:address":"29157 156th Ave",
    "sg:city":"Cold Spring",
    "sg:classifiers":[
        {
            "category":"Retail",
            "subcategory":"Repair Shop",
            "type":"Services"
        }
    ],
    "sg:phone":"+1 320 685 7519",
    "sg:postcode":"56320",
    "sg:province":"MN",
    "sg:tags":[
        "welding"
    ],
    "wof:name":"Gruber's Welding",
    "wof:placetype":"venue"
},
  "geometry": {"coordinates":[-94.431298,45.54552],"type":"Point"}
}