{
  "type": "Feature",
  "properties": {
    "iso:country":"US",
    "sg:address":"895 Hamel Rd",
    "sg:city":"Hamel",
    "sg:classifiers":[
        {
            "category":"Farming",
            "subcategory":"Dairy Farm",
            "type":"Manufacturing & Wholesale Goods"
        }
    ],
    "sg:phone":"+1 763 478 6686",
    "sg:postcode":"55340",
    "sg:province":"MN",
    "wof:name":"Laurent Dairy Farms",
    "wof:placetype":"venue"
},
  "geometry": {"coordinates":[-93.546421,45.042556],"type":"Point"}
}