{
  "type": "Feature",
  "properties": {
    "addr:full":"2490 Cates Ranch Dr Hamel MN 55340",
    "addr:postcode":"2490;55340",
    "addr:street":"Cates Ranch Dr Hamel",
    "iso:country":"US",
    "sg:address":"2490 Cates Ranch Dr",
    "sg:city":"Hamel",
    "sg:classifiers":[
        {
            "category":"Farming",
            "subcategory":"Farm",
            "type":"Manufacturing & Wholesale Goods"
        }
    ],
    "sg:phone":"+1 763 478 6216",
    "sg:postcode":"55340",
    "sg:province":"MN",
    "sg:tags":[
        "crop",
        "general"
    ],
    "wof:name":"Wh Cates Farms",
    "wof:placetype":"venue"
},
  "geometry": {"coordinates":[-93.588514,45.062291],"type":"Point"}
}