{
  "type": "Feature",
  "properties": {
    "addr:full":"410 Park St N Fairfax MN 55332",
    "addr:housenumber":"410",
    "addr:postcode":"55332",
    "addr:street":"Park St N",
    "iso:country":"US",
    "sg:address":"410 Park St N",
    "sg:city":"Fairfax",
    "sg:classifiers":[
        {
            "category":"Freight",
            "type":"Transportation"
        }
    ],
    "sg:phone":"+1 507 426 7841",
    "sg:postcode":"55332",
    "sg:province":"MN",
    "sg:tags":[
        "operator",
        "trucking"
    ],
    "wof:name":"Wagner Trucking",
    "wof:placetype":"venue"
},
  "geometry": {"coordinates":[-94.720479,44.535417],"type":"Point"}
}