{
  "type": "Feature",
  "properties": {
    "iso:country":"US",
    "sg:address":"5964 McArthur Rd",
    "sg:city":"Culver",
    "sg:classifiers":[
        {
            "category":"Building & Trades",
            "subcategory":"Plumbing",
            "type":"Services"
        },
        {
            "category":"Professional",
            "subcategory":"Computer Services",
            "type":"Services"
        }
    ],
    "sg:phone":"+1 218 729 5036",
    "sg:postcode":"55779",
    "sg:province":"MN",
    "sg:tags":[
        "mechanical",
        "design",
        "system",
        "contractor"
    ],
    "wof:name":"Pinnacle Concepts",
    "wof:placetype":"venue"
},
  "geometry": {"coordinates":[-92.512709,46.941636],"type":"Point"}
}