{
  "type": "Feature",
  "properties": {
    "addr:full":"23693 Kestrel Ave Mc Grath MN 56350",
    "addr:housenumber":"23693",
    "addr:postcode":"56350",
    "addr:street":"Kestrel Ave Mc Grath",
    "iso:country":"US",
    "sg:address":"23693 Kestrel Ave",
    "sg:city":"Mc Grath",
    "sg:classifiers":[
        {
            "category":"Manufacturing",
            "subcategory":"Lumber",
            "type":"Manufacturing & Wholesale Goods"
        }
    ],
    "sg:phone":"+1 218 658 4609",
    "sg:postcode":"56350",
    "sg:province":"MN",
    "sg:tags":[
        "logging"
    ],
    "wof:name":"Simcoe & Habisch Logging",
    "wof:placetype":"venue"
},
  "geometry": {"coordinates":[-93.090622,46.360662],"type":"Point"}
}