{
  "type": "Feature",
  "properties": {
    "addr:full":"13117 Natchez Ave Savage MN 55378",
    "addr:housenumber":"13117",
    "addr:postcode":"55378",
    "addr:street":"Natchez Ave",
    "iso:country":"US",
    "sg:address":"13117 Natchez Ave",
    "sg:city":"Savage",
    "sg:classifiers":[
        {
            "category":"Professional",
            "subcategory":"Advertising",
            "type":"Services"
        }
    ],
    "sg:phone":"+1 952 882 0749",
    "sg:postcode":"55378",
    "sg:province":"MN",
    "wof:name":"Minneapolis Yardsale",
    "wof:placetype":"venue"
},
  "geometry": {"coordinates":[-93.338297,44.766875],"type":"Point"}
}