{
  "type": "Feature",
  "properties": {
    "iso:country":"US",
    "sg:address":"1550 91st Ave NE",
    "sg:city":"Minneapolis",
    "sg:classifiers":[
        {
            "category":"Wholesale",
            "subcategory":"Medical Equipment & Supplies",
            "type":"Manufacturing & Wholesale Goods"
        },
        {
            "category":"Professional",
            "subcategory":"Engineering",
            "type":"Services"
        },
        {
            "category":"Wholesale",
            "subcategory":"Construction Materials",
            "type":"Manufacturing & Wholesale Goods"
        },
        {
            "category":"Building & Trades",
            "subcategory":"Construction",
            "type":"Services"
        }
    ],
    "sg:phone":"+1 763 515 9979",
    "sg:postcode":"55449",
    "sg:province":"MN",
    "sg:tags":[
        "industrial",
        "lift",
        "ramp",
        "elevator",
        "passenger-commercial",
        "elevators-freight",
        "wheelchair"
    ],
    "sg:website":"http://www.arrow-lift.com",
    "wof:name":"Arrow Lift",
    "wof:placetype":"venue"
},
  "geometry": {"coordinates":[-93.231283,45.135441],"type":"Point"}
}