{
  "type": "Feature",
  "properties": {
    "addr:full":"38478 State Hwy 89 Roseau MN 56751",
    "addr:housenumber":"38478",
    "addr:postcode":"56751",
    "addr:street":"State Hwy 89",
    "iso:country":"US",
    "sg:address":"38478 State Hwy 89",
    "sg:city":"Roseau",
    "sg:phone":"+1 218 463 3643",
    "sg:postcode":"56751",
    "sg:province":"MN",
    "sg:tags":[
        "farm",
        "wheat"
    ],
    "wof:name":"Elmer Dahl",
    "wof:placetype":"venue"
},
  "geometry": {"coordinates":[-95.920928,48.953523],"type":"Point"}
}