{
  "type": "Feature",
  "properties": {
    "iso:country":"US",
    "sg:address":"558 Hassan St SE",
    "sg:city":"Hutchinson",
    "sg:classifiers":[
        {
            "category":"Retail",
            "subcategory":"Photofinishing",
            "type":"Services"
        }
    ],
    "sg:phone":"+1 320 587 2494",
    "sg:postcode":"55350",
    "sg:province":"MN",
    "sg:tags":[
        "laboratory",
        "portrait",
        "studio",
        "photo"
    ],
    "wof:name":"Jon I Otteson Photography",
    "wof:placetype":"venue"
},
  "geometry": {"coordinates":[-94.367727,44.885064],"type":"Point"}
}