{
  "type": "Feature",
  "properties": {
    "addr:full":"19350 Ireland Ct Lakeville MN 55044",
    "addr:housenumber":"19350",
    "addr:postcode":"55044",
    "addr:street":"Ireland Ct",
    "iso:country":"US",
    "sg:address":"19350 Ireland Ct",
    "sg:city":"Lakeville",
    "sg:classifiers":[
        {
            "category":"Shopping",
            "subcategory":"Gifts & Souvenirs",
            "type":"Retail Goods"
        }
    ],
    "sg:phone":"+1 952 469 9797",
    "sg:postcode":"55044",
    "sg:province":"MN",
    "sg:tags":[
        "greeting",
        "card"
    ],
    "sg:website":"http://www.woundedcoot.com",
    "wof:name":"Wounded Coot Greetings",
    "wof:placetype":"venue"
},
  "geometry": {"coordinates":[-93.261061,44.66856],"type":"Point"}
}