{
  "type": "Feature",
  "properties": {
    "addr:full":"19270 Martin St NW Cedar MN 55011",
    "addr:housenumber":"19270",
    "addr:postcode":"55011",
    "addr:street":"Martin St Nw Cedar",
    "iso:country":"US",
    "sg:address":"19270 Martin St NW",
    "sg:city":"Cedar",
    "sg:classifiers":[
        {
            "category":"Building & Trades",
            "subcategory":"Electrical",
            "type":"Services"
        }
    ],
    "sg:phone":"+1 763 753 4359",
    "sg:postcode":"55011",
    "sg:province":"MN",
    "sg:tags":[
        "electrical",
        "contractor"
    ],
    "wof:name":"Saturn Electric Inc",
    "wof:placetype":"venue"
},
  "geometry": {"coordinates":[-93.31538500000001,45.319375],"type":"Point"}
}