{
  "type": "Feature",
  "properties": {
    "addr:full":"310 4th Ave Minneapolis MN 55408",
    "addr:housenumber":"310",
    "addr:postcode":"55408",
    "addr:street":"4Th Ave",
    "iso:country":"US",
    "sg:address":"310 4th Ave",
    "sg:city":"Minneapolis",
    "sg:classifiers":[
        {
            "category":"Professional",
            "subcategory":"Lawyer & Legal Services",
            "type":"Services"
        }
    ],
    "sg:phone":"+1 612 339 2022",
    "sg:postcode":"55408",
    "sg:province":"MN",
    "sg:tags":[
        "personal",
        "injury"
    ],
    "sg:website":"www.jeffreyellislaw.com",
    "wof:name":"Ellis Jeffrey M Atty",
    "wof:placetype":"venue"
},
  "geometry": {"coordinates":[-93.263884,44.978263],"type":"Point"}
}