{
  "type": "Feature",
  "properties": {
    "addr:full":"48644 State Highway 38 Marcell MN 56657",
    "addr:housenumber":"48644",
    "addr:postcode":"56657",
    "addr:street":"State Highway 38",
    "iso:country":"US",
    "sg:address":"48644 State Highway 38",
    "sg:city":"Marcell",
    "sg:classifiers":[
        {
            "category":"Bars & Pubs",
            "type":"Food & Drink"
        },
        {
            "category":"Restaurant",
            "type":"Food & Drink"
        }
    ],
    "sg:phone":"+1 218 832 3906",
    "sg:postcode":"56657",
    "sg:province":"MN",
    "sg:tags":[
        "tavern",
        "american"
    ],
    "wof:name":"Richi's Marcell Inn",
    "wof:placetype":"venue"
},
  "geometry": {"coordinates":[-93.672856,47.608391],"type":"Point"}
}