{
  "type": "Feature",
  "properties": {
    "addr:full":"41833 County Highway 16 Morgan MN 56266",
    "addr:housenumber":"41833",
    "addr:postcode":"56266",
    "addr:street":"County Highway 16 Morgan",
    "iso:country":"US",
    "sg:address":"41833 County Highway 16",
    "sg:city":"Morgan",
    "sg:classifiers":[
        {
            "category":"Manufacturing",
            "subcategory":"Food",
            "type":"Manufacturing & Wholesale Goods"
        },
        {
            "category":"Farming",
            "subcategory":"Farm",
            "type":"Manufacturing & Wholesale Goods"
        }
    ],
    "sg:phone":"+1 507 249 3885",
    "sg:postcode":"56266",
    "sg:province":"MN",
    "sg:tags":[
        "corn",
        "product"
    ],
    "wof:name":"Laurie Hoffbeck",
    "wof:placetype":"venue"
},
  "geometry": {"coordinates":[-94.95032399999999,44.383881],"type":"Point"}
}