{
  "type": "Feature",
  "properties": {
    "addr:full":"215 Old Hwy 11 E Greenbush MN 56726",
    "addr:housenumber":"215",
    "addr:postcode":"56726",
    "addr:street":"Old Hwy 11 E",
    "iso:country":"US",
    "sg:address":"215 Old Hwy 11 E",
    "sg:city":"Greenbush",
    "sg:classifiers":[
        {
            "category":"Retail",
            "subcategory":"Repair Shop",
            "type":"Services"
        }
    ],
    "sg:phone":"+1 218 782 3003",
    "sg:postcode":"56726",
    "sg:province":"MN",
    "sg:tags":[
        "related"
    ],
    "wof:name":"Trail Tamers Repair",
    "wof:placetype":"venue"
},
  "geometry": {"coordinates":[-96.174958,48.704846],"type":"Point"}
}