{
  "type": "Feature",
  "properties": {
    "iso:country":"US",
    "sg:address":"106 N Main St",
    "sg:city":"Blue Earth",
    "sg:classifiers":[
        {
            "category":"Retail",
            "subcategory":"Laundry & Dry Cleaning",
            "type":"Services"
        }
    ],
    "sg:phone":"+1 507 526 3295",
    "sg:postcode":"56013",
    "sg:province":"MN",
    "sg:tags":[
        "household",
        "appliance"
    ],
    "wof:name":"Micheles Sales & Service",
    "wof:placetype":"venue"
},
  "geometry": {"coordinates":[-94.102407,43.639591],"type":"Point"}
}