{
  "type": "Feature",
  "properties": {
    "iso:country":"US",
    "sg:address":"4913 Airport Rd",
    "sg:city":"Hermantown",
    "sg:classifiers":[
        {
            "category":"Airline",
            "type":"Transportation"
        }
    ],
    "sg:phone":"+1 218 722 1555",
    "sg:postcode":"55811",
    "sg:province":"MN",
    "sg:tags":[
        "company"
    ],
    "wof:name":"Jetduluth",
    "wof:placetype":"venue"
},
  "geometry": {"coordinates":[-92.200926,46.837282],"type":"Point"}
}