{
  "type": "Feature",
  "properties": {
    "addr:full":"223 E 7th St Crookston MN 56716",
    "addr:housenumber":"223",
    "addr:postcode":"56716",
    "addr:street":"E 7Th St",
    "iso:country":"US",
    "sg:address":"223 E 7th St",
    "sg:city":"Crookston",
    "sg:classifiers":[
        {
            "category":"Organizations",
            "subcategory":"Non-profit Organization",
            "type":"Services"
        }
    ],
    "sg:phone":"+1 218 281 7442",
    "sg:postcode":"56716",
    "sg:province":"MN",
    "sg:tags":[
        "information",
        "alcoholism",
        "treatment"
    ],
    "wof:name":"Migrant Health Chemical",
    "wof:placetype":"venue"
},
  "geometry": {"coordinates":[-96.600847,47.778769],"type":"Point"}
}