{
  "type": "Feature",
  "properties": {
    "addr:full":"313 Main St Lakefield MN 56150",
    "addr:housenumber":"313",
    "addr:postcode":"56150",
    "addr:street":"Main St",
    "iso:country":"US",
    "sg:address":"313 Main St",
    "sg:city":"Lakefield",
    "sg:classifiers":[
        {
            "category":"Banks & Credit Unions",
            "subcategory":"Bank",
            "type":"Services"
        }
    ],
    "sg:phone":"+1 507 662 6680",
    "sg:postcode":"56150",
    "sg:province":"MN",
    "sg:tags":[
        "federal",
        "savings",
        "institution"
    ],
    "wof:name":"Lakefield Savings Bank",
    "wof:placetype":"venue"
},
  "geometry": {"coordinates":[-95.172112,43.678398],"type":"Point"}
}