{
  "type": "Feature",
  "properties": {
    "iso:country":"US",
    "sg:address":"305 S Eliot Ave",
    "sg:city":"Rush City",
    "sg:classifiers":[
        {
            "category":"Recreation",
            "type":"Entertainment"
        }
    ],
    "sg:phone":"+1 320 358 0004",
    "sg:postcode":"55069",
    "sg:province":"MN",
    "sg:tags":[
        "instruction",
        "gymnastic"
    ],
    "wof:name":"Northern Flight Gymnastics",
    "wof:placetype":"venue"
},
  "geometry": {"coordinates":[-92.96608500000001,45.686209],"type":"Point"}
}