{
  "type": "Feature",
  "properties": {
    "addr:full":"6201 Auto Club Rd Minneapolis MN 55438",
    "addr:housenumber":"6201",
    "addr:postcode":"55438",
    "addr:street":"Club Rd",
    "iso:country":"US",
    "sg:address":"6201 Auto Club Rd",
    "sg:city":"Minneapolis",
    "sg:classifiers":[
        {
            "category":"Shopping",
            "subcategory":"Computers & Home Electronics",
            "type":"Retail Goods"
        }
    ],
    "sg:phone":"+1 952 881 8331",
    "sg:postcode":"55438",
    "sg:province":"MN",
    "sg:tags":[
        "consulting",
        "management"
    ],
    "wof:name":"Wealth Planning Systems Inc",
    "wof:placetype":"venue"
},
  "geometry": {"coordinates":[-93.358093,44.79301],"type":"Point"}
}