{
  "type": "Feature",
  "properties": {
    "iso:country":"US",
    "sg:address":"6431 University Ave NE",
    "sg:city":"Minneapolis",
    "sg:classifiers":[
        {
            "category":"Government",
            "subcategory":"Fire Station",
            "type":"Public Place"
        }
    ],
    "sg:phone":"+1 763 572 3613",
    "sg:postcode":"55432",
    "sg:province":"MN",
    "sg:tags":[
        "department"
    ],
    "sg:website":"http://www.springbrooknaturecenter.org",
    "wof:name":"Fridley Fire Department",
    "wof:placetype":"venue"
},
  "geometry": {"coordinates":[-93.263623,45.084083],"type":"Point"}
}