{
  "type": "Feature",
  "properties": {
    "addr:full":"331 Cynthia St Maynard MN 56260",
    "addr:housenumber":"331",
    "addr:postcode":"56260",
    "addr:street":"Cynthia St",
    "iso:country":"US",
    "sg:address":"331 Cynthia St",
    "sg:city":"Maynard",
    "sg:classifiers":[
        {
            "category":"Banks & Credit Unions",
            "subcategory":"Bank",
            "type":"Services"
        }
    ],
    "sg:phone":"+1 320 367 2183",
    "sg:postcode":"56260",
    "sg:province":"MN",
    "sg:tags":[
        "state"
    ],
    "wof:name":"Citizens State Bank",
    "wof:placetype":"venue"
},
  "geometry": {"coordinates":[-95.469553,44.907769],"type":"Point"}
}