{
  "type": "Feature",
  "properties": {
    "addr:full":"7615 Welcome Ave N Minneapolis MN 55443",
    "addr:housenumber":"7615",
    "addr:postcode":"55443",
    "addr:street":"Welcome Ave N",
    "iso:country":"US",
    "sg:address":"7615 Welcome Ave N",
    "sg:city":"Minneapolis",
    "sg:classifiers":[
        {
            "category":"Food & Beverages",
            "subcategory":"Groceries & Convenience Stores",
            "type":"Retail Goods"
        }
    ],
    "sg:phone":"+1 763 566 2338",
    "sg:postcode":"55443",
    "sg:province":"MN",
    "wof:name":"Etosha Markets Inc",
    "wof:placetype":"venue"
},
  "geometry": {"coordinates":[-93.353724,45.093373],"type":"Point"}
}