{
  "type": "Feature",
  "properties": {
    "iso:country":"US",
    "sg:address":"425 Portland Ave S",
    "sg:city":"Minneapolis",
    "sg:classifiers":[
        {
            "category":"Banks & Credit Unions",
            "subcategory":"Bank",
            "type":"Services"
        }
    ],
    "sg:phone":"+1 612 673 4284",
    "sg:postcode":"55415",
    "sg:province":"MN",
    "wof:name":"Star Tribune Employees Cr Un",
    "wof:placetype":"venue"
},
  "geometry": {"coordinates":[-93.26217800000001,44.975602],"type":"Point"}
}