{
  "type": "Feature",
  "properties": {
    "iso:country":"US",
    "sg:address":"129 S Union St",
    "sg:city":"Mora",
    "sg:classifiers":[
        {
            "category":"Personal",
            "subcategory":"Barber",
            "type":"Services"
        }
    ],
    "sg:phone":"+1 320 679 1991",
    "sg:postcode":"55051",
    "sg:province":"MN",
    "sg:tags":[
        "shop"
    ],
    "wof:name":"Downstown Barber Shop",
    "wof:placetype":"venue"
},
  "geometry": {"coordinates":[-93.29714199999999,45.876366],"type":"Point"}
}