{
  "type": "Feature",
  "properties": {
    "addr:full":"817 N Minnesota Ave St Peter MN 56082",
    "addr:housenumber":"817",
    "addr:postcode":"56082",
    "addr:street":"N Minnesota Ave",
    "iso:country":"US",
    "sg:address":"817 N Minnesota Ave",
    "sg:city":"St Peter",
    "sg:classifiers":[
        {
            "category":"Building & Trades",
            "subcategory":"Construction",
            "type":"Services"
        }
    ],
    "sg:phone":"+1 507 934 5688",
    "sg:postcode":"56082",
    "sg:province":"MN",
    "sg:tags":[
        "general",
        "contractor"
    ],
    "wof:name":"Tate Construction",
    "wof:placetype":"venue"
},
  "geometry": {"coordinates":[-93.949189,44.33344],"type":"Point"}
}