{
  "type": "Feature",
  "properties": {
    "addr:full":"401 4th St NW East Grand Forks MN 56721",
    "addr:housenumber":"401",
    "addr:postcode":"56721",
    "addr:street":"4Th St Nw",
    "iso:country":"US",
    "sg:address":"401 4th St NW",
    "sg:city":"East Grand Forks",
    "sg:classifiers":[
        {
            "category":"Government",
            "subcategory":"Office",
            "type":"Public Place"
        }
    ],
    "sg:phone":"+1 218 773 1110",
    "sg:postcode":"56721",
    "sg:province":"MN",
    "wof:name":"Senator Mark Dayton",
    "wof:placetype":"venue"
},
  "geometry": {"coordinates":[-97.025386,47.93033],"type":"Point"}
}