{
  "type": "Feature",
  "properties": {
    "iso:country":"US",
    "sg:address":"965 US Hwy 169",
    "sg:city":"Minneapolis",
    "sg:classifiers":[
        {
            "category":"Professional",
            "type":"Services"
        }
    ],
    "sg:phone":"+1 763 544 0115",
    "sg:postcode":"55441",
    "sg:province":"MN",
    "wof:name":"Peter Kivestu",
    "wof:placetype":"venue"
},
  "geometry": {"coordinates":[-93.400657,44.972853],"type":"Point"}
}