{
  "type": "Feature",
  "properties": {
    "iso:country":"US",
    "sg:address":"4455 Main St NE",
    "sg:city":"Minneapolis",
    "sg:classifiers":[
        {
            "category":"Taxi",
            "type":"Transportation"
        }
    ],
    "sg:phone":"+1 763 784 9000",
    "sg:postcode":"55421",
    "sg:province":"MN",
    "sg:tags":[
        "taxicab"
    ],
    "wof:name":"Advanced Car & Limousine Svc",
    "wof:placetype":"venue"
},
  "geometry": {"coordinates":[-93.267881,45.048992],"type":"Point"}
}