{
  "type": "Feature",
  "properties": {
    "addr:full":"1137 Canterbury Rd Shakopee MN 55379",
    "addr:housenumber":"1137",
    "addr:postcode":"55379",
    "addr:street":"Canterbury Rd",
    "iso:country":"US",
    "sg:address":"1137 Canterbury Rd",
    "sg:city":"Shakopee",
    "sg:classifiers":[
        {
            "category":"Professional",
            "subcategory":"Accounting & Tax Preparation",
            "type":"Services"
        }
    ],
    "sg:phone":"+1 952 233 8803",
    "sg:postcode":"55379",
    "sg:province":"MN",
    "sg:tags":[
        "return",
        "filing"
    ],
    "wof:name":"Jackson Hewitt Tax Svc",
    "wof:placetype":"venue"
},
  "geometry": {"coordinates":[-93.469831,44.789979],"type":"Point"}
}