{
  "type": "Feature",
  "properties": {
    "addr:full":"1025 Main St N Pine City MN 55063",
    "addr:housenumber":"1025",
    "addr:postcode":"55063",
    "addr:street":"Main St N",
    "iso:country":"US",
    "sg:address":"1025 Main St N",
    "sg:city":"Pine City",
    "sg:classifiers":[
        {
            "category":"Retail",
            "subcategory":"Auto Repair",
            "type":"Services"
        }
    ],
    "sg:phone":"+1 320 629 6193",
    "sg:postcode":"55063",
    "sg:province":"MN",
    "sg:tags":[
        "repairing",
        "automobile",
        "radiator"
    ],
    "wof:name":"Stan's Radiator Svc",
    "wof:placetype":"venue"
},
  "geometry": {"coordinates":[-92.9692,45.839331],"type":"Point"}
}