{
  "type": "Feature",
  "properties": {
    "iso:country":"US",
    "sg:address":"4191 2nd St S",
    "sg:city":"St Cloud",
    "sg:classifiers":[
        {
            "category":"Insurance",
            "subcategory":"Insurance Agent",
            "type":"Services"
        }
    ],
    "sg:phone":"+1 320 253 3525",
    "sg:postcode":"56301",
    "sg:province":"MN",
    "wof:name":"Stearns Insurance Svc",
    "wof:placetype":"venue"
},
  "geometry": {"coordinates":[-94.20928600000001,45.549842],"type":"Point"}
}