{
  "type": "Feature",
  "properties": {
    "addr:full":"47427 180th Ave Zumbrota MN 55992",
    "addr:housenumber":"47427",
    "addr:postcode":"55992",
    "addr:street":"180Th Ave",
    "iso:country":"US",
    "sg:address":"47427 180th Ave",
    "sg:city":"Zumbrota",
    "sg:classifiers":[
        {
            "category":"Real Estate",
            "subcategory":"Real Estate Operator",
            "type":"Services"
        }
    ],
    "sg:phone":"+1 507 732 7792",
    "sg:postcode":"55992",
    "sg:province":"MN",
    "sg:tags":[
        "property",
        "lessor"
    ],
    "wof:name":"Swain Ordean",
    "wof:placetype":"venue"
},
  "geometry": {"coordinates":[-92.670717,44.261337],"type":"Point"}
}