{
  "type": "Feature",
  "properties": {
    "iso:country":"US",
    "sg:address":"37254 340th St",
    "sg:city":"Storden",
    "sg:phone":"+1 507 445 3390",
    "sg:postcode":"56174",
    "sg:province":"MN",
    "sg:tags":[
        "farm",
        "soy",
        "corn",
        "bean"
    ],
    "wof:name":"Dean Nelson",
    "wof:placetype":"venue"
},
  "geometry": {"coordinates":[-95.33455499999999,43.992835],"type":"Point"}
}