{
  "type": "Feature",
  "properties": {
    "addr:full":"2425 Earl Ln South Saint Paul MN 55075",
    "addr:housenumber":"2425",
    "addr:postcode":"55075",
    "addr:street":"Earl Ln South",
    "iso:country":"US",
    "sg:address":"2425 Earl Ln",
    "sg:city":"South Saint Paul",
    "sg:classifiers":[
        {
            "category":"Building & Trades",
            "subcategory":"Construction",
            "type":"Services"
        }
    ],
    "sg:phone":"+1 651 455 8926",
    "sg:postcode":"55075",
    "sg:province":"MN",
    "sg:tags":[
        "general",
        "contractor"
    ],
    "wof:name":"Roger Hammitt Construction",
    "wof:placetype":"venue"
},
  "geometry": {"coordinates":[-93.064956,44.892714],"type":"Point"}
}