{
  "type": "Feature",
  "properties": {
    "addr:full":"2000 1st Ave N Moorhead MN 56560",
    "addr:housenumber":"2000",
    "addr:postcode":"56560",
    "addr:street":"1St Ave N",
    "iso:country":"US",
    "sg:address":"2000 1st Ave N",
    "sg:city":"Moorhead",
    "sg:classifiers":[
        {
            "category":"Wholesale",
            "subcategory":"Groceries",
            "type":"Manufacturing & Wholesale Goods"
        }
    ],
    "sg:phone":"+1 218 236 7165",
    "sg:postcode":"56560",
    "sg:province":"MN",
    "wof:name":"Coca-Cola",
    "wof:placetype":"venue"
},
  "geometry": {"coordinates":[-96.748912,46.87618],"type":"Point"}
}