{
  "type": "Feature",
  "properties": {
    "addr:full":"8500 Normandale Blvd Minneapolis MN 55437",
    "addr:housenumber":"8500",
    "addr:postcode":"55437",
    "addr:street":"Normandale Blvd",
    "iso:country":"US",
    "sg:address":"8500 Normandale Blvd",
    "sg:city":"Minneapolis",
    "sg:classifiers":[
        {
            "category":"Education",
            "subcategory":"Vocational School",
            "type":"Public Place"
        }
    ],
    "sg:phone":"+1 952 921 8844",
    "sg:postcode":"55437",
    "sg:province":"MN",
    "sg:tags":[
        "training",
        "computer",
        "consulting"
    ],
    "wof:name":"Executrain",
    "wof:placetype":"venue"
},
  "geometry": {"coordinates":[-93.350301,44.850203],"type":"Point"}
}