{
  "type": "Feature",
  "properties": {
    "addr:full":"7112 Hwy 30 SE Stewartville MN 55976",
    "addr:housenumber":"7112",
    "addr:postcode":"55976",
    "addr:street":"Hwy 30 Se",
    "iso:country":"US",
    "sg:address":"7112 Hwy 30 SE",
    "sg:city":"Stewartville",
    "sg:classifiers":[
        {
            "category":"Farming",
            "subcategory":"Livestock Farm",
            "type":"Manufacturing & Wholesale Goods"
        }
    ],
    "sg:phone":"+1 507 533 4750",
    "sg:postcode":"55976",
    "sg:province":"MN",
    "sg:tags":[
        "beef",
        "feedlot",
        "cattle"
    ],
    "wof:name":"Ron Greenslade",
    "wof:placetype":"venue"
},
  "geometry": {"coordinates":[-92.336197,43.862515],"type":"Point"}
}