{
  "type": "Feature",
  "properties": {
    "iso:country":"US",
    "sg:address":"30536 223rd Ave",
    "sg:city":"Albany",
    "sg:classifiers":[
        {
            "category":"Freight",
            "type":"Transportation"
        }
    ],
    "sg:phone":"+1 320 845 7418",
    "sg:postcode":"56307",
    "sg:province":"MN",
    "sg:tags":[
        "operator",
        "local",
        "trucking"
    ],
    "wof:name":"Jf Melton Trucking",
    "wof:placetype":"venue"
},
  "geometry": {"coordinates":[-94.566298,45.567323],"type":"Point"}
}