{
  "type": "Feature",
  "properties": {
    "addr:full":"217 1st St NE Avon MN 56310",
    "addr:housenumber":"217",
    "addr:postcode":"56310",
    "addr:street":"1St St Ne",
    "iso:country":"US",
    "sg:address":"217 1st St NE",
    "sg:city":"Avon",
    "sg:classifiers":[
        {
            "category":"Retail",
            "subcategory":"Auto Repair",
            "type":"Services"
        }
    ],
    "sg:phone":"+1 320 356 7550",
    "sg:postcode":"56310",
    "sg:province":"MN",
    "sg:tags":[
        "repairing",
        "automobile"
    ],
    "wof:name":"Avon Auto Repair",
    "wof:placetype":"venue"
},
  "geometry": {"coordinates":[-94.448555,45.609782],"type":"Point"}
}