{
  "type": "Feature",
  "properties": {
    "addr:full":"320 Broadway Ave N Cokato MN 55321",
    "addr:housenumber":"320",
    "addr:postcode":"55321",
    "addr:street":"Broadway Ave N",
    "iso:country":"US",
    "sg:address":"320 Broadway Ave N",
    "sg:city":"Cokato",
    "sg:classifiers":[
        {
            "category":"Personal",
            "subcategory":"Beauty Salon",
            "type":"Services"
        }
    ],
    "sg:phone":"+1 320 286 5292",
    "sg:postcode":"55321",
    "sg:province":"MN",
    "wof:name":"Joan's Hair Design",
    "wof:placetype":"venue"
},
  "geometry": {"coordinates":[-94.190156,45.08192],"type":"Point"}
}