{
  "type": "Feature",
  "properties": {
    "addr:full":"9509 Blackoaks Ln N Osseo MN 55311",
    "addr:housenumber":"9509",
    "addr:postcode":"55311",
    "addr:street":"Blackoaks Ln N",
    "iso:country":"US",
    "sg:address":"9509 Blackoaks Ln N",
    "sg:city":"Osseo",
    "sg:classifiers":[
        {
            "category":"Shopping",
            "subcategory":"Mobile Phones",
            "type":"Retail Goods"
        }
    ],
    "sg:phone":"+1 763 416 4555",
    "sg:postcode":"55311",
    "sg:province":"MN",
    "sg:website":"www.sprint.com",
    "wof:name":"Sprint Nextel",
    "wof:placetype":"venue"
},
  "geometry": {"coordinates":[-93.489406,45.128063],"type":"Point"}
}