{
  "type": "Feature",
  "properties": {
    "addr:full":"614 Benson Ave SW Willmar MN 56201",
    "addr:housenumber":"614",
    "addr:postcode":"56201",
    "addr:street":"Benson Ave Sw",
    "iso:country":"US",
    "sg:address":"614 Benson Ave SW",
    "sg:city":"Willmar",
    "sg:classifiers":[
        {
            "category":"Shopping",
            "subcategory":"Used Merchandise",
            "type":"Retail Goods"
        }
    ],
    "sg:phone":"+1 320 231 3748",
    "sg:postcode":"56201",
    "sg:province":"MN",
    "sg:tags":[
        "antique"
    ],
    "wof:name":"L & J Antiques",
    "wof:placetype":"venue"
},
  "geometry": {"coordinates":[-95.05118899999999,45.121708],"type":"Point"}
}