{
  "type": "Feature",
  "properties": {
    "addr:full":"1566 Thomas Ave Saint Paul MN 55104",
    "addr:housenumber":"1566",
    "addr:postcode":"55104",
    "addr:street":"Thomas Ave",
    "iso:country":"US",
    "sg:address":"1566 Thomas Ave",
    "sg:city":"Saint Paul",
    "sg:classifiers":[
        {
            "category":"Social Services",
            "subcategory":"Child Care",
            "type":"Services"
        }
    ],
    "sg:phone":"+1 651 646 5272",
    "sg:postcode":"55104",
    "sg:province":"MN",
    "sg:tags":[
        "day"
    ],
    "sg:website":"www.jehovahlutheran.org",
    "wof:name":"Jehovah Lutheran Church",
    "wof:placetype":"venue"
},
  "geometry": {"coordinates":[-93.16089599999999,44.9566],"type":"Point"}
}