{
  "type": "Feature",
  "properties": {
    "addr:full":"1201 Harmon Pl Minneapolis MN 55403",
    "addr:housenumber":"1201",
    "addr:postcode":"55403",
    "addr:street":"Harmon Pl",
    "iso:country":"US",
    "sg:address":"1201 Harmon Pl",
    "sg:city":"Minneapolis",
    "sg:classifiers":[
        {
            "category":"Professional",
            "subcategory":"Business Services",
            "type":"Services"
        }
    ],
    "sg:phone":"+1 612 359 3643",
    "sg:postcode":"55403",
    "sg:province":"MN",
    "sg:tags":[
        "consultant",
        "coach"
    ],
    "wof:name":"Sphere Works",
    "wof:placetype":"venue"
},
  "geometry": {"coordinates":[-93.279556,44.973808],"type":"Point"}
}