{
  "type": "Feature",
  "properties": {
    "iso:country":"US",
    "sg:address":"3070 Juniper Ave",
    "sg:city":"Slayton",
    "sg:classifiers":[
        {
            "category":"Freight",
            "type":"Transportation"
        }
    ],
    "sg:phone":"+1 507 836 6932",
    "sg:postcode":"56172",
    "sg:province":"MN",
    "sg:tags":[
        "operator",
        "local",
        "trucking"
    ],
    "wof:name":"Smith Trucking",
    "wof:placetype":"venue"
},
  "geometry": {"coordinates":[-95.75924999999999,43.98395],"type":"Point"}
}