{
  "type": "Feature",
  "properties": {
    "addr:full":"110 3rd Ave W Lamberton MN 56152",
    "addr:housenumber":"110",
    "addr:postcode":"56152",
    "addr:street":"3Rd Ave W Lamberton",
    "iso:country":"US",
    "sg:address":"110 3rd Ave W",
    "sg:city":"Lamberton",
    "sg:classifiers":[
        {
            "category":"Retail",
            "subcategory":"Veterinary Services",
            "type":"Services"
        }
    ],
    "sg:phone":"+1 507 752 7785",
    "sg:postcode":"56152",
    "sg:province":"MN",
    "sg:tags":[
        "veterinarian"
    ],
    "wof:name":"Brockway Brown Veterinary Clnc",
    "wof:placetype":"venue"
},
  "geometry": {"coordinates":[-95.264038,44.230263],"type":"Point"}
}