{
  "type": "Feature",
  "properties": {
    "iso:country":"US",
    "sg:address":"19517 Jackie Ln",
    "sg:city":"Rogers",
    "sg:classifiers":[
        {
            "category":"Manufacturing",
            "subcategory":"Tools & Machinery",
            "type":"Manufacturing & Wholesale Goods"
        }
    ],
    "sg:phone":"+1 763 428 4071",
    "sg:postcode":"55374",
    "sg:province":"MN",
    "sg:tags":[
        "mfg"
    ],
    "wof:name":"D & M Tool & Die",
    "wof:placetype":"venue"
},
  "geometry": {"coordinates":[-93.534318,45.151417],"type":"Point"}
}