{
  "type": "Feature",
  "properties": {
    "addr:full":"504 Beltrami Ave NW Bemidji MN 56601",
    "addr:housenumber":"504",
    "addr:postcode":"56601",
    "addr:street":"Beltrami Ave Nw",
    "iso:country":"US",
    "sg:address":"504 Beltrami Ave NW",
    "sg:city":"Bemidji",
    "sg:classifiers":[
        {
            "category":"Professional",
            "subcategory":"Lawyer & Legal Services",
            "type":"Services"
        }
    ],
    "sg:phone":"+1 218 751 6116",
    "sg:postcode":"56601",
    "sg:province":"MN",
    "sg:tags":[
        "attorney"
    ],
    "wof:name":"Ruffenach Law Office",
    "wof:placetype":"venue"
},
  "geometry": {"coordinates":[-94.881136,47.47363],"type":"Point"}
}