{
  "type": "Feature",
  "properties": {
    "addr:full":"2780 290th St Marshall MN 56258",
    "addr:housenumber":"2780",
    "addr:postcode":"56258",
    "addr:street":"290Th St",
    "iso:country":"US",
    "sg:address":"2780 290th St",
    "sg:city":"Marshall",
    "sg:classifiers":[
        {
            "category":"Farming",
            "subcategory":"Livestock Farm",
            "type":"Manufacturing & Wholesale Goods"
        }
    ],
    "sg:phone":"+1 507 537 1822",
    "sg:postcode":"56258",
    "sg:province":"MN",
    "sg:tags":[
        "hog",
        "or",
        "feedlot"
    ],
    "wof:name":"Duane Carrow",
    "wof:placetype":"venue"
},
  "geometry": {"coordinates":[-95.73950499999999,44.472316],"type":"Point"}
}