{
  "type": "Feature",
  "properties": {
    "addr:full":"36749 820th St Okabena MN 56161",
    "addr:housenumber":"36749",
    "addr:postcode":"56161",
    "addr:street":"820Th St",
    "iso:country":"US",
    "sg:address":"36749 820th St",
    "sg:city":"Okabena",
    "sg:classifiers":[
        {
            "category":"Professional",
            "subcategory":"Management & Consulting",
            "type":"Services"
        }
    ],
    "sg:phone":"+1 507 842 5423",
    "sg:postcode":"56161",
    "sg:province":"MN",
    "sg:tags":[
        "farm"
    ],
    "wof:name":"Hank Bauman",
    "wof:placetype":"venue"
},
  "geometry": {"coordinates":[-95.338066,43.674259],"type":"Point"}
}