{
  "type": "Feature",
  "properties": {
    "addr:full":"8548 Ski Chalet Dr Pequot Lakes MN 56472",
    "addr:postcode":"8548;56472",
    "addr:street":"Chalet",
    "iso:country":"US",
    "sg:address":"8548 Ski Chalet Dr",
    "sg:city":"Pequot Lakes",
    "sg:classifiers":[
        {
            "category":"Restaurant",
            "type":"Food & Drink"
        }
    ],
    "sg:phone":"+1 218 562 6013",
    "sg:postcode":"56472",
    "sg:province":"MN",
    "sg:tags":[
        "eating"
    ],
    "wof:name":"Primetime Snow Tubing",
    "wof:placetype":"venue"
},
  "geometry": {"coordinates":[-94.223868,46.60192],"type":"Point"}
}