{
  "type": "Feature",
  "properties": {
    "addr:full":"224 E Bridge Ave Warren MN 56762",
    "addr:housenumber":"224",
    "addr:postcode":"56762",
    "addr:street":"E Bridge Ave",
    "iso:country":"US",
    "sg:address":"224 E Bridge Ave",
    "sg:city":"Warren",
    "sg:classifiers":[
        {
            "category":"Education",
            "subcategory":"School",
            "type":"Public Place"
        }
    ],
    "sg:phone":"+1 218 745 4636",
    "sg:postcode":"56762",
    "sg:province":"MN",
    "sg:tags":[
        "independent",
        "district"
    ],
    "wof:name":"Warren School District 2176",
    "wof:placetype":"venue"
},
  "geometry": {"coordinates":[-96.768513,48.195087],"type":"Point"}
}