{
  "type": "Feature",
  "properties": {
    "addr:full":"202 S Main St Upsala MN 56384",
    "addr:housenumber":"202",
    "addr:postcode":"56384",
    "addr:street":"S Main St",
    "iso:country":"US",
    "sg:address":"202 S Main St",
    "sg:city":"Upsala",
    "sg:classifiers":[
        {
            "category":"Organizations",
            "subcategory":"Religious Organization",
            "type":"Services"
        }
    ],
    "sg:phone":"+1 320 573 2673",
    "sg:postcode":"56384",
    "sg:province":"MN",
    "sg:tags":[
        "clergy"
    ],
    "wof:name":"Craig Johnson",
    "wof:placetype":"venue"
},
  "geometry": {"coordinates":[-94.57144700000001,45.80238],"type":"Point"}
}