{
  "type": "Feature",
  "properties": {
    "iso:country":"US",
    "sg:address":"7535 148th St W",
    "sg:city":"Saint Paul",
    "sg:classifiers":[
        {
            "category":"Shopping",
            "subcategory":"Florist",
            "type":"Retail Goods"
        }
    ],
    "sg:phone":"+1 952 997 7669",
    "sg:postcode":"55124",
    "sg:province":"MN",
    "sg:website":"www.acountryflowermarket.com",
    "wof:name":"A Country Flower Market",
    "wof:placetype":"venue"
},
  "geometry": {"coordinates":[-93.18705,44.735503],"type":"Point"}
}