{
  "type": "Feature",
  "properties": {
    "addr:full":"1704 7TH ST NW ROCHESTER MN 55901",
    "addr:housenumber":"1704",
    "addr:postcode":"55901",
    "addr:street":"7Th St Nw",
    "iso:country":"US",
    "sg:address":"1704 7TH ST NW",
    "sg:city":"ROCHESTER",
    "sg:classifiers":[
        {
            "category":"Home & Garden",
            "subcategory":"Household Appliances",
            "type":"Retail Goods"
        },
        {
            "category":"Retail",
            "subcategory":"Laundry & Dry Cleaning",
            "type":"Services"
        },
        {
            "category":"Building & Trades",
            "subcategory":"Cleaning & Sanitation",
            "type":"Services"
        }
    ],
    "sg:phone":"+1 507 282 5747",
    "sg:postcode":"55901",
    "sg:province":"MN",
    "sg:tags":[
        "cleaner",
        "upholstery",
        "duct",
        "house",
        "rug",
        "air",
        "ventilation",
        "cleaning-industrial",
        "vacuum",
        "curtain",
        "drapery",
        "carpet"
    ],
    "sg:website":"http://www.servicemasterclean.com/reslf/smclean_leadform.asp?url=http://www.servicemasterclean.com/reslf/smclean_leadform.asp&partnerName=YellowPages.com&adName=yptl&HGProp=SMClean",
    "wof:name":"ServiceMaster Clean",
    "wof:placetype":"venue"
},
  "geometry": {"coordinates":[-92.488885,44.032954],"type":"Point"}
}