{
  "type": "Feature",
  "properties": {
    "iso:country":"US",
    "sg:address":"5335 385th Ave",
    "sg:city":"Elmore",
    "sg:phone":"+1 507 526 5576",
    "sg:postcode":"56027",
    "sg:province":"MN",
    "sg:tags":[
        "farm",
        "corn",
        "soybean"
    ],
    "wof:name":"Kelly Drake",
    "wof:placetype":"venue"
},
  "geometry": {"coordinates":[-94.097769,43.56265],"type":"Point"}
}