{
  "type": "Feature",
  "properties": {
    "iso:country":"US",
    "sg:address":"7449 Imperial Dr N",
    "sg:city":"Minneapolis",
    "sg:classifiers":[
        {
            "category":"Real Estate",
            "subcategory":"Real Estate Services",
            "type":"Services"
        }
    ],
    "sg:phone":"+1 866 751 5791",
    "sg:postcode":"55443",
    "sg:province":"MN",
    "sg:tags":[
        "apartment",
        "management",
        "rental",
        "finder"
    ],
    "sg:website":"http://www.forrent.com/apartment-community-profile/1005340.php?cmp=CAC-CSearchProfile",
    "wof:name":"Imperial Gates",
    "wof:placetype":"venue"
},
  "geometry": {"coordinates":[-93.347551,45.090218],"type":"Point"}
}