{
  "type": "Feature",
  "properties": {
    "addr:full":"2012 135th Ln NE Anoka MN 55304",
    "addr:housenumber":"2012",
    "addr:postcode":"55304",
    "addr:street":"135Th Ln Ne",
    "iso:country":"US",
    "sg:address":"2012 135th Ln NE",
    "sg:city":"Anoka",
    "sg:classifiers":[
        {
            "category":"Building & Trades",
            "subcategory":"Electrical",
            "type":"Services"
        }
    ],
    "sg:phone":"+1 763 757 2706",
    "sg:postcode":"55304",
    "sg:province":"MN",
    "sg:tags":[
        "electrical",
        "contractor"
    ],
    "wof:name":"All For One Electric Inc",
    "wof:placetype":"venue"
},
  "geometry": {"coordinates":[-93.218906,45.215731],"type":"Point"}
}