{
  "type": "Feature",
  "properties": {
    "iso:country":"US",
    "sg:address":"4760 Bon Arbor Ln",
    "sg:city":"Brainerd",
    "sg:classifiers":[
        {
            "category":"Shopping",
            "subcategory":"Gifts & Souvenirs",
            "type":"Retail Goods"
        }
    ],
    "sg:phone":"+1 218 828 9010",
    "sg:postcode":"56401",
    "sg:province":"MN",
    "sg:tags":[
        "shop"
    ],
    "wof:name":"Green Porch",
    "wof:placetype":"venue"
},
  "geometry": {"coordinates":[-94.301901,46.42779],"type":"Point"}
}