{
  "type": "Feature",
  "properties": {
    "addr:full":"208 Pine St Nicollet MN 56074",
    "addr:housenumber":"208",
    "addr:postcode":"56074",
    "addr:street":"Pine St",
    "iso:country":"US",
    "sg:address":"208 Pine St",
    "sg:city":"Nicollet",
    "sg:classifiers":[
        {
            "category":"Professional",
            "subcategory":"Art Services",
            "type":"Services"
        }
    ],
    "sg:phone":"+1 507 232 3462",
    "sg:postcode":"56074",
    "sg:province":"MN",
    "sg:tags":[
        "graphic",
        "designer"
    ],
    "sg:website":"www.conceptanddesign.com",
    "wof:name":"Concept & Design",
    "wof:placetype":"venue"
},
  "geometry": {"coordinates":[-94.187894,44.276478],"type":"Point"}
}