{
  "type": "Feature",
  "properties": {
    "iso:country":"US",
    "sg:address":"419 Briar Ln",
    "sg:city":"Taylors Falls",
    "sg:classifiers":[
        {
            "category":"Personal",
            "subcategory":"Beauty Salon",
            "type":"Services"
        }
    ],
    "sg:phone":"+1 651 465 1229",
    "sg:postcode":"55084",
    "sg:province":"MN",
    "sg:tags":[
        "shop"
    ],
    "wof:name":"Lories Hair Care",
    "wof:placetype":"venue"
},
  "geometry": {"coordinates":[-92.657014,45.417937],"type":"Point"}
}