{
  "type": "Feature",
  "properties": {
    "iso:country":"US",
    "sg:address":"1614 Rosehill Cir",
    "sg:city":"Saint Paul",
    "sg:classifiers":[
        {
            "category":"Professional",
            "subcategory":"Computer Services",
            "type":"Services"
        }
    ],
    "sg:phone":"+1 651 644 7287",
    "sg:postcode":"55108",
    "sg:province":"MN",
    "sg:tags":[
        "related"
    ],
    "wof:name":"Anthony M Starfield Cons",
    "wof:placetype":"venue"
},
  "geometry": {"coordinates":[-93.199614,44.991117],"type":"Point"}
}