{
  "type": "Feature",
  "properties": {
    "iso:country":"US",
    "sg:address":"14415 Spring Lake Rd",
    "sg:city":"Minnetonka",
    "sg:classifiers":[
        {
            "category":"Professional",
            "subcategory":"Business Services",
            "type":"Services"
        }
    ],
    "sg:phone":"+1 952 945 7076",
    "sg:postcode":"55345",
    "sg:province":"MN",
    "wof:name":"Cplh Resources Group Inc",
    "wof:placetype":"venue"
},
  "geometry": {"coordinates":[-93.46227500000001,44.93123],"type":"Point"}
}