{
  "type": "Feature",
  "properties": {
    "addr:full":"625 N 6th St Montevideo MN 56265",
    "addr:housenumber":"625",
    "addr:postcode":"56265",
    "addr:street":"N 6Th St",
    "iso:country":"US",
    "sg:address":"625 N 6th St",
    "sg:city":"Montevideo",
    "sg:classifiers":[
        {
            "category":"Autos & Motor Vehicles",
            "subcategory":"Fuel & Gas Station",
            "type":"Retail Goods"
        }
    ],
    "sg:phone":"+1 320 269 8666",
    "sg:postcode":"56265",
    "sg:province":"MN",
    "sg:tags":[
        "oil"
    ],
    "wof:name":"Super America",
    "wof:placetype":"venue"
},
  "geometry": {"coordinates":[-95.719149,44.951423],"type":"Point"}
}