{
  "type": "Feature",
  "properties": {
    "addr:full":"82 Orlin Ave SE Minneapolis MN 55414",
    "addr:housenumber":"82",
    "addr:postcode":"55414",
    "addr:street":"Orlin Ave Se",
    "iso:country":"US",
    "sg:address":"82 Orlin Ave SE",
    "sg:city":"Minneapolis",
    "sg:classifiers":[
        {
            "category":"Professional",
            "subcategory":"Management & Consulting",
            "type":"Services"
        }
    ],
    "sg:phone":"+1 612 625 2338",
    "sg:postcode":"55414",
    "sg:province":"MN",
    "sg:tags":[
        "business"
    ],
    "wof:name":"Abrahamson Energy",
    "wof:placetype":"venue"
},
  "geometry": {"coordinates":[-93.211913,44.966502],"type":"Point"}
}