{
  "type": "Feature",
  "properties": {
    "iso:country":"US",
    "sg:address":"303 E Nicollet Blvd Ste 200",
    "sg:city":"Burnsville",
    "sg:classifiers":[
        {
            "category":"Health Services",
            "subcategory":"Hospital",
            "type":"Services"
        }
    ],
    "sg:phone":"+1 952 885 6235",
    "sg:postcode":"55337",
    "sg:province":"MN",
    "wof:name":"Fairview Ridges Clinic",
    "wof:placetype":"venue"
},
  "geometry": {"coordinates":[-93.272887,44.749963],"type":"Point"}
}