{
  "type": "Feature",
  "properties": {
    "addr:full":"4921 Babcock Trl Inver Grove Hts MN 55077",
    "addr:housenumber":"4921",
    "addr:postcode":"55077",
    "addr:street":"Babcock Trl",
    "iso:country":"US",
    "sg:address":"4921 Babcock Trl",
    "sg:city":"Inver Grove Hts",
    "sg:classifiers":[
        {
            "category":"Building & Trades",
            "subcategory":"Electrical",
            "type":"Services"
        }
    ],
    "sg:phone":"+1 651 450 0352",
    "sg:postcode":"55077",
    "sg:province":"MN",
    "sg:tags":[
        "electric",
        "contractor"
    ],
    "wof:name":"Electric Fire & Security Inc",
    "wof:placetype":"venue"
},
  "geometry": {"coordinates":[-93.065051,44.877008],"type":"Point"}
}