{
  "type": "Feature",
  "properties": {
    "iso:country":"US",
    "sg:address":"4101 W Division St",
    "sg:city":"St Cloud",
    "sg:classifiers":[
        {
            "category":"Professional",
            "type":"Services"
        },
        {
            "category":"Shopping",
            "subcategory":"Gifts & Souvenirs",
            "type":"Retail Goods"
        }
    ],
    "sg:phone":"+1 320 255 1383",
    "sg:postcode":"56301",
    "sg:province":"MN",
    "sg:tags":[
        "sculptor"
    ],
    "wof:name":"Okongo Enterprises",
    "wof:placetype":"venue"
},
  "geometry": {"coordinates":[-94.21331499999999,45.553492],"type":"Point"}
}