{
  "type": "Feature",
  "properties": {
    "addr:full":"26890 62nd St NE Belgrade MN 56312",
    "addr:housenumber":"26890",
    "addr:postcode":"56312",
    "addr:street":"62Nd St Ne",
    "iso:country":"US",
    "sg:address":"26890 62nd St NE",
    "sg:city":"Belgrade",
    "sg:classifiers":[
        {
            "category":"Farming",
            "subcategory":"Farm",
            "type":"Manufacturing & Wholesale Goods"
        }
    ],
    "sg:phone":"+1 320 254 3593",
    "sg:postcode":"56312",
    "sg:province":"MN",
    "sg:tags":[
        "crop",
        "general"
    ],
    "wof:name":"Conservation Reserve",
    "wof:placetype":"venue"
},
  "geometry": {"coordinates":[-94.958178,45.383541],"type":"Point"}
}