{
  "type": "Feature",
  "properties": {
    "iso:country":"US",
    "sg:address":"3040 13th Ter NW",
    "sg:city":"Saint Paul",
    "sg:classifiers":[
        {
            "category":"Building & Trades",
            "subcategory":"Construction",
            "type":"Services"
        }
    ],
    "sg:phone":"+1 651 636 9585",
    "sg:postcode":"55112",
    "sg:province":"MN",
    "sg:tags":[
        "house"
    ],
    "wof:name":"Robert Gary Builders",
    "wof:placetype":"venue"
},
  "geometry": {"coordinates":[-93.22426299999999,45.07074],"type":"Point"}
}