{
  "type": "Feature",
  "properties": {
    "addr:full":"30 W Central St Springfield MN 56087",
    "addr:housenumber":"30",
    "addr:postcode":"56087",
    "addr:street":"W Central St",
    "iso:country":"US",
    "sg:address":"30 W Central St",
    "sg:city":"Springfield",
    "sg:classifiers":[
        {
            "category":"Real Estate",
            "subcategory":"Real Estate Agent",
            "type":"Services"
        }
    ],
    "sg:phone":"+1 507 723 5233",
    "sg:postcode":"56087",
    "sg:province":"MN",
    "wof:name":"Reiner RE & Auctioneering",
    "wof:placetype":"venue"
},
  "geometry": {"coordinates":[-94.97639599999999,44.239036],"type":"Point"}
}