{
  "type": "Feature",
  "properties": {
    "addr:full":"252 E 3rd St Winona MN 55987",
    "addr:housenumber":"252",
    "addr:postcode":"55987",
    "addr:street":"E 3Rd St",
    "iso:country":"US",
    "sg:address":"252 E 3rd St",
    "sg:city":"Winona",
    "sg:classifiers":[
        {
            "category":"Bars & Pubs",
            "type":"Food & Drink"
        }
    ],
    "sg:phone":"+1 507 474 0600",
    "sg:postcode":"55987",
    "sg:province":"MN",
    "sg:tags":[
        "drinking"
    ],
    "wof:name":"Swede's Bar",
    "wof:placetype":"venue"
},
  "geometry": {"coordinates":[-91.63112099999999,44.050942],"type":"Point"}
}