{
  "type": "Feature",
  "properties": {
    "iso:country":"US",
    "sg:address":"108 W 5th St",
    "sg:city":"Starbuck",
    "sg:classifiers":[
        {
            "category":"Shopping",
            "subcategory":"Used Merchandise",
            "type":"Retail Goods"
        }
    ],
    "sg:phone":"+1 320 239 4042",
    "sg:postcode":"56381",
    "sg:province":"MN",
    "wof:name":"Vintage House Antiques",
    "wof:placetype":"venue"
},
  "geometry": {"coordinates":[-95.531234,45.612445],"type":"Point"}
}