{
  "type": "Feature",
  "properties": {
    "iso:country":"US",
    "sg:address":"10210 Crosstown Cir",
    "sg:city":"Eden Prairie",
    "sg:classifiers":[
        {
            "category":"Professional",
            "type":"Services"
        }
    ],
    "sg:phone":"+1 952 983 0401",
    "sg:postcode":"55344",
    "sg:province":"MN",
    "sg:tags":[
        "establishment"
    ],
    "wof:name":"Box World Wide Inc",
    "wof:placetype":"venue"
},
  "geometry": {"coordinates":[-93.40591499999999,44.886137],"type":"Point"}
}