{
  "type": "Feature",
  "properties": {
    "iso:country":"US",
    "sg:address":"912 12th Ave NE",
    "sg:city":"Brainerd",
    "sg:classifiers":[
        {
            "category":"Building & Trades",
            "subcategory":"Construction",
            "type":"Services"
        }
    ],
    "sg:phone":"+1 218 820 4146",
    "sg:postcode":"56401",
    "sg:province":"MN",
    "sg:tags":[
        "wallcoverings-installation",
        "wallpaper",
        "painting",
        "contractor"
    ],
    "wof:name":"Backwoods Interiors",
    "wof:placetype":"venue"
},
  "geometry": {"coordinates":[-94.171661,46.368256],"type":"Point"}
}