{
  "type": "Feature",
  "properties": {
    "iso:country":"US",
    "sg:address":"2565 King Ave",
    "sg:city":"Slayton",
    "sg:classifiers":[
        {
            "category":"Banks & Credit Unions",
            "subcategory":"Investment Brokerage",
            "type":"Services"
        }
    ],
    "sg:phone":"+1 507 836 8814",
    "sg:postcode":"56172",
    "sg:province":"MN",
    "sg:tags":[
        "security"
    ],
    "wof:name":"Minnesota Valley Investments",
    "wof:placetype":"venue"
},
  "geometry": {"coordinates":[-95.757741,43.988291],"type":"Point"}
}