{
  "type": "Feature",
  "properties": {
    "addr:full":"2800 Joppa Ave S Minneapolis MN 55416",
    "addr:housenumber":"2800",
    "addr:postcode":"55416",
    "addr:street":"Joppa Ave S",
    "iso:country":"US",
    "sg:address":"2800 Joppa Ave S",
    "sg:city":"Minneapolis",
    "sg:classifiers":[
        {
            "category":"Education",
            "subcategory":"School",
            "type":"Public Place"
        }
    ],
    "sg:phone":"+1 952 920 7117",
    "sg:postcode":"55416",
    "sg:province":"MN",
    "sg:tags":[
        "high",
        "middle",
        "elementary"
    ],
    "wof:name":"Torah Academy of Mpls",
    "wof:placetype":"venue"
},
  "geometry": {"coordinates":[-93.334,44.9515],"type":"Point"}
}