{
  "type": "Feature",
  "properties": {
    "addr:full":"36 South 9th Street Minneapolis MN 55402",
    "addr:housenumber":"36",
    "addr:postcode":"55402",
    "addr:street":"South 9Th Street",
    "iso:country":"US",
    "sg:address":"36 South 9th Street",
    "sg:city":"Minneapolis",
    "sg:classifiers":[
        {
            "category":"Real Estate",
            "subcategory":"Real Estate Operator",
            "type":"Services"
        }
    ],
    "sg:phone":"+1 612 321 9888",
    "sg:postcode":"55402",
    "sg:province":"MN",
    "sg:tags":[
        "apartment"
    ],
    "wof:name":"LaSalle Apartments",
    "wof:placetype":"venue"
},
  "geometry": {"coordinates":[-93.275312,44.975628],"type":"Point"}
}