{
  "type": "Feature",
  "properties": {
    "addr:full":"210 Alaska Ave Hoffman MN 56339",
    "addr:housenumber":"210",
    "addr:postcode":"56339",
    "addr:street":"Alaska Ave",
    "iso:country":"US",
    "sg:address":"210 Alaska Ave",
    "sg:city":"Hoffman",
    "sg:classifiers":[
        {
            "category":"Building & Trades",
            "subcategory":"Construction",
            "type":"Services"
        }
    ],
    "sg:phone":"+1 320 986 2585",
    "sg:postcode":"56339",
    "sg:province":"MN",
    "sg:tags":[
        "resurfacing",
        "floor",
        "laying",
        "refinishing",
        "contractor"
    ],
    "wof:name":"Anderson's Floor Care",
    "wof:placetype":"venue"
},
  "geometry": {"coordinates":[-95.790406,45.83162],"type":"Point"}
}