{
  "type": "Feature",
  "properties": {
    "iso:country":"US",
    "sg:address":"581 Marschall Rd",
    "sg:city":"Shakopee",
    "sg:classifiers":[
        {
            "category":"Travel",
            "subcategory":"Hotels & Motels",
            "type":"Entertainment"
        }
    ],
    "sg:phone":"+1 952 445 4221",
    "sg:postcode":"55379",
    "sg:province":"MN",
    "sg:website":"www.super8.com",
    "wof:name":"Super 8 Motel",
    "wof:placetype":"venue"
},
  "geometry": {"coordinates":[-93.507896,44.7943],"type":"Point"}
}