{
  "type": "Feature",
  "properties": {
    "iso:country":"US",
    "sg:address":"7136 Sunshine Dr",
    "sg:city":"Eden Prairie",
    "sg:classifiers":[
        {
            "category":"Professional",
            "type":"Services"
        }
    ],
    "sg:phone":"+1 952 975 9589",
    "sg:postcode":"55346",
    "sg:province":"MN",
    "wof:name":"Leadership Challenge Institute",
    "wof:placetype":"venue"
},
  "geometry": {"coordinates":[-93.466505,44.87209],"type":"Point"}
}