{
  "type": "Feature",
  "properties": {
    "iso:country":"US",
    "sg:address":"518 7th Ave NE",
    "sg:city":"Brainerd",
    "sg:classifiers":[
        {
            "category":"Building & Trades",
            "subcategory":"Construction",
            "type":"Services"
        }
    ],
    "sg:phone":"+1 218 927 7004",
    "sg:postcode":"56401",
    "sg:province":"MN",
    "sg:tags":[
        "contractor"
    ],
    "wof:name":"M C Builders & Developers",
    "wof:placetype":"venue"
},
  "geometry": {"coordinates":[-94.178794,46.364793],"type":"Point"}
}