{
  "type": "Feature",
  "properties": {
    "addr:full":"8312 Sheridan Ave S Minneapolis MN 55431",
    "addr:housenumber":"8312",
    "addr:postcode":"55431",
    "addr:street":"Sheridan Ave S",
    "iso:country":"US",
    "sg:address":"8312 Sheridan Ave S",
    "sg:city":"Minneapolis",
    "sg:classifiers":[
        {
            "category":"Shopping",
            "subcategory":"Florist",
            "type":"Retail Goods"
        }
    ],
    "sg:phone":"+1 952 881 3452",
    "sg:postcode":"55431",
    "sg:province":"MN",
    "wof:name":"Forever Yours Silk Floral Dsgn",
    "wof:placetype":"venue"
},
  "geometry": {"coordinates":[-93.312963,44.854114],"type":"Point"}
}