{
  "type": "Feature",
  "properties": {
    "iso:country":"US",
    "sg:address":"1100 Zane Ave N Studio 4",
    "sg:city":"Minneapolis",
    "sg:classifiers":[
        {
            "category":"Communications",
            "subcategory":"Film & Video Production",
            "type":"Services"
        },
        {
            "category":"Professional",
            "subcategory":"Art Services",
            "type":"Services"
        }
    ],
    "sg:phone":"+1 612 382 7988",
    "sg:postcode":"55422",
    "sg:province":"MN",
    "sg:tags":[
        "photographer",
        "photography",
        "videography",
        "aerial"
    ],
    "sg:website":"http://www.landmarkphotodesign.com",
    "wof:name":"Landmark Photography & Design LLP",
    "wof:placetype":"venue"
},
  "geometry": {"coordinates":[-93.35508,44.990089],"type":"Point"}
}