{
  "type": "Feature",
  "properties": {
    "addr:full":"39954 Co Rd 150 Frazee MN 56544",
    "addr:housenumber":"39954;150",
    "addr:postcode":"56544",
    "addr:street":"Co Rd",
    "iso:country":"US",
    "sg:address":"39954 Co Rd 150",
    "sg:city":"Frazee",
    "sg:classifiers":[
        {
            "category":"Farming",
            "subcategory":"Livestock Farm",
            "type":"Manufacturing & Wholesale Goods"
        }
    ],
    "sg:phone":"+1 218 334 4642",
    "sg:postcode":"56544",
    "sg:province":"MN",
    "sg:tags":[
        "hog",
        "or",
        "feedlot"
    ],
    "wof:name":"Mike Byer",
    "wof:placetype":"venue"
},
  "geometry": {"coordinates":[-95.567386,46.730338],"type":"Point"}
}