{
  "type": "Feature",
  "properties": {
    "addr:full":"9263 Cherry Pt Rd SW Alexandria MN 56308",
    "addr:housenumber":"9263",
    "addr:postcode":"56308",
    "addr:street":"Cherry Pt Rd Sw",
    "iso:country":"US",
    "sg:address":"9263 Cherry Pt Rd SW",
    "sg:city":"Alexandria",
    "sg:classifiers":[
        {
            "category":"Building & Trades",
            "subcategory":"Landscaping Services",
            "type":"Services"
        }
    ],
    "sg:phone":"+1 320 834 6211",
    "sg:postcode":"56308",
    "sg:province":"MN",
    "sg:tags":[
        "landscape",
        "contractor"
    ],
    "wof:name":"Lakes Area Landscaping Inc",
    "wof:placetype":"venue"
},
  "geometry": {"coordinates":[-95.510789,45.880798],"type":"Point"}
}