{
  "type": "Feature",
  "properties": {
    "addr:full":"427 Sundial Dr Waite Park MN 56387",
    "addr:housenumber":"427",
    "addr:postcode":"56387",
    "addr:street":"Sundial Dr",
    "iso:country":"US",
    "sg:address":"427 Sundial Dr",
    "sg:city":"Waite Park",
    "sg:classifiers":[
        {
            "category":"Building & Trades",
            "subcategory":"Construction",
            "type":"Services"
        }
    ],
    "sg:phone":"+1 320 230 7700",
    "sg:postcode":"56387",
    "sg:province":"MN",
    "sg:tags":[
        "contractor"
    ],
    "wof:name":"Klaphake Construction",
    "wof:placetype":"venue"
},
  "geometry": {"coordinates":[-94.222686,45.543235],"type":"Point"}
}