{
  "type": "Feature",
  "properties": {
    "addr:full":"308 Park Ave N Park Rapids MN 56470",
    "addr:housenumber":"308",
    "addr:postcode":"56470",
    "addr:street":"Park Ave N",
    "iso:country":"US",
    "sg:address":"308 Park Ave N",
    "sg:city":"Park Rapids",
    "sg:classifiers":[
        {
            "category":"Retail",
            "subcategory":"Auto Repair",
            "type":"Services"
        }
    ],
    "sg:phone":"+1 218 732 0882",
    "sg:postcode":"56470",
    "sg:province":"MN",
    "sg:tags":[
        "automobile",
        "installation",
        "glass"
    ],
    "wof:name":"American Auto Glass",
    "wof:placetype":"venue"
},
  "geometry": {"coordinates":[-95.058423,46.925673],"type":"Point"}
}