{
  "type": "Feature",
  "properties": {
    "addr:full":"7200 France Ave S Minneapolis MN 55435",
    "addr:housenumber":"7200",
    "addr:postcode":"55435",
    "addr:street":"France Ave S",
    "iso:country":"US",
    "sg:address":"7200 France Ave S",
    "sg:city":"Minneapolis",
    "sg:classifiers":[
        {
            "category":"Travel",
            "subcategory":"Travel Agent",
            "type":"Entertainment"
        }
    ],
    "sg:phone":"+1 952 831 3233",
    "sg:postcode":"55435",
    "sg:province":"MN",
    "sg:tags":[
        "agency",
        "services-commercial"
    ],
    "wof:name":"Ex-Press Travel",
    "wof:placetype":"venue"
},
  "geometry": {"coordinates":[-93.329018,44.87273],"type":"Point"}
}