{
  "type": "Feature",
  "properties": {
    "iso:country":"US",
    "sg:address":"500 S Maple St",
    "sg:city":"Waconia",
    "sg:classifiers":[
        {
            "category":"Health Services",
            "subcategory":"Doctor",
            "type":"Services"
        }
    ],
    "sg:phone":"+1 952 446 1200",
    "sg:postcode":"55387",
    "sg:province":"MN",
    "sg:tags":[
        "medical"
    ],
    "wof:name":"Emergency Physician Consu",
    "wof:placetype":"venue"
},
  "geometry": {"coordinates":[-93.790784,44.843539],"type":"Point"}
}