{
  "type": "Feature",
  "properties": {
    "iso:country":"US",
    "sg:address":"1771 Premiere Dr",
    "sg:city":"Mankato",
    "sg:classifiers":[
        {
            "category":"Utilities",
            "subcategory":"Mobile Phone",
            "type":"Services"
        }
    ],
    "sg:phone":"+1 507 625 3340",
    "sg:postcode":"56001",
    "sg:province":"MN",
    "sg:tags":[
        "telephone",
        "cellular"
    ],
    "wof:name":"Trio Wireless",
    "wof:placetype":"venue"
},
  "geometry": {"coordinates":[-93.952105,44.183472],"type":"Point"}
}