{
  "type": "Feature",
  "properties": {
    "addr:full":"15400 296th Ave Zimmerman MN 55398",
    "addr:housenumber":"15400",
    "addr:postcode":"55398",
    "addr:street":"296Th Ave",
    "iso:country":"US",
    "sg:address":"15400 296th Ave",
    "sg:city":"Zimmerman",
    "sg:classifiers":[
        {
            "category":"Professional",
            "type":"Services"
        }
    ],
    "sg:phone":"+1 763 633 4650",
    "sg:postcode":"55398",
    "sg:province":"MN",
    "wof:name":"L & T Tool Service",
    "wof:placetype":"venue"
},
  "geometry": {"coordinates":[-93.65640500000001,45.507419],"type":"Point"}
}