{
  "type": "Feature",
  "properties": {
    "iso:country":"US",
    "sg:address":"25892 Verdin St NW",
    "sg:city":"Isanti",
    "sg:classifiers":[
        {
            "category":"Building & Trades",
            "subcategory":"Construction",
            "type":"Services"
        }
    ],
    "sg:phone":"+1 763 434 0189",
    "sg:postcode":"55040",
    "sg:province":"MN",
    "sg:tags":[
        "carpentry",
        "contractor"
    ],
    "wof:name":"SC Cabinets",
    "wof:placetype":"venue"
},
  "geometry": {"coordinates":[-93.32701,45.437709],"type":"Point"}
}