{
  "type": "Feature",
  "properties": {
    "addr:full":"515 Skyline Blvd Cloquet MN 55720",
    "addr:housenumber":"515",
    "addr:postcode":"55720",
    "addr:street":"Skyline Blvd",
    "iso:country":"US",
    "sg:address":"515 Skyline Blvd",
    "sg:city":"Cloquet",
    "sg:classifiers":[
        {
            "category":"Organizations",
            "subcategory":"Religious Organization",
            "type":"Services"
        }
    ],
    "sg:phone":"+1 218 879 3380",
    "sg:postcode":"55720",
    "sg:province":"MN",
    "sg:tags":[
        "child",
        "day",
        "care"
    ],
    "wof:name":"Our Redeemer Lutheran Church",
    "wof:placetype":"venue"
},
  "geometry": {"coordinates":[-92.46220700000001,46.732055],"type":"Point"}
}