{
  "type": "Feature",
  "properties": {
    "iso:country":"US",
    "sg:address":"54304 190th St",
    "sg:city":"Mankato",
    "sg:phone":"+1 507 278 4865",
    "sg:postcode":"56001",
    "sg:province":"MN",
    "sg:tags":[
        "farm",
        "corn",
        "soybean"
    ],
    "wof:name":"Byron Nelson",
    "wof:placetype":"venue"
},
  "geometry": {"coordinates":[-94.09906100000001,44.094032],"type":"Point"}
}