{
  "type": "Feature",
  "properties": {
    "addr:full":"10808 Zieglers Dr N Minneapolis MN 55443",
    "addr:housenumber":"10808",
    "addr:postcode":"55443",
    "addr:street":"Zieglers Dr N",
    "iso:country":"US",
    "sg:address":"10808 Zieglers Dr N",
    "sg:city":"Minneapolis",
    "sg:classifiers":[
        {
            "category":"Banks & Credit Unions",
            "subcategory":"Financial Services",
            "type":"Services"
        }
    ],
    "sg:phone":"+1 763 427 1808",
    "sg:postcode":"55443",
    "sg:province":"MN",
    "sg:tags":[
        "trust",
        "management"
    ],
    "wof:name":"Chupurdia Family Ltd Part",
    "wof:placetype":"venue"
},
  "geometry": {"coordinates":[-93.32823999999999,45.148749],"type":"Point"}
}