{
  "type": "Feature",
  "properties": {
    "iso:country":"US",
    "sg:address":"6080 60th Ave NE",
    "sg:city":"Murdock",
    "sg:classifiers":[
        {
            "category":"Farming",
            "subcategory":"Farm",
            "type":"Manufacturing & Wholesale Goods"
        }
    ],
    "sg:phone":"+1 320 875 3433",
    "sg:postcode":"56271",
    "sg:province":"MN",
    "wof:name":"Duane Neal Farms",
    "wof:placetype":"venue"
},
  "geometry": {"coordinates":[-95.472336,45.119892],"type":"Point"}
}