{
  "type": "Feature",
  "properties": {
    "addr:full":"1324 E 4th St Duluth MN 55805",
    "addr:housenumber":"1324",
    "addr:postcode":"55805",
    "addr:street":"E 4Th St",
    "iso:country":"US",
    "sg:address":"1324 E 4th St",
    "sg:city":"Duluth",
    "sg:classifiers":[
        {
            "category":"Autos & Motor Vehicles",
            "subcategory":"Auto Supplies",
            "type":"Retail Goods"
        },
        {
            "category":"Wholesale",
            "subcategory":"Electrical",
            "type":"Manufacturing & Wholesale Goods"
        },
        {
            "category":"Wholesale",
            "subcategory":"Auto Parts",
            "type":"Manufacturing & Wholesale Goods"
        }
    ],
    "sg:phone":"+1 218 724 8961",
    "sg:postcode":"55805",
    "sg:province":"MN",
    "sg:tags":[
        "battery",
        "automobile",
        "accessory",
        "equipment",
        "truck",
        "engines-supplies"
    ],
    "sg:website":"http://ad.doubleclick.net/clk;221862232;45455595;j?http://www.carquest.com/carquest/store_locator.html",
    "wof:name":"CARQUEST Auto Parts",
    "wof:placetype":"venue"
},
  "geometry": {"coordinates":[-92.086095,46.80229],"type":"Point"}
}