{
  "type": "Feature",
  "properties": {
    "addr:full":"9781 260th Ave Pierz MN 56364",
    "addr:housenumber":"9781",
    "addr:postcode":"56364",
    "addr:street":"260Th Ave",
    "iso:country":"US",
    "sg:address":"9781 260th Ave",
    "sg:city":"Pierz",
    "sg:classifiers":[
        {
            "category":"Shopping",
            "type":"Retail Goods"
        }
    ],
    "sg:phone":"+1 320 468 0221",
    "sg:postcode":"56364",
    "sg:province":"MN",
    "sg:tags":[
        "merchandise"
    ],
    "wof:name":"Smallfields D & S Elc Mtr Repr",
    "wof:placetype":"venue"
},
  "geometry": {"coordinates":[-94.11559800000001,45.900959],"type":"Point"}
}