{
  "type": "Feature",
  "properties": {
    "addr:full":"6942 Pleasant View Dr Saint Paul MN 55112",
    "addr:housenumber":"6942",
    "addr:postcode":"55112",
    "addr:street":"Pleasant View Dr",
    "iso:country":"US",
    "sg:address":"6942 Pleasant View Dr",
    "sg:city":"Saint Paul",
    "sg:classifiers":[
        {
            "category":"Social Services",
            "subcategory":"Child Care",
            "type":"Services"
        }
    ],
    "sg:phone":"+1 763 784 8140",
    "sg:postcode":"55112",
    "sg:province":"MN",
    "sg:tags":[
        "day"
    ],
    "wof:name":"Joan Sundvall",
    "wof:placetype":"venue"
},
  "geometry": {"coordinates":[-93.22653,45.09613],"type":"Point"}
}