{
  "type": "Feature",
  "properties": {
    "iso:country":"US",
    "sg:address":"103 Main St S",
    "sg:city":"Aurora",
    "sg:classifiers":[
        {
            "category":"Professional",
            "type":"Services"
        }
    ],
    "sg:phone":"+1 218 229 2240",
    "sg:postcode":"55705",
    "sg:province":"MN",
    "sg:tags":[
        "establishment"
    ],
    "wof:name":"A & W Aurora",
    "wof:placetype":"venue"
},
  "geometry": {"coordinates":[-92.237245,47.526342],"type":"Point"}
}