{
  "type": "Feature",
  "properties": {
    "addr:full":"2990 Centre Pointe Dr Saint Paul MN 55113",
    "addr:housenumber":"2990",
    "addr:postcode":"55113",
    "addr:street":"Centre Pointe Dr",
    "iso:country":"US",
    "sg:address":"2990 Centre Pointe Dr",
    "sg:city":"Saint Paul",
    "sg:classifiers":[
        {
            "category":"Banks & Credit Unions",
            "subcategory":"Bank",
            "type":"Services"
        }
    ],
    "sg:phone":"+1 651 276 2666",
    "sg:postcode":"55113",
    "sg:province":"MN",
    "sg:tags":[
        "mortgage"
    ],
    "wof:name":"US Bank",
    "wof:placetype":"venue"
},
  "geometry": {"coordinates":[-93.18879200000001,45.031285],"type":"Point"}
}