{
  "type": "Feature",
  "properties": {
    "addr:full":"507 N Otter Ave Parkers Prairie MN 56361",
    "addr:housenumber":"507",
    "addr:postcode":"56361",
    "addr:street":"N Otter Ave",
    "iso:country":"US",
    "sg:address":"507 N Otter Ave",
    "sg:city":"Parkers Prairie",
    "sg:classifiers":[
        {
            "category":"Autos & Motor Vehicles",
            "subcategory":"Fuel & Gas Station",
            "type":"Retail Goods"
        }
    ],
    "sg:phone":"+1 218 338 5750",
    "sg:postcode":"56361",
    "sg:province":"MN",
    "sg:tags":[
        "excavation",
        "work",
        "gasoline",
        "convenience",
        "station",
        "store"
    ],
    "wof:name":"Jjs Company",
    "wof:placetype":"venue"
},
  "geometry": {"coordinates":[-95.330288,46.161423],"type":"Point"}
}