{
  "type": "Feature",
  "properties": {
    "addr:full":"15250 SW 62nd Ave Ellendale MN 56026",
    "addr:housenumber":"15250",
    "addr:postcode":"56026",
    "addr:street":"Sw 62Nd Ave",
    "iso:country":"US",
    "sg:address":"15250 SW 62nd Ave",
    "sg:city":"Ellendale",
    "sg:phone":"+1 507 684 2258",
    "sg:postcode":"56026",
    "sg:province":"MN",
    "sg:tags":[
        "farm",
        "corn",
        "soybean"
    ],
    "wof:name":"Brent Reese",
    "wof:placetype":"venue"
},
  "geometry": {"coordinates":[-93.32646200000001,43.866528],"type":"Point"}
}