{
  "type": "Feature",
  "properties": {
    "addr:full":"524 Snelling Ave St Paul MN 55104",
    "addr:housenumber":"524",
    "addr:postcode":"55104",
    "addr:street":"Snelling Ave",
    "iso:country":"US",
    "sg:address":"524 Snelling Ave",
    "sg:city":"St Paul",
    "sg:classifiers":[
        {
            "category":"Shopping",
            "subcategory":"Musical Instruments",
            "type":"Retail Goods"
        }
    ],
    "sg:phone":"+1 651 603 0900",
    "sg:postcode":"55104",
    "sg:province":"MN",
    "wof:name":"Risen Drums",
    "wof:placetype":"venue"
},
  "geometry": {"coordinates":[-93.16692500000001,44.957072],"type":"Point"}
}