{
  "type": "Feature",
  "properties": {
    "addr:full":"18473 233rd Ct Hutchinson MN 55350",
    "addr:housenumber":"18473",
    "addr:postcode":"55350",
    "addr:street":"233Rd Ct",
    "iso:country":"US",
    "sg:address":"18473 233rd Ct",
    "sg:city":"Hutchinson",
    "sg:classifiers":[
        {
            "category":"Building & Trades",
            "subcategory":"Construction",
            "type":"Services"
        }
    ],
    "sg:phone":"+1 320 587 3345",
    "sg:postcode":"55350",
    "sg:province":"MN",
    "sg:tags":[
        "housing",
        "family"
    ],
    "wof:name":"Dave Skoog Construction",
    "wof:placetype":"venue"
},
  "geometry": {"coordinates":[-94.36793,44.953239],"type":"Point"}
}