{
  "type": "Feature",
  "properties": {
    "addr:full":"4318 Xerxes Ave N Minneapolis MN 55412",
    "addr:housenumber":"4318",
    "addr:postcode":"55412",
    "addr:street":"Xerxes Ave N",
    "iso:country":"US",
    "sg:address":"4318 Xerxes Ave N",
    "sg:city":"Minneapolis",
    "sg:classifiers":[
        {
            "category":"Professional",
            "subcategory":"Lawyer & Legal Services",
            "type":"Services"
        }
    ],
    "sg:phone":"+1 612 529 6041",
    "sg:postcode":"55412",
    "sg:province":"MN",
    "wof:name":"Johnson Duane G Attorney At Law PA",
    "wof:placetype":"venue"
},
  "geometry": {"coordinates":[-93.31848100000001,45.033787],"type":"Point"}
}