{
  "type": "Feature",
  "properties": {
    "iso:country":"US",
    "sg:address":"4144 11th Ave S",
    "sg:city":"Minneapolis",
    "sg:classifiers":[
        {
            "category":"Professional",
            "subcategory":"Computer Services",
            "type":"Services"
        }
    ],
    "sg:phone":"+1 612 388 0404",
    "sg:postcode":"55407",
    "sg:province":"MN",
    "sg:tags":[
        "datum"
    ],
    "wof:name":"Green Pumpkin Design",
    "wof:placetype":"venue"
},
  "geometry": {"coordinates":[-93.258785,44.927746],"type":"Point"}
}