{
  "type": "Feature",
  "properties": {
    "iso:country":"US",
    "sg:address":"25433 Old Mill Rd",
    "sg:city":"Merrifield",
    "sg:classifiers":[
        {
            "category":"Building & Trades",
            "subcategory":"Construction",
            "type":"Services"
        }
    ],
    "sg:phone":"+1 218 765 4235",
    "sg:postcode":"56465",
    "sg:province":"MN",
    "sg:tags":[
        "general",
        "contractor"
    ],
    "wof:name":"Pine Country Construction",
    "wof:placetype":"venue"
},
  "geometry": {"coordinates":[-94.119855,46.520424],"type":"Point"}
}