{
  "type": "Feature",
  "properties": {
    "iso:country":"US",
    "sg:address":"10260 176th St W",
    "sg:city":"Lakeville",
    "sg:classifiers":[
        {
            "category":"Professional",
            "subcategory":"Management & Consulting",
            "type":"Services"
        }
    ],
    "sg:phone":"+1 952 435 1768",
    "sg:postcode":"55044",
    "sg:province":"MN",
    "wof:name":"Mary Carroll & Assoc LLC",
    "wof:placetype":"venue"
},
  "geometry": {"coordinates":[-93.28482099999999,44.693928],"type":"Point"}
}