{
  "type": "Feature",
  "properties": {
    "iso:country":"US",
    "sg:address":"316 Nokomis St",
    "sg:city":"Alexandria",
    "sg:classifiers":[
        {
            "category":"Insurance",
            "subcategory":"Hazard Insurance",
            "type":"Services"
        },
        {
            "category":"Banks & Credit Unions",
            "subcategory":"Financial Services",
            "type":"Services"
        },
        {
            "category":"Insurance",
            "subcategory":"Health Insurance",
            "type":"Services"
        }
    ],
    "sg:phone":"+1 877 649 1645",
    "sg:postcode":"56308",
    "sg:province":"MN",
    "sg:tags":[
        "sharing",
        "profit",
        "benefit",
        "plan",
        "employee",
        "pension"
    ],
    "wof:name":"Assurant Health Insurance",
    "wof:placetype":"venue"
},
  "geometry": {"coordinates":[-95.366646,45.889036],"type":"Point"}
}