{
  "type": "Feature",
  "properties": {
    "iso:country":"US",
    "sg:address":"1201 Garfield Ave",
    "sg:city":"Albert Lea",
    "sg:classifiers":[
        {
            "category":"Autos & Motor Vehicles",
            "subcategory":"Recreational Vehicle Sales",
            "type":"Retail Goods"
        }
    ],
    "sg:phone":"+1 507 373 5349",
    "sg:postcode":"56007",
    "sg:province":"MN",
    "sg:tags":[
        "automobile",
        "used"
    ],
    "wof:name":"Zetterholm Motors Inc",
    "wof:placetype":"venue"
},
  "geometry": {"coordinates":[-93.354191,43.660083],"type":"Point"}
}