{
  "type": "Feature",
  "properties": {
    "iso:country":"US",
    "sg:address":"412 Lakeland Dr NE",
    "sg:city":"Willmar",
    "sg:classifiers":[
        {
            "category":"Organizations",
            "subcategory":"Labor Organization",
            "type":"Services"
        }
    ],
    "sg:phone":"+1 320 235 4874",
    "sg:postcode":"56201",
    "sg:province":"MN",
    "wof:name":"Christian Labor Assn",
    "wof:placetype":"venue"
},
  "geometry": {"coordinates":[-95.022209,45.125472],"type":"Point"}
}