{
  "type": "Feature",
  "properties": {
    "addr:full":"14581 Grand Ave Burnsville MN 55306",
    "addr:housenumber":"14581",
    "addr:postcode":"55306",
    "addr:street":"Grand Ave",
    "iso:country":"US",
    "sg:address":"14581 Grand Ave",
    "sg:city":"Burnsville",
    "sg:classifiers":[
        {
            "category":"Recreation",
            "type":"Entertainment"
        }
    ],
    "sg:phone":"+1 952 892 7477",
    "sg:postcode":"55306",
    "sg:province":"MN",
    "wof:name":"Midwest Myofascial Therapy Cen",
    "wof:placetype":"venue"
},
  "geometry": {"coordinates":[-93.280112,44.741024],"type":"Point"}
}