{
  "type": "Feature",
  "properties": {
    "addr:full":"8670 Monticello Ln N Osseo MN 55369",
    "addr:housenumber":"8670",
    "addr:postcode":"55369",
    "addr:street":"Monticello Ln N",
    "iso:country":"US",
    "sg:address":"8670 Monticello Ln N",
    "sg:city":"Osseo",
    "sg:classifiers":[
        {
            "category":"Professional",
            "type":"Services"
        }
    ],
    "sg:phone":"+1 763 315 4030",
    "sg:postcode":"55369",
    "sg:province":"MN",
    "wof:name":"Key Services Midwest",
    "wof:placetype":"venue"
},
  "geometry": {"coordinates":[-93.40575200000001,45.112162],"type":"Point"}
}