{
  "type": "Feature",
  "properties": {
    "iso:country":"US",
    "sg:address":"3410 Winnetka Ave",
    "sg:city":"New Hope",
    "sg:classifiers":[
        {
            "category":"Professional",
            "type":"Services"
        }
    ],
    "sg:phone":"+1 763 542 8664",
    "sg:postcode":"55427",
    "sg:province":"MN",
    "sg:tags":[
        "establishment"
    ],
    "wof:name":"Melster Enterprises",
    "wof:placetype":"venue"
},
  "geometry": {"coordinates":[-93.38018700000001,45.01849],"type":"Point"}
}