{
  "type": "Feature",
  "properties": {
    "addr:full":"114 W 9th St Fairmont MN 56031",
    "addr:housenumber":"114",
    "addr:postcode":"56031",
    "addr:street":"W 9Th St",
    "iso:country":"US",
    "sg:address":"114 W 9th St",
    "sg:city":"Fairmont",
    "sg:classifiers":[
        {
            "category":"Social Services",
            "subcategory":"Child Care",
            "type":"Services"
        }
    ],
    "sg:phone":"+1 507 238 4000",
    "sg:postcode":"56031",
    "sg:province":"MN",
    "sg:tags":[
        "day",
        "provider"
    ],
    "wof:name":"Peggy J Goeke",
    "wof:placetype":"venue"
},
  "geometry": {"coordinates":[-94.463015,43.660592],"type":"Point"}
}