{
  "type": "Feature",
  "properties": {
    "iso:country":"US",
    "sg:address":"18803 State Hwy 65",
    "sg:city":"Cedar",
    "sg:classifiers":[
        {
            "category":"Shopping",
            "subcategory":"Used Merchandise",
            "type":"Retail Goods"
        }
    ],
    "sg:phone":"+1 763 434 2121",
    "sg:postcode":"55011",
    "sg:province":"MN",
    "wof:name":"Rainbows End Antiques & Decor",
    "wof:placetype":"venue"
},
  "geometry": {"coordinates":[-93.23565000000001,45.310949],"type":"Point"}
}