{
  "type": "Feature",
  "properties": {
    "iso:country":"US",
    "sg:address":"8651 Basswood Rd",
    "sg:city":"Eden Prairie",
    "sg:classifiers":[
        {
            "category":"Real Estate",
            "subcategory":"Real Estate Operator",
            "type":"Services"
        },
        {
            "category":"Organizations",
            "subcategory":"Community Association",
            "type":"Services"
        }
    ],
    "sg:phone":"+1 952 944 7355",
    "sg:postcode":"55344",
    "sg:province":"MN",
    "sg:tags":[
        "condominium"
    ],
    "wof:name":"Ironwood Condominiums Assn",
    "wof:placetype":"venue"
},
  "geometry": {"coordinates":[-93.412712,44.843078],"type":"Point"}
}