{
  "type": "Feature",
  "properties": {
    "addr:full":"1200 Highway 3 S Northfield MN 55057",
    "addr:housenumber":"1200",
    "addr:postcode":"55057",
    "addr:street":"Highway 3 S",
    "iso:country":"US",
    "sg:address":"1200 Highway 3 S",
    "sg:city":"Northfield",
    "sg:classifiers":[
        {
            "category":"Retail",
            "subcategory":"Veterinary Services",
            "type":"Services"
        }
    ],
    "sg:phone":"+1 888 445 1196",
    "sg:postcode":"55057",
    "sg:province":"MN",
    "sg:tags":[
        "emergency",
        "hospital",
        "specialty",
        "laboratories-veterinary",
        "clinic",
        "veterinarian"
    ],
    "sg:website":"http://local.ingenio.com/Listings/Details.aspx?NUM=a%3a9244783%3a13%3a4859924%3a14%3a0%3a7",
    "wof:name":"Cannon Valley Veterinary Clinic",
    "wof:placetype":"venue"
},
  "geometry": {"coordinates":[-93.17449999999999,44.446435],"type":"Point"}
}