{
  "type": "Feature",
  "properties": {
    "addr:full":"5610 Rowland Rd Hopkins MN 55343",
    "addr:housenumber":"5610",
    "addr:postcode":"55343",
    "addr:street":"Rowland Rd",
    "iso:country":"US",
    "sg:address":"5610 Rowland Rd",
    "sg:city":"Hopkins",
    "sg:classifiers":[
        {
            "category":"Health Services",
            "subcategory":"Hospital",
            "type":"Services"
        }
    ],
    "sg:phone":"+1 952 930 9304",
    "sg:postcode":"55343",
    "sg:province":"MN",
    "sg:tags":[
        "equipment",
        "supply"
    ],
    "wof:name":"Osteologic Inc",
    "wof:placetype":"venue"
},
  "geometry": {"coordinates":[-93.44414,44.903282],"type":"Point"}
}