{
  "type": "Feature",
  "properties": {
    "iso:country":"US",
    "sg:address":"585 Old Crystal Bay Rd N",
    "sg:city":"Long Lake",
    "sg:classifiers":[
        {
            "category":"Organizations",
            "subcategory":"Religious Organization",
            "type":"Services"
        }
    ],
    "sg:phone":"+1 952 475 3000",
    "sg:postcode":"55356",
    "sg:province":"MN",
    "sg:tags":[
        "clergy"
    ],
    "wof:name":"Paul W Berggren",
    "wof:placetype":"venue"
},
  "geometry": {"coordinates":[-93.5943,44.985806],"type":"Point"}
}