{
  "type": "Feature",
  "properties": {
    "iso:country":"US",
    "sg:address":"819 E 3rd St",
    "sg:city":"Duluth",
    "sg:classifiers":[
        {
            "category":"Retail",
            "subcategory":"Repair Shop",
            "type":"Services"
        }
    ],
    "sg:phone":"+1 218 727 1560",
    "sg:postcode":"55805",
    "sg:province":"MN",
    "sg:tags":[
        "lock",
        "locksmith"
    ],
    "wof:name":"A Mattson Lock & Safe Service",
    "wof:placetype":"venue"
},
  "geometry": {"coordinates":[-92.090435,46.797399],"type":"Point"}
}