{
  "type": "Feature",
  "properties": {
    "iso:country":"US",
    "sg:address":"104 5th Ave S",
    "sg:city":"South St Paul",
    "sg:classifiers":[
        {
            "category":"Education",
            "subcategory":"School",
            "type":"Public Place"
        }
    ],
    "sg:phone":"+1 651 457 9400",
    "sg:postcode":"55075",
    "sg:province":"MN",
    "wof:name":"South St Paul School District",
    "wof:placetype":"venue"
},
  "geometry": {"coordinates":[-93.039986,44.889845],"type":"Point"}
}