{
  "type": "Feature",
  "properties": {
    "iso:country":"US",
    "sg:address":"475 N Cleveland Ave",
    "sg:city":"St Paul",
    "sg:classifiers":[
        {
            "category":"Professional",
            "subcategory":"Art Services",
            "type":"Services"
        }
    ],
    "sg:phone":"+1 651 645 3463",
    "sg:postcode":"55104",
    "sg:province":"MN",
    "sg:tags":[
        "graphic",
        "design",
        "designer"
    ],
    "wof:name":"Whaley Design Ltd",
    "wof:placetype":"venue"
},
  "geometry": {"coordinates":[-93.18745199999999,44.955197],"type":"Point"}
}