{
  "type": "Feature",
  "properties": {
    "addr:full":"1910 W Co Rd C Saint Paul MN 55113",
    "addr:housenumber":"1910",
    "addr:postcode":"55113",
    "addr:street":"W Co Rd C",
    "iso:country":"US",
    "sg:address":"1910 W Co Rd C",
    "sg:city":"Saint Paul",
    "sg:classifiers":[
        {
            "category":"Wholesale",
            "subcategory":"Durable Goods & Equipment",
            "type":"Manufacturing & Wholesale Goods"
        }
    ],
    "sg:phone":"+1 651 631 0124",
    "sg:postcode":"55113",
    "sg:province":"MN",
    "sg:tags":[
        "professional"
    ],
    "wof:name":"Bankers Service Company Inc",
    "wof:placetype":"venue"
},
  "geometry": {"coordinates":[-93.181076,45.021022],"type":"Point"}
}