{
  "type": "Feature",
  "properties": {
    "iso:country":"US",
    "sg:address":"60 W Broadway Ave",
    "sg:city":"Bloomington",
    "sg:classifiers":[
        {
            "category":"Food & Beverages",
            "subcategory":"Specialty",
            "type":"Retail Goods"
        }
    ],
    "sg:phone":"+1 952 853 0872",
    "sg:postcode":"55411",
    "sg:province":"MN",
    "sg:tags":[
        "health",
        "diet"
    ],
    "wof:name":"Your Body Repair Shop",
    "wof:placetype":"venue"
},
  "geometry": {"coordinates":[-93.278809,44.999187],"type":"Point"}
}