{
  "type": "Feature",
  "properties": {
    "iso:country":"US",
    "sg:address":"32 10th Ave S",
    "sg:city":"Hopkins",
    "sg:classifiers":[
        {
            "category":"Retail",
            "subcategory":"Repair Shop",
            "type":"Services"
        }
    ],
    "sg:phone":"+1 952 930 9831",
    "sg:postcode":"55343",
    "sg:province":"MN",
    "sg:tags":[
        "lock",
        "locksmith"
    ],
    "wof:name":"Unican Electronic",
    "wof:placetype":"venue"
},
  "geometry": {"coordinates":[-93.412876,44.923009],"type":"Point"}
}