{
  "type": "Feature",
  "properties": {
    "iso:country":"US",
    "sg:address":"286 Knudsen St",
    "sg:city":"Evan",
    "sg:classifiers":[
        {
            "category":"Bars & Pubs",
            "type":"Food & Drink"
        }
    ],
    "sg:phone":"+1 507 794 2581",
    "sg:postcode":"56266",
    "sg:province":"MN",
    "wof:name":"Main Street Bar II",
    "wof:placetype":"venue"
},
  "geometry": {"coordinates":[-94.841134,44.353555],"type":"Point"}
}