{
  "type": "Feature",
  "properties": {
    "addr:full":"2000 Market Dr Stillwater MN 55082",
    "addr:housenumber":"2000",
    "addr:postcode":"55082",
    "addr:street":"Market Dr",
    "iso:country":"US",
    "sg:address":"2000 Market Dr",
    "sg:city":"Stillwater",
    "sg:classifiers":[
        {
            "category":"Retail",
            "subcategory":"Laundry & Dry Cleaning",
            "type":"Services"
        }
    ],
    "sg:phone":"+1 651 439 1690",
    "sg:postcode":"55082",
    "sg:province":"MN",
    "sg:tags":[
        "cleaners"
    ],
    "wof:name":"Clean 'N' Press",
    "wof:placetype":"venue"
},
  "geometry": {"coordinates":[-92.840193,45.036555],"type":"Point"}
}