{
  "type": "Feature",
  "properties": {
    "addr:full":"540 Apollo Ave NE Saint Cloud MN 56304",
    "addr:housenumber":"540",
    "addr:postcode":"56304",
    "addr:street":"Apollo Ave Ne",
    "iso:country":"US",
    "sg:address":"540 Apollo Ave NE",
    "sg:city":"Saint Cloud",
    "sg:classifiers":[
        {
            "category":"Professional",
            "subcategory":"Management & Consulting",
            "type":"Services"
        }
    ],
    "sg:phone":"+1 320 240 6520",
    "sg:postcode":"56304",
    "sg:province":"MN",
    "sg:tags":[
        "food"
    ],
    "wof:name":"Herbalife Independant Distr",
    "wof:placetype":"venue"
},
  "geometry": {"coordinates":[-94.150514,45.576169],"type":"Point"}
}