{
  "type": "Feature",
  "properties": {
    "iso:country":"US",
    "sg:address":"105 Fillmore St E",
    "sg:city":"Preston",
    "sg:classifiers":[
        {
            "category":"Social Services",
            "type":"Services"
        }
    ],
    "sg:phone":"+1 507 765 3667",
    "sg:postcode":"55965",
    "sg:province":"MN",
    "sg:tags":[
        "probation"
    ],
    "wof:name":"Fillmore County Probation Ofc",
    "wof:placetype":"venue"
},
  "geometry": {"coordinates":[-92.080517,43.670385],"type":"Point"}
}