{
  "type": "Feature",
  "properties": {
    "iso:country":"US",
    "sg:address":"4740 Mall Dr",
    "sg:city":"Duluth",
    "sg:classifiers":[
        {
            "category":"Retail",
            "subcategory":"Portrait Studio",
            "type":"Services"
        }
    ],
    "sg:phone":"+1 218 720 6117",
    "sg:postcode":"55811",
    "sg:province":"MN",
    "sg:tags":[
        "photo"
    ],
    "wof:name":"Wal-Mart Prtrait Studio 01757",
    "wof:placetype":"venue"
},
  "geometry": {"coordinates":[-92.180119,46.813875],"type":"Point"}
}