{
  "type": "Feature",
  "properties": {
    "iso:country":"US",
    "sg:address":"13185 43rd St NE",
    "sg:city":"St Michael",
    "sg:classifiers":[
        {
            "category":"Wholesale",
            "subcategory":"Construction Materials",
            "type":"Manufacturing & Wholesale Goods"
        },
        {
            "category":"Manufacturing",
            "subcategory":"Glass & Minerals",
            "type":"Manufacturing & Wholesale Goods"
        }
    ],
    "sg:phone":"+1 763 497 5450",
    "sg:postcode":"55376",
    "sg:province":"MN",
    "sg:tags":[
        "stone",
        "cut",
        "quarry",
        "mfg",
        "dimension",
        "marble"
    ],
    "sg:website":"www.kingsmarble.com",
    "wof:name":"Kings Marble Inc",
    "wof:placetype":"venue"
},
  "geometry": {"coordinates":[-93.62405699999999,45.213822],"type":"Point"}
}