{
  "type": "Feature",
  "properties": {
    "iso:country":"US",
    "sg:address":"40587 State Hwy 6",
    "sg:city":"Emily",
    "sg:classifiers":[
        {
            "category":"Building & Trades",
            "subcategory":"Construction",
            "type":"Services"
        }
    ],
    "sg:phone":"+1 218 763 4200",
    "sg:postcode":"56447",
    "sg:province":"MN",
    "sg:tags":[
        "general",
        "contractor"
    ],
    "wof:name":"Genz Construction",
    "wof:placetype":"venue"
},
  "geometry": {"coordinates":[-93.963291,46.738749],"type":"Point"}
}