{
  "type": "Feature",
  "properties": {
    "iso:country":"US",
    "sg:address":"4346 349th Ave NW",
    "sg:city":"Cambridge",
    "sg:classifiers":[
        {
            "category":"Freight",
            "type":"Transportation"
        }
    ],
    "sg:phone":"+1 763 689 5106",
    "sg:postcode":"55008",
    "sg:province":"MN",
    "sg:tags":[
        "operator",
        "local",
        "trucking"
    ],
    "wof:name":"Friez Trucking",
    "wof:placetype":"venue"
},
  "geometry": {"coordinates":[-93.37764799999999,45.601434],"type":"Point"}
}