{
  "type": "Feature",
  "properties": {
    "iso:country":"US",
    "sg:address":"201 Lake Ave",
    "sg:city":"Fairmont",
    "sg:classifiers":[
        {
            "category":"Government",
            "subcategory":"Office",
            "type":"Public Place"
        }
    ],
    "sg:phone":"+1 507 235 3341",
    "sg:postcode":"56031",
    "sg:province":"MN",
    "wof:name":"Martin County Minnesota Ext",
    "wof:placetype":"venue"
},
  "geometry": {"coordinates":[-94.46587599999999,43.654576],"type":"Point"}
}