{
  "type": "Feature",
  "properties": {
    "iso:country":"US",
    "sg:address":"208 5th Ave NE",
    "sg:city":"Minneapolis",
    "sg:classifiers":[
        {
            "category":"Structure",
            "subcategory":"Office Building",
            "type":"Public Place"
        }
    ],
    "sg:phone":"+1 612 378 0965",
    "sg:postcode":"55413",
    "sg:province":"MN",
    "sg:tags":[
        "park"
    ],
    "wof:name":"Ray Corp Properties",
    "wof:placetype":"venue"
},
  "geometry": {"coordinates":[-93.26154099999999,44.993151],"type":"Point"}
}