{
  "type": "Feature",
  "properties": {
    "iso:country":"US",
    "sg:address":"6497 Glacier Ln N",
    "sg:city":"Osseo",
    "sg:classifiers":[
        {
            "category":"Arts & Performance",
            "subcategory":"Theater",
            "type":"Entertainment"
        }
    ],
    "sg:phone":"+1 763 553 2079",
    "sg:postcode":"55311",
    "sg:province":"MN",
    "sg:tags":[
        "magician"
    ],
    "wof:name":"AAA Quality Clowning",
    "wof:placetype":"venue"
},
  "geometry": {"coordinates":[-93.46054700000001,45.072992],"type":"Point"}
}