{
  "type": "Feature",
  "properties": {
    "addr:full":"21701 John Deere Ln Rogers MN 55374",
    "addr:housenumber":"21701",
    "addr:postcode":"55374",
    "addr:street":"John Deere Ln",
    "iso:country":"US",
    "sg:address":"21701 John Deere Ln",
    "sg:city":"Rogers",
    "sg:classifiers":[
        {
            "category":"Autos & Motor Vehicles",
            "subcategory":"Auto Supplies",
            "type":"Retail Goods"
        },
        {
            "category":"Wholesale",
            "subcategory":"Auto Parts",
            "type":"Manufacturing & Wholesale Goods"
        },
        {
            "category":"Retail",
            "subcategory":"Auto Repair",
            "type":"Services"
        }
    ],
    "sg:phone":"+1 763 428 4331",
    "sg:postcode":"55374",
    "sg:province":"MN",
    "sg:tags":[
        "wheel",
        "automobile",
        "vehicles-supplies",
        "trailers-repair",
        "drive",
        "four",
        "equipment",
        "truck",
        "accessory"
    ],
    "wof:name":"Catco Parts and Service",
    "wof:placetype":"venue"
},
  "geometry": {"coordinates":[-93.553421,45.19051],"type":"Point"}
}