{
  "type": "Feature",
  "properties": {
    "addr:full":"23185 Lawrence Way Hastings MN 55033",
    "addr:housenumber":"23185",
    "addr:postcode":"55033",
    "addr:street":"Lawrence Way",
    "iso:country":"US",
    "sg:address":"23185 Lawrence Way",
    "sg:city":"Hastings",
    "sg:classifiers":[
        {
            "category":"Coffee & Tea",
            "type":"Food & Drink"
        },
        {
            "category":"Restaurant",
            "type":"Food & Drink"
        }
    ],
    "sg:phone":"+1 651 438 3608",
    "sg:postcode":"55033",
    "sg:province":"MN",
    "sg:tags":[
        "espresso"
    ],
    "wof:name":"Solos Pizza Cafe",
    "wof:placetype":"venue"
},
  "geometry": {"coordinates":[-92.858751,44.612193],"type":"Point"}
}