{
  "type": "Feature",
  "properties": {
    "addr:full":"2551 Central Ave NE Minneapolis MN 55418",
    "addr:housenumber":"2551",
    "addr:postcode":"55418",
    "addr:street":"Central Ave Ne",
    "iso:country":"US",
    "sg:address":"2551 Central Ave NE",
    "sg:city":"Minneapolis",
    "sg:classifiers":[
        {
            "category":"Food & Beverages",
            "subcategory":"Bakery",
            "type":"Retail Goods"
        }
    ],
    "sg:phone":"+1 612 781 0548",
    "sg:postcode":"55418",
    "sg:province":"MN",
    "sg:tags":[
        "baker"
    ],
    "wof:name":"Taystee Bakery Outlet Stores",
    "wof:placetype":"venue"
},
  "geometry": {"coordinates":[-93.247337,45.013161],"type":"Point"}
}