{
  "type": "Feature",
  "properties": {
    "iso:country":"US",
    "sg:address":"18 Drew Ave NE",
    "sg:city":"Madelia",
    "sg:classifiers":[
        {
            "category":"Autos & Motor Vehicles",
            "subcategory":"Automobile Sales",
            "type":"Retail Goods"
        }
    ],
    "sg:phone":"+1 507 642 8888",
    "sg:postcode":"56062",
    "sg:province":"MN",
    "sg:tags":[
        "new",
        "used",
        "car"
    ],
    "wof:name":"Dick Olson Motors, Inc.",
    "wof:placetype":"venue"
},
  "geometry": {"coordinates":[-94.409339,44.050973],"type":"Point"}
}