{
  "type": "Feature",
  "properties": {
    "iso:country":"US",
    "sg:address":"25126 Co Hwy 88",
    "sg:city":"Fergus Falls",
    "sg:classifiers":[
        {
            "category":"Professional",
            "subcategory":"Business Services",
            "type":"Services"
        }
    ],
    "sg:phone":"+1 218 736 4797",
    "sg:postcode":"56537",
    "sg:province":"MN",
    "sg:tags":[
        "operator",
        "local",
        "trucking"
    ],
    "wof:name":"Lakes Moving",
    "wof:placetype":"venue"
},
  "geometry": {"coordinates":[-96.113015,46.332497],"type":"Point"}
}