{
  "type": "Feature",
  "properties": {
    "iso:country":"US",
    "sg:address":"821 W Broadway Ave",
    "sg:city":"Minneapolis",
    "sg:classifiers":[
        {
            "category":"Personal",
            "subcategory":"Barber",
            "type":"Services"
        }
    ],
    "sg:phone":"+1 612 521 0219",
    "sg:postcode":"55411",
    "sg:province":"MN",
    "sg:tags":[
        "shop"
    ],
    "wof:name":"House Of Fades",
    "wof:placetype":"venue"
},
  "geometry": {"coordinates":[-93.290806,44.999065],"type":"Point"}
}