{
  "type": "Feature",
  "properties": {
    "iso:country":"US",
    "sg:address":"400 3rd St NE",
    "sg:city":"Plainview",
    "sg:classifiers":[
        {
            "category":"Professional",
            "subcategory":"Computer Services",
            "type":"Services"
        }
    ],
    "sg:phone":"+1 507 534 3719",
    "sg:postcode":"55964",
    "sg:province":"MN",
    "sg:tags":[
        "programing",
        "custom"
    ],
    "wof:name":"Marshik Home Cmpt Assistance",
    "wof:placetype":"venue"
},
  "geometry": {"coordinates":[-92.161675,44.169702],"type":"Point"}
}