{
  "type": "Feature",
  "properties": {
    "iso:country":"US",
    "sg:address":"14235 Jodis Dr",
    "sg:city":"Rogers",
    "sg:classifiers":[
        {
            "category":"Building & Trades",
            "subcategory":"Construction",
            "type":"Services"
        }
    ],
    "sg:phone":"+1 763 428 7376",
    "sg:postcode":"55374",
    "sg:province":"MN",
    "sg:tags":[
        "wallcoverings-installation",
        "wallpaper",
        "painting",
        "contractor"
    ],
    "wof:name":"Becker Painting",
    "wof:placetype":"venue"
},
  "geometry": {"coordinates":[-93.583899,45.211637],"type":"Point"}
}