{
  "type": "Feature",
  "properties": {
    "addr:full":"1326 2nd Ave Worthington MN 56187",
    "addr:housenumber":"1326",
    "addr:postcode":"56187",
    "addr:street":"2Nd Ave",
    "iso:country":"US",
    "sg:address":"1326 2nd Ave",
    "sg:city":"Worthington",
    "sg:classifiers":[
        {
            "category":"Professional",
            "subcategory":"Accounting & Tax Preparation",
            "type":"Services"
        }
    ],
    "sg:phone":"+1 507 376 4108",
    "sg:postcode":"56187",
    "sg:province":"MN",
    "sg:tags":[
        "return",
        "filing"
    ],
    "sg:website":"www.hrblock.com",
    "wof:name":"H & R Block Tax Svc",
    "wof:placetype":"venue"
},
  "geometry": {"coordinates":[-95.59098400000001,43.621615],"type":"Point"}
}