{
  "type": "Feature",
  "properties": {
    "iso:country":"US",
    "sg:address":"16783 Oster Point Rd",
    "sg:city":"Cold Spring",
    "sg:classifiers":[
        {
            "category":"Professional",
            "subcategory":"Computer Services",
            "type":"Services"
        }
    ],
    "sg:phone":"+1 320 685 7506",
    "sg:postcode":"56320",
    "sg:province":"MN",
    "sg:tags":[
        "datum"
    ],
    "wof:name":"Aleksandar Tomovic",
    "wof:placetype":"venue"
},
  "geometry": {"coordinates":[-94.45023500000001,45.442082],"type":"Point"}
}