{
  "type": "Feature",
  "properties": {
    "addr:full":"20260 172nd St Big Lake MN 55309",
    "addr:housenumber":"20260",
    "addr:postcode":"55309",
    "addr:street":"172Nd St",
    "iso:country":"US",
    "sg:address":"20260 172nd St",
    "sg:city":"Big Lake",
    "sg:classifiers":[
        {
            "category":"Farming",
            "subcategory":"Livestock Farm",
            "type":"Manufacturing & Wholesale Goods"
        }
    ],
    "sg:phone":"+1 763 263 2159",
    "sg:postcode":"55309",
    "sg:province":"MN",
    "sg:tags":[
        "beef",
        "feedlot",
        "cattle"
    ],
    "wof:name":"Jim Gallus",
    "wof:placetype":"venue"
},
  "geometry": {"coordinates":[-93.706014,45.340289],"type":"Point"}
}