{
  "type": "Feature",
  "properties": {
    "addr:full":"757 Snelling Ave S Saint Paul MN 55116",
    "addr:housenumber":"757",
    "addr:postcode":"55116",
    "addr:street":"Snelling Ave S",
    "iso:country":"US",
    "sg:address":"757 Snelling Ave S",
    "sg:city":"Saint Paul",
    "sg:classifiers":[
        {
            "category":"Communications",
            "subcategory":"Newspaper",
            "type":"Services"
        }
    ],
    "sg:phone":"+1 651 699 6501",
    "sg:postcode":"55116",
    "sg:province":"MN",
    "sg:tags":[
        "print",
        "medium"
    ],
    "wof:name":"Grand Gazette Newspaper",
    "wof:placetype":"venue"
},
  "geometry": {"coordinates":[-93.166901,44.917999],"type":"Point"}
}