{
  "type": "Feature",
  "properties": {
    "addr:full":"31565 330th St Morgan MN 56266",
    "addr:housenumber":"31565",
    "addr:postcode":"56266",
    "addr:street":"330Th St",
    "iso:country":"US",
    "sg:address":"31565 330th St",
    "sg:city":"Morgan",
    "sg:phone":"+1 507 249 3984",
    "sg:postcode":"56266",
    "sg:province":"MN",
    "sg:tags":[
        "farm",
        "grain",
        "cash"
    ],
    "wof:name":"Esther Greenberg",
    "wof:placetype":"venue"
},
  "geometry": {"coordinates":[-94.824415,44.441572],"type":"Point"}
}