{
  "type": "Feature",
  "properties": {
    "addr:full":"1317 6th Ave E Alexandria MN 56308",
    "addr:housenumber":"1317",
    "addr:postcode":"56308",
    "addr:street":"6Th Ave E",
    "iso:country":"US",
    "sg:address":"1317 6th Ave E",
    "sg:city":"Alexandria",
    "sg:classifiers":[
        {
            "category":"Building & Trades",
            "subcategory":"Construction",
            "type":"Services"
        }
    ],
    "sg:phone":"+1 320 760 9452",
    "sg:postcode":"56308",
    "sg:province":"MN",
    "sg:tags":[
        "concrete",
        "contractor"
    ],
    "wof:name":"Martin Steffens Concrete",
    "wof:placetype":"venue"
},
  "geometry": {"coordinates":[-95.35921,45.885909],"type":"Point"}
}