{
  "type": "Feature",
  "properties": {
    "iso:country":"US",
    "sg:address":"9801 Dupont Ave S Ste 380",
    "sg:city":"Minneapolis",
    "sg:classifiers":[
        {
            "category":"Organizations",
            "subcategory":"Non-profit Organization",
            "type":"Services"
        }
    ],
    "sg:phone":"+1 952 224 0333",
    "sg:postcode":"55431",
    "sg:province":"MN",
    "sg:tags":[
        "service/non-profit",
        "community"
    ],
    "wof:name":"Partnership For Youth",
    "wof:placetype":"venue"
},
  "geometry": {"coordinates":[-93.2938,44.826199],"type":"Point"}
}