{
  "type": "Feature",
  "properties": {
    "addr:full":"617 S Kniss Ave Luverne MN 56156",
    "addr:housenumber":"617",
    "addr:postcode":"56156",
    "addr:street":"S Kniss Ave",
    "iso:country":"US",
    "sg:address":"617 S Kniss Ave",
    "sg:city":"Luverne",
    "sg:classifiers":[
        {
            "category":"Shopping",
            "type":"Retail Goods"
        }
    ],
    "sg:phone":"+1 507 449 6050",
    "sg:postcode":"56156",
    "sg:province":"MN",
    "sg:tags":[
        "pet",
        "food",
        "supply"
    ],
    "wof:name":"Luverne True Value",
    "wof:placetype":"venue"
},
  "geometry": {"coordinates":[-96.21299999999999,43.647839],"type":"Point"}
}