{
  "type": "Feature",
  "properties": {
    "iso:country":"US",
    "sg:address":"6213 Bury Dr",
    "sg:city":"Eden Prairie",
    "sg:classifiers":[
        {
            "category":"Wholesale",
            "subcategory":"Electrical",
            "type":"Manufacturing & Wholesale Goods"
        }
    ],
    "sg:phone":"+1 952 294 0222",
    "sg:postcode":"55346",
    "sg:province":"MN",
    "sg:tags":[
        "battery"
    ],
    "wof:name":"OSI Batteries",
    "wof:placetype":"venue"
},
  "geometry": {"coordinates":[-93.45221100000001,44.891988],"type":"Point"}
}