{
  "type": "Feature",
  "properties": {
    "addr:full":"225 Labree Ave S Thief River Fls MN 56701",
    "addr:housenumber":"225",
    "addr:postcode":"56701",
    "addr:street":"Labree Ave S Thief River Fls",
    "iso:country":"US",
    "sg:address":"225 Labree Ave S",
    "sg:city":"Thief River Fls",
    "sg:classifiers":[
        {
            "category":"Real Estate",
            "subcategory":"Real Estate Operator",
            "type":"Services"
        }
    ],
    "sg:phone":"+1 218 681 7657",
    "sg:postcode":"56701",
    "sg:province":"MN",
    "sg:tags":[
        "apartment"
    ],
    "wof:name":"Riverside Terrace",
    "wof:placetype":"venue"
},
  "geometry": {"coordinates":[-96.180092,48.116583],"type":"Point"}
}