{
  "type": "Feature",
  "properties": {
    "addr:full":"18576 83rd St Royalton MN 56373",
    "addr:housenumber":"18576",
    "addr:postcode":"56373",
    "addr:street":"83Rd St",
    "iso:country":"US",
    "sg:address":"18576 83rd St",
    "sg:city":"Royalton",
    "sg:classifiers":[
        {
            "category":"Farming",
            "subcategory":"Farm",
            "type":"Manufacturing & Wholesale Goods"
        }
    ],
    "sg:phone":"+1 320 584 5370",
    "sg:postcode":"56373",
    "sg:province":"MN",
    "sg:tags":[
        "alfalfa",
        "corn",
        "farmer"
    ],
    "wof:name":"Lanners Dairy",
    "wof:placetype":"venue"
},
  "geometry": {"coordinates":[-94.26548,45.881965],"type":"Point"}
}