{
  "type": "Feature",
  "properties": {
    "iso:country":"US",
    "sg:address":"901 Mall Dr",
    "sg:city":"Duluth",
    "sg:classifiers":[
        {
            "category":"Fast Food",
            "type":"Food & Drink"
        },
        {
            "category":"Restaurant",
            "type":"Food & Drink"
        }
    ],
    "sg:phone":"+1 218 727 2623",
    "sg:postcode":"55811",
    "sg:province":"MN",
    "sg:tags":[
        "style",
        "family",
        "american",
        "take",
        "pasta",
        "italian"
    ],
    "sg:website":"http://www.olivegarden.com",
    "wof:name":"Olive Garden",
    "wof:placetype":"venue"
},
  "geometry": {"coordinates":[-92.14859800000001,46.80212],"type":"Point"}
}