{
  "type": "Feature",
  "properties": {
    "addr:full":"931 Chalet Dr NW Rochester MN 55901",
    "addr:housenumber":"931",
    "addr:postcode":"55901",
    "addr:street":"Chalet Dr Nw",
    "iso:country":"US",
    "sg:address":"931 Chalet Dr NW",
    "sg:city":"Rochester",
    "sg:classifiers":[
        {
            "category":"Insurance",
            "subcategory":"Insurance Agent",
            "type":"Services"
        }
    ],
    "sg:phone":"+1 507 282 5306",
    "sg:postcode":"55901",
    "sg:province":"MN",
    "sg:tags":[
        "consulting",
        "business"
    ],
    "wof:name":"Wilkins & Assoc Inc",
    "wof:placetype":"venue"
},
  "geometry": {"coordinates":[-92.473634,44.05919],"type":"Point"}
}