{
  "type": "Feature",
  "properties": {
    "iso:country":"US",
    "sg:address":"321 5th St SW",
    "sg:city":"Willmar",
    "sg:classifiers":[
        {
            "category":"Personal",
            "type":"Services"
        },
        {
            "category":"Health Services",
            "subcategory":"Health Practitioner",
            "type":"Services"
        }
    ],
    "sg:phone":"+1 320 235 8166",
    "sg:postcode":"56201",
    "sg:province":"MN",
    "sg:tags":[
        "therapist",
        "massage"
    ],
    "wof:name":"Massage Therapy By Edna",
    "wof:placetype":"venue"
},
  "geometry": {"coordinates":[-95.049361,45.121043],"type":"Point"}
}