{
  "type": "Feature",
  "properties": {
    "addr:full":"503 S Whitney St Marshall MN 56258",
    "addr:housenumber":"503",
    "addr:postcode":"56258",
    "addr:street":"S Whitney St",
    "iso:country":"US",
    "sg:address":"503 S Whitney St",
    "sg:city":"Marshall",
    "sg:classifiers":[
        {
            "category":"Organizations",
            "subcategory":"Religious Organization",
            "type":"Services"
        }
    ],
    "sg:phone":"+1 507 532 3306",
    "sg:postcode":"56258",
    "sg:province":"MN",
    "wof:name":"Holy Rdeemer Religious Educatn",
    "wof:placetype":"venue"
},
  "geometry": {"coordinates":[-95.780405,44.446488],"type":"Point"}
}