{
  "type": "Feature",
  "properties": {
    "iso:country":"US",
    "sg:address":"1120 Mill Ave",
    "sg:city":"Brainerd",
    "sg:classifiers":[
        {
            "category":"Retail",
            "subcategory":"Auto Repair",
            "type":"Services"
        }
    ],
    "sg:phone":"+1 218 829 8382",
    "sg:postcode":"56401",
    "sg:province":"MN",
    "sg:tags":[
        "general"
    ],
    "wof:name":"D JS Auto Service",
    "wof:placetype":"venue"
},
  "geometry": {"coordinates":[-94.178355,46.370724],"type":"Point"}
}