{
  "type": "Feature",
  "properties": {
    "iso:country":"US",
    "sg:address":"2203 Grange Rd NW",
    "sg:city":"Bemidji",
    "sg:classifiers":[
        {
            "category":"Building & Trades",
            "subcategory":"Construction",
            "type":"Services"
        }
    ],
    "sg:phone":"+1 218 243 2579",
    "sg:postcode":"56601",
    "sg:province":"MN",
    "sg:tags":[
        "floor",
        "laying",
        "contractor"
    ],
    "wof:name":"Wood Floor Crafter",
    "wof:placetype":"venue"
},
  "geometry": {"coordinates":[-94.905914,47.584836],"type":"Point"}
}