{
  "type": "Feature",
  "properties": {
    "addr:full":"9289 Mound Prairie Dr Houston MN 55943",
    "addr:housenumber":"9289",
    "addr:postcode":"55943",
    "addr:street":"Mound Prairie Dr",
    "iso:country":"US",
    "sg:address":"9289 Mound Prairie Dr",
    "sg:city":"Houston",
    "sg:classifiers":[
        {
            "category":"Farming",
            "subcategory":"Dairy Farm",
            "type":"Manufacturing & Wholesale Goods"
        }
    ],
    "sg:phone":"+1 507 894 4218",
    "sg:postcode":"55943",
    "sg:province":"MN",
    "wof:name":"Marian Lynch",
    "wof:placetype":"venue"
},
  "geometry": {"coordinates":[-91.432529,43.757835],"type":"Point"}
}