{
  "type": "Feature",
  "properties": {
    "iso:country":"US",
    "sg:address":"1010 60th St SE",
    "sg:city":"Montevideo",
    "sg:phone":"+1 320 269 6249",
    "sg:postcode":"56265",
    "sg:province":"MN",
    "sg:tags":[
        "farm",
        "beet"
    ],
    "wof:name":"Jason Sachariason",
    "wof:placetype":"venue"
},
  "geometry": {"coordinates":[-95.57491899999999,44.934588],"type":"Point"}
}