{
  "type": "Feature",
  "properties": {
    "iso:country":"US",
    "sg:address":"1617 3rd Ave NE",
    "sg:city":"Rochester",
    "sg:classifiers":[
        {
            "category":"Building & Trades",
            "subcategory":"Construction",
            "type":"Services"
        }
    ],
    "sg:phone":"+1 507 292 9780",
    "sg:postcode":"55906",
    "sg:province":"MN",
    "sg:tags":[
        "house"
    ],
    "wof:name":"Willis Construction & Rmdlg",
    "wof:placetype":"venue"
},
  "geometry": {"coordinates":[-92.45835099999999,44.040875],"type":"Point"}
}