{
  "type": "Feature",
  "properties": {
    "iso:country":"US",
    "sg:address":"9011 University Ave NE",
    "sg:city":"Blaine",
    "sg:classifiers":[
        {
            "category":"Shopping",
            "subcategory":"Musical Instruments",
            "type":"Retail Goods"
        }
    ],
    "sg:phone":"+1 763 792 4686",
    "sg:postcode":"55434",
    "sg:province":"MN",
    "sg:website":"www.dcmusicusa.com",
    "wof:name":"DC Music USA",
    "wof:placetype":"venue"
},
  "geometry": {"coordinates":[-93.26682700000001,45.133773],"type":"Point"}
}