{
  "type": "Feature",
  "properties": {
    "addr:full":"715 W Hayden Lake Rd Champlin MN 55316",
    "addr:housenumber":"715",
    "addr:postcode":"55316",
    "addr:street":"W Hayden Lake Rd",
    "iso:country":"US",
    "sg:address":"715 W Hayden Lake Rd",
    "sg:city":"Champlin",
    "sg:classifiers":[
        {
            "category":"Retail",
            "subcategory":"Repair Shop",
            "type":"Services"
        }
    ],
    "sg:phone":"+1 763 576 0000",
    "sg:postcode":"55316",
    "sg:province":"MN",
    "sg:tags":[
        "lock",
        "locksmith"
    ],
    "wof:name":"A2Z Lock & Key",
    "wof:placetype":"venue"
},
  "geometry": {"coordinates":[-93.41179200000001,45.180743],"type":"Point"}
}