{
  "type": "Feature",
  "properties": {
    "addr:full":"32653 Roberts Ave Worthington MN 56187",
    "addr:housenumber":"32653",
    "addr:postcode":"56187",
    "addr:street":"Roberts Ave",
    "iso:country":"US",
    "sg:address":"32653 Roberts Ave",
    "sg:city":"Worthington",
    "sg:phone":"+1 507 372 7834",
    "sg:postcode":"56187",
    "sg:province":"MN",
    "sg:tags":[
        "farm",
        "corn",
        "soybean"
    ],
    "wof:name":"Brad Strandberg",
    "wof:placetype":"venue"
},
  "geometry": {"coordinates":[-95.55421,43.521038],"type":"Point"}
}