{
  "type": "Feature",
  "properties": {
    "addr:full":"1795 Radio Dr St Paul MN 55125",
    "addr:housenumber":"1795",
    "addr:postcode":"55125",
    "addr:street":"Radio Dr",
    "iso:country":"US",
    "sg:address":"1795 Radio Dr",
    "sg:city":"St Paul",
    "sg:classifiers":[
        {
            "category":"Restaurant",
            "type":"Food & Drink"
        }
    ],
    "sg:phone":"+1 651 714 0083",
    "sg:postcode":"55125",
    "sg:province":"MN",
    "wof:name":"Quiznos Sub",
    "wof:placetype":"venue"
},
  "geometry": {"coordinates":[-92.933998,44.920456],"type":"Point"}
}