{
  "type": "Feature",
  "properties": {
    "iso:country":"US",
    "sg:address":"3393 Northdale Blvd NW",
    "sg:city":"Minneapolis",
    "sg:classifiers":[
        {
            "category":"Wholesale",
            "subcategory":"Construction Materials",
            "type":"Manufacturing & Wholesale Goods"
        },
        {
            "category":"Home & Garden",
            "subcategory":"Building Materials",
            "type":"Retail Goods"
        }
    ],
    "sg:phone":"+1 612 987 3510",
    "sg:postcode":"55448",
    "sg:province":"MN",
    "sg:tags":[
        "windows-wholesale",
        "window",
        "manufacturer"
    ],
    "wof:name":"Goodfellas",
    "wof:placetype":"venue"
},
  "geometry": {"coordinates":[-93.352687,45.207043],"type":"Point"}
}