{
  "type": "Feature",
  "properties": {
    "addr:full":"1110 Mainstreet Hopkins MN 55343",
    "addr:housenumber":"1110",
    "addr:postcode":"55343",
    "addr:street":"Mainstreet",
    "iso:country":"US",
    "sg:address":"1110 Mainstreet",
    "sg:city":"Hopkins",
    "sg:classifiers":[
        {
            "category":"Restaurant",
            "type":"Food & Drink"
        }
    ],
    "sg:phone":"+1 952 938 0022",
    "sg:postcode":"55343",
    "sg:province":"MN",
    "sg:tags":[
        "shop",
        "coffee"
    ],
    "wof:name":"Caffehaus",
    "wof:placetype":"venue"
},
  "geometry": {"coordinates":[-93.41515200000001,44.924287],"type":"Point"}
}