{
  "type": "Feature",
  "properties": {
    "addr:full":"244 6th St Kandiyohi MN 56251",
    "addr:housenumber":"244",
    "addr:postcode":"56251",
    "addr:street":"6Th St",
    "iso:country":"US",
    "sg:address":"244 6th St",
    "sg:city":"Kandiyohi",
    "sg:classifiers":[
        {
            "category":"Retail",
            "subcategory":"Repair Shop",
            "type":"Services"
        }
    ],
    "sg:phone":"+1 320 382 6442",
    "sg:postcode":"56251",
    "sg:province":"MN",
    "sg:tags":[
        "upholsterer"
    ],
    "wof:name":"Pederson & Pederson",
    "wof:placetype":"venue"
},
  "geometry": {"coordinates":[-94.93355,45.134105],"type":"Point"}
}