{
  "type": "Feature",
  "properties": {
    "iso:country":"US",
    "sg:address":"37902 120th St",
    "sg:city":"Waseca",
    "sg:phone":"+1 507 835 4725",
    "sg:postcode":"56093",
    "sg:province":"MN",
    "sg:tags":[
        "farm",
        "grain",
        "cash"
    ],
    "wof:name":"G W Singlestad",
    "wof:placetype":"venue"
},
  "geometry": {"coordinates":[-93.52698599999999,44.10746],"type":"Point"}
}