{
  "type": "Feature",
  "properties": {
    "iso:country":"US",
    "sg:address":"Glenwood North",
    "sg:city":"Minneapolis",
    "sg:classifiers":[
        {
            "category":"Bars & Pubs",
            "subcategory":"Nightclub",
            "type":"Food & Drink"
        }
    ],
    "sg:postcode":"55474",
    "sg:province":"MN",
    "sg:tags":[
        "nightlife"
    ],
    "wof:name":"Lee's Liquour Lounge",
    "wof:placetype":"venue"
},
  "geometry": {"coordinates":[-93.289483,44.979664],"type":"Point"}
}