{
  "type": "Feature",
  "properties": {
    "iso:country":"US",
    "sg:address":"807 N Broad St",
    "sg:city":"Mankato",
    "sg:classifiers":[
        {
            "category":"Professional",
            "subcategory":"Detective & Security Services",
            "type":"Services"
        }
    ],
    "sg:phone":"+1 507 625 7542",
    "sg:postcode":"56001",
    "sg:province":"MN",
    "sg:tags":[
        "information",
        "bureau"
    ],
    "wof:name":"Habilitative Services",
    "wof:placetype":"venue"
},
  "geometry": {"coordinates":[-93.993797,44.172729],"type":"Point"}
}