{
  "type": "Feature",
  "properties": {
    "addr:full":"2301 Sioux Blvd Saint Paul MN 55112",
    "addr:housenumber":"2301",
    "addr:postcode":"55112",
    "addr:street":"Sioux Blvd",
    "iso:country":"US",
    "sg:address":"2301 Sioux Blvd",
    "sg:city":"Saint Paul",
    "sg:classifiers":[
        {
            "category":"Building & Trades",
            "subcategory":"Plumbing",
            "type":"Services"
        }
    ],
    "sg:phone":"+1 651 263 2440",
    "sg:postcode":"55112",
    "sg:province":"MN",
    "sg:tags":[
        "contractor"
    ],
    "wof:name":"S M Mechanical",
    "wof:placetype":"venue"
},
  "geometry": {"coordinates":[-93.21319099999999,45.055192],"type":"Point"}
}