{
  "type": "Feature",
  "properties": {
    "addr:full":"107 River St Paynesville MN 56362",
    "addr:housenumber":"107",
    "addr:postcode":"56362",
    "addr:street":"River St",
    "iso:country":"US",
    "sg:address":"107 River St",
    "sg:city":"Paynesville",
    "sg:classifiers":[
        {
            "category":"Organizations",
            "subcategory":"Community Association",
            "type":"Services"
        },
        {
            "category":"Social Services",
            "type":"Services"
        }
    ],
    "sg:phone":"+1 320 243 4953",
    "sg:postcode":"56362",
    "sg:province":"MN",
    "wof:name":"Community Service Center",
    "wof:placetype":"venue"
},
  "geometry": {"coordinates":[-94.71571400000001,45.382995],"type":"Point"}
}