{
  "type": "Feature",
  "properties": {
    "iso:country":"US",
    "sg:address":"6320 US Hwy 10",
    "sg:city":"Anoka",
    "sg:classifiers":[
        {
            "category":"Manufacturing",
            "subcategory":"Printing",
            "type":"Manufacturing & Wholesale Goods"
        }
    ],
    "sg:phone":"+1 763 421 0840",
    "sg:postcode":"55303",
    "sg:province":"MN",
    "sg:tags":[
        "commercial",
        "offset"
    ],
    "wof:name":"All-Brite Graphics Inc",
    "wof:placetype":"venue"
},
  "geometry": {"coordinates":[-93.428618,45.219637],"type":"Point"}
}