{
  "type": "Feature",
  "properties": {
    "addr:full":"1402 N 19th Ave E Ely MN 55731",
    "addr:housenumber":"1402",
    "addr:postcode":"55731",
    "addr:street":"N 19Th Ave E Ely",
    "iso:country":"US",
    "sg:address":"1402 N 19th Ave E",
    "sg:city":"Ely",
    "sg:classifiers":[
        {
            "category":"Farming",
            "subcategory":"Farm",
            "type":"Manufacturing & Wholesale Goods"
        }
    ],
    "sg:phone":"+1 218 365 3946",
    "sg:postcode":"55731",
    "sg:province":"MN",
    "sg:tags":[
        "house",
        "construction",
        "crop",
        "general"
    ],
    "wof:name":"Jandrey Construction",
    "wof:placetype":"venue"
},
  "geometry": {"coordinates":[-91.83765699999999,47.916071],"type":"Point"}
}