{
  "type": "Feature",
  "properties": {
    "iso:country":"US",
    "sg:address":"5601 Green Valley Dr",
    "sg:city":"Minneapolis",
    "sg:classifiers":[
        {
            "category":"Professional",
            "subcategory":"Employment Agencies",
            "type":"Services"
        }
    ],
    "sg:phone":"+1 952 918 3666",
    "sg:postcode":"55437",
    "sg:province":"MN",
    "sg:tags":[
        "supply",
        "computer",
        "help",
        "programing",
        "custom"
    ],
    "wof:name":"Techwise Solutions LLC",
    "wof:placetype":"venue"
},
  "geometry": {"coordinates":[-93.35369799999999,44.858391],"type":"Point"}
}