{
  "type": "Feature",
  "properties": {
    "iso:country":"US",
    "sg:address":"4112 18th Ave NW",
    "sg:city":"Rochester",
    "sg:classifiers":[
        {
            "category":"Retail",
            "subcategory":"Self-service Laundry",
            "type":"Services"
        }
    ],
    "sg:phone":"+1 507 288 9864",
    "sg:postcode":"55901",
    "sg:province":"MN",
    "wof:name":"Cedarwood Laundromat",
    "wof:placetype":"venue"
},
  "geometry": {"coordinates":[-92.488826,44.066434],"type":"Point"}
}