{
  "type": "Feature",
  "properties": {
    "addr:full":"3759 Fremont Ave N Minneapolis MN 55412",
    "addr:housenumber":"3759",
    "addr:postcode":"55412",
    "addr:street":"Fremont Ave N",
    "iso:country":"US",
    "sg:address":"3759 Fremont Ave N",
    "sg:city":"Minneapolis",
    "sg:classifiers":[
        {
            "category":"Professional",
            "subcategory":"Business Services",
            "type":"Services"
        },
        {
            "category":"Shopping",
            "subcategory":"Gifts & Souvenirs",
            "type":"Retail Goods"
        }
    ],
    "sg:phone":"+1 612 588 0603",
    "sg:postcode":"55412",
    "sg:province":"MN",
    "sg:tags":[
        "decorating",
        "contractor"
    ],
    "wof:name":"Aardvark Balloons Inc",
    "wof:placetype":"venue"
},
  "geometry": {"coordinates":[-93.295664,45.022916],"type":"Point"}
}