{
  "type": "Feature",
  "properties": {
    "addr:full":"800 N Hampden Ave Saint Paul MN 55114",
    "addr:housenumber":"800",
    "addr:postcode":"55114",
    "addr:street":"N Hampden Ave",
    "iso:country":"US",
    "sg:address":"800 N Hampden Ave",
    "sg:city":"Saint Paul",
    "sg:classifiers":[
        {
            "category":"Professional",
            "type":"Services"
        }
    ],
    "sg:phone":"+1 651 698 9198",
    "sg:postcode":"55114",
    "sg:province":"MN",
    "wof:name":"Daniel A Greenberg",
    "wof:placetype":"venue"
},
  "geometry": {"coordinates":[-93.192466,44.963181],"type":"Point"}
}