{
  "type": "Feature",
  "properties": {
    "iso:country":"US",
    "sg:address":"1805 15th St S",
    "sg:city":"Moorhead",
    "sg:classifiers":[
        {
            "category":"Freight",
            "type":"Transportation"
        }
    ],
    "sg:phone":"+1 218 236 6405",
    "sg:postcode":"56560",
    "sg:province":"MN",
    "sg:tags":[
        "operator",
        "local",
        "trucking"
    ],
    "wof:name":"Ron Hogenson Trucking",
    "wof:placetype":"venue"
},
  "geometry": {"coordinates":[-96.756078,46.855042],"type":"Point"}
}