{
  "type": "Feature",
  "properties": {
    "iso:country":"US",
    "sg:address":"637 US Hwy 12",
    "sg:city":"Litchfield",
    "sg:classifiers":[
        {
            "category":"Wholesale",
            "subcategory":"Medical Equipment & Supplies",
            "type":"Manufacturing & Wholesale Goods"
        }
    ],
    "sg:phone":"+1 320 214 0999",
    "sg:postcode":"55355",
    "sg:province":"MN",
    "sg:tags":[
        "physician",
        "surgeon"
    ],
    "wof:name":"Imperial Medical",
    "wof:placetype":"venue"
},
  "geometry": {"coordinates":[-94.52823600000001,45.133013],"type":"Point"}
}