{
  "type": "Feature",
  "properties": {
    "addr:full":"16 E Derrynane St Le Center MN 56057",
    "addr:housenumber":"16",
    "addr:postcode":"56057",
    "addr:street":"E Derrynane St",
    "iso:country":"US",
    "sg:address":"16 E Derrynane St",
    "sg:city":"Le Center",
    "sg:classifiers":[
        {
            "category":"Home & Garden",
            "subcategory":"Carpets & Floor Coverings",
            "type":"Retail Goods"
        }
    ],
    "sg:phone":"+1 507 357 6810",
    "sg:postcode":"56057",
    "sg:province":"MN",
    "wof:name":"Main Floor NMore",
    "wof:placetype":"venue"
},
  "geometry": {"coordinates":[-93.731388,44.384458],"type":"Point"}
}