{
  "type": "Feature",
  "properties": {
    "iso:country":"US",
    "sg:address":"402 4th St W",
    "sg:city":"Winthrop",
    "sg:classifiers":[
        {
            "category":"Shopping",
            "type":"Retail Goods"
        }
    ],
    "sg:phone":"+1 507 647 7673",
    "sg:postcode":"55396",
    "sg:province":"MN",
    "sg:tags":[
        "wedding",
        "supply"
    ],
    "wof:name":"Blooming Basket Boutique",
    "wof:placetype":"venue"
},
  "geometry": {"coordinates":[-94.37102,44.54304],"type":"Point"}
}