{
  "type": "Feature",
  "properties": {
    "addr:full":"500 S Milton St Saint Paul MN 55102",
    "addr:housenumber":"500",
    "addr:postcode":"55102",
    "addr:street":"S Milton St",
    "iso:country":"US",
    "sg:address":"500 S Milton St",
    "sg:city":"Saint Paul",
    "sg:classifiers":[
        {
            "category":"Wholesale",
            "subcategory":"Farm Supplies",
            "type":"Manufacturing & Wholesale Goods"
        }
    ],
    "sg:phone":"+1 651 451 1042",
    "sg:postcode":"55102",
    "sg:province":"MN",
    "sg:tags":[
        "distributor",
        "horticultural",
        "product"
    ],
    "wof:name":"Schumachers",
    "wof:placetype":"venue"
},
  "geometry": {"coordinates":[-93.13891700000001,44.92655],"type":"Point"}
}