{
  "type": "Feature",
  "properties": {
    "iso:country":"US",
    "sg:address":"7826 Portland Ave S",
    "sg:city":"Minneapolis",
    "sg:phone":"+1 952 884 1067",
    "sg:postcode":"55420",
    "sg:province":"MN",
    "wof:name":"Tbs India Cafe",
    "wof:placetype":"venue"
},
  "geometry": {"coordinates":[-93.26817,44.860571],"type":"Point"}
}