{
  "type": "Feature",
  "properties": {
    "iso:country":"US",
    "sg:address":"230 E 2nd St",
    "sg:city":"Redwood Falls",
    "sg:classifiers":[
        {
            "category":"Professional",
            "type":"Services"
        }
    ],
    "sg:phone":"+1 507 637 5165",
    "sg:postcode":"56283",
    "sg:province":"MN",
    "wof:name":"Don Hardin",
    "wof:placetype":"venue"
},
  "geometry": {"coordinates":[-95.117513,44.540401],"type":"Point"}
}