{
  "type": "Feature",
  "properties": {
    "addr:full":"6861 60th Ave NW Oronoco MN 55960",
    "addr:housenumber":"6861",
    "addr:postcode":"55960",
    "addr:street":"60Th Ave Nw",
    "iso:country":"US",
    "sg:address":"6861 60th Ave NW",
    "sg:city":"Oronoco",
    "sg:classifiers":[
        {
            "category":"Farming",
            "subcategory":"Farm",
            "type":"Manufacturing & Wholesale Goods"
        }
    ],
    "sg:phone":"+1 507 282 5921",
    "sg:postcode":"55960",
    "sg:province":"MN",
    "sg:tags":[
        "crop",
        "general"
    ],
    "wof:name":"F Mathews",
    "wof:placetype":"venue"
},
  "geometry": {"coordinates":[-92.558375,44.097045],"type":"Point"}
}