{
  "type": "Feature",
  "properties": {
    "iso:country":"US",
    "sg:address":"516 Litchfield Ave SW",
    "sg:city":"Willmar",
    "sg:classifiers":[
        {
            "category":"Professional",
            "subcategory":"Lawyer & Legal Services",
            "type":"Services"
        }
    ],
    "sg:phone":"+1 320 235 3022",
    "sg:postcode":"56201",
    "sg:province":"MN",
    "sg:tags":[
        "attorney"
    ],
    "wof:name":"Jones & Fischer",
    "wof:placetype":"venue"
},
  "geometry": {"coordinates":[-95.049673,45.121305],"type":"Point"}
}