{
  "type": "Feature",
  "properties": {
    "addr:full":"2006 Lyndale Ave S Minneapolis MN 55405",
    "addr:housenumber":"2006",
    "addr:postcode":"55405",
    "addr:street":"Lyndale Ave S",
    "iso:country":"US",
    "sg:address":"2006 Lyndale Ave S",
    "sg:city":"Minneapolis",
    "sg:classifiers":[
        {
            "category":"Personal",
            "subcategory":"Barber",
            "type":"Services"
        }
    ],
    "sg:phone":"+1 612 871 9560",
    "sg:postcode":"55405",
    "sg:province":"MN",
    "wof:name":"One 21",
    "wof:placetype":"venue"
},
  "geometry": {"coordinates":[-93.288016,44.962633],"type":"Point"}
}