{
  "type": "Feature",
  "properties": {
    "addr:full":"1317 College Way Fergus Falls MN 56537",
    "addr:housenumber":"1317",
    "addr:postcode":"56537",
    "addr:street":"College Way",
    "iso:country":"US",
    "sg:address":"1317 College Way",
    "sg:city":"Fergus Falls",
    "sg:classifiers":[
        {
            "category":"Retail",
            "subcategory":"Animal Services",
            "type":"Services"
        }
    ],
    "sg:phone":"+1 218 739 9937",
    "sg:postcode":"56537",
    "sg:province":"MN",
    "sg:tags":[
        "pet",
        "boarding",
        "sitting"
    ],
    "wof:name":"T & A Pet Boarding & Grooming",
    "wof:placetype":"venue"
},
  "geometry": {"coordinates":[-96.099692,46.28647],"type":"Point"}
}