{
  "type": "Feature",
  "properties": {
    "iso:country":"US",
    "sg:address":"6822 SE 58th St",
    "sg:city":"Owatonna",
    "sg:classifiers":[
        {
            "category":"Building & Trades",
            "subcategory":"Electrical",
            "type":"Services"
        }
    ],
    "sg:phone":"+1 507 446 8991",
    "sg:postcode":"55060",
    "sg:province":"MN",
    "sg:tags":[
        "electrician"
    ],
    "wof:name":"Coyote Creek Electric",
    "wof:placetype":"venue"
},
  "geometry": {"coordinates":[-93.105228,44.008264],"type":"Point"}
}