{
  "type": "Feature",
  "properties": {
    "addr:full":"207 W Superior St Duluth MN 55802",
    "addr:housenumber":"207",
    "addr:postcode":"55802",
    "addr:street":"W Superior St",
    "iso:country":"US",
    "sg:address":"207 W Superior St",
    "sg:city":"Duluth",
    "sg:classifiers":[
        {
            "category":"Deli",
            "type":"Food & Drink"
        }
    ],
    "sg:menulink":"http://www.allmenus.com/mn/duluth/99688-schlotzskys/menu/",
    "sg:phone":"+1 218 722 5417",
    "sg:postcode":"55802",
    "sg:province":"MN",
    "sg:tags":[
        "wrap",
        "american",
        "sandwich",
        "pizza"
    ],
    "wof:name":"Schlotzsky's",
    "wof:placetype":"venue"
},
  "geometry": {"coordinates":[-92.100708,46.784942],"type":"Point"}
}