{
  "type": "Feature",
  "properties": {
    "addr:full":"1889 E Hwy 2 Grand Rapids MN 55744",
    "addr:housenumber":"1889",
    "addr:postcode":"55744",
    "addr:street":"E Hwy 2",
    "iso:country":"US",
    "sg:address":"1889 E Hwy 2",
    "sg:city":"Grand Rapids",
    "sg:classifiers":[
        {
            "category":"Government",
            "subcategory":"Office",
            "type":"Public Place"
        }
    ],
    "sg:phone":"+1 218 326 6595",
    "sg:postcode":"55744",
    "sg:province":"MN",
    "sg:tags":[
        "federal"
    ],
    "wof:name":"Natural Resources Conservation",
    "wof:placetype":"venue"
},
  "geometry": {"coordinates":[-93.49854999999999,47.22729],"type":"Point"}
}