{
  "type": "Feature",
  "properties": {
    "iso:country":"US",
    "sg:address":"824 S 12th St",
    "sg:city":"Montevideo",
    "sg:classifiers":[
        {
            "category":"Building & Trades",
            "subcategory":"Construction",
            "type":"Services"
        }
    ],
    "sg:phone":"+1 320 269 6223",
    "sg:postcode":"56265",
    "sg:province":"MN",
    "sg:tags":[
        "house"
    ],
    "wof:name":"Scott K Johnson",
    "wof:placetype":"venue"
},
  "geometry": {"coordinates":[-95.71188100000001,44.937543],"type":"Point"}
}