{
  "type": "Feature",
  "properties": {
    "iso:country":"US",
    "sg:address":"425 7th St NW",
    "sg:city":"Cass Lake",
    "sg:classifiers":[
        {
            "category":"Health Services",
            "subcategory":"Nursing And Care Facility",
            "type":"Services"
        }
    ],
    "sg:phone":"+1 218 335 3445",
    "sg:postcode":"56633",
    "sg:province":"MN",
    "wof:name":"Cass Lake",
    "wof:placetype":"venue"
},
  "geometry": {"coordinates":[-94.610091,47.384011],"type":"Point"}
}