{
  "type": "Feature",
  "properties": {
    "iso:country":"US",
    "sg:address":"1204 Park Ave S",
    "sg:city":"Park Rapids",
    "sg:classifiers":[
        {
            "category":"Organizations",
            "subcategory":"Professional Association",
            "type":"Services"
        }
    ],
    "sg:phone":"+1 218 732 4111",
    "sg:postcode":"56470",
    "sg:province":"MN",
    "sg:tags":[
        "chambers",
        "commerce"
    ],
    "wof:name":"Park Rapids Chamber-Commerce",
    "wof:placetype":"venue"
},
  "geometry": {"coordinates":[-95.05815699999999,46.911098],"type":"Point"}
}