{
  "type": "Feature",
  "properties": {
    "addr:full":"2446 University Ave W Saint Paul MN 55114",
    "addr:housenumber":"2446",
    "addr:postcode":"55114",
    "addr:street":"University Ave W",
    "iso:country":"US",
    "sg:address":"2446 University Ave W",
    "sg:city":"Saint Paul",
    "sg:classifiers":[
        {
            "category":"Shopping",
            "subcategory":"Clothing, Apparel, & Fashions",
            "type":"Retail Goods"
        }
    ],
    "sg:phone":"+1 651 251 0061",
    "sg:postcode":"55114",
    "sg:province":"MN",
    "sg:tags":[
        "accessory",
        "clothing",
        "women's"
    ],
    "wof:name":"Amal Latest Fashion",
    "wof:placetype":"venue"
},
  "geometry": {"coordinates":[-93.19899700000001,44.964401],"type":"Point"}
}