{
  "type": "Feature",
  "properties": {
    "addr:full":"303 Railroad St SW Bemidji MN 56601",
    "addr:housenumber":"303",
    "addr:postcode":"56601",
    "addr:street":"Railroad St Sw",
    "iso:country":"US",
    "sg:address":"303 Railroad St SW",
    "sg:city":"Bemidji",
    "sg:classifiers":[
        {
            "category":"Building & Trades",
            "subcategory":"Construction",
            "type":"Services"
        }
    ],
    "sg:phone":"+1 218 751 3958",
    "sg:postcode":"56601",
    "sg:province":"MN",
    "sg:tags":[
        "general",
        "contractor"
    ],
    "wof:name":"M J Construction",
    "wof:placetype":"venue"
},
  "geometry": {"coordinates":[-94.88323099999999,47.467167],"type":"Point"}
}