{
  "type": "Feature",
  "properties": {
    "iso:country":"US",
    "sg:address":"1 Coon Rapids Blvd NW",
    "sg:city":"Minneapolis",
    "sg:classifiers":[
        {
            "category":"Government",
            "subcategory":"Office",
            "type":"Public Place"
        }
    ],
    "sg:phone":"+1 763 323 5777",
    "sg:postcode":"55433",
    "sg:province":"MN",
    "wof:name":"Anoka License Bureau",
    "wof:placetype":"venue"
},
  "geometry": {"coordinates":[-93.26846500000001,45.134226],"type":"Point"}
}