{
  "type": "Feature",
  "properties": {
    "addr:full":"2717 Hwy 14 W Rochester MN 55901",
    "addr:housenumber":"2717",
    "addr:postcode":"55901",
    "addr:street":"Hwy 14 W",
    "iso:country":"US",
    "sg:address":"2717 Hwy 14 W",
    "sg:city":"Rochester",
    "sg:classifiers":[
        {
            "category":"Wholesale",
            "subcategory":"Electrical",
            "type":"Manufacturing & Wholesale Goods"
        }
    ],
    "sg:phone":"+1 507 289 4874",
    "sg:postcode":"55901",
    "sg:province":"MN",
    "sg:tags":[
        "control"
    ],
    "wof:name":"PAAPE Energy Svc",
    "wof:placetype":"venue"
},
  "geometry": {"coordinates":[-92.49719899999999,44.032509],"type":"Point"}
}