{
  "type": "Feature",
  "properties": {
    "iso:country":"US",
    "sg:address":"12002 12th Ave S",
    "sg:city":"Burnsville",
    "sg:classifiers":[
        {
            "category":"Professional",
            "type":"Services"
        }
    ],
    "sg:phone":"+1 952 890 7770",
    "sg:postcode":"55337",
    "sg:province":"MN",
    "wof:name":"Krazee Krazees Inc",
    "wof:placetype":"venue"
},
  "geometry": {"coordinates":[-93.258309,44.786988],"type":"Point"}
}