{
  "type": "Feature",
  "properties": {
    "iso:country":"US",
    "sg:address":"2840 42nd Ave S",
    "sg:city":"Minneapolis",
    "sg:classifiers":[
        {
            "category":"Manufacturing",
            "subcategory":"Food",
            "type":"Manufacturing & Wholesale Goods"
        }
    ],
    "sg:phone":"+1 612 729 0238",
    "sg:postcode":"55406",
    "sg:province":"MN",
    "sg:tags":[
        "product",
        "supplement",
        "dairy",
        "vitamin",
        "mfg"
    ],
    "wof:name":"Horsman Enterprises",
    "wof:placetype":"venue"
},
  "geometry": {"coordinates":[-93.21272999999999,44.951226],"type":"Point"}
}