{
  "type": "Feature",
  "properties": {
    "iso:country":"US",
    "sg:address":"10125 Courthouse Blvd",
    "sg:city":"Inver Grove Hts",
    "sg:classifiers":[
        {
            "category":"Retail",
            "subcategory":"Auto Rental",
            "type":"Services"
        }
    ],
    "sg:phone":"+1 651 554 8496",
    "sg:postcode":"55077",
    "sg:province":"MN",
    "sg:tags":[
        "renting",
        "truck",
        "leasing"
    ],
    "wof:name":"U-Haul Co",
    "wof:placetype":"venue"
},
  "geometry": {"coordinates":[-93.039781,44.803118],"type":"Point"}
}