{
  "type": "Feature",
  "properties": {
    "iso:country":"US",
    "sg:address":"1100 County Road 42 E",
    "sg:city":"Burnsville",
    "sg:classifiers":[
        {
            "category":"Personal",
            "subcategory":"Massage",
            "type":"Services"
        }
    ],
    "sg:phone":"+1 952 953 3313",
    "sg:postcode":"55337",
    "sg:province":"MN",
    "wof:name":"Keep In Touch",
    "wof:placetype":"venue"
},
  "geometry": {"coordinates":[-93.260902,44.738098],"type":"Point"}
}