{
  "type": "Feature",
  "properties": {
    "iso:country":"US",
    "sg:address":"324 E 44th St",
    "sg:city":"Minneapolis",
    "sg:classifiers":[
        {
            "category":"Banks & Credit Unions",
            "subcategory":"Bank",
            "type":"Services"
        }
    ],
    "sg:phone":"+1 612 824 2835",
    "sg:postcode":"55409",
    "sg:province":"MN",
    "sg:tags":[
        "loan",
        "real estate"
    ],
    "wof:name":"Liberty Processing Group",
    "wof:placetype":"venue"
},
  "geometry": {"coordinates":[-93.272049,44.923373],"type":"Point"}
}