{
  "type": "Feature",
  "properties": {
    "iso:country":"US",
    "sg:address":"39309 Fort Rd",
    "sg:city":"Saint Peter",
    "sg:phone":"+1 507 931 4288",
    "sg:postcode":"56082",
    "sg:province":"MN",
    "sg:tags":[
        "farm",
        "wheat"
    ],
    "wof:name":"Triple E Farms",
    "wof:placetype":"venue"
},
  "geometry": {"coordinates":[-94.05382899999999,44.33565],"type":"Point"}
}