{
  "type": "Feature",
  "properties": {
    "addr:full":"104 Jackson Ave Ortonville MN 56278",
    "addr:housenumber":"104",
    "addr:postcode":"56278",
    "addr:street":"Jackson Ave",
    "iso:country":"US",
    "sg:address":"104 Jackson Ave",
    "sg:city":"Ortonville",
    "sg:classifiers":[
        {
            "category":"Government",
            "subcategory":"Post Office",
            "type":"Public Place"
        }
    ],
    "sg:phone":"+1 320 839 2883",
    "sg:postcode":"56278",
    "sg:province":"MN",
    "sg:tags":[
        "postal",
        "us"
    ],
    "wof:name":"US Post Office",
    "wof:placetype":"venue"
},
  "geometry": {"coordinates":[-96.445505,45.304521],"type":"Point"}
}