{
  "type": "Feature",
  "properties": {
    "iso:country":"US",
    "sg:address":"416 S Marshall Ave",
    "sg:city":"Litchfield",
    "sg:classifiers":[
        {
            "category":"Utilities",
            "subcategory":"Refuse",
            "type":"Services"
        }
    ],
    "sg:phone":"+1 320 593 0850",
    "sg:postcode":"55355",
    "sg:province":"MN",
    "sg:tags":[
        "garbage",
        "collection"
    ],
    "wof:name":"N M J's Hauling & Cleanup Svc",
    "wof:placetype":"venue"
},
  "geometry": {"coordinates":[-94.52668300000001,45.122364],"type":"Point"}
}