{
  "type": "Feature",
  "properties": {
    "iso:country":"US",
    "sg:address":"412 E Howard St",
    "sg:city":"Hibbing",
    "sg:classifiers":[
        {
            "category":"Bars & Pubs",
            "type":"Food & Drink"
        }
    ],
    "sg:phone":"+1 218 263 5296",
    "sg:postcode":"55746",
    "sg:province":"MN",
    "wof:name":"Bar 412",
    "wof:placetype":"venue"
},
  "geometry": {"coordinates":[-92.937777,47.427402],"type":"Point"}
}