{
  "type": "Feature",
  "properties": {
    "iso:country":"US",
    "sg:address":"1980 Market Dr",
    "sg:city":"Stillwater",
    "sg:classifiers":[
        {
            "category":"Restaurant",
            "type":"Food & Drink"
        }
    ],
    "sg:phone":"+1 651 430 9888",
    "sg:postcode":"55082",
    "sg:province":"MN",
    "sg:tags":[
        "delivery",
        "take",
        "pizza"
    ],
    "sg:website":"http://broadwaypizza.com",
    "wof:name":"Broadway Pizza",
    "wof:placetype":"venue"
},
  "geometry": {"coordinates":[-92.840428,45.036762],"type":"Point"}
}