{
  "type": "Feature",
  "properties": {
    "iso:country":"US",
    "sg:address":"6005 Logan Ave S",
    "sg:city":"Minneapolis",
    "sg:classifiers":[
        {
            "category":"Professional",
            "type":"Services"
        }
    ],
    "sg:phone":"+1 612 866 7552",
    "sg:postcode":"55419",
    "sg:province":"MN",
    "wof:name":"R & C Weiss Inc",
    "wof:placetype":"venue"
},
  "geometry": {"coordinates":[-93.303997,44.891936],"type":"Point"}
}