{
  "type": "Feature",
  "properties": {
    "addr:full":"715 Katrina Ln Big Lake MN 55309",
    "addr:housenumber":"715",
    "addr:postcode":"55309",
    "addr:street":"Katrina Ln",
    "iso:country":"US",
    "sg:address":"715 Katrina Ln",
    "sg:city":"Big Lake",
    "sg:classifiers":[
        {
            "category":"Real Estate",
            "subcategory":"Real Estate Agent",
            "type":"Services"
        }
    ],
    "sg:phone":"+1 763 263 7411",
    "sg:postcode":"55309",
    "sg:province":"MN",
    "wof:name":"Progressive Realty Inc",
    "wof:placetype":"venue"
},
  "geometry": {"coordinates":[-93.751716,45.324426],"type":"Point"}
}