{
  "type": "Feature",
  "properties": {
    "addr:full":"819 E Elm St Redwood Falls MN 56283",
    "addr:housenumber":"819",
    "addr:postcode":"56283",
    "addr:street":"E Elm St",
    "iso:country":"US",
    "sg:address":"819 E Elm St",
    "sg:city":"Redwood Falls",
    "sg:classifiers":[
        {
            "category":"Social Services",
            "subcategory":"Child Care",
            "type":"Services"
        }
    ],
    "sg:phone":"+1 507 637 8083",
    "sg:postcode":"56283",
    "sg:province":"MN",
    "sg:tags":[
        "daycare",
        "provider"
    ],
    "wof:name":"Dianne Curtis",
    "wof:placetype":"venue"
},
  "geometry": {"coordinates":[-95.106768,44.544129],"type":"Point"}
}