{
  "type": "Feature",
  "properties": {
    "addr:full":"208 N Rum River Dr Princeton MN 55371",
    "addr:housenumber":"208",
    "addr:postcode":"55371",
    "addr:street":"N Rum River Dr",
    "iso:country":"US",
    "sg:address":"208 N Rum River Dr",
    "sg:city":"Princeton",
    "sg:classifiers":[
        {
            "category":"Autos & Motor Vehicles",
            "subcategory":"Auto Supplies",
            "type":"Retail Goods"
        }
    ],
    "sg:phone":"+1 763 631 1160",
    "sg:postcode":"55371",
    "sg:province":"MN",
    "sg:tags":[
        "accessories-wholesale",
        "automobile",
        "part",
        "parts",
        "manufacturer"
    ],
    "wof:name":"Arrowhead Elec Product",
    "wof:placetype":"venue"
},
  "geometry": {"coordinates":[-93.58010899999999,45.571093],"type":"Point"}
}