{
  "type": "Feature",
  "properties": {
    "addr:full":"103 Pine St Monticello MN 55362",
    "addr:housenumber":"103",
    "addr:postcode":"55362",
    "addr:street":"Pine St",
    "iso:country":"US",
    "sg:address":"103 Pine St",
    "sg:city":"Monticello",
    "sg:classifiers":[
        {
            "category":"Shopping",
            "subcategory":"Used Merchandise",
            "type":"Retail Goods"
        }
    ],
    "sg:phone":"+1 763 295 4444",
    "sg:postcode":"55362",
    "sg:province":"MN",
    "sg:tags":[
        "antique"
    ],
    "wof:name":"Riverstreet Station",
    "wof:placetype":"venue"
},
  "geometry": {"coordinates":[-93.79357,45.306743],"type":"Point"}
}