{
  "type": "Feature",
  "properties": {
    "addr:full":"18150 Co Rd 81 Osseo MN 55369",
    "addr:housenumber":"18150;81",
    "addr:postcode":"55369",
    "addr:street":"Co Rd",
    "iso:country":"US",
    "sg:address":"18150 Co Rd 81",
    "sg:city":"Osseo",
    "sg:classifiers":[
        {
            "category":"Building & Trades",
            "subcategory":"Construction",
            "type":"Services"
        }
    ],
    "sg:phone":"+1 763 428 2929",
    "sg:postcode":"55369",
    "sg:province":"MN",
    "sg:tags":[
        "excavating",
        "contractor"
    ],
    "wof:name":"Spaanem Contracting Inc",
    "wof:placetype":"venue"
},
  "geometry": {"coordinates":[-93.513718,45.166084],"type":"Point"}
}