{
  "type": "Feature",
  "properties": {
    "iso:country":"US",
    "sg:address":"261 Chester St",
    "sg:city":"St Paul",
    "sg:classifiers":[
        {
            "category":"Freight",
            "type":"Transportation"
        }
    ],
    "sg:phone":"+1 651 291 7965",
    "sg:postcode":"55107",
    "sg:province":"MN",
    "sg:tags":[
        "delivery"
    ],
    "wof:name":"Fed Ex",
    "wof:placetype":"venue"
},
  "geometry": {"coordinates":[-93.072102,44.939258],"type":"Point"}
}