{
  "type": "Feature",
  "properties": {
    "addr:full":"3785 E 255th St Webster MN 55088",
    "addr:housenumber":"3785",
    "addr:postcode":"55088",
    "addr:street":"E 255Th St",
    "iso:country":"US",
    "sg:address":"3785 E 255th St",
    "sg:city":"Webster",
    "sg:classifiers":[
        {
            "category":"Farming",
            "subcategory":"Farm",
            "type":"Manufacturing & Wholesale Goods"
        }
    ],
    "sg:phone":"+1 952 461 1109",
    "sg:postcode":"55088",
    "sg:province":"MN",
    "wof:name":"Creekside Country Farm",
    "wof:placetype":"venue"
},
  "geometry": {"coordinates":[-93.443808,44.579819],"type":"Point"}
}