{
  "type": "Feature",
  "properties": {
    "iso:country":"US",
    "sg:address":"81300 370th St",
    "sg:city":"Olivia",
    "sg:classifiers":[
        {
            "category":"Farming",
            "subcategory":"Livestock Farm",
            "type":"Manufacturing & Wholesale Goods"
        }
    ],
    "sg:phone":"+1 320 365 4071",
    "sg:postcode":"56277",
    "sg:province":"MN",
    "sg:tags":[
        "hog",
        "or",
        "feedlot"
    ],
    "wof:name":"Scott Tersteeg",
    "wof:placetype":"venue"
},
  "geometry": {"coordinates":[-94.935835,44.763812],"type":"Point"}
}