{
  "type": "Feature",
  "properties": {
    "addr:full":"7400 University Ave NE D Minneapolis MN 55432",
    "addr:housenumber":"7400",
    "addr:postcode":"55432",
    "addr:street":"University Ave Ne D",
    "iso:country":"US",
    "sg:address":"7400 University Ave NE D",
    "sg:city":"Minneapolis",
    "sg:classifiers":[
        {
            "category":"Professional",
            "subcategory":"Management & Consulting",
            "type":"Services"
        },
        {
            "category":"Banks & Credit Unions",
            "subcategory":"Investment Brokerage",
            "type":"Services"
        },
        {
            "category":"Professional",
            "subcategory":"Lawyer & Legal Services",
            "type":"Services"
        },
        {
            "category":"Banks & Credit Unions",
            "subcategory":"Financial Services",
            "type":"Services"
        }
    ],
    "sg:phone":"+1 763 571 5633",
    "sg:postcode":"55432",
    "sg:province":"MN",
    "sg:tags":[
        "advisory",
        "attorney",
        "planner",
        "estate",
        "consultant",
        "wills",
        "financing",
        "planning",
        "trust"
    ],
    "wof:name":"Molinari Financial",
    "wof:placetype":"venue"
},
  "geometry": {"coordinates":[-93.26357299999999,45.107616],"type":"Point"}
}