{
  "type": "Feature",
  "properties": {
    "addr:full":"701 1st St N Minneapolis MN 55401",
    "addr:housenumber":"701",
    "addr:postcode":"55401",
    "addr:street":"1St St N",
    "iso:country":"US",
    "sg:address":"701 1st St N",
    "sg:city":"Minneapolis",
    "sg:classifiers":[
        {
            "category":"Professional",
            "subcategory":"Business Services",
            "type":"Services"
        }
    ],
    "sg:phone":"+1 612 333 3771",
    "sg:postcode":"55401",
    "sg:province":"MN",
    "wof:name":"Jonettes Studio",
    "wof:placetype":"venue"
},
  "geometry": {"coordinates":[-93.274415,44.988864],"type":"Point"}
}