{
  "type": "Feature",
  "properties": {
    "addr:full":"3935 Hwy 14 SE Rochester MN 55904",
    "addr:housenumber":"3935",
    "addr:postcode":"55904",
    "addr:street":"Hwy 14 Se",
    "iso:country":"US",
    "sg:address":"3935 Hwy 14 SE",
    "sg:city":"Rochester",
    "sg:classifiers":[
        {
            "category":"Utilities",
            "subcategory":"Electric",
            "type":"Services"
        }
    ],
    "sg:phone":"+1 507 288 4004",
    "sg:postcode":"55904",
    "sg:province":"MN",
    "sg:tags":[
        "company"
    ],
    "sg:website":"www.peoplesrec.com",
    "wof:name":"Peoples Cooperative Svc",
    "wof:placetype":"venue"
},
  "geometry": {"coordinates":[-92.400687,44.012434],"type":"Point"}
}