{
  "type": "Feature",
  "properties": {
    "addr:full":"2154 82nd St NE Remer MN 56672",
    "addr:housenumber":"2154",
    "addr:postcode":"56672",
    "addr:street":"82Nd St Ne",
    "iso:country":"US",
    "sg:address":"2154 82nd St NE",
    "sg:city":"Remer",
    "sg:classifiers":[
        {
            "category":"Real Estate",
            "subcategory":"Real Estate Agent",
            "type":"Services"
        }
    ],
    "sg:phone":"+1 218 889 2500",
    "sg:postcode":"56672",
    "sg:province":"MN",
    "wof:name":"True North Realty",
    "wof:placetype":"venue"
},
  "geometry": {"coordinates":[-94.1741,47.104379],"type":"Point"}
}