{
  "type": "Feature",
  "properties": {
    "iso:country":"US",
    "sg:address":"209 Grand Ave NE",
    "sg:city":"Princeton",
    "sg:classifiers":[
        {
            "category":"Manufacturing",
            "subcategory":"Metals",
            "type":"Manufacturing & Wholesale Goods"
        }
    ],
    "sg:phone":"+1 763 389 4353",
    "sg:postcode":"55376",
    "sg:province":"MN",
    "sg:tags":[
        "stampings",
        "mfg"
    ],
    "wof:name":"Pbc Deputy Registrar Inc",
    "wof:placetype":"venue"
},
  "geometry": {"coordinates":[-93.66222999999999,45.217776],"type":"Point"}
}