{
  "type": "Feature",
  "properties": {
    "iso:country":"US",
    "sg:address":"31184 221st Ave",
    "sg:city":"Le Sueur",
    "sg:classifiers":[
        {
            "category":"Professional",
            "type":"Services"
        }
    ],
    "sg:phone":"+1 507 931 2045",
    "sg:postcode":"56057",
    "sg:province":"MN",
    "sg:tags":[
        "establishment"
    ],
    "wof:name":"Pheasant Run Inc",
    "wof:placetype":"venue"
},
  "geometry": {"coordinates":[-93.70726500000001,44.497692],"type":"Point"}
}