{
  "type": "Feature",
  "properties": {
    "iso:country":"US",
    "sg:address":"8840 181st Ave NW",
    "sg:city":"Anoka",
    "sg:classifiers":[
        {
            "category":"Professional",
            "subcategory":"Business Services",
            "type":"Services"
        }
    ],
    "sg:phone":"+1 763 441 8774",
    "sg:postcode":"55303",
    "sg:province":"MN",
    "wof:name":"Quality First Inspections",
    "wof:placetype":"venue"
},
  "geometry": {"coordinates":[-93.490825,45.299281],"type":"Point"}
}