{
  "type": "Feature",
  "properties": {
    "iso:country":"US",
    "sg:address":"37764 Sage Rd",
    "sg:city":"Grand Rapids",
    "sg:classifiers":[
        {
            "category":"Banks & Credit Unions",
            "subcategory":"Investment Brokerage",
            "type":"Services"
        }
    ],
    "sg:phone":"+1 863 299 9941",
    "sg:postcode":"55744",
    "sg:province":"MN",
    "sg:tags":[
        "banking"
    ],
    "wof:name":"CMA Group LLC",
    "wof:placetype":"venue"
},
  "geometry": {"coordinates":[-93.55022,47.416047],"type":"Point"}
}