{
  "type": "Feature",
  "properties": {
    "addr:full":"33 5th Ave NW Saint Paul MN 55112",
    "addr:housenumber":"33",
    "addr:postcode":"55112",
    "addr:street":"5Th Ave Nw",
    "iso:country":"US",
    "sg:address":"33 5th Ave NW",
    "sg:city":"Saint Paul",
    "sg:classifiers":[
        {
            "category":"Professional",
            "subcategory":"Computer Services",
            "type":"Services"
        }
    ],
    "sg:phone":"+1 651 634 6100",
    "sg:postcode":"55112",
    "sg:province":"MN",
    "sg:tags":[
        "repair"
    ],
    "wof:name":"Marco Business Products",
    "wof:placetype":"venue"
},
  "geometry": {"coordinates":[-93.192902,45.051399],"type":"Point"}
}