{
  "type": "Feature",
  "properties": {
    "iso:country":"US",
    "sg:address":"2120 Kenwood Pkwy",
    "sg:city":"Minneapolis",
    "sg:classifiers":[
        {
            "category":"Professional",
            "subcategory":"Management & Consulting",
            "type":"Services"
        }
    ],
    "sg:phone":"+1 612 377 9685",
    "sg:postcode":"55405",
    "sg:province":"MN",
    "sg:tags":[
        "environmental"
    ],
    "wof:name":"Ecolibrium Inc",
    "wof:placetype":"venue"
},
  "geometry": {"coordinates":[-93.31054899999999,44.960392],"type":"Point"}
}