{
  "type": "Feature",
  "properties": {
    "iso:country":"US",
    "sg:address":"14800 28th Ave N",
    "sg:city":"Minneapolis",
    "sg:classifiers":[
        {
            "category":"Shopping",
            "subcategory":"Computers & Home Electronics",
            "type":"Retail Goods"
        }
    ],
    "sg:phone":"+1 763 553 0644",
    "sg:postcode":"55447",
    "sg:province":"MN",
    "sg:tags":[
        "mfg",
        "electronic",
        "pu"
    ],
    "wof:name":"A D P Claims Solutions Group",
    "wof:placetype":"venue"
},
  "geometry": {"coordinates":[-93.46808799999999,45.01175],"type":"Point"}
}