{
  "type": "Feature",
  "properties": {
    "addr:full":"411 Washington Ave N Minneapolis MN 55401",
    "addr:housenumber":"411",
    "addr:postcode":"55401",
    "addr:street":"Washington Ave N",
    "iso:country":"US",
    "sg:address":"411 Washington Ave N",
    "sg:city":"Minneapolis",
    "sg:classifiers":[
        {
            "category":"Professional",
            "subcategory":"Computer Services",
            "type":"Services"
        }
    ],
    "sg:phone":"+1 612 339 8070",
    "sg:postcode":"55401",
    "sg:province":"MN",
    "sg:tags":[
        "provider",
        "internet"
    ],
    "wof:name":"Infotec",
    "wof:placetype":"venue"
},
  "geometry": {"coordinates":[-93.274002,44.9855],"type":"Point"}
}