{
  "type": "Feature",
  "properties": {
    "iso:country":"US",
    "sg:address":"87 Lyon St",
    "sg:city":"Saint Paul",
    "sg:classifiers":[
        {
            "category":"Manufacturing",
            "subcategory":"Tools & Machinery",
            "type":"Manufacturing & Wholesale Goods"
        }
    ],
    "sg:phone":"+1 651 772 2650",
    "sg:postcode":"55106",
    "sg:province":"MN",
    "sg:tags":[
        "industrial",
        "electrical",
        "apparatus",
        "mfg"
    ],
    "wof:name":"Tg Sales Agency",
    "wof:placetype":"venue"
},
  "geometry": {"coordinates":[-93.02908600000001,44.946046],"type":"Point"}
}