{
  "type": "Feature",
  "properties": {
    "addr:full":"405 S Broadway Wells MN 56097",
    "addr:housenumber":"405",
    "addr:postcode":"56097",
    "addr:street":"S Broadway",
    "iso:country":"US",
    "sg:address":"405 S Broadway",
    "sg:city":"Wells",
    "sg:classifiers":[
        {
            "category":"Organizations",
            "subcategory":"Religious Organization",
            "type":"Services"
        }
    ],
    "sg:phone":"+1 507 553 3511",
    "sg:postcode":"56097",
    "sg:province":"MN",
    "wof:name":"Assembly Of God Church",
    "wof:placetype":"venue"
},
  "geometry": {"coordinates":[-93.725419,43.740944],"type":"Point"}
}