{
  "type": "Feature",
  "properties": {
    "iso:country":"US",
    "sg:address":"5919 Medicine Lake Rd",
    "sg:city":"Minneapolis",
    "sg:classifiers":[
        {
            "category":"Wholesale",
            "subcategory":"Computers",
            "type":"Manufacturing & Wholesale Goods"
        },
        {
            "category":"Professional",
            "subcategory":"Computer Services",
            "type":"Services"
        },
        {
            "category":"Internet Cafe",
            "subcategory":"None",
            "type":"Food & Drink"
        }
    ],
    "sg:phone":"+1 763 546 0044",
    "sg:postcode":"55422",
    "sg:province":"MN",
    "sg:tags":[
        "product",
        "manufacturer",
        "computer-wholesale",
        "software"
    ],
    "wof:name":"Digital Computer Software",
    "wof:placetype":"venue"
},
  "geometry": {"coordinates":[-93.355411,45.008629],"type":"Point"}
}