{
  "type": "Feature",
  "properties": {
    "iso:country":"US",
    "sg:address":"19550 490th St",
    "sg:city":"Aldrich",
    "sg:classifiers":[
        {
            "category":"Organizations",
            "subcategory":"Religious Organization",
            "type":"Services"
        }
    ],
    "sg:phone":"+1 218 445 5698",
    "sg:postcode":"56434",
    "sg:province":"MN",
    "sg:tags":[
        "church"
    ],
    "wof:name":"Balsamlund Lutheran Church",
    "wof:placetype":"venue"
},
  "geometry": {"coordinates":[-94.95630800000001,46.339986],"type":"Point"}
}