{
  "type": "Feature",
  "properties": {
    "addr:full":"34170 Warsaw Trl Cannon Falls MN 55009",
    "addr:postcode":"34170;55009",
    "addr:street":"Warsaw Trl",
    "iso:country":"US",
    "sg:address":"34170 Warsaw Trl",
    "sg:city":"Cannon Falls",
    "sg:classifiers":[
        {
            "category":"Recreation",
            "type":"Entertainment"
        }
    ],
    "sg:phone":"+1 507 263 9278",
    "sg:postcode":"55009",
    "sg:province":"MN",
    "wof:name":"Manes & Tails LLC",
    "wof:placetype":"venue"
},
  "geometry": {"coordinates":[-92.928377,44.451038],"type":"Point"}
}