{
  "type": "Feature",
  "properties": {
    "addr:full":"212 N 2nd St Ste 3 Minneapolis MN 55401",
    "addr:housenumber":"212",
    "addr:postcode":"55401",
    "addr:street":"N 2Nd St Ste 3",
    "iso:country":"US",
    "sg:address":"212 N 2nd St Ste 3",
    "sg:city":"Minneapolis",
    "sg:classifiers":[
        {
            "category":"Shopping",
            "subcategory":"Jewelry",
            "type":"Retail Goods"
        },
        {
            "category":"Manufacturing",
            "subcategory":"Jewelry",
            "type":"Manufacturing & Wholesale Goods"
        }
    ],
    "sg:phone":"+1 612 372 6797",
    "sg:postcode":"55401",
    "sg:province":"MN",
    "sg:tags":[
        "designer",
        "jeweler"
    ],
    "wof:name":"S Vicent Jewelers Inc",
    "wof:placetype":"venue"
},
  "geometry": {"coordinates":[-93.27031700000001,44.984649],"type":"Point"}
}