{
  "type": "Feature",
  "properties": {
    "addr:full":"1025 Industrial Dr Spring Valley MN 55975",
    "addr:housenumber":"1025",
    "addr:postcode":"55975",
    "addr:street":"Industrial Dr",
    "iso:country":"US",
    "sg:address":"1025 Industrial Dr",
    "sg:city":"Spring Valley",
    "sg:classifiers":[
        {
            "category":"Professional",
            "subcategory":"Business Services",
            "type":"Services"
        }
    ],
    "sg:phone":"+1 507 346 2440",
    "sg:postcode":"55975",
    "sg:province":"MN",
    "sg:tags":[
        "real estate",
        "auctioneer"
    ],
    "sg:website":"www.cuedspeech.com",
    "wof:name":"Grafe Auction & Realty",
    "wof:placetype":"venue"
},
  "geometry": {"coordinates":[-92.402136,43.70035],"type":"Point"}
}