{
  "type": "Feature",
  "properties": {
    "iso:country":"US",
    "sg:address":"3717 165th Ave NE",
    "sg:city":"Andover",
    "sg:classifiers":[
        {
            "category":"Professional",
            "type":"Services"
        }
    ],
    "sg:phone":"+1 763 434 6077",
    "sg:postcode":"55304",
    "sg:province":"MN",
    "sg:tags":[
        "establishment"
    ],
    "wof:name":"Beebe & Beebe",
    "wof:placetype":"venue"
},
  "geometry": {"coordinates":[-93.174846,45.269118],"type":"Point"}
}