{
  "type": "Feature",
  "properties": {
    "iso:country":"US",
    "sg:address":"17757 Zarr Rd",
    "sg:city":"Deerwood",
    "sg:classifiers":[
        {
            "category":"Building & Trades",
            "subcategory":"Construction",
            "type":"Services"
        }
    ],
    "sg:phone":"+1 218 546 6183",
    "sg:postcode":"56455",
    "sg:province":"MN",
    "sg:tags":[
        "resurfacing",
        "floor",
        "laying",
        "refinishing",
        "contractor"
    ],
    "wof:name":"Dobson Floor Sanding Inc",
    "wof:placetype":"venue"
},
  "geometry": {"coordinates":[-94.026483,46.42883],"type":"Point"}
}