{
  "type": "Feature",
  "properties": {
    "addr:full":"4219 Shirlee Ln N Saint Paul MN 55126",
    "addr:housenumber":"4219",
    "addr:postcode":"55126",
    "addr:street":"Shirlee Ln N",
    "iso:country":"US",
    "sg:address":"4219 Shirlee Ln N",
    "sg:city":"Saint Paul",
    "sg:classifiers":[
        {
            "category":"Education",
            "subcategory":"Special Training",
            "type":"Public Place"
        }
    ],
    "sg:phone":"+1 651 483 5628",
    "sg:postcode":"55126",
    "sg:province":"MN",
    "wof:name":"Judith Rohde",
    "wof:placetype":"venue"
},
  "geometry": {"coordinates":[-93.13858999999999,45.069232],"type":"Point"}
}