{
  "type": "Feature",
  "properties": {
    "addr:full":"1538 Wilshire Woods Ln NE Rochester MN 55906",
    "addr:housenumber":"1538",
    "addr:postcode":"55906",
    "addr:street":"Wilshire Woods Ln Ne",
    "iso:country":"US",
    "sg:address":"1538 Wilshire Woods Ln NE",
    "sg:city":"Rochester",
    "sg:classifiers":[
        {
            "category":"Professional",
            "subcategory":"Business Services",
            "type":"Services"
        }
    ],
    "sg:phone":"+1 507 285 3152",
    "sg:postcode":"55906",
    "sg:province":"MN",
    "wof:name":"Mantis Enterprises",
    "wof:placetype":"venue"
},
  "geometry": {"coordinates":[-92.438757,44.046722],"type":"Point"}
}