{
  "type": "Feature",
  "properties": {
    "iso:country":"US",
    "sg:address":"7851 Metro Pkwy",
    "sg:city":"Minneapolis",
    "sg:classifiers":[
        {
            "category":"Airport",
            "type":"Transportation"
        }
    ],
    "sg:phone":"+1 952 854 3043",
    "sg:postcode":"55425",
    "sg:province":"MN",
    "wof:name":"Prime Flight Aviation",
    "wof:placetype":"venue"
},
  "geometry": {"coordinates":[-93.22906500000001,44.861048],"type":"Point"}
}