{
  "type": "Feature",
  "properties": {
    "addr:full":"432 Atlantic Ave Kandiyohi MN 56251",
    "addr:housenumber":"432",
    "addr:postcode":"56251",
    "addr:street":"Atlantic Ave",
    "iso:country":"US",
    "sg:address":"432 Atlantic Ave",
    "sg:city":"Kandiyohi",
    "sg:classifiers":[
        {
            "category":"Professional",
            "type":"Services"
        }
    ],
    "sg:phone":"+1 320 382 6109",
    "sg:postcode":"56251",
    "sg:province":"MN",
    "sg:tags":[
        "establishment"
    ],
    "wof:name":"Kandiyohi Civic Ctr",
    "wof:placetype":"venue"
},
  "geometry": {"coordinates":[-94.93171100000001,45.132592],"type":"Point"}
}