{
  "type": "Feature",
  "properties": {
    "addr:full":"2621 Fairway Dr Moorhead MN 56560",
    "addr:housenumber":"2621",
    "addr:postcode":"56560",
    "addr:street":"Fairway Dr",
    "iso:country":"US",
    "sg:address":"2621 Fairway Dr",
    "sg:city":"Moorhead",
    "sg:classifiers":[
        {
            "category":"Restaurant",
            "type":"Food & Drink"
        }
    ],
    "sg:phone":"+1 218 287 9477",
    "sg:postcode":"56560",
    "sg:province":"MN",
    "sg:tags":[
        "eating"
    ],
    "wof:name":"Private Events By Terry",
    "wof:placetype":"venue"
},
  "geometry": {"coordinates":[-96.766498,46.900223],"type":"Point"}
}