{
  "type": "Feature",
  "properties": {
    "addr:full":"1738 2nd St NW Rochester MN 55901",
    "addr:housenumber":"1738",
    "addr:postcode":"55901",
    "addr:street":"2Nd St Nw",
    "iso:country":"US",
    "sg:address":"1738 2nd St NW",
    "sg:city":"Rochester",
    "sg:classifiers":[
        {
            "category":"Professional",
            "subcategory":"Business Services",
            "type":"Services"
        }
    ],
    "sg:phone":"+1 507 289 2153",
    "sg:postcode":"55901",
    "sg:province":"MN",
    "wof:name":"Home Inspection Top To Bottom",
    "wof:placetype":"venue"
},
  "geometry": {"coordinates":[-92.489947,44.025235],"type":"Point"}
}