{
  "type": "Feature",
  "properties": {
    "iso:country":"US",
    "sg:address":"7685 Washington Ave S",
    "sg:city":"Edina",
    "sg:classifiers":[
        {
            "category":"Professional",
            "subcategory":"Computer Services",
            "type":"Services"
        }
    ],
    "sg:phone":"+1 651 641 1933",
    "sg:postcode":"55439",
    "sg:province":"MN",
    "wof:name":"Micro Computer Solutions",
    "wof:placetype":"venue"
},
  "geometry": {"coordinates":[-93.398585,44.865146],"type":"Point"}
}