{
  "type": "Feature",
  "properties": {
    "addr:full":"10 E 1st St Morris MN 56267",
    "addr:housenumber":"10",
    "addr:postcode":"56267",
    "addr:street":"E 1St St",
    "iso:country":"US",
    "sg:address":"10 E 1st St",
    "sg:city":"Morris",
    "sg:classifiers":[
        {
            "category":"Professional",
            "subcategory":"Employment Agencies",
            "type":"Services"
        }
    ],
    "sg:phone":"+1 320 589 7377",
    "sg:postcode":"56267",
    "sg:province":"MN",
    "sg:tags":[
        "opportunity"
    ],
    "wof:name":"Minnesota Cep",
    "wof:placetype":"venue"
},
  "geometry": {"coordinates":[-95.90920800000001,45.583305],"type":"Point"}
}