{
  "type": "Feature",
  "properties": {
    "addr:full":"2807 E 29th St Minneapolis MN 55406",
    "addr:housenumber":"2807",
    "addr:postcode":"55406",
    "addr:street":"E 29Th St",
    "iso:country":"US",
    "sg:address":"2807 E 29th St",
    "sg:city":"Minneapolis",
    "sg:classifiers":[
        {
            "category":"Professional",
            "type":"Services"
        }
    ],
    "sg:phone":"+1 612 722 1829",
    "sg:postcode":"55406",
    "sg:province":"MN",
    "wof:name":"Consumers Information Service",
    "wof:placetype":"venue"
},
  "geometry": {"coordinates":[-93.23004899999999,44.950101],"type":"Point"}
}