{
  "type": "Feature",
  "properties": {
    "addr:full":"590 W Park Rd Redwood Falls MN 56283",
    "addr:housenumber":"590",
    "addr:postcode":"56283",
    "addr:street":"W Park Rd",
    "iso:country":"US",
    "sg:address":"590 W Park Rd",
    "sg:city":"Redwood Falls",
    "sg:classifiers":[
        {
            "category":"Manufacturing",
            "subcategory":"Food",
            "type":"Manufacturing & Wholesale Goods"
        }
    ],
    "sg:phone":"+1 507 641 3831",
    "sg:postcode":"56283",
    "sg:province":"MN",
    "sg:tags":[
        "rendering",
        "company"
    ],
    "sg:website":"www.centralbi.com",
    "wof:name":"Central-Bi Products",
    "wof:placetype":"venue"
},
  "geometry": {"coordinates":[-95.095462,44.545869],"type":"Point"}
}