{
  "type": "Feature",
  "properties": {
    "addr:full":"16224 247th Ave Paynesville MN 56362",
    "addr:housenumber":"16224",
    "addr:postcode":"56362",
    "addr:street":"247Th Ave",
    "iso:country":"US",
    "sg:address":"16224 247th Ave",
    "sg:city":"Paynesville",
    "sg:classifiers":[
        {
            "category":"Manufacturing",
            "subcategory":"Tools & Machinery",
            "type":"Manufacturing & Wholesale Goods"
        }
    ],
    "sg:phone":"+1 320 453 2699",
    "sg:postcode":"56362",
    "sg:province":"MN",
    "sg:tags":[
        "machine",
        "shop"
    ],
    "wof:name":"Tried & True Machine",
    "wof:placetype":"venue"
},
  "geometry": {"coordinates":[-94.622907,45.356718],"type":"Point"}
}