{
  "type": "Feature",
  "properties": {
    "iso:country":"US",
    "sg:address":"9315 Andrea Rd",
    "sg:city":"Saint Paul",
    "sg:classifiers":[
        {
            "category":"Building & Trades",
            "subcategory":"Construction",
            "type":"Services"
        }
    ],
    "sg:phone":"+1 651 501 9699",
    "sg:postcode":"55125",
    "sg:province":"MN",
    "sg:tags":[
        "carpentry",
        "contractor"
    ],
    "wof:name":"Wood Wonders",
    "wof:placetype":"venue"
},
  "geometry": {"coordinates":[-92.917174,44.904087],"type":"Point"}
}