{
  "type": "Feature",
  "properties": {
    "addr:full":"6022 Blue Circle Dr Hopkins MN 55343",
    "addr:housenumber":"6022",
    "addr:postcode":"55343",
    "addr:street":"Blue Circle Dr",
    "iso:country":"US",
    "sg:address":"6022 Blue Circle Dr",
    "sg:city":"Hopkins",
    "sg:classifiers":[
        {
            "category":"Building & Trades",
            "subcategory":"Construction",
            "type":"Services"
        }
    ],
    "sg:phone":"+1 952 345 2900",
    "sg:postcode":"55343",
    "sg:province":"MN",
    "sg:tags":[
        "hanging",
        "contractor"
    ],
    "sg:website":"www.schoenfelderpainting.com",
    "wof:name":"Schoenfelder Painting Inc",
    "wof:placetype":"venue"
},
  "geometry": {"coordinates":[-93.406837,44.89194],"type":"Point"}
}