{
  "type": "Feature",
  "properties": {
    "addr:full":"1759 Selby Ave Saint Paul MN 55104",
    "addr:housenumber":"1759",
    "addr:postcode":"55104",
    "addr:street":"Selby Ave",
    "iso:country":"US",
    "sg:address":"1759 Selby Ave",
    "sg:city":"Saint Paul",
    "sg:classifiers":[
        {
            "category":"Shopping",
            "type":"Retail Goods"
        }
    ],
    "sg:phone":"+1 651 209 8090",
    "sg:postcode":"55104",
    "sg:province":"MN",
    "sg:tags":[
        "merchandise"
    ],
    "wof:name":"Acticor Technologies",
    "wof:placetype":"venue"
},
  "geometry": {"coordinates":[-93.177114,44.946621],"type":"Point"}
}