{
  "type": "Feature",
  "properties": {
    "addr:full":"17 E Sheridan St Ely MN 55731",
    "addr:housenumber":"17",
    "addr:postcode":"55731",
    "addr:street":"E Sheridan St",
    "iso:country":"US",
    "sg:address":"17 E Sheridan St",
    "sg:city":"Ely",
    "sg:classifiers":[
        {
            "category":"Bars & Pubs",
            "type":"Food & Drink"
        }
    ],
    "sg:phone":"+1 218 365 3896",
    "sg:postcode":"55731",
    "sg:province":"MN",
    "sg:tags":[
        "club",
        "night"
    ],
    "wof:name":"Dee's Bar & Lounge",
    "wof:placetype":"venue"
},
  "geometry": {"coordinates":[-91.866726,47.903293],"type":"Point"}
}