{
  "type": "Feature",
  "properties": {
    "iso:country":"US",
    "sg:address":"912 E 24th St",
    "sg:city":"Minneapolis",
    "sg:classifiers":[
        {
            "category":"Banks & Credit Unions",
            "subcategory":"Bank",
            "type":"Services"
        }
    ],
    "sg:phone":"+1 612 879 6580",
    "sg:postcode":"55404",
    "sg:province":"MN",
    "sg:tags":[
        "depository",
        "banking"
    ],
    "wof:name":"North America Moneywire Corp",
    "wof:placetype":"venue"
},
  "geometry": {"coordinates":[-93.260166,44.959202],"type":"Point"}
}