{
  "type": "Feature",
  "properties": {
    "addr:full":"9801 Dupont Ave S Minneapolis MN 55431",
    "addr:housenumber":"9801",
    "addr:postcode":"55431",
    "addr:street":"Dupont Ave S",
    "iso:country":"US",
    "sg:address":"9801 Dupont Ave S",
    "sg:city":"Minneapolis",
    "sg:classifiers":[
        {
            "category":"Wholesale",
            "subcategory":"Computers",
            "type":"Manufacturing & Wholesale Goods"
        }
    ],
    "sg:phone":"+1 952 881 6323",
    "sg:postcode":"55431",
    "sg:province":"MN",
    "sg:tags":[
        "hardware",
        "accounting",
        "software"
    ],
    "wof:name":"Business Info Systems Inc",
    "wof:placetype":"venue"
},
  "geometry": {"coordinates":[-93.29376999999999,44.825213],"type":"Point"}
}