{
  "type": "Feature",
  "properties": {
    "addr:full":"14450 Hayes Rd Saint Paul MN 55124",
    "addr:housenumber":"14450",
    "addr:postcode":"55124",
    "addr:street":"Hayes Rd",
    "iso:country":"US",
    "sg:address":"14450 Hayes Rd",
    "sg:city":"Saint Paul",
    "sg:classifiers":[
        {
            "category":"Education",
            "subcategory":"School",
            "type":"Public Place"
        }
    ],
    "sg:phone":"+1 952 431 8200",
    "sg:postcode":"55124",
    "sg:province":"MN",
    "sg:tags":[
        "high",
        "middle",
        "elementary"
    ],
    "wof:name":"Independent School District 196",
    "wof:placetype":"venue"
},
  "geometry": {"coordinates":[-93.232827,44.739389],"type":"Point"}
}