{
  "type": "Feature",
  "properties": {
    "addr:full":"12700 Zenith Ave S Burnsville MN 55337",
    "addr:housenumber":"12700",
    "addr:postcode":"55337",
    "addr:street":"Zenith Ave S",
    "iso:country":"US",
    "sg:address":"12700 Zenith Ave S",
    "sg:city":"Burnsville",
    "sg:classifiers":[
        {
            "category":"Professional",
            "subcategory":"Advertising",
            "type":"Services"
        }
    ],
    "sg:phone":"+1 952 808 1400",
    "sg:postcode":"55337",
    "sg:province":"MN",
    "wof:name":"WEBB Co",
    "wof:placetype":"venue"
},
  "geometry": {"coordinates":[-93.32043899999999,44.774703],"type":"Point"}
}