{
  "type": "Feature",
  "properties": {
    "iso:country":"US",
    "sg:address":"506 1st Ave S",
    "sg:city":"St James",
    "sg:classifiers":[
        {
            "category":"Shopping",
            "type":"Retail Goods"
        }
    ],
    "sg:phone":"+1 507 375 5653",
    "sg:postcode":"56081",
    "sg:province":"MN",
    "sg:tags":[
        "art",
        "gallery",
        "dealer"
    ],
    "wof:name":"Prairieland Art Ctr",
    "wof:placetype":"venue"
},
  "geometry": {"coordinates":[-94.62828500000001,43.981899],"type":"Point"}
}