{
  "type": "Feature",
  "properties": {
    "iso:country":"US",
    "sg:address":"804 Oak St",
    "sg:city":"Brainerd",
    "sg:classifiers":[
        {
            "category":"Education",
            "subcategory":"School",
            "type":"Public Place"
        }
    ],
    "sg:phone":"+1 218 828 6720",
    "sg:postcode":"56401",
    "sg:province":"MN",
    "sg:tags":[
        "combined"
    ],
    "wof:name":"Washington Middle School",
    "wof:placetype":"venue"
},
  "geometry": {"coordinates":[-94.19756700000001,46.352575],"type":"Point"}
}