{
  "type": "Feature",
  "properties": {
    "addr:full":"1015 Summit Ave N Sauk Rapids MN 56379",
    "addr:housenumber":"1015",
    "addr:postcode":"56379",
    "addr:street":"Summit Ave N Sauk",
    "iso:country":"US",
    "sg:address":"1015 Summit Ave N",
    "sg:city":"Sauk Rapids",
    "sg:classifiers":[
        {
            "category":"Social Services",
            "subcategory":"Child Care",
            "type":"Services"
        }
    ],
    "sg:phone":"+1 320 253 3440",
    "sg:postcode":"56379",
    "sg:province":"MN",
    "sg:tags":[
        "daycare",
        "provider"
    ],
    "wof:name":"Patricia Froelich",
    "wof:placetype":"venue"
},
  "geometry": {"coordinates":[-94.15898900000001,45.601024],"type":"Point"}
}