{
  "type": "Feature",
  "properties": {
    "addr:full":"1518 Industrial Park Blvd Mora MN 55051",
    "addr:housenumber":"1518",
    "addr:postcode":"55051",
    "addr:street":"Industrial Park Blvd",
    "iso:country":"US",
    "sg:address":"1518 Industrial Park Blvd",
    "sg:city":"Mora",
    "sg:classifiers":[
        {
            "category":"Manufacturing",
            "subcategory":"Tools & Machinery",
            "type":"Manufacturing & Wholesale Goods"
        }
    ],
    "sg:phone":"+1 320 679 4535",
    "sg:postcode":"55051",
    "sg:province":"MN",
    "sg:tags":[
        "mold",
        "special"
    ],
    "wof:name":"PTE Inc",
    "wof:placetype":"venue"
},
  "geometry": {"coordinates":[-93.274945,45.881246],"type":"Point"}
}