{
  "type": "Feature",
  "properties": {
    "addr:full":"11526 Shag Rd New Ulm MN 56073",
    "addr:housenumber":"11526",
    "addr:postcode":"56073",
    "addr:street":"Shag Rd",
    "iso:country":"US",
    "sg:address":"11526 Shag Rd",
    "sg:city":"New Ulm",
    "sg:classifiers":[
        {
            "category":"Retail",
            "subcategory":"Repair Shop",
            "type":"Services"
        }
    ],
    "sg:phone":"+1 507 354 4232",
    "sg:postcode":"56073",
    "sg:province":"MN",
    "sg:tags":[
        "refinishing",
        "furniture"
    ],
    "wof:name":"Alice Tanley Furniture Rfnshng",
    "wof:placetype":"venue"
},
  "geometry": {"coordinates":[-94.424633,44.266959],"type":"Point"}
}