{
  "type": "Feature",
  "properties": {
    "addr:full":"60451 250th St Gibbon MN 55335",
    "addr:housenumber":"60451",
    "addr:postcode":"55335",
    "addr:street":"250Th St",
    "iso:country":"US",
    "sg:address":"60451 250th St",
    "sg:city":"Gibbon",
    "sg:phone":"+1 507 834 6330",
    "sg:postcode":"55335",
    "sg:province":"MN",
    "sg:tags":[
        "farm",
        "corn",
        "cash",
        "general",
        "grain",
        "animal"
    ],
    "wof:name":"Jim Dingels",
    "wof:placetype":"venue"
},
  "geometry": {"coordinates":[-94.485283,44.586393],"type":"Point"}
}