{
  "type": "Feature",
  "properties": {
    "addr:full":"136 Main St SE Preston MN 55965",
    "addr:housenumber":"136",
    "addr:postcode":"55965",
    "addr:street":"Main St Se",
    "iso:country":"US",
    "sg:address":"136 Main St SE",
    "sg:city":"Preston",
    "sg:classifiers":[
        {
            "category":"Shopping",
            "subcategory":"Pharmacy",
            "type":"Retail Goods"
        }
    ],
    "sg:phone":"+1 507 765 2156",
    "sg:postcode":"55965",
    "sg:province":"MN",
    "wof:name":"Haugan's Pharmacy",
    "wof:placetype":"venue"
},
  "geometry": {"coordinates":[-92.08017599999999,43.669347],"type":"Point"}
}