{
  "type": "Feature",
  "properties": {
    "addr:full":"3449 Harriet Ave S Minneapolis MN 55408",
    "addr:housenumber":"3449",
    "addr:postcode":"55408",
    "addr:street":"Harriet Ave S",
    "iso:country":"US",
    "sg:address":"3449 Harriet Ave S",
    "sg:city":"Minneapolis",
    "sg:classifiers":[
        {
            "category":"Food & Beverages",
            "subcategory":"Groceries & Convenience Stores",
            "type":"Retail Goods"
        }
    ],
    "sg:phone":"+1 612 374 3080",
    "sg:postcode":"55408",
    "sg:province":"MN",
    "wof:name":"Stop and Buy Market",
    "wof:placetype":"venue"
},
  "geometry": {"coordinates":[-93.285528,44.94041],"type":"Point"}
}