{
  "type": "Feature",
  "properties": {
    "addr:full":"2875 US Hwy 14 Owatonna MN 55060",
    "addr:housenumber":"2875",
    "addr:postcode":"55060",
    "addr:street":"Us Hwy 14",
    "iso:country":"US",
    "sg:address":"2875 US Hwy 14",
    "sg:city":"Owatonna",
    "sg:classifiers":[
        {
            "category":"Wholesale",
            "subcategory":"Machinery & Supplies",
            "type":"Manufacturing & Wholesale Goods"
        }
    ],
    "sg:phone":"+1 507 451 4073",
    "sg:postcode":"55060",
    "sg:province":"MN",
    "sg:tags":[
        "truck"
    ],
    "wof:name":"American Equipment Svc",
    "wof:placetype":"venue"
},
  "geometry": {"coordinates":[-93.181799,44.059654],"type":"Point"}
}