{
  "type": "Feature",
  "properties": {
    "addr:full":"16000 41st Ave N Minneapolis MN 55446",
    "addr:housenumber":"16000",
    "addr:postcode":"55446",
    "addr:street":"41St Ave N",
    "iso:country":"US",
    "sg:address":"16000 41st Ave N",
    "sg:city":"Minneapolis",
    "sg:classifiers":[
        {
            "category":"Organizations",
            "subcategory":"Religious Organization",
            "type":"Services"
        }
    ],
    "sg:phone":"+1 763 559 1469",
    "sg:postcode":"55446",
    "sg:province":"MN",
    "sg:tags":[
        "church"
    ],
    "wof:name":"Plymouth Creek Christn Church",
    "wof:placetype":"venue"
},
  "geometry": {"coordinates":[-93.48244200000001,45.030873],"type":"Point"}
}