{
  "type": "Feature",
  "properties": {
    "iso:country":"US",
    "sg:address":"5527 70th Ave SE",
    "sg:city":"Rochester",
    "sg:classifiers":[
        {
            "category":"Farming",
            "subcategory":"Dairy Farm",
            "type":"Manufacturing & Wholesale Goods"
        }
    ],
    "sg:phone":"+1 507 282 3687",
    "sg:postcode":"55904",
    "sg:province":"MN",
    "wof:name":"Pagel Alton",
    "wof:placetype":"venue"
},
  "geometry": {"coordinates":[-92.338792,43.942728],"type":"Point"}
}