{
  "type": "Feature",
  "properties": {
    "iso:country":"US",
    "sg:address":"21670 Hamburg Ave",
    "sg:city":"Lakeville",
    "sg:classifiers":[
        {
            "category":"Manufacturing",
            "subcategory":"Rubber & Plastics",
            "type":"Manufacturing & Wholesale Goods"
        }
    ],
    "sg:phone":"+1 952 469 2191",
    "sg:postcode":"55044",
    "sg:province":"MN",
    "sg:tags":[
        "pipe",
        "product",
        "manufacturer",
        "plastics-finished-wholesale",
        "mfg"
    ],
    "wof:name":"Poly Technology",
    "wof:placetype":"venue"
},
  "geometry": {"coordinates":[-93.227762,44.636327],"type":"Point"}
}