{
  "type": "Feature",
  "properties": {
    "addr:full":"1216 E Reaney Ave St Paul MN 55106",
    "addr:housenumber":"1216",
    "addr:postcode":"55106",
    "addr:street":"E Reaney Ave",
    "iso:country":"US",
    "sg:address":"1216 E Reaney Ave",
    "sg:city":"St Paul",
    "sg:classifiers":[
        {
            "category":"Shopping",
            "subcategory":"Clothing, Apparel, & Fashions",
            "type":"Retail Goods"
        }
    ],
    "sg:phone":"+1 651 776 2955",
    "sg:postcode":"55106",
    "sg:province":"MN",
    "sg:tags":[
        "lingerie"
    ],
    "wof:name":"Just Imagine Boutique",
    "wof:placetype":"venue"
},
  "geometry": {"coordinates":[-93.049386,44.963938],"type":"Point"}
}