{
  "type": "Feature",
  "properties": {
    "addr:full":"4557 Bloomington Ave Minneapolis MN 55407",
    "addr:housenumber":"4557",
    "addr:postcode":"55407",
    "addr:street":"Bloomington Ave",
    "iso:country":"US",
    "sg:address":"4557 Bloomington Ave",
    "sg:city":"Minneapolis",
    "sg:phone":"+1 612 722 3933",
    "sg:postcode":"55407",
    "sg:province":"MN",
    "wof:name":"Sister Sludge Coffee",
    "wof:placetype":"venue"
},
  "geometry": {"coordinates":[-93.252376,44.920485],"type":"Point"}
}