{
  "type": "Feature",
  "properties": {
    "addr:full":"4608 33rd Ave S Minneapolis MN 55406",
    "addr:housenumber":"4608",
    "addr:postcode":"55406",
    "addr:street":"33Rd Ave S",
    "iso:country":"US",
    "sg:address":"4608 33rd Ave S",
    "sg:city":"Minneapolis",
    "sg:classifiers":[
        {
            "category":"Professional",
            "subcategory":"Art Services",
            "type":"Services"
        }
    ],
    "sg:phone":"+1 612 729 7453",
    "sg:postcode":"55406",
    "sg:province":"MN",
    "sg:tags":[
        "commercial",
        "design"
    ],
    "wof:name":"Paul Jensen Designs",
    "wof:placetype":"venue"
},
  "geometry": {"coordinates":[-93.224373,44.9181],"type":"Point"}
}