{
  "type": "Feature",
  "properties": {
    "iso:country":"US",
    "sg:address":"14046 250th St",
    "sg:city":"Milaca",
    "sg:classifiers":[
        {
            "category":"Retail",
            "subcategory":"Repair Shop",
            "type":"Services"
        }
    ],
    "sg:phone":"+1 320 983 2308",
    "sg:postcode":"56353",
    "sg:province":"MN",
    "wof:name":"Toms Bike & Sport Shop",
    "wof:placetype":"venue"
},
  "geometry": {"coordinates":[-93.705561,45.908588],"type":"Point"}
}