{
  "type": "Feature",
  "properties": {
    "addr:full":"506 S 11th St Olivia MN 56277",
    "addr:housenumber":"506",
    "addr:postcode":"56277",
    "addr:street":"S 11Th St",
    "iso:country":"US",
    "sg:address":"506 S 11th St",
    "sg:city":"Olivia",
    "sg:classifiers":[
        {
            "category":"Organizations",
            "subcategory":"Community Association",
            "type":"Services"
        }
    ],
    "sg:phone":"+1 320 523 5656",
    "sg:postcode":"56277",
    "sg:province":"MN",
    "wof:name":"Catholic Order of Foresters",
    "wof:placetype":"venue"
},
  "geometry": {"coordinates":[-94.99262899999999,44.772237],"type":"Point"}
}