{
  "type": "Feature",
  "properties": {
    "iso:country":"US",
    "sg:address":"9130 202nd St W",
    "sg:city":"Lakeville",
    "sg:classifiers":[
        {
            "category":"Home & Garden",
            "subcategory":"Building Materials",
            "type":"Retail Goods"
        }
    ],
    "sg:phone":"+1 952 469 2116",
    "sg:postcode":"55044",
    "sg:province":"MN",
    "sg:tags":[
        "lumber"
    ],
    "wof:name":"United Building Ctr",
    "wof:placetype":"venue"
},
  "geometry": {"coordinates":[-93.249933,44.655888],"type":"Point"}
}