{
  "type": "Feature",
  "properties": {
    "addr:full":"886 N Shore Dr Forest Lake MN 55025",
    "addr:housenumber":"886",
    "addr:postcode":"55025",
    "addr:street":"N Shore Dr",
    "iso:country":"US",
    "sg:address":"886 N Shore Dr",
    "sg:city":"Forest Lake",
    "sg:classifiers":[
        {
            "category":"Organizations",
            "subcategory":"Religious Organization",
            "type":"Services"
        }
    ],
    "sg:phone":"+1 651 464 3323",
    "sg:postcode":"55025",
    "sg:province":"MN",
    "sg:tags":[
        "lutheran",
        "church"
    ],
    "sg:website":"www.faithfl.org",
    "wof:name":"Faith Lutheran Church Elca",
    "wof:placetype":"venue"
},
  "geometry": {"coordinates":[-92.97833,45.28826],"type":"Point"}
}