{
  "type": "Feature",
  "properties": {
    "addr:full":"38537 Timber Ln Saint Peter MN 56082",
    "addr:housenumber":"38537",
    "addr:postcode":"56082",
    "addr:street":"Timber Ln",
    "iso:country":"US",
    "sg:address":"38537 Timber Ln",
    "sg:city":"Saint Peter",
    "sg:classifiers":[
        {
            "category":"Freight",
            "type":"Transportation"
        }
    ],
    "sg:phone":"+1 507 625 3964",
    "sg:postcode":"56082",
    "sg:province":"MN",
    "sg:tags":[
        "operator",
        "trucking"
    ],
    "wof:name":"Gunderson Trucking",
    "wof:placetype":"venue"
},
  "geometry": {"coordinates":[-94.03778200000001,44.257748],"type":"Point"}
}