{
  "type": "Feature",
  "properties": {
    "addr:full":"403 NW 16th Ave Grand Rapids MN 55744",
    "addr:housenumber":"403",
    "addr:postcode":"55744",
    "addr:street":"Nw 16Th Ave",
    "iso:country":"US",
    "sg:address":"403 NW 16th Ave",
    "sg:city":"Grand Rapids",
    "sg:classifiers":[
        {
            "category":"Home & Garden",
            "subcategory":"Building Materials",
            "type":"Retail Goods"
        }
    ],
    "sg:phone":"+1 218 326 2403",
    "sg:postcode":"55744",
    "sg:province":"MN",
    "sg:tags":[
        "lumber"
    ],
    "wof:name":"Northside Lumber Co",
    "wof:placetype":"venue"
},
  "geometry": {"coordinates":[-93.552734,47.236031],"type":"Point"}
}