{
  "type": "Feature",
  "properties": {
    "addr:full":"30839 Old Hwy 371 Pequot Lakes MN 56472",
    "addr:housenumber":"30839",
    "addr:postcode":"56472",
    "addr:street":"Old Hwy 371",
    "iso:country":"US",
    "sg:address":"30839 Old Hwy 371",
    "sg:city":"Pequot Lakes",
    "sg:classifiers":[
        {
            "category":"Personal",
            "subcategory":"Beauty Salon",
            "type":"Services"
        }
    ],
    "sg:phone":"+1 218 568 8771",
    "sg:postcode":"56472",
    "sg:province":"MN",
    "sg:tags":[
        "shop"
    ],
    "wof:name":"Salon Couture",
    "wof:placetype":"venue"
},
  "geometry": {"coordinates":[-94.30958,46.600493],"type":"Point"}
}