{
  "type": "Feature",
  "properties": {
    "addr:full":"12900 Ventura Ct Shakopee MN 55379",
    "addr:housenumber":"12900",
    "addr:postcode":"55379",
    "addr:street":"Ventura Ct",
    "iso:country":"US",
    "sg:address":"12900 Ventura Ct",
    "sg:city":"Shakopee",
    "sg:classifiers":[
        {
            "category":"Manufacturing",
            "subcategory":"Building Materials",
            "type":"Manufacturing & Wholesale Goods"
        }
    ],
    "sg:phone":"+1 952 445 4407",
    "sg:postcode":"55379",
    "sg:province":"MN",
    "wof:name":"Hardwood Lumber Inc",
    "wof:placetype":"venue"
},
  "geometry": {"coordinates":[-93.57823500000001,44.764033],"type":"Point"}
}