{
  "type": "Feature",
  "properties": {
    "addr:full":"209 Saint Olaf Ave N Canby MN 56220",
    "addr:housenumber":"209",
    "addr:postcode":"56220",
    "addr:street":"Saint Olaf Ave N",
    "iso:country":"US",
    "sg:address":"209 Saint Olaf Ave N",
    "sg:city":"Canby",
    "sg:classifiers":[
        {
            "category":"Social Services",
            "type":"Services"
        }
    ],
    "sg:phone":"+1 507 223 5559",
    "sg:postcode":"56220",
    "sg:province":"MN",
    "wof:name":"Connection",
    "wof:placetype":"venue"
},
  "geometry": {"coordinates":[-96.274117,44.710308],"type":"Point"}
}