{
  "type": "Feature",
  "properties": {
    "addr:full":"2595 Hamline Ave N Saint Paul MN 55113",
    "addr:housenumber":"2595",
    "addr:postcode":"55113",
    "addr:street":"Hamline Ave N",
    "iso:country":"US",
    "sg:address":"2595 Hamline Ave N",
    "sg:city":"Saint Paul",
    "sg:classifiers":[
        {
            "category":"Wholesale",
            "subcategory":"Auto Parts",
            "type":"Manufacturing & Wholesale Goods"
        }
    ],
    "sg:phone":"+1 651 639 4261",
    "sg:postcode":"55113",
    "sg:province":"MN",
    "wof:name":"Triple R America Company Ltd",
    "wof:placetype":"venue"
},
  "geometry": {"coordinates":[-93.156887,45.019585],"type":"Point"}
}