{
  "type": "Feature",
  "properties": {
    "addr:full":"4805 261st St Wyoming MN 55092",
    "addr:housenumber":"4805",
    "addr:postcode":"55092",
    "addr:street":"261St St",
    "iso:country":"US",
    "sg:address":"4805 261st St",
    "sg:city":"Wyoming",
    "sg:classifiers":[
        {
            "category":"Building & Trades",
            "subcategory":"Construction",
            "type":"Services"
        }
    ],
    "sg:phone":"+1 651 462 1416",
    "sg:postcode":"55092",
    "sg:province":"MN",
    "sg:tags":[
        "house"
    ],
    "wof:name":"Jjs Home Improvements",
    "wof:placetype":"venue"
},
  "geometry": {"coordinates":[-93.009643,45.326213],"type":"Point"}
}