{
  "type": "Feature",
  "properties": {
    "iso:country":"US",
    "sg:address":"7760 France Ave S",
    "sg:city":"Minneapolis",
    "sg:classifiers":[
        {
            "category":"Real Estate",
            "subcategory":"Real Estate Agent",
            "type":"Services"
        }
    ],
    "sg:phone":"+1 952 924 4600",
    "sg:postcode":"55435",
    "sg:province":"MN",
    "sg:tags":[
        "commercial",
        "broker"
    ],
    "wof:name":"CB Commercial RE Group",
    "wof:placetype":"venue"
},
  "geometry": {"coordinates":[-93.328929,44.860934],"type":"Point"}
}