{
  "type": "Feature",
  "properties": {
    "addr:full":"133 Sandberg Rd Monticello MN 55362",
    "addr:housenumber":"133",
    "addr:postcode":"55362",
    "addr:street":"Sandberg Rd",
    "iso:country":"US",
    "sg:address":"133 Sandberg Rd",
    "sg:city":"Monticello",
    "sg:classifiers":[
        {
            "category":"Health Services",
            "subcategory":"Health Practitioner",
            "type":"Services"
        }
    ],
    "sg:phone":"+1 763 271 8100",
    "sg:postcode":"55362",
    "sg:province":"MN",
    "wof:name":"Daisy English Health Touch",
    "wof:placetype":"venue"
},
  "geometry": {"coordinates":[-93.802497,45.296623],"type":"Point"}
}