{
  "type": "Feature",
  "properties": {
    "iso:country":"US",
    "sg:address":"3721 Co Rd 42 W",
    "sg:city":"Burnsville",
    "sg:classifiers":[
        {
            "category":"Manufacturing",
            "subcategory":"Tools & Machinery",
            "type":"Manufacturing & Wholesale Goods"
        }
    ],
    "sg:phone":"+1 952 894 1482",
    "sg:postcode":"55306",
    "sg:province":"MN",
    "sg:tags":[
        "machine",
        "shop",
        "machining",
        "precision"
    ],
    "wof:name":"Waymon Technology Inc",
    "wof:placetype":"venue"
},
  "geometry": {"coordinates":[-93.324467,44.746288],"type":"Point"}
}