{
  "type": "Feature",
  "properties": {
    "iso:country":"US",
    "sg:address":"1640 Como Ave",
    "sg:city":"St Paul",
    "sg:classifiers":[
        {
            "category":"Communications",
            "subcategory":"Television Station",
            "type":"Services"
        }
    ],
    "sg:phone":"+1 651 645 2323",
    "sg:postcode":"55108",
    "sg:province":"MN",
    "sg:tags":[
        "broadcasting",
        "co"
    ],
    "wof:name":"W B",
    "wof:placetype":"venue"
},
  "geometry": {"coordinates":[-93.175788,44.977199],"type":"Point"}
}