{
  "type": "Feature",
  "properties": {
    "iso:country":"US",
    "sg:address":"1941 Crown Point Dr",
    "sg:city":"Saint Paul",
    "sg:classifiers":[
        {
            "category":"Real Estate",
            "subcategory":"Developer",
            "type":"Services"
        }
    ],
    "sg:phone":"+1 651 452 4574",
    "sg:postcode":"55118",
    "sg:province":"MN",
    "wof:name":"Northwest Development Pro",
    "wof:placetype":"venue"
},
  "geometry": {"coordinates":[-93.132925,44.886278],"type":"Point"}
}