{
  "type": "Feature",
  "properties": {
    "iso:country":"US",
    "sg:address":"212 W Main St",
    "sg:city":"Marshall",
    "sg:classifiers":[
        {
            "category":"Personal",
            "subcategory":"Beauty Salon",
            "type":"Services"
        }
    ],
    "sg:phone":"+1 507 532 3129",
    "sg:postcode":"56258",
    "sg:province":"MN",
    "sg:tags":[
        "shop"
    ],
    "wof:name":"Lasting Image Electrolysis",
    "wof:placetype":"venue"
},
  "geometry": {"coordinates":[-95.78966699999999,44.447705],"type":"Point"}
}