{
  "type": "Feature",
  "properties": {
    "addr:full":"1933 11th St Fulda MN 56131",
    "addr:housenumber":"1933",
    "addr:postcode":"56131",
    "addr:street":"11Th St",
    "iso:country":"US",
    "sg:address":"1933 11th St",
    "sg:city":"Fulda",
    "sg:phone":"+1 507 425 2890",
    "sg:postcode":"56131",
    "sg:province":"MN",
    "sg:tags":[
        "hog",
        "farm",
        "cash",
        "grain",
        "or",
        "feedlot"
    ],
    "wof:name":"Heintz Farms",
    "wof:placetype":"venue"
},
  "geometry": {"coordinates":[-95.681997,43.862525],"type":"Point"}
}