{
  "type": "Feature",
  "properties": {
    "addr:full":"16011 Guberud Hill Dr Spring Grove MN 55974",
    "addr:postcode":"16011;55974",
    "addr:street":"Guberud Hill Dr",
    "iso:country":"US",
    "sg:address":"16011 Guberud Hill Dr",
    "sg:city":"Spring Grove",
    "sg:classifiers":[
        {
            "category":"Wholesale",
            "subcategory":"Farm Supplies",
            "type":"Manufacturing & Wholesale Goods"
        }
    ],
    "sg:phone":"+1 507 498 5202",
    "sg:postcode":"55974",
    "sg:province":"MN",
    "sg:tags":[
        "livestock"
    ],
    "wof:name":"Pork Central Feeder Pigs",
    "wof:placetype":"venue"
},
  "geometry": {"coordinates":[-91.568684,43.576313],"type":"Point"}
}