{
  "type": "Feature",
  "properties": {
    "addr:full":"1409 1st St S Willmar MN 56201",
    "addr:housenumber":"1409",
    "addr:postcode":"56201",
    "addr:street":"1St St S",
    "iso:country":"US",
    "sg:address":"1409 1st St S",
    "sg:city":"Willmar",
    "sg:classifiers":[
        {
            "category":"Personal",
            "subcategory":"Beauty Salon",
            "type":"Services"
        }
    ],
    "sg:phone":"+1 320 235 3551",
    "sg:postcode":"56201",
    "sg:province":"MN",
    "sg:tags":[
        "shop"
    ],
    "wof:name":"Finishing Touch Beauty Salon",
    "wof:placetype":"venue"
},
  "geometry": {"coordinates":[-95.04263400000001,45.109334],"type":"Point"}
}