{
  "type": "Feature",
  "properties": {
    "iso:country":"US",
    "sg:address":"261 School Ave",
    "sg:city":"Excelsior",
    "sg:classifiers":[
        {
            "category":"Professional",
            "subcategory":"Business Services",
            "type":"Services"
        }
    ],
    "sg:phone":"+1 952 474 1675",
    "sg:postcode":"55331",
    "sg:province":"MN",
    "wof:name":"Pinnacle Business Systems",
    "wof:placetype":"venue"
},
  "geometry": {"coordinates":[-93.564761,44.901783],"type":"Point"}
}