{
  "type": "Feature",
  "properties": {
    "iso:country":"US",
    "sg:address":"206 Main St S",
    "sg:city":"Hector",
    "sg:classifiers":[
        {
            "category":"Banks & Credit Unions",
            "subcategory":"Bank",
            "type":"Services"
        }
    ],
    "sg:phone":"+1 320 848 2222",
    "sg:postcode":"55342",
    "sg:province":"MN",
    "wof:name":"Rural American Bank Of Hector",
    "wof:placetype":"venue"
},
  "geometry": {"coordinates":[-94.715265,44.743943],"type":"Point"}
}