{
  "type": "Feature",
  "properties": {
    "addr:full":"3812 21st St SE Rochester MN 55904",
    "addr:housenumber":"3812",
    "addr:postcode":"55904",
    "addr:street":"21St St Se",
    "iso:country":"US",
    "sg:address":"3812 21st St SE",
    "sg:city":"Rochester",
    "sg:classifiers":[
        {
            "category":"Building & Trades",
            "subcategory":"Electrical",
            "type":"Services"
        }
    ],
    "sg:phone":"+1 507 288 5151",
    "sg:postcode":"55904",
    "sg:province":"MN",
    "sg:tags":[
        "electrical",
        "contractor"
    ],
    "wof:name":"Advanced Contractors Inc",
    "wof:placetype":"venue"
},
  "geometry": {"coordinates":[-92.40137199999999,43.990247],"type":"Point"}
}