{
  "type": "Feature",
  "properties": {
    "iso:country":"US",
    "sg:address":"4080 W Broadway Ave",
    "sg:city":"Minneapolis",
    "sg:classifiers":[
        {
            "category":"Professional",
            "subcategory":"Employment Agencies",
            "type":"Services"
        }
    ],
    "sg:phone":"+1 763 537 1225",
    "sg:postcode":"55422",
    "sg:province":"MN",
    "sg:tags":[
        "opportunity"
    ],
    "sg:website":"www.atastaffing.com",
    "wof:name":"Ata Staffing",
    "wof:placetype":"venue"
},
  "geometry": {"coordinates":[-93.336304,45.0289],"type":"Point"}
}