{
  "type": "Feature",
  "properties": {
    "addr:full":"140 Birch Ave E Hector MN 55342",
    "addr:housenumber":"140",
    "addr:postcode":"55342",
    "addr:street":"Birch Ave E Hector",
    "iso:country":"US",
    "sg:address":"140 Birch Ave E",
    "sg:city":"Hector",
    "sg:classifiers":[
        {
            "category":"Autos & Motor Vehicles",
            "subcategory":"Automobile Sales",
            "type":"Retail Goods"
        },
        {
            "category":"Autos & Motor Vehicles",
            "subcategory":"Auto Supplies",
            "type":"Retail Goods"
        }
    ],
    "sg:phone":"+1 320 848 6131",
    "sg:postcode":"55342",
    "sg:province":"MN",
    "sg:tags":[
        "equipment",
        "part",
        "electrical",
        "accessory"
    ],
    "wof:name":"Lang's Automotive Ctr",
    "wof:placetype":"venue"
},
  "geometry": {"coordinates":[-94.71455400000001,44.744011],"type":"Point"}
}