{
  "type": "Feature",
  "properties": {
    "iso:country":"US",
    "sg:address":"244 Primrose Pl",
    "sg:city":"Watertown",
    "sg:classifiers":[
        {
            "category":"Building & Trades",
            "subcategory":"Construction",
            "type":"Services"
        }
    ],
    "sg:phone":"+1 952 955 1266",
    "sg:postcode":"55388",
    "sg:province":"MN",
    "sg:tags":[
        "house"
    ],
    "wof:name":"Lone Wolf Construction",
    "wof:placetype":"venue"
},
  "geometry": {"coordinates":[-93.82522299999999,44.955363],"type":"Point"}
}