{
  "type": "Feature",
  "properties": {
    "addr:full":"9600 W 76th St Eden Prairie MN 55344",
    "addr:housenumber":"9600",
    "addr:postcode":"55344",
    "addr:street":"W 76Th St",
    "iso:country":"US",
    "sg:address":"9600 W 76th St",
    "sg:city":"Eden Prairie",
    "sg:classifiers":[
        {
            "category":"Wholesale",
            "subcategory":"Electrical",
            "type":"Manufacturing & Wholesale Goods"
        }
    ],
    "sg:phone":"+1 952 944 3456",
    "sg:postcode":"55344",
    "sg:province":"MN",
    "sg:tags":[
        "electronic"
    ],
    "wof:name":"Stan Clothier Company",
    "wof:placetype":"venue"
},
  "geometry": {"coordinates":[-93.39860400000001,44.865573],"type":"Point"}
}