{
  "type": "Feature",
  "properties": {
    "addr:full":"31757 State Hwy 106 Deer Creek MN 56527",
    "addr:housenumber":"31757",
    "addr:postcode":"56527",
    "addr:street":"State Hwy 106",
    "iso:country":"US",
    "sg:address":"31757 State Hwy 106",
    "sg:city":"Deer Creek",
    "sg:classifiers":[
        {
            "category":"Building & Trades",
            "subcategory":"Construction",
            "type":"Services"
        }
    ],
    "sg:phone":"+1 218 462 2516",
    "sg:postcode":"56527",
    "sg:province":"MN",
    "sg:tags":[
        "farm",
        "field",
        "corn",
        "crop"
    ],
    "wof:name":"Ronald Sakry",
    "wof:placetype":"venue"
},
  "geometry": {"coordinates":[-95.32224600000001,46.412946],"type":"Point"}
}