{
  "type": "Feature",
  "properties": {
    "iso:country":"US",
    "sg:address":"15862 Eagle Creek Ave NE",
    "sg:city":"Prior Lake",
    "sg:classifiers":[
        {
            "category":"Recreation",
            "subcategory":"Marina",
            "type":"Entertainment"
        }
    ],
    "sg:phone":"+1 952 447 4300",
    "sg:postcode":"55372",
    "sg:province":"MN",
    "sg:tags":[
        "full"
    ],
    "wof:name":"Wagon Bridge Marina & Service",
    "wof:placetype":"venue"
},
  "geometry": {"coordinates":[-93.43791299999999,44.720462],"type":"Point"}
}