{
  "type": "Feature",
  "properties": {
    "addr:full":"704 Water St SW Sleepy Eye MN 56085",
    "addr:housenumber":"704",
    "addr:postcode":"56085",
    "addr:street":"Water St Sw Sleepy",
    "iso:country":"US",
    "sg:address":"704 Water St SW",
    "sg:city":"Sleepy Eye",
    "sg:classifiers":[
        {
            "category":"Building & Trades",
            "subcategory":"Construction",
            "type":"Services"
        }
    ],
    "sg:phone":"+1 507 794 3188",
    "sg:postcode":"56085",
    "sg:province":"MN",
    "sg:tags":[
        "house"
    ],
    "wof:name":"Wahl Construction",
    "wof:placetype":"venue"
},
  "geometry": {"coordinates":[-94.733611,44.294164],"type":"Point"}
}