{
  "type": "Feature",
  "properties": {
    "addr:full":"1200 Main St NE Chatfield MN 55923",
    "addr:housenumber":"1200",
    "addr:postcode":"55923",
    "addr:street":"Main St Ne",
    "iso:country":"US",
    "sg:address":"1200 Main St NE",
    "sg:city":"Chatfield",
    "sg:classifiers":[
        {
            "category":"Wholesale",
            "subcategory":"Farm Supplies",
            "type":"Manufacturing & Wholesale Goods"
        }
    ],
    "sg:phone":"+1 507 867 9009",
    "sg:postcode":"55923",
    "sg:province":"MN",
    "sg:tags":[
        "bean"
    ],
    "wof:name":"Valley Systems",
    "wof:placetype":"venue"
},
  "geometry": {"coordinates":[-92.193515,43.855906],"type":"Point"}
}