{
  "type": "Feature",
  "properties": {
    "iso:country":"US",
    "sg:address":"928 5th St SE",
    "sg:city":"Minneapolis",
    "sg:classifiers":[
        {
            "category":"Organizations",
            "subcategory":"Community Association",
            "type":"Services"
        }
    ],
    "sg:phone":"+1 612 379 1121",
    "sg:postcode":"55414",
    "sg:province":"MN",
    "wof:name":"Kappa University of Minnesota",
    "wof:placetype":"venue"
},
  "geometry": {"coordinates":[-93.24073,44.983698],"type":"Point"}
}