{
  "type": "Feature",
  "properties": {
    "addr:full":"31912 440th Ave NW Argyle MN 56713",
    "addr:housenumber":"31912",
    "addr:postcode":"56713",
    "addr:street":"440Th Ave Nw",
    "iso:country":"US",
    "sg:address":"31912 440th Ave NW",
    "sg:city":"Argyle",
    "sg:phone":"+1 218 437 6353",
    "sg:postcode":"56713",
    "sg:province":"MN",
    "sg:tags":[
        "farm",
        "grain",
        "cash"
    ],
    "wof:name":"McFarland Corner Farms",
    "wof:placetype":"venue"
},
  "geometry": {"coordinates":[-97.000771,48.338334],"type":"Point"}
}