{
  "type": "Feature",
  "properties": {
    "addr:full":"700 Olive St Saint Paul MN 55130",
    "addr:housenumber":"700",
    "addr:postcode":"55130",
    "addr:street":"Olive St",
    "iso:country":"US",
    "sg:address":"700 Olive St",
    "sg:city":"Saint Paul",
    "sg:classifiers":[
        {
            "category":"Organizations",
            "subcategory":"Labor Organization",
            "type":"Services"
        }
    ],
    "sg:phone":"+1 651 646 7207",
    "sg:postcode":"55130",
    "sg:province":"MN",
    "wof:name":"Lakes Plins Rgonal Council Car",
    "wof:placetype":"venue"
},
  "geometry": {"coordinates":[-93.087549,44.958169],"type":"Point"}
}