{
  "type": "Feature",
  "properties": {
    "addr:full":"108 E Main St Elysian MN 56028",
    "addr:housenumber":"108",
    "addr:postcode":"56028",
    "addr:street":"E Main St",
    "iso:country":"US",
    "sg:address":"108 E Main St",
    "sg:city":"Elysian",
    "sg:classifiers":[
        {
            "category":"Personal",
            "subcategory":"Beauty Salon",
            "type":"Services"
        }
    ],
    "sg:phone":"+1 507 267 4922",
    "sg:postcode":"56028",
    "sg:province":"MN",
    "sg:tags":[
        "shop"
    ],
    "wof:name":"Trailside Trim",
    "wof:placetype":"venue"
},
  "geometry": {"coordinates":[-93.675521,44.198761],"type":"Point"}
}