{
  "type": "Feature",
  "properties": {
    "iso:country":"US",
    "sg:address":"625 E Vernon Ave",
    "sg:city":"Fergus Falls",
    "sg:classifiers":[
        {
            "category":"Food & Beverages",
            "subcategory":"Groceries & Convenience Stores",
            "type":"Retail Goods"
        }
    ],
    "sg:phone":"+1 218 739 9946",
    "sg:postcode":"56537",
    "sg:province":"MN",
    "wof:name":"Casey's General Store",
    "wof:placetype":"venue"
},
  "geometry": {"coordinates":[-96.06499100000001,46.278411],"type":"Point"}
}