{
  "type": "Feature",
  "properties": {
    "addr:full":"213 2nd Ave NW Deer River MN 56636",
    "addr:housenumber":"213",
    "addr:postcode":"56636",
    "addr:street":"2Nd Ave Nw Deer",
    "iso:country":"US",
    "sg:address":"213 2nd Ave NW",
    "sg:city":"Deer River",
    "sg:classifiers":[
        {
            "category":"Retail",
            "subcategory":"Auto Repair",
            "type":"Services"
        }
    ],
    "sg:phone":"+1 218 246 9290",
    "sg:postcode":"56636",
    "sg:province":"MN",
    "sg:tags":[
        "machine",
        "automobile",
        "shop"
    ],
    "wof:name":"Deer River Tire & Auto Repair",
    "wof:placetype":"venue"
},
  "geometry": {"coordinates":[-93.79513900000001,47.33483],"type":"Point"}
}