{
  "type": "Feature",
  "properties": {
    "addr:full":"33155 Hemmingway Ave Stacy MN 55079",
    "addr:postcode":"33155;55079",
    "addr:street":"Hemmingway Ave",
    "iso:country":"US",
    "sg:address":"33155 Hemmingway Ave",
    "sg:city":"Stacy",
    "sg:classifiers":[
        {
            "category":"Real Estate",
            "subcategory":"Real Estate Operator",
            "type":"Services"
        }
    ],
    "sg:phone":"+1 651 462 3009",
    "sg:postcode":"55079",
    "sg:province":"MN",
    "wof:name":"Lent Town Hall",
    "wof:placetype":"venue"
},
  "geometry": {"coordinates":[-92.95847500000001,45.428622],"type":"Point"}
}