{
  "type": "Feature",
  "properties": {
    "iso:country":"US",
    "sg:address":"9852 Lyndale Ave S",
    "sg:city":"Bloomington",
    "sg:classifiers":[
        {
            "category":"Retail",
            "subcategory":"Repair Shop",
            "type":"Services"
        }
    ],
    "sg:phone":"+1 952 884 3465",
    "sg:postcode":"55420",
    "sg:province":"MN",
    "sg:tags":[
        "electronics"
    ],
    "sg:website":"www.alexav.com",
    "wof:name":"Alex's Audio & Video Service Inc",
    "wof:placetype":"venue"
},
  "geometry": {"coordinates":[-93.288701,44.825299],"type":"Point"}
}