{
  "type": "Feature",
  "properties": {
    "addr:full":"4520 Co Rd 33 New Germany MN 55367",
    "addr:housenumber":"4520;33",
    "addr:postcode":"55367",
    "addr:street":"Co Rd",
    "iso:country":"US",
    "sg:address":"4520 Co Rd 33",
    "sg:city":"New Germany",
    "sg:classifiers":[
        {
            "category":"Farming",
            "subcategory":"Livestock Farm",
            "type":"Manufacturing & Wholesale Goods"
        }
    ],
    "sg:phone":"+1 952 353 2462",
    "sg:postcode":"55367",
    "sg:province":"MN",
    "sg:tags":[
        "feedlot",
        "grain",
        "cash",
        "beef",
        "cattle"
    ],
    "wof:name":"Peterman Farm",
    "wof:placetype":"venue"
},
  "geometry": {"coordinates":[-93.97121199999999,44.920829],"type":"Point"}
}