{
  "type": "Feature",
  "properties": {
    "iso:country":"US",
    "sg:address":"6110 Lamar Ave S",
    "sg:city":"Cottage Grove",
    "sg:classifiers":[
        {
            "category":"Professional",
            "subcategory":"Computer Services",
            "type":"Services"
        }
    ],
    "sg:phone":"+1 651 459 4808",
    "sg:postcode":"55016",
    "sg:province":"MN",
    "sg:tags":[
        "development",
        "designer",
        "consultant",
        "custom",
        "project",
        "coordinator",
        "programing",
        "software"
    ],
    "wof:name":"Top Desk Applications & Dev",
    "wof:placetype":"venue"
},
  "geometry": {"coordinates":[-92.881613,44.858821],"type":"Point"}
}