{
  "type": "Feature",
  "properties": {
    "iso:country":"US",
    "sg:address":"3923 6th St S",
    "sg:city":"Moorhead",
    "sg:classifiers":[
        {
            "category":"Personal",
            "type":"Services"
        }
    ],
    "sg:phone":"+1 218 236 8031",
    "sg:postcode":"56560",
    "sg:province":"MN",
    "wof:name":"Time For ME Massage Therapy",
    "wof:placetype":"venue"
},
  "geometry": {"coordinates":[-96.770571,46.834254],"type":"Point"}
}