{
  "type": "Feature",
  "properties": {
    "addr:full":"6455 Oakgreen Ave S Hastings MN 55033",
    "addr:housenumber":"6455",
    "addr:postcode":"55033",
    "addr:street":"Oakgreen Ave S Hastings",
    "iso:country":"US",
    "sg:address":"6455 Oakgreen Ave S",
    "sg:city":"Hastings",
    "sg:classifiers":[
        {
            "category":"Farming",
            "subcategory":"Farm",
            "type":"Manufacturing & Wholesale Goods"
        }
    ],
    "sg:phone":"+1 651 436 2778",
    "sg:postcode":"55033",
    "sg:province":"MN",
    "sg:website":"www.freshearthfarms.com",
    "wof:name":"Fresh Earth Farms",
    "wof:placetype":"venue"
},
  "geometry": {"coordinates":[-92.82154199999999,44.853787],"type":"Point"}
}