{
  "type": "Feature",
  "properties": {
    "addr:full":"4744 Garfield Ave S Minneapolis MN 55419",
    "addr:housenumber":"4744",
    "addr:postcode":"55419",
    "addr:street":"Garfield Ave S",
    "iso:country":"US",
    "sg:address":"4744 Garfield Ave S",
    "sg:city":"Minneapolis",
    "sg:classifiers":[
        {
            "category":"Shopping",
            "subcategory":"Bicycles & Sporting Goods",
            "type":"Retail Goods"
        }
    ],
    "sg:phone":"+1 612 825 0859",
    "sg:postcode":"55419",
    "sg:province":"MN",
    "sg:tags":[
        "mfg",
        "trimming"
    ],
    "wof:name":"Callum Sports",
    "wof:placetype":"venue"
},
  "geometry": {"coordinates":[-93.28708,44.916764],"type":"Point"}
}