{
  "type": "Feature",
  "properties": {
    "iso:country":"US",
    "sg:address":"102 E Grove St",
    "sg:city":"Caledonia",
    "sg:classifiers":[
        {
            "category":"Banks & Credit Unions",
            "subcategory":"Bank",
            "type":"Services"
        }
    ],
    "sg:phone":"+1 507 724 2424",
    "sg:postcode":"55921",
    "sg:province":"MN",
    "sg:tags":[
        "loan",
        "real estate"
    ],
    "wof:name":"Westview Mortgage Corp",
    "wof:placetype":"venue"
},
  "geometry": {"coordinates":[-91.496978,43.63354],"type":"Point"}
}