{
  "type": "Feature",
  "properties": {
    "addr:full":"1010 Bandana Blvd W St Paul MN 55108",
    "addr:housenumber":"1010",
    "addr:postcode":"55108",
    "addr:street":"Bandana Blvd W",
    "iso:country":"US",
    "sg:address":"1010 Bandana Blvd W",
    "sg:city":"St Paul",
    "sg:classifiers":[
        {
            "category":"Travel",
            "subcategory":"Hotels & Motels",
            "type":"Entertainment"
        }
    ],
    "sg:phone":"+1 651 647 1637",
    "sg:postcode":"55108",
    "sg:province":"MN",
    "wof:name":"Holiday Inn Express St Paul",
    "wof:placetype":"venue"
},
  "geometry": {"coordinates":[-93.154572,44.97095],"type":"Point"}
}