{
  "type": "Feature",
  "properties": {
    "iso:country":"US",
    "sg:address":"9318 Zane Ave N",
    "sg:city":"Minneapolis",
    "sg:classifiers":[
        {
            "category":"Food & Beverages",
            "subcategory":"Liquor & Beverages",
            "type":"Retail Goods"
        }
    ],
    "sg:phone":"+1 763 493 9463",
    "sg:postcode":"55443",
    "sg:province":"MN",
    "sg:tags":[
        "beer",
        "spirit",
        "wine"
    ],
    "wof:name":"Wine and Beer",
    "wof:placetype":"venue"
},
  "geometry": {"coordinates":[-93.35600700000001,45.123362],"type":"Point"}
}