{
  "type": "Feature",
  "properties": {
    "iso:country":"US",
    "sg:address":"1043 Grand Ave",
    "sg:city":"Saint Paul",
    "sg:classifiers":[
        {
            "category":"Real Estate",
            "subcategory":"Real Estate Services",
            "type":"Services"
        }
    ],
    "sg:phone":"+1 651 225 9436",
    "sg:postcode":"55105",
    "sg:province":"MN",
    "sg:tags":[
        "abstract",
        "title"
    ],
    "wof:name":"Title Recording Srvcs",
    "wof:placetype":"venue"
},
  "geometry": {"coordinates":[-93.146542,44.940072],"type":"Point"}
}