{
  "type": "Feature",
  "properties": {
    "iso:country":"US",
    "sg:address":"2405 Central Ave NE",
    "sg:city":"Minneapolis",
    "sg:classifiers":[
        {
            "category":"Restaurant",
            "type":"Food & Drink"
        }
    ],
    "sg:phone":"+1 612 789 2526",
    "sg:postcode":"55418",
    "sg:province":"MN",
    "sg:tags":[
        "mexican"
    ],
    "sg:website":"www.adelitasmexicanrestaurant.com/",
    "wof:name":"Adelita's Mexican Restaurant",
    "wof:placetype":"venue"
},
  "geometry": {"coordinates":[-93.246934,45.012417],"type":"Point"}
}