{
  "type": "Feature",
  "properties": {
    "addr:full":"416 7th St S Moorhead MN 56560",
    "addr:housenumber":"416",
    "addr:postcode":"56560",
    "addr:street":"7Th St S",
    "iso:country":"US",
    "sg:address":"416 7th St S",
    "sg:city":"Moorhead",
    "sg:classifiers":[
        {
            "category":"Science Facility",
            "type":"Public Place"
        }
    ],
    "sg:phone":"+1 701 238 7779",
    "sg:postcode":"56560",
    "sg:province":"MN",
    "sg:tags":[
        "development",
        "laboratories-research"
    ],
    "wof:name":"Kathleen Hamilton",
    "wof:placetype":"venue"
},
  "geometry": {"coordinates":[-96.769353,46.870488],"type":"Point"}
}