{
  "type": "Feature",
  "properties": {
    "addr:full":"2100 Snelling Avenue N Roseville MN 55113",
    "addr:housenumber":"2100",
    "addr:postcode":"55113",
    "addr:street":"Snelling Avenue N",
    "iso:country":"US",
    "sg:address":"2100 Snelling Avenue N",
    "sg:city":"Roseville",
    "sg:classifiers":[
        {
            "category":"Fast Food",
            "type":"Food & Drink"
        }
    ],
    "sg:phone":"+1 651 251 0220",
    "sg:postcode":"55113",
    "sg:province":"MN",
    "sg:tags":[
        "burger"
    ],
    "sg:website":"www.smashburger.com",
    "wof:name":"Smashburger",
    "wof:placetype":"venue"
},
  "geometry": {"coordinates":[-93.164416,45.003613],"type":"Point"}
}