{
  "type": "Feature",
  "properties": {
    "addr:full":"309 State Ave N Thief River Falls MN 56701",
    "addr:housenumber":"309",
    "addr:postcode":"56701",
    "addr:street":"State Ave N",
    "iso:country":"US",
    "sg:address":"309 State Ave N",
    "sg:city":"Thief River Falls",
    "sg:classifiers":[
        {
            "category":"Bars & Pubs",
            "type":"Food & Drink"
        }
    ],
    "sg:phone":"+1 218 681 0494",
    "sg:postcode":"56701",
    "sg:province":"MN",
    "sg:tags":[
        "drinking"
    ],
    "wof:name":"Nu Moon Cafe",
    "wof:placetype":"venue"
},
  "geometry": {"coordinates":[-96.187833,48.120092],"type":"Point"}
}