{
  "type": "Feature",
  "properties": {
    "addr:full":"410 N Cedar St Belle Plaine MN 56011",
    "addr:housenumber":"410",
    "addr:postcode":"56011",
    "addr:street":"N Cedar St;Plaine",
    "iso:country":"US",
    "sg:address":"410 N Cedar St",
    "sg:city":"Belle Plaine",
    "sg:classifiers":[
        {
            "category":"Museum",
            "type":"Entertainment"
        },
        {
            "category":"Recreation",
            "type":"Entertainment"
        }
    ],
    "sg:phone":"+1 952 873 6109",
    "sg:postcode":"56011",
    "sg:province":"MN",
    "sg:tags":[
        "gallery",
        "historical"
    ],
    "wof:name":"Belle Plaine Historical Soc",
    "wof:placetype":"venue"
},
  "geometry": {"coordinates":[-93.765327,44.626186],"type":"Point"}
}