{
  "type": "Feature",
  "properties": {
    "iso:country":"US",
    "sg:address":"1707 19th Ave NW",
    "sg:city":"Rochester",
    "sg:classifiers":[
        {
            "category":"Education",
            "subcategory":"School",
            "type":"Public Place"
        }
    ],
    "sg:phone":"+1 507 281 6107",
    "sg:postcode":"55901",
    "sg:province":"MN",
    "sg:tags":[
        "elementary"
    ],
    "sg:website":"www.rochester.k12.mn.us",
    "wof:name":"Sunset Terrace Elementary Schl",
    "wof:placetype":"venue"
},
  "geometry": {"coordinates":[-92.4927,44.040755],"type":"Point"}
}