{
  "type": "Feature",
  "properties": {
    "addr:full":"10552 Cameo Cir Glencoe MN 55336",
    "addr:housenumber":"10552",
    "addr:postcode":"55336",
    "addr:street":"Cameo Cir",
    "iso:country":"US",
    "sg:address":"10552 Cameo Cir",
    "sg:city":"Glencoe",
    "sg:classifiers":[
        {
            "category":"Organizations",
            "subcategory":"Political Organization",
            "type":"Services"
        }
    ],
    "sg:phone":"+1 320 864 5986",
    "sg:postcode":"55336",
    "sg:province":"MN",
    "sg:tags":[
        "daycare",
        "provider"
    ],
    "wof:name":"Carolann Schlechter",
    "wof:placetype":"venue"
},
  "geometry": {"coordinates":[-94.07898900000001,44.76979],"type":"Point"}
}