{
  "type": "Feature",
  "properties": {
    "addr:full":"557 E Sanborn St Winona MN 55987",
    "addr:housenumber":"557",
    "addr:postcode":"55987",
    "addr:street":"E Sanborn St",
    "iso:country":"US",
    "sg:address":"557 E Sanborn St",
    "sg:city":"Winona",
    "sg:classifiers":[
        {
            "category":"Building & Trades",
            "subcategory":"Construction",
            "type":"Services"
        }
    ],
    "sg:phone":"+1 507 453 9640",
    "sg:postcode":"55987",
    "sg:province":"MN",
    "sg:tags":[
        "repairing",
        "home",
        "remodeling",
        "maintenance",
        "contractor"
    ],
    "wof:name":"Total Home Construction Inc",
    "wof:placetype":"venue"
},
  "geometry": {"coordinates":[-91.62575099999999,44.043684],"type":"Point"}
}