{
  "type": "Feature",
  "properties": {
    "addr:full":"16780 Kenrick Ave Lakeville MN 55044",
    "addr:postcode":"16780;55044",
    "addr:street":"Kenrick Ave",
    "iso:country":"US",
    "sg:address":"16780 Kenrick Ave",
    "sg:city":"Lakeville",
    "sg:classifiers":[
        {
            "category":"Government",
            "subcategory":"Department Of Motor Vehicles",
            "type":"Public Place"
        }
    ],
    "sg:phone":"+1 952 435 6480",
    "sg:postcode":"55044",
    "sg:province":"MN",
    "sg:tags":[
        "dust",
        "control",
        "oiling",
        "road"
    ],
    "sg:website":"http://www.me.umn.edu",
    "wof:name":"Mn Dept Trans Lakeville S",
    "wof:placetype":"venue"
},
  "geometry": {"coordinates":[-93.283539,44.706589],"type":"Point"}
}