{
  "type": "Feature",
  "properties": {
    "iso:country":"US",
    "sg:address":"34128 Co Rd 14",
    "sg:city":"Starbuck",
    "sg:classifiers":[
        {
            "category":"Farming",
            "subcategory":"Livestock Farm",
            "type":"Manufacturing & Wholesale Goods"
        }
    ],
    "sg:phone":"+1 320 239 2462",
    "sg:postcode":"56381",
    "sg:province":"MN",
    "sg:tags":[
        "feedlot",
        "corn",
        "soybean",
        "beef",
        "cattle"
    ],
    "wof:name":"Donald Runquist",
    "wof:placetype":"venue"
},
  "geometry": {"coordinates":[-95.628441,45.542566],"type":"Point"}
}