{
  "type": "Feature",
  "properties": {
    "iso:country":"US",
    "sg:address":"1405 W Edmund Ave",
    "sg:city":"Saint Paul",
    "sg:classifiers":[
        {
            "category":"Building & Trades",
            "subcategory":"Construction",
            "type":"Services"
        }
    ],
    "sg:phone":"+1 612 340 0454",
    "sg:postcode":"55104",
    "sg:province":"MN",
    "sg:tags":[
        "contractor"
    ],
    "wof:name":"Jaw Contracting Inc",
    "wof:placetype":"venue"
},
  "geometry": {"coordinates":[-93.161799,44.958462],"type":"Point"}
}