{
  "type": "Feature",
  "properties": {
    "addr:full":"120 Garfield St N Cambridge MN 55008",
    "addr:housenumber":"120",
    "addr:postcode":"55008",
    "addr:street":"Garfield St N",
    "iso:country":"US",
    "sg:address":"120 Garfield St N",
    "sg:city":"Cambridge",
    "sg:classifiers":[
        {
            "category":"Fast Food",
            "type":"Food & Drink"
        },
        {
            "category":"Restaurant",
            "type":"Food & Drink"
        },
        {
            "category":"Food & Beverages",
            "subcategory":"Groceries & Convenience Stores",
            "type":"Retail Goods"
        }
    ],
    "sg:phone":"+1 763 689 4954",
    "sg:postcode":"55008",
    "sg:province":"MN",
    "sg:tags":[
        "shop",
        "american",
        "sandwich",
        "take"
    ],
    "sg:website":"http://www.subway.com",
    "wof:name":"Subway",
    "wof:placetype":"venue"
},
  "geometry": {"coordinates":[-93.213936,45.57361],"type":"Point"}
}