{
  "type": "Feature",
  "properties": {
    "iso:country":"US",
    "sg:address":"2205 Shenandoah Ln N",
    "sg:city":"Minneapolis",
    "sg:classifiers":[
        {
            "category":"Real Estate",
            "subcategory":"Real Estate Operator",
            "type":"Services"
        }
    ],
    "sg:phone":"+1 763 249 7769",
    "sg:postcode":"55447",
    "sg:province":"MN",
    "sg:tags":[
        "building",
        "apartment"
    ],
    "wof:name":"Purgatory Creek Townhomes",
    "wof:placetype":"venue"
},
  "geometry": {"coordinates":[-93.476778,45.002537],"type":"Point"}
}