{
  "type": "Feature",
  "properties": {
    "iso:country":"US",
    "sg:address":"2224 Sheridan Ave S",
    "sg:city":"Minneapolis",
    "sg:classifiers":[
        {
            "category":"Professional",
            "subcategory":"Secretarial Services",
            "type":"Services"
        }
    ],
    "sg:phone":"+1 612 377 9732",
    "sg:postcode":"55405",
    "sg:province":"MN",
    "sg:tags":[
        "proofreading",
        "reporting"
    ],
    "wof:name":"Precision Proofing Inc",
    "wof:placetype":"venue"
},
  "geometry": {"coordinates":[-93.313518,44.959359],"type":"Point"}
}