{
  "type": "Feature",
  "properties": {
    "addr:full":"318 Elton Hills Dr NW Rochester MN 55901",
    "addr:housenumber":"318",
    "addr:postcode":"55901",
    "addr:street":"Elton Hills Dr Nw",
    "iso:country":"US",
    "sg:address":"318 Elton Hills Dr NW",
    "sg:city":"Rochester",
    "sg:classifiers":[
        {
            "category":"Personal",
            "subcategory":"Beauty Salon",
            "type":"Services"
        }
    ],
    "sg:phone":"+1 507 280 8674",
    "sg:postcode":"55901",
    "sg:province":"MN",
    "sg:tags":[
        "shop"
    ],
    "wof:name":"Classic Cuts",
    "wof:placetype":"venue"
},
  "geometry": {"coordinates":[-92.46833700000001,44.044873],"type":"Point"}
}