{
  "type": "Feature",
  "properties": {
    "addr:full":"2520 Park Ave Minneapolis MN 55404",
    "addr:housenumber":"2520",
    "addr:postcode":"55404",
    "addr:street":"Park Ave",
    "iso:country":"US",
    "sg:address":"2520 Park Ave",
    "sg:city":"Minneapolis",
    "sg:classifiers":[
        {
            "category":"Professional",
            "subcategory":"Lawyer & Legal Services",
            "type":"Services"
        }
    ],
    "sg:phone":"+1 612 872 1100",
    "sg:postcode":"55404",
    "sg:province":"MN",
    "wof:name":"Ward & Ward Llc",
    "wof:placetype":"venue"
},
  "geometry": {"coordinates":[-93.265297,44.956402],"type":"Point"}
}