{
  "type": "Feature",
  "properties": {
    "iso:country":"US",
    "sg:address":"4814 5th St NE",
    "sg:city":"Minneapolis",
    "sg:classifiers":[
        {
            "category":"Communications",
            "subcategory":"Film & Video Production",
            "type":"Services"
        }
    ],
    "sg:phone":"+1 763 571 7327",
    "sg:postcode":"55421",
    "sg:province":"MN",
    "sg:tags":[
        "tv",
        "radio",
        "services-commercial",
        "companies-film"
    ],
    "wof:name":"Flying Freeload Productions",
    "wof:placetype":"venue"
},
  "geometry": {"coordinates":[-93.26026899999999,45.055679],"type":"Point"}
}