{
  "type": "Feature",
  "properties": {
    "iso:country":"US",
    "sg:address":"920 E. Lake St., Suite 151 Midtown Global Market",
    "sg:city":"Minneapolis",
    "sg:classifiers":[
        {
            "category":"Fast Food",
            "type":"Food & Drink"
        },
        {
            "category":"Restaurant",
            "type":"Food & Drink"
        }
    ],
    "sg:phone":"+1 612 886 2602",
    "sg:postcode":"55407",
    "sg:province":"MN",
    "sg:tags":[
        "burger",
        "breakfast",
        "brunch"
    ],
    "sg:website":"www.midtownglobalmarket.org/?q=d...",
    "wof:name":"Andy's Garage",
    "wof:placetype":"venue"
},
  "geometry": {"coordinates":[-93.261117,44.948348],"type":"Point"}
}