{
  "type": "Feature",
  "properties": {
    "addr:full":"4938 Brooklyn Blvd Minneapolis MN 55429",
    "addr:housenumber":"4938",
    "addr:postcode":"55429",
    "addr:street":"Brooklyn Blvd",
    "iso:country":"US",
    "sg:address":"4938 Brooklyn Blvd",
    "sg:city":"Minneapolis",
    "sg:classifiers":[
        {
            "category":"Health Services",
            "subcategory":"Clinic",
            "type":"Services"
        }
    ],
    "sg:phone":"+1 763 535 7265",
    "sg:postcode":"55429",
    "sg:province":"MN",
    "sg:tags":[
        "rehabilitation"
    ],
    "wof:name":"Alano Twin Lake",
    "wof:placetype":"venue"
},
  "geometry": {"coordinates":[-93.319731,45.044793],"type":"Point"}
}