{
  "type": "Feature",
  "properties": {
    "iso:country":"US",
    "sg:address":"2110 20th Ave SW",
    "sg:city":"Willmar",
    "sg:classifiers":[
        {
            "category":"Professional",
            "type":"Services"
        }
    ],
    "sg:phone":"+1 320 235 4513",
    "sg:postcode":"56201",
    "sg:province":"MN",
    "wof:name":"Rachel M Coleman",
    "wof:placetype":"venue"
},
  "geometry": {"coordinates":[-95.073505,45.10234],"type":"Point"}
}