{
  "type": "Feature",
  "properties": {
    "addr:full":"4001 Regent Ave N Minneapolis MN 55422",
    "addr:housenumber":"4001",
    "addr:postcode":"55422",
    "addr:street":"Regent Ave N",
    "iso:country":"US",
    "sg:address":"4001 Regent Ave N",
    "sg:city":"Minneapolis",
    "sg:classifiers":[
        {
            "category":"Shopping",
            "subcategory":"Baby Store",
            "type":"Retail Goods"
        }
    ],
    "sg:phone":"+1 763 533 2741",
    "sg:postcode":"55422",
    "sg:province":"MN",
    "sg:tags":[
        "children's",
        "infant",
        "wear"
    ],
    "wof:name":"Once Upon A Miracle",
    "wof:placetype":"venue"
},
  "geometry": {"coordinates":[-93.344223,45.02774],"type":"Point"}
}