{
  "type": "Feature",
  "properties": {
    "addr:full":"5711 Knox Ave N Minneapolis MN 55430",
    "addr:housenumber":"5711",
    "addr:postcode":"55430",
    "addr:street":"Knox Ave N",
    "iso:country":"US",
    "sg:address":"5711 Knox Ave N",
    "sg:city":"Minneapolis",
    "sg:classifiers":[
        {
            "category":"Banks & Credit Unions",
            "subcategory":"Bank",
            "type":"Services"
        }
    ],
    "sg:phone":"+1 763 560 8637",
    "sg:postcode":"55430",
    "sg:province":"MN",
    "sg:tags":[
        "broker",
        "mortgage"
    ],
    "wof:name":"Marbley & Associates Inc",
    "wof:placetype":"venue"
},
  "geometry": {"coordinates":[-93.30279,45.060059],"type":"Point"}
}