{
  "type": "Feature",
  "properties": {
    "addr:full":"5807 Grand Ave Duluth MN 55807",
    "addr:housenumber":"5807",
    "addr:postcode":"55807",
    "addr:street":"Grand Ave",
    "iso:country":"US",
    "sg:address":"5807 Grand Ave",
    "sg:city":"Duluth",
    "sg:classifiers":[
        {
            "category":"Health Services",
            "subcategory":"Chiropractor",
            "type":"Services"
        }
    ],
    "sg:phone":"+1 218 624 2452",
    "sg:postcode":"55807",
    "sg:province":"MN",
    "wof:name":"Duluth Chiropractic Clinic",
    "wof:placetype":"venue"
},
  "geometry": {"coordinates":[-92.172062,46.737053],"type":"Point"}
}