{
  "type": "Feature",
  "properties": {
    "addr:full":"428 235th Ave Fulda MN 56131",
    "addr:housenumber":"428",
    "addr:postcode":"56131",
    "addr:street":"235Th Ave",
    "iso:country":"US",
    "sg:address":"428 235th Ave",
    "sg:city":"Fulda",
    "sg:classifiers":[
        {
            "category":"Farming",
            "subcategory":"Livestock Farm",
            "type":"Manufacturing & Wholesale Goods"
        }
    ],
    "sg:phone":"+1 507 425 2730",
    "sg:postcode":"56131",
    "sg:province":"MN",
    "sg:tags":[
        "beef",
        "feedlot",
        "cattle"
    ],
    "wof:name":"Linus Dardis",
    "wof:placetype":"venue"
},
  "geometry": {"coordinates":[-95.59232900000001,43.91741],"type":"Point"}
}