{
  "type": "Feature",
  "properties": {
    "iso:country":"US",
    "sg:address":"4155 Co Rd 101",
    "sg:city":"Minneapolis",
    "sg:classifiers":[
        {
            "category":"Recreation",
            "type":"Entertainment"
        }
    ],
    "sg:phone":"+1 763 478 6443",
    "sg:postcode":"55446",
    "sg:province":"MN",
    "sg:tags":[
        "range",
        "practice",
        "golf"
    ],
    "wof:name":"B & V Golf Range",
    "wof:placetype":"venue"
},
  "geometry": {"coordinates":[-93.507445,45.029888],"type":"Point"}
}