{
  "type": "Feature",
  "properties": {
    "addr:full":"3011 W 50th St Minneapolis MN 55410",
    "addr:housenumber":"3011",
    "addr:postcode":"55410",
    "addr:street":"W 50Th St",
    "iso:country":"US",
    "sg:address":"3011 W 50th St",
    "sg:city":"Minneapolis",
    "sg:classifiers":[
        {
            "category":"Arts & Performance",
            "subcategory":"Art Gallery",
            "type":"Entertainment"
        }
    ],
    "sg:phone":"+1 612 925 2662",
    "sg:postcode":"55410",
    "sg:province":"MN",
    "wof:name":"Winchester Gallery",
    "wof:placetype":"venue"
},
  "geometry": {"coordinates":[-93.31759599999999,44.912399],"type":"Point"}
}