{
  "type": "Feature",
  "properties": {
    "addr:full":"8600 Highway 7 Minneapolis MN 55426",
    "addr:housenumber":"8600",
    "addr:postcode":"55426",
    "addr:street":"Highway 7",
    "iso:country":"US",
    "sg:address":"8600 Highway 7",
    "sg:city":"Minneapolis",
    "sg:classifiers":[
        {
            "category":"Banks & Credit Unions",
            "subcategory":"Bank",
            "type":"Services"
        },
        {
            "category":"Banks & Credit Unions",
            "subcategory":"Financial Services",
            "type":"Services"
        }
    ],
    "sg:phone":"+1 612 316 3988",
    "sg:postcode":"55426",
    "sg:province":"MN",
    "sg:tags":[
        "commercial",
        "loan",
        "saving"
    ],
    "sg:website":"http://www.wellsfargo.com",
    "wof:name":"Wells Fargo Bank",
    "wof:placetype":"venue"
},
  "geometry": {"coordinates":[-93.38886100000001,44.935253],"type":"Point"}
}