{
  "type": "Feature",
  "properties": {
    "addr:full":"2381 100th Ave Balaton MN 56115",
    "addr:housenumber":"2381",
    "addr:postcode":"56115",
    "addr:street":"100Th Ave",
    "iso:country":"US",
    "sg:address":"2381 100th Ave",
    "sg:city":"Balaton",
    "sg:classifiers":[
        {
            "category":"Farming",
            "subcategory":"Farm & Veterinary Services",
            "type":"Manufacturing & Wholesale Goods"
        }
    ],
    "sg:phone":"+1 507 734 3061",
    "sg:postcode":"56115",
    "sg:province":"MN",
    "sg:tags":[
        "livestock"
    ],
    "wof:name":"Lynn Wichmann",
    "wof:placetype":"venue"
},
  "geometry": {"coordinates":[-95.86395899999999,44.196259],"type":"Point"}
}