{
  "type": "Feature",
  "properties": {
    "addr:full":"5775 Wayzata Blvd Minneapolis MN 55416",
    "addr:housenumber":"5775",
    "addr:postcode":"55416",
    "addr:street":"Wayzata Blvd",
    "iso:country":"US",
    "sg:address":"5775 Wayzata Blvd",
    "sg:city":"Minneapolis",
    "sg:classifiers":[
        {
            "category":"Professional",
            "subcategory":"Lawyer & Legal Services",
            "type":"Services"
        }
    ],
    "sg:phone":"+1 952 525 2276",
    "sg:postcode":"55416",
    "sg:province":"MN",
    "wof:name":"Wilczynski Ann",
    "wof:placetype":"venue"
},
  "geometry": {"coordinates":[-93.35368,44.969819],"type":"Point"}
}