{
  "type": "Feature",
  "properties": {
    "addr:full":"450 Eastvold Ave Ortonville MN 56278",
    "addr:housenumber":"450",
    "addr:postcode":"56278",
    "addr:street":"Eastvold Ave",
    "iso:country":"US",
    "sg:address":"450 Eastvold Ave",
    "sg:city":"Ortonville",
    "sg:classifiers":[
        {
            "category":"Professional",
            "subcategory":"Research",
            "type":"Services"
        }
    ],
    "sg:phone":"+1 320 839 4135",
    "sg:postcode":"56278",
    "sg:province":"MN",
    "sg:tags":[
        "foundation",
        "philanthropic"
    ],
    "wof:name":"Big Stone Healthcare Fndtn",
    "wof:placetype":"venue"
},
  "geometry": {"coordinates":[-96.44666599999999,45.314779],"type":"Point"}
}