{
  "type": "Feature",
  "properties": {
    "addr:full":"2204 18th Ave SW Austin MN 55912",
    "addr:housenumber":"2204",
    "addr:postcode":"55912",
    "addr:street":"18Th Ave Sw",
    "iso:country":"US",
    "sg:address":"2204 18th Ave SW",
    "sg:city":"Austin",
    "sg:classifiers":[
        {
            "category":"Social Services",
            "subcategory":"Child Care",
            "type":"Services"
        }
    ],
    "sg:phone":"+1 507 437 8595",
    "sg:postcode":"55912",
    "sg:province":"MN",
    "sg:tags":[
        "day",
        "provider"
    ],
    "wof:name":"Lynette M Hegna",
    "wof:placetype":"venue"
},
  "geometry": {"coordinates":[-93.00293600000001,43.65012],"type":"Point"}
}