{
  "type": "Feature",
  "properties": {
    "addr:full":"1016 US Hwy 75 N Breckenridge MN 56520",
    "addr:housenumber":"1016",
    "addr:postcode":"56520",
    "addr:street":"Us Hwy 75 N",
    "iso:country":"US",
    "sg:address":"1016 US Hwy 75 N",
    "sg:city":"Breckenridge",
    "sg:classifiers":[
        {
            "category":"Building & Trades",
            "subcategory":"Landscaping Services",
            "type":"Services"
        }
    ],
    "sg:phone":"+1 218 643 8338",
    "sg:postcode":"56520",
    "sg:province":"MN",
    "sg:tags":[
        "landscape",
        "contractor"
    ],
    "wof:name":"Landmark Landscaping Inc",
    "wof:placetype":"venue"
},
  "geometry": {"coordinates":[-96.58719600000001,46.274591],"type":"Point"}
}