{
  "type": "Feature",
  "properties": {
    "iso:country":"US",
    "sg:address":"2513 Midway Ln",
    "sg:city":"Grand Rapids",
    "sg:classifiers":[
        {
            "category":"Wholesale",
            "subcategory":"Vending Machines",
            "type":"Manufacturing & Wholesale Goods"
        }
    ],
    "sg:phone":"+1 218 326 3559",
    "sg:postcode":"55744",
    "sg:province":"MN",
    "sg:tags":[
        "operator"
    ],
    "wof:name":"Norvend Inc of Grand Rapids",
    "wof:placetype":"venue"
},
  "geometry": {"coordinates":[-93.469168,47.256434],"type":"Point"}
}