{
  "type": "Feature",
  "properties": {
    "iso:country":"US",
    "sg:address":"7373 147th St W",
    "sg:city":"Saint Paul",
    "sg:classifiers":[
        {
            "category":"Wholesale",
            "subcategory":"Machinery & Supplies",
            "type":"Manufacturing & Wholesale Goods"
        }
    ],
    "sg:phone":"+1 952 431 4133",
    "sg:postcode":"55124",
    "sg:province":"MN",
    "sg:tags":[
        "industrial"
    ],
    "wof:name":"Timken Company",
    "wof:placetype":"venue"
},
  "geometry": {"coordinates":[-93.215492,44.734917],"type":"Point"}
}