{
  "type": "Feature",
  "properties": {
    "addr:full":"12815 1st Ave N Lindstrom MN 55045",
    "addr:housenumber":"12815",
    "addr:postcode":"55045",
    "addr:street":"1St Ave N Lindstrom",
    "iso:country":"US",
    "sg:address":"12815 1st Ave N",
    "sg:city":"Lindstrom",
    "sg:classifiers":[
        {
            "category":"Professional",
            "subcategory":"Computer Services",
            "type":"Services"
        }
    ],
    "sg:phone":"+1 651 257 9507",
    "sg:postcode":"55045",
    "sg:province":"MN",
    "sg:tags":[
        "internet"
    ],
    "wof:name":"Cornernet Communications",
    "wof:placetype":"venue"
},
  "geometry": {"coordinates":[-92.847111,45.39023],"type":"Point"}
}