{
  "type": "Feature",
  "properties": {
    "iso:country":"US",
    "sg:address":"28522 Maple Hill Dr",
    "sg:city":"Grand Rapids",
    "sg:classifiers":[
        {
            "category":"Wholesale",
            "subcategory":"Non-durable Goods",
            "type":"Manufacturing & Wholesale Goods"
        }
    ],
    "sg:phone":"+1 218 326 1712",
    "sg:postcode":"55744",
    "sg:province":"MN",
    "wof:name":"Artco Promotional Products",
    "wof:placetype":"venue"
},
  "geometry": {"coordinates":[-93.584361,47.289339],"type":"Point"}
}