{
  "type": "Feature",
  "properties": {
    "addr:full":"761 W 78th St Chanhassen MN 55317",
    "addr:housenumber":"761",
    "addr:postcode":"55317",
    "addr:street":"W 78Th St",
    "iso:country":"US",
    "sg:address":"761 W 78th St",
    "sg:city":"Chanhassen",
    "sg:classifiers":[
        {
            "category":"Banks & Credit Unions",
            "subcategory":"Bank",
            "type":"Services"
        }
    ],
    "sg:phone":"+1 952 974 2977",
    "sg:postcode":"55317",
    "sg:province":"MN",
    "sg:website":"www.mibank.com",
    "wof:name":"M & I Bank",
    "wof:placetype":"venue"
},
  "geometry": {"coordinates":[-93.539748,44.862042],"type":"Point"}
}