{
  "type": "Feature",
  "properties": {
    "iso:country":"US",
    "sg:address":"1700 12th St S",
    "sg:city":"Princeton",
    "sg:classifiers":[
        {
            "category":"Autos & Motor Vehicles",
            "subcategory":"Auto Supplies",
            "type":"Retail Goods"
        }
    ],
    "sg:phone":"+1 763 389 4440",
    "sg:postcode":"55371",
    "sg:province":"MN",
    "sg:tags":[
        "engine",
        "alternator",
        "generators-automotive",
        "starter"
    ],
    "wof:name":"Westling Manufacturing Co",
    "wof:placetype":"venue"
},
  "geometry": {"coordinates":[-93.598671,45.555431],"type":"Point"}
}