{
  "type": "Feature",
  "properties": {
    "iso:country":"US",
    "sg:address":"6513 227th Ave NE",
    "sg:city":"Stacy",
    "sg:classifiers":[
        {
            "category":"Professional",
            "type":"Services"
        }
    ],
    "sg:phone":"+1 651 462 8009",
    "sg:postcode":"55079",
    "sg:province":"MN",
    "wof:name":"Johns Handy Man Service",
    "wof:placetype":"venue"
},
  "geometry": {"coordinates":[-93.103105,45.381184],"type":"Point"}
}