{
  "type": "Feature",
  "properties": {
    "iso:country":"US",
    "sg:address":"10423 10th St SW",
    "sg:city":"Howard Lake",
    "sg:classifiers":[
        {
            "category":"Farming",
            "subcategory":"Dairy Farm",
            "type":"Manufacturing & Wholesale Goods"
        }
    ],
    "sg:phone":"+1 320 286 5839",
    "sg:postcode":"55349",
    "sg:province":"MN",
    "wof:name":"Joey Berg",
    "wof:placetype":"venue"
},
  "geometry": {"coordinates":[-94.102087,45.137677],"type":"Point"}
}