{
  "type": "Feature",
  "properties": {
    "addr:full":"602 S Front St Mankato MN 56001",
    "addr:housenumber":"602",
    "addr:postcode":"56001",
    "addr:street":"S Front St",
    "iso:country":"US",
    "sg:address":"602 S Front St",
    "sg:city":"Mankato",
    "sg:classifiers":[
        {
            "category":"Shopping",
            "subcategory":"Pharmacy",
            "type":"Retail Goods"
        }
    ],
    "sg:phone":"+1 507 387 3028",
    "sg:postcode":"56001",
    "sg:province":"MN",
    "wof:name":"Snyder Drug Store",
    "wof:placetype":"venue"
},
  "geometry": {"coordinates":[-94.00736999999999,44.162762],"type":"Point"}
}