{
  "type": "Feature",
  "properties": {
    "addr:full":"22050 Langford Ave Jordan MN 55352",
    "addr:housenumber":"22050",
    "addr:postcode":"55352",
    "addr:street":"Langford Ave",
    "iso:country":"US",
    "sg:address":"22050 Langford Ave",
    "sg:city":"Jordan",
    "sg:classifiers":[
        {
            "category":"Farming",
            "subcategory":"Farm",
            "type":"Manufacturing & Wholesale Goods"
        }
    ],
    "sg:phone":"+1 952 492 2251",
    "sg:postcode":"55352",
    "sg:province":"MN",
    "sg:tags":[
        "crop",
        "general"
    ],
    "wof:name":"William Busacker Farm",
    "wof:placetype":"venue"
},
  "geometry": {"coordinates":[-93.501746,44.629764],"type":"Point"}
}