{
  "type": "Feature",
  "properties": {
    "iso:country":"US",
    "sg:address":"29614 391st Ave",
    "sg:city":"Henderson",
    "sg:classifiers":[
        {
            "category":"Farming",
            "subcategory":"Farm",
            "type":"Manufacturing & Wholesale Goods"
        }
    ],
    "sg:phone":"+1 507 964 5350",
    "sg:postcode":"56044",
    "sg:province":"MN",
    "sg:tags":[
        "crop",
        "general"
    ],
    "wof:name":"Harlan Otto",
    "wof:placetype":"venue"
},
  "geometry": {"coordinates":[-94.049983,44.519614],"type":"Point"}
}