{
  "type": "Feature",
  "properties": {
    "iso:country":"US",
    "sg:address":"1098 Reponen Rd",
    "sg:city":"Cloquet",
    "sg:classifiers":[
        {
            "category":"Manufacturing",
            "subcategory":"Lumber",
            "type":"Manufacturing & Wholesale Goods"
        }
    ],
    "sg:phone":"+1 218 879 8767",
    "sg:postcode":"55720",
    "sg:province":"MN",
    "sg:tags":[
        "logging"
    ],
    "wof:name":"Berthiaume Logging",
    "wof:placetype":"venue"
},
  "geometry": {"coordinates":[-92.571456,46.69753],"type":"Point"}
}