{
  "type": "Feature",
  "properties": {
    "iso:country":"US",
    "sg:address":"49058 180th Ave",
    "sg:city":"Pine Island",
    "sg:classifiers":[
        {
            "category":"Farming",
            "subcategory":"Nursery",
            "type":"Manufacturing & Wholesale Goods"
        }
    ],
    "sg:phone":"+1 507 356 4041",
    "sg:postcode":"55963",
    "sg:province":"MN",
    "sg:tags":[
        "ornamental",
        "greenhouse",
        "supply"
    ],
    "wof:name":"Joel's Greenhouse",
    "wof:placetype":"venue"
},
  "geometry": {"coordinates":[-92.67072,44.226898],"type":"Point"}
}