{
  "type": "Feature",
  "properties": {
    "addr:full":"1600 Co Rd J W St Paul MN 55126",
    "addr:housenumber":"1600",
    "addr:postcode":"55126",
    "addr:street":"Co Rd J W",
    "iso:country":"US",
    "sg:address":"1600 Co Rd J W",
    "sg:city":"St Paul",
    "sg:classifiers":[
        {
            "category":"Real Estate",
            "subcategory":"Developer",
            "type":"Services"
        }
    ],
    "sg:phone":"+1 651 784 0961",
    "sg:postcode":"55126",
    "sg:province":"MN",
    "sg:tags":[
        "mobile",
        "home"
    ],
    "wof:name":"Tri-Park Investments",
    "wof:placetype":"venue"
},
  "geometry": {"coordinates":[-93.17349900000001,45.124251],"type":"Point"}
}