{
  "type": "Feature",
  "properties": {
    "iso:country":"US",
    "sg:address":"521 Jackson St",
    "sg:city":"St Paul",
    "sg:classifiers":[
        {
            "category":"Manufacturing",
            "subcategory":"Printing",
            "type":"Manufacturing & Wholesale Goods"
        }
    ],
    "sg:phone":"+1 651 222 7825",
    "sg:postcode":"55101",
    "sg:province":"MN",
    "sg:tags":[
        "screen",
        "commercial"
    ],
    "wof:name":"Lowertown Printing Company",
    "wof:placetype":"venue"
},
  "geometry": {"coordinates":[-93.094005,44.952738],"type":"Point"}
}