{
  "type": "Feature",
  "properties": {
    "addr:full":"3062 Cleveland Ave N Roseville MN 55113",
    "addr:housenumber":"3062",
    "addr:postcode":"55113",
    "addr:street":"Cleveland Ave N",
    "iso:country":"US",
    "sg:address":"3062 Cleveland Ave N",
    "sg:city":"Roseville",
    "sg:classifiers":[
        {
            "category":"Manufacturing",
            "subcategory":"Metals",
            "type":"Manufacturing & Wholesale Goods"
        }
    ],
    "sg:phone":"+1 651 633 1143",
    "sg:postcode":"55113",
    "sg:province":"MN",
    "sg:tags":[
        "finisher"
    ],
    "sg:website":"www.simoco-metalfinishing.com",
    "wof:name":"Simoco",
    "wof:placetype":"venue"
},
  "geometry": {"coordinates":[-93.187628,45.035622],"type":"Point"}
}