{
  "type": "Feature",
  "properties": {
    "addr:full":"901 Twelve Oaks Center Dr, Suite 934 Minneapolis MN 55391",
    "addr:housenumber":"901",
    "addr:postcode":"55391",
    "addr:street":"Twelve Oaks Center Dr Suite 934",
    "iso:country":"US",
    "sg:address":"901 Twelve Oaks Center Dr, Suite 934",
    "sg:city":"Minneapolis",
    "sg:classifiers":[
        {
            "category":"Professional",
            "subcategory":"Computer Services",
            "type":"Services"
        }
    ],
    "sg:postcode":"55391",
    "sg:province":"MN",
    "sg:tags":[
        "document-collaboration-approval-easy-track-changes-team-group-edit-editing-google-docs-buzzword-zoho-writer"
    ],
    "sg:website":"http://www.redliner.com",
    "wof:name":"Redliner",
    "wof:placetype":"venue"
},
  "geometry": {"coordinates":[-93.474571,44.972916],"type":"Point"}
}