{
  "type": "Feature",
  "properties": {
    "iso:country":"US",
    "sg:address":"10627 165th St W",
    "sg:city":"Lakeville",
    "sg:classifiers":[
        {
            "category":"Professional",
            "subcategory":"Accounting & Tax Preparation",
            "type":"Services"
        }
    ],
    "sg:phone":"+1 952 435 6630",
    "sg:postcode":"55044",
    "sg:province":"MN",
    "sg:tags":[
        "accountant",
        "payroll"
    ],
    "sg:website":"www.mattsonradziej.com",
    "wof:name":"Mattson & Radziej Ltd",
    "wof:placetype":"venue"
},
  "geometry": {"coordinates":[-93.280906,44.710261],"type":"Point"}
}