{
  "type": "Feature",
  "properties": {
    "iso:country":"US",
    "sg:address":"611 37th Ave S",
    "sg:city":"Moorhead",
    "sg:classifiers":[
        {
            "category":"Place Of Worship",
            "subcategory":"Church",
            "type":"Public Place"
        },
        {
            "category":"Place Of Worship",
            "type":"Public Place"
        },
        {
            "category":"Organizations",
            "subcategory":"Religious Organization",
            "type":"Services"
        }
    ],
    "sg:phone":"+1 218 233 7856",
    "sg:postcode":"56560",
    "sg:province":"MN",
    "sg:tags":[
        "churches-interdenominational",
        "churches-various",
        "denomination"
    ],
    "sg:website":"http://www.rrvcc.org",
    "wof:name":"Valley Christian Church",
    "wof:placetype":"venue"
},
  "geometry": {"coordinates":[-96.769852,46.83672],"type":"Point"}
}