{
  "type": "Feature",
  "properties": {
    "iso:country":"US",
    "sg:address":"2727 Leisure Ln",
    "sg:city":"Brainerd",
    "sg:classifiers":[
        {
            "category":"Travel",
            "subcategory":"Hotels & Motels",
            "type":"Entertainment"
        }
    ],
    "sg:phone":"+1 218 829 4524",
    "sg:postcode":"56401",
    "sg:province":"MN",
    "sg:tags":[
        "resort"
    ],
    "wof:name":"Noka Sippi Resorts",
    "wof:placetype":"venue"
},
  "geometry": {"coordinates":[-94.02814600000001,46.325785],"type":"Point"}
}