{
  "type": "Feature",
  "properties": {
    "iso:country":"US",
    "sg:address":"625 2nd Ave S Ste 408",
    "sg:city":"Minneapolis",
    "sg:classifiers":[
        {
            "category":"Travel",
            "subcategory":"Travel Agent",
            "type":"Entertainment"
        }
    ],
    "sg:phone":"+1 612 305 0025",
    "sg:postcode":"55402",
    "sg:province":"MN",
    "sg:tags":[
        "agency",
        "services-commercial"
    ],
    "sg:website":"http://www.newdepartures.com",
    "wof:name":"New Departures Travel",
    "wof:placetype":"venue"
},
  "geometry": {"coordinates":[-93.26888099999999,44.976509],"type":"Point"}
}