{
  "type": "Feature",
  "properties": {
    "addr:full":"1019 Co Rd 101 Minneapolis MN 55447",
    "addr:housenumber":"1019",
    "addr:postcode":"55447",
    "addr:street":"Co Rd 101",
    "iso:country":"US",
    "sg:address":"1019 Co Rd 101",
    "sg:city":"Minneapolis",
    "sg:classifiers":[
        {
            "category":"Professional",
            "subcategory":"Business Services",
            "type":"Services"
        }
    ],
    "sg:phone":"+1 612 338 4212",
    "sg:postcode":"55447",
    "sg:province":"MN",
    "sg:tags":[
        "buyer",
        "grain"
    ],
    "wof:name":"Quaker Oats",
    "wof:placetype":"venue"
},
  "geometry": {"coordinates":[-93.50219199999999,44.989592],"type":"Point"}
}