{
  "type": "Feature",
  "properties": {
    "iso:country":"US",
    "sg:address":"11450 Kingsborough Trl",
    "sg:city":"Cottage Grove",
    "sg:classifiers":[
        {
            "category":"Professional",
            "subcategory":"Research",
            "type":"Services"
        }
    ],
    "sg:phone":"+1 651 438 9154",
    "sg:postcode":"55016",
    "sg:province":"MN",
    "sg:tags":[
        "organization",
        "noncommercial"
    ],
    "wof:name":"Jill Cernohous",
    "wof:placetype":"venue"
},
  "geometry": {"coordinates":[-92.884101,44.78302],"type":"Point"}
}