{
  "type": "Feature",
  "properties": {
    "addr:full":"7689 Main St NE Minneapolis MN 55432",
    "addr:housenumber":"7689",
    "addr:postcode":"55432",
    "addr:street":"Main St Ne",
    "iso:country":"US",
    "sg:address":"7689 Main St NE",
    "sg:city":"Minneapolis",
    "sg:classifiers":[
        {
            "category":"Shopping",
            "subcategory":"Bicycles & Sporting Goods",
            "type":"Retail Goods"
        }
    ],
    "sg:phone":"+1 763 571 7234",
    "sg:postcode":"55432",
    "sg:province":"MN",
    "sg:tags":[
        "gun",
        "gunsmith"
    ],
    "wof:name":"Tiger Rifles & Shotguns",
    "wof:placetype":"venue"
},
  "geometry": {"coordinates":[-93.26813199999999,45.107033],"type":"Point"}
}