{
  "type": "Feature",
  "properties": {
    "addr:full":"205 Nynas Rd Esko MN 55733",
    "addr:housenumber":"205",
    "addr:postcode":"55733",
    "addr:street":"Nynas Rd",
    "iso:country":"US",
    "sg:address":"205 Nynas Rd",
    "sg:city":"Esko",
    "sg:classifiers":[
        {
            "category":"Freight",
            "type":"Transportation"
        }
    ],
    "sg:phone":"+1 218 879 4353",
    "sg:postcode":"55733",
    "sg:province":"MN",
    "sg:tags":[
        "operator",
        "local",
        "trucking"
    ],
    "wof:name":"John Halvorson Trucking",
    "wof:placetype":"venue"
},
  "geometry": {"coordinates":[-92.31487799999999,46.692065],"type":"Point"}
}