{
  "type": "Feature",
  "properties": {
    "addr:full":"832 3rd Ave NE Byron MN 55920",
    "addr:housenumber":"832",
    "addr:postcode":"55920",
    "addr:street":"3Rd Ave Ne",
    "iso:country":"US",
    "sg:address":"832 3rd Ave NE",
    "sg:city":"Byron",
    "sg:classifiers":[
        {
            "category":"Social Services",
            "subcategory":"Child Care",
            "type":"Services"
        }
    ],
    "sg:phone":"+1 507 775 6436",
    "sg:postcode":"55920",
    "sg:province":"MN",
    "sg:tags":[
        "day",
        "provider"
    ],
    "wof:name":"Reinold L Nelson",
    "wof:placetype":"venue"
},
  "geometry": {"coordinates":[-92.640081,44.039833],"type":"Point"}
}