{
  "type": "Feature",
  "properties": {
    "addr:full":"8249 Oakwood Dr Becker MN 55308",
    "addr:housenumber":"8249",
    "addr:postcode":"55308",
    "addr:street":"Oakwood Dr",
    "iso:country":"US",
    "sg:address":"8249 Oakwood Dr",
    "sg:city":"Becker",
    "sg:classifiers":[
        {
            "category":"Wholesale",
            "subcategory":"Machinery & Supplies",
            "type":"Manufacturing & Wholesale Goods"
        }
    ],
    "sg:phone":"+1 763 262 8050",
    "sg:postcode":"55308",
    "sg:province":"MN",
    "sg:tags":[
        "equipment",
        "irrigation",
        "system"
    ],
    "wof:name":"Greenland Irrigation",
    "wof:placetype":"venue"
},
  "geometry": {"coordinates":[-93.89917699999999,45.450421],"type":"Point"}
}