{
  "type": "Feature",
  "properties": {
    "iso:country":"US",
    "sg:address":"1029 Paul Pkwy NE",
    "sg:city":"Minneapolis",
    "sg:classifiers":[
        {
            "category":"Building & Trades",
            "subcategory":"Construction",
            "type":"Services"
        }
    ],
    "sg:phone":"+1 763 754 8774",
    "sg:postcode":"55434",
    "sg:province":"MN",
    "sg:tags":[
        "floor",
        "laying",
        "contractor"
    ],
    "wof:name":"Ram Flooring",
    "wof:placetype":"venue"
},
  "geometry": {"coordinates":[-93.24406500000001,45.193016],"type":"Point"}
}