{
  "type": "Feature",
  "properties": {
    "iso:country":"US",
    "sg:address":"27385 114th St",
    "sg:city":"Zimmerman",
    "sg:classifiers":[
        {
            "category":"Building & Trades",
            "subcategory":"Construction",
            "type":"Services"
        }
    ],
    "sg:phone":"+1 763 856 4508",
    "sg:postcode":"55398",
    "sg:province":"MN",
    "sg:tags":[
        "excavation",
        "contractor"
    ],
    "wof:name":"Twin Pines Earthworks",
    "wof:placetype":"venue"
},
  "geometry": {"coordinates":[-93.55866899999999,45.467605],"type":"Point"}
}