{
  "type": "Feature",
  "properties": {
    "iso:country":"US",
    "sg:address":"1340 Warren St",
    "sg:city":"Mankato",
    "sg:classifiers":[
        {
            "category":"Real Estate",
            "subcategory":"Real Estate Operator",
            "type":"Services"
        }
    ],
    "sg:phone":"+1 507 387 5426",
    "sg:postcode":"56001",
    "sg:province":"MN",
    "sg:tags":[
        "apartment"
    ],
    "wof:name":"Campus View Townhomes",
    "wof:placetype":"venue"
},
  "geometry": {"coordinates":[-93.99427799999999,44.149457],"type":"Point"}
}