{
  "type": "Feature",
  "properties": {
    "addr:full":"210 N Broadway Crookston MN 56716",
    "addr:housenumber":"210",
    "addr:postcode":"56716",
    "addr:street":"N Broadway",
    "iso:country":"US",
    "sg:address":"210 N Broadway",
    "sg:city":"Crookston",
    "sg:classifiers":[
        {
            "category":"Real Estate",
            "subcategory":"Real Estate Services",
            "type":"Services"
        }
    ],
    "sg:phone":"+1 218 281 1191",
    "sg:postcode":"56716",
    "sg:province":"MN",
    "wof:name":"Strander Abstract Inc",
    "wof:placetype":"venue"
},
  "geometry": {"coordinates":[-96.605395,47.775479],"type":"Point"}
}