{
  "type": "Feature",
  "properties": {
    "addr:full":"5478 Mountain Iron Dr Virginia MN 55792",
    "addr:housenumber":"5478",
    "addr:postcode":"55792",
    "addr:street":"Mountain Iron Dr",
    "iso:country":"US",
    "sg:address":"5478 Mountain Iron Dr",
    "sg:city":"Virginia",
    "sg:classifiers":[
        {
            "category":"Building & Trades",
            "subcategory":"Construction",
            "type":"Services"
        }
    ],
    "sg:phone":"+1 218 741 7506",
    "sg:postcode":"55792",
    "sg:province":"MN",
    "sg:tags":[
        "contractor"
    ],
    "wof:name":"Star Homes and Builders",
    "wof:placetype":"venue"
},
  "geometry": {"coordinates":[-92.561694,47.514872],"type":"Point"}
}