{
  "type": "Feature",
  "properties": {
    "iso:country":"US",
    "sg:address":"4855 Babcock Trl",
    "sg:city":"Inver Grove Heights",
    "sg:classifiers":[
        {
            "category":"Manufacturing",
            "subcategory":"Food",
            "type":"Manufacturing & Wholesale Goods"
        }
    ],
    "sg:phone":"+1 651 455 6374",
    "sg:postcode":"55077",
    "sg:province":"MN",
    "sg:tags":[
        "mix",
        "concentrate",
        "drink"
    ],
    "wof:name":"Bloody Mary Maker",
    "wof:placetype":"venue"
},
  "geometry": {"coordinates":[-93.06634200000001,44.878675],"type":"Point"}
}