{
  "type": "Feature",
  "properties": {
    "addr:full":"849 University Ave W St Paul MN 55104",
    "addr:housenumber":"849",
    "addr:postcode":"55104",
    "addr:street":"University Ave W",
    "iso:country":"US",
    "sg:address":"849 University Ave W",
    "sg:city":"St Paul",
    "sg:classifiers":[
        {
            "category":"Shopping",
            "subcategory":"Clothing, Apparel, & Fashions",
            "type":"Retail Goods"
        }
    ],
    "sg:phone":"+1 651 278 0202",
    "sg:postcode":"55104",
    "sg:province":"MN",
    "wof:name":"Unique Fashions",
    "wof:placetype":"venue"
},
  "geometry": {"coordinates":[-93.13499899999999,44.955797],"type":"Point"}
}