{
  "type": "Feature",
  "properties": {
    "addr:full":"739 Willow St Faribault MN 55021",
    "addr:housenumber":"739",
    "addr:postcode":"55021",
    "addr:street":"Willow St",
    "iso:country":"US",
    "sg:address":"739 Willow St",
    "sg:city":"Faribault",
    "sg:classifiers":[
        {
            "category":"Shopping",
            "subcategory":"Gifts & Souvenirs",
            "type":"Retail Goods"
        }
    ],
    "sg:phone":"+1 507 334 4404",
    "sg:postcode":"55021",
    "sg:province":"MN",
    "sg:tags":[
        "shop",
        "sewing"
    ],
    "wof:name":"Annie Belle Creations",
    "wof:placetype":"venue"
},
  "geometry": {"coordinates":[-93.271203,44.283321],"type":"Point"}
}