{
  "type": "Feature",
  "properties": {
    "iso:country":"US",
    "sg:address":"5027 Miller Trunk Hwy",
    "sg:city":"Hermantown",
    "sg:classifiers":[
        {
            "category":"Professional",
            "subcategory":"Detective & Security Services",
            "type":"Services"
        }
    ],
    "sg:phone":"+1 218 729 6697",
    "sg:postcode":"55811",
    "sg:province":"MN",
    "sg:tags":[
        "information",
        "bureau"
    ],
    "wof:name":"Noaa National Weather Svc",
    "wof:placetype":"venue"
},
  "geometry": {"coordinates":[-92.209007,46.835861],"type":"Point"}
}