{
  "type": "Feature",
  "properties": {
    "iso:country":"US",
    "sg:address":"890 18th Ave SE",
    "sg:city":"Minneapolis",
    "sg:classifiers":[
        {
            "category":"Real Estate",
            "subcategory":"Real Estate Agent",
            "type":"Services"
        }
    ],
    "sg:phone":"+1 612 379 3474",
    "sg:postcode":"55414",
    "sg:province":"MN",
    "wof:name":"Re/Max",
    "wof:placetype":"venue"
},
  "geometry": {"coordinates":[-93.226854,44.98653],"type":"Point"}
}