{
  "type": "Feature",
  "properties": {
    "addr:full":"3146 Viking Blvd NW Cedar MN 55011",
    "addr:housenumber":"3146",
    "addr:postcode":"55011",
    "addr:street":"Viking Blvd Nw Cedar",
    "iso:country":"US",
    "sg:address":"3146 Viking Blvd NW",
    "sg:city":"Cedar",
    "sg:classifiers":[
        {
            "category":"Food & Beverages",
            "subcategory":"Liquor & Beverages",
            "type":"Retail Goods"
        }
    ],
    "sg:phone":"+1 763 753 9280",
    "sg:postcode":"55011",
    "sg:province":"MN",
    "wof:name":"C T Liquor Store",
    "wof:placetype":"venue"
},
  "geometry": {"coordinates":[-93.345555,45.319877],"type":"Point"}
}