{
  "type": "Feature",
  "properties": {
    "addr:full":"3235 Vicksburg Ln N # F Minneapolis MN 55447",
    "addr:housenumber":"3235",
    "addr:postcode":"55447",
    "addr:street":"Vicksburg Ln N # F",
    "iso:country":"US",
    "sg:address":"3235 Vicksburg Ln N # F",
    "sg:city":"Minneapolis",
    "sg:classifiers":[
        {
            "category":"Restaurant",
            "type":"Food & Drink"
        }
    ],
    "sg:phone":"+1 763 398 7505",
    "sg:postcode":"55447",
    "sg:province":"MN",
    "sg:tags":[
        "chinese"
    ],
    "wof:name":"Chin's",
    "wof:placetype":"venue"
},
  "geometry": {"coordinates":[-93.481917,45.01663],"type":"Point"}
}