{
  "type": "Feature",
  "properties": {
    "addr:full":"1700 Hwy 36 W Roseville MN 55113",
    "addr:housenumber":"1700",
    "addr:postcode":"55113",
    "addr:street":"Hwy 36 W",
    "iso:country":"US",
    "sg:address":"1700 Hwy 36 W",
    "sg:city":"Roseville",
    "sg:classifiers":[
        {
            "category":"Social Services",
            "type":"Services"
        }
    ],
    "sg:phone":"+1 651 633 5347",
    "sg:postcode":"55113",
    "sg:province":"MN",
    "sg:tags":[
        "counselor",
        "marriage",
        "family"
    ],
    "wof:name":"AAMFT-American Assn",
    "wof:placetype":"venue"
},
  "geometry": {"coordinates":[-93.171706,45.010265],"type":"Point"}
}