{
  "type": "Feature",
  "properties": {
    "iso:country":"US",
    "sg:address":"1910 Co Rd B W",
    "sg:city":"Saint Paul",
    "sg:classifiers":[
        {
            "category":"Organizations",
            "subcategory":"Professional Association",
            "type":"Services"
        }
    ],
    "sg:phone":"+1 651 628 0023",
    "sg:postcode":"55113",
    "sg:province":"MN",
    "wof:name":"Twin Cities Dst Dietc Assn",
    "wof:placetype":"venue"
},
  "geometry": {"coordinates":[-93.18086700000001,45.006058],"type":"Point"}
}