{
  "type": "Feature",
  "properties": {
    "addr:full":"8008 Minnetonka Blvd Minneapolis MN 55426",
    "addr:housenumber":"8008",
    "addr:postcode":"55426",
    "addr:street":"Minnetonka Blvd",
    "iso:country":"US",
    "sg:address":"8008 Minnetonka Blvd",
    "sg:city":"Minneapolis",
    "sg:classifiers":[
        {
            "category":"Shopping",
            "subcategory":"Pawn Shop",
            "type":"Retail Goods"
        }
    ],
    "sg:phone":"+1 952 920 1588",
    "sg:postcode":"55426",
    "sg:province":"MN",
    "sg:tags":[
        "pawnbroker"
    ],
    "wof:name":"Excel Pawn",
    "wof:placetype":"venue"
},
  "geometry": {"coordinates":[-93.38125599999999,44.94944],"type":"Point"}
}