{
  "type": "Feature",
  "properties": {
    "addr:full":"514 Central Ave N Faribault MN 55021",
    "addr:housenumber":"514",
    "addr:postcode":"55021",
    "addr:street":"Central Ave N",
    "iso:country":"US",
    "sg:address":"514 Central Ave N",
    "sg:city":"Faribault",
    "sg:classifiers":[
        {
            "category":"Manufacturing",
            "subcategory":"Printing",
            "type":"Manufacturing & Wholesale Goods"
        }
    ],
    "sg:phone":"+1 507 333 3100",
    "sg:postcode":"55021",
    "sg:province":"MN",
    "sg:tags":[
        "newspaper"
    ],
    "wof:name":"Faribault Daily News",
    "wof:placetype":"venue"
},
  "geometry": {"coordinates":[-93.268497,44.296847],"type":"Point"}
}