{
  "type": "Feature",
  "properties": {
    "iso:country":"US",
    "sg:address":"10108 Abbott Ave S",
    "sg:city":"Minneapolis",
    "sg:classifiers":[
        {
            "category":"Wholesale",
            "subcategory":"Durable Goods & Equipment",
            "type":"Manufacturing & Wholesale Goods"
        }
    ],
    "sg:phone":"+1 952 831 0229",
    "sg:postcode":"55431",
    "sg:province":"MN",
    "sg:tags":[
        "representative",
        "manufacturer"
    ],
    "wof:name":"E C Electronic Sales",
    "wof:placetype":"venue"
},
  "geometry": {"coordinates":[-93.323362,44.821267],"type":"Point"}
}