{
  "type": "Feature",
  "properties": {
    "iso:country":"US",
    "sg:address":"204 W Hatting St",
    "sg:city":"Luverne",
    "sg:classifiers":[
        {
            "category":"Freight",
            "type":"Transportation"
        }
    ],
    "sg:phone":"+1 507 283 4639",
    "sg:postcode":"56156",
    "sg:province":"MN",
    "sg:tags":[
        "operator",
        "trucking"
    ],
    "wof:name":"Christensen's Trucking",
    "wof:placetype":"venue"
},
  "geometry": {"coordinates":[-96.211674,43.645567],"type":"Point"}
}