{
  "type": "Feature",
  "properties": {
    "iso:country":"US",
    "sg:address":"125 W Lincoln Ave",
    "sg:city":"Fergus Falls",
    "sg:classifiers":[
        {
            "category":"Government",
            "subcategory":"Office",
            "type":"Public Place"
        },
        {
            "category":"Social Services",
            "type":"Services"
        }
    ],
    "sg:phone":"+1 218 739 7565",
    "sg:postcode":"56537",
    "sg:province":"MN",
    "sg:tags":[
        "disabled",
        "state",
        "program",
        "rehabilitation"
    ],
    "wof:name":"Rehabilitation Services Dept",
    "wof:placetype":"venue"
},
  "geometry": {"coordinates":[-96.07450300000001,46.283423],"type":"Point"}
}