{
  "type": "Feature",
  "properties": {
    "addr:full":"20920 Buchanan St NE Cedar MN 55011",
    "addr:housenumber":"20920",
    "addr:postcode":"55011",
    "addr:street":"Buchanan St Ne Cedar",
    "iso:country":"US",
    "sg:address":"20920 Buchanan St NE",
    "sg:city":"Cedar",
    "sg:classifiers":[
        {
            "category":"Building & Trades",
            "subcategory":"Construction",
            "type":"Services"
        }
    ],
    "sg:phone":"+1 763 434 8333",
    "sg:postcode":"55011",
    "sg:province":"MN",
    "sg:tags":[
        "house"
    ],
    "wof:name":"TW Builders Inc",
    "wof:placetype":"venue"
},
  "geometry": {"coordinates":[-93.242256,45.349956],"type":"Point"}
}