{
  "type": "Feature",
  "properties": {
    "iso:country":"US",
    "sg:address":"1000 E 146th St Ste 121",
    "sg:city":"Burnsville",
    "sg:classifiers":[
        {
            "category":"Communications",
            "type":"Services"
        }
    ],
    "sg:phone":"+1 952 953 9533",
    "sg:postcode":"55337",
    "sg:province":"MN",
    "sg:tags":[
        "web",
        "design"
    ],
    "sg:website":"www.audnet.com",
    "wof:name":"Audnet Inc",
    "wof:placetype":"venue"
},
  "geometry": {"coordinates":[-93.26096200000001,44.73907],"type":"Point"}
}