{
  "type": "Feature",
  "properties": {
    "iso:country":"US",
    "sg:address":"36066 Co Rd 66",
    "sg:city":"Crosslake",
    "sg:classifiers":[
        {
            "category":"Shopping",
            "type":"Retail Goods"
        }
    ],
    "sg:phone":"+1 218 692 5331",
    "sg:postcode":"56442",
    "sg:province":"MN",
    "sg:tags":[
        "equipment",
        "merchandise"
    ],
    "wof:name":"North Central Medical Supply",
    "wof:placetype":"venue"
},
  "geometry": {"coordinates":[-94.108724,46.675861],"type":"Point"}
}