{
  "type": "Feature",
  "properties": {
    "iso:country":"US",
    "sg:address":"402 1st Ave NW",
    "sg:city":"Dodge Center",
    "sg:classifiers":[
        {
            "category":"Food & Beverages",
            "subcategory":"Groceries & Convenience Stores",
            "type":"Retail Goods"
        }
    ],
    "sg:phone":"+1 507 374 2109",
    "sg:postcode":"55927",
    "sg:province":"MN",
    "sg:tags":[
        "product"
    ],
    "wof:name":"Watkins Products",
    "wof:placetype":"venue"
},
  "geometry": {"coordinates":[-92.856303,44.032401],"type":"Point"}
}