{
  "type": "Feature",
  "properties": {
    "addr:full":"6350 S Thunder Lake Dr NE Remer MN 56672",
    "addr:housenumber":"6350",
    "addr:postcode":"56672",
    "addr:street":"S Thunder Lake Dr Ne",
    "iso:country":"US",
    "sg:address":"6350 S Thunder Lake Dr NE",
    "sg:city":"Remer",
    "sg:classifiers":[
        {
            "category":"Building & Trades",
            "subcategory":"Landscaping Services",
            "type":"Services"
        }
    ],
    "sg:phone":"+1 218 566 1311",
    "sg:postcode":"56672",
    "sg:province":"MN",
    "sg:tags":[
        "lawn",
        "maintenance",
        "grounds"
    ],
    "wof:name":"Thunder Lake Lawn Service",
    "wof:placetype":"venue"
},
  "geometry": {"coordinates":[-93.95946499999999,46.92979],"type":"Point"}
}