{
  "type": "Feature",
  "properties": {
    "addr:full":"5217 James Ave S Minneapolis MN 55419",
    "addr:housenumber":"5217",
    "addr:postcode":"55419",
    "addr:street":"James Ave S",
    "iso:country":"US",
    "sg:address":"5217 James Ave S",
    "sg:city":"Minneapolis",
    "sg:classifiers":[
        {
            "category":"Real Estate",
            "subcategory":"Architect",
            "type":"Services"
        }
    ],
    "sg:phone":"+1 612 926 2424",
    "sg:postcode":"55419",
    "sg:province":"MN",
    "wof:name":"Newland Architecture",
    "wof:placetype":"venue"
},
  "geometry": {"coordinates":[-93.30090300000001,44.9081],"type":"Point"}
}