{
  "type": "Feature",
  "properties": {
    "iso:country":"US",
    "sg:address":"35 Pokegama Ave W",
    "sg:city":"Henriette",
    "sg:classifiers":[
        {
            "category":"Professional",
            "subcategory":"Business Services",
            "type":"Services"
        }
    ],
    "sg:phone":"+1 320 679 2704",
    "sg:postcode":"55036",
    "sg:province":"MN",
    "wof:name":"Ebiz Knowledge Bank",
    "wof:placetype":"venue"
},
  "geometry": {"coordinates":[-93.118731,45.871924],"type":"Point"}
}