{
  "type": "Feature",
  "properties": {
    "iso:country":"US",
    "sg:address":"2444 Enterprise Dr",
    "sg:city":"St Paul",
    "sg:classifiers":[
        {
            "category":"Restaurant",
            "type":"Food & Drink"
        }
    ],
    "sg:phone":"+1 651 405 3070",
    "sg:postcode":"55120",
    "sg:province":"MN",
    "wof:name":"Rain Forest Cafe Dist",
    "wof:placetype":"venue"
},
  "geometry": {"coordinates":[-93.162964,44.867843],"type":"Point"}
}