{
  "type": "Feature",
  "properties": {
    "iso:country":"US",
    "sg:address":"800 Hennepin Ave",
    "sg:city":"Minneapolis",
    "sg:classifiers":[
        {
            "category":"Professional",
            "type":"Services"
        }
    ],
    "sg:phone":"+1 612 332 6651",
    "sg:postcode":"55403",
    "sg:province":"MN",
    "wof:name":"City Place",
    "wof:placetype":"venue"
},
  "geometry": {"coordinates":[-93.27697499999999,44.976417],"type":"Point"}
}