{
  "type": "Feature",
  "properties": {
    "addr:full":"54237 192nd St Mankato MN 56001",
    "addr:housenumber":"54237",
    "addr:postcode":"56001",
    "addr:street":"192Nd St",
    "iso:country":"US",
    "sg:address":"54237 192nd St",
    "sg:city":"Mankato",
    "sg:classifiers":[
        {
            "category":"Building & Trades",
            "subcategory":"Construction",
            "type":"Services"
        }
    ],
    "sg:phone":"+1 507 278 3991",
    "sg:postcode":"56001",
    "sg:province":"MN",
    "sg:tags":[
        "house"
    ],
    "wof:name":"Novel Homes",
    "wof:placetype":"venue"
},
  "geometry": {"coordinates":[-94.10686200000001,44.101104],"type":"Point"}
}