{
  "type": "Feature",
  "properties": {
    "iso:country":"US",
    "sg:address":"13005 Main St",
    "sg:city":"Rogers",
    "sg:classifiers":[
        {
            "category":"Professional",
            "subcategory":"Lawyer & Legal Services",
            "type":"Services"
        }
    ],
    "sg:phone":"+1 763 428 2297",
    "sg:postcode":"55374",
    "sg:province":"MN",
    "wof:name":"Robert M Pearson",
    "wof:placetype":"venue"
},
  "geometry": {"coordinates":[-93.55266399999999,45.190035],"type":"Point"}
}