{
  "type": "Feature",
  "properties": {
    "iso:country":"US",
    "sg:address":"12751 Co Rd 5",
    "sg:city":"Burnsville",
    "sg:classifiers":[
        {
            "category":"Professional",
            "subcategory":"Accounting & Tax Preparation",
            "type":"Services"
        }
    ],
    "sg:phone":"+1 952 808 7933",
    "sg:postcode":"55337",
    "sg:province":"MN",
    "sg:tags":[
        "return",
        "filing"
    ],
    "wof:name":"New Century Tax Professionals",
    "wof:placetype":"venue"
},
  "geometry": {"coordinates":[-93.304751,44.771621],"type":"Point"}
}