{
  "type": "Feature",
  "properties": {
    "iso:country":"US",
    "sg:address":"3825 42nd Ave S",
    "sg:city":"Minneapolis",
    "sg:classifiers":[
        {
            "category":"Shopping",
            "subcategory":"Computers & Home Electronics",
            "type":"Retail Goods"
        }
    ],
    "sg:phone":"+1 952 220 1912",
    "sg:postcode":"55406",
    "sg:province":"MN",
    "wof:name":"Protocol Computers",
    "wof:placetype":"venue"
},
  "geometry": {"coordinates":[-93.21268499999999,44.932896],"type":"Point"}
}