{
  "type": "Feature",
  "properties": {
    "iso:country":"US",
    "sg:address":"650 3rd Ave S",
    "sg:city":"Minneapolis",
    "sg:classifiers":[
        {
            "category":"Professional",
            "subcategory":"Lawyer & Legal Services",
            "type":"Services"
        }
    ],
    "sg:phone":"+1 612 436 1121",
    "sg:postcode":"55404",
    "sg:province":"MN",
    "sg:tags":[
        "attorney"
    ],
    "wof:name":"Heins Mills & Olson",
    "wof:placetype":"venue"
},
  "geometry": {"coordinates":[-93.267912,44.975677],"type":"Point"}
}