{
  "type": "Feature",
  "properties": {
    "addr:full":"13930 60th Ave N Minneapolis MN 55446",
    "addr:housenumber":"13930",
    "addr:postcode":"55446",
    "addr:street":"60Th Ave N",
    "iso:country":"US",
    "sg:address":"13930 60th Ave N",
    "sg:city":"Minneapolis",
    "sg:classifiers":[
        {
            "category":"Professional",
            "subcategory":"Management & Consulting",
            "type":"Services"
        }
    ],
    "sg:phone":"+1 763 383 1777",
    "sg:postcode":"55446",
    "sg:province":"MN",
    "wof:name":"Truck Care Network",
    "wof:placetype":"venue"
},
  "geometry": {"coordinates":[-93.456007,45.062816],"type":"Point"}
}