{
  "type": "Feature",
  "properties": {
    "addr:full":"5217 Westmill Rd Minnetonka MN 55345",
    "addr:housenumber":"5217",
    "addr:postcode":"55345",
    "addr:street":"Westmill Rd",
    "iso:country":"US",
    "sg:address":"5217 Westmill Rd",
    "sg:city":"Minnetonka",
    "sg:classifiers":[
        {
            "category":"Home & Garden",
            "subcategory":"Building Materials",
            "type":"Retail Goods"
        },
        {
            "category":"Building & Trades",
            "subcategory":"Construction",
            "type":"Services"
        }
    ],
    "sg:phone":"+1 952 934 9494",
    "sg:postcode":"55345",
    "sg:province":"MN",
    "sg:tags":[
        "insulation",
        "equipment",
        "supply",
        "contractor"
    ],
    "sg:website":"http://www.krollassociates.biz",
    "wof:name":"Kroll WM H O & Associates Inc",
    "wof:placetype":"venue"
},
  "geometry": {"coordinates":[-93.49823499999999,44.90894],"type":"Point"}
}