{
  "type": "Feature",
  "properties": {
    "addr:full":"1091 W Pierce Butler Rte St Paul MN 55104",
    "addr:housenumber":"1091",
    "addr:postcode":"55104",
    "addr:street":"W Pierce;Rte St Paul",
    "iso:country":"US",
    "sg:address":"1091 W Pierce Butler Rte",
    "sg:city":"St Paul",
    "sg:classifiers":[
        {
            "category":"Wholesale",
            "subcategory":"Vending Machines",
            "type":"Manufacturing & Wholesale Goods"
        }
    ],
    "sg:phone":"+1 651 488 0515",
    "sg:postcode":"55104",
    "sg:province":"MN",
    "wof:name":"Canteen Corp",
    "wof:placetype":"venue"
},
  "geometry": {"coordinates":[-93.145056,44.966526],"type":"Point"}
}