{
  "type": "Feature",
  "properties": {
    "addr:full":"400 Kristin Dr NW Rochester MN 55901",
    "addr:housenumber":"400",
    "addr:postcode":"55901",
    "addr:street":"Kristin Dr Nw",
    "iso:country":"US",
    "sg:address":"400 Kristin Dr NW",
    "sg:city":"Rochester",
    "sg:classifiers":[
        {
            "category":"Real Estate",
            "subcategory":"Real Estate Agent",
            "type":"Services"
        }
    ],
    "sg:phone":"+1 507 252 1615",
    "sg:postcode":"55901",
    "sg:province":"MN",
    "sg:tags":[
        "appraiser"
    ],
    "wof:name":"Warfield Messner Appraisals",
    "wof:placetype":"venue"
},
  "geometry": {"coordinates":[-92.462361,44.096101],"type":"Point"}
}