{
  "type": "Feature",
  "properties": {
    "addr:full":"9865 Norma Ln Saint Paul MN 55125",
    "addr:housenumber":"9865",
    "addr:postcode":"55125",
    "addr:street":"Norma Ln",
    "iso:country":"US",
    "sg:address":"9865 Norma Ln",
    "sg:city":"Saint Paul",
    "sg:classifiers":[
        {
            "category":"Retail",
            "subcategory":"Auto Repair",
            "type":"Services"
        }
    ],
    "sg:phone":"+1 651 501 7700",
    "sg:postcode":"55125",
    "sg:province":"MN",
    "sg:tags":[
        "general"
    ],
    "wof:name":"Rainier Capital Inc",
    "wof:placetype":"venue"
},
  "geometry": {"coordinates":[-92.90537399999999,44.946776],"type":"Point"}
}