{
  "type": "Feature",
  "properties": {
    "addr:full":"12555 Ulysses St NE Minneapolis MN 55434",
    "addr:postcode":"12555;55434",
    "addr:street":"Ulysses St Ne",
    "iso:country":"US",
    "sg:address":"12555 Ulysses St NE",
    "sg:city":"Minneapolis",
    "sg:classifiers":[
        {
            "category":"Coffee & Tea",
            "type":"Food & Drink"
        }
    ],
    "sg:menulink":"http://www.allmenus.com/mn/blaine/119661-starbucks-coffee/menu/",
    "sg:phone":"+1 763 862 9910",
    "sg:postcode":"55434",
    "sg:province":"MN",
    "sg:tags":[
        "american"
    ],
    "wof:name":"Starbucks Coffee",
    "wof:placetype":"venue"
},
  "geometry": {"coordinates":[-93.237612,45.197863],"type":"Point"}
}