{
  "type": "Feature",
  "properties": {
    "addr:full":"13090 Alabama Ave S Savage MN 55378",
    "addr:housenumber":"13090",
    "addr:postcode":"55378",
    "addr:street":"Alabama Ave S",
    "iso:country":"US",
    "sg:address":"13090 Alabama Ave S",
    "sg:city":"Savage",
    "sg:classifiers":[
        {
            "category":"Education",
            "subcategory":"Library",
            "type":"Public Place"
        }
    ],
    "sg:phone":"+1 952 707 1760",
    "sg:postcode":"55378",
    "sg:province":"MN",
    "sg:website":"www.scott.lib.mn.us",
    "wof:name":"Scott County Library Syst Admn",
    "wof:placetype":"venue"
},
  "geometry": {"coordinates":[-93.356773,44.763932],"type":"Point"}
}