{
  "type": "Feature",
  "properties": {
    "iso:country":"US",
    "sg:address":"213 N Oak St",
    "sg:city":"Lake City",
    "sg:classifiers":[
        {
            "category":"Organizations",
            "subcategory":"Religious Organization",
            "type":"Services"
        }
    ],
    "sg:phone":"+1 651 345 3625",
    "sg:postcode":"55041",
    "sg:province":"MN",
    "wof:name":"United Methodist Church",
    "wof:placetype":"venue"
},
  "geometry": {"coordinates":[-92.27062100000001,44.449139],"type":"Point"}
}