{
  "type": "Feature",
  "properties": {
    "addr:full":"7300 Metro Blvd Ste 450 Minneapolis MN 55439",
    "addr:postcode":"7300;55439",
    "addr:street":"Metro Blvd Ste 450",
    "iso:country":"US",
    "sg:address":"7300 Metro Blvd Ste 450",
    "sg:city":"Minneapolis",
    "sg:classifiers":[
        {
            "category":"Banks & Credit Unions",
            "subcategory":"Investment Brokerage",
            "type":"Services"
        },
        {
            "category":"Insurance",
            "subcategory":"Hazard Insurance",
            "type":"Services"
        },
        {
            "category":"Banks & Credit Unions",
            "subcategory":"Financial Services",
            "type":"Services"
        },
        {
            "category":"Insurance",
            "subcategory":"Health Insurance",
            "type":"Services"
        }
    ],
    "sg:phone":"+1 952 806 4300",
    "sg:postcode":"55439",
    "sg:province":"MN",
    "sg:tags":[
        "advisory",
        "retirement",
        "profit",
        "annuity",
        "sharing",
        "benefit",
        "planning",
        "plan",
        "employee",
        "pension"
    ],
    "sg:website":"http://www.tsc401k.com",
    "wof:name":"TSC - Tax Sheltered Compensation Inc",
    "wof:placetype":"venue"
},
  "geometry": {"coordinates":[-93.351122,44.87195],"type":"Point"}
}