{
  "type": "Feature",
  "properties": {
    "iso:country":"US",
    "sg:address":"9650 Flintlock Trl",
    "sg:city":"Chanhassen",
    "sg:classifiers":[
        {
            "category":"Manufacturing",
            "subcategory":"Metals",
            "type":"Manufacturing & Wholesale Goods"
        }
    ],
    "sg:phone":"+1 952 445 6826",
    "sg:postcode":"55317",
    "sg:province":"MN",
    "sg:tags":[
        "stampings",
        "mfg"
    ],
    "wof:name":"Baklund Machine Company",
    "wof:placetype":"venue"
},
  "geometry": {"coordinates":[-93.54597200000001,44.829142],"type":"Point"}
}