{
  "type": "Feature",
  "properties": {
    "iso:country":"US",
    "sg:address":"567 Shoreview Park Rd",
    "sg:city":"St Paul",
    "sg:classifiers":[
        {
            "category":"Wholesale",
            "subcategory":"Durable Goods & Equipment",
            "type":"Manufacturing & Wholesale Goods"
        }
    ],
    "sg:phone":"+1 651 486 0055",
    "sg:postcode":"55126",
    "sg:province":"MN",
    "sg:tags":[
        "gaming",
        "supply"
    ],
    "sg:website":"www.3diamond.com",
    "wof:name":"3 Diamond Corp",
    "wof:placetype":"venue"
},
  "geometry": {"coordinates":[-93.124568,45.053184],"type":"Point"}
}