{
  "type": "Feature",
  "properties": {
    "iso:country":"US",
    "sg:address":"625 30th Ave S",
    "sg:city":"Moorhead",
    "sg:classifiers":[
        {
            "category":"Restaurant",
            "type":"Food & Drink"
        }
    ],
    "sg:phone":"+1 218 287 8412",
    "sg:postcode":"56560",
    "sg:province":"MN",
    "wof:name":"Snap Dragon",
    "wof:placetype":"venue"
},
  "geometry": {"coordinates":[-96.770988,46.84401],"type":"Point"}
}