{
  "type": "Feature",
  "properties": {
    "iso:country":"US",
    "sg:address":"310 3rd Ave NW",
    "sg:city":"Milaca",
    "sg:classifiers":[
        {
            "category":"Organizations",
            "subcategory":"Religious Organization",
            "type":"Services"
        }
    ],
    "sg:phone":"+1 320 983 6325",
    "sg:postcode":"56353",
    "sg:province":"MN",
    "sg:website":"www.milacaumc.com",
    "wof:name":"Milaca United Methodist Church",
    "wof:placetype":"venue"
},
  "geometry": {"coordinates":[-93.655475,45.758097],"type":"Point"}
}