{
  "type": "Feature",
  "properties": {
    "addr:full":"203 10th St Windom MN 56101",
    "addr:housenumber":"203",
    "addr:postcode":"56101",
    "addr:street":"10Th St",
    "iso:country":"US",
    "sg:address":"203 10th St",
    "sg:city":"Windom",
    "sg:classifiers":[
        {
            "category":"Banks & Credit Unions",
            "subcategory":"Investment Brokerage",
            "type":"Services"
        }
    ],
    "sg:phone":"+1 507 831 9211",
    "sg:postcode":"56101",
    "sg:province":"MN",
    "sg:tags":[
        "security"
    ],
    "wof:name":"Community First Investment Svc",
    "wof:placetype":"venue"
},
  "geometry": {"coordinates":[-95.115617,43.866475],"type":"Point"}
}