{
  "type": "Feature",
  "properties": {
    "addr:full":"43826 Peaceful Valley Rd Harris MN 55032",
    "addr:postcode":"43826;55032",
    "addr:street":"Peaceful Valley Rd",
    "iso:country":"US",
    "sg:address":"43826 Peaceful Valley Rd",
    "sg:city":"Harris",
    "sg:classifiers":[
        {
            "category":"Farming",
            "subcategory":"Livestock Farm",
            "type":"Manufacturing & Wholesale Goods"
        }
    ],
    "sg:phone":"+1 651 674 7711",
    "sg:postcode":"55032",
    "sg:province":"MN",
    "sg:tags":[
        "feedlot",
        "hog",
        "or",
        "beef",
        "cattle"
    ],
    "wof:name":"James Fairbanks",
    "wof:placetype":"venue"
},
  "geometry": {"coordinates":[-92.919406,45.573883],"type":"Point"}
}