{
  "type": "Feature",
  "properties": {
    "addr:full":"11680 Fernbrook Ln N Osseo MN 55369",
    "addr:housenumber":"11680",
    "addr:postcode":"55369",
    "addr:street":"Fernbrook Ln N",
    "iso:country":"US",
    "sg:address":"11680 Fernbrook Ln N",
    "sg:city":"Osseo",
    "sg:classifiers":[
        {
            "category":"Organizations",
            "subcategory":"Community Association",
            "type":"Services"
        }
    ],
    "sg:phone":"+1 763 420 6138",
    "sg:postcode":"55369",
    "sg:province":"MN",
    "wof:name":"Lions Club Dayton",
    "wof:placetype":"venue"
},
  "geometry": {"coordinates":[-93.461913,45.16166],"type":"Point"}
}