{
  "type": "Feature",
  "properties": {
    "iso:country":"US",
    "sg:address":"104 Blessum St",
    "sg:city":"Hanska",
    "sg:classifiers":[
        {
            "category":"Arts & Performance",
            "subcategory":"Theater",
            "type":"Entertainment"
        }
    ],
    "sg:phone":"+1 507 439 6709",
    "sg:postcode":"56041",
    "sg:province":"MN",
    "sg:tags":[
        "karaoke"
    ],
    "wof:name":"Me & You Karaoke & DJ",
    "wof:placetype":"venue"
},
  "geometry": {"coordinates":[-94.49476799999999,44.145866],"type":"Point"}
}