{
  "type": "Feature",
  "properties": {
    "addr:full":"4614 480th Ave Frost MN 56033",
    "addr:housenumber":"4614",
    "addr:postcode":"56033",
    "addr:street":"480Th Ave",
    "iso:country":"US",
    "sg:address":"4614 480th Ave",
    "sg:city":"Frost",
    "sg:phone":"+1 507 878 3232",
    "sg:postcode":"56033",
    "sg:province":"MN",
    "sg:tags":[
        "farm",
        "corn"
    ],
    "wof:name":"Robert Hanson",
    "wof:placetype":"venue"
},
  "geometry": {"coordinates":[-93.908295,43.548032],"type":"Point"}
}