{
  "type": "Feature",
  "properties": {
    "iso:country":"US",
    "sg:address":"529 Heritage Way",
    "sg:city":"Farmington",
    "sg:classifiers":[
        {
            "category":"Building & Trades",
            "subcategory":"Construction",
            "type":"Services"
        }
    ],
    "sg:phone":"+1 651 460 6721",
    "sg:postcode":"55024",
    "sg:province":"MN",
    "sg:tags":[
        "house"
    ],
    "wof:name":"Brekke Construction",
    "wof:placetype":"venue"
},
  "geometry": {"coordinates":[-93.14336,44.624923],"type":"Point"}
}