{
  "type": "Feature",
  "properties": {
    "iso:country":"US",
    "sg:address":"9444 Deerwood Ln N",
    "sg:city":"Osseo",
    "sg:classifiers":[
        {
            "category":"Manufacturing",
            "subcategory":"Chemicals & Compounds",
            "type":"Manufacturing & Wholesale Goods"
        }
    ],
    "sg:phone":"+1 763 315 4246",
    "sg:postcode":"55369",
    "sg:province":"MN",
    "sg:tags":[
        "product",
        "mfg"
    ],
    "wof:name":"Natural Wood Solutions",
    "wof:placetype":"venue"
},
  "geometry": {"coordinates":[-93.42594,45.126166],"type":"Point"}
}