{
  "type": "Feature",
  "properties": {
    "addr:full":"14693 61st Ave NW Cass Lake MN 56633",
    "addr:housenumber":"14693",
    "addr:postcode":"56633",
    "addr:street":"61St Ave Nw Cass",
    "iso:country":"US",
    "sg:address":"14693 61st Ave NW",
    "sg:city":"Cass Lake",
    "sg:classifiers":[
        {
            "category":"Manufacturing",
            "subcategory":"Lumber",
            "type":"Manufacturing & Wholesale Goods"
        }
    ],
    "sg:phone":"+1 218 335 2952",
    "sg:postcode":"56633",
    "sg:province":"MN",
    "sg:tags":[
        "forestry",
        "wildlife"
    ],
    "wof:name":"Kevin Fuller",
    "wof:placetype":"venue"
},
  "geometry": {"coordinates":[-94.60818500000001,47.3239],"type":"Point"}
}