{
  "type": "Feature",
  "properties": {
    "addr:full":"124 1st Ave N Appleton MN 56208",
    "addr:housenumber":"124",
    "addr:postcode":"56208",
    "addr:street":"1St Ave N",
    "iso:country":"US",
    "sg:address":"124 1st Ave N",
    "sg:city":"Appleton",
    "sg:classifiers":[
        {
            "category":"Wholesale",
            "subcategory":"Machinery & Supplies",
            "type":"Manufacturing & Wholesale Goods"
        }
    ],
    "sg:phone":"+1 320 289 2433",
    "sg:postcode":"56208",
    "sg:province":"MN",
    "sg:tags":[
        "farm",
        "corn"
    ],
    "wof:name":"Telford Shop",
    "wof:placetype":"venue"
},
  "geometry": {"coordinates":[-96.019261,45.209085],"type":"Point"}
}