{
  "type": "Feature",
  "properties": {
    "iso:country":"US",
    "sg:address":"6355 Osman Ave N",
    "sg:city":"Oak Park Heights",
    "sg:classifiers":[
        {
            "category":"Building & Trades",
            "subcategory":"Construction",
            "type":"Services"
        }
    ],
    "sg:phone":"+1 651 439 4044",
    "sg:postcode":"55082",
    "sg:province":"MN",
    "sg:tags":[
        "company"
    ],
    "wof:name":"Braden Construction",
    "wof:placetype":"venue"
},
  "geometry": {"coordinates":[-92.806226,45.040594],"type":"Point"}
}