{
  "type": "Feature",
  "properties": {
    "addr:full":"876 30th St SW Buffalo MN 55313",
    "addr:housenumber":"876",
    "addr:postcode":"55313",
    "addr:street":"30Th St Sw",
    "iso:country":"US",
    "sg:address":"876 30th St SW",
    "sg:city":"Buffalo",
    "sg:classifiers":[
        {
            "category":"Building & Trades",
            "subcategory":"Construction",
            "type":"Services"
        }
    ],
    "sg:phone":"+1 763 675 3554",
    "sg:postcode":"55313",
    "sg:province":"MN",
    "sg:tags":[
        "excavation",
        "contractor"
    ],
    "wof:name":"Ted Solberg Contractor",
    "wof:placetype":"venue"
},
  "geometry": {"coordinates":[-93.911171,45.108464],"type":"Point"}
}