{
  "type": "Feature",
  "properties": {
    "addr:full":"107 3rd Ave NE Pierz MN 56364",
    "addr:housenumber":"107",
    "addr:postcode":"56364",
    "addr:street":"3Rd Ave Ne",
    "iso:country":"US",
    "sg:address":"107 3rd Ave NE",
    "sg:city":"Pierz",
    "sg:classifiers":[
        {
            "category":"Health Services",
            "subcategory":"Doctor",
            "type":"Services"
        }
    ],
    "sg:phone":"+1 320 468 2504",
    "sg:postcode":"56364",
    "sg:province":"MN",
    "sg:tags":[
        "dentist"
    ],
    "wof:name":"Pierz Northtown Dental Clinic",
    "wof:placetype":"venue"
},
  "geometry": {"coordinates":[-94.10512,45.983352],"type":"Point"}
}