{
  "type": "Feature",
  "properties": {
    "addr:full":"1801 101st Ave NE Blaine MN 55449",
    "addr:housenumber":"1801",
    "addr:postcode":"55449",
    "addr:street":"101St Ave Ne",
    "iso:country":"US",
    "sg:address":"1801 101st Ave NE",
    "sg:city":"Blaine",
    "sg:classifiers":[
        {
            "category":"Government",
            "subcategory":"Office",
            "type":"Public Place"
        }
    ],
    "sg:phone":"+1 763 785 6165",
    "sg:postcode":"55449",
    "sg:province":"MN",
    "sg:tags":[
        "village"
    ],
    "sg:website":"www.ci.blaine.mn.us",
    "wof:name":"Blaine Street Maintenance",
    "wof:placetype":"venue"
},
  "geometry": {"coordinates":[-93.22586099999999,45.153547],"type":"Point"}
}