{
  "type": "Feature",
  "properties": {
    "addr:full":"4940 360th Ave Blue Earth MN 56013",
    "addr:housenumber":"4940",
    "addr:postcode":"56013",
    "addr:street":"360Th Ave",
    "iso:country":"US",
    "sg:address":"4940 360th Ave",
    "sg:city":"Blue Earth",
    "sg:phone":"+1 507 526 2454",
    "sg:postcode":"56013",
    "sg:province":"MN",
    "sg:tags":[
        "farm",
        "corn",
        "grain",
        "cash"
    ],
    "wof:name":"Steele Farms Inc",
    "wof:placetype":"venue"
},
  "geometry": {"coordinates":[-94.14785999999999,43.55802],"type":"Point"}
}