{
  "type": "Feature",
  "properties": {
    "addr:full":"3216 E 29th St Minneapolis MN 55406",
    "addr:housenumber":"3216",
    "addr:postcode":"55406",
    "addr:street":"E 29Th St",
    "iso:country":"US",
    "sg:address":"3216 E 29th St",
    "sg:city":"Minneapolis",
    "sg:classifiers":[
        {
            "category":"Place Of Worship",
            "type":"Public Place"
        },
        {
            "category":"Organizations",
            "subcategory":"Religious Organization",
            "type":"Services"
        }
    ],
    "sg:phone":"+1 612 729 5392",
    "sg:postcode":"55406",
    "sg:province":"MN",
    "sg:tags":[
        "church"
    ],
    "wof:name":"St Albert the Great Church",
    "wof:placetype":"venue"
},
  "geometry": {"coordinates":[-93.22541699999999,44.950366],"type":"Point"}
}