{
  "type": "Feature",
  "properties": {
    "addr:full":"52658 Co Hwy 142 New York Mills MN 56567",
    "addr:housenumber":"52658",
    "addr:postcode":"56567",
    "addr:street":"Co Hwy 142",
    "iso:country":"US",
    "sg:address":"52658 Co Hwy 142",
    "sg:city":"New York Mills",
    "sg:classifiers":[
        {
            "category":"Building & Trades",
            "subcategory":"Construction",
            "type":"Services"
        }
    ],
    "sg:phone":"+1 218 385 3637",
    "sg:postcode":"56567",
    "sg:province":"MN",
    "sg:tags":[
        "house",
        "con"
    ],
    "wof:name":"Triple H Construction",
    "wof:placetype":"venue"
},
  "geometry": {"coordinates":[-95.394313,46.470172],"type":"Point"}
}