{
  "type": "Feature",
  "properties": {
    "addr:full":"44362 454th Ave Perham MN 56573",
    "addr:housenumber":"44362",
    "addr:postcode":"56573",
    "addr:street":"454Th Ave",
    "iso:country":"US",
    "sg:address":"44362 454th Ave",
    "sg:city":"Perham",
    "sg:classifiers":[
        {
            "category":"Building & Trades",
            "subcategory":"Construction",
            "type":"Services"
        }
    ],
    "sg:phone":"+1 218 346 3250",
    "sg:postcode":"56573",
    "sg:province":"MN",
    "sg:tags":[
        "system",
        "specialty",
        "heating",
        "contractor",
        "air conditioning"
    ],
    "wof:name":"Geo-Tech of Minnesota",
    "wof:placetype":"venue"
},
  "geometry": {"coordinates":[-95.54661299999999,46.605016],"type":"Point"}
}