{
  "type": "Feature",
  "properties": {
    "iso:country":"US",
    "sg:address":"17241 Co Rd 83",
    "sg:city":"Pengilly",
    "sg:classifiers":[
        {
            "category":"Shopping",
            "subcategory":"Clothing, Apparel, & Fashions",
            "type":"Retail Goods"
        }
    ],
    "sg:phone":"+1 218 247 0160",
    "sg:postcode":"55775",
    "sg:province":"MN",
    "wof:name":"Angies Bridal",
    "wof:placetype":"venue"
},
  "geometry": {"coordinates":[-93.225273,47.326204],"type":"Point"}
}