{
  "type": "Feature",
  "properties": {
    "iso:country":"US",
    "sg:address":"6543 Holly Dr",
    "sg:city":"Virginia",
    "sg:classifiers":[
        {
            "category":"Social Services",
            "subcategory":"Child Care",
            "type":"Services"
        }
    ],
    "sg:phone":"+1 218 749 6488",
    "sg:postcode":"55792",
    "sg:province":"MN",
    "sg:tags":[
        "day",
        "provides"
    ],
    "wof:name":"Sylvia Anderson",
    "wof:placetype":"venue"
},
  "geometry": {"coordinates":[-92.540496,47.592411],"type":"Point"}
}