{
  "type": "Feature",
  "properties": {
    "addr:full":"1230 Ashland Ave St Paul Park MN 55071",
    "addr:housenumber":"1230",
    "addr:postcode":"55071",
    "addr:street":"Ashland Ave St;Park",
    "iso:country":"US",
    "sg:address":"1230 Ashland Ave",
    "sg:city":"St Paul Park",
    "sg:classifiers":[
        {
            "category":"Professional",
            "subcategory":"Advertising",
            "type":"Services"
        }
    ],
    "sg:phone":"+1 651 387 9091",
    "sg:postcode":"55071",
    "sg:province":"MN",
    "sg:tags":[
        "distribution"
    ],
    "wof:name":"Herbalife Independent Dist",
    "wof:placetype":"venue"
},
  "geometry": {"coordinates":[-92.98700599999999,44.8353],"type":"Point"}
}