{
  "type": "Feature",
  "properties": {
    "addr:full":"7900 Highway 55 Minneapolis MN 55427",
    "addr:housenumber":"7900",
    "addr:postcode":"55427",
    "addr:street":"Highway 55",
    "iso:country":"US",
    "sg:address":"7900 Highway 55",
    "sg:city":"Minneapolis",
    "sg:classifiers":[
        {
            "category":"Utilities",
            "subcategory":"Mobile Phone",
            "type":"Services"
        },
        {
            "category":"Shopping",
            "subcategory":"Mobile Phones",
            "type":"Retail Goods"
        },
        {
            "category":"Utilities",
            "subcategory":"Telephone",
            "type":"Services"
        },
        {
            "category":"Professional",
            "subcategory":"Computer Services",
            "type":"Services"
        }
    ],
    "sg:phone":"+1 763 546 7887",
    "sg:postcode":"55427",
    "sg:province":"MN",
    "sg:tags":[
        "telecommunication",
        "supply",
        "communication",
        "system",
        "wireless",
        "equipment",
        "cellular"
    ],
    "sg:website":"http://clickserve.dartsearch.net/link/click?lid=43000000308049899",
    "wof:name":"T-Mobile",
    "wof:placetype":"venue"
},
  "geometry": {"coordinates":[-93.381035,44.983948],"type":"Point"}
}