{
  "type": "Feature",
  "properties": {
    "iso:country":"US",
    "sg:address":"1650 150th St",
    "sg:city":"Canby",
    "sg:classifiers":[
        {
            "category":"Farming",
            "subcategory":"Farm",
            "type":"Manufacturing & Wholesale Goods"
        }
    ],
    "sg:phone":"+1 507 223 5060",
    "sg:postcode":"56220",
    "sg:province":"MN",
    "wof:name":"Ernest L Chrtt",
    "wof:placetype":"venue"
},
  "geometry": {"coordinates":[-96.35838099999999,44.638262],"type":"Point"}
}