{
  "type": "Feature",
  "properties": {
    "iso:country":"US",
    "sg:address":"1330 Conway St",
    "sg:city":"St Paul",
    "sg:classifiers":[
        {
            "category":"Banks & Credit Unions",
            "subcategory":"Bank",
            "type":"Services"
        }
    ],
    "sg:phone":"+1 651 772 8744",
    "sg:postcode":"55106",
    "sg:province":"MN",
    "wof:name":"St Paul Federal Credit Union",
    "wof:placetype":"venue"
},
  "geometry": {"coordinates":[-93.044917,44.955811],"type":"Point"}
}