{
  "type": "Feature",
  "properties": {
    "addr:full":"3507 W 50th St Minneapolis MN 55410",
    "addr:housenumber":"3507",
    "addr:postcode":"55410",
    "addr:street":"W 50Th St",
    "iso:country":"US",
    "sg:address":"3507 W 50th St",
    "sg:city":"Minneapolis",
    "sg:classifiers":[
        {
            "category":"Banks & Credit Unions",
            "subcategory":"Bank",
            "type":"Services"
        }
    ],
    "sg:phone":"+1 952 469 5858",
    "sg:postcode":"55410",
    "sg:province":"MN",
    "sg:tags":[
        "broker",
        "mortgage"
    ],
    "wof:name":"Hom Financial Inc",
    "wof:placetype":"venue"
},
  "geometry": {"coordinates":[-93.325171,44.912426],"type":"Point"}
}