{
  "type": "Feature",
  "properties": {
    "addr:full":"306 3rd St NE Roseau MN 56751",
    "addr:housenumber":"306",
    "addr:postcode":"56751",
    "addr:street":"3Rd St Ne",
    "iso:country":"US",
    "sg:address":"306 3rd St NE",
    "sg:city":"Roseau",
    "sg:classifiers":[
        {
            "category":"Building & Trades",
            "subcategory":"Equipment Rental",
            "type":"Services"
        }
    ],
    "sg:phone":"+1 218 469 1735",
    "sg:postcode":"56751",
    "sg:province":"MN",
    "sg:tags":[
        "crane"
    ],
    "wof:name":"Corrugated Metals Inc",
    "wof:placetype":"venue"
},
  "geometry": {"coordinates":[-95.758613,48.847994],"type":"Point"}
}