{
  "type": "Feature",
  "properties": {
    "iso:country":"US",
    "sg:address":"505 W 37th St",
    "sg:city":"Hibbing",
    "sg:classifiers":[
        {
            "category":"Building & Trades",
            "subcategory":"Construction",
            "type":"Services"
        }
    ],
    "sg:phone":"+1 218 262 3406",
    "sg:postcode":"55746",
    "sg:province":"MN",
    "sg:tags":[
        "repair"
    ],
    "sg:website":"www.ulland.com",
    "wof:name":"Ulland Brothers Inc",
    "wof:placetype":"venue"
},
  "geometry": {"coordinates":[-92.946898,47.407604],"type":"Point"}
}