{
  "type": "Feature",
  "properties": {
    "iso:country":"US",
    "sg:address":"5820 74th Ave N",
    "sg:city":"Minneapolis",
    "sg:classifiers":[
        {
            "category":"Health Services",
            "subcategory":"Doctor",
            "type":"Services"
        }
    ],
    "sg:phone":"+1 763 561 7000",
    "sg:postcode":"55443",
    "sg:province":"MN",
    "wof:name":"Sandpiper Dental Square",
    "wof:placetype":"venue"
},
  "geometry": {"coordinates":[-93.355844,45.089854],"type":"Point"}
}