{
  "type": "Feature",
  "properties": {
    "iso:country":"US",
    "sg:address":"2115 S 6th St",
    "sg:city":"Brainerd",
    "sg:classifiers":[
        {
            "category":"Restaurant",
            "type":"Food & Drink"
        }
    ],
    "sg:menulink":"http://www.allmenus.com/mn/brainerd/23652-green-mill/menu/",
    "sg:phone":"+1 218 829 4100",
    "sg:postcode":"56401",
    "sg:province":"MN",
    "sg:tags":[
        "american",
        "pizza"
    ],
    "wof:name":"Green Mill",
    "wof:placetype":"venue"
},
  "geometry": {"coordinates":[-94.20069700000001,46.332486],"type":"Point"}
}