{
  "type": "Feature",
  "properties": {
    "addr:full":"9130 Knollwood Dr N Stillwater MN 55082",
    "addr:housenumber":"9130",
    "addr:postcode":"55082",
    "addr:street":"Knollwood Dr N",
    "iso:country":"US",
    "sg:address":"9130 Knollwood Dr N",
    "sg:city":"Stillwater",
    "sg:classifiers":[
        {
            "category":"Museum",
            "type":"Entertainment"
        }
    ],
    "sg:phone":"+1 651 430 9936",
    "sg:postcode":"55082",
    "sg:province":"MN",
    "sg:tags":[
        "consulting",
        "gallery",
        "business"
    ],
    "wof:name":"Jco Enterprises LLC",
    "wof:placetype":"venue"
},
  "geometry": {"coordinates":[-92.888699,45.083256],"type":"Point"}
}