{
  "type": "Feature",
  "properties": {
    "iso:country":"US",
    "sg:address":"8875 Co Rd 43",
    "sg:city":"Chaska",
    "sg:classifiers":[
        {
            "category":"Building & Trades",
            "subcategory":"Plumbing",
            "type":"Services"
        }
    ],
    "sg:phone":"+1 952 443 2915",
    "sg:postcode":"55318",
    "sg:province":"MN",
    "sg:tags":[
        "contractor"
    ],
    "wof:name":"Dan S Heating Air Cond",
    "wof:placetype":"venue"
},
  "geometry": {"coordinates":[-93.681775,44.845553],"type":"Point"}
}