{
  "type": "Feature",
  "properties": {
    "addr:full":"415 1st Ave E Shakopee MN 55379",
    "addr:housenumber":"415",
    "addr:postcode":"55379",
    "addr:street":"1St Ave E",
    "iso:country":"US",
    "sg:address":"415 1st Ave E",
    "sg:city":"Shakopee",
    "sg:classifiers":[
        {
            "category":"Health Services",
            "subcategory":"Dentist",
            "type":"Services"
        }
    ],
    "sg:phone":"+1 952 445 5510",
    "sg:postcode":"55379",
    "sg:province":"MN",
    "wof:name":"Family Dental Care",
    "wof:placetype":"venue"
},
  "geometry": {"coordinates":[-93.522284,44.799287],"type":"Point"}
}