{
  "type": "Feature",
  "properties": {
    "iso:country":"US",
    "sg:address":"33952 348th St",
    "sg:city":"Le Sueur",
    "sg:classifiers":[
        {
            "category":"Recreation",
            "type":"Entertainment"
        }
    ],
    "sg:phone":"+1 507 665 2297",
    "sg:postcode":"56058",
    "sg:province":"MN",
    "sg:tags":[
        "household",
        "appliance"
    ],
    "wof:name":"Judys Knit & Sew",
    "wof:placetype":"venue"
},
  "geometry": {"coordinates":[-93.94838,44.446058],"type":"Point"}
}