{
  "type": "Feature",
  "properties": {
    "addr:full":"249 6th Ave N Bayport MN 55003",
    "addr:housenumber":"249",
    "addr:postcode":"55003",
    "addr:street":"6Th Ave N",
    "iso:country":"US",
    "sg:address":"249 6th Ave N",
    "sg:city":"Bayport",
    "sg:classifiers":[
        {
            "category":"Real Estate",
            "subcategory":"Real Estate Agent",
            "type":"Services"
        }
    ],
    "sg:phone":"+1 651 275 1830",
    "sg:postcode":"55003",
    "sg:province":"MN",
    "wof:name":"Riverview Rentals",
    "wof:placetype":"venue"
},
  "geometry": {"coordinates":[-92.78033000000001,45.02269],"type":"Point"}
}