{
  "type": "Feature",
  "properties": {
    "addr:full":"18584 310th St Glenwood MN 56334",
    "addr:housenumber":"18584",
    "addr:postcode":"56334",
    "addr:street":"310Th St",
    "iso:country":"US",
    "sg:address":"18584 310th St",
    "sg:city":"Glenwood",
    "sg:classifiers":[
        {
            "category":"Farming",
            "subcategory":"Dairy Farm",
            "type":"Manufacturing & Wholesale Goods"
        }
    ],
    "sg:phone":"+1 320 278 3571",
    "sg:postcode":"56334",
    "sg:province":"MN",
    "wof:name":"Charles Holtkamp",
    "wof:placetype":"venue"
},
  "geometry": {"coordinates":[-95.306032,45.457436],"type":"Point"}
}