{
  "type": "Feature",
  "properties": {
    "addr:full":"7777 Highway 65 NE Spring Lake Park MN 55432",
    "addr:housenumber":"7777",
    "addr:postcode":"55432",
    "addr:street":"Highway 65 Ne;Park",
    "iso:country":"US",
    "sg:address":"7777 Highway 65 NE",
    "sg:city":"Spring Lake Park",
    "sg:classifiers":[
        {
            "category":"Restaurant",
            "type":"Food & Drink"
        }
    ],
    "sg:menulink":"http://www.allmenus.com/mn/spring-lake-park/120794-rong-cheng/menu/",
    "sg:phone":"+1 763 785 8889",
    "sg:postcode":"55432",
    "sg:province":"MN",
    "sg:tags":[
        "asian",
        "chinese"
    ],
    "wof:name":"Rong Cheng",
    "wof:placetype":"venue"
},
  "geometry": {"coordinates":[-93.243359,45.109021],"type":"Point"}
}