{
  "type": "Feature",
  "properties": {
    "iso:country":"US",
    "sg:address":"9948 Nesbitt Cir",
    "sg:city":"Minneapolis",
    "sg:classifiers":[
        {
            "category":"Real Estate",
            "subcategory":"Real Estate Agent",
            "type":"Services"
        }
    ],
    "sg:phone":"+1 952 925 6008",
    "sg:postcode":"55437",
    "sg:province":"MN",
    "sg:tags":[
        "appraiser"
    ],
    "wof:name":"Guldseth Appraisals",
    "wof:placetype":"venue"
},
  "geometry": {"coordinates":[-93.358727,44.823542],"type":"Point"}
}