{
  "type": "Feature",
  "properties": {
    "addr:full":"808 E Main St Ada MN 56510",
    "addr:housenumber":"808",
    "addr:postcode":"56510",
    "addr:street":"E Main St",
    "iso:country":"US",
    "sg:address":"808 E Main St",
    "sg:city":"Ada",
    "sg:classifiers":[
        {
            "category":"Utilities",
            "subcategory":"Refuse",
            "type":"Services"
        }
    ],
    "sg:phone":"+1 218 784 4090",
    "sg:postcode":"56510",
    "sg:province":"MN",
    "sg:tags":[
        "garbage",
        "collection"
    ],
    "wof:name":"Al's Disposal",
    "wof:placetype":"venue"
},
  "geometry": {"coordinates":[-96.51602699999999,47.304021],"type":"Point"}
}