{
  "type": "Feature",
  "properties": {
    "iso:country":"US",
    "sg:address":"630 Calhoun Pl",
    "sg:city":"Cambridge",
    "sg:classifiers":[
        {
            "category":"Retail",
            "subcategory":"Car Wash",
            "type":"Services"
        }
    ],
    "sg:phone":"+1 763 689 2803",
    "sg:postcode":"55008",
    "sg:province":"MN",
    "sg:tags":[
        "carwash",
        "water",
        "transport"
    ],
    "wof:name":"Ultra Shine Auto Detailing",
    "wof:placetype":"venue"
},
  "geometry": {"coordinates":[-93.21909100000001,45.577896],"type":"Point"}
}