{
  "type": "Feature",
  "properties": {
    "addr:full":"6400 Barrie Rd Apt 1607 Minneapolis MN 55435",
    "addr:postcode":"6400;1607;55435",
    "addr:street":"Barrie Rd Apt",
    "iso:country":"US",
    "sg:address":"6400 Barrie Rd Apt 1607",
    "sg:city":"Minneapolis",
    "sg:classifiers":[
        {
            "category":"Professional",
            "subcategory":"Advertising",
            "type":"Services"
        }
    ],
    "sg:phone":"+1 952 836 0264",
    "sg:postcode":"55435",
    "sg:province":"MN",
    "sg:tags":[
        "telemarketing"
    ],
    "sg:website":"http://www.crystalmap.com",
    "wof:name":"Crystalmap.Com",
    "wof:placetype":"venue"
},
  "geometry": {"coordinates":[-93.32238,44.886352],"type":"Point"}
}