{
  "type": "Feature",
  "properties": {
    "addr:full":"31938 18th Ave Cushing MN 56443",
    "addr:housenumber":"31938",
    "addr:postcode":"56443",
    "addr:street":"18Th Ave",
    "iso:country":"US",
    "sg:address":"31938 18th Ave",
    "sg:city":"Cushing",
    "sg:classifiers":[
        {
            "category":"Home & Garden",
            "subcategory":"Furniture",
            "type":"Retail Goods"
        }
    ],
    "sg:phone":"+1 218 575 2092",
    "sg:postcode":"56443",
    "sg:province":"MN",
    "wof:name":"Finishing Touch Enterprises",
    "wof:placetype":"venue"
},
  "geometry": {"coordinates":[-94.62631500000001,46.220877],"type":"Point"}
}