{
  "type": "Feature",
  "properties": {
    "iso:country":"US",
    "sg:address":"7016 6th St N",
    "sg:city":"Saint Paul",
    "sg:classifiers":[
        {
            "category":"Manufacturing",
            "subcategory":"Tools & Machinery",
            "type":"Manufacturing & Wholesale Goods"
        }
    ],
    "sg:phone":"+1 651 501 8114",
    "sg:postcode":"55128",
    "sg:province":"MN",
    "sg:tags":[
        "instrument",
        "mfg"
    ],
    "wof:name":"Eye Tech LLC",
    "wof:placetype":"venue"
},
  "geometry": {"coordinates":[-92.96377,44.956668],"type":"Point"}
}