{
  "type": "Feature",
  "properties": {
    "addr:full":"403 S State St Fairmont MN 56031",
    "addr:housenumber":"403",
    "addr:postcode":"56031",
    "addr:street":"S State St",
    "iso:country":"US",
    "sg:address":"403 S State St",
    "sg:city":"Fairmont",
    "sg:classifiers":[
        {
            "category":"Insurance",
            "subcategory":"Insurance Agent",
            "type":"Services"
        }
    ],
    "sg:phone":"+1 507 235 3397",
    "sg:postcode":"56031",
    "sg:province":"MN",
    "wof:name":"State Farm Insurance",
    "wof:placetype":"venue"
},
  "geometry": {"coordinates":[-94.447272,43.649939],"type":"Point"}
}