{
  "type": "Feature",
  "properties": {
    "addr:full":"3638 Hwy 67 Boyd MN 56218",
    "addr:housenumber":"3638",
    "addr:postcode":"56218",
    "addr:street":"Hwy 67 Boyd",
    "iso:country":"US",
    "sg:address":"3638 Hwy 67",
    "sg:city":"Boyd",
    "sg:phone":"+1 320 669 7637",
    "sg:postcode":"56218",
    "sg:province":"MN",
    "sg:tags":[
        "hog",
        "wheat",
        "farm",
        "corn",
        "soybean",
        "or",
        "feedlot"
    ],
    "wof:name":"Satre Marlin",
    "wof:placetype":"venue"
},
  "geometry": {"coordinates":[-95.928605,44.790698],"type":"Point"}
}