{
  "type": "Feature",
  "properties": {
    "iso:country":"US",
    "sg:address":"2015 Northdale Blvd NW",
    "sg:city":"Minneapolis",
    "sg:classifiers":[
        {
            "category":"Food & Beverages",
            "subcategory":"Groceries & Convenience Stores",
            "type":"Retail Goods"
        }
    ],
    "sg:phone":"+1 763 755 9666",
    "sg:postcode":"55433",
    "sg:province":"MN",
    "wof:name":"Super America",
    "wof:placetype":"venue"
},
  "geometry": {"coordinates":[-93.31919000000001,45.181965],"type":"Point"}
}