{
  "type": "Feature",
  "properties": {
    "iso:country":"US",
    "sg:address":"928 Grand Ave",
    "sg:city":"St Paul",
    "sg:classifiers":[
        {
            "category":"Autos & Motor Vehicles",
            "subcategory":"Auto Supplies",
            "type":"Retail Goods"
        }
    ],
    "sg:phone":"+1 651 221 0014",
    "sg:postcode":"55105",
    "sg:province":"MN",
    "sg:tags":[
        "filter",
        "gas"
    ],
    "wof:name":"D P Filter Supply",
    "wof:placetype":"venue"
},
  "geometry": {"coordinates":[-93.141263,44.939895],"type":"Point"}
}