{
  "type": "Feature",
  "properties": {
    "iso:country":"US",
    "sg:address":"6121 Excelsior Blvd",
    "sg:city":"Minneapolis",
    "sg:classifiers":[
        {
            "category":"Organizations",
            "subcategory":"Community Association",
            "type":"Services"
        }
    ],
    "sg:phone":"+1 952 926 9384",
    "sg:postcode":"55416",
    "sg:province":"MN",
    "wof:name":"Eastern Star Minn Grnd Chapter",
    "wof:placetype":"venue"
},
  "geometry": {"coordinates":[-93.357766,44.927707],"type":"Point"}
}