{
  "type": "Feature",
  "properties": {
    "addr:full":"26101 Newton Cir Elko MN 55020",
    "addr:housenumber":"26101",
    "addr:postcode":"55020",
    "addr:street":"Newton Cir",
    "iso:country":"US",
    "sg:address":"26101 Newton Cir",
    "sg:city":"Elko",
    "sg:classifiers":[
        {
            "category":"Wholesale",
            "subcategory":"Non-durable Goods",
            "type":"Manufacturing & Wholesale Goods"
        }
    ],
    "sg:phone":"+1 952 461 1975",
    "sg:postcode":"55020",
    "sg:province":"MN",
    "sg:tags":[
        "pet",
        "supply"
    ],
    "wof:name":"Love On The Wing",
    "wof:placetype":"venue"
},
  "geometry": {"coordinates":[-93.307281,44.571845],"type":"Point"}
}