{
  "type": "Feature",
  "properties": {
    "iso:country":"US",
    "sg:address":"18440 Burns Pkwy",
    "sg:city":"Anoka",
    "sg:classifiers":[
        {
            "category":"Building & Trades",
            "subcategory":"Landscaping Services",
            "type":"Services"
        }
    ],
    "sg:phone":"+1 763 274 2301",
    "sg:postcode":"55303",
    "sg:province":"MN",
    "sg:tags":[
        "sanitary",
        "landscape"
    ],
    "wof:name":"Ww Services Inc",
    "wof:placetype":"venue"
},
  "geometry": {"coordinates":[-93.48518199999999,45.304941],"type":"Point"}
}