{
  "type": "Feature",
  "properties": {
    "addr:full":"1737 McMenemy St St Paul MN 55117",
    "addr:housenumber":"1737",
    "addr:postcode":"55117",
    "addr:street":"Mcmenemy St",
    "iso:country":"US",
    "sg:address":"1737 McMenemy St",
    "sg:city":"St Paul",
    "sg:classifiers":[
        {
            "category":"Recreation",
            "type":"Entertainment"
        },
        {
            "category":"Food & Beverages",
            "subcategory":"Bakery",
            "type":"Retail Goods"
        }
    ],
    "sg:phone":"+1 651 776 3224",
    "sg:postcode":"55117",
    "sg:province":"MN",
    "sg:tags":[
        "eating",
        "concessionaire"
    ],
    "wof:name":"Charanko's Mini Donuts",
    "wof:placetype":"venue"
},
  "geometry": {"coordinates":[-93.086426,44.995194],"type":"Point"}
}