{
  "type": "Feature",
  "properties": {
    "addr:full":"190 Victoria Dr Chaska MN 55318",
    "addr:housenumber":"190",
    "addr:postcode":"55318",
    "addr:street":"Victoria Dr",
    "iso:country":"US",
    "sg:address":"190 Victoria Dr",
    "sg:city":"Chaska",
    "sg:classifiers":[
        {
            "category":"Shopping",
            "subcategory":"Pharmacy",
            "type":"Retail Goods"
        }
    ],
    "sg:phone":"+1 952 448 2737",
    "sg:postcode":"55318",
    "sg:province":"MN",
    "wof:name":"Snyder Drug Store",
    "wof:placetype":"venue"
},
  "geometry": {"coordinates":[-93.60338900000001,44.799536],"type":"Point"}
}