{
  "type": "Feature",
  "properties": {
    "addr:full":"1551 S College Rd Baxter MN 56425",
    "addr:housenumber":"1551",
    "addr:postcode":"56425",
    "addr:street":"S College Rd",
    "iso:country":"US",
    "sg:address":"1551 S College Rd",
    "sg:city":"Baxter",
    "sg:classifiers":[
        {
            "category":"Professional",
            "subcategory":"Business Services",
            "type":"Services"
        }
    ],
    "sg:phone":"+1 218 825 8974",
    "sg:postcode":"56425",
    "sg:province":"MN",
    "sg:tags":[
        "water",
        "treatment"
    ],
    "wof:name":"Ecowater Systems",
    "wof:placetype":"venue"
},
  "geometry": {"coordinates":[-94.23450200000001,46.344755],"type":"Point"}
}