{
  "type": "Feature",
  "properties": {
    "iso:country":"US",
    "sg:address":"21198 Akin Rd",
    "sg:city":"Farmington",
    "sg:classifiers":[
        {
            "category":"Restaurant",
            "type":"Food & Drink"
        }
    ],
    "sg:menulink":"http://www.allmenus.com/mn/farmington/58439-dominos-pizza/menu/",
    "sg:phone":"+1 651 463 3030",
    "sg:postcode":"55024",
    "sg:province":"MN",
    "sg:tags":[
        "american",
        "wing",
        "pizza"
    ],
    "wof:name":"Domino's Pizza",
    "wof:placetype":"venue"
},
  "geometry": {"coordinates":[-93.17693800000001,44.646746],"type":"Point"}
}