{
  "type": "Feature",
  "properties": {
    "addr:full":"5765 Quam Ave NE St Michael MN 55376",
    "addr:housenumber":"5765",
    "addr:postcode":"55376",
    "addr:street":"Quam Ave Ne St",
    "iso:country":"US",
    "sg:address":"5765 Quam Ave NE",
    "sg:city":"St Michael",
    "sg:classifiers":[
        {
            "category":"Home & Garden",
            "subcategory":"Building Materials",
            "type":"Retail Goods"
        },
        {
            "category":"Building & Trades",
            "subcategory":"Construction",
            "type":"Services"
        }
    ],
    "sg:phone":"+1 763 428 1800",
    "sg:postcode":"55376",
    "sg:province":"MN",
    "sg:tags":[
        "flat",
        "window",
        "glass",
        "plate",
        "contractor"
    ],
    "wof:name":"Glass Products Inc",
    "wof:placetype":"venue"
},
  "geometry": {"coordinates":[-93.554722,45.231271],"type":"Point"}
}