{
  "type": "Feature",
  "properties": {
    "addr:full":"2910 54th St E Inver Grove Hts MN 55076",
    "addr:housenumber":"2910",
    "addr:postcode":"55076",
    "addr:street":"54Th St E",
    "iso:country":"US",
    "sg:address":"2910 54th St E",
    "sg:city":"Inver Grove Hts",
    "sg:classifiers":[
        {
            "category":"Building & Trades",
            "subcategory":"Pest Control",
            "type":"Services"
        }
    ],
    "sg:phone":"+1 651 450 2030",
    "sg:postcode":"55076",
    "sg:province":"MN",
    "wof:name":"Jerry's Pest Control LLC",
    "wof:placetype":"venue"
},
  "geometry": {"coordinates":[-93.04585299999999,44.870831],"type":"Point"}
}