{
  "type": "Feature",
  "properties": {
    "iso:country":"US",
    "sg:address":"3840 Perry Ave N",
    "sg:city":"Minneapolis",
    "sg:classifiers":[
        {
            "category":"Real Estate",
            "subcategory":"Real Estate Services",
            "type":"Services"
        },
        {
            "category":"Real Estate",
            "subcategory":"Real Estate Agent",
            "type":"Services"
        }
    ],
    "sg:phone":"+1 763 537 2207",
    "sg:postcode":"55422",
    "sg:province":"MN",
    "sg:tags":[
        "buyer",
        "broker"
    ],
    "wof:name":"Iq Realty",
    "wof:placetype":"venue"
},
  "geometry": {"coordinates":[-93.34155199999999,45.024858],"type":"Point"}
}