{
  "type": "Feature",
  "properties": {
    "addr:full":"3600 Minnesota Dr Ste. 300 Minneapolis MN 55435",
    "addr:housenumber":"3600",
    "addr:postcode":"55435",
    "addr:street":"Minnesota Dr Ste. 300",
    "iso:country":"US",
    "sg:address":"3600 Minnesota Dr Ste. 300",
    "sg:city":"Minneapolis",
    "sg:classifiers":[
        {
            "category":"Banks & Credit Unions",
            "subcategory":"Investment Brokerage",
            "type":"Services"
        },
        {
            "category":"Insurance",
            "subcategory":"Life Insurance",
            "type":"Services"
        },
        {
            "category":"Banks & Credit Unions",
            "subcategory":"Financial Services",
            "type":"Services"
        }
    ],
    "sg:phone":"+1 952 806 9626",
    "sg:postcode":"55435",
    "sg:province":"MN",
    "sg:tags":[
        "term",
        "retirement",
        "annuity",
        "long",
        "plan",
        "care"
    ],
    "sg:website":"http://www.nmfn.com/ryanalexander",
    "wof:name":"Northwestern Mutual Financial Network",
    "wof:placetype":"venue"
},
  "geometry": {"coordinates":[-93.32563,44.862005],"type":"Point"}
}