{
  "type": "Feature",
  "properties": {
    "addr:full":"200 Broadway St W Monticello MN 55362",
    "addr:housenumber":"200",
    "addr:postcode":"55362",
    "addr:street":"Broadway St W",
    "iso:country":"US",
    "sg:address":"200 Broadway St W",
    "sg:city":"Monticello",
    "sg:classifiers":[
        {
            "category":"Autos & Motor Vehicles",
            "subcategory":"Fuel & Gas Station",
            "type":"Retail Goods"
        }
    ],
    "sg:phone":"+1 763 295 4130",
    "sg:postcode":"55362",
    "sg:province":"MN",
    "sg:tags":[
        "oil"
    ],
    "wof:name":"Red's Marathon Svc",
    "wof:placetype":"venue"
},
  "geometry": {"coordinates":[-93.79707999999999,45.306672],"type":"Point"}
}