{
  "type": "Feature",
  "properties": {
    "addr:full":"36052 Rush Lake Loop Ottertail MN 56571",
    "addr:housenumber":"36052",
    "addr:postcode":"56571",
    "addr:street":"Rush Lake Loop",
    "iso:country":"US",
    "sg:address":"36052 Rush Lake Loop",
    "sg:city":"Ottertail",
    "sg:classifiers":[
        {
            "category":"Travel",
            "subcategory":"Hotels & Motels",
            "type":"Entertainment"
        }
    ],
    "sg:phone":"+1 218 346 6007",
    "sg:postcode":"56571",
    "sg:province":"MN",
    "sg:tags":[
        "resort"
    ],
    "sg:website":"www.hooklinesucher.com",
    "wof:name":"Hook Line & Sucher Resort",
    "wof:placetype":"venue"
},
  "geometry": {"coordinates":[-95.573508,46.484357],"type":"Point"}
}