{
  "type": "Feature",
  "properties": {
    "addr:full":"312 7th Ave S Sartell MN 56377",
    "addr:housenumber":"312",
    "addr:postcode":"56377",
    "addr:street":"7Th Ave S Sartell",
    "iso:country":"US",
    "sg:address":"312 7th Ave S",
    "sg:city":"Sartell",
    "sg:classifiers":[
        {
            "category":"Wholesale",
            "subcategory":"Machinery & Supplies",
            "type":"Manufacturing & Wholesale Goods"
        }
    ],
    "sg:phone":"+1 320 255 5570",
    "sg:postcode":"56377",
    "sg:province":"MN",
    "sg:tags":[
        "equipment",
        "establishment"
    ],
    "wof:name":"Rueter Sprinkler System",
    "wof:placetype":"venue"
},
  "geometry": {"coordinates":[-94.214915,45.612911],"type":"Point"}
}