{
  "type": "Feature",
  "properties": {
    "addr:full":"104 7th St S Moorhead MN 56560",
    "addr:housenumber":"104",
    "addr:postcode":"56560",
    "addr:street":"7Th St S",
    "iso:country":"US",
    "sg:address":"104 7th St S",
    "sg:city":"Moorhead",
    "sg:classifiers":[
        {
            "category":"Fast Food",
            "type":"Food & Drink"
        },
        {
            "category":"Restaurant",
            "type":"Food & Drink"
        },
        {
            "category":"Food & Beverages",
            "subcategory":"Groceries & Convenience Stores",
            "type":"Retail Goods"
        }
    ],
    "sg:phone":"+1 218 236 8058",
    "sg:postcode":"56560",
    "sg:province":"MN",
    "sg:tags":[
        "shop",
        "american",
        "sandwich",
        "take"
    ],
    "sg:website":"http://www.subway.com",
    "wof:name":"Subway",
    "wof:placetype":"venue"
},
  "geometry": {"coordinates":[-96.769311,46.873767],"type":"Point"}
}