{
  "type": "Feature",
  "properties": {
    "iso:country":"US",
    "sg:address":"295 Orchard Ct.",
    "sg:city":"Shakopee",
    "sg:classifiers":[
        {
            "category":"Home & Garden",
            "subcategory":"Carpets & Floor Coverings",
            "type":"Retail Goods"
        }
    ],
    "sg:phone":"+1 952 261 3748",
    "sg:postcode":"55379",
    "sg:province":"MN",
    "sg:tags":[
        "flooring"
    ],
    "wof:name":"Restyle TIle and Stone",
    "wof:placetype":"venue"
},
  "geometry": {"coordinates":[-93.52682900000001,44.779111],"type":"Point"}
}