{
  "type": "Feature",
  "properties": {
    "addr:full":"7204 W 27th St Minneapolis MN 55426",
    "addr:housenumber":"7204",
    "addr:postcode":"55426",
    "addr:street":"W 27Th St",
    "iso:country":"US",
    "sg:address":"7204 W 27th St",
    "sg:city":"Minneapolis",
    "sg:classifiers":[
        {
            "category":"Organizations",
            "subcategory":"Religious Organization",
            "type":"Services"
        }
    ],
    "sg:phone":"+1 952 285 6836",
    "sg:postcode":"55426",
    "sg:province":"MN",
    "wof:name":"Buenas Aires Bara America",
    "wof:placetype":"venue"
},
  "geometry": {"coordinates":[-93.37494700000001,44.954932],"type":"Point"}
}