{
  "type": "Feature",
  "properties": {
    "iso:country":"US",
    "sg:address":"6993 Hwy 2",
    "sg:city":"Saginaw",
    "sg:classifiers":[
        {
            "category":"Food & Beverages",
            "subcategory":"Groceries & Convenience Stores",
            "type":"Retail Goods"
        }
    ],
    "sg:phone":"+1 218 729 7634",
    "sg:postcode":"55779",
    "sg:province":"MN",
    "wof:name":"Saginaw Grand Lake Station",
    "wof:placetype":"venue"
},
  "geometry": {"coordinates":[-92.395122,46.825893],"type":"Point"}
}