{
  "type": "Feature",
  "properties": {
    "iso:country":"US",
    "sg:address":"8394 Horizon Dr",
    "sg:city":"Shakopee",
    "sg:classifiers":[
        {
            "category":"Manufacturing",
            "subcategory":"Tools & Machinery",
            "type":"Manufacturing & Wholesale Goods"
        }
    ],
    "sg:phone":"+1 952 496 9082",
    "sg:postcode":"55379",
    "sg:province":"MN",
    "sg:tags":[
        "industrial",
        "mfg"
    ],
    "wof:name":"Control Grinding",
    "wof:placetype":"venue"
},
  "geometry": {"coordinates":[-93.409943,44.758113],"type":"Point"}
}