{
  "type": "Feature",
  "properties": {
    "addr:full":"17380 110th St Young America MN 55397",
    "addr:housenumber":"17380",
    "addr:postcode":"55397",
    "addr:street":"110Th St",
    "iso:country":"US",
    "sg:address":"17380 110th St",
    "sg:city":"Young America",
    "sg:classifiers":[
        {
            "category":"Shopping",
            "subcategory":"Crafts & Fabrics",
            "type":"Retail Goods"
        }
    ],
    "sg:phone":"+1 952 467 9645",
    "sg:postcode":"55397",
    "sg:province":"MN",
    "sg:tags":[
        "sewing"
    ],
    "wof:name":"D & K Embroidery",
    "wof:placetype":"venue"
},
  "geometry": {"coordinates":[-93.958079,44.804261],"type":"Point"}
}