{
  "type": "Feature",
  "properties": {
    "iso:country":"US",
    "sg:address":"336 Grace Ave",
    "sg:city":"Clontarf",
    "sg:classifiers":[
        {
            "category":"Building & Trades",
            "subcategory":"Plumbing",
            "type":"Services"
        }
    ],
    "sg:phone":"+1 320 843 4709",
    "sg:postcode":"56226",
    "sg:province":"MN",
    "sg:tags":[
        "septic"
    ],
    "wof:name":"Harry's Pumping Svc",
    "wof:placetype":"venue"
},
  "geometry": {"coordinates":[-95.685453,45.37648],"type":"Point"}
}