{
  "type": "Feature",
  "properties": {
    "iso:country":"US",
    "sg:address":"570 Hale Ave N",
    "sg:city":"St Paul",
    "sg:classifiers":[
        {
            "category":"Professional",
            "subcategory":"Research",
            "type":"Services"
        }
    ],
    "sg:phone":"+1 651 730 6203",
    "sg:postcode":"55128",
    "sg:province":"MN",
    "sg:tags":[
        "development",
        "manufacture",
        "material",
        "contract",
        "laboratory"
    ],
    "sg:website":"www.superfabric.com",
    "wof:name":"Higher Dimension Research Inc",
    "wof:placetype":"venue"
},
  "geometry": {"coordinates":[-92.961231,44.955304],"type":"Point"}
}