{
  "type": "Feature",
  "properties": {
    "addr:full":"33 Little Canada Rd E Little Canada MN 55117",
    "addr:housenumber":"33",
    "addr:postcode":"55117",
    "addr:street":"Little Canada Rd E",
    "iso:country":"US",
    "sg:address":"33 Little Canada Rd E",
    "sg:city":"Little Canada",
    "sg:classifiers":[
        {
            "category":"Restaurant",
            "type":"Food & Drink"
        }
    ],
    "sg:phone":"+1 651 486 9218",
    "sg:postcode":"55117",
    "sg:province":"MN",
    "sg:tags":[
        "eating",
        "caterer"
    ],
    "wof:name":"Cher's Deli",
    "wof:placetype":"venue"
},
  "geometry": {"coordinates":[-93.099313,45.02556],"type":"Point"}
}