{
  "type": "Feature",
  "properties": {
    "addr:full":"17661 George Moran Dr Eden Prairie MN 55347",
    "addr:housenumber":"17661",
    "addr:postcode":"55347",
    "addr:street":"George Moran Dr",
    "iso:country":"US",
    "sg:address":"17661 George Moran Dr",
    "sg:city":"Eden Prairie",
    "sg:classifiers":[
        {
            "category":"Professional",
            "subcategory":"Computer Services",
            "type":"Services"
        }
    ],
    "sg:phone":"+1 952 974 3853",
    "sg:postcode":"55347",
    "sg:province":"MN",
    "sg:tags":[
        "related"
    ],
    "wof:name":"Medha Group Inc",
    "wof:placetype":"venue"
},
  "geometry": {"coordinates":[-93.501175,44.855603],"type":"Point"}
}