{
  "type": "Feature",
  "properties": {
    "addr:full":"38503 Scenic Hwy Bovey MN 55709",
    "addr:housenumber":"38503",
    "addr:postcode":"55709",
    "addr:street":"Scenic Hwy",
    "iso:country":"US",
    "sg:address":"38503 Scenic Hwy",
    "sg:city":"Bovey",
    "sg:classifiers":[
        {
            "category":"Personal",
            "subcategory":"Beauty Salon",
            "type":"Services"
        }
    ],
    "sg:phone":"+1 218 245 2045",
    "sg:postcode":"55709",
    "sg:province":"MN",
    "wof:name":"Eva Card Hair Care",
    "wof:placetype":"venue"
},
  "geometry": {"coordinates":[-93.37906599999999,47.440971],"type":"Point"}
}