{
  "type": "Feature",
  "properties": {
    "addr:full":"44322 State Hwy 111 Nicollet MN 56074",
    "addr:housenumber":"44322",
    "addr:postcode":"56074",
    "addr:street":"State Hwy 111",
    "iso:country":"US",
    "sg:address":"44322 State Hwy 111",
    "sg:city":"Nicollet",
    "sg:phone":"+1 507 232 3621",
    "sg:postcode":"56074",
    "sg:province":"MN",
    "sg:tags":[
        "farm",
        "corn",
        "soybean"
    ],
    "wof:name":"Paul Honken",
    "wof:placetype":"venue"
},
  "geometry": {"coordinates":[-94.19063,44.3121],"type":"Point"}
}