{
  "type": "Feature",
  "properties": {
    "addr:full":"28685 700th Ave Redwood Falls MN 56283",
    "addr:housenumber":"28685",
    "addr:postcode":"56283",
    "addr:street":"700Th Ave",
    "iso:country":"US",
    "sg:address":"28685 700th Ave",
    "sg:city":"Redwood Falls",
    "sg:phone":"+1 507 641 3177",
    "sg:postcode":"56283",
    "sg:province":"MN",
    "sg:tags":[
        "farm",
        "corn",
        "soybean"
    ],
    "wof:name":"Dolezal Miloyd",
    "wof:placetype":"venue"
},
  "geometry": {"coordinates":[-95.094725,44.599583],"type":"Point"}
}