{
  "type": "Feature",
  "properties": {
    "addr:full":"2907 Pentagon Dr Minneapolis MN 55418",
    "addr:housenumber":"2907",
    "addr:postcode":"55418",
    "addr:street":"Pentagon Dr",
    "iso:country":"US",
    "sg:address":"2907 Pentagon Dr",
    "sg:city":"Minneapolis",
    "sg:classifiers":[
        {
            "category":"Education",
            "subcategory":"Dance Studio",
            "type":"Public Place"
        }
    ],
    "sg:phone":"+1 612 789 0001",
    "sg:postcode":"55418",
    "sg:province":"MN",
    "sg:tags":[
        "instruction",
        "dancing"
    ],
    "wof:name":"Dance & Cheer Factory",
    "wof:placetype":"venue"
},
  "geometry": {"coordinates":[-93.220198,45.016268],"type":"Point"}
}