{
  "type": "Feature",
  "properties": {
    "addr:full":"12651 Zenith Ave S Burnsville MN 55337",
    "addr:housenumber":"12651",
    "addr:postcode":"55337",
    "addr:street":"Zenith Ave S",
    "iso:country":"US",
    "sg:address":"12651 Zenith Ave S",
    "sg:city":"Burnsville",
    "sg:classifiers":[
        {
            "category":"Building & Trades",
            "subcategory":"Electrical",
            "type":"Services"
        }
    ],
    "sg:phone":"+1 952 890 8882",
    "sg:postcode":"55337",
    "sg:province":"MN",
    "sg:tags":[
        "electrical",
        "contractor"
    ],
    "wof:name":"Jenkins Electric & Automation",
    "wof:placetype":"venue"
},
  "geometry": {"coordinates":[-93.32028699999999,44.774095],"type":"Point"}
}