{
  "type": "Feature",
  "properties": {
    "addr:full":"4520 240th St E Faribault MN 55021",
    "addr:housenumber":"4520",
    "addr:postcode":"55021",
    "addr:street":"240Th St E",
    "iso:country":"US",
    "sg:address":"4520 240th St E",
    "sg:city":"Faribault",
    "sg:classifiers":[
        {
            "category":"Shopping",
            "subcategory":"Gifts & Souvenirs",
            "type":"Retail Goods"
        }
    ],
    "sg:phone":"+1 507 334 4169",
    "sg:postcode":"55021",
    "sg:province":"MN",
    "wof:name":"R & S Cnstr of Faribault",
    "wof:placetype":"venue"
},
  "geometry": {"coordinates":[-93.214685,44.23993],"type":"Point"}
}