{
  "type": "Feature",
  "properties": {
    "addr:full":"16582 Havelock Way Lakeville MN 55044",
    "addr:housenumber":"16582",
    "addr:postcode":"55044",
    "addr:street":"Havelock Way",
    "iso:country":"US",
    "sg:address":"16582 Havelock Way",
    "sg:city":"Lakeville",
    "sg:classifiers":[
        {
            "category":"Food & Beverages",
            "subcategory":"Specialty",
            "type":"Retail Goods"
        }
    ],
    "sg:phone":"+1 952 432 1817",
    "sg:postcode":"55044",
    "sg:province":"MN",
    "sg:tags":[
        "product",
        "health",
        "diet"
    ],
    "wof:name":"Kevin Walters",
    "wof:placetype":"venue"
},
  "geometry": {"coordinates":[-93.228511,44.708633],"type":"Point"}
}