{
  "type": "Feature",
  "properties": {
    "addr:full":"15255 23rd Ave N Minneapolis MN 55447",
    "addr:housenumber":"15255",
    "addr:postcode":"55447",
    "addr:street":"23Rd Ave N",
    "iso:country":"US",
    "sg:address":"15255 23rd Ave N",
    "sg:city":"Minneapolis",
    "sg:classifiers":[
        {
            "category":"Wholesale",
            "subcategory":"Photographic Equipment",
            "type":"Manufacturing & Wholesale Goods"
        }
    ],
    "sg:phone":"+1 763 404 1248",
    "sg:postcode":"55447",
    "sg:province":"MN",
    "sg:tags":[
        "supplies-wholesale",
        "manufacturer"
    ],
    "wof:name":"Loon Photographic, Inc",
    "wof:placetype":"venue"
},
  "geometry": {"coordinates":[-93.473263,45.00388],"type":"Point"}
}