{
  "type": "Feature",
  "properties": {
    "addr:full":"4205 Minnesota Ln N Minneapolis MN 55446",
    "addr:housenumber":"4205",
    "addr:postcode":"55446",
    "addr:street":"Minnesota Ln N",
    "iso:country":"US",
    "sg:address":"4205 Minnesota Ln N",
    "sg:city":"Minneapolis",
    "sg:classifiers":[
        {
            "category":"Professional",
            "subcategory":"Business Services",
            "type":"Services"
        }
    ],
    "sg:phone":"+1 612 673 1158",
    "sg:postcode":"55446",
    "sg:province":"MN",
    "sg:tags":[
        "interior",
        "consultant",
        "design",
        "decorator"
    ],
    "wof:name":"Kathryn Johnson Interior Dsgn",
    "wof:placetype":"venue"
},
  "geometry": {"coordinates":[-93.47083000000001,45.032225],"type":"Point"}
}