{
  "type": "Feature",
  "properties": {
    "iso:country":"US",
    "sg:address":"499 Arrowhead Ln",
    "sg:city":"Moose Lake",
    "sg:classifiers":[
        {
            "category":"Retail",
            "subcategory":"Veterinary Services",
            "type":"Services"
        }
    ],
    "sg:phone":"+1 218 485 4539",
    "sg:postcode":"55767",
    "sg:province":"MN",
    "sg:tags":[
        "veterinarian"
    ],
    "wof:name":"Arrowhead Lane Pet Clinic",
    "wof:placetype":"venue"
},
  "geometry": {"coordinates":[-92.75986399999999,46.455618],"type":"Point"}
}