{
  "type": "Feature",
  "properties": {
    "iso:country":"US",
    "sg:address":"3451 W Burnsville Pkwy",
    "sg:city":"Burnsville",
    "sg:classifiers":[
        {
            "category":"Communications",
            "type":"Services"
        }
    ],
    "sg:phone":"+1 952 890 9025",
    "sg:postcode":"55337",
    "sg:province":"MN",
    "wof:name":"Cyclone Communications",
    "wof:placetype":"venue"
},
  "geometry": {"coordinates":[-93.322897,44.747104],"type":"Point"}
}