{
  "type": "Feature",
  "properties": {
    "addr:full":"1418 Co Rd 19 Rothsay MN 56548",
    "addr:housenumber":"1418;19",
    "addr:postcode":"56548",
    "addr:street":"Co Rd",
    "iso:country":"US",
    "sg:address":"1418 Co Rd 19",
    "sg:city":"Rothsay",
    "sg:classifiers":[
        {
            "category":"Farming",
            "subcategory":"Livestock Farm",
            "type":"Manufacturing & Wholesale Goods"
        }
    ],
    "sg:phone":"+1 218 867 2650",
    "sg:postcode":"56548",
    "sg:province":"MN",
    "sg:tags":[
        "animal",
        "general"
    ],
    "wof:name":"Wayne Nosal",
    "wof:placetype":"venue"
},
  "geometry": {"coordinates":[-96.769547,47.361133],"type":"Point"}
}