{
  "type": "Feature",
  "properties": {
    "addr:full":"1092 161st St Pipestone MN 56164",
    "addr:housenumber":"1092",
    "addr:postcode":"56164",
    "addr:street":"161St St",
    "iso:country":"US",
    "sg:address":"1092 161st St",
    "sg:city":"Pipestone",
    "sg:classifiers":[
        {
            "category":"Building & Trades",
            "subcategory":"Construction",
            "type":"Services"
        }
    ],
    "sg:phone":"+1 507 820 1061",
    "sg:postcode":"56164",
    "sg:province":"MN",
    "sg:tags":[
        "concrete",
        "contractor"
    ],
    "wof:name":"Fuller Paving",
    "wof:placetype":"venue"
},
  "geometry": {"coordinates":[-96.244968,44.081196],"type":"Point"}
}