{
  "type": "Feature",
  "properties": {
    "addr:full":"11203 Sunset Trl Minneapolis MN 55441",
    "addr:housenumber":"11203",
    "addr:postcode":"55441",
    "addr:street":"Sunset Trl",
    "iso:country":"US",
    "sg:address":"11203 Sunset Trl",
    "sg:city":"Minneapolis",
    "sg:classifiers":[
        {
            "category":"Professional",
            "subcategory":"Business Services",
            "type":"Services"
        }
    ],
    "sg:phone":"+1 763 542 3090",
    "sg:postcode":"55441",
    "sg:province":"MN",
    "sg:tags":[
        "consultant",
        "coach"
    ],
    "wof:name":"Patrick Casey Consulting",
    "wof:placetype":"venue"
},
  "geometry": {"coordinates":[-93.42289599999999,44.983918],"type":"Point"}
}