{
  "type": "Feature",
  "properties": {
    "iso:country":"US",
    "sg:address":"4741 Patterson Trl",
    "sg:city":"Brainerd",
    "sg:classifiers":[
        {
            "category":"Building & Trades",
            "subcategory":"Plumbing",
            "type":"Services"
        }
    ],
    "sg:phone":"+1 218 828 1552",
    "sg:postcode":"56401",
    "sg:province":"MN",
    "sg:tags":[
        "contractor"
    ],
    "wof:name":"Jibec Co Inc",
    "wof:placetype":"venue"
},
  "geometry": {"coordinates":[-94.30437499999999,46.379643],"type":"Point"}
}