{
  "type": "Feature",
  "properties": {
    "iso:country":"US",
    "sg:address":"3745 Ximines Ln N",
    "sg:city":"Minneapolis",
    "sg:classifiers":[
        {
            "category":"Retail",
            "subcategory":"Portrait Studio",
            "type":"Services"
        },
        {
            "category":"Professional",
            "subcategory":"Art Services",
            "type":"Services"
        }
    ],
    "sg:phone":"+1 763 544 1231",
    "sg:postcode":"55441",
    "sg:province":"MN",
    "sg:tags":[
        "photographer",
        "design",
        "commercial",
        "photo"
    ],
    "wof:name":"Adams Street Photography",
    "wof:placetype":"venue"
},
  "geometry": {"coordinates":[-93.420002,45.024393],"type":"Point"}
}