{
  "type": "Feature",
  "properties": {
    "addr:full":"113 W 1st St Minneota MN 56264",
    "addr:housenumber":"113",
    "addr:postcode":"56264",
    "addr:street":"W 1St St",
    "iso:country":"US",
    "sg:address":"113 W 1st St",
    "sg:city":"Minneota",
    "sg:classifiers":[
        {
            "category":"Autos & Motor Vehicles",
            "subcategory":"Automobile Sales",
            "type":"Retail Goods"
        }
    ],
    "sg:phone":"+1 507 872 5941",
    "sg:postcode":"56264",
    "sg:province":"MN",
    "sg:tags":[
        "used"
    ],
    "wof:name":"Country Side Auto",
    "wof:placetype":"venue"
},
  "geometry": {"coordinates":[-95.988981,44.560275],"type":"Point"}
}