{
  "type": "Feature",
  "properties": {
    "addr:full":"133 W 1st St Waconia MN 55387",
    "addr:housenumber":"133",
    "addr:postcode":"55387",
    "addr:street":"W 1St St",
    "iso:country":"US",
    "sg:address":"133 W 1st St",
    "sg:city":"Waconia",
    "sg:classifiers":[
        {
            "category":"Health Services",
            "subcategory":"Dentist",
            "type":"Services"
        }
    ],
    "sg:phone":"+1 952 442 2816",
    "sg:postcode":"55387",
    "sg:province":"MN",
    "sg:tags":[
        "product",
        "whitening",
        "teeth"
    ],
    "sg:website":"http://www.dmadentistry.com",
    "wof:name":"Drs. Dungey, Menser & Associates",
    "wof:placetype":"venue"
},
  "geometry": {"coordinates":[-93.788112,44.849354],"type":"Point"}
}