{
  "type": "Feature",
  "properties": {
    "addr:full":"818 W 46th St Minneapolis MN 55419",
    "addr:housenumber":"818",
    "addr:postcode":"55419",
    "addr:street":"W 46Th St",
    "iso:country":"US",
    "sg:address":"818 W 46th St",
    "sg:city":"Minneapolis",
    "sg:classifiers":[
        {
            "category":"Coffee & Tea",
            "type":"Food & Drink"
        },
        {
            "category":"Restaurant",
            "type":"Food & Drink"
        }
    ],
    "sg:phone":"+1 612 825 2183",
    "sg:postcode":"55419",
    "sg:province":"MN",
    "sg:tags":[
        "brunch",
        "breakfast"
    ],
    "sg:website":"www.jacksmpls.com/",
    "wof:name":"Jack's",
    "wof:placetype":"venue"
},
  "geometry": {"coordinates":[-93.29042099999999,44.919555],"type":"Point"}
}