{
  "type": "Feature",
  "properties": {
    "iso:country":"US",
    "sg:address":"30130 360th St NW",
    "sg:city":"Argyle",
    "sg:classifiers":[
        {
            "category":"Real Estate",
            "subcategory":"Real Estate Operator",
            "type":"Services"
        }
    ],
    "sg:phone":"+1 218 437 8267",
    "sg:postcode":"56713",
    "sg:province":"MN",
    "sg:tags":[
        "property",
        "lessor"
    ],
    "wof:name":"Conrad Hapka",
    "wof:placetype":"venue"
},
  "geometry": {"coordinates":[-96.695986,48.398937],"type":"Point"}
}