{
  "type": "Feature",
  "properties": {
    "iso:country":"US",
    "sg:address":"722 N Pokegama Ave",
    "sg:city":"Grand Rapids",
    "sg:classifiers":[
        {
            "category":"Social Services",
            "subcategory":"Adult Care",
            "type":"Services"
        }
    ],
    "sg:phone":"+1 218 326 3469",
    "sg:postcode":"55744",
    "sg:province":"MN",
    "sg:tags":[
        "home",
        "retirement"
    ],
    "wof:name":"Manor House",
    "wof:placetype":"venue"
},
  "geometry": {"coordinates":[-93.528216,47.240045],"type":"Point"}
}