{
  "type": "Feature",
  "properties": {
    "addr:full":"215 Saint Olaf Ave N Canby MN 56220",
    "addr:housenumber":"215",
    "addr:postcode":"56220",
    "addr:street":"Saint Olaf Ave N",
    "iso:country":"US",
    "sg:address":"215 Saint Olaf Ave N",
    "sg:city":"Canby",
    "sg:classifiers":[
        {
            "category":"Building & Trades",
            "subcategory":"Construction",
            "type":"Services"
        }
    ],
    "sg:phone":"+1 507 223 7791",
    "sg:postcode":"56220",
    "sg:province":"MN",
    "sg:tags":[
        "designer"
    ],
    "wof:name":"Epcos Inc",
    "wof:placetype":"venue"
},
  "geometry": {"coordinates":[-96.274168,44.710256],"type":"Point"}
}