{
  "type": "Feature",
  "properties": {
    "addr:full":"8851 Zealand Ave N Minneapolis MN 55445",
    "addr:housenumber":"8851",
    "addr:postcode":"55445",
    "addr:street":"Zealand Ave N",
    "iso:country":"US",
    "sg:address":"8851 Zealand Ave N",
    "sg:city":"Minneapolis",
    "sg:classifiers":[
        {
            "category":"Banks & Credit Unions",
            "subcategory":"Bank",
            "type":"Services"
        }
    ],
    "sg:phone":"+1 763 416 9393",
    "sg:postcode":"55445",
    "sg:province":"MN",
    "sg:tags":[
        "loan",
        "real estate"
    ],
    "wof:name":"Global Mortgage",
    "wof:placetype":"venue"
},
  "geometry": {"coordinates":[-93.388228,45.114227],"type":"Point"}
}