{
  "type": "Feature",
  "properties": {
    "addr:full":"7406 Central Ave NE Minneapolis MN 55432",
    "addr:housenumber":"7406",
    "addr:postcode":"55432",
    "addr:street":"Central Ave Ne",
    "iso:country":"US",
    "sg:address":"7406 Central Ave NE",
    "sg:city":"Minneapolis",
    "sg:classifiers":[
        {
            "category":"Building & Trades",
            "subcategory":"Electrical",
            "type":"Services"
        },
        {
            "category":"Utilities",
            "subcategory":"Cable",
            "type":"Services"
        }
    ],
    "sg:phone":"+1 763 780 6270",
    "sg:postcode":"55432",
    "sg:province":"MN",
    "sg:tags":[
        "product",
        "wire",
        "products-wholesale",
        "manufacturer"
    ],
    "sg:website":"http://www.tensacc.com",
    "wof:name":"Tens-Acc, Inc.",
    "wof:placetype":"venue"
},
  "geometry": {"coordinates":[-93.23809799999999,45.102341],"type":"Point"}
}