{
  "type": "Feature",
  "properties": {
    "addr:full":"2608 Tranquility Dr Saint Cloud MN 56301",
    "addr:housenumber":"2608",
    "addr:postcode":"56301",
    "addr:street":"Tranquility Dr",
    "iso:country":"US",
    "sg:address":"2608 Tranquility Dr",
    "sg:city":"Saint Cloud",
    "sg:classifiers":[
        {
            "category":"Building & Trades",
            "subcategory":"Plumbing",
            "type":"Services"
        }
    ],
    "sg:phone":"+1 320 202 5999",
    "sg:postcode":"56301",
    "sg:province":"MN",
    "sg:tags":[
        "m",
        "contractor"
    ],
    "wof:name":"Sprinkler Guy",
    "wof:placetype":"venue"
},
  "geometry": {"coordinates":[-94.176225,45.529246],"type":"Point"}
}