{
  "type": "Feature",
  "properties": {
    "addr:full":"10 Alice Ct South St Paul MN 55075",
    "addr:housenumber":"10",
    "addr:postcode":"55075",
    "addr:street":"Alice Ct",
    "iso:country":"US",
    "sg:address":"10 Alice Ct",
    "sg:city":"South St Paul",
    "sg:classifiers":[
        {
            "category":"Professional",
            "subcategory":"Management & Consulting",
            "type":"Services"
        }
    ],
    "sg:phone":"+1 651 552 8301",
    "sg:postcode":"55075",
    "sg:province":"MN",
    "sg:tags":[
        "consultant",
        "business"
    ],
    "wof:name":"St Anthony Consulting",
    "wof:placetype":"venue"
},
  "geometry": {"coordinates":[-93.05637299999999,44.885426],"type":"Point"}
}