{
  "type": "Feature",
  "properties": {
    "iso:country":"US",
    "sg:address":"1143 E Jessamine Ave",
    "sg:city":"Saint Paul",
    "sg:classifiers":[
        {
            "category":"Building & Trades",
            "subcategory":"Construction",
            "type":"Services"
        }
    ],
    "sg:phone":"+1 612 978 5275",
    "sg:postcode":"55106",
    "sg:province":"MN",
    "sg:tags":[
        "house"
    ],
    "wof:name":"Trimsaw Construction LLC",
    "wof:placetype":"venue"
},
  "geometry": {"coordinates":[-93.05143200000001,44.9749],"type":"Point"}
}