{
  "type": "Feature",
  "properties": {
    "iso:country":"US",
    "sg:address":"1577 Grand Ave",
    "sg:city":"Saint Paul",
    "sg:classifiers":[
        {
            "category":"Restaurant",
            "type":"Food & Drink"
        }
    ],
    "sg:menulink":"http://www.allmenus.com/mn/st-paul/174614-jamba-juice/menu/",
    "sg:phone":"+1 651 695 0080",
    "sg:postcode":"55105",
    "sg:province":"MN",
    "sg:tags":[
        "smoothy",
        "juice",
        "american"
    ],
    "wof:name":"Jamba Juice",
    "wof:placetype":"venue"
},
  "geometry": {"coordinates":[-93.166605,44.940047],"type":"Point"}
}