{
  "type": "Feature",
  "properties": {
    "addr:full":"7037 Cahill Rd Minneapolis MN 55439",
    "addr:housenumber":"7037",
    "addr:postcode":"55439",
    "addr:street":"Cahill Rd",
    "iso:country":"US",
    "sg:address":"7037 Cahill Rd",
    "sg:city":"Minneapolis",
    "sg:classifiers":[
        {
            "category":"Sports & Exercise",
            "subcategory":"Gym",
            "type":"Entertainment"
        }
    ],
    "sg:phone":"+1 952 918 9000",
    "sg:postcode":"55439",
    "sg:province":"MN",
    "sg:tags":[
        "fitness",
        "physical",
        "facility"
    ],
    "wof:name":"Arete Healthfit",
    "wof:placetype":"venue"
},
  "geometry": {"coordinates":[-93.363344,44.875833],"type":"Point"}
}