{
  "type": "Feature",
  "properties": {
    "addr:full":"35972 704th Ave Kimball MN 55353",
    "addr:housenumber":"35972",
    "addr:postcode":"55353",
    "addr:street":"704Th Ave",
    "iso:country":"US",
    "sg:address":"35972 704th Ave",
    "sg:city":"Kimball",
    "sg:phone":"+1 320 398 8110",
    "sg:postcode":"55353",
    "sg:province":"MN",
    "sg:tags":[
        "farm",
        "corn",
        "wheat"
    ],
    "wof:name":"Heid Brothers Harvesting Inc",
    "wof:placetype":"venue"
},
  "geometry": {"coordinates":[-94.348099,45.264443],"type":"Point"}
}