{
  "type": "Feature",
  "properties": {
    "iso:country":"US",
    "sg:address":"1041 Deer Ridge Ct NW",
    "sg:city":"Lonsdale",
    "sg:classifiers":[
        {
            "category":"Food & Beverages",
            "subcategory":"Specialty",
            "type":"Retail Goods"
        }
    ],
    "sg:phone":"+1 507 744 5820",
    "sg:postcode":"55046",
    "sg:province":"MN",
    "sg:tags":[
        "water",
        "bulk",
        "company"
    ],
    "wof:name":"Jim's Water Svc",
    "wof:placetype":"venue"
},
  "geometry": {"coordinates":[-93.445179,44.483158],"type":"Point"}
}