{
  "type": "Feature",
  "properties": {
    "iso:country":"US",
    "sg:address":"14447 Hwy 10",
    "sg:city":"Glyndon",
    "sg:classifiers":[
        {
            "category":"Freight",
            "type":"Transportation"
        }
    ],
    "sg:phone":"+1 218 236 9162",
    "sg:postcode":"56547",
    "sg:province":"MN",
    "sg:tags":[
        "carriage"
    ],
    "wof:name":"Alpine Carriages & Sleighs",
    "wof:placetype":"venue"
},
  "geometry": {"coordinates":[-96.49632699999999,46.876988],"type":"Point"}
}