{
  "type": "Feature",
  "properties": {
    "addr:full":"90 Library Ln SW Chatfield MN 55923",
    "addr:housenumber":"90",
    "addr:postcode":"55923",
    "addr:street":"Library Ln Sw",
    "iso:country":"US",
    "sg:address":"90 Library Ln SW",
    "sg:city":"Chatfield",
    "sg:classifiers":[
        {
            "category":"Government",
            "subcategory":"Office",
            "type":"Public Place"
        }
    ],
    "sg:phone":"+1 507 867 4321",
    "sg:postcode":"55923",
    "sg:province":"MN",
    "sg:tags":[
        "village"
    ],
    "wof:name":"Chatfield Wastewater Plant",
    "wof:placetype":"venue"
},
  "geometry": {"coordinates":[-92.18591600000001,43.839228],"type":"Point"}
}