{
  "type": "Feature",
  "properties": {
    "addr:full":"5391 Maple Ridge Ct Hopkins MN 55343",
    "addr:housenumber":"5391",
    "addr:postcode":"55343",
    "addr:street":"Maple Ridge Ct",
    "iso:country":"US",
    "sg:address":"5391 Maple Ridge Ct",
    "sg:city":"Hopkins",
    "sg:classifiers":[
        {
            "category":"Wholesale",
            "subcategory":"Apparel",
            "type":"Manufacturing & Wholesale Goods"
        }
    ],
    "sg:phone":"+1 952 936 0272",
    "sg:postcode":"55343",
    "sg:province":"MN",
    "sg:tags":[
        "apparel-wholesale",
        "manufacturer",
        "clothing",
        "women's"
    ],
    "wof:name":"Jane Harrison Inc",
    "wof:placetype":"venue"
},
  "geometry": {"coordinates":[-93.43905700000001,44.905252],"type":"Point"}
}