{
  "type": "Feature",
  "properties": {
    "addr:full":"3260 Gorham Ave Minneapolis MN 55426",
    "addr:housenumber":"3260",
    "addr:postcode":"55426",
    "addr:street":"Gorham Ave",
    "iso:country":"US",
    "sg:address":"3260 Gorham Ave",
    "sg:city":"Minneapolis",
    "sg:classifiers":[
        {
            "category":"Building & Trades",
            "subcategory":"Construction",
            "type":"Services"
        }
    ],
    "sg:phone":"+1 952 929 6767",
    "sg:postcode":"55426",
    "sg:province":"MN",
    "sg:tags":[
        "system",
        "contractor",
        "air conditioning"
    ],
    "sg:website":"http://www.vogtheating.com",
    "wof:name":"Fred Vogt & Co.",
    "wof:placetype":"venue"
},
  "geometry": {"coordinates":[-93.370121,44.94408],"type":"Point"}
}