{
  "type": "Feature",
  "properties": {
    "addr:full":"7031 Glenwood Ave Minneapolis MN 55427",
    "addr:housenumber":"7031",
    "addr:postcode":"55427",
    "addr:street":"Glenwood Ave",
    "iso:country":"US",
    "sg:address":"7031 Glenwood Ave",
    "sg:city":"Minneapolis",
    "sg:classifiers":[
        {
            "category":"Professional",
            "subcategory":"Art Services",
            "type":"Services"
        }
    ],
    "sg:phone":"+1 763 545 0051",
    "sg:postcode":"55427",
    "sg:province":"MN",
    "sg:tags":[
        "photography",
        "videography",
        "commercial"
    ],
    "wof:name":"Peter Marcus Photography",
    "wof:placetype":"venue"
},
  "geometry": {"coordinates":[-93.36950299999999,44.981862],"type":"Point"}
}