{
  "type": "Feature",
  "properties": {
    "addr:full":"10 US Hwy 2 Cohasset MN 55721",
    "addr:housenumber":"10",
    "addr:postcode":"55721",
    "addr:street":"Us Hwy 2",
    "iso:country":"US",
    "sg:address":"10 US Hwy 2",
    "sg:city":"Cohasset",
    "sg:classifiers":[
        {
            "category":"Government",
            "subcategory":"Post Office",
            "type":"Public Place"
        }
    ],
    "sg:phone":"+1 218 328 5109",
    "sg:postcode":"55721",
    "sg:province":"MN",
    "wof:name":"US Post Office",
    "wof:placetype":"venue"
},
  "geometry": {"coordinates":[-93.61862499999999,47.262646],"type":"Point"}
}