{
  "type": "Feature",
  "properties": {
    "addr:full":"105 Benjamin St Jackson MN 56143",
    "addr:housenumber":"105",
    "addr:postcode":"56143",
    "addr:street":"Benjamin St",
    "iso:country":"US",
    "sg:address":"105 Benjamin St",
    "sg:city":"Jackson",
    "sg:classifiers":[
        {
            "category":"Building & Trades",
            "subcategory":"Construction",
            "type":"Services"
        }
    ],
    "sg:phone":"+1 507 847 3470",
    "sg:postcode":"56143",
    "sg:province":"MN",
    "sg:tags":[
        "painting",
        "contractor"
    ],
    "wof:name":"Gary L Kaderabek",
    "wof:placetype":"venue"
},
  "geometry": {"coordinates":[-94.984461,43.623633],"type":"Point"}
}