{
  "type": "Feature",
  "properties": {
    "addr:full":"266 33rd Ave S St Cloud MN 56301",
    "addr:housenumber":"266",
    "addr:postcode":"56301",
    "addr:street":"33Rd Ave S",
    "iso:country":"US",
    "sg:address":"266 33rd Ave S",
    "sg:city":"St Cloud",
    "sg:classifiers":[
        {
            "category":"Home & Garden",
            "subcategory":"Furniture",
            "type":"Retail Goods"
        }
    ],
    "sg:phone":"+1 320 203 0850",
    "sg:postcode":"56301",
    "sg:province":"MN",
    "wof:name":"Payments Plus",
    "wof:placetype":"venue"
},
  "geometry": {"coordinates":[-94.198138,45.54771],"type":"Point"}
}