{
  "type": "Feature",
  "properties": {
    "addr:full":"315 W 49th St Minneapolis MN 55419",
    "addr:housenumber":"315",
    "addr:postcode":"55419",
    "addr:street":"W 49Th St",
    "iso:country":"US",
    "sg:address":"315 W 49th St",
    "sg:city":"Minneapolis",
    "sg:classifiers":[
        {
            "category":"Shopping",
            "type":"Retail Goods"
        }
    ],
    "sg:phone":"+1 612 824 8362",
    "sg:postcode":"55419",
    "sg:province":"MN",
    "sg:tags":[
        "merchandise"
    ],
    "wof:name":"D3 Visual Accessories",
    "wof:placetype":"venue"
},
  "geometry": {"coordinates":[-93.28569,44.91415],"type":"Point"}
}