{
  "type": "Feature",
  "properties": {
    "iso:country":"US",
    "sg:address":"725 Minnehaha Ave E",
    "sg:city":"St Paul",
    "sg:classifiers":[
        {
            "category":"Building & Trades",
            "subcategory":"Construction",
            "type":"Services"
        }
    ],
    "sg:phone":"+1 651 771 8923",
    "sg:postcode":"55106",
    "sg:province":"MN",
    "sg:tags":[
        "contractor"
    ],
    "wof:name":"Just Roto Inc",
    "wof:placetype":"venue"
},
  "geometry": {"coordinates":[-93.070488,44.963104],"type":"Point"}
}