{
  "type": "Feature",
  "properties": {
    "addr:full":"36163 S Rose Lake Rd Frazee MN 56544",
    "addr:housenumber":"36163",
    "addr:postcode":"56544",
    "addr:street":"S Rose Lake Rd",
    "iso:country":"US",
    "sg:address":"36163 S Rose Lake Rd",
    "sg:city":"Frazee",
    "sg:classifiers":[
        {
            "category":"Professional",
            "type":"Services"
        }
    ],
    "sg:phone":"+1 218 342 3266",
    "sg:postcode":"56544",
    "sg:province":"MN",
    "sg:tags":[
        "establishment"
    ],
    "wof:name":"Frazier & Frazier",
    "wof:placetype":"venue"
},
  "geometry": {"coordinates":[-95.738866,46.662753],"type":"Point"}
}