{
  "type": "Feature",
  "properties": {
    "addr:full":"785 Lake St E Wayzata MN 55391",
    "addr:housenumber":"785",
    "addr:postcode":"55391",
    "addr:street":"Lake St E",
    "iso:country":"US",
    "sg:address":"785 Lake St E",
    "sg:city":"Wayzata",
    "sg:classifiers":[
        {
            "category":"Personal",
            "subcategory":"Beauty Salon",
            "type":"Services"
        }
    ],
    "sg:phone":"+1 952 258 0200",
    "sg:postcode":"55391",
    "sg:province":"MN",
    "wof:name":"Twiggs Salonspa",
    "wof:placetype":"venue"
},
  "geometry": {"coordinates":[-93.510938,44.969259],"type":"Point"}
}