{
  "type": "Feature",
  "properties": {
    "iso:country":"US",
    "sg:address":"502 Silver St E",
    "sg:city":"Mapleton",
    "sg:classifiers":[
        {
            "category":"Freight",
            "type":"Transportation"
        }
    ],
    "sg:phone":"+1 507 524 4404",
    "sg:postcode":"56065",
    "sg:province":"MN",
    "sg:tags":[
        "grain",
        "elevator"
    ],
    "wof:name":"Grain Commerce Inc",
    "wof:placetype":"venue"
},
  "geometry": {"coordinates":[-93.953495,43.927823],"type":"Point"}
}