{
  "type": "Feature",
  "properties": {
    "addr:full":"23568 Birch Rd Rogers MN 55374",
    "addr:housenumber":"23568",
    "addr:postcode":"55374",
    "addr:street":"Birch Rd",
    "iso:country":"US",
    "sg:address":"23568 Birch Rd",
    "sg:city":"Rogers",
    "sg:classifiers":[
        {
            "category":"Arena",
            "subcategory":"Sports Club",
            "type":"Entertainment"
        }
    ],
    "sg:phone":"+1 763 428 5879",
    "sg:postcode":"55374",
    "sg:province":"MN",
    "sg:tags":[
        "health"
    ],
    "wof:name":"Extreme Training",
    "wof:placetype":"venue"
},
  "geometry": {"coordinates":[-93.581678,45.202895],"type":"Point"}
}