{
  "type": "Feature",
  "properties": {
    "addr:full":"25350 Cedar Lake Rd Long Prairie MN 56347",
    "addr:housenumber":"25350",
    "addr:postcode":"56347",
    "addr:street":"Cedar Lake Rd",
    "iso:country":"US",
    "sg:address":"25350 Cedar Lake Rd",
    "sg:city":"Long Prairie",
    "sg:classifiers":[
        {
            "category":"Farming",
            "subcategory":"Dairy Farm",
            "type":"Manufacturing & Wholesale Goods"
        }
    ],
    "sg:phone":"+1 320 285 4212",
    "sg:postcode":"56347",
    "sg:province":"MN",
    "wof:name":"Ronald Sunderman",
    "wof:placetype":"venue"
},
  "geometry": {"coordinates":[-94.84270600000001,45.846452],"type":"Point"}
}