{
  "type": "Feature",
  "properties": {
    "addr:full":"14430 28th Pl N Minneapolis MN 55447",
    "addr:housenumber":"14430",
    "addr:postcode":"55447",
    "addr:street":"28Th Pl N",
    "iso:country":"US",
    "sg:address":"14430 28th Pl N",
    "sg:city":"Minneapolis",
    "sg:classifiers":[
        {
            "category":"Restaurant",
            "type":"Food & Drink"
        }
    ],
    "sg:phone":"+1 763 559 2557",
    "sg:postcode":"55447",
    "sg:province":"MN",
    "sg:tags":[
        "eating"
    ],
    "wof:name":"Burger King",
    "wof:placetype":"venue"
},
  "geometry": {"coordinates":[-93.462931,45.011464],"type":"Point"}
}