{
  "type": "Feature",
  "properties": {
    "iso:country":"US",
    "sg:address":"14545 Roosevelt Rd SE",
    "sg:city":"Bemidji",
    "sg:classifiers":[
        {
            "category":"Food & Beverages",
            "subcategory":"Groceries & Convenience Stores",
            "type":"Retail Goods"
        }
    ],
    "sg:phone":"+1 218 335 2035",
    "sg:postcode":"56601",
    "sg:province":"MN",
    "wof:name":"Midway Convenience Store",
    "wof:placetype":"venue"
},
  "geometry": {"coordinates":[-94.669506,47.432011],"type":"Point"}
}