{
  "type": "Feature",
  "properties": {
    "iso:country":"US",
    "sg:address":"1020 Bandana Blvd W",
    "sg:city":"St Paul",
    "sg:classifiers":[
        {
            "category":"Shopping",
            "subcategory":"Optical Goods",
            "type":"Retail Goods"
        }
    ],
    "sg:phone":"+1 651 641 7125",
    "sg:postcode":"55108",
    "sg:province":"MN",
    "wof:name":"Beam Optical",
    "wof:placetype":"venue"
},
  "geometry": {"coordinates":[-93.154579,44.970803],"type":"Point"}
}