{
  "type": "Feature",
  "properties": {
    "iso:country":"US",
    "sg:address":"6181 Benjamin St NE",
    "sg:city":"Minneapolis",
    "sg:classifiers":[
        {
            "category":"Professional",
            "subcategory":"Advertising",
            "type":"Services"
        }
    ],
    "sg:phone":"+1 763 572 2212",
    "sg:postcode":"55432",
    "sg:province":"MN",
    "sg:tags":[
        "counselor"
    ],
    "wof:name":"Ram Comm Group",
    "wof:placetype":"venue"
},
  "geometry": {"coordinates":[-93.230026,45.079127],"type":"Point"}
}