{
  "type": "Feature",
  "properties": {
    "addr:full":"10450 Swede Lake Rd Watertown MN 55388",
    "addr:housenumber":"10450",
    "addr:postcode":"55388",
    "addr:street":"Swede Lake Rd",
    "iso:country":"US",
    "sg:address":"10450 Swede Lake Rd",
    "sg:city":"Watertown",
    "sg:classifiers":[
        {
            "category":"Health Services",
            "subcategory":"Health Practitioner",
            "type":"Services"
        }
    ],
    "sg:phone":"+1 952 474 1123",
    "sg:postcode":"55388",
    "sg:province":"MN",
    "sg:tags":[
        "addiction",
        "abuse",
        "drug"
    ],
    "wof:name":"Jerry Elliott",
    "wof:placetype":"venue"
},
  "geometry": {"coordinates":[-93.78810799999999,44.934212],"type":"Point"}
}