{
  "type": "Feature",
  "properties": {
    "addr:full":"2001 Killebrew Dr Bloomington MN 55425",
    "addr:housenumber":"2001",
    "addr:postcode":"55425",
    "addr:street":"Killebrew Dr",
    "iso:country":"US",
    "sg:address":"2001 Killebrew Dr",
    "sg:city":"Bloomington",
    "sg:classifiers":[
        {
            "category":"Professional",
            "subcategory":"Engineering",
            "type":"Services"
        }
    ],
    "sg:phone":"+1 952 854 6555",
    "sg:postcode":"55425",
    "sg:province":"MN",
    "sg:tags":[
        "engineer"
    ],
    "sg:website":"www.williamsengineeringcompany.com",
    "wof:name":"Williams Engineering",
    "wof:placetype":"venue"
},
  "geometry": {"coordinates":[-93.23898800000001,44.852191],"type":"Point"}
}