{
  "type": "Feature",
  "properties": {
    "addr:full":"2340 Niagara Ln N Minneapolis MN 55447",
    "addr:housenumber":"2340",
    "addr:postcode":"55447",
    "addr:street":"Niagara Ln N",
    "iso:country":"US",
    "sg:address":"2340 Niagara Ln N",
    "sg:city":"Minneapolis",
    "sg:classifiers":[
        {
            "category":"Wholesale",
            "subcategory":"Machinery & Supplies",
            "type":"Manufacturing & Wholesale Goods"
        },
        {
            "category":"Wholesale",
            "subcategory":"Hardware",
            "type":"Manufacturing & Wholesale Goods"
        }
    ],
    "sg:phone":"+1 763 473 4640",
    "sg:postcode":"55447",
    "sg:province":"MN",
    "sg:tags":[
        "specialty",
        "air",
        "pump",
        "heating",
        "conditioning",
        "stocking"
    ],
    "wof:name":"R M Cotton Co",
    "wof:placetype":"venue"
},
  "geometry": {"coordinates":[-93.47150499999999,45.005778],"type":"Point"}
}