{
  "type": "Feature",
  "properties": {
    "addr:full":"1291 Tasha Blvd Shakopee MN 55379",
    "addr:housenumber":"1291",
    "addr:postcode":"55379",
    "addr:street":"Tasha Blvd",
    "iso:country":"US",
    "sg:address":"1291 Tasha Blvd",
    "sg:city":"Shakopee",
    "sg:classifiers":[
        {
            "category":"Shopping",
            "subcategory":"Pharmacy",
            "type":"Retail Goods"
        }
    ],
    "sg:phone":"+1 952 233 7321",
    "sg:postcode":"55379",
    "sg:province":"MN",
    "sg:website":"www.walgreens.com",
    "wof:name":"Walgreens",
    "wof:placetype":"venue"
},
  "geometry": {"coordinates":[-93.50685900000001,44.781331],"type":"Point"}
}