{
  "type": "Feature",
  "properties": {
    "addr:full":"517 Minnesota Ave W Walker MN 56484",
    "addr:housenumber":"517",
    "addr:postcode":"56484",
    "addr:street":"Minnesota Ave W",
    "iso:country":"US",
    "sg:address":"517 Minnesota Ave W",
    "sg:city":"Walker",
    "sg:classifiers":[
        {
            "category":"Organizations",
            "subcategory":"Religious Organization",
            "type":"Services"
        }
    ],
    "sg:phone":"+1 218 547 1919",
    "sg:postcode":"56484",
    "sg:province":"MN",
    "sg:tags":[
        "church"
    ],
    "wof:name":"Living Water",
    "wof:placetype":"venue"
},
  "geometry": {"coordinates":[-94.582819,47.101777],"type":"Point"}
}