{
  "type": "Feature",
  "properties": {
    "addr:full":"627 Snelling Ave S St Paul MN 55116",
    "addr:housenumber":"627",
    "addr:postcode":"55116",
    "addr:street":"Snelling Ave S",
    "iso:country":"US",
    "sg:address":"627 Snelling Ave S",
    "sg:city":"St Paul",
    "sg:classifiers":[
        {
            "category":"Health Services",
            "subcategory":"Health Practitioner",
            "type":"Services"
        }
    ],
    "sg:phone":"+1 651 699 7050",
    "sg:postcode":"55116",
    "sg:province":"MN",
    "sg:tags":[
        "psychologist"
    ],
    "wof:name":"Stellrecht Clinic",
    "wof:placetype":"venue"
},
  "geometry": {"coordinates":[-93.1671,44.923109],"type":"Point"}
}