{
  "type": "Feature",
  "properties": {
    "iso:country":"US",
    "sg:address":"106 Burlwood Cir",
    "sg:city":"Big Lake",
    "sg:classifiers":[
        {
            "category":"Retail",
            "subcategory":"Laundry & Dry Cleaning",
            "type":"Services"
        }
    ],
    "sg:phone":"+1 763 263 0891",
    "sg:postcode":"55309",
    "sg:province":"MN",
    "sg:tags":[
        "drycleaning",
        "plant"
    ],
    "wof:name":"Northern Lights Cleaners",
    "wof:placetype":"venue"
},
  "geometry": {"coordinates":[-93.74521,45.324097],"type":"Point"}
}