{
  "type": "Feature",
  "properties": {
    "addr:full":"124 9th St S Olivia MN 56277",
    "addr:housenumber":"124",
    "addr:postcode":"56277",
    "addr:street":"9Th St S Olivia",
    "iso:country":"US",
    "sg:address":"124 9th St S",
    "sg:city":"Olivia",
    "sg:classifiers":[
        {
            "category":"Home & Garden",
            "subcategory":"Hardware",
            "type":"Retail Goods"
        }
    ],
    "sg:phone":"+1 320 523 1011",
    "sg:postcode":"56277",
    "sg:province":"MN",
    "sg:tags":[
        "store"
    ],
    "wof:name":"Olivia Hardware Inc",
    "wof:placetype":"venue"
},
  "geometry": {"coordinates":[-94.98947699999999,44.776218],"type":"Point"}
}