{
  "type": "Feature",
  "properties": {
    "iso:country":"US",
    "sg:address":"802 E Lincoln Ave",
    "sg:city":"Olivia",
    "sg:classifiers":[
        {
            "category":"Food & Beverages",
            "subcategory":"Liquor & Beverages",
            "type":"Retail Goods"
        }
    ],
    "sg:phone":"+1 320 523 9988",
    "sg:postcode":"56277",
    "sg:province":"MN",
    "sg:tags":[
        "store"
    ],
    "wof:name":"Olivia Municipal Liquors",
    "wof:placetype":"venue"
},
  "geometry": {"coordinates":[-94.987982,44.776512],"type":"Point"}
}