{
  "type": "Feature",
  "properties": {
    "addr:full":"2812 27th Ave S Minneapolis MN 55406",
    "addr:housenumber":"2812",
    "addr:postcode":"55406",
    "addr:street":"27Th Ave S",
    "iso:country":"US",
    "sg:address":"2812 27th Ave S",
    "sg:city":"Minneapolis",
    "sg:classifiers":[
        {
            "category":"Transit Center",
            "subcategory":"Freight",
            "type":"Transportation"
        },
        {
            "category":"Freight",
            "type":"Transportation"
        }
    ],
    "sg:phone":"+1 612 721 6193",
    "sg:postcode":"55406",
    "sg:province":"MN",
    "sg:tags":[
        "local",
        "trucking-motor",
        "trucking"
    ],
    "wof:name":"Dan Wenker Trucking",
    "wof:placetype":"venue"
},
  "geometry": {"coordinates":[-93.233143,44.951794],"type":"Point"}
}