{
  "type": "Feature",
  "properties": {
    "addr:full":"1316 4th St SE Minneapolis MN 55414",
    "addr:housenumber":"1316",
    "addr:postcode":"55414",
    "addr:street":"4Th St Se",
    "iso:country":"US",
    "sg:address":"1316 4th St SE",
    "sg:city":"Minneapolis",
    "sg:classifiers":[
        {
            "category":"Restaurant",
            "type":"Food & Drink"
        }
    ],
    "sg:phone":"+1 612 746 5628",
    "sg:postcode":"55414",
    "sg:province":"MN",
    "sg:tags":[
        "eating"
    ],
    "wof:name":"Red Rocket Sandwiches",
    "wof:placetype":"venue"
},
  "geometry": {"coordinates":[-93.235906,44.980644],"type":"Point"}
}