{
  "type": "Feature",
  "properties": {
    "iso:country":"US",
    "sg:address":"3060 Centerville Rd",
    "sg:city":"Little Canada",
    "sg:classifiers":[
        {
            "category":"Home & Garden",
            "subcategory":"Furniture",
            "type":"Retail Goods"
        }
    ],
    "sg:phone":"+1 651 482 7500",
    "sg:postcode":"55117",
    "sg:province":"MN",
    "sg:website":"www.slumberland.com",
    "wof:name":"Slumberland Inc",
    "wof:placetype":"venue"
},
  "geometry": {"coordinates":[-93.08747099999999,45.03296],"type":"Point"}
}