{
  "type": "Feature",
  "properties": {
    "iso:country":"US",
    "sg:address":"597 Central Ave W",
    "sg:city":"St Michael",
    "sg:classifiers":[
        {
            "category":"Manufacturing",
            "subcategory":"Building Materials",
            "type":"Manufacturing & Wholesale Goods"
        }
    ],
    "sg:phone":"+1 763 497 3496",
    "sg:postcode":"55376",
    "sg:province":"MN",
    "sg:tags":[
        "mfg",
        "wood",
        "kitchen",
        "cabinet"
    ],
    "wof:name":"Gardas Cabinets",
    "wof:placetype":"venue"
},
  "geometry": {"coordinates":[-93.677317,45.207138],"type":"Point"}
}