{
  "type": "Feature",
  "properties": {
    "iso:country":"US",
    "sg:address":"358 Maple St NE",
    "sg:city":"Minneapolis",
    "sg:classifiers":[
        {
            "category":"Building & Trades",
            "subcategory":"Construction",
            "type":"Services"
        }
    ],
    "sg:phone":"+1 763 783 0708",
    "sg:postcode":"55432",
    "sg:province":"MN",
    "sg:tags":[
        "siding",
        "contractor"
    ],
    "wof:name":"Affordable Stucco Company",
    "wof:placetype":"venue"
},
  "geometry": {"coordinates":[-93.259597,45.123472],"type":"Point"}
}