{
  "type": "Feature",
  "properties": {
    "addr:full":"135 2nd Ave NW Harmony MN 55939",
    "addr:housenumber":"135",
    "addr:postcode":"55939",
    "addr:street":"2Nd Ave Nw",
    "iso:country":"US",
    "sg:address":"135 2nd Ave NW",
    "sg:city":"Harmony",
    "sg:classifiers":[
        {
            "category":"Freight",
            "type":"Transportation"
        }
    ],
    "sg:phone":"+1 507 886 2215",
    "sg:postcode":"55939",
    "sg:province":"MN",
    "sg:tags":[
        "frozen",
        "food",
        "locker",
        "plant"
    ],
    "wof:name":"Harmony Cold Storage",
    "wof:placetype":"venue"
},
  "geometry": {"coordinates":[-92.012505,43.555976],"type":"Point"}
}