{
  "type": "Feature",
  "properties": {
    "iso:country":"US",
    "sg:address":"150 S 5th St",
    "sg:city":"Minneapolis",
    "sg:classifiers":[
        {
            "category":"Professional",
            "subcategory":"Lawyer & Legal Services",
            "type":"Services"
        }
    ],
    "sg:phone":"+1 612 335 1609",
    "sg:postcode":"55402",
    "sg:province":"MN",
    "wof:name":"Nancy A Wiltgen",
    "wof:placetype":"venue"
},
  "geometry": {"coordinates":[-93.26833999999999,44.978009],"type":"Point"}
}