{
  "type": "Feature",
  "properties": {
    "iso:country":"US",
    "sg:address":"225 S 6th St",
    "sg:city":"Minneapolis",
    "sg:classifiers":[
        {
            "category":"Coffee & Tea",
            "type":"Food & Drink"
        }
    ],
    "sg:menulink":"http://www.allmenus.com/mn/minneapolis/58605-caribou-coffee/menu/",
    "sg:phone":"+1 612 333 5003",
    "sg:postcode":"55402",
    "sg:province":"MN",
    "sg:tags":[
        "american"
    ],
    "wof:name":"Caribou Coffee",
    "wof:placetype":"venue"
},
  "geometry": {"coordinates":[-93.26829600000001,44.976541],"type":"Point"}
}