{
  "type": "Feature",
  "properties": {
    "addr:full":"6048 Lakeland Ave N Minneapolis MN 55428",
    "addr:housenumber":"6048",
    "addr:postcode":"55428",
    "addr:street":"Lakeland Ave N",
    "iso:country":"US",
    "sg:address":"6048 Lakeland Ave N",
    "sg:city":"Minneapolis",
    "sg:classifiers":[
        {
            "category":"Autos & Motor Vehicles",
            "subcategory":"Automobile Sales",
            "type":"Retail Goods"
        }
    ],
    "sg:phone":"+1 763 535 2277",
    "sg:postcode":"55428",
    "sg:province":"MN",
    "sg:tags":[
        "dealers-used",
        "used",
        "cars-wholesale",
        "car"
    ],
    "wof:name":"Premier Motors",
    "wof:placetype":"venue"
},
  "geometry": {"coordinates":[-93.36377899999999,45.063233],"type":"Point"}
}