{
  "type": "Feature",
  "properties": {
    "addr:full":"8750 Bentwood Dr Eden Prairie MN 55344",
    "addr:housenumber":"8750",
    "addr:postcode":"55344",
    "addr:street":"Bentwood Dr",
    "iso:country":"US",
    "sg:address":"8750 Bentwood Dr",
    "sg:city":"Eden Prairie",
    "sg:classifiers":[
        {
            "category":"Freight",
            "type":"Transportation"
        }
    ],
    "sg:phone":"+1 952 944 2559",
    "sg:postcode":"55344",
    "sg:province":"MN",
    "sg:tags":[
        "operator",
        "trucking"
    ],
    "wof:name":"Siems Trking Inc",
    "wof:placetype":"venue"
},
  "geometry": {"coordinates":[-93.411073,44.844776],"type":"Point"}
}