{
  "type": "Feature",
  "properties": {
    "addr:full":"2633 23rd Ave SE Rochester MN 55904",
    "addr:housenumber":"2633",
    "addr:postcode":"55904",
    "addr:street":"23Rd Ave Se",
    "iso:country":"US",
    "sg:address":"2633 23rd Ave SE",
    "sg:city":"Rochester",
    "sg:classifiers":[
        {
            "category":"Shopping",
            "subcategory":"Photographic Equipment",
            "type":"Retail Goods"
        }
    ],
    "sg:phone":"+1 507 288 5034",
    "sg:postcode":"55904",
    "sg:province":"MN",
    "sg:tags":[
        "supply"
    ],
    "wof:name":"Creative Memories",
    "wof:placetype":"venue"
},
  "geometry": {"coordinates":[-92.431012,43.982371],"type":"Point"}
}