{
  "type": "Feature",
  "properties": {
    "addr:full":"5585 W 78th St Minneapolis MN 55439",
    "addr:housenumber":"5585",
    "addr:postcode":"55439",
    "addr:street":"W 78Th St",
    "iso:country":"US",
    "sg:address":"5585 W 78th St",
    "sg:city":"Minneapolis",
    "sg:classifiers":[
        {
            "category":"Professional",
            "subcategory":"Business Services",
            "type":"Services"
        }
    ],
    "sg:phone":"+1 952 941 5300",
    "sg:postcode":"55439",
    "sg:province":"MN",
    "sg:tags":[
        "inventory"
    ],
    "wof:name":"Big Apple Inc",
    "wof:placetype":"venue"
},
  "geometry": {"coordinates":[-93.361693,44.862074],"type":"Point"}
}