{
  "type": "Feature",
  "properties": {
    "addr:full":"35287 Co Rd 3 Crosslake MN 56442",
    "addr:housenumber":"35287",
    "addr:postcode":"56442",
    "addr:street":"Co Rd 3",
    "iso:country":"US",
    "sg:address":"35287 Co Rd 3",
    "sg:city":"Crosslake",
    "sg:classifiers":[
        {
            "category":"Real Estate",
            "subcategory":"Real Estate Agent",
            "type":"Services"
        }
    ],
    "sg:phone":"+1 218 692 2200",
    "sg:postcode":"56442",
    "sg:province":"MN",
    "wof:name":"Bonnie Jean's Realty Inc",
    "wof:placetype":"venue"
},
  "geometry": {"coordinates":[-94.11352100000001,46.666759],"type":"Point"}
}