{
  "type": "Feature",
  "properties": {
    "addr:full":"613 3rd Ave Two Harbors MN 55616",
    "addr:housenumber":"613",
    "addr:postcode":"55616",
    "addr:street":"3Rd Ave",
    "iso:country":"US",
    "sg:address":"613 3rd Ave",
    "sg:city":"Two Harbors",
    "sg:classifiers":[
        {
            "category":"Government",
            "subcategory":"Police Station",
            "type":"Public Place"
        }
    ],
    "sg:phone":"+1 218 834 5566",
    "sg:postcode":"55616",
    "sg:province":"MN",
    "sg:tags":[
        "department"
    ],
    "wof:name":"Two Harbors Police Dept",
    "wof:placetype":"venue"
},
  "geometry": {"coordinates":[-91.67113500000001,47.021845],"type":"Point"}
}