{
  "type": "Feature",
  "properties": {
    "iso:country":"US",
    "sg:address":"6020 28th Ave S Ste 102",
    "sg:city":"Minneapolis",
    "sg:classifiers":[
        {
            "category":"Government",
            "subcategory":"Office",
            "type":"Public Place"
        }
    ],
    "sg:phone":"+1 612 713 4350",
    "sg:postcode":"55450",
    "sg:province":"MN",
    "sg:tags":[
        "government-state"
    ],
    "sg:website":"http://www.faa.gov",
    "wof:name":"Airport District Office",
    "wof:placetype":"venue"
},
  "geometry": {"coordinates":[-93.232429,44.893943],"type":"Point"}
}