{
  "type": "Feature",
  "properties": {
    "iso:country":"US",
    "sg:address":"2254 Golden Spike Rd NE",
    "sg:city":"Sauk Rapids",
    "sg:classifiers":[
        {
            "category":"Retail",
            "subcategory":"Repair Shop",
            "type":"Services"
        },
        {
            "category":"Home & Garden",
            "subcategory":"Furniture",
            "type":"Retail Goods"
        }
    ],
    "sg:phone":"+1 320 259 6434",
    "sg:postcode":"56379",
    "sg:province":"MN",
    "sg:tags":[
        "refinishing"
    ],
    "wof:name":"Quality Furniture Svc",
    "wof:placetype":"venue"
},
  "geometry": {"coordinates":[-94.11637899999999,45.607573],"type":"Point"}
}