{
  "type": "Feature",
  "properties": {
    "addr:full":"253 7th St W Saint Paul MN 55102",
    "addr:housenumber":"253",
    "addr:postcode":"55102",
    "addr:street":"7Th St W",
    "iso:country":"US",
    "sg:address":"253 7th St W",
    "sg:city":"Saint Paul",
    "sg:classifiers":[
        {
            "category":"Restaurant",
            "type":"Food & Drink"
        }
    ],
    "sg:menulink":"http://www.allmenus.com/mn/st-paul/11781-downtowner-woodfire-grill/menu/",
    "sg:phone":"+1 651 228 9500",
    "sg:postcode":"55102",
    "sg:province":"MN",
    "sg:tags":[
        "american"
    ],
    "wof:name":"Downtowner Woodfire Grill",
    "wof:placetype":"venue"
},
  "geometry": {"coordinates":[-93.10502200000001,44.942651],"type":"Point"}
}