{
  "type": "Feature",
  "properties": {
    "addr:full":"1 Lake St Redlake MN 56634",
    "addr:housenumber":"1",
    "addr:postcode":"56634",
    "addr:street":"Lake St",
    "iso:country":"US",
    "sg:address":"1 Lake St",
    "sg:city":"Redlake",
    "sg:classifiers":[
        {
            "category":"Health Services",
            "subcategory":"Clinic",
            "type":"Services"
        }
    ],
    "sg:phone":"+1 218 679 3316",
    "sg:postcode":"56634",
    "sg:province":"MN",
    "wof:name":"Comprehensive Health",
    "wof:placetype":"venue"
},
  "geometry": {"coordinates":[-95.42701,47.69782],"type":"Point"}
}