{
  "type": "Feature",
  "properties": {
    "addr:full":"2214 US Hwy 10 Saint Paul MN 55112",
    "addr:housenumber":"2214",
    "addr:postcode":"55112",
    "addr:street":"Us Hwy 10",
    "iso:country":"US",
    "sg:address":"2214 US Hwy 10",
    "sg:city":"Saint Paul",
    "sg:classifiers":[
        {
            "category":"Building & Trades",
            "subcategory":"Construction",
            "type":"Services"
        }
    ],
    "sg:phone":"+1 763 780 9380",
    "sg:postcode":"55112",
    "sg:province":"MN",
    "sg:tags":[
        "house",
        "contractor"
    ],
    "wof:name":"Dakota Sunrooms",
    "wof:placetype":"venue"
},
  "geometry": {"coordinates":[-93.19308599999999,45.095194],"type":"Point"}
}