{
  "type": "Feature",
  "properties": {
    "addr:full":"13601 80th Cir N Maple Grove MN 55369",
    "addr:housenumber":"13601",
    "addr:postcode":"55369",
    "addr:street":"80Th Cir N",
    "iso:country":"US",
    "sg:address":"13601 80th Cir N",
    "sg:city":"Maple Grove",
    "sg:classifiers":[
        {
            "category":"Real Estate",
            "subcategory":"Real Estate Agent",
            "type":"Services"
        }
    ],
    "sg:phone":"+1 763 420 7080",
    "sg:postcode":"55369",
    "sg:province":"MN",
    "wof:name":"Counselor Realty Inc",
    "wof:placetype":"venue"
},
  "geometry": {"coordinates":[-93.453355,45.100558],"type":"Point"}
}