{
  "type": "Feature",
  "properties": {
    "iso:country":"US",
    "sg:address":"207 Lafayette St",
    "sg:city":"Winona",
    "sg:classifiers":[
        {
            "category":"Recreation",
            "type":"Entertainment"
        }
    ],
    "sg:phone":"+1 507 457 8258",
    "sg:postcode":"55987",
    "sg:province":"MN",
    "sg:tags":[
        "parks"
    ],
    "wof:name":"Winona City Recreation Dept",
    "wof:placetype":"venue"
},
  "geometry": {"coordinates":[-91.635807,44.050927],"type":"Point"}
}