{
  "type": "Feature",
  "properties": {
    "iso:country":"US",
    "sg:address":"5183 Rice Lake Rd",
    "sg:city":"Duluth",
    "sg:classifiers":[
        {
            "category":"Professional",
            "subcategory":"Business Services",
            "type":"Services"
        }
    ],
    "sg:phone":"+1 218 310 0194",
    "sg:postcode":"55803",
    "sg:province":"MN",
    "sg:tags":[
        "consultant",
        "coach"
    ],
    "wof:name":"Xtreme Clean Image",
    "wof:placetype":"venue"
},
  "geometry": {"coordinates":[-92.15353,46.885413],"type":"Point"}
}