{
  "type": "Feature",
  "properties": {
    "iso:country":"US",
    "sg:address":"110 N Plainview Ave",
    "sg:city":"Mankato",
    "sg:classifiers":[
        {
            "category":"Building & Trades",
            "subcategory":"Landscaping Services",
            "type":"Services"
        }
    ],
    "sg:phone":"+1 507 345 8786",
    "sg:postcode":"56001",
    "sg:province":"MN",
    "sg:tags":[
        "tree"
    ],
    "wof:name":"Quality Tree Svc",
    "wof:placetype":"venue"
},
  "geometry": {"coordinates":[-93.971155,44.162702],"type":"Point"}
}