{
  "type": "Feature",
  "properties": {
    "addr:full":"1932 Turquoise Trl Saint Paul MN 55122",
    "addr:housenumber":"1932",
    "addr:postcode":"55122",
    "addr:street":"Turquoise Trl",
    "iso:country":"US",
    "sg:address":"1932 Turquoise Trl",
    "sg:city":"Saint Paul",
    "sg:classifiers":[
        {
            "category":"Building & Trades",
            "subcategory":"Construction",
            "type":"Services"
        }
    ],
    "sg:phone":"+1 612 799 7648",
    "sg:postcode":"55122",
    "sg:province":"MN",
    "sg:tags":[
        "house"
    ],
    "wof:name":"Oak Leaf Construction LLC",
    "wof:placetype":"venue"
},
  "geometry": {"coordinates":[-93.20566700000001,44.811822],"type":"Point"}
}