{
  "type": "Feature",
  "properties": {
    "addr:full":"4512 36th Ave NW Hackensack MN 56452",
    "addr:housenumber":"4512",
    "addr:postcode":"56452",
    "addr:street":"36Th Ave Nw",
    "iso:country":"US",
    "sg:address":"4512 36th Ave NW",
    "sg:city":"Hackensack",
    "sg:classifiers":[
        {
            "category":"Retail",
            "subcategory":"Repair Shop",
            "type":"Services"
        }
    ],
    "sg:phone":"+1 218 675 6343",
    "sg:postcode":"56452",
    "sg:province":"MN",
    "wof:name":"Nature Art Taxidermy",
    "wof:placetype":"venue"
},
  "geometry": {"coordinates":[-94.469674,46.969101],"type":"Point"}
}