{
  "type": "Feature",
  "properties": {
    "addr:full":"4690 Bald Eagle Ave Saint Paul MN 55110",
    "addr:housenumber":"4690",
    "addr:postcode":"55110",
    "addr:street":"Bald Eagle Ave",
    "iso:country":"US",
    "sg:address":"4690 Bald Eagle Ave",
    "sg:city":"Saint Paul",
    "sg:classifiers":[
        {
            "category":"Social Services",
            "subcategory":"Child Care",
            "type":"Services"
        }
    ],
    "sg:phone":"+1 651 429 5378",
    "sg:postcode":"55110",
    "sg:province":"MN",
    "sg:tags":[
        "day"
    ],
    "wof:name":"St Mary of Lake Preschool",
    "wof:placetype":"venue"
},
  "geometry": {"coordinates":[-93.01533999999999,45.082446],"type":"Point"}
}