{
  "type": "Feature",
  "properties": {
    "iso:country":"US",
    "sg:address":"101 Lake St S",
    "sg:city":"Big Lake",
    "sg:classifiers":[
        {
            "category":"Retail",
            "subcategory":"Auto Repair",
            "type":"Services"
        }
    ],
    "sg:phone":"+1 763 263 7867",
    "sg:postcode":"55309",
    "sg:province":"MN",
    "sg:tags":[
        "body",
        "automobile",
        "painting"
    ],
    "wof:name":"Autostop Inc",
    "wof:placetype":"venue"
},
  "geometry": {"coordinates":[-93.745953,45.331373],"type":"Point"}
}