{
  "type": "Feature",
  "properties": {
    "addr:full":"6215 Brooklyn Blvd Minneapolis MN 55429",
    "addr:housenumber":"6215",
    "addr:postcode":"55429",
    "addr:street":"Brooklyn Blvd",
    "iso:country":"US",
    "sg:address":"6215 Brooklyn Blvd",
    "sg:city":"Minneapolis",
    "sg:classifiers":[
        {
            "category":"Food & Beverages",
            "subcategory":"Groceries & Convenience Stores",
            "type":"Retail Goods"
        }
    ],
    "sg:phone":"+1 763 531 8114",
    "sg:postcode":"55429",
    "sg:province":"MN",
    "sg:tags":[
        "japanese"
    ],
    "wof:name":"Vinai Market Inc",
    "wof:placetype":"venue"
},
  "geometry": {"coordinates":[-93.327035,45.067747],"type":"Point"}
}