{
  "type": "Feature",
  "properties": {
    "addr:full":"412 Prairie Ave SW Faribault MN 55021",
    "addr:housenumber":"412",
    "addr:postcode":"55021",
    "addr:street":"Prairie Ave Sw",
    "iso:country":"US",
    "sg:address":"412 Prairie Ave SW",
    "sg:city":"Faribault",
    "sg:classifiers":[
        {
            "category":"Taxi",
            "type":"Transportation"
        }
    ],
    "sg:phone":"+1 507 333 4452",
    "sg:postcode":"55021",
    "sg:province":"MN",
    "sg:tags":[
        "taxicab"
    ],
    "wof:name":"Jj Faribo Taxi",
    "wof:placetype":"venue"
},
  "geometry": {"coordinates":[-93.287772,44.286738],"type":"Point"}
}