{
  "type": "Feature",
  "properties": {
    "addr:full":"716 2nd St W Hastings MN 55033",
    "addr:housenumber":"716",
    "addr:postcode":"55033",
    "addr:street":"2Nd St W",
    "iso:country":"US",
    "sg:address":"716 2nd St W",
    "sg:city":"Hastings",
    "sg:classifiers":[
        {
            "category":"Professional",
            "subcategory":"Lawyer & Legal Services",
            "type":"Services"
        }
    ],
    "sg:phone":"+1 651 437 4083",
    "sg:postcode":"55033",
    "sg:province":"MN",
    "wof:name":"Millett V OConnell",
    "wof:placetype":"venue"
},
  "geometry": {"coordinates":[-92.86299200000001,44.744367],"type":"Point"}
}