{
  "type": "Feature",
  "properties": {
    "iso:country":"US",
    "sg:address":"1387 Cope Ave E",
    "sg:city":"Maplewood",
    "sg:classifiers":[
        {
            "category":"Manufacturing",
            "subcategory":"Metals",
            "type":"Manufacturing & Wholesale Goods"
        },
        {
            "category":"Building & Trades",
            "subcategory":"Plumbing",
            "type":"Services"
        }
    ],
    "sg:phone":"+1 651 704 0300",
    "sg:postcode":"55109",
    "sg:province":"MN",
    "sg:tags":[
        "sheet",
        "mfg",
        "work",
        "contractor",
        "architectural",
        "metalwork"
    ],
    "sg:website":"www.mcgrathshtmtl.com",
    "wof:name":"M G Mc Grath Inc",
    "wof:placetype":"venue"
},
  "geometry": {"coordinates":[-93.04172199999999,45.010151],"type":"Point"}
}