{
  "type": "Feature",
  "properties": {
    "addr:full":"21309 280th St Badger MN 56714",
    "addr:housenumber":"21309",
    "addr:postcode":"56714",
    "addr:street":"280Th St",
    "iso:country":"US",
    "sg:address":"21309 280th St",
    "sg:city":"Badger",
    "sg:classifiers":[
        {
            "category":"Place Of Worship",
            "subcategory":"Church",
            "type":"Public Place"
        },
        {
            "category":"Place Of Worship",
            "type":"Public Place"
        }
    ],
    "sg:phone":"+1 218 782 3211",
    "sg:postcode":"56714",
    "sg:province":"MN",
    "sg:tags":[
        "lutheran",
        "denomination",
        "churches-lutheran-evangelical",
        "churches-interdenominational",
        "america",
        "churches-various",
        "churches-lutheran"
    ],
    "wof:name":"Oiland Church",
    "wof:placetype":"venue"
},
  "geometry": {"coordinates":[-96.17443400000001,48.80509],"type":"Point"}
}