{
  "type": "Feature",
  "properties": {
    "iso:country":"US",
    "sg:address":"2310 Horizon Cir",
    "sg:city":"Shakopee",
    "sg:classifiers":[
        {
            "category":"Professional",
            "subcategory":"Computer Services",
            "type":"Services"
        }
    ],
    "sg:phone":"+1 952 888 9963",
    "sg:postcode":"55379",
    "sg:province":"MN",
    "sg:tags":[
        "prepackaged",
        "software"
    ],
    "wof:name":"Software House International",
    "wof:placetype":"venue"
},
  "geometry": {"coordinates":[-93.41014,44.759017],"type":"Point"}
}