{
  "type": "Feature",
  "properties": {
    "iso:country":"US",
    "sg:address":"1026 Main St",
    "sg:city":"Red Wing",
    "sg:classifiers":[
        {
            "category":"Autos & Motor Vehicles",
            "subcategory":"Recreational Vehicle Sales",
            "type":"Retail Goods"
        }
    ],
    "sg:phone":"+1 651 388 1535",
    "sg:postcode":"55066",
    "sg:province":"MN",
    "wof:name":"Red Wing Motor Sports",
    "wof:placetype":"venue"
},
  "geometry": {"coordinates":[-92.542216,44.563066],"type":"Point"}
}