{
  "type": "Feature",
  "properties": {
    "iso:country":"US",
    "sg:address":"1950 27th St N",
    "sg:city":"Worthington",
    "sg:classifiers":[
        {
            "category":"Government",
            "subcategory":"Office",
            "type":"Public Place"
        }
    ],
    "sg:phone":"+1 507 372 8660",
    "sg:postcode":"56187",
    "sg:province":"MN",
    "sg:tags":[
        "village"
    ],
    "wof:name":"Worthington Wastewater Trtmnt",
    "wof:placetype":"venue"
},
  "geometry": {"coordinates":[-95.582154,43.645305],"type":"Point"}
}