{
  "type": "Feature",
  "properties": {
    "iso:country":"US",
    "sg:address":"4486 Timberline Ct",
    "sg:city":"Saint Paul",
    "sg:classifiers":[
        {
            "category":"Professional",
            "subcategory":"Management & Consulting",
            "type":"Services"
        }
    ],
    "sg:phone":"+1 651 481 9734",
    "sg:postcode":"55127",
    "sg:province":"MN",
    "wof:name":"Horwath Resource Group",
    "wof:placetype":"venue"
},
  "geometry": {"coordinates":[-93.09120799999999,45.07686],"type":"Point"}
}