{
  "type": "Feature",
  "properties": {
    "addr:full":"138 Main Ave W Bemidji MN 56601",
    "addr:housenumber":"138",
    "addr:postcode":"56601",
    "addr:street":"Main Ave W",
    "iso:country":"US",
    "sg:address":"138 Main Ave W",
    "sg:city":"Bemidji",
    "sg:classifiers":[
        {
            "category":"Building & Trades",
            "subcategory":"Electrical",
            "type":"Services"
        }
    ],
    "sg:phone":"+1 218 586 2693",
    "sg:postcode":"56601",
    "sg:province":"MN",
    "sg:tags":[
        "electrical",
        "contractor"
    ],
    "wof:name":"Hamilton Electric",
    "wof:placetype":"venue"
},
  "geometry": {"coordinates":[-94.767796,47.587917],"type":"Point"}
}