{
  "type": "Feature",
  "properties": {
    "iso:country":"US",
    "sg:address":"2439 Northridge Ave N",
    "sg:city":"Stillwater",
    "sg:classifiers":[
        {
            "category":"Professional",
            "subcategory":"Computer Services",
            "type":"Services"
        }
    ],
    "sg:phone":"+1 651 351 7150",
    "sg:postcode":"55082",
    "sg:province":"MN",
    "sg:tags":[
        "related"
    ],
    "wof:name":"Alpine Springs Consulting",
    "wof:placetype":"venue"
},
  "geometry": {"coordinates":[-92.830505,44.98359],"type":"Point"}
}