{
  "type": "Feature",
  "properties": {
    "iso:country":"US",
    "sg:address":"9805 Nicollet Ave S",
    "sg:city":"Minneapolis",
    "sg:classifiers":[
        {
            "category":"Retail",
            "subcategory":"Auto Rental",
            "type":"Services"
        }
    ],
    "sg:phone":"+1 612 871 1437",
    "sg:postcode":"55420",
    "sg:province":"MN",
    "sg:tags":[
        "renting",
        "leasing",
        "truck",
        "trailer"
    ],
    "wof:name":"India Mart Llc",
    "wof:placetype":"venue"
},
  "geometry": {"coordinates":[-93.278503,44.826152],"type":"Point"}
}