{
  "type": "Feature",
  "properties": {
    "addr:full":"120 E Juniper Ave Frazee MN 56544",
    "addr:housenumber":"120",
    "addr:postcode":"56544",
    "addr:street":"E Juniper Ave",
    "iso:country":"US",
    "sg:address":"120 E Juniper Ave",
    "sg:city":"Frazee",
    "sg:classifiers":[
        {
            "category":"Restaurant",
            "type":"Food & Drink"
        }
    ],
    "sg:phone":"+1 218 334 5144",
    "sg:postcode":"56544",
    "sg:province":"MN",
    "wof:name":"Richard G Wah",
    "wof:placetype":"venue"
},
  "geometry": {"coordinates":[-95.70131600000001,46.726694],"type":"Point"}
}