{
  "type": "Feature",
  "properties": {
    "addr:full":"8517 Mitchell Rd Eden Prairie MN 55347",
    "addr:housenumber":"8517",
    "addr:postcode":"55347",
    "addr:street":"Mitchell Rd",
    "iso:country":"US",
    "sg:address":"8517 Mitchell Rd",
    "sg:city":"Eden Prairie",
    "sg:classifiers":[
        {
            "category":"Social Services",
            "subcategory":"Child Care",
            "type":"Services"
        }
    ],
    "sg:phone":"+1 952 949 2017",
    "sg:postcode":"55347",
    "sg:province":"MN",
    "sg:tags":[
        "day"
    ],
    "wof:name":"Susan Byron",
    "wof:placetype":"venue"
},
  "geometry": {"coordinates":[-93.46006,44.849605],"type":"Point"}
}