{
  "type": "Feature",
  "properties": {
    "addr:full":"15121 Ute St NW Anoka MN 55303",
    "addr:housenumber":"15121",
    "addr:postcode":"55303",
    "addr:street":"Ute St Nw",
    "iso:country":"US",
    "sg:address":"15121 Ute St NW",
    "sg:city":"Anoka",
    "sg:classifiers":[
        {
            "category":"Professional",
            "subcategory":"Business Services",
            "type":"Services"
        }
    ],
    "sg:phone":"+1 763 576 0157",
    "sg:postcode":"55303",
    "sg:province":"MN",
    "sg:tags":[
        "design"
    ],
    "wof:name":"P C S Services Inc",
    "wof:placetype":"venue"
},
  "geometry": {"coordinates":[-93.39277800000001,45.247998],"type":"Point"}
}