{
  "type": "Feature",
  "properties": {
    "addr:full":"521 S Shore Dr Detroit Lakes MN 56501",
    "addr:housenumber":"521",
    "addr:postcode":"56501",
    "addr:street":"S Shore Dr",
    "iso:country":"US",
    "sg:address":"521 S Shore Dr",
    "sg:city":"Detroit Lakes",
    "sg:classifiers":[
        {
            "category":"Building & Trades",
            "subcategory":"Electrical",
            "type":"Services"
        }
    ],
    "sg:phone":"+1 218 847 5255",
    "sg:postcode":"56501",
    "sg:province":"MN",
    "sg:tags":[
        "electrical",
        "electric",
        "contractor"
    ],
    "wof:name":"Schatts Electric Inc",
    "wof:placetype":"venue"
},
  "geometry": {"coordinates":[-95.84559,46.77468],"type":"Point"}
}