{
  "type": "Feature",
  "properties": {
    "addr:full":"831 William St Hamburg MN 55339",
    "addr:housenumber":"831",
    "addr:postcode":"55339",
    "addr:street":"William St",
    "iso:country":"US",
    "sg:address":"831 William St",
    "sg:city":"Hamburg",
    "sg:classifiers":[
        {
            "category":"Freight",
            "type":"Transportation"
        }
    ],
    "sg:phone":"+1 952 467 2579",
    "sg:postcode":"55339",
    "sg:province":"MN",
    "sg:tags":[
        "operator",
        "trucking"
    ],
    "wof:name":"M & R Trucking Inc",
    "wof:placetype":"venue"
},
  "geometry": {"coordinates":[-93.958043,44.733068],"type":"Point"}
}