{
  "type": "Feature",
  "properties": {
    "iso:country":"US",
    "sg:address":"22566 450th St",
    "sg:city":"Mazeppa",
    "sg:classifiers":[
        {
            "category":"Building & Trades",
            "subcategory":"Construction",
            "type":"Services"
        }
    ],
    "sg:phone":"+1 507 843 4119",
    "sg:postcode":"55956",
    "sg:province":"MN",
    "sg:tags":[
        "contractor"
    ],
    "wof:name":"Sommerfield & Sommerfield",
    "wof:placetype":"venue"
},
  "geometry": {"coordinates":[-92.579808,44.295982],"type":"Point"}
}