{
  "type": "Feature",
  "properties": {
    "iso:country":"US",
    "sg:address":"425 N 2nd Ave",
    "sg:city":"Fergus Falls",
    "sg:classifiers":[
        {
            "category":"Real Estate",
            "subcategory":"Real Estate Operator",
            "type":"Services"
        }
    ],
    "sg:phone":"+1 218 736 6683",
    "sg:postcode":"56537",
    "sg:province":"MN",
    "sg:tags":[
        "apartment"
    ],
    "wof:name":"West Town Manor Apartments",
    "wof:placetype":"venue"
},
  "geometry": {"coordinates":[-96.090569,46.287365],"type":"Point"}
}