{
  "type": "Feature",
  "properties": {
    "addr:full":"720 W Lake Dr Detroit Lakes MN 56501",
    "addr:housenumber":"720",
    "addr:postcode":"56501",
    "addr:street":"W Lake Dr",
    "iso:country":"US",
    "sg:address":"720 W Lake Dr",
    "sg:city":"Detroit Lakes",
    "sg:classifiers":[
        {
            "category":"Restaurant",
            "type":"Food & Drink"
        }
    ],
    "sg:phone":"+1 218 844 5333",
    "sg:postcode":"56501",
    "sg:province":"MN",
    "wof:name":"Speedway Restaurant",
    "wof:placetype":"venue"
},
  "geometry": {"coordinates":[-95.85539799999999,46.804382],"type":"Point"}
}