{
  "type": "Feature",
  "properties": {
    "iso:country":"US",
    "sg:address":"18615 Co Hwy 38",
    "sg:city":"Frazee",
    "sg:classifiers":[
        {
            "category":"Farming",
            "subcategory":"Dairy Farm",
            "type":"Manufacturing & Wholesale Goods"
        }
    ],
    "sg:phone":"+1 218 538 6744",
    "sg:postcode":"56544",
    "sg:province":"MN",
    "wof:name":"Aho Brothers Dairy",
    "wof:placetype":"venue"
},
  "geometry": {"coordinates":[-95.41384600000001,46.845942],"type":"Point"}
}