{
  "type": "Feature",
  "properties": {
    "iso:country":"US",
    "sg:address":"545 4th St SE",
    "sg:city":"Milaca",
    "sg:classifiers":[
        {
            "category":"Insurance",
            "subcategory":"Insurance Agent",
            "type":"Services"
        }
    ],
    "sg:phone":"+1 320 983 6880",
    "sg:postcode":"56353",
    "sg:province":"MN",
    "wof:name":"American Family Insurance",
    "wof:placetype":"venue"
},
  "geometry": {"coordinates":[-93.64220899999999,45.752585],"type":"Point"}
}