{
  "type": "Feature",
  "properties": {
    "addr:full":"121 2nd Ave SW Milaca MN 56353",
    "addr:housenumber":"121",
    "addr:postcode":"56353",
    "addr:street":"2Nd Ave Sw",
    "iso:country":"US",
    "sg:address":"121 2nd Ave SW",
    "sg:city":"Milaca",
    "sg:classifiers":[
        {
            "category":"Health Services",
            "subcategory":"Doctor",
            "type":"Services"
        },
        {
            "category":"Social Services",
            "type":"Services"
        }
    ],
    "sg:phone":"+1 320 983 3771",
    "sg:postcode":"56353",
    "sg:province":"MN",
    "sg:tags":[
        "pregnancy",
        "counseling",
        "medical",
        "information"
    ],
    "wof:name":"Rum River Life Choices",
    "wof:placetype":"venue"
},
  "geometry": {"coordinates":[-93.652918,45.754644],"type":"Point"}
}