{
  "type": "Feature",
  "properties": {
    "iso:country":"US",
    "sg:address":"10603 University Ave NE",
    "sg:city":"Minneapolis",
    "sg:classifiers":[
        {
            "category":"Restaurant",
            "type":"Food & Drink"
        }
    ],
    "sg:phone":"+1 763 755 3735",
    "sg:postcode":"55434",
    "sg:province":"MN",
    "sg:tags":[
        "barbecue"
    ],
    "wof:name":"Wing Joint",
    "wof:placetype":"venue"
},
  "geometry": {"coordinates":[-93.26625799999999,45.163461],"type":"Point"}
}