{
  "type": "Feature",
  "properties": {
    "iso:country":"US",
    "sg:address":"9201 Penn Ave S",
    "sg:city":"Minneapolis",
    "sg:classifiers":[
        {
            "category":"Professional",
            "type":"Services"
        },
        {
            "category":"Manufacturing",
            "subcategory":"Tools & Machinery",
            "type":"Manufacturing & Wholesale Goods"
        }
    ],
    "sg:phone":"+1 952 224 0880",
    "sg:postcode":"55431",
    "sg:province":"MN",
    "sg:tags":[
        "industrial",
        "mfg"
    ],
    "wof:name":"Cragg Motive Power Corp",
    "wof:placetype":"venue"
},
  "geometry": {"coordinates":[-93.308768,44.838108],"type":"Point"}
}