{
  "type": "Feature",
  "properties": {
    "iso:country":"US",
    "sg:address":"943 S Prairie Ave",
    "sg:city":"Fairmont",
    "sg:classifiers":[
        {
            "category":"Building & Trades",
            "subcategory":"Construction",
            "type":"Services"
        }
    ],
    "sg:phone":"+1 507 235 2622",
    "sg:postcode":"56031",
    "sg:province":"MN",
    "sg:tags":[
        "excavation",
        "contractor"
    ],
    "wof:name":"F & J Excavating",
    "wof:placetype":"venue"
},
  "geometry": {"coordinates":[-94.45725299999999,43.642902],"type":"Point"}
}