{
  "type": "Feature",
  "properties": {
    "iso:country":"US",
    "sg:address":"2009 E 121st St Apt 112",
    "sg:city":"Burnsville",
    "sg:classifiers":[
        {
            "category":"Real Estate",
            "subcategory":"Real Estate Services",
            "type":"Services"
        }
    ],
    "sg:phone":"+1 952 884 1244",
    "sg:postcode":"55337",
    "sg:province":"MN",
    "sg:tags":[
        "rental"
    ],
    "wof:name":"Ultra Prop",
    "wof:placetype":"venue"
},
  "geometry": {"coordinates":[-93.24674899999999,44.7842],"type":"Point"}
}