{
  "type": "Feature",
  "properties": {
    "iso:country":"US",
    "sg:address":"4300 Baker Rd",
    "sg:city":"Hopkins",
    "sg:classifiers":[
        {
            "category":"Professional",
            "subcategory":"Advertising",
            "type":"Services"
        }
    ],
    "sg:phone":"+1 952 936 9567",
    "sg:postcode":"55343",
    "sg:province":"MN",
    "sg:tags":[
        "outdoor"
    ],
    "wof:name":"Adams Outdoor Advg Ltd Partnr",
    "wof:placetype":"venue"
},
  "geometry": {"coordinates":[-93.44742100000001,44.924665],"type":"Point"}
}