{
  "type": "Feature",
  "properties": {
    "addr:full":"1246 1st Ave N Moorhead MN 56560",
    "addr:housenumber":"1246",
    "addr:postcode":"56560",
    "addr:street":"1St Ave N",
    "iso:country":"US",
    "sg:address":"1246 1st Ave N",
    "sg:city":"Moorhead",
    "sg:classifiers":[
        {
            "category":"Personal",
            "subcategory":"Shoe Repair & Shine",
            "type":"Services"
        }
    ],
    "sg:phone":"+1 218 233 5450",
    "sg:postcode":"56560",
    "sg:province":"MN",
    "sg:tags":[
        "parlor"
    ],
    "wof:name":"Anderson Shoe & Tarp Repair",
    "wof:placetype":"venue"
},
  "geometry": {"coordinates":[-96.760216,46.876211],"type":"Point"}
}