{
  "type": "Feature",
  "properties": {
    "addr:full":"2501 38th Ave NE Minneapolis MN 55421",
    "addr:housenumber":"2501",
    "addr:postcode":"55421",
    "addr:street":"38Th Ave Ne",
    "iso:country":"US",
    "sg:address":"2501 38th Ave NE",
    "sg:city":"Minneapolis",
    "sg:classifiers":[
        {
            "category":"Real Estate",
            "subcategory":"Real Estate Operator",
            "type":"Services"
        }
    ],
    "sg:phone":"+1 866 444 2714",
    "sg:postcode":"55421",
    "sg:province":"MN",
    "sg:tags":[
        "apartment"
    ],
    "sg:website":"www.dominiumapartments.com/Landi...",
    "wof:name":"The Landings at Silver Lake Village",
    "wof:placetype":"venue"
},
  "geometry": {"coordinates":[-93.22480400000001,45.037483],"type":"Point"}
}