{
  "type": "Feature",
  "properties": {
    "addr:full":"308 8th Ave SE Pipestone MN 56164",
    "addr:housenumber":"308",
    "addr:postcode":"56164",
    "addr:street":"8Th Ave Se",
    "iso:country":"US",
    "sg:address":"308 8th Ave SE",
    "sg:city":"Pipestone",
    "sg:classifiers":[
        {
            "category":"Insurance",
            "subcategory":"Insurance Agent",
            "type":"Services"
        }
    ],
    "sg:phone":"+1 507 825 5824",
    "sg:postcode":"56164",
    "sg:province":"MN",
    "wof:name":"Latham Insurance Inc",
    "wof:placetype":"venue"
},
  "geometry": {"coordinates":[-96.307548,43.99827],"type":"Point"}
}