{
  "type": "Feature",
  "properties": {
    "addr:full":"201 W 1st St Waconia MN 55387",
    "addr:housenumber":"201",
    "addr:postcode":"55387",
    "addr:street":"W 1St St",
    "iso:country":"US",
    "sg:address":"201 W 1st St",
    "sg:city":"Waconia",
    "sg:classifiers":[
        {
            "category":"Manufacturing",
            "subcategory":"Tools & Machinery",
            "type":"Manufacturing & Wholesale Goods"
        }
    ],
    "sg:phone":"+1 952 442 3233",
    "sg:postcode":"55387",
    "sg:province":"MN",
    "sg:tags":[
        "surgical",
        "mfg"
    ],
    "wof:name":"Rebound Orthotics & Prosthetic",
    "wof:placetype":"venue"
},
  "geometry": {"coordinates":[-93.790666,44.849354],"type":"Point"}
}