{
  "type": "Feature",
  "properties": {
    "iso:country":"US",
    "sg:address":"7034 159th St W",
    "sg:city":"Apple Valley",
    "sg:classifiers":[
        {
            "category":"Personal",
            "subcategory":"Beauty Salon",
            "type":"Services"
        }
    ],
    "sg:phone":"+1 952 997 2005",
    "sg:postcode":"55124",
    "sg:province":"MN",
    "wof:name":"Eileen's",
    "wof:placetype":"venue"
},
  "geometry": {"coordinates":[-93.209631,44.719023],"type":"Point"}
}