{
  "type": "Feature",
  "properties": {
    "iso:country":"US",
    "sg:address":"8762 Pinehurst Bay",
    "sg:city":"Saint Paul",
    "sg:classifiers":[
        {
            "category":"Professional",
            "subcategory":"Computer Services",
            "type":"Services"
        }
    ],
    "sg:phone":"+1 651 714 9041",
    "sg:postcode":"55125",
    "sg:province":"MN",
    "sg:tags":[
        "prepackaged",
        "software"
    ],
    "wof:name":"Maximum Vizion",
    "wof:placetype":"venue"
},
  "geometry": {"coordinates":[-92.92864,44.928462],"type":"Point"}
}