{
  "type": "Feature",
  "properties": {
    "addr:full":"7240 Brooklyn Blvd Minneapolis MN 55429",
    "addr:housenumber":"7240",
    "addr:postcode":"55429",
    "addr:street":"Brooklyn Blvd",
    "iso:country":"US",
    "sg:address":"7240 Brooklyn Blvd",
    "sg:city":"Minneapolis",
    "sg:classifiers":[
        {
            "category":"Health Services",
            "subcategory":"Dentist",
            "type":"Services"
        }
    ],
    "sg:phone":"+1 763 561 1570",
    "sg:postcode":"55429",
    "sg:province":"MN",
    "sg:tags":[
        "dentists-cosmetic",
        "denture",
        "dental",
        "clinic",
        "dentistry",
        "dentists-prosthodontists"
    ],
    "sg:website":"http://www.creekbridgedental.com",
    "wof:name":"CreekBridge Dental",
    "wof:placetype":"venue"
},
  "geometry": {"coordinates":[-93.34442900000001,45.087261],"type":"Point"}
}