{
  "type": "Feature",
  "properties": {
    "addr:full":"9375 Co Rd 6 SW Stewartville MN 55976",
    "addr:housenumber":"9375",
    "addr:postcode":"55976",
    "addr:street":"Co Rd 6 Sw",
    "iso:country":"US",
    "sg:address":"9375 Co Rd 6 SW",
    "sg:city":"Stewartville",
    "sg:phone":"+1 507 533 8375",
    "sg:postcode":"55976",
    "sg:province":"MN",
    "sg:tags":[
        "farm",
        "corn"
    ],
    "wof:name":"Alvin Wendt",
    "wof:placetype":"venue"
},
  "geometry": {"coordinates":[-92.623313,43.841339],"type":"Point"}
}