{
  "type": "Feature",
  "properties": {
    "iso:country":"US",
    "sg:address":"1116 4th Ave NW",
    "sg:city":"Faribault",
    "sg:classifiers":[
        {
            "category":"Wholesale",
            "subcategory":"Meat",
            "type":"Manufacturing & Wholesale Goods"
        }
    ],
    "sg:phone":"+1 507 334 5555",
    "sg:postcode":"55021",
    "sg:province":"MN",
    "sg:tags":[
        "poultry",
        "plant",
        "processing"
    ],
    "sg:website":"www.theturkeystore.com",
    "wof:name":"Jennie-O Turkey Store Inc",
    "wof:placetype":"venue"
},
  "geometry": {"coordinates":[-93.27478000000001,44.303698],"type":"Point"}
}