{
  "type": "Feature",
  "properties": {
    "addr:full":"1832 Wayzata Blvd Long Lake MN 55356",
    "addr:housenumber":"1832",
    "addr:postcode":"55356",
    "addr:street":"Wayzata Blvd",
    "iso:country":"US",
    "sg:address":"1832 Wayzata Blvd",
    "sg:city":"Long Lake",
    "sg:classifiers":[
        {
            "category":"Restaurant",
            "type":"Food & Drink"
        }
    ],
    "sg:phone":"+1 952 473 4089",
    "sg:postcode":"55356",
    "sg:province":"MN",
    "wof:name":"Red Rooster Lounge & Rstrnt",
    "wof:placetype":"venue"
},
  "geometry": {"coordinates":[-93.571353,44.986428],"type":"Point"}
}