{
  "type": "Feature",
  "properties": {
    "iso:country":"US",
    "sg:address":"410 5th St S",
    "sg:city":"Hallock",
    "sg:classifiers":[
        {
            "category":"Professional",
            "subcategory":"Business Services",
            "type":"Services"
        }
    ],
    "sg:phone":"+1 218 843 3333",
    "sg:postcode":"56728",
    "sg:province":"MN",
    "sg:tags":[
        "water",
        "conservation"
    ],
    "wof:name":"Two River Watershed District",
    "wof:placetype":"venue"
},
  "geometry": {"coordinates":[-96.940084,48.772416],"type":"Point"}
}