{
  "type": "Feature",
  "properties": {
    "addr:full":"9658 Xylon Ave S Minneapolis MN 55438",
    "addr:housenumber":"9658",
    "addr:postcode":"55438",
    "addr:street":"Xylon Ave S",
    "iso:country":"US",
    "sg:address":"9658 Xylon Ave S",
    "sg:city":"Minneapolis",
    "sg:classifiers":[
        {
            "category":"Professional",
            "subcategory":"Art Services",
            "type":"Services"
        }
    ],
    "sg:phone":"+1 952 829 7177",
    "sg:postcode":"55438",
    "sg:province":"MN",
    "sg:tags":[
        "commercial",
        "design"
    ],
    "wof:name":"Pizzazz Graphics Inc",
    "wof:placetype":"venue"
},
  "geometry": {"coordinates":[-93.38851099999999,44.82841],"type":"Point"}
}