{
  "type": "Feature",
  "properties": {
    "addr:full":"113 Aspen Ave S Menahga MN 56464",
    "addr:housenumber":"113",
    "addr:postcode":"56464",
    "addr:street":"Aspen Ave S Menahga",
    "iso:country":"US",
    "sg:address":"113 Aspen Ave S",
    "sg:city":"Menahga",
    "sg:classifiers":[
        {
            "category":"Manufacturing",
            "subcategory":"Printing",
            "type":"Manufacturing & Wholesale Goods"
        }
    ],
    "sg:phone":"+1 218 564 4559",
    "sg:postcode":"56464",
    "sg:province":"MN",
    "sg:tags":[
        "newspaper"
    ],
    "sg:website":"www.reviewmessenger.com",
    "wof:name":"Review Messenger",
    "wof:placetype":"venue"
},
  "geometry": {"coordinates":[-95.097281,46.752902],"type":"Point"}
}