{
  "type": "Feature",
  "properties": {
    "iso:country":"US",
    "sg:address":"2650 Morris Thomas Rd",
    "sg:city":"Duluth",
    "sg:classifiers":[
        {
            "category":"Manufacturing",
            "subcategory":"Building Materials",
            "type":"Manufacturing & Wholesale Goods"
        }
    ],
    "sg:phone":"+1 218 723 8198",
    "sg:postcode":"55811",
    "sg:province":"MN",
    "sg:tags":[
        "mfg"
    ],
    "wof:name":"Abbotts Custom Trellis & Arbor",
    "wof:placetype":"venue"
},
  "geometry": {"coordinates":[-92.16260800000001,46.778483],"type":"Point"}
}