{
  "type": "Feature",
  "properties": {
    "addr:full":"19690 Halwood Rd Glenwood MN 56334",
    "addr:housenumber":"19690",
    "addr:postcode":"56334",
    "addr:street":"Halwood Rd",
    "iso:country":"US",
    "sg:address":"19690 Halwood Rd",
    "sg:city":"Glenwood",
    "sg:classifiers":[
        {
            "category":"Government",
            "subcategory":"Office",
            "type":"Public Place"
        }
    ],
    "sg:phone":"+1 320 634 5414",
    "sg:postcode":"56334",
    "sg:province":"MN",
    "sg:tags":[
        "management"
    ],
    "wof:name":"B & L Utility Company",
    "wof:placetype":"venue"
},
  "geometry": {"coordinates":[-95.401037,45.625024],"type":"Point"}
}