{
  "type": "Feature",
  "properties": {
    "addr:full":"7240 Dresser Dr NE Rochester MN 55906",
    "addr:housenumber":"7240",
    "addr:postcode":"55906",
    "addr:street":"Dresser Dr Ne",
    "iso:country":"US",
    "sg:address":"7240 Dresser Dr NE",
    "sg:city":"Rochester",
    "sg:classifiers":[
        {
            "category":"Place Of Worship",
            "type":"Public Place"
        },
        {
            "category":"Education",
            "subcategory":"School",
            "type":"Public Place"
        },
        {
            "category":"Organizations",
            "subcategory":"Religious Organization",
            "type":"Services"
        }
    ],
    "sg:phone":"+1 507 282 7981",
    "sg:postcode":"55906",
    "sg:province":"MN",
    "sg:tags":[
        "interest",
        "private",
        "k-",
        "church"
    ],
    "sg:website":"http://www.rochester24.adventistchurchconnect.org",
    "wof:name":"Green Valley Sda School",
    "wof:placetype":"venue"
},
  "geometry": {"coordinates":[-92.429748,44.103756],"type":"Point"}
}