{
  "type": "Feature",
  "properties": {
    "addr:full":"33352 250th St Underwood MN 56586",
    "addr:housenumber":"33352",
    "addr:postcode":"56586",
    "addr:street":"250Th St",
    "iso:country":"US",
    "sg:address":"33352 250th St",
    "sg:city":"Underwood",
    "sg:classifiers":[
        {
            "category":"Building & Trades",
            "subcategory":"Construction",
            "type":"Services"
        }
    ],
    "sg:phone":"+1 218 826 6152",
    "sg:postcode":"56586",
    "sg:province":"MN",
    "sg:tags":[
        "contractor"
    ],
    "wof:name":"Stans Brothers",
    "wof:placetype":"venue"
},
  "geometry": {"coordinates":[-95.793345,46.325758],"type":"Point"}
}