{
  "type": "Feature",
  "properties": {
    "iso:country":"US",
    "sg:address":"1653 N Woodbridge St",
    "sg:city":"St Paul",
    "sg:classifiers":[
        {
            "category":"Building & Trades",
            "subcategory":"Cleaning & Sanitation",
            "type":"Services"
        }
    ],
    "sg:phone":"+1 651 488 8554",
    "sg:postcode":"55117",
    "sg:province":"MN",
    "sg:tags":[
        "janitor"
    ],
    "wof:name":"Detailed Cleaning Svc",
    "wof:placetype":"venue"
},
  "geometry": {"coordinates":[-93.108481,44.991104],"type":"Point"}
}