{
  "type": "Feature",
  "properties": {
    "addr:full":"501 Broadway E Little Falls MN 56345",
    "addr:housenumber":"501",
    "addr:postcode":"56345",
    "addr:street":"Broadway E",
    "iso:country":"US",
    "sg:address":"501 Broadway E",
    "sg:city":"Little Falls",
    "sg:classifiers":[
        {
            "category":"Insurance",
            "subcategory":"Insurance Agent",
            "type":"Services"
        }
    ],
    "sg:phone":"+1 320 632 5439",
    "sg:postcode":"56345",
    "sg:province":"MN",
    "wof:name":"State Farm Insurance",
    "wof:placetype":"venue"
},
  "geometry": {"coordinates":[-94.35636,45.975618],"type":"Point"}
}