{
  "type": "Feature",
  "properties": {
    "iso:country":"US",
    "sg:address":"2300 Silver Creek Rd NE",
    "sg:city":"Rochester",
    "sg:classifiers":[
        {
            "category":"Government",
            "subcategory":"Office",
            "type":"Public Place"
        }
    ],
    "sg:phone":"+1 507 285 7427",
    "sg:postcode":"55906",
    "sg:province":"MN",
    "sg:tags":[
        "state",
        "program"
    ],
    "wof:name":"DNR Regional Fisheries",
    "wof:placetype":"venue"
},
  "geometry": {"coordinates":[-92.428822,44.027819],"type":"Point"}
}