{
  "type": "Feature",
  "properties": {
    "iso:country":"US",
    "sg:address":"600 US Hwy 169",
    "sg:city":"St Louis Park",
    "sg:classifiers":[
        {
            "category":"Real Estate",
            "subcategory":"Real Estate Agent",
            "type":"Services"
        }
    ],
    "sg:phone":"+1 952 512 5500",
    "sg:postcode":"55426",
    "sg:province":"MN",
    "sg:tags":[
        "relocation"
    ],
    "sg:website":"www.plusrelo.com",
    "wof:name":"Plus Relocation Svc",
    "wof:placetype":"venue"
},
  "geometry": {"coordinates":[-93.40041100000001,44.975609],"type":"Point"}
}