{
  "type": "Feature",
  "properties": {
    "iso:country":"US",
    "sg:address":"709 Wilson St",
    "sg:city":"Albert Lea",
    "sg:classifiers":[
        {
            "category":"Insurance",
            "subcategory":"Insurance Agent",
            "type":"Services"
        }
    ],
    "sg:phone":"+1 507 377 8904",
    "sg:postcode":"56007",
    "sg:province":"MN",
    "sg:website":"www.cafourek.com",
    "wof:name":"Cafourek & Assoc Inc",
    "wof:placetype":"venue"
},
  "geometry": {"coordinates":[-93.359461,43.651825],"type":"Point"}
}