{
  "type": "Feature",
  "properties": {
    "addr:full":"60231 Jessica Dr Madison Lake MN 56063",
    "addr:housenumber":"60231",
    "addr:postcode":"56063",
    "addr:street":"Jessica Dr",
    "iso:country":"US",
    "sg:address":"60231 Jessica Dr",
    "sg:city":"Madison Lake",
    "sg:classifiers":[
        {
            "category":"Real Estate",
            "subcategory":"Architect",
            "type":"Services"
        }
    ],
    "sg:phone":"+1 507 243 3071",
    "sg:postcode":"56063",
    "sg:province":"MN",
    "wof:name":"Rice Architects",
    "wof:placetype":"venue"
},
  "geometry": {"coordinates":[-93.879767,44.237468],"type":"Point"}
}