{
  "type": "Feature",
  "properties": {
    "iso:country":"US",
    "sg:address":"401 N Granum Ave",
    "sg:city":"Fosston",
    "sg:classifiers":[
        {
            "category":"Building & Trades",
            "subcategory":"Construction",
            "type":"Services"
        }
    ],
    "sg:phone":"+1 218 435 1317",
    "sg:postcode":"56542",
    "sg:province":"MN",
    "sg:tags":[
        "product",
        "asphalt"
    ],
    "wof:name":"North Country Asphalt Maintnce",
    "wof:placetype":"venue"
},
  "geometry": {"coordinates":[-95.74754900000001,47.579336],"type":"Point"}
}