{
  "type": "Feature",
  "properties": {
    "addr:full":"2590 60th St SW Appleton MN 56208",
    "addr:housenumber":"2590",
    "addr:postcode":"56208",
    "addr:street":"60Th St Sw",
    "iso:country":"US",
    "sg:address":"2590 60th St SW",
    "sg:city":"Appleton",
    "sg:phone":"+1 320 289 1278",
    "sg:postcode":"56208",
    "sg:province":"MN",
    "sg:tags":[
        "farm",
        "corn"
    ],
    "wof:name":"Craig Semler",
    "wof:placetype":"venue"
},
  "geometry": {"coordinates":[-96.114925,45.239776],"type":"Point"}
}