{
  "type": "Feature",
  "properties": {
    "iso:country":"US",
    "sg:address":"5857 Hwy 73",
    "sg:city":"Chisholm",
    "sg:classifiers":[
        {
            "category":"Building & Trades",
            "subcategory":"Construction",
            "type":"Services"
        }
    ],
    "sg:phone":"+1 218 254 3919",
    "sg:postcode":"55719",
    "sg:province":"MN",
    "sg:tags":[
        "excavating",
        "contractor"
    ],
    "wof:name":"Iverson Construction Inc",
    "wof:placetype":"venue"
},
  "geometry": {"coordinates":[-92.87961799999999,47.540639],"type":"Point"}
}