{
  "type": "Feature",
  "properties": {
    "addr:full":"314 Meadow Ln Benson MN 56215",
    "addr:housenumber":"314",
    "addr:postcode":"56215",
    "addr:street":"Meadow Ln",
    "iso:country":"US",
    "sg:address":"314 Meadow Ln",
    "sg:city":"Benson",
    "sg:phone":"+1 320 843 2869",
    "sg:postcode":"56215",
    "sg:province":"MN",
    "sg:tags":[
        "farm",
        "corn",
        "soybean"
    ],
    "wof:name":"Trans Wood",
    "wof:placetype":"venue"
},
  "geometry": {"coordinates":[-95.610445,45.319632],"type":"Point"}
}