{
  "type": "Feature",
  "properties": {
    "iso:country":"US",
    "sg:address":"21258 Durfee Ave",
    "sg:city":"Adrian",
    "sg:classifiers":[
        {
            "category":"Farming",
            "subcategory":"Dairy Farm",
            "type":"Manufacturing & Wholesale Goods"
        }
    ],
    "sg:phone":"+1 507 483 2078",
    "sg:postcode":"56110",
    "sg:province":"MN",
    "wof:name":"Brian Gengler",
    "wof:placetype":"venue"
},
  "geometry": {"coordinates":[-95.89310999999999,43.684826],"type":"Point"}
}