{
  "type": "Feature",
  "properties": {
    "addr:full":"2501 37th Ave NE Minneapolis MN 55421",
    "addr:housenumber":"2501",
    "addr:postcode":"55421",
    "addr:street":"37Th Ave Ne",
    "iso:country":"US",
    "sg:address":"2501 37th Ave NE",
    "sg:city":"Minneapolis",
    "sg:classifiers":[
        {
            "category":"Professional",
            "subcategory":"Art Services",
            "type":"Services"
        }
    ],
    "sg:phone":"+1 612 250 7387",
    "sg:postcode":"55421",
    "sg:province":"MN",
    "sg:tags":[
        "photographer"
    ],
    "wof:name":"Petography",
    "wof:placetype":"venue"
},
  "geometry": {"coordinates":[-93.223732,45.035683],"type":"Point"}
}