{
  "type": "Feature",
  "properties": {
    "iso:country":"US",
    "sg:address":"10404 Eagle St NW",
    "sg:city":"Minneapolis",
    "sg:classifiers":[
        {
            "category":"Social Services",
            "subcategory":"Child Care",
            "type":"Services"
        }
    ],
    "sg:phone":"+1 763 754 6396",
    "sg:postcode":"55433",
    "sg:province":"MN",
    "sg:tags":[
        "daycare",
        "provider"
    ],
    "wof:name":"Shelly Hagen",
    "wof:placetype":"venue"
},
  "geometry": {"coordinates":[-93.30080700000001,45.156766],"type":"Point"}
}