{
  "type": "Feature",
  "properties": {
    "iso:country":"US",
    "sg:address":"840 Elm St E",
    "sg:city":"Annandale",
    "sg:classifiers":[
        {
            "category":"Autos & Motor Vehicles",
            "subcategory":"Automobile Sales",
            "type":"Retail Goods"
        }
    ],
    "sg:phone":"+1 320 274 3064",
    "sg:postcode":"55302",
    "sg:province":"MN",
    "sg:tags":[
        "car",
        "dealer"
    ],
    "sg:website":"www.countrychev.com",
    "wof:name":"Country Chevrolet Inc",
    "wof:placetype":"venue"
},
  "geometry": {"coordinates":[-94.110147,45.256202],"type":"Point"}
}