{
  "type": "Feature",
  "properties": {
    "iso:country":"US",
    "sg:address":"548 Johnson St",
    "sg:city":"Dawson",
    "sg:classifiers":[
        {
            "category":"Building & Trades",
            "subcategory":"Construction",
            "type":"Services"
        }
    ],
    "sg:phone":"+1 320 769 2596",
    "sg:postcode":"56232",
    "sg:province":"MN",
    "sg:tags":[
        "farm",
        "water",
        "sewer",
        "drainage"
    ],
    "wof:name":"Larson Tiling Inc",
    "wof:placetype":"venue"
},
  "geometry": {"coordinates":[-96.053763,44.937089],"type":"Point"}
}