{
  "type": "Feature",
  "properties": {
    "addr:full":"1176 Highland Ave Northfield MN 55057",
    "addr:housenumber":"1176",
    "addr:postcode":"55057",
    "addr:street":"Highland Ave",
    "iso:country":"US",
    "sg:address":"1176 Highland Ave",
    "sg:city":"Northfield",
    "sg:classifiers":[
        {
            "category":"Professional",
            "subcategory":"Business Services",
            "type":"Services"
        }
    ],
    "sg:phone":"+1 507 645 2450",
    "sg:postcode":"55057",
    "sg:province":"MN",
    "wof:name":"String Solutions",
    "wof:placetype":"venue"
},
  "geometry": {"coordinates":[-93.176784,44.465266],"type":"Point"}
}