{
  "type": "Feature",
  "properties": {
    "iso:country":"US",
    "sg:address":"914 Upper Valley Dr",
    "sg:city":"Blue Earth",
    "sg:classifiers":[
        {
            "category":"Building & Trades",
            "subcategory":"Construction",
            "type":"Services"
        }
    ],
    "sg:phone":"+1 507 526 5548",
    "sg:postcode":"56013",
    "sg:province":"MN",
    "sg:tags":[
        "house"
    ],
    "wof:name":"Blue Earth Builders",
    "wof:placetype":"venue"
},
  "geometry": {"coordinates":[-94.08857999999999,43.647251],"type":"Point"}
}