{
  "type": "Feature",
  "properties": {
    "addr:full":"34569 442nd Pl Aitkin MN 56431",
    "addr:housenumber":"34569",
    "addr:postcode":"56431",
    "addr:street":"442Nd Pl",
    "iso:country":"US",
    "sg:address":"34569 442nd Pl",
    "sg:city":"Aitkin",
    "sg:classifiers":[
        {
            "category":"Shopping",
            "subcategory":"Catalog Store",
            "type":"Retail Goods"
        }
    ],
    "sg:phone":"+1 218 927 3097",
    "sg:postcode":"56431",
    "sg:province":"MN",
    "sg:tags":[
        "mail",
        "house"
    ],
    "wof:name":"Simplicity Counts",
    "wof:placetype":"venue"
},
  "geometry": {"coordinates":[-93.77772299999999,46.508966],"type":"Point"}
}