{
  "type": "Feature",
  "properties": {
    "addr:full":"461 240th St Odin MN 56160",
    "addr:housenumber":"461",
    "addr:postcode":"56160",
    "addr:street":"240Th St",
    "iso:country":"US",
    "sg:address":"461 240th St",
    "sg:city":"Odin",
    "sg:classifiers":[
        {
            "category":"Farming",
            "subcategory":"Farm",
            "type":"Manufacturing & Wholesale Goods"
        }
    ],
    "sg:phone":"+1 507 736 4780",
    "sg:postcode":"56160",
    "sg:province":"MN",
    "sg:tags":[
        "crop",
        "general"
    ],
    "wof:name":"Howard Hockel",
    "wof:placetype":"venue"
},
  "geometry": {"coordinates":[-94.78231100000001,43.83406],"type":"Point"}
}