{
  "type": "Feature",
  "properties": {
    "iso:country":"US",
    "sg:address":"114 Center Ave",
    "sg:city":"Eyota",
    "sg:classifiers":[
        {
            "category":"Food & Beverages",
            "subcategory":"Meat & Fish",
            "type":"Retail Goods"
        }
    ],
    "sg:phone":"+1 507 545 9904",
    "sg:postcode":"55934",
    "sg:province":"MN",
    "wof:name":"Burt's Meats & Poultry",
    "wof:placetype":"venue"
},
  "geometry": {"coordinates":[-92.229055,43.989644],"type":"Point"}
}