{
  "type": "Feature",
  "properties": {
    "addr:full":"900 Hilligoss Blvd SE Fosston MN 56542",
    "addr:housenumber":"900",
    "addr:postcode":"56542",
    "addr:street":"Hilligoss Blvd Se",
    "iso:country":"US",
    "sg:address":"900 Hilligoss Blvd SE",
    "sg:city":"Fosston",
    "sg:classifiers":[
        {
            "category":"Health Services",
            "subcategory":"Doctor",
            "type":"Services"
        }
    ],
    "sg:phone":"+1 218 435 1500",
    "sg:postcode":"56542",
    "sg:province":"MN",
    "sg:tags":[
        "physician",
        "pediatrics-orthopedic",
        "surgeons",
        "orthopedics",
        "surgery",
        "surgeon"
    ],
    "wof:name":"Headwaters Orthopedics",
    "wof:placetype":"venue"
},
  "geometry": {"coordinates":[-95.740639,47.572105],"type":"Point"}
}