{
  "type": "Feature",
  "properties": {
    "addr:full":"18785 Perkins Valley Dr Houston MN 55943",
    "addr:housenumber":"18785",
    "addr:postcode":"55943",
    "addr:street":"Perkins Valley Dr",
    "iso:country":"US",
    "sg:address":"18785 Perkins Valley Dr",
    "sg:city":"Houston",
    "sg:classifiers":[
        {
            "category":"Farming",
            "subcategory":"Farm",
            "type":"Manufacturing & Wholesale Goods"
        }
    ],
    "sg:phone":"+1 507 896 2273",
    "sg:postcode":"55943",
    "sg:province":"MN",
    "sg:tags":[
        "crop",
        "general"
    ],
    "wof:name":"Lowell Kinstler",
    "wof:placetype":"venue"
},
  "geometry": {"coordinates":[-91.634112,43.7871],"type":"Point"}
}