{
  "type": "Feature",
  "properties": {
    "addr:full":"720 Widsten Cir Wayzata MN 55391",
    "addr:housenumber":"720",
    "addr:postcode":"55391",
    "addr:street":"Widsten Cir",
    "iso:country":"US",
    "sg:address":"720 Widsten Cir",
    "sg:city":"Wayzata",
    "sg:classifiers":[
        {
            "category":"Professional",
            "type":"Services"
        }
    ],
    "sg:phone":"+1 952 473 5346",
    "sg:postcode":"55391",
    "sg:province":"MN",
    "wof:name":"David J Lentz",
    "wof:placetype":"venue"
},
  "geometry": {"coordinates":[-93.509001,44.970198],"type":"Point"}
}