{
  "type": "Feature",
  "properties": {
    "addr:full":"7575 Golden Valley Rd # 140 Minneapolis MN 55427",
    "addr:housenumber":"7575",
    "addr:postcode":"55427",
    "addr:street":"Golden Valley Rd # 140",
    "iso:country":"US",
    "sg:address":"7575 Golden Valley Rd # 140",
    "sg:city":"Minneapolis",
    "sg:classifiers":[
        {
            "category":"Professional",
            "subcategory":"Accounting & Tax Preparation",
            "type":"Services"
        }
    ],
    "sg:phone":"+1 763 557 9093",
    "sg:postcode":"55427",
    "sg:province":"MN",
    "sg:tags":[
        "return",
        "preparation-business"
    ],
    "wof:name":"Hensen Jane Tax & Business Services",
    "wof:placetype":"venue"
},
  "geometry": {"coordinates":[-93.376379,44.986306],"type":"Point"}
}