{
  "type": "Feature",
  "properties": {
    "addr:full":"2641 29th Ave S Minneapolis MN 55406",
    "addr:housenumber":"2641",
    "addr:postcode":"55406",
    "addr:street":"29Th Ave S",
    "iso:country":"US",
    "sg:address":"2641 29th Ave S",
    "sg:city":"Minneapolis",
    "sg:classifiers":[
        {
            "category":"Building & Trades",
            "subcategory":"Construction",
            "type":"Services"
        }
    ],
    "sg:phone":"+1 612 722 5611",
    "sg:postcode":"55406",
    "sg:province":"MN",
    "sg:tags":[
        "roofing",
        "siding",
        "contractor",
        "general"
    ],
    "wof:name":"Gamber Roofing Company",
    "wof:placetype":"venue"
},
  "geometry": {"coordinates":[-93.229862,44.954515],"type":"Point"}
}