{
  "type": "Feature",
  "properties": {
    "iso:country":"US",
    "sg:address":"7964 Brooklyn Blvd",
    "sg:city":"Minneapolis",
    "sg:classifiers":[
        {
            "category":"Building & Trades",
            "subcategory":"Locksmith",
            "type":"Services"
        }
    ],
    "sg:phone":"+1 763 463 0703",
    "sg:postcode":"55445",
    "sg:province":"MN",
    "sg:tags":[
        "lock",
        "industrial",
        "locksmiths-commercial"
    ],
    "sg:website":"http://www.tclocksmiths.com",
    "wof:name":"TClocksmiths inc.",
    "wof:placetype":"venue"
},
  "geometry": {"coordinates":[-93.37498600000001,45.09456],"type":"Point"}
}