{
  "type": "Feature",
  "properties": {
    "iso:country":"US",
    "sg:address":"31995 Eveleth Ave",
    "sg:city":"Northfield",
    "sg:classifiers":[
        {
            "category":"Professional",
            "subcategory":"Engineering",
            "type":"Services"
        }
    ],
    "sg:phone":"+1 507 645 7784",
    "sg:postcode":"55057",
    "sg:province":"MN",
    "wof:name":"Mathew Langer",
    "wof:placetype":"venue"
},
  "geometry": {"coordinates":[-93.18079299999999,44.485852],"type":"Point"}
}