{
  "type": "Feature",
  "properties": {
    "addr:full":"29 7th Ave NE Minneapolis MN 55413",
    "addr:housenumber":"29",
    "addr:postcode":"55413",
    "addr:street":"7Th Ave Ne",
    "iso:country":"US",
    "sg:address":"29 7th Ave NE",
    "sg:city":"Minneapolis",
    "sg:classifiers":[
        {
            "category":"Manufacturing",
            "subcategory":"Tools & Machinery",
            "type":"Manufacturing & Wholesale Goods"
        }
    ],
    "sg:phone":"+1 612 379 7025",
    "sg:postcode":"55413",
    "sg:province":"MN",
    "sg:tags":[
        "snow",
        "plowing"
    ],
    "wof:name":"TW Nelson Snow Plowing Inc",
    "wof:placetype":"venue"
},
  "geometry": {"coordinates":[-93.268992,44.993329],"type":"Point"}
}