{
  "type": "Feature",
  "properties": {
    "iso:country":"US",
    "sg:address":"3500 Vicksburg Ln N Ste 500",
    "sg:city":"Minneapolis",
    "sg:classifiers":[
        {
            "category":"Restaurant",
            "type":"Food & Drink"
        }
    ],
    "sg:phone":"+1 763 553 2900",
    "sg:postcode":"55447",
    "sg:province":"MN",
    "sg:tags":[
        "barbecue",
        "american"
    ],
    "sg:website":"http://www.rudolphsribs.com",
    "wof:name":"Rudolphs Bar-b-que",
    "wof:placetype":"venue"
},
  "geometry": {"coordinates":[-93.48168200000001,45.020802],"type":"Point"}
}