{
  "type": "Feature",
  "properties": {
    "addr:full":"1056 Burnsville Ctr Burnsville MN 55306",
    "addr:housenumber":"1056",
    "addr:postcode":"55306",
    "addr:street":"Burnsville Ctr",
    "iso:country":"US",
    "sg:address":"1056 Burnsville Ctr",
    "sg:city":"Burnsville",
    "sg:classifiers":[
        {
            "category":"Shopping",
            "subcategory":"Optical Goods",
            "type":"Retail Goods"
        }
    ],
    "sg:phone":"+1 952 435 2662",
    "sg:postcode":"55306",
    "sg:province":"MN",
    "sg:tags":[
        "eyeglass"
    ],
    "wof:name":"Double Image Incorporated",
    "wof:placetype":"venue"
},
  "geometry": {"coordinates":[-93.284319,44.744478],"type":"Point"}
}