{
  "type": "Feature",
  "properties": {
    "iso:country":"US",
    "sg:address":"119 W Lincoln Ave",
    "sg:city":"Fergus Falls",
    "sg:classifiers":[
        {
            "category":"Shopping",
            "subcategory":"Used Merchandise",
            "type":"Retail Goods"
        }
    ],
    "sg:phone":"+1 218 739 5464",
    "sg:postcode":"56537",
    "sg:province":"MN",
    "wof:name":"Classic Antq & Collectibles",
    "wof:placetype":"venue"
},
  "geometry": {"coordinates":[-96.074428,46.283424],"type":"Point"}
}