{
  "type": "Feature",
  "properties": {
    "iso:country":"US",
    "sg:address":"1948 175th St",
    "sg:city":"Lester Prairie",
    "sg:classifiers":[
        {
            "category":"Retail",
            "subcategory":"Auto Repair",
            "type":"Services"
        }
    ],
    "sg:phone":"+1 320 395 2881",
    "sg:postcode":"55354",
    "sg:province":"MN",
    "sg:tags":[
        "exchanging",
        "engine"
    ],
    "wof:name":"Lester Prairie Engine",
    "wof:placetype":"venue"
},
  "geometry": {"coordinates":[-94.03043700000001,44.869452],"type":"Point"}
}