{
  "type": "Feature",
  "properties": {
    "addr:full":"13071 Zero Ave Plato MN 55370",
    "addr:postcode":"13071;55370",
    "addr:street":"Zero Ave",
    "iso:country":"US",
    "sg:address":"13071 Zero Ave",
    "sg:city":"Plato",
    "sg:classifiers":[
        {
            "category":"Farming",
            "subcategory":"Livestock Farm",
            "type":"Manufacturing & Wholesale Goods"
        }
    ],
    "sg:phone":"+1 320 238 2386",
    "sg:postcode":"55370",
    "sg:province":"MN",
    "sg:tags":[
        "corn",
        "beef",
        "feedlot",
        "cattle"
    ],
    "wof:name":"Roger Martin",
    "wof:placetype":"venue"
},
  "geometry": {"coordinates":[-94.020262,44.804985],"type":"Point"}
}