{
  "type": "Feature",
  "properties": {
    "addr:full":"1699 Birch Lake Ave St Paul MN 55110",
    "addr:housenumber":"1699",
    "addr:postcode":"55110",
    "addr:street":"Birch Lake Ave",
    "iso:country":"US",
    "sg:address":"1699 Birch Lake Ave",
    "sg:city":"St Paul",
    "sg:classifiers":[
        {
            "category":"Building & Trades",
            "subcategory":"Construction",
            "type":"Services"
        }
    ],
    "sg:phone":"+1 651 493 4783",
    "sg:postcode":"55110",
    "sg:province":"MN",
    "sg:tags":[
        "home",
        "improvement"
    ],
    "wof:name":"Helpfull Repair",
    "wof:placetype":"venue"
},
  "geometry": {"coordinates":[-93.031066,45.082921],"type":"Point"}
}