{
  "type": "Feature",
  "properties": {
    "iso:country":"US",
    "sg:address":"305 Rice St E",
    "sg:city":"Wayzata",
    "sg:classifiers":[
        {
            "category":"Real Estate",
            "subcategory":"Real Estate Agent",
            "type":"Services"
        }
    ],
    "sg:phone":"+1 952 473 0313",
    "sg:postcode":"55391",
    "sg:province":"MN",
    "sg:tags":[
        "appraiser"
    ],
    "wof:name":"William C Warner & Assoc",
    "wof:placetype":"venue"
},
  "geometry": {"coordinates":[-93.51549799999999,44.972393],"type":"Point"}
}