{
  "type": "Feature",
  "properties": {
    "iso:country":"US",
    "sg:address":"500 Kingston Ave",
    "sg:city":"St Paul",
    "sg:classifiers":[
        {
            "category":"Local Transit",
            "type":"Transportation"
        }
    ],
    "sg:phone":"+1 651 246 2080",
    "sg:postcode":"55117",
    "sg:province":"MN",
    "wof:name":"Asian Elder Transportation",
    "wof:placetype":"venue"
},
  "geometry": {"coordinates":[-93.076224,44.993711],"type":"Point"}
}