{
  "type": "Feature",
  "properties": {
    "addr:full":"8100 W 78th St Minneapolis MN 55439",
    "addr:housenumber":"8100",
    "addr:postcode":"55439",
    "addr:street":"W 78Th St",
    "iso:country":"US",
    "sg:address":"8100 W 78th St",
    "sg:city":"Minneapolis",
    "sg:classifiers":[
        {
            "category":"Health Services",
            "subcategory":"Medical Lab",
            "type":"Services"
        }
    ],
    "sg:phone":"+1 952 914 8046",
    "sg:postcode":"55439",
    "sg:province":"MN",
    "sg:tags":[
        "laboratories-pathological",
        "laboratory"
    ],
    "wof:name":"Allina Medical Laboratori",
    "wof:placetype":"venue"
},
  "geometry": {"coordinates":[-93.39035,44.859928],"type":"Point"}
}