{
  "type": "Feature",
  "properties": {
    "addr:full":"14910 Florence Trl Apple Valley MN 55124",
    "addr:housenumber":"14910",
    "addr:postcode":"55124",
    "addr:street":"Florence Trl",
    "iso:country":"US",
    "sg:address":"14910 Florence Trl",
    "sg:city":"Apple Valley",
    "sg:classifiers":[
        {
            "category":"Home & Garden",
            "subcategory":"Home Furnishings",
            "type":"Retail Goods"
        }
    ],
    "sg:phone":"+1 952 432 1730",
    "sg:postcode":"55124",
    "sg:province":"MN",
    "sg:tags":[
        "housewares"
    ],
    "wof:name":"Bed Bath & Beyond Inc",
    "wof:placetype":"venue"
},
  "geometry": {"coordinates":[-93.203885,44.7329],"type":"Point"}
}