{
  "type": "Feature",
  "properties": {
    "iso:country":"US",
    "sg:address":"305 Minnetonka Ave S # 250",
    "sg:city":"Wayzata",
    "sg:classifiers":[
        {
            "category":"Real Estate",
            "subcategory":"Real Estate Services",
            "type":"Services"
        },
        {
            "category":"Social Services",
            "subcategory":"Retirement Home",
            "type":"Services"
        },
        {
            "category":"Real Estate",
            "subcategory":"Real Estate Operator",
            "type":"Services"
        }
    ],
    "sg:phone":"+1 763 479 4321",
    "sg:postcode":"55391",
    "sg:province":"MN",
    "sg:tags":[
        "boarding",
        "vacancy",
        "apartment",
        "house",
        "rooming",
        "listing",
        "rental",
        "finder"
    ],
    "sg:website":"http://www.creativehousingsolutions.com",
    "wof:name":"Creative Housing Solutions Inc.",
    "wof:placetype":"venue"
},
  "geometry": {"coordinates":[-93.51461999999999,44.970964],"type":"Point"}
}