{
  "type": "Feature",
  "properties": {
    "addr:full":"490 Co Rd B E Saint Paul MN 55117",
    "addr:housenumber":"490",
    "addr:postcode":"55117",
    "addr:street":"Co Rd B E",
    "iso:country":"US",
    "sg:address":"490 Co Rd B E",
    "sg:city":"Saint Paul",
    "sg:classifiers":[
        {
            "category":"Professional",
            "subcategory":"Management & Consulting",
            "type":"Services"
        }
    ],
    "sg:phone":"+1 651 776 7511",
    "sg:postcode":"55117",
    "sg:province":"MN",
    "sg:tags":[
        "lobbying"
    ],
    "wof:name":"Boland Associates",
    "wof:placetype":"venue"
},
  "geometry": {"coordinates":[-93.080752,45.006224],"type":"Point"}
}