{
  "type": "Feature",
  "properties": {
    "iso:country":"US",
    "sg:address":"301 E Mark St",
    "sg:city":"Winona",
    "sg:classifiers":[
        {
            "category":"Restaurant",
            "type":"Food & Drink"
        }
    ],
    "sg:phone":"+1 507 452 3150",
    "sg:postcode":"55987",
    "sg:province":"MN",
    "sg:tags":[
        "eating"
    ],
    "wof:name":"Steak Shop Catering Service",
    "wof:placetype":"venue"
},
  "geometry": {"coordinates":[-91.63396899999999,44.042809],"type":"Point"}
}