{
  "type": "Feature",
  "properties": {
    "iso:country":"US",
    "sg:address":"119 5th St N",
    "sg:city":"Breckenridge",
    "sg:classifiers":[
        {
            "category":"Personal",
            "subcategory":"Shoe Repair & Shine",
            "type":"Services"
        }
    ],
    "sg:phone":"+1 218 643 2150",
    "sg:postcode":"56520",
    "sg:province":"MN",
    "sg:tags":[
        "repairing",
        "retail",
        "boot",
        "footwear"
    ],
    "wof:name":"Jim's Shoe Repair",
    "wof:placetype":"venue"
},
  "geometry": {"coordinates":[-96.588035,46.264573],"type":"Point"}
}