{
  "type": "Feature",
  "properties": {
    "addr:full":"2315 14th St S Moorhead MN 56560",
    "addr:housenumber":"2315",
    "addr:postcode":"56560",
    "addr:street":"14Th St S",
    "iso:country":"US",
    "sg:address":"2315 14th St S",
    "sg:city":"Moorhead",
    "sg:classifiers":[
        {
            "category":"Farming",
            "subcategory":"Farm",
            "type":"Manufacturing & Wholesale Goods"
        }
    ],
    "sg:phone":"+1 218 236 7539",
    "sg:postcode":"56560",
    "sg:province":"MN",
    "sg:tags":[
        "local",
        "general",
        "storage",
        "crop",
        "trucking"
    ],
    "wof:name":"Jerry Mjolsness Ltd",
    "wof:placetype":"venue"
},
  "geometry": {"coordinates":[-96.757594,46.851483],"type":"Point"}
}