{
  "type": "Feature",
  "properties": {
    "iso:country":"US",
    "sg:address":"12221 Riverwood Dr",
    "sg:city":"Burnsville",
    "sg:classifiers":[
        {
            "category":"Retail",
            "subcategory":"Portrait Studio",
            "type":"Services"
        }
    ],
    "sg:phone":"+1 952 890 2200",
    "sg:postcode":"55337",
    "sg:province":"MN",
    "sg:tags":[
        "photography",
        "store"
    ],
    "wof:name":"Herff Jones Photo Processing Plant",
    "wof:placetype":"venue"
},
  "geometry": {"coordinates":[-93.261002,44.785702],"type":"Point"}
}