{
  "type": "Feature",
  "properties": {
    "addr:full":"17631 Hillwood Ave Lakeville MN 55044",
    "addr:housenumber":"17631",
    "addr:postcode":"55044",
    "addr:street":"Hillwood Ave",
    "iso:country":"US",
    "sg:address":"17631 Hillwood Ave",
    "sg:city":"Lakeville",
    "sg:classifiers":[
        {
            "category":"Shopping",
            "subcategory":"Gifts & Souvenirs",
            "type":"Retail Goods"
        }
    ],
    "sg:phone":"+1 952 432 8385",
    "sg:postcode":"55044",
    "sg:province":"MN",
    "wof:name":"Jeff Cornwell",
    "wof:placetype":"venue"
},
  "geometry": {"coordinates":[-93.242757,44.692812],"type":"Point"}
}