{
  "type": "Feature",
  "properties": {
    "addr:full":"108 2nd St E Canby MN 56220",
    "addr:housenumber":"108",
    "addr:postcode":"56220",
    "addr:street":"2Nd St E",
    "iso:country":"US",
    "sg:address":"108 2nd St E",
    "sg:city":"Canby",
    "sg:classifiers":[
        {
            "category":"Personal",
            "subcategory":"Beauty Salon",
            "type":"Services"
        }
    ],
    "sg:phone":"+1 507 223 7444",
    "sg:postcode":"56220",
    "sg:province":"MN",
    "wof:name":"Hair Styles By Jean",
    "wof:placetype":"venue"
},
  "geometry": {"coordinates":[-96.275265,44.709461],"type":"Point"}
}