{
  "type": "Feature",
  "properties": {
    "addr:full":"3706 14th Ave S Minneapolis MN 55407",
    "addr:housenumber":"3706",
    "addr:postcode":"55407",
    "addr:street":"14Th Ave S",
    "iso:country":"US",
    "sg:address":"3706 14th Ave S",
    "sg:city":"Minneapolis",
    "sg:classifiers":[
        {
            "category":"Building & Trades",
            "subcategory":"Construction",
            "type":"Services"
        }
    ],
    "sg:phone":"+1 612 824 8858",
    "sg:postcode":"55407",
    "sg:province":"MN",
    "sg:tags":[
        "painting",
        "contractor"
    ],
    "wof:name":"A1 Perfection Painting",
    "wof:placetype":"venue"
},
  "geometry": {"coordinates":[-93.25492800000001,44.935819],"type":"Point"}
}