{
  "type": "Feature",
  "properties": {
    "addr:full":"1029 2nd Ave Worthington MN 56187",
    "addr:housenumber":"1029",
    "addr:postcode":"56187",
    "addr:street":"2Nd Ave",
    "iso:country":"US",
    "sg:address":"1029 2nd Ave",
    "sg:city":"Worthington",
    "sg:classifiers":[
        {
            "category":"Manufacturing",
            "subcategory":"Tools & Machinery",
            "type":"Manufacturing & Wholesale Goods"
        }
    ],
    "sg:phone":"+1 507 372 2869",
    "sg:postcode":"56187",
    "sg:province":"MN",
    "sg:tags":[
        "industry",
        "mfg"
    ],
    "wof:name":"Docs Popcorn Co",
    "wof:placetype":"venue"
},
  "geometry": {"coordinates":[-95.595287,43.618973],"type":"Point"}
}