{
  "type": "Feature",
  "properties": {
    "addr:full":"503 W Main St Marshall MN 56258",
    "addr:housenumber":"503",
    "addr:postcode":"56258",
    "addr:street":"W Main St",
    "iso:country":"US",
    "sg:address":"503 W Main St",
    "sg:city":"Marshall",
    "sg:classifiers":[
        {
            "category":"Professional",
            "subcategory":"Advertising",
            "type":"Services"
        }
    ],
    "sg:phone":"+1 507 532 5769",
    "sg:postcode":"56258",
    "sg:province":"MN",
    "wof:name":"Cattoor's T & I Marketing",
    "wof:placetype":"venue"
},
  "geometry": {"coordinates":[-95.793643,44.450307],"type":"Point"}
}