{
  "type": "Feature",
  "properties": {
    "addr:full":"8700 Old Cedar Ave S Bloomington MN 55425",
    "addr:housenumber":"8700",
    "addr:postcode":"55425",
    "addr:street":"Old Cedar Ave S",
    "iso:country":"US",
    "sg:address":"8700 Old Cedar Ave S",
    "sg:city":"Bloomington",
    "sg:classifiers":[
        {
            "category":"Organizations",
            "subcategory":"Religious Organization",
            "type":"Services"
        }
    ],
    "sg:phone":"+1 952 854 6638",
    "sg:postcode":"55425",
    "sg:province":"MN",
    "sg:tags":[
        "church"
    ],
    "sg:website":"www.gracebythemall.org",
    "wof:name":"Grace Lutheran Church E L C A",
    "wof:placetype":"venue"
},
  "geometry": {"coordinates":[-93.24788599999999,44.8456],"type":"Point"}
}