{
  "type": "Feature",
  "properties": {
    "iso:country":"US",
    "sg:address":"2370 Lemay Lake Rd",
    "sg:city":"Mendota Heights",
    "sg:classifiers":[
        {
            "category":"Retail",
            "subcategory":"Repair Shop",
            "type":"Services"
        }
    ],
    "sg:phone":"+1 651 456 9139",
    "sg:postcode":"55120",
    "sg:province":"MN",
    "sg:tags":[
        "refinishing",
        "furniture"
    ],
    "wof:name":"Hussman Furniture Restoration",
    "wof:placetype":"venue"
},
  "geometry": {"coordinates":[-93.161834,44.874055],"type":"Point"}
}