{
  "type": "Feature",
  "properties": {
    "addr:full":"4454 Morristown Blvd Faribault MN 55021",
    "addr:housenumber":"4454",
    "addr:postcode":"55021",
    "addr:street":"Morristown Blvd",
    "iso:country":"US",
    "sg:address":"4454 Morristown Blvd",
    "sg:city":"Faribault",
    "sg:classifiers":[
        {
            "category":"Manufacturing",
            "subcategory":"Tools & Machinery",
            "type":"Manufacturing & Wholesale Goods"
        }
    ],
    "sg:phone":"+1 507 334 6193",
    "sg:postcode":"55021",
    "sg:province":"MN",
    "sg:tags":[
        "stairway",
        "moving",
        "elevator"
    ],
    "sg:website":"www.humphrey-manlift.com",
    "wof:name":"Humphrey Manlift Co",
    "wof:placetype":"venue"
},
  "geometry": {"coordinates":[-93.341269,44.264474],"type":"Point"}
}