{
  "type": "Feature",
  "properties": {
    "addr:full":"4210 W 44th St Edina MN 55424",
    "addr:housenumber":"4210",
    "addr:postcode":"55424",
    "addr:street":"W 44Th St",
    "iso:country":"US",
    "sg:address":"4210 W 44th St",
    "sg:city":"Edina",
    "sg:classifiers":[
        {
            "category":"Social Services",
            "type":"Services"
        }
    ],
    "sg:phone":"+1 952 920 9291",
    "sg:postcode":"55424",
    "sg:province":"MN",
    "sg:tags":[
        "organization",
        "welfare"
    ],
    "wof:name":"Integrity Living Options Inc",
    "wof:placetype":"venue"
},
  "geometry": {"coordinates":[-93.335769,44.921424],"type":"Point"}
}