{
  "type": "Feature",
  "properties": {
    "iso:country":"US",
    "sg:address":"7334 Fort Ridgley Rd",
    "sg:city":"Houston",
    "sg:phone":"+1 507 896 2265",
    "sg:postcode":"55943",
    "sg:province":"MN",
    "sg:tags":[
        "farm",
        "corn"
    ],
    "wof:name":"Unnasch Burdette",
    "wof:placetype":"venue"
},
  "geometry": {"coordinates":[-91.532365,43.743084],"type":"Point"}
}