{
  "type": "Feature",
  "properties": {
    "addr:full":"127 3rd Ave N Minneapolis MN 55401",
    "addr:housenumber":"127",
    "addr:postcode":"55401",
    "addr:street":"3Rd Ave N",
    "iso:country":"US",
    "sg:address":"127 3rd Ave N",
    "sg:city":"Minneapolis",
    "sg:classifiers":[
        {
            "category":"Professional",
            "type":"Services"
        }
    ],
    "sg:phone":"+1 612 343 4300",
    "sg:postcode":"55401",
    "sg:province":"MN",
    "wof:name":"Axlmail Co",
    "wof:placetype":"venue"
},
  "geometry": {"coordinates":[-93.271074,44.985519],"type":"Point"}
}