{
  "type": "Feature",
  "properties": {
    "iso:country":"US",
    "sg:address":"407 Central Ave SE",
    "sg:city":"Minneapolis",
    "sg:classifiers":[
        {
            "category":"Professional",
            "subcategory":"Employment Agencies",
            "type":"Services"
        }
    ],
    "sg:phone":"+1 612 379 2911",
    "sg:postcode":"55414",
    "sg:province":"MN",
    "sg:tags":[
        "photography",
        "commercial",
        "help",
        "supply"
    ],
    "wof:name":"Buccina Studios Limited",
    "wof:placetype":"venue"
},
  "geometry": {"coordinates":[-93.253182,44.988664],"type":"Point"}
}