{
  "type": "Feature",
  "properties": {
    "iso:country":"US",
    "sg:address":"325 Cedar St",
    "sg:city":"Saint Paul",
    "sg:classifiers":[
        {
            "category":"Professional",
            "subcategory":"Lawyer & Legal Services",
            "type":"Services"
        }
    ],
    "sg:phone":"+1 651 221 4050",
    "sg:postcode":"55103",
    "sg:province":"MN",
    "wof:name":"Kirchoff Law Firm",
    "wof:placetype":"venue"
},
  "geometry": {"coordinates":[-93.093976,44.947102],"type":"Point"}
}