{
  "type": "Feature",
  "properties": {
    "iso:country":"US",
    "sg:address":"2358 103rd Ave",
    "sg:city":"Braham",
    "sg:classifiers":[
        {
            "category":"Shopping",
            "subcategory":"Used Merchandise",
            "type":"Retail Goods"
        }
    ],
    "sg:phone":"+1 320 396 3530",
    "sg:postcode":"55006",
    "sg:province":"MN",
    "sg:website":"www.theswapshop.org",
    "wof:name":"Swap Shop",
    "wof:placetype":"venue"
},
  "geometry": {"coordinates":[-93.233417,45.7344],"type":"Point"}
}