{
  "type": "Feature",
  "properties": {
    "iso:country":"US",
    "sg:address":"7400 Lyndale Ave S #180",
    "sg:city":"Minneapolis",
    "sg:classifiers":[
        {
            "category":"Professional",
            "subcategory":"Lawyer & Legal Services",
            "type":"Services"
        }
    ],
    "sg:phone":"+1 612 392 5740",
    "sg:postcode":"55423",
    "sg:province":"MN",
    "sg:tags":[
        "practice",
        "attorney",
        "criminal",
        "law"
    ],
    "sg:website":"http://www.dexknows.com/rd?dku=http://ohlenbergrichardpattorneyatlaw.com%3Fmkt=65901",
    "wof:name":"Richard P. Ohlenberg Attorney at Law",
    "wof:placetype":"venue"
},
  "geometry": {"coordinates":[-93.288399,44.869091],"type":"Point"}
}