{
  "type": "Feature",
  "properties": {
    "addr:full":"1201 Haven Rd Little Falls MN 56345",
    "addr:housenumber":"1201",
    "addr:postcode":"56345",
    "addr:street":"Haven Rd",
    "iso:country":"US",
    "sg:address":"1201 Haven Rd",
    "sg:city":"Little Falls",
    "sg:classifiers":[
        {
            "category":"Travel",
            "subcategory":"Hotels & Motels",
            "type":"Entertainment"
        }
    ],
    "sg:phone":"+1 320 632 5488",
    "sg:postcode":"56345",
    "sg:province":"MN",
    "wof:name":"Clifwood Motel",
    "wof:placetype":"venue"
},
  "geometry": {"coordinates":[-94.35128899999999,45.990427],"type":"Point"}
}