{
  "type": "Feature",
  "properties": {
    "iso:country":"US",
    "sg:address":"5100 Thimsen Ave Ste 228",
    "sg:city":"Minnetonka",
    "sg:classifiers":[
        {
            "category":"Communications",
            "type":"Services"
        }
    ],
    "sg:phone":"+1 952 767 6700",
    "sg:postcode":"55345",
    "sg:province":"MN",
    "sg:tags":[
        "web",
        "design"
    ],
    "sg:website":"www.frontierwebdev.com",
    "wof:name":"Frontier Web Development",
    "wof:placetype":"venue"
},
  "geometry": {"coordinates":[-93.505308,44.912711],"type":"Point"}
}