{
  "type": "Feature",
  "properties": {
    "addr:full":"1516 18th St S Moorhead MN 56560",
    "addr:housenumber":"1516",
    "addr:postcode":"56560",
    "addr:street":"18Th St S",
    "iso:country":"US",
    "sg:address":"1516 18th St S",
    "sg:city":"Moorhead",
    "sg:classifiers":[
        {
            "category":"Building & Trades",
            "subcategory":"Construction",
            "type":"Services"
        }
    ],
    "sg:phone":"+1 218 789 7608",
    "sg:postcode":"56560",
    "sg:province":"MN",
    "sg:tags":[
        "concrete",
        "contractor"
    ],
    "wof:name":"Custom Concrete of Fargo Inc",
    "wof:placetype":"venue"
},
  "geometry": {"coordinates":[-96.751609,46.859565],"type":"Point"}
}