{
  "type": "Feature",
  "properties": {
    "addr:full":"540 Emerson St N Cambridge MN 55008",
    "addr:housenumber":"540",
    "addr:postcode":"55008",
    "addr:street":"Emerson St N",
    "iso:country":"US",
    "sg:address":"540 Emerson St N",
    "sg:city":"Cambridge",
    "sg:classifiers":[
        {
            "category":"Communications",
            "subcategory":"Radio Station",
            "type":"Services"
        }
    ],
    "sg:phone":"+1 763 689 1055",
    "sg:postcode":"55008",
    "sg:province":"MN",
    "sg:tags":[
        "company",
        "broadcasting"
    ],
    "wof:name":"WGVXYZ",
    "wof:placetype":"venue"
},
  "geometry": {"coordinates":[-93.216149,45.579329],"type":"Point"}
}