{
  "type": "Feature",
  "properties": {
    "iso:country":"US",
    "sg:address":"1110 S Minnesota Ave",
    "sg:city":"Oronoco",
    "sg:classifiers":[
        {
            "category":"Shopping",
            "subcategory":"Used Merchandise",
            "type":"Retail Goods"
        }
    ],
    "sg:phone":"+1 507 367 2600",
    "sg:postcode":"55960",
    "sg:province":"MN",
    "sg:tags":[
        "antique"
    ],
    "wof:name":"Moms Antique Mall",
    "wof:placetype":"venue"
},
  "geometry": {"coordinates":[-92.538422,44.151569],"type":"Point"}
}