{
  "type": "Feature",
  "properties": {
    "addr:full":"550 Abbey Way Saint Paul MN 55120",
    "addr:housenumber":"550",
    "addr:postcode":"55120",
    "addr:street":"Abbey Way",
    "iso:country":"US",
    "sg:address":"550 Abbey Way",
    "sg:city":"Saint Paul",
    "sg:classifiers":[
        {
            "category":"Building & Trades",
            "subcategory":"Construction",
            "type":"Services"
        }
    ],
    "sg:phone":"+1 651 405 8346",
    "sg:postcode":"55120",
    "sg:province":"MN",
    "sg:tags":[
        "contractor"
    ],
    "wof:name":"550 Design LLC",
    "wof:placetype":"venue"
},
  "geometry": {"coordinates":[-93.10781799999999,44.864358],"type":"Point"}
}