{
  "type": "Feature",
  "properties": {
    "iso:country":"US",
    "sg:address":"24923 Co Hwy 37",
    "sg:city":"Detroit Lakes",
    "sg:classifiers":[
        {
            "category":"Building & Trades",
            "subcategory":"Construction",
            "type":"Services"
        }
    ],
    "sg:phone":"+1 218 847 8848",
    "sg:postcode":"56501",
    "sg:province":"MN",
    "sg:tags":[
        "floor",
        "laying",
        "contractor"
    ],
    "wof:name":"K S Enterprises Inc",
    "wof:placetype":"venue"
},
  "geometry": {"coordinates":[-95.493854,46.933254],"type":"Point"}
}