{
  "type": "Feature",
  "properties": {
    "iso:country":"US",
    "sg:address":"1940 Greeley St S",
    "sg:city":"Stillwater",
    "sg:classifiers":[
        {
            "category":"Professional",
            "subcategory":"Accounting & Tax Preparation",
            "type":"Services"
        }
    ],
    "sg:phone":"+1 651 439 0955",
    "sg:postcode":"55082",
    "sg:province":"MN",
    "wof:name":"Dennis J Hoskin LTD",
    "wof:placetype":"venue"
},
  "geometry": {"coordinates":[-92.821051,45.038085],"type":"Point"}
}