{
  "type": "Feature",
  "properties": {
    "iso:country":"US",
    "sg:address":"7832 NE River Rd",
    "sg:city":"Rice",
    "sg:classifiers":[
        {
            "category":"Building & Trades",
            "subcategory":"Construction",
            "type":"Services"
        }
    ],
    "sg:phone":"+1 320 251 2411",
    "sg:postcode":"56367",
    "sg:province":"MN",
    "sg:tags":[
        "coping",
        "plastering",
        "tiling",
        "pool",
        "swimming"
    ],
    "wof:name":"Prig's Pool Svc",
    "wof:placetype":"venue"
},
  "geometry": {"coordinates":[-94.195369,45.683553],"type":"Point"}
}