{
  "type": "Feature",
  "properties": {
    "iso:country":"US",
    "sg:address":"620 Main St W",
    "sg:city":"Detroit Lakes",
    "sg:classifiers":[
        {
            "category":"Professional",
            "subcategory":"Detective & Security Services",
            "type":"Services"
        }
    ],
    "sg:phone":"+1 218 847 9244",
    "sg:postcode":"56501",
    "sg:province":"MN",
    "sg:tags":[
        "consulting",
        "management",
        "system"
    ],
    "wof:name":"Ace Security Inc",
    "wof:placetype":"venue"
},
  "geometry": {"coordinates":[-95.85367599999999,46.820591],"type":"Point"}
}