{
  "type": "Feature",
  "properties": {
    "addr:full":"1500 Bracketts Point Rd Wayzata MN 55391",
    "addr:housenumber":"1500",
    "addr:postcode":"55391",
    "addr:street":"Bracketts Point Rd",
    "iso:country":"US",
    "sg:address":"1500 Bracketts Point Rd",
    "sg:city":"Wayzata",
    "sg:classifiers":[
        {
            "category":"Professional",
            "subcategory":"Business Services",
            "type":"Services"
        }
    ],
    "sg:phone":"+1 952 249 5289",
    "sg:postcode":"55391",
    "sg:province":"MN",
    "wof:name":"Build Partners LLC",
    "wof:placetype":"venue"
},
  "geometry": {"coordinates":[-93.560678,44.956498],"type":"Point"}
}