{
  "type": "Feature",
  "properties": {
    "iso:country":"US",
    "sg:address":"301 Lexington Ave N",
    "sg:city":"New Prague",
    "sg:classifiers":[
        {
            "category":"Farming",
            "subcategory":"Dairy Farm",
            "type":"Manufacturing & Wholesale Goods"
        }
    ],
    "sg:phone":"+1 952 758 3406",
    "sg:postcode":"56071",
    "sg:province":"MN",
    "wof:name":"Mark Wolf",
    "wof:placetype":"venue"
},
  "geometry": {"coordinates":[-93.56699999999999,44.547022],"type":"Point"}
}