{
  "type": "Feature",
  "properties": {
    "addr:full":"1045 Southdale Ctr Minneapolis MN 55435",
    "addr:housenumber":"1045",
    "addr:postcode":"55435",
    "addr:street":"Southdale Ctr",
    "iso:country":"US",
    "sg:address":"1045 Southdale Ctr",
    "sg:city":"Minneapolis",
    "sg:classifiers":[
        {
            "category":"Shopping",
            "subcategory":"Clothing, Apparel, & Fashions",
            "type":"Retail Goods"
        }
    ],
    "sg:phone":"+1 952 285 1800",
    "sg:postcode":"55435",
    "sg:province":"MN",
    "sg:tags":[
        "accessory",
        "handbag",
        "apparel",
        "women's",
        "sportswear"
    ],
    "sg:website":"http://www.talbots.com",
    "wof:name":"Talbots",
    "wof:placetype":"venue"
},
  "geometry": {"coordinates":[-93.328468,44.8804],"type":"Point"}
}