{
  "type": "Feature",
  "properties": {
    "iso:country":"US",
    "sg:address":"306 3rd St NW",
    "sg:city":"St Michael",
    "sg:classifiers":[
        {
            "category":"Freight",
            "type":"Transportation"
        }
    ],
    "sg:phone":"+1 763 497 9003",
    "sg:postcode":"55376",
    "sg:province":"MN",
    "sg:tags":[
        "operator",
        "delivery",
        "local",
        "trucking"
    ],
    "wof:name":"Fastrack Couriers Inc",
    "wof:placetype":"venue"
},
  "geometry": {"coordinates":[-93.66978,45.213384],"type":"Point"}
}