{
  "type": "Feature",
  "properties": {
    "addr:full":"4997 Maki Rd Brookston MN 55711",
    "addr:housenumber":"4997",
    "addr:postcode":"55711",
    "addr:street":"Maki Rd",
    "iso:country":"US",
    "sg:address":"4997 Maki Rd",
    "sg:city":"Brookston",
    "sg:classifiers":[
        {
            "category":"Building & Trades",
            "subcategory":"Construction",
            "type":"Services"
        }
    ],
    "sg:phone":"+1 218 878 1299",
    "sg:postcode":"55711",
    "sg:province":"MN",
    "sg:tags":[
        "contractor"
    ],
    "wof:name":"Ekman Roofing",
    "wof:placetype":"venue"
},
  "geometry": {"coordinates":[-92.722478,46.876186],"type":"Point"}
}