{
  "type": "Feature",
  "properties": {
    "addr:full":"2212 Jefferson St Duluth MN 55812",
    "addr:housenumber":"2212",
    "addr:postcode":"55812",
    "addr:street":"Jefferson St",
    "iso:country":"US",
    "sg:address":"2212 Jefferson St",
    "sg:city":"Duluth",
    "sg:classifiers":[
        {
            "category":"Retail",
            "subcategory":"Car Wash",
            "type":"Services"
        }
    ],
    "sg:phone":"+1 218 723 8830",
    "sg:postcode":"55812",
    "sg:province":"MN",
    "sg:tags":[
        "carwash"
    ],
    "wof:name":"Lspt LLC",
    "wof:placetype":"venue"
},
  "geometry": {"coordinates":[-92.067087,46.806791],"type":"Point"}
}