{
  "type": "Feature",
  "properties": {
    "addr:full":"9300 Co Rd 15 Maple Plain MN 55359",
    "addr:housenumber":"9300;15",
    "addr:postcode":"55359",
    "addr:street":"Co Rd;Plain",
    "iso:country":"US",
    "sg:address":"9300 Co Rd 15",
    "sg:city":"Maple Plain",
    "sg:classifiers":[
        {
            "category":"Professional",
            "type":"Services"
        }
    ],
    "sg:phone":"+1 763 434 9634",
    "sg:postcode":"55359",
    "sg:province":"MN",
    "sg:tags":[
        "water",
        "analysis"
    ],
    "wof:name":"J T Testing Svc",
    "wof:placetype":"venue"
},
  "geometry": {"coordinates":[-93.759165,44.949076],"type":"Point"}
}