{
  "type": "Feature",
  "properties": {
    "iso:country":"US",
    "sg:address":"7705 Bush Lake Rd",
    "sg:city":"Minneapolis",
    "sg:classifiers":[
        {
            "category":"Building & Trades",
            "subcategory":"Construction",
            "type":"Services"
        }
    ],
    "sg:phone":"+1 952 941 8533",
    "sg:postcode":"55439",
    "sg:province":"MN",
    "sg:tags":[
        "floor",
        "laying",
        "contractor"
    ],
    "wof:name":"Cracked Tile",
    "wof:placetype":"venue"
},
  "geometry": {"coordinates":[-93.361237,44.862038],"type":"Point"}
}