{
  "type": "Feature",
  "properties": {
    "iso:country":"US",
    "sg:address":"555 Stoltzman Rd",
    "sg:city":"Mankato",
    "sg:classifiers":[
        {
            "category":"Government",
            "subcategory":"Office",
            "type":"Public Place"
        }
    ],
    "sg:phone":"+1 507 387 8585",
    "sg:postcode":"56001",
    "sg:province":"MN",
    "sg:tags":[
        "village"
    ],
    "wof:name":"Mankato Elks Nature Ctr",
    "wof:placetype":"venue"
},
  "geometry": {"coordinates":[-94.008824,44.150106],"type":"Point"}
}