{
  "type": "Feature",
  "properties": {
    "iso:country":"US",
    "sg:address":"129 Grand Ave NE",
    "sg:city":"Princeton",
    "sg:classifiers":[
        {
            "category":"Professional",
            "subcategory":"Art Services",
            "type":"Services"
        }
    ],
    "sg:phone":"+1 763 389 4901",
    "sg:postcode":"55376",
    "sg:province":"MN",
    "sg:tags":[
        "commercial",
        "design"
    ],
    "wof:name":"Mystic Air",
    "wof:placetype":"venue"
},
  "geometry": {"coordinates":[-93.66301,45.217782],"type":"Point"}
}