{
  "type": "Feature",
  "properties": {
    "iso:country":"US",
    "sg:address":"12489 Co Rd 16",
    "sg:city":"Crosslake",
    "sg:classifiers":[
        {
            "category":"Building & Trades",
            "subcategory":"Construction",
            "type":"Services"
        }
    ],
    "sg:phone":"+1 218 543 4745",
    "sg:postcode":"56442",
    "sg:province":"MN",
    "sg:tags":[
        "contractor"
    ],
    "wof:name":"Reliable Insulation",
    "wof:placetype":"venue"
},
  "geometry": {"coordinates":[-94.141223,46.679199],"type":"Point"}
}