{
  "type": "Feature",
  "properties": {
    "addr:full":"610 Front St Brainerd MN 56401",
    "addr:housenumber":"610",
    "addr:postcode":"56401",
    "addr:street":"Front St",
    "iso:country":"US",
    "sg:address":"610 Front St",
    "sg:city":"Brainerd",
    "sg:classifiers":[
        {
            "category":"Retail",
            "subcategory":"Portrait Studio",
            "type":"Services"
        }
    ],
    "sg:phone":"+1 218 828 7731",
    "sg:postcode":"56401",
    "sg:province":"MN",
    "sg:tags":[
        "photographer"
    ],
    "wof:name":"Images By Angel",
    "wof:placetype":"venue"
},
  "geometry": {"coordinates":[-94.200553,46.356743],"type":"Point"}
}