{
  "type": "Feature",
  "properties": {
    "addr:full":"2378 Hwy 332 Internatl Falls MN 56649",
    "addr:housenumber":"2378",
    "addr:postcode":"56649",
    "addr:street":"Hwy 332 Internatl",
    "iso:country":"US",
    "sg:address":"2378 Hwy 332",
    "sg:city":"Internatl Falls",
    "sg:classifiers":[
        {
            "category":"Wholesale",
            "subcategory":"Scrap",
            "type":"Manufacturing & Wholesale Goods"
        }
    ],
    "sg:phone":"+1 218 283 3292",
    "sg:postcode":"56649",
    "sg:province":"MN",
    "sg:tags":[
        "recycling",
        "center"
    ],
    "wof:name":"J S & K Recycling",
    "wof:placetype":"venue"
},
  "geometry": {"coordinates":[-93.374915,48.581198],"type":"Point"}
}