{
  "type": "Feature",
  "properties": {
    "addr:full":"4030 Revere Ln N Minneapolis MN 55441",
    "addr:housenumber":"4030",
    "addr:postcode":"55441",
    "addr:street":"Revere Ln N",
    "iso:country":"US",
    "sg:address":"4030 Revere Ln N",
    "sg:city":"Minneapolis",
    "sg:classifiers":[
        {
            "category":"Manufacturing",
            "subcategory":"Signs",
            "type":"Manufacturing & Wholesale Goods"
        }
    ],
    "sg:phone":"+1 763 550 0441",
    "sg:postcode":"55441",
    "sg:province":"MN",
    "sg:tags":[
        "specialty",
        "mfg"
    ],
    "wof:name":"Quick Sign",
    "wof:placetype":"venue"
},
  "geometry": {"coordinates":[-93.41060899999999,45.030181],"type":"Point"}
}