{
  "type": "Feature",
  "properties": {
    "addr:full":"950 14th St Granite Falls MN 56241",
    "addr:housenumber":"950",
    "addr:postcode":"56241",
    "addr:street":"14Th St",
    "iso:country":"US",
    "sg:address":"950 14th St",
    "sg:city":"Granite Falls",
    "sg:classifiers":[
        {
            "category":"Wholesale",
            "subcategory":"Machinery & Supplies",
            "type":"Manufacturing & Wholesale Goods"
        }
    ],
    "sg:phone":"+1 320 564 9009",
    "sg:postcode":"56241",
    "sg:province":"MN",
    "sg:tags":[
        "equipment",
        "hydraulic"
    ],
    "sg:website":"www.gfpmf.com",
    "wof:name":"Granite Fluid Power Machining",
    "wof:placetype":"venue"
},
  "geometry": {"coordinates":[-95.558345,44.809478],"type":"Point"}
}