{
  "type": "Feature",
  "properties": {
    "iso:country":"US",
    "sg:address":"575 170th Ave NE",
    "sg:city":"Sunburg",
    "sg:phone":"+1 320 366 3495",
    "sg:postcode":"56289",
    "sg:province":"MN",
    "sg:tags":[
        "farm",
        "corn"
    ],
    "wof:name":"Hollen Morine",
    "wof:placetype":"venue"
},
  "geometry": {"coordinates":[-95.275886,45.383692],"type":"Point"}
}