{
  "type": "Feature",
  "properties": {
    "iso:country":"US",
    "sg:address":"616 Ruth St N",
    "sg:city":"St Paul",
    "sg:classifiers":[
        {
            "category":"Organizations",
            "subcategory":"Religious Organization",
            "type":"Services"
        },
        {
            "category":"Education",
            "subcategory":"School",
            "type":"Public Place"
        }
    ],
    "sg:phone":"+1 651 735 4179",
    "sg:postcode":"55119",
    "sg:province":"MN",
    "sg:tags":[
        "church"
    ],
    "wof:name":"Eastern Heights Lutheran Schl",
    "wof:placetype":"venue"
},
  "geometry": {"coordinates":[-93.015103,44.960837],"type":"Point"}
}