{
  "type": "Feature",
  "properties": {
    "addr:full":"1055 Hwy 110 Inver Grove Hts MN 55077",
    "addr:housenumber":"1055",
    "addr:postcode":"55077",
    "addr:street":"Hwy 110",
    "iso:country":"US",
    "sg:address":"1055 Hwy 110",
    "sg:city":"Inver Grove Hts",
    "sg:classifiers":[
        {
            "category":"Autos & Motor Vehicles",
            "subcategory":"Automobile Sales",
            "type":"Retail Goods"
        }
    ],
    "sg:phone":"+1 651 451 2211",
    "sg:postcode":"55077",
    "sg:province":"MN",
    "sg:tags":[
        "passenger",
        "general",
        "dealer",
        "car",
        "repair"
    ],
    "sg:website":"www.dennyhecker.com",
    "wof:name":"Southview Chevrolet Jeep",
    "wof:placetype":"venue"
},
  "geometry": {"coordinates":[-93.0766,44.876225],"type":"Point"}
}