{
  "type": "Feature",
  "properties": {
    "iso:country":"US",
    "sg:address":"21801 Meadow Wood Ct",
    "sg:city":"Jordan",
    "sg:classifiers":[
        {
            "category":"Farming",
            "subcategory":"Livestock Farm",
            "type":"Manufacturing & Wholesale Goods"
        }
    ],
    "sg:phone":"+1 952 492 6095",
    "sg:postcode":"55352",
    "sg:province":"MN",
    "sg:tags":[
        "beef",
        "feedlot",
        "cattle"
    ],
    "wof:name":"Jerry Edelman",
    "wof:placetype":"venue"
},
  "geometry": {"coordinates":[-93.49315,44.634628],"type":"Point"}
}