{
  "type": "Feature",
  "properties": {
    "addr:full":"1717 Woodland Ave Mankato MN 56001",
    "addr:housenumber":"1717",
    "addr:postcode":"56001",
    "addr:street":"Woodland Ave",
    "iso:country":"US",
    "sg:address":"1717 Woodland Ave",
    "sg:city":"Mankato",
    "sg:classifiers":[
        {
            "category":"Farming",
            "subcategory":"Farm",
            "type":"Manufacturing & Wholesale Goods"
        }
    ],
    "sg:phone":"+1 507 388 5132",
    "sg:postcode":"56001",
    "sg:province":"MN",
    "sg:tags":[
        "crop",
        "general"
    ],
    "wof:name":"Christopher Krohn Farm",
    "wof:placetype":"venue"
},
  "geometry": {"coordinates":[-94.029262,44.146008],"type":"Point"}
}