{
  "type": "Feature",
  "properties": {
    "addr:full":"2012 26th Ave NW Rochester MN 55901",
    "addr:housenumber":"2012",
    "addr:postcode":"55901",
    "addr:street":"26Th Ave Nw",
    "iso:country":"US",
    "sg:address":"2012 26th Ave NW",
    "sg:city":"Rochester",
    "sg:classifiers":[
        {
            "category":"Professional",
            "subcategory":"Management & Consulting",
            "type":"Services"
        }
    ],
    "sg:phone":"+1 507 280 7917",
    "sg:postcode":"55901",
    "sg:province":"MN",
    "wof:name":"Rochester Consulting Group",
    "wof:placetype":"venue"
},
  "geometry": {"coordinates":[-92.500252,44.045491],"type":"Point"}
}