{
  "type": "Feature",
  "properties": {
    "addr:full":"101 E Center Ave Mcgregor MN 55760",
    "addr:housenumber":"101",
    "addr:postcode":"55760",
    "addr:street":"E Center Ave",
    "iso:country":"US",
    "sg:address":"101 E Center Ave",
    "sg:city":"Mcgregor",
    "sg:classifiers":[
        {
            "category":"Government",
            "subcategory":"Office",
            "type":"Public Place"
        }
    ],
    "sg:phone":"+1 218 768 2717",
    "sg:postcode":"55760",
    "sg:province":"MN",
    "sg:tags":[
        "city"
    ],
    "wof:name":"Mc Gregor City Clerk",
    "wof:placetype":"venue"
},
  "geometry": {"coordinates":[-93.30762900000001,46.606811],"type":"Point"}
}