{
  "type": "Feature",
  "properties": {
    "addr:full":"25 12th Ave SW Pelican Rapids MN 56572",
    "addr:housenumber":"25",
    "addr:postcode":"56572",
    "addr:street":"12Th Ave Sw",
    "iso:country":"US",
    "sg:address":"25 12th Ave SW",
    "sg:city":"Pelican Rapids",
    "sg:classifiers":[
        {
            "category":"Local Transit",
            "type":"Transportation"
        }
    ],
    "sg:phone":"+1 218 863 7000",
    "sg:postcode":"56572",
    "sg:province":"MN",
    "sg:tags":[
        "bus",
        "line"
    ],
    "wof:name":"Christianson Bus Svc",
    "wof:placetype":"venue"
},
  "geometry": {"coordinates":[-96.08621100000001,46.557366],"type":"Point"}
}