{
  "type": "Feature",
  "properties": {
    "iso:country":"US",
    "sg:address":"17548 Freeport Way",
    "sg:city":"Farmington",
    "sg:classifiers":[
        {
            "category":"Building & Trades",
            "subcategory":"Plumbing",
            "type":"Services"
        }
    ],
    "sg:phone":"+1 952 297 2125",
    "sg:postcode":"55024",
    "sg:province":"MN",
    "sg:tags":[
        "plumber",
        "industrial",
        "contractors-commercial"
    ],
    "sg:website":"http://www.jameswalkerplumbing.com",
    "wof:name":"James Walker Plumbing",
    "wof:placetype":"venue"
},
  "geometry": {"coordinates":[-93.202798,44.696178],"type":"Point"}
}