{
  "type": "Feature",
  "properties": {
    "iso:country":"US",
    "sg:address":"2055 12th St SE",
    "sg:city":"St Cloud",
    "sg:classifiers":[
        {
            "category":"Shopping",
            "subcategory":"Department Store",
            "type":"Retail Goods"
        }
    ],
    "sg:phone":"+1 320 251 7200",
    "sg:postcode":"56304",
    "sg:province":"MN",
    "sg:tags":[
        "shop"
    ],
    "wof:name":"Denny Hecker's Bargain Lot",
    "wof:placetype":"venue"
},
  "geometry": {"coordinates":[-94.121285,45.551875],"type":"Point"}
}