{
  "type": "Feature",
  "properties": {
    "addr:full":"2088 Marschall Rd Shakopee MN 55379",
    "addr:housenumber":"2088",
    "addr:postcode":"55379",
    "addr:street":"Marschall Rd",
    "iso:country":"US",
    "sg:address":"2088 Marschall Rd",
    "sg:city":"Shakopee",
    "sg:phone":"+1 952 445 5383",
    "sg:postcode":"55379",
    "sg:province":"MN",
    "sg:tags":[
        "farm",
        "corn",
        "wheat"
    ],
    "wof:name":"Marcshall Farms",
    "wof:placetype":"venue"
},
  "geometry": {"coordinates":[-93.50537,44.766434],"type":"Point"}
}