{
  "type": "Feature",
  "properties": {
    "addr:full":"2711 Commerce Dr NW Rochester MN 55901",
    "addr:housenumber":"2711",
    "addr:postcode":"55901",
    "addr:street":"Commerce Dr Nw",
    "iso:country":"US",
    "sg:address":"2711 Commerce Dr NW",
    "sg:city":"Rochester",
    "sg:classifiers":[
        {
            "category":"Restaurant",
            "type":"Food & Drink"
        }
    ],
    "sg:menulink":"http://www.allmenus.com/mn/rochester/151270-subway/menu/",
    "sg:phone":"+1 507 281 0520",
    "sg:postcode":"55901",
    "sg:province":"MN",
    "sg:tags":[
        "american",
        "sandwich"
    ],
    "wof:name":"Subway",
    "wof:placetype":"venue"
},
  "geometry": {"coordinates":[-92.520968,44.052423],"type":"Point"}
}