{
  "type": "Feature",
  "properties": {
    "addr:full":"13570 Grove Dr Osseo MN 55311",
    "addr:housenumber":"13570",
    "addr:postcode":"55311",
    "addr:street":"Grove Dr",
    "iso:country":"US",
    "sg:address":"13570 Grove Dr",
    "sg:city":"Osseo",
    "sg:classifiers":[
        {
            "category":"Professional",
            "subcategory":"Business Services",
            "type":"Services"
        }
    ],
    "sg:phone":"+1 763 416 4720",
    "sg:postcode":"55311",
    "sg:province":"MN",
    "sg:tags":[
        "credit",
        "card"
    ],
    "wof:name":"First Financial USA",
    "wof:placetype":"venue"
},
  "geometry": {"coordinates":[-93.45235700000001,45.103008],"type":"Point"}
}