{
  "type": "Feature",
  "properties": {
    "addr:full":"3393 Northdale Blvd NW Minneapolis MN 55448",
    "addr:housenumber":"3393",
    "addr:postcode":"55448",
    "addr:street":"Northdale Blvd Nw",
    "iso:country":"US",
    "sg:address":"3393 Northdale Blvd NW",
    "sg:city":"Minneapolis",
    "sg:classifiers":[
        {
            "category":"Building & Trades",
            "subcategory":"Construction",
            "type":"Services"
        }
    ],
    "sg:phone":"+1 612 371 0270",
    "sg:postcode":"55448",
    "sg:province":"MN",
    "sg:tags":[
        "house"
    ],
    "wof:name":"Gwh Construction LLC",
    "wof:placetype":"venue"
},
  "geometry": {"coordinates":[-93.348949,45.193318],"type":"Point"}
}