{
  "type": "Feature",
  "properties": {
    "iso:country":"US",
    "sg:address":"932 Naylor Dr SE",
    "sg:city":"Bemidji",
    "sg:classifiers":[
        {
            "category":"Building & Trades",
            "subcategory":"Construction",
            "type":"Services"
        }
    ],
    "sg:phone":"+1 218 751 2707",
    "sg:postcode":"56601",
    "sg:province":"MN",
    "sg:tags":[
        "pipeline",
        "oil",
        "gas"
    ],
    "wof:name":"SEI",
    "wof:placetype":"venue"
},
  "geometry": {"coordinates":[-94.857544,47.446606],"type":"Point"}
}