{
  "type": "Feature",
  "properties": {
    "addr:full":"9165 Shoestring Loop NW Rice MN 56367",
    "addr:housenumber":"9165",
    "addr:postcode":"56367",
    "addr:street":"Shoestring Loop Nw",
    "iso:country":"US",
    "sg:address":"9165 Shoestring Loop NW",
    "sg:city":"Rice",
    "sg:classifiers":[
        {
            "category":"Professional",
            "type":"Services"
        }
    ],
    "sg:phone":"+1 320 393 2080",
    "sg:postcode":"56367",
    "sg:province":"MN",
    "wof:name":"Lakeshore Dock Service Inc",
    "wof:placetype":"venue"
},
  "geometry": {"coordinates":[-94.20446699999999,45.698361],"type":"Point"}
}