{
  "type": "Feature",
  "properties": {
    "iso:country":"US",
    "sg:address":"1141 University Ave W",
    "sg:city":"St Paul",
    "sg:classifiers":[
        {
            "category":"Health Services",
            "subcategory":"Chiropractor",
            "type":"Services"
        }
    ],
    "sg:phone":"+1 651 645 6711",
    "sg:postcode":"55104",
    "sg:province":"MN",
    "wof:name":"Kimble Chiropractic",
    "wof:placetype":"venue"
},
  "geometry": {"coordinates":[-93.147946,44.955799],"type":"Point"}
}