{
  "type": "Feature",
  "properties": {
    "addr:full":"116 Main St S Stillwater MN 55082",
    "addr:housenumber":"116",
    "addr:postcode":"55082",
    "addr:street":"Main St S",
    "iso:country":"US",
    "sg:address":"116 Main St S",
    "sg:city":"Stillwater",
    "sg:classifiers":[
        {
            "category":"Shopping",
            "subcategory":"Gifts & Souvenirs",
            "type":"Retail Goods"
        }
    ],
    "sg:phone":"+1 651 430 3898",
    "sg:postcode":"55082",
    "sg:province":"MN",
    "sg:tags":[
        "shop"
    ],
    "wof:name":"Noahs Ark",
    "wof:placetype":"venue"
},
  "geometry": {"coordinates":[-92.805932,45.055918],"type":"Point"}
}