{
  "type": "Feature",
  "properties": {
    "iso:country":"US",
    "sg:address":"901 Vineland Ct",
    "sg:city":"Chanhassen",
    "sg:classifiers":[
        {
            "category":"Professional",
            "subcategory":"Management & Consulting",
            "type":"Services"
        }
    ],
    "sg:phone":"+1 952 474 2435",
    "sg:postcode":"55317",
    "sg:province":"MN",
    "sg:tags":[
        "business"
    ],
    "wof:name":"Douglas Olsen",
    "wof:placetype":"venue"
},
  "geometry": {"coordinates":[-93.543475,44.885033],"type":"Point"}
}