{
  "type": "Feature",
  "properties": {
    "iso:country":"US",
    "sg:address":"9050 Golden Valley Rd",
    "sg:city":"Minneapolis",
    "sg:classifiers":[
        {
            "category":"Restaurant",
            "type":"Food & Drink"
        }
    ],
    "sg:menulink":"http://www.allmenus.com/mn/golden-valley/176576-kfc---kentucky-fried-chicken/menu/",
    "sg:phone":"+1 763 595 8208",
    "sg:postcode":"55427",
    "sg:province":"MN",
    "sg:tags":[
        "american",
        "chicken"
    ],
    "wof:name":"KFC - Kentucky Fried Chicken",
    "wof:placetype":"venue"
},
  "geometry": {"coordinates":[-93.395038,44.985253],"type":"Point"}
}