{
  "type": "Feature",
  "properties": {
    "addr:full":"3540 38th Ave S Minneapolis MN 55406",
    "addr:housenumber":"3540",
    "addr:postcode":"55406",
    "addr:street":"38Th Ave S",
    "iso:country":"US",
    "sg:address":"3540 38th Ave S",
    "sg:city":"Minneapolis",
    "sg:classifiers":[
        {
            "category":"Home & Garden",
            "subcategory":"Furniture",
            "type":"Retail Goods"
        }
    ],
    "sg:phone":"+1 612 721 2396",
    "sg:postcode":"55406",
    "sg:province":"MN",
    "wof:name":"Luther Enterprize",
    "wof:placetype":"venue"
},
  "geometry": {"coordinates":[-93.21793700000001,44.938561],"type":"Point"}
}