{
  "type": "Feature",
  "properties": {
    "addr:full":"6690 Sturgeon Lake Rd Welch MN 55089",
    "addr:housenumber":"6690",
    "addr:postcode":"55089",
    "addr:street":"Sturgeon Lake Rd",
    "iso:country":"US",
    "sg:address":"6690 Sturgeon Lake Rd",
    "sg:city":"Welch",
    "sg:classifiers":[
        {
            "category":"Food & Beverages",
            "subcategory":"Groceries & Convenience Stores",
            "type":"Retail Goods"
        }
    ],
    "sg:phone":"+1 651 388 1563",
    "sg:postcode":"55089",
    "sg:province":"MN",
    "wof:name":"A C Express",
    "wof:placetype":"venue"
},
  "geometry": {"coordinates":[-92.66477500000001,44.629741],"type":"Point"}
}