{
  "type": "Feature",
  "properties": {
    "addr:full":"1362 W Arrowhead Rd Duluth MN 55811",
    "addr:housenumber":"1362",
    "addr:postcode":"55811",
    "addr:street":"W Arrowhead Rd",
    "iso:country":"US",
    "sg:address":"1362 W Arrowhead Rd",
    "sg:city":"Duluth",
    "sg:classifiers":[
        {
            "category":"Restaurant",
            "type":"Food & Drink"
        }
    ],
    "sg:phone":"+1 218 724 2442",
    "sg:postcode":"55811",
    "sg:province":"MN",
    "wof:name":"Hardee's",
    "wof:placetype":"venue"
},
  "geometry": {"coordinates":[-92.099677,46.822055],"type":"Point"}
}