{
  "type": "Feature",
  "properties": {
    "addr:full":"23407 Great Pine Trl Nevis MN 56467",
    "addr:housenumber":"23407",
    "addr:postcode":"56467",
    "addr:street":"Great Pine Trl",
    "iso:country":"US",
    "sg:address":"23407 Great Pine Trl",
    "sg:city":"Nevis",
    "sg:classifiers":[
        {
            "category":"Professional",
            "type":"Services"
        }
    ],
    "sg:phone":"+1 218 652 2389",
    "sg:postcode":"56467",
    "sg:province":"MN",
    "sg:tags":[
        "establishment"
    ],
    "wof:name":"Sheridan & Sheridan",
    "wof:placetype":"venue"
},
  "geometry": {"coordinates":[-94.839457,46.998216],"type":"Point"}
}