{
  "type": "Feature",
  "properties": {
    "addr:full":"21944 Deep Lake Rd Richmond MN 56368",
    "addr:housenumber":"21944",
    "addr:postcode":"56368",
    "addr:street":"Deep Lake Rd",
    "iso:country":"US",
    "sg:address":"21944 Deep Lake Rd",
    "sg:city":"Richmond",
    "sg:classifiers":[
        {
            "category":"Building & Trades",
            "subcategory":"Construction",
            "type":"Services"
        }
    ],
    "sg:phone":"+1 320 597 2438",
    "sg:postcode":"56368",
    "sg:province":"MN",
    "sg:tags":[
        "carpentry",
        "contractor"
    ],
    "wof:name":"Gerald P Sand",
    "wof:placetype":"venue"
},
  "geometry": {"coordinates":[-94.560338,45.400554],"type":"Point"}
}