{
  "type": "Feature",
  "properties": {
    "iso:country":"US",
    "sg:address":"922 6th Ave E",
    "sg:city":"Alexandria",
    "sg:classifiers":[
        {
            "category":"Freight",
            "type":"Transportation"
        }
    ],
    "sg:phone":"+1 320 763 5273",
    "sg:postcode":"56308",
    "sg:province":"MN",
    "sg:tags":[
        "operator",
        "trucking"
    ],
    "wof:name":"Midnight Blue",
    "wof:placetype":"venue"
},
  "geometry": {"coordinates":[-95.364931,45.885792],"type":"Point"}
}