{
  "type": "Feature",
  "properties": {
    "iso:country":"US",
    "sg:address":"9973 Valley View Rd",
    "sg:city":"Eden Prairie",
    "sg:classifiers":[
        {
            "category":"Real Estate",
            "subcategory":"Architect",
            "type":"Services"
        },
        {
            "category":"Building & Trades",
            "subcategory":"Construction",
            "type":"Services"
        }
    ],
    "sg:phone":"+1 952 903 9299",
    "sg:postcode":"55344",
    "sg:province":"MN",
    "sg:tags":[
        "a",
        "industrial",
        "commercial",
        "contractor"
    ],
    "sg:website":"www.rjddesign1.com",
    "wof:name":"Design 1",
    "wof:placetype":"venue"
},
  "geometry": {"coordinates":[-93.40406,44.871229],"type":"Point"}
}