{
  "type": "Feature",
  "properties": {
    "iso:country":"US",
    "sg:address":"212 N 2nd St",
    "sg:city":"Minneapolis",
    "sg:classifiers":[
        {
            "category":"Manufacturing",
            "subcategory":"Paper Products",
            "type":"Manufacturing & Wholesale Goods"
        }
    ],
    "sg:phone":"+1 612 359 0645",
    "sg:postcode":"55401",
    "sg:province":"MN",
    "wof:name":"Cave Paper",
    "wof:placetype":"venue"
},
  "geometry": {"coordinates":[-93.271343,44.985354],"type":"Point"}
}