{
  "type": "Feature",
  "properties": {
    "addr:full":"2100 95th Ave NE Sauk Rapids MN 56379",
    "addr:housenumber":"2100",
    "addr:postcode":"56379",
    "addr:street":"95Th Ave Ne",
    "iso:country":"US",
    "sg:address":"2100 95th Ave NE",
    "sg:city":"Sauk Rapids",
    "sg:phone":"+1 320 968 7804",
    "sg:postcode":"56379",
    "sg:province":"MN",
    "sg:tags":[
        "farm"
    ],
    "wof:name":"Melvin Hauck",
    "wof:placetype":"venue"
},
  "geometry": {"coordinates":[-93.96538,45.597431],"type":"Point"}
}