{
  "type": "Feature",
  "properties": {
    "addr:full":"1990 Co Rd D E Saint Paul MN 55109",
    "addr:housenumber":"1990",
    "addr:postcode":"55109",
    "addr:street":"Co Rd D E",
    "iso:country":"US",
    "sg:address":"1990 Co Rd D E",
    "sg:city":"Saint Paul",
    "sg:classifiers":[
        {
            "category":"Retail",
            "subcategory":"Auto Repair",
            "type":"Services"
        }
    ],
    "sg:phone":"+1 651 779 8113",
    "sg:postcode":"55109",
    "sg:province":"MN",
    "sg:tags":[
        "automotive",
        "exhaust"
    ],
    "wof:name":"Meineke Discount Mufflers",
    "wof:placetype":"venue"
},
  "geometry": {"coordinates":[-93.018759,45.035709],"type":"Point"}
}