{
  "type": "Feature",
  "properties": {
    "addr:full":"631 N Division St Warren MN 56762",
    "addr:housenumber":"631",
    "addr:postcode":"56762",
    "addr:street":"N Division St",
    "iso:country":"US",
    "sg:address":"631 N Division St",
    "sg:city":"Warren",
    "sg:classifiers":[
        {
            "category":"Real Estate",
            "subcategory":"Real Estate Operator",
            "type":"Services"
        }
    ],
    "sg:phone":"+1 218 745 5428",
    "sg:postcode":"56762",
    "sg:province":"MN",
    "sg:tags":[
        "property",
        "lessor"
    ],
    "wof:name":"Frank Judovsky",
    "wof:placetype":"venue"
},
  "geometry": {"coordinates":[-96.77717800000001,48.19747],"type":"Point"}
}