{
  "type": "Feature",
  "properties": {
    "addr:full":"1116 Sandy Ln Monticello MN 55362",
    "addr:housenumber":"1116",
    "addr:postcode":"55362",
    "addr:street":"Sandy Ln",
    "iso:country":"US",
    "sg:address":"1116 Sandy Ln",
    "sg:city":"Monticello",
    "sg:classifiers":[
        {
            "category":"Bars & Pubs",
            "type":"Food & Drink"
        }
    ],
    "sg:phone":"+1 763 497 5251",
    "sg:postcode":"55362",
    "sg:province":"MN",
    "sg:tags":[
        "drinking"
    ],
    "wof:name":"Albertville Bar",
    "wof:placetype":"venue"
},
  "geometry": {"coordinates":[-93.811252,45.312661],"type":"Point"}
}