{
  "type": "Feature",
  "properties": {
    "addr:full":"7732 Shingle Creek Dr Minneapolis MN 55443",
    "addr:housenumber":"7732",
    "addr:postcode":"55443",
    "addr:street":"Shingle Creek Dr",
    "iso:country":"US",
    "sg:address":"7732 Shingle Creek Dr",
    "sg:city":"Minneapolis",
    "sg:classifiers":[
        {
            "category":"Manufacturing",
            "subcategory":"Tools & Machinery",
            "type":"Manufacturing & Wholesale Goods"
        }
    ],
    "sg:phone":"+1 763 560 3663",
    "sg:postcode":"55443",
    "sg:province":"MN",
    "sg:tags":[
        "forming",
        "metal"
    ],
    "wof:name":"D J Noonan Co Inc",
    "wof:placetype":"venue"
},
  "geometry": {"coordinates":[-93.361035,45.095385],"type":"Point"}
}