{
  "type": "Feature",
  "properties": {
    "addr:full":"1209 Mainstreet Hopkins MN 55343",
    "addr:housenumber":"1209",
    "addr:postcode":"55343",
    "addr:street":"Mainstreet",
    "iso:country":"US",
    "sg:address":"1209 Mainstreet",
    "sg:city":"Hopkins",
    "sg:classifiers":[
        {
            "category":"Building & Trades",
            "subcategory":"Cleaning & Sanitation",
            "type":"Services"
        }
    ],
    "sg:phone":"+1 952 938 4210",
    "sg:postcode":"55343",
    "sg:province":"MN",
    "sg:tags":[
        "maintenance"
    ],
    "wof:name":"Smid Building Maintenance",
    "wof:placetype":"venue"
},
  "geometry": {"coordinates":[-93.415841,44.924434],"type":"Point"}
}