{
  "type": "Feature",
  "properties": {
    "iso:country":"US",
    "sg:address":"15219 Feller St NE",
    "sg:city":"Forest Lake",
    "sg:classifiers":[
        {
            "category":"Autos & Motor Vehicles",
            "subcategory":"Boat Sales",
            "type":"Retail Goods"
        }
    ],
    "sg:phone":"+1 651 464 3135",
    "sg:postcode":"55025",
    "sg:province":"MN",
    "sg:tags":[
        "dealer",
        "marine",
        "sales",
        "motorcycle"
    ],
    "wof:name":"Forest Lake Motor Sports Inc",
    "wof:placetype":"venue"
},
  "geometry": {"coordinates":[-93.026475,45.244597],"type":"Point"}
}