{
  "type": "Feature",
  "properties": {
    "addr:full":"513 2nd St Jackson MN 56143",
    "addr:housenumber":"513",
    "addr:postcode":"56143",
    "addr:street":"2Nd St",
    "iso:country":"US",
    "sg:address":"513 2nd St",
    "sg:city":"Jackson",
    "sg:classifiers":[
        {
            "category":"Professional",
            "subcategory":"Lawyer & Legal Services",
            "type":"Services"
        }
    ],
    "sg:phone":"+1 507 847 2587",
    "sg:postcode":"56143",
    "sg:province":"MN",
    "sg:tags":[
        "attorney"
    ],
    "wof:name":"Talkington Fletcher Law Office",
    "wof:placetype":"venue"
},
  "geometry": {"coordinates":[-94.987762,43.622228],"type":"Point"}
}