{
  "type": "Feature",
  "properties": {
    "addr:full":"1009 Humboldt Ave West St Paul MN 55118",
    "addr:housenumber":"1009",
    "addr:postcode":"55118",
    "addr:street":"Humboldt Ave",
    "iso:country":"US",
    "sg:address":"1009 Humboldt Ave",
    "sg:city":"West St Paul",
    "sg:classifiers":[
        {
            "category":"Professional",
            "type":"Services"
        }
    ],
    "sg:phone":"+1 651 340 5744",
    "sg:postcode":"55118",
    "sg:province":"MN",
    "sg:tags":[
        "establishment"
    ],
    "wof:name":"Care Nancy",
    "wof:placetype":"venue"
},
  "geometry": {"coordinates":[-93.08511300000001,44.914709],"type":"Point"}
}