{
  "type": "Feature",
  "properties": {
    "iso:country":"US",
    "sg:address":"210 Wexford Heights Dr",
    "sg:city":"Saint Paul",
    "sg:classifiers":[
        {
            "category":"Wholesale",
            "subcategory":"Vending Machines",
            "type":"Manufacturing & Wholesale Goods"
        }
    ],
    "sg:phone":"+1 651 271 6717",
    "sg:postcode":"55112",
    "sg:province":"MN",
    "sg:tags":[
        "operator"
    ],
    "wof:name":"VIP Vending Inc",
    "wof:placetype":"venue"
},
  "geometry": {"coordinates":[-93.221287,45.052931],"type":"Point"}
}