{
  "type": "Feature",
  "properties": {
    "addr:full":"181 Main Ave W Winsted MN 55395",
    "addr:housenumber":"181",
    "addr:postcode":"55395",
    "addr:street":"Main Ave W",
    "iso:country":"US",
    "sg:address":"181 Main Ave W",
    "sg:city":"Winsted",
    "sg:classifiers":[
        {
            "category":"Professional",
            "subcategory":"Management & Consulting",
            "type":"Services"
        }
    ],
    "sg:phone":"+1 320 485 5544",
    "sg:postcode":"55395",
    "sg:province":"MN",
    "sg:tags":[
        "marketing",
        "program"
    ],
    "wof:name":"C Two Marketing",
    "wof:placetype":"venue"
},
  "geometry": {"coordinates":[-94.047692,44.9642],"type":"Point"}
}