{
  "type": "Feature",
  "properties": {
    "addr:full":"2105 43rd St NW Rochester MN 55901",
    "addr:housenumber":"2105",
    "addr:postcode":"55901",
    "addr:street":"43Rd St Nw",
    "iso:country":"US",
    "sg:address":"2105 43rd St NW",
    "sg:city":"Rochester",
    "sg:classifiers":[
        {
            "category":"Building & Trades",
            "subcategory":"Construction",
            "type":"Services"
        }
    ],
    "sg:phone":"+1 507 281 1095",
    "sg:postcode":"55901",
    "sg:province":"MN",
    "sg:tags":[
        "house"
    ],
    "wof:name":"Rah Builders",
    "wof:placetype":"venue"
},
  "geometry": {"coordinates":[-92.495914,44.068591],"type":"Point"}
}