{
  "type": "Feature",
  "properties": {
    "addr:full":"3421 50th St NE Buffalo MN 55313",
    "addr:housenumber":"3421",
    "addr:postcode":"55313",
    "addr:street":"50Th St Ne",
    "iso:country":"US",
    "sg:address":"3421 50th St NE",
    "sg:city":"Buffalo",
    "sg:classifiers":[
        {
            "category":"Professional",
            "subcategory":"Research",
            "type":"Services"
        }
    ],
    "sg:phone":"+1 763 682 5505",
    "sg:postcode":"55313",
    "sg:province":"MN",
    "sg:tags":[
        "organization",
        "noncommercial"
    ],
    "wof:name":"Korosensorcom Inc",
    "wof:placetype":"venue"
},
  "geometry": {"coordinates":[-93.816693,45.222925],"type":"Point"}
}