{
  "type": "Feature",
  "properties": {
    "iso:country":"US",
    "sg:address":"25 E Broadway",
    "sg:city":"Plainview",
    "sg:classifiers":[
        {
            "category":"Farming",
            "subcategory":"Farm",
            "type":"Manufacturing & Wholesale Goods"
        }
    ],
    "sg:phone":"+1 507 534 2395",
    "sg:postcode":"55964",
    "sg:province":"MN",
    "sg:tags":[
        "crop",
        "general"
    ],
    "wof:name":"Severson Derald",
    "wof:placetype":"venue"
},
  "geometry": {"coordinates":[-92.165402,44.16489],"type":"Point"}
}