{
  "type": "Feature",
  "properties": {
    "addr:full":"20030 148th Cir N Rogers MN 55374",
    "addr:housenumber":"20030",
    "addr:postcode":"55374",
    "addr:street":"148Th Cir N",
    "iso:country":"US",
    "sg:address":"20030 148th Cir N",
    "sg:city":"Rogers",
    "sg:classifiers":[
        {
            "category":"Shopping",
            "subcategory":"Florist",
            "type":"Retail Goods"
        }
    ],
    "sg:phone":"+1 763 428 0282",
    "sg:postcode":"55374",
    "sg:province":"MN",
    "wof:name":"Floral Consultants Inc",
    "wof:placetype":"venue"
},
  "geometry": {"coordinates":[-93.535313,45.223544],"type":"Point"}
}