{
  "type": "Feature",
  "properties": {
    "addr:full":"10419 Lee Dr Eden Prairie MN 55347",
    "addr:housenumber":"10419",
    "addr:postcode":"55347",
    "addr:street":"Lee Dr",
    "iso:country":"US",
    "sg:address":"10419 Lee Dr",
    "sg:city":"Eden Prairie",
    "sg:classifiers":[
        {
            "category":"Social Services",
            "subcategory":"Child Care",
            "type":"Services"
        }
    ],
    "sg:phone":"+1 952 943 2268",
    "sg:postcode":"55347",
    "sg:province":"MN",
    "sg:tags":[
        "day"
    ],
    "wof:name":"Franlo Park Montessori Inc",
    "wof:placetype":"venue"
},
  "geometry": {"coordinates":[-93.412966,44.820815],"type":"Point"}
}