{
  "type": "Feature",
  "properties": {
    "iso:country":"US",
    "sg:address":"16211 Turnberry Turn NW",
    "sg:city":"Anoka",
    "sg:classifiers":[
        {
            "category":"Real Estate",
            "subcategory":"Real Estate Services",
            "type":"Services"
        },
        {
            "category":"Real Estate",
            "subcategory":"Real Estate Agent",
            "type":"Services"
        }
    ],
    "sg:phone":"+1 763 463 9490",
    "sg:postcode":"55303",
    "sg:province":"MN",
    "sg:tags":[
        "buyer",
        "broker"
    ],
    "wof:name":"Luke Realty",
    "wof:placetype":"venue"
},
  "geometry": {"coordinates":[-93.504783,45.264763],"type":"Point"}
}