{
  "type": "Feature",
  "properties": {
    "iso:country":"US",
    "sg:address":"301 Main St",
    "sg:city":"Lakefield",
    "sg:classifiers":[
        {
            "category":"Government",
            "subcategory":"Office",
            "type":"Public Place"
        }
    ],
    "sg:phone":"+1 507 662 5457",
    "sg:postcode":"56150",
    "sg:province":"MN",
    "sg:tags":[
        "village"
    ],
    "wof:name":"City Administrator",
    "wof:placetype":"venue"
},
  "geometry": {"coordinates":[-95.17203499999999,43.678526],"type":"Point"}
}