{
  "type": "Feature",
  "properties": {
    "addr:full":"4513 E Superior St Duluth MN 55804",
    "addr:housenumber":"4513",
    "addr:postcode":"55804",
    "addr:street":"E Superior St",
    "iso:country":"US",
    "sg:address":"4513 E Superior St",
    "sg:city":"Duluth",
    "sg:classifiers":[
        {
            "category":"Personal",
            "subcategory":"Barber",
            "type":"Services"
        }
    ],
    "sg:phone":"+1 218 525 3571",
    "sg:postcode":"55804",
    "sg:province":"MN",
    "sg:tags":[
        "shop"
    ],
    "wof:name":"Lakeside Barber",
    "wof:placetype":"venue"
},
  "geometry": {"coordinates":[-92.031316,46.828064],"type":"Point"}
}