{
  "type": "Feature",
  "properties": {
    "addr:full":"44660 Golf Course Rd Saint Peter MN 56082",
    "addr:housenumber":"44660",
    "addr:postcode":"56082",
    "addr:street":"Golf Course Rd",
    "iso:country":"US",
    "sg:address":"44660 Golf Course Rd",
    "sg:city":"Saint Peter",
    "sg:classifiers":[
        {
            "category":"Manufacturing",
            "subcategory":"Chemicals & Compounds",
            "type":"Manufacturing & Wholesale Goods"
        }
    ],
    "sg:phone":"+1 507 931 1833",
    "sg:postcode":"56082",
    "sg:province":"MN",
    "sg:tags":[
        "preparation",
        "mfg"
    ],
    "wof:name":"Norwegian Leather Care Pdts",
    "wof:placetype":"venue"
},
  "geometry": {"coordinates":[-93.931584,44.310993],"type":"Point"}
}