{
  "type": "Feature",
  "properties": {
    "iso:country":"US",
    "sg:address":"1070 Briar Creek Rd",
    "sg:city":"Eagan",
    "sg:classifiers":[
        {
            "category":"Arts & Performance",
            "subcategory":"Theater",
            "type":"Entertainment"
        }
    ],
    "sg:phone":"+1 651 454 1922",
    "sg:postcode":"55123",
    "sg:province":"MN",
    "sg:tags":[
        "band",
        "orchestra"
    ],
    "wof:name":"Pizzazz Jazz",
    "wof:placetype":"venue"
},
  "geometry": {"coordinates":[-93.144372,44.818306],"type":"Point"}
}