{
  "type": "Feature",
  "properties": {
    "addr:full":"4065 W 6th St Winona MN 55987",
    "addr:housenumber":"4065",
    "addr:postcode":"55987",
    "addr:street":"W 6Th St",
    "iso:country":"US",
    "sg:address":"4065 W 6th St",
    "sg:city":"Winona",
    "sg:classifiers":[
        {
            "category":"Shopping",
            "subcategory":"Hobbies, Toys, & Games",
            "type":"Retail Goods"
        }
    ],
    "sg:phone":"+1 507 474 0313",
    "sg:postcode":"55987",
    "sg:province":"MN",
    "sg:tags":[
        "supply"
    ],
    "wof:name":"Game Room",
    "wof:placetype":"venue"
},
  "geometry": {"coordinates":[-91.695291,44.062049],"type":"Point"}
}