{
  "type": "Feature",
  "properties": {
    "iso:country":"US",
    "sg:address":"6313 Aldrich Ave S",
    "sg:city":"Minneapolis",
    "sg:classifiers":[
        {
            "category":"Retail",
            "subcategory":"Repair Shop",
            "type":"Services"
        }
    ],
    "sg:phone":"+1 612 866 8307",
    "sg:postcode":"55423",
    "sg:province":"MN",
    "sg:tags":[
        "electrical"
    ],
    "wof:name":"Old Chestnut Forge",
    "wof:placetype":"venue"
},
  "geometry": {"coordinates":[-93.289536,44.887861],"type":"Point"}
}