{
  "type": "Feature",
  "properties": {
    "addr:full":"8483 Ingram Ave SW Howard Lake MN 55349",
    "addr:housenumber":"8483",
    "addr:postcode":"55349",
    "addr:street":"Ingram Ave Sw Howard Lake",
    "iso:country":"US",
    "sg:address":"8483 Ingram Ave SW",
    "sg:city":"Howard Lake",
    "sg:classifiers":[
        {
            "category":"Bus Charters",
            "type":"Transportation"
        }
    ],
    "sg:phone":"+1 320 543 2854",
    "sg:postcode":"55349",
    "sg:province":"MN",
    "sg:tags":[
        "coach"
    ],
    "wof:name":"Lachermeier Tours",
    "wof:placetype":"venue"
},
  "geometry": {"coordinates":[-94.057693,45.028918],"type":"Point"}
}