{
  "type": "Feature",
  "properties": {
    "iso:country":"US",
    "sg:address":"7391 Co Rd 39 NW",
    "sg:city":"Maple Lake",
    "sg:classifiers":[
        {
            "category":"Farming",
            "subcategory":"Dairy Farm",
            "type":"Manufacturing & Wholesale Goods"
        }
    ],
    "sg:phone":"+1 320 963 5473",
    "sg:postcode":"55358",
    "sg:province":"MN",
    "wof:name":"T & P Little Acre Dairy",
    "wof:placetype":"venue"
},
  "geometry": {"coordinates":[-94.038191,45.289596],"type":"Point"}
}