{
  "type": "Feature",
  "properties": {
    "iso:country":"US",
    "sg:address":"10620 Prairie Ln",
    "sg:city":"Hanover",
    "sg:classifiers":[
        {
            "category":"Wholesale",
            "subcategory":"Home Furnishings",
            "type":"Manufacturing & Wholesale Goods"
        }
    ],
    "sg:phone":"+1 763 498 7062",
    "sg:postcode":"55341",
    "sg:province":"MN",
    "wof:name":"Modulo USA LLC",
    "wof:placetype":"venue"
},
  "geometry": {"coordinates":[-93.657321,45.149071],"type":"Point"}
}