{
  "type": "Feature",
  "properties": {
    "addr:full":"301 Hwy 75 S Wolverton MN 56560",
    "addr:housenumber":"301",
    "addr:postcode":"56560",
    "addr:street":"Hwy 75 S Wolverton",
    "iso:country":"US",
    "sg:address":"301 Hwy 75 S",
    "sg:city":"Wolverton",
    "sg:classifiers":[
        {
            "category":"Government",
            "subcategory":"Fire Station",
            "type":"Public Place"
        }
    ],
    "sg:phone":"+1 218 995 2525",
    "sg:postcode":"56560",
    "sg:province":"MN",
    "sg:tags":[
        "department"
    ],
    "wof:name":"Wolverton Fire Dept",
    "wof:placetype":"venue"
},
  "geometry": {"coordinates":[-96.767912,46.87064],"type":"Point"}
}