{
  "type": "Feature",
  "properties": {
    "addr:full":"410 Dakota St W Cannon Falls MN 55009",
    "addr:housenumber":"410",
    "addr:postcode":"55009",
    "addr:street":"Dakota St W",
    "iso:country":"US",
    "sg:address":"410 Dakota St W",
    "sg:city":"Cannon Falls",
    "sg:classifiers":[
        {
            "category":"Organizations",
            "subcategory":"Religious Organization",
            "type":"Services"
        }
    ],
    "sg:phone":"+1 507 263 3559",
    "sg:postcode":"55009",
    "sg:province":"MN",
    "wof:name":"Church Of Christ",
    "wof:placetype":"venue"
},
  "geometry": {"coordinates":[-92.906807,44.51587],"type":"Point"}
}