{
  "type": "Feature",
  "properties": {
    "iso:country":"US",
    "sg:address":"1114 Zane Ave N",
    "sg:city":"Minneapolis",
    "sg:classifiers":[
        {
            "category":"Wholesale",
            "subcategory":"Non-durable Goods",
            "type":"Manufacturing & Wholesale Goods"
        }
    ],
    "sg:phone":"+1 763 545 0845",
    "sg:postcode":"55422",
    "sg:province":"MN",
    "sg:tags":[
        "dry",
        "goods-wholesale"
    ],
    "wof:name":"Western Supply Corporation",
    "wof:placetype":"venue"
},
  "geometry": {"coordinates":[-93.355183,44.990256],"type":"Point"}
}