{
  "type": "Feature",
  "properties": {
    "iso:country":"US",
    "sg:address":"301 4th St NE",
    "sg:city":"Kasson",
    "sg:classifiers":[
        {
            "category":"Building & Trades",
            "subcategory":"Construction",
            "type":"Services"
        }
    ],
    "sg:phone":"+1 507 634 7425",
    "sg:postcode":"55944",
    "sg:province":"MN",
    "sg:tags":[
        "house",
        "contractor"
    ],
    "wof:name":"Sc Builders",
    "wof:placetype":"venue"
},
  "geometry": {"coordinates":[-92.74476,44.03311],"type":"Point"}
}