{
  "type": "Feature",
  "properties": {
    "addr:full":"475 Clover Leaf Pkwy NE Minneapolis MN 55434",
    "addr:housenumber":"475",
    "addr:postcode":"55434",
    "addr:street":"Clover Leaf Pkwy Ne",
    "iso:country":"US",
    "sg:address":"475 Clover Leaf Pkwy NE",
    "sg:city":"Minneapolis",
    "sg:classifiers":[
        {
            "category":"Building & Trades",
            "subcategory":"Construction",
            "type":"Services"
        }
    ],
    "sg:phone":"+1 763 786 9059",
    "sg:postcode":"55434",
    "sg:province":"MN",
    "sg:tags":[
        "carpenter"
    ],
    "wof:name":"Randy Rengo",
    "wof:placetype":"venue"
},
  "geometry": {"coordinates":[-93.257088,45.144347],"type":"Point"}
}