{
  "type": "Feature",
  "properties": {
    "addr:full":"3634 Scheuneman Rd St Paul MN 55110",
    "addr:housenumber":"3634",
    "addr:postcode":"55110",
    "addr:street":"Scheuneman Rd",
    "iso:country":"US",
    "sg:address":"3634 Scheuneman Rd",
    "sg:city":"St Paul",
    "sg:classifiers":[
        {
            "category":"Autos & Motor Vehicles",
            "subcategory":"Auto Supplies",
            "type":"Retail Goods"
        }
    ],
    "sg:phone":"+1 651 426 4640",
    "sg:postcode":"55110",
    "sg:province":"MN",
    "sg:tags":[
        "tire"
    ],
    "wof:name":"Pods Tires & Wheels",
    "wof:placetype":"venue"
},
  "geometry": {"coordinates":[-93.033146,45.054231],"type":"Point"}
}