{
  "type": "Feature",
  "properties": {
    "iso:country":"US",
    "sg:address":"2146 Birch Point Rd",
    "sg:city":"Tower",
    "sg:classifiers":[
        {
            "category":"Professional",
            "type":"Services"
        }
    ],
    "sg:phone":"+1 218 753 5491",
    "sg:postcode":"55790",
    "sg:province":"MN",
    "wof:name":"Beatty Portage Company Inc",
    "wof:placetype":"venue"
},
  "geometry": {"coordinates":[-92.364988,47.857863],"type":"Point"}
}