{
  "type": "Feature",
  "properties": {
    "iso:country":"US",
    "sg:address":"2501 Cleveland Ave N",
    "sg:city":"Saint Paul",
    "sg:classifiers":[
        {
            "category":"Government",
            "subcategory":"Office",
            "type":"Public Place"
        }
    ],
    "sg:phone":"+1 651 296 2335",
    "sg:postcode":"55113",
    "sg:province":"MN",
    "sg:tags":[
        "transportation"
    ],
    "wof:name":"Transportation Minnesota Dept",
    "wof:placetype":"venue"
},
  "geometry": {"coordinates":[-93.18716499999999,45.015815],"type":"Point"}
}