{
  "type": "Feature",
  "properties": {
    "iso:country":"US",
    "sg:address":"2411 Kenwood Dr SW",
    "sg:city":"Willmar",
    "sg:classifiers":[
        {
            "category":"Real Estate",
            "subcategory":"Real Estate Agent",
            "type":"Services"
        }
    ],
    "sg:phone":"+1 320 235 2424",
    "sg:postcode":"56201",
    "sg:province":"MN",
    "wof:name":"Renstrom Realty",
    "wof:placetype":"venue"
},
  "geometry": {"coordinates":[-95.044606,45.098426],"type":"Point"}
}