{
  "type": "Feature",
  "properties": {
    "addr:full":"8512 Eldorado St NE Minneapolis MN 55449",
    "addr:housenumber":"8512",
    "addr:postcode":"55449",
    "addr:street":"Eldorado St Ne",
    "iso:country":"US",
    "sg:address":"8512 Eldorado St NE",
    "sg:city":"Minneapolis",
    "sg:classifiers":[
        {
            "category":"Banks & Credit Unions",
            "subcategory":"Financial Services",
            "type":"Services"
        }
    ],
    "sg:phone":"+1 763 780 4293",
    "sg:postcode":"55449",
    "sg:province":"MN",
    "sg:tags":[
        "investor"
    ],
    "wof:name":"Kids First Our Investment",
    "wof:placetype":"venue"
},
  "geometry": {"coordinates":[-93.228692,45.127926],"type":"Point"}
}