{
  "type": "Feature",
  "properties": {
    "addr:full":"1616 E River Ter Minneapolis MN 55414",
    "addr:housenumber":"1616",
    "addr:postcode":"55414",
    "addr:street":"E River Ter",
    "iso:country":"US",
    "sg:address":"1616 E River Ter",
    "sg:city":"Minneapolis",
    "sg:classifiers":[
        {
            "category":"Retail",
            "subcategory":"Repair Shop",
            "type":"Services"
        }
    ],
    "sg:phone":"+1 612 861 5577",
    "sg:postcode":"55414",
    "sg:province":"MN",
    "sg:tags":[
        "reupholstery",
        "furniture"
    ],
    "wof:name":"Recovery Room Upholstrey",
    "wof:placetype":"venue"
},
  "geometry": {"coordinates":[-93.21448700000001,44.961902],"type":"Point"}
}