{
  "type": "Feature",
  "properties": {
    "addr:full":"10106 Fernwood Ln N Champlin MN 55316",
    "addr:housenumber":"10106",
    "addr:postcode":"55316",
    "addr:street":"Fernwood Ln N",
    "iso:country":"US",
    "sg:address":"10106 Fernwood Ln N",
    "sg:city":"Champlin",
    "sg:classifiers":[
        {
            "category":"Professional",
            "type":"Services"
        }
    ],
    "sg:phone":"+1 763 427 9030",
    "sg:postcode":"55316",
    "sg:province":"MN",
    "wof:name":"Tonia Swennes",
    "wof:placetype":"venue"
},
  "geometry": {"coordinates":[-93.410562,45.16057],"type":"Point"}
}