{
  "type": "Feature",
  "properties": {
    "iso:country":"US",
    "sg:address":"3294 Anderson Rd",
    "sg:city":"Hibbing",
    "sg:classifiers":[
        {
            "category":"Freight",
            "type":"Transportation"
        }
    ],
    "sg:phone":"+1 218 263 4132",
    "sg:postcode":"55746",
    "sg:province":"MN",
    "sg:tags":[
        "trucking"
    ],
    "wof:name":"Mc Comb Trucking",
    "wof:placetype":"venue"
},
  "geometry": {"coordinates":[-92.96965400000001,47.344614],"type":"Point"}
}