{
  "type": "Feature",
  "properties": {
    "iso:country":"US",
    "sg:address":"1249 Marion Rd SE",
    "sg:city":"Rochester",
    "sg:classifiers":[
        {
            "category":"Shopping",
            "subcategory":"Clothing, Apparel, & Fashions",
            "type":"Retail Goods"
        }
    ],
    "sg:phone":"+1 507 289 6637",
    "sg:postcode":"55904",
    "sg:province":"MN",
    "sg:tags":[
        "infant",
        "wear"
    ],
    "wof:name":"Children's Exchange",
    "wof:placetype":"venue"
},
  "geometry": {"coordinates":[-92.441125,44.008298],"type":"Point"}
}