{
  "type": "Feature",
  "properties": {
    "addr:full":"6402 Timber Rdg Minneapolis MN 55439",
    "addr:housenumber":"6402",
    "addr:postcode":"55439",
    "addr:street":"Timber Rdg",
    "iso:country":"US",
    "sg:address":"6402 Timber Rdg",
    "sg:city":"Minneapolis",
    "sg:classifiers":[
        {
            "category":"Ice Cream",
            "type":"Food & Drink"
        }
    ],
    "sg:phone":"+1 952 941 5833",
    "sg:postcode":"55439",
    "sg:province":"MN",
    "sg:tags":[
        "frozen",
        "dessert"
    ],
    "wof:name":"Robbins Company",
    "wof:placetype":"venue"
},
  "geometry": {"coordinates":[-93.388901,44.887932],"type":"Point"}
}