{
  "type": "Feature",
  "properties": {
    "iso:country":"US",
    "sg:address":"2179 4th St",
    "sg:city":"St Paul",
    "sg:classifiers":[
        {
            "category":"Professional",
            "type":"Services"
        }
    ],
    "sg:phone":"+1 651 653 5141",
    "sg:postcode":"55110",
    "sg:province":"MN",
    "sg:tags":[
        "geographer"
    ],
    "wof:name":"Plan Sight",
    "wof:placetype":"venue"
},
  "geometry": {"coordinates":[-93.00843500000001,45.085462],"type":"Point"}
}