{
  "type": "Feature",
  "properties": {
    "iso:country":"US",
    "sg:address":"6765 Hwy 14 SE",
    "sg:city":"Rochester",
    "sg:classifiers":[
        {
            "category":"Manufacturing",
            "subcategory":"Metals",
            "type":"Manufacturing & Wholesale Goods"
        }
    ],
    "sg:phone":"+1 507 288 6005",
    "sg:postcode":"55904",
    "sg:province":"MN",
    "sg:tags":[
        "product",
        "primary",
        "mfg"
    ],
    "wof:name":"Midwest Manufacturing",
    "wof:placetype":"venue"
},
  "geometry": {"coordinates":[-92.344094,44.003421],"type":"Point"}
}