{
  "type": "Feature",
  "properties": {
    "addr:full":"340 7th Ave S St Cloud MN 56301",
    "addr:housenumber":"340",
    "addr:postcode":"56301",
    "addr:street":"7Th Ave S",
    "iso:country":"US",
    "sg:address":"340 7th Ave S",
    "sg:city":"St Cloud",
    "sg:classifiers":[
        {
            "category":"Organizations",
            "subcategory":"Religious Organization",
            "type":"Services"
        }
    ],
    "sg:phone":"+1 320 253 8379",
    "sg:postcode":"56301",
    "sg:province":"MN",
    "sg:tags":[
        "church"
    ],
    "wof:name":"Cornerstone Church",
    "wof:placetype":"venue"
},
  "geometry": {"coordinates":[-94.157363,45.556521],"type":"Point"}
}