{
  "type": "Feature",
  "properties": {
    "addr:full":"3287 Normanna Rd Duluth MN 55803",
    "addr:housenumber":"3287",
    "addr:postcode":"55803",
    "addr:street":"Normanna Rd",
    "iso:country":"US",
    "sg:address":"3287 Normanna Rd",
    "sg:city":"Duluth",
    "sg:classifiers":[
        {
            "category":"Building & Trades",
            "subcategory":"Construction",
            "type":"Services"
        }
    ],
    "sg:phone":"+1 218 525 6261",
    "sg:postcode":"55803",
    "sg:province":"MN",
    "sg:tags":[
        "contractor"
    ],
    "wof:name":"Mike Mielke Contracting",
    "wof:placetype":"venue"
},
  "geometry": {"coordinates":[-92.025929,46.983855],"type":"Point"}
}