{
  "type": "Feature",
  "properties": {
    "addr:full":"7180 Northland Cir N # 130 Minneapolis MN 55428",
    "addr:housenumber":"7180",
    "addr:postcode":"55428",
    "addr:street":"Northland Cir N # 130",
    "iso:country":"US",
    "sg:address":"7180 Northland Cir N # 130",
    "sg:city":"Minneapolis",
    "sg:classifiers":[
        {
            "category":"Shopping",
            "subcategory":"Stationery & Office Supplies",
            "type":"Retail Goods"
        }
    ],
    "sg:phone":"+1 763 531 9022",
    "sg:postcode":"55428",
    "sg:province":"MN",
    "sg:tags":[
        "packing",
        "materials-shipping"
    ],
    "sg:website":"http://www.posi-pack.com",
    "wof:name":"Posi-Pack Corporation, Inc",
    "wof:placetype":"venue"
},
  "geometry": {"coordinates":[-93.390309,45.085179],"type":"Point"}
}