{
  "type": "Feature",
  "properties": {
    "iso:country":"US",
    "sg:address":"3172 Laketown Rd",
    "sg:city":"Sturgeon Lake",
    "sg:classifiers":[
        {
            "category":"Retail",
            "subcategory":"Car Wash",
            "type":"Services"
        }
    ],
    "sg:phone":"+1 218 372 8527",
    "sg:postcode":"55783",
    "sg:province":"MN",
    "sg:tags":[
        "automobile",
        "detail",
        "clean"
    ],
    "wof:name":"Carty's Automotive & Custom",
    "wof:placetype":"venue"
},
  "geometry": {"coordinates":[-92.81466899999999,46.38138],"type":"Point"}
}