{
  "type": "Feature",
  "properties": {
    "iso:country":"US",
    "sg:address":"1037 1st Ave E",
    "sg:city":"Shakopee",
    "sg:classifiers":[
        {
            "category":"Coffee & Tea",
            "type":"Food & Drink"
        },
        {
            "category":"Food & Beverages",
            "subcategory":"Bakery",
            "type":"Retail Goods"
        },
        {
            "category":"Bakery",
            "type":"Food & Drink"
        },
        {
            "category":"Donuts",
            "type":"Food & Drink"
        }
    ],
    "sg:menulink":"http://www.allmenus.com/mn/shakopee/222448-donut-connection/menu/",
    "sg:phone":"+1 952 496 2040",
    "sg:postcode":"55379",
    "sg:province":"MN",
    "sg:tags":[
        "tea",
        "coffee",
        "bakery",
        "american",
        "pastry"
    ],
    "wof:name":"Donut Connection",
    "wof:placetype":"venue"
},
  "geometry": {"coordinates":[-93.51321799999999,44.800715],"type":"Point"}
}