{
  "type": "Feature",
  "properties": {
    "iso:country":"US",
    "sg:address":"1424 Mainstreet",
    "sg:city":"Hopkins",
    "sg:classifiers":[
        {
            "category":"Home & Garden",
            "subcategory":"Home Furnishings",
            "type":"Retail Goods"
        }
    ],
    "sg:phone":"+1 952 935 6739",
    "sg:postcode":"55343",
    "sg:province":"MN",
    "sg:tags":[
        "equipment",
        "electrical"
    ],
    "wof:name":"Electric Craftsman Inc",
    "wof:placetype":"venue"
},
  "geometry": {"coordinates":[-93.41883199999999,44.924273],"type":"Point"}
}