{
  "type": "Feature",
  "properties": {
    "iso:country":"US",
    "sg:address":"1732 7th St SE",
    "sg:city":"St Cloud",
    "sg:classifiers":[
        {
            "category":"Retail",
            "subcategory":"Repair Shop",
            "type":"Services"
        },
        {
            "category":"Farming",
            "subcategory":"Aquatic Farm",
            "type":"Manufacturing & Wholesale Goods"
        }
    ],
    "sg:phone":"+1 320 251 4549",
    "sg:postcode":"56304",
    "sg:province":"MN",
    "sg:tags":[
        "related"
    ],
    "wof:name":"New Wave Aquaria",
    "wof:placetype":"venue"
},
  "geometry": {"coordinates":[-94.12449700000001,45.5596],"type":"Point"}
}