{
  "type": "Feature",
  "properties": {
    "addr:full":"1414 Cougar Ct Sartell MN 56377",
    "addr:housenumber":"1414",
    "addr:postcode":"56377",
    "addr:street":"Cougar Ct",
    "iso:country":"US",
    "sg:address":"1414 Cougar Ct",
    "sg:city":"Sartell",
    "sg:classifiers":[
        {
            "category":"Professional",
            "type":"Services"
        }
    ],
    "sg:phone":"+1 320 255 0517",
    "sg:postcode":"56377",
    "sg:province":"MN",
    "wof:name":"Multicultural Art Studio",
    "wof:placetype":"venue"
},
  "geometry": {"coordinates":[-94.23665200000001,45.631972],"type":"Point"}
}