{
  "type": "Feature",
  "properties": {
    "addr:full":"3801 W 50th St Minneapolis MN 55410",
    "addr:housenumber":"3801",
    "addr:postcode":"55410",
    "addr:street":"W 50Th St",
    "iso:country":"US",
    "sg:address":"3801 W 50th St",
    "sg:city":"Minneapolis",
    "sg:classifiers":[
        {
            "category":"Sports & Exercise",
            "subcategory":"Gym",
            "type":"Entertainment"
        }
    ],
    "sg:phone":"+1 612 920 3494",
    "sg:postcode":"55410",
    "sg:province":"MN",
    "sg:website":"www.curves.com",
    "wof:name":"Curves For Women",
    "wof:placetype":"venue"
},
  "geometry": {"coordinates":[-93.327772,44.912472],"type":"Point"}
}