{
  "type": "Feature",
  "properties": {
    "addr:full":"23881 560th Ave Alberta MN 56243",
    "addr:housenumber":"23881",
    "addr:postcode":"56243",
    "addr:street":"560Th Ave",
    "iso:country":"US",
    "sg:address":"23881 560th Ave",
    "sg:city":"Alberta",
    "sg:phone":"+1 320 324 7368",
    "sg:postcode":"56243",
    "sg:province":"MN",
    "sg:tags":[
        "farm",
        "corn",
        "soybean"
    ],
    "wof:name":"Larry Fynboh",
    "wof:placetype":"venue"
},
  "geometry": {"coordinates":[-94.64505200000001,45.146532],"type":"Point"}
}