{
  "type": "Feature",
  "properties": {
    "addr:full":"121 Broadway Ave N New Richland MN 56072",
    "addr:housenumber":"121",
    "addr:postcode":"56072",
    "addr:street":"Broadway Ave N New",
    "iso:country":"US",
    "sg:address":"121 Broadway Ave N",
    "sg:city":"New Richland",
    "sg:classifiers":[
        {
            "category":"Insurance",
            "subcategory":"Insurance Agent",
            "type":"Services"
        }
    ],
    "sg:phone":"+1 507 465 8111",
    "sg:postcode":"56072",
    "sg:province":"MN",
    "wof:name":"New Richland Insurance",
    "wof:placetype":"venue"
},
  "geometry": {"coordinates":[-93.49378400000001,43.894734],"type":"Point"}
}