{
  "type": "Feature",
  "properties": {
    "addr:full":"2753 Geneva Ave N Saint Paul MN 55128",
    "addr:housenumber":"2753",
    "addr:postcode":"55128",
    "addr:street":"Geneva Ave N",
    "iso:country":"US",
    "sg:address":"2753 Geneva Ave N",
    "sg:city":"Saint Paul",
    "sg:classifiers":[
        {
            "category":"Retail",
            "subcategory":"Auto Repair",
            "type":"Services"
        }
    ],
    "sg:phone":"+1 651 777 8129",
    "sg:postcode":"55128",
    "sg:province":"MN",
    "sg:tags":[
        "shop"
    ],
    "wof:name":"M & H Import & Dom Auto Repr",
    "wof:placetype":"venue"
},
  "geometry": {"coordinates":[-92.984627,44.988188],"type":"Point"}
}