{
  "type": "Feature",
  "properties": {
    "iso:country":"US",
    "sg:address":"1031 Mechanic St",
    "sg:city":"Edgerton",
    "sg:classifiers":[
        {
            "category":"Building & Trades",
            "subcategory":"Construction",
            "type":"Services"
        }
    ],
    "sg:phone":"+1 507 631 8488",
    "sg:postcode":"56128",
    "sg:province":"MN",
    "sg:tags":[
        "cabinet",
        "carpentry",
        "maker",
        "contractor"
    ],
    "wof:name":"Prestige Dental Cabinets Inc",
    "wof:placetype":"venue"
},
  "geometry": {"coordinates":[-96.12711899999999,43.87101],"type":"Point"}
}