{
  "type": "Feature",
  "properties": {
    "iso:country":"US",
    "sg:address":"23577 US Hwy 10",
    "sg:city":"Detroit Lakes",
    "sg:classifiers":[
        {
            "category":"Building & Trades",
            "subcategory":"Plumbing",
            "type":"Services"
        }
    ],
    "sg:phone":"+1 218 844 5678",
    "sg:postcode":"56501",
    "sg:province":"MN",
    "sg:tags":[
        "mechanical",
        "contractor"
    ],
    "wof:name":"Viking Mechanical",
    "wof:placetype":"venue"
},
  "geometry": {"coordinates":[-95.91108199999999,46.835038],"type":"Point"}
}