{
  "type": "Feature",
  "properties": {
    "addr:full":"3211 W 108th St Minneapolis MN 55431",
    "addr:housenumber":"3211",
    "addr:postcode":"55431",
    "addr:street":"W 108Th St",
    "iso:country":"US",
    "sg:address":"3211 W 108th St",
    "sg:city":"Minneapolis",
    "sg:classifiers":[
        {
            "category":"Organizations",
            "subcategory":"Religious Organization",
            "type":"Services"
        }
    ],
    "sg:phone":"+1 952 888 5166",
    "sg:postcode":"55431",
    "sg:province":"MN",
    "wof:name":"Eden Prairie Congregation",
    "wof:placetype":"venue"
},
  "geometry": {"coordinates":[-93.32073200000001,44.808341],"type":"Point"}
}