{
  "type": "Feature",
  "properties": {
    "addr:full":"201 N Chestnut St La Crescent MN 55947",
    "addr:housenumber":"201",
    "addr:postcode":"55947",
    "addr:street":"N Chestnut St;Crescent",
    "iso:country":"US",
    "sg:address":"201 N Chestnut St",
    "sg:city":"La Crescent",
    "sg:classifiers":[
        {
            "category":"Wholesale",
            "subcategory":"Office Equipment",
            "type":"Manufacturing & Wholesale Goods"
        }
    ],
    "sg:phone":"+1 507 895 4081",
    "sg:postcode":"55947",
    "sg:province":"MN",
    "sg:tags":[
        "electrical"
    ],
    "wof:name":"Ban-Koe Systems Inc",
    "wof:placetype":"venue"
},
  "geometry": {"coordinates":[-91.302362,43.831897],"type":"Point"}
}