{
  "type": "Feature",
  "properties": {
    "iso:country":"US",
    "sg:address":"1335 Dundas Cir",
    "sg:city":"Monticello",
    "sg:classifiers":[
        {
            "category":"Autos & Motor Vehicles",
            "subcategory":"Automobile Sales",
            "type":"Retail Goods"
        }
    ],
    "sg:phone":"+1 763 295 7433",
    "sg:postcode":"55362",
    "sg:province":"MN",
    "wof:name":"Ready To Ride LTD",
    "wof:placetype":"venue"
},
  "geometry": {"coordinates":[-93.792045,45.291101],"type":"Point"}
}