{
  "type": "Feature",
  "properties": {
    "addr:full":"13700 Memorywood Dr Baxter MN 56425",
    "addr:housenumber":"13700",
    "addr:postcode":"56425",
    "addr:street":"Memorywood Dr",
    "iso:country":"US",
    "sg:address":"13700 Memorywood Dr",
    "sg:city":"Baxter",
    "sg:classifiers":[
        {
            "category":"Communications",
            "subcategory":"Film & Video Production",
            "type":"Services"
        }
    ],
    "sg:phone":"+1 218 828 9109",
    "sg:postcode":"56425",
    "sg:province":"MN",
    "sg:tags":[
        "tv",
        "radio",
        "services-commercial",
        "companies-film"
    ],
    "wof:name":"Kids Act Productions",
    "wof:placetype":"venue"
},
  "geometry": {"coordinates":[-94.297057,46.350001],"type":"Point"}
}