{
  "type": "Feature",
  "properties": {
    "iso:country":"US",
    "sg:address":"1114 S State St",
    "sg:city":"Fairmont",
    "sg:classifiers":[
        {
            "category":"Organizations",
            "subcategory":"Religious Organization",
            "type":"Services"
        }
    ],
    "sg:phone":"+1 507 238 2865",
    "sg:postcode":"56031",
    "sg:province":"MN",
    "sg:tags":[
        "clergy"
    ],
    "wof:name":"Richard T Reynertson",
    "wof:placetype":"venue"
},
  "geometry": {"coordinates":[-94.45034200000001,43.642472],"type":"Point"}
}