{
  "type": "Feature",
  "properties": {
    "addr:full":"451 N Lexington Pkwy St Paul MN 55104",
    "addr:housenumber":"451",
    "addr:postcode":"55104",
    "addr:street":"N Lexington Pkwy",
    "iso:country":"US",
    "sg:address":"451 N Lexington Pkwy",
    "sg:city":"St Paul",
    "sg:classifiers":[
        {
            "category":"Autos & Motor Vehicles",
            "subcategory":"Automobile Sales",
            "type":"Retail Goods"
        }
    ],
    "sg:phone":"+1 651 646 4071",
    "sg:postcode":"55104",
    "sg:province":"MN",
    "sg:tags":[
        "performance",
        "race",
        "dealer"
    ],
    "wof:name":"Intense Audio & Import Racing",
    "wof:placetype":"venue"
},
  "geometry": {"coordinates":[-93.1467,44.954798],"type":"Point"}
}