{
  "type": "Feature",
  "properties": {
    "iso:country":"US",
    "sg:address":"19131 Hwy 23 NE",
    "sg:city":"Paynesville",
    "sg:classifiers":[
        {
            "category":"Retail",
            "subcategory":"Repair Shop",
            "type":"Services"
        }
    ],
    "sg:phone":"+1 320 243 4018",
    "sg:postcode":"56362",
    "sg:province":"MN",
    "wof:name":"Kascht Motors Specialty",
    "wof:placetype":"venue"
},
  "geometry": {"coordinates":[-94.78374599999999,45.355107],"type":"Point"}
}