{
  "type": "Feature",
  "properties": {
    "addr:full":"2 E Franklin Ave Ste 7 Minneapolis MN 55404",
    "addr:housenumber":"2",
    "addr:postcode":"55404",
    "addr:street":"E Franklin Ave Ste 7",
    "iso:country":"US",
    "sg:address":"2 E Franklin Ave Ste 7",
    "sg:city":"Minneapolis",
    "sg:classifiers":[
        {
            "category":"Communications",
            "subcategory":"Film & Video Production",
            "type":"Services"
        },
        {
            "category":"Professional",
            "subcategory":"Printing & Photocopies",
            "type":"Services"
        }
    ],
    "sg:phone":"+1 612 874 1999",
    "sg:postcode":"55404",
    "sg:province":"MN",
    "sg:tags":[
        "companies-film",
        "tv",
        "services-commercial",
        "radio",
        "photographers-commercial"
    ],
    "wof:name":"Parallel Productions Inc",
    "wof:placetype":"venue"
},
  "geometry": {"coordinates":[-93.27780199999999,44.962688],"type":"Point"}
}