{
  "type": "Feature",
  "properties": {
    "addr:full":"1805 Red Oak Dr NE Alexandria MN 56308",
    "addr:housenumber":"1805",
    "addr:postcode":"56308",
    "addr:street":"Red Oak Dr Ne",
    "iso:country":"US",
    "sg:address":"1805 Red Oak Dr NE",
    "sg:city":"Alexandria",
    "sg:classifiers":[
        {
            "category":"Home & Garden",
            "subcategory":"Building Materials",
            "type":"Retail Goods"
        }
    ],
    "sg:phone":"+1 320 763 6223",
    "sg:postcode":"56308",
    "sg:province":"MN",
    "wof:name":"Kelly Kreations",
    "wof:placetype":"venue"
},
  "geometry": {"coordinates":[-95.347025,45.91385],"type":"Point"}
}