{
  "type": "Feature",
  "properties": {
    "addr:full":"6390 Town Hall Dr Loretto MN 55357",
    "addr:housenumber":"6390",
    "addr:postcode":"55357",
    "addr:street":"Town Hall Dr",
    "iso:country":"US",
    "sg:address":"6390 Town Hall Dr",
    "sg:city":"Loretto",
    "sg:classifiers":[
        {
            "category":"Government",
            "subcategory":"Police Station",
            "type":"Public Place"
        }
    ],
    "sg:phone":"+1 763 477 6464",
    "sg:postcode":"55357",
    "sg:province":"MN",
    "sg:tags":[
        "protection"
    ],
    "wof:name":"Greenfield City Hall",
    "wof:placetype":"venue"
},
  "geometry": {"coordinates":[-93.67361200000001,45.08026],"type":"Point"}
}