{
  "type": "Feature",
  "properties": {
    "addr:full":"29813 390th Ave NE Grygla MN 56727",
    "addr:housenumber":"29813",
    "addr:postcode":"56727",
    "addr:street":"390Th Ave Ne",
    "iso:country":"US",
    "sg:address":"29813 390th Ave NE",
    "sg:city":"Grygla",
    "sg:classifiers":[
        {
            "category":"Freight",
            "type":"Transportation"
        }
    ],
    "sg:phone":"+1 218 294 6282",
    "sg:postcode":"56727",
    "sg:province":"MN",
    "sg:tags":[
        "operator",
        "local",
        "trucking"
    ],
    "wof:name":"Lee Saurdiff",
    "wof:placetype":"venue"
},
  "geometry": {"coordinates":[-95.63646199999999,48.327318],"type":"Point"}
}