{
  "type": "Feature",
  "properties": {
    "iso:country":"US",
    "sg:address":"1228 E Vierling Dr",
    "sg:city":"Shakopee",
    "sg:classifiers":[
        {
            "category":"Real Estate",
            "subcategory":"Real Estate Services",
            "type":"Services"
        }
    ],
    "sg:phone":"+1 952 445 6400",
    "sg:postcode":"55379",
    "sg:province":"MN",
    "sg:website":"www.shakopee.edinarealty.com",
    "wof:name":"Edina Realty",
    "wof:placetype":"venue"
},
  "geometry": {"coordinates":[-93.506888,44.780495],"type":"Point"}
}