{
  "type": "Feature",
  "properties": {
    "addr:full":"5400 Main St NE Minneapolis MN 55421",
    "addr:housenumber":"5400",
    "addr:postcode":"55421",
    "addr:street":"Main St Ne",
    "iso:country":"US",
    "sg:address":"5400 Main St NE",
    "sg:city":"Minneapolis",
    "sg:classifiers":[
        {
            "category":"Professional",
            "subcategory":"Business Services",
            "type":"Services"
        }
    ],
    "sg:phone":"+1 763 571 5719",
    "sg:postcode":"55421",
    "sg:province":"MN",
    "sg:tags":[
        "document",
        "storage"
    ],
    "wof:name":"All-Data Storage",
    "wof:placetype":"venue"
},
  "geometry": {"coordinates":[-93.26809,45.066604],"type":"Point"}
}