{
  "type": "Feature",
  "properties": {
    "iso:country":"US",
    "sg:address":"9008 W River Rd",
    "sg:city":"Brooklyn Park",
    "sg:classifiers":[
        {
            "category":"Professional",
            "subcategory":"Accounting & Tax Preparation",
            "type":"Services"
        }
    ],
    "sg:phone":"+1 763 560 7818",
    "sg:postcode":"55444",
    "sg:province":"MN",
    "sg:tags":[
        "bookkeeping",
        "general"
    ],
    "wof:name":"Bookkeeping Plus",
    "wof:placetype":"venue"
},
  "geometry": {"coordinates":[-93.298198,45.118919],"type":"Point"}
}