{
  "type": "Feature",
  "properties": {
    "iso:country":"US",
    "sg:address":"651 University Ave W",
    "sg:city":"Saint Paul",
    "sg:classifiers":[
        {
            "category":"Professional",
            "type":"Services"
        }
    ],
    "sg:phone":"+1 651 230 0721",
    "sg:postcode":"55104",
    "sg:province":"MN",
    "wof:name":"Mihailo Temali",
    "wof:placetype":"venue"
},
  "geometry": {"coordinates":[-93.12846999999999,44.955794],"type":"Point"}
}