{
  "type": "Feature",
  "properties": {
    "iso:country":"US",
    "sg:address":"3110 Strand Rd",
    "sg:city":"Duluth",
    "sg:classifiers":[
        {
            "category":"Recreation",
            "type":"Entertainment"
        }
    ],
    "sg:phone":"+1 218 525 2939",
    "sg:postcode":"55803",
    "sg:province":"MN",
    "sg:tags":[
        "center"
    ],
    "wof:name":"Lakewood Recreation Center",
    "wof:placetype":"venue"
},
  "geometry": {"coordinates":[-92.00609900000001,46.887537],"type":"Point"}
}