{
  "type": "Feature",
  "properties": {
    "addr:full":"7916 83rd Ave N Minneapolis MN 55445",
    "addr:housenumber":"7916",
    "addr:postcode":"55445",
    "addr:street":"83Rd Ave N",
    "iso:country":"US",
    "sg:address":"7916 83rd Ave N",
    "sg:city":"Minneapolis",
    "sg:classifiers":[
        {
            "category":"Home & Garden",
            "subcategory":"Home Furnishings",
            "type":"Retail Goods"
        }
    ],
    "sg:phone":"+1 763 493 3966",
    "sg:postcode":"55445",
    "sg:province":"MN",
    "wof:name":"Tupperware Dealer",
    "wof:placetype":"venue"
},
  "geometry": {"coordinates":[-93.38523000000001,45.104887],"type":"Point"}
}