{
  "type": "Feature",
  "properties": {
    "addr:full":"127 6th Ave N St Cloud MN 56303",
    "addr:housenumber":"127",
    "addr:postcode":"56303",
    "addr:street":"6Th Ave N",
    "iso:country":"US",
    "sg:address":"127 6th Ave N",
    "sg:city":"St Cloud",
    "sg:classifiers":[
        {
            "category":"Home & Garden",
            "subcategory":"Building Materials",
            "type":"Retail Goods"
        }
    ],
    "sg:phone":"+1 320 252 1920",
    "sg:postcode":"56303",
    "sg:province":"MN",
    "sg:tags":[
        "lumber"
    ],
    "sg:website":"www.mathewhall.com",
    "wof:name":"Mathew Hall Lumber Co",
    "wof:placetype":"venue"
},
  "geometry": {"coordinates":[-94.160954,45.562467],"type":"Point"}
}