{
  "type": "Feature",
  "properties": {
    "addr:full":"9130 160th St E Hastings MN 55033",
    "addr:housenumber":"9130",
    "addr:postcode":"55033",
    "addr:street":"160Th St E",
    "iso:country":"US",
    "sg:address":"9130 160th St E",
    "sg:city":"Hastings",
    "sg:phone":"+1 651 437 5819",
    "sg:postcode":"55033",
    "sg:province":"MN",
    "sg:tags":[
        "farm",
        "corn",
        "soybean"
    ],
    "wof:name":"Weiland Service",
    "wof:placetype":"venue"
},
  "geometry": {"coordinates":[-92.924401,44.716825],"type":"Point"}
}