{
  "type": "Feature",
  "properties": {
    "addr:full":"34754 737th Ave Kimball MN 55382",
    "addr:housenumber":"34754",
    "addr:postcode":"55382",
    "addr:street":"737Th Ave",
    "iso:country":"US",
    "sg:address":"34754 737th Ave",
    "sg:city":"Kimball",
    "sg:classifiers":[
        {
            "category":"Education",
            "subcategory":"Special Training",
            "type":"Public Place"
        }
    ],
    "sg:phone":"+1 320 398 7375",
    "sg:postcode":"55382",
    "sg:province":"MN",
    "sg:tags":[
        "management"
    ],
    "sg:website":"www.fastchangeover.com",
    "wof:name":"George Vigoren & Assoc",
    "wof:placetype":"venue"
},
  "geometry": {"coordinates":[-94.281075,45.25002],"type":"Point"}
}