{
  "type": "Feature",
  "properties": {
    "addr:full":"250 Division St N Rice MN 56373",
    "addr:housenumber":"250",
    "addr:postcode":"56373",
    "addr:street":"Division St N",
    "iso:country":"US",
    "sg:address":"250 Division St N",
    "sg:city":"Rice",
    "sg:classifiers":[
        {
            "category":"Retail",
            "subcategory":"Repair Shop",
            "type":"Services"
        }
    ],
    "sg:phone":"+1 320 393 2123",
    "sg:postcode":"56373",
    "sg:province":"MN",
    "sg:tags":[
        "cesspool",
        "cleaning"
    ],
    "wof:name":"Fiedler Cesspool",
    "wof:placetype":"venue"
},
  "geometry": {"coordinates":[-94.221594,45.754501],"type":"Point"}
}