{
  "type": "Feature",
  "properties": {
    "iso:country":"US",
    "sg:address":"9110 W River Rd",
    "sg:city":"Minneapolis",
    "sg:classifiers":[
        {
            "category":"Building & Trades",
            "subcategory":"Cleaning & Sanitation",
            "type":"Services"
        },
        {
            "category":"Home & Garden",
            "subcategory":"Building Materials",
            "type":"Retail Goods"
        },
        {
            "category":"Building & Trades",
            "subcategory":"Construction",
            "type":"Services"
        }
    ],
    "sg:phone":"+1 612 852 8796",
    "sg:postcode":"55444",
    "sg:province":"MN",
    "sg:tags":[
        "concrete-stamped",
        "asphalt",
        "contractor",
        "concrete",
        "decorative",
        "restoration",
        "sealcoating",
        "staining",
        "sealing",
        "paving"
    ],
    "sg:website":"http://www.servicemagic.com/rated.EnduranceConcreteInc.11031594.AllCats.html?m=cahscitysrchxm&entry_point_id=479710",
    "wof:name":"Endurance Concrete, Inc.",
    "wof:placetype":"venue"
},
  "geometry": {"coordinates":[-93.29826799999999,45.119324],"type":"Point"}
}