{
  "type": "Feature",
  "properties": {
    "iso:country":"US",
    "sg:address":"4542 Main St",
    "sg:city":"Pequot Lakes",
    "sg:classifiers":[
        {
            "category":"Shopping",
            "subcategory":"Computers & Home Electronics",
            "type":"Retail Goods"
        }
    ],
    "sg:phone":"+1 218 568 6626",
    "sg:postcode":"56472",
    "sg:province":"MN",
    "sg:tags":[
        "equipment",
        "dealer"
    ],
    "sg:website":"www.cascadecomputers.com",
    "wof:name":"Cascade Computers",
    "wof:placetype":"venue"
},
  "geometry": {"coordinates":[-94.308764,46.602947],"type":"Point"}
}