{
  "type": "Feature",
  "properties": {
    "addr:full":"203 US Hwy 59 Fulda MN 56131",
    "addr:housenumber":"203",
    "addr:postcode":"56131",
    "addr:street":"Us Hwy 59",
    "iso:country":"US",
    "sg:address":"203 US Hwy 59",
    "sg:city":"Fulda",
    "sg:classifiers":[
        {
            "category":"Autos & Motor Vehicles",
            "subcategory":"Auto Supplies",
            "type":"Retail Goods"
        }
    ],
    "sg:phone":"+1 507 425 2318",
    "sg:postcode":"56131",
    "sg:province":"MN",
    "sg:tags":[
        "automobile",
        "parts"
    ],
    "wof:name":"Witzel Pronto Auto Parts",
    "wof:placetype":"venue"
},
  "geometry": {"coordinates":[-95.59251500000001,43.878786],"type":"Point"}
}