{
  "type": "Feature",
  "properties": {
    "addr:full":"668 S Josephine Pl St Paul MN 55116",
    "addr:housenumber":"668",
    "addr:postcode":"55116",
    "addr:street":"S Josephine Pl",
    "iso:country":"US",
    "sg:address":"668 S Josephine Pl",
    "sg:city":"St Paul",
    "sg:classifiers":[
        {
            "category":"Real Estate",
            "subcategory":"Real Estate Agent",
            "type":"Services"
        }
    ],
    "sg:phone":"+1 651 690 3018",
    "sg:postcode":"55116",
    "sg:province":"MN",
    "wof:name":"Highland Realty",
    "wof:placetype":"venue"
},
  "geometry": {"coordinates":[-93.179166,44.921617],"type":"Point"}
}