{
  "type": "Feature",
  "properties": {
    "addr:full":"301 2nd St NW Waseca MN 56093",
    "addr:housenumber":"301",
    "addr:postcode":"56093",
    "addr:street":"2Nd St Nw",
    "iso:country":"US",
    "sg:address":"301 2nd St NW",
    "sg:city":"Waseca",
    "sg:classifiers":[
        {
            "category":"Personal",
            "subcategory":"Beauty Salon",
            "type":"Services"
        }
    ],
    "sg:phone":"+1 507 835 4440",
    "sg:postcode":"56093",
    "sg:province":"MN",
    "sg:tags":[
        "shop"
    ],
    "wof:name":"Magic Mirror Beauty Salon",
    "wof:placetype":"venue"
},
  "geometry": {"coordinates":[-93.50881099999999,44.080808],"type":"Point"}
}