{
  "type": "Feature",
  "properties": {
    "iso:country":"US",
    "sg:address":"1725 St. Mary's St",
    "sg:city":"Falcon Heights",
    "sg:classifiers":[
        {
            "category":"Professional",
            "subcategory":"Art Services",
            "type":"Services"
        }
    ],
    "sg:phone":"+1 612 598 3161",
    "sg:postcode":"55113",
    "sg:province":"MN",
    "sg:tags":[
        "graphic",
        "design"
    ],
    "sg:website":"tianamaedesign.com",
    "wof:name":"Tiana Mae Design",
    "wof:placetype":"venue"
},
  "geometry": {"coordinates":[-93.169269,44.993153],"type":"Point"}
}