{
  "type": "Feature",
  "properties": {
    "iso:country":"US",
    "sg:address":"6780 Green Valley Rd",
    "sg:city":"Anoka",
    "sg:classifiers":[
        {
            "category":"Building & Trades",
            "subcategory":"Construction",
            "type":"Services"
        }
    ],
    "sg:phone":"+1 763 753 5350",
    "sg:postcode":"55303",
    "sg:province":"MN",
    "sg:tags":[
        "house"
    ],
    "wof:name":"Hcr Contracting",
    "wof:placetype":"venue"
},
  "geometry": {"coordinates":[-93.44106600000001,45.291333],"type":"Point"}
}