{
  "type": "Feature",
  "properties": {
    "iso:country":"US",
    "sg:address":"3103 Penn Ave N",
    "sg:city":"Minneapolis",
    "sg:classifiers":[
        {
            "category":"Shopping",
            "subcategory":"Computers & Home Electronics",
            "type":"Retail Goods"
        }
    ],
    "sg:phone":"+1 612 396 9476",
    "sg:postcode":"55411",
    "sg:province":"MN",
    "sg:tags":[
        "consulting",
        "it",
        "sales"
    ],
    "wof:name":"Leefnet Corporation",
    "wof:placetype":"venue"
},
  "geometry": {"coordinates":[-93.308235,45.013241],"type":"Point"}
}