{
  "type": "Feature",
  "properties": {
    "iso:country":"US",
    "sg:address":"1109 Zane Ave N",
    "sg:city":"Minneapolis",
    "sg:classifiers":[
        {
            "category":"Professional",
            "subcategory":"Computer Services",
            "type":"Services"
        }
    ],
    "sg:phone":"+1 763 543 6000",
    "sg:postcode":"55422",
    "sg:province":"MN",
    "sg:tags":[
        "repair"
    ],
    "wof:name":"Express Point Technology",
    "wof:placetype":"venue"
},
  "geometry": {"coordinates":[-93.3554,44.990299],"type":"Point"}
}