{
  "type": "Feature",
  "properties": {
    "addr:full":"206 Kneale Ave S Thief River Fls MN 56701",
    "addr:housenumber":"206",
    "addr:postcode":"56701",
    "addr:street":"Kneale Ave S Thief River Fls",
    "iso:country":"US",
    "sg:address":"206 Kneale Ave S",
    "sg:city":"Thief River Fls",
    "sg:classifiers":[
        {
            "category":"Professional",
            "subcategory":"Business Services",
            "type":"Services"
        }
    ],
    "sg:phone":"+1 218 681 8700",
    "sg:postcode":"56701",
    "sg:province":"MN",
    "wof:name":"Elite Business Concepts Inc",
    "wof:placetype":"venue"
},
  "geometry": {"coordinates":[-96.165204,48.115692],"type":"Point"}
}