{
  "type": "Feature",
  "properties": {
    "addr:full":"1555 Viewcrest Ln Burnsville MN 55306",
    "addr:housenumber":"1555",
    "addr:postcode":"55306",
    "addr:street":"Viewcrest Ln",
    "iso:country":"US",
    "sg:address":"1555 Viewcrest Ln",
    "sg:city":"Burnsville",
    "sg:classifiers":[
        {
            "category":"Banks & Credit Unions",
            "subcategory":"Bank",
            "type":"Services"
        }
    ],
    "sg:phone":"+1 612 749 6567",
    "sg:postcode":"55306",
    "sg:province":"MN",
    "sg:tags":[
        "broker",
        "mortgage"
    ],
    "wof:name":"Wimbley Financial",
    "wof:placetype":"venue"
},
  "geometry": {"coordinates":[-93.299953,44.730048],"type":"Point"}
}