{
  "type": "Feature",
  "properties": {
    "addr:full":"35170 Wadena Line Rd Menahga MN 56464",
    "addr:postcode":"35170;56464",
    "addr:street":"Wadena Line Rd",
    "iso:country":"US",
    "sg:address":"35170 Wadena Line Rd",
    "sg:city":"Menahga",
    "sg:classifiers":[
        {
            "category":"Shopping",
            "type":"Retail Goods"
        }
    ],
    "sg:phone":"+1 218 564 4958",
    "sg:postcode":"56464",
    "sg:province":"MN",
    "sg:tags":[
        "machinery",
        "merchandise"
    ],
    "wof:name":"Dairy Land Equipment",
    "wof:placetype":"venue"
},
  "geometry": {"coordinates":[-95.163669,46.736279],"type":"Point"}
}