{
  "type": "Feature",
  "properties": {
    "iso:country":"US",
    "sg:address":"3841 Saint Francis Blvd",
    "sg:city":"Anoka",
    "sg:classifiers":[
        {
            "category":"Personal",
            "subcategory":"Nail Salon",
            "type":"Services"
        }
    ],
    "sg:phone":"+1 763 427 7782",
    "sg:postcode":"55303",
    "sg:province":"MN",
    "wof:name":"Envy Nails",
    "wof:placetype":"venue"
},
  "geometry": {"coordinates":[-93.395599,45.2225],"type":"Point"}
}