{
  "type": "Feature",
  "properties": {
    "addr:full":"801 Willmar Ave SW Willmar MN 56201",
    "addr:housenumber":"801",
    "addr:postcode":"56201",
    "addr:street":"Willmar Ave Sw",
    "iso:country":"US",
    "sg:address":"801 Willmar Ave SW",
    "sg:city":"Willmar",
    "sg:classifiers":[
        {
            "category":"Organizations",
            "subcategory":"Religious Organization",
            "type":"Services"
        }
    ],
    "sg:phone":"+1 320 235 3010",
    "sg:postcode":"56201",
    "sg:province":"MN",
    "sg:website":"www.fccwillmar.org",
    "wof:name":"First Covenant Church",
    "wof:placetype":"venue"
},
  "geometry": {"coordinates":[-95.05289999999999,45.110624],"type":"Point"}
}