{
  "type": "Feature",
  "properties": {
    "addr:full":"105 W Main St Kasson MN 55944",
    "addr:housenumber":"105",
    "addr:postcode":"55944",
    "addr:street":"W Main St",
    "iso:country":"US",
    "sg:address":"105 W Main St",
    "sg:city":"Kasson",
    "sg:classifiers":[
        {
            "category":"Professional",
            "subcategory":"Accounting & Tax Preparation",
            "type":"Services"
        }
    ],
    "sg:phone":"+1 507 634 7606",
    "sg:postcode":"55944",
    "sg:province":"MN",
    "sg:tags":[
        "return",
        "filing"
    ],
    "wof:name":"Jensen Tax Preparation",
    "wof:placetype":"venue"
},
  "geometry": {"coordinates":[-92.750725,44.029558],"type":"Point"}
}