{
  "type": "Feature",
  "properties": {
    "iso:country":"US",
    "sg:address":"21987 Garfield Ave",
    "sg:city":"Morristown",
    "sg:classifiers":[
        {
            "category":"Farming",
            "subcategory":"Livestock Farm",
            "type":"Manufacturing & Wholesale Goods"
        }
    ],
    "sg:phone":"+1 507 334 8075",
    "sg:postcode":"55052",
    "sg:province":"MN",
    "sg:tags":[
        "beef",
        "feedlot",
        "cattle"
    ],
    "wof:name":"Glenn Borchert",
    "wof:placetype":"venue"
},
  "geometry": {"coordinates":[-93.40357299999999,44.26904],"type":"Point"}
}