{
  "type": "Feature",
  "properties": {
    "addr:full":"14668 Valley Creek Trl Afton MN 55001",
    "addr:housenumber":"14668",
    "addr:postcode":"55001",
    "addr:street":"Valley Creek Trl",
    "iso:country":"US",
    "sg:address":"14668 Valley Creek Trl",
    "sg:city":"Afton",
    "sg:classifiers":[
        {
            "category":"Wholesale",
            "subcategory":"Electrical",
            "type":"Manufacturing & Wholesale Goods"
        }
    ],
    "sg:phone":"+1 651 436 7841",
    "sg:postcode":"55001",
    "sg:province":"MN",
    "sg:tags":[
        "electronic"
    ],
    "wof:name":"System Solutions",
    "wof:placetype":"venue"
},
  "geometry": {"coordinates":[-92.807804,44.917216],"type":"Point"}
}