{
  "type": "Feature",
  "properties": {
    "addr:full":"76906 Petersburg Rd Jackson MN 56143",
    "addr:postcode":"76906;56143",
    "addr:street":"Petersburg Rd",
    "iso:country":"US",
    "sg:address":"76906 Petersburg Rd",
    "sg:city":"Jackson",
    "sg:classifiers":[
        {
            "category":"Real Estate",
            "subcategory":"Real Estate Agent",
            "type":"Services"
        }
    ],
    "sg:phone":"+1 507 847 2104",
    "sg:postcode":"56143",
    "sg:province":"MN",
    "wof:name":"Stan Sievert Agency",
    "wof:placetype":"venue"
},
  "geometry": {"coordinates":[-94.982024,43.602505],"type":"Point"}
}