{
  "type": "Feature",
  "properties": {
    "iso:country":"US",
    "sg:address":"17741 Co Rd 11",
    "sg:city":"Crosby",
    "sg:classifiers":[
        {
            "category":"Professional",
            "subcategory":"Business Services",
            "type":"Services"
        }
    ],
    "sg:phone":"+1 218 546 6510",
    "sg:postcode":"56441",
    "sg:province":"MN",
    "sg:tags":[
        "embroidery"
    ],
    "wof:name":"Northwoods Embroidery",
    "wof:placetype":"venue"
},
  "geometry": {"coordinates":[-94.035968,46.576058],"type":"Point"}
}