{
  "type": "Feature",
  "properties": {
    "addr:full":"4250 Otter Lake Rd St Paul MN 55110",
    "addr:housenumber":"4250",
    "addr:postcode":"55110",
    "addr:street":"Otter Lake Rd",
    "iso:country":"US",
    "sg:address":"4250 Otter Lake Rd",
    "sg:city":"St Paul",
    "sg:classifiers":[
        {
            "category":"Wholesale",
            "subcategory":"Construction Materials",
            "type":"Manufacturing & Wholesale Goods"
        }
    ],
    "sg:phone":"+1 651 407 2800",
    "sg:postcode":"55110",
    "sg:province":"MN",
    "sg:tags":[
        "hardwood",
        "lumber",
        "m"
    ],
    "sg:website":"www.scvh.com",
    "wof:name":"St Croix Valley Hardwoods Inc",
    "wof:placetype":"venue"
},
  "geometry": {"coordinates":[-93.031329,45.06945],"type":"Point"}
}