{
  "type": "Feature",
  "properties": {
    "addr:full":"208 1st Ave S Brownton MN 55312",
    "addr:housenumber":"208",
    "addr:postcode":"55312",
    "addr:street":"1St Ave S Brownton",
    "iso:country":"US",
    "sg:address":"208 1st Ave S",
    "sg:city":"Brownton",
    "sg:classifiers":[
        {
            "category":"Building & Trades",
            "subcategory":"Construction",
            "type":"Services"
        }
    ],
    "sg:phone":"+1 320 328 5317",
    "sg:postcode":"55312",
    "sg:province":"MN",
    "sg:tags":[
        "grading",
        "contractor"
    ],
    "wof:name":"Highway Dept-Garage",
    "wof:placetype":"venue"
},
  "geometry": {"coordinates":[-94.355924,44.730652],"type":"Point"}
}