{
  "type": "Feature",
  "properties": {
    "addr:full":"2497 7th St W St Paul MN 55116",
    "addr:housenumber":"2497",
    "addr:postcode":"55116",
    "addr:street":"7Th St W",
    "iso:country":"US",
    "sg:address":"2497 7th St W",
    "sg:city":"St Paul",
    "sg:classifiers":[
        {
            "category":"Professional",
            "subcategory":"Business Services",
            "type":"Services"
        }
    ],
    "sg:phone":"+1 651 699 9434",
    "sg:postcode":"55116",
    "sg:province":"MN",
    "sg:tags":[
        "liquidator"
    ],
    "wof:name":"National Liquidators Of Hotel",
    "wof:placetype":"venue"
},
  "geometry": {"coordinates":[-93.16935100000001,44.902602],"type":"Point"}
}