{
  "type": "Feature",
  "properties": {
    "iso:country":"US",
    "sg:address":"366 E George St",
    "sg:city":"Ivanhoe",
    "sg:classifiers":[
        {
            "category":"Professional",
            "type":"Services"
        }
    ],
    "sg:phone":"+1 507 694 1658",
    "sg:postcode":"56142",
    "sg:province":"MN",
    "sg:tags":[
        "establishment"
    ],
    "wof:name":"Western Human Development Ctr",
    "wof:placetype":"venue"
},
  "geometry": {"coordinates":[-96.24226400000001,44.459177],"type":"Point"}
}