{
  "type": "Feature",
  "properties": {
    "iso:country":"US",
    "sg:address":"650 Parker Ave W",
    "sg:city":"Dassel",
    "sg:classifiers":[
        {
            "category":"Professional",
            "subcategory":"Accounting & Tax Preparation",
            "type":"Services"
        }
    ],
    "sg:phone":"+1 320 275 3387",
    "sg:postcode":"55325",
    "sg:province":"MN",
    "sg:tags":[
        "accountant",
        "return"
    ],
    "wof:name":"Gordon Donald Accounting",
    "wof:placetype":"venue"
},
  "geometry": {"coordinates":[-94.31769199999999,45.080873],"type":"Point"}
}