{
  "type": "Feature",
  "properties": {
    "iso:country":"US",
    "sg:address":"1515 5th St S",
    "sg:city":"Hopkins",
    "sg:classifiers":[
        {
            "category":"Building & Trades",
            "subcategory":"Plumbing",
            "type":"Services"
        }
    ],
    "sg:phone":"+1 952 938 3143",
    "sg:postcode":"55343",
    "sg:province":"MN",
    "sg:tags":[
        "plumbing",
        "contractor"
    ],
    "wof:name":"Voson Plumbing Inc",
    "wof:placetype":"venue"
},
  "geometry": {"coordinates":[-93.420658,44.917196],"type":"Point"}
}