{
  "type": "Feature",
  "properties": {
    "addr:full":"16302 Pleasant Valley Rd Caledonia MN 55921",
    "addr:housenumber":"16302",
    "addr:postcode":"55921",
    "addr:street":"Pleasant Valley Rd",
    "iso:country":"US",
    "sg:address":"16302 Pleasant Valley Rd",
    "sg:city":"Caledonia",
    "sg:classifiers":[
        {
            "category":"Farming",
            "subcategory":"Livestock Farm",
            "type":"Manufacturing & Wholesale Goods"
        }
    ],
    "sg:phone":"+1 507 724 2962",
    "sg:postcode":"55921",
    "sg:province":"MN",
    "sg:tags":[
        "beef",
        "feedlot",
        "cattle"
    ],
    "wof:name":"Lampert Farms",
    "wof:placetype":"venue"
},
  "geometry": {"coordinates":[-91.36855799999999,43.611509],"type":"Point"}
}