{
  "type": "Feature",
  "properties": {
    "iso:country":"US",
    "sg:address":"101 22nd St SE",
    "sg:city":"Owatonna",
    "sg:classifiers":[
        {
            "category":"Professional",
            "type":"Services"
        }
    ],
    "sg:phone":"+1 507 455 1750",
    "sg:postcode":"55060",
    "sg:province":"MN",
    "sg:tags":[
        "establishment"
    ],
    "wof:name":"Sterling Drug",
    "wof:placetype":"venue"
},
  "geometry": {"coordinates":[-93.226102,44.061805],"type":"Point"}
}