{
  "type": "Feature",
  "properties": {
    "iso:country":"US",
    "sg:address":"1021 74th St",
    "sg:city":"Victoria",
    "sg:classifiers":[
        {
            "category":"Professional",
            "type":"Services"
        }
    ],
    "sg:phone":"+1 952 443 2209",
    "sg:postcode":"55386",
    "sg:province":"MN",
    "sg:tags":[
        "establishment"
    ],
    "wof:name":"Hdc Companies",
    "wof:placetype":"venue"
},
  "geometry": {"coordinates":[-93.64612200000001,44.869863],"type":"Point"}
}