{
  "type": "Feature",
  "properties": {
    "addr:full":"3800 Silver Lake Rd NE Minneapolis MN 55421",
    "addr:housenumber":"3800",
    "addr:postcode":"55421",
    "addr:street":"Silver Lake Rd Ne",
    "iso:country":"US",
    "sg:address":"3800 Silver Lake Rd NE",
    "sg:city":"Minneapolis",
    "sg:classifiers":[
        {
            "category":"Shopping",
            "subcategory":"Department Store",
            "type":"Retail Goods"
        }
    ],
    "sg:phone":"+1 763 789 2422",
    "sg:postcode":"55421",
    "sg:province":"MN",
    "wof:name":"Herbergers",
    "wof:placetype":"venue"
},
  "geometry": {"coordinates":[-93.2182,45.038656],"type":"Point"}
}