{
  "type": "Feature",
  "properties": {
    "iso:country":"US",
    "sg:address":"438 1st St SE",
    "sg:city":"Avon",
    "sg:classifiers":[
        {
            "category":"Personal",
            "subcategory":"Beauty Salon",
            "type":"Services"
        }
    ],
    "sg:phone":"+1 320 356 9002",
    "sg:postcode":"56310",
    "sg:province":"MN",
    "wof:name":"Country Classics Spa",
    "wof:placetype":"venue"
},
  "geometry": {"coordinates":[-94.446088,45.606229],"type":"Point"}
}