{
  "type": "Feature",
  "properties": {
    "addr:full":"120 N McKenzie St Luverne MN 56156",
    "addr:housenumber":"120",
    "addr:postcode":"56156",
    "addr:street":"N Mckenzie St",
    "iso:country":"US",
    "sg:address":"120 N McKenzie St",
    "sg:city":"Luverne",
    "sg:classifiers":[
        {
            "category":"Professional",
            "subcategory":"Lawyer & Legal Services",
            "type":"Services"
        }
    ],
    "sg:phone":"+1 507 283 9111",
    "sg:postcode":"56156",
    "sg:province":"MN",
    "wof:name":"Law Offcs Skewes Klosterbuer",
    "wof:placetype":"venue"
},
  "geometry": {"coordinates":[-96.206467,43.655007],"type":"Point"}
}