{
  "type": "Feature",
  "properties": {
    "iso:country":"US",
    "sg:address":"5910 236th Ave NW",
    "sg:city":"Saint Francis",
    "sg:classifiers":[
        {
            "category":"Retail",
            "subcategory":"Repair Shop",
            "type":"Services"
        }
    ],
    "sg:phone":"+1 763 753 1022",
    "sg:postcode":"55070",
    "sg:province":"MN",
    "wof:name":"Hemis Mobile Locksmith",
    "wof:placetype":"venue"
},
  "geometry": {"coordinates":[-93.416753,45.397164],"type":"Point"}
}