{
  "type": "Feature",
  "properties": {
    "addr:full":"10514 Lancaster Ln N Osseo MN 55369",
    "addr:housenumber":"10514",
    "addr:postcode":"55369",
    "addr:street":"Lancaster Ln N",
    "iso:country":"US",
    "sg:address":"10514 Lancaster Ln N",
    "sg:city":"Osseo",
    "sg:classifiers":[
        {
            "category":"Manufacturing",
            "subcategory":"Tools & Machinery",
            "type":"Manufacturing & Wholesale Goods"
        }
    ],
    "sg:phone":"+1 763 493 2635",
    "sg:postcode":"55369",
    "sg:province":"MN",
    "sg:tags":[
        "assembles",
        "computer",
        "doe"
    ],
    "wof:name":"Advanced Microsystems",
    "wof:placetype":"venue"
},
  "geometry": {"coordinates":[-93.402311,45.14615],"type":"Point"}
}