{
  "type": "Feature",
  "properties": {
    "iso:country":"US",
    "sg:address":"313 3rd St",
    "sg:city":"Tracy",
    "sg:phone":"+1 507 629 4468",
    "sg:postcode":"56175",
    "sg:province":"MN",
    "sg:tags":[
        "farm",
        "corn",
        "soybean"
    ],
    "wof:name":"Arlen Thomas",
    "wof:placetype":"venue"
},
  "geometry": {"coordinates":[-95.617796,44.2352],"type":"Point"}
}