{
  "type": "Feature",
  "properties": {
    "addr:full":"6599 261st Ave NW St Francis MN 55070",
    "addr:housenumber":"6599",
    "addr:postcode":"55070",
    "addr:street":"261St Ave Nw St Francis",
    "iso:country":"US",
    "sg:address":"6599 261st Ave NW",
    "sg:city":"St Francis",
    "sg:classifiers":[
        {
            "category":"Recreation",
            "type":"Entertainment"
        }
    ],
    "sg:phone":"+1 763 444 6722",
    "sg:postcode":"55070",
    "sg:province":"MN",
    "sg:tags":[
        "stable"
    ],
    "wof:name":"Manahan Stables",
    "wof:placetype":"venue"
},
  "geometry": {"coordinates":[-93.43275,45.442603],"type":"Point"}
}