{
  "type": "Feature",
  "properties": {
    "addr:full":"1911 Woodstone Ln Victoria MN 55386",
    "addr:housenumber":"1911",
    "addr:postcode":"55386",
    "addr:street":"Woodstone Ln",
    "iso:country":"US",
    "sg:address":"1911 Woodstone Ln",
    "sg:city":"Victoria",
    "sg:classifiers":[
        {
            "category":"Manufacturing",
            "subcategory":"Buildings",
            "type":"Manufacturing & Wholesale Goods"
        },
        {
            "category":"Building & Trades",
            "subcategory":"Construction",
            "type":"Services"
        }
    ],
    "sg:phone":"+1 952 443 0191",
    "sg:postcode":"55386",
    "sg:province":"MN",
    "sg:tags":[
        "industrial",
        "specialty",
        "builder",
        "heating",
        "contractor",
        "contractors-commercial",
        "home"
    ],
    "sg:website":"http://www.pathanilyassoc.com",
    "wof:name":"Hanily & Associates Inc Patrick",
    "wof:placetype":"venue"
},
  "geometry": {"coordinates":[-93.665802,44.849499],"type":"Point"}
}