{
  "type": "Feature",
  "properties": {
    "iso:country":"US",
    "sg:address":"2501 E 22nd St",
    "sg:city":"Minneapolis",
    "sg:classifiers":[
        {
            "category":"Place Of Worship",
            "type":"Public Place"
        }
    ],
    "sg:phone":"+1 612 724 6701",
    "sg:postcode":"55406",
    "sg:province":"MN",
    "sg:tags":[
        "church"
    ],
    "wof:name":"Emmanuel Tabernacle",
    "wof:placetype":"venue"
},
  "geometry": {"coordinates":[-93.236183,44.96096],"type":"Point"}
}