{
  "type": "Feature",
  "properties": {
    "addr:full":"9670 Colorado Ln N Minneapolis MN 55445",
    "addr:housenumber":"9670",
    "addr:postcode":"55445",
    "addr:street":"Colorado Ln N",
    "iso:country":"US",
    "sg:address":"9670 Colorado Ln N",
    "sg:city":"Minneapolis",
    "sg:classifiers":[
        {
            "category":"Restaurant",
            "type":"Food & Drink"
        }
    ],
    "sg:phone":"+1 763 424 9944",
    "sg:postcode":"55445",
    "sg:province":"MN",
    "sg:tags":[
        "pizza"
    ],
    "sg:website":"www.jimmyjohns.com",
    "wof:name":"Jimmy John's",
    "wof:placetype":"venue"
},
  "geometry": {"coordinates":[-93.36040300000001,45.13508],"type":"Point"}
}