{
  "type": "Feature",
  "properties": {
    "addr:full":"7731 Kentucky Cir N Minneapolis MN 55445",
    "addr:housenumber":"7731",
    "addr:postcode":"55445",
    "addr:street":"Kentucky Cir N",
    "iso:country":"US",
    "sg:address":"7731 Kentucky Cir N",
    "sg:city":"Minneapolis",
    "sg:classifiers":[
        {
            "category":"Shopping",
            "subcategory":"Pets & Pet Supplies",
            "type":"Retail Goods"
        },
        {
            "category":"Retail",
            "subcategory":"Animal Services",
            "type":"Services"
        }
    ],
    "sg:phone":"+1 763 424 2479",
    "sg:postcode":"55445",
    "sg:province":"MN",
    "sg:tags":[
        "grooming",
        "dog",
        "cat"
    ],
    "wof:name":"K9 Paws Grooming",
    "wof:placetype":"venue"
},
  "geometry": {"coordinates":[-93.373491,45.095411],"type":"Point"}
}