{
  "type": "Feature",
  "properties": {
    "addr:full":"1165 COLUMBIA RD S GR FKS Crookston MN 56716",
    "addr:housenumber":"1165",
    "addr:postcode":"56716",
    "addr:street":"Columbia Rd",
    "iso:country":"US",
    "sg:address":"1165 COLUMBIA RD S GR FKS",
    "sg:city":"Crookston",
    "sg:classifiers":[
        {
            "category":"Health Services",
            "subcategory":"Dentist",
            "type":"Services"
        }
    ],
    "sg:phone":"+1 800 637 6445",
    "sg:postcode":"56716",
    "sg:province":"MN",
    "wof:name":"Frokjer Greg DDS",
    "wof:placetype":"venue"
},
  "geometry": {"coordinates":[-96.630871,48.118229],"type":"Point"}
}