{
  "type": "Feature",
  "properties": {
    "addr:full":"6077 640th Ave Wheaton MN 56296",
    "addr:housenumber":"6077",
    "addr:postcode":"56296",
    "addr:street":"640Th Ave",
    "iso:country":"US",
    "sg:address":"6077 640th Ave",
    "sg:city":"Wheaton",
    "sg:classifiers":[
        {
            "category":"Manufacturing",
            "subcategory":"Food",
            "type":"Manufacturing & Wholesale Goods"
        },
        {
            "category":"Farming",
            "subcategory":"Farm",
            "type":"Manufacturing & Wholesale Goods"
        }
    ],
    "sg:phone":"+1 320 563 4494",
    "sg:postcode":"56296",
    "sg:province":"MN",
    "sg:tags":[
        "corn",
        "product"
    ],
    "wof:name":"Quinton Kracht Farm",
    "wof:placetype":"venue"
},
  "geometry": {"coordinates":[-96.552153,45.740959],"type":"Point"}
}