{
  "type": "Feature",
  "properties": {
    "addr:full":"1400 Cedar Ln Newport MN 55055",
    "addr:housenumber":"1400",
    "addr:postcode":"55055",
    "addr:street":"Cedar Ln",
    "iso:country":"US",
    "sg:address":"1400 Cedar Ln",
    "sg:city":"Newport",
    "sg:classifiers":[
        {
            "category":"Home & Garden",
            "subcategory":"Carpets & Floor Coverings",
            "type":"Retail Goods"
        },
        {
            "category":"Building & Trades",
            "subcategory":"Construction",
            "type":"Services"
        }
    ],
    "sg:phone":"+1 651 769 1180",
    "sg:postcode":"55055",
    "sg:province":"MN",
    "sg:tags":[
        "tile",
        "dealer"
    ],
    "wof:name":"Superior Floor Covering Inc",
    "wof:placetype":"venue"
},
  "geometry": {"coordinates":[-93.007599,44.869772],"type":"Point"}
}