{
  "type": "Feature",
  "properties": {
    "addr:full":"4736 McDonald Drive Pl N Stillwater MN 55082",
    "addr:housenumber":"4736",
    "addr:postcode":"55082",
    "addr:street":"Mcdonald Drive Pl N",
    "iso:country":"US",
    "sg:address":"4736 McDonald Drive Pl N",
    "sg:city":"Stillwater",
    "sg:classifiers":[
        {
            "category":"Professional",
            "subcategory":"Management & Consulting",
            "type":"Services"
        }
    ],
    "sg:phone":"+1 651 351 7225",
    "sg:postcode":"55082",
    "sg:province":"MN",
    "wof:name":"Sage Health",
    "wof:placetype":"venue"
},
  "geometry": {"coordinates":[-92.855208,45.015888],"type":"Point"}
}