{
  "type": "Feature",
  "properties": {
    "iso:country":"US",
    "sg:address":"3843 Co Rd 4",
    "sg:city":"Mahtowa",
    "sg:classifiers":[
        {
            "category":"Building & Trades",
            "subcategory":"Construction",
            "type":"Services"
        }
    ],
    "sg:phone":"+1 218 389 6973",
    "sg:postcode":"55718",
    "sg:province":"MN",
    "sg:tags":[
        "concrete",
        "contractor"
    ],
    "wof:name":"Cutting Edge Construction",
    "wof:placetype":"venue"
},
  "geometry": {"coordinates":[-92.71339999999999,46.59187],"type":"Point"}
}