{
  "type": "Feature",
  "properties": {
    "iso:country":"US",
    "sg:address":"18315 Erkium St NW",
    "sg:city":"Anoka",
    "sg:classifiers":[
        {
            "category":"Home & Garden",
            "subcategory":"Home Furnishings",
            "type":"Retail Goods"
        }
    ],
    "sg:phone":"+1 763 753 3512",
    "sg:postcode":"55303",
    "sg:province":"MN",
    "wof:name":"Home Interiors-Anoka",
    "wof:placetype":"venue"
},
  "geometry": {"coordinates":[-93.405173,45.302157],"type":"Point"}
}