{
  "type": "Feature",
  "properties": {
    "iso:country":"US",
    "sg:address":"12 Minnesota Ave N",
    "sg:city":"Aitkin",
    "sg:classifiers":[
        {
            "category":"Autos & Motor Vehicles",
            "subcategory":"Automobile Sales",
            "type":"Retail Goods"
        }
    ],
    "sg:phone":"+1 218 927 2713",
    "sg:postcode":"56431",
    "sg:province":"MN",
    "sg:tags":[
        "car",
        "dealer"
    ],
    "sg:website":"www.macdonaldwold.com",
    "wof:name":"Mac Donald-WOLD Inc",
    "wof:placetype":"venue"
},
  "geometry": {"coordinates":[-93.706489,46.532293],"type":"Point"}
}