{
  "type": "Feature",
  "properties": {
    "addr:full":"1101 Hillock St Isanti MN 55040",
    "addr:housenumber":"1101",
    "addr:postcode":"55040",
    "addr:street":"Hillock St",
    "iso:country":"US",
    "sg:address":"1101 Hillock St",
    "sg:city":"Isanti",
    "sg:classifiers":[
        {
            "category":"Building & Trades",
            "subcategory":"Electrical",
            "type":"Services"
        }
    ],
    "sg:phone":"+1 763 300 0487",
    "sg:postcode":"55040",
    "sg:province":"MN",
    "sg:tags":[
        "electrician"
    ],
    "wof:name":"Ultimate Controls Electric",
    "wof:placetype":"venue"
},
  "geometry": {"coordinates":[-93.26282500000001,45.496209],"type":"Point"}
}