{
  "type": "Feature",
  "properties": {
    "addr:full":"7125 151st St W Saint Paul MN 55124",
    "addr:housenumber":"7125",
    "addr:postcode":"55124",
    "addr:street":"151St St W",
    "iso:country":"US",
    "sg:address":"7125 151st St W",
    "sg:city":"Saint Paul",
    "sg:classifiers":[
        {
            "category":"Autos & Motor Vehicles",
            "subcategory":"Auto Supplies",
            "type":"Retail Goods"
        },
        {
            "category":"Retail",
            "subcategory":"Auto Repair",
            "type":"Services"
        }
    ],
    "sg:phone":"+1 952 431 2700",
    "sg:postcode":"55124",
    "sg:province":"MN",
    "sg:tags":[
        "tire"
    ],
    "wof:name":"Mr Tire Valley Care Care",
    "wof:placetype":"venue"
},
  "geometry": {"coordinates":[-93.209999,44.730598],"type":"Point"}
}