{
  "type": "Feature",
  "properties": {
    "addr:full":"1615 London Rd Duluth MN 55812",
    "addr:housenumber":"1615",
    "addr:postcode":"55812",
    "addr:street":"London Rd",
    "iso:country":"US",
    "sg:address":"1615 London Rd",
    "sg:city":"Duluth",
    "sg:classifiers":[
        {
            "category":"Personal",
            "subcategory":"Beauty Salon",
            "type":"Services"
        }
    ],
    "sg:phone":"+1 218 728 5111",
    "sg:postcode":"55812",
    "sg:province":"MN",
    "sg:tags":[
        "shop"
    ],
    "wof:name":"Hanenburg Fay",
    "wof:placetype":"venue"
},
  "geometry": {"coordinates":[-92.07507200000001,46.801479],"type":"Point"}
}