{
  "type": "Feature",
  "properties": {
    "addr:full":"7000 18th Ave S Minneapolis MN 55423",
    "addr:housenumber":"7000",
    "addr:postcode":"55423",
    "addr:street":"18Th Ave S",
    "iso:country":"US",
    "sg:address":"7000 18th Ave S",
    "sg:city":"Minneapolis",
    "sg:classifiers":[
        {
            "category":"Building & Trades",
            "subcategory":"Construction",
            "type":"Services"
        }
    ],
    "sg:phone":"+1 612 866 2935",
    "sg:postcode":"55423",
    "sg:province":"MN",
    "sg:tags":[
        "contractor"
    ],
    "wof:name":"Midwest Woodworking",
    "wof:placetype":"venue"
},
  "geometry": {"coordinates":[-93.24897799999999,44.875797],"type":"Point"}
}