{
  "type": "Feature",
  "properties": {
    "addr:full":"14770 14th St N Stillwater MN 55082",
    "addr:housenumber":"14770",
    "addr:postcode":"55082",
    "addr:street":"14Th St N",
    "iso:country":"US",
    "sg:address":"14770 14th St N",
    "sg:city":"Stillwater",
    "sg:classifiers":[
        {
            "category":"Retail",
            "subcategory":"Self-service Laundry",
            "type":"Services"
        }
    ],
    "sg:phone":"+1 651 998 1259",
    "sg:postcode":"55082",
    "sg:province":"MN",
    "sg:tags":[
        "coin"
    ],
    "wof:name":"Speedwash Inc",
    "wof:placetype":"venue"
},
  "geometry": {"coordinates":[-92.806459,44.968166],"type":"Point"}
}