{
  "type": "Feature",
  "properties": {
    "iso:country":"US",
    "sg:address":"1160 Cushing Cir",
    "sg:city":"Saint Paul",
    "sg:classifiers":[
        {
            "category":"Shopping",
            "subcategory":"Shoes",
            "type":"Retail Goods"
        }
    ],
    "sg:phone":"+1 651 644 1557",
    "sg:postcode":"55108",
    "sg:province":"MN",
    "wof:name":"Lace-Em-Up Athletic Shoes",
    "wof:placetype":"venue"
},
  "geometry": {"coordinates":[-93.148697,44.97255],"type":"Point"}
}