{
  "type": "Feature",
  "properties": {
    "iso:country":"US",
    "sg:address":"3400 Parklawn Ave",
    "sg:city":"Minneapolis",
    "sg:classifiers":[
        {
            "category":"Real Estate",
            "subcategory":"Real Estate Operator",
            "type":"Services"
        }
    ],
    "sg:phone":"+1 952 831 3372",
    "sg:postcode":"55435",
    "sg:province":"MN",
    "sg:tags":[
        "building",
        "apartment"
    ],
    "wof:name":"Southhaven",
    "wof:placetype":"venue"
},
  "geometry": {"coordinates":[-93.323139,44.868291],"type":"Point"}
}