{
  "type": "Feature",
  "properties": {
    "iso:country":"US",
    "sg:address":"2000 Oakdale Ave",
    "sg:city":"Saint Paul",
    "sg:classifiers":[
        {
            "category":"Health Services",
            "subcategory":"Nursing And Care Facility",
            "type":"Services"
        }
    ],
    "sg:phone":"+1 651 451 1821",
    "sg:postcode":"55118",
    "sg:province":"MN",
    "sg:tags":[
        "home",
        "skilled",
        "convalescent"
    ],
    "wof:name":"Southview Acres Hlth Care Ctr",
    "wof:placetype":"venue"
},
  "geometry": {"coordinates":[-93.07033,44.884785],"type":"Point"}
}