{
  "type": "Feature",
  "properties": {
    "addr:full":"2438 117th St E Burnsville MN 55337",
    "addr:housenumber":"2438",
    "addr:postcode":"55337",
    "addr:street":"117Th St",
    "iso:country":"US",
    "sg:address":"2438 117th St E",
    "sg:city":"Burnsville",
    "sg:classifiers":[
        {
            "category":"Organizations",
            "subcategory":"Professional Association",
            "type":"Services"
        }
    ],
    "sg:phone":"+1 952 895 8765",
    "sg:postcode":"55337",
    "sg:province":"MN",
    "wof:name":"National Fleet Network",
    "wof:placetype":"venue"
},
  "geometry": {"coordinates":[-93.24185300000001,44.793813],"type":"Point"}
}