{
  "type": "Feature",
  "properties": {
    "addr:full":"22770 347th St SE Erskine MN 56535",
    "addr:housenumber":"22770",
    "addr:postcode":"56535",
    "addr:street":"347Th St Se",
    "iso:country":"US",
    "sg:address":"22770 347th St SE",
    "sg:city":"Erskine",
    "sg:classifiers":[
        {
            "category":"Wholesale",
            "subcategory":"Poultry",
            "type":"Manufacturing & Wholesale Goods"
        },
        {
            "category":"Farming",
            "subcategory":"Livestock Farm",
            "type":"Manufacturing & Wholesale Goods"
        }
    ],
    "sg:phone":"+1 218 687 3651",
    "sg:postcode":"56535",
    "sg:province":"MN",
    "sg:tags":[
        "buyer",
        "auction",
        "ranch",
        "market"
    ],
    "sg:website":"http://www.easywaycattlecare.com",
    "wof:name":"Easy Way Cattle Care",
    "wof:placetype":"venue"
},
  "geometry": {"coordinates":[-95.985201,47.662201],"type":"Point"}
}