{
  "type": "Feature",
  "properties": {
    "iso:country":"US",
    "sg:address":"502 N Faxon Rd",
    "sg:city":"Norwood",
    "sg:classifiers":[
        {
            "category":"Food & Beverages",
            "subcategory":"Groceries & Convenience Stores",
            "type":"Retail Goods"
        }
    ],
    "sg:phone":"+1 952 467 3075",
    "sg:postcode":"55368",
    "sg:province":"MN",
    "wof:name":"Short Stop",
    "wof:placetype":"venue"
},
  "geometry": {"coordinates":[-93.919607,44.7708],"type":"Point"}
}