{
  "type": "Feature",
  "properties": {
    "iso:country":"US",
    "sg:address":"13036 378th St",
    "sg:city":"Menahga",
    "sg:classifiers":[
        {
            "category":"Retail",
            "subcategory":"Auto Repair",
            "type":"Services"
        }
    ],
    "sg:phone":"+1 218 564 4055",
    "sg:postcode":"56464",
    "sg:province":"MN",
    "sg:tags":[
        "general"
    ],
    "wof:name":"Herbet J McCormick",
    "wof:placetype":"venue"
},
  "geometry": {"coordinates":[-95.103945,46.772683],"type":"Point"}
}