{
  "type": "Feature",
  "properties": {
    "addr:full":"410 Main Ave N Harmony MN 55939",
    "addr:housenumber":"410",
    "addr:postcode":"55939",
    "addr:street":"Main Ave N",
    "iso:country":"US",
    "sg:address":"410 Main Ave N",
    "sg:city":"Harmony",
    "sg:classifiers":[
        {
            "category":"Real Estate",
            "subcategory":"Real Estate Agent",
            "type":"Services"
        }
    ],
    "sg:phone":"+1 507 886 5263",
    "sg:postcode":"55939",
    "sg:province":"MN",
    "wof:name":"Bluff Country Real Estate",
    "wof:placetype":"venue"
},
  "geometry": {"coordinates":[-92.009873,43.55893],"type":"Point"}
}