{
  "type": "Feature",
  "properties": {
    "iso:country":"US",
    "sg:address":"135 W Winona Ave",
    "sg:city":"Kellogg",
    "sg:classifiers":[
        {
            "category":"Professional",
            "subcategory":"Computer Services",
            "type":"Services"
        }
    ],
    "sg:phone":"+1 507 767 4962",
    "sg:postcode":"55945",
    "sg:province":"MN",
    "sg:tags":[
        "programing",
        "custom"
    ],
    "wof:name":"Deep River Design",
    "wof:placetype":"venue"
},
  "geometry": {"coordinates":[-92.000017,44.308758],"type":"Point"}
}