{
  "type": "Feature",
  "properties": {
    "addr:full":"239 7th St W Saint Paul MN 55102",
    "addr:housenumber":"239",
    "addr:postcode":"55102",
    "addr:street":"7Th St W",
    "iso:country":"US",
    "sg:address":"239 7th St W",
    "sg:city":"Saint Paul",
    "sg:classifiers":[
        {
            "category":"Professional",
            "subcategory":"Advertising",
            "type":"Services"
        }
    ],
    "sg:phone":"+1 651 292 1185",
    "sg:postcode":"55102",
    "sg:province":"MN",
    "wof:name":"Wholesale Imprints Promotions",
    "wof:placetype":"venue"
},
  "geometry": {"coordinates":[-93.10492000000001,44.942943],"type":"Point"}
}