{
  "type": "Feature",
  "properties": {
    "addr:full":"2445 Humboldt Ave S Minneapolis MN 55405",
    "addr:housenumber":"2445",
    "addr:postcode":"55405",
    "addr:street":"Humboldt Ave S",
    "iso:country":"US",
    "sg:address":"2445 Humboldt Ave S",
    "sg:city":"Minneapolis",
    "sg:classifiers":[
        {
            "category":"Professional",
            "subcategory":"Management & Consulting",
            "type":"Services"
        }
    ],
    "sg:phone":"+1 612 381 9737",
    "sg:postcode":"55405",
    "sg:province":"MN",
    "sg:tags":[
        "consultant",
        "medical",
        "practice",
        "health",
        "hospital"
    ],
    "wof:name":"Alexander Rothman",
    "wof:placetype":"venue"
},
  "geometry": {"coordinates":[-93.298187,44.958307],"type":"Point"}
}