{
  "type": "Feature",
  "properties": {
    "iso:country":"US",
    "sg:address":"3100 W Lake St Ste 210",
    "sg:city":"Minneapolis",
    "sg:classifiers":[
        {
            "category":"Education",
            "subcategory":"School",
            "type":"Public Place"
        },
        {
            "category":"Sports & Exercise",
            "subcategory":"Playing Field",
            "type":"Entertainment"
        }
    ],
    "sg:phone":"+1 612 929 6115",
    "sg:postcode":"55416",
    "sg:province":"MN",
    "sg:tags":[
        "personal",
        "development"
    ],
    "sg:website":"http://www.gamblersalternativetreatment.com",
    "wof:name":"Gamblers Alternatives",
    "wof:placetype":"venue"
},
  "geometry": {"coordinates":[-93.318466,44.948441],"type":"Point"}
}