{
  "type": "Feature",
  "properties": {
    "iso:country":"US",
    "sg:address":"1603 University Ave W",
    "sg:city":"Saint Paul",
    "sg:classifiers":[
        {
            "category":"Banks & Credit Unions",
            "subcategory":"Atm",
            "type":"Services"
        }
    ],
    "sg:phone":"+1 651 387 6575",
    "sg:postcode":"55104",
    "sg:province":"MN",
    "sg:tags":[
        "bankruptcy"
    ],
    "wof:name":"Law Offices of Edward P Russell",
    "wof:placetype":"venue"
},
  "geometry": {"coordinates":[-93.16799899999999,44.9557],"type":"Point"}
}