{
  "type": "Feature",
  "properties": {
    "iso:country":"US",
    "sg:address":"8640 Harriet Ave S",
    "sg:city":"Minneapolis",
    "sg:classifiers":[
        {
            "category":"Building & Trades",
            "subcategory":"Plumbing",
            "type":"Services"
        }
    ],
    "sg:phone":"+1 952 881 3355",
    "sg:postcode":"55420",
    "sg:province":"MN",
    "sg:tags":[
        "plumbing",
        "contractor"
    ],
    "wof:name":"Richfield Plumbing Co",
    "wof:placetype":"venue"
},
  "geometry": {"coordinates":[-93.286089,44.846594],"type":"Point"}
}