{
  "type": "Feature",
  "properties": {
    "addr:full":"3534 Oliver Ave N Minneapolis MN 55412",
    "addr:housenumber":"3534",
    "addr:postcode":"55412",
    "addr:street":"Oliver Ave N",
    "iso:country":"US",
    "sg:address":"3534 Oliver Ave N",
    "sg:city":"Minneapolis",
    "sg:classifiers":[
        {
            "category":"Building & Trades",
            "subcategory":"Construction",
            "type":"Services"
        }
    ],
    "sg:phone":"+1 612 588 7056",
    "sg:postcode":"55412",
    "sg:province":"MN",
    "sg:tags":[
        "house"
    ],
    "wof:name":"Parks Family Construction Inc",
    "wof:placetype":"venue"
},
  "geometry": {"coordinates":[-93.306922,45.019827],"type":"Point"}
}