{
  "type": "Feature",
  "properties": {
    "addr:full":"8915 Penn Ave S Bloomington MN 55431",
    "addr:housenumber":"8915",
    "addr:postcode":"55431",
    "addr:street":"Penn Ave S",
    "iso:country":"US",
    "sg:address":"8915 Penn Ave S",
    "sg:city":"Bloomington",
    "sg:classifiers":[
        {
            "category":"Food & Beverages",
            "subcategory":"Liquor & Beverages",
            "type":"Retail Goods"
        }
    ],
    "sg:phone":"+1 952 881 8667",
    "sg:postcode":"55431",
    "sg:province":"MN",
    "wof:name":"United Liquors Bloomington",
    "wof:placetype":"venue"
},
  "geometry": {"coordinates":[-93.308784,44.841064],"type":"Point"}
}