{
  "type": "Feature",
  "properties": {
    "iso:country":"US",
    "sg:address":"9278 Isanti St NE",
    "sg:city":"Minneapolis",
    "sg:classifiers":[
        {
            "category":"Building & Trades",
            "subcategory":"Construction",
            "type":"Services"
        }
    ],
    "sg:phone":"+1 763 432 4000",
    "sg:postcode":"55449",
    "sg:province":"MN",
    "sg:tags":[
        "equipment",
        "supply",
        "drywall",
        "contractor"
    ],
    "wof:name":"United Drywall Corporation",
    "wof:placetype":"venue"
},
  "geometry": {"coordinates":[-93.223923,45.13827],"type":"Point"}
}