{
  "type": "Feature",
  "properties": {
    "iso:country":"US",
    "sg:address":"17673 Kenwood Trl",
    "sg:city":"Lakeville",
    "sg:classifiers":[
        {
            "category":"Retail",
            "subcategory":"Animal Services",
            "type":"Services"
        }
    ],
    "sg:phone":"+1 952 898 9407",
    "sg:postcode":"55044",
    "sg:province":"MN",
    "sg:tags":[
        "pet",
        "grooming",
        "washing"
    ],
    "wof:name":"Groomingdale's Pet Salons",
    "wof:placetype":"venue"
},
  "geometry": {"coordinates":[-93.284297,44.693408],"type":"Point"}
}