{
  "type": "Feature",
  "properties": {
    "addr:full":"504 6th Ave W Alexandria MN 56308",
    "addr:housenumber":"504",
    "addr:postcode":"56308",
    "addr:street":"6Th Ave W",
    "iso:country":"US",
    "sg:address":"504 6th Ave W",
    "sg:city":"Alexandria",
    "sg:classifiers":[
        {
            "category":"Social Services",
            "subcategory":"Child Care",
            "type":"Services"
        }
    ],
    "sg:phone":"+1 320 763 6322",
    "sg:postcode":"56308",
    "sg:province":"MN",
    "sg:tags":[
        "day",
        "provider"
    ],
    "wof:name":"Susan M Breitkreutz",
    "wof:placetype":"venue"
},
  "geometry": {"coordinates":[-95.385459,45.885914],"type":"Point"}
}