{
  "type": "Feature",
  "properties": {
    "addr:full":"10525 Chowen Ave S Minneapolis MN 55431",
    "addr:housenumber":"10525",
    "addr:postcode":"55431",
    "addr:street":"Chowen Ave S",
    "iso:country":"US",
    "sg:address":"10525 Chowen Ave S",
    "sg:city":"Minneapolis",
    "sg:classifiers":[
        {
            "category":"Shopping",
            "type":"Retail Goods"
        }
    ],
    "sg:phone":"+1 952 884 8758",
    "sg:postcode":"55431",
    "sg:province":"MN",
    "sg:tags":[
        "merchandise"
    ],
    "wof:name":"Ram Marketing Inc",
    "wof:placetype":"venue"
},
  "geometry": {"coordinates":[-93.325575,44.811771],"type":"Point"}
}