{
  "type": "Feature",
  "properties": {
    "iso:country":"US",
    "sg:address":"2015 Franklin Ave SE",
    "sg:city":"Minneapolis",
    "sg:classifiers":[
        {
            "category":"Building & Trades",
            "subcategory":"Construction",
            "type":"Services"
        }
    ],
    "sg:phone":"+1 612 874 6981",
    "sg:postcode":"55414",
    "sg:province":"MN",
    "sg:tags":[
        "general",
        "contractor"
    ],
    "wof:name":"Beeman Birrenbach Construction",
    "wof:placetype":"venue"
},
  "geometry": {"coordinates":[-93.210362,44.964662],"type":"Point"}
}