{
  "type": "Feature",
  "properties": {
    "iso:country":"US",
    "sg:address":"207 3rd St E",
    "sg:city":"Northfield",
    "sg:classifiers":[
        {
            "category":"Real Estate",
            "subcategory":"Real Estate Agent",
            "type":"Services"
        }
    ],
    "sg:phone":"+1 507 645 7260",
    "sg:postcode":"55057",
    "sg:province":"MN",
    "wof:name":"Northfield Appraisal & Mgt",
    "wof:placetype":"venue"
},
  "geometry": {"coordinates":[-93.158531,44.457453],"type":"Point"}
}