{
  "type": "Feature",
  "properties": {
    "addr:full":"1006 Atlantic Ave Benson MN 56215",
    "addr:housenumber":"1006",
    "addr:postcode":"56215",
    "addr:street":"Atlantic Ave",
    "iso:country":"US",
    "sg:address":"1006 Atlantic Ave",
    "sg:city":"Benson",
    "sg:classifiers":[
        {
            "category":"Autos & Motor Vehicles",
            "subcategory":"Fuel & Gas Station",
            "type":"Retail Goods"
        }
    ],
    "sg:phone":"+1 320 842 5141",
    "sg:postcode":"56215",
    "sg:province":"MN",
    "sg:tags":[
        "grocery",
        "station",
        "gasoline"
    ],
    "wof:name":"Kellys Convenience Store",
    "wof:placetype":"venue"
},
  "geometry": {"coordinates":[-95.597399,45.314078],"type":"Point"}
}