{
  "type": "Feature",
  "properties": {
    "addr:full":"150 Co Hwy 34 Jackson MN 56143",
    "addr:housenumber":"150",
    "addr:postcode":"56143",
    "addr:street":"Co Hwy 34",
    "iso:country":"US",
    "sg:address":"150 Co Hwy 34",
    "sg:city":"Jackson",
    "sg:classifiers":[
        {
            "category":"Professional",
            "type":"Services"
        }
    ],
    "sg:phone":"+1 507 847 2772",
    "sg:postcode":"56143",
    "sg:province":"MN",
    "wof:name":"Skyview Flight Svc",
    "wof:placetype":"venue"
},
  "geometry": {"coordinates":[-94.988668,43.620001],"type":"Point"}
}