{
  "type": "Feature",
  "properties": {
    "iso:country":"US",
    "sg:address":"3254 W Lake St",
    "sg:city":"Minneapolis",
    "sg:classifiers":[
        {
            "category":"Bars & Pubs",
            "type":"Food & Drink"
        },
        {
            "category":"Food & Beverages",
            "subcategory":"Liquor & Beverages",
            "type":"Retail Goods"
        },
        {
            "category":"Bars & Pubs",
            "subcategory":"Lounge",
            "type":"Food & Drink"
        }
    ],
    "sg:phone":"+1 612 922 1130",
    "sg:postcode":"55416",
    "sg:province":"MN",
    "sg:tags":[
        "cocktail",
        "wine"
    ],
    "wof:name":"MGM Liquor",
    "wof:placetype":"venue"
},
  "geometry": {"coordinates":[-93.32141300000001,44.948473],"type":"Point"}
}