{
  "type": "Feature",
  "properties": {
    "addr:full":"213 Degraff Ave Swanville MN 56382",
    "addr:housenumber":"213",
    "addr:postcode":"56382",
    "addr:street":"Degraff Ave",
    "iso:country":"US",
    "sg:address":"213 Degraff Ave",
    "sg:city":"Swanville",
    "sg:classifiers":[
        {
            "category":"Education",
            "subcategory":"Library",
            "type":"Public Place"
        }
    ],
    "sg:phone":"+1 320 547 2346",
    "sg:postcode":"56382",
    "sg:province":"MN",
    "sg:website":"http://www.griver.org",
    "wof:name":"Swanville Branch Library",
    "wof:placetype":"venue"
},
  "geometry": {"coordinates":[-94.64070100000001,45.914593],"type":"Point"}
}