{
  "type": "Feature",
  "properties": {
    "addr:full":"680 Constance Blvd NW Anoka MN 55304",
    "addr:housenumber":"680",
    "addr:postcode":"55304",
    "addr:street":"Constance Blvd Nw",
    "iso:country":"US",
    "sg:address":"680 Constance Blvd NW",
    "sg:city":"Anoka",
    "sg:classifiers":[
        {
            "category":"Manufacturing",
            "subcategory":"Rubber & Plastics",
            "type":"Manufacturing & Wholesale Goods"
        },
        {
            "category":"Manufacturing",
            "subcategory":"Tools & Machinery",
            "type":"Manufacturing & Wholesale Goods"
        }
    ],
    "sg:phone":"+1 763 434 6688",
    "sg:postcode":"55304",
    "sg:province":"MN",
    "sg:tags":[
        "fiberglass",
        "custom",
        "mold",
        "molding"
    ],
    "wof:name":"Diversified Fiberglass Inc",
    "wof:placetype":"venue"
},
  "geometry": {"coordinates":[-93.281654,45.262137],"type":"Point"}
}