{
  "type": "Feature",
  "properties": {
    "addr:full":"1350 Shilhon Rd Duluth MN 55804",
    "addr:housenumber":"1350",
    "addr:postcode":"55804",
    "addr:street":"Shilhon Rd",
    "iso:country":"US",
    "sg:address":"1350 Shilhon Rd",
    "sg:city":"Duluth",
    "sg:classifiers":[
        {
            "category":"Manufacturing",
            "subcategory":"Glass & Minerals",
            "type":"Manufacturing & Wholesale Goods"
        }
    ],
    "sg:phone":"+1 218 834 3305",
    "sg:postcode":"55804",
    "sg:province":"MN",
    "sg:tags":[
        "product",
        "mfg"
    ],
    "wof:name":"Benson Glass Art",
    "wof:placetype":"venue"
},
  "geometry": {"coordinates":[-91.845882,46.952741],"type":"Point"}
}