{
  "type": "Feature",
  "properties": {
    "addr:full":"530 W Main St Ste 7 Anoka MN 55303",
    "addr:housenumber":"530",
    "addr:postcode":"55303",
    "addr:street":"W Main St Ste 7",
    "iso:country":"US",
    "sg:address":"530 W Main St Ste 7",
    "sg:city":"Anoka",
    "sg:classifiers":[
        {
            "category":"Food & Beverages",
            "subcategory":"Bakery",
            "type":"Retail Goods"
        },
        {
            "category":"Bakery",
            "type":"Food & Drink"
        }
    ],
    "sg:phone":"+1 763 712 5566",
    "sg:postcode":"55303",
    "sg:province":"MN",
    "sg:tags":[
        "bakers-wholesale"
    ],
    "wof:name":"Milagros Bakery",
    "wof:placetype":"venue"
},
  "geometry": {"coordinates":[-93.399512,45.203986],"type":"Point"}
}