{
  "type": "Feature",
  "properties": {
    "iso:country":"US",
    "sg:address":"12212 103rd Ave",
    "sg:city":"Kimball",
    "sg:classifiers":[
        {
            "category":"Farming",
            "subcategory":"Dairy Farm",
            "type":"Manufacturing & Wholesale Goods"
        },
        {
            "category":"Farming",
            "subcategory":"Farm",
            "type":"Manufacturing & Wholesale Goods"
        }
    ],
    "sg:phone":"+1 320 398 3153",
    "sg:postcode":"55353",
    "sg:province":"MN",
    "wof:name":"Robert Epple",
    "wof:placetype":"venue"
},
  "geometry": {"coordinates":[-94.322906,45.300644],"type":"Point"}
}