{
  "type": "Feature",
  "properties": {
    "iso:country":"US",
    "sg:address":"11614 640th St",
    "sg:city":"Claremont",
    "sg:classifiers":[
        {
            "category":"Farming",
            "subcategory":"Livestock Farm",
            "type":"Manufacturing & Wholesale Goods"
        }
    ],
    "sg:phone":"+1 507 528 2657",
    "sg:postcode":"55924",
    "sg:province":"MN",
    "sg:tags":[
        "feedlot",
        "field",
        "crop",
        "beef",
        "cattle"
    ],
    "wof:name":"Bernard Davis",
    "wof:placetype":"venue"
},
  "geometry": {"coordinates":[-93.018237,44.022917],"type":"Point"}
}