{
  "type": "Feature",
  "properties": {
    "iso:country":"US",
    "sg:address":"2769 Winnetka Ave",
    "sg:city":"Minneapolis",
    "sg:classifiers":[
        {
            "category":"Retail",
            "subcategory":"Self-service Laundry",
            "type":"Services"
        }
    ],
    "sg:phone":"+1 763 542 0618",
    "sg:postcode":"55427",
    "sg:province":"MN",
    "sg:tags":[
        "coin"
    ],
    "wof:name":"Mega Wash Coin Laudries",
    "wof:placetype":"venue"
},
  "geometry": {"coordinates":[-93.38029400000001,45.009743],"type":"Point"}
}