{
  "type": "Feature",
  "properties": {
    "iso:country":"US",
    "sg:address":"3230 Spruce St",
    "sg:city":"Little Canada",
    "sg:classifiers":[
        {
            "category":"Government",
            "subcategory":"Office",
            "type":"Public Place"
        }
    ],
    "sg:phone":"+1 651 484 4572",
    "sg:postcode":"55117",
    "sg:province":"MN",
    "sg:tags":[
        "state",
        "program",
        "health"
    ],
    "wof:name":"Gentec Health Care Inc",
    "wof:placetype":"venue"
},
  "geometry": {"coordinates":[-93.100846,45.037971],"type":"Point"}
}