{
  "type": "Feature",
  "properties": {
    "iso:country":"US",
    "sg:address":"217 Havana St",
    "sg:city":"Willmar",
    "sg:classifiers":[
        {
            "category":"Social Services",
            "subcategory":"Child Care",
            "type":"Services"
        }
    ],
    "sg:phone":"+1 320 235 5408",
    "sg:postcode":"56201",
    "sg:province":"MN",
    "sg:tags":[
        "day",
        "provides"
    ],
    "wof:name":"Ronald C Hagen",
    "wof:placetype":"venue"
},
  "geometry": {"coordinates":[-95.03877799999999,45.126259],"type":"Point"}
}