{
  "type": "Feature",
  "properties": {
    "addr:full":"3208 Hennepin Ave S Minneapolis MN 55408",
    "addr:housenumber":"3208",
    "addr:postcode":"55408",
    "addr:street":"Hennepin Ave S",
    "iso:country":"US",
    "sg:address":"3208 Hennepin Ave S",
    "sg:city":"Minneapolis",
    "sg:classifiers":[
        {
            "category":"Personal",
            "subcategory":"Beauty Salon",
            "type":"Services"
        },
        {
            "category":"Personal",
            "subcategory":"Barber",
            "type":"Services"
        }
    ],
    "sg:phone":"+1 612 554 5522",
    "sg:postcode":"55408",
    "sg:province":"MN",
    "sg:tags":[
        "hair"
    ],
    "sg:website":"www.chopnblow.com",
    "wof:name":"Chop & Blow Salon",
    "wof:placetype":"venue"
},
  "geometry": {"coordinates":[-93.298688,44.944301],"type":"Point"}
}