{
  "type": "Feature",
  "properties": {
    "addr:full":"890 Rice St St Paul MN 55117",
    "addr:housenumber":"890",
    "addr:postcode":"55117",
    "addr:street":"Rice St",
    "iso:country":"US",
    "sg:address":"890 Rice St",
    "sg:city":"St Paul",
    "sg:classifiers":[
        {
            "category":"Shopping",
            "subcategory":"Tobacco",
            "type":"Retail Goods"
        }
    ],
    "sg:phone":"+1 651 489 0239",
    "sg:postcode":"55117",
    "sg:province":"MN",
    "sg:tags":[
        "cigarette",
        "product",
        "cigar",
        "dealer"
    ],
    "wof:name":"Neighboorhood Puff & Snuff Inc",
    "wof:placetype":"venue"
},
  "geometry": {"coordinates":[-93.105875,44.968015],"type":"Point"}
}