{
  "type": "Feature",
  "properties": {
    "iso:country":"US",
    "sg:address":"50 Sherburne Ave",
    "sg:city":"St Paul",
    "sg:classifiers":[
        {
            "category":"Government",
            "subcategory":"Office",
            "type":"Public Place"
        }
    ],
    "sg:phone":"+1 651 296 2600",
    "sg:postcode":"55103",
    "sg:province":"MN",
    "sg:tags":[
        "state"
    ],
    "sg:website":"www.mmd.admin.state.mn.us",
    "wof:name":"Materials Management Div",
    "wof:placetype":"venue"
},
  "geometry": {"coordinates":[-93.101647,44.956767],"type":"Point"}
}