{
  "type": "Feature",
  "properties": {
    "iso:country":"US",
    "sg:address":"950 Main St S",
    "sg:city":"Pine City",
    "sg:classifiers":[
        {
            "category":"Banks & Credit Unions",
            "subcategory":"Bank",
            "type":"Services"
        }
    ],
    "sg:phone":"+1 320 629 5533",
    "sg:postcode":"55063",
    "sg:province":"MN",
    "sg:tags":[
        "loan",
        "real estate"
    ],
    "wof:name":"Chisago Lakes Mortgage Inc",
    "wof:placetype":"venue"
},
  "geometry": {"coordinates":[-92.970344,45.81823],"type":"Point"}
}