{
  "type": "Feature",
  "properties": {
    "iso:country":"US",
    "sg:address":"2478 Vermilion Dr",
    "sg:city":"Cook",
    "sg:classifiers":[
        {
            "category":"Manufacturing",
            "subcategory":"Building Materials",
            "type":"Manufacturing & Wholesale Goods"
        }
    ],
    "sg:phone":"+1 218 666 2903",
    "sg:postcode":"55723",
    "sg:province":"MN",
    "sg:tags":[
        "mfg"
    ],
    "wof:name":"Plv Enterprises",
    "wof:placetype":"venue"
},
  "geometry": {"coordinates":[-92.65990499999999,47.901029],"type":"Point"}
}