{
  "type": "Feature",
  "properties": {
    "addr:full":"500 Central Ave W Aurora MN 55705",
    "addr:housenumber":"500",
    "addr:postcode":"55705",
    "addr:street":"Central Ave W",
    "iso:country":"US",
    "sg:address":"500 Central Ave W",
    "sg:city":"Aurora",
    "sg:classifiers":[
        {
            "category":"Place Of Worship",
            "subcategory":"Church",
            "type":"Public Place"
        },
        {
            "category":"Place Of Worship",
            "type":"Public Place"
        }
    ],
    "sg:phone":"+1 218 229 3208",
    "sg:postcode":"55705",
    "sg:province":"MN",
    "sg:tags":[
        "lutheran",
        "america",
        "churches-lutheran",
        "churches-lutheran-evangelical"
    ],
    "wof:name":"Redeemer Lutheran Church Missouri Synod",
    "wof:placetype":"venue"
},
  "geometry": {"coordinates":[-92.24659,47.52747],"type":"Point"}
}