{
  "type": "Feature",
  "properties": {
    "addr:full":"1672 Sandbar Cir Waconia MN 55387",
    "addr:housenumber":"1672",
    "addr:postcode":"55387",
    "addr:street":"Sandbar Cir",
    "iso:country":"US",
    "sg:address":"1672 Sandbar Cir",
    "sg:city":"Waconia",
    "sg:classifiers":[
        {
            "category":"Banks & Credit Unions",
            "subcategory":"Bank",
            "type":"Services"
        }
    ],
    "sg:phone":"+1 612 868 9226",
    "sg:postcode":"55387",
    "sg:province":"MN",
    "sg:tags":[
        "loan",
        "real estate"
    ],
    "wof:name":"JGF Mortgage",
    "wof:placetype":"venue"
},
  "geometry": {"coordinates":[-93.818022,44.857064],"type":"Point"}
}