{
  "type": "Feature",
  "properties": {
    "addr:full":"473 Hayward Ave N St Paul MN 55128",
    "addr:housenumber":"473",
    "addr:postcode":"55128",
    "addr:street":"Hayward Ave N",
    "iso:country":"US",
    "sg:address":"473 Hayward Ave N",
    "sg:city":"St Paul",
    "sg:classifiers":[
        {
            "category":"Manufacturing",
            "subcategory":"Tools & Machinery",
            "type":"Manufacturing & Wholesale Goods"
        },
        {
            "category":"Health Services",
            "subcategory":"Doctor",
            "type":"Services"
        }
    ],
    "sg:phone":"+1 651 730 1008",
    "sg:postcode":"55128",
    "sg:province":"MN",
    "sg:tags":[
        "physician",
        "surgeon",
        "medical",
        "devices"
    ],
    "sg:website":"www.birchpoint.net",
    "wof:name":"Birch Point Medical Inc",
    "wof:placetype":"venue"
},
  "geometry": {"coordinates":[-92.95688800000001,44.956106],"type":"Point"}
}