{
  "type": "Feature",
  "properties": {
    "addr:full":"1202 Dale St N Saint Paul MN 55117",
    "addr:housenumber":"1202",
    "addr:postcode":"55117",
    "addr:street":"Dale St N",
    "iso:country":"US",
    "sg:address":"1202 Dale St N",
    "sg:city":"Saint Paul",
    "sg:classifiers":[
        {
            "category":"Professional",
            "type":"Services"
        }
    ],
    "sg:phone":"+1 651 487 0014",
    "sg:postcode":"55117",
    "sg:province":"MN",
    "wof:name":"McTire Service",
    "wof:placetype":"venue"
},
  "geometry": {"coordinates":[-93.126319,44.979166],"type":"Point"}
}