{
  "type": "Feature",
  "properties": {
    "addr:full":"270 Main St W Trimont MN 56176",
    "addr:housenumber":"270",
    "addr:postcode":"56176",
    "addr:street":"Main St W Trimont",
    "iso:country":"US",
    "sg:address":"270 Main St W",
    "sg:city":"Trimont",
    "sg:classifiers":[
        {
            "category":"Retail",
            "subcategory":"Auto Repair",
            "type":"Services"
        }
    ],
    "sg:phone":"+1 507 639 3082",
    "sg:postcode":"56176",
    "sg:province":"MN",
    "sg:tags":[
        "repairing",
        "automobile"
    ],
    "wof:name":"Borntrager Auto Body & Towing",
    "wof:placetype":"venue"
},
  "geometry": {"coordinates":[-94.71887700000001,43.762081],"type":"Point"}
}