{
  "type": "Feature",
  "properties": {
    "addr:full":"607 1st St Madison MN 56256",
    "addr:housenumber":"607",
    "addr:postcode":"56256",
    "addr:street":"1St St",
    "iso:country":"US",
    "sg:address":"607 1st St",
    "sg:city":"Madison",
    "sg:classifiers":[
        {
            "category":"Food & Beverages",
            "subcategory":"Liquor & Beverages",
            "type":"Retail Goods"
        }
    ],
    "sg:phone":"+1 320 598 7900",
    "sg:postcode":"56256",
    "sg:province":"MN",
    "sg:tags":[
        "alcoholic"
    ],
    "wof:name":"Municipal Liquor Store",
    "wof:placetype":"venue"
},
  "geometry": {"coordinates":[-96.193836,45.009606],"type":"Point"}
}