{
  "type": "Feature",
  "properties": {
    "iso:country":"US",
    "sg:address":"3985 Shadowwood Dr NE",
    "sg:city":"Sauk Rapids",
    "sg:classifiers":[
        {
            "category":"Autos & Motor Vehicles",
            "subcategory":"Automobile Sales",
            "type":"Retail Goods"
        },
        {
            "category":"Autos & Motor Vehicles",
            "subcategory":"Motorcycle Sales",
            "type":"Retail Goods"
        }
    ],
    "sg:phone":"+1 320 252 1556",
    "sg:postcode":"56379",
    "sg:province":"MN",
    "sg:tags":[
        "repair",
        "all",
        "terrain"
    ],
    "wof:name":"Pro Cycle & Snowmobile Inc",
    "wof:placetype":"venue"
},
  "geometry": {"coordinates":[-94.080708,45.581518],"type":"Point"}
}