{
  "type": "Feature",
  "properties": {
    "addr:full":"1720 Burlington Ave Worthington MN 56187",
    "addr:housenumber":"1720",
    "addr:postcode":"56187",
    "addr:street":"Burlington Ave",
    "iso:country":"US",
    "sg:address":"1720 Burlington Ave",
    "sg:city":"Worthington",
    "sg:classifiers":[
        {
            "category":"Organizations",
            "subcategory":"Religious Organization",
            "type":"Services"
        }
    ],
    "sg:phone":"+1 507 376 6517",
    "sg:postcode":"56187",
    "sg:province":"MN",
    "sg:tags":[
        "church"
    ],
    "wof:name":"American Reformed Church",
    "wof:placetype":"venue"
},
  "geometry": {"coordinates":[-95.590963,43.632922],"type":"Point"}
}