{
  "type": "Feature",
  "properties": {
    "addr:full":"333 1st St N Hackensack MN 56452",
    "addr:housenumber":"333",
    "addr:postcode":"56452",
    "addr:street":"1St St N",
    "iso:country":"US",
    "sg:address":"333 1st St N",
    "sg:city":"Hackensack",
    "sg:classifiers":[
        {
            "category":"Shopping",
            "subcategory":"Bicycles & Sporting Goods",
            "type":"Retail Goods"
        }
    ],
    "sg:phone":"+1 218 675 6176",
    "sg:postcode":"56452",
    "sg:province":"MN",
    "wof:name":"Swanson",
    "wof:placetype":"venue"
},
  "geometry": {"coordinates":[-94.520623,46.936184],"type":"Point"}
}