{
  "type": "Feature",
  "properties": {
    "iso:country":"US",
    "sg:address":"303 22nd Ave W",
    "sg:city":"Alexandria",
    "sg:classifiers":[
        {
            "category":"Government",
            "subcategory":"Office",
            "type":"Public Place"
        }
    ],
    "sg:phone":"+1 320 762 7800",
    "sg:postcode":"56308",
    "sg:province":"MN",
    "wof:name":"Jobs Service",
    "wof:placetype":"venue"
},
  "geometry": {"coordinates":[-95.386269,45.867541],"type":"Point"}
}