{
  "type": "Feature",
  "properties": {
    "addr:full":"13008 Minnetonka Blvd Hopkins MN 55305",
    "addr:housenumber":"13008",
    "addr:postcode":"55305",
    "addr:street":"Minnetonka Blvd",
    "iso:country":"US",
    "sg:address":"13008 Minnetonka Blvd",
    "sg:city":"Hopkins",
    "sg:classifiers":[
        {
            "category":"Shopping",
            "type":"Retail Goods"
        },
        {
            "category":"Autos & Motor Vehicles",
            "subcategory":"Fuel & Gas Station",
            "type":"Retail Goods"
        }
    ],
    "sg:phone":"+1 952 935 8890",
    "sg:postcode":"55305",
    "sg:province":"MN",
    "sg:tags":[
        "pet",
        "feed",
        "station",
        "food",
        "supply"
    ],
    "wof:name":"Bennis Feed and Fuel",
    "wof:placetype":"venue"
},
  "geometry": {"coordinates":[-93.44328,44.941655],"type":"Point"}
}