{
  "type": "Feature",
  "properties": {
    "iso:country":"US",
    "sg:address":"429 Central Ave N",
    "sg:city":"Faribault",
    "sg:classifiers":[
        {
            "category":"Travel",
            "subcategory":"Hotels & Motels",
            "type":"Entertainment"
        }
    ],
    "sg:phone":"+1 507 334 8263",
    "sg:postcode":"55021",
    "sg:province":"MN",
    "sg:tags":[
        "building",
        "operator",
        "operation",
        "apartment"
    ],
    "wof:name":"Hotel Faribault Apartments",
    "wof:placetype":"venue"
},
  "geometry": {"coordinates":[-93.268316,44.295569],"type":"Point"}
}