{
  "type": "Feature",
  "properties": {
    "iso:country":"US",
    "sg:address":"8111 Pillsbury Ave S",
    "sg:city":"Bloomington",
    "sg:classifiers":[
        {
            "category":"Manufacturing",
            "subcategory":"Printing",
            "type":"Manufacturing & Wholesale Goods"
        }
    ],
    "sg:phone":"+1 952 885 0064",
    "sg:postcode":"55420",
    "sg:province":"MN",
    "sg:tags":[
        "printer",
        "commercial",
        "offset"
    ],
    "wof:name":"Island Press Inc",
    "wof:placetype":"venue"
},
  "geometry": {"coordinates":[-93.28207399999999,44.855344],"type":"Point"}
}