{
  "type": "Feature",
  "properties": {
    "addr:full":"43932 Mosquito Heights Rd Perham MN 56573",
    "addr:postcode":"43932;56573",
    "addr:street":"Mosquito Heights Rd",
    "iso:country":"US",
    "sg:address":"43932 Mosquito Heights Rd",
    "sg:city":"Perham",
    "sg:classifiers":[
        {
            "category":"Building & Trades",
            "subcategory":"Construction",
            "type":"Services"
        }
    ],
    "sg:phone":"+1 218 346 7062",
    "sg:postcode":"56573",
    "sg:province":"MN",
    "sg:tags":[
        "house"
    ],
    "wof:name":"Walt Seifert Construction",
    "wof:placetype":"venue"
},
  "geometry": {"coordinates":[-95.515676,46.598719],"type":"Point"}
}