{
  "type": "Feature",
  "properties": {
    "addr:full":"816 Oriole Ln Chaska MN 55318",
    "addr:housenumber":"816",
    "addr:postcode":"55318",
    "addr:street":"Oriole Ln",
    "iso:country":"US",
    "sg:address":"816 Oriole Ln",
    "sg:city":"Chaska",
    "sg:phone":"+1 952 448 5304",
    "sg:postcode":"55318",
    "sg:province":"MN",
    "sg:tags":[
        "farm",
        "wheat",
        "grain",
        "cash"
    ],
    "wof:name":"Douglas Jensen Farm",
    "wof:placetype":"venue"
},
  "geometry": {"coordinates":[-93.583535,44.824603],"type":"Point"}
}