{
  "type": "Feature",
  "properties": {
    "iso:country":"US",
    "sg:address":"2726 Rushmore Rd",
    "sg:city":"Hastings",
    "sg:classifiers":[
        {
            "category":"Professional",
            "subcategory":"Art Services",
            "type":"Services"
        }
    ],
    "sg:phone":"+1 651 343 2080",
    "sg:postcode":"55033",
    "sg:province":"MN",
    "sg:tags":[
        "designer",
        "display",
        "producer"
    ],
    "wof:name":"Mezzano Design International I",
    "wof:placetype":"venue"
},
  "geometry": {"coordinates":[-92.826184,44.719699],"type":"Point"}
}