{
  "type": "Feature",
  "properties": {
    "addr:full":"3355 Plymouth Blvd Minneapolis MN 55447",
    "addr:housenumber":"3355",
    "addr:postcode":"55447",
    "addr:street":"Plymouth Blvd",
    "iso:country":"US",
    "sg:address":"3355 Plymouth Blvd",
    "sg:city":"Minneapolis",
    "sg:classifiers":[
        {
            "category":"Food & Beverages",
            "subcategory":"Specialty",
            "type":"Retail Goods"
        }
    ],
    "sg:phone":"+1 763 557 9727",
    "sg:postcode":"55447",
    "sg:province":"MN",
    "sg:tags":[
        "health",
        "diet"
    ],
    "wof:name":"Nutrition Central Inc",
    "wof:placetype":"venue"
},
  "geometry": {"coordinates":[-93.47393700000001,45.018195],"type":"Point"}
}