{
  "type": "Feature",
  "properties": {
    "iso:country":"US",
    "sg:address":"4444 Chatsworth St N",
    "sg:city":"Saint Paul",
    "sg:classifiers":[
        {
            "category":"Wholesale",
            "subcategory":"Durable Goods & Equipment",
            "type":"Manufacturing & Wholesale Goods"
        }
    ],
    "sg:phone":"+1 651 481 9677",
    "sg:postcode":"55126",
    "sg:province":"MN",
    "wof:name":"Carol Kramer",
    "wof:placetype":"venue"
},
  "geometry": {"coordinates":[-93.144217,45.07494],"type":"Point"}
}