{
  "type": "Feature",
  "properties": {
    "addr:full":"5725 International Pkwy Minneapolis MN 55428",
    "addr:housenumber":"5725",
    "addr:postcode":"55428",
    "addr:street":"International Pkwy",
    "iso:country":"US",
    "sg:address":"5725 International Pkwy",
    "sg:city":"Minneapolis",
    "sg:classifiers":[
        {
            "category":"Wholesale",
            "subcategory":"Non-durable Goods",
            "type":"Manufacturing & Wholesale Goods"
        }
    ],
    "sg:phone":"+1 763 535 8669",
    "sg:postcode":"55428",
    "sg:province":"MN",
    "sg:tags":[
        "equipment",
        "industrial"
    ],
    "sg:website":"www.dynamicpkg.com",
    "wof:name":"Dynamic Packaging Inc",
    "wof:placetype":"venue"
},
  "geometry": {"coordinates":[-93.39634,45.056883],"type":"Point"}
}