{
  "type": "Feature",
  "properties": {
    "addr:full":"39191 Judson Bottom Rd Mankato MN 56003",
    "addr:housenumber":"39191",
    "addr:postcode":"56003",
    "addr:street":"Judson Bottom Rd",
    "iso:country":"US",
    "sg:address":"39191 Judson Bottom Rd",
    "sg:city":"Mankato",
    "sg:classifiers":[
        {
            "category":"Restaurant",
            "type":"Food & Drink"
        }
    ],
    "sg:phone":"+1 507 344 8981",
    "sg:postcode":"56003",
    "sg:province":"MN",
    "sg:tags":[
        "eating"
    ],
    "wof:name":"Brendons Ice Cream Express",
    "wof:placetype":"venue"
},
  "geometry": {"coordinates":[-94.051531,44.16243],"type":"Point"}
}