{
  "type": "Feature",
  "properties": {
    "addr:full":"27160 Co Rd 2 Comfrey MN 56019",
    "addr:postcode":"27160;56019",
    "addr:street":"Co Rd 2 Comfrey",
    "iso:country":"US",
    "sg:address":"27160 Co Rd 2",
    "sg:city":"Comfrey",
    "sg:classifiers":[
        {
            "category":"Government",
            "subcategory":"Office",
            "type":"Public Place"
        }
    ],
    "sg:phone":"+1 507 628 5591",
    "sg:postcode":"56019",
    "sg:province":"MN",
    "sg:tags":[
        "historic",
        "site"
    ],
    "wof:name":"Jeffers Petroglyphs",
    "wof:placetype":"venue"
},
  "geometry": {"coordinates":[-95.060084,44.091218],"type":"Point"}
}