{
  "type": "Feature",
  "properties": {
    "iso:country":"US",
    "sg:address":"2999 Highview Ln",
    "sg:city":"Mound",
    "sg:classifiers":[
        {
            "category":"Manufacturing",
            "subcategory":"Chemicals & Compounds",
            "type":"Manufacturing & Wholesale Goods"
        }
    ],
    "sg:phone":"+1 952 472 7024",
    "sg:postcode":"55364",
    "sg:province":"MN",
    "sg:tags":[
        "biological",
        "product",
        "mfg"
    ],
    "wof:name":"Gish Biomedical Incorporated",
    "wof:placetype":"venue"
},
  "geometry": {"coordinates":[-93.687049,44.923819],"type":"Point"}
}