{
  "type": "Feature",
  "properties": {
    "iso:country":"US",
    "sg:address":"10393 W 70th St",
    "sg:city":"Eden Prairie",
    "sg:classifiers":[
        {
            "category":"Manufacturing",
            "subcategory":"Tools & Machinery",
            "type":"Manufacturing & Wholesale Goods"
        }
    ],
    "sg:phone":"+1 952 947 1200",
    "sg:postcode":"55344",
    "sg:province":"MN",
    "sg:tags":[
        "instrument",
        "surgical"
    ],
    "wof:name":"Arizant Inc",
    "wof:placetype":"venue"
},
  "geometry": {"coordinates":[-93.406206,44.876565],"type":"Point"}
}