{
  "type": "Feature",
  "properties": {
    "addr:full":"76 Saint Croix Trl N Lakeland MN 55043",
    "addr:housenumber":"76",
    "addr:postcode":"55043",
    "addr:street":"Saint Croix Trl N",
    "iso:country":"US",
    "sg:address":"76 Saint Croix Trl N",
    "sg:city":"Lakeland",
    "sg:classifiers":[
        {
            "category":"Building & Trades",
            "subcategory":"Construction",
            "type":"Services"
        }
    ],
    "sg:phone":"+1 651 436 8559",
    "sg:postcode":"55043",
    "sg:province":"MN",
    "sg:tags":[
        "asbestos",
        "detection",
        "removal"
    ],
    "wof:name":"Vci Asbestos Abatement, Inc",
    "wof:placetype":"venue"
},
  "geometry": {"coordinates":[-92.77092,44.950048],"type":"Point"}
}