{
  "type": "Feature",
  "properties": {
    "addr:full":"6950 146th St W St Paul MN 55124",
    "addr:housenumber":"6950",
    "addr:postcode":"55124",
    "addr:street":"146Th St W",
    "iso:country":"US",
    "sg:address":"6950 146th St W",
    "sg:city":"St Paul",
    "sg:classifiers":[
        {
            "category":"Building & Trades",
            "subcategory":"Pest Control",
            "type":"Services"
        }
    ],
    "sg:phone":"+1 651 482 0405",
    "sg:postcode":"55124",
    "sg:province":"MN",
    "wof:name":"Bat Elimination",
    "wof:placetype":"venue"
},
  "geometry": {"coordinates":[-93.205405,44.737373],"type":"Point"}
}