{
  "type": "Feature",
  "properties": {
    "iso:country":"US",
    "sg:address":"606 NW 1st Ave",
    "sg:city":"Grand Rapids",
    "sg:classifiers":[
        {
            "category":"Organizations",
            "subcategory":"Religious Organization",
            "type":"Services"
        }
    ],
    "sg:phone":"+1 218 244 5127",
    "sg:postcode":"55744",
    "sg:province":"MN",
    "sg:tags":[
        "church"
    ],
    "sg:website":"www.northlandbaptist.tk",
    "wof:name":"Northland Bible Baptist Church",
    "wof:placetype":"venue"
},
  "geometry": {"coordinates":[-93.529785,47.238063],"type":"Point"}
}