{
  "type": "Feature",
  "properties": {
    "iso:country":"US",
    "sg:address":"113 2nd Ave NW",
    "sg:city":"Bertha",
    "sg:classifiers":[
        {
            "category":"Government",
            "subcategory":"City Hall",
            "type":"Public Place"
        },
        {
            "category":"Government",
            "subcategory":"Office",
            "type":"Public Place"
        }
    ],
    "sg:phone":"+1 218 924 4454",
    "sg:postcode":"56437",
    "sg:province":"MN",
    "sg:tags":[
        "town",
        "township",
        "planner",
        "government-city",
        "village"
    ],
    "wof:name":"City Of Bertha",
    "wof:placetype":"venue"
},
  "geometry": {"coordinates":[-95.065788,46.266748],"type":"Point"}
}