{
  "type": "Feature",
  "properties": {
    "addr:full":"660 Mendelssohn Ave N Minneapolis MN 55427",
    "addr:housenumber":"660",
    "addr:postcode":"55427",
    "addr:street":"Mendelssohn Ave N",
    "iso:country":"US",
    "sg:address":"660 Mendelssohn Ave N",
    "sg:city":"Minneapolis",
    "sg:classifiers":[
        {
            "category":"Building & Trades",
            "subcategory":"Construction",
            "type":"Services"
        }
    ],
    "sg:phone":"+1 763 542 8826",
    "sg:postcode":"55427",
    "sg:province":"MN",
    "sg:tags":[
        "home",
        "improvement"
    ],
    "sg:website":"www.homedepot.com",
    "wof:name":"Home Depot",
    "wof:placetype":"venue"
},
  "geometry": {"coordinates":[-93.399805,44.988639],"type":"Point"}
}