{
  "type": "Feature",
  "properties": {
    "iso:country":"US",
    "sg:address":"20307 State Hwy 66",
    "sg:city":"Mankato",
    "sg:classifiers":[
        {
            "category":"Wholesale",
            "subcategory":"Office Equipment",
            "type":"Manufacturing & Wholesale Goods"
        }
    ],
    "sg:phone":"+1 507 345 7048",
    "sg:postcode":"56001",
    "sg:province":"MN",
    "sg:tags":[
        "machine",
        "mailing"
    ],
    "sg:website":"www.mantronics.com",
    "wof:name":"Mantronics Mailing Systems",
    "wof:placetype":"venue"
},
  "geometry": {"coordinates":[-94.040791,44.13184],"type":"Point"}
}