{
  "type": "Feature",
  "properties": {
    "addr:full":"1635 Coon Rapids Blvd NW Minneapolis MN 55433",
    "addr:housenumber":"1635",
    "addr:postcode":"55433",
    "addr:street":"Coon Rapids Blvd Nw",
    "iso:country":"US",
    "sg:address":"1635 Coon Rapids Blvd NW",
    "sg:city":"Minneapolis",
    "sg:classifiers":[
        {
            "category":"Real Estate",
            "subcategory":"Real Estate Agent",
            "type":"Services"
        }
    ],
    "sg:phone":"+1 763 441 6713",
    "sg:postcode":"55433",
    "sg:province":"MN",
    "wof:name":"Maximum Realty LLC",
    "wof:placetype":"venue"
},
  "geometry": {"coordinates":[-93.309437,45.156444],"type":"Point"}
}