{
  "type": "Feature",
  "properties": {
    "addr:full":"20746 Ibex Ave Lakeville MN 55044",
    "addr:housenumber":"20746",
    "addr:postcode":"55044",
    "addr:street":"Ibex Ave",
    "iso:country":"US",
    "sg:address":"20746 Ibex Ave",
    "sg:city":"Lakeville",
    "sg:classifiers":[
        {
            "category":"Real Estate",
            "subcategory":"Real Estate Operator",
            "type":"Services"
        }
    ],
    "sg:phone":"+1 952 469 3095",
    "sg:postcode":"55044",
    "sg:province":"MN",
    "sg:tags":[
        "building",
        "nonresidential"
    ],
    "wof:name":"Asmsr Properties LLC",
    "wof:placetype":"venue"
},
  "geometry": {"coordinates":[-93.251949,44.648039],"type":"Point"}
}