{
  "type": "Feature",
  "properties": {
    "iso:country":"US",
    "sg:address":"2415 3rd Ave S Apt A40",
    "sg:city":"Minneapolis",
    "sg:classifiers":[
        {
            "category":"Real Estate",
            "subcategory":"Real Estate Operator",
            "type":"Services"
        }
    ],
    "sg:phone":"+1 612 870 0331",
    "sg:postcode":"55404",
    "sg:province":"MN",
    "sg:tags":[
        "apartment"
    ],
    "sg:website":"fairoaksmpls.com",
    "wof:name":"Fair Oaks Apartment Homes",
    "wof:placetype":"venue"
},
  "geometry": {"coordinates":[-93.27273599999999,44.958911],"type":"Point"}
}