{
  "type": "Feature",
  "properties": {
    "addr:full":"14051 Cha-Lisa Rd Lake Park MN 56554",
    "addr:housenumber":"14051",
    "addr:postcode":"56554",
    "addr:street":"Cha-Lisa Rd",
    "iso:country":"US",
    "sg:address":"14051 Cha-Lisa Rd",
    "sg:city":"Lake Park",
    "sg:classifiers":[
        {
            "category":"Insurance",
            "subcategory":"Insurance Agent",
            "type":"Services"
        }
    ],
    "sg:phone":"+1 218 532 3107",
    "sg:postcode":"56554",
    "sg:province":"MN",
    "wof:name":"Lakes Insurance Agency",
    "wof:placetype":"venue"
},
  "geometry": {"coordinates":[-96.078057,46.777088],"type":"Point"}
}