{
  "type": "Feature",
  "properties": {
    "iso:country":"US",
    "sg:address":"14308 Park Ave",
    "sg:city":"Burnsville",
    "sg:classifiers":[
        {
            "category":"Shopping",
            "subcategory":"Gifts & Souvenirs",
            "type":"Retail Goods"
        }
    ],
    "sg:phone":"+1 952 891 3300",
    "sg:postcode":"55337",
    "sg:province":"MN",
    "wof:name":"Spectacular Gifts Inc",
    "wof:placetype":"venue"
},
  "geometry": {"coordinates":[-93.261421,44.742796],"type":"Point"}
}