{
  "type": "Feature",
  "properties": {
    "iso:country":"US",
    "sg:address":"27138 Bayshore Dr NW",
    "sg:city":"Isanti",
    "sg:classifiers":[
        {
            "category":"Building & Trades",
            "subcategory":"Construction",
            "type":"Services"
        }
    ],
    "sg:phone":"+1 612 328 1446",
    "sg:postcode":"55040",
    "sg:province":"MN",
    "sg:tags":[
        "house"
    ],
    "wof:name":"Deck Works Design & Cnstr",
    "wof:placetype":"venue"
},
  "geometry": {"coordinates":[-93.354632,45.458591],"type":"Point"}
}