{
  "type": "Feature",
  "properties": {
    "addr:full":"355 Wagon Wheel Ln Chaska MN 55318",
    "addr:housenumber":"355",
    "addr:postcode":"55318",
    "addr:street":"Wagon Wheel Ln",
    "iso:country":"US",
    "sg:address":"355 Wagon Wheel Ln",
    "sg:city":"Chaska",
    "sg:classifiers":[
        {
            "category":"Insurance",
            "subcategory":"Insurance Agent",
            "type":"Services"
        }
    ],
    "sg:phone":"+1 952 361 3779",
    "sg:postcode":"55318",
    "sg:province":"MN",
    "wof:name":"Horstman Insurance Agency",
    "wof:placetype":"venue"
},
  "geometry": {"coordinates":[-93.596215,44.825129],"type":"Point"}
}