{
  "type": "Feature",
  "properties": {
    "addr:full":"501 8th St N Northwood MN 50459",
    "addr:housenumber":"501",
    "addr:postcode":"50459",
    "addr:street":"8Th St N",
    "iso:country":"US",
    "sg:address":"501 8th St N",
    "sg:city":"Northwood",
    "sg:classifiers":[
        {
            "category":"Shopping",
            "subcategory":"Used Merchandise",
            "type":"Retail Goods"
        }
    ],
    "sg:phone":"+1 641 324 2988",
    "sg:postcode":"50459",
    "sg:province":"MN",
    "sg:tags":[
        "shop",
        "consignment"
    ],
    "wof:name":"Rhonda's Re-Threads & Antiques",
    "wof:placetype":"venue"
},
  "geometry": {"coordinates":[-93.22089099999999,43.450671],"type":"Point"}
}