{
  "type": "Feature",
  "properties": {
    "iso:country":"US",
    "sg:address":"1806 Saint Clair Ave",
    "sg:city":"Saint Paul",
    "sg:classifiers":[
        {
            "category":"Restaurant",
            "type":"Food & Drink"
        }
    ],
    "sg:phone":"+1 651 690 0555",
    "sg:postcode":"55105",
    "sg:province":"MN",
    "wof:name":"Pierres Grill & Cafe",
    "wof:placetype":"venue"
},
  "geometry": {"coordinates":[-93.17600299999999,44.934399],"type":"Point"}
}