{
  "type": "Feature",
  "properties": {
    "iso:country":"US",
    "sg:address":"1174 44th St NE",
    "sg:city":"Buffalo",
    "sg:classifiers":[
        {
            "category":"Organizations",
            "subcategory":"Religious Organization",
            "type":"Services"
        }
    ],
    "sg:phone":"+1 763 682 4616",
    "sg:postcode":"55313",
    "sg:province":"MN",
    "sg:tags":[
        "church"
    ],
    "wof:name":"Buffalo Unitarian Unvrslst",
    "wof:placetype":"venue"
},
  "geometry": {"coordinates":[-93.867769,45.214175],"type":"Point"}
}