{
  "type": "Feature",
  "properties": {
    "addr:full":"26001 Heinz Rd Willow River MN 55795",
    "addr:postcode":"26001;55795",
    "addr:street":"Heinz Rd",
    "iso:country":"US",
    "sg:address":"26001 Heinz Rd",
    "sg:city":"Willow River",
    "sg:classifiers":[
        {
            "category":"Travel",
            "subcategory":"Campground",
            "type":"Entertainment"
        }
    ],
    "sg:phone":"+1 218 372 3988",
    "sg:postcode":"55795",
    "sg:province":"MN",
    "sg:tags":[
        "camp"
    ],
    "sg:website":"www.campheartland.org",
    "wof:name":"Camp Heartland Ctr",
    "wof:placetype":"venue"
},
  "geometry": {"coordinates":[-92.86657700000001,46.299192],"type":"Point"}
}