{
  "type": "Feature",
  "properties": {
    "iso:country":"US",
    "sg:address":"2700 Winter St NE",
    "sg:city":"Minneapolis",
    "sg:classifiers":[
        {
            "category":"Shopping",
            "subcategory":"Department Store",
            "type":"Retail Goods"
        }
    ],
    "sg:phone":"+1 612 379 5600",
    "sg:postcode":"55413",
    "sg:province":"MN",
    "sg:tags":[
        "outlet"
    ],
    "wof:name":"Sear Logistics Services",
    "wof:placetype":"venue"
},
  "geometry": {"coordinates":[-93.217044,44.993426],"type":"Point"}
}