{
  "type": "Feature",
  "properties": {
    "addr:full":"2017 96th Ave N Minneapolis MN 55444",
    "addr:housenumber":"2017",
    "addr:postcode":"55444",
    "addr:street":"96Th Ave N",
    "iso:country":"US",
    "sg:address":"2017 96th Ave N",
    "sg:city":"Minneapolis",
    "sg:classifiers":[
        {
            "category":"Home & Garden",
            "subcategory":"Garden Supply",
            "type":"Retail Goods"
        }
    ],
    "sg:phone":"+1 763 425 1992",
    "sg:postcode":"55444",
    "sg:province":"MN",
    "sg:tags":[
        "embroidery"
    ],
    "wof:name":"Jackman Embroidery",
    "wof:placetype":"venue"
},
  "geometry": {"coordinates":[-93.307086,45.129082],"type":"Point"}
}