{
  "type": "Feature",
  "properties": {
    "iso:country":"US",
    "sg:address":"20945 Independence Ave",
    "sg:city":"Lakeville",
    "sg:classifiers":[
        {
            "category":"Building & Trades",
            "subcategory":"Construction",
            "type":"Services"
        }
    ],
    "sg:phone":"+1 612 852 8542",
    "sg:postcode":"55044",
    "sg:province":"MN",
    "sg:tags":[
        "tile-contractors",
        "contractor"
    ],
    "wof:name":"Full Tile Installation Company",
    "wof:placetype":"venue"
},
  "geometry": {"coordinates":[-93.255922,44.6458],"type":"Point"}
}