{
  "type": "Feature",
  "properties": {
    "iso:country":"US",
    "sg:address":"1561 2nd Ave",
    "sg:city":"Heron Lake",
    "sg:classifiers":[
        {
            "category":"Real Estate",
            "subcategory":"Real Estate Agent",
            "type":"Services"
        }
    ],
    "sg:phone":"+1 507 793 0008",
    "sg:postcode":"56137",
    "sg:province":"MN",
    "sg:tags":[
        "cooperative"
    ],
    "wof:name":"New Vision Co-Op",
    "wof:placetype":"venue"
},
  "geometry": {"coordinates":[-95.325748,43.791309],"type":"Point"}
}