{
  "type": "Feature",
  "properties": {
    "iso:country":"US",
    "sg:address":"511 N 4th St",
    "sg:city":"Le Sueur",
    "sg:classifiers":[
        {
            "category":"Education",
            "subcategory":"School",
            "type":"Public Place"
        }
    ],
    "sg:phone":"+1 507 665 2489",
    "sg:postcode":"56058",
    "sg:province":"MN",
    "wof:name":"St Anne's School",
    "wof:placetype":"venue"
},
  "geometry": {"coordinates":[-93.90799800000001,44.464679],"type":"Point"}
}