{
  "type": "Feature",
  "properties": {
    "iso:country":"US",
    "sg:address":"312 1st St N",
    "sg:city":"Cold Spring",
    "sg:classifiers":[
        {
            "category":"Real Estate",
            "subcategory":"Real Estate Services",
            "type":"Services"
        }
    ],
    "sg:phone":"+1 320 685 8308",
    "sg:postcode":"56320",
    "sg:province":"MN",
    "sg:tags":[
        "abstract",
        "title"
    ],
    "wof:name":"Universal Title",
    "wof:placetype":"venue"
},
  "geometry": {"coordinates":[-94.42750700000001,45.456835],"type":"Point"}
}