{
  "type": "Feature",
  "properties": {
    "iso:country":"US",
    "sg:address":"6115 Stacy Trl",
    "sg:city":"Stacy",
    "sg:classifiers":[
        {
            "category":"Professional",
            "subcategory":"Accounting & Tax Preparation",
            "type":"Services"
        }
    ],
    "sg:phone":"+1 651 462 4882",
    "sg:postcode":"55079",
    "sg:province":"MN",
    "wof:name":"Ptm Tax Service",
    "wof:placetype":"venue"
},
  "geometry": {"coordinates":[-92.982377,45.396595],"type":"Point"}
}