{
  "type": "Feature",
  "properties": {
    "addr:full":"1005 Main St N Pine City MN 55063",
    "addr:housenumber":"1005",
    "addr:postcode":"55063",
    "addr:street":"Main St N",
    "iso:country":"US",
    "sg:address":"1005 Main St N",
    "sg:city":"Pine City",
    "sg:classifiers":[
        {
            "category":"Home & Garden",
            "subcategory":"Garden Supply",
            "type":"Retail Goods"
        }
    ],
    "sg:phone":"+1 320 629 7828",
    "sg:postcode":"55063",
    "sg:province":"MN",
    "sg:tags":[
        "equipment",
        "snow",
        "removal"
    ],
    "wof:name":"CESI-Promark Svc",
    "wof:placetype":"venue"
},
  "geometry": {"coordinates":[-92.9692,45.839331],"type":"Point"}
}