{
  "type": "Feature",
  "properties": {
    "addr:full":"184 Co Rd 14 Grand Marais MN 55604",
    "addr:housenumber":"184;14",
    "addr:postcode":"55604",
    "addr:street":"Co Rd",
    "iso:country":"US",
    "sg:address":"184 Co Rd 14",
    "sg:city":"Grand Marais",
    "sg:classifiers":[
        {
            "category":"Travel",
            "subcategory":"Hotels & Motels",
            "type":"Entertainment"
        }
    ],
    "sg:phone":"+1 218 387 1476",
    "sg:postcode":"55604",
    "sg:province":"MN",
    "sg:tags":[
        "operation"
    ],
    "wof:name":"Jager Haus Bed & Breakfast",
    "wof:placetype":"venue"
},
  "geometry": {"coordinates":[-90.17925,47.798242],"type":"Point"}
}