{
  "type": "Feature",
  "properties": {
    "addr:full":"6549 147th St W Savage MN 55378",
    "addr:housenumber":"6549",
    "addr:postcode":"55378",
    "addr:street":"147Th St W",
    "iso:country":"US",
    "sg:address":"6549 147th St W",
    "sg:city":"Savage",
    "sg:classifiers":[
        {
            "category":"Building & Trades",
            "subcategory":"Plumbing",
            "type":"Services"
        }
    ],
    "sg:phone":"+1 952 894 4555",
    "sg:postcode":"55378",
    "sg:province":"MN",
    "wof:name":"Salzer Plumbing Llc",
    "wof:placetype":"venue"
},
  "geometry": {"coordinates":[-93.365898,44.738998],"type":"Point"}
}