{
  "type": "Feature",
  "properties": {
    "addr:full":"226 1st St E Fosston MN 56542",
    "addr:housenumber":"226",
    "addr:postcode":"56542",
    "addr:street":"1St St E",
    "iso:country":"US",
    "sg:address":"226 1st St E",
    "sg:city":"Fosston",
    "sg:classifiers":[
        {
            "category":"Manufacturing",
            "subcategory":"Buildings",
            "type":"Manufacturing & Wholesale Goods"
        },
        {
            "category":"Building & Trades",
            "subcategory":"Construction",
            "type":"Services"
        }
    ],
    "sg:phone":"+1 218 435 1116",
    "sg:postcode":"56542",
    "sg:province":"MN",
    "sg:tags":[
        "home",
        "builder",
        "contractor"
    ],
    "wof:name":"A And R Building Contractors",
    "wof:placetype":"venue"
},
  "geometry": {"coordinates":[-95.749602,47.575099],"type":"Point"}
}