{
  "type": "Feature",
  "properties": {
    "iso:country":"US",
    "sg:address":"6900 Canby Trl",
    "sg:city":"Northfield",
    "sg:classifiers":[
        {
            "category":"Sports & Exercise",
            "subcategory":"Golf",
            "type":"Entertainment"
        }
    ],
    "sg:phone":"+1 952 652 2500",
    "sg:postcode":"55057",
    "sg:province":"MN",
    "sg:tags":[
        "shop",
        "course",
        "pro",
        "public"
    ],
    "sg:website":"www.willingersgc.com",
    "wof:name":"Willinger's Golf Club",
    "wof:placetype":"venue"
},
  "geometry": {"coordinates":[-93.320908,44.489594],"type":"Point"}
}