{
  "type": "Feature",
  "properties": {
    "addr:full":"10445 99th Pl N Osseo MN 55369",
    "addr:housenumber":"10445",
    "addr:postcode":"55369",
    "addr:street":"99Th Pl N",
    "iso:country":"US",
    "sg:address":"10445 99th Pl N",
    "sg:city":"Osseo",
    "sg:classifiers":[
        {
            "category":"Freight",
            "type":"Transportation"
        }
    ],
    "sg:phone":"+1 763 315 5966",
    "sg:postcode":"55369",
    "sg:province":"MN",
    "wof:name":"Joy Transportation",
    "wof:placetype":"venue"
},
  "geometry": {"coordinates":[-93.413085,45.136095],"type":"Point"}
}