{
  "type": "Feature",
  "properties": {
    "addr:full":"106 E Ross Ave Erskine MN 56535",
    "addr:housenumber":"106",
    "addr:postcode":"56535",
    "addr:street":"E Ross Ave",
    "iso:country":"US",
    "sg:address":"106 E Ross Ave",
    "sg:city":"Erskine",
    "sg:classifiers":[
        {
            "category":"Retail",
            "subcategory":"Repair Shop",
            "type":"Services"
        }
    ],
    "sg:phone":"+1 218 687 2525",
    "sg:postcode":"56535",
    "sg:province":"MN",
    "sg:tags":[
        "welding"
    ],
    "wof:name":"Erskine Welding",
    "wof:placetype":"venue"
},
  "geometry": {"coordinates":[-96.00854699999999,47.667778],"type":"Point"}
}