{
  "type": "Feature",
  "properties": {
    "addr:full":"9240 Lake Ave S Spicer MN 56288",
    "addr:housenumber":"9240",
    "addr:postcode":"56288",
    "addr:street":"Lake Ave S Spicer",
    "iso:country":"US",
    "sg:address":"9240 Lake Ave S",
    "sg:city":"Spicer",
    "sg:classifiers":[
        {
            "category":"Building & Trades",
            "subcategory":"Construction",
            "type":"Services"
        }
    ],
    "sg:phone":"+1 320 796 5583",
    "sg:postcode":"56288",
    "sg:province":"MN",
    "sg:tags":[
        "excavation",
        "contractor"
    ],
    "wof:name":"Jager Excavating",
    "wof:placetype":"venue"
},
  "geometry": {"coordinates":[-94.918887,45.228378],"type":"Point"}
}