{
  "type": "Feature",
  "properties": {
    "iso:country":"US",
    "sg:address":"3412 Library Ln",
    "sg:city":"Minneapolis",
    "sg:classifiers":[
        {
            "category":"Wholesale",
            "subcategory":"Sporting Goods",
            "type":"Manufacturing & Wholesale Goods"
        }
    ],
    "sg:phone":"+1 952 922 8471",
    "sg:postcode":"55426",
    "sg:province":"MN",
    "wof:name":"Human Performance Systems",
    "wof:placetype":"venue"
},
  "geometry": {"coordinates":[-93.36658300000001,44.942383],"type":"Point"}
}