{
  "type": "Feature",
  "properties": {
    "iso:country":"US",
    "sg:address":"5806 Blackshire Path",
    "sg:city":"Inver Grove Heights",
    "sg:classifiers":[
        {
            "category":"Building & Trades",
            "subcategory":"Cleaning & Sanitation",
            "type":"Services"
        }
    ],
    "sg:phone":"+1 651 457 9070",
    "sg:postcode":"55076",
    "sg:province":"MN",
    "sg:tags":[
        "maintenance"
    ],
    "wof:name":"Aztec Services Inc",
    "wof:placetype":"venue"
},
  "geometry": {"coordinates":[-93.053042,44.864794],"type":"Point"}
}