{
  "type": "Feature",
  "properties": {
    "iso:country":"US",
    "sg:address":"10633 Kade Point Rd",
    "sg:city":"Brainerd",
    "sg:classifiers":[
        {
            "category":"Building & Trades",
            "subcategory":"Construction",
            "type":"Services"
        }
    ],
    "sg:phone":"+1 218 828 7076",
    "sg:postcode":"56401",
    "sg:province":"MN",
    "sg:tags":[
        "general",
        "contractor"
    ],
    "wof:name":"Miller Brothers",
    "wof:placetype":"venue"
},
  "geometry": {"coordinates":[-94.224518,46.309233],"type":"Point"}
}