{
  "type": "Feature",
  "properties": {
    "addr:full":"2627 E 7th St Duluth MN 55812",
    "addr:housenumber":"2627",
    "addr:postcode":"55812",
    "addr:street":"E 7Th St",
    "iso:country":"US",
    "sg:address":"2627 E 7th St",
    "sg:city":"Duluth",
    "sg:classifiers":[
        {
            "category":"Wholesale",
            "subcategory":"Durable Goods & Equipment",
            "type":"Manufacturing & Wholesale Goods"
        }
    ],
    "sg:phone":"+1 218 724 7912",
    "sg:postcode":"55812",
    "sg:province":"MN",
    "sg:tags":[
        "mfr",
        "rep"
    ],
    "wof:name":"Business Case Resources",
    "wof:placetype":"venue"
},
  "geometry": {"coordinates":[-92.072575,46.817172],"type":"Point"}
}