{
  "type": "Feature",
  "properties": {
    "iso:country":"US",
    "sg:address":"7044 James Ave S",
    "sg:city":"Minneapolis",
    "sg:classifiers":[
        {
            "category":"Building & Trades",
            "subcategory":"Construction",
            "type":"Services"
        }
    ],
    "sg:phone":"+1 612 386 3588",
    "sg:postcode":"55423",
    "sg:province":"MN",
    "sg:tags":[
        "heavy"
    ],
    "wof:name":"Blackstone Corporation",
    "wof:placetype":"venue"
},
  "geometry": {"coordinates":[-93.30107,44.875307],"type":"Point"}
}