{
  "type": "Feature",
  "properties": {
    "addr:full":"400 2nd St S St Cloud MN 56301",
    "addr:housenumber":"400",
    "addr:postcode":"56301",
    "addr:street":"2Nd St S",
    "iso:country":"US",
    "sg:address":"400 2nd St S",
    "sg:city":"St Cloud",
    "sg:classifiers":[
        {
            "category":"Government",
            "subcategory":"Office",
            "type":"Public Place"
        }
    ],
    "sg:phone":"+1 320 650 3120",
    "sg:postcode":"56301",
    "sg:province":"MN",
    "sg:tags":[
        "village"
    ],
    "wof:name":"St Cloud Plumbing Inspection",
    "wof:placetype":"venue"
},
  "geometry": {"coordinates":[-94.15652,45.55927],"type":"Point"}
}