{
  "type": "Feature",
  "properties": {
    "addr:full":"25577 470th St Laporte MN 56461",
    "addr:housenumber":"25577",
    "addr:postcode":"56461",
    "addr:street":"470Th St",
    "iso:country":"US",
    "sg:address":"25577 470th St",
    "sg:city":"Laporte",
    "sg:classifiers":[
        {
            "category":"Building & Trades",
            "subcategory":"Construction",
            "type":"Services"
        }
    ],
    "sg:phone":"+1 218 224 2158",
    "sg:postcode":"56461",
    "sg:province":"MN",
    "sg:tags":[
        "concrete",
        "contractor"
    ],
    "wof:name":"Lauderbaugh Concrete & Masonry",
    "wof:placetype":"venue"
},
  "geometry": {"coordinates":[-94.82091,47.337883],"type":"Point"}
}