{
  "type": "Feature",
  "properties": {
    "addr:full":"10110 Hage Dr Rogers MN 55374",
    "addr:postcode":"10110;55374",
    "addr:street":"Hage Dr",
    "iso:country":"US",
    "sg:address":"10110 Hage Dr",
    "sg:city":"Rogers",
    "sg:classifiers":[
        {
            "category":"Home & Garden",
            "subcategory":"Building Materials",
            "type":"Retail Goods"
        }
    ],
    "sg:phone":"+1 763 498 7946",
    "sg:postcode":"55374",
    "sg:province":"MN",
    "wof:name":"Bobs Custom Stained Glass",
    "wof:placetype":"venue"
},
  "geometry": {"coordinates":[-93.61657599999999,45.139349],"type":"Point"}
}