{
  "type": "Feature",
  "properties": {
    "addr:full":"16817 Duluth Ave SE Prior Lake MN 55372",
    "addr:housenumber":"16817",
    "addr:postcode":"55372",
    "addr:street":"Duluth Ave Se",
    "iso:country":"US",
    "sg:address":"16817 Duluth Ave SE",
    "sg:city":"Prior Lake",
    "sg:classifiers":[
        {
            "category":"Building & Trades",
            "subcategory":"Landscaping Services",
            "type":"Services"
        }
    ],
    "sg:phone":"+1 952 447 0955",
    "sg:postcode":"55372",
    "sg:province":"MN",
    "sg:tags":[
        "residential",
        "construction",
        "general",
        "contractor"
    ],
    "wof:name":"Rock Creek Designers Bldrs LLC",
    "wof:placetype":"venue"
},
  "geometry": {"coordinates":[-93.430063,44.70651],"type":"Point"}
}