{
  "type": "Feature",
  "properties": {
    "addr:full":"1514 W 25th St Minneapolis MN 55405",
    "addr:housenumber":"1514",
    "addr:postcode":"55405",
    "addr:street":"W 25Th St",
    "iso:country":"US",
    "sg:address":"1514 W 25th St",
    "sg:city":"Minneapolis",
    "sg:classifiers":[
        {
            "category":"Personal",
            "type":"Services"
        }
    ],
    "sg:phone":"+1 612 377 3386",
    "sg:postcode":"55405",
    "sg:province":"MN",
    "wof:name":"Housing Consultant & Colorist",
    "wof:placetype":"venue"
},
  "geometry": {"coordinates":[-93.299582,44.957411],"type":"Point"}
}