{
  "type": "Feature",
  "properties": {
    "iso:country":"US",
    "sg:address":"859 Lakewood Hills Rd N",
    "sg:city":"Saint Paul",
    "sg:classifiers":[
        {
            "category":"Freight",
            "type":"Transportation"
        }
    ],
    "sg:phone":"+1 651 274 7756",
    "sg:postcode":"55123",
    "sg:province":"MN",
    "wof:name":"Rockwood Logistics Inc",
    "wof:placetype":"venue"
},
  "geometry": {"coordinates":[-93.13164999999999,44.793088],"type":"Point"}
}