{
  "type": "Feature",
  "properties": {
    "addr:full":"4517 Minnetonka Blvd Minneapolis MN 55416",
    "addr:housenumber":"4517",
    "addr:postcode":"55416",
    "addr:street":"Minnetonka Blvd",
    "iso:country":"US",
    "sg:address":"4517 Minnetonka Blvd",
    "sg:city":"Minneapolis",
    "sg:classifiers":[
        {
            "category":"Arts & Performance",
            "subcategory":"Theater",
            "type":"Entertainment"
        }
    ],
    "sg:phone":"+1 952 927 7144",
    "sg:postcode":"55416",
    "sg:province":"MN",
    "sg:tags":[
        "entertainer"
    ],
    "sg:website":"www.aaa-classicdancers.com",
    "wof:name":"AIM Consultation Inc",
    "wof:placetype":"venue"
},
  "geometry": {"coordinates":[-93.33647999999999,44.948382],"type":"Point"}
}