{
  "type": "Feature",
  "properties": {
    "iso:country":"US",
    "sg:address":"9260 County 17 Blvd",
    "sg:city":"Cannon Falls",
    "sg:classifiers":[
        {
            "category":"Wholesale",
            "subcategory":"Construction Materials",
            "type":"Manufacturing & Wholesale Goods"
        }
    ],
    "sg:phone":"+1 507 263 2995",
    "sg:postcode":"55009",
    "sg:province":"MN",
    "sg:tags":[
        "limestone",
        "lime"
    ],
    "wof:name":"Cliff Knoblauch Lime & Rock",
    "wof:placetype":"venue"
},
  "geometry": {"coordinates":[-92.844874,44.532209],"type":"Point"}
}