{
  "type": "Feature",
  "properties": {
    "addr:full":"1801 E 27th St Minneapolis MN 55407",
    "addr:housenumber":"1801",
    "addr:postcode":"55407",
    "addr:street":"E 27Th St",
    "iso:country":"US",
    "sg:address":"1801 E 27th St",
    "sg:city":"Minneapolis",
    "sg:classifiers":[
        {
            "category":"Professional",
            "subcategory":"Computer Services",
            "type":"Services"
        }
    ],
    "sg:phone":"+1 612 721 0086",
    "sg:postcode":"55407",
    "sg:province":"MN",
    "sg:tags":[
        "publisher",
        "software",
        "developer",
        "services-wholesale"
    ],
    "wof:name":"Olrich International Vent",
    "wof:placetype":"venue"
},
  "geometry": {"coordinates":[-93.24865699999999,44.953751],"type":"Point"}
}