{
  "type": "Feature",
  "properties": {
    "iso:country":"US",
    "sg:address":"25458 Co St Aid Hwy 17",
    "sg:city":"Freeport",
    "sg:classifiers":[
        {
            "category":"Professional",
            "subcategory":"Business Services",
            "type":"Services"
        }
    ],
    "sg:phone":"+1 320 836 2881",
    "sg:postcode":"56331",
    "sg:province":"MN",
    "sg:tags":[
        "broker",
        "merchandise"
    ],
    "wof:name":"Us Heavy Equipment Broker",
    "wof:placetype":"venue"
},
  "geometry": {"coordinates":[-94.642678,45.730384],"type":"Point"}
}