{
  "type": "Feature",
  "properties": {
    "iso:country":"US",
    "sg:address":"802 E 7th St",
    "sg:city":"Morris",
    "sg:classifiers":[
        {
            "category":"Organizations",
            "subcategory":"Membership Organization",
            "type":"Services"
        }
    ],
    "sg:phone":"+1 320 589 8898",
    "sg:postcode":"56267",
    "sg:province":"MN",
    "sg:tags":[
        "athletic"
    ],
    "wof:name":"Morris Baseball Assn",
    "wof:placetype":"venue"
},
  "geometry": {"coordinates":[-95.90196899999999,45.594217],"type":"Point"}
}