{
  "type": "Feature",
  "properties": {
    "iso:country":"US",
    "sg:address":"2603 166th Ave NW",
    "sg:city":"Andover",
    "sg:classifiers":[
        {
            "category":"Professional",
            "type":"Services"
        }
    ],
    "sg:phone":"+1 763 753 1861",
    "sg:postcode":"55304",
    "sg:province":"MN",
    "sg:tags":[
        "establishment"
    ],
    "wof:name":"Amalloy Inc",
    "wof:placetype":"venue"
},
  "geometry": {"coordinates":[-93.329999,45.271227],"type":"Point"}
}