{
  "type": "Feature",
  "properties": {
    "addr:full":"8713 Beard Rd Minneapolis MN 55431",
    "addr:housenumber":"8713",
    "addr:postcode":"55431",
    "addr:street":"Beard Rd",
    "iso:country":"US",
    "sg:address":"8713 Beard Rd",
    "sg:city":"Minneapolis",
    "sg:classifiers":[
        {
            "category":"Bars & Pubs",
            "type":"Food & Drink"
        }
    ],
    "sg:phone":"+1 952 835 2626",
    "sg:postcode":"55431",
    "sg:province":"MN",
    "sg:tags":[
        "drinking"
    ],
    "wof:name":"Cocktails CA",
    "wof:placetype":"venue"
},
  "geometry": {"coordinates":[-93.324551,44.845594],"type":"Point"}
}