{
  "type": "Feature",
  "properties": {
    "iso:country":"US",
    "sg:address":"16740 Welcome Ave SE",
    "sg:city":"Prior Lake",
    "sg:classifiers":[
        {
            "category":"Building & Trades",
            "subcategory":"Construction",
            "type":"Services"
        }
    ],
    "sg:phone":"+1 952 447 6084",
    "sg:postcode":"55372",
    "sg:province":"MN",
    "sg:tags":[
        "designer",
        "dealer",
        "pool",
        "swimming"
    ],
    "wof:name":"Designer Pools By Vossen Inc",
    "wof:placetype":"venue"
},
  "geometry": {"coordinates":[-93.40158599999999,44.707485],"type":"Point"}
}