{
  "type": "Feature",
  "properties": {
    "addr:full":"1918 8th Ave Two Harbors MN 55616",
    "addr:housenumber":"1918",
    "addr:postcode":"55616",
    "addr:street":"8Th Ave",
    "iso:country":"US",
    "sg:address":"1918 8th Ave",
    "sg:city":"Two Harbors",
    "sg:classifiers":[
        {
            "category":"Building & Trades",
            "subcategory":"Construction",
            "type":"Services"
        }
    ],
    "sg:phone":"+1 218 834 3868",
    "sg:postcode":"55616",
    "sg:province":"MN",
    "sg:tags":[
        "excavation",
        "contractor"
    ],
    "wof:name":"Bill Twining Electrical Contr",
    "wof:placetype":"venue"
},
  "geometry": {"coordinates":[-91.698504,47.025991],"type":"Point"}
}