{
  "type": "Feature",
  "properties": {
    "iso:country":"US",
    "sg:address":"11276 210th St W",
    "sg:city":"Lakeville",
    "sg:classifiers":[
        {
            "category":"Restaurant",
            "type":"Food & Drink"
        }
    ],
    "sg:phone":"+1 952 469 6699",
    "sg:postcode":"55044",
    "sg:province":"MN",
    "wof:name":"Pizza 'N' Pasta",
    "wof:placetype":"venue"
},
  "geometry": {"coordinates":[-93.29846999999999,44.645123],"type":"Point"}
}