{
  "type": "Feature",
  "properties": {
    "addr:full":"24917 Co Rd 7 Saint Cloud MN 56301",
    "addr:housenumber":"24917;7",
    "addr:postcode":"56301",
    "addr:street":"Co Rd",
    "iso:country":"US",
    "sg:address":"24917 Co Rd 7",
    "sg:city":"Saint Cloud",
    "sg:classifiers":[
        {
            "category":"Freight",
            "type":"Transportation"
        }
    ],
    "sg:phone":"+1 320 251 7271",
    "sg:postcode":"56301",
    "sg:province":"MN",
    "sg:tags":[
        "operator",
        "trucking"
    ],
    "wof:name":"M & K Express Inc",
    "wof:placetype":"venue"
},
  "geometry": {"coordinates":[-94.153586,45.483836],"type":"Point"}
}