{
  "type": "Feature",
  "properties": {
    "addr:full":"7445 France Ave S Edina MN 55435",
    "addr:housenumber":"7445",
    "addr:postcode":"55435",
    "addr:street":"France Ave S",
    "iso:country":"US",
    "sg:address":"7445 France Ave S",
    "sg:city":"Edina",
    "sg:classifiers":[
        {
            "category":"Professional",
            "subcategory":"Business Services",
            "type":"Services"
        }
    ],
    "sg:phone":"+1 952 941 8331",
    "sg:postcode":"55435",
    "sg:province":"MN",
    "sg:tags":[
        "appraiser"
    ],
    "wof:name":"R J Reese & Co Inc",
    "wof:placetype":"venue"
},
  "geometry": {"coordinates":[-93.328941,44.871105],"type":"Point"}
}