{
  "type": "Feature",
  "properties": {
    "iso:country":"US",
    "sg:address":"321 Central Ave E",
    "sg:city":"St Michael",
    "sg:classifiers":[
        {
            "category":"Personal",
            "subcategory":"Beauty Salon",
            "type":"Services"
        }
    ],
    "sg:phone":"+1 763 497 3848",
    "sg:postcode":"55376",
    "sg:province":"MN",
    "wof:name":"Central Hair Design",
    "wof:placetype":"venue"
},
  "geometry": {"coordinates":[-93.65488499999999,45.209921],"type":"Point"}
}