{
  "type": "Feature",
  "properties": {
    "addr:full":"14964 Appleton Ave NW Monticello MN 55362",
    "addr:housenumber":"14964",
    "addr:postcode":"55362",
    "addr:street":"Appleton Ave Nw",
    "iso:country":"US",
    "sg:address":"14964 Appleton Ave NW",
    "sg:city":"Monticello",
    "sg:classifiers":[
        {
            "category":"Manufacturing",
            "subcategory":"Textiles",
            "type":"Manufacturing & Wholesale Goods"
        }
    ],
    "sg:phone":"+1 763 878 2992",
    "sg:postcode":"55362",
    "sg:province":"MN",
    "sg:tags":[
        "finishing",
        "plant",
        "cotton"
    ],
    "wof:name":"Michael D Chouinard",
    "wof:placetype":"venue"
},
  "geometry": {"coordinates":[-93.90898900000001,45.3671],"type":"Point"}
}