{
  "type": "Feature",
  "properties": {
    "iso:country":"US",
    "sg:address":"281 E Kellogg Blvd",
    "sg:city":"St Paul",
    "sg:classifiers":[
        {
            "category":"Building & Trades",
            "subcategory":"Construction",
            "type":"Services"
        }
    ],
    "sg:phone":"+1 651 293 1532",
    "sg:postcode":"55105",
    "sg:province":"MN",
    "sg:tags":[
        "general",
        "contractor"
    ],
    "wof:name":"Frerichs Construction",
    "wof:placetype":"venue"
},
  "geometry": {"coordinates":[-93.08361600000001,44.948625],"type":"Point"}
}