{
  "type": "Feature",
  "properties": {
    "addr:full":"537 36 1/2 Ave NE Minneapolis MN 55418",
    "addr:housenumber":"1 / 2",
    "addr:postcode":"55418",
    "addr:street":"537 36;Ave Ne",
    "iso:country":"US",
    "sg:address":"537 36 1/2 Ave NE",
    "sg:city":"Minneapolis",
    "sg:classifiers":[
        {
            "category":"Education",
            "subcategory":"Music School",
            "type":"Public Place"
        }
    ],
    "sg:phone":"+1 612 781 5799",
    "sg:postcode":"55418",
    "sg:province":"MN",
    "sg:tags":[
        "instrument",
        "teacher",
        "musical"
    ],
    "wof:name":"Bartig Violin Service",
    "wof:placetype":"venue"
},
  "geometry": {"coordinates":[-93.258608,45.034785],"type":"Point"}
}