{
  "type": "Feature",
  "properties": {
    "iso:country":"US",
    "sg:address":"4924 33rd Ave S",
    "sg:city":"Minneapolis",
    "sg:classifiers":[
        {
            "category":"Casinos & Gambling",
            "type":"Entertainment"
        }
    ],
    "sg:phone":"+1 952 929 8718",
    "sg:postcode":"55417",
    "sg:province":"MN",
    "sg:website":"www.a-surebet.com",
    "wof:name":"Sure Bet",
    "wof:placetype":"venue"
},
  "geometry": {"coordinates":[-93.224406,44.913973],"type":"Point"}
}