{
  "type": "Feature",
  "properties": {
    "addr:full":"2233 University Ave W Saint Paul MN 55104",
    "addr:housenumber":"2233",
    "addr:postcode":"55104",
    "addr:street":"University Ave W",
    "iso:country":"US",
    "sg:address":"2233 University Ave W",
    "sg:city":"Saint Paul",
    "sg:classifiers":[
        {
            "category":"Professional",
            "subcategory":"Lawyer & Legal Services",
            "type":"Services"
        }
    ],
    "sg:phone":"+1 651 645 1211",
    "sg:postcode":"55104",
    "sg:province":"MN",
    "wof:name":"Winter Law Office",
    "wof:placetype":"venue"
},
  "geometry": {"coordinates":[-93.192123,44.961715],"type":"Point"}
}