{
  "type": "Feature",
  "properties": {
    "addr:full":"2009 Big Oak Dr Burnsville MN 55337",
    "addr:housenumber":"2009",
    "addr:postcode":"55337",
    "addr:street":"Big Oak Dr",
    "iso:country":"US",
    "sg:address":"2009 Big Oak Dr",
    "sg:city":"Burnsville",
    "sg:classifiers":[
        {
            "category":"Building & Trades",
            "subcategory":"Construction",
            "type":"Services"
        }
    ],
    "sg:phone":"+1 952 895 8854",
    "sg:postcode":"55337",
    "sg:province":"MN",
    "sg:tags":[
        "siding",
        "contractor"
    ],
    "wof:name":"Eagle Siding",
    "wof:placetype":"venue"
},
  "geometry": {"coordinates":[-93.305667,44.766075],"type":"Point"}
}