{
  "type": "Feature",
  "properties": {
    "iso:country":"US",
    "sg:address":"2575 W Doswell Ave",
    "sg:city":"St Paul",
    "sg:classifiers":[
        {
            "category":"Wholesale",
            "subcategory":"Scrap",
            "type":"Manufacturing & Wholesale Goods"
        }
    ],
    "sg:phone":"+1 612 282 3159",
    "sg:postcode":"55108",
    "sg:province":"MN",
    "sg:tags":[
        "recycling",
        "center"
    ],
    "wof:name":"BPA Recyclers/Schwartzman Co",
    "wof:placetype":"venue"
},
  "geometry": {"coordinates":[-93.20566599999999,44.981271],"type":"Point"}
}