{
  "type": "Feature",
  "properties": {
    "iso:country":"US",
    "sg:address":"400 S Broadway",
    "sg:city":"Rochester",
    "sg:classifiers":[
        {
            "category":"Health Services",
            "subcategory":"Health Practitioner",
            "type":"Services"
        }
    ],
    "sg:phone":"+1 507 252 5700",
    "sg:postcode":"55904",
    "sg:province":"MN",
    "sg:tags":[
        "psychologist"
    ],
    "wof:name":"Center For Personal & Pro",
    "wof:placetype":"venue"
},
  "geometry": {"coordinates":[-92.46314,44.01706],"type":"Point"}
}