{
  "type": "Feature",
  "properties": {
    "iso:country":"US",
    "sg:address":"2 Appletree Sq Fl 4",
    "sg:city":"Minneapolis",
    "sg:classifiers":[
        {
            "category":"Professional",
            "subcategory":"Advertising",
            "type":"Services"
        },
        {
            "category":"Communications",
            "subcategory":"Radio Station",
            "type":"Services"
        },
        {
            "category":"Professional",
            "subcategory":"Business Services",
            "type":"Services"
        }
    ],
    "sg:phone":"+1 952 854 3100",
    "sg:postcode":"55425",
    "sg:province":"MN",
    "sg:tags":[
        "coach",
        "publicity",
        "consultant",
        "agency",
        "specialty",
        "broker",
        "medium"
    ],
    "sg:website":"http://www.campusmediagroupinc.com",
    "wof:name":"Campus Media Group, Inc.",
    "wof:placetype":"venue"
},
  "geometry": {"coordinates":[-93.222137,44.857166],"type":"Point"}
}