{
  "type": "Feature",
  "properties": {
    "addr:full":"303 E Nicollet Blvd Ste 160 Burnsville MN 55337",
    "addr:housenumber":"303",
    "addr:postcode":"55337",
    "addr:street":"E Nicollet Blvd Ste 160",
    "iso:country":"US",
    "sg:address":"303 E Nicollet Blvd Ste 160",
    "sg:city":"Burnsville",
    "sg:classifiers":[
        {
            "category":"Health Services",
            "subcategory":"Doctor",
            "type":"Services"
        }
    ],
    "sg:phone":"+1 952 892 8770",
    "sg:postcode":"55337",
    "sg:province":"MN",
    "sg:tags":[
        "medicine",
        "physician",
        "surgeon",
        "internal",
        "surgeons"
    ],
    "wof:name":"Pallegar Krishna Md",
    "wof:placetype":"venue"
},
  "geometry": {"coordinates":[-93.271311,44.750112],"type":"Point"}
}