{
  "type": "Feature",
  "properties": {
    "addr:full":"481 2nd St Excelsior MN 55331",
    "addr:housenumber":"481",
    "addr:postcode":"55331",
    "addr:street":"2Nd St",
    "iso:country":"US",
    "sg:address":"481 2nd St",
    "sg:city":"Excelsior",
    "sg:classifiers":[
        {
            "category":"Autos & Motor Vehicles",
            "subcategory":"Fuel & Gas Station",
            "type":"Retail Goods"
        },
        {
            "category":"Food & Beverages",
            "subcategory":"Groceries & Convenience Stores",
            "type":"Retail Goods"
        }
    ],
    "sg:phone":"+1 952 470 6600",
    "sg:postcode":"55331",
    "sg:province":"MN",
    "sg:website":"www.bp.com",
    "wof:name":"Koehnen's Bp",
    "wof:placetype":"venue"
},
  "geometry": {"coordinates":[-93.56454100000001,44.902907],"type":"Point"}
}