{
  "type": "Feature",
  "properties": {
    "iso:country":"US",
    "sg:address":"2056 W Broadway Ave",
    "sg:city":"Minneapolis",
    "sg:classifiers":[
        {
            "category":"Real Estate",
            "subcategory":"Real Estate Agent",
            "type":"Services"
        }
    ],
    "sg:phone":"+1 612 522 8888",
    "sg:postcode":"55411",
    "sg:province":"MN",
    "wof:name":"Hometown Realty MN",
    "wof:placetype":"venue"
},
  "geometry": {"coordinates":[-93.30579299999999,45.00225],"type":"Point"}
}