{
  "type": "Feature",
  "properties": {
    "addr:full":"18230 360th Ave Cyrus MN 56323",
    "addr:housenumber":"18230",
    "addr:postcode":"56323",
    "addr:street":"360Th Ave",
    "iso:country":"US",
    "sg:address":"18230 360th Ave",
    "sg:city":"Cyrus",
    "sg:classifiers":[
        {
            "category":"Personal",
            "subcategory":"Beauty Salon",
            "type":"Services"
        }
    ],
    "sg:phone":"+1 320 239 2929",
    "sg:postcode":"56323",
    "sg:province":"MN",
    "sg:tags":[
        "shop"
    ],
    "wof:name":"Hair Mix",
    "wof:placetype":"venue"
},
  "geometry": {"coordinates":[-95.676079,45.640116],"type":"Point"}
}