{
  "type": "Feature",
  "properties": {
    "addr:full":"1406 Prairie Ave NW Staples MN 56479",
    "addr:housenumber":"1406",
    "addr:postcode":"56479",
    "addr:street":"Prairie Ave Nw",
    "iso:country":"US",
    "sg:address":"1406 Prairie Ave NW",
    "sg:city":"Staples",
    "sg:classifiers":[
        {
            "category":"Building & Trades",
            "subcategory":"Construction",
            "type":"Services"
        }
    ],
    "sg:phone":"+1 218 894 0074",
    "sg:postcode":"56479",
    "sg:province":"MN",
    "sg:tags":[
        "concrete",
        "contractor"
    ],
    "sg:website":"www.stampedinstone.com",
    "wof:name":"Verlennich Masonry & Concrete",
    "wof:placetype":"venue"
},
  "geometry": {"coordinates":[-94.814527,46.375694],"type":"Point"}
}