{
  "type": "Feature",
  "properties": {
    "iso:country":"US",
    "sg:address":"9031 Victoria Gdns",
    "sg:city":"Minneapolis",
    "sg:classifiers":[
        {
            "category":"Building & Trades",
            "subcategory":"Construction",
            "type":"Services"
        }
    ],
    "sg:phone":"+1 763 425 7678",
    "sg:postcode":"55443",
    "sg:province":"MN",
    "sg:tags":[
        "painter"
    ],
    "wof:name":"A-1 Superior Painting Inc",
    "wof:placetype":"venue"
},
  "geometry": {"coordinates":[-93.35189800000001,45.118599],"type":"Point"}
}