{
  "type": "Feature",
  "properties": {
    "addr:full":"2988 Rice St Saint Paul MN 55113",
    "addr:housenumber":"2988",
    "addr:postcode":"55113",
    "addr:street":"Rice St",
    "iso:country":"US",
    "sg:address":"2988 Rice St",
    "sg:city":"Saint Paul",
    "sg:classifiers":[
        {
            "category":"Professional",
            "subcategory":"Lawyer & Legal Services",
            "type":"Services"
        }
    ],
    "sg:phone":"+1 651 486 6323",
    "sg:postcode":"55113",
    "sg:province":"MN",
    "wof:name":"Fry Renae Lillegard",
    "wof:placetype":"venue"
},
  "geometry": {"coordinates":[-93.106082,45.029144],"type":"Point"}
}