{
  "type": "Feature",
  "properties": {
    "addr:full":"208 Co Rd 19 Odin MN 56128",
    "addr:housenumber":"208;19",
    "addr:postcode":"56128",
    "addr:street":"Co Rd",
    "iso:country":"US",
    "sg:address":"208 Co Rd 19",
    "sg:city":"Odin",
    "sg:classifiers":[
        {
            "category":"Organizations",
            "subcategory":"Religious Organization",
            "type":"Services"
        }
    ],
    "sg:phone":"+1 507 736 4546",
    "sg:postcode":"56128",
    "sg:province":"MN",
    "wof:name":"Zion/St Olaf Parsonage",
    "wof:placetype":"venue"
},
  "geometry": {"coordinates":[-96.023184,43.835107],"type":"Point"}
}