{
  "type": "Feature",
  "properties": {
    "iso:country":"US",
    "sg:address":"1608 4th Ave N",
    "sg:city":"Sartell",
    "sg:classifiers":[
        {
            "category":"Building & Trades",
            "subcategory":"Landscaping Services",
            "type":"Services"
        }
    ],
    "sg:phone":"+1 320 202 8100",
    "sg:postcode":"56377",
    "sg:province":"MN",
    "sg:tags":[
        "landscape"
    ],
    "wof:name":"Pine Creek Landscapes",
    "wof:placetype":"venue"
},
  "geometry": {"coordinates":[-94.211219,45.642019],"type":"Point"}
}