{
  "type": "Feature",
  "properties": {
    "iso:country":"US",
    "sg:address":"529 7th St S",
    "sg:city":"Minneapolis",
    "sg:classifiers":[
        {
            "category":"Real Estate",
            "subcategory":"Real Estate Operator",
            "type":"Services"
        }
    ],
    "sg:phone":"+1 612 332 8405",
    "sg:postcode":"55415",
    "sg:province":"MN",
    "sg:tags":[
        "property",
        "management"
    ],
    "wof:name":"Saint Anthony Real Estate",
    "wof:placetype":"venue"
},
  "geometry": {"coordinates":[-93.26436699999999,44.973538],"type":"Point"}
}