{
  "type": "Feature",
  "properties": {
    "iso:country":"US",
    "sg:address":"10000 Valley View Rd",
    "sg:city":"Eden Prairie",
    "sg:classifiers":[
        {
            "category":"Manufacturing",
            "subcategory":"Chemicals & Compounds",
            "type":"Manufacturing & Wholesale Goods"
        }
    ],
    "sg:phone":"+1 952 947 8700",
    "sg:postcode":"55344",
    "sg:province":"MN",
    "sg:tags":[
        "preparation",
        "pharmaceutical",
        "mfg",
        "testing",
        "laboratory"
    ],
    "wof:name":"Cima Labs Inc",
    "wof:placetype":"venue"
},
  "geometry": {"coordinates":[-93.403854,44.87139],"type":"Point"}
}