{
  "type": "Feature",
  "properties": {
    "addr:full":"27592 US Hwy 61 Red Wing MN 55066",
    "addr:postcode":"27592;55066",
    "addr:street":"Us Hwy 61",
    "iso:country":"US",
    "sg:address":"27592 US Hwy 61",
    "sg:city":"Red Wing",
    "sg:classifiers":[
        {
            "category":"Manufacturing",
            "subcategory":"Glass & Minerals",
            "type":"Manufacturing & Wholesale Goods"
        }
    ],
    "sg:phone":"+1 651 388 8996",
    "sg:postcode":"55066",
    "sg:province":"MN",
    "sg:tags":[
        "ready"
    ],
    "wof:name":"Cemstone Products Inc",
    "wof:placetype":"venue"
},
  "geometry": {"coordinates":[-92.480155,44.555938],"type":"Point"}
}