{
  "type": "Feature",
  "properties": {
    "addr:full":"125 Cleveland Ave SW Mcintosh MN 56556",
    "addr:housenumber":"125",
    "addr:postcode":"56556",
    "addr:street":"Cleveland Ave Sw",
    "iso:country":"US",
    "sg:address":"125 Cleveland Ave SW",
    "sg:city":"Mcintosh",
    "sg:classifiers":[
        {
            "category":"Food & Beverages",
            "subcategory":"Meat & Fish",
            "type":"Retail Goods"
        }
    ],
    "sg:phone":"+1 218 563 4945",
    "sg:postcode":"56556",
    "sg:province":"MN",
    "sg:tags":[
        "market"
    ],
    "wof:name":"Neil's Quality Meats",
    "wof:placetype":"venue"
},
  "geometry": {"coordinates":[-95.887733,47.636795],"type":"Point"}
}