{
  "type": "Feature",
  "properties": {
    "addr:full":"11747 Manning Ave S Hastings MN 55033",
    "addr:housenumber":"11747",
    "addr:postcode":"55033",
    "addr:street":"Manning Ave S Hastings",
    "iso:country":"US",
    "sg:address":"11747 Manning Ave S",
    "sg:city":"Hastings",
    "sg:classifiers":[
        {
            "category":"Personal",
            "type":"Services"
        }
    ],
    "sg:phone":"+1 651 325 5772",
    "sg:postcode":"55033",
    "sg:province":"MN",
    "sg:tags":[
        "towing"
    ],
    "wof:name":"Race Towing",
    "wof:placetype":"venue"
},
  "geometry": {"coordinates":[-92.8629,44.780261],"type":"Point"}
}