{
  "type": "Feature",
  "properties": {
    "addr:full":"5406 King Arthur Dr NW Rochester MN 55901",
    "addr:housenumber":"5406",
    "addr:postcode":"55901",
    "addr:street":"King Arthur Dr Nw",
    "iso:country":"US",
    "sg:address":"5406 King Arthur Dr NW",
    "sg:city":"Rochester",
    "sg:classifiers":[
        {
            "category":"Social Services",
            "subcategory":"Child Care",
            "type":"Services"
        }
    ],
    "sg:phone":"+1 507 281 1936",
    "sg:postcode":"55901",
    "sg:province":"MN",
    "sg:tags":[
        "day"
    ],
    "wof:name":"Christine A Long",
    "wof:placetype":"venue"
},
  "geometry": {"coordinates":[-92.553079,44.078307],"type":"Point"}
}