{
  "type": "Feature",
  "properties": {
    "addr:full":"211 W Main St Ada MN 56510",
    "addr:housenumber":"211",
    "addr:postcode":"56510",
    "addr:street":"W Main St",
    "iso:country":"US",
    "sg:address":"211 W Main St",
    "sg:city":"Ada",
    "sg:classifiers":[
        {
            "category":"Government",
            "subcategory":"Office",
            "type":"Public Place"
        }
    ],
    "sg:phone":"+1 218 784 3061",
    "sg:postcode":"56510",
    "sg:province":"MN",
    "wof:name":"Norman County ASC",
    "wof:placetype":"venue"
},
  "geometry": {"coordinates":[-96.51652199999999,47.298444],"type":"Point"}
}