{
  "type": "Feature",
  "properties": {
    "iso:country":"US",
    "sg:address":"118 Central Ave",
    "sg:city":"Nashwauk",
    "sg:classifiers":[
        {
            "category":"Professional",
            "subcategory":"Management & Consulting",
            "type":"Services"
        }
    ],
    "sg:phone":"+1 218 885 3242",
    "sg:postcode":"55769",
    "sg:province":"MN",
    "sg:tags":[
        "organization",
        "labor"
    ],
    "wof:name":"Minnesota Council 65",
    "wof:placetype":"venue"
},
  "geometry": {"coordinates":[-93.16737500000001,47.380393],"type":"Point"}
}