{
  "type": "Feature",
  "properties": {
    "iso:country":"US",
    "sg:address":"1474 210th Ave",
    "sg:city":"Canby",
    "sg:classifiers":[
        {
            "category":"Farming",
            "subcategory":"Livestock Farm",
            "type":"Manufacturing & Wholesale Goods"
        }
    ],
    "sg:phone":"+1 507 223 7970",
    "sg:postcode":"56220",
    "sg:province":"MN",
    "sg:tags":[
        "hog",
        "beef",
        "far",
        "corn",
        "cattle",
        "or",
        "feedlot"
    ],
    "wof:name":"J Reyerson",
    "wof:placetype":"venue"
},
  "geometry": {"coordinates":[-96.35897199999999,44.703205],"type":"Point"}
}