{
  "type": "Feature",
  "properties": {
    "addr:full":"664 Transfer Rd Saint Paul MN 55114",
    "addr:housenumber":"664",
    "addr:postcode":"55114",
    "addr:street":"Transfer Rd",
    "iso:country":"US",
    "sg:address":"664 Transfer Rd",
    "sg:city":"Saint Paul",
    "sg:classifiers":[
        {
            "category":"Professional",
            "subcategory":"Management & Consulting",
            "type":"Services"
        }
    ],
    "sg:phone":"+1 651 917 5300",
    "sg:postcode":"55114",
    "sg:province":"MN",
    "sg:tags":[
        "business"
    ],
    "wof:name":"Safety Awareness Inc No 734",
    "wof:placetype":"venue"
},
  "geometry": {"coordinates":[-93.183171,44.968811],"type":"Point"}
}