{
  "type": "Feature",
  "properties": {
    "addr:full":"300 1st St N Hackensack MN 56452",
    "addr:housenumber":"300",
    "addr:postcode":"56452",
    "addr:street":"1St St N",
    "iso:country":"US",
    "sg:address":"300 1st St N",
    "sg:city":"Hackensack",
    "sg:classifiers":[
        {
            "category":"Organizations",
            "subcategory":"Religious Organization",
            "type":"Services"
        }
    ],
    "sg:phone":"+1 218 675 6101",
    "sg:postcode":"56452",
    "sg:province":"MN",
    "wof:name":"Sacred Heart Catholic Church",
    "wof:placetype":"venue"
},
  "geometry": {"coordinates":[-94.521261,46.933232],"type":"Point"}
}