{
  "type": "Feature",
  "properties": {
    "addr:full":"15708 Highview Dr Saint Paul MN 55124",
    "addr:housenumber":"15708",
    "addr:postcode":"55124",
    "addr:street":"Highview Dr",
    "iso:country":"US",
    "sg:address":"15708 Highview Dr",
    "sg:city":"Saint Paul",
    "sg:classifiers":[
        {
            "category":"Manufacturing",
            "subcategory":"Toys & Sporting Goods",
            "type":"Manufacturing & Wholesale Goods"
        }
    ],
    "sg:phone":"+1 952 431 7438",
    "sg:postcode":"55124",
    "sg:province":"MN",
    "sg:tags":[
        "product",
        "mfg"
    ],
    "wof:name":"Bad Dog Lures",
    "wof:placetype":"venue"
},
  "geometry": {"coordinates":[-93.241077,44.722414],"type":"Point"}
}