{
  "type": "Feature",
  "properties": {
    "addr:full":"841 Main St N Winnebago MN 56098",
    "addr:housenumber":"841",
    "addr:postcode":"56098",
    "addr:street":"Main St N",
    "iso:country":"US",
    "sg:address":"841 Main St N",
    "sg:city":"Winnebago",
    "sg:classifiers":[
        {
            "category":"Government",
            "subcategory":"Office",
            "type":"Public Place"
        }
    ],
    "sg:phone":"+1 507 893 4621",
    "sg:postcode":"56098",
    "sg:province":"MN",
    "wof:name":"Faribault County Garage",
    "wof:placetype":"venue"
},
  "geometry": {"coordinates":[-94.165616,43.778024],"type":"Point"}
}