{
  "type": "Feature",
  "properties": {
    "addr:full":"3000 N Chestnut St Ste 20 Chaska MN 55318",
    "addr:housenumber":"3000",
    "addr:postcode":"55318",
    "addr:street":"N Chestnut St Ste 20",
    "iso:country":"US",
    "sg:address":"3000 N Chestnut St Ste 20",
    "sg:city":"Chaska",
    "sg:classifiers":[
        {
            "category":"Health Services",
            "subcategory":"Dentist",
            "type":"Services"
        }
    ],
    "sg:phone":"+1 952 361 0777",
    "sg:postcode":"55318",
    "sg:province":"MN",
    "sg:website":"www.parkdental.com",
    "wof:name":"Park Dental Chaska",
    "wof:placetype":"venue"
},
  "geometry": {"coordinates":[-93.602501,44.8214],"type":"Point"}
}