{
  "type": "Feature",
  "properties": {
    "addr:full":"5573 N Shore Dr Duluth MN 55804",
    "addr:housenumber":"5573",
    "addr:postcode":"55804",
    "addr:street":"N Shore Dr",
    "iso:country":"US",
    "sg:address":"5573 N Shore Dr",
    "sg:city":"Duluth",
    "sg:classifiers":[
        {
            "category":"Manufacturing",
            "subcategory":"Retail Goods",
            "type":"Manufacturing & Wholesale Goods"
        }
    ],
    "sg:phone":"+1 218 525 6765",
    "sg:postcode":"55804",
    "sg:province":"MN",
    "sg:tags":[
        "product",
        "mfg"
    ],
    "wof:name":"Engel Canada Inc",
    "wof:placetype":"venue"
},
  "geometry": {"coordinates":[-91.866299,46.909252],"type":"Point"}
}