{
  "type": "Feature",
  "properties": {
    "iso:country":"US",
    "sg:address":"1560 Hwy 55",
    "sg:city":"Hastings",
    "sg:classifiers":[
        {
            "category":"Government",
            "subcategory":"Court House",
            "type":"Public Place"
        }
    ],
    "sg:phone":"+1 651 438 4325",
    "sg:postcode":"55033",
    "sg:province":"MN",
    "sg:tags":[
        "state"
    ],
    "wof:name":"Dakota County District Court",
    "wof:placetype":"venue"
},
  "geometry": {"coordinates":[-92.885593,44.738426],"type":"Point"}
}