{
  "type": "Feature",
  "properties": {
    "addr:full":"7014 Co Rd 15 Montevideo MN 56265",
    "addr:housenumber":"7014",
    "addr:postcode":"56265",
    "addr:street":"Co Rd 15",
    "iso:country":"US",
    "sg:address":"7014 Co Rd 15",
    "sg:city":"Montevideo",
    "sg:classifiers":[
        {
            "category":"Retail",
            "subcategory":"Auto Repair",
            "type":"Services"
        }
    ],
    "sg:phone":"+1 320 226 5249",
    "sg:postcode":"56265",
    "sg:province":"MN",
    "sg:tags":[
        "truck"
    ],
    "wof:name":"Bradley's",
    "wof:placetype":"venue"
},
  "geometry": {"coordinates":[-95.748052,44.949382],"type":"Point"}
}