{
  "type": "Feature",
  "properties": {
    "addr:full":"275 3rd St S Suite 203 Stillwater MN 55082",
    "addr:housenumber":"275",
    "addr:postcode":"55082",
    "addr:street":"3Rd St S Suite 203",
    "iso:country":"US",
    "sg:address":"275 3rd St S Suite 203",
    "sg:city":"Stillwater",
    "sg:classifiers":[
        {
            "category":"Professional",
            "subcategory":"Lawyer & Legal Services",
            "type":"Services"
        }
    ],
    "sg:phone":"+1 651 439 1112",
    "sg:postcode":"55082",
    "sg:province":"MN",
    "sg:tags":[
        "attorney",
        "injury",
        "duo",
        "personal",
        "criminal",
        "dwi",
        "law"
    ],
    "sg:website":"http://www.tholelaw.com",
    "wof:name":"Eric Thole Law Office",
    "wof:placetype":"venue"
},
  "geometry": {"coordinates":[-92.808222,45.054583],"type":"Point"}
}