{
  "type": "Feature",
  "properties": {
    "addr:full":"33198 Co Hwy 61 Hinckley MN 55037",
    "addr:housenumber":"33198",
    "addr:postcode":"55037",
    "addr:street":"Co Hwy 61",
    "iso:country":"US",
    "sg:address":"33198 Co Hwy 61",
    "sg:city":"Hinckley",
    "sg:classifiers":[
        {
            "category":"Utilities",
            "subcategory":"Refuse",
            "type":"Services"
        }
    ],
    "sg:phone":"+1 320 384 6596",
    "sg:postcode":"55037",
    "sg:province":"MN",
    "sg:tags":[
        "landfill"
    ],
    "wof:name":"Hinckley Solid Waste Transfer",
    "wof:placetype":"venue"
},
  "geometry": {"coordinates":[-92.933089,46.035575],"type":"Point"}
}