{
  "type": "Feature",
  "properties": {
    "addr:full":"3103 Atwood Dr Hopkins MN 55305",
    "addr:housenumber":"3103",
    "addr:postcode":"55305",
    "addr:street":"Atwood Dr",
    "iso:country":"US",
    "sg:address":"3103 Atwood Dr",
    "sg:city":"Hopkins",
    "sg:classifiers":[
        {
            "category":"Wholesale",
            "subcategory":"Vending Machines",
            "type":"Manufacturing & Wholesale Goods"
        }
    ],
    "sg:phone":"+1 952 935 1209",
    "sg:postcode":"55305",
    "sg:province":"MN",
    "sg:tags":[
        "operator"
    ],
    "wof:name":"Oasis Vending Mtka",
    "wof:placetype":"venue"
},
  "geometry": {"coordinates":[-93.449459,44.947095],"type":"Point"}
}