{
  "type": "Feature",
  "properties": {
    "addr:full":"615 Anne St NW Ste A Bemidji MN 56601",
    "addr:housenumber":"615",
    "addr:postcode":"56601",
    "addr:street":"Anne St Nw Ste A",
    "iso:country":"US",
    "sg:address":"615 Anne St NW Ste A",
    "sg:city":"Bemidji",
    "sg:classifiers":[
        {
            "category":"Insurance",
            "subcategory":"Hazard Insurance",
            "type":"Services"
        }
    ],
    "sg:phone":"+1 218 751 0939",
    "sg:postcode":"56601",
    "sg:province":"MN",
    "sg:tags":[
        "commercial",
        "business"
    ],
    "sg:website":"http://www.statefarm.com",
    "wof:name":"State Farm Insurance",
    "wof:placetype":"venue"
},
  "geometry": {"coordinates":[-94.88534300000001,47.504978],"type":"Point"}
}