{
  "type": "Feature",
  "properties": {
    "iso:country":"US",
    "sg:address":"137 W Ciro St",
    "sg:city":"Truman",
    "sg:classifiers":[
        {
            "category":"Restaurant",
            "type":"Food & Drink"
        }
    ],
    "sg:phone":"+1 507 776 8388",
    "sg:postcode":"56088",
    "sg:province":"MN",
    "wof:name":"Truman Cafe",
    "wof:placetype":"venue"
},
  "geometry": {"coordinates":[-94.43660300000001,43.827644],"type":"Point"}
}