{
  "type": "Feature",
  "properties": {
    "addr:full":"3505 90th Ave SE Eyota MN 55934",
    "addr:housenumber":"3505",
    "addr:postcode":"55934",
    "addr:street":"90Th Ave Se",
    "iso:country":"US",
    "sg:address":"3505 90th Ave SE",
    "sg:city":"Eyota",
    "sg:classifiers":[
        {
            "category":"Shopping",
            "subcategory":"Clothing, Apparel, & Fashions",
            "type":"Retail Goods"
        }
    ],
    "sg:phone":"+1 507 545 2071",
    "sg:postcode":"55934",
    "sg:province":"MN",
    "sg:tags":[
        "r"
    ],
    "wof:name":"Sewing By Carolyn",
    "wof:placetype":"venue"
},
  "geometry": {"coordinates":[-92.29828000000001,43.963824],"type":"Point"}
}