{
  "type": "Feature",
  "properties": {
    "iso:country":"US",
    "sg:address":"2625 US Hwy 14",
    "sg:city":"Owatonna",
    "sg:classifiers":[
        {
            "category":"Shopping",
            "subcategory":"Clothing, Apparel, & Fashions",
            "type":"Retail Goods"
        }
    ],
    "sg:phone":"+1 507 451 1850",
    "sg:postcode":"55060",
    "sg:province":"MN",
    "sg:tags":[
        "shop",
        "bridal"
    ],
    "wof:name":"Mrs B's Bridal & Sewing",
    "wof:placetype":"venue"
},
  "geometry": {"coordinates":[-93.17953,44.05956],"type":"Point"}
}