{
  "type": "Feature",
  "properties": {
    "iso:country":"US",
    "sg:address":"32990 545th Ave",
    "sg:city":"New York Mills",
    "sg:phone":"+1 218 385 2832",
    "sg:postcode":"56567",
    "sg:province":"MN",
    "sg:tags":[
        "farm",
        "field",
        "grain",
        "cash",
        "crop"
    ],
    "wof:name":"Walter Tumberg",
    "wof:placetype":"venue"
},
  "geometry": {"coordinates":[-95.353201,46.439673],"type":"Point"}
}