{
  "type": "Feature",
  "properties": {
    "addr:full":"11112 Co Rd 17 SE Delano MN 55328",
    "addr:housenumber":"11112;17",
    "addr:postcode":"55328",
    "addr:street":"Co Rd;Se Delano",
    "iso:country":"US",
    "sg:address":"11112 Co Rd 17 SE",
    "sg:city":"Delano",
    "sg:classifiers":[
        {
            "category":"Building & Trades",
            "subcategory":"Construction",
            "type":"Services"
        }
    ],
    "sg:phone":"+1 763 972 2846",
    "sg:postcode":"55328",
    "sg:province":"MN",
    "sg:tags":[
        "floor",
        "laying",
        "contractor"
    ],
    "wof:name":"Kustom Karpet & Tile",
    "wof:placetype":"venue"
},
  "geometry": {"coordinates":[-93.778271,44.992257],"type":"Point"}
}