{
  "type": "Feature",
  "properties": {
    "iso:country":"US",
    "sg:address":"6525 Clementa Ave SW",
    "sg:city":"Montrose",
    "sg:classifiers":[
        {
            "category":"Personal",
            "subcategory":"Beauty Salon",
            "type":"Services"
        }
    ],
    "sg:phone":"+1 763 675 3349",
    "sg:postcode":"55363",
    "sg:province":"MN",
    "sg:tags":[
        "shop"
    ],
    "wof:name":"Judys Hair Styling",
    "wof:placetype":"venue"
},
  "geometry": {"coordinates":[-93.931695,45.057174],"type":"Point"}
}