{
  "type": "Feature",
  "properties": {
    "iso:country":"US",
    "sg:address":"24376 343rd Ave",
    "sg:city":"Belgrade",
    "sg:classifiers":[
        {
            "category":"Food & Beverages",
            "subcategory":"Dairy",
            "type":"Retail Goods"
        }
    ],
    "sg:phone":"+1 320 243 3238",
    "sg:postcode":"56312",
    "sg:province":"MN",
    "sg:tags":[
        "product"
    ],
    "wof:name":"Triple S Farms",
    "wof:placetype":"venue"
},
  "geometry": {"coordinates":[-94.82463,45.485279],"type":"Point"}
}