{
  "type": "Feature",
  "properties": {
    "addr:full":"33576 Xkimo St NW Cambridge MN 55008",
    "addr:postcode":"33576;55008",
    "addr:street":"Xkimo St Nw",
    "iso:country":"US",
    "sg:address":"33576 Xkimo St NW",
    "sg:city":"Cambridge",
    "sg:classifiers":[
        {
            "category":"Building & Trades",
            "subcategory":"Construction",
            "type":"Services"
        }
    ],
    "sg:phone":"+1 763 689 5721",
    "sg:postcode":"55008",
    "sg:province":"MN",
    "sg:tags":[
        "repairing",
        "remodeling",
        "contractor"
    ],
    "wof:name":"G A Austin Construction",
    "wof:placetype":"venue"
},
  "geometry": {"coordinates":[-93.397035,45.576961],"type":"Point"}
}