{
  "type": "Feature",
  "properties": {
    "addr:full":"43838 Falcon Ave Harris MN 55032",
    "addr:housenumber":"43838",
    "addr:postcode":"55032",
    "addr:street":"Falcon Ave",
    "iso:country":"US",
    "sg:address":"43838 Falcon Ave",
    "sg:city":"Harris",
    "sg:classifiers":[
        {
            "category":"Retail",
            "subcategory":"Auto Repair",
            "type":"Services"
        }
    ],
    "sg:phone":"+1 651 674 5449",
    "sg:postcode":"55032",
    "sg:province":"MN",
    "sg:tags":[
        "general"
    ],
    "wof:name":"Johns Transm Svc & Towing",
    "wof:placetype":"venue"
},
  "geometry": {"coordinates":[-93.00181600000001,45.584212],"type":"Point"}
}