{
  "type": "Feature",
  "properties": {
    "iso:country":"US",
    "sg:address":"1189 Eckert Ave SE",
    "sg:city":"Buffalo",
    "sg:classifiers":[
        {
            "category":"Professional",
            "subcategory":"Advertising",
            "type":"Services"
        }
    ],
    "sg:phone":"+1 763 684 1463",
    "sg:postcode":"55313",
    "sg:province":"MN",
    "wof:name":"Joshua Lee",
    "wof:placetype":"venue"
},
  "geometry": {"coordinates":[-93.796869,45.133897],"type":"Point"}
}