{
  "type": "Feature",
  "properties": {
    "iso:country":"US",
    "sg:address":"30 W Main St",
    "sg:city":"Crosby",
    "sg:classifiers":[
        {
            "category":"Communications",
            "subcategory":"Film & Video Production",
            "type":"Services"
        }
    ],
    "sg:phone":"+1 218 546 5967",
    "sg:postcode":"56441",
    "sg:province":"MN",
    "sg:tags":[
        "taping"
    ],
    "wof:name":"Ci Video Productions",
    "wof:placetype":"venue"
},
  "geometry": {"coordinates":[-93.953693,46.482352],"type":"Point"}
}