{
  "type": "Feature",
  "properties": {
    "iso:country":"US",
    "sg:address":"3300 Oakdale Ave N",
    "sg:city":"Robbinsdale",
    "sg:classifiers":[
        {
            "category":"Health Services",
            "subcategory":"Health Practitioner",
            "type":"Services"
        }
    ],
    "sg:phone":"+1 763 520 5906",
    "sg:postcode":"55422",
    "sg:province":"MN",
    "sg:tags":[
        "therapy"
    ],
    "wof:name":"Enterstomal Therapy",
    "wof:placetype":"venue"
},
  "geometry": {"coordinates":[-93.321692,45.014313],"type":"Point"}
}