{
  "type": "Feature",
  "properties": {
    "addr:full":"5737 State Hwy 70 Pine City MN 55063",
    "addr:housenumber":"5737",
    "addr:postcode":"55063",
    "addr:street":"State Hwy 70 Pine",
    "iso:country":"US",
    "sg:address":"5737 State Hwy 70",
    "sg:city":"Pine City",
    "sg:classifiers":[
        {
            "category":"Restaurant",
            "type":"Food & Drink"
        }
    ],
    "sg:phone":"+1 320 629 2645",
    "sg:postcode":"55063",
    "sg:province":"MN",
    "sg:tags":[
        "cafe"
    ],
    "wof:name":"Rock Creek Cafe Inc",
    "wof:placetype":"venue"
},
  "geometry": {"coordinates":[-92.992062,45.766775],"type":"Point"}
}