{
  "type": "Feature",
  "properties": {
    "addr:full":"7756 450th St Holdingford MN 56340",
    "addr:housenumber":"7756",
    "addr:postcode":"56340",
    "addr:street":"450Th St",
    "iso:country":"US",
    "sg:address":"7756 450th St",
    "sg:city":"Holdingford",
    "sg:classifiers":[
        {
            "category":"Farming",
            "subcategory":"Farm",
            "type":"Manufacturing & Wholesale Goods"
        }
    ],
    "sg:phone":"+1 320 573 2569",
    "sg:postcode":"56340",
    "sg:province":"MN",
    "sg:tags":[
        "crop",
        "general"
    ],
    "wof:name":"Robert Koehn",
    "wof:placetype":"venue"
},
  "geometry": {"coordinates":[-94.51260499999999,45.774467],"type":"Point"}
}