{
  "type": "Feature",
  "properties": {
    "addr:full":"4245 Pleason Ave NW Annandale MN 55302",
    "addr:housenumber":"4245",
    "addr:postcode":"55302",
    "addr:street":"Pleason Ave Nw",
    "iso:country":"US",
    "sg:address":"4245 Pleason Ave NW",
    "sg:city":"Annandale",
    "sg:classifiers":[
        {
            "category":"Building & Trades",
            "subcategory":"Construction",
            "type":"Services"
        }
    ],
    "sg:phone":"+1 320 274 8303",
    "sg:postcode":"55302",
    "sg:province":"MN",
    "sg:tags":[
        "concrete",
        "contractor"
    ],
    "wof:name":"French Lake Curb Co",
    "wof:placetype":"venue"
},
  "geometry": {"coordinates":[-94.210853,45.216128],"type":"Point"}
}