{
  "type": "Feature",
  "properties": {
    "addr:full":"119 Central Ave Lester Prairie MN 55354",
    "addr:housenumber":"119",
    "addr:postcode":"55354",
    "addr:street":"Central Ave",
    "iso:country":"US",
    "sg:address":"119 Central Ave",
    "sg:city":"Lester Prairie",
    "sg:classifiers":[
        {
            "category":"Professional",
            "subcategory":"Business Services",
            "type":"Services"
        }
    ],
    "sg:phone":"+1 320 395 2181",
    "sg:postcode":"55354",
    "sg:province":"MN",
    "sg:tags":[
        "embroidery"
    ],
    "wof:name":"J & P Stitches Embroidery",
    "wof:placetype":"venue"
},
  "geometry": {"coordinates":[-94.045041,44.884492],"type":"Point"}
}