{
  "type": "Feature",
  "properties": {
    "addr:full":"5525 Emerald Ave Mountain Iron MN 55768",
    "addr:housenumber":"5525",
    "addr:postcode":"55768",
    "addr:street":"Emerald Ave",
    "iso:country":"US",
    "sg:address":"5525 Emerald Ave",
    "sg:city":"Mountain Iron",
    "sg:classifiers":[
        {
            "category":"Professional",
            "subcategory":"Management & Consulting",
            "type":"Services"
        }
    ],
    "sg:phone":"+1 218 741 0750",
    "sg:postcode":"55768",
    "sg:province":"MN",
    "sg:tags":[
        "insurance",
        "business"
    ],
    "wof:name":"Northeast Service Cooperative",
    "wof:placetype":"venue"
},
  "geometry": {"coordinates":[-92.593485,47.516836],"type":"Point"}
}