{
  "type": "Feature",
  "properties": {
    "addr:full":"700 Dunwoody Blvd Minneapolis MN 55403",
    "addr:housenumber":"700",
    "addr:postcode":"55403",
    "addr:street":"Dunwoody Blvd",
    "iso:country":"US",
    "sg:address":"700 Dunwoody Blvd",
    "sg:city":"Minneapolis",
    "sg:classifiers":[
        {
            "category":"Social Services",
            "subcategory":"Job Training",
            "type":"Services"
        }
    ],
    "sg:phone":"+1 612 377 8432",
    "sg:postcode":"55403",
    "sg:province":"MN",
    "sg:tags":[
        "apprenticeship",
        "program"
    ],
    "wof:name":"Minneapolis Pipefitters Joint",
    "wof:placetype":"venue"
},
  "geometry": {"coordinates":[-93.289261,44.972057],"type":"Point"}
}