{
  "type": "Feature",
  "properties": {
    "iso:country":"US",
    "sg:address":"3169 Wellner Dr NE",
    "sg:city":"Rochester",
    "sg:classifiers":[
        {
            "category":"Personal",
            "subcategory":"Beauty Salon",
            "type":"Services"
        }
    ],
    "sg:phone":"+1 507 281 6393",
    "sg:postcode":"55906",
    "sg:province":"MN",
    "sg:tags":[
        "shop"
    ],
    "wof:name":"Salon Nouvo",
    "wof:placetype":"venue"
},
  "geometry": {"coordinates":[-92.45228899999999,44.05714],"type":"Point"}
}