{
  "type": "Feature",
  "properties": {
    "addr:full":"3804 Grand Ave S Minneapolis MN 55409",
    "addr:housenumber":"3804",
    "addr:postcode":"55409",
    "addr:street":"Grand Ave S",
    "iso:country":"US",
    "sg:address":"3804 Grand Ave S",
    "sg:city":"Minneapolis",
    "sg:classifiers":[
        {
            "category":"Restaurant",
            "type":"Food & Drink"
        }
    ],
    "sg:phone":"+1 612 822 8260",
    "sg:postcode":"55409",
    "sg:province":"MN",
    "sg:tags":[
        "new",
        "american",
        "brunch",
        "breakfast"
    ],
    "sg:website":"www.grandcafempls.com",
    "wof:name":"Grand Caf?",
    "wof:placetype":"venue"
},
  "geometry": {"coordinates":[-93.284718,44.933835],"type":"Point"}
}