{
  "type": "Feature",
  "properties": {
    "addr:full":"535 8th St NE Milaca MN 56353",
    "addr:housenumber":"535",
    "addr:postcode":"56353",
    "addr:street":"8Th St Ne",
    "iso:country":"US",
    "sg:address":"535 8th St NE",
    "sg:city":"Milaca",
    "sg:classifiers":[
        {
            "category":"Local Transit",
            "type":"Transportation"
        }
    ],
    "sg:phone":"+1 320 983 2494",
    "sg:postcode":"56353",
    "sg:province":"MN",
    "sg:tags":[
        "line"
    ],
    "wof:name":"Rum River Transportation",
    "wof:placetype":"venue"
},
  "geometry": {"coordinates":[-93.646497,45.762288],"type":"Point"}
}