{
  "type": "Feature",
  "properties": {
    "iso:country":"US",
    "sg:address":"1000 22nd St",
    "sg:city":"Cloquet",
    "sg:classifiers":[
        {
            "category":"Social Services",
            "subcategory":"Adult Care",
            "type":"Services"
        }
    ],
    "sg:phone":"+1 218 879 3547",
    "sg:postcode":"55720",
    "sg:province":"MN",
    "sg:tags":[
        "foster"
    ],
    "wof:name":"Pine Ridge Homes Spruce Home",
    "wof:placetype":"venue"
},
  "geometry": {"coordinates":[-92.4387,46.70803],"type":"Point"}
}