{
  "type": "Feature",
  "properties": {
    "iso:country":"US",
    "sg:address":"710 9th Ave S",
    "sg:city":"Sauk Rapids",
    "sg:classifiers":[
        {
            "category":"Building & Trades",
            "subcategory":"Plumbing",
            "type":"Services"
        }
    ],
    "sg:phone":"+1 320 252 3111",
    "sg:postcode":"56379",
    "sg:province":"MN",
    "sg:tags":[
        "conditioning",
        "air",
        "system",
        "contractor"
    ],
    "wof:name":"Granite City Refrigeration",
    "wof:placetype":"venue"
},
  "geometry": {"coordinates":[-94.1536,45.582547],"type":"Point"}
}