{
  "type": "Feature",
  "properties": {
    "addr:full":"735 9th St N Mountain Lake MN 56159",
    "addr:housenumber":"735",
    "addr:postcode":"56159",
    "addr:street":"9Th St N",
    "iso:country":"US",
    "sg:address":"735 9th St N",
    "sg:city":"Mountain Lake",
    "sg:classifiers":[
        {
            "category":"Shopping",
            "subcategory":"Gifts & Souvenirs",
            "type":"Retail Goods"
        }
    ],
    "sg:phone":"+1 507 427 2094",
    "sg:postcode":"56159",
    "sg:province":"MN",
    "wof:name":"Younique Printing & Crafts",
    "wof:placetype":"venue"
},
  "geometry": {"coordinates":[-94.934218,43.943856],"type":"Point"}
}