{
  "type": "Feature",
  "properties": {
    "addr:full":"190 Hunters Glen Rd Wayzata MN 55391",
    "addr:housenumber":"190",
    "addr:postcode":"55391",
    "addr:street":"Hunters Glen Rd",
    "iso:country":"US",
    "sg:address":"190 Hunters Glen Rd",
    "sg:city":"Wayzata",
    "sg:classifiers":[
        {
            "category":"Health Services",
            "subcategory":"Doctor",
            "type":"Services"
        }
    ],
    "sg:phone":"+1 952 470 9071",
    "sg:postcode":"55391",
    "sg:province":"MN",
    "sg:tags":[
        "physician",
        "surgery",
        "oral",
        "surgeons"
    ],
    "wof:name":"William P Frantzich",
    "wof:placetype":"venue"
},
  "geometry": {"coordinates":[-93.486435,44.975419],"type":"Point"}
}