{
  "type": "Feature",
  "properties": {
    "iso:country":"US",
    "sg:address":"10924 Greenbrier Rd",
    "sg:city":"Hopkins",
    "sg:classifiers":[
        {
            "category":"Sports & Exercise",
            "subcategory":"Gym",
            "type":"Entertainment"
        }
    ],
    "sg:phone":"+1 952 546 0777",
    "sg:postcode":"55305",
    "sg:province":"MN",
    "sg:tags":[
        "club",
        "health",
        "studio",
        "gymnasium"
    ],
    "wof:name":"Arete Health Fit",
    "wof:placetype":"venue"
},
  "geometry": {"coordinates":[-93.417682,44.951051],"type":"Point"}
}