{
  "type": "Feature",
  "properties": {
    "addr:full":"170 89th Ave NE Blaine MN 55434",
    "addr:housenumber":"170",
    "addr:postcode":"55434",
    "addr:street":"89Th Ave Ne",
    "iso:country":"US",
    "sg:address":"170 89th Ave NE",
    "sg:city":"Blaine",
    "sg:classifiers":[
        {
            "category":"Autos & Motor Vehicles",
            "subcategory":"Auto Supplies",
            "type":"Retail Goods"
        }
    ],
    "sg:phone":"+1 763 784 1040",
    "sg:postcode":"55434",
    "sg:province":"MN",
    "sg:tags":[
        "automobile",
        "parts"
    ],
    "wof:name":"Checker Auto Parts",
    "wof:placetype":"venue"
},
  "geometry": {"coordinates":[-93.26190699999999,45.131755],"type":"Point"}
}