{
  "type": "Feature",
  "properties": {
    "addr:full":"36182 County 7 Blvd Goodhue MN 55027",
    "addr:housenumber":"36182",
    "addr:postcode":"55027",
    "addr:street":"County 7 Blvd",
    "iso:country":"US",
    "sg:address":"36182 County 7 Blvd",
    "sg:city":"Goodhue",
    "sg:classifiers":[
        {
            "category":"Farming",
            "subcategory":"Dairy Farm",
            "type":"Manufacturing & Wholesale Goods"
        }
    ],
    "sg:phone":"+1 651 258 4112",
    "sg:postcode":"55027",
    "sg:province":"MN",
    "wof:name":"Leo Ryan",
    "wof:placetype":"venue"
},
  "geometry": {"coordinates":[-92.731801,44.424697],"type":"Point"}
}