{
  "type": "Feature",
  "properties": {
    "iso:country":"US",
    "sg:address":"1520 Co Rd 40",
    "sg:city":"Carver",
    "sg:classifiers":[
        {
            "category":"Building & Trades",
            "subcategory":"Construction",
            "type":"Services"
        }
    ],
    "sg:phone":"+1 952 448 3728",
    "sg:postcode":"55315",
    "sg:province":"MN",
    "sg:tags":[
        "excavation",
        "contractor"
    ],
    "wof:name":"Dwight Schultz Construction",
    "wof:placetype":"venue"
},
  "geometry": {"coordinates":[-93.63963699999999,44.751957],"type":"Point"}
}