{
  "type": "Feature",
  "properties": {
    "addr:full":"11239 Foley Blvd NW Coon Rapids MN 55448",
    "addr:housenumber":"11239",
    "addr:postcode":"55448",
    "addr:street":"Foley Blvd Nw",
    "iso:country":"US",
    "sg:address":"11239 Foley Blvd NW",
    "sg:city":"Coon Rapids",
    "sg:classifiers":[
        {
            "category":"Food & Beverages",
            "subcategory":"Liquor & Beverages",
            "type":"Retail Goods"
        }
    ],
    "sg:phone":"+1 763 755 5020",
    "sg:postcode":"55448",
    "sg:province":"MN",
    "wof:name":"Coon Rapids Warehouse Liquor",
    "wof:placetype":"venue"
},
  "geometry": {"coordinates":[-93.276498,45.172061],"type":"Point"}
}