{
  "type": "Feature",
  "properties": {
    "iso:country":"US",
    "sg:address":"7420 Unity Ave N",
    "sg:city":"Minneapolis",
    "sg:classifiers":[
        {
            "category":"Insurance",
            "subcategory":"Hazard Insurance",
            "type":"Services"
        }
    ],
    "sg:phone":"+1 763 503 0140",
    "sg:postcode":"55443",
    "sg:province":"MN",
    "sg:tags":[
        "commercial",
        "business"
    ],
    "wof:name":"Jeff Michaelson Agency",
    "wof:placetype":"venue"
},
  "geometry": {"coordinates":[-93.35236399999999,45.090149],"type":"Point"}
}