{
  "type": "Feature",
  "properties": {
    "addr:full":"2900 5th St S Moorhead MN 56560",
    "addr:housenumber":"2900",
    "addr:postcode":"56560",
    "addr:street":"5Th St S",
    "iso:country":"US",
    "sg:address":"2900 5th St S",
    "sg:city":"Moorhead",
    "sg:classifiers":[
        {
            "category":"Organizations",
            "subcategory":"Religious Organization",
            "type":"Services"
        }
    ],
    "sg:phone":"+1 218 233 1192",
    "sg:postcode":"56560",
    "sg:province":"MN",
    "sg:tags":[
        "church"
    ],
    "sg:website":"www.moorheadpresbyterian.org",
    "wof:name":"First Presbyterian Church",
    "wof:placetype":"venue"
},
  "geometry": {"coordinates":[-96.771744,46.845909],"type":"Point"}
}