{
  "type": "Feature",
  "properties": {
    "iso:country":"US",
    "sg:address":"56510 Doc Jones Rd",
    "sg:city":"Mankato",
    "sg:classifiers":[
        {
            "category":"Professional",
            "subcategory":"Business Services",
            "type":"Services"
        }
    ],
    "sg:phone":"+1 507 387 5487",
    "sg:postcode":"56001",
    "sg:province":"MN",
    "sg:tags":[
        "interior",
        "consultant",
        "design",
        "decorator"
    ],
    "wof:name":"Eunice Swanson-Classic Intrs",
    "wof:placetype":"venue"
},
  "geometry": {"coordinates":[-94.01265100000001,44.137566],"type":"Point"}
}