{
  "type": "Feature",
  "properties": {
    "addr:full":"38293 State Hwy 6 Emily MN 56447",
    "addr:housenumber":"38293",
    "addr:postcode":"56447",
    "addr:street":"State Hwy 6 Emily",
    "iso:country":"US",
    "sg:address":"38293 State Hwy 6",
    "sg:city":"Emily",
    "sg:classifiers":[
        {
            "category":"Building & Trades",
            "subcategory":"Construction",
            "type":"Services"
        }
    ],
    "sg:phone":"+1 218 763 2347",
    "sg:postcode":"56447",
    "sg:province":"MN",
    "sg:tags":[
        "general",
        "contractor"
    ],
    "wof:name":"J R Martz Construction",
    "wof:placetype":"venue"
},
  "geometry": {"coordinates":[-93.955753,46.705162],"type":"Point"}
}