{
  "type": "Feature",
  "properties": {
    "iso:country":"US",
    "sg:address":"1060 Commerce Blvd",
    "sg:city":"Howard Lake",
    "sg:classifiers":[
        {
            "category":"Manufacturing",
            "subcategory":"Tools & Machinery",
            "type":"Manufacturing & Wholesale Goods"
        }
    ],
    "sg:phone":"+1 320 543 3222",
    "sg:postcode":"55364",
    "sg:province":"MN",
    "sg:tags":[
        "polishing",
        "buffing",
        "lapping",
        "grinding"
    ],
    "wof:name":"Mass Finishing Inc",
    "wof:placetype":"venue"
},
  "geometry": {"coordinates":[-93.665814,44.95888],"type":"Point"}
}