{
  "type": "Feature",
  "properties": {
    "addr:full":"17846 447th Ave Glencoe MN 55336",
    "addr:housenumber":"17846",
    "addr:postcode":"55336",
    "addr:street":"447Th Ave",
    "iso:country":"US",
    "sg:address":"17846 447th Ave",
    "sg:city":"Glencoe",
    "sg:classifiers":[
        {
            "category":"Banks & Credit Unions",
            "subcategory":"Investment Brokerage",
            "type":"Services"
        }
    ],
    "sg:phone":"+1 320 864 3257",
    "sg:postcode":"55336",
    "sg:province":"MN",
    "sg:tags":[
        "advisory",
        "financial"
    ],
    "wof:name":"Agstar Financial Svc",
    "wof:placetype":"venue"
},
  "geometry": {"coordinates":[-94.167923,44.691033],"type":"Point"}
}