{
  "type": "Feature",
  "properties": {
    "addr:full":"3935 Solway Rd Duluth MN 55810",
    "addr:housenumber":"3935",
    "addr:postcode":"55810",
    "addr:street":"Solway Rd",
    "iso:country":"US",
    "sg:address":"3935 Solway Rd",
    "sg:city":"Duluth",
    "sg:classifiers":[
        {
            "category":"Home & Garden",
            "subcategory":"Garden Supply",
            "type":"Retail Goods"
        }
    ],
    "sg:phone":"+1 218 729 5549",
    "sg:postcode":"55810",
    "sg:province":"MN",
    "sg:tags":[
        "center"
    ],
    "wof:name":"Garden Creek",
    "wof:placetype":"venue"
},
  "geometry": {"coordinates":[-92.301877,46.796516],"type":"Point"}
}