{
  "type": "Feature",
  "properties": {
    "iso:country":"US",
    "sg:address":"10651 Grey Cloud Trl S",
    "sg:city":"Cottage Grove",
    "sg:classifiers":[
        {
            "category":"Building & Trades",
            "subcategory":"Landscaping Services",
            "type":"Services"
        }
    ],
    "sg:phone":"+1 651 459 4581",
    "sg:postcode":"55016",
    "sg:province":"MN",
    "wof:name":"Witzel Tree Moving",
    "wof:placetype":"venue"
},
  "geometry": {"coordinates":[-92.978071,44.792882],"type":"Point"}
}