{
  "type": "Feature",
  "properties": {
    "addr:full":"151 Northdale Blvd NW Coon Rapids MN 55448",
    "addr:housenumber":"151",
    "addr:postcode":"55448",
    "addr:street":"Northdale Blvd Nw",
    "iso:country":"US",
    "sg:address":"151 Northdale Blvd NW",
    "sg:city":"Coon Rapids",
    "sg:classifiers":[
        {
            "category":"Education",
            "subcategory":"School",
            "type":"Public Place"
        }
    ],
    "sg:phone":"+1 763 506 2300",
    "sg:postcode":"55448",
    "sg:province":"MN",
    "wof:name":"Eisenhower Elementary School",
    "wof:placetype":"venue"
},
  "geometry": {"coordinates":[-93.27002,45.170996],"type":"Point"}
}