{
  "type": "Feature",
  "properties": {
    "addr:full":"927 N Riverfront Dr Mankato MN 56001",
    "addr:housenumber":"927",
    "addr:postcode":"56001",
    "addr:street":"N Riverfront Dr",
    "iso:country":"US",
    "sg:address":"927 N Riverfront Dr",
    "sg:city":"Mankato",
    "sg:classifiers":[
        {
            "category":"Autos & Motor Vehicles",
            "subcategory":"Auto Supplies",
            "type":"Retail Goods"
        },
        {
            "category":"Retail",
            "subcategory":"Auto Repair",
            "type":"Services"
        }
    ],
    "sg:phone":"+1 866 313 6732",
    "sg:postcode":"56001",
    "sg:province":"MN",
    "sg:tags":[
        "automobile",
        "part",
        "truck"
    ],
    "sg:website":"http://clickserve.dartsearch.net/link/click?lid=43000000313870192&ds_s_kwgid=58000000006820725&ds_e_matchtype={MatchType}&ds_e_kwdid={OrderItemId}&ds_e_adid={AdId}&ds_url_v=2",
    "wof:name":"Tacheny's Autotronics",
    "wof:placetype":"venue"
},
  "geometry": {"coordinates":[-93.995141,44.17537],"type":"Point"}
}