{
  "type": "Feature",
  "properties": {
    "addr:full":"806 W Center St Apt 1 Rochester MN 55902",
    "addr:housenumber":"806;1",
    "addr:postcode":"55902",
    "addr:street":"W Center St Apt",
    "iso:country":"US",
    "sg:address":"806 W Center St Apt 1",
    "sg:city":"Rochester",
    "sg:classifiers":[
        {
            "category":"Building & Trades",
            "subcategory":"Construction",
            "type":"Services"
        }
    ],
    "sg:phone":"+1 507 398 3813",
    "sg:postcode":"55902",
    "sg:province":"MN",
    "sg:tags":[
        "wallcoverings-installation",
        "wallpaper",
        "painting",
        "contractor"
    ],
    "wof:name":"Lynwood & Sons Construction Services",
    "wof:placetype":"venue"
},
  "geometry": {"coordinates":[-92.47452800000001,44.023465],"type":"Point"}
}