{
  "type": "Feature",
  "properties": {
    "addr:full":"316 Pine St Monticello MN 55362",
    "addr:housenumber":"316",
    "addr:postcode":"55362",
    "addr:street":"Pine St",
    "iso:country":"US",
    "sg:address":"316 Pine St",
    "sg:city":"Monticello",
    "sg:classifiers":[
        {
            "category":"Utilities",
            "subcategory":"Telephone",
            "type":"Services"
        }
    ],
    "sg:phone":"+1 763 295 2974",
    "sg:postcode":"55362",
    "sg:province":"MN",
    "sg:tags":[
        "communications"
    ],
    "wof:name":"TDS",
    "wof:placetype":"venue"
},
  "geometry": {"coordinates":[-93.79492,45.304457],"type":"Point"}
}