{
  "type": "Feature",
  "properties": {
    "iso:country":"US",
    "sg:address":"318 Central Ave N",
    "sg:city":"Faribault",
    "sg:classifiers":[
        {
            "category":"Restaurant",
            "type":"Food & Drink"
        }
    ],
    "sg:phone":"+1 507 334 3002",
    "sg:postcode":"55021",
    "sg:province":"MN",
    "sg:tags":[
        "eating"
    ],
    "wof:name":"Long Cheng",
    "wof:placetype":"venue"
},
  "geometry": {"coordinates":[-93.268452,44.294554],"type":"Point"}
}