{
  "type": "Feature",
  "properties": {
    "addr:full":"608 Edgewater Dr Alexandria MN 56308",
    "addr:housenumber":"608",
    "addr:postcode":"56308",
    "addr:street":"Edgewater Dr",
    "iso:country":"US",
    "sg:address":"608 Edgewater Dr",
    "sg:city":"Alexandria",
    "sg:classifiers":[
        {
            "category":"Professional",
            "type":"Services"
        }
    ],
    "sg:phone":"+1 320 763 7535",
    "sg:postcode":"56308",
    "sg:province":"MN",
    "sg:tags":[
        "establishment"
    ],
    "wof:name":"All Stop-Virnig Heidi",
    "wof:placetype":"venue"
},
  "geometry": {"coordinates":[-95.379891,45.89666],"type":"Point"}
}