{
  "type": "Feature",
  "properties": {
    "addr:full":"21716 Kenrick Ave Lakeville MN 55044",
    "addr:postcode":"21716;55044",
    "addr:street":"Kenrick Ave",
    "iso:country":"US",
    "sg:address":"21716 Kenrick Ave",
    "sg:city":"Lakeville",
    "sg:classifiers":[
        {
            "category":"Freight",
            "type":"Transportation"
        }
    ],
    "sg:phone":"+1 952 985 5008",
    "sg:postcode":"55044",
    "sg:province":"MN",
    "sg:tags":[
        "storage",
        "household",
        "commercial",
        "special"
    ],
    "sg:website":"http://www.dunhamrental.com",
    "wof:name":"Dunham Rental Properties",
    "wof:placetype":"venue"
},
  "geometry": {"coordinates":[-93.293363,44.634787],"type":"Point"}
}