{
  "type": "Feature",
  "properties": {
    "addr:full":"26393 6th St W Zimmerman MN 55398",
    "addr:housenumber":"26393",
    "addr:postcode":"55398",
    "addr:street":"6Th St W",
    "iso:country":"US",
    "sg:address":"26393 6th St W",
    "sg:city":"Zimmerman",
    "sg:classifiers":[
        {
            "category":"Building & Trades",
            "subcategory":"Landscaping Services",
            "type":"Services"
        }
    ],
    "sg:phone":"+1 763 263 2275",
    "sg:postcode":"55398",
    "sg:province":"MN",
    "sg:tags":[
        "tree"
    ],
    "wof:name":"Oak Hill Tree & Landscaping",
    "wof:placetype":"venue"
},
  "geometry": {"coordinates":[-93.595873,45.447216],"type":"Point"}
}