{
  "type": "Feature",
  "properties": {
    "iso:country":"US",
    "sg:address":"1131 Oxford St",
    "sg:city":"Worthington",
    "sg:classifiers":[
        {
            "category":"Banks & Credit Unions",
            "subcategory":"Bank",
            "type":"Services"
        }
    ],
    "sg:phone":"+1 507 376 6450",
    "sg:postcode":"56187",
    "sg:province":"MN",
    "wof:name":"Bank Of The West",
    "wof:placetype":"venue"
},
  "geometry": {"coordinates":[-95.59961300000001,43.631235],"type":"Point"}
}