{
  "type": "Feature",
  "properties": {
    "addr:full":"8700 W 36th St Ste 207W Minneapolis MN 55426",
    "addr:housenumber":"8700",
    "addr:postcode":"55426",
    "addr:street":"W 36Th St Ste 207W",
    "iso:country":"US",
    "sg:address":"8700 W 36th St Ste 207W",
    "sg:city":"Minneapolis",
    "sg:classifiers":[
        {
            "category":"Insurance",
            "subcategory":"Insurance Agent",
            "type":"Services"
        },
        {
            "category":"Insurance",
            "subcategory":"Hazard Insurance",
            "type":"Services"
        },
        {
            "category":"Banks & Credit Unions",
            "subcategory":"Financial Services",
            "type":"Services"
        },
        {
            "category":"Professional",
            "subcategory":"Credit Reporting & Collection",
            "type":"Services"
        }
    ],
    "sg:phone":"+1 952 939 0431",
    "sg:postcode":"55426",
    "sg:province":"MN",
    "sg:tags":[
        "debt",
        "adjuster",
        "agency"
    ],
    "wof:name":"A & I Claim Service Inc",
    "wof:placetype":"venue"
},
  "geometry": {"coordinates":[-93.389427,44.938709],"type":"Point"}
}