{
  "type": "Feature",
  "properties": {
    "iso:country":"US",
    "sg:address":"15380 Co Rd 32",
    "sg:city":"Young America",
    "sg:classifiers":[
        {
            "category":"Real Estate",
            "subcategory":"Real Estate Operator",
            "type":"Services"
        }
    ],
    "sg:phone":"+1 952 657 2431",
    "sg:postcode":"55397",
    "sg:province":"MN",
    "sg:tags":[
        "property",
        "lessor"
    ],
    "wof:name":"Roger Sauerbrey",
    "wof:placetype":"venue"
},
  "geometry": {"coordinates":[-93.912415,44.848211],"type":"Point"}
}