{
  "type": "Feature",
  "properties": {
    "iso:country":"US",
    "sg:address":"9000 Lyndale Ave S",
    "sg:city":"Minneapolis",
    "sg:classifiers":[
        {
            "category":"Autos & Motor Vehicles",
            "subcategory":"Auto Supplies",
            "type":"Retail Goods"
        },
        {
            "category":"Retail",
            "subcategory":"Auto Repair",
            "type":"Services"
        }
    ],
    "sg:phone":"+1 952 884 6152",
    "sg:postcode":"55420",
    "sg:province":"MN",
    "sg:tags":[
        "tire"
    ],
    "wof:name":"Leroy's Great Bear Tire & Auto",
    "wof:placetype":"venue"
},
  "geometry": {"coordinates":[-93.289236,44.840349],"type":"Point"}
}