{
  "type": "Feature",
  "properties": {
    "iso:country":"US",
    "sg:address":"1624 Ridgewood Ln S",
    "sg:city":"Saint Paul",
    "sg:classifiers":[
        {
            "category":"Professional",
            "subcategory":"Employment Agencies",
            "type":"Services"
        }
    ],
    "sg:phone":"+1 651 251 1484",
    "sg:postcode":"55113",
    "sg:province":"MN",
    "wof:name":"Employment Counselors Inc",
    "wof:placetype":"venue"
},
  "geometry": {"coordinates":[-93.170709,45.001154],"type":"Point"}
}