{
  "type": "Feature",
  "properties": {
    "iso:country":"US",
    "sg:address":"8200 Ryan Lake Dr NE",
    "sg:city":"Stacy",
    "sg:classifiers":[
        {
            "category":"Building & Trades",
            "subcategory":"Construction",
            "type":"Services"
        }
    ],
    "sg:phone":"+1 651 462 5193",
    "sg:postcode":"55079",
    "sg:province":"MN",
    "sg:tags":[
        "excavation",
        "contractor"
    ],
    "wof:name":"Ronnie Bowman Excavating",
    "wof:placetype":"venue"
},
  "geometry": {"coordinates":[-93.059934,45.393693],"type":"Point"}
}