{
  "type": "Feature",
  "properties": {
    "addr:full":"1117 Civic Center Dr NW Rochester MN 55901",
    "addr:housenumber":"1117",
    "addr:postcode":"55901",
    "addr:street":"Civic Center Dr Nw",
    "iso:country":"US",
    "sg:address":"1117 Civic Center Dr NW",
    "sg:city":"Rochester",
    "sg:classifiers":[
        {
            "category":"Home & Garden",
            "subcategory":"Building Materials",
            "type":"Retail Goods"
        },
        {
            "category":"Manufacturing",
            "subcategory":"Building Materials",
            "type":"Manufacturing & Wholesale Goods"
        }
    ],
    "sg:phone":"+1 877 565 8447",
    "sg:postcode":"55901",
    "sg:province":"MN",
    "sg:tags":[
        "frames",
        "window",
        "doors",
        "accessory"
    ],
    "sg:website":"http://redirect.searchignite.com/si/cm/tracking/DGTrackingRedirect.aspx?siclientid=3825&siredirect=https%3A%2F%2Fweb%2Epella%2Ecom%2Fsupportcenter%2FPages%2FConsultation%2Easpx&sisearchengine=32&siproduct=DEX%5FEP&clearppc=1",
    "wof:name":"Pella Windows & Doors",
    "wof:placetype":"venue"
},
  "geometry": {"coordinates":[-92.484013,44.03005],"type":"Point"}
}