{
  "type": "Feature",
  "properties": {
    "addr:full":"7333 Lakeside Park Dr NE Remer MN 56672",
    "addr:housenumber":"7333",
    "addr:postcode":"56672",
    "addr:street":"Lakeside Park Dr Ne",
    "iso:country":"US",
    "sg:address":"7333 Lakeside Park Dr NE",
    "sg:city":"Remer",
    "sg:classifiers":[
        {
            "category":"Real Estate",
            "subcategory":"Real Estate Services",
            "type":"Services"
        },
        {
            "category":"Real Estate",
            "subcategory":"Real Estate Agent",
            "type":"Services"
        }
    ],
    "sg:phone":"+1 218 566 4843",
    "sg:postcode":"56672",
    "sg:province":"MN",
    "sg:tags":[
        "buyer",
        "broker"
    ],
    "wof:name":"Greg Merz",
    "wof:placetype":"venue"
},
  "geometry": {"coordinates":[-93.95545199999999,47.070622],"type":"Point"}
}