{
  "type": "Feature",
  "properties": {
    "addr:full":"31745 Oasis Rd Center City MN 55012",
    "addr:housenumber":"31745",
    "addr:postcode":"55012",
    "addr:street":"Oasis Rd",
    "iso:country":"US",
    "sg:address":"31745 Oasis Rd",
    "sg:city":"Center City",
    "sg:classifiers":[
        {
            "category":"Wholesale",
            "subcategory":"Construction Materials",
            "type":"Manufacturing & Wholesale Goods"
        }
    ],
    "sg:phone":"+1 651 257 8956",
    "sg:postcode":"55012",
    "sg:province":"MN",
    "sg:tags":[
        "sand",
        "gravel"
    ],
    "wof:name":"Kampa Trucking",
    "wof:placetype":"venue"
},
  "geometry": {"coordinates":[-92.816373,45.408],"type":"Point"}
}