{
  "type": "Feature",
  "properties": {
    "iso:country":"US",
    "sg:address":"1911 Grand Ave",
    "sg:city":"St Paul",
    "sg:classifiers":[
        {
            "category":"Personal",
            "subcategory":"Beauty Salon",
            "type":"Services"
        }
    ],
    "sg:phone":"+1 651 698 8925",
    "sg:postcode":"55105",
    "sg:province":"MN",
    "wof:name":"Rosemary's Swirls & Curls",
    "wof:placetype":"venue"
},
  "geometry": {"coordinates":[-93.181342,44.940177],"type":"Point"}
}