{
  "type": "Feature",
  "properties": {
    "iso:country":"US",
    "sg:address":"200 N Mill St",
    "sg:city":"Fertile",
    "sg:classifiers":[
        {
            "category":"Shopping",
            "subcategory":"Florist",
            "type":"Retail Goods"
        }
    ],
    "sg:phone":"+1 218 945 3801",
    "sg:postcode":"56540",
    "sg:province":"MN",
    "wof:name":"Prairie Rose Flowers & Gifts",
    "wof:placetype":"venue"
},
  "geometry": {"coordinates":[-96.28049,47.536151],"type":"Point"}
}