{
  "type": "Feature",
  "properties": {
    "addr:full":"280 Tiffany Dr Hastings MN 55033",
    "addr:housenumber":"280",
    "addr:postcode":"55033",
    "addr:street":"Tiffany Dr",
    "iso:country":"US",
    "sg:address":"280 Tiffany Dr",
    "sg:city":"Hastings",
    "sg:classifiers":[
        {
            "category":"Building & Trades",
            "subcategory":"Construction",
            "type":"Services"
        }
    ],
    "sg:phone":"+1 651 437 4974",
    "sg:postcode":"55033",
    "sg:province":"MN",
    "sg:tags":[
        "house"
    ],
    "wof:name":"Gmr Construction",
    "wof:placetype":"venue"
},
  "geometry": {"coordinates":[-92.843699,44.711486],"type":"Point"}
}