{
  "type": "Feature",
  "properties": {
    "iso:country":"US",
    "sg:address":"1604 W Broadway Ave",
    "sg:city":"Minneapolis",
    "sg:classifiers":[
        {
            "category":"Autos & Motor Vehicles",
            "subcategory":"Fuel & Gas Station",
            "type":"Retail Goods"
        }
    ],
    "sg:phone":"+1 612 521 4811",
    "sg:postcode":"55411",
    "sg:province":"MN",
    "wof:name":"One Stop",
    "wof:placetype":"venue"
},
  "geometry": {"coordinates":[-93.300797,44.999599],"type":"Point"}
}