{
  "type": "Feature",
  "properties": {
    "iso:country":"US",
    "sg:address":"604 S Prairie Ave",
    "sg:city":"Fairmont",
    "sg:classifiers":[
        {
            "category":"Social Services",
            "subcategory":"Child Care",
            "type":"Services"
        }
    ],
    "sg:phone":"+1 507 235 3880",
    "sg:postcode":"56031",
    "sg:province":"MN",
    "sg:tags":[
        "day",
        "provider"
    ],
    "wof:name":"Patricia A Bliesmer",
    "wof:placetype":"venue"
},
  "geometry": {"coordinates":[-94.457515,43.648054],"type":"Point"}
}