{
  "type": "Feature",
  "properties": {
    "addr:full":"1921 South St Duluth MN 55812",
    "addr:housenumber":"1921",
    "addr:postcode":"55812",
    "addr:street":"South St",
    "iso:country":"US",
    "sg:address":"1921 South St",
    "sg:city":"Duluth",
    "sg:classifiers":[
        {
            "category":"Utilities",
            "subcategory":"Fuel Oil & Lpg",
            "type":"Services"
        }
    ],
    "sg:phone":"+1 218 728 2877",
    "sg:postcode":"55812",
    "sg:province":"MN",
    "sg:tags":[
        "oils-fuel"
    ],
    "wof:name":"All Home Oil Inc",
    "wof:placetype":"venue"
},
  "geometry": {"coordinates":[-92.070998,46.802387],"type":"Point"}
}