{
  "type": "Feature",
  "properties": {
    "addr:full":"3346 Cable Rd Swanville MN 56382",
    "addr:housenumber":"3346",
    "addr:postcode":"56382",
    "addr:street":"Cable Rd",
    "iso:country":"US",
    "sg:address":"3346 Cable Rd",
    "sg:city":"Swanville",
    "sg:classifiers":[
        {
            "category":"Building & Trades",
            "subcategory":"Construction",
            "type":"Services"
        }
    ],
    "sg:phone":"+1 320 573 4249",
    "sg:postcode":"56382",
    "sg:province":"MN",
    "sg:tags":[
        "house"
    ],
    "wof:name":"Alliance Const",
    "wof:placetype":"venue"
},
  "geometry": {"coordinates":[-94.588804,45.91956],"type":"Point"}
}