{
  "type": "Feature",
  "properties": {
    "addr:full":"14349 Timber Crest Ct Osseo MN 55311",
    "addr:housenumber":"14349",
    "addr:postcode":"55311",
    "addr:street":"Timber Crest Ct",
    "iso:country":"US",
    "sg:address":"14349 Timber Crest Ct",
    "sg:city":"Osseo",
    "sg:classifiers":[
        {
            "category":"Organizations",
            "subcategory":"Religious Organization",
            "type":"Services"
        }
    ],
    "sg:phone":"+1 763 557 6880",
    "sg:postcode":"55311",
    "sg:province":"MN",
    "wof:name":"Cme Services Inc",
    "wof:placetype":"venue"
},
  "geometry": {"coordinates":[-93.462502,45.079949],"type":"Point"}
}