{
  "type": "Feature",
  "properties": {
    "addr:full":"31973 182nd Ave Avon MN 56310",
    "addr:housenumber":"31973",
    "addr:postcode":"56310",
    "addr:street":"182Nd Ave",
    "iso:country":"US",
    "sg:address":"31973 182nd Ave",
    "sg:city":"Avon",
    "sg:classifiers":[
        {
            "category":"Professional",
            "subcategory":"Detective & Security Services",
            "type":"Services"
        }
    ],
    "sg:phone":"+1 320 845 6070",
    "sg:postcode":"56310",
    "sg:province":"MN",
    "sg:tags":[
        "guard"
    ],
    "wof:name":"Professional & Trustworthy SEC",
    "wof:placetype":"venue"
},
  "geometry": {"coordinates":[-94.483745,45.581054],"type":"Point"}
}