{
  "type": "Feature",
  "properties": {
    "addr:full":"68275 200th St Elkton MN 55933",
    "addr:housenumber":"68275",
    "addr:postcode":"55933",
    "addr:street":"200Th St",
    "iso:country":"US",
    "sg:address":"68275 200th St",
    "sg:city":"Elkton",
    "sg:classifiers":[
        {
            "category":"Home & Garden",
            "subcategory":"Garden Supply",
            "type":"Retail Goods"
        }
    ],
    "sg:phone":"+1 507 754 5478",
    "sg:postcode":"55933",
    "sg:province":"MN",
    "wof:name":"Kinney AG Service",
    "wof:placetype":"venue"
},
  "geometry": {"coordinates":[-92.685068,43.644749],"type":"Point"}
}