{
  "type": "Feature",
  "properties": {
    "addr:full":"7908 Bryant Ct N Minneapolis MN 55444",
    "addr:housenumber":"7908",
    "addr:postcode":"55444",
    "addr:street":"Bryant Ct N",
    "iso:country":"US",
    "sg:address":"7908 Bryant Ct N",
    "sg:city":"Minneapolis",
    "sg:classifiers":[
        {
            "category":"Manufacturing",
            "subcategory":"Tools & Machinery",
            "type":"Manufacturing & Wholesale Goods"
        }
    ],
    "sg:phone":"+1 763 560 1246",
    "sg:postcode":"55444",
    "sg:province":"MN",
    "sg:tags":[
        "machine",
        "shop"
    ],
    "wof:name":"Five Star Machine",
    "wof:placetype":"venue"
},
  "geometry": {"coordinates":[-93.292985,45.098686],"type":"Point"}
}