{
  "type": "Feature",
  "properties": {
    "iso:country":"US",
    "sg:address":"11800 Singletree Ln",
    "sg:city":"Eden Prairie",
    "sg:classifiers":[
        {
            "category":"Insurance",
            "subcategory":"Insurance Agent",
            "type":"Services"
        }
    ],
    "sg:phone":"+1 952 828 9790",
    "sg:postcode":"55344",
    "sg:province":"MN",
    "wof:name":"Farm Bureau Insurance",
    "wof:placetype":"venue"
},
  "geometry": {"coordinates":[-93.428192,44.856944],"type":"Point"}
}