{
  "type": "Feature",
  "properties": {
    "iso:country":"US",
    "sg:address":"700 Twelve Oaks Center Dr",
    "sg:city":"Wayzata",
    "sg:classifiers":[
        {
            "category":"Banks & Credit Unions",
            "subcategory":"Financial Services",
            "type":"Services"
        }
    ],
    "sg:phone":"+1 952 449 6060",
    "sg:postcode":"55391",
    "sg:province":"MN",
    "sg:tags":[
        "company",
        "holding"
    ],
    "wof:name":"Becho Corp",
    "wof:placetype":"venue"
},
  "geometry": {"coordinates":[-93.472419,44.973524],"type":"Point"}
}