{
  "type": "Feature",
  "properties": {
    "addr:full":"110 2nd St S Waite Park MN 56387",
    "addr:housenumber":"110",
    "addr:postcode":"56387",
    "addr:street":"2Nd St S",
    "iso:country":"US",
    "sg:address":"110 2nd St S",
    "sg:city":"Waite Park",
    "sg:classifiers":[
        {
            "category":"Banks & Credit Unions",
            "subcategory":"Investment Brokerage",
            "type":"Services"
        }
    ],
    "sg:phone":"+1 320 251 6007",
    "sg:postcode":"56387",
    "sg:province":"MN",
    "sg:tags":[
        "security"
    ],
    "wof:name":"Wachovia Securities",
    "wof:placetype":"venue"
},
  "geometry": {"coordinates":[-94.21523999999999,45.549774],"type":"Point"}
}