{
  "type": "Feature",
  "properties": {
    "addr:full":"28954 Mindy Ct Lindstrom MN 55045",
    "addr:housenumber":"28954",
    "addr:postcode":"55045",
    "addr:street":"Mindy Ct",
    "iso:country":"US",
    "sg:address":"28954 Mindy Ct",
    "sg:city":"Lindstrom",
    "sg:classifiers":[
        {
            "category":"Manufacturing",
            "subcategory":"Tools & Machinery",
            "type":"Manufacturing & Wholesale Goods"
        }
    ],
    "sg:phone":"+1 651 433 8199",
    "sg:postcode":"55045",
    "sg:province":"MN",
    "sg:tags":[
        "physician",
        "surgeon"
    ],
    "wof:name":"Health Card Solutions",
    "wof:placetype":"venue"
},
  "geometry": {"coordinates":[-92.84546899999999,45.367062],"type":"Point"}
}