{
  "type": "Feature",
  "properties": {
    "iso:country":"US",
    "sg:address":"2259 Co Hwy 21",
    "sg:city":"Ely",
    "sg:classifiers":[
        {
            "category":"Retail",
            "subcategory":"Auto Repair",
            "type":"Services"
        }
    ],
    "sg:phone":"+1 218 365 3170",
    "sg:postcode":"55731",
    "sg:province":"MN",
    "sg:tags":[
        "general"
    ],
    "wof:name":"Bills Autoworx",
    "wof:placetype":"venue"
},
  "geometry": {"coordinates":[-91.868261,47.890877],"type":"Point"}
}