{
  "type": "Feature",
  "properties": {
    "iso:country":"US",
    "sg:address":"50 S 6th St",
    "sg:city":"Minneapolis",
    "sg:classifiers":[
        {
            "category":"Professional",
            "subcategory":"Lawyer & Legal Services",
            "type":"Services"
        }
    ],
    "sg:phone":"+1 612 333 2343",
    "sg:postcode":"55402",
    "sg:province":"MN",
    "sg:tags":[
        "personal",
        "injury"
    ],
    "sg:website":"www.actionlawyers.com",
    "wof:name":"Action Lawyers",
    "wof:placetype":"venue"
},
  "geometry": {"coordinates":[-93.272015,44.978265],"type":"Point"}
}