{
  "type": "Feature",
  "properties": {
    "iso:country":"US",
    "sg:address":"3123 Girard Ave N",
    "sg:city":"Minneapolis",
    "sg:classifiers":[
        {
            "category":"Local Transit",
            "type":"Transportation"
        }
    ],
    "sg:phone":"+1 612 521 8844",
    "sg:postcode":"55411",
    "sg:province":"MN",
    "wof:name":"Mlk Transit Company",
    "wof:placetype":"venue"
},
  "geometry": {"coordinates":[-93.29691699999999,45.012052],"type":"Point"}
}