{
  "type": "Feature",
  "properties": {
    "iso:country":"US",
    "sg:address":"300 S Garden St",
    "sg:city":"Lake City",
    "sg:classifiers":[
        {
            "category":"Professional",
            "subcategory":"Computer Services",
            "type":"Services"
        }
    ],
    "sg:phone":"+1 651 345 0149",
    "sg:postcode":"55041",
    "sg:province":"MN",
    "sg:tags":[
        "datum"
    ],
    "wof:name":"Mr Net",
    "wof:placetype":"venue"
},
  "geometry": {"coordinates":[-92.267341,44.445805],"type":"Point"}
}