{
  "type": "Feature",
  "properties": {
    "addr:full":"408 W Thomas Ave Marshall MN 56258",
    "addr:housenumber":"408",
    "addr:postcode":"56258",
    "addr:street":"W Thomas Ave",
    "iso:country":"US",
    "sg:address":"408 W Thomas Ave",
    "sg:city":"Marshall",
    "sg:classifiers":[
        {
            "category":"Social Services",
            "subcategory":"Adult Care",
            "type":"Services"
        }
    ],
    "sg:phone":"+1 507 532 2745",
    "sg:postcode":"56258",
    "sg:province":"MN",
    "sg:tags":[
        "residential"
    ],
    "wof:name":"R Em Whitney Inc",
    "wof:placetype":"venue"
},
  "geometry": {"coordinates":[-95.79910599999999,44.433645],"type":"Point"}
}