{
  "type": "Feature",
  "properties": {
    "addr:full":"430 7th Ave N Waite Park MN 56387",
    "addr:housenumber":"430",
    "addr:postcode":"56387",
    "addr:street":"7Th Ave N",
    "iso:country":"US",
    "sg:address":"430 7th Ave N",
    "sg:city":"Waite Park",
    "sg:classifiers":[
        {
            "category":"Manufacturing",
            "subcategory":"Tools & Machinery",
            "type":"Manufacturing & Wholesale Goods"
        }
    ],
    "sg:phone":"+1 320 251 8616",
    "sg:postcode":"56387",
    "sg:province":"MN",
    "sg:tags":[
        "h",
        "industrial",
        "mfg"
    ],
    "wof:name":"Tc/Amrcan Mnorail Inc Hamel MN",
    "wof:placetype":"venue"
},
  "geometry": {"coordinates":[-94.22531499999999,45.55754],"type":"Point"}
}