{
  "type": "Feature",
  "properties": {
    "iso:country":"US",
    "sg:address":"3195 Neil Armstrong Blvd",
    "sg:city":"Eagan",
    "sg:classifiers":[
        {
            "category":"Professional",
            "subcategory":"Business Services",
            "type":"Services"
        },
        {
            "category":"Social Services",
            "subcategory":"Job Training",
            "type":"Services"
        }
    ],
    "sg:phone":"+1 651 686 0405",
    "sg:postcode":"55121",
    "sg:province":"MN",
    "sg:tags":[
        "packaging",
        "syn",
        "mfg"
    ],
    "wof:name":"Proact Inc",
    "wof:placetype":"venue"
},
  "geometry": {"coordinates":[-93.141819,44.84197],"type":"Point"}
}