{
  "type": "Feature",
  "properties": {
    "addr:full":"2012 6th Ave E Hibbing MN 55746",
    "addr:housenumber":"2012",
    "addr:postcode":"55746",
    "addr:street":"6Th Ave E Hibbing",
    "iso:country":"US",
    "sg:address":"2012 6th Ave E",
    "sg:city":"Hibbing",
    "sg:classifiers":[
        {
            "category":"Social Services",
            "subcategory":"Child Care",
            "type":"Services"
        }
    ],
    "sg:phone":"+1 218 263 8243",
    "sg:postcode":"55746",
    "sg:province":"MN",
    "sg:tags":[
        "day",
        "provider"
    ],
    "wof:name":"Pats Little People",
    "wof:placetype":"venue"
},
  "geometry": {"coordinates":[-92.935123,47.427362],"type":"Point"}
}