{
  "type": "Feature",
  "properties": {
    "iso:country":"US",
    "sg:address":"101 Mount Curve Rd",
    "sg:city":"Mankato",
    "sg:classifiers":[
        {
            "category":"Food & Beverages",
            "subcategory":"Candy",
            "type":"Retail Goods"
        }
    ],
    "sg:phone":"+1 507 388 5797",
    "sg:postcode":"56001",
    "sg:province":"MN",
    "wof:name":"Hand Maid Sweets Inc",
    "wof:placetype":"venue"
},
  "geometry": {"coordinates":[-94.006771,44.139155],"type":"Point"}
}