{
  "type": "Feature",
  "properties": {
    "addr:full":"4741 Zealand Ave N Minneapolis MN 55428",
    "addr:housenumber":"4741",
    "addr:postcode":"55428",
    "addr:street":"Zealand Ave N",
    "iso:country":"US",
    "sg:address":"4741 Zealand Ave N",
    "sg:city":"Minneapolis",
    "sg:classifiers":[
        {
            "category":"Social Services",
            "type":"Services"
        }
    ],
    "sg:phone":"+1 763 561 1410",
    "sg:postcode":"55428",
    "sg:province":"MN",
    "sg:tags":[
        "human"
    ],
    "wof:name":"Love In The Nm Of Cht Nw Hope",
    "wof:placetype":"venue"
},
  "geometry": {"coordinates":[-93.387901,45.04025],"type":"Point"}
}