{
  "type": "Feature",
  "properties": {
    "iso:country":"US",
    "sg:address":"7710 Computer Ave",
    "sg:city":"Minneapolis",
    "sg:classifiers":[
        {
            "category":"Real Estate",
            "subcategory":"Real Estate Services",
            "type":"Services"
        },
        {
            "category":"Professional",
            "subcategory":"Research",
            "type":"Services"
        }
    ],
    "sg:phone":"+1 952 224 0690",
    "sg:postcode":"55435",
    "sg:province":"MN",
    "sg:tags":[
        "abstracter",
        "title"
    ],
    "wof:name":"Ace Abstracting Services",
    "wof:placetype":"venue"
},
  "geometry": {"coordinates":[-93.345645,44.863078],"type":"Point"}
}