{
  "type": "Feature",
  "properties": {
    "addr:full":"542 Snelling Ave S St Paul MN 55116",
    "addr:housenumber":"542",
    "addr:postcode":"55116",
    "addr:street":"Snelling Ave S",
    "iso:country":"US",
    "sg:address":"542 Snelling Ave S",
    "sg:city":"St Paul",
    "sg:classifiers":[
        {
            "category":"Health Services",
            "subcategory":"Doctor",
            "type":"Services"
        }
    ],
    "sg:phone":"+1 651 690 2147",
    "sg:postcode":"55116",
    "sg:province":"MN",
    "sg:tags":[
        "dentist"
    ],
    "wof:name":"Children's Dental Care Specs",
    "wof:placetype":"venue"
},
  "geometry": {"coordinates":[-93.16695,44.924329],"type":"Point"}
}