{
  "type": "Feature",
  "properties": {
    "addr:full":"720 US Hwy 14 Walnut Grove MN 56180",
    "addr:housenumber":"720",
    "addr:postcode":"56180",
    "addr:street":"Us Hwy 14 Walnut Grove",
    "iso:country":"US",
    "sg:address":"720 US Hwy 14",
    "sg:city":"Walnut Grove",
    "sg:classifiers":[
        {
            "category":"Retail",
            "subcategory":"Auto Repair",
            "type":"Services"
        }
    ],
    "sg:phone":"+1 507 859 2117",
    "sg:postcode":"56180",
    "sg:province":"MN",
    "sg:tags":[
        "repairing",
        "automobile"
    ],
    "wof:name":"Bruce's Service",
    "wof:placetype":"venue"
},
  "geometry": {"coordinates":[-95.47150999999999,44.225149],"type":"Point"}
}