{
  "type": "Feature",
  "properties": {
    "addr:full":"904 19th Ave S Minneapolis MN 55404",
    "addr:housenumber":"904",
    "addr:postcode":"55404",
    "addr:street":"19Th Ave S",
    "iso:country":"US",
    "sg:address":"904 19th Ave S",
    "sg:city":"Minneapolis",
    "sg:classifiers":[
        {
            "category":"Autos & Motor Vehicles",
            "subcategory":"Motorcycle Sales",
            "type":"Retail Goods"
        }
    ],
    "sg:phone":"+1 612 340 0400",
    "sg:postcode":"55404",
    "sg:province":"MN",
    "wof:name":"Easyriders of Minneapolis",
    "wof:placetype":"venue"
},
  "geometry": {"coordinates":[-93.245903,44.963001],"type":"Point"}
}