{
  "type": "Feature",
  "properties": {
    "addr:full":"3800 American Blvd E Minneapolis MN 55425",
    "addr:housenumber":"3800",
    "addr:postcode":"55425",
    "addr:street":"American Blvd E",
    "iso:country":"US",
    "sg:address":"3800 American Blvd E",
    "sg:city":"Minneapolis",
    "sg:classifiers":[
        {
            "category":"Retail",
            "subcategory":"Auto Rental",
            "type":"Services"
        }
    ],
    "sg:phone":"+1 952 854 3003",
    "sg:postcode":"55425",
    "sg:province":"MN",
    "sg:tags":[
        "renting",
        "automobile"
    ],
    "wof:name":"Dollar Rent A Car",
    "wof:placetype":"venue"
},
  "geometry": {"coordinates":[-93.215836,44.861272],"type":"Point"}
}