{
  "type": "Feature",
  "properties": {
    "addr:full":"23500 Zane Ave Lakeville MN 55044",
    "addr:housenumber":"23500",
    "addr:postcode":"55044",
    "addr:street":"Zane Ave",
    "iso:country":"US",
    "sg:address":"23500 Zane Ave",
    "sg:city":"Lakeville",
    "sg:classifiers":[
        {
            "category":"Manufacturing",
            "subcategory":"Tools & Machinery",
            "type":"Manufacturing & Wholesale Goods"
        }
    ],
    "sg:phone":"+1 952 461 3409",
    "sg:postcode":"55044",
    "sg:province":"MN",
    "sg:tags":[
        "control",
        "environmental",
        "mfg"
    ],
    "wof:name":"Circle H Enterprises",
    "wof:placetype":"venue"
},
  "geometry": {"coordinates":[-93.354203,44.607375],"type":"Point"}
}