{
  "type": "Feature",
  "properties": {
    "iso:country":"US",
    "sg:address":"965 Prairie Center Dr",
    "sg:city":"Eden Prairie",
    "sg:classifiers":[
        {
            "category":"Insurance",
            "subcategory":"Insurance Agent",
            "type":"Services"
        }
    ],
    "sg:phone":"+1 952 975 0500",
    "sg:postcode":"55344",
    "sg:province":"MN",
    "wof:name":"Allstate Insurance",
    "wof:placetype":"venue"
},
  "geometry": {"coordinates":[-93.443555,44.865971],"type":"Point"}
}