{
  "type": "Feature",
  "properties": {
    "addr:full":"901 W 5th St Winona MN 55987",
    "addr:housenumber":"901",
    "addr:postcode":"55987",
    "addr:street":"W 5Th St",
    "iso:country":"US",
    "sg:address":"901 W 5th St",
    "sg:city":"Winona",
    "sg:classifiers":[
        {
            "category":"Bars & Pubs",
            "type":"Food & Drink"
        }
    ],
    "sg:phone":"+1 507 457 3319",
    "sg:postcode":"55987",
    "sg:province":"MN",
    "sg:tags":[
        "drinking"
    ],
    "wof:name":"Cozy Corner Bar",
    "wof:placetype":"venue"
},
  "geometry": {"coordinates":[-91.66189,44.05394],"type":"Point"}
}