{
  "type": "Feature",
  "properties": {
    "addr:full":"4691 Paisley Rd Mound MN 55364",
    "addr:housenumber":"4691",
    "addr:postcode":"55364",
    "addr:street":"Paisley Rd",
    "iso:country":"US",
    "sg:address":"4691 Paisley Rd",
    "sg:city":"Mound",
    "sg:classifiers":[
        {
            "category":"Building & Trades",
            "subcategory":"Construction",
            "type":"Services"
        }
    ],
    "sg:phone":"+1 952 472 2374",
    "sg:postcode":"55364",
    "sg:province":"MN",
    "sg:tags":[
        "contractor"
    ],
    "wof:name":"Gerry Garvais Tops",
    "wof:placetype":"venue"
},
  "geometry": {"coordinates":[-93.64276599999999,44.922608],"type":"Point"}
}