{
  "type": "Feature",
  "properties": {
    "addr:full":"400 10th St NE Staples MN 56479",
    "addr:housenumber":"400",
    "addr:postcode":"56479",
    "addr:street":"10Th St Ne",
    "iso:country":"US",
    "sg:address":"400 10th St NE",
    "sg:city":"Staples",
    "sg:classifiers":[
        {
            "category":"Building & Trades",
            "subcategory":"Construction",
            "type":"Services"
        }
    ],
    "sg:phone":"+1 218 894 1742",
    "sg:postcode":"56479",
    "sg:province":"MN",
    "sg:tags":[
        "house"
    ],
    "wof:name":"Bendson Construction",
    "wof:placetype":"venue"
},
  "geometry": {"coordinates":[-94.786326,46.35893],"type":"Point"}
}