{
  "type": "Feature",
  "properties": {
    "addr:full":"20134 Kenwood Trl Lakeville MN 55044",
    "addr:housenumber":"20134",
    "addr:postcode":"55044",
    "addr:street":"Kenwood Trl",
    "iso:country":"US",
    "sg:address":"20134 Kenwood Trl",
    "sg:city":"Lakeville",
    "sg:classifiers":[
        {
            "category":"Retail",
            "subcategory":"Funeral Services",
            "type":"Services"
        }
    ],
    "sg:phone":"+1 952 469 2723",
    "sg:postcode":"55044",
    "sg:province":"MN",
    "wof:name":"White Funeral Home Inc",
    "wof:placetype":"venue"
},
  "geometry": {"coordinates":[-93.25378600000001,44.656558],"type":"Point"}
}