{
  "type": "Feature",
  "properties": {
    "addr:full":"1697 Ash St Hugo MN 55038",
    "addr:housenumber":"1697",
    "addr:postcode":"55038",
    "addr:street":"Ash St",
    "iso:country":"US",
    "sg:address":"1697 Ash St",
    "sg:city":"Hugo",
    "sg:classifiers":[
        {
            "category":"Professional",
            "subcategory":"Management & Consulting",
            "type":"Services"
        }
    ],
    "sg:phone":"+1 651 762 8117",
    "sg:postcode":"55038",
    "sg:province":"MN",
    "sg:tags":[
        "public",
        "relations"
    ],
    "wof:name":"Donlin Rm Ltd",
    "wof:placetype":"venue"
},
  "geometry": {"coordinates":[-93.061481,45.1278],"type":"Point"}
}