{
  "type": "Feature",
  "properties": {
    "iso:country":"US",
    "sg:address":"136 Bridge Ave",
    "sg:city":"Wabasha",
    "sg:classifiers":[
        {
            "category":"Retail",
            "subcategory":"Funeral Services",
            "type":"Services"
        }
    ],
    "sg:phone":"+1 651 565 2004",
    "sg:postcode":"55981",
    "sg:province":"MN",
    "wof:name":"Buckman Schierts Koch Fnrl Hm",
    "wof:placetype":"venue"
},
  "geometry": {"coordinates":[-92.035403,44.384787],"type":"Point"}
}