{
  "type": "Feature",
  "properties": {
    "iso:country":"US",
    "sg:address":"132 1st Ave SE",
    "sg:city":"Winnebago",
    "sg:classifiers":[
        {
            "category":"Education",
            "subcategory":"School",
            "type":"Public Place"
        }
    ],
    "sg:phone":"+1 507 893 3176",
    "sg:postcode":"56098",
    "sg:province":"MN",
    "wof:name":"Winnebago Elementary School",
    "wof:placetype":"venue"
},
  "geometry": {"coordinates":[-94.16325000000001,43.766538],"type":"Point"}
}