{
  "type": "Feature",
  "properties": {
    "addr:full":"117 Main St Ashby MN 56309",
    "addr:housenumber":"117",
    "addr:postcode":"56309",
    "addr:street":"Main St",
    "iso:country":"US",
    "sg:address":"117 Main St",
    "sg:city":"Ashby",
    "sg:classifiers":[
        {
            "category":"Food & Beverages",
            "subcategory":"Groceries & Convenience Stores",
            "type":"Retail Goods"
        }
    ],
    "sg:phone":"+1 218 747 2660",
    "sg:postcode":"56309",
    "sg:province":"MN",
    "sg:tags":[
        "grocer"
    ],
    "wof:name":"Anderson Foods",
    "wof:placetype":"venue"
},
  "geometry": {"coordinates":[-95.81591,46.09303],"type":"Point"}
}