{
  "type": "Feature",
  "properties": {
    "addr:full":"7524 Lyndale Ave S Minneapolis MN 55423",
    "addr:housenumber":"7524",
    "addr:postcode":"55423",
    "addr:street":"Lyndale Ave S",
    "iso:country":"US",
    "sg:address":"7524 Lyndale Ave S",
    "sg:city":"Minneapolis",
    "sg:classifiers":[
        {
            "category":"Retail",
            "subcategory":"Auto Repair",
            "type":"Services"
        }
    ],
    "sg:phone":"+1 612 798 4855",
    "sg:postcode":"55423",
    "sg:province":"MN",
    "sg:tags":[
        "body",
        "painting",
        "repairing",
        "automobile"
    ],
    "wof:name":"Dent B Gone",
    "wof:placetype":"venue"
},
  "geometry": {"coordinates":[-93.288405,44.86686],"type":"Point"}
}