{
  "type": "Feature",
  "properties": {
    "addr:full":"413 2nd St W Hastings MN 55033",
    "addr:housenumber":"413",
    "addr:postcode":"55033",
    "addr:street":"2Nd St W",
    "iso:country":"US",
    "sg:address":"413 2nd St W",
    "sg:city":"Hastings",
    "sg:classifiers":[
        {
            "category":"Building & Trades",
            "subcategory":"Landscaping Services",
            "type":"Services"
        }
    ],
    "sg:phone":"+1 651 437 8529",
    "sg:postcode":"55033",
    "sg:province":"MN",
    "wof:name":"Melson Custom Maintenance",
    "wof:placetype":"venue"
},
  "geometry": {"coordinates":[-92.856504,44.744279],"type":"Point"}
}