{
  "type": "Feature",
  "properties": {
    "addr:full":"97 S Owasso Blvd E Little Canada MN 55117",
    "addr:housenumber":"97",
    "addr:postcode":"55117",
    "addr:street":"S Owasso Blvd E",
    "iso:country":"US",
    "sg:address":"97 S Owasso Blvd E",
    "sg:city":"Little Canada",
    "sg:classifiers":[
        {
            "category":"Retail",
            "subcategory":"Auto Repair",
            "type":"Services"
        }
    ],
    "sg:phone":"+1 651 483 4493",
    "sg:postcode":"55117",
    "sg:province":"MN",
    "sg:tags":[
        "body",
        "automobile",
        "painting"
    ],
    "wof:name":"Wayne-Val Auto Body",
    "wof:placetype":"venue"
},
  "geometry": {"coordinates":[-93.099148,45.031639],"type":"Point"}
}