{
  "type": "Feature",
  "properties": {
    "addr:full":"160 E 6th St Saint Charles MN 55972",
    "addr:housenumber":"160",
    "addr:postcode":"55972",
    "addr:street":"E 6Th St",
    "iso:country":"US",
    "sg:address":"160 E 6th St",
    "sg:city":"Saint Charles",
    "sg:classifiers":[
        {
            "category":"Food & Beverages",
            "subcategory":"Groceries & Convenience Stores",
            "type":"Retail Goods"
        }
    ],
    "sg:phone":"+1 507 932 4673",
    "sg:postcode":"55972",
    "sg:province":"MN",
    "wof:name":"Kwik Trip",
    "wof:placetype":"venue"
},
  "geometry": {"coordinates":[-92.064036,43.971796],"type":"Point"}
}