{
  "type": "Feature",
  "properties": {
    "addr:full":"172 Rosedale Shopping Center Roseville MN 55113",
    "addr:housenumber":"172",
    "addr:postcode":"55113",
    "addr:street":"Rosedale Shopping Center",
    "iso:country":"US",
    "sg:address":"172 Rosedale Shopping Center",
    "sg:city":"Roseville",
    "sg:classifiers":[
        {
            "category":"Food & Beverages",
            "subcategory":"Candy",
            "type":"Retail Goods"
        }
    ],
    "sg:phone":"+1 651 636 2693",
    "sg:postcode":"55113",
    "sg:province":"MN",
    "sg:tags":[
        "confectionery"
    ],
    "wof:name":"Karmelkorn Shoppes",
    "wof:placetype":"venue"
},
  "geometry": {"coordinates":[-93.172307,45.013827],"type":"Point"}
}