{
  "type": "Feature",
  "properties": {
    "iso:country":"US",
    "sg:address":"326 Laurel St",
    "sg:city":"Brainerd",
    "sg:classifiers":[
        {
            "category":"Government",
            "subcategory":"Office",
            "type":"Public Place"
        }
    ],
    "sg:phone":"+1 218 824 1137",
    "sg:postcode":"56401",
    "sg:province":"MN",
    "wof:name":"Crow Wing Cnty Juvenile Prbtn",
    "wof:placetype":"venue"
},
  "geometry": {"coordinates":[-94.204988,46.355714],"type":"Point"}
}