{
  "type": "Feature",
  "properties": {
    "addr:full":"101 W 5th St Starbuck MN 56381",
    "addr:housenumber":"101",
    "addr:postcode":"56381",
    "addr:street":"W 5Th St",
    "iso:country":"US",
    "sg:address":"101 W 5th St",
    "sg:city":"Starbuck",
    "sg:classifiers":[
        {
            "category":"Social Services",
            "type":"Services"
        }
    ],
    "sg:phone":"+1 320 239 4276",
    "sg:postcode":"56381",
    "sg:province":"MN",
    "sg:tags":[
        "organization",
        "welfare"
    ],
    "wof:name":"Pope County DT & H",
    "wof:placetype":"venue"
},
  "geometry": {"coordinates":[-95.53115099999999,45.61237],"type":"Point"}
}