{
  "type": "Feature",
  "properties": {
    "addr:full":"15672 Fremont Ave NW Prior Lake MN 55372",
    "addr:housenumber":"15672",
    "addr:postcode":"55372",
    "addr:street":"Fremont Ave Nw",
    "iso:country":"US",
    "sg:address":"15672 Fremont Ave NW",
    "sg:city":"Prior Lake",
    "sg:classifiers":[
        {
            "category":"Real Estate",
            "subcategory":"Real Estate Operator",
            "type":"Services"
        }
    ],
    "sg:phone":"+1 952 440 2270",
    "sg:postcode":"55372",
    "sg:province":"MN",
    "sg:tags":[
        "building",
        "nonresidential"
    ],
    "wof:name":"Finn Properties",
    "wof:placetype":"venue"
},
  "geometry": {"coordinates":[-93.450102,44.721895],"type":"Point"}
}