{
  "type": "Feature",
  "properties": {
    "addr:full":"3031 37th Ave SE St Cloud MN 56304",
    "addr:housenumber":"3031",
    "addr:postcode":"56304",
    "addr:street":"37Th Ave Se",
    "iso:country":"US",
    "sg:address":"3031 37th Ave SE",
    "sg:city":"St Cloud",
    "sg:classifiers":[
        {
            "category":"Building & Trades",
            "subcategory":"Landscaping Services",
            "type":"Services"
        }
    ],
    "sg:phone":"+1 320 258 2800",
    "sg:postcode":"56304",
    "sg:province":"MN",
    "sg:tags":[
        "lawn",
        "maintenance",
        "grounds"
    ],
    "wof:name":"Natura Lawn Of America",
    "wof:placetype":"venue"
},
  "geometry": {"coordinates":[-94.08444900000001,45.525063],"type":"Point"}
}