{
  "type": "Feature",
  "properties": {
    "iso:country":"US",
    "sg:address":"954 W Lincoln Ave",
    "sg:city":"Saint Paul",
    "sg:classifiers":[
        {
            "category":"Banks & Credit Unions",
            "subcategory":"Financial Services",
            "type":"Services"
        }
    ],
    "sg:phone":"+1 651 222 3860",
    "sg:postcode":"55105",
    "sg:province":"MN",
    "sg:tags":[
        "investor"
    ],
    "wof:name":"SGB Investment Group",
    "wof:placetype":"venue"
},
  "geometry": {"coordinates":[-93.14045,44.938813],"type":"Point"}
}