{
  "type": "Feature",
  "properties": {
    "addr:full":"3447 Upton Ave N Minneapolis MN 55412",
    "addr:housenumber":"3447",
    "addr:postcode":"55412",
    "addr:street":"Upton Ave N",
    "iso:country":"US",
    "sg:address":"3447 Upton Ave N",
    "sg:city":"Minneapolis",
    "sg:classifiers":[
        {
            "category":"Building & Trades",
            "subcategory":"Landscaping Services",
            "type":"Services"
        }
    ],
    "sg:phone":"+1 612 522 5213",
    "sg:postcode":"55412",
    "sg:province":"MN",
    "wof:name":"Duypree Snow & Lawn Services",
    "wof:placetype":"venue"
},
  "geometry": {"coordinates":[-93.314688,45.017817],"type":"Point"}
}