{
  "type": "Feature",
  "properties": {
    "iso:country":"US",
    "sg:address":"6029 Jerry Rd",
    "sg:city":"Duluth",
    "sg:classifiers":[
        {
            "category":"Freight",
            "type":"Transportation"
        }
    ],
    "sg:phone":"+1 218 624 7935",
    "sg:postcode":"55810",
    "sg:province":"MN",
    "sg:tags":[
        "operator",
        "trucking"
    ],
    "wof:name":"Parker Trucking Inc",
    "wof:placetype":"venue"
},
  "geometry": {"coordinates":[-92.33650400000001,46.786862],"type":"Point"}
}