{
  "type": "Feature",
  "properties": {
    "iso:country":"US",
    "sg:address":"308 N Redwood Dr",
    "sg:city":"Mankato",
    "sg:classifiers":[
        {
            "category":"Social Services",
            "subcategory":"Job Training",
            "type":"Services"
        }
    ],
    "sg:phone":"+1 507 345 8114",
    "sg:postcode":"56001",
    "sg:province":"MN",
    "sg:tags":[
        "rehabilitation"
    ],
    "wof:name":"Habilitative Services Inc",
    "wof:placetype":"venue"
},
  "geometry": {"coordinates":[-93.974867,44.162119],"type":"Point"}
}