{
  "type": "Feature",
  "properties": {
    "iso:country":"US",
    "sg:address":"626 E Crescent Ln",
    "sg:city":"Litchfield",
    "sg:classifiers":[
        {
            "category":"Farming",
            "subcategory":"Farm",
            "type":"Manufacturing & Wholesale Goods"
        }
    ],
    "sg:phone":"+1 320 693 9353",
    "sg:postcode":"55355",
    "sg:province":"MN",
    "sg:tags":[
        "crop",
        "general"
    ],
    "wof:name":"Vincent Desutter Farm",
    "wof:placetype":"venue"
},
  "geometry": {"coordinates":[-94.513176,45.133943],"type":"Point"}
}