{
  "type": "Feature",
  "properties": {
    "iso:country":"US",
    "sg:address":"17509 Bay Ln",
    "sg:city":"Wayzata",
    "sg:classifiers":[
        {
            "category":"Professional",
            "type":"Services"
        }
    ],
    "sg:phone":"+1 952 473 2731",
    "sg:postcode":"55391",
    "sg:province":"MN",
    "wof:name":"Bill Traff",
    "wof:placetype":"venue"
},
  "geometry": {"coordinates":[-93.50103,44.947368],"type":"Point"}
}