{
  "type": "Feature",
  "properties": {
    "iso:country":"US",
    "sg:address":"88 S Park Ave",
    "sg:city":"Le Center",
    "sg:classifiers":[
        {
            "category":"Government",
            "subcategory":"Office",
            "type":"Public Place"
        }
    ],
    "sg:phone":"+1 507 388 5302",
    "sg:postcode":"56057",
    "sg:province":"MN",
    "sg:website":"www.co.le-sueur.mn.us",
    "wof:name":"Le Sueur County Courthouse",
    "wof:placetype":"venue"
},
  "geometry": {"coordinates":[-93.7316,44.388324],"type":"Point"}
}