{
  "type": "Feature",
  "properties": {
    "iso:country":"US",
    "sg:address":"1163 115 St",
    "sg:city":"Tyler",
    "sg:phone":"+1 507 247 3258",
    "sg:postcode":"56178",
    "sg:province":"MN",
    "sg:tags":[
        "farm",
        "corn",
        "soybean"
    ],
    "wof:name":"Charles Bakker",
    "wof:placetype":"venue"
},
  "geometry": {"coordinates":[-96.06316,44.218379],"type":"Point"}
}