{
  "type": "Feature",
  "properties": {
    "iso:country":"US",
    "sg:address":"3601 E Lake St",
    "sg:city":"Minneapolis",
    "sg:classifiers":[
        {
            "category":"Bars & Pubs",
            "type":"Food & Drink"
        }
    ],
    "sg:phone":"+1 612 216 2419",
    "sg:postcode":"55406",
    "sg:province":"MN",
    "sg:website":"merlinsrest.com",
    "wof:name":"Merlins Rest Pub",
    "wof:placetype":"venue"
},
  "geometry": {"coordinates":[-93.22036900000001,44.948294],"type":"Point"}
}