{
  "type": "Feature",
  "properties": {
    "iso:country":"US",
    "sg:address":"8601 73rd Ave N",
    "sg:city":"Brooklyn Park",
    "sg:classifiers":[
        {
            "category":"Social Services",
            "subcategory":"Job Training",
            "type":"Services"
        }
    ],
    "sg:phone":"+1 763 533 0214",
    "sg:postcode":"55428",
    "sg:province":"MN",
    "sg:tags":[
        "employment"
    ],
    "wof:name":"Intermediate District 287",
    "wof:placetype":"venue"
},
  "geometry": {"coordinates":[-93.39099400000001,45.087303],"type":"Point"}
}