{
  "type": "Feature",
  "properties": {
    "addr:full":"371 E Highway 210 Mcgregor MN 55760",
    "addr:housenumber":"371",
    "addr:postcode":"55760",
    "addr:street":"E Highway 210 Mcgregor",
    "iso:country":"US",
    "sg:address":"371 E Highway 210",
    "sg:city":"Mcgregor",
    "sg:classifiers":[
        {
            "category":"Shopping",
            "subcategory":"Clothing, Apparel, & Fashions",
            "type":"Retail Goods"
        }
    ],
    "sg:phone":"+1 218 768 2556",
    "sg:postcode":"55760",
    "sg:province":"MN",
    "sg:tags":[
        "shirts-custom",
        "made",
        "alterations-clothing"
    ],
    "wof:name":"Timeless Treasures Of Mc",
    "wof:placetype":"venue"
},
  "geometry": {"coordinates":[-93.30027800000001,46.60746],"type":"Point"}
}