{
  "type": "Feature",
  "properties": {
    "addr:full":"14 1st Ave NE Deer River MN 56636",
    "addr:housenumber":"14",
    "addr:postcode":"56636",
    "addr:street":"1St Ave Ne",
    "iso:country":"US",
    "sg:address":"14 1st Ave NE",
    "sg:city":"Deer River",
    "sg:classifiers":[
        {
            "category":"Retail",
            "subcategory":"Funeral Services",
            "type":"Services"
        }
    ],
    "sg:phone":"+1 218 246 8181",
    "sg:postcode":"56636",
    "sg:province":"MN",
    "sg:tags":[
        "director"
    ],
    "wof:name":"Carroll Funeral Home Inc",
    "wof:placetype":"venue"
},
  "geometry": {"coordinates":[-93.79507599999999,47.333712],"type":"Point"}
}