{
  "type": "Feature",
  "properties": {
    "iso:country":"US",
    "sg:address":"650 Dellwood Dr N",
    "sg:city":"Baxter",
    "sg:classifiers":[
        {
            "category":"Restaurant",
            "type":"Food & Drink"
        }
    ],
    "sg:phone":"+1 218 828 1415",
    "sg:postcode":"56425",
    "sg:province":"MN",
    "wof:name":"Bonanza Steakhouse",
    "wof:placetype":"venue"
},
  "geometry": {"coordinates":[-94.243925,46.359434],"type":"Point"}
}