{
  "type": "Feature",
  "properties": {
    "addr:full":"110690 Village Rd Chaska MN 55318",
    "addr:housenumber":"110690",
    "addr:postcode":"55318",
    "addr:street":"Village Rd",
    "iso:country":"US",
    "sg:address":"110690 Village Rd",
    "sg:city":"Chaska",
    "sg:classifiers":[
        {
            "category":"Food & Beverages",
            "subcategory":"Groceries & Convenience Stores",
            "type":"Retail Goods"
        }
    ],
    "sg:phone":"+1 952 448 6888",
    "sg:postcode":"55318",
    "sg:province":"MN",
    "wof:name":"Jonathan General",
    "wof:placetype":"venue"
},
  "geometry": {"coordinates":[-93.609398,44.8265],"type":"Point"}
}