{
  "type": "Feature",
  "properties": {
    "addr:full":"8971 71st St NE Spicer MN 56288",
    "addr:housenumber":"8971",
    "addr:postcode":"56288",
    "addr:street":"71St St Ne",
    "iso:country":"US",
    "sg:address":"8971 71st St NE",
    "sg:city":"Spicer",
    "sg:classifiers":[
        {
            "category":"Building & Trades",
            "subcategory":"Plumbing",
            "type":"Services"
        }
    ],
    "sg:phone":"+1 320 796 2865",
    "sg:postcode":"56288",
    "sg:province":"MN",
    "sg:tags":[
        "plumbing",
        "contractor"
    ],
    "wof:name":"Strom Ron Plumbing & Heating",
    "wof:placetype":"venue"
},
  "geometry": {"coordinates":[-94.94789299999999,45.212531],"type":"Point"}
}