{
  "type": "Feature",
  "properties": {
    "addr:full":"32743 15th St Janesville MN 56048",
    "addr:housenumber":"32743",
    "addr:postcode":"56048",
    "addr:street":"15Th St",
    "iso:country":"US",
    "sg:address":"32743 15th St",
    "sg:city":"Janesville",
    "sg:classifiers":[
        {
            "category":"Manufacturing",
            "subcategory":"Food",
            "type":"Manufacturing & Wholesale Goods"
        },
        {
            "category":"Farming",
            "subcategory":"Farm",
            "type":"Manufacturing & Wholesale Goods"
        }
    ],
    "sg:phone":"+1 507 234 5282",
    "sg:postcode":"56048",
    "sg:province":"MN",
    "sg:tags":[
        "corn",
        "product"
    ],
    "wof:name":"Donald Myers Farm",
    "wof:placetype":"venue"
},
  "geometry": {"coordinates":[-93.732606,44.032698],"type":"Point"}
}