{
  "type": "Feature",
  "properties": {
    "iso:country":"US",
    "sg:address":"15245 Old Territorial Rd",
    "sg:city":"Chatfield",
    "sg:classifiers":[
        {
            "category":"Professional",
            "type":"Services"
        }
    ],
    "sg:phone":"+1 507 867 4267",
    "sg:postcode":"55923",
    "sg:province":"MN",
    "wof:name":"Scullectric",
    "wof:placetype":"venue"
},
  "geometry": {"coordinates":[-92.17304,43.85077],"type":"Point"}
}