{
  "type": "Feature",
  "properties": {
    "iso:country":"US",
    "sg:address":"3739 Brentwood Dr",
    "sg:city":"Monticello",
    "sg:classifiers":[
        {
            "category":"Real Estate",
            "subcategory":"Real Estate Agent",
            "type":"Services"
        }
    ],
    "sg:phone":"+1 763 295 5541",
    "sg:postcode":"55362",
    "sg:province":"MN",
    "wof:name":"Douglas Dickie Incorporated",
    "wof:placetype":"venue"
},
  "geometry": {"coordinates":[-93.814927,45.297007],"type":"Point"}
}