{
  "type": "Feature",
  "properties": {
    "iso:country":"US",
    "sg:address":"3553 Penn Ave N",
    "sg:city":"Minneapolis",
    "sg:classifiers":[
        {
            "category":"Health Services",
            "subcategory":"Doctor",
            "type":"Services"
        }
    ],
    "sg:phone":"+1 612 522 9361",
    "sg:postcode":"55412",
    "sg:province":"MN",
    "sg:tags":[
        "dentist"
    ],
    "wof:name":"Penn Dental Center",
    "wof:placetype":"venue"
},
  "geometry": {"coordinates":[-93.308347,45.019501],"type":"Point"}
}