{
  "type": "Feature",
  "properties": {
    "iso:country":"US",
    "sg:address":"400 N Sibley St",
    "sg:city":"St Paul",
    "sg:classifiers":[
        {
            "category":"Wholesale",
            "subcategory":"Durable Goods & Equipment",
            "type":"Manufacturing & Wholesale Goods"
        }
    ],
    "sg:phone":"+1 651 221 0517",
    "sg:postcode":"55101",
    "sg:province":"MN",
    "sg:tags":[
        "representative",
        "manufacturer"
    ],
    "wof:name":"M Ketcham Assoc",
    "wof:placetype":"venue"
},
  "geometry": {"coordinates":[-93.089551,44.950264],"type":"Point"}
}