{
  "type": "Feature",
  "properties": {
    "addr:full":"1013 Rivercrest Rd N Lakeland MN 55043",
    "addr:housenumber":"1013",
    "addr:postcode":"55043",
    "addr:street":"Rivercrest Rd N",
    "iso:country":"US",
    "sg:address":"1013 Rivercrest Rd N",
    "sg:city":"Lakeland",
    "sg:classifiers":[
        {
            "category":"Taxi",
            "type":"Transportation"
        }
    ],
    "sg:phone":"+1 651 439 9999",
    "sg:postcode":"55043",
    "sg:province":"MN",
    "sg:tags":[
        "taxicab"
    ],
    "wof:name":"A Taxi",
    "wof:placetype":"venue"
},
  "geometry": {"coordinates":[-92.77109,44.963488],"type":"Point"}
}