{
  "type": "Feature",
  "properties": {
    "addr:full":"13840 247th Ave Zimmerman MN 55398",
    "addr:housenumber":"13840",
    "addr:postcode":"55398",
    "addr:street":"247Th Ave",
    "iso:country":"US",
    "sg:address":"13840 247th Ave",
    "sg:city":"Zimmerman",
    "sg:classifiers":[
        {
            "category":"Utilities",
            "subcategory":"Refuse",
            "type":"Services"
        },
        {
            "category":"Professional",
            "subcategory":"Employment Agencies",
            "type":"Services"
        }
    ],
    "sg:phone":"+1 763 274 0925",
    "sg:postcode":"55398",
    "sg:province":"MN",
    "sg:tags":[
        "garbage",
        "help",
        "collection",
        "supply"
    ],
    "wof:name":"Steinbrecher Co Inc",
    "wof:placetype":"venue"
},
  "geometry": {"coordinates":[-93.62034800000001,45.418446],"type":"Point"}
}