{
  "type": "Feature",
  "properties": {
    "addr:full":"7717 W 99th Street Cir Minneapolis MN 55438",
    "addr:housenumber":"7717",
    "addr:postcode":"55438",
    "addr:street":"W 99Th Street Cir",
    "iso:country":"US",
    "sg:address":"7717 W 99th Street Cir",
    "sg:city":"Minneapolis",
    "sg:classifiers":[
        {
            "category":"Wholesale",
            "subcategory":"Office Equipment",
            "type":"Manufacturing & Wholesale Goods"
        }
    ],
    "sg:phone":"+1 952 941 7772",
    "sg:postcode":"55438",
    "sg:province":"MN",
    "sg:tags":[
        "equipment-wholesale",
        "manufacturer",
        "furniture"
    ],
    "wof:name":"Ylinen & Assoc",
    "wof:placetype":"venue"
},
  "geometry": {"coordinates":[-93.384618,44.823114],"type":"Point"}
}