{
  "type": "Feature",
  "properties": {
    "addr:full":"6705 40th St SW Howard Lake MN 55349",
    "addr:housenumber":"6705",
    "addr:postcode":"55349",
    "addr:street":"40Th St Sw",
    "iso:country":"US",
    "sg:address":"6705 40th St SW",
    "sg:city":"Howard Lake",
    "sg:phone":"+1 320 543 2808",
    "sg:postcode":"55349",
    "sg:province":"MN",
    "sg:tags":[
        "farm",
        "corn"
    ],
    "wof:name":"Daryl Buttenhoff",
    "wof:placetype":"venue"
},
  "geometry": {"coordinates":[-94.025622,45.094454],"type":"Point"}
}