{
  "type": "Feature",
  "properties": {
    "addr:full":"1950 Excel Dr Mankato MN 56001",
    "addr:housenumber":"1950",
    "addr:postcode":"56001",
    "addr:street":"Excel Dr",
    "iso:country":"US",
    "sg:address":"1950 Excel Dr",
    "sg:city":"Mankato",
    "sg:classifiers":[
        {
            "category":"Manufacturing",
            "subcategory":"Electronics",
            "type":"Manufacturing & Wholesale Goods"
        }
    ],
    "sg:phone":"+1 507 625 7231",
    "sg:postcode":"56001",
    "sg:province":"MN",
    "sg:tags":[
        "component",
        "mfg"
    ],
    "sg:website":"www.winland.com",
    "wof:name":"Winland Electronics Inc",
    "wof:placetype":"venue"
},
  "geometry": {"coordinates":[-93.946952,44.177784],"type":"Point"}
}