{
  "type": "Feature",
  "properties": {
    "iso:country":"US",
    "sg:address":"35435 130 St",
    "sg:city":"Frazee",
    "sg:classifiers":[
        {
            "category":"Retail",
            "subcategory":"Repair Shop",
            "type":"Services"
        }
    ],
    "sg:phone":"+1 218 334 5791",
    "sg:postcode":"56544",
    "sg:province":"MN",
    "wof:name":"Rons TV Service",
    "wof:placetype":"venue"
},
  "geometry": {"coordinates":[-95.78827099999999,46.760096],"type":"Point"}
}