{
  "type": "Feature",
  "properties": {
    "addr:full":"7207 Forestview Ln N Osseo MN 55369",
    "addr:housenumber":"7207",
    "addr:postcode":"55369",
    "addr:street":"Forestview Ln N",
    "iso:country":"US",
    "sg:address":"7207 Forestview Ln N",
    "sg:city":"Osseo",
    "sg:classifiers":[
        {
            "category":"Professional",
            "subcategory":"Business Services",
            "type":"Services"
        }
    ],
    "sg:phone":"+1 763 201 1122",
    "sg:postcode":"55369",
    "sg:province":"MN",
    "wof:name":"Preferred Resource Group",
    "wof:placetype":"venue"
},
  "geometry": {"coordinates":[-93.428785,45.086449],"type":"Point"}
}