{
  "type": "Feature",
  "properties": {
    "addr:full":"850 Lake St E Wayzata MN 55391",
    "addr:housenumber":"850",
    "addr:postcode":"55391",
    "addr:street":"Lake St E",
    "iso:country":"US",
    "sg:address":"850 Lake St E",
    "sg:city":"Wayzata",
    "sg:classifiers":[
        {
            "category":"Recreation",
            "type":"Entertainment"
        }
    ],
    "sg:phone":"+1 763 473 8454",
    "sg:postcode":"55391",
    "sg:province":"MN",
    "wof:name":"Wayzata Art Gallery",
    "wof:placetype":"venue"
},
  "geometry": {"coordinates":[-93.504514,44.967469],"type":"Point"}
}