{
  "type": "Feature",
  "properties": {
    "iso:country":"US",
    "sg:address":"324 W Superior St",
    "sg:city":"Duluth",
    "sg:classifiers":[
        {
            "category":"Health Services",
            "subcategory":"Dentist",
            "type":"Services"
        }
    ],
    "sg:phone":"+1 218 722 0219",
    "sg:postcode":"55802",
    "sg:province":"MN",
    "sg:website":"http://www.timlangguth.com",
    "wof:name":"Langguth, Timothy R",
    "wof:placetype":"venue"
},
  "geometry": {"coordinates":[-92.102183,46.783845],"type":"Point"}
}