{
  "type": "Feature",
  "properties": {
    "addr:full":"411 S Main St Zumbrota MN 55992",
    "addr:housenumber":"411",
    "addr:postcode":"55992",
    "addr:street":"S Main St",
    "iso:country":"US",
    "sg:address":"411 S Main St",
    "sg:city":"Zumbrota",
    "sg:classifiers":[
        {
            "category":"Professional",
            "subcategory":"Management & Consulting",
            "type":"Services"
        }
    ],
    "sg:phone":"+1 507 732 5804",
    "sg:postcode":"55992",
    "sg:province":"MN",
    "sg:tags":[
        "consultant",
        "energy",
        "conservation"
    ],
    "wof:name":"Cimco Resources",
    "wof:placetype":"venue"
},
  "geometry": {"coordinates":[-92.669066,44.293166],"type":"Point"}
}