{
  "type": "Feature",
  "properties": {
    "addr:full":"16 1/2 Loring Rd Ste 100 Hopkins MN 55305",
    "addr:housenumber":"1 / 2",
    "addr:postcode":"55305",
    "addr:street":"16;Loring Rd Ste 100",
    "iso:country":"US",
    "sg:address":"16 1/2 Loring Rd Ste 100",
    "sg:city":"Hopkins",
    "sg:classifiers":[
        {
            "category":"Professional",
            "subcategory":"Management & Consulting",
            "type":"Services"
        },
        {
            "category":"Professional",
            "subcategory":"Employment Agencies",
            "type":"Services"
        },
        {
            "category":"Professional",
            "subcategory":"Engineering",
            "type":"Services"
        }
    ],
    "sg:phone":"+1 952 938 3032",
    "sg:postcode":"55305",
    "sg:province":"MN",
    "sg:tags":[
        "consultant",
        "resource",
        "human",
        "engineer"
    ],
    "sg:website":"http://www.lawson-intl.com",
    "wof:name":"Lawson International Ltd",
    "wof:placetype":"venue"
},
  "geometry": {"coordinates":[-93.41473999999999,44.943045],"type":"Point"}
}