{
  "type": "Feature",
  "properties": {
    "iso:country":"US",
    "sg:address":"3268 117th Ave NW",
    "sg:city":"Minneapolis",
    "sg:classifiers":[
        {
            "category":"Social Services",
            "subcategory":"Child Care",
            "type":"Services"
        }
    ],
    "sg:phone":"+1 763 427 5568",
    "sg:postcode":"55433",
    "sg:province":"MN",
    "sg:tags":[
        "daycare",
        "provider"
    ],
    "wof:name":"Mary Jones",
    "wof:placetype":"venue"
},
  "geometry": {"coordinates":[-93.349963,45.183508],"type":"Point"}
}