{
  "type": "Feature",
  "properties": {
    "iso:country":"US",
    "sg:address":"2800 Lasalle Plz",
    "sg:city":"Minneapolis",
    "sg:classifiers":[
        {
            "category":"Professional",
            "subcategory":"Lawyer & Legal Services",
            "type":"Services"
        }
    ],
    "sg:phone":"+1 612 349 0820",
    "sg:postcode":"55401",
    "sg:province":"MN",
    "wof:name":"Spreng Kevin S",
    "wof:placetype":"venue"
},
  "geometry": {"coordinates":[-93.269997,44.984501],"type":"Point"}
}