{
  "type": "Feature",
  "properties": {
    "addr:full":"416 N Central Ave Duluth MN 55807",
    "addr:housenumber":"416",
    "addr:postcode":"55807",
    "addr:street":"N Central Ave",
    "iso:country":"US",
    "sg:address":"416 N Central Ave",
    "sg:city":"Duluth",
    "sg:classifiers":[
        {
            "category":"Health Services",
            "subcategory":"Doctor",
            "type":"Services"
        }
    ],
    "sg:phone":"+1 218 624 2095",
    "sg:postcode":"55807",
    "sg:province":"MN",
    "sg:tags":[
        "medical"
    ],
    "wof:name":"Theobald Family Eye Care",
    "wof:placetype":"venue"
},
  "geometry": {"coordinates":[-92.16644700000001,46.739562],"type":"Point"}
}