{
  "type": "Feature",
  "properties": {
    "addr:full":"2123 Chicago Ave S Minneapolis MN 55404",
    "addr:housenumber":"2123",
    "addr:postcode":"55404",
    "addr:street":"Chicago Ave S",
    "iso:country":"US",
    "sg:address":"2123 Chicago Ave S",
    "sg:city":"Minneapolis",
    "sg:classifiers":[
        {
            "category":"Organizations",
            "subcategory":"Religious Organization",
            "type":"Services"
        }
    ],
    "sg:phone":"+1 612 872 8587",
    "sg:postcode":"55404",
    "sg:province":"MN",
    "sg:tags":[
        "church"
    ],
    "wof:name":"Christian Restoration Chr",
    "wof:placetype":"venue"
},
  "geometry": {"coordinates":[-93.26248200000001,44.96112],"type":"Point"}
}