{
  "type": "Feature",
  "properties": {
    "addr:full":"184 Appleblossom Ln Shakopee MN 55379",
    "addr:housenumber":"184",
    "addr:postcode":"55379",
    "addr:street":"Appleblossom Ln",
    "iso:country":"US",
    "sg:address":"184 Appleblossom Ln",
    "sg:city":"Shakopee",
    "sg:classifiers":[
        {
            "category":"Personal",
            "subcategory":"Beauty Salon",
            "type":"Services"
        }
    ],
    "sg:phone":"+1 952 496 0819",
    "sg:postcode":"55379",
    "sg:province":"MN",
    "sg:tags":[
        "shop"
    ],
    "wof:name":"P K Nails",
    "wof:placetype":"venue"
},
  "geometry": {"coordinates":[-93.52646,44.777246],"type":"Point"}
}