{
  "type": "Feature",
  "properties": {
    "addr:full":"4804 Harriet Ave Minneapolis MN 55419",
    "addr:housenumber":"4804",
    "addr:postcode":"55419",
    "addr:street":"Harriet Ave",
    "iso:country":"US",
    "sg:address":"4804 Harriet Ave",
    "sg:city":"Minneapolis",
    "sg:classifiers":[
        {
            "category":"Wholesale",
            "subcategory":"Farm Supplies",
            "type":"Manufacturing & Wholesale Goods"
        }
    ],
    "sg:phone":"+1 612 825 0149",
    "sg:postcode":"55419",
    "sg:province":"MN",
    "sg:tags":[
        "equipment"
    ],
    "wof:name":"Farmhealth",
    "wof:placetype":"venue"
},
  "geometry": {"coordinates":[-93.285713,44.915881],"type":"Point"}
}