{
  "type": "Feature",
  "properties": {
    "iso:country":"US",
    "sg:address":"6256 34th Ave NW",
    "sg:city":"Rochester",
    "sg:classifiers":[
        {
            "category":"Wholesale",
            "subcategory":"Machinery & Supplies",
            "type":"Manufacturing & Wholesale Goods"
        },
        {
            "category":"Retail",
            "subcategory":"Veterinary Services",
            "type":"Services"
        }
    ],
    "sg:phone":"+1 507 281 1000",
    "sg:postcode":"55901",
    "sg:province":"MN",
    "sg:tags":[
        "wholesaler",
        "equipment",
        "implant",
        "orthopedics",
        "veterinarian"
    ],
    "wof:name":"Innovative Animal Products LLC",
    "wof:placetype":"venue"
},
  "geometry": {"coordinates":[-92.51405,44.091022],"type":"Point"}
}