{
  "type": "Feature",
  "properties": {
    "addr:full":"6213 Kahler Dr NE Albertville MN 55301",
    "addr:postcode":"6213;55301",
    "addr:street":"Kahler Dr Ne",
    "iso:country":"US",
    "sg:address":"6213 Kahler Dr NE",
    "sg:city":"Albertville",
    "sg:classifiers":[
        {
            "category":"Building & Trades",
            "subcategory":"Construction",
            "type":"Services"
        }
    ],
    "sg:phone":"+1 763 497 0336",
    "sg:postcode":"55301",
    "sg:province":"MN",
    "wof:name":"Ultimate Base & Prep",
    "wof:placetype":"venue"
},
  "geometry": {"coordinates":[-93.672433,45.243293],"type":"Point"}
}