{
  "type": "Feature",
  "properties": {
    "iso:country":"US",
    "sg:address":"1156 W Broadway Ave",
    "sg:city":"Forest Lake",
    "sg:classifiers":[
        {
            "category":"Personal",
            "subcategory":"Beauty Salon",
            "type":"Services"
        }
    ],
    "sg:phone":"+1 651 464 6717",
    "sg:postcode":"55025",
    "sg:province":"MN",
    "sg:tags":[
        "shop"
    ],
    "wof:name":"Pt Nails",
    "wof:placetype":"venue"
},
  "geometry": {"coordinates":[-92.998081,45.279378],"type":"Point"}
}