{
  "type": "Feature",
  "properties": {
    "addr:full":"723 Pierce St NE Minneapolis MN 55413",
    "addr:housenumber":"723",
    "addr:postcode":"55413",
    "addr:street":"Pierce St Ne",
    "iso:country":"US",
    "sg:address":"723 Pierce St NE",
    "sg:city":"Minneapolis",
    "sg:classifiers":[
        {
            "category":"Professional",
            "type":"Services"
        }
    ],
    "sg:phone":"+1 612 623 8196",
    "sg:postcode":"55413",
    "sg:province":"MN",
    "sg:tags":[
        "publication",
        "editorial"
    ],
    "sg:website":"http://www.marybyers.com",
    "wof:name":"Mary Byers",
    "wof:placetype":"venue"
},
  "geometry": {"coordinates":[-93.24099099999999,44.997303],"type":"Point"}
}