{
  "type": "Feature",
  "properties": {
    "iso:country":"US",
    "sg:address":"822 Selby Ave",
    "sg:city":"Saint Paul",
    "sg:classifiers":[
        {
            "category":"Building & Trades",
            "subcategory":"Cleaning & Sanitation",
            "type":"Services"
        }
    ],
    "sg:phone":"+1 651 222 4217",
    "sg:postcode":"55104",
    "sg:province":"MN",
    "wof:name":"L & L Cleaning Service Inc",
    "wof:placetype":"venue"
},
  "geometry": {"coordinates":[-93.136393,44.946519],"type":"Point"}
}