{
  "type": "Feature",
  "properties": {
    "addr:full":"1825 Curve Crest Blvd W Stillwater MN 55082",
    "addr:housenumber":"1825",
    "addr:postcode":"55082",
    "addr:street":"Curve Crest Blvd W",
    "iso:country":"US",
    "sg:address":"1825 Curve Crest Blvd W",
    "sg:city":"Stillwater",
    "sg:classifiers":[
        {
            "category":"Government",
            "subcategory":"Office",
            "type":"Public Place"
        }
    ],
    "sg:phone":"+1 651 351 7946",
    "sg:postcode":"55082",
    "sg:province":"MN",
    "sg:tags":[
        "farm",
        "agency"
    ],
    "wof:name":"Farm Service Agency",
    "wof:placetype":"venue"
},
  "geometry": {"coordinates":[-92.830703,45.040283],"type":"Point"}
}