{
  "type": "Feature",
  "properties": {
    "iso:country":"US",
    "sg:address":"3099 65th St E",
    "sg:city":"Inver Grove Hts",
    "sg:classifiers":[
        {
            "category":"Building & Trades",
            "subcategory":"Landscaping Services",
            "type":"Services"
        }
    ],
    "sg:phone":"+1 651 450 6228",
    "sg:postcode":"55076",
    "sg:province":"MN",
    "sg:tags":[
        "lawn",
        "snowplowing",
        "maintenance",
        "grounds"
    ],
    "wof:name":"Total Lawn Care Maintenance",
    "wof:placetype":"venue"
},
  "geometry": {"coordinates":[-93.04495,44.85528],"type":"Point"}
}