{
  "type": "Feature",
  "properties": {
    "addr:full":"626 E Center St Rochester MN 55904",
    "addr:housenumber":"626",
    "addr:postcode":"55904",
    "addr:street":"E Center St",
    "iso:country":"US",
    "sg:address":"626 E Center St",
    "sg:city":"Rochester",
    "sg:classifiers":[
        {
            "category":"Real Estate",
            "subcategory":"Real Estate Operator",
            "type":"Services"
        }
    ],
    "sg:phone":"+1 507 285 9469",
    "sg:postcode":"55904",
    "sg:province":"MN",
    "sg:tags":[
        "building",
        "apartment"
    ],
    "wof:name":"Center St Village Apartments",
    "wof:placetype":"venue"
},
  "geometry": {"coordinates":[-92.454139,44.023398],"type":"Point"}
}