{
  "type": "Feature",
  "properties": {
    "iso:country":"US",
    "sg:address":"220 Saint Paul St NW",
    "sg:city":"Preston",
    "sg:classifiers":[
        {
            "category":"Manufacturing",
            "subcategory":"Food",
            "type":"Manufacturing & Wholesale Goods"
        }
    ],
    "sg:phone":"+1 507 765 3831",
    "sg:postcode":"55965",
    "sg:province":"MN",
    "sg:tags":[
        "dry",
        "prod",
        "dairy"
    ],
    "sg:website":"www.foremostfarms.com",
    "wof:name":"Foremost Farms USA",
    "wof:placetype":"venue"
},
  "geometry": {"coordinates":[-92.083206,43.672926],"type":"Point"}
}