{
  "type": "Feature",
  "properties": {
    "iso:country":"US",
    "sg:address":"3016 Colfax Ave S",
    "sg:city":"Minneapolis",
    "sg:classifiers":[
        {
            "category":"Shopping",
            "subcategory":"Bicycles & Sporting Goods",
            "type":"Retail Goods"
        }
    ],
    "sg:phone":"+1 612 822 8978",
    "sg:postcode":"55408",
    "sg:province":"MN",
    "wof:name":"R P Cycling Inc",
    "wof:placetype":"venue"
},
  "geometry": {"coordinates":[-93.292002,44.946887],"type":"Point"}
}