{
  "type": "Feature",
  "properties": {
    "addr:full":"1011 Feltl Ct Hopkins MN 55343",
    "addr:housenumber":"1011",
    "addr:postcode":"55343",
    "addr:street":"Feltl Ct",
    "iso:country":"US",
    "sg:address":"1011 Feltl Ct",
    "sg:city":"Hopkins",
    "sg:classifiers":[
        {
            "category":"Health Services",
            "subcategory":"Nursing And Care Facility",
            "type":"Services"
        }
    ],
    "sg:phone":"+1 952 392 8330",
    "sg:postcode":"55343",
    "sg:province":"MN",
    "sg:tags":[
        "home",
        "retirement",
        "people",
        "community",
        "homes-elderly"
    ],
    "sg:website":"http://www.sttheresesouthwest.com",
    "wof:name":"St Therese Southwest",
    "wof:placetype":"venue"
},
  "geometry": {"coordinates":[-93.419157,44.907921],"type":"Point"}
}