{
  "type": "Feature",
  "properties": {
    "addr:full":"26813 Co Rd 6 Grey Eagle MN 56336",
    "addr:housenumber":"26813",
    "addr:postcode":"56336",
    "addr:street":"Co Rd 6",
    "iso:country":"US",
    "sg:address":"26813 Co Rd 6",
    "sg:city":"Grey Eagle",
    "sg:phone":"+1 320 285 2388",
    "sg:postcode":"56336",
    "sg:province":"MN",
    "sg:tags":[
        "farm",
        "field",
        "corn",
        "crop"
    ],
    "wof:name":"Thomas Berscheit",
    "wof:placetype":"venue"
},
  "geometry": {"coordinates":[-94.811362,45.839406],"type":"Point"}
}