{
  "type": "Feature",
  "properties": {
    "iso:country":"US",
    "sg:address":"15265 Minnetonka Blvd",
    "sg:city":"Minnetonka",
    "sg:classifiers":[
        {
            "category":"Wholesale",
            "subcategory":"Electrical",
            "type":"Manufacturing & Wholesale Goods"
        }
    ],
    "sg:phone":"+1 952 944 8387",
    "sg:postcode":"55345",
    "sg:province":"MN",
    "sg:tags":[
        "light",
        "tube",
        "bulb"
    ],
    "sg:website":"www.budgetlighting.com",
    "wof:name":"Ameri-Star Lighting",
    "wof:placetype":"venue"
},
  "geometry": {"coordinates":[-93.470264,44.937397],"type":"Point"}
}