{
  "type": "Feature",
  "properties": {
    "addr:full":"11 Main St N New London MN 56273",
    "addr:housenumber":"11",
    "addr:postcode":"56273",
    "addr:street":"Main St N",
    "iso:country":"US",
    "sg:address":"11 Main St N",
    "sg:city":"New London",
    "sg:classifiers":[
        {
            "category":"Shopping",
            "subcategory":"Florist",
            "type":"Retail Goods"
        }
    ],
    "sg:phone":"+1 320 354 7241",
    "sg:postcode":"56273",
    "sg:province":"MN",
    "sg:website":"www.angelsandivynewlondon.com",
    "wof:name":"Angels & Ivy",
    "wof:placetype":"venue"
},
  "geometry": {"coordinates":[-94.943966,45.301771],"type":"Point"}
}