{
  "type": "Feature",
  "properties": {
    "addr:full":"1590 Hwy 55 Hastings MN 55033",
    "addr:housenumber":"1590",
    "addr:postcode":"55033",
    "addr:street":"Hwy 55",
    "iso:country":"US",
    "sg:address":"1590 Hwy 55",
    "sg:city":"Hastings",
    "sg:classifiers":[
        {
            "category":"Government",
            "subcategory":"Office",
            "type":"Public Place"
        }
    ],
    "sg:phone":"+1 651 438 4353",
    "sg:postcode":"55033",
    "sg:province":"MN",
    "wof:name":"Dakota County Property Mgmt",
    "wof:placetype":"venue"
},
  "geometry": {"coordinates":[-92.88610300000001,44.738428],"type":"Point"}
}