{
  "type": "Feature",
  "properties": {
    "addr:full":"196 36th Ave NW Rochester MN 55901",
    "addr:housenumber":"196",
    "addr:postcode":"55901",
    "addr:street":"36Th Ave Nw",
    "iso:country":"US",
    "sg:address":"196 36th Ave NW",
    "sg:city":"Rochester",
    "sg:classifiers":[
        {
            "category":"Social Services",
            "subcategory":"Child Care",
            "type":"Services"
        }
    ],
    "sg:phone":"+1 507 288 2090",
    "sg:postcode":"55901",
    "sg:province":"MN",
    "sg:tags":[
        "daycare"
    ],
    "wof:name":"Cynthia A Hoban",
    "wof:placetype":"venue"
},
  "geometry": {"coordinates":[-92.51709700000001,44.022195],"type":"Point"}
}