{
  "type": "Feature",
  "properties": {
    "iso:country":"US",
    "sg:address":"1550 Hwy 71 NE",
    "sg:city":"Willmar",
    "sg:classifiers":[
        {
            "category":"Government",
            "subcategory":"Office",
            "type":"Public Place"
        }
    ],
    "sg:phone":"+1 320 231 5962",
    "sg:postcode":"56201",
    "sg:province":"MN",
    "sg:tags":[
        "state"
    ],
    "wof:name":"Ombudsman For Mental Health",
    "wof:placetype":"venue"
},
  "geometry": {"coordinates":[-95.023894,45.139518],"type":"Point"}
}