{
  "type": "Feature",
  "properties": {
    "iso:country":"US",
    "sg:address":"1170 Main St NW",
    "sg:city":"Elk River",
    "sg:classifiers":[
        {
            "category":"Education",
            "subcategory":"School",
            "type":"Public Place"
        }
    ],
    "sg:phone":"+1 763 241 3510",
    "sg:postcode":"55330",
    "sg:province":"MN",
    "sg:tags":[
        "elementary"
    ],
    "wof:name":"Handke Elementary School",
    "wof:placetype":"venue"
},
  "geometry": {"coordinates":[-93.552509,45.312816],"type":"Point"}
}