{
  "type": "Feature",
  "properties": {
    "addr:full":"616 45th Ave N Minneapolis MN 55412",
    "addr:housenumber":"616",
    "addr:postcode":"55412",
    "addr:street":"45Th Ave N",
    "iso:country":"US",
    "sg:address":"616 45th Ave N",
    "sg:city":"Minneapolis",
    "sg:classifiers":[
        {
            "category":"Retail",
            "subcategory":"Auto Repair",
            "type":"Services"
        }
    ],
    "sg:phone":"+1 612 529 7300",
    "sg:postcode":"55412",
    "sg:province":"MN",
    "wof:name":"Milan's Motor Towing & Service",
    "wof:placetype":"venue"
},
  "geometry": {"coordinates":[-93.28780399999999,45.0369],"type":"Point"}
}