{
  "type": "Feature",
  "properties": {
    "iso:country":"US",
    "sg:address":"1644 N Victoria St",
    "sg:city":"St Paul",
    "sg:classifiers":[
        {
            "category":"Real Estate",
            "subcategory":"Real Estate Agent",
            "type":"Services"
        }
    ],
    "sg:phone":"+1 651 487 8062",
    "sg:postcode":"55117",
    "sg:province":"MN",
    "wof:name":"Home Sale Svc Of Minnesota",
    "wof:placetype":"venue"
},
  "geometry": {"coordinates":[-93.137669,44.990285],"type":"Point"}
}