{
  "type": "Feature",
  "properties": {
    "addr:full":"5832 Olinger Blvd Minneapolis MN 55436",
    "addr:housenumber":"5832",
    "addr:postcode":"55436",
    "addr:street":"Olinger Blvd",
    "iso:country":"US",
    "sg:address":"5832 Olinger Blvd",
    "sg:city":"Minneapolis",
    "sg:classifiers":[
        {
            "category":"Wholesale",
            "subcategory":"Motor Vehicles",
            "type":"Manufacturing & Wholesale Goods"
        }
    ],
    "sg:phone":"+1 952 920 1529",
    "sg:postcode":"55436",
    "sg:province":"MN",
    "wof:name":"Burris Marketing Inc",
    "wof:placetype":"venue"
},
  "geometry": {"coordinates":[-93.38042,44.898459],"type":"Point"}
}