{
  "type": "Feature",
  "properties": {
    "iso:country":"US",
    "sg:address":"329 Division St S",
    "sg:city":"Northfield",
    "sg:classifiers":[
        {
            "category":"Banks & Credit Unions",
            "subcategory":"Bank",
            "type":"Services"
        }
    ],
    "sg:phone":"+1 507 645 5656",
    "sg:postcode":"55057",
    "sg:province":"MN",
    "sg:website":"www.firstnationalnfld.com",
    "wof:name":"First National Bank",
    "wof:placetype":"venue"
},
  "geometry": {"coordinates":[-93.159615,44.457027],"type":"Point"}
}