{
  "type": "Feature",
  "properties": {
    "addr:full":"6000 Pleasant Ave Minneapolis MN 55419",
    "addr:housenumber":"6000",
    "addr:postcode":"55419",
    "addr:street":"Pleasant Ave",
    "iso:country":"US",
    "sg:address":"6000 Pleasant Ave",
    "sg:city":"Minneapolis",
    "sg:classifiers":[
        {
            "category":"Building & Trades",
            "subcategory":"Landscaping Services",
            "type":"Services"
        }
    ],
    "sg:phone":"+1 612 825 8000",
    "sg:postcode":"55419",
    "sg:province":"MN",
    "sg:tags":[
        "gardener",
        "lawn",
        "snow",
        "maintenance",
        "removal"
    ],
    "sg:website":"http://www.lawnandturfonline.com",
    "wof:name":"Lawn & Turf Corp",
    "wof:placetype":"venue"
},
  "geometry": {"coordinates":[-93.28346000000001,44.89422],"type":"Point"}
}