{
  "type": "Feature",
  "properties": {
    "iso:country":"US",
    "sg:address":"1265 20th St",
    "sg:city":"Windom",
    "sg:classifiers":[
        {
            "category":"Social Services",
            "subcategory":"Child Care",
            "type":"Services"
        }
    ],
    "sg:phone":"+1 507 831 1646",
    "sg:postcode":"56101",
    "sg:province":"MN",
    "sg:tags":[
        "day",
        "provides"
    ],
    "wof:name":"Storybook Daycare",
    "wof:placetype":"venue"
},
  "geometry": {"coordinates":[-95.126969,43.877295],"type":"Point"}
}