{
  "type": "Feature",
  "properties": {
    "addr:full":"2239 Carter Ave St Paul MN 55108",
    "addr:housenumber":"2239",
    "addr:postcode":"55108",
    "addr:street":"Carter Ave",
    "iso:country":"US",
    "sg:address":"2239 Carter Ave",
    "sg:city":"St Paul",
    "sg:classifiers":[
        {
            "category":"Health Services",
            "subcategory":"Health Practitioner",
            "type":"Services"
        }
    ],
    "sg:phone":"+1 651 646 9656",
    "sg:postcode":"55108",
    "sg:province":"MN",
    "sg:tags":[
        "psychologist"
    ],
    "wof:name":"Claude Riedel",
    "wof:placetype":"venue"
},
  "geometry": {"coordinates":[-93.19707,44.980797],"type":"Point"}
}