{
  "type": "Feature",
  "properties": {
    "iso:country":"US",
    "sg:address":"1030 Hwy 96 E",
    "sg:city":"Saint Paul",
    "sg:classifiers":[
        {
            "category":"Retail",
            "subcategory":"Laundry & Dry Cleaning",
            "type":"Services"
        }
    ],
    "sg:phone":"+1 651 426 8856",
    "sg:postcode":"55127",
    "sg:province":"MN",
    "sg:tags":[
        "drycleaning",
        "plant"
    ],
    "wof:name":"Clean N Press",
    "wof:placetype":"venue"
},
  "geometry": {"coordinates":[-93.061251,45.079255],"type":"Point"}
}