{
  "type": "Feature",
  "properties": {
    "addr:full":"930 Crestview Ln Owatonna MN 55060",
    "addr:housenumber":"930",
    "addr:postcode":"55060",
    "addr:street":"Crestview Ln",
    "iso:country":"US",
    "sg:address":"930 Crestview Ln",
    "sg:city":"Owatonna",
    "sg:classifiers":[
        {
            "category":"Health Services",
            "subcategory":"Chiropractor",
            "type":"Services"
        }
    ],
    "sg:phone":"+1 507 455 1025",
    "sg:postcode":"55060",
    "sg:province":"MN",
    "wof:name":"I A C O H C",
    "wof:placetype":"venue"
},
  "geometry": {"coordinates":[-93.193128,44.093265],"type":"Point"}
}