{
  "type": "Feature",
  "properties": {
    "addr:full":"610 N Main St Starbuck MN 56381",
    "addr:housenumber":"610",
    "addr:postcode":"56381",
    "addr:street":"N Main St",
    "iso:country":"US",
    "sg:address":"610 N Main St",
    "sg:city":"Starbuck",
    "sg:classifiers":[
        {
            "category":"Food & Beverages",
            "subcategory":"Groceries & Convenience Stores",
            "type":"Retail Goods"
        }
    ],
    "sg:phone":"+1 320 239 4587",
    "sg:postcode":"56381",
    "sg:province":"MN",
    "wof:name":"Petro Plus Inc",
    "wof:placetype":"venue"
},
  "geometry": {"coordinates":[-95.53105100000001,45.614394],"type":"Point"}
}