{
  "type": "Feature",
  "properties": {
    "iso:country":"US",
    "sg:address":"12678 Lake Blvd",
    "sg:city":"Lindstrom",
    "sg:classifiers":[
        {
            "category":"Restaurant",
            "type":"Food & Drink"
        }
    ],
    "sg:phone":"+1 651 257 4072",
    "sg:postcode":"55045",
    "sg:province":"MN",
    "sg:website":"www.swedishinn.com",
    "wof:name":"Swedish Inn",
    "wof:placetype":"venue"
},
  "geometry": {"coordinates":[-92.850325,45.389996],"type":"Point"}
}