{
  "type": "Feature",
  "properties": {
    "addr:full":"1304 2nd St NE Minneapolis MN 55413",
    "addr:housenumber":"1304",
    "addr:postcode":"55413",
    "addr:street":"2Nd St Ne",
    "iso:country":"US",
    "sg:address":"1304 2nd St NE",
    "sg:city":"Minneapolis",
    "sg:classifiers":[
        {
            "category":"Shopping",
            "type":"Retail Goods"
        }
    ],
    "sg:phone":"+1 612 331 4882",
    "sg:postcode":"55413",
    "sg:province":"MN",
    "sg:tags":[
        "picture"
    ],
    "wof:name":"Lefavor Pictures Inc",
    "wof:placetype":"venue"
},
  "geometry": {"coordinates":[-93.266203,45.001951],"type":"Point"}
}