{
  "type": "Feature",
  "properties": {
    "addr:full":"20993 Elkview Cir Richmond MN 56368",
    "addr:postcode":"20993;56368",
    "addr:street":"Elkview Cir",
    "iso:country":"US",
    "sg:address":"20993 Elkview Cir",
    "sg:city":"Richmond",
    "sg:classifiers":[
        {
            "category":"Building & Trades",
            "subcategory":"Construction",
            "type":"Services"
        }
    ],
    "sg:phone":"+1 320 597 3188",
    "sg:postcode":"56368",
    "sg:province":"MN",
    "sg:tags":[
        "house"
    ],
    "wof:name":"Dons Building & Remodeling",
    "wof:placetype":"venue"
},
  "geometry": {"coordinates":[-94.526529,45.429612],"type":"Point"}
}