{
  "type": "Feature",
  "properties": {
    "iso:country":"US",
    "sg:address":"1959 Sloan St",
    "sg:city":"Saint Paul",
    "sg:classifiers":[
        {
            "category":"Professional",
            "subcategory":"Lawyer & Legal Services",
            "type":"Services"
        }
    ],
    "sg:phone":"+1 651 631 1746",
    "sg:postcode":"55117",
    "sg:province":"MN",
    "wof:name":"Clark Thurn",
    "wof:placetype":"venue"
},
  "geometry": {"coordinates":[-93.08819200000001,44.998382],"type":"Point"}
}