{
  "type": "Feature",
  "properties": {
    "addr:full":"502 S 6th St Brainerd MN 56401",
    "addr:housenumber":"502",
    "addr:postcode":"56401",
    "addr:street":"S 6Th St",
    "iso:country":"US",
    "sg:address":"502 S 6th St",
    "sg:city":"Brainerd",
    "sg:classifiers":[
        {
            "category":"Building & Trades",
            "subcategory":"Construction",
            "type":"Services"
        }
    ],
    "sg:phone":"+1 218 828 2021",
    "sg:postcode":"56401",
    "sg:province":"MN",
    "sg:tags":[
        "material",
        "contractor"
    ],
    "wof:name":"Unique Furnishings & Fixture",
    "wof:placetype":"venue"
},
  "geometry": {"coordinates":[-94.200745,46.353663],"type":"Point"}
}