{
  "type": "Feature",
  "properties": {
    "iso:country":"US",
    "sg:address":"121 8th St S",
    "sg:city":"Minneapolis",
    "sg:classifiers":[
        {
            "category":"Banks & Credit Unions",
            "subcategory":"Investment Brokerage",
            "type":"Services"
        }
    ],
    "sg:phone":"+1 612 630 2090",
    "sg:postcode":"55402",
    "sg:province":"MN",
    "sg:tags":[
        "advisory",
        "financial"
    ],
    "sg:website":"www.falkerinvestments.com",
    "wof:name":"Falker Investments",
    "wof:placetype":"venue"
},
  "geometry": {"coordinates":[-93.270574,44.974797],"type":"Point"}
}