{
  "type": "Feature",
  "properties": {
    "addr:full":"210 Nokomis St Alexandria MN 56308",
    "addr:housenumber":"210",
    "addr:postcode":"56308",
    "addr:street":"Nokomis St",
    "iso:country":"US",
    "sg:address":"210 Nokomis St",
    "sg:city":"Alexandria",
    "sg:classifiers":[
        {
            "category":"Banks & Credit Unions",
            "subcategory":"Bank",
            "type":"Services"
        }
    ],
    "sg:phone":"+1 320 859 2006",
    "sg:postcode":"56308",
    "sg:province":"MN",
    "sg:tags":[
        "mortgage"
    ],
    "wof:name":"Mortgage & Investment Services",
    "wof:placetype":"venue"
},
  "geometry": {"coordinates":[-95.366704,45.890445],"type":"Point"}
}