{
  "type": "Feature",
  "properties": {
    "iso:country":"US",
    "sg:address":"137 9th Ave N",
    "sg:city":"Hopkins",
    "sg:classifiers":[
        {
            "category":"Professional",
            "subcategory":"Accounting & Tax Preparation",
            "type":"Services"
        }
    ],
    "sg:phone":"+1 952 912 0858",
    "sg:postcode":"55343",
    "sg:province":"MN",
    "sg:tags":[
        "consulting",
        "management",
        "s"
    ],
    "wof:name":"Pro Forma Cfo Services",
    "wof:placetype":"venue"
},
  "geometry": {"coordinates":[-93.41116599999999,44.927377],"type":"Point"}
}