{
  "type": "Feature",
  "properties": {
    "iso:country":"US",
    "sg:address":"1600 5th Ave W",
    "sg:city":"Hibbing",
    "sg:classifiers":[
        {
            "category":"Professional",
            "subcategory":"Testing Lab",
            "type":"Services"
        }
    ],
    "sg:phone":"+1 218 262 3456",
    "sg:postcode":"55746",
    "sg:province":"MN",
    "sg:tags":[
        "chemist"
    ],
    "wof:name":"Lerch Brothers Inc",
    "wof:placetype":"venue"
},
  "geometry": {"coordinates":[-92.947289,47.42878],"type":"Point"}
}