{
  "type": "Feature",
  "properties": {
    "iso:country":"US",
    "sg:address":"11779 565th Ave",
    "sg:city":"Wells",
    "sg:classifiers":[
        {
            "category":"Real Estate",
            "subcategory":"Real Estate Operator",
            "type":"Services"
        }
    ],
    "sg:phone":"+1 507 553 6107",
    "sg:postcode":"56097",
    "sg:province":"MN",
    "sg:tags":[
        "property",
        "lessor"
    ],
    "wof:name":"Huston John",
    "wof:placetype":"venue"
},
  "geometry": {"coordinates":[-93.743264,43.666106],"type":"Point"}
}