{
  "type": "Feature",
  "properties": {
    "addr:full":"2019 Knollwood Dr Grand Rapids MN 55744",
    "addr:housenumber":"2019",
    "addr:postcode":"55744",
    "addr:street":"Knollwood Dr",
    "iso:country":"US",
    "sg:address":"2019 Knollwood Dr",
    "sg:city":"Grand Rapids",
    "sg:classifiers":[
        {
            "category":"Building & Trades",
            "subcategory":"Construction",
            "type":"Services"
        }
    ],
    "sg:phone":"+1 218 244 4309",
    "sg:postcode":"55744",
    "sg:province":"MN",
    "sg:tags":[
        "contractor"
    ],
    "wof:name":"Creative Concepts Construction",
    "wof:placetype":"venue"
},
  "geometry": {"coordinates":[-93.540527,47.257474],"type":"Point"}
}