{
  "type": "Feature",
  "properties": {
    "iso:country":"US",
    "sg:address":"4738 Bald Eagle Ave",
    "sg:city":"White Bear Lake",
    "sg:classifiers":[
        {
            "category":"Retail",
            "subcategory":"Funeral Services",
            "type":"Services"
        }
    ],
    "sg:phone":"+1 952 888 3144",
    "sg:postcode":"55110",
    "sg:province":"MN",
    "sg:tags":[
        "crematory"
    ],
    "sg:website":"www.nationalcremation.com",
    "wof:name":"National Cremation Svc",
    "wof:placetype":"venue"
},
  "geometry": {"coordinates":[-93.015412,45.08537],"type":"Point"}
}