{
  "type": "Feature",
  "properties": {
    "addr:full":"60 Carriage Ln Burnsville MN 55306",
    "addr:housenumber":"60",
    "addr:postcode":"55306",
    "addr:street":"Carriage Ln",
    "iso:country":"US",
    "sg:address":"60 Carriage Ln",
    "sg:city":"Burnsville",
    "sg:classifiers":[
        {
            "category":"Professional",
            "subcategory":"Business Services",
            "type":"Services"
        }
    ],
    "sg:phone":"+1 952 898 6565",
    "sg:postcode":"55306",
    "sg:province":"MN",
    "wof:name":"Arizona Events",
    "wof:placetype":"venue"
},
  "geometry": {"coordinates":[-93.27394,44.734652],"type":"Point"}
}