{
  "type": "Feature",
  "properties": {
    "addr:full":"20997 Co Hwy 23 Winona MN 55987",
    "addr:housenumber":"20997",
    "addr:postcode":"55987",
    "addr:street":"Co Hwy 23",
    "iso:country":"US",
    "sg:address":"20997 Co Hwy 23",
    "sg:city":"Winona",
    "sg:classifiers":[
        {
            "category":"Farming",
            "subcategory":"Livestock Farm",
            "type":"Manufacturing & Wholesale Goods"
        }
    ],
    "sg:phone":"+1 507 689 2388",
    "sg:postcode":"55987",
    "sg:province":"MN",
    "sg:tags":[
        "beef",
        "feedlot",
        "cattle"
    ],
    "wof:name":"Al Butenhoff",
    "wof:placetype":"venue"
},
  "geometry": {"coordinates":[-91.765023,44.020832],"type":"Point"}
}