{
  "type": "Feature",
  "properties": {
    "addr:full":"3224 Salem Point Dr SW Rochester MN 55902",
    "addr:housenumber":"3224",
    "addr:postcode":"55902",
    "addr:street":"Salem Point Dr Sw",
    "iso:country":"US",
    "sg:address":"3224 Salem Point Dr SW",
    "sg:city":"Rochester",
    "sg:classifiers":[
        {
            "category":"Home & Garden",
            "subcategory":"Home Furnishings",
            "type":"Retail Goods"
        },
        {
            "category":"Professional",
            "subcategory":"Business Services",
            "type":"Services"
        }
    ],
    "sg:phone":"+1 507 292 6214",
    "sg:postcode":"55902",
    "sg:province":"MN",
    "sg:tags":[
        "development",
        "planning",
        "design",
        "plan"
    ],
    "wof:name":"Grand Memory Ln Studios",
    "wof:placetype":"venue"
},
  "geometry": {"coordinates":[-92.51328599999999,44.003541],"type":"Point"}
}