{
  "type": "Feature",
  "properties": {
    "addr:full":"1432 98th Ln NW Minneapolis MN 55433",
    "addr:housenumber":"1432",
    "addr:postcode":"55433",
    "addr:street":"98Th Ln Nw",
    "iso:country":"US",
    "sg:address":"1432 98th Ln NW",
    "sg:city":"Minneapolis",
    "sg:classifiers":[
        {
            "category":"Professional",
            "type":"Services"
        }
    ],
    "sg:phone":"+1 763 757 0239",
    "sg:postcode":"55433",
    "sg:province":"MN",
    "wof:name":"Shiltz Rollie",
    "wof:placetype":"venue"
},
  "geometry": {"coordinates":[-93.30455000000001,45.149074],"type":"Point"}
}