{
  "type": "Feature",
  "properties": {
    "addr:full":"2036 220th St Truman MN 56088",
    "addr:housenumber":"2036",
    "addr:postcode":"56088",
    "addr:street":"220Th St",
    "iso:country":"US",
    "sg:address":"2036 220th St",
    "sg:city":"Truman",
    "sg:classifiers":[
        {
            "category":"Farming",
            "subcategory":"Livestock Farm",
            "type":"Manufacturing & Wholesale Goods"
        }
    ],
    "sg:phone":"+1 507 776 7029",
    "sg:postcode":"56088",
    "sg:province":"MN",
    "sg:tags":[
        "hog",
        "or",
        "feedlot"
    ],
    "wof:name":"Dale Simpson",
    "wof:placetype":"venue"
},
  "geometry": {"coordinates":[-94.454657,43.80378],"type":"Point"}
}