{
  "type": "Feature",
  "properties": {
    "iso:country":"US",
    "sg:address":"16731 Iodine St NW",
    "sg:city":"Anoka",
    "sg:classifiers":[
        {
            "category":"Professional",
            "subcategory":"Management & Consulting",
            "type":"Services"
        }
    ],
    "sg:phone":"+1 763 753 6283",
    "sg:postcode":"55303",
    "sg:province":"MN",
    "sg:tags":[
        "environmental",
        "consultant"
    ],
    "wof:name":"Miller & Associates Inc",
    "wof:placetype":"venue"
},
  "geometry": {"coordinates":[-93.411669,45.274861],"type":"Point"}
}