{
  "type": "Feature",
  "properties": {
    "addr:full":"3111 Abert Ave NE Buffalo MN 55313",
    "addr:housenumber":"3111",
    "addr:postcode":"55313",
    "addr:street":"Abert Ave Ne",
    "iso:country":"US",
    "sg:address":"3111 Abert Ave NE",
    "sg:city":"Buffalo",
    "sg:classifiers":[
        {
            "category":"Building & Trades",
            "subcategory":"Landscaping Services",
            "type":"Services"
        }
    ],
    "sg:phone":"+1 763 682 3308",
    "sg:postcode":"55313",
    "sg:province":"MN",
    "sg:tags":[
        "lawn",
        "maintenance",
        "grounds"
    ],
    "wof:name":"Proview Lawn & Snow",
    "wof:placetype":"venue"
},
  "geometry": {"coordinates":[-93.886239,45.196822],"type":"Point"}
}