{
  "type": "Feature",
  "properties": {
    "iso:country":"US",
    "sg:address":"420 8th St S",
    "sg:city":"Moorhead",
    "sg:classifiers":[
        {
            "category":"Restaurant",
            "type":"Food & Drink"
        }
    ],
    "sg:phone":"+1 218 284 1237",
    "sg:postcode":"56560",
    "sg:province":"MN",
    "sg:tags":[
        "eating"
    ],
    "wof:name":"Selah House Of Coffee",
    "wof:placetype":"venue"
},
  "geometry": {"coordinates":[-96.767899,46.86957],"type":"Point"}
}