{
  "type": "Feature",
  "properties": {
    "addr:full":"2301 E Main St Albert Lea MN 56007",
    "addr:housenumber":"2301",
    "addr:postcode":"56007",
    "addr:street":"E Main St",
    "iso:country":"US",
    "sg:address":"2301 E Main St",
    "sg:city":"Albert Lea",
    "sg:classifiers":[
        {
            "category":"Bars & Pubs",
            "type":"Food & Drink"
        }
    ],
    "sg:phone":"+1 507 377 1165",
    "sg:postcode":"56007",
    "sg:province":"MN",
    "sg:tags":[
        "drinking",
        "eating"
    ],
    "wof:name":"Andys Road House Bar & Grill",
    "wof:placetype":"venue"
},
  "geometry": {"coordinates":[-93.33366599999999,43.658522],"type":"Point"}
}