{
  "type": "Feature",
  "properties": {
    "addr:full":"810 Center Ave W Dilworth MN 56529",
    "addr:housenumber":"810",
    "addr:postcode":"56529",
    "addr:street":"Center Ave W",
    "iso:country":"US",
    "sg:address":"810 Center Ave W",
    "sg:city":"Dilworth",
    "sg:classifiers":[
        {
            "category":"Social Services",
            "type":"Services"
        }
    ],
    "sg:phone":"+1 218 287 3594",
    "sg:postcode":"56529",
    "sg:province":"MN",
    "sg:tags":[
        "human"
    ],
    "wof:name":"Disability Resource Inc",
    "wof:placetype":"venue"
},
  "geometry": {"coordinates":[-96.715923,46.87645],"type":"Point"}
}