{
  "type": "Feature",
  "properties": {
    "addr:full":"5304 Twig Blvd Saginaw MN 55779",
    "addr:housenumber":"5304",
    "addr:postcode":"55779",
    "addr:street":"Twig Blvd",
    "iso:country":"US",
    "sg:address":"5304 Twig Blvd",
    "sg:city":"Saginaw",
    "sg:classifiers":[
        {
            "category":"Shopping",
            "subcategory":"Used Merchandise",
            "type":"Retail Goods"
        }
    ],
    "sg:phone":"+1 218 729 5956",
    "sg:postcode":"55779",
    "sg:province":"MN",
    "sg:tags":[
        "antique"
    ],
    "wof:name":"D B Enterprises Antiques",
    "wof:placetype":"venue"
},
  "geometry": {"coordinates":[-92.364604,46.895285],"type":"Point"}
}