{
  "type": "Feature",
  "properties": {
    "addr:full":"9705 63rd Ave N Osseo MN 55369",
    "addr:housenumber":"9705",
    "addr:postcode":"55369",
    "addr:street":"63Rd Ave N",
    "iso:country":"US",
    "sg:address":"9705 63rd Ave N",
    "sg:city":"Osseo",
    "sg:classifiers":[
        {
            "category":"Building & Trades",
            "subcategory":"Construction",
            "type":"Services"
        }
    ],
    "sg:phone":"+1 763 531 0714",
    "sg:postcode":"55369",
    "sg:province":"MN",
    "sg:tags":[
        "general",
        "dwelling",
        "family",
        "contractor"
    ],
    "wof:name":"Sunset Homes Corporation",
    "wof:placetype":"venue"
},
  "geometry": {"coordinates":[-93.402463,45.069265],"type":"Point"}
}