{
  "type": "Feature",
  "properties": {
    "iso:country":"US",
    "sg:address":"5111 Russell Ave N",
    "sg:city":"Minneapolis",
    "sg:classifiers":[
        {
            "category":"Real Estate",
            "subcategory":"Real Estate Agent",
            "type":"Services"
        }
    ],
    "sg:phone":"+1 612 521 9864",
    "sg:postcode":"55430",
    "sg:province":"MN",
    "sg:tags":[
        "appraiser"
    ],
    "wof:name":"Moses Appraisal Svc",
    "wof:placetype":"venue"
},
  "geometry": {"coordinates":[-93.311954,45.049228],"type":"Point"}
}