{
  "type": "Feature",
  "properties": {
    "iso:country":"US",
    "sg:address":"10606 King Rd",
    "sg:city":"Orr",
    "sg:classifiers":[
        {
            "category":"Professional",
            "subcategory":"Detective & Security Services",
            "type":"Services"
        }
    ],
    "sg:phone":"+1 218 757 0191",
    "sg:postcode":"55771",
    "sg:province":"MN",
    "sg:tags":[
        "information",
        "bureau"
    ],
    "wof:name":"Gabrielson Heating & Svc Inc",
    "wof:placetype":"venue"
},
  "geometry": {"coordinates":[-92.821882,48.065592],"type":"Point"}
}