{
  "type": "Feature",
  "properties": {
    "addr:full":"3093 W Owasso Blvd Saint Paul MN 55113",
    "addr:housenumber":"3093",
    "addr:postcode":"55113",
    "addr:street":"W Owasso Blvd",
    "iso:country":"US",
    "sg:address":"3093 W Owasso Blvd",
    "sg:city":"Saint Paul",
    "sg:classifiers":[
        {
            "category":"Building & Trades",
            "subcategory":"Construction",
            "type":"Services"
        }
    ],
    "sg:phone":"+1 651 766 5717",
    "sg:postcode":"55113",
    "sg:province":"MN",
    "sg:tags":[
        "hanging",
        "contractor"
    ],
    "wof:name":"Jeffrey Decorating",
    "wof:placetype":"venue"
},
  "geometry": {"coordinates":[-93.13136,45.032437],"type":"Point"}
}