{
  "type": "Feature",
  "properties": {
    "iso:country":"US",
    "sg:address":"19867 Twin Lakes Rd",
    "sg:city":"Little Falls",
    "sg:classifiers":[
        {
            "category":"Shopping",
            "subcategory":"Used Merchandise",
            "type":"Retail Goods"
        }
    ],
    "sg:phone":"+1 320 632 5088",
    "sg:postcode":"56345",
    "sg:province":"MN",
    "wof:name":"Schmidt Electric Company",
    "wof:placetype":"venue"
},
  "geometry": {"coordinates":[-94.473,46.043539],"type":"Point"}
}