{
  "type": "Feature",
  "properties": {
    "iso:country":"US",
    "sg:address":"1114 N Park St",
    "sg:city":"Fairmont",
    "sg:classifiers":[
        {
            "category":"Freight",
            "type":"Transportation"
        }
    ],
    "sg:phone":"+1 507 235 5277",
    "sg:postcode":"56031",
    "sg:province":"MN",
    "sg:tags":[
        "operator",
        "trucking"
    ],
    "wof:name":"Bradley D Hall",
    "wof:placetype":"venue"
},
  "geometry": {"coordinates":[-94.460904,43.664037],"type":"Point"}
}