{
  "type": "Feature",
  "properties": {
    "iso:country":"US",
    "sg:address":"3162 Deegan Dr SE",
    "sg:city":"Buffalo",
    "sg:classifiers":[
        {
            "category":"Building & Trades",
            "subcategory":"Construction",
            "type":"Services"
        }
    ],
    "sg:phone":"+1 763 682 4678",
    "sg:postcode":"55313",
    "sg:province":"MN",
    "sg:tags":[
        "general",
        "contractor"
    ],
    "wof:name":"Ernst General Construction Inc",
    "wof:placetype":"venue"
},
  "geometry": {"coordinates":[-93.814837,45.13303],"type":"Point"}
}