{
  "type": "Feature",
  "properties": {
    "addr:full":"259 Kragness Ave Worthington MN 56187",
    "addr:housenumber":"259",
    "addr:postcode":"56187",
    "addr:street":"Kragness Ave",
    "iso:country":"US",
    "sg:address":"259 Kragness Ave",
    "sg:city":"Worthington",
    "sg:classifiers":[
        {
            "category":"Shopping",
            "subcategory":"Used Merchandise",
            "type":"Retail Goods"
        }
    ],
    "sg:phone":"+1 507 372 5678",
    "sg:postcode":"56187",
    "sg:province":"MN",
    "sg:tags":[
        "antique"
    ],
    "wof:name":"Martin's Antiques",
    "wof:placetype":"venue"
},
  "geometry": {"coordinates":[-95.58043499999999,43.620526],"type":"Point"}
}