{
  "type": "Feature",
  "properties": {
    "addr:full":"302 Elton Hills Dr NW Rochester MN 55901",
    "addr:housenumber":"302",
    "addr:postcode":"55901",
    "addr:street":"Elton Hills Dr Nw",
    "iso:country":"US",
    "sg:address":"302 Elton Hills Dr NW",
    "sg:city":"Rochester",
    "sg:classifiers":[
        {
            "category":"Professional",
            "subcategory":"Lawyer & Legal Services",
            "type":"Services"
        }
    ],
    "sg:phone":"+1 507 281 3949",
    "sg:postcode":"55901",
    "sg:province":"MN",
    "sg:tags":[
        "attorney"
    ],
    "wof:name":"Vanderheyden & Ruffalo",
    "wof:placetype":"venue"
},
  "geometry": {"coordinates":[-92.467973,44.044669],"type":"Point"}
}