{
  "type": "Feature",
  "properties": {
    "addr:full":"699 Snelling Ave St Paul MN 55104",
    "addr:housenumber":"699",
    "addr:postcode":"55104",
    "addr:street":"Snelling Ave",
    "iso:country":"US",
    "sg:address":"699 Snelling Ave",
    "sg:city":"St Paul",
    "sg:classifiers":[
        {
            "category":"Retail",
            "subcategory":"Auto Repair",
            "type":"Services"
        }
    ],
    "sg:phone":"+1 651 647 0190",
    "sg:postcode":"55104",
    "sg:province":"MN",
    "sg:tags":[
        "automobile",
        "oil",
        "change",
        "lubrication"
    ],
    "wof:name":"Valvoline Instant Oil Change",
    "wof:placetype":"venue"
},
  "geometry": {"coordinates":[-93.167126,44.962506],"type":"Point"}
}