{
  "type": "Feature",
  "properties": {
    "iso:country":"US",
    "sg:address":"7740 48th Ave N",
    "sg:city":"Minneapolis",
    "sg:classifiers":[
        {
            "category":"Social Services",
            "subcategory":"Child Care",
            "type":"Services"
        }
    ],
    "sg:phone":"+1 763 535 6549",
    "sg:postcode":"55428",
    "sg:province":"MN",
    "sg:tags":[
        "daycare",
        "provider"
    ],
    "wof:name":"Hansen Marlys",
    "wof:placetype":"venue"
},
  "geometry": {"coordinates":[-93.38010300000001,45.042383],"type":"Point"}
}