{
  "type": "Feature",
  "properties": {
    "addr:full":"3672 180th St E Prior Lake MN 55372",
    "addr:housenumber":"3672",
    "addr:postcode":"55372",
    "addr:street":"180Th St E",
    "iso:country":"US",
    "sg:address":"3672 180th St E",
    "sg:city":"Prior Lake",
    "sg:classifiers":[
        {
            "category":"Building & Trades",
            "subcategory":"Construction",
            "type":"Services"
        }
    ],
    "sg:phone":"+1 612 850 1868",
    "sg:postcode":"55372",
    "sg:province":"MN",
    "sg:tags":[
        "hanging",
        "painter",
        "contractor"
    ],
    "wof:name":"Home Detailers Inc",
    "wof:placetype":"venue"
},
  "geometry": {"coordinates":[-93.449606,44.688717],"type":"Point"}
}