{
  "type": "Feature",
  "properties": {
    "iso:country":"US",
    "sg:address":"401 2nd Ave S",
    "sg:city":"Minneapolis",
    "sg:classifiers":[
        {
            "category":"Professional",
            "subcategory":"Computer Services",
            "type":"Services"
        }
    ],
    "sg:phone":"+1 612 253 2010",
    "sg:postcode":"55401",
    "sg:province":"MN",
    "sg:tags":[
        "internet"
    ],
    "wof:name":"TCQ Internet",
    "wof:placetype":"venue"
},
  "geometry": {"coordinates":[-93.26782799999999,44.977711],"type":"Point"}
}