{
  "type": "Feature",
  "properties": {
    "iso:country":"US",
    "sg:address":"2050 1st St E",
    "sg:city":"Maynard",
    "sg:classifiers":[
        {
            "category":"Farming",
            "subcategory":"Dairy Farm",
            "type":"Manufacturing & Wholesale Goods"
        }
    ],
    "sg:phone":"+1 320 367 2556",
    "sg:postcode":"56260",
    "sg:province":"MN",
    "wof:name":"Koenen Dairy Farm",
    "wof:placetype":"venue"
},
  "geometry": {"coordinates":[-95.553218,45.021211],"type":"Point"}
}