{
  "type": "Feature",
  "properties": {
    "addr:full":"324 Main St S Stillwater MN 55082",
    "addr:housenumber":"324",
    "addr:postcode":"55082",
    "addr:street":"Main St S",
    "iso:country":"US",
    "sg:address":"324 Main St S",
    "sg:city":"Stillwater",
    "sg:classifiers":[
        {
            "category":"Retail",
            "subcategory":"Auto Repair",
            "type":"Services"
        }
    ],
    "sg:phone":"+1 651 275 8988",
    "sg:postcode":"55082",
    "sg:province":"MN",
    "sg:tags":[
        "repairing",
        "automobile"
    ],
    "wof:name":"Grand Garage Of Stillwater",
    "wof:placetype":"venue"
},
  "geometry": {"coordinates":[-92.805403,45.05466],"type":"Point"}
}