{
  "type": "Feature",
  "properties": {
    "iso:country":"US",
    "sg:address":"20550 Hackamore Rd",
    "sg:city":"Hamel",
    "sg:classifiers":[
        {
            "category":"Building & Trades",
            "subcategory":"Construction",
            "type":"Services"
        }
    ],
    "sg:phone":"+1 763 478 2076",
    "sg:postcode":"55340",
    "sg:province":"MN",
    "sg:tags":[
        "insulation",
        "contractor"
    ],
    "wof:name":"Ambient Control Corp",
    "wof:placetype":"venue"
},
  "geometry": {"coordinates":[-93.558288,45.065783],"type":"Point"}
}