{
  "type": "Feature",
  "properties": {
    "addr:full":"220 E Maple Ave Mora MN 55051",
    "addr:housenumber":"220",
    "addr:postcode":"55051",
    "addr:street":"E Maple Ave",
    "iso:country":"US",
    "sg:address":"220 E Maple Ave",
    "sg:city":"Mora",
    "sg:classifiers":[
        {
            "category":"Recreation",
            "type":"Entertainment"
        }
    ],
    "sg:phone":"+1 320 679 3492",
    "sg:postcode":"55051",
    "sg:province":"MN",
    "wof:name":"Mora Town House",
    "wof:placetype":"venue"
},
  "geometry": {"coordinates":[-93.29538100000001,45.87789],"type":"Point"}
}