{
  "type": "Feature",
  "properties": {
    "addr:full":"8670 160th St E Hastings MN 55033",
    "addr:housenumber":"8670",
    "addr:postcode":"55033",
    "addr:street":"160Th St E",
    "iso:country":"US",
    "sg:address":"8670 160th St E",
    "sg:city":"Hastings",
    "sg:classifiers":[
        {
            "category":"Freight",
            "type":"Transportation"
        }
    ],
    "sg:phone":"+1 651 437 3551",
    "sg:postcode":"55033",
    "sg:province":"MN",
    "sg:tags":[
        "operator",
        "mover",
        "local",
        "trucking"
    ],
    "wof:name":"Robinson Transfer Inc Furn",
    "wof:placetype":"venue"
},
  "geometry": {"coordinates":[-92.916624,44.716877],"type":"Point"}
}