{
  "type": "Feature",
  "properties": {
    "iso:country":"US",
    "sg:address":"8450 80th Ave SW",
    "sg:city":"Stewartville",
    "sg:phone":"+1 507 365 8267",
    "sg:postcode":"55976",
    "sg:province":"MN",
    "sg:tags":[
        "farm",
        "corn",
        "soybean"
    ],
    "wof:name":"Mark Golberg",
    "wof:placetype":"venue"
},
  "geometry": {"coordinates":[-92.598236,43.891982],"type":"Point"}
}