{
  "type": "Feature",
  "properties": {
    "addr:full":"7401 42nd Ave N Ste 201 Minneapolis MN 55427",
    "addr:housenumber":"7401",
    "addr:postcode":"55427",
    "addr:street":"42Nd Ave N Ste 201",
    "iso:country":"US",
    "sg:address":"7401 42nd Ave N Ste 201",
    "sg:city":"Minneapolis",
    "sg:classifiers":[
        {
            "category":"Health Services",
            "subcategory":"Medical Lab",
            "type":"Services"
        }
    ],
    "sg:phone":"+1 612 522 4323",
    "sg:postcode":"55427",
    "sg:province":"MN",
    "sg:tags":[
        "laboratory",
        "dental"
    ],
    "wof:name":"Crest Dental Laboratory, Inc",
    "wof:placetype":"venue"
},
  "geometry": {"coordinates":[-93.37415300000001,45.032822],"type":"Point"}
}