{
  "type": "Feature",
  "properties": {
    "addr:full":"1250 State Hwy 284 Waconia MN 55387",
    "addr:housenumber":"1250",
    "addr:postcode":"55387",
    "addr:street":"State Hwy 284 Waconia",
    "iso:country":"US",
    "sg:address":"1250 State Hwy 284",
    "sg:city":"Waconia",
    "sg:classifiers":[
        {
            "category":"Building & Trades",
            "subcategory":"Construction",
            "type":"Services"
        }
    ],
    "sg:phone":"+1 952 442 2615",
    "sg:postcode":"55387",
    "sg:province":"MN",
    "sg:tags":[
        "marking",
        "maintenance",
        "parking"
    ],
    "wof:name":"Waconia Public Works",
    "wof:placetype":"venue"
},
  "geometry": {"coordinates":[-93.788415,44.840052],"type":"Point"}
}