{
  "type": "Feature",
  "properties": {
    "iso:country":"US",
    "sg:address":"317 N Cascade St",
    "sg:city":"Fergus Falls",
    "sg:classifiers":[
        {
            "category":"Manufacturing",
            "subcategory":"Signs",
            "type":"Manufacturing & Wholesale Goods"
        }
    ],
    "sg:phone":"+1 218 739 3529",
    "sg:postcode":"56537",
    "sg:province":"MN",
    "sg:tags":[
        "commercial",
        "specialty",
        "mfg"
    ],
    "wof:name":"Sign & Design",
    "wof:placetype":"venue"
},
  "geometry": {"coordinates":[-96.072941,46.286473],"type":"Point"}
}