{
  "type": "Feature",
  "properties": {
    "addr:full":"3201 Co Rd 92 Maple Plain MN 55359",
    "addr:housenumber":"3201;92",
    "addr:postcode":"55359",
    "addr:street":"Co Rd;Plain",
    "iso:country":"US",
    "sg:address":"3201 Co Rd 92",
    "sg:city":"Maple Plain",
    "sg:classifiers":[
        {
            "category":"Professional",
            "subcategory":"Computer Services",
            "type":"Services"
        }
    ],
    "sg:phone":"+1 763 479 6870",
    "sg:postcode":"55359",
    "sg:province":"MN",
    "sg:tags":[
        "application",
        "provider"
    ],
    "wof:name":"Webstack Corp",
    "wof:placetype":"venue"
},
  "geometry": {"coordinates":[-93.715332,45.031886],"type":"Point"}
}