{
  "type": "Feature",
  "properties": {
    "addr:full":"9025 Idaho Ave N Brooklyn Park MN 55445",
    "addr:housenumber":"9025",
    "addr:postcode":"55445",
    "addr:street":"Idaho Ave N",
    "iso:country":"US",
    "sg:address":"9025 Idaho Ave N",
    "sg:city":"Brooklyn Park",
    "sg:classifiers":[
        {
            "category":"Education",
            "subcategory":"School",
            "type":"Public Place"
        }
    ],
    "sg:phone":"+1 763 425 0865",
    "sg:postcode":"55445",
    "sg:province":"MN",
    "wof:name":"Serving & Learning Together",
    "wof:placetype":"venue"
},
  "geometry": {"coordinates":[-93.36726299999999,45.117803],"type":"Point"}
}