{
  "type": "Feature",
  "properties": {
    "iso:country":"US",
    "sg:address":"130 Forest Ave W",
    "sg:city":"Mora",
    "sg:classifiers":[
        {
            "category":"Personal",
            "subcategory":"Beauty Salon",
            "type":"Services"
        }
    ],
    "sg:phone":"+1 320 679 4433",
    "sg:postcode":"55051",
    "sg:province":"MN",
    "wof:name":"Alternative Hair",
    "wof:placetype":"venue"
},
  "geometry": {"coordinates":[-93.298202,45.875598],"type":"Point"}
}