{
  "type": "Feature",
  "properties": {
    "addr:full":"404 Main St NW Elk River MN 55330",
    "addr:housenumber":"404",
    "addr:postcode":"55330",
    "addr:street":"Main St Nw",
    "iso:country":"US",
    "sg:address":"404 Main St NW",
    "sg:city":"Elk River",
    "sg:classifiers":[
        {
            "category":"Banks & Credit Unions",
            "subcategory":"Bank",
            "type":"Services"
        }
    ],
    "sg:phone":"+1 763 441 9077",
    "sg:postcode":"55330",
    "sg:province":"MN",
    "sg:tags":[
        "broker",
        "mortgage"
    ],
    "wof:name":"Rossman Financial Inc",
    "wof:placetype":"venue"
},
  "geometry": {"coordinates":[-93.552516,45.312712],"type":"Point"}
}