{
  "type": "Feature",
  "properties": {
    "iso:country":"US",
    "sg:address":"3842 Dupont Ave N",
    "sg:city":"Minneapolis",
    "sg:classifiers":[
        {
            "category":"Health Services",
            "subcategory":"Nursing And Care Facility",
            "type":"Services"
        },
        {
            "category":"Freight",
            "type":"Transportation"
        }
    ],
    "sg:phone":"+1 612 522 6662",
    "sg:postcode":"55412",
    "sg:province":"MN",
    "sg:tags":[
        "home",
        "convalescent",
        "arrangement"
    ],
    "wof:name":"We Care Health Care Services",
    "wof:placetype":"venue"
},
  "geometry": {"coordinates":[-93.29303,45.025006],"type":"Point"}
}