{
  "type": "Feature",
  "properties": {
    "addr:full":"6904 Ives Ln N Osseo MN 55369",
    "addr:housenumber":"6904",
    "addr:postcode":"55369",
    "addr:street":"Ives Ln N",
    "iso:country":"US",
    "sg:address":"6904 Ives Ln N",
    "sg:city":"Osseo",
    "sg:classifiers":[
        {
            "category":"Real Estate",
            "subcategory":"Real Estate Agent",
            "type":"Services"
        }
    ],
    "sg:phone":"+1 763 544 3127",
    "sg:postcode":"55369",
    "sg:province":"MN",
    "wof:name":"Carey Development Co",
    "wof:placetype":"venue"
},
  "geometry": {"coordinates":[-93.432068,45.081478],"type":"Point"}
}