{
  "type": "Feature",
  "properties": {
    "addr:full":"9733 Quincy St NE Minneapolis MN 55434",
    "addr:housenumber":"9733",
    "addr:postcode":"55434",
    "addr:street":"Quincy St Ne",
    "iso:country":"US",
    "sg:address":"9733 Quincy St NE",
    "sg:city":"Minneapolis",
    "sg:classifiers":[
        {
            "category":"Building & Trades",
            "subcategory":"Construction",
            "type":"Services"
        }
    ],
    "sg:phone":"+1 763 786 0792",
    "sg:postcode":"55434",
    "sg:province":"MN",
    "sg:tags":[
        "floor",
        "laying",
        "contractor"
    ],
    "wof:name":"Wayne A Urista",
    "wof:placetype":"venue"
},
  "geometry": {"coordinates":[-93.251406,45.147047],"type":"Point"}
}