{
  "type": "Feature",
  "properties": {
    "addr:full":"53815 Balsam Ave W Braham MN 55006",
    "addr:housenumber":"53815",
    "addr:postcode":"55006",
    "addr:street":"Balsam Ave W Braham",
    "iso:country":"US",
    "sg:address":"53815 Balsam Ave W",
    "sg:city":"Braham",
    "sg:classifiers":[
        {
            "category":"Building & Trades",
            "subcategory":"Construction",
            "type":"Services"
        }
    ],
    "sg:phone":"+1 320 396 2555",
    "sg:postcode":"55006",
    "sg:province":"MN",
    "sg:tags":[
        "house"
    ],
    "wof:name":"Rush Area Builders",
    "wof:placetype":"venue"
},
  "geometry": {"coordinates":[-93.12463,45.716757],"type":"Point"}
}