{
  "type": "Feature",
  "properties": {
    "iso:country":"US",
    "sg:address":"28810 US Hwy 169",
    "sg:city":"Princeton",
    "sg:classifiers":[
        {
            "category":"Building & Trades",
            "subcategory":"Construction",
            "type":"Services"
        }
    ],
    "sg:phone":"+1 612 801 3570",
    "sg:postcode":"55371",
    "sg:province":"MN",
    "sg:tags":[
        "roofing",
        "contractor"
    ],
    "wof:name":"Slt Roofing",
    "wof:placetype":"venue"
},
  "geometry": {"coordinates":[-93.58151599999999,45.488292],"type":"Point"}
}