{
  "type": "Feature",
  "properties": {
    "addr:full":"15 Hansen Hjemsted Lutsen MN 55612",
    "addr:housenumber":"15",
    "addr:postcode":"55612",
    "addr:street":"Hansen Hjemsted",
    "iso:country":"US",
    "sg:address":"15 Hansen Hjemsted",
    "sg:city":"Lutsen",
    "sg:classifiers":[
        {
            "category":"Professional",
            "subcategory":"Management & Consulting",
            "type":"Services"
        }
    ],
    "sg:phone":"+1 218 663 7363",
    "sg:postcode":"55612",
    "sg:province":"MN",
    "sg:tags":[
        "school"
    ],
    "wof:name":"Great Expectations School",
    "wof:placetype":"venue"
},
  "geometry": {"coordinates":[-90.63866400000001,47.666277],"type":"Point"}
}