{
  "type": "Feature",
  "properties": {
    "addr:full":"2828 Sun Ter St Paul MN 55110",
    "addr:housenumber":"2828",
    "addr:postcode":"55110",
    "addr:street":"Sun Ter",
    "iso:country":"US",
    "sg:address":"2828 Sun Ter",
    "sg:city":"St Paul",
    "sg:classifiers":[
        {
            "category":"Professional",
            "subcategory":"Engineering",
            "type":"Services"
        }
    ],
    "sg:phone":"+1 651 429 9461",
    "sg:postcode":"55110",
    "sg:province":"MN",
    "sg:tags":[
        "engineer"
    ],
    "wof:name":"J T Consulting",
    "wof:placetype":"venue"
},
  "geometry": {"coordinates":[-92.98269999999999,45.054804],"type":"Point"}
}