{
  "type": "Feature",
  "properties": {
    "addr:full":"6514 Maple Grove Rd Cloquet MN 55720",
    "addr:housenumber":"6514",
    "addr:postcode":"55720",
    "addr:street":"Maple Grove Rd",
    "iso:country":"US",
    "sg:address":"6514 Maple Grove Rd",
    "sg:city":"Cloquet",
    "sg:classifiers":[
        {
            "category":"Freight",
            "type":"Transportation"
        }
    ],
    "sg:phone":"+1 218 729 8778",
    "sg:postcode":"55720",
    "sg:province":"MN",
    "sg:tags":[
        "gravel",
        "hauling"
    ],
    "wof:name":"Steve Baublitz Trucking",
    "wof:placetype":"venue"
},
  "geometry": {"coordinates":[-92.37299299999999,46.808159],"type":"Point"}
}