{
  "type": "Feature",
  "properties": {
    "iso:country":"US",
    "sg:address":"9008 Vickors Xing",
    "sg:city":"Minneapolis",
    "sg:classifiers":[
        {
            "category":"Banks & Credit Unions",
            "subcategory":"Investment Brokerage",
            "type":"Services"
        }
    ],
    "sg:phone":"+1 763 391 6460",
    "sg:postcode":"55443",
    "sg:province":"MN",
    "sg:tags":[
        "advisory",
        "financial"
    ],
    "wof:name":"Fiscal Fitness Inc",
    "wof:placetype":"venue"
},
  "geometry": {"coordinates":[-93.31755800000001,45.117487],"type":"Point"}
}