{
  "type": "Feature",
  "properties": {
    "addr:full":"310 4th Ave S Minneapolis MN 55415",
    "addr:housenumber":"310",
    "addr:postcode":"55415",
    "addr:street":"4Th Ave S",
    "iso:country":"US",
    "sg:address":"310 4th Ave S",
    "sg:city":"Minneapolis",
    "sg:classifiers":[
        {
            "category":"Professional",
            "subcategory":"Lawyer & Legal Services",
            "type":"Services"
        }
    ],
    "sg:phone":"+1 612 338 3400",
    "sg:postcode":"55415",
    "sg:province":"MN",
    "sg:tags":[
        "information",
        "attorney",
        "injury",
        "personal",
        "referral"
    ],
    "wof:name":"Dunlap & Ritts",
    "wof:placetype":"venue"
},
  "geometry": {"coordinates":[-93.263603,44.978298],"type":"Point"}
}