{
  "type": "Feature",
  "properties": {
    "addr:full":"535 E Hwy 2 Grand Rapids MN 55744",
    "addr:housenumber":"535",
    "addr:postcode":"55744",
    "addr:street":"E Hwy 2",
    "iso:country":"US",
    "sg:address":"535 E Hwy 2",
    "sg:city":"Grand Rapids",
    "sg:classifiers":[
        {
            "category":"Banks & Credit Unions",
            "subcategory":"Bank",
            "type":"Services"
        }
    ],
    "sg:phone":"+1 218 326 5989",
    "sg:postcode":"55744",
    "sg:province":"MN",
    "wof:name":"Affinity Plus Fed Credit Union",
    "wof:placetype":"venue"
},
  "geometry": {"coordinates":[-93.52011400000001,47.235975],"type":"Point"}
}