{
  "type": "Feature",
  "properties": {
    "iso:country":"US",
    "sg:address":"500 Clark St",
    "sg:city":"Mora",
    "sg:classifiers":[
        {
            "category":"Organizations",
            "subcategory":"Religious Organization",
            "type":"Services"
        }
    ],
    "sg:phone":"+1 320 679 2713",
    "sg:postcode":"55051",
    "sg:province":"MN",
    "wof:name":"Mora United Methodist Church",
    "wof:placetype":"venue"
},
  "geometry": {"coordinates":[-93.29200899999999,45.872226],"type":"Point"}
}