{
  "type": "Feature",
  "properties": {
    "iso:country":"US",
    "sg:address":"5775 Wayzata Blvd Ste 995",
    "sg:city":"Minneapolis",
    "sg:classifiers":[
        {
            "category":"Professional",
            "subcategory":"Employment Agencies",
            "type":"Services"
        }
    ],
    "sg:phone":"+1 952 542 1958",
    "sg:postcode":"55416",
    "sg:province":"MN",
    "sg:website":"www.mastersonpersonnel.com",
    "wof:name":"Masterson Personnel Inc",
    "wof:placetype":"venue"
},
  "geometry": {"coordinates":[-93.35368,44.969819],"type":"Point"}
}