{
  "type": "Feature",
  "properties": {
    "addr:full":"8300 Country Club Rd W Byron MN 55920",
    "addr:housenumber":"8300",
    "addr:postcode":"55920",
    "addr:street":"Country Club Rd W",
    "iso:country":"US",
    "sg:address":"8300 Country Club Rd W",
    "sg:city":"Byron",
    "sg:classifiers":[
        {
            "category":"Building & Trades",
            "subcategory":"Electrical",
            "type":"Services"
        }
    ],
    "sg:phone":"+1 507 775 2387",
    "sg:postcode":"55920",
    "sg:province":"MN",
    "sg:tags":[
        "electrical",
        "contractor"
    ],
    "wof:name":"Pearson & Stemper Electri",
    "wof:placetype":"venue"
},
  "geometry": {"coordinates":[-92.60814999999999,44.02175],"type":"Point"}
}