{
  "type": "Feature",
  "properties": {
    "addr:full":"1316 Griffing Way Buffalo MN 55313",
    "addr:housenumber":"1316",
    "addr:postcode":"55313",
    "addr:street":"Griffing Way",
    "iso:country":"US",
    "sg:address":"1316 Griffing Way",
    "sg:city":"Buffalo",
    "sg:classifiers":[
        {
            "category":"Building & Trades",
            "subcategory":"Plumbing",
            "type":"Services"
        }
    ],
    "sg:phone":"+1 763 682 9221",
    "sg:postcode":"55313",
    "sg:province":"MN",
    "sg:tags":[
        "contractor"
    ],
    "wof:name":"Jeffries Enterprises Inc",
    "wof:placetype":"venue"
},
  "geometry": {"coordinates":[-93.866838,45.189159],"type":"Point"}
}