{
  "type": "Feature",
  "properties": {
    "addr:full":"1944 Shawnee Rd St Paul MN 55122",
    "addr:housenumber":"1944",
    "addr:postcode":"55122",
    "addr:street":"Shawnee Rd",
    "iso:country":"US",
    "sg:address":"1944 Shawnee Rd",
    "sg:city":"St Paul",
    "sg:classifiers":[
        {
            "category":"Professional",
            "subcategory":"Business Services",
            "type":"Services"
        }
    ],
    "sg:phone":"+1 952 997 6965",
    "sg:postcode":"55122",
    "sg:province":"MN",
    "sg:tags":[
        "embroidery"
    ],
    "wof:name":"Images In Ink",
    "wof:placetype":"venue"
},
  "geometry": {"coordinates":[-93.20276200000001,44.826064],"type":"Point"}
}