{
  "type": "Feature",
  "properties": {
    "iso:country":"US",
    "sg:address":"426 Osceola Ave",
    "sg:city":"St Paul",
    "sg:classifiers":[
        {
            "category":"Education",
            "subcategory":"School",
            "type":"Public Place"
        }
    ],
    "sg:phone":"+1 651 228 1167",
    "sg:postcode":"55102",
    "sg:province":"MN",
    "wof:name":"St Francis-St James United",
    "wof:placetype":"venue"
},
  "geometry": {"coordinates":[-93.12812599999999,44.92838],"type":"Point"}
}