{
  "type": "Feature",
  "properties": {
    "iso:country":"US",
    "sg:address":"18846 Heather St NW",
    "sg:city":"Cedar",
    "sg:classifiers":[
        {
            "category":"Home & Garden",
            "subcategory":"Building Materials",
            "type":"Retail Goods"
        }
    ],
    "sg:phone":"+1 763 753 2984",
    "sg:postcode":"55011",
    "sg:province":"MN",
    "wof:name":"Jrs Sand & Gravel Inc",
    "wof:placetype":"venue"
},
  "geometry": {"coordinates":[-93.34295,45.312266],"type":"Point"}
}