{
  "type": "Feature",
  "properties": {
    "addr:full":"476 Hansen Rd Wrenshall MN 55797",
    "addr:housenumber":"476",
    "addr:postcode":"55797",
    "addr:street":"Hansen Rd",
    "iso:country":"US",
    "sg:address":"476 Hansen Rd",
    "sg:city":"Wrenshall",
    "sg:classifiers":[
        {
            "category":"Freight",
            "type":"Transportation"
        }
    ],
    "sg:phone":"+1 218 384 9709",
    "sg:postcode":"55797",
    "sg:province":"MN",
    "sg:tags":[
        "haul",
        "long",
        "trucking"
    ],
    "wof:name":"Fulkerson Enterprise Inc",
    "wof:placetype":"venue"
},
  "geometry": {"coordinates":[-92.34225600000001,46.562369],"type":"Point"}
}