{
  "type": "Feature",
  "properties": {
    "iso:country":"US",
    "sg:address":"7550 165th St E",
    "sg:city":"Hastings",
    "sg:classifiers":[
        {
            "category":"Building & Trades",
            "subcategory":"Construction",
            "type":"Services"
        }
    ],
    "sg:phone":"+1 651 437 0294",
    "sg:postcode":"55033",
    "sg:province":"MN",
    "sg:tags":[
        "sandblasting"
    ],
    "wof:name":"Aw Bead Blasting",
    "wof:placetype":"venue"
},
  "geometry": {"coordinates":[-92.95,44.710809],"type":"Point"}
}