{
  "type": "Feature",
  "properties": {
    "iso:country":"US",
    "sg:address":"7035 Donlea Ln",
    "sg:city":"Eden Prairie",
    "sg:classifiers":[
        {
            "category":"Professional",
            "subcategory":"Business Services",
            "type":"Services"
        }
    ],
    "sg:phone":"+1 952 941 2773",
    "sg:postcode":"55346",
    "sg:province":"MN",
    "wof:name":"Don Hedquist Associaties",
    "wof:placetype":"venue"
},
  "geometry": {"coordinates":[-93.44198,44.875115],"type":"Point"}
}