{
  "type": "Feature",
  "properties": {
    "addr:full":"104 S Van Buren Ave Eveleth MN 55734",
    "addr:housenumber":"104",
    "addr:postcode":"55734",
    "addr:street":"S Van Buren Ave",
    "iso:country":"US",
    "sg:address":"104 S Van Buren Ave",
    "sg:city":"Eveleth",
    "sg:classifiers":[
        {
            "category":"Manufacturing",
            "subcategory":"Textiles",
            "type":"Manufacturing & Wholesale Goods"
        }
    ],
    "sg:phone":"+1 218 744 2911",
    "sg:postcode":"55734",
    "sg:province":"MN",
    "sg:tags":[
        "textiles-manufacturers"
    ],
    "wof:name":"Www Teesonya Co",
    "wof:placetype":"venue"
},
  "geometry": {"coordinates":[-92.52655900000001,47.459809],"type":"Point"}
}