{
  "type": "Feature",
  "properties": {
    "iso:country":"US",
    "sg:address":"3863 10th Ave SW",
    "sg:city":"Rochester",
    "sg:classifiers":[
        {
            "category":"Building & Trades",
            "subcategory":"Construction",
            "type":"Services"
        }
    ],
    "sg:phone":"+1 507 289 7129",
    "sg:postcode":"55902",
    "sg:province":"MN",
    "wof:name":"Image Builders",
    "wof:placetype":"venue"
},
  "geometry": {"coordinates":[-92.47790000000001,43.967288],"type":"Point"}
}