{
  "type": "Feature",
  "properties": {
    "addr:full":"8550 Edinburgh Centre Dr N Brooklyn Park MN 55443",
    "addr:housenumber":"8550",
    "addr:postcode":"55443",
    "addr:street":"Edinburgh Centre Dr N",
    "iso:country":"US",
    "sg:address":"8550 Edinburgh Centre Dr N",
    "sg:city":"Brooklyn Park",
    "sg:classifiers":[
        {
            "category":"Retail",
            "subcategory":"Auto Repair",
            "type":"Services"
        }
    ],
    "sg:phone":"+1 763 493 5625",
    "sg:postcode":"55443",
    "sg:province":"MN",
    "sg:tags":[
        "automobile",
        "lubrication",
        "automotive"
    ],
    "sg:website":"www.vioc.com",
    "wof:name":"Valvoline Instant Oil Change",
    "wof:placetype":"venue"
},
  "geometry": {"coordinates":[-93.303375,45.110096],"type":"Point"}
}