{
  "type": "Feature",
  "properties": {
    "iso:country":"US",
    "sg:address":"2085 Old N Shore Rd",
    "sg:city":"Duluth",
    "sg:classifiers":[
        {
            "category":"Building & Trades",
            "subcategory":"Construction",
            "type":"Services"
        }
    ],
    "sg:phone":"+1 218 525 1074",
    "sg:postcode":"55804",
    "sg:province":"MN",
    "sg:tags":[
        "carpentry",
        "carpenter",
        "contractor"
    ],
    "wof:name":"Sjodin Chuck Carpentry",
    "wof:placetype":"venue"
},
  "geometry": {"coordinates":[-91.89388599999999,46.910229],"type":"Point"}
}