{
  "type": "Feature",
  "properties": {
    "addr:full":"32643 US Hwy 10 Motley MN 56466",
    "addr:postcode":"32643;56466",
    "addr:street":"Us Hwy 10 Motley",
    "iso:country":"US",
    "sg:address":"32643 US Hwy 10",
    "sg:city":"Motley",
    "sg:classifiers":[
        {
            "category":"Building & Trades",
            "subcategory":"Construction",
            "type":"Services"
        }
    ],
    "sg:phone":"+1 218 352 6674",
    "sg:postcode":"56466",
    "sg:province":"MN",
    "sg:tags":[
        "water",
        "repair",
        "well",
        "drilling"
    ],
    "wof:name":"Fluegge Well Drilling and Svc",
    "wof:placetype":"venue"
},
  "geometry": {"coordinates":[-94.68451899999999,46.342372],"type":"Point"}
}