{
  "type": "Feature",
  "properties": {
    "iso:country":"US",
    "sg:address":"315 N 6th St",
    "sg:city":"Brainerd",
    "sg:classifiers":[
        {
            "category":"Organizations",
            "subcategory":"Religious Organization",
            "type":"Services"
        }
    ],
    "sg:phone":"+1 218 829 4116",
    "sg:postcode":"56401",
    "sg:province":"MN",
    "wof:name":"Park United Methodist Church",
    "wof:placetype":"venue"
},
  "geometry": {"coordinates":[-94.200743,46.360029],"type":"Point"}
}