{
  "type": "Feature",
  "properties": {
    "iso:country":"US",
    "sg:address":"3021 Wisconsin Ave N",
    "sg:city":"Minneapolis",
    "sg:classifiers":[
        {
            "category":"Manufacturing",
            "subcategory":"Wood Products",
            "type":"Manufacturing & Wholesale Goods"
        },
        {
            "category":"Home & Garden",
            "subcategory":"Furniture",
            "type":"Retail Goods"
        }
    ],
    "sg:phone":"+1 763 542 0904",
    "sg:postcode":"55427",
    "sg:province":"MN",
    "sg:tags":[
        "manufacturer",
        "cabinets-wholesale",
        "cabinet"
    ],
    "wof:name":"Ken's Custom Kitchens",
    "wof:placetype":"venue"
},
  "geometry": {"coordinates":[-93.38591700000001,45.0121],"type":"Point"}
}