{
  "type": "Feature",
  "properties": {
    "iso:country":"US",
    "sg:address":"22401 190th St NE",
    "sg:city":"Paynesville",
    "sg:phone":"+1 320 276 8319",
    "sg:postcode":"56362",
    "sg:province":"MN",
    "sg:tags":[
        "farm",
        "corn",
        "dairy"
    ],
    "wof:name":"Larry Herem",
    "wof:placetype":"venue"
},
  "geometry": {"coordinates":[-94.783703,45.336817],"type":"Point"}
}