{
  "type": "Feature",
  "properties": {
    "iso:country":"US",
    "sg:address":"183 Mitzner Rd",
    "sg:city":"Esko",
    "sg:classifiers":[
        {
            "category":"Freight",
            "type":"Transportation"
        }
    ],
    "sg:phone":"+1 218 879 2225",
    "sg:postcode":"55733",
    "sg:province":"MN",
    "sg:tags":[
        "operator",
        "local",
        "trucking"
    ],
    "wof:name":"Michael R Hansen",
    "wof:placetype":"venue"
},
  "geometry": {"coordinates":[-92.3595,46.735199],"type":"Point"}
}