{
  "type": "Feature",
  "properties": {
    "addr:full":"1813 Riverside Ave Minneapolis MN 55454",
    "addr:housenumber":"1813",
    "addr:postcode":"55454",
    "addr:street":"Riverside Ave",
    "iso:country":"US",
    "sg:address":"1813 Riverside Ave",
    "sg:city":"Minneapolis",
    "sg:classifiers":[
        {
            "category":"Restaurant",
            "type":"Food & Drink"
        }
    ],
    "sg:phone":"+1 612 338 4238",
    "sg:postcode":"55454",
    "sg:province":"MN",
    "wof:name":"K Wok",
    "wof:placetype":"venue"
},
  "geometry": {"coordinates":[-93.2469,44.970066],"type":"Point"}
}