{
  "type": "Feature",
  "properties": {
    "iso:country":"US",
    "sg:address":"19400 Embers Ave",
    "sg:city":"Farmington",
    "sg:classifiers":[
        {
            "category":"Building & Trades",
            "subcategory":"Construction",
            "type":"Services"
        }
    ],
    "sg:phone":"+1 651 463 9344",
    "sg:postcode":"55024",
    "sg:province":"MN",
    "sg:tags":[
        "house"
    ],
    "wof:name":"Rudolph Construction Inc",
    "wof:placetype":"venue"
},
  "geometry": {"coordinates":[-93.163304,44.670634],"type":"Point"}
}