{
  "type": "Feature",
  "properties": {
    "addr:full":"5330 Goldenrod Ln N Minneapolis MN 55442",
    "addr:housenumber":"5330",
    "addr:postcode":"55442",
    "addr:street":"Goldenrod Ln N",
    "iso:country":"US",
    "sg:address":"5330 Goldenrod Ln N",
    "sg:city":"Minneapolis",
    "sg:classifiers":[
        {
            "category":"Insurance",
            "subcategory":"Hazard Insurance",
            "type":"Services"
        }
    ],
    "sg:phone":"+1 763 559 2323",
    "sg:postcode":"55442",
    "sg:province":"MN",
    "sg:tags":[
        "commercial",
        "business"
    ],
    "wof:name":"Theodore J Becker",
    "wof:placetype":"venue"
},
  "geometry": {"coordinates":[-93.430251,45.049506],"type":"Point"}
}