{
  "type": "Feature",
  "properties": {
    "addr:full":"703 W 5th St Winona MN 55987",
    "addr:housenumber":"703",
    "addr:postcode":"55987",
    "addr:street":"W 5Th St",
    "iso:country":"US",
    "sg:address":"703 W 5th St",
    "sg:city":"Winona",
    "sg:classifiers":[
        {
            "category":"Freight",
            "type":"Transportation"
        }
    ],
    "sg:phone":"+1 507 288 9501",
    "sg:postcode":"55987",
    "sg:province":"MN",
    "sg:tags":[
        "mover",
        "moving"
    ],
    "wof:name":"Royal Economy Moving",
    "wof:placetype":"venue"
},
  "geometry": {"coordinates":[-91.656684,44.053916],"type":"Point"}
}