{
  "type": "Feature",
  "properties": {
    "iso:country":"US",
    "sg:address":"4388 River Bend Pl",
    "sg:city":"Savage",
    "sg:classifiers":[
        {
            "category":"Professional",
            "subcategory":"Computer Services",
            "type":"Services"
        }
    ],
    "sg:phone":"+1 952 707 6744",
    "sg:postcode":"55378",
    "sg:province":"MN",
    "sg:tags":[
        "related"
    ],
    "wof:name":"Teledata Online Svcs",
    "wof:placetype":"venue"
},
  "geometry": {"coordinates":[-93.334936,44.745283],"type":"Point"}
}