{
  "type": "Feature",
  "properties": {
    "iso:country":"US",
    "sg:address":"421 Commercial Ave N",
    "sg:city":"Sandstone",
    "sg:classifiers":[
        {
            "category":"Restaurant",
            "type":"Food & Drink"
        }
    ],
    "sg:phone":"+1 320 245 3114",
    "sg:postcode":"55072",
    "sg:province":"MN",
    "wof:name":"Kittys Corner Cafe",
    "wof:placetype":"venue"
},
  "geometry": {"coordinates":[-92.86552399999999,46.131756],"type":"Point"}
}