{
  "type": "Feature",
  "properties": {
    "addr:full":"307 14th St Kerkhoven MN 56252",
    "addr:housenumber":"307",
    "addr:postcode":"56252",
    "addr:street":"14Th St",
    "iso:country":"US",
    "sg:address":"307 14th St",
    "sg:city":"Kerkhoven",
    "sg:classifiers":[
        {
            "category":"Retail",
            "subcategory":"Funeral Services",
            "type":"Services"
        }
    ],
    "sg:phone":"+1 320 264 3261",
    "sg:postcode":"56252",
    "sg:province":"MN",
    "wof:name":"Kerkhoven Funeral Home",
    "wof:placetype":"venue"
},
  "geometry": {"coordinates":[-95.319259,45.195096],"type":"Point"}
}