{
  "type": "Feature",
  "properties": {
    "addr:full":"7800 Metro Pkwy Bloomington MN 55425",
    "addr:postcode":"7800;55425",
    "addr:street":"Metro Pkwy",
    "iso:country":"US",
    "sg:address":"7800 Metro Pkwy",
    "sg:city":"Bloomington",
    "sg:classifiers":[
        {
            "category":"Real Estate",
            "subcategory":"Real Estate Agent",
            "type":"Services"
        }
    ],
    "sg:phone":"+1 952 853 0036",
    "sg:postcode":"55425",
    "sg:province":"MN",
    "sg:tags":[
        "management"
    ],
    "wof:name":"Spectrum Property Mgmt Co Inc",
    "wof:placetype":"venue"
},
  "geometry": {"coordinates":[-93.229148,44.860199],"type":"Point"}
}