{
  "type": "Feature",
  "properties": {
    "iso:country":"US",
    "sg:address":"231 190th Ln NW",
    "sg:city":"Cedar",
    "sg:classifiers":[
        {
            "category":"Professional",
            "type":"Services"
        }
    ],
    "sg:phone":"+1 763 413 0611",
    "sg:postcode":"55011",
    "sg:province":"MN",
    "wof:name":"Randy Golfway",
    "wof:placetype":"venue"
},
  "geometry": {"coordinates":[-93.271168,45.314451],"type":"Point"}
}