{
  "type": "Feature",
  "properties": {
    "addr:full":"39782 170th St Brewster MN 56119",
    "addr:housenumber":"39782",
    "addr:postcode":"56119",
    "addr:street":"170Th St",
    "iso:country":"US",
    "sg:address":"39782 170th St",
    "sg:city":"Brewster",
    "sg:classifiers":[
        {
            "category":"Manufacturing",
            "subcategory":"Food",
            "type":"Manufacturing & Wholesale Goods"
        },
        {
            "category":"Farming",
            "subcategory":"Farm",
            "type":"Manufacturing & Wholesale Goods"
        }
    ],
    "sg:phone":"+1 507 842 5382",
    "sg:postcode":"56119",
    "sg:province":"MN",
    "sg:tags":[
        "corn",
        "product"
    ],
    "wof:name":"Eugene Zinnel",
    "wof:placetype":"venue"
},
  "geometry": {"coordinates":[-95.45604,43.74645],"type":"Point"}
}