{
  "type": "Feature",
  "properties": {
    "addr:full":"514 5th St SE Wadena MN 56482",
    "addr:housenumber":"514",
    "addr:postcode":"56482",
    "addr:street":"5Th St Se",
    "iso:country":"US",
    "sg:address":"514 5th St SE",
    "sg:city":"Wadena",
    "sg:classifiers":[
        {
            "category":"Home & Garden",
            "subcategory":"Building Materials",
            "type":"Retail Goods"
        }
    ],
    "sg:phone":"+1 218 564 4530",
    "sg:postcode":"56482",
    "sg:province":"MN",
    "sg:tags":[
        "mixed",
        "concrete"
    ],
    "wof:name":"Menahga Block & Concrete Prod",
    "wof:placetype":"venue"
},
  "geometry": {"coordinates":[-95.13334500000001,46.435371],"type":"Point"}
}