{
  "type": "Feature",
  "properties": {
    "addr:full":"7626 Langly Ave S Cottage Grove MN 55016",
    "addr:housenumber":"7626",
    "addr:postcode":"55016",
    "addr:street":"Langly Ave S Cottage Grove",
    "iso:country":"US",
    "sg:address":"7626 Langly Ave S",
    "sg:city":"Cottage Grove",
    "sg:classifiers":[
        {
            "category":"Retail",
            "subcategory":"Animal Services",
            "type":"Services"
        }
    ],
    "sg:phone":"+1 651 459 4606",
    "sg:postcode":"55016",
    "sg:province":"MN",
    "wof:name":"Old Grove Grooming",
    "wof:placetype":"venue"
},
  "geometry": {"coordinates":[-92.88078899999999,44.838893],"type":"Point"}
}