{
  "type": "Feature",
  "properties": {
    "addr:full":"20729 330th St Rushmore MN 56168",
    "addr:housenumber":"20729",
    "addr:postcode":"56168",
    "addr:street":"330Th St",
    "iso:country":"US",
    "sg:address":"20729 330th St",
    "sg:city":"Rushmore",
    "sg:classifiers":[
        {
            "category":"Professional",
            "subcategory":"Business Services",
            "type":"Services"
        }
    ],
    "sg:phone":"+1 507 394 2322",
    "sg:postcode":"56168",
    "sg:province":"MN",
    "wof:name":"Pork Storks II",
    "wof:placetype":"venue"
},
  "geometry": {"coordinates":[-95.83814099999999,43.514494],"type":"Point"}
}