{
  "type": "Feature",
  "properties": {
    "addr:full":"215 Co Rd B E Little Canada MN 55117",
    "addr:housenumber":"215",
    "addr:postcode":"55117",
    "addr:street":"Co Rd B E",
    "iso:country":"US",
    "sg:address":"215 Co Rd B E",
    "sg:city":"Little Canada",
    "sg:classifiers":[
        {
            "category":"Real Estate",
            "subcategory":"Real Estate Operator",
            "type":"Services"
        }
    ],
    "sg:phone":"+1 651 484 8833",
    "sg:postcode":"55117",
    "sg:province":"MN",
    "sg:tags":[
        "apartment"
    ],
    "wof:name":"Grand Pre East Apartments",
    "wof:placetype":"venue"
},
  "geometry": {"coordinates":[-93.09195099999999,45.006335],"type":"Point"}
}