{
  "type": "Feature",
  "properties": {
    "addr:full":"20990 Cedar Ave Lakeville MN 55044",
    "addr:housenumber":"20990",
    "addr:postcode":"55044",
    "addr:street":"Cedar Ave",
    "iso:country":"US",
    "sg:address":"20990 Cedar Ave",
    "sg:city":"Lakeville",
    "sg:classifiers":[
        {
            "category":"Real Estate",
            "subcategory":"Real Estate Operator",
            "type":"Services"
        }
    ],
    "sg:phone":"+1 952 469 5319",
    "sg:postcode":"55044",
    "sg:province":"MN",
    "sg:tags":[
        "mobile",
        "home",
        "site"
    ],
    "wof:name":"Ardmor Village",
    "wof:placetype":"venue"
},
  "geometry": {"coordinates":[-93.218001,44.645322],"type":"Point"}
}