{
  "type": "Feature",
  "properties": {
    "iso:country":"US",
    "sg:address":"107 2nd St SE",
    "sg:city":"Rose Creek",
    "sg:classifiers":[
        {
            "category":"Manufacturing",
            "subcategory":"Furniture",
            "type":"Manufacturing & Wholesale Goods"
        }
    ],
    "sg:phone":"+1 507 433 8799",
    "sg:postcode":"55970",
    "sg:province":"MN",
    "sg:tags":[
        "household",
        "wood",
        "mfg"
    ],
    "wof:name":"Flatlandherr",
    "wof:placetype":"venue"
},
  "geometry": {"coordinates":[-92.82995,43.604231],"type":"Point"}
}