{
  "type": "Feature",
  "properties": {
    "iso:country":"US",
    "sg:address":"202 Main Ave N",
    "sg:city":"Roseau",
    "sg:classifiers":[
        {
            "category":"Real Estate",
            "subcategory":"Real Estate Services",
            "type":"Services"
        }
    ],
    "sg:phone":"+1 218 463 3313",
    "sg:postcode":"56751",
    "sg:province":"MN",
    "wof:name":"Roseau-Lake Of The Woods Title",
    "wof:placetype":"venue"
},
  "geometry": {"coordinates":[-95.762725,48.847176],"type":"Point"}
}