{
  "type": "Feature",
  "properties": {
    "addr:full":"3216 Dakota Ave S Minneapolis MN 55416",
    "addr:housenumber":"3216",
    "addr:postcode":"55416",
    "addr:street":"Dakota Ave S",
    "iso:country":"US",
    "sg:address":"3216 Dakota Ave S",
    "sg:city":"Minneapolis",
    "sg:classifiers":[
        {
            "category":"Building & Trades",
            "subcategory":"Construction",
            "type":"Services"
        }
    ],
    "sg:phone":"+1 952 920 6543",
    "sg:postcode":"55416",
    "sg:province":"MN",
    "sg:tags":[
        "repairing",
        "remodeling",
        "contractor"
    ],
    "sg:website":"www.orfielddesign.com",
    "wof:name":"Orfield Design & Constr Inc",
    "wof:placetype":"venue"
},
  "geometry": {"coordinates":[-93.360484,44.944982],"type":"Point"}
}