{
  "type": "Feature",
  "properties": {
    "iso:country":"US",
    "sg:address":"2524 Hennepin Ave S",
    "sg:city":"Minneapolis",
    "sg:classifiers":[
        {
            "category":"Professional",
            "subcategory":"Accounting & Tax Preparation",
            "type":"Services"
        }
    ],
    "sg:phone":"+1 612 825 5700",
    "sg:postcode":"55405",
    "sg:province":"MN",
    "sg:tags":[
        "consultant"
    ],
    "wof:name":"Clarion Group Inc",
    "wof:placetype":"venue"
},
  "geometry": {"coordinates":[-93.296269,44.956365],"type":"Point"}
}