{
  "type": "Feature",
  "properties": {
    "iso:country":"US",
    "sg:address":"11628 Tanglewood Dr",
    "sg:city":"Eden Prairie",
    "sg:classifiers":[
        {
            "category":"Professional",
            "subcategory":"Business Services",
            "type":"Services"
        }
    ],
    "sg:phone":"+1 952 942 8864",
    "sg:postcode":"55347",
    "sg:province":"MN",
    "wof:name":"Winning Edge Sales",
    "wof:placetype":"venue"
},
  "geometry": {"coordinates":[-93.424554,44.817669],"type":"Point"}
}