{
  "type": "Feature",
  "properties": {
    "addr:full":"520 Western Ave Fergus Falls MN 56537",
    "addr:housenumber":"520",
    "addr:postcode":"56537",
    "addr:street":"Western Ave",
    "iso:country":"US",
    "sg:address":"520 Western Ave",
    "sg:city":"Fergus Falls",
    "sg:classifiers":[
        {
            "category":"Bars & Pubs",
            "type":"Food & Drink"
        }
    ],
    "sg:phone":"+1 218 998 5100",
    "sg:postcode":"56537",
    "sg:province":"MN",
    "sg:tags":[
        "drinking"
    ],
    "wof:name":"Speedway Grill & Tavern",
    "wof:placetype":"venue"
},
  "geometry": {"coordinates":[-96.11299,46.284822],"type":"Point"}
}