{
  "type": "Feature",
  "properties": {
    "addr:full":"512 Harold Dr Burnsville MN 55337",
    "addr:housenumber":"512",
    "addr:postcode":"55337",
    "addr:street":"Harold Dr",
    "iso:country":"US",
    "sg:address":"512 Harold Dr",
    "sg:city":"Burnsville",
    "sg:classifiers":[
        {
            "category":"Manufacturing",
            "subcategory":"Metals",
            "type":"Manufacturing & Wholesale Goods"
        }
    ],
    "sg:phone":"+1 952 882 9100",
    "sg:postcode":"55337",
    "sg:province":"MN",
    "sg:tags":[
        "machine",
        "screw",
        "product"
    ],
    "wof:name":"Jones Associates",
    "wof:placetype":"venue"
},
  "geometry": {"coordinates":[-93.28657,44.764629],"type":"Point"}
}