{
  "type": "Feature",
  "properties": {
    "iso:country":"US",
    "sg:address":"8762 Peyton Ave SW",
    "sg:city":"Cokato",
    "sg:classifiers":[
        {
            "category":"Farming",
            "subcategory":"Farm",
            "type":"Manufacturing & Wholesale Goods"
        }
    ],
    "sg:phone":"+1 320 286 5161",
    "sg:postcode":"55321",
    "sg:province":"MN",
    "sg:tags":[
        "crop",
        "general"
    ],
    "wof:name":"Sand-Son Farm",
    "wof:placetype":"venue"
},
  "geometry": {"coordinates":[-94.201842,45.023961],"type":"Point"}
}