{
  "type": "Feature",
  "properties": {
    "addr:full":"735 NE 1st Ave Grand Rapids MN 55744",
    "addr:housenumber":"735",
    "addr:postcode":"55744",
    "addr:street":"Ne 1St Ave",
    "iso:country":"US",
    "sg:address":"735 NE 1st Ave",
    "sg:city":"Grand Rapids",
    "sg:classifiers":[
        {
            "category":"Organizations",
            "subcategory":"Religious Organization",
            "type":"Services"
        }
    ],
    "sg:phone":"+1 218 326 5453",
    "sg:postcode":"55744",
    "sg:province":"MN",
    "sg:tags":[
        "church"
    ],
    "wof:name":"First Evangelical Lutheran Chr",
    "wof:placetype":"venue"
},
  "geometry": {"coordinates":[-93.52684499999999,47.239445],"type":"Point"}
}