{
  "type": "Feature",
  "properties": {
    "addr:full":"8154 E River Rd Minneapolis MN 55432",
    "addr:housenumber":"8154",
    "addr:postcode":"55432",
    "addr:street":"E River Rd",
    "iso:country":"US",
    "sg:address":"8154 E River Rd",
    "sg:city":"Minneapolis",
    "sg:classifiers":[
        {
            "category":"Retail",
            "subcategory":"Laundry & Dry Cleaning",
            "type":"Services"
        }
    ],
    "sg:phone":"+1 763 231 0246",
    "sg:postcode":"55432",
    "sg:province":"MN",
    "sg:tags":[
        "cleaner"
    ],
    "wof:name":"Ultra Wash Coin Laundry",
    "wof:placetype":"venue"
},
  "geometry": {"coordinates":[-93.283371,45.116119],"type":"Point"}
}