{
  "type": "Feature",
  "properties": {
    "addr:full":"12781 Wayzata Blvd Hopkins MN 55305",
    "addr:housenumber":"12781",
    "addr:postcode":"55305",
    "addr:street":"Wayzata Blvd",
    "iso:country":"US",
    "sg:address":"12781 Wayzata Blvd",
    "sg:city":"Hopkins",
    "sg:classifiers":[
        {
            "category":"Professional",
            "subcategory":"Art Services",
            "type":"Services"
        }
    ],
    "sg:phone":"+1 952 546 1192",
    "sg:postcode":"55305",
    "sg:province":"MN",
    "sg:tags":[
        "designer",
        "display",
        "producer"
    ],
    "wof:name":"Sal By Design",
    "wof:placetype":"venue"
},
  "geometry": {"coordinates":[-93.44067200000001,44.970518],"type":"Point"}
}