{
  "type": "Feature",
  "properties": {
    "iso:country":"US",
    "sg:address":"3410 E 42nd St",
    "sg:city":"Minneapolis",
    "sg:classifiers":[
        {
            "category":"Building & Trades",
            "subcategory":"Electrical",
            "type":"Services"
        }
    ],
    "sg:phone":"+1 612 721 4083",
    "sg:postcode":"55406",
    "sg:province":"MN",
    "sg:tags":[
        "electrical",
        "contractor"
    ],
    "wof:name":"Integra Electric",
    "wof:placetype":"venue"
},
  "geometry": {"coordinates":[-93.223264,44.92699],"type":"Point"}
}