{
  "type": "Feature",
  "properties": {
    "iso:country":"US",
    "sg:address":"15712 Wayzata Blvd",
    "sg:city":"Wayzata",
    "sg:classifiers":[
        {
            "category":"Retail",
            "subcategory":"Veterinary Services",
            "type":"Services"
        }
    ],
    "sg:phone":"+1 877 784 5459",
    "sg:postcode":"55391",
    "sg:province":"MN",
    "sg:tags":[
        "veterinarian"
    ],
    "wof:name":"Wayzata Pet Hospital",
    "wof:placetype":"venue"
},
  "geometry": {"coordinates":[-93.474935,44.971449],"type":"Point"}
}