{
  "type": "Feature",
  "properties": {
    "iso:country":"US",
    "sg:address":"32713 382nd Pl",
    "sg:city":"Aitkin",
    "sg:classifiers":[
        {
            "category":"Personal",
            "subcategory":"Beauty Salon",
            "type":"Services"
        }
    ],
    "sg:phone":"+1 218 927 7001",
    "sg:postcode":"56431",
    "sg:province":"MN",
    "sg:tags":[
        "shop"
    ],
    "wof:name":"Mer-Lynn's Family Hair Care",
    "wof:placetype":"venue"
},
  "geometry": {"coordinates":[-93.643411,46.491182],"type":"Point"}
}