{
  "type": "Feature",
  "properties": {
    "iso:country":"US",
    "sg:address":"16603 Lakeland Dr",
    "sg:city":"Minnetonka",
    "sg:classifiers":[
        {
            "category":"Professional",
            "subcategory":"Detective & Security Services",
            "type":"Services"
        }
    ],
    "sg:phone":"+1 952 934 9409",
    "sg:postcode":"55345",
    "sg:province":"MN",
    "sg:tags":[
        "guard"
    ],
    "wof:name":"Gerald Hermstad",
    "wof:placetype":"venue"
},
  "geometry": {"coordinates":[-93.490656,44.900838],"type":"Point"}
}