{
  "type": "Feature",
  "properties": {
    "addr:full":"9633 Parkside Trl N Champlin MN 55316",
    "addr:housenumber":"9633",
    "addr:postcode":"55316",
    "addr:street":"Parkside Trl N",
    "iso:country":"US",
    "sg:address":"9633 Parkside Trl N",
    "sg:city":"Champlin",
    "sg:classifiers":[
        {
            "category":"Banks & Credit Unions",
            "subcategory":"Bank",
            "type":"Services"
        }
    ],
    "sg:phone":"+1 763 712 9493",
    "sg:postcode":"55316",
    "sg:province":"MN",
    "sg:tags":[
        "broker",
        "mortgage"
    ],
    "wof:name":"Triad Home Finance Group Inc",
    "wof:placetype":"venue"
},
  "geometry": {"coordinates":[-93.401484,45.161442],"type":"Point"}
}