{
  "type": "Feature",
  "properties": {
    "iso:country":"US",
    "sg:address":"7600 Penn Ave S",
    "sg:city":"Minneapolis",
    "sg:classifiers":[
        {
            "category":"Shopping",
            "subcategory":"Discount & Variety Stores",
            "type":"Retail Goods"
        }
    ],
    "sg:phone":"+1 612 798 4018",
    "sg:postcode":"55423",
    "sg:province":"MN",
    "sg:tags":[
        "apparel"
    ],
    "wof:name":"American Supply",
    "wof:placetype":"venue"
},
  "geometry": {"coordinates":[-93.308678,44.863662],"type":"Point"}
}