{
  "type": "Feature",
  "properties": {
    "iso:country":"US",
    "sg:address":"1620 9th Ave NE",
    "sg:city":"Owatonna",
    "sg:classifiers":[
        {
            "category":"Social Services",
            "subcategory":"Child Care",
            "type":"Services"
        }
    ],
    "sg:phone":"+1 507 451 9509",
    "sg:postcode":"55060",
    "sg:province":"MN",
    "sg:tags":[
        "day"
    ],
    "wof:name":"Linda Jeno",
    "wof:placetype":"venue"
},
  "geometry": {"coordinates":[-93.209047,44.099812],"type":"Point"}
}