{
  "type": "Feature",
  "properties": {
    "addr:full":"72823 220th St Albert Lea MN 56007",
    "addr:housenumber":"72823",
    "addr:postcode":"56007",
    "addr:street":"220Th St",
    "iso:country":"US",
    "sg:address":"72823 220th St",
    "sg:city":"Albert Lea",
    "sg:classifiers":[
        {
            "category":"Government",
            "subcategory":"Office",
            "type":"Public Place"
        }
    ],
    "sg:phone":"+1 507 373 4925",
    "sg:postcode":"56007",
    "sg:province":"MN",
    "sg:tags":[
        "management"
    ],
    "wof:name":"Shell Rock River Watershed",
    "wof:placetype":"venue"
},
  "geometry": {"coordinates":[-93.410939,43.669458],"type":"Point"}
}