{
  "type": "Feature",
  "properties": {
    "iso:country":"US",
    "sg:address":"1211 143rd Ln NW",
    "sg:city":"Anoka",
    "sg:classifiers":[
        {
            "category":"Social Services",
            "subcategory":"Child Care",
            "type":"Services"
        }
    ],
    "sg:phone":"+1 763 434 1435",
    "sg:postcode":"55304",
    "sg:province":"MN",
    "sg:tags":[
        "day"
    ],
    "wof:name":"Tammy Tot Daycare",
    "wof:placetype":"venue"
},
  "geometry": {"coordinates":[-93.297363,45.231507],"type":"Point"}
}