{
  "type": "Feature",
  "properties": {
    "iso:country":"US",
    "sg:address":"470 W 78th St Ste 150",
    "sg:city":"Chanhassen",
    "sg:classifiers":[
        {
            "category":"Personal",
            "subcategory":"Massage",
            "type":"Services"
        },
        {
            "category":"Personal",
            "subcategory":"Hair Removal",
            "type":"Services"
        },
        {
            "category":"Personal",
            "subcategory":"Skin Care",
            "type":"Services"
        },
        {
            "category":"Personal",
            "subcategory":"Day Spa",
            "type":"Services"
        }
    ],
    "sg:phone":"+1 952 401 1288",
    "sg:postcode":"55317",
    "sg:province":"MN",
    "sg:tags":[
        "therapist"
    ],
    "wof:name":"Stonehaven Wellness Center",
    "wof:placetype":"venue"
},
  "geometry": {"coordinates":[-93.53233299999999,44.861992],"type":"Point"}
}