{
  "type": "Feature",
  "properties": {
    "addr:full":"110 Downtown Plz Fairmont MN 56031",
    "addr:postcode":"56031",
    "iso:country":"US",
    "sg:address":"110 Downtown Plz",
    "sg:city":"Fairmont",
    "sg:classifiers":[
        {
            "category":"Banks & Credit Unions",
            "subcategory":"Investment Brokerage",
            "type":"Services"
        }
    ],
    "sg:phone":"+1 507 235 5115",
    "sg:postcode":"56031",
    "sg:province":"MN",
    "sg:tags":[
        "advisory"
    ],
    "wof:name":"L P L Financial Services",
    "wof:placetype":"venue"
},
  "geometry": {"coordinates":[-94.46228600000001,43.653437],"type":"Point"}
}