{
  "type": "Feature",
  "properties": {
    "addr:full":"2024 Lyndale Ave N Minneapolis MN 55411",
    "addr:housenumber":"2024",
    "addr:postcode":"55411",
    "addr:street":"Lyndale Ave N",
    "iso:country":"US",
    "sg:address":"2024 Lyndale Ave N",
    "sg:city":"Minneapolis",
    "sg:classifiers":[
        {
            "category":"Social Services",
            "type":"Services"
        }
    ],
    "sg:phone":"+1 612 522 4871",
    "sg:postcode":"55411",
    "sg:province":"MN",
    "sg:tags":[
        "church",
        "place",
        "worship",
        "welfare"
    ],
    "sg:website":"http://www.salvationarmyusa.org/",
    "wof:name":"Salvation Army",
    "wof:placetype":"venue"
},
  "geometry": {"coordinates":[-93.287987,44.999406],"type":"Point"}
}