{
  "type": "Feature",
  "properties": {
    "iso:country":"US",
    "sg:address":"411 3rd St N",
    "sg:city":"Waite Park",
    "sg:classifiers":[
        {
            "category":"Home & Garden",
            "subcategory":"Household Appliances",
            "type":"Retail Goods"
        }
    ],
    "sg:phone":"+1 320 529 8184",
    "sg:postcode":"56387",
    "sg:province":"MN",
    "wof:name":"Airtech",
    "wof:placetype":"venue"
},
  "geometry": {"coordinates":[-94.222634,45.558985],"type":"Point"}
}