{
  "type": "Feature",
  "properties": {
    "addr:full":"10420 Aquila Cir Minneapolis MN 55438",
    "addr:postcode":"10420;55438",
    "addr:street":"Aquila Cir",
    "iso:country":"US",
    "sg:address":"10420 Aquila Cir",
    "sg:city":"Minneapolis",
    "sg:classifiers":[
        {
            "category":"Building & Trades",
            "subcategory":"Construction",
            "type":"Services"
        }
    ],
    "sg:phone":"+1 952 828 0859",
    "sg:postcode":"55438",
    "sg:province":"MN",
    "sg:tags":[
        "house"
    ],
    "wof:name":"Briesemeister Constructio",
    "wof:placetype":"venue"
},
  "geometry": {"coordinates":[-93.39337999999999,44.814087],"type":"Point"}
}