{
  "type": "Feature",
  "properties": {
    "addr:full":"112 SE 3rd Ave Grand Rapids MN 55744",
    "addr:housenumber":"112",
    "addr:postcode":"55744",
    "addr:street":"Se 3Rd Ave",
    "iso:country":"US",
    "sg:address":"112 SE 3rd Ave",
    "sg:city":"Grand Rapids",
    "sg:classifiers":[
        {
            "category":"Building & Trades",
            "subcategory":"Construction",
            "type":"Services"
        }
    ],
    "sg:phone":"+1 218 326 7006",
    "sg:postcode":"55744",
    "sg:province":"MN",
    "sg:tags":[
        "contractor"
    ],
    "wof:name":"Mark Lowe Construction",
    "wof:placetype":"venue"
},
  "geometry": {"coordinates":[-93.52377199999999,47.230417],"type":"Point"}
}