{
  "type": "Feature",
  "properties": {
    "addr:full":"310 Main St Lakefield MN 56150",
    "addr:housenumber":"310",
    "addr:postcode":"56150",
    "addr:street":"Main St",
    "iso:country":"US",
    "sg:address":"310 Main St",
    "sg:city":"Lakefield",
    "sg:classifiers":[
        {
            "category":"Professional",
            "subcategory":"Lawyer & Legal Services",
            "type":"Services"
        }
    ],
    "sg:phone":"+1 507 662 6621",
    "sg:postcode":"56150",
    "sg:province":"MN",
    "sg:tags":[
        "attorney"
    ],
    "sg:website":"www.kubbgame.com",
    "wof:name":"Costello Carlson & Butzon",
    "wof:placetype":"venue"
},
  "geometry": {"coordinates":[-95.17196199999999,43.678417],"type":"Point"}
}