{
  "type": "Feature",
  "properties": {
    "addr:full":"707 Hwy 33 S Cloquet MN 55720",
    "addr:housenumber":"707",
    "addr:postcode":"55720",
    "addr:street":"Hwy 33 S",
    "iso:country":"US",
    "sg:address":"707 Hwy 33 S",
    "sg:city":"Cloquet",
    "sg:classifiers":[
        {
            "category":"Shopping",
            "subcategory":"Florist",
            "type":"Retail Goods"
        }
    ],
    "sg:phone":"+1 218 879 6911",
    "sg:postcode":"55720",
    "sg:province":"MN",
    "sg:tags":[
        "plant"
    ],
    "wof:name":"Plant Place",
    "wof:placetype":"venue"
},
  "geometry": {"coordinates":[-92.461339,46.721366],"type":"Point"}
}