{
  "type": "Feature",
  "properties": {
    "addr:full":"2949 Viking Blvd NE Wyoming MN 55092",
    "addr:housenumber":"2949",
    "addr:postcode":"55092",
    "addr:street":"Viking Blvd Ne",
    "iso:country":"US",
    "sg:address":"2949 Viking Blvd NE",
    "sg:city":"Wyoming",
    "sg:classifiers":[
        {
            "category":"Building & Trades",
            "subcategory":"Construction",
            "type":"Services"
        }
    ],
    "sg:phone":"+1 763 434 3618",
    "sg:postcode":"55092",
    "sg:province":"MN",
    "sg:tags":[
        "excavation",
        "repair",
        "contractor"
    ],
    "wof:name":"Caspers Excavating Inc",
    "wof:placetype":"venue"
},
  "geometry": {"coordinates":[-93.196585,45.319589],"type":"Point"}
}