{
  "type": "Feature",
  "properties": {
    "addr:full":"8565 Aspen Ln N Brooklyn Park MN 55445",
    "addr:housenumber":"8565",
    "addr:postcode":"55445",
    "addr:street":"Aspen Ln N",
    "iso:country":"US",
    "sg:address":"8565 Aspen Ln N",
    "sg:city":"Brooklyn Park",
    "sg:classifiers":[
        {
            "category":"Retail",
            "subcategory":"Auto Repair",
            "type":"Services"
        }
    ],
    "sg:phone":"+1 763 424 4149",
    "sg:postcode":"55445",
    "sg:province":"MN",
    "sg:tags":[
        "automobile",
        "lubrication",
        "automotive"
    ],
    "sg:website":"www.vioc.com",
    "wof:name":"Valvoline Instant Oil Change",
    "wof:placetype":"venue"
},
  "geometry": {"coordinates":[-93.39384800000001,45.110272],"type":"Point"}
}