{
  "type": "Feature",
  "properties": {
    "addr:full":"116 US Hwy 12 Darwin MN 55324",
    "addr:housenumber":"116",
    "addr:postcode":"55324",
    "addr:street":"Us Hwy 12",
    "iso:country":"US",
    "sg:address":"116 US Hwy 12",
    "sg:city":"Darwin",
    "sg:classifiers":[
        {
            "category":"Wholesale",
            "subcategory":"Construction Materials",
            "type":"Manufacturing & Wholesale Goods"
        }
    ],
    "sg:phone":"+1 320 693 8440",
    "sg:postcode":"55324",
    "sg:province":"MN",
    "sg:tags":[
        "concrete",
        "product"
    ],
    "wof:name":"Precast Systems",
    "wof:placetype":"venue"
},
  "geometry": {"coordinates":[-94.412425,45.099937],"type":"Point"}
}