{
  "type": "Feature",
  "properties": {
    "addr:full":"218 Wisconsin St Grand Marais MN 55604",
    "addr:housenumber":"218",
    "addr:postcode":"55604",
    "addr:street":"Wisconsin St",
    "iso:country":"US",
    "sg:address":"218 Wisconsin St",
    "sg:city":"Grand Marais",
    "sg:classifiers":[
        {
            "category":"Professional",
            "subcategory":"Business Services",
            "type":"Services"
        }
    ],
    "sg:phone":"+1 218 387 3191",
    "sg:postcode":"55604",
    "sg:province":"MN",
    "sg:tags":[
        "information",
        "bureau",
        "convention"
    ],
    "wof:name":"Gunflint Trail Information Ctr",
    "wof:placetype":"venue"
},
  "geometry": {"coordinates":[-90.337445,47.749444],"type":"Point"}
}