{
  "type": "Feature",
  "properties": {
    "addr:full":"106 Washington Ave NW Fertile MN 56540",
    "addr:housenumber":"106",
    "addr:postcode":"56540",
    "addr:street":"Washington Ave Nw",
    "iso:country":"US",
    "sg:address":"106 Washington Ave NW",
    "sg:city":"Fertile",
    "sg:classifiers":[
        {
            "category":"Restaurant",
            "type":"Food & Drink"
        }
    ],
    "sg:phone":"+1 218 945 9952",
    "sg:postcode":"56540",
    "sg:province":"MN",
    "wof:name":"Mac's Cafe & Dining",
    "wof:placetype":"venue"
},
  "geometry": {"coordinates":[-96.281683,47.536204],"type":"Point"}
}