{
  "type": "Feature",
  "properties": {
    "addr:full":"26742 Co Rd 175 Belgrade MN 56312",
    "addr:housenumber":"26742;175",
    "addr:postcode":"56312",
    "addr:street":"Co Rd",
    "iso:country":"US",
    "sg:address":"26742 Co Rd 175",
    "sg:city":"Belgrade",
    "sg:classifiers":[
        {
            "category":"Farming",
            "subcategory":"Dairy Farm",
            "type":"Manufacturing & Wholesale Goods"
        }
    ],
    "sg:phone":"+1 320 987 3189",
    "sg:postcode":"56312",
    "sg:province":"MN",
    "wof:name":"Daniel Schwieters",
    "wof:placetype":"venue"
},
  "geometry": {"coordinates":[-94.885903,45.508849],"type":"Point"}
}