{
  "type": "Feature",
  "properties": {
    "addr:full":"625 River Rd W Preston MN 55965",
    "addr:housenumber":"625",
    "addr:postcode":"55965",
    "addr:street":"River Rd W",
    "iso:country":"US",
    "sg:address":"625 River Rd W",
    "sg:city":"Preston",
    "sg:classifiers":[
        {
            "category":"Government",
            "subcategory":"Office",
            "type":"Public Place"
        }
    ],
    "sg:phone":"+1 507 765 3611",
    "sg:postcode":"55965",
    "sg:province":"MN",
    "sg:tags":[
        "govt",
        "city"
    ],
    "wof:name":"Preston Wastewater Treatment",
    "wof:placetype":"venue"
},
  "geometry": {"coordinates":[-92.09185100000001,43.670842],"type":"Point"}
}