{
  "type": "Feature",
  "properties": {
    "iso:country":"US",
    "sg:address":"268 W Broadway Ave",
    "sg:city":"Minneapolis",
    "sg:classifiers":[
        {
            "category":"Shopping",
            "subcategory":"Clothing, Apparel, & Fashions",
            "type":"Retail Goods"
        }
    ],
    "sg:phone":"+1 952 854 7198",
    "sg:postcode":"55411",
    "sg:province":"MN",
    "sg:tags":[
        "wear"
    ],
    "wof:name":"Zutopia",
    "wof:placetype":"venue"
},
  "geometry": {"coordinates":[-93.28297999999999,44.999209],"type":"Point"}
}