{
  "type": "Feature",
  "properties": {
    "iso:country":"US",
    "sg:address":"3812 Coon Rapids Blvd NW",
    "sg:city":"Minneapolis",
    "sg:classifiers":[
        {
            "category":"Real Estate",
            "subcategory":"Real Estate Agent",
            "type":"Services"
        }
    ],
    "sg:phone":"+1 763 785 0185",
    "sg:postcode":"55433",
    "sg:province":"MN",
    "wof:name":"Preferred Service Realty Inc",
    "wof:placetype":"venue"
},
  "geometry": {"coordinates":[-93.36459000000001,45.182313],"type":"Point"}
}