{
  "type": "Feature",
  "properties": {
    "iso:country":"US",
    "sg:address":"900 Mount Curve Ave",
    "sg:city":"Minneapolis",
    "sg:classifiers":[
        {
            "category":"Social Services",
            "subcategory":"Child Care",
            "type":"Services"
        },
        {
            "category":"Education",
            "subcategory":"Preschool",
            "type":"Public Place"
        },
        {
            "category":"Education",
            "subcategory":"School",
            "type":"Public Place"
        }
    ],
    "sg:phone":"+1 612 377 1698",
    "sg:postcode":"55403",
    "sg:province":"MN",
    "sg:tags":[
        "elementary",
        "day"
    ],
    "wof:name":"Child Gdn Totl Envrnmnt Mntssri Schls and Dy Cre C",
    "wof:placetype":"venue"
},
  "geometry": {"coordinates":[-93.29070299999999,44.967098],"type":"Point"}
}