{
  "type": "Feature",
  "properties": {
    "addr:full":"400 Groveland Ave Minneapolis MN 55403",
    "addr:housenumber":"400",
    "addr:postcode":"55403",
    "addr:street":"Groveland Ave",
    "iso:country":"US",
    "sg:address":"400 Groveland Ave",
    "sg:city":"Minneapolis",
    "sg:classifiers":[
        {
            "category":"Professional",
            "subcategory":"Computer Services",
            "type":"Services"
        }
    ],
    "sg:phone":"+1 612 870 1525",
    "sg:postcode":"55403",
    "sg:province":"MN",
    "sg:tags":[
        "related"
    ],
    "wof:name":"Simitron",
    "wof:placetype":"venue"
},
  "geometry": {"coordinates":[-93.284226,44.965188],"type":"Point"}
}