{
  "type": "Feature",
  "properties": {
    "addr:full":"312 Water St Jordan MN 55352",
    "addr:housenumber":"312",
    "addr:postcode":"55352",
    "addr:street":"Water St",
    "iso:country":"US",
    "sg:address":"312 Water St",
    "sg:city":"Jordan",
    "sg:classifiers":[
        {
            "category":"Building & Trades",
            "subcategory":"Construction",
            "type":"Services"
        }
    ],
    "sg:phone":"+1 952 873 2708",
    "sg:postcode":"55352",
    "sg:province":"MN",
    "sg:tags":[
        "excavation",
        "contractor"
    ],
    "wof:name":"Dirt Werx of Minn Inc",
    "wof:placetype":"venue"
},
  "geometry": {"coordinates":[-93.62607199999999,44.665221],"type":"Point"}
}