{
  "type": "Feature",
  "properties": {
    "addr:full":"624 Central Ave Osseo MN 55369",
    "addr:housenumber":"624",
    "addr:postcode":"55369",
    "addr:street":"Central Ave",
    "iso:country":"US",
    "sg:address":"624 Central Ave",
    "sg:city":"Osseo",
    "sg:classifiers":[
        {
            "category":"Wholesale",
            "subcategory":"Electrical",
            "type":"Manufacturing & Wholesale Goods"
        }
    ],
    "sg:phone":"+1 763 315 3791",
    "sg:postcode":"55369",
    "sg:province":"MN",
    "sg:tags":[
        "lighting",
        "fixture",
        "supply"
    ],
    "wof:name":"Dennison Lighting Inc",
    "wof:placetype":"venue"
},
  "geometry": {"coordinates":[-93.40199800000001,45.122959],"type":"Point"}
}