{
  "type": "Feature",
  "properties": {
    "iso:country":"US",
    "sg:address":"807 Heinel Dr",
    "sg:city":"St Paul",
    "sg:classifiers":[
        {
            "category":"Professional",
            "subcategory":"Business Services",
            "type":"Services"
        }
    ],
    "sg:phone":"+1 612 378 0999",
    "sg:postcode":"55113",
    "sg:province":"MN",
    "sg:tags":[
        "interior",
        "consultant",
        "design",
        "decorator"
    ],
    "wof:name":"Inside Story Interior Design",
    "wof:placetype":"venue"
},
  "geometry": {"coordinates":[-93.130909,45.025424],"type":"Point"}
}