{
  "type": "Feature",
  "properties": {
    "iso:country":"US",
    "sg:address":"15108 Traff Dr",
    "sg:city":"Houston",
    "sg:classifiers":[
        {
            "category":"Farming",
            "subcategory":"Livestock Farm",
            "type":"Manufacturing & Wholesale Goods"
        }
    ],
    "sg:phone":"+1 507 896 3724",
    "sg:postcode":"55943",
    "sg:province":"MN",
    "sg:tags":[
        "feedlot",
        "ranch",
        "equine",
        "beef",
        "cattle"
    ],
    "wof:name":"Lenard Tostenson",
    "wof:placetype":"venue"
},
  "geometry": {"coordinates":[-91.554024,43.8219],"type":"Point"}
}