{
  "type": "Feature",
  "properties": {
    "addr:full":"1750 W. Highway 36 Roseville MN 55113",
    "addr:housenumber":"1750",
    "addr:postcode":"55113",
    "addr:street":"W. Highway 36",
    "iso:country":"US",
    "sg:address":"1750 W. Highway 36",
    "sg:city":"Roseville",
    "sg:classifiers":[
        {
            "category":"Shopping",
            "subcategory":"Bicycles & Sporting Goods",
            "type":"Retail Goods"
        }
    ],
    "sg:phone":"+1 651 638 3000",
    "sg:postcode":"55113",
    "sg:province":"MN",
    "sg:website":"www.sportsauthority.com",
    "wof:name":"Sports Authority",
    "wof:placetype":"venue"
},
  "geometry": {"coordinates":[-93.17244700000001,45.010026],"type":"Point"}
}