{
  "type": "Feature",
  "properties": {
    "addr:full":"2210 Hennepin Ave Minneapolis MN 55405",
    "addr:housenumber":"2210",
    "addr:postcode":"55405",
    "addr:street":"Hennepin Ave",
    "iso:country":"US",
    "sg:address":"2210 Hennepin Ave",
    "sg:city":"Minneapolis",
    "sg:classifiers":[
        {
            "category":"Restaurant",
            "type":"Food & Drink"
        }
    ],
    "sg:menulink":"http://www.allmenus.com/mn/minneapolis/119778-damico--sons/menu/",
    "sg:phone":"+1 612 374 1858",
    "sg:postcode":"55405",
    "sg:province":"MN",
    "sg:tags":[
        "italian"
    ],
    "wof:name":"D'amico & Sons",
    "wof:placetype":"venue"
},
  "geometry": {"coordinates":[-93.292704,44.960832],"type":"Point"}
}