{
  "type": "Feature",
  "properties": {
    "iso:country":"US",
    "sg:address":"3000 Hundertmark Rd Ste 11",
    "sg:city":"Chaska",
    "sg:classifiers":[
        {
            "category":"Health Services",
            "subcategory":"Doctor",
            "type":"Services"
        }
    ],
    "sg:phone":"+1 952 556 0155",
    "sg:postcode":"55318",
    "sg:province":"MN",
    "sg:website":"www.ridgeviewmedical.com",
    "wof:name":"Meccia John W MD",
    "wof:placetype":"venue"
},
  "geometry": {"coordinates":[-93.611397,44.8097],"type":"Point"}
}