{
  "type": "Feature",
  "properties": {
    "iso:country":"US",
    "sg:address":"541 Manor Dr NE",
    "sg:city":"Minneapolis",
    "sg:classifiers":[
        {
            "category":"Building & Trades",
            "subcategory":"Construction",
            "type":"Services"
        }
    ],
    "sg:phone":"+1 763 784 0132",
    "sg:postcode":"55432",
    "sg:province":"MN",
    "sg:tags":[
        "hanging",
        "contractor"
    ],
    "wof:name":"General Walls Systems Inc",
    "wof:placetype":"venue"
},
  "geometry": {"coordinates":[-93.25619,45.122856],"type":"Point"}
}