{
  "type": "Feature",
  "properties": {
    "iso:country":"US",
    "sg:address":"1685 Wall Ave",
    "sg:city":"Bock",
    "sg:classifiers":[
        {
            "category":"Retail",
            "subcategory":"Auto Repair",
            "type":"Services"
        }
    ],
    "sg:phone":"+1 320 556 3414",
    "sg:postcode":"56313",
    "sg:province":"MN",
    "sg:tags":[
        "lubricating"
    ],
    "wof:name":"TNT Food & Gas",
    "wof:placetype":"venue"
},
  "geometry": {"coordinates":[-93.55275399999999,45.786407],"type":"Point"}
}