{
  "type": "Feature",
  "properties": {
    "addr:full":"204 S Main St Le Sueur MN 56058",
    "addr:housenumber":"204",
    "addr:postcode":"56058",
    "addr:street":"S Main St",
    "iso:country":"US",
    "sg:address":"204 S Main St",
    "sg:city":"Le Sueur",
    "sg:classifiers":[
        {
            "category":"Professional",
            "subcategory":"Accounting & Tax Preparation",
            "type":"Services"
        }
    ],
    "sg:phone":"+1 507 665 6376",
    "sg:postcode":"56058",
    "sg:province":"MN",
    "sg:tags":[
        "return",
        "filing"
    ],
    "wof:name":"H & R Block Tax Svc",
    "wof:placetype":"venue"
},
  "geometry": {"coordinates":[-93.916884,44.459611],"type":"Point"}
}