{
  "type": "Feature",
  "properties": {
    "addr:full":"15835 Cicerone Path Rosemount MN 55068",
    "addr:housenumber":"15835",
    "addr:postcode":"55068",
    "addr:street":"Cicerone Path",
    "iso:country":"US",
    "sg:address":"15835 Cicerone Path",
    "sg:city":"Rosemount",
    "sg:classifiers":[
        {
            "category":"Building & Trades",
            "subcategory":"Electrical",
            "type":"Services"
        }
    ],
    "sg:phone":"+1 952 423 4328",
    "sg:postcode":"55068",
    "sg:province":"MN",
    "sg:tags":[
        "electrical",
        "contractor"
    ],
    "wof:name":"Roehning Electric",
    "wof:placetype":"venue"
},
  "geometry": {"coordinates":[-93.139606,44.722211],"type":"Point"}
}