{
  "type": "Feature",
  "properties": {
    "addr:full":"1819 Kenwood Ave Duluth MN 55811",
    "addr:housenumber":"1819",
    "addr:postcode":"55811",
    "addr:street":"Kenwood Ave",
    "iso:country":"US",
    "sg:address":"1819 Kenwood Ave",
    "sg:city":"Duluth",
    "sg:classifiers":[
        {
            "category":"Professional",
            "type":"Services"
        }
    ],
    "sg:phone":"+1 218 728 2330",
    "sg:postcode":"55811",
    "sg:province":"MN",
    "wof:name":"Lucille M Rich",
    "wof:placetype":"venue"
},
  "geometry": {"coordinates":[-92.100476,46.825475],"type":"Point"}
}