{
  "type": "Feature",
  "properties": {
    "iso:country":"US",
    "sg:address":"4345 Nathan Ln N",
    "sg:city":"Minneapolis",
    "sg:classifiers":[
        {
            "category":"Restaurant",
            "type":"Food & Drink"
        }
    ],
    "sg:phone":"+1 763 559 6006",
    "sg:postcode":"55442",
    "sg:province":"MN",
    "sg:tags":[
        "pan",
        "japanese",
        "chinese",
        "asian"
    ],
    "wof:name":"1 Chinese & Japanese Cuisine",
    "wof:placetype":"venue"
},
  "geometry": {"coordinates":[-93.408565,45.033679],"type":"Point"}
}