{
  "type": "Feature",
  "properties": {
    "addr:full":"6670 Lucia Ln NE Apt 2 Minneapolis MN 55432",
    "addr:housenumber":"6670;2",
    "addr:postcode":"55432",
    "addr:street":"Lucia Ln Ne Apt",
    "iso:country":"US",
    "sg:address":"6670 Lucia Ln NE Apt 2",
    "sg:city":"Minneapolis",
    "sg:classifiers":[
        {
            "category":"Building & Trades",
            "subcategory":"Electrical",
            "type":"Services"
        }
    ],
    "sg:phone":"+1 763 571 1005",
    "sg:postcode":"55432",
    "sg:province":"MN",
    "sg:tags":[
        "electrician"
    ],
    "wof:name":"Tormanen Elec Contr",
    "wof:placetype":"venue"
},
  "geometry": {"coordinates":[-93.24181299999999,45.088213],"type":"Point"}
}