{
  "type": "Feature",
  "properties": {
    "iso:country":"US",
    "sg:address":"5581 Tower Dr",
    "sg:city":"Saint Paul",
    "sg:classifiers":[
        {
            "category":"Banks & Credit Unions",
            "subcategory":"Financial Services",
            "type":"Services"
        }
    ],
    "sg:phone":"+1 651 459 5158",
    "sg:postcode":"55129",
    "sg:province":"MN",
    "sg:tags":[
        "investor"
    ],
    "wof:name":"Jacobson Investments",
    "wof:placetype":"venue"
},
  "geometry": {"coordinates":[-92.943895,44.867971],"type":"Point"}
}