{
  "type": "Feature",
  "properties": {
    "iso:country":"US",
    "sg:address":"10965 53rd Ave N",
    "sg:city":"Minneapolis",
    "sg:classifiers":[
        {
            "category":"Science Facility",
            "type":"Public Place"
        }
    ],
    "sg:phone":"+1 612 998 9783",
    "sg:postcode":"55442",
    "sg:province":"MN",
    "sg:tags":[
        "development",
        "laboratories-research"
    ],
    "wof:name":"Last Chance Tissue Adhesives Corporation",
    "wof:placetype":"venue"
},
  "geometry": {"coordinates":[-93.419533,45.050788],"type":"Point"}
}