{
  "type": "Feature",
  "properties": {
    "iso:country":"US",
    "sg:address":"120 Derby Ln",
    "sg:city":"Willernie",
    "sg:classifiers":[
        {
            "category":"Freight",
            "type":"Transportation"
        }
    ],
    "sg:phone":"+1 651 653 6476",
    "sg:postcode":"55090",
    "sg:province":"MN",
    "sg:tags":[
        "dock"
    ],
    "wof:name":"White Bear Lift & Dock Makers",
    "wof:placetype":"venue"
},
  "geometry": {"coordinates":[-92.95893100000001,45.056563],"type":"Point"}
}