{
  "type": "Feature",
  "properties": {
    "iso:country":"US",
    "sg:address":"1955 English St",
    "sg:city":"Saint Paul",
    "sg:classifiers":[
        {
            "category":"Shopping",
            "subcategory":"Bicycles & Sporting Goods",
            "type":"Retail Goods"
        }
    ],
    "sg:phone":"+1 651 774 8787",
    "sg:postcode":"55109",
    "sg:province":"MN",
    "wof:name":"Left & Right Pro Shop",
    "wof:placetype":"venue"
},
  "geometry": {"coordinates":[-93.045785,45.00018],"type":"Point"}
}