{
  "type": "Feature",
  "properties": {
    "iso:country":"US",
    "sg:address":"4950 31st Ave NW",
    "sg:city":"Rochester",
    "sg:classifiers":[
        {
            "category":"Organizations",
            "subcategory":"Religious Organization",
            "type":"Services"
        }
    ],
    "sg:phone":"+1 507 289 2990",
    "sg:postcode":"55901",
    "sg:province":"MN",
    "sg:website":"www.rochcov.org",
    "wof:name":"Rochester Covenant Church",
    "wof:placetype":"venue"
},
  "geometry": {"coordinates":[-92.508624,44.071096],"type":"Point"}
}