{
  "type": "Feature",
  "properties": {
    "addr:full":"504 Division St S Northfield MN 55057",
    "addr:housenumber":"504",
    "addr:postcode":"55057",
    "addr:street":"Division St S",
    "iso:country":"US",
    "sg:address":"504 Division St S",
    "sg:city":"Northfield",
    "sg:classifiers":[
        {
            "category":"Banks & Credit Unions",
            "subcategory":"Investment Brokerage",
            "type":"Services"
        }
    ],
    "sg:phone":"+1 507 664 0464",
    "sg:postcode":"55057",
    "sg:province":"MN",
    "sg:tags":[
        "security"
    ],
    "wof:name":"First Choice Financial",
    "wof:placetype":"venue"
},
  "geometry": {"coordinates":[-93.160231,44.45505],"type":"Point"}
}