{
  "type": "Feature",
  "properties": {
    "addr:full":"819 49th Ave NE Columbia Heights MN 55421",
    "addr:housenumber":"819",
    "addr:postcode":"55421",
    "addr:street":"49Th Ave Ne;Heights",
    "iso:country":"US",
    "sg:address":"819 49th Ave NE",
    "sg:city":"Columbia Heights",
    "sg:classifiers":[
        {
            "category":"Wholesale",
            "subcategory":"Machinery & Supplies",
            "type":"Manufacturing & Wholesale Goods"
        }
    ],
    "sg:phone":"+1 763 571 4437",
    "sg:postcode":"55421",
    "sg:province":"MN",
    "sg:tags":[
        "machine",
        "knitting"
    ],
    "wof:name":"Daisy Knits & Machines",
    "wof:placetype":"venue"
},
  "geometry": {"coordinates":[-93.24990099999999,45.057273],"type":"Point"}
}