{
  "type": "Feature",
  "properties": {
    "iso:country":"US",
    "sg:address":"13180 Glenhurst Ave",
    "sg:city":"Savage",
    "sg:classifiers":[
        {
            "category":"Real Estate",
            "subcategory":"Real Estate Operator",
            "type":"Services"
        }
    ],
    "sg:phone":"+1 952 895 0555",
    "sg:postcode":"55378",
    "sg:province":"MN",
    "sg:tags":[
        "building",
        "nonresidential"
    ],
    "wof:name":"Moss Property LLC",
    "wof:placetype":"venue"
},
  "geometry": {"coordinates":[-93.329393,44.763875],"type":"Point"}
}