{
  "type": "Feature",
  "properties": {
    "addr:full":"726 Main St Wabasso MN 56293",
    "addr:housenumber":"726",
    "addr:postcode":"56293",
    "addr:street":"Main St",
    "iso:country":"US",
    "sg:address":"726 Main St",
    "sg:city":"Wabasso",
    "sg:classifiers":[
        {
            "category":"Insurance",
            "subcategory":"Insurance Agent",
            "type":"Services"
        }
    ],
    "sg:phone":"+1 507 342 5112",
    "sg:postcode":"56293",
    "sg:province":"MN",
    "wof:name":"Wabasso State Agency Inc",
    "wof:placetype":"venue"
},
  "geometry": {"coordinates":[-95.25653699999999,44.40193],"type":"Point"}
}