{
  "type": "Feature",
  "properties": {
    "addr:full":"23260 Co Rd 10 Rogers MN 55374",
    "addr:housenumber":"23260;10",
    "addr:postcode":"55374",
    "addr:street":"Co Rd",
    "iso:country":"US",
    "sg:address":"23260 Co Rd 10",
    "sg:city":"Rogers",
    "sg:classifiers":[
        {
            "category":"Building & Trades",
            "subcategory":"Landscaping Services",
            "type":"Services"
        }
    ],
    "sg:phone":"+1 763 498 6546",
    "sg:postcode":"55374",
    "sg:province":"MN",
    "wof:name":"Complete Lawn Salon",
    "wof:placetype":"venue"
},
  "geometry": {"coordinates":[-93.63056899999999,45.123631],"type":"Point"}
}