{
  "type": "Feature",
  "properties": {
    "addr:full":"1107 Lochmist Ln NW Alexandria MN 56308",
    "addr:housenumber":"1107",
    "addr:postcode":"56308",
    "addr:street":"Lochmist Ln Nw",
    "iso:country":"US",
    "sg:address":"1107 Lochmist Ln NW",
    "sg:city":"Alexandria",
    "sg:classifiers":[
        {
            "category":"Professional",
            "subcategory":"Detective & Security Services",
            "type":"Services"
        }
    ],
    "sg:phone":"+1 320 763 4599",
    "sg:postcode":"56308",
    "sg:province":"MN",
    "sg:tags":[
        "information",
        "bureau"
    ],
    "wof:name":"Living Services Progressive",
    "wof:placetype":"venue"
},
  "geometry": {"coordinates":[-95.396095,45.904631],"type":"Point"}
}