{
  "type": "Feature",
  "properties": {
    "iso:country":"US",
    "sg:address":"2199 State Hwy 36 E",
    "sg:city":"Saint Paul",
    "sg:classifiers":[
        {
            "category":"Shopping",
            "subcategory":"Department Store",
            "type":"Retail Goods"
        }
    ],
    "sg:phone":"+1 651 770 1351",
    "sg:postcode":"55109",
    "sg:province":"MN",
    "wof:name":"Target 23",
    "wof:placetype":"venue"
},
  "geometry": {"coordinates":[-93.01251499999999,45.012091],"type":"Point"}
}