{
  "type": "Feature",
  "properties": {
    "addr:full":"910 Cloquet Ave Cloquet MN 55720",
    "addr:housenumber":"910",
    "addr:postcode":"55720",
    "addr:street":"Cloquet Ave",
    "iso:country":"US",
    "sg:address":"910 Cloquet Ave",
    "sg:city":"Cloquet",
    "sg:classifiers":[
        {
            "category":"Utilities",
            "subcategory":"Natural Gas",
            "type":"Services"
        }
    ],
    "sg:phone":"+1 218 879 1571",
    "sg:postcode":"55720",
    "sg:province":"MN",
    "sg:tags":[
        "distribution"
    ],
    "wof:name":"Aquila Networks",
    "wof:placetype":"venue"
},
  "geometry": {"coordinates":[-92.45456799999999,46.721565],"type":"Point"}
}