{
  "type": "Feature",
  "properties": {
    "iso:country":"US",
    "sg:address":"3 Minnesota Ave E",
    "sg:city":"Glenwood",
    "sg:classifiers":[
        {
            "category":"Shopping",
            "subcategory":"Pharmacy",
            "type":"Retail Goods"
        }
    ],
    "sg:phone":"+1 320 634 4434",
    "sg:postcode":"56334",
    "sg:province":"MN",
    "wof:name":"Corner Drug Store",
    "wof:placetype":"venue"
},
  "geometry": {"coordinates":[-95.390005,45.650305],"type":"Point"}
}