{
  "type": "Feature",
  "properties": {
    "iso:country":"US",
    "sg:address":"1111 Washington Ave S",
    "sg:city":"Minneapolis",
    "sg:classifiers":[
        {
            "category":"Shopping",
            "subcategory":"Music",
            "type":"Retail Goods"
        }
    ],
    "sg:phone":"+1 612 781 6120",
    "sg:postcode":"55415",
    "sg:province":"MN",
    "sg:tags":[
        "dvd's"
    ],
    "wof:name":"Amrep",
    "wof:placetype":"venue"
},
  "geometry": {"coordinates":[-93.25306399999999,44.975274],"type":"Point"}
}