{
  "type": "Feature",
  "properties": {
    "addr:full":"27303 Quinlan Ave Lindstrom MN 55045",
    "addr:housenumber":"27303",
    "addr:postcode":"55045",
    "addr:street":"Quinlan Ave",
    "iso:country":"US",
    "sg:address":"27303 Quinlan Ave",
    "sg:city":"Lindstrom",
    "sg:classifiers":[
        {
            "category":"Building & Trades",
            "subcategory":"Construction",
            "type":"Services"
        }
    ],
    "sg:phone":"+1 651 257 9370",
    "sg:postcode":"55045",
    "sg:province":"MN",
    "sg:tags":[
        "house"
    ],
    "wof:name":"Elite Custom Builders Inc",
    "wof:placetype":"venue"
},
  "geometry": {"coordinates":[-92.77394700000001,45.345958],"type":"Point"}
}