{
  "type": "Feature",
  "properties": {
    "iso:country":"US",
    "sg:address":"10881 Le Sueur Ave",
    "sg:city":"Montgomery",
    "sg:classifiers":[
        {
            "category":"Retail",
            "subcategory":"Auto Repair",
            "type":"Services"
        }
    ],
    "sg:phone":"+1 507 364 5527",
    "sg:postcode":"56069",
    "sg:province":"MN",
    "sg:tags":[
        "body",
        "general"
    ],
    "wof:name":"Tony Service",
    "wof:placetype":"venue"
},
  "geometry": {"coordinates":[-93.52453199999999,44.428573],"type":"Point"}
}