{
  "type": "Feature",
  "properties": {
    "iso:country":"US",
    "sg:address":"7801 Southtown Ctr",
    "sg:city":"Minneapolis",
    "sg:classifiers":[
        {
            "category":"Food Court",
            "type":"Food & Drink"
        },
        {
            "category":"Restaurant",
            "type":"Food & Drink"
        },
        {
            "category":"Bagels",
            "subcategory":"None",
            "type":"Food & Drink"
        },
        {
            "category":"Coffee & Tea",
            "type":"Food & Drink"
        },
        {
            "category":"Bakery",
            "type":"Food & Drink"
        },
        {
            "category":"Food & Beverages",
            "subcategory":"Groceries & Convenience Stores",
            "type":"Retail Goods"
        }
    ],
    "sg:phone":"+1 952 703 0443",
    "sg:postcode":"55431",
    "sg:province":"MN",
    "sg:tags":[
        "shop",
        "box",
        "sandwich",
        "espresso",
        "lunch",
        "brunch",
        "breakfast"
    ],
    "sg:website":"http://www.brueggers.com",
    "wof:name":"Bruegger's",
    "wof:placetype":"venue"
},
  "geometry": {"coordinates":[-93.301804,44.861435],"type":"Point"}
}