{
  "type": "Feature",
  "properties": {
    "iso:country":"US",
    "sg:address":"5149 29th Ave S",
    "sg:city":"Minneapolis",
    "sg:classifiers":[
        {
            "category":"Food & Beverages",
            "subcategory":"Specialty",
            "type":"Retail Goods"
        }
    ],
    "sg:phone":"+1 612 824 8695",
    "sg:postcode":"55417",
    "sg:province":"MN",
    "sg:tags":[
        "tea",
        "coffee"
    ],
    "wof:name":"Nokomis Cup",
    "wof:placetype":"venue"
},
  "geometry": {"coordinates":[-93.23087200000001,44.909854],"type":"Point"}
}