{
  "type": "Feature",
  "properties": {
    "addr:full":"4333 W 280th St New Prague MN 56071",
    "addr:housenumber":"4333",
    "addr:postcode":"56071",
    "addr:street":"W 280Th St",
    "iso:country":"US",
    "sg:address":"4333 W 280th St",
    "sg:city":"New Prague",
    "sg:classifiers":[
        {
            "category":"Farming",
            "subcategory":"Livestock Farm",
            "type":"Manufacturing & Wholesale Goods"
        }
    ],
    "sg:phone":"+1 952 758 6380",
    "sg:postcode":"56071",
    "sg:province":"MN",
    "sg:tags":[
        "hog",
        "or",
        "feedlot"
    ],
    "wof:name":"Phil Meyer",
    "wof:placetype":"venue"
},
  "geometry": {"coordinates":[-93.61208600000001,44.543829],"type":"Point"}
}