{
  "type": "Feature",
  "properties": {
    "addr:full":"24812 Ulysses Ct NE Isanti MN 55040",
    "addr:postcode":"24812;55040",
    "addr:street":"Ulysses Ct Ne",
    "iso:country":"US",
    "sg:address":"24812 Ulysses Ct NE",
    "sg:city":"Isanti",
    "sg:classifiers":[
        {
            "category":"Manufacturing",
            "subcategory":"Metals",
            "type":"Manufacturing & Wholesale Goods"
        }
    ],
    "sg:phone":"+1 763 444 4386",
    "sg:postcode":"55040",
    "sg:province":"MN",
    "sg:tags":[
        "hardware",
        "mfg",
        "industrial",
        "supply"
    ],
    "wof:name":"Clinch Fast Inc",
    "wof:placetype":"venue"
},
  "geometry": {"coordinates":[-93.236132,45.419754],"type":"Point"}
}