{
  "type": "Feature",
  "properties": {
    "addr:full":"6596 Emerson Ave SW Waverly MN 55390",
    "addr:housenumber":"6596",
    "addr:postcode":"55390",
    "addr:street":"Emerson Ave Sw",
    "iso:country":"US",
    "sg:address":"6596 Emerson Ave SW",
    "sg:city":"Waverly",
    "sg:classifiers":[
        {
            "category":"Manufacturing",
            "subcategory":"Furniture",
            "type":"Manufacturing & Wholesale Goods"
        }
    ],
    "sg:phone":"+1 763 658 4814",
    "sg:postcode":"55390",
    "sg:province":"MN",
    "sg:tags":[
        "mfg",
        "household",
        "wood",
        "nonresidential"
    ],
    "wof:name":"Waverly Woodcraft",
    "wof:placetype":"venue"
},
  "geometry": {"coordinates":[-93.982179,45.056759],"type":"Point"}
}