{
  "type": "Feature",
  "properties": {
    "iso:country":"US",
    "sg:address":"19421 Northfield Blvd",
    "sg:city":"Hastings",
    "sg:classifiers":[
        {
            "category":"Manufacturing",
            "subcategory":"Tools & Machinery",
            "type":"Manufacturing & Wholesale Goods"
        }
    ],
    "sg:phone":"+1 651 437 2423",
    "sg:postcode":"55033",
    "sg:province":"MN",
    "sg:tags":[
        "packaging",
        "mfg"
    ],
    "sg:website":"www.rothermachine.com",
    "wof:name":"Rother Machine Shop Inc",
    "wof:placetype":"venue"
},
  "geometry": {"coordinates":[-92.92941999999999,44.672535],"type":"Point"}
}