{
  "type": "Feature",
  "properties": {
    "addr:full":"42492 270th Ave NW Strandquist MN 56758",
    "addr:housenumber":"42492",
    "addr:postcode":"56758",
    "addr:street":"270Th Ave Nw Strandquist",
    "iso:country":"US",
    "sg:address":"42492 270th Ave NW",
    "sg:city":"Strandquist",
    "sg:classifiers":[
        {
            "category":"Manufacturing",
            "subcategory":"Food",
            "type":"Manufacturing & Wholesale Goods"
        },
        {
            "category":"Farming",
            "subcategory":"Farm",
            "type":"Manufacturing & Wholesale Goods"
        }
    ],
    "sg:phone":"+1 218 478 3572",
    "sg:postcode":"56758",
    "sg:province":"MN",
    "sg:tags":[
        "corn",
        "product"
    ],
    "wof:name":"Ludwig Stusynski",
    "wof:placetype":"venue"
},
  "geometry": {"coordinates":[-96.627566,48.489802],"type":"Point"}
}