{
  "type": "Feature",
  "properties": {
    "addr:full":"7013 Ximines Ln N Osseo MN 55369",
    "addr:housenumber":"7013",
    "addr:postcode":"55369",
    "addr:street":"Ximines Ln N",
    "iso:country":"US",
    "sg:address":"7013 Ximines Ln N",
    "sg:city":"Osseo",
    "sg:classifiers":[
        {
            "category":"Professional",
            "subcategory":"Employment Agencies",
            "type":"Services"
        }
    ],
    "sg:phone":"+1 763 424 7170",
    "sg:postcode":"55369",
    "sg:province":"MN",
    "sg:tags":[
        "recruiter"
    ],
    "wof:name":"JFK Search",
    "wof:placetype":"venue"
},
  "geometry": {"coordinates":[-93.418554,45.081947],"type":"Point"}
}