{
  "type": "Feature",
  "properties": {
    "iso:country":"US",
    "sg:address":"7013 Ximines Ln N",
    "sg:city":"Osseo",
    "sg:classifiers":[
        {
            "category":"Professional",
            "subcategory":"Employment Agencies",
            "type":"Services"
        }
    ],
    "sg:phone":"+1 763 424 7170",
    "sg:postcode":"55369",
    "sg:province":"MN",
    "sg:tags":[
        "recruiter"
    ],
    "wof:name":"JFK Search",
    "wof:placetype":"venue"
},
  "geometry": {"coordinates":[-93.418554,45.081947],"type":"Point"}
}