{
  "type": "Feature",
  "properties": {
    "addr:full":"1500 Hwy 36 W Roseville MN 55113",
    "addr:housenumber":"1500",
    "addr:postcode":"55113",
    "addr:street":"Hwy 36 W",
    "iso:country":"US",
    "sg:address":"1500 Hwy 36 W",
    "sg:city":"Roseville",
    "sg:classifiers":[
        {
            "category":"Government",
            "subcategory":"Office",
            "type":"Public Place"
        }
    ],
    "sg:phone":"+1 651 582 8833",
    "sg:postcode":"55113",
    "sg:province":"MN",
    "wof:name":"Teaching Board",
    "wof:placetype":"venue"
},
  "geometry": {"coordinates":[-93.165588,45.010291],"type":"Point"}
}