{
  "type": "Feature",
  "properties": {
    "addr:full":"4550 Johnny Cake Ridge Rd Eagan MN 55122",
    "addr:housenumber":"4550",
    "addr:postcode":"55122",
    "addr:street":"Johnny Cake Ridge Rd",
    "iso:country":"US",
    "sg:address":"4550 Johnny Cake Ridge Rd",
    "sg:city":"Eagan",
    "sg:classifiers":[
        {
            "category":"Professional",
            "subcategory":"Business Services",
            "type":"Services"
        },
        {
            "category":"Real Estate",
            "subcategory":"Real Estate Agent",
            "type":"Services"
        }
    ],
    "sg:phone":"+1 651 365 8687",
    "sg:postcode":"55122",
    "sg:province":"MN",
    "sg:tags":[
        "home",
        "inspector",
        "inspection"
    ],
    "wof:name":"Protection Plus Home Inspections",
    "wof:placetype":"venue"
},
  "geometry": {"coordinates":[-93.186589,44.791867],"type":"Point"}
}