{
  "type": "Feature",
  "properties": {
    "addr:full":"2908 340th Ave Hinckley MN 55037",
    "addr:housenumber":"2908",
    "addr:postcode":"55037",
    "addr:street":"340Th Ave",
    "iso:country":"US",
    "sg:address":"2908 340th Ave",
    "sg:city":"Hinckley",
    "sg:classifiers":[
        {
            "category":"Building & Trades",
            "subcategory":"Construction",
            "type":"Services"
        }
    ],
    "sg:phone":"+1 320 384 6035",
    "sg:postcode":"55037",
    "sg:province":"MN",
    "sg:tags":[
        "carpentry",
        "contractor"
    ],
    "wof:name":"Thomas J Linder",
    "wof:placetype":"venue"
},
  "geometry": {"coordinates":[-93.128676,46.0861],"type":"Point"}
}