{
  "type": "Feature",
  "properties": {
    "addr:full":"419 N Wheeler St Saint Paul MN 55104",
    "addr:housenumber":"419",
    "addr:postcode":"55104",
    "addr:street":"N Wheeler St",
    "iso:country":"US",
    "sg:address":"419 N Wheeler St",
    "sg:city":"Saint Paul",
    "sg:classifiers":[
        {
            "category":"Retail",
            "subcategory":"Auto Repair",
            "type":"Services"
        }
    ],
    "sg:phone":"+1 651 603 0755",
    "sg:postcode":"55104",
    "sg:province":"MN",
    "sg:tags":[
        "general"
    ],
    "wof:name":"All Automotive Repair Inc",
    "wof:placetype":"venue"
},
  "geometry": {"coordinates":[-93.174712,44.952499],"type":"Point"}
}