{
  "type": "Feature",
  "properties": {
    "addr:full":"17689 Ames Trl Faribault MN 55021",
    "addr:housenumber":"17689",
    "addr:postcode":"55021",
    "addr:street":"Ames Trl",
    "iso:country":"US",
    "sg:address":"17689 Ames Trl",
    "sg:city":"Faribault",
    "sg:classifiers":[
        {
            "category":"Farming",
            "subcategory":"Farm",
            "type":"Manufacturing & Wholesale Goods"
        }
    ],
    "sg:phone":"+1 507 334 8818",
    "sg:postcode":"55021",
    "sg:province":"MN",
    "sg:tags":[
        "crop",
        "general"
    ],
    "wof:name":"Louade Degen",
    "wof:placetype":"venue"
},
  "geometry": {"coordinates":[-93.26348,44.328288],"type":"Point"}
}