{
  "type": "Feature",
  "properties": {
    "addr:full":"303 21st St Newport MN 55055",
    "addr:housenumber":"303",
    "addr:postcode":"55055",
    "addr:street":"21St St",
    "iso:country":"US",
    "sg:address":"303 21st St",
    "sg:city":"Newport",
    "sg:classifiers":[
        {
            "category":"Government",
            "subcategory":"Post Office",
            "type":"Public Place"
        }
    ],
    "sg:phone":"+1 651 768 0558",
    "sg:postcode":"55055",
    "sg:province":"MN",
    "wof:name":"US Post Office",
    "wof:placetype":"venue"
},
  "geometry": {"coordinates":[-93.00519,44.880034],"type":"Point"}
}