{
  "type": "Feature",
  "properties": {
    "addr:full":"3 Appletree Sq Minneapolis MN 55425",
    "addr:housenumber":"3",
    "addr:postcode":"55425",
    "addr:street":"Appletree Sq",
    "iso:country":"US",
    "sg:address":"3 Appletree Sq",
    "sg:city":"Minneapolis",
    "sg:classifiers":[
        {
            "category":"Travel",
            "subcategory":"Hotels & Motels",
            "type":"Entertainment"
        },
        {
            "category":"Retail",
            "subcategory":"Event Space",
            "type":"Services"
        },
        {
            "category":"Travel",
            "subcategory":"Resort",
            "type":"Entertainment"
        }
    ],
    "sg:phone":"+1 800 345 8082",
    "sg:postcode":"55425",
    "sg:province":"MN",
    "sg:tags":[
        "hall",
        "lodging",
        "banquet",
        "reception",
        "facility"
    ],
    "sg:website":"http://ad.doubleclick.net/clk;223371278;47096201;d?http://www.holidayinn.com/redirect?path=hd&brandCode=hi&hotelCode=mspia&_PMID=99601036&cm_mmc=mdpr-_-yellowpages-_-hi-_-mspia",
    "wof:name":"Holiday Inn Hotel & Suites Mpls Intl Arpt-Mall Of America",
    "wof:placetype":"venue"
},
  "geometry": {"coordinates":[-93.221283,44.857151],"type":"Point"}
}