{
  "type": "Feature",
  "properties": {
    "addr:full":"3151 Hennepin Ave S Minneapolis MN 55408",
    "addr:housenumber":"3151",
    "addr:postcode":"55408",
    "addr:street":"Hennepin Ave S",
    "iso:country":"US",
    "sg:address":"3151 Hennepin Ave S",
    "sg:city":"Minneapolis",
    "sg:classifiers":[
        {
            "category":"Shopping",
            "subcategory":"Books",
            "type":"Retail Goods"
        }
    ],
    "sg:phone":"+1 612 822 2309",
    "sg:postcode":"55408",
    "sg:province":"MN",
    "sg:tags":[
        "comic"
    ],
    "wof:name":"College Comic Book Knowledge",
    "wof:placetype":"venue"
},
  "geometry": {"coordinates":[-93.298236,44.945651],"type":"Point"}
}