{
  "type": "Feature",
  "properties": {
    "addr:full":"6957 US Hwy 10 Ramsey MN 55303",
    "addr:housenumber":"6957",
    "addr:postcode":"55303",
    "addr:street":"Us Hwy 10",
    "iso:country":"US",
    "sg:address":"6957 US Hwy 10",
    "sg:city":"Ramsey",
    "sg:classifiers":[
        {
            "category":"Professional",
            "subcategory":"Accounting & Tax Preparation",
            "type":"Services"
        }
    ],
    "sg:phone":"+1 763 427 4511",
    "sg:postcode":"55303",
    "sg:province":"MN",
    "sg:tags":[
        "bookkeeping",
        "general"
    ],
    "wof:name":"Bookeeping Accounting Svc Sta",
    "wof:placetype":"venue"
},
  "geometry": {"coordinates":[-93.442162,45.224514],"type":"Point"}
}