{
  "type": "Feature",
  "properties": {
    "iso:country":"US",
    "sg:address":"12940 Old Brick Yard Rd",
    "sg:city":"Shakopee",
    "sg:classifiers":[
        {
            "category":"Professional",
            "type":"Services"
        }
    ],
    "sg:phone":"+1 952 402 0418",
    "sg:postcode":"55379",
    "sg:province":"MN",
    "wof:name":"Minnesota Automated Med Entp",
    "wof:placetype":"venue"
},
  "geometry": {"coordinates":[-93.561255,44.762518],"type":"Point"}
}