{
  "type": "Feature",
  "properties": {
    "iso:country":"US",
    "sg:address":"4301 Highway 7 Ste 100",
    "sg:city":"Minneapolis",
    "sg:classifiers":[
        {
            "category":"Building & Trades",
            "subcategory":"Construction",
            "type":"Services"
        }
    ],
    "sg:phone":"+1 952 920 8555",
    "sg:postcode":"55416",
    "sg:province":"MN",
    "sg:tags":[
        "manufactured",
        "housing-communities"
    ],
    "wof:name":"Capital Housing Corp",
    "wof:placetype":"venue"
},
  "geometry": {"coordinates":[-93.33395400000001,44.947151],"type":"Point"}
}