{
  "type": "Feature",
  "properties": {
    "iso:country":"US",
    "sg:address":"234 Main St N",
    "sg:city":"Cambridge",
    "sg:classifiers":[
        {
            "category":"Autos & Motor Vehicles",
            "subcategory":"Auto Supplies",
            "type":"Retail Goods"
        },
        {
            "category":"Wholesale",
            "subcategory":"Electrical",
            "type":"Manufacturing & Wholesale Goods"
        },
        {
            "category":"Wholesale",
            "subcategory":"Auto Parts",
            "type":"Manufacturing & Wholesale Goods"
        }
    ],
    "sg:phone":"+1 763 689 3670",
    "sg:postcode":"55008",
    "sg:province":"MN",
    "sg:tags":[
        "body",
        "battery",
        "automobile",
        "accessory",
        "equipment",
        "truck"
    ],
    "sg:website":"http://www.oreillyauto.com?utm_source=yellowpages&utm_medium=iyp&utm_campaign=3295",
    "wof:name":"O'Reilly Auto Parts",
    "wof:placetype":"venue"
},
  "geometry": {"coordinates":[-93.224144,45.574001],"type":"Point"}
}