{
  "type": "Feature",
  "properties": {
    "iso:country":"US",
    "sg:address":"13169 Arcadia Ct NE",
    "sg:city":"Bemidji",
    "sg:classifiers":[
        {
            "category":"Manufacturing",
            "subcategory":"Paper Products",
            "type":"Manufacturing & Wholesale Goods"
        }
    ],
    "sg:phone":"+1 218 243 3354",
    "sg:postcode":"56601",
    "sg:province":"MN",
    "sg:tags":[
        "mfg"
    ],
    "wof:name":"International Paper",
    "wof:placetype":"venue"
},
  "geometry": {"coordinates":[-94.85272999999999,47.598292],"type":"Point"}
}