{
  "type": "Feature",
  "properties": {
    "addr:full":"319 SW 3rd Ave Grand Rapids MN 55744",
    "addr:housenumber":"319",
    "addr:postcode":"55744",
    "addr:street":"Sw 3Rd Ave",
    "iso:country":"US",
    "sg:address":"319 SW 3rd Ave",
    "sg:city":"Grand Rapids",
    "sg:classifiers":[
        {
            "category":"Shopping",
            "subcategory":"Musical Instruments",
            "type":"Retail Goods"
        }
    ],
    "sg:phone":"+1 218 326 3156",
    "sg:postcode":"55744",
    "sg:province":"MN",
    "sg:tags":[
        "dry",
        "plant",
        "cleaning"
    ],
    "wof:name":"Arrowhead Dry Cleaners",
    "wof:placetype":"venue"
},
  "geometry": {"coordinates":[-93.532639,47.228141],"type":"Point"}
}