{
  "type": "Feature",
  "properties": {
    "addr:full":"10050 Powers Lake Cir Saint Paul MN 55129",
    "addr:housenumber":"10050",
    "addr:postcode":"55129",
    "addr:street":"Powers Lake Cir",
    "iso:country":"US",
    "sg:address":"10050 Powers Lake Cir",
    "sg:city":"Saint Paul",
    "sg:classifiers":[
        {
            "category":"Manufacturing",
            "subcategory":"Printing",
            "type":"Manufacturing & Wholesale Goods"
        }
    ],
    "sg:phone":"+1 651 578 1581",
    "sg:postcode":"55129",
    "sg:province":"MN",
    "sg:tags":[
        "publishing"
    ],
    "wof:name":"Resurrection Resources",
    "wof:placetype":"venue"
},
  "geometry": {"coordinates":[-92.902112,44.925193],"type":"Point"}
}