{
  "type": "Feature",
  "properties": {
    "iso:country":"US",
    "sg:address":"216 E Main St",
    "sg:city":"Albert Lea",
    "sg:classifiers":[
        {
            "category":"Personal",
            "subcategory":"Beauty Salon",
            "type":"Services"
        }
    ],
    "sg:phone":"+1 507 377 2059",
    "sg:postcode":"56007",
    "sg:province":"MN",
    "wof:name":"Beauty & Body Works Studio",
    "wof:placetype":"venue"
},
  "geometry": {"coordinates":[-93.36618900000001,43.647761],"type":"Point"}
}