{
  "type": "Feature",
  "properties": {
    "addr:full":"6550 E River Rd Minneapolis MN 55432",
    "addr:housenumber":"6550",
    "addr:postcode":"55432",
    "addr:street":"E River Rd",
    "iso:country":"US",
    "sg:address":"6550 E River Rd",
    "sg:city":"Minneapolis",
    "sg:classifiers":[
        {
            "category":"Professional",
            "subcategory":"Employment Agencies",
            "type":"Services"
        }
    ],
    "sg:phone":"+1 763 572 9509",
    "sg:postcode":"55432",
    "sg:province":"MN",
    "sg:tags":[
        "repair",
        "help",
        "supply"
    ],
    "wof:name":"Groves Steve",
    "wof:placetype":"venue"
},
  "geometry": {"coordinates":[-93.27530400000001,45.086734],"type":"Point"}
}