{
  "type": "Feature",
  "properties": {
    "iso:country":"US",
    "sg:address":"380 Beltrami Ln SW",
    "sg:city":"Kelliher",
    "sg:classifiers":[
        {
            "category":"Real Estate",
            "subcategory":"Real Estate Operator",
            "type":"Services"
        }
    ],
    "sg:phone":"+1 218 647 8886",
    "sg:postcode":"56650",
    "sg:province":"MN",
    "sg:tags":[
        "apartment"
    ],
    "wof:name":"Kelliher Apartments Manager",
    "wof:placetype":"venue"
},
  "geometry": {"coordinates":[-94.453425,47.940001],"type":"Point"}
}