{
  "type": "Feature",
  "properties": {
    "iso:country":"US",
    "sg:address":"702 NW 4th St",
    "sg:city":"Grand Rapids",
    "sg:classifiers":[
        {
            "category":"Food & Beverages",
            "subcategory":"Liquor & Beverages",
            "type":"Retail Goods"
        }
    ],
    "sg:phone":"+1 218 326 9119",
    "sg:postcode":"55744",
    "sg:province":"MN",
    "wof:name":"Madden's Off Sale Liquor",
    "wof:placetype":"venue"
},
  "geometry": {"coordinates":[-93.53894099999999,47.235864],"type":"Point"}
}