{
  "type": "Feature",
  "properties": {
    "addr:full":"830 W Prairie St Le Center MN 56057",
    "addr:housenumber":"830",
    "addr:postcode":"56057",
    "addr:street":"W Prairie St",
    "iso:country":"US",
    "sg:address":"830 W Prairie St",
    "sg:city":"Le Center",
    "sg:classifiers":[
        {
            "category":"Building & Trades",
            "subcategory":"Construction",
            "type":"Services"
        }
    ],
    "sg:phone":"+1 507 357 4021",
    "sg:postcode":"56057",
    "sg:province":"MN",
    "sg:tags":[
        "painter"
    ],
    "wof:name":"Anderson Painting",
    "wof:placetype":"venue"
},
  "geometry": {"coordinates":[-93.74546100000001,44.398924],"type":"Point"}
}