{
  "type": "Feature",
  "properties": {
    "addr:full":"6707 113th Ave NE Spicer MN 56288",
    "addr:housenumber":"6707",
    "addr:postcode":"56288",
    "addr:street":"113Th Ave Ne",
    "iso:country":"US",
    "sg:address":"6707 113th Ave NE",
    "sg:city":"Spicer",
    "sg:classifiers":[
        {
            "category":"Home & Garden",
            "subcategory":"Furniture",
            "type":"Retail Goods"
        }
    ],
    "sg:phone":"+1 320 222 6673",
    "sg:postcode":"56288",
    "sg:province":"MN",
    "wof:name":"GRS Furniture & More",
    "wof:placetype":"venue"
},
  "geometry": {"coordinates":[-94.95184399999999,45.232886],"type":"Point"}
}