{
  "type": "Feature",
  "properties": {
    "iso:country":"US",
    "sg:address":"1619 Wilshire Ct NE",
    "sg:city":"Rochester",
    "sg:classifiers":[
        {
            "category":"Professional",
            "subcategory":"Business Services",
            "type":"Services"
        }
    ],
    "sg:phone":"+1 507 289 6233",
    "sg:postcode":"55906",
    "sg:province":"MN",
    "wof:name":"Jl Interiors",
    "wof:placetype":"venue"
},
  "geometry": {"coordinates":[-92.441329,44.040307],"type":"Point"}
}