{
  "type": "Feature",
  "properties": {
    "iso:country":"US",
    "sg:address":"1275 County Road D E",
    "sg:city":"Saint Paul",
    "sg:classifiers":[
        {
            "category":"Restaurant",
            "type":"Food & Drink"
        }
    ],
    "sg:menulink":"http://www.allmenus.com/mn/vadnais-heights/151169-subway/menu/",
    "sg:phone":"+1 651 783 5873",
    "sg:postcode":"55109",
    "sg:province":"MN",
    "sg:tags":[
        "american",
        "sandwich"
    ],
    "wof:name":"Subway",
    "wof:placetype":"venue"
},
  "geometry": {"coordinates":[-93.047195,45.036018],"type":"Point"}
}