{
  "type": "Feature",
  "properties": {
    "addr:full":"2831 S Coon Creek Dr NW Anoka MN 55304",
    "addr:housenumber":"2831",
    "addr:postcode":"55304",
    "addr:street":"S Coon Creek Dr Nw",
    "iso:country":"US",
    "sg:address":"2831 S Coon Creek Dr NW",
    "sg:city":"Anoka",
    "sg:classifiers":[
        {
            "category":"Retail",
            "subcategory":"Auto Repair",
            "type":"Services"
        }
    ],
    "sg:phone":"+1 763 422 4046",
    "sg:postcode":"55304",
    "sg:province":"MN",
    "sg:tags":[
        "general"
    ],
    "wof:name":"Precision Tune Auto Care",
    "wof:placetype":"venue"
},
  "geometry": {"coordinates":[-93.338598,45.234097],"type":"Point"}
}