{
  "type": "Feature",
  "properties": {
    "addr:full":"10503 SE 54th Ave Blooming Prairie MN 55917",
    "addr:housenumber":"10503",
    "addr:postcode":"55917",
    "addr:street":"Se 54Th Ave",
    "iso:country":"US",
    "sg:address":"10503 SE 54th Ave",
    "sg:city":"Blooming Prairie",
    "sg:classifiers":[
        {
            "category":"Farming",
            "subcategory":"Farm & Veterinary Services",
            "type":"Manufacturing & Wholesale Goods"
        }
    ],
    "sg:phone":"+1 507 583 7353",
    "sg:postcode":"55917",
    "sg:province":"MN",
    "sg:tags":[
        "livestock"
    ],
    "wof:name":"Tammy Larson",
    "wof:placetype":"venue"
},
  "geometry": {"coordinates":[-93.125793,43.937767],"type":"Point"}
}