{
  "type": "Feature",
  "properties": {
    "addr:full":"869 E Ivy Ave Saint Paul MN 55106",
    "addr:housenumber":"869",
    "addr:postcode":"55106",
    "addr:street":"E Ivy Ave",
    "iso:country":"US",
    "sg:address":"869 E Ivy Ave",
    "sg:city":"Saint Paul",
    "sg:classifiers":[
        {
            "category":"Social Services",
            "subcategory":"Child Care",
            "type":"Services"
        }
    ],
    "sg:phone":"+1 651 774 7526",
    "sg:postcode":"55106",
    "sg:province":"MN",
    "sg:tags":[
        "day"
    ],
    "wof:name":"Smiling Faces Stay/Ply Dy Care",
    "wof:placetype":"venue"
},
  "geometry": {"coordinates":[-93.06494000000001,44.981207],"type":"Point"}
}