{
  "type": "Feature",
  "properties": {
    "addr:full":"201 Jackson St Anoka MN 55303",
    "addr:housenumber":"201",
    "addr:postcode":"55303",
    "addr:street":"Jackson St",
    "iso:country":"US",
    "sg:address":"201 Jackson St",
    "sg:city":"Anoka",
    "sg:classifiers":[
        {
            "category":"Restaurant",
            "type":"Food & Drink"
        }
    ],
    "sg:phone":"+1 763 323 0020",
    "sg:postcode":"55303",
    "sg:province":"MN",
    "sg:tags":[
        "mexican"
    ],
    "wof:name":"Estebans Mexican Restauran",
    "wof:placetype":"venue"
},
  "geometry": {"coordinates":[-93.389363,45.198797],"type":"Point"}
}