{
  "type": "Feature",
  "properties": {
    "addr:full":"25406 Co Rd 51 Bovey MN 55709",
    "addr:housenumber":"25406;51",
    "addr:postcode":"55709",
    "addr:street":"Co Rd",
    "iso:country":"US",
    "sg:address":"25406 Co Rd 51",
    "sg:city":"Bovey",
    "sg:classifiers":[
        {
            "category":"Travel",
            "subcategory":"Hotels & Motels",
            "type":"Entertainment"
        }
    ],
    "sg:phone":"+1 218 245 3537",
    "sg:postcode":"55709",
    "sg:province":"MN",
    "sg:tags":[
        "operation"
    ],
    "wof:name":"Birch Haven Resort",
    "wof:placetype":"venue"
},
  "geometry": {"coordinates":[-93.391503,47.521877],"type":"Point"}
}