{
  "type": "Feature",
  "properties": {
    "addr:full":"9142 Fox Run Cir Eden Prairie MN 55347",
    "addr:housenumber":"9142",
    "addr:postcode":"55347",
    "addr:street":"Fox Run Cir",
    "iso:country":"US",
    "sg:address":"9142 Fox Run Cir",
    "sg:city":"Eden Prairie",
    "sg:classifiers":[
        {
            "category":"Professional",
            "subcategory":"Computer Services",
            "type":"Services"
        }
    ],
    "sg:phone":"+1 952 829 8008",
    "sg:postcode":"55347",
    "sg:province":"MN",
    "sg:tags":[
        "precious",
        "metal",
        "jewelry",
        "related",
        "mfg"
    ],
    "wof:name":"Xxxxx",
    "wof:placetype":"venue"
},
  "geometry": {"coordinates":[-93.411691,44.837481],"type":"Point"}
}