{
  "type": "Feature",
  "properties": {
    "iso:country":"US",
    "sg:address":"1700 University Ave W",
    "sg:city":"St Paul",
    "sg:classifiers":[
        {
            "category":"Health Services",
            "subcategory":"Doctor",
            "type":"Services"
        }
    ],
    "sg:phone":"+1 651 232 5348",
    "sg:postcode":"55104",
    "sg:province":"MN",
    "sg:tags":[
        "physician",
        "surgeon"
    ],
    "wof:name":"Healtheast Pain Care",
    "wof:placetype":"venue"
},
  "geometry": {"coordinates":[-93.17080799999999,44.955666],"type":"Point"}
}