{
  "type": "Feature",
  "properties": {
    "addr:full":"1829 E Superior St Duluth MN 55812",
    "addr:housenumber":"1829",
    "addr:postcode":"55812",
    "addr:street":"E Superior St",
    "iso:country":"US",
    "sg:address":"1829 E Superior St",
    "sg:city":"Duluth",
    "sg:classifiers":[
        {
            "category":"Social Services",
            "type":"Services"
        }
    ],
    "sg:phone":"+1 218 724 5958",
    "sg:postcode":"55812",
    "sg:province":"MN",
    "wof:name":"Choice Unlimited",
    "wof:placetype":"venue"
},
  "geometry": {"coordinates":[-92.074938,46.804817],"type":"Point"}
}