{
  "type": "Feature",
  "properties": {
    "iso:country":"US",
    "sg:address":"7751 US Hwy 10",
    "sg:city":"Anoka",
    "sg:classifiers":[
        {
            "category":"Autos & Motor Vehicles",
            "subcategory":"Recreational Vehicle Sales",
            "type":"Retail Goods"
        }
    ],
    "sg:phone":"+1 763 712 9244",
    "sg:postcode":"55303",
    "sg:province":"MN",
    "wof:name":"Majestic Rv Inc",
    "wof:placetype":"venue"
},
  "geometry": {"coordinates":[-93.46442500000001,45.23188],"type":"Point"}
}