{
  "type": "Feature",
  "properties": {
    "iso:country":"US",
    "sg:address":"2438 26th St",
    "sg:city":"Slayton",
    "sg:classifiers":[
        {
            "category":"Social Services",
            "type":"Services"
        }
    ],
    "sg:phone":"+1 507 836 6201",
    "sg:postcode":"56172",
    "sg:province":"MN",
    "sg:tags":[
        "organization",
        "welfare"
    ],
    "wof:name":"Southwest Minnesota Senior Fed",
    "wof:placetype":"venue"
},
  "geometry": {"coordinates":[-95.757295,43.987774],"type":"Point"}
}