{
  "type": "Feature",
  "properties": {
    "addr:full":"22814 Hwy 25 Pierz MN 56364",
    "addr:housenumber":"22814",
    "addr:postcode":"56364",
    "addr:street":"Hwy 25 Pierz",
    "iso:country":"US",
    "sg:address":"22814 Hwy 25",
    "sg:city":"Pierz",
    "sg:classifiers":[
        {
            "category":"Manufacturing",
            "subcategory":"Toys & Sporting Goods",
            "type":"Manufacturing & Wholesale Goods"
        }
    ],
    "sg:phone":"+1 320 468 6268",
    "sg:postcode":"56364",
    "sg:province":"MN",
    "sg:tags":[
        "mfg"
    ],
    "wof:name":"Litke Wholesale Live Bait",
    "wof:placetype":"venue"
},
  "geometry": {"coordinates":[-94.10341200000001,46.097911],"type":"Point"}
}