{
  "type": "Feature",
  "properties": {
    "addr:full":"1113 110th St Welcome MN 56181",
    "addr:housenumber":"1113",
    "addr:postcode":"56181",
    "addr:street":"110Th St",
    "iso:country":"US",
    "sg:address":"1113 110th St",
    "sg:city":"Welcome",
    "sg:classifiers":[
        {
            "category":"Manufacturing",
            "subcategory":"Food",
            "type":"Manufacturing & Wholesale Goods"
        },
        {
            "category":"Farming",
            "subcategory":"Farm",
            "type":"Manufacturing & Wholesale Goods"
        }
    ],
    "sg:phone":"+1 507 728 8292",
    "sg:postcode":"56181",
    "sg:province":"MN",
    "sg:tags":[
        "corn",
        "product"
    ],
    "wof:name":"Bruce Eisenmenger",
    "wof:placetype":"venue"
},
  "geometry": {"coordinates":[-94.653363,43.64541],"type":"Point"}
}