{
  "type": "Feature",
  "properties": {
    "addr:full":"18371 180th Ave New Ulm MN 56073",
    "addr:housenumber":"18371",
    "addr:postcode":"56073",
    "addr:street":"180Th Ave",
    "iso:country":"US",
    "sg:address":"18371 180th Ave",
    "sg:city":"New Ulm",
    "sg:phone":"+1 507 359 9712",
    "sg:postcode":"56073",
    "sg:province":"MN",
    "sg:tags":[
        "farm",
        "corn"
    ],
    "wof:name":"Myron Forstner",
    "wof:placetype":"venue"
},
  "geometry": {"coordinates":[-94.532774,44.225446],"type":"Point"}
}