{
  "type": "Feature",
  "properties": {
    "iso:country":"US",
    "sg:address":"1264 Easter Ln",
    "sg:city":"Saint Paul",
    "sg:classifiers":[
        {
            "category":"Professional",
            "subcategory":"Management & Consulting",
            "type":"Services"
        }
    ],
    "sg:phone":"+1 651 452 6113",
    "sg:postcode":"55123",
    "sg:province":"MN",
    "wof:name":"Ltl Enterprises",
    "wof:placetype":"venue"
},
  "geometry": {"coordinates":[-93.158434,44.803917],"type":"Point"}
}