{
  "type": "Feature",
  "properties": {
    "addr:full":"3326 Edward St NE Minneapolis MN 55418",
    "addr:housenumber":"3326",
    "addr:postcode":"55418",
    "addr:street":"Edward St Ne",
    "iso:country":"US",
    "sg:address":"3326 Edward St NE",
    "sg:city":"Minneapolis",
    "sg:classifiers":[
        {
            "category":"Professional",
            "subcategory":"Business Services",
            "type":"Services"
        }
    ],
    "sg:phone":"+1 612 788 2004",
    "sg:postcode":"55418",
    "sg:province":"MN",
    "wof:name":"Dickson & Assoc Inc",
    "wof:placetype":"venue"
},
  "geometry": {"coordinates":[-93.223742,45.029062],"type":"Point"}
}