{
  "type": "Feature",
  "properties": {
    "iso:country":"US",
    "sg:address":"413 N Prairie St",
    "sg:city":"Sherburn",
    "sg:classifiers":[
        {
            "category":"Shopping",
            "subcategory":"Gifts & Souvenirs",
            "type":"Retail Goods"
        }
    ],
    "sg:phone":"+1 507 764 2689",
    "sg:postcode":"56171",
    "sg:province":"MN",
    "sg:tags":[
        "greeting",
        "card"
    ],
    "wof:name":"Prairie St Cards",
    "wof:placetype":"venue"
},
  "geometry": {"coordinates":[-94.731133,43.656236],"type":"Point"}
}