{
  "type": "Feature",
  "properties": {
    "addr:full":"2023 260th Ave Mahnomen MN 56548",
    "addr:housenumber":"2023",
    "addr:postcode":"56548",
    "addr:street":"260Th Ave",
    "iso:country":"US",
    "sg:address":"2023 260th Ave",
    "sg:city":"Mahnomen",
    "sg:phone":"+1 218 935 5720",
    "sg:postcode":"56548",
    "sg:province":"MN",
    "sg:tags":[
        "farm",
        "wheat"
    ],
    "wof:name":"Eugene Timmer",
    "wof:placetype":"venue"
},
  "geometry": {"coordinates":[-96.64003200000001,47.382881],"type":"Point"}
}