{
  "type": "Feature",
  "properties": {
    "addr:full":"530 Dover St NE Fridley MN 55432",
    "addr:housenumber":"530",
    "addr:postcode":"55432",
    "addr:street":"Dover St Ne",
    "iso:country":"US",
    "sg:address":"530 Dover St NE",
    "sg:city":"Fridley",
    "sg:classifiers":[
        {
            "category":"Building & Trades",
            "subcategory":"Construction",
            "type":"Services"
        }
    ],
    "sg:phone":"+1 763 792 4999",
    "sg:postcode":"55432",
    "sg:province":"MN",
    "sg:tags":[
        "house",
        "contractor"
    ],
    "wof:name":"Time Wise Construction Inc",
    "wof:placetype":"venue"
},
  "geometry": {"coordinates":[-93.28563699999999,45.113642],"type":"Point"}
}