{
  "type": "Feature",
  "properties": {
    "addr:full":"37513 550th Ave New York Mills MN 56567",
    "addr:housenumber":"37513",
    "addr:postcode":"56567",
    "addr:street":"550Th Ave",
    "iso:country":"US",
    "sg:address":"37513 550th Ave",
    "sg:city":"New York Mills",
    "sg:classifiers":[
        {
            "category":"Building & Trades",
            "subcategory":"Plumbing",
            "type":"Services"
        }
    ],
    "sg:phone":"+1 218 385 2087",
    "sg:postcode":"56567",
    "sg:province":"MN",
    "sg:tags":[
        "electrical",
        "contractor"
    ],
    "wof:name":"Electric Plus",
    "wof:placetype":"venue"
},
  "geometry": {"coordinates":[-95.342961,46.508127],"type":"Point"}
}