{
  "type": "Feature",
  "properties": {
    "iso:country":"US",
    "sg:address":"2487 7th Ave E",
    "sg:city":"Saint Paul",
    "sg:classifiers":[
        {
            "category":"Arts & Performance",
            "subcategory":"Theater",
            "type":"Entertainment"
        }
    ],
    "sg:phone":"+1 651 770 7518",
    "sg:postcode":"55109",
    "sg:province":"MN",
    "sg:tags":[
        "group"
    ],
    "wof:name":"MN Finest Dj Service",
    "wof:placetype":"venue"
},
  "geometry": {"coordinates":[-92.996032,45.009941],"type":"Point"}
}