{
  "type": "Feature",
  "properties": {
    "iso:country":"US",
    "sg:address":"41372 Little Clara Dr",
    "sg:city":"Deer River",
    "sg:classifiers":[
        {
            "category":"Building & Trades",
            "subcategory":"Construction",
            "type":"Services"
        }
    ],
    "sg:phone":"+1 218 246 2926",
    "sg:postcode":"56636",
    "sg:province":"MN",
    "sg:tags":[
        "residential"
    ],
    "wof:name":"Stromberg Construction",
    "wof:placetype":"venue"
},
  "geometry": {"coordinates":[-93.73981000000001,47.386114],"type":"Point"}
}