{
  "type": "Feature",
  "properties": {
    "iso:country":"US",
    "sg:address":"20152 Kenrick Ave",
    "sg:city":"Lakeville",
    "sg:classifiers":[
        {
            "category":"Personal",
            "type":"Services"
        },
        {
            "category":"Retail",
            "subcategory":"Auto Repair",
            "type":"Services"
        }
    ],
    "sg:phone":"+1 952 469 3182",
    "sg:postcode":"55044",
    "sg:province":"MN",
    "sg:tags":[
        "towing"
    ],
    "wof:name":"Marek's Towing & Repair Inc",
    "wof:placetype":"venue"
},
  "geometry": {"coordinates":[-93.29344,44.657839],"type":"Point"}
}