{
  "type": "Feature",
  "properties": {
    "iso:country":"US",
    "sg:address":"11424 Jay St NW",
    "sg:city":"Minneapolis",
    "sg:classifiers":[
        {
            "category":"Building & Trades",
            "subcategory":"Construction",
            "type":"Services"
        }
    ],
    "sg:phone":"+1 612 751 2478",
    "sg:postcode":"55433",
    "sg:province":"MN",
    "sg:tags":[
        "window",
        "contractor"
    ],
    "wof:name":"Extreme Exteriors Const Inc",
    "wof:placetype":"venue"
},
  "geometry": {"coordinates":[-93.31374099999999,45.177983],"type":"Point"}
}