{
  "type": "Feature",
  "properties": {
    "iso:country":"US",
    "sg:address":"1509 Lakeside Dr",
    "sg:city":"Alexandria",
    "sg:classifiers":[
        {
            "category":"Professional",
            "subcategory":"Research",
            "type":"Services"
        }
    ],
    "sg:phone":"+1 320 763 3343",
    "sg:postcode":"56308",
    "sg:province":"MN",
    "sg:tags":[
        "development",
        "marketing",
        "product"
    ],
    "wof:name":"Avant Garde Assoc",
    "wof:placetype":"venue"
},
  "geometry": {"coordinates":[-95.397718,45.875398],"type":"Point"}
}