{
  "type": "Feature",
  "properties": {
    "addr:full":"400 Little Canada Rd E St Paul MN 55117",
    "addr:housenumber":"400",
    "addr:postcode":"55117",
    "addr:street":"Little Canada Rd E",
    "iso:country":"US",
    "sg:address":"400 Little Canada Rd E",
    "sg:city":"St Paul",
    "sg:classifiers":[
        {
            "category":"Banks & Credit Unions",
            "subcategory":"Bank",
            "type":"Services"
        }
    ],
    "sg:phone":"+1 651 484 0265",
    "sg:postcode":"55117",
    "sg:province":"MN",
    "sg:tags":[
        "state"
    ],
    "wof:name":"St John's Little Canada CU",
    "wof:placetype":"venue"
},
  "geometry": {"coordinates":[-93.079793,45.020762],"type":"Point"}
}