{
  "type": "Feature",
  "properties": {
    "addr:full":"4817 Boone Cir N Minneapolis MN 55428",
    "addr:housenumber":"4817",
    "addr:postcode":"55428",
    "addr:street":"Boone Cir N",
    "iso:country":"US",
    "sg:address":"4817 Boone Cir N",
    "sg:city":"Minneapolis",
    "sg:classifiers":[
        {
            "category":"Retail",
            "subcategory":"Repair Shop",
            "type":"Services"
        }
    ],
    "sg:phone":"+1 763 533 0281",
    "sg:postcode":"55428",
    "sg:province":"MN",
    "wof:name":"Gartners Instrument Repa",
    "wof:placetype":"venue"
},
  "geometry": {"coordinates":[-93.391446,45.042541],"type":"Point"}
}