{
  "type": "Feature",
  "properties": {
    "iso:country":"US",
    "sg:address":"1022 W Lyon Ave",
    "sg:city":"Lake City",
    "sg:classifiers":[
        {
            "category":"Retail",
            "subcategory":"Funeral Services",
            "type":"Services"
        }
    ],
    "sg:phone":"+1 651 345 2113",
    "sg:postcode":"55041",
    "sg:province":"MN",
    "wof:name":"Anderson Peterson Mahn Fnrl HM",
    "wof:placetype":"venue"
},
  "geometry": {"coordinates":[-92.275521,44.442269],"type":"Point"}
}