{
  "type": "Feature",
  "properties": {
    "iso:country":"US",
    "sg:address":"102 W Center St",
    "sg:city":"Lake City",
    "sg:classifiers":[
        {
            "category":"Sports & Exercise",
            "subcategory":"Golf",
            "type":"Entertainment"
        }
    ],
    "sg:phone":"+1 651 345 2672",
    "sg:postcode":"55041",
    "sg:province":"MN",
    "sg:tags":[
        "course"
    ],
    "wof:name":"Jewel Golf Course",
    "wof:placetype":"venue"
},
  "geometry": {"coordinates":[-92.2657,44.448759],"type":"Point"}
}