{
  "type": "Feature",
  "properties": {
    "iso:country":"US",
    "sg:address":"9572 Iron Junction Rd",
    "sg:city":"Iron",
    "sg:classifiers":[
        {
            "category":"Professional",
            "type":"Services"
        }
    ],
    "sg:phone":"+1 218 262 5135",
    "sg:postcode":"55751",
    "sg:province":"MN",
    "wof:name":"Brad Adkins",
    "wof:placetype":"venue"
},
  "geometry": {"coordinates":[-92.693366,47.415585],"type":"Point"}
}