{
  "type": "Feature",
  "properties": {
    "addr:full":"3425 Outer Dr Hibbing MN 55746",
    "addr:housenumber":"3425",
    "addr:postcode":"55746",
    "addr:street":"Outer Dr Hibbing",
    "iso:country":"US",
    "sg:address":"3425 Outer Dr",
    "sg:city":"Hibbing",
    "sg:classifiers":[
        {
            "category":"Organizations",
            "subcategory":"Non-profit Organization",
            "type":"Services"
        }
    ],
    "sg:phone":"+1 218 263 9773",
    "sg:postcode":"55746",
    "sg:province":"MN",
    "sg:tags":[
        "social"
    ],
    "wof:name":"National Assoc of Retired",
    "wof:placetype":"venue"
},
  "geometry": {"coordinates":[-92.936232,47.411331],"type":"Point"}
}