{
  "type": "Feature",
  "properties": {
    "addr:full":"15229 Impala Ave Lamberton MN 56152",
    "addr:housenumber":"15229",
    "addr:postcode":"56152",
    "addr:street":"Impala Ave",
    "iso:country":"US",
    "sg:address":"15229 Impala Ave",
    "sg:city":"Lamberton",
    "sg:phone":"+1 507 752 7649",
    "sg:postcode":"56152",
    "sg:province":"MN",
    "sg:tags":[
        "farm",
        "corn",
        "soybean"
    ],
    "wof:name":"Ervin Runck",
    "wof:placetype":"venue"
},
  "geometry": {"coordinates":[-95.248994,44.268483],"type":"Point"}
}