{
  "type": "Feature",
  "properties": {
    "addr:full":"3101 S Frontage Rd Moorhead MN 56560",
    "addr:housenumber":"3101",
    "addr:postcode":"56560",
    "addr:street":"S Frontage Rd",
    "iso:country":"US",
    "sg:address":"3101 S Frontage Rd",
    "sg:city":"Moorhead",
    "sg:classifiers":[
        {
            "category":"Professional",
            "subcategory":"Engineering",
            "type":"Services"
        }
    ],
    "sg:phone":"+1 218 299 5610",
    "sg:postcode":"56560",
    "sg:province":"MN",
    "sg:tags":[
        "engineer"
    ],
    "sg:website":"www.ae2s.com",
    "wof:name":"Advanced Engineering",
    "wof:placetype":"venue"
},
  "geometry": {"coordinates":[-96.73314999999999,46.876244],"type":"Point"}
}