{
  "type": "Feature",
  "properties": {
    "iso:country":"US",
    "sg:address":"5320 Hyland Greens Dr",
    "sg:city":"Minneapolis",
    "sg:classifiers":[
        {
            "category":"Health Services",
            "subcategory":"Optometrist",
            "type":"Services"
        }
    ],
    "sg:phone":"+1 952 993 2400",
    "sg:postcode":"55437",
    "sg:province":"MN",
    "sg:tags":[
        "ophthalmologist"
    ],
    "sg:website":"www.parknicollet.com",
    "wof:name":"Scheper Toni J OD",
    "wof:placetype":"venue"
},
  "geometry": {"coordinates":[-93.351097,44.8237],"type":"Point"}
}