{
  "type": "Feature",
  "properties": {
    "addr:full":"5140 Fremont Ave N Minneapolis MN 55430",
    "addr:housenumber":"5140",
    "addr:postcode":"55430",
    "addr:street":"Fremont Ave N",
    "iso:country":"US",
    "sg:address":"5140 Fremont Ave N",
    "sg:city":"Minneapolis",
    "sg:classifiers":[
        {
            "category":"Education",
            "subcategory":"School",
            "type":"Public Place"
        }
    ],
    "sg:phone":"+1 612 529 7781",
    "sg:postcode":"55430",
    "sg:province":"MN",
    "sg:tags":[
        "religious"
    ],
    "sg:website":"www.sesscs.org",
    "wof:name":"St Elizabeth Seton School",
    "wof:placetype":"venue"
},
  "geometry": {"coordinates":[-93.296553,45.048597],"type":"Point"}
}