{
  "type": "Feature",
  "properties": {
    "addr:full":"21044 Co Rd 75 Clearwater MN 55320",
    "addr:housenumber":"21044;75",
    "addr:postcode":"55320",
    "addr:street":"Co Rd",
    "iso:country":"US",
    "sg:address":"21044 Co Rd 75",
    "sg:city":"Clearwater",
    "sg:classifiers":[
        {
            "category":"Real Estate",
            "subcategory":"Real Estate Operator",
            "type":"Services"
        }
    ],
    "sg:phone":"+1 320 558 6685",
    "sg:postcode":"55320",
    "sg:province":"MN",
    "sg:tags":[
        "property",
        "lessor"
    ],
    "wof:name":"Richard Kloeppner",
    "wof:placetype":"venue"
},
  "geometry": {"coordinates":[-94.096401,45.435666],"type":"Point"}
}