{
  "type": "Feature",
  "properties": {
    "addr:full":"707 Elm Ave E Delano MN 55328",
    "addr:housenumber":"707",
    "addr:postcode":"55328",
    "addr:street":"Elm Ave E Delano",
    "iso:country":"US",
    "sg:address":"707 Elm Ave E",
    "sg:city":"Delano",
    "sg:classifiers":[
        {
            "category":"Health Services",
            "subcategory":"Doctor",
            "type":"Services"
        }
    ],
    "sg:phone":"+1 763 972 2800",
    "sg:postcode":"55328",
    "sg:province":"MN",
    "sg:tags":[
        "dentist"
    ],
    "sg:website":"http://www.delanodental.com",
    "wof:name":"Delano Family Dental Clinic",
    "wof:placetype":"venue"
},
  "geometry": {"coordinates":[-93.776146,45.042885],"type":"Point"}
}