{
  "type": "Feature",
  "properties": {
    "iso:country":"US",
    "sg:address":"814 4th St NE",
    "sg:city":"Little Falls",
    "sg:classifiers":[
        {
            "category":"Social Services",
            "subcategory":"Child Care",
            "type":"Services"
        }
    ],
    "sg:phone":"+1 320 632 5861",
    "sg:postcode":"56345",
    "sg:province":"MN",
    "sg:tags":[
        "daycare",
        "provider"
    ],
    "wof:name":"Frances Mennig",
    "wof:placetype":"venue"
},
  "geometry": {"coordinates":[-94.355104,45.985406],"type":"Point"}
}