{
  "type": "Feature",
  "properties": {
    "iso:country":"US",
    "sg:address":"6510 Galaxy Rd",
    "sg:city":"St Cloud",
    "sg:classifiers":[
        {
            "category":"Wholesale",
            "subcategory":"Beer",
            "type":"Manufacturing & Wholesale Goods"
        }
    ],
    "sg:phone":"+1 320 656 0050",
    "sg:postcode":"56301",
    "sg:province":"MN",
    "sg:tags":[
        "ale"
    ],
    "wof:name":"Lenneman Beverage Distributors",
    "wof:placetype":"venue"
},
  "geometry": {"coordinates":[-94.24444800000001,45.466323],"type":"Point"}
}