{
  "type": "Feature",
  "properties": {
    "iso:country":"US",
    "sg:address":"22140 Chippendale Ave W",
    "sg:city":"Farmington",
    "sg:classifiers":[
        {
            "category":"Banks & Credit Unions",
            "subcategory":"Bank",
            "type":"Services"
        },
        {
            "category":"Banks & Credit Unions",
            "subcategory":"Financial Services",
            "type":"Services"
        }
    ],
    "sg:phone":"+1 651 463 4014",
    "sg:postcode":"55024",
    "sg:province":"MN",
    "sg:tags":[
        "saving",
        "loan",
        "commercial"
    ],
    "sg:website":"http://www.castlerockbank.net",
    "wof:name":"Castle Rock Bank",
    "wof:placetype":"venue"
},
  "geometry": {"coordinates":[-93.136805,44.629123],"type":"Point"}
}