{
  "type": "Feature",
  "properties": {
    "addr:full":"1801 Lakeridge Way Waconia MN 55387",
    "addr:housenumber":"1801",
    "addr:postcode":"55387",
    "addr:street":"Lakeridge Way",
    "iso:country":"US",
    "sg:address":"1801 Lakeridge Way",
    "sg:city":"Waconia",
    "sg:classifiers":[
        {
            "category":"Real Estate",
            "subcategory":"Real Estate Agent",
            "type":"Services"
        }
    ],
    "sg:phone":"+1 952 442 1923",
    "sg:postcode":"55387",
    "sg:province":"MN",
    "wof:name":"Boffs Ltd",
    "wof:placetype":"venue"
},
  "geometry": {"coordinates":[-93.814528,44.854599],"type":"Point"}
}