{
  "type": "Feature",
  "properties": {
    "iso:country":"US",
    "sg:address":"1101 W Lincoln Ave",
    "sg:city":"Olivia",
    "sg:classifiers":[
        {
            "category":"Social Services",
            "subcategory":"Child Care",
            "type":"Services"
        }
    ],
    "sg:phone":"+1 320 523 1196",
    "sg:postcode":"56277",
    "sg:province":"MN",
    "sg:tags":[
        "day"
    ],
    "wof:name":"Tender Touch Child Care Center",
    "wof:placetype":"venue"
},
  "geometry": {"coordinates":[-94.99411499999999,44.776467],"type":"Point"}
}