{
  "type": "Feature",
  "properties": {
    "iso:country":"US",
    "sg:address":"26715 733rd Ave",
    "sg:city":"Dassel",
    "sg:classifiers":[
        {
            "category":"Social Services",
            "subcategory":"Child Care",
            "type":"Services"
        }
    ],
    "sg:phone":"+1 320 275 9906",
    "sg:postcode":"55325",
    "sg:province":"MN",
    "sg:tags":[
        "day"
    ],
    "wof:name":"Learning Curve Seminars Ltd",
    "wof:placetype":"venue"
},
  "geometry": {"coordinates":[-94.290074,45.129552],"type":"Point"}
}