{
  "type": "Feature",
  "properties": {
    "addr:full":"5563 Nichols Ave Mountain Iron MN 55768",
    "addr:housenumber":"5563",
    "addr:postcode":"55768",
    "addr:street":"Nichols Ave",
    "iso:country":"US",
    "sg:address":"5563 Nichols Ave",
    "sg:city":"Mountain Iron",
    "sg:classifiers":[
        {
            "category":"Education",
            "subcategory":"Special Training",
            "type":"Public Place"
        }
    ],
    "sg:phone":"+1 218 742 3447",
    "sg:postcode":"55768",
    "sg:province":"MN",
    "wof:name":"IMT College",
    "wof:placetype":"venue"
},
  "geometry": {"coordinates":[-92.581491,47.521746],"type":"Point"}
}