{
  "type": "Feature",
  "properties": {
    "iso:country":"US",
    "sg:address":"2201 44th Ave N",
    "sg:city":"Minneapolis",
    "sg:classifiers":[
        {
            "category":"Food & Beverages",
            "subcategory":"Specialty",
            "type":"Retail Goods"
        }
    ],
    "sg:phone":"+1 612 287 8399",
    "sg:postcode":"55412",
    "sg:province":"MN",
    "sg:tags":[
        "tea",
        "coffee"
    ],
    "sg:website":"www.steamworkscoffee.com",
    "wof:name":"Steamworks Coffee & Tea Co",
    "wof:placetype":"venue"
},
  "geometry": {"coordinates":[-93.309105,45.03545],"type":"Point"}
}