{
  "type": "Feature",
  "properties": {
    "addr:full":"1 Federal Dr Saint Paul MN 55111",
    "addr:housenumber":"1",
    "addr:postcode":"55111",
    "addr:street":"Federal Dr",
    "iso:country":"US",
    "sg:address":"1 Federal Dr",
    "sg:city":"Saint Paul",
    "sg:classifiers":[
        {
            "category":"Government",
            "subcategory":"Office",
            "type":"Public Place"
        }
    ],
    "sg:phone":"+1 612 713 5306",
    "sg:postcode":"55111",
    "sg:province":"MN",
    "sg:tags":[
        "conservation"
    ],
    "wof:name":"Assistant Rgnl Dir Budget",
    "wof:placetype":"venue"
},
  "geometry": {"coordinates":[-93.197693,44.894701],"type":"Point"}
}