{
  "type": "Feature",
  "properties": {
    "addr:full":"2010 235th St Lynd MN 56157",
    "addr:housenumber":"2010",
    "addr:postcode":"56157",
    "addr:street":"235Th St",
    "iso:country":"US",
    "sg:address":"2010 235th St",
    "sg:city":"Lynd",
    "sg:classifiers":[
        {
            "category":"Real Estate",
            "subcategory":"Real Estate Agent",
            "type":"Services"
        }
    ],
    "sg:phone":"+1 507 865 4634",
    "sg:postcode":"56157",
    "sg:province":"MN",
    "wof:name":"Max E Norris",
    "wof:placetype":"venue"
},
  "geometry": {"coordinates":[-95.896686,44.393226],"type":"Point"}
}