{
  "type": "Feature",
  "properties": {
    "iso:country":"US",
    "sg:address":"47 N Broadway",
    "sg:city":"Pelican Rapids",
    "sg:classifiers":[
        {
            "category":"Real Estate",
            "subcategory":"Real Estate Agent",
            "type":"Services"
        }
    ],
    "sg:phone":"+1 218 863 5936",
    "sg:postcode":"56572",
    "sg:province":"MN",
    "wof:name":"Seifert's Realty & Auction Co",
    "wof:placetype":"venue"
},
  "geometry": {"coordinates":[-96.08347000000001,46.57094],"type":"Point"}
}