{
  "type": "Feature",
  "properties": {
    "iso:country":"US",
    "sg:address":"4670 Balsam Ln N",
    "sg:city":"Minneapolis",
    "sg:classifiers":[
        {
            "category":"Professional",
            "type":"Services"
        }
    ],
    "sg:phone":"+1 763 559 5416",
    "sg:postcode":"55442",
    "sg:province":"MN",
    "wof:name":"Bill Appelt",
    "wof:placetype":"venue"
},
  "geometry": {"coordinates":[-93.42288000000001,45.04028],"type":"Point"}
}