{
  "type": "Feature",
  "properties": {
    "addr:full":"385 S Clinton Ave Saint Paul MN 55107",
    "addr:housenumber":"385",
    "addr:postcode":"55107",
    "addr:street":"S Clinton Ave",
    "iso:country":"US",
    "sg:address":"385 S Clinton Ave",
    "sg:city":"Saint Paul",
    "sg:classifiers":[
        {
            "category":"Banks & Credit Unions",
            "subcategory":"Financial Services",
            "type":"Services"
        }
    ],
    "sg:phone":"+1 651 248 2736",
    "sg:postcode":"55107",
    "sg:province":"MN",
    "sg:tags":[
        "company",
        "holding"
    ],
    "wof:name":"Up North Holdings",
    "wof:placetype":"venue"
},
  "geometry": {"coordinates":[-93.079491,44.934663],"type":"Point"}
}