{
  "type": "Feature",
  "properties": {
    "addr:full":"7168 Roosevelt Rd SE Bemidji MN 56601",
    "addr:housenumber":"7168",
    "addr:postcode":"56601",
    "addr:street":"Roosevelt Rd Se",
    "iso:country":"US",
    "sg:address":"7168 Roosevelt Rd SE",
    "sg:city":"Bemidji",
    "sg:classifiers":[
        {
            "category":"Farming",
            "subcategory":"Livestock Farm",
            "type":"Manufacturing & Wholesale Goods"
        }
    ],
    "sg:phone":"+1 218 751 5111",
    "sg:postcode":"56601",
    "sg:province":"MN",
    "sg:tags":[
        "feedlot",
        "field",
        "crop",
        "beef",
        "cattle"
    ],
    "wof:name":"James Langerak",
    "wof:placetype":"venue"
},
  "geometry": {"coordinates":[-94.774582,47.453929],"type":"Point"}
}