{
  "type": "Feature",
  "properties": {
    "addr:full":"1801 W Fir Ave Fergus Falls MN 56537",
    "addr:housenumber":"1801",
    "addr:postcode":"56537",
    "addr:street":"W Fir Ave",
    "iso:country":"US",
    "sg:address":"1801 W Fir Ave",
    "sg:city":"Fergus Falls",
    "sg:classifiers":[
        {
            "category":"Manufacturing",
            "subcategory":"Signs",
            "type":"Manufacturing & Wholesale Goods"
        }
    ],
    "sg:phone":"+1 218 736 2216",
    "sg:postcode":"56537",
    "sg:province":"MN",
    "sg:website":"www.artnsign.com",
    "wof:name":"Art-N-Sign",
    "wof:placetype":"venue"
},
  "geometry": {"coordinates":[-96.091616,46.303261],"type":"Point"}
}