{
  "type": "Feature",
  "properties": {
    "iso:country":"US",
    "sg:address":"5520 Maple Heights Rd",
    "sg:city":"Excelsior",
    "sg:classifiers":[
        {
            "category":"Building & Trades",
            "subcategory":"Equipment Rental",
            "type":"Services"
        }
    ],
    "sg:phone":"+1 952 470 3931",
    "sg:postcode":"55331",
    "sg:province":"MN",
    "sg:tags":[
        "medical"
    ],
    "wof:name":"Mobil Medical Diagnostics Inc",
    "wof:placetype":"venue"
},
  "geometry": {"coordinates":[-93.54673699999999,44.905386],"type":"Point"}
}