{
  "type": "Feature",
  "properties": {
    "addr:full":"201 16th Ave SE Waseca MN 56093",
    "addr:housenumber":"201",
    "addr:postcode":"56093",
    "addr:street":"16Th Ave Se",
    "iso:country":"US",
    "sg:address":"201 16th Ave SE",
    "sg:city":"Waseca",
    "sg:classifiers":[
        {
            "category":"Professional",
            "subcategory":"Engineering",
            "type":"Services"
        },
        {
            "category":"Professional",
            "subcategory":"Computer Services",
            "type":"Services"
        }
    ],
    "sg:phone":"+1 507 833 8220",
    "sg:postcode":"56093",
    "sg:province":"MN",
    "sg:tags":[
        "control",
        "plant",
        "industrial",
        "for",
        "floor",
        "system",
        "automation"
    ],
    "wof:name":"Minnesota Control Co",
    "wof:placetype":"venue"
},
  "geometry": {"coordinates":[-93.506542,44.062353],"type":"Point"}
}