{
  "type": "Feature",
  "properties": {
    "addr:full":"828 Hadley Ave N Saint Paul MN 55128",
    "addr:housenumber":"828",
    "addr:postcode":"55128",
    "addr:street":"Hadley Ave N",
    "iso:country":"US",
    "sg:address":"828 Hadley Ave N",
    "sg:city":"Saint Paul",
    "sg:classifiers":[
        {
            "category":"Retail",
            "subcategory":"Photofinishing",
            "type":"Services"
        }
    ],
    "sg:phone":"+1 651 739 6026",
    "sg:postcode":"55128",
    "sg:province":"MN",
    "sg:tags":[
        "laboratory"
    ],
    "wof:name":"Oakdale Photo Shoppe",
    "wof:placetype":"venue"
},
  "geometry": {"coordinates":[-92.964546,44.959916],"type":"Point"}
}