{
  "type": "Feature",
  "properties": {
    "iso:country":"US",
    "sg:address":"309 3rd St",
    "sg:city":"International Falls",
    "sg:classifiers":[
        {
            "category":"Professional",
            "subcategory":"Management & Consulting",
            "type":"Services"
        }
    ],
    "sg:phone":"+1 218 283 3051",
    "sg:postcode":"56649",
    "sg:province":"MN",
    "wof:name":"American Express",
    "wof:placetype":"venue"
},
  "geometry": {"coordinates":[-93.403695,48.602646],"type":"Point"}
}