{
  "type": "Feature",
  "properties": {
    "addr:full":"24435 Drexel Ave New Prague MN 56071",
    "addr:housenumber":"24435",
    "addr:postcode":"56071",
    "addr:street":"Drexel Ave",
    "iso:country":"US",
    "sg:address":"24435 Drexel Ave",
    "sg:city":"New Prague",
    "sg:classifiers":[
        {
            "category":"Recreation",
            "type":"Entertainment"
        }
    ],
    "sg:phone":"+1 952 758 2560",
    "sg:postcode":"56071",
    "sg:province":"MN",
    "sg:tags":[
        "stable"
    ],
    "wof:name":"Schoenbauer's Country Corral",
    "wof:placetype":"venue"
},
  "geometry": {"coordinates":[-93.557518,44.600809],"type":"Point"}
}