{
  "type": "Feature",
  "properties": {
    "addr:full":"3492 Co Hwy 44 South Haven MN 55382",
    "addr:housenumber":"3492",
    "addr:postcode":"55382",
    "addr:street":"Co Hwy 44;Haven",
    "iso:country":"US",
    "sg:address":"3492 Co Hwy 44",
    "sg:city":"South Haven",
    "sg:classifiers":[
        {
            "category":"Building & Trades",
            "subcategory":"Construction",
            "type":"Services"
        }
    ],
    "sg:phone":"+1 320 236 7512",
    "sg:postcode":"55382",
    "sg:province":"MN",
    "sg:tags":[
        "contractor"
    ],
    "wof:name":"John Erickson",
    "wof:placetype":"venue"
},
  "geometry": {"coordinates":[-94.188894,45.326289],"type":"Point"}
}