{
  "type": "Feature",
  "properties": {
    "addr:full":"3931 Crestview Dr Excelsior MN 55331",
    "addr:housenumber":"3931",
    "addr:postcode":"55331",
    "addr:street":"Crestview Dr",
    "iso:country":"US",
    "sg:address":"3931 Crestview Dr",
    "sg:city":"Excelsior",
    "sg:classifiers":[
        {
            "category":"Professional",
            "subcategory":"Detective & Security Services",
            "type":"Services"
        }
    ],
    "sg:phone":"+1 952 474 3136",
    "sg:postcode":"55331",
    "sg:province":"MN",
    "sg:tags":[
        "car"
    ],
    "wof:name":"Lvd Investigations Inc",
    "wof:placetype":"venue"
},
  "geometry": {"coordinates":[-93.620616,44.883966],"type":"Point"}
}