{
  "type": "Feature",
  "properties": {
    "iso:country":"US",
    "sg:address":"308 W 59th St",
    "sg:city":"Minneapolis",
    "sg:classifiers":[
        {
            "category":"Building & Trades",
            "subcategory":"Construction",
            "type":"Services"
        }
    ],
    "sg:phone":"+1 612 866 4954",
    "sg:postcode":"55419",
    "sg:province":"MN",
    "sg:tags":[
        "plastering",
        "contractor"
    ],
    "wof:name":"A E Conrad Co",
    "wof:placetype":"venue"
},
  "geometry": {"coordinates":[-93.284645,44.896338],"type":"Point"}
}