{
  "type": "Feature",
  "properties": {
    "iso:country":"US",
    "sg:address":"102 E Central Entrance",
    "sg:city":"Duluth",
    "sg:classifiers":[
        {
            "category":"Retail",
            "subcategory":"Auto Repair",
            "type":"Services"
        }
    ],
    "sg:phone":"+1 218 723 1795",
    "sg:postcode":"55811",
    "sg:province":"MN",
    "sg:tags":[
        "installs",
        "automotive",
        "glass"
    ],
    "wof:name":"Triumph Auto Glass",
    "wof:placetype":"venue"
},
  "geometry": {"coordinates":[-92.13042,46.800298],"type":"Point"}
}