{
  "type": "Feature",
  "properties": {
    "iso:country":"US",
    "sg:address":"315 2nd St E",
    "sg:city":"Hastings",
    "sg:classifiers":[
        {
            "category":"Manufacturing",
            "subcategory":"Printing",
            "type":"Manufacturing & Wholesale Goods"
        }
    ],
    "sg:phone":"+1 651 437 6459",
    "sg:postcode":"55033",
    "sg:province":"MN",
    "sg:tags":[
        "printer"
    ],
    "sg:website":"www.gd-inc.com",
    "wof:name":"Graphic Design Inc",
    "wof:placetype":"venue"
},
  "geometry": {"coordinates":[-92.848809,44.744422],"type":"Point"}
}