{
  "type": "Feature",
  "properties": {
    "iso:country":"US",
    "sg:address":"42538 231st Ave",
    "sg:city":"Le Center",
    "sg:phone":"+1 507 357 6380",
    "sg:postcode":"56057",
    "sg:province":"MN",
    "sg:tags":[
        "farm",
        "corn"
    ],
    "wof:name":"Melvin Schley",
    "wof:placetype":"venue"
},
  "geometry": {"coordinates":[-93.727425,44.333587],"type":"Point"}
}