{
  "type": "Feature",
  "properties": {
    "iso:country":"US",
    "sg:address":"16858 Hwy 10 NW",
    "sg:city":"Elk River",
    "sg:classifiers":[
        {
            "category":"Wholesale",
            "subcategory":"Auto Parts",
            "type":"Manufacturing & Wholesale Goods"
        }
    ],
    "sg:phone":"+1 763 633 0911",
    "sg:postcode":"55330",
    "sg:province":"MN",
    "sg:tags":[
        "truck",
        "accessory"
    ],
    "wof:name":"Auto Trends",
    "wof:placetype":"venue"
},
  "geometry": {"coordinates":[-93.555172,45.314074],"type":"Point"}
}