{
  "type": "Feature",
  "properties": {
    "addr:full":"9629 Anderson Lakes Pkwy Eden Prairie MN 55344",
    "addr:housenumber":"9629",
    "addr:postcode":"55344",
    "addr:street":"Anderson Lakes Pkwy",
    "iso:country":"US",
    "sg:address":"9629 Anderson Lakes Pkwy",
    "sg:city":"Eden Prairie",
    "sg:classifiers":[
        {
            "category":"Shopping",
            "subcategory":"Clothing, Apparel, & Fashions",
            "type":"Retail Goods"
        }
    ],
    "sg:phone":"+1 952 833 1531",
    "sg:postcode":"55344",
    "sg:province":"MN",
    "wof:name":"Hydrangea",
    "wof:placetype":"venue"
},
  "geometry": {"coordinates":[-93.39981,44.836783],"type":"Point"}
}