{
  "type": "Feature",
  "properties": {
    "iso:country":"US",
    "sg:address":"115 3rd Ave W",
    "sg:city":"Alexandria",
    "sg:classifiers":[
        {
            "category":"Social Services",
            "subcategory":"Job Training",
            "type":"Services"
        }
    ],
    "sg:phone":"+1 320 763 5888",
    "sg:postcode":"56308",
    "sg:province":"MN",
    "sg:tags":[
        "rehabilitation"
    ],
    "wof:name":"Ken Moberg Career & Voc Svc",
    "wof:placetype":"venue"
},
  "geometry": {"coordinates":[-95.378612,45.889561],"type":"Point"}
}