{
  "type": "Feature",
  "properties": {
    "iso:country":"US",
    "sg:address":"101 11th Ave N",
    "sg:city":"South Saint Paul",
    "sg:classifiers":[
        {
            "category":"Professional",
            "type":"Services"
        }
    ],
    "sg:phone":"+1 651 457 3140",
    "sg:postcode":"55075",
    "sg:province":"MN",
    "wof:name":"National 5 & 10",
    "wof:placetype":"venue"
},
  "geometry": {"coordinates":[-93.04755299999999,44.891622],"type":"Point"}
}