{
  "type": "Feature",
  "properties": {
    "iso:country":"US",
    "sg:address":"12613 Old Number 7 SE",
    "sg:city":"Chatfield",
    "sg:classifiers":[
        {
            "category":"Building & Trades",
            "subcategory":"Construction",
            "type":"Services"
        }
    ],
    "sg:phone":"+1 507 867 3487",
    "sg:postcode":"55923",
    "sg:province":"MN",
    "sg:tags":[
        "material",
        "contractor"
    ],
    "wof:name":"Southeast Siding & Window Co",
    "wof:placetype":"venue"
},
  "geometry": {"coordinates":[-92.22493299999999,43.894499],"type":"Point"}
}