{
  "type": "Feature",
  "properties": {
    "addr:full":"2520 Clover Field Dr Chaska MN 55318",
    "addr:housenumber":"2520",
    "addr:postcode":"55318",
    "addr:street":"Clover Field Dr",
    "iso:country":"US",
    "sg:address":"2520 Clover Field Dr",
    "sg:city":"Chaska",
    "sg:classifiers":[
        {
            "category":"Professional",
            "subcategory":"Advertising",
            "type":"Services"
        },
        {
            "category":"Professional",
            "subcategory":"Art Services",
            "type":"Services"
        }
    ],
    "sg:phone":"+1 952 368 7224",
    "sg:postcode":"55318",
    "sg:province":"MN",
    "sg:tags":[
        "designer",
        "agency",
        "producer",
        "display"
    ],
    "wof:name":"Todd Dexter",
    "wof:placetype":"venue"
},
  "geometry": {"coordinates":[-93.634922,44.813821],"type":"Point"}
}