{
  "type": "Feature",
  "properties": {
    "addr:full":"1022 NW 2nd Ave Grand Rapids MN 55744",
    "addr:housenumber":"1022",
    "addr:postcode":"55744",
    "addr:street":"Nw 2Nd Ave",
    "iso:country":"US",
    "sg:address":"1022 NW 2nd Ave",
    "sg:city":"Grand Rapids",
    "sg:classifiers":[
        {
            "category":"Health Services",
            "subcategory":"Doctor",
            "type":"Services"
        }
    ],
    "sg:phone":"+1 218 326 4208",
    "sg:postcode":"55744",
    "sg:province":"MN",
    "sg:tags":[
        "medical"
    ],
    "wof:name":"Charles P Kampen MD",
    "wof:placetype":"venue"
},
  "geometry": {"coordinates":[-93.531335,47.24402],"type":"Point"}
}