{
  "type": "Feature",
  "properties": {
    "iso:country":"US",
    "sg:address":"11516 K-Tel Dr",
    "sg:city":"Hopkins",
    "sg:classifiers":[
        {
            "category":"Wholesale",
            "subcategory":"Electrical",
            "type":"Manufacturing & Wholesale Goods"
        }
    ],
    "sg:phone":"+1 952 935 5117",
    "sg:postcode":"55343",
    "sg:province":"MN",
    "sg:tags":[
        "equipment"
    ],
    "wof:name":"Bonthius Electrical Sales Co",
    "wof:placetype":"venue"
},
  "geometry": {"coordinates":[-93.42789399999999,44.912845],"type":"Point"}
}