{
  "type": "Feature",
  "properties": {
    "iso:country":"US",
    "sg:address":"5901 Brooklyn Blvd",
    "sg:city":"Minneapolis",
    "sg:classifiers":[
        {
            "category":"Professional",
            "subcategory":"Accounting & Tax Preparation",
            "type":"Services"
        }
    ],
    "sg:phone":"+1 763 566 3530",
    "sg:postcode":"55429",
    "sg:province":"MN",
    "sg:tags":[
        "accountant"
    ],
    "wof:name":"Paul F Jahnke CPA",
    "wof:placetype":"venue"
},
  "geometry": {"coordinates":[-93.325462,45.063511],"type":"Point"}
}