{
  "type": "Feature",
  "properties": {
    "iso:country":"US",
    "sg:address":"13560 Grove Dr",
    "sg:city":"Osseo",
    "sg:classifiers":[
        {
            "category":"Shopping",
            "subcategory":"Clothing, Apparel, & Fashions",
            "type":"Retail Goods"
        }
    ],
    "sg:phone":"+1 763 494 3333",
    "sg:postcode":"55311",
    "sg:province":"MN",
    "wof:name":"Expressew Tlrg & Alterations",
    "wof:placetype":"venue"
},
  "geometry": {"coordinates":[-93.452246,45.103011],"type":"Point"}
}