{
  "type": "Feature",
  "properties": {
    "addr:full":"114 E State St Kiester MN 56051",
    "addr:housenumber":"114",
    "addr:postcode":"56051",
    "addr:street":"E State St",
    "iso:country":"US",
    "sg:address":"114 E State St",
    "sg:city":"Kiester",
    "sg:classifiers":[
        {
            "category":"Social Services",
            "subcategory":"Child Care",
            "type":"Services"
        }
    ],
    "sg:phone":"+1 507 294 3224",
    "sg:postcode":"56051",
    "sg:province":"MN",
    "sg:tags":[
        "day",
        "provider"
    ],
    "wof:name":"Lori J Olson",
    "wof:placetype":"venue"
},
  "geometry": {"coordinates":[-93.707955,43.535947],"type":"Point"}
}