{
  "type": "Feature",
  "properties": {
    "iso:country":"US",
    "sg:address":"118 Lake Ave N",
    "sg:city":"Spicer",
    "sg:classifiers":[
        {
            "category":"Shopping",
            "subcategory":"Gifts & Souvenirs",
            "type":"Retail Goods"
        }
    ],
    "sg:phone":"+1 320 796 0622",
    "sg:postcode":"56288",
    "sg:province":"MN",
    "sg:tags":[
        "shop"
    ],
    "wof:name":"Sofia's Gift Gallery",
    "wof:placetype":"venue"
},
  "geometry": {"coordinates":[-94.938765,45.233785],"type":"Point"}
}