{
  "type": "Feature",
  "properties": {
    "iso:country":"US",
    "sg:address":"233 Glasgow Ave S",
    "sg:city":"Kellogg",
    "sg:classifiers":[
        {
            "category":"Manufacturing",
            "subcategory":"Toys & Sporting Goods",
            "type":"Manufacturing & Wholesale Goods"
        }
    ],
    "sg:phone":"+1 507 767 4994",
    "sg:postcode":"55945",
    "sg:province":"MN",
    "sg:tags":[
        "stuffed",
        "doll"
    ],
    "sg:website":"www.bouquetent.com",
    "wof:name":"Bouquet Enterprises Inc",
    "wof:placetype":"venue"
},
  "geometry": {"coordinates":[-92.00229899999999,44.306143],"type":"Point"}
}