{
  "type": "Feature",
  "properties": {
    "iso:country":"US",
    "sg:address":"219 Main St N",
    "sg:city":"Austin",
    "sg:classifiers":[
        {
            "category":"Shopping",
            "subcategory":"Bicycles & Sporting Goods",
            "type":"Retail Goods"
        }
    ],
    "sg:phone":"+1 507 433 7571",
    "sg:postcode":"55912",
    "sg:province":"MN",
    "sg:tags":[
        "ski"
    ],
    "sg:website":"www.rydjor.com",
    "wof:name":"Rydjor Bike Shop",
    "wof:placetype":"venue"
},
  "geometry": {"coordinates":[-92.974912,43.668171],"type":"Point"}
}