{
  "type": "Feature",
  "properties": {
    "iso:country":"US",
    "sg:address":"5240 York Ave S",
    "sg:city":"Minneapolis",
    "sg:classifiers":[
        {
            "category":"Banks & Credit Unions",
            "subcategory":"Financial Services",
            "type":"Services"
        }
    ],
    "sg:phone":"+1 612 929 5310",
    "sg:postcode":"55410",
    "sg:province":"MN",
    "sg:tags":[
        "profit",
        "sharing",
        "plan",
        "pension"
    ],
    "wof:name":"Pension & Tax Management",
    "wof:placetype":"venue"
},
  "geometry": {"coordinates":[-93.32012,44.907741],"type":"Point"}
}