{
  "type": "Feature",
  "properties": {
    "iso:country":"US",
    "sg:address":"13795 Frontier Ct",
    "sg:city":"Burnsville",
    "sg:classifiers":[
        {
            "category":"Building & Trades",
            "subcategory":"Construction",
            "type":"Services"
        }
    ],
    "sg:phone":"+1 952 997 7838",
    "sg:postcode":"55337",
    "sg:province":"MN",
    "sg:tags":[
        "home",
        "builder",
        "contractor"
    ],
    "wof:name":"Rmc Development Corp",
    "wof:placetype":"venue"
},
  "geometry": {"coordinates":[-93.251099,44.754398],"type":"Point"}
}