{
  "type": "Feature",
  "properties": {
    "addr:full":"12436 Shea Rd NW Garfield MN 56332",
    "addr:housenumber":"12436",
    "addr:postcode":"56332",
    "addr:street":"Shea Rd Nw",
    "iso:country":"US",
    "sg:address":"12436 Shea Rd NW",
    "sg:city":"Garfield",
    "sg:classifiers":[
        {
            "category":"Farming",
            "subcategory":"Dairy Farm",
            "type":"Manufacturing & Wholesale Goods"
        },
        {
            "category":"Farming",
            "subcategory":"Farm",
            "type":"Manufacturing & Wholesale Goods"
        }
    ],
    "sg:phone":"+1 320 834 2573",
    "sg:postcode":"56332",
    "sg:province":"MN",
    "wof:name":"Kevin Roers",
    "wof:placetype":"venue"
},
  "geometry": {"coordinates":[-95.485022,46.020411],"type":"Point"}
}