{
  "type": "Feature",
  "properties": {
    "addr:full":"13986 Maple Knoll Way Osseo MN 55369",
    "addr:housenumber":"13986",
    "addr:postcode":"55369",
    "addr:street":"Maple Knoll Way",
    "iso:country":"US",
    "sg:address":"13986 Maple Knoll Way",
    "sg:city":"Osseo",
    "sg:classifiers":[
        {
            "category":"Health Services",
            "subcategory":"Doctor",
            "type":"Services"
        }
    ],
    "sg:phone":"+1 763 420 5484",
    "sg:postcode":"55369",
    "sg:province":"MN",
    "wof:name":"Pdhc Ltd",
    "wof:placetype":"venue"
},
  "geometry": {"coordinates":[-93.45656,45.106895],"type":"Point"}
}