{
  "type": "Feature",
  "properties": {
    "addr:full":"860 Commerce Rd Long Prairie MN 56347",
    "addr:housenumber":"860",
    "addr:postcode":"56347",
    "addr:street":"Commerce Rd",
    "iso:country":"US",
    "sg:address":"860 Commerce Rd",
    "sg:city":"Long Prairie",
    "sg:classifiers":[
        {
            "category":"Retail",
            "subcategory":"Auto Repair",
            "type":"Services"
        }
    ],
    "sg:phone":"+1 320 732 6764",
    "sg:postcode":"56347",
    "sg:province":"MN",
    "sg:tags":[
        "general"
    ],
    "wof:name":"J&R Auto Care Center",
    "wof:placetype":"venue"
},
  "geometry": {"coordinates":[-94.86537,45.957705],"type":"Point"}
}