{
  "type": "Feature",
  "properties": {
    "addr:full":"206 Central Ave S Eagle Bend MN 56446",
    "addr:housenumber":"206",
    "addr:postcode":"56446",
    "addr:street":"Central Ave S",
    "iso:country":"US",
    "sg:address":"206 Central Ave S",
    "sg:city":"Eagle Bend",
    "sg:classifiers":[
        {
            "category":"Insurance",
            "subcategory":"Insurance Agent",
            "type":"Services"
        }
    ],
    "sg:phone":"+1 218 738 3442",
    "sg:postcode":"56446",
    "sg:province":"MN",
    "wof:name":"Klein Insurance Inc",
    "wof:placetype":"venue"
},
  "geometry": {"coordinates":[-95.03652,46.163827],"type":"Point"}
}