{
  "type": "Feature",
  "properties": {
    "iso:country":"US",
    "sg:address":"4315 N Shore Dr",
    "sg:city":"Mound",
    "sg:classifiers":[
        {
            "category":"Real Estate",
            "subcategory":"Real Estate Agent",
            "type":"Services"
        }
    ],
    "sg:phone":"+1 952 472 3219",
    "sg:postcode":"55364",
    "sg:province":"MN",
    "wof:name":"Guaranty Escrow Of Minnesota",
    "wof:placetype":"venue"
},
  "geometry": {"coordinates":[-93.635284,44.952942],"type":"Point"}
}