{
  "type": "Feature",
  "properties": {
    "addr:full":"15879 Docken Dr Milaca MN 56353",
    "addr:housenumber":"15879",
    "addr:postcode":"56353",
    "addr:street":"Docken Dr",
    "iso:country":"US",
    "sg:address":"15879 Docken Dr",
    "sg:city":"Milaca",
    "sg:classifiers":[
        {
            "category":"Freight",
            "type":"Transportation"
        },
        {
            "category":"Building & Trades",
            "subcategory":"Construction",
            "type":"Services"
        }
    ],
    "sg:phone":"+1 320 983 3883",
    "sg:postcode":"56353",
    "sg:province":"MN",
    "sg:tags":[
        "local",
        "hauling",
        "trucking"
    ],
    "wof:name":"Andrew J Clemens & Sons",
    "wof:placetype":"venue"
},
  "geometry": {"coordinates":[-93.66583199999999,45.776886],"type":"Point"}
}