{
  "type": "Feature",
  "properties": {
    "addr:full":"2097 Grand Ave Saint Paul MN 55105",
    "addr:housenumber":"2097",
    "addr:postcode":"55105",
    "addr:street":"Grand Ave",
    "iso:country":"US",
    "sg:address":"2097 Grand Ave",
    "sg:city":"Saint Paul",
    "sg:classifiers":[
        {
            "category":"Government",
            "subcategory":"Police Station",
            "type":"Public Place"
        }
    ],
    "sg:phone":"+1 651 962 5107",
    "sg:postcode":"55105",
    "sg:province":"MN",
    "sg:tags":[
        "protection"
    ],
    "wof:name":"Police Dept",
    "wof:placetype":"venue"
},
  "geometry": {"coordinates":[-93.188817,44.940194],"type":"Point"}
}