{
  "type": "Feature",
  "properties": {
    "addr:full":"7917 Hallmark Way Saint Paul MN 55124",
    "addr:housenumber":"7917",
    "addr:postcode":"55124",
    "addr:street":"Hallmark Way",
    "iso:country":"US",
    "sg:address":"7917 Hallmark Way",
    "sg:city":"Saint Paul",
    "sg:classifiers":[
        {
            "category":"Utilities",
            "subcategory":"Telephone",
            "type":"Services"
        }
    ],
    "sg:phone":"+1 952 431 5384",
    "sg:postcode":"55124",
    "sg:province":"MN",
    "sg:tags":[
        "communications"
    ],
    "wof:name":"Business Telephone Products",
    "wof:placetype":"venue"
},
  "geometry": {"coordinates":[-93.22733599999999,44.723741],"type":"Point"}
}