{
  "type": "Feature",
  "properties": {
    "iso:country":"US",
    "sg:address":"2619 Oak Ridge Trl",
    "sg:city":"Woodbury",
    "sg:classifiers":[
        {
            "category":"Professional",
            "type":"Services"
        }
    ],
    "sg:phone":"+1 651 714 1126",
    "sg:postcode":"55125",
    "sg:province":"MN",
    "sg:tags":[
        "establishment"
    ],
    "wof:name":"Reedspectrum",
    "wof:placetype":"venue"
},
  "geometry": {"coordinates":[-92.931315,44.910341],"type":"Point"}
}