{
  "type": "Feature",
  "properties": {
    "addr:full":"1110 Hwy 55 Hastings MN 55033",
    "addr:housenumber":"1110",
    "addr:postcode":"55033",
    "addr:street":"Hwy 55",
    "iso:country":"US",
    "sg:address":"1110 Hwy 55",
    "sg:city":"Hastings",
    "sg:classifiers":[
        {
            "category":"Insurance",
            "subcategory":"Insurance Agent",
            "type":"Services"
        }
    ],
    "sg:phone":"+1 651 437 6006",
    "sg:postcode":"55033",
    "sg:province":"MN",
    "wof:name":"Ries Insurance Agency",
    "wof:placetype":"venue"
},
  "geometry": {"coordinates":[-92.87206399999999,44.738404],"type":"Point"}
}