{
  "type": "Feature",
  "properties": {
    "iso:country":"US",
    "sg:address":"4 1st Ave SE",
    "sg:city":"Remer",
    "sg:classifiers":[
        {
            "category":"Shopping",
            "subcategory":"Discount & Variety Stores",
            "type":"Retail Goods"
        }
    ],
    "sg:phone":"+1 218 566 4114",
    "sg:postcode":"56672",
    "sg:province":"MN",
    "wof:name":"Bargains Up North",
    "wof:placetype":"venue"
},
  "geometry": {"coordinates":[-93.916152,47.055724],"type":"Point"}
}