{
  "type": "Feature",
  "properties": {
    "addr:full":"1489 W Iowa Ave Saint Paul MN 55108",
    "addr:housenumber":"1489",
    "addr:postcode":"55108",
    "addr:street":"W Iowa Ave",
    "iso:country":"US",
    "sg:address":"1489 W Iowa Ave",
    "sg:city":"Saint Paul",
    "sg:classifiers":[
        {
            "category":"Manufacturing",
            "subcategory":"Printing",
            "type":"Manufacturing & Wholesale Goods"
        }
    ],
    "sg:phone":"+1 651 290 2800",
    "sg:postcode":"55108",
    "sg:province":"MN",
    "sg:tags":[
        "book"
    ],
    "wof:name":"Emc2",
    "wof:placetype":"venue"
},
  "geometry": {"coordinates":[-93.163521,44.989156],"type":"Point"}
}