{
  "type": "Feature",
  "properties": {
    "addr:full":"12808 Taylor St NE Minneapolis MN 55434",
    "addr:housenumber":"12808",
    "addr:postcode":"55434",
    "addr:street":"Taylor St Ne",
    "iso:country":"US",
    "sg:address":"12808 Taylor St NE",
    "sg:city":"Minneapolis",
    "sg:classifiers":[
        {
            "category":"Social Services",
            "subcategory":"Child Care",
            "type":"Services"
        }
    ],
    "sg:phone":"+1 763 757 9223",
    "sg:postcode":"55434",
    "sg:province":"MN",
    "sg:tags":[
        "daycare",
        "provider"
    ],
    "wof:name":"Toni Platz",
    "wof:placetype":"venue"
},
  "geometry": {"coordinates":[-93.244417,45.204187],"type":"Point"}
}